{
  "type": "Feature",
  "properties": {
    "addr:full":"4088 Old Village Ln Memphis MS 38125",
    "addr:housenumber":"4088",
    "addr:postcode":"38125",
    "addr:street":"Old Village Ln",
    "iso:country":"US",
    "sg:address":"4088 Old Village Ln",
    "sg:city":"Memphis",
    "sg:classifiers":[
        {
            "category":"Building & Trades",
            "subcategory":"Cleaning & Sanitation",
            "type":"Services"
        }
    ],
    "sg:phone":"+1 901 752 1062",
    "sg:postcode":"38125",
    "sg:province":"MS",
    "sg:tags":[
        "maintenance"
    ],
    "wof:name":"C&N Janitoral Services",
    "wof:placetype":"venue"
},
  "geometry": {"coordinates":[-89.82822299999999,35.037947],"type":"Point"}
}