{
  "type": "Feature",
  "properties": {
    "iso:country":"US",
    "sg:address":"10445 G C Roberts Rd",
    "sg:city":"Meridian",
    "sg:classifiers":[
        {
            "category":"Real Estate",
            "subcategory":"Real Estate Agent",
            "type":"Services"
        }
    ],
    "sg:phone":"+1 601 482 8818",
    "sg:postcode":"39307",
    "sg:province":"MS",
    "wof:name":"Boyd Williams Real Estate Co",
    "wof:placetype":"venue"
},
  "geometry": {"coordinates":[-88.794078,32.337042],"type":"Point"}
}