{
  "type": "Feature",
  "properties": {
    "iso:country":"US",
    "sg:address":"3930 South Dr",
    "sg:city":"Jackson",
    "sg:classifiers":[
        {
            "category":"Organizations",
            "subcategory":"Religious Organization",
            "type":"Services"
        }
    ],
    "sg:phone":"+1 601 355 3121",
    "sg:postcode":"39209",
    "sg:province":"MS",
    "wof:name":"Rosemont Mssnary Baptst Church",
    "wof:placetype":"venue"
},
  "geometry": {"coordinates":[-90.236512,32.319765],"type":"Point"}
}