{
  "type": "Feature",
  "properties": {
    "iso:country":"US",
    "sg:address":"642 Ponderosa Rd",
    "sg:city":"Lawrence",
    "sg:phone":"+1 601 683 6321",
    "sg:postcode":"39336",
    "sg:province":"MS",
    "sg:tags":[
        "farm",
        "corn",
        "soybean",
        "cotton"
    ],
    "wof:name":"Ponderosa Farms",
    "wof:placetype":"venue"
},
  "geometry": {"coordinates":[-89.280916,32.284202],"type":"Point"}
}