{
  "type": "Feature",
  "properties": {
    "iso:country":"US",
    "sg:address":"169 Porter Ave",
    "sg:city":"Biloxi",
    "sg:classifiers":[
        {
            "category":"Professional",
            "subcategory":"Employment Agencies",
            "type":"Services"
        }
    ],
    "sg:phone":"+1 228 432 0240",
    "sg:postcode":"39530",
    "sg:province":"MS",
    "sg:tags":[
        "temp",
        "labor"
    ],
    "wof:name":"Labor Ready 1311",
    "wof:placetype":"venue"
},
  "geometry": {"coordinates":[-88.901921,30.397159],"type":"Point"}
}