{
  "type": "Feature",
  "properties": {
    "iso:country":"US",
    "sg:address":"2626 N Hills St",
    "sg:city":"Meridian",
    "sg:classifiers":[
        {
            "category":"Banks & Credit Unions",
            "subcategory":"Bank",
            "type":"Services"
        }
    ],
    "sg:phone":"+1 601 483 8786",
    "sg:postcode":"39305",
    "sg:province":"MS",
    "sg:tags":[
        "personal",
        "institution"
    ],
    "wof:name":"Redy Cash",
    "wof:placetype":"venue"
},
  "geometry": {"coordinates":[-88.707933,32.408672],"type":"Point"}
}