{
  "type": "Feature",
  "properties": {
    "iso:country":"US",
    "sg:address":"2902 Hardy St",
    "sg:city":"Hattiesburg",
    "sg:classifiers":[
        {
            "category":"Restaurant",
            "type":"Food & Drink"
        }
    ],
    "sg:menulink":"http://www.allmenus.com/ms/hattiesburg/235096-roly-poly-sandwiches/menu/",
    "sg:phone":"+1 601 579 9215",
    "sg:postcode":"39401",
    "sg:province":"MS",
    "sg:tags":[
        "wrap",
        "american",
        "sandwich"
    ],
    "wof:name":"Roly Poly Sandwiches",
    "wof:placetype":"venue"
},
  "geometry": {"coordinates":[-89.33344700000001,31.324829],"type":"Point"}
}