{
  "type": "Feature",
  "properties": {
    "addr:full":"976 S Beach Blvd Bay St Louis MS 39520",
    "addr:housenumber":"976",
    "addr:postcode":"39520",
    "addr:street":"S Beach Blvd",
    "iso:country":"US",
    "sg:address":"976 S Beach Blvd",
    "sg:city":"Bay St Louis",
    "sg:classifiers":[
        {
            "category":"Professional",
            "subcategory":"Lawyer & Legal Services",
            "type":"Services"
        }
    ],
    "sg:phone":"+1 228 467 0092",
    "sg:postcode":"39520",
    "sg:province":"MS",
    "sg:tags":[
        "attorney"
    ],
    "wof:name":"Southern Disability Law Ctr",
    "wof:placetype":"venue"
},
  "geometry": {"coordinates":[-89.372742,30.278149],"type":"Point"}
}