{
  "type": "Feature",
  "properties": {
    "addr:full":"1704 21st Ave Gulfport MS 39501",
    "addr:housenumber":"1704",
    "addr:postcode":"39501",
    "addr:street":"21St Ave",
    "iso:country":"US",
    "sg:address":"1704 21st Ave",
    "sg:city":"Gulfport",
    "sg:classifiers":[
        {
            "category":"Real Estate",
            "subcategory":"Real Estate Operator",
            "type":"Services"
        }
    ],
    "sg:phone":"+1 228 864 7330",
    "sg:postcode":"39501",
    "sg:province":"MS",
    "sg:tags":[
        "building",
        "apartment"
    ],
    "wof:name":"Mark Waters",
    "wof:placetype":"venue"
},
  "geometry": {"coordinates":[-89.087354,30.371011],"type":"Point"}
}