{
  "type": "Feature",
  "properties": {
    "iso:country":"US",
    "sg:address":"403 Towne Center Blvd",
    "sg:city":"Ridgeland",
    "sg:classifiers":[
        {
            "category":"Mining & Drilling",
            "type":"Manufacturing & Wholesale Goods"
        }
    ],
    "sg:phone":"+1 601 898 0051",
    "sg:postcode":"39157",
    "sg:province":"MS",
    "sg:tags":[
        "oil",
        "producer",
        "gas",
        "wells",
        "operates",
        "producing"
    ],
    "wof:name":"Hughes Eastern Corporation",
    "wof:placetype":"venue"
},
  "geometry": {"coordinates":[-90.118285,32.408684],"type":"Point"}
}