{
  "type": "Feature",
  "properties": {
    "addr:full":"200 Hwy 6 Amory MS 38821",
    "addr:housenumber":"200",
    "addr:postcode":"38821",
    "addr:street":"Hwy 6 Amory",
    "iso:country":"US",
    "sg:address":"200 Hwy 6",
    "sg:city":"Amory",
    "sg:classifiers":[
        {
            "category":"Building & Trades",
            "subcategory":"Construction",
            "type":"Services"
        }
    ],
    "sg:phone":"+1 662 256 8408",
    "sg:postcode":"38821",
    "sg:province":"MS",
    "sg:tags":[
        "contractor"
    ],
    "wof:name":"Dick Sanderson Construction Co",
    "wof:placetype":"venue"
},
  "geometry": {"coordinates":[-88.494187,33.994526],"type":"Point"}
}