{
  "type": "Feature",
  "properties": {
    "iso:country":"US",
    "sg:address":"4400 Leisure Time Dr",
    "sg:city":"Diamondhead",
    "sg:classifiers":[
        {
            "category":"Professional",
            "type":"Services"
        }
    ],
    "sg:phone":"+1 228 255 8660",
    "sg:postcode":"39525",
    "sg:province":"MS",
    "sg:tags":[
        "establishment"
    ],
    "wof:name":"Patriot Technologies LLC",
    "wof:placetype":"venue"
},
  "geometry": {"coordinates":[-89.38073199999999,30.376565],"type":"Point"}
}