{
  "type": "Feature",
  "properties": {
    "iso:country":"US",
    "sg:address":"3920 State Hwy 43",
    "sg:city":"Canton",
    "sg:classifiers":[
        {
            "category":"Organizations",
            "subcategory":"Religious Organization",
            "type":"Services"
        }
    ],
    "sg:phone":"+1 601 859 5186",
    "sg:postcode":"39046",
    "sg:province":"MS",
    "sg:tags":[
        "church"
    ],
    "wof:name":"Pleasant Green Baptist Church",
    "wof:placetype":"venue"
},
  "geometry": {"coordinates":[-89.87282399999999,32.697068],"type":"Point"}
}