{
  "type": "Feature",
  "properties": {
    "iso:country":"US",
    "sg:address":"370 Rosalie Maria Dr",
    "sg:city":"Biloxi",
    "sg:classifiers":[
        {
            "category":"Professional",
            "subcategory":"Business Services",
            "type":"Services"
        }
    ],
    "sg:phone":"+1 228 385 1028",
    "sg:postcode":"39531",
    "sg:province":"MS",
    "sg:tags":[
        "water",
        "treatment"
    ],
    "wof:name":"OPTECH",
    "wof:placetype":"venue"
},
  "geometry": {"coordinates":[-88.969573,30.409151],"type":"Point"}
}