{
  "type": "Feature",
  "properties": {
    "iso:country":"US",
    "sg:address":"49 US Hwy 61",
    "sg:city":"Hollandale",
    "sg:classifiers":[
        {
            "category":"Farming",
            "subcategory":"Livestock Farm",
            "type":"Manufacturing & Wholesale Goods"
        }
    ],
    "sg:phone":"+1 662 827 2900",
    "sg:postcode":"38748",
    "sg:province":"MS",
    "sg:tags":[
        "beef",
        "feedlot",
        "soybean",
        "cattle"
    ],
    "wof:name":"Dean Dean & Dean",
    "wof:placetype":"venue"
},
  "geometry": {"coordinates":[-90.879375,33.108319],"type":"Point"}
}