{
  "type": "Feature",
  "properties": {
    "addr:full":"15621 Howells Ferry Rd Wilmer AL 36587",
    "addr:postcode":"15621;36587",
    "addr:street":"Howells Ferry Rd",
    "iso:country":"US",
    "sg:address":"15621 Howells Ferry Rd",
    "sg:city":"Wilmer",
    "sg:classifiers":[
        {
            "category":"Farming",
            "subcategory":"Dairy Farm",
            "type":"Manufacturing & Wholesale Goods"
        }
    ],
    "sg:phone":"+1 251 649 8145",
    "sg:postcode":"36587",
    "sg:province":"AL",
    "wof:name":"Spivey Keevan",
    "wof:placetype":"venue"
},
  "geometry": {"coordinates":[-88.41482600000001,30.785536],"type":"Point"}
}