{
  "type": "Feature",
  "properties": {
    "addr:full":"7245 English Dr Memphis MS 38125",
    "addr:housenumber":"7245",
    "addr:postcode":"38125",
    "addr:street":"English Dr",
    "iso:country":"US",
    "sg:address":"7245 English Dr",
    "sg:city":"Memphis",
    "sg:classifiers":[
        {
            "category":"Freight",
            "type":"Transportation"
        }
    ],
    "sg:phone":"+1 901 756 8663",
    "sg:postcode":"38125",
    "sg:province":"MS",
    "sg:tags":[
        "broker",
        "trucking"
    ],
    "wof:name":"Bill's Freight Svc",
    "wof:placetype":"venue"
},
  "geometry": {"coordinates":[-89.82212,35.02414],"type":"Point"}
}