{
  "type": "Feature",
  "properties": {
    "iso:country":"US",
    "sg:address":"3630 Rainey Rd",
    "sg:city":"Jackson",
    "sg:classifiers":[
        {
            "category":"Real Estate",
            "subcategory":"Real Estate Operator",
            "type":"Services"
        }
    ],
    "sg:phone":"+1 601 372 2752",
    "sg:postcode":"39212",
    "sg:province":"MS",
    "sg:tags":[
        "building",
        "apartment"
    ],
    "wof:name":"Vriarclill",
    "wof:placetype":"venue"
},
  "geometry": {"coordinates":[-90.253495,32.245725],"type":"Point"}
}