{
  "type": "Feature",
  "properties": {
    "addr:full":"1151 Hwy 35 S Forest MS 39074",
    "addr:housenumber":"1151",
    "addr:postcode":"39074",
    "addr:street":"Hwy 35 S Forest",
    "iso:country":"US",
    "sg:address":"1151 Hwy 35 S",
    "sg:city":"Forest",
    "sg:classifiers":[
        {
            "category":"Health Services",
            "subcategory":"Doctor",
            "type":"Services"
        }
    ],
    "sg:phone":"+1 601 469 3390",
    "sg:postcode":"39074",
    "sg:province":"MS",
    "sg:tags":[
        "clinic"
    ],
    "wof:name":"Central Dialysis Unit-Forest",
    "wof:placetype":"venue"
},
  "geometry": {"coordinates":[-89.481927,32.349412],"type":"Point"}
}