{
  "type": "Feature",
  "properties": {
    "addr:full":"5038 Raymond Ave Tupelo MS 38801",
    "addr:housenumber":"5038",
    "addr:postcode":"38801",
    "addr:street":"Raymond Ave",
    "iso:country":"US",
    "sg:address":"5038 Raymond Ave",
    "sg:city":"Tupelo",
    "sg:classifiers":[
        {
            "category":"Social Services",
            "subcategory":"Child Care",
            "type":"Services"
        }
    ],
    "sg:phone":"+1 662 566 1104",
    "sg:postcode":"38801",
    "sg:province":"MS",
    "wof:name":"Faye's Playhouse & Learning",
    "wof:placetype":"venue"
},
  "geometry": {"coordinates":[-88.71986800000001,34.193655],"type":"Point"}
}