{
  "type": "Feature",
  "properties": {
    "addr:full":"2412 9th St Meridian MS 39301",
    "addr:housenumber":"2412",
    "addr:postcode":"39301",
    "addr:street":"9Th St",
    "iso:country":"US",
    "sg:address":"2412 9th St",
    "sg:city":"Meridian",
    "sg:classifiers":[
        {
            "category":"Freight",
            "type":"Transportation"
        }
    ],
    "sg:phone":"+1 601 479 1158",
    "sg:postcode":"39301",
    "sg:province":"MS",
    "sg:tags":[
        "commercial",
        "storage"
    ],
    "wof:name":"Econo Storage",
    "wof:placetype":"venue"
},
  "geometry": {"coordinates":[-88.703534,32.366034],"type":"Point"}
}