{
  "type": "Feature",
  "properties": {
    "addr:full":"3371 Augusta Rd Ellisville MS 39437",
    "addr:housenumber":"3371",
    "addr:postcode":"39437",
    "addr:street":"Augusta Rd",
    "iso:country":"US",
    "sg:address":"3371 Augusta Rd",
    "sg:city":"Ellisville",
    "sg:classifiers":[
        {
            "category":"Health Services",
            "subcategory":"Nursing And Care Facility",
            "type":"Services"
        }
    ],
    "sg:phone":"+1 601 583 6885",
    "sg:postcode":"39437",
    "sg:province":"MS",
    "sg:tags":[
        "personal",
        "home"
    ],
    "wof:name":"Total Care Alternative Home",
    "wof:placetype":"venue"
},
  "geometry": {"coordinates":[-89.19409400000001,31.450312],"type":"Point"}
}