{
  "type": "Feature",
  "properties": {
    "iso:country":"US",
    "sg:address":"7256 Whitten Place Cove",
    "sg:city":"Olive Branch",
    "sg:classifiers":[
        {
            "category":"Wholesale",
            "subcategory":"Home Furnishings",
            "type":"Manufacturing & Wholesale Goods"
        }
    ],
    "sg:phone":"+1 662 890 9600",
    "sg:postcode":"38654",
    "sg:province":"MS",
    "sg:tags":[
        "material",
        "floor"
    ],
    "wof:name":"Carpet Network",
    "wof:placetype":"venue"
},
  "geometry": {"coordinates":[-89.92644199999999,34.966651],"type":"Point"}
}