{
  "type": "Feature",
  "properties": {
    "addr:full":"1001 E County Line Rd Jackson MS 39211",
    "addr:housenumber":"1001",
    "addr:postcode":"39211",
    "addr:street":"E County Line Rd",
    "iso:country":"US",
    "sg:address":"1001 E County Line Rd",
    "sg:city":"Jackson",
    "sg:classifiers":[
        {
            "category":"Restaurant",
            "type":"Food & Drink"
        }
    ],
    "sg:phone":"+1 601 957 1515",
    "sg:postcode":"39211",
    "sg:province":"MS",
    "wof:name":"Huntingtons Grille",
    "wof:placetype":"venue"
},
  "geometry": {"coordinates":[-90.14282300000001,32.399648],"type":"Point"}
}