{
  "type": "Feature",
  "properties": {
    "addr:full":"980 Elks Lake Rd Hattiesburg MS 39401",
    "addr:housenumber":"980",
    "addr:postcode":"39401",
    "addr:street":"Elks Lake Rd",
    "iso:country":"US",
    "sg:address":"980 Elks Lake Rd",
    "sg:city":"Hattiesburg",
    "sg:classifiers":[
        {
            "category":"Retail",
            "subcategory":"Auto Repair",
            "type":"Services"
        }
    ],
    "sg:phone":"+1 601 583 2872",
    "sg:postcode":"39401",
    "sg:province":"MS",
    "sg:tags":[
        "wrecker"
    ],
    "wof:name":"Absolute Towing & Recovery",
    "wof:placetype":"venue"
},
  "geometry": {"coordinates":[-89.293817,31.208668],"type":"Point"}
}