{
  "type": "Feature",
  "properties": {
    "iso:country":"US",
    "sg:address":"1876 Old Hwy 49",
    "sg:city":"Bentonia",
    "sg:classifiers":[
        {
            "category":"Shopping",
            "subcategory":"Gifts & Souvenirs",
            "type":"Retail Goods"
        }
    ],
    "sg:phone":"+1 662 755 0181",
    "sg:postcode":"39040",
    "sg:province":"MS",
    "wof:name":"Fosters Gifts",
    "wof:placetype":"venue"
},
  "geometry": {"coordinates":[-90.380554,32.674116],"type":"Point"}
}