{
  "type": "Feature",
  "properties": {
    "addr:full":"1336 Old Hwy 51 NE Brookhaven MS 39601",
    "addr:housenumber":"1336",
    "addr:postcode":"39601",
    "addr:street":"Old Hwy 51 Ne",
    "iso:country":"US",
    "sg:address":"1336 Old Hwy 51 NE",
    "sg:city":"Brookhaven",
    "sg:classifiers":[
        {
            "category":"Government",
            "subcategory":"Office",
            "type":"Public Place"
        }
    ],
    "sg:phone":"+1 601 833 6101",
    "sg:postcode":"39601",
    "sg:province":"MS",
    "sg:tags":[
        "federal",
        "security"
    ],
    "wof:name":"US Army Reserve 296 Trans Co",
    "wof:placetype":"venue"
},
  "geometry": {"coordinates":[-90.412927,31.606545],"type":"Point"}
}