{
  "type": "Feature",
  "properties": {
    "addr:full":"3544 Main St Moss Point MS 39563",
    "addr:housenumber":"3544",
    "addr:postcode":"39563",
    "addr:street":"Main St",
    "iso:country":"US",
    "sg:address":"3544 Main St",
    "sg:city":"Moss Point",
    "sg:classifiers":[
        {
            "category":"Shopping",
            "subcategory":"Discount & Variety Stores",
            "type":"Retail Goods"
        },
        {
            "category":"Shopping",
            "subcategory":"Department Store",
            "type":"Retail Goods"
        }
    ],
    "sg:phone":"+1 228 475 0112",
    "sg:postcode":"39563",
    "sg:province":"MS",
    "sg:tags":[
        "shop"
    ],
    "wof:name":"Family Dollar Stores",
    "wof:placetype":"venue"
},
  "geometry": {"coordinates":[-88.535657,30.39086],"type":"Point"}
}