{
  "type": "Feature",
  "properties": {
    "iso:country":"US",
    "sg:address":"1601 14th St",
    "sg:city":"Meridian",
    "sg:classifiers":[
        {
            "category":"Insurance",
            "subcategory":"Insurance Agent",
            "type":"Services"
        }
    ],
    "sg:phone":"+1 601 483 7577",
    "sg:postcode":"39301",
    "sg:province":"MS",
    "wof:name":"Shelter Insurance",
    "wof:placetype":"venue"
},
  "geometry": {"coordinates":[-88.695736,32.370635],"type":"Point"}
}