{
  "type": "Feature",
  "properties": {
    "iso:country":"US",
    "sg:address":"608 Pass Rd",
    "sg:city":"Gulfport",
    "sg:classifiers":[
        {
            "category":"Banks & Credit Unions",
            "subcategory":"Bank",
            "type":"Services"
        }
    ],
    "sg:phone":"+1 228 539 7029",
    "sg:postcode":"39501",
    "sg:province":"MS",
    "wof:name":"Gulf Coast Comm Fed Cu",
    "wof:placetype":"venue"
},
  "geometry": {"coordinates":[-89.062904,30.388489],"type":"Point"}
}