{
  "type": "Feature",
  "properties": {
    "iso:country":"US",
    "sg:address":"202 Sandpiper Rd",
    "sg:city":"Brandon",
    "sg:classifiers":[
        {
            "category":"Airport",
            "type":"Transportation"
        }
    ],
    "sg:phone":"+1 601 992 6806",
    "sg:postcode":"39047",
    "sg:province":"MS",
    "wof:name":"Mike S Aircraft Service",
    "wof:placetype":"venue"
},
  "geometry": {"coordinates":[-90.011605,32.383467],"type":"Point"}
}