{
  "type": "Feature",
  "properties": {
    "addr:full":"1902 Martin Luther King Jr Blvd Greenville MS 38701",
    "addr:housenumber":"1902",
    "addr:postcode":"38701",
    "addr:street":"Martin Luther King Jr Blvd",
    "iso:country":"US",
    "sg:address":"1902 Martin Luther King Jr Blvd",
    "sg:city":"Greenville",
    "sg:classifiers":[
        {
            "category":"Building & Trades",
            "subcategory":"Construction",
            "type":"Services"
        }
    ],
    "sg:phone":"+1 662 335 2650",
    "sg:postcode":"38701",
    "sg:province":"MS",
    "sg:tags":[
        "general",
        "contractor"
    ],
    "wof:name":"Reed Construction Inc",
    "wof:placetype":"venue"
},
  "geometry": {"coordinates":[-91.040115,33.369535],"type":"Point"}
}