{
  "type": "Feature",
  "properties": {
    "iso:country":"US",
    "sg:address":"1121 Jackson Ave",
    "sg:city":"Pascagoula",
    "sg:classifiers":[
        {
            "category":"Insurance",
            "subcategory":"Insurance Agent",
            "type":"Services"
        }
    ],
    "sg:phone":"+1 228 712 2525",
    "sg:postcode":"39567",
    "sg:province":"MS",
    "wof:name":"Fox Everett Inc",
    "wof:placetype":"venue"
},
  "geometry": {"coordinates":[-88.55289,30.365663],"type":"Point"}
}