{
  "type": "Feature",
  "properties": {
    "addr:full":"200 State St Natchez MS 39120",
    "addr:housenumber":"200",
    "addr:postcode":"39120",
    "addr:street":"State St",
    "iso:country":"US",
    "sg:address":"200 State St",
    "sg:city":"Natchez",
    "sg:classifiers":[
        {
            "category":"Shopping",
            "type":"Retail Goods"
        }
    ],
    "sg:phone":"+1 601 445 8811",
    "sg:postcode":"39120",
    "sg:province":"MS",
    "sg:tags":[
        "pet",
        "food",
        "supply"
    ],
    "wof:name":"Fideaux's Pet Co",
    "wof:placetype":"venue"
},
  "geometry": {"coordinates":[-91.40628,31.56056],"type":"Point"}
}