{
  "type": "Feature",
  "properties": {
    "iso:country":"US",
    "sg:address":"300 Oak St",
    "sg:city":"Greenwood",
    "sg:classifiers":[
        {
            "category":"Retail",
            "subcategory":"Funeral Services",
            "type":"Services"
        }
    ],
    "sg:phone":"+1 662 453 6524",
    "sg:postcode":"38930",
    "sg:province":"MS",
    "wof:name":"Great Southern Funeral Home",
    "wof:placetype":"venue"
},
  "geometry": {"coordinates":[-90.17084199999999,33.516441],"type":"Point"}
}