{
  "type": "Feature",
  "properties": {
    "addr:full":"49 Northtown Dr Jackson MS 39211",
    "addr:housenumber":"49",
    "addr:postcode":"39211",
    "addr:street":"Northtown Dr",
    "iso:country":"US",
    "sg:address":"49 Northtown Dr",
    "sg:city":"Jackson",
    "sg:classifiers":[
        {
            "category":"Professional",
            "subcategory":"Secretarial Services",
            "type":"Services"
        }
    ],
    "sg:phone":"+1 601 278 9781",
    "sg:postcode":"39211",
    "sg:province":"MS",
    "sg:tags":[
        "reporting",
        "court"
    ],
    "wof:name":"Jackson Venita",
    "wof:placetype":"venue"
},
  "geometry": {"coordinates":[-90.113677,32.385899],"type":"Point"}
}