{
  "type": "Feature",
  "properties": {
    "iso:country":"US",
    "sg:address":"516 Wedgewood Dr",
    "sg:city":"Oxford",
    "sg:classifiers":[
        {
            "category":"Manufacturing",
            "subcategory":"Food",
            "type":"Manufacturing & Wholesale Goods"
        }
    ],
    "sg:phone":"+1 662 281 8000",
    "sg:postcode":"38655",
    "sg:province":"MS",
    "wof:name":"Mereseph Foods Inc",
    "wof:placetype":"venue"
},
  "geometry": {"coordinates":[-89.574414,34.369822],"type":"Point"}
}