{
  "type": "Feature",
  "properties": {
    "addr:full":"1320 High St Jackson MS 39202",
    "addr:housenumber":"1320",
    "addr:postcode":"39202",
    "addr:street":"High St",
    "iso:country":"US",
    "sg:address":"1320 High St",
    "sg:city":"Jackson",
    "sg:classifiers":[
        {
            "category":"Restaurant",
            "type":"Food & Drink"
        }
    ],
    "sg:phone":"+1 601 896 0074",
    "sg:postcode":"39202",
    "sg:province":"MS",
    "wof:name":"Suncoast Restaurant LLC",
    "wof:placetype":"venue"
},
  "geometry": {"coordinates":[-90.170767,32.303529],"type":"Point"}
}