{
  "type": "Feature",
  "properties": {
    "iso:country":"US",
    "sg:address":"132 Scenic Dr",
    "sg:city":"Hattiesburg",
    "sg:classifiers":[
        {
            "category":"Freight",
            "type":"Transportation"
        }
    ],
    "sg:phone":"+1 601 545 3943",
    "sg:postcode":"39401",
    "sg:province":"MS",
    "sg:tags":[
        "operator",
        "hauling",
        "trucking"
    ],
    "wof:name":"Bouie River Trucking Inc",
    "wof:placetype":"venue"
},
  "geometry": {"coordinates":[-89.302603,31.369978],"type":"Point"}
}