{
  "type": "Feature",
  "properties": {
    "iso:country":"US",
    "sg:address":"1027 Hwy 471",
    "sg:city":"Brandon",
    "sg:classifiers":[
        {
            "category":"Communications",
            "subcategory":"Radio Station",
            "type":"Services"
        }
    ],
    "sg:phone":"+1 601 825 5045",
    "sg:postcode":"39042",
    "sg:province":"MS",
    "sg:tags":[
        "company",
        "broadcasting"
    ],
    "wof:name":"WRKN",
    "wof:placetype":"venue"
},
  "geometry": {"coordinates":[-89.994822,32.30091],"type":"Point"}
}