{
  "type": "Feature",
  "properties": {
    "iso:country":"US",
    "sg:address":"301 Winfield Dr",
    "sg:city":"Tupelo",
    "sg:classifiers":[
        {
            "category":"Wholesale",
            "subcategory":"Construction Materials",
            "type":"Manufacturing & Wholesale Goods"
        }
    ],
    "sg:phone":"+1 662 566 2040",
    "sg:postcode":"38801",
    "sg:province":"MS",
    "wof:name":"Lentz Construction Inc",
    "wof:placetype":"venue"
},
  "geometry": {"coordinates":[-88.747353,34.259358],"type":"Point"}
}