{
  "type": "Feature",
  "properties": {
    "addr:full":"2318 Ingalls Ave Pascagoula MS 39567",
    "addr:housenumber":"2318",
    "addr:postcode":"39567",
    "addr:street":"Ingalls Ave",
    "iso:country":"US",
    "sg:address":"2318 Ingalls Ave",
    "sg:city":"Pascagoula",
    "sg:classifiers":[
        {
            "category":"Restaurant",
            "type":"Food & Drink"
        }
    ],
    "sg:phone":"+1 228 762 7464",
    "sg:postcode":"39567",
    "sg:province":"MS",
    "wof:name":"Marguerite's Italian Village",
    "wof:placetype":"venue"
},
  "geometry": {"coordinates":[-88.53948200000001,30.354776],"type":"Point"}
}