{
  "type": "Feature",
  "properties": {
    "iso:country":"US",
    "sg:address":"4007 Oakridge Pl",
    "sg:city":"Biloxi",
    "sg:classifiers":[
        {
            "category":"Real Estate",
            "subcategory":"Real Estate Agent",
            "type":"Services"
        }
    ],
    "sg:phone":"+1 228 396 3572",
    "sg:postcode":"39532",
    "sg:province":"MS",
    "wof:name":"Fountain Homes Inc",
    "wof:placetype":"venue"
},
  "geometry": {"coordinates":[-88.90113100000001,30.472173],"type":"Point"}
}