{
  "type": "Feature",
  "properties": {
    "addr:full":"598 McElroy Dr Oxford MS 38655",
    "addr:housenumber":"598",
    "addr:postcode":"38655",
    "addr:street":"Mcelroy Dr",
    "iso:country":"US",
    "sg:address":"598 McElroy Dr",
    "sg:city":"Oxford",
    "sg:classifiers":[
        {
            "category":"Education",
            "subcategory":"Library",
            "type":"Public Place"
        }
    ],
    "sg:phone":"+1 662 232 2920",
    "sg:postcode":"38655",
    "sg:province":"MS",
    "wof:name":"National Sedimentation Lab",
    "wof:placetype":"venue"
},
  "geometry": {"coordinates":[-89.540205,34.380725],"type":"Point"}
}