{
  "type": "Feature",
  "properties": {
    "iso:country":"US",
    "sg:address":"506 E Lee St",
    "sg:city":"Sardis",
    "sg:classifiers":[
        {
            "category":"Autos & Motor Vehicles",
            "subcategory":"Automobile Sales",
            "type":"Retail Goods"
        }
    ],
    "sg:phone":"+1 662 487 2207",
    "sg:postcode":"38666",
    "sg:province":"MS",
    "sg:tags":[
        "car",
        "dealer"
    ],
    "wof:name":"Pugh's Auto Plex",
    "wof:placetype":"venue"
},
  "geometry": {"coordinates":[-89.897244,34.437109],"type":"Point"}
}