{
  "type": "Feature",
  "properties": {
    "iso:country":"US",
    "sg:address":"4330 Southern Manor Dr N",
    "sg:city":"Lake Cormorant",
    "sg:classifiers":[
        {
            "category":"Professional",
            "subcategory":"Business Services",
            "type":"Services"
        }
    ],
    "sg:phone":"+1 662 349 5971",
    "sg:postcode":"38641",
    "sg:province":"MS",
    "sg:tags":[
        "appraiser"
    ],
    "wof:name":"Judy Kitchens Appraisals",
    "wof:placetype":"venue"
},
  "geometry": {"coordinates":[-90.089105,34.919652],"type":"Point"}
}