{
  "type": "Feature",
  "properties": {
    "addr:full":"109 S 6th St Amory MS 38821",
    "addr:housenumber":"109",
    "addr:postcode":"38821",
    "addr:street":"S 6Th St",
    "iso:country":"US",
    "sg:address":"109 S 6th St",
    "sg:city":"Amory",
    "sg:classifiers":[
        {
            "category":"Food & Beverages",
            "subcategory":"Groceries & Convenience Stores",
            "type":"Retail Goods"
        }
    ],
    "sg:phone":"+1 662 256 3827",
    "sg:postcode":"38821",
    "sg:province":"MS",
    "wof:name":"Save-A-Lot Discount Foods",
    "wof:placetype":"venue"
},
  "geometry": {"coordinates":[-88.484861,33.987606],"type":"Point"}
}