{
  "type": "Feature",
  "properties": {
    "iso:country":"US",
    "sg:address":"3055 N Washington St",
    "sg:city":"Vicksburg",
    "sg:classifiers":[
        {
            "category":"Organizations",
            "subcategory":"Religious Organization",
            "type":"Services"
        }
    ],
    "sg:phone":"+1 601 630 9278",
    "sg:postcode":"39183",
    "sg:province":"MS",
    "sg:tags":[
        "church"
    ],
    "wof:name":"Bethlehem MB Church",
    "wof:placetype":"venue"
},
  "geometry": {"coordinates":[-90.855874,32.393469],"type":"Point"}
}