{
  "type": "Feature",
  "properties": {
    "iso:country":"US",
    "sg:address":"4647 Van Winkle Park Dr",
    "sg:city":"Jackson",
    "sg:classifiers":[
        {
            "category":"Retail",
            "subcategory":"Repair Shop",
            "type":"Services"
        }
    ],
    "sg:phone":"+1 601 922 8420",
    "sg:postcode":"39209",
    "sg:province":"MS",
    "sg:tags":[
        "refinishing",
        "furniture"
    ],
    "wof:name":"Walley's Furniture Repair Inc",
    "wof:placetype":"venue"
},
  "geometry": {"coordinates":[-90.263965,32.304514],"type":"Point"}
}