{
  "type": "Feature",
  "properties": {
    "addr:full":"1611 E Church St Booneville MS 38829",
    "addr:housenumber":"1611",
    "addr:postcode":"38829",
    "addr:street":"E Church St",
    "iso:country":"US",
    "sg:address":"1611 E Church St",
    "sg:city":"Booneville",
    "sg:classifiers":[
        {
            "category":"Personal",
            "subcategory":"Barber",
            "type":"Services"
        }
    ],
    "sg:phone":"+1 662 728 3391",
    "sg:postcode":"38829",
    "sg:province":"MS",
    "wof:name":"Hare's Barber & Beauty Salon",
    "wof:placetype":"venue"
},
  "geometry": {"coordinates":[-88.54168,34.653459],"type":"Point"}
}