{
  "type": "Feature",
  "properties": {
    "iso:country":"US",
    "sg:address":"515 Mannings Crossing Rd",
    "sg:city":"Tylertown",
    "sg:classifiers":[
        {
            "category":"Government",
            "subcategory":"Office",
            "type":"Public Place"
        },
        {
            "category":"Utilities",
            "subcategory":"Water",
            "type":"Services"
        }
    ],
    "sg:phone":"+1 601 876 4838",
    "sg:postcode":"39667",
    "sg:province":"MS",
    "sg:tags":[
        "company",
        "management",
        "sewage"
    ],
    "wof:name":"Magee's Creek Water Assn",
    "wof:placetype":"venue"
},
  "geometry": {"coordinates":[-90.20111,31.27761],"type":"Point"}
}