{
  "type": "Feature",
  "properties": {
    "iso:country":"US",
    "sg:address":"200 Bowles St",
    "sg:city":"Belzoni",
    "sg:classifiers":[
        {
            "category":"Communications",
            "type":"Services"
        }
    ],
    "sg:phone":"+1 662 247 0999",
    "sg:postcode":"39038",
    "sg:province":"MS",
    "wof:name":"Ikano Communications",
    "wof:placetype":"venue"
},
  "geometry": {"coordinates":[-90.486794,33.178929],"type":"Point"}
}