{
  "type": "Feature",
  "properties": {
    "iso:country":"US",
    "sg:address":"507 Main St",
    "sg:city":"Brookhaven",
    "sg:classifiers":[
        {
            "category":"Mining & Drilling",
            "type":"Manufacturing & Wholesale Goods"
        }
    ],
    "sg:phone":"+1 601 833 3261",
    "sg:postcode":"39601",
    "sg:province":"MS",
    "sg:tags":[
        "field",
        "oil"
    ],
    "wof:name":"Natco-National Tank Co",
    "wof:placetype":"venue"
},
  "geometry": {"coordinates":[-90.430307,31.588745],"type":"Point"}
}