{
  "type": "Feature",
  "properties": {
    "iso:country":"US",
    "sg:address":"218 Hwy 42",
    "sg:city":"Petal",
    "sg:classifiers":[
        {
            "category":"Restaurant",
            "type":"Food & Drink"
        }
    ],
    "sg:phone":"+1 601 544 4671",
    "sg:postcode":"39465",
    "sg:province":"MS",
    "sg:tags":[
        "eating"
    ],
    "wof:name":"Wards Restaurant",
    "wof:placetype":"venue"
},
  "geometry": {"coordinates":[-89.25769200000001,31.346576],"type":"Point"}
}