{
  "type": "Feature",
  "properties": {
    "iso:country":"US",
    "sg:address":"6686 Hunters Glen",
    "sg:city":"Southaven",
    "sg:classifiers":[
        {
            "category":"Arts & Performance",
            "subcategory":"Theater",
            "type":"Entertainment"
        }
    ],
    "sg:phone":"+1 662 536 0062",
    "sg:postcode":"38671",
    "sg:province":"MS",
    "sg:tags":[
        "theatrical"
    ],
    "wof:name":"Traveler Enterprises Inc",
    "wof:placetype":"venue"
},
  "geometry": {"coordinates":[-89.95757399999999,34.958148],"type":"Point"}
}