{
  "type": "Feature",
  "properties": {
    "iso:country":"US",
    "sg:address":"1068 Highland Colony Pkwy",
    "sg:city":"Ridgeland",
    "sg:classifiers":[
        {
            "category":"Building & Trades",
            "subcategory":"Construction",
            "type":"Services"
        }
    ],
    "sg:phone":"+1 601 898 3576",
    "sg:postcode":"39157",
    "sg:province":"MS",
    "sg:tags":[
        "general",
        "contractor"
    ],
    "wof:name":"W G Yates & Sons Construction",
    "wof:placetype":"venue"
},
  "geometry": {"coordinates":[-90.15369699999999,32.453359],"type":"Point"}
}