{
  "type": "Feature",
  "properties": {
    "iso:country":"US",
    "sg:address":"4117 Washington St",
    "sg:city":"Vicksburg",
    "sg:classifiers":[
        {
            "category":"Retail",
            "subcategory":"Auto Repair",
            "type":"Services"
        }
    ],
    "sg:phone":"+1 601 638 4441",
    "sg:postcode":"39180",
    "sg:province":"MS",
    "sg:tags":[
        "transmission",
        "automotive"
    ],
    "wof:name":"Automatic Transmission Service",
    "wof:placetype":"venue"
},
  "geometry": {"coordinates":[-90.89779900000001,32.31655],"type":"Point"}
}