{
  "type": "Feature",
  "properties": {
    "addr:full":"3827 Bethlehem Rd Potts Camp MS 38659",
    "addr:housenumber":"3827",
    "addr:postcode":"38659",
    "addr:street":"Bethlehem Rd",
    "iso:country":"US",
    "sg:address":"3827 Bethlehem Rd",
    "sg:city":"Potts Camp",
    "sg:classifiers":[
        {
            "category":"Farming",
            "subcategory":"Livestock Farm",
            "type":"Manufacturing & Wholesale Goods"
        }
    ],
    "sg:phone":"+1 662 333 7579",
    "sg:postcode":"38659",
    "sg:province":"MS",
    "sg:tags":[
        "beef",
        "feedlot",
        "cattle"
    ],
    "wof:name":"Ash Tilden",
    "wof:placetype":"venue"
},
  "geometry": {"coordinates":[-89.375426,34.574],"type":"Point"}
}