{
  "type": "Feature",
  "properties": {
    "iso:country":"US",
    "sg:address":"743 Beulah Ave",
    "sg:city":"Tylertown",
    "sg:classifiers":[
        {
            "category":"Shopping",
            "subcategory":"Jewelry",
            "type":"Retail Goods"
        }
    ],
    "sg:phone":"+1 601 876 3461",
    "sg:postcode":"39667",
    "sg:province":"MS",
    "sg:tags":[
        "repair",
        "jeweler"
    ],
    "wof:name":"Rawls' Jewelers",
    "wof:placetype":"venue"
},
  "geometry": {"coordinates":[-90.164911,31.123679],"type":"Point"}
}