{
  "type": "Feature",
  "properties": {
    "iso:country":"US",
    "sg:address":"4253 Old Forest Cove",
    "sg:city":"Memphis",
    "sg:classifiers":[
        {
            "category":"Professional",
            "subcategory":"Management & Consulting",
            "type":"Services"
        }
    ],
    "sg:phone":"+1 901 737 8014",
    "sg:postcode":"38125",
    "sg:province":"MS",
    "wof:name":"A & J Capital Management LLC",
    "wof:placetype":"venue"
},
  "geometry": {"coordinates":[-89.809708,35.032327],"type":"Point"}
}