{
  "type": "Feature",
  "properties": {
    "addr:full":"570 Hwy 12 W Starkville MS 39759",
    "addr:housenumber":"570",
    "addr:postcode":"39759",
    "addr:street":"Hwy 12 W",
    "iso:country":"US",
    "sg:address":"570 Hwy 12 W",
    "sg:city":"Starkville",
    "sg:classifiers":[
        {
            "category":"Retail",
            "subcategory":"Auto Rental",
            "type":"Services"
        }
    ],
    "sg:phone":"+1 662 323 5092",
    "sg:postcode":"39759",
    "sg:province":"MS",
    "sg:tags":[
        "renting",
        "truck",
        "leasing"
    ],
    "wof:name":"U-Haul Co",
    "wof:placetype":"venue"
},
  "geometry": {"coordinates":[-88.828765,33.453992],"type":"Point"}
}