{
  "type": "Feature",
  "properties": {
    "addr:full":"100 Warfield Point Park Rd Greenville MS 38701",
    "addr:housenumber":"100",
    "addr:postcode":"38701",
    "addr:street":"Warfield Point Park Rd",
    "iso:country":"US",
    "sg:address":"100 Warfield Point Park Rd",
    "sg:city":"Greenville",
    "sg:classifiers":[
        {
            "category":"Wholesale",
            "subcategory":"Machinery & Supplies",
            "type":"Manufacturing & Wholesale Goods"
        }
    ],
    "sg:phone":"+1 662 335 2526",
    "sg:postcode":"38701",
    "sg:province":"MS",
    "sg:tags":[
        "ship",
        "chandler"
    ],
    "wof:name":"Wepfer Marine Of Greenville",
    "wof:placetype":"venue"
},
  "geometry": {"coordinates":[-91.125446,33.347583],"type":"Point"}
}