{
  "type": "Feature",
  "properties": {
    "iso:country":"US",
    "sg:address":"660 Main St",
    "sg:city":"Woodville",
    "sg:classifiers":[
        {
            "category":"Food & Beverages",
            "subcategory":"Liquor & Beverages",
            "type":"Retail Goods"
        }
    ],
    "sg:phone":"+1 601 888 6465",
    "sg:postcode":"39669",
    "sg:province":"MS",
    "wof:name":"Main Street Package",
    "wof:placetype":"venue"
},
  "geometry": {"coordinates":[-91.29998399999999,31.10417],"type":"Point"}
}