{
  "type": "Feature",
  "properties": {
    "iso:country":"US",
    "sg:address":"1046 Church Rd W",
    "sg:city":"Southaven",
    "sg:classifiers":[
        {
            "category":"Banks & Credit Unions",
            "subcategory":"Bank",
            "type":"Services"
        }
    ],
    "sg:phone":"+1 662 536 5000",
    "sg:postcode":"38671",
    "sg:province":"MS",
    "wof:name":"Bancorp South Bank",
    "wof:placetype":"venue"
},
  "geometry": {"coordinates":[-90.00774699999999,34.933561],"type":"Point"}
}