{
  "type": "Feature",
  "properties": {
    "iso:country":"US",
    "sg:address":"2454 Hwy 80 E",
    "sg:city":"Pearl",
    "sg:classifiers":[
        {
            "category":"Autos & Motor Vehicles",
            "subcategory":"Fuel & Gas Station",
            "type":"Retail Goods"
        }
    ],
    "sg:phone":"+1 601 932 6151",
    "sg:postcode":"39208",
    "sg:province":"MS",
    "sg:tags":[
        "oil"
    ],
    "wof:name":"Jubilee Chevron",
    "wof:placetype":"venue"
},
  "geometry": {"coordinates":[-90.131708,32.2806],"type":"Point"}
}