{
  "type": "Feature",
  "properties": {
    "iso:country":"US",
    "sg:address":"1201 Washington Ave",
    "sg:city":"Gulfport",
    "sg:classifiers":[
        {
            "category":"Restaurant",
            "type":"Food & Drink"
        }
    ],
    "sg:phone":"+1 228 896 9812",
    "sg:postcode":"39507",
    "sg:province":"MS",
    "sg:tags":[
        "eating"
    ],
    "sg:website":"www.blowflyinn.com",
    "wof:name":"Blow Fly Inn",
    "wof:placetype":"venue"
},
  "geometry": {"coordinates":[-89.03125199999999,30.403159],"type":"Point"}
}