{
  "type": "Feature",
  "properties": {
    "iso:country":"US",
    "sg:address":"1106 Washington St",
    "sg:city":"Vicksburg",
    "sg:classifiers":[
        {
            "category":"Manufacturing",
            "subcategory":"Motor Vehicles & Parts",
            "type":"Manufacturing & Wholesale Goods"
        }
    ],
    "sg:phone":"+1 601 634 8163",
    "sg:postcode":"39183",
    "sg:province":"MS",
    "sg:tags":[
        "signing",
        "graphic",
        "screen",
        "printing",
        "design",
        "silk"
    ],
    "wof:name":"Artistic Lettering & Design",
    "wof:placetype":"venue"
},
  "geometry": {"coordinates":[-90.88185199999999,32.35203],"type":"Point"}
}