{
  "type": "Feature",
  "properties": {
    "iso:country":"US",
    "sg:address":"714 Beulah Ave",
    "sg:city":"Tylertown",
    "sg:classifiers":[
        {
            "category":"Building & Trades",
            "subcategory":"Equipment Rental",
            "type":"Services"
        }
    ],
    "sg:phone":"+1 601 876 2616",
    "sg:postcode":"39667",
    "sg:province":"MS",
    "sg:tags":[
        "appliance"
    ],
    "wof:name":"Insta Color Rentals",
    "wof:placetype":"venue"
},
  "geometry": {"coordinates":[-90.169703,31.126425],"type":"Point"}
}