{
  "type": "Feature",
  "properties": {
    "iso:country":"US",
    "sg:address":"104 Byram Dr",
    "sg:city":"Byram",
    "sg:classifiers":[
        {
            "category":"Retail",
            "subcategory":"Animal Services",
            "type":"Services"
        }
    ],
    "sg:phone":"+1 601 371 7400",
    "sg:postcode":"39272",
    "sg:province":"MS",
    "sg:tags":[
        "pet",
        "grooming",
        "washing"
    ],
    "wof:name":"Diane's Sassy Scissors Pet",
    "wof:placetype":"venue"
},
  "geometry": {"coordinates":[-90.23049899999999,32.251219],"type":"Point"}
}