{
  "type": "Feature",
  "properties": {
    "iso:country":"US",
    "sg:address":"147 Daniel Lake Blvd",
    "sg:city":"Jackson",
    "sg:classifiers":[
        {
            "category":"Organizations",
            "subcategory":"Religious Organization",
            "type":"Services"
        }
    ],
    "sg:phone":"+1 601 372 5185",
    "sg:postcode":"39212",
    "sg:province":"MS",
    "sg:tags":[
        "church"
    ],
    "wof:name":"All Saints Episcopal Church",
    "wof:placetype":"venue"
},
  "geometry": {"coordinates":[-90.224188,32.252011],"type":"Point"}
}