{
  "type": "Feature",
  "properties": {
    "iso:country":"US",
    "sg:address":"7007 Channel 16 Way",
    "sg:city":"Jackson",
    "sg:classifiers":[
        {
            "category":"Wholesale",
            "subcategory":"Machinery & Supplies",
            "type":"Manufacturing & Wholesale Goods"
        }
    ],
    "sg:phone":"+1 601 922 1364",
    "sg:postcode":"39209",
    "sg:province":"MS",
    "sg:tags":[
        "compressor",
        "industrial",
        "gas",
        "equipment"
    ],
    "wof:name":"Gulf States Engineering Co Inc",
    "wof:placetype":"venue"
},
  "geometry": {"coordinates":[-90.29158099999999,32.276079],"type":"Point"}
}