{
  "type": "Feature",
  "properties": {
    "iso:country":"US",
    "sg:address":"1833 Hwy 82 E",
    "sg:city":"Greenville",
    "sg:classifiers":[
        {
            "category":"Restaurant",
            "type":"Food & Drink"
        }
    ],
    "sg:phone":"+1 662 335 8688",
    "sg:postcode":"38703",
    "sg:province":"MS",
    "wof:name":"Little China Buffet",
    "wof:placetype":"venue"
},
  "geometry": {"coordinates":[-91.02910199999999,33.399566],"type":"Point"}
}