{
  "type": "Feature",
  "properties": {
    "addr:full":"92 Front St Burnsville MS 38833",
    "addr:housenumber":"92",
    "addr:postcode":"38833",
    "addr:street":"Front St",
    "iso:country":"US",
    "sg:address":"92 Front St",
    "sg:city":"Burnsville",
    "sg:classifiers":[
        {
            "category":"Government",
            "subcategory":"Police Station",
            "type":"Public Place"
        }
    ],
    "sg:phone":"+1 662 427 9526",
    "sg:postcode":"38833",
    "sg:province":"MS",
    "sg:tags":[
        "department"
    ],
    "wof:name":"Burnsville Police Dept",
    "wof:placetype":"venue"
},
  "geometry": {"coordinates":[-88.319681,34.842494],"type":"Point"}
}