{
  "type": "Feature",
  "properties": {
    "addr:full":"805 W Park Ave Greenwood MS 38930",
    "addr:housenumber":"805",
    "addr:postcode":"38930",
    "addr:street":"W Park Ave",
    "iso:country":"US",
    "sg:address":"805 W Park Ave",
    "sg:city":"Greenwood",
    "sg:classifiers":[
        {
            "category":"Restaurant",
            "type":"Food & Drink"
        }
    ],
    "sg:menulink":"http://www.allmenus.com/ms/minter-city/133101-subway/menu/",
    "sg:phone":"+1 662 453 0490",
    "sg:postcode":"38930",
    "sg:province":"MS",
    "sg:tags":[
        "american",
        "sandwich"
    ],
    "wof:name":"Subway",
    "wof:placetype":"venue"
},
  "geometry": {"coordinates":[-90.204975,33.526517],"type":"Point"}
}