{
  "type": "Feature",
  "properties": {
    "iso:country":"US",
    "sg:address":"182 Main St",
    "sg:city":"Nettleton",
    "sg:classifiers":[
        {
            "category":"Education",
            "subcategory":"Library",
            "type":"Public Place"
        }
    ],
    "sg:phone":"+1 662 963 2014",
    "sg:postcode":"38858",
    "sg:province":"MS",
    "wof:name":"Nettleton City Library",
    "wof:placetype":"venue"
},
  "geometry": {"coordinates":[-88.627595,34.089013],"type":"Point"}
}