{
  "type": "Feature",
  "properties": {
    "iso:country":"US",
    "sg:address":"1703 Main St",
    "sg:city":"Southaven",
    "sg:classifiers":[
        {
            "category":"Shopping",
            "subcategory":"Florist",
            "type":"Retail Goods"
        }
    ],
    "sg:phone":"+1 662 393 9402",
    "sg:postcode":"38671",
    "sg:province":"MS",
    "wof:name":"A To Z Florist & Gifts",
    "wof:placetype":"venue"
},
  "geometry": {"coordinates":[-90.019693,34.991771],"type":"Point"}
}