{
  "type": "Feature",
  "properties": {
    "addr:full":"3249 Antioch Rd Randolph MS 38864",
    "addr:housenumber":"3249",
    "addr:postcode":"38864",
    "addr:street":"Antioch Rd",
    "iso:country":"US",
    "sg:address":"3249 Antioch Rd",
    "sg:city":"Randolph",
    "sg:classifiers":[
        {
            "category":"Building & Trades",
            "subcategory":"Construction",
            "type":"Services"
        }
    ],
    "sg:phone":"+1 662 489 7541",
    "sg:postcode":"38864",
    "sg:province":"MS",
    "sg:tags":[
        "contractor",
        "sub",
        "carpentry"
    ],
    "wof:name":"Kitchen Works Unlimited Inc",
    "wof:placetype":"venue"
},
  "geometry": {"coordinates":[-89.22829900000001,34.210315],"type":"Point"}
}