{
  "type": "Feature",
  "properties": {
    "iso:country":"US",
    "sg:address":"1818 Short Main St",
    "sg:city":"Columbus",
    "sg:classifiers":[
        {
            "category":"Retail",
            "subcategory":"Laundry & Dry Cleaning",
            "type":"Services"
        },
        {
            "category":"Shopping",
            "subcategory":"Clothing, Apparel, & Fashions",
            "type":"Retail Goods"
        }
    ],
    "sg:phone":"+1 662 245 1453",
    "sg:postcode":"39701",
    "sg:province":"MS",
    "sg:tags":[
        "alteration"
    ],
    "wof:name":"Sarah's Sewing Expertise",
    "wof:placetype":"venue"
},
  "geometry": {"coordinates":[-88.412077,33.497244],"type":"Point"}
}