{
  "type": "Feature",
  "properties": {
    "iso:country":"US",
    "sg:address":"1711 Graveline Rd",
    "sg:city":"Gautier",
    "sg:classifiers":[
        {
            "category":"Health Services",
            "subcategory":"Health Practitioner",
            "type":"Services"
        }
    ],
    "sg:phone":"+1 228 497 6000",
    "sg:postcode":"39553",
    "sg:province":"MS",
    "wof:name":"David N Penton Dr",
    "wof:placetype":"venue"
},
  "geometry": {"coordinates":[-88.636568,30.366781],"type":"Point"}
}