{
  "type": "Feature",
  "properties": {
    "iso:country":"US",
    "sg:address":"313 W Broadway St",
    "sg:city":"Yazoo City",
    "sg:classifiers":[
        {
            "category":"Restaurant",
            "type":"Food & Drink"
        }
    ],
    "sg:phone":"+1 662 746 9555",
    "sg:postcode":"39194",
    "sg:province":"MS",
    "wof:name":"P & K Kitchen",
    "wof:placetype":"venue"
},
  "geometry": {"coordinates":[-90.416631,32.848361],"type":"Point"}
}