{
  "type": "Feature",
  "properties": {
    "addr:full":"132 Westover Dr Hattiesburg MS 39402",
    "addr:housenumber":"132",
    "addr:postcode":"39402",
    "addr:street":"Westover Dr",
    "iso:country":"US",
    "sg:address":"132 Westover Dr",
    "sg:city":"Hattiesburg",
    "sg:classifiers":[
        {
            "category":"Government",
            "subcategory":"Court House",
            "type":"Public Place"
        }
    ],
    "sg:phone":"+1 601 264 2257",
    "sg:postcode":"39402",
    "sg:province":"MS",
    "sg:tags":[
        "legal"
    ],
    "sg:website":"www.richlandtitle.com",
    "wof:name":"Richard & Thomas",
    "wof:placetype":"venue"
},
  "geometry": {"coordinates":[-89.356279,31.324906],"type":"Point"}
}