{
  "type": "Feature",
  "properties": {
    "iso:country":"US",
    "sg:address":"2710 State Hwy 43 S",
    "sg:city":"Picayune",
    "sg:classifiers":[
        {
            "category":"Organizations",
            "subcategory":"Religious Organization",
            "type":"Services"
        }
    ],
    "sg:phone":"+1 601 798 6193",
    "sg:postcode":"39466",
    "sg:province":"MS",
    "wof:name":"Goodyear Baptist Church",
    "wof:placetype":"venue"
},
  "geometry": {"coordinates":[-89.63274800000001,30.51625],"type":"Point"}
}