{
  "type": "Feature",
  "properties": {
    "iso:country":"US",
    "sg:address":"401 N Main St",
    "sg:city":"Leland",
    "sg:classifiers":[
        {
            "category":"Banks & Credit Unions",
            "subcategory":"Bank",
            "type":"Services"
        }
    ],
    "sg:phone":"+1 662 686 4700",
    "sg:postcode":"38756",
    "sg:province":"MS",
    "sg:tags":[
        "depository",
        "banking",
        "check",
        "cashing"
    ],
    "wof:name":"A-1 Check Cashing Inc",
    "wof:placetype":"venue"
},
  "geometry": {"coordinates":[-90.897561,33.407275],"type":"Point"}
}