{
  "type": "Feature",
  "properties": {
    "iso:country":"US",
    "sg:address":"5250 Mini Farm Rd",
    "sg:city":"Meridian",
    "sg:classifiers":[
        {
            "category":"Building & Trades",
            "subcategory":"Landscaping Services",
            "type":"Services"
        }
    ],
    "sg:phone":"+1 601 485 4244",
    "sg:postcode":"39301",
    "sg:province":"MS",
    "sg:tags":[
        "landscape",
        "contractor"
    ],
    "wof:name":"Salazar's Lawn Care",
    "wof:placetype":"venue"
},
  "geometry": {"coordinates":[-88.651695,32.28946],"type":"Point"}
}