{
  "type": "Feature",
  "properties": {
    "iso:country":"US",
    "sg:address":"430 Hwy 80 E",
    "sg:city":"Jackson",
    "sg:classifiers":[
        {
            "category":"Freight",
            "type":"Transportation"
        }
    ],
    "sg:phone":"+1 601 939 4323",
    "sg:postcode":"39232",
    "sg:province":"MS",
    "sg:tags":[
        "operator",
        "trucking"
    ],
    "wof:name":"Landstar",
    "wof:placetype":"venue"
},
  "geometry": {"coordinates":[-90.17557600000001,32.281019],"type":"Point"}
}