{
  "type": "Feature",
  "properties": {
    "addr:full":"3350 Players Club Pkwy Memphis MS 38125",
    "addr:housenumber":"3350",
    "addr:postcode":"38125",
    "addr:street":"Players Club Pkwy",
    "iso:country":"US",
    "sg:address":"3350 Players Club Pkwy",
    "sg:city":"Memphis",
    "sg:classifiers":[
        {
            "category":"Restaurant",
            "type":"Food & Drink"
        }
    ],
    "sg:phone":"+1 901 255 8370",
    "sg:postcode":"38125",
    "sg:province":"MS",
    "wof:name":"Wencoast Restaurant Inc",
    "wof:placetype":"venue"
},
  "geometry": {"coordinates":[-89.785568,35.058186],"type":"Point"}
}