{
  "type": "Feature",
  "properties": {
    "addr:full":"414 E End St Cleveland MS 38732",
    "addr:housenumber":"414",
    "addr:postcode":"38732",
    "addr:street":"E End St",
    "iso:country":"US",
    "sg:address":"414 E End St",
    "sg:city":"Cleveland",
    "sg:classifiers":[
        {
            "category":"Organizations",
            "subcategory":"Religious Organization",
            "type":"Services"
        }
    ],
    "sg:phone":"+1 662 846 1119",
    "sg:postcode":"38732",
    "sg:province":"MS",
    "sg:tags":[
        "church"
    ],
    "wof:name":"New Life Church",
    "wof:placetype":"venue"
},
  "geometry": {"coordinates":[-90.712688,33.74528],"type":"Point"}
}