{
  "type": "Feature",
  "properties": {
    "iso:country":"US",
    "sg:address":"2211 5th St",
    "sg:city":"Meridian",
    "sg:classifiers":[
        {
            "category":"Banks & Credit Unions",
            "subcategory":"Bank",
            "type":"Services"
        }
    ],
    "sg:phone":"+1 601 481 1051",
    "sg:postcode":"39301",
    "sg:province":"MS",
    "wof:name":"First State Bank",
    "wof:placetype":"venue"
},
  "geometry": {"coordinates":[-88.699923,32.363817],"type":"Point"}
}