{
  "type": "Feature",
  "properties": {
    "iso:country":"US",
    "sg:address":"4423 I- 55 N",
    "sg:city":"Jackson",
    "sg:classifiers":[
        {
            "category":"Organizations",
            "subcategory":"Religious Organization",
            "type":"Services"
        }
    ],
    "sg:phone":"+1 601 366 2055",
    "sg:postcode":"39206",
    "sg:province":"MS",
    "sg:tags":[
        "church"
    ],
    "wof:name":"Christ Lutheran Church L C M S",
    "wof:placetype":"venue"
},
  "geometry": {"coordinates":[-90.153882,32.35068],"type":"Point"}
}