{
  "type": "Feature",
  "properties": {
    "addr:full":"914 Co Rd 413 Houlka MS 38850",
    "addr:housenumber":"914",
    "addr:postcode":"38850",
    "addr:street":"Co Rd 413 Houlka",
    "iso:country":"US",
    "sg:address":"914 Co Rd 413",
    "sg:city":"Houlka",
    "sg:classifiers":[
        {
            "category":"Insurance",
            "subcategory":"Insurance Agent",
            "type":"Services"
        }
    ],
    "sg:phone":"+1 662 568 3354",
    "sg:postcode":"38850",
    "sg:province":"MS",
    "wof:name":"Safeco Insurance",
    "wof:placetype":"venue"
},
  "geometry": {"coordinates":[-88.94302999999999,34.060418],"type":"Point"}
}