{
  "type": "Feature",
  "properties": {
    "iso:country":"US",
    "sg:address":"945 N State St",
    "sg:city":"Jackson",
    "sg:classifiers":[
        {
            "category":"Insurance",
            "subcategory":"Insurance Agent",
            "type":"Services"
        }
    ],
    "sg:phone":"+1 601 355 7489",
    "sg:postcode":"39202",
    "sg:province":"MS",
    "wof:name":"Transamerica Insurance",
    "wof:placetype":"venue"
},
  "geometry": {"coordinates":[-90.17821499999999,32.3112],"type":"Point"}
}