{
  "type": "Feature",
  "properties": {
    "iso:country":"US",
    "sg:address":"4892 Welch Rd",
    "sg:city":"Liberty",
    "sg:classifiers":[
        {
            "category":"Bars & Pubs",
            "type":"Food & Drink"
        }
    ],
    "sg:phone":"+1 601 639 4031",
    "sg:postcode":"39645",
    "sg:province":"MS",
    "sg:tags":[
        "drinking"
    ],
    "wof:name":"Club 33",
    "wof:placetype":"venue"
},
  "geometry": {"coordinates":[-90.775156,31.252783],"type":"Point"}
}