{
  "type": "Feature",
  "properties": {
    "addr:full":"718 Hwy 373 Columbus MS 39705",
    "addr:housenumber":"718",
    "addr:postcode":"39705",
    "addr:street":"Hwy 373",
    "iso:country":"US",
    "sg:address":"718 Hwy 373",
    "sg:city":"Columbus",
    "sg:classifiers":[
        {
            "category":"Restaurant",
            "type":"Food & Drink"
        }
    ],
    "sg:phone":"+1 662 329 5210",
    "sg:postcode":"39705",
    "sg:province":"MS",
    "wof:name":"Family Pit",
    "wof:placetype":"venue"
},
  "geometry": {"coordinates":[-88.447765,33.590276],"type":"Point"}
}