{
  "type": "Feature",
  "properties": {
    "iso:country":"US",
    "sg:address":"378 N Slayden Rd",
    "sg:city":"Lamar",
    "sg:classifiers":[
        {
            "category":"Building & Trades",
            "subcategory":"Construction",
            "type":"Services"
        }
    ],
    "sg:phone":"+1 662 781 8090",
    "sg:postcode":"38642",
    "sg:province":"MS",
    "sg:tags":[
        "maintenance",
        "contractor"
    ],
    "wof:name":"Exterior Design & Maintenance",
    "wof:placetype":"venue"
},
  "geometry": {"coordinates":[-89.441084,34.95828],"type":"Point"}
}