{
  "type": "Feature",
  "properties": {
    "iso:country":"US",
    "sg:address":"10461 Bayou Bernard Rd S",
    "sg:city":"Gulfport",
    "sg:classifiers":[
        {
            "category":"Manufacturing",
            "subcategory":"Retail Goods",
            "type":"Manufacturing & Wholesale Goods"
        }
    ],
    "sg:phone":"+1 228 832 9572",
    "sg:postcode":"39503",
    "sg:province":"MS",
    "sg:tags":[
        "product",
        "mfg"
    ],
    "wof:name":"Mg Mfg",
    "wof:placetype":"venue"
},
  "geometry": {"coordinates":[-89.154213,30.436751],"type":"Point"}
}