{
  "type": "Feature",
  "properties": {
    "addr:full":"1062 Highland Colony Pkwy Ridgeland MS 39157",
    "addr:housenumber":"1062",
    "addr:postcode":"39157",
    "addr:street":"Highland Colony Pkwy",
    "iso:country":"US",
    "sg:address":"1062 Highland Colony Pkwy",
    "sg:city":"Ridgeland",
    "sg:classifiers":[
        {
            "category":"Organizations",
            "subcategory":"Professional Association",
            "type":"Services"
        }
    ],
    "sg:phone":"+1 601 605 2554",
    "sg:postcode":"39157",
    "sg:province":"MS",
    "sg:tags":[
        "business"
    ],
    "wof:name":"Madison Cnty Chamber Commerce",
    "wof:placetype":"venue"
},
  "geometry": {"coordinates":[-90.15441800000001,32.454132],"type":"Point"}
}