{
  "type": "Feature",
  "properties": {
    "iso:country":"US",
    "sg:address":"127 S George St",
    "sg:city":"Petal",
    "sg:classifiers":[
        {
            "category":"Professional",
            "subcategory":"Business Services",
            "type":"Services"
        }
    ],
    "sg:phone":"+1 601 450 1676",
    "sg:postcode":"39465",
    "sg:province":"MS",
    "sg:tags":[
        "electrical",
        "system",
        "power"
    ],
    "wof:name":"M & C Contractors",
    "wof:placetype":"venue"
},
  "geometry": {"coordinates":[-89.26715,31.34597],"type":"Point"}
}