{
  "type": "Feature",
  "properties": {
    "iso:country":"US",
    "sg:address":"1325 Gum Grove Rd SW",
    "sg:city":"Brookhaven",
    "sg:classifiers":[
        {
            "category":"Professional",
            "subcategory":"Business Services",
            "type":"Services"
        }
    ],
    "sg:phone":"+1 601 823 5443",
    "sg:postcode":"39601",
    "sg:province":"MS",
    "sg:tags":[
        "automotive",
        "electronics"
    ],
    "wof:name":"Alfords Automotive Electronics",
    "wof:placetype":"venue"
},
  "geometry": {"coordinates":[-90.566958,31.469655],"type":"Point"}
}