{
  "type": "Feature",
  "properties": {
    "iso:country":"US",
    "sg:address":"327 1st St",
    "sg:city":"Houston",
    "sg:classifiers":[
        {
            "category":"Recreation",
            "type":"Entertainment"
        }
    ],
    "sg:phone":"+1 662 456 4161",
    "sg:postcode":"38851",
    "sg:province":"MS",
    "sg:tags":[
        "skating",
        "rink"
    ],
    "wof:name":"Houston Funland Skating Rink",
    "wof:placetype":"venue"
},
  "geometry": {"coordinates":[-89.005178,33.909165],"type":"Point"}
}