{
  "type": "Feature",
  "properties": {
    "iso:country":"US",
    "sg:address":"1301 Monroe Ave",
    "sg:city":"Oxford",
    "sg:classifiers":[
        {
            "category":"Government",
            "subcategory":"Court House",
            "type":"Public Place"
        }
    ],
    "sg:phone":"+1 662 234 3304",
    "sg:postcode":"38655",
    "sg:province":"MS",
    "sg:tags":[
        "county",
        "counsel"
    ],
    "wof:name":"Lafayette District Attorney",
    "wof:placetype":"venue"
},
  "geometry": {"coordinates":[-89.51793600000001,34.367312],"type":"Point"}
}