{
  "type": "Feature",
  "properties": {
    "addr:full":"615 Pearl Park Plz Pearl MS 39208",
    "addr:housenumber":"615",
    "addr:postcode":"39208",
    "addr:street":"Pearl Park Plz",
    "iso:country":"US",
    "sg:address":"615 Pearl Park Plz",
    "sg:city":"Pearl",
    "sg:classifiers":[
        {
            "category":"Retail",
            "subcategory":"Laundry & Dry Cleaning",
            "type":"Services"
        }
    ],
    "sg:phone":"+1 601 664 0244",
    "sg:postcode":"39208",
    "sg:province":"MS",
    "sg:tags":[
        "cleaners",
        "rug",
        "carpet"
    ],
    "wof:name":"TPS Carpet Care Inc",
    "wof:placetype":"venue"
},
  "geometry": {"coordinates":[-90.119389,32.285209],"type":"Point"}
}