{
  "type": "Feature",
  "properties": {
    "iso:country":"US",
    "sg:address":"1720 16th Ave",
    "sg:city":"Meridian",
    "sg:classifiers":[
        {
            "category":"Real Estate",
            "subcategory":"Real Estate Agent",
            "type":"Services"
        }
    ],
    "sg:phone":"+1 601 483 3981",
    "sg:postcode":"39301",
    "sg:province":"MS",
    "sg:tags":[
        "management"
    ],
    "wof:name":"Global Housing Ctr",
    "wof:placetype":"venue"
},
  "geometry": {"coordinates":[-88.694447,32.3752],"type":"Point"}
}