{
  "type": "Feature",
  "properties": {
    "addr:full":"18381 28th St Long Beach MS 39560",
    "addr:housenumber":"18381",
    "addr:postcode":"39560",
    "addr:street":"28Th St",
    "iso:country":"US",
    "sg:address":"18381 28th St",
    "sg:city":"Long Beach",
    "sg:classifiers":[
        {
            "category":"Organizations",
            "subcategory":"Religious Organization",
            "type":"Services"
        }
    ],
    "sg:phone":"+1 228 868 9500",
    "sg:postcode":"39560",
    "sg:province":"MS",
    "sg:tags":[
        "church"
    ],
    "sg:website":"www.gcworshipcenter.org",
    "wof:name":"Gulf Coast Worship Ctr",
    "wof:placetype":"venue"
},
  "geometry": {"coordinates":[-89.147088,30.383781],"type":"Point"}
}