{
  "type": "Feature",
  "properties": {
    "iso:country":"US",
    "sg:address":"210 Cypress St",
    "sg:city":"Hollandale",
    "sg:classifiers":[
        {
            "category":"Farming",
            "subcategory":"Aquatic Farm",
            "type":"Manufacturing & Wholesale Goods"
        }
    ],
    "sg:phone":"+1 662 827 2408",
    "sg:postcode":"38748",
    "sg:province":"MS",
    "wof:name":"Elizabeth B Domino",
    "wof:placetype":"venue"
},
  "geometry": {"coordinates":[-90.850844,33.18076],"type":"Point"}
}