{
  "type": "Feature",
  "properties": {
    "iso:country":"US",
    "sg:address":"7100 State Hwy 584",
    "sg:city":"Osyka",
    "sg:classifiers":[
        {
            "category":"Farming",
            "subcategory":"Dairy Farm",
            "type":"Manufacturing & Wholesale Goods"
        }
    ],
    "sg:phone":"+1 601 542 5810",
    "sg:postcode":"39657",
    "sg:province":"MS",
    "wof:name":"Lawson Dairy Farm",
    "wof:placetype":"venue"
},
  "geometry": {"coordinates":[-90.648507,31.024063],"type":"Point"}
}