{
  "type": "Feature",
  "properties": {
    "iso:country":"US",
    "sg:address":"702 Briarwood Rd",
    "sg:city":"Meridian",
    "sg:classifiers":[
        {
            "category":"Education",
            "subcategory":"School",
            "type":"Public Place"
        }
    ],
    "sg:phone":"+1 601 679 8670",
    "sg:postcode":"39305",
    "sg:province":"MS",
    "wof:name":"Lauderdale Northeast High",
    "wof:placetype":"venue"
},
  "geometry": {"coordinates":[-88.646682,32.47202],"type":"Point"}
}