{
  "type": "Feature",
  "properties": {
    "iso:country":"US",
    "sg:address":"2802 Market St",
    "sg:city":"Pascagoula",
    "sg:classifiers":[
        {
            "category":"Professional",
            "type":"Services"
        }
    ],
    "sg:phone":"+1 228 762 3536",
    "sg:postcode":"39567",
    "sg:province":"MS",
    "sg:tags":[
        "establishment"
    ],
    "wof:name":"Harper Lanelle Enterprises",
    "wof:placetype":"venue"
},
  "geometry": {"coordinates":[-88.548441,30.36294],"type":"Point"}
}