{
  "type": "Feature",
  "properties": {
    "iso:country":"US",
    "sg:address":"21110 Pineville Rd",
    "sg:city":"Long Beach",
    "sg:classifiers":[
        {
            "category":"Retail",
            "subcategory":"Portrait Studio",
            "type":"Services"
        }
    ],
    "sg:phone":"+1 228 863 3608",
    "sg:postcode":"39560",
    "sg:province":"MS",
    "sg:tags":[
        "photo"
    ],
    "wof:name":"James Wedworth Photography",
    "wof:placetype":"venue"
},
  "geometry": {"coordinates":[-89.196535,30.361651],"type":"Point"}
}