{
  "type": "Feature",
  "properties": {
    "iso:country":"US",
    "sg:address":"235 Alabama St",
    "sg:city":"Columbus",
    "sg:classifiers":[
        {
            "category":"Government",
            "subcategory":"Post Office",
            "type":"Public Place"
        }
    ],
    "sg:phone":"+1 662 328 0341",
    "sg:postcode":"39702",
    "sg:province":"MS",
    "sg:tags":[
        "postal",
        "us"
    ],
    "wof:name":"Fairlane Station",
    "wof:placetype":"venue"
},
  "geometry": {"coordinates":[-88.383449,33.495957],"type":"Point"}
}