{
  "type": "Feature",
  "properties": {
    "iso:country":"US",
    "sg:address":"236 Brendalwood Blvd",
    "sg:city":"Brandon",
    "sg:classifiers":[
        {
            "category":"Retail",
            "subcategory":"Repair Shop",
            "type":"Services"
        }
    ],
    "sg:phone":"+1 601 919 0842",
    "sg:postcode":"39047",
    "sg:province":"MS",
    "wof:name":"Lindas Custom Cleaning",
    "wof:placetype":"venue"
},
  "geometry": {"coordinates":[-90.034306,32.381278],"type":"Point"}
}