{
  "type": "Feature",
  "properties": {
    "iso:country":"US",
    "sg:address":"902 Goodman Rd W",
    "sg:city":"Horn Lake",
    "sg:classifiers":[
        {
            "category":"Restaurant",
            "type":"Food & Drink"
        }
    ],
    "sg:phone":"+1 662 349 0646",
    "sg:postcode":"38637",
    "sg:province":"MS",
    "sg:tags":[
        "eating"
    ],
    "wof:name":"Popeyes Chicken & Biscuits",
    "wof:placetype":"venue"
},
  "geometry": {"coordinates":[-90.004384,34.962784],"type":"Point"}
}