{
  "type": "Feature",
  "properties": {
    "iso:country":"US",
    "sg:address":"2990 Co Rd 548",
    "sg:city":"Ripley",
    "sg:classifiers":[
        {
            "category":"Utilities",
            "subcategory":"Mobile Phone",
            "type":"Services"
        }
    ],
    "sg:phone":"+1 662 837 8375",
    "sg:postcode":"38663",
    "sg:province":"MS",
    "sg:tags":[
        "telephone",
        "cellular"
    ],
    "wof:name":"Century Tel",
    "wof:placetype":"venue"
},
  "geometry": {"coordinates":[-88.71859499999999,34.725034],"type":"Point"}
}