{
  "type": "Feature",
  "properties": {
    "iso:country":"US",
    "sg:address":"2128 Ingalls Ave",
    "sg:city":"Pascagoula",
    "sg:classifiers":[
        {
            "category":"Professional",
            "subcategory":"Lawyer & Legal Services",
            "type":"Services"
        }
    ],
    "sg:phone":"+1 228 762 8153",
    "sg:postcode":"39567",
    "sg:province":"MS",
    "wof:name":"Mestayer Roland J Jr",
    "wof:placetype":"venue"
},
  "geometry": {"coordinates":[-88.54244199999999,30.354772],"type":"Point"}
}