{
  "type": "Feature",
  "properties": {
    "iso:country":"US",
    "sg:address":"5473 Pine Lane Dr",
    "sg:city":"Jackson",
    "sg:classifiers":[
        {
            "category":"Shopping",
            "subcategory":"Florist",
            "type":"Retail Goods"
        }
    ],
    "sg:phone":"+1 601 978 3066",
    "sg:postcode":"39211",
    "sg:province":"MS",
    "wof:name":"Roberts Mindy J Flowers Tables",
    "wof:placetype":"venue"
},
  "geometry": {"coordinates":[-90.145025,32.37868],"type":"Point"}
}