{
  "type": "Feature",
  "properties": {
    "iso:country":"US",
    "sg:address":"1702 Weed St",
    "sg:city":"Ocean Springs",
    "sg:classifiers":[
        {
            "category":"Organizations",
            "subcategory":"Religious Organization",
            "type":"Services"
        }
    ],
    "sg:phone":"+1 228 875 4008",
    "sg:postcode":"39564",
    "sg:province":"MS",
    "sg:tags":[
        "church"
    ],
    "wof:name":"Macedonia Baptist Church",
    "wof:placetype":"venue"
},
  "geometry": {"coordinates":[-88.818803,30.414652],"type":"Point"}
}