{
  "type": "Feature",
  "properties": {
    "iso:country":"US",
    "sg:address":"208 Pine St",
    "sg:city":"Seminary",
    "sg:classifiers":[
        {
            "category":"Organizations",
            "subcategory":"Religious Organization",
            "type":"Services"
        }
    ],
    "sg:phone":"+1 601 722 4650",
    "sg:postcode":"39479",
    "sg:province":"MS",
    "sg:tags":[
        "church"
    ],
    "wof:name":"Seminary United Methodist Chr",
    "wof:placetype":"venue"
},
  "geometry": {"coordinates":[-89.49265200000001,31.563695],"type":"Point"}
}