{
  "type": "Feature",
  "properties": {
    "iso:country":"US",
    "sg:address":"2429 5th St N",
    "sg:city":"Columbus",
    "sg:classifiers":[
        {
            "category":"Social Services",
            "subcategory":"Job Training",
            "type":"Services"
        }
    ],
    "sg:phone":"+1 662 328 4542",
    "sg:postcode":"39705",
    "sg:province":"MS",
    "sg:tags":[
        "rehabilitation"
    ],
    "wof:name":"Rehab At Work",
    "wof:placetype":"venue"
},
  "geometry": {"coordinates":[-88.42900899999999,33.523989],"type":"Point"}
}