{
  "type": "Feature",
  "properties": {
    "iso:country":"US",
    "sg:address":"535 Schwem Ave",
    "sg:city":"Brookhaven",
    "sg:classifiers":[
        {
            "category":"Real Estate",
            "subcategory":"Real Estate Agent",
            "type":"Services"
        }
    ],
    "sg:phone":"+1 601 833 4077",
    "sg:postcode":"39601",
    "sg:province":"MS",
    "wof:name":"Joyce Asken Realty",
    "wof:placetype":"venue"
},
  "geometry": {"coordinates":[-90.44931,31.582626],"type":"Point"}
}