{
  "type": "Feature",
  "properties": {
    "iso:country":"US",
    "sg:address":"1350 Hwy 80 W",
    "sg:city":"Jackson",
    "sg:classifiers":[
        {
            "category":"Home & Garden",
            "subcategory":"Building Materials",
            "type":"Retail Goods"
        }
    ],
    "sg:phone":"+1 601 354 5441",
    "sg:postcode":"39204",
    "sg:province":"MS",
    "sg:tags":[
        "plumbing",
        "fixture",
        "supply"
    ],
    "sg:website":"www.noland.com",
    "wof:name":"Noland Co",
    "wof:placetype":"venue"
},
  "geometry": {"coordinates":[-90.210166,32.28665],"type":"Point"}
}