{
  "type": "Feature",
  "properties": {
    "addr:full":"10 Morgantown Rd Natchez MS 39120",
    "addr:housenumber":"10",
    "addr:postcode":"39120",
    "addr:street":"Morgantown Rd",
    "iso:country":"US",
    "sg:address":"10 Morgantown Rd",
    "sg:city":"Natchez",
    "sg:classifiers":[
        {
            "category":"Organizations",
            "subcategory":"Religious Organization",
            "type":"Services"
        }
    ],
    "sg:phone":"+1 601 442 7250",
    "sg:postcode":"39120",
    "sg:province":"MS",
    "sg:tags":[
        "church"
    ],
    "wof:name":"Assumption Catholic Church",
    "wof:placetype":"venue"
},
  "geometry": {"coordinates":[-91.353776,31.564449],"type":"Point"}
}