{
  "type": "Feature",
  "properties": {
    "addr:full":"617 Renaissance Way Ridgeland MS 39157",
    "addr:housenumber":"617",
    "addr:postcode":"39157",
    "addr:street":"Renaissance Way",
    "iso:country":"US",
    "sg:address":"617 Renaissance Way",
    "sg:city":"Ridgeland",
    "sg:classifiers":[
        {
            "category":"Real Estate",
            "subcategory":"Real Estate Agent",
            "type":"Services"
        }
    ],
    "sg:phone":"+1 601 992 0121",
    "sg:postcode":"39157",
    "sg:province":"MS",
    "sg:website":"www.goodearthrealty.com",
    "wof:name":"Good Earth Realty Inc",
    "wof:placetype":"venue"
},
  "geometry": {"coordinates":[-90.160618,32.417611],"type":"Point"}
}