{
  "type": "Feature",
  "properties": {
    "addr:full":"715 E McDowell Rd Jackson MS 39204",
    "addr:housenumber":"715",
    "addr:postcode":"39204",
    "addr:street":"E Mcdowell Rd",
    "iso:country":"US",
    "sg:address":"715 E McDowell Rd",
    "sg:city":"Jackson",
    "sg:classifiers":[
        {
            "category":"Manufacturing",
            "subcategory":"Rubber & Plastics",
            "type":"Manufacturing & Wholesale Goods"
        }
    ],
    "sg:phone":"+1 601 948 2575",
    "sg:postcode":"39204",
    "sg:province":"MS",
    "sg:tags":[
        "gasket"
    ],
    "sg:website":"www.msrubber.com",
    "wof:name":"M S Rubber",
    "wof:placetype":"venue"
},
  "geometry": {"coordinates":[-90.203253,32.268201],"type":"Point"}
}