{
  "type": "Feature",
  "properties": {
    "iso:country":"US",
    "sg:address":"4305 Denny Ave",
    "sg:city":"Pascagoula",
    "sg:classifiers":[
        {
            "category":"Health Services",
            "subcategory":"Doctor",
            "type":"Services"
        }
    ],
    "sg:phone":"+1 228 762 2044",
    "sg:postcode":"39581",
    "sg:province":"MS",
    "sg:tags":[
        "physician",
        "surgeon"
    ],
    "wof:name":"Cooper Family Medical Ctr",
    "wof:placetype":"venue"
},
  "geometry": {"coordinates":[-88.527325,30.378046],"type":"Point"}
}