{
  "type": "Feature",
  "properties": {
    "iso:country":"US",
    "sg:address":"301 Boardman Ave",
    "sg:city":"Bay St Louis",
    "sg:classifiers":[
        {
            "category":"Arts & Performance",
            "subcategory":"Theater",
            "type":"Entertainment"
        }
    ],
    "sg:phone":"+1 228 467 2587",
    "sg:postcode":"39520",
    "sg:province":"MS",
    "wof:name":"Bay St Louis Little Theater",
    "wof:placetype":"venue"
},
  "geometry": {"coordinates":[-89.338875,30.331521],"type":"Point"}
}