{
  "type": "Feature",
  "properties": {
    "iso:country":"US",
    "sg:address":"252 Turnpike Rd",
    "sg:city":"Pontotoc",
    "sg:classifiers":[
        {
            "category":"Shopping",
            "subcategory":"Florist",
            "type":"Retail Goods"
        }
    ],
    "sg:phone":"+1 662 489 1751",
    "sg:postcode":"38863",
    "sg:province":"MS",
    "wof:name":"Parker Place Flowers & Gifts",
    "wof:placetype":"venue"
},
  "geometry": {"coordinates":[-89.019988,34.258392],"type":"Point"}
}