{
  "type": "Feature",
  "properties": {
    "iso:country":"US",
    "sg:address":"803 Stansel Dr",
    "sg:city":"Ruleville",
    "sg:classifiers":[
        {
            "category":"Social Services",
            "subcategory":"Child Care",
            "type":"Services"
        }
    ],
    "sg:phone":"+1 662 756 2607",
    "sg:postcode":"38771",
    "sg:province":"MS",
    "sg:tags":[
        "kindergarten",
        "academic",
        "school"
    ],
    "wof:name":"Ruleville Community Headstart",
    "wof:placetype":"venue"
},
  "geometry": {"coordinates":[-90.542783,33.736108],"type":"Point"}
}