{
  "type": "Feature",
  "properties": {
    "addr:full":"1311 Ellis Ave Jackson MS 39204",
    "addr:housenumber":"1311",
    "addr:postcode":"39204",
    "addr:street":"Ellis Ave",
    "iso:country":"US",
    "sg:address":"1311 Ellis Ave",
    "sg:city":"Jackson",
    "sg:classifiers":[
        {
            "category":"Shopping",
            "subcategory":"Used Merchandise",
            "type":"Retail Goods"
        }
    ],
    "sg:phone":"+1 601 352 7300",
    "sg:postcode":"39204",
    "sg:province":"MS",
    "sg:tags":[
        "pawnbroker"
    ],
    "wof:name":"Speedee Cash",
    "wof:placetype":"venue"
},
  "geometry": {"coordinates":[-90.227903,32.294895],"type":"Point"}
}