{
  "type": "Feature",
  "properties": {
    "iso:country":"US",
    "sg:address":"499 S Gloster St",
    "sg:city":"Tupelo",
    "sg:classifiers":[
        {
            "category":"Shopping",
            "subcategory":"Gifts & Souvenirs",
            "type":"Retail Goods"
        }
    ],
    "sg:phone":"+1 662 841 5644",
    "sg:postcode":"38801",
    "sg:province":"MS",
    "sg:tags":[
        "party",
        "supply"
    ],
    "wof:name":"Extreme Glow Na Corp",
    "wof:placetype":"venue"
},
  "geometry": {"coordinates":[-88.71647,34.25022],"type":"Point"}
}