{
  "type": "Feature",
  "properties": {
    "addr:full":"141 Pine Grove Ave Biloxi MS 39531",
    "addr:housenumber":"141",
    "addr:postcode":"39531",
    "addr:street":"Pine Grove Ave",
    "iso:country":"US",
    "sg:address":"141 Pine Grove Ave",
    "sg:city":"Biloxi",
    "sg:classifiers":[
        {
            "category":"Professional",
            "type":"Services"
        },
        {
            "category":"Professional",
            "subcategory":"Management & Consulting",
            "type":"Services"
        }
    ],
    "sg:phone":"+1 228 594 0199",
    "sg:postcode":"39531",
    "sg:province":"MS",
    "sg:tags":[
        "establishment"
    ],
    "wof:name":"Bright Star Group LLC",
    "wof:placetype":"venue"
},
  "geometry": {"coordinates":[-88.980405,30.393457],"type":"Point"}
}