{
  "type": "Feature",
  "properties": {
    "addr:full":"1230 Payton Dr N Southaven MS 38671",
    "addr:housenumber":"1230",
    "addr:postcode":"38671",
    "addr:street":"Payton Dr N",
    "iso:country":"US",
    "sg:address":"1230 Payton Dr N",
    "sg:city":"Southaven",
    "sg:classifiers":[
        {
            "category":"Real Estate",
            "subcategory":"Real Estate Services",
            "type":"Services"
        }
    ],
    "sg:phone":"+1 662 280 1177",
    "sg:postcode":"38671",
    "sg:province":"MS",
    "sg:tags":[
        "abstract",
        "title"
    ],
    "wof:name":"Thomas Abstract",
    "wof:placetype":"venue"
},
  "geometry": {"coordinates":[-90.012041,34.939948],"type":"Point"}
}