{
  "type": "Feature",
  "properties": {
    "addr:full":"713 N 13th St Columbus MS 39701",
    "addr:housenumber":"713",
    "addr:postcode":"39701",
    "addr:street":"N 13Th St",
    "iso:country":"US",
    "sg:address":"713 N 13th St",
    "sg:city":"Columbus",
    "sg:classifiers":[
        {
            "category":"Personal",
            "subcategory":"Beauty Salon",
            "type":"Services"
        }
    ],
    "sg:phone":"+1 662 327 9202",
    "sg:postcode":"39701",
    "sg:province":"MS",
    "sg:tags":[
        "shop",
        "manicuring"
    ],
    "wof:name":"Ruby's House Of Royalty",
    "wof:placetype":"venue"
},
  "geometry": {"coordinates":[-88.419788,33.503489],"type":"Point"}
}