{
  "type": "Feature",
  "properties": {
    "addr:full":"1204 Love St Brookhaven MS 39601",
    "addr:housenumber":"1204",
    "addr:postcode":"39601",
    "addr:street":"Love St",
    "iso:country":"US",
    "sg:address":"1204 Love St",
    "sg:city":"Brookhaven",
    "sg:classifiers":[
        {
            "category":"Organizations",
            "subcategory":"Religious Organization",
            "type":"Services"
        }
    ],
    "sg:phone":"+1 601 833 8661",
    "sg:postcode":"39601",
    "sg:province":"MS",
    "sg:tags":[
        "church"
    ],
    "wof:name":"First Apostolic United Pent",
    "wof:placetype":"venue"
},
  "geometry": {"coordinates":[-90.44844500000001,31.597212],"type":"Point"}
}