{
  "type": "Feature",
  "properties": {
    "iso:country":"US",
    "sg:address":"810 Harrison St",
    "sg:city":"Tupelo",
    "sg:classifiers":[
        {
            "category":"Shopping",
            "subcategory":"Used Merchandise",
            "type":"Retail Goods"
        }
    ],
    "sg:phone":"+1 662 840 8100",
    "sg:postcode":"38801",
    "sg:province":"MS",
    "wof:name":"Shabby Chic Boutique",
    "wof:placetype":"venue"
},
  "geometry": {"coordinates":[-88.717456,34.245323],"type":"Point"}
}