{
  "type": "Feature",
  "properties": {
    "iso:country":"US",
    "sg:address":"3504 Rocky Branch Rd",
    "sg:city":"Sumrall",
    "sg:classifiers":[
        {
            "category":"Retail",
            "subcategory":"Veterinary Services",
            "type":"Services"
        }
    ],
    "sg:phone":"+1 601 758 4040",
    "sg:postcode":"39482",
    "sg:province":"MS",
    "sg:tags":[
        "hospital",
        "animal"
    ],
    "wof:name":"V P's Animal Clinic",
    "wof:placetype":"venue"
},
  "geometry": {"coordinates":[-89.579419,31.375451],"type":"Point"}
}