{
  "type": "Feature",
  "properties": {
    "iso:country":"US",
    "sg:address":"3994 N Gloster St",
    "sg:city":"Tupelo",
    "sg:classifiers":[
        {
            "category":"Restaurant",
            "type":"Food & Drink"
        }
    ],
    "sg:phone":"+1 662 844 6777",
    "sg:postcode":"38804",
    "sg:province":"MS",
    "sg:tags":[
        "eating"
    ],
    "wof:name":"Waffle House",
    "wof:placetype":"venue"
},
  "geometry": {"coordinates":[-88.706698,34.315542],"type":"Point"}
}