{
  "type": "Feature",
  "properties": {
    "iso:country":"US",
    "sg:address":"2550 Crestleigh Mnr",
    "sg:city":"Jackson",
    "sg:classifiers":[
        {
            "category":"Building & Trades",
            "subcategory":"Landscaping Services",
            "type":"Services"
        }
    ],
    "sg:phone":"+1 601 346 6369",
    "sg:postcode":"39204",
    "sg:province":"MS",
    "wof:name":"Commercial Mobile Lawn Eqp",
    "wof:placetype":"venue"
},
  "geometry": {"coordinates":[-90.26714,32.272889],"type":"Point"}
}