{
  "type": "Feature",
  "properties": {
    "addr:full":"204 Race St Rolling Fork MS 39159",
    "addr:housenumber":"204",
    "addr:postcode":"39159",
    "addr:street":"Race St",
    "iso:country":"US",
    "sg:address":"204 Race St",
    "sg:city":"Rolling Fork",
    "sg:classifiers":[
        {
            "category":"Social Services",
            "subcategory":"Child Care",
            "type":"Services"
        }
    ],
    "sg:phone":"+1 662 873 2183",
    "sg:postcode":"39159",
    "sg:province":"MS",
    "wof:name":"Kids Under Construction",
    "wof:placetype":"venue"
},
  "geometry": {"coordinates":[-90.880872,32.905785],"type":"Point"}
}