{
  "type": "Feature",
  "properties": {
    "addr:full":"221 Lower Woodville Rd Natchez MS 39120",
    "addr:housenumber":"221",
    "addr:postcode":"39120",
    "addr:street":"Lower Woodville Rd",
    "iso:country":"US",
    "sg:address":"221 Lower Woodville Rd",
    "sg:city":"Natchez",
    "sg:classifiers":[
        {
            "category":"Government",
            "subcategory":"Jail",
            "type":"Public Place"
        }
    ],
    "sg:phone":"+1 601 446 7296",
    "sg:postcode":"39120",
    "sg:province":"MS",
    "sg:tags":[
        "govt",
        "state",
        "institution"
    ],
    "wof:name":"Corrections DEPT",
    "wof:placetype":"venue"
},
  "geometry": {"coordinates":[-91.404042,31.528459],"type":"Point"}
}