{
  "type": "Feature",
  "properties": {
    "addr:full":"1022 N 7th Ave Laurel MS 39440",
    "addr:housenumber":"1022",
    "addr:postcode":"39440",
    "addr:street":"N 7Th Ave",
    "iso:country":"US",
    "sg:address":"1022 N 7th Ave",
    "sg:city":"Laurel",
    "sg:classifiers":[
        {
            "category":"Professional",
            "subcategory":"Business Services",
            "type":"Services"
        }
    ],
    "sg:phone":"+1 601 422 0356",
    "sg:postcode":"39440",
    "sg:province":"MS",
    "wof:name":"Advertising Design Services",
    "wof:placetype":"venue"
},
  "geometry": {"coordinates":[-89.134675,31.701992],"type":"Point"}
}