{
  "type": "Feature",
  "properties": {
    "iso:country":"US",
    "sg:address":"186 E College Ave",
    "sg:city":"Holly Springs",
    "sg:classifiers":[
        {
            "category":"Banks & Credit Unions",
            "subcategory":"Bank",
            "type":"Services"
        }
    ],
    "sg:phone":"+1 662 252 3423",
    "sg:postcode":"38635",
    "sg:province":"MS",
    "wof:name":"Merchants & Farmers Bank",
    "wof:placetype":"venue"
},
  "geometry": {"coordinates":[-89.44734200000001,34.768524],"type":"Point"}
}