{
  "type": "Feature",
  "properties": {
    "iso:country":"US",
    "sg:address":"556 Cypress Ln",
    "sg:city":"Greenville",
    "sg:classifiers":[
        {
            "category":"Organizations",
            "subcategory":"Religious Organization",
            "type":"Services"
        }
    ],
    "sg:phone":"+1 662 378 8818",
    "sg:postcode":"38701",
    "sg:province":"MS",
    "sg:tags":[
        "place",
        "worship",
        "church"
    ],
    "sg:website":"www.maranathaag.org",
    "wof:name":"Maranatha Assembly Of God",
    "wof:placetype":"venue"
},
  "geometry": {"coordinates":[-91.06707400000001,33.377762],"type":"Point"}
}