{
  "type": "Feature",
  "properties": {
    "addr:full":"203 Walnut St Benoit MS 38725",
    "addr:housenumber":"203",
    "addr:postcode":"38725",
    "addr:street":"Walnut",
    "iso:country":"US",
    "sg:address":"203 Walnut St",
    "sg:city":"Benoit",
    "sg:classifiers":[
        {
            "category":"Professional",
            "subcategory":"Business Services",
            "type":"Services"
        }
    ],
    "sg:phone":"+1 662 742 3316",
    "sg:postcode":"38725",
    "sg:province":"MS",
    "wof:name":"Verified Credentials Inc",
    "wof:placetype":"venue"
},
  "geometry": {"coordinates":[-91.009654,33.64898],"type":"Point"}
}