{
  "type": "Feature",
  "properties": {
    "iso:country":"US",
    "sg:address":"9085 Millbranch Rd",
    "sg:city":"Southaven",
    "sg:classifiers":[
        {
            "category":"Food & Beverages",
            "subcategory":"Groceries & Convenience Stores",
            "type":"Retail Goods"
        }
    ],
    "sg:phone":"+1 662 342 6740",
    "sg:postcode":"38671",
    "sg:province":"MS",
    "wof:name":"Mercado Rosita",
    "wof:placetype":"venue"
},
  "geometry": {"coordinates":[-90.008032,34.992901],"type":"Point"}
}