{
  "type": "Feature",
  "properties": {
    "addr:full":"900 E County Line Rd Ridgeland MS 39157",
    "addr:housenumber":"900",
    "addr:postcode":"39157",
    "addr:street":"E County Line Rd",
    "iso:country":"US",
    "sg:address":"900 E County Line Rd",
    "sg:city":"Ridgeland",
    "sg:classifiers":[
        {
            "category":"Insurance",
            "subcategory":"Insurance Agent",
            "type":"Services"
        }
    ],
    "sg:phone":"+1 601 957 2020",
    "sg:postcode":"39157",
    "sg:province":"MS",
    "sg:tags":[
        "agency"
    ],
    "wof:name":"Allstate",
    "wof:placetype":"venue"
},
  "geometry": {"coordinates":[-90.142015,32.399554],"type":"Point"}
}