{
  "type": "Feature",
  "properties": {
    "iso:country":"US",
    "sg:address":"13056 Canal Rd",
    "sg:city":"Gulfport",
    "sg:classifiers":[
        {
            "category":"Shopping",
            "subcategory":"Discount & Variety Stores",
            "type":"Retail Goods"
        }
    ],
    "sg:phone":"+1 228 832 9945",
    "sg:postcode":"39503",
    "sg:province":"MS",
    "sg:tags":[
        "merchandise",
        "general"
    ],
    "wof:name":"Canal Country Store",
    "wof:placetype":"venue"
},
  "geometry": {"coordinates":[-89.136887,30.464371],"type":"Point"}
}