{
  "type": "Feature",
  "properties": {
    "iso:country":"US",
    "sg:address":"62944 Hwy 25 N",
    "sg:city":"Amory",
    "sg:classifiers":[
        {
            "category":"Manufacturing",
            "subcategory":"Signs",
            "type":"Manufacturing & Wholesale Goods"
        }
    ],
    "sg:phone":"+1 662 257 4033",
    "sg:postcode":"38821",
    "sg:province":"MS",
    "wof:name":"Sign Engineers",
    "wof:placetype":"venue"
},
  "geometry": {"coordinates":[-88.46102399999999,34.021626],"type":"Point"}
}