{
  "type": "Feature",
  "properties": {
    "iso:country":"US",
    "sg:address":"7052 Wolf Rd",
    "sg:city":"Columbus",
    "sg:classifiers":[
        {
            "category":"Professional",
            "subcategory":"Business Services",
            "type":"Services"
        }
    ],
    "sg:phone":"+1 662 356 9249",
    "sg:postcode":"39705",
    "sg:province":"MS",
    "wof:name":"Laster Enterprise Inc",
    "wof:placetype":"venue"
},
  "geometry": {"coordinates":[-88.35450899999999,33.64635],"type":"Point"}
}