{
  "type": "Feature",
  "properties": {
    "iso:country":"US",
    "sg:address":"411 US Hwy 61 Bus",
    "sg:city":"Natchez",
    "sg:classifiers":[
        {
            "category":"Professional",
            "type":"Services"
        }
    ],
    "sg:phone":"+1 601 445 6002",
    "sg:postcode":"39120",
    "sg:province":"MS",
    "sg:tags":[
        "establishment"
    ],
    "wof:name":"Genpass",
    "wof:placetype":"venue"
},
  "geometry": {"coordinates":[-91.402207,31.554324],"type":"Point"}
}