{
  "type": "Feature",
  "properties": {
    "addr:full":"1303 Nutter Dr Picayune MS 39466",
    "addr:housenumber":"1303",
    "addr:postcode":"39466",
    "addr:street":"Nutter Dr",
    "iso:country":"US",
    "sg:address":"1303 Nutter Dr",
    "sg:city":"Picayune",
    "sg:classifiers":[
        {
            "category":"Building & Trades",
            "subcategory":"Construction",
            "type":"Services"
        }
    ],
    "sg:phone":"+1 601 798 1044",
    "sg:postcode":"39466",
    "sg:province":"MS",
    "sg:tags":[
        "residential"
    ],
    "wof:name":"Edward Stubbs",
    "wof:placetype":"venue"
},
  "geometry": {"coordinates":[-89.694926,30.516682],"type":"Point"}
}