{
  "type": "Feature",
  "properties": {
    "iso:country":"US",
    "sg:address":"1103 S Theobald St",
    "sg:city":"Greenville",
    "sg:classifiers":[
        {
            "category":"Food & Beverages",
            "subcategory":"Groceries & Convenience Stores",
            "type":"Retail Goods"
        }
    ],
    "sg:phone":"+1 662 335 4218",
    "sg:postcode":"38701",
    "sg:province":"MS",
    "sg:tags":[
        "grocer",
        "super",
        "supermarket"
    ],
    "wof:name":"Friendly Market",
    "wof:placetype":"venue"
},
  "geometry": {"coordinates":[-91.067127,33.396899],"type":"Point"}
}