{
  "type": "Feature",
  "properties": {
    "addr:full":"3420 Bienville Blvd Ocean Springs MS 39564",
    "addr:housenumber":"3420",
    "addr:postcode":"39564",
    "addr:street":"Bienville Blvd",
    "iso:country":"US",
    "sg:address":"3420 Bienville Blvd",
    "sg:city":"Ocean Springs",
    "sg:classifiers":[
        {
            "category":"Manufacturing",
            "subcategory":"Printing",
            "type":"Manufacturing & Wholesale Goods"
        }
    ],
    "sg:phone":"+1 228 872 2766",
    "sg:postcode":"39564",
    "sg:province":"MS",
    "sg:tags":[
        "screen"
    ],
    "sg:website":"www.vl-inc.com",
    "wof:name":"T J's Custom Apparell",
    "wof:placetype":"venue"
},
  "geometry": {"coordinates":[-88.777209,30.412123],"type":"Point"}
}