{
  "type": "Feature",
  "properties": {
    "iso:country":"US",
    "sg:address":"12306 N Oaklawn Ln",
    "sg:city":"Biloxi",
    "sg:classifiers":[
        {
            "category":"Wholesale",
            "subcategory":"Machinery & Supplies",
            "type":"Manufacturing & Wholesale Goods"
        }
    ],
    "sg:phone":"+1 228 392 9922",
    "sg:postcode":"39532",
    "sg:province":"MS",
    "sg:tags":[
        "contractor"
    ],
    "wof:name":"Lee Tractor Co Inc",
    "wof:placetype":"venue"
},
  "geometry": {"coordinates":[-88.974867,30.461748],"type":"Point"}
}