{
  "type": "Feature",
  "properties": {
    "iso:country":"US",
    "sg:address":"1605 Timber Lane Rd",
    "sg:city":"Gautier",
    "sg:classifiers":[
        {
            "category":"Building & Trades",
            "subcategory":"Cleaning & Sanitation",
            "type":"Services"
        }
    ],
    "sg:phone":"+1 228 497 9190",
    "sg:postcode":"39553",
    "sg:province":"MS",
    "sg:tags":[
        "pressure",
        "window",
        "washing"
    ],
    "wof:name":"Birds Win Wshg Pressure Wshg",
    "wof:placetype":"venue"
},
  "geometry": {"coordinates":[-88.63814499999999,30.442488],"type":"Point"}
}