{
  "type": "Feature",
  "properties": {
    "addr:full":"1533 Orchid Dr Clarksdale MS 38614",
    "addr:housenumber":"1533",
    "addr:postcode":"38614",
    "addr:street":"Orchid Dr Clarksdale",
    "iso:country":"US",
    "sg:address":"1533 Orchid Dr",
    "sg:city":"Clarksdale",
    "sg:classifiers":[
        {
            "category":"Shopping",
            "subcategory":"Beauty & Cosmetics",
            "type":"Retail Goods"
        },
        {
            "category":"Personal",
            "subcategory":"Barber",
            "type":"Services"
        }
    ],
    "sg:phone":"+1 662 624 9164",
    "sg:postcode":"38614",
    "sg:province":"MS",
    "sg:tags":[
        "equipment",
        "salons-equipment",
        "supply"
    ],
    "wof:name":"Ks Beauty & Hair Supply Inc",
    "wof:placetype":"venue"
},
  "geometry": {"coordinates":[-90.603393,34.20881],"type":"Point"}
}