{
  "type": "Feature",
  "properties": {
    "iso:country":"US",
    "sg:address":"130 Old Town Rd",
    "sg:city":"Bruce",
    "sg:classifiers":[
        {
            "category":"Retail",
            "subcategory":"Laundry & Dry Cleaning",
            "type":"Services"
        }
    ],
    "sg:phone":"+1 662 983 2330",
    "sg:postcode":"38951",
    "sg:province":"MS",
    "sg:tags":[
        "cleaners"
    ],
    "wof:name":"Bruce Dry Cleaners",
    "wof:placetype":"venue"
},
  "geometry": {"coordinates":[-89.301969,33.968574],"type":"Point"}
}