{
  "type": "Feature",
  "properties": {
    "iso:country":"US",
    "sg:address":"101 China St",
    "sg:city":"Lexington",
    "sg:classifiers":[
        {
            "category":"Personal",
            "type":"Services"
        }
    ],
    "sg:phone":"+1 662 834 3210",
    "sg:postcode":"39038",
    "sg:province":"MS",
    "wof:name":"Cut and Curl",
    "wof:placetype":"venue"
},
  "geometry": {"coordinates":[-90.49117699999999,33.188583],"type":"Point"}
}