{
  "type": "Feature",
  "properties": {
    "iso:country":"US",
    "sg:address":"160 Co Rd 1040",
    "sg:city":"Booneville",
    "sg:classifiers":[
        {
            "category":"Restaurant",
            "type":"Food & Drink"
        }
    ],
    "sg:phone":"+1 662 720 0080",
    "sg:postcode":"38829",
    "sg:province":"MS",
    "wof:name":"Thrasher Quick Foods",
    "wof:placetype":"venue"
},
  "geometry": {"coordinates":[-88.544892,34.712446],"type":"Point"}
}