{
  "type": "Feature",
  "properties": {
    "addr:full":"202 Downing Rd Natchez MS 39120",
    "addr:housenumber":"202",
    "addr:postcode":"39120",
    "addr:street":"Downing Rd",
    "iso:country":"US",
    "sg:address":"202 Downing Rd",
    "sg:city":"Natchez",
    "sg:classifiers":[
        {
            "category":"Banks & Credit Unions",
            "subcategory":"Financial Services",
            "type":"Services"
        }
    ],
    "sg:phone":"+1 601 445 5013",
    "sg:postcode":"39120",
    "sg:province":"MS",
    "sg:tags":[
        "investor"
    ],
    "wof:name":"Investment Club of Ujamaa",
    "wof:placetype":"venue"
},
  "geometry": {"coordinates":[-91.37639900000001,31.569178],"type":"Point"}
}