{
  "type": "Feature",
  "properties": {
    "iso:country":"US",
    "sg:address":"6055 Ridgewood Rd",
    "sg:city":"Jackson",
    "sg:classifiers":[
        {
            "category":"Building & Trades",
            "subcategory":"Construction",
            "type":"Services"
        }
    ],
    "sg:phone":"+1 601 977 8929",
    "sg:postcode":"39211",
    "sg:province":"MS",
    "sg:tags":[
        "excavating",
        "contractor"
    ],
    "wof:name":"Southeast Utilities",
    "wof:placetype":"venue"
},
  "geometry": {"coordinates":[-90.141373,32.392787],"type":"Point"}
}