{
  "type": "Feature",
  "properties": {
    "iso:country":"US",
    "sg:address":"2781 W Benwood Dr",
    "sg:city":"Jackson",
    "sg:classifiers":[
        {
            "category":"Building & Trades",
            "subcategory":"Plumbing",
            "type":"Services"
        }
    ],
    "sg:phone":"+1 601 371 8382",
    "sg:postcode":"39204",
    "sg:province":"MS",
    "sg:tags":[
        "conditioning",
        "air",
        "system",
        "contractor"
    ],
    "wof:name":"Ray Shoemaker Air Conditioning",
    "wof:placetype":"venue"
},
  "geometry": {"coordinates":[-90.24747000000001,32.271292],"type":"Point"}
}