{
  "type": "Feature",
  "properties": {
    "iso:country":"US",
    "sg:address":"554 Line St",
    "sg:city":"Philadelphia",
    "sg:classifiers":[
        {
            "category":"Personal",
            "subcategory":"Barber",
            "type":"Services"
        }
    ],
    "sg:phone":"+1 601 656 1162",
    "sg:postcode":"39350",
    "sg:province":"MS",
    "wof:name":"Myers Barber Shop",
    "wof:placetype":"venue"
},
  "geometry": {"coordinates":[-89.104558,32.761519],"type":"Point"}
}