{
  "type": "Feature",
  "properties": {
    "iso:country":"US",
    "sg:address":"366 Lampton Rd",
    "sg:city":"Sumrall",
    "sg:classifiers":[
        {
            "category":"Organizations",
            "subcategory":"Religious Organization",
            "type":"Services"
        }
    ],
    "sg:phone":"+1 601 758 0505",
    "sg:postcode":"39482",
    "sg:province":"MS",
    "sg:tags":[
        "church"
    ],
    "wof:name":"Second Hopewell Missionary",
    "wof:placetype":"venue"
},
  "geometry": {"coordinates":[-89.638001,31.302757],"type":"Point"}
}