{
  "type": "Feature",
  "properties": {
    "addr:full":"1105 Jackson Ave W Oxford MS 38655",
    "addr:housenumber":"1105",
    "addr:postcode":"38655",
    "addr:street":"Jackson Ave W",
    "iso:country":"US",
    "sg:address":"1105 Jackson Ave W",
    "sg:city":"Oxford",
    "sg:classifiers":[
        {
            "category":"Utilities",
            "subcategory":"Mobile Phone",
            "type":"Services"
        }
    ],
    "sg:phone":"+1 662 513 4456",
    "sg:postcode":"38655",
    "sg:province":"MS",
    "sg:tags":[
        "telephone",
        "cellular"
    ],
    "wof:name":"Summit South Wireless",
    "wof:placetype":"venue"
},
  "geometry": {"coordinates":[-89.543232,34.369918],"type":"Point"}
}