{
  "type": "Feature",
  "properties": {
    "iso:country":"US",
    "sg:address":"172 Hwy 309 S",
    "sg:city":"Byhalia",
    "sg:classifiers":[
        {
            "category":"Education",
            "subcategory":"School",
            "type":"Public Place"
        }
    ],
    "sg:phone":"+1 662 838 2591",
    "sg:postcode":"38611",
    "sg:province":"MS",
    "wof:name":"Henry School",
    "wof:placetype":"venue"
},
  "geometry": {"coordinates":[-89.688862,34.867789],"type":"Point"}
}