{
  "type": "Feature",
  "properties": {
    "addr:full":"104 Water Oaks Cove Ocean Springs MS 39564",
    "addr:housenumber":"104",
    "addr:postcode":"39564",
    "addr:street":"Water Oaks Cove",
    "iso:country":"US",
    "sg:address":"104 Water Oaks Cove",
    "sg:city":"Ocean Springs",
    "sg:classifiers":[
        {
            "category":"Shopping",
            "subcategory":"Gifts & Souvenirs",
            "type":"Retail Goods"
        }
    ],
    "sg:phone":"+1 228 872 8879",
    "sg:postcode":"39564",
    "sg:province":"MS",
    "wof:name":"Longberger Consultant",
    "wof:placetype":"venue"
},
  "geometry": {"coordinates":[-88.783754,30.402371],"type":"Point"}
}