{
  "type": "Feature",
  "properties": {
    "iso:country":"US",
    "sg:address":"7128 State Hwy 301",
    "sg:city":"Horn Lake",
    "sg:classifiers":[
        {
            "category":"Shopping",
            "subcategory":"Tobacco",
            "type":"Retail Goods"
        }
    ],
    "sg:phone":"+1 662 781 0970",
    "sg:postcode":"38637",
    "sg:province":"MS",
    "sg:tags":[
        "shop"
    ],
    "wof:name":"A & J Tobacco Shack",
    "wof:placetype":"venue"
},
  "geometry": {"coordinates":[-90.096036,34.96404],"type":"Point"}
}