{
  "type": "Feature",
  "properties": {
    "iso:country":"US",
    "sg:address":"112 Overlook Pointe Dr",
    "sg:city":"Ridgeland",
    "sg:classifiers":[
        {
            "category":"Professional",
            "subcategory":"Business Services",
            "type":"Services"
        }
    ],
    "sg:phone":"+1 601 853 7780",
    "sg:postcode":"39157",
    "sg:province":"MS",
    "wof:name":"Goldilocks Enterprises LLC",
    "wof:placetype":"venue"
},
  "geometry": {"coordinates":[-90.077529,32.427033],"type":"Point"}
}