{
  "type": "Feature",
  "properties": {
    "iso:country":"US",
    "sg:address":"511 Ulman Ave",
    "sg:city":"Bay St Louis",
    "sg:classifiers":[
        {
            "category":"Education",
            "subcategory":"Special Training",
            "type":"Public Place"
        }
    ],
    "sg:phone":"+1 228 466 2808",
    "sg:postcode":"39520",
    "sg:province":"MS",
    "sg:tags":[
        "school",
        "instruction",
        "art"
    ],
    "wof:name":"Painted Palm Studio",
    "wof:placetype":"venue"
},
  "geometry": {"coordinates":[-89.34085,30.318483],"type":"Point"}
}