{
  "type": "Feature",
  "properties": {
    "iso:country":"US",
    "sg:address":"71 Arbor Ln",
    "sg:city":"Columbus",
    "sg:classifiers":[
        {
            "category":"Health Services",
            "subcategory":"Clinic",
            "type":"Services"
        }
    ],
    "sg:phone":"+1 662 328 0119",
    "sg:postcode":"39702",
    "sg:province":"MS",
    "wof:name":"Laffoon Medical Ltd",
    "wof:placetype":"venue"
},
  "geometry": {"coordinates":[-88.29132199999999,33.489459],"type":"Point"}
}