{
  "type": "Feature",
  "properties": {
    "addr:full":"1286 E Northside Dr Jackson MS 39213",
    "addr:housenumber":"1286",
    "addr:postcode":"39213",
    "addr:street":"E Northside Dr",
    "iso:country":"US",
    "sg:address":"1286 E Northside Dr",
    "sg:city":"Jackson",
    "sg:classifiers":[
        {
            "category":"Professional",
            "subcategory":"Accounting & Tax Preparation",
            "type":"Services"
        }
    ],
    "sg:phone":"+1 601 362 0348",
    "sg:postcode":"39213",
    "sg:province":"MS",
    "sg:tags":[
        "bookkeeping",
        "general"
    ],
    "wof:name":"Equitax",
    "wof:placetype":"venue"
},
  "geometry": {"coordinates":[-90.194974,32.355987],"type":"Point"}
}