{
  "type": "Feature",
  "properties": {
    "iso:country":"US",
    "sg:address":"1501 Main St",
    "sg:city":"Columbus",
    "sg:classifiers":[
        {
            "category":"Government",
            "subcategory":"Police Station",
            "type":"Public Place"
        }
    ],
    "sg:phone":"+1 662 244 3540",
    "sg:postcode":"39701",
    "sg:province":"MS",
    "sg:tags":[
        "department"
    ],
    "wof:name":"Columbus-Lowndes Narcotic Unit",
    "wof:placetype":"venue"
},
  "geometry": {"coordinates":[-88.415037,33.496919],"type":"Point"}
}