{
  "type": "Feature",
  "properties": {
    "iso:country":"US",
    "sg:address":"3220 Forest Ave Exd",
    "sg:city":"Jackson",
    "sg:classifiers":[
        {
            "category":"Organizations",
            "subcategory":"Religious Organization",
            "type":"Services"
        }
    ],
    "sg:phone":"+1 601 366 0133",
    "sg:postcode":"39213",
    "sg:province":"MS",
    "sg:tags":[
        "church"
    ],
    "wof:name":"New Heights Seventh Day Church",
    "wof:placetype":"venue"
},
  "geometry": {"coordinates":[-90.231658,32.370704],"type":"Point"}
}