{
  "type": "Feature",
  "properties": {
    "addr:full":"117 Fawnwood Dr Brandon MS 39042",
    "addr:housenumber":"117",
    "addr:postcode":"39042",
    "addr:street":"Fawnwood Dr",
    "iso:country":"US",
    "sg:address":"117 Fawnwood Dr",
    "sg:city":"Brandon",
    "sg:classifiers":[
        {
            "category":"Banks & Credit Unions",
            "subcategory":"Financial Services",
            "type":"Services"
        }
    ],
    "sg:phone":"+1 601 825 7629",
    "sg:postcode":"39042",
    "sg:province":"MS",
    "sg:tags":[
        "company",
        "holding"
    ],
    "wof:name":"Nicole Holdings",
    "wof:placetype":"venue"
},
  "geometry": {"coordinates":[-90.013402,32.297325],"type":"Point"}
}