{
  "type": "Feature",
  "properties": {
    "iso:country":"US",
    "sg:address":"200 Apple Wood Ln",
    "sg:city":"Brandon",
    "sg:classifiers":[
        {
            "category":"Food & Beverages",
            "subcategory":"Groceries & Convenience Stores",
            "type":"Retail Goods"
        }
    ],
    "sg:phone":"+1 601 824 2193",
    "sg:postcode":"39042",
    "sg:province":"MS",
    "sg:tags":[
        "grocer"
    ],
    "wof:name":"King's Corner",
    "wof:placetype":"venue"
},
  "geometry": {"coordinates":[-89.968677,32.189731],"type":"Point"}
}