{
  "type": "Feature",
  "properties": {
    "addr:full":"408 S 11th St Oxford MS 38655",
    "addr:housenumber":"408",
    "addr:postcode":"38655",
    "addr:street":"S 11Th St",
    "iso:country":"US",
    "sg:address":"408 S 11th St",
    "sg:city":"Oxford",
    "sg:classifiers":[
        {
            "category":"Insurance",
            "subcategory":"Insurance Agent",
            "type":"Services"
        }
    ],
    "sg:phone":"+1 662 236 2644",
    "sg:postcode":"38655",
    "sg:province":"MS",
    "wof:name":"Northwestern Mutual Financial",
    "wof:placetype":"venue"
},
  "geometry": {"coordinates":[-89.52009099999999,34.365141],"type":"Point"}
}