{
  "type": "Feature",
  "properties": {
    "iso:country":"US",
    "sg:address":"135 E Bay St",
    "sg:city":"Magnolia",
    "sg:classifiers":[
        {
            "category":"Health Services",
            "subcategory":"Health Practitioner",
            "type":"Services"
        }
    ],
    "sg:phone":"+1 601 783 9840",
    "sg:postcode":"39652",
    "sg:province":"MS",
    "wof:name":"Magnolia Rehab Company",
    "wof:placetype":"venue"
},
  "geometry": {"coordinates":[-90.461046,31.144368],"type":"Point"}
}