{
  "type": "Feature",
  "properties": {
    "iso:country":"US",
    "sg:address":"127 Woodgate Dr",
    "sg:city":"Brandon",
    "sg:classifiers":[
        {
            "category":"Restaurant",
            "type":"Food & Drink"
        }
    ],
    "sg:phone":"+1 601 362 5557",
    "sg:postcode":"39042",
    "sg:province":"MS",
    "sg:tags":[
        "eating"
    ],
    "wof:name":"New Deli Grill L L C",
    "wof:placetype":"venue"
},
  "geometry": {"coordinates":[-90.024776,32.297934],"type":"Point"}
}