{
  "type": "Feature",
  "properties": {
    "iso:country":"US",
    "sg:address":"2384 Hwy 80 W",
    "sg:city":"Jackson",
    "sg:classifiers":[
        {
            "category":"Local Transit",
            "type":"Transportation"
        }
    ],
    "sg:phone":"+1 601 944 4048",
    "sg:postcode":"39204",
    "sg:province":"MS",
    "sg:tags":[
        "passenger"
    ],
    "wof:name":"Regency Transportation Inc",
    "wof:placetype":"venue"
},
  "geometry": {"coordinates":[-90.22687500000001,32.290958],"type":"Point"}
}