{
  "type": "Feature",
  "properties": {
    "addr:full":"218 Yerger St Jackson MS 39203",
    "addr:housenumber":"218",
    "addr:postcode":"39203",
    "addr:street":"Yerger St",
    "iso:country":"US",
    "sg:address":"218 Yerger St",
    "sg:city":"Jackson",
    "sg:classifiers":[
        {
            "category":"Manufacturing",
            "subcategory":"Metals",
            "type":"Manufacturing & Wholesale Goods"
        }
    ],
    "sg:phone":"+1 601 355 4208",
    "sg:postcode":"39203",
    "sg:province":"MS",
    "sg:tags":[
        "treating",
        "heat"
    ],
    "sg:website":"www.precisionheattreating.com",
    "wof:name":"Precision Heat Treating",
    "wof:placetype":"venue"
},
  "geometry": {"coordinates":[-90.19756599999999,32.306741],"type":"Point"}
}