{
  "type": "Feature",
  "properties": {
    "addr:full":"300 N Mill St Jackson MS 39202",
    "addr:housenumber":"300",
    "addr:postcode":"39202",
    "addr:street":"N Mill St",
    "iso:country":"US",
    "sg:address":"300 N Mill St",
    "sg:city":"Jackson",
    "sg:classifiers":[
        {
            "category":"Taxi",
            "type":"Transportation"
        }
    ],
    "sg:phone":"+1 601 355 8319",
    "sg:postcode":"39202",
    "sg:province":"MS",
    "sg:tags":[
        "taxicab"
    ],
    "wof:name":"Citi-Cab Co",
    "wof:placetype":"venue"
},
  "geometry": {"coordinates":[-90.19083999999999,32.303717],"type":"Point"}
}