{
  "type": "Feature",
  "properties": {
    "iso:country":"US",
    "sg:address":"526 Marilyn Dr",
    "sg:city":"Pearl",
    "sg:classifiers":[
        {
            "category":"Building & Trades",
            "subcategory":"Equipment Rental",
            "type":"Services"
        }
    ],
    "sg:phone":"+1 601 932 7166",
    "sg:postcode":"39208",
    "sg:province":"MS",
    "sg:tags":[
        "crane"
    ],
    "wof:name":"Jerry's Lift Svc",
    "wof:placetype":"venue"
},
  "geometry": {"coordinates":[-90.10528600000001,32.292491],"type":"Point"}
}