{
  "type": "Feature",
  "properties": {
    "iso:country":"US",
    "sg:address":"3002 Hwy 178",
    "sg:city":"Tupelo",
    "sg:classifiers":[
        {
            "category":"Banks & Credit Unions",
            "subcategory":"Bank",
            "type":"Services"
        }
    ],
    "sg:phone":"+1 662 680 1066",
    "sg:postcode":"38804",
    "sg:province":"MS",
    "sg:tags":[
        "state",
        "commercial"
    ],
    "wof:name":"Peoples Bank & Trust",
    "wof:placetype":"venue"
},
  "geometry": {"coordinates":[-88.62545299999999,34.265833],"type":"Point"}
}