{
  "type": "Feature",
  "properties": {
    "addr:full":"8450 W Sandidge Rd Olive Branch MS 38654",
    "addr:housenumber":"8450",
    "addr:postcode":"38654",
    "addr:street":"W Sandidge Rd",
    "iso:country":"US",
    "sg:address":"8450 W Sandidge Rd",
    "sg:city":"Olive Branch",
    "sg:classifiers":[
        {
            "category":"Manufacturing",
            "subcategory":"Textiles",
            "type":"Manufacturing & Wholesale Goods"
        }
    ],
    "sg:phone":"+1 662 893 3747",
    "sg:postcode":"38654",
    "sg:province":"MS",
    "sg:tags":[
        "curtain"
    ],
    "wof:name":"Contract Drapes & Spreads Inc",
    "wof:placetype":"venue"
},
  "geometry": {"coordinates":[-89.830777,34.943293],"type":"Point"}
}