{
  "type": "Feature",
  "properties": {
    "addr:full":"425 W Main St Senatobia MS 38668",
    "addr:housenumber":"425",
    "addr:postcode":"38668",
    "addr:street":"W Main St",
    "iso:country":"US",
    "sg:address":"425 W Main St",
    "sg:city":"Senatobia",
    "sg:classifiers":[
        {
            "category":"Home & Garden",
            "subcategory":"Furniture",
            "type":"Retail Goods"
        }
    ],
    "sg:phone":"+1 662 562 7661",
    "sg:postcode":"38668",
    "sg:province":"MS",
    "wof:name":"Mc Crary Furniture",
    "wof:placetype":"venue"
},
  "geometry": {"coordinates":[-89.966323,34.618473],"type":"Point"}
}