{
  "type": "Feature",
  "properties": {
    "iso:country":"US",
    "sg:address":"102 Erin Cove",
    "sg:city":"Clinton",
    "sg:classifiers":[
        {
            "category":"Food & Beverages",
            "subcategory":"Groceries & Convenience Stores",
            "type":"Retail Goods"
        }
    ],
    "sg:phone":"+1 601 924 7158",
    "sg:postcode":"39056",
    "sg:province":"MS",
    "wof:name":"Cosma USA Inc",
    "wof:placetype":"venue"
},
  "geometry": {"coordinates":[-90.30368799999999,32.340556],"type":"Point"}
}