{
  "type": "Feature",
  "properties": {
    "addr:full":"207 W Government St Brandon MS 39042",
    "addr:housenumber":"207",
    "addr:postcode":"39042",
    "addr:street":"W Government St",
    "iso:country":"US",
    "sg:address":"207 W Government St",
    "sg:city":"Brandon",
    "sg:classifiers":[
        {
            "category":"Manufacturing",
            "subcategory":"Printing",
            "type":"Manufacturing & Wholesale Goods"
        }
    ],
    "sg:phone":"+1 601 825 5133",
    "sg:postcode":"39042",
    "sg:province":"MS",
    "sg:tags":[
        "newspaper"
    ],
    "wof:name":"Weekly Leader",
    "wof:placetype":"venue"
},
  "geometry": {"coordinates":[-89.991923,32.273237],"type":"Point"}
}