{
  "type": "Feature",
  "properties": {
    "addr:full":"320 Greymont Ave Jackson MS 39202",
    "addr:housenumber":"320",
    "addr:postcode":"39202",
    "addr:street":"Greymont Ave",
    "iso:country":"US",
    "sg:address":"320 Greymont Ave",
    "sg:city":"Jackson",
    "sg:classifiers":[
        {
            "category":"Travel",
            "subcategory":"Hotels & Motels",
            "type":"Entertainment"
        }
    ],
    "sg:phone":"+1 601 352 1700",
    "sg:postcode":"39202",
    "sg:province":"MS",
    "sg:tags":[
        "operation"
    ],
    "wof:name":"Hampton Inn",
    "wof:placetype":"venue"
},
  "geometry": {"coordinates":[-90.176751,32.297727],"type":"Point"}
}