{
  "type": "Feature",
  "properties": {
    "addr:full":"1800 Spurlock Rd Columbus MS 39702",
    "addr:housenumber":"1800",
    "addr:postcode":"39702",
    "addr:street":"Spurlock Rd",
    "iso:country":"US",
    "sg:address":"1800 Spurlock Rd",
    "sg:city":"Columbus",
    "sg:classifiers":[
        {
            "category":"Manufacturing",
            "subcategory":"Lumber",
            "type":"Manufacturing & Wholesale Goods"
        }
    ],
    "sg:phone":"+1 662 327 8240",
    "sg:postcode":"39702",
    "sg:province":"MS",
    "sg:tags":[
        "logging"
    ],
    "wof:name":"Chains Logging",
    "wof:placetype":"venue"
},
  "geometry": {"coordinates":[-88.320751,33.332339],"type":"Point"}
}