{
  "type": "Feature",
  "properties": {
    "iso:country":"US",
    "sg:address":"1880 Haile Rd",
    "sg:city":"Gore Springs",
    "sg:classifiers":[
        {
            "category":"Freight",
            "type":"Transportation"
        }
    ],
    "sg:phone":"+1 662 229 0025",
    "sg:postcode":"38929",
    "sg:province":"MS",
    "sg:tags":[
        "trucking"
    ],
    "wof:name":"Jeff Harrison Trucking Inc",
    "wof:placetype":"venue"
},
  "geometry": {"coordinates":[-89.59078700000001,33.738776],"type":"Point"}
}