{
  "type": "Feature",
  "properties": {
    "iso:country":"US",
    "sg:address":"804 North St",
    "sg:city":"Jackson",
    "sg:classifiers":[
        {
            "category":"Professional",
            "type":"Services"
        }
    ],
    "sg:phone":"+1 601 969 6009",
    "sg:postcode":"39202",
    "sg:province":"MS",
    "sg:tags":[
        "establishment"
    ],
    "wof:name":"Stimley Brown & Assoc",
    "wof:placetype":"venue"
},
  "geometry": {"coordinates":[-90.177199,32.308141],"type":"Point"}
}