{
  "type": "Feature",
  "properties": {
    "iso:country":"US",
    "sg:address":"130 S Industrial Rd",
    "sg:city":"Tupelo",
    "sg:classifiers":[
        {
            "category":"Shopping",
            "subcategory":"Clothing, Apparel, & Fashions",
            "type":"Retail Goods"
        }
    ],
    "sg:phone":"+1 662 844 0200",
    "sg:postcode":"38801",
    "sg:province":"MS",
    "sg:tags":[
        "ready"
    ],
    "wof:name":"Alexis Boutique LLC",
    "wof:placetype":"venue"
},
  "geometry": {"coordinates":[-88.72036900000001,34.256822],"type":"Point"}
}