{
  "type": "Feature",
  "properties": {
    "iso:country":"US",
    "sg:address":"1020 Hwy 35 S",
    "sg:city":"Forest",
    "sg:classifiers":[
        {
            "category":"Health Services",
            "subcategory":"Health Practitioner",
            "type":"Services"
        }
    ],
    "sg:phone":"+1 601 469 8292",
    "sg:postcode":"39074",
    "sg:province":"MS",
    "wof:name":"Forest Mssage Therapy Nail Spa",
    "wof:placetype":"venue"
},
  "geometry": {"coordinates":[-89.48124300000001,32.35393],"type":"Point"}
}