{
  "type": "Feature",
  "properties": {
    "addr:full":"200 E Washington St Greenwood MS 38930",
    "addr:housenumber":"200",
    "addr:postcode":"38930",
    "addr:street":"E Washington St",
    "iso:country":"US",
    "sg:address":"200 E Washington St",
    "sg:city":"Greenwood",
    "sg:classifiers":[
        {
            "category":"Manufacturing",
            "subcategory":"Lumber",
            "type":"Manufacturing & Wholesale Goods"
        }
    ],
    "sg:phone":"+1 662 453 0681",
    "sg:postcode":"38930",
    "sg:province":"MS",
    "sg:tags":[
        "government"
    ],
    "wof:name":"Forestry Dept",
    "wof:placetype":"venue"
},
  "geometry": {"coordinates":[-90.17891899999999,33.520229],"type":"Point"}
}