{
  "type": "Feature",
  "properties": {
    "iso:country":"US",
    "sg:address":"7123 Shadow Oaks Dr",
    "sg:city":"Memphis",
    "sg:classifiers":[
        {
            "category":"Professional",
            "subcategory":"Management & Consulting",
            "type":"Services"
        }
    ],
    "sg:phone":"+1 901 756 0946",
    "sg:postcode":"38125",
    "sg:province":"MS",
    "sg:tags":[
        "consultant",
        "resource",
        "human"
    ],
    "wof:name":"People Connection",
    "wof:placetype":"venue"
},
  "geometry": {"coordinates":[-89.82604600000001,35.029702],"type":"Point"}
}