{
  "type": "Feature",
  "properties": {
    "iso:country":"US",
    "sg:address":"7672 Hwy 84 E",
    "sg:city":"Waynesboro",
    "sg:classifiers":[
        {
            "category":"Home & Garden",
            "subcategory":"Building Materials",
            "type":"Retail Goods"
        }
    ],
    "sg:phone":"+1 601 735 3323",
    "sg:postcode":"39367",
    "sg:province":"MS",
    "sg:tags":[
        "lumber"
    ],
    "wof:name":"Stanley Lumber Products Mfg",
    "wof:placetype":"venue"
},
  "geometry": {"coordinates":[-88.612308,31.713911],"type":"Point"}
}