{
  "type": "Feature",
  "properties": {
    "iso:country":"US",
    "sg:address":"119 S President St",
    "sg:city":"Jackson",
    "sg:classifiers":[
        {
            "category":"Banks & Credit Unions",
            "subcategory":"Investment Brokerage",
            "type":"Services"
        }
    ],
    "sg:phone":"+1 601 949 3105",
    "sg:postcode":"39201",
    "sg:province":"MS",
    "sg:tags":[
        "advisory",
        "financial"
    ],
    "wof:name":"Earnest Partners",
    "wof:placetype":"venue"
},
  "geometry": {"coordinates":[-90.182013,32.298578],"type":"Point"}
}