{
  "type": "Feature",
  "properties": {
    "iso:country":"US",
    "sg:address":"2302 27th Ave",
    "sg:city":"Meridian",
    "sg:classifiers":[
        {
            "category":"Building & Trades",
            "subcategory":"Construction",
            "type":"Services"
        }
    ],
    "sg:phone":"+1 601 693 3662",
    "sg:postcode":"39301",
    "sg:province":"MS",
    "sg:tags":[
        "general",
        "contractor"
    ],
    "wof:name":"Griffins Construction",
    "wof:placetype":"venue"
},
  "geometry": {"coordinates":[-88.705519,32.38263],"type":"Point"}
}