{
  "type": "Feature",
  "properties": {
    "iso:country":"US",
    "sg:address":"101 Shadow Lake Dr",
    "sg:city":"Hattiesburg",
    "sg:classifiers":[
        {
            "category":"Sports & Exercise",
            "subcategory":"Golf",
            "type":"Entertainment"
        }
    ],
    "sg:phone":"+1 601 296 0286",
    "sg:postcode":"39402",
    "sg:province":"MS",
    "sg:tags":[
        "course",
        "courses-private"
    ],
    "wof:name":"Shadow Ridge Golf Course",
    "wof:placetype":"venue"
},
  "geometry": {"coordinates":[-89.396004,31.322651],"type":"Point"}
}