{
  "type": "Feature",
  "properties": {
    "iso:country":"US",
    "sg:address":"22036 Adams Rd",
    "sg:city":"Saucier",
    "sg:classifiers":[
        {
            "category":"Retail",
            "subcategory":"Photofinishing",
            "type":"Services"
        }
    ],
    "sg:phone":"+1 228 831 0290",
    "sg:postcode":"39574",
    "sg:province":"MS",
    "sg:tags":[
        "laboratory"
    ],
    "wof:name":"Mobile Event Photography",
    "wof:placetype":"venue"
},
  "geometry": {"coordinates":[-89.11910399999999,30.606633],"type":"Point"}
}