{
  "type": "Feature",
  "properties": {
    "iso:country":"US",
    "sg:address":"1821 Hwy 39 N",
    "sg:city":"Meridian",
    "sg:classifiers":[
        {
            "category":"Real Estate",
            "subcategory":"Real Estate Agent",
            "type":"Services"
        }
    ],
    "sg:phone":"+1 601 693 5056",
    "sg:postcode":"39301",
    "sg:province":"MS",
    "wof:name":"Business Center",
    "wof:placetype":"venue"
},
  "geometry": {"coordinates":[-88.681314,32.37656],"type":"Point"}
}