{
  "type": "Feature",
  "properties": {
    "iso:country":"US",
    "sg:address":"67 Quail Hollow Dr",
    "sg:city":"Hattiesburg",
    "sg:classifiers":[
        {
            "category":"Insurance",
            "subcategory":"Insurance Agent",
            "type":"Services"
        }
    ],
    "sg:phone":"+1 601 268 5588",
    "sg:postcode":"39402",
    "sg:province":"MS",
    "sg:tags":[
        "broker"
    ],
    "wof:name":"Paul Williams",
    "wof:placetype":"venue"
},
  "geometry": {"coordinates":[-89.40134999999999,31.294241],"type":"Point"}
}