{
  "type": "Feature",
  "properties": {
    "iso:country":"US",
    "sg:address":"921 Ocean Ave",
    "sg:city":"Ocean Springs",
    "sg:classifiers":[
        {
            "category":"Social Services",
            "subcategory":"Child Care",
            "type":"Services"
        }
    ],
    "sg:phone":"+1 228 872 2835",
    "sg:postcode":"39564",
    "sg:province":"MS",
    "sg:tags":[
        "day"
    ],
    "wof:name":"Childrens Hse Montessori Schl",
    "wof:placetype":"venue"
},
  "geometry": {"coordinates":[-88.828233,30.407778],"type":"Point"}
}