{
  "type": "Feature",
  "properties": {
    "addr:full":"203 N Railroad Ave New Albany MS 38652",
    "addr:housenumber":"203",
    "addr:postcode":"38652",
    "addr:street":"N Railroad Ave",
    "iso:country":"US",
    "sg:address":"203 N Railroad Ave",
    "sg:city":"New Albany",
    "sg:classifiers":[
        {
            "category":"Organizations",
            "subcategory":"Religious Organization",
            "type":"Services"
        }
    ],
    "sg:phone":"+1 662 534 2069",
    "sg:postcode":"38652",
    "sg:province":"MS",
    "sg:tags":[
        "church"
    ],
    "wof:name":"Love Praise Tabernacle",
    "wof:placetype":"venue"
},
  "geometry": {"coordinates":[-89.007859,34.494836],"type":"Point"}
}