{
  "type": "Feature",
  "properties": {
    "iso:country":"US",
    "sg:address":"1006 Jefferson Ave",
    "sg:city":"Oxford",
    "sg:classifiers":[
        {
            "category":"Professional",
            "subcategory":"Business Services",
            "type":"Services"
        }
    ],
    "sg:phone":"+1 662 281 1100",
    "sg:postcode":"38655",
    "sg:province":"MS",
    "sg:tags":[
        "interior",
        "consultant",
        "design",
        "decorator"
    ],
    "wof:name":"French Foyer",
    "wof:placetype":"venue"
},
  "geometry": {"coordinates":[-89.520145,34.368842],"type":"Point"}
}