{
  "type": "Feature",
  "properties": {
    "addr:full":"301 W Eastport St Iuka MS 38852",
    "addr:housenumber":"301",
    "addr:postcode":"38852",
    "addr:street":"W Eastport St",
    "iso:country":"US",
    "sg:address":"301 W Eastport St",
    "sg:city":"Iuka",
    "sg:classifiers":[
        {
            "category":"Insurance",
            "subcategory":"Insurance Agent",
            "type":"Services"
        }
    ],
    "sg:phone":"+1 662 423 6151",
    "sg:postcode":"38852",
    "sg:province":"MS",
    "wof:name":"Tishomingo County Farm Bureau",
    "wof:placetype":"venue"
},
  "geometry": {"coordinates":[-88.191604,34.812141],"type":"Point"}
}