{
  "type": "Feature",
  "properties": {
    "addr:full":"2391 Main Ext Greenville MS 38701",
    "addr:housenumber":"2391",
    "addr:postcode":"38701",
    "addr:street":"Main Ext",
    "iso:country":"US",
    "sg:address":"2391 Main Ext",
    "sg:city":"Greenville",
    "sg:classifiers":[
        {
            "category":"Retail",
            "subcategory":"Laundry & Dry Cleaning",
            "type":"Services"
        }
    ],
    "sg:phone":"+1 662 335 4764",
    "sg:postcode":"38701",
    "sg:province":"MS",
    "sg:tags":[
        "cleaner",
        "rug",
        "carpet"
    ],
    "wof:name":"Professional Cleaning Of Greenville",
    "wof:placetype":"venue"
},
  "geometry": {"coordinates":[-91.06068399999999,33.369005],"type":"Point"}
}