{
  "type": "Feature",
  "properties": {
    "iso:country":"US",
    "sg:address":"6858 Swinnea Rd Ste 6A",
    "sg:city":"Southaven",
    "sg:classifiers":[
        {
            "category":"Real Estate",
            "subcategory":"Real Estate Services",
            "type":"Services"
        },
        {
            "category":"Banks & Credit Unions",
            "subcategory":"Financial Services",
            "type":"Services"
        }
    ],
    "sg:phone":"+1 662 536 2111",
    "sg:postcode":"38671",
    "sg:province":"MS",
    "sg:tags":[
        "loan",
        "mortgage"
    ],
    "wof:name":"Premier Capital Mortgage Group",
    "wof:placetype":"venue"
},
  "geometry": {"coordinates":[-89.97215199999999,34.960671],"type":"Point"}
}