{
  "type": "Feature",
  "properties": {
    "iso:country":"US",
    "sg:address":"1608 Brown St",
    "sg:city":"Laurel",
    "sg:classifiers":[
        {
            "category":"Food & Beverages",
            "subcategory":"Groceries & Convenience Stores",
            "type":"Retail Goods"
        }
    ],
    "sg:phone":"+1 601 426 2069",
    "sg:postcode":"39440",
    "sg:province":"MS",
    "sg:tags":[
        "grocer"
    ],
    "wof:name":"E's Curb Store",
    "wof:placetype":"venue"
},
  "geometry": {"coordinates":[-89.14442,31.663995],"type":"Point"}
}