{
  "type": "Feature",
  "properties": {
    "iso:country":"US",
    "sg:address":"1004 Munsford Dr",
    "sg:city":"New Albany",
    "sg:classifiers":[
        {
            "category":"Autos & Motor Vehicles",
            "subcategory":"Auto Supplies",
            "type":"Retail Goods"
        }
    ],
    "sg:phone":"+1 662 534 7671",
    "sg:postcode":"38652",
    "sg:province":"MS",
    "sg:tags":[
        "tire"
    ],
    "sg:website":"www.friendlycitytire.com",
    "wof:name":"Friendly City Tire",
    "wof:placetype":"venue"
},
  "geometry": {"coordinates":[-89.03827800000001,34.510506],"type":"Point"}
}