{
  "type": "Feature",
  "properties": {
    "addr:full":"3411 Washington Ave Gulfport MS 39507",
    "addr:housenumber":"3411",
    "addr:postcode":"39507",
    "addr:street":"Washington Ave",
    "iso:country":"US",
    "sg:address":"3411 Washington Ave",
    "sg:city":"Gulfport",
    "sg:classifiers":[
        {
            "category":"Wholesale",
            "subcategory":"Tobacco Products",
            "type":"Manufacturing & Wholesale Goods"
        }
    ],
    "sg:phone":"+1 228 864 6718",
    "sg:postcode":"39507",
    "sg:province":"MS",
    "sg:tags":[
        "cigarette",
        "cigar",
        "dealer"
    ],
    "wof:name":"Discount Tobacco Mart",
    "wof:placetype":"venue"
},
  "geometry": {"coordinates":[-89.052419,30.392495],"type":"Point"}
}