{
  "type": "Feature",
  "properties": {
    "iso:country":"US",
    "sg:address":"6 St Catherine St",
    "sg:city":"Natchez",
    "sg:classifiers":[
        {
            "category":"Shopping",
            "subcategory":"Clothing, Apparel, & Fashions",
            "type":"Retail Goods"
        }
    ],
    "sg:phone":"+1 601 446 9316",
    "sg:postcode":"39120",
    "sg:province":"MS",
    "sg:tags":[
        "t"
    ],
    "wof:name":"Ebony Barber & Beauty Shop",
    "wof:placetype":"venue"
},
  "geometry": {"coordinates":[-91.397002,31.558713],"type":"Point"}
}