{
  "type": "Feature",
  "properties": {
    "iso:country":"US",
    "sg:address":"1410 Highway 80 W",
    "sg:city":"Jackson",
    "sg:phone":"+1 601 948 2886",
    "sg:postcode":"39204",
    "sg:province":"MS",
    "sg:website":"http://www.ccctirepros.com",
    "wof:name":"Capital Car Care",
    "wof:placetype":"venue"
},
  "geometry": {"coordinates":[-90.207939,32.286176],"type":"Point"}
}