{
  "type": "Feature",
  "properties": {
    "addr:full":"120 Guthrie Dr Southaven MS 38671",
    "addr:housenumber":"120",
    "addr:postcode":"38671",
    "addr:street":"Guthrie Dr",
    "iso:country":"US",
    "sg:address":"120 Guthrie Dr",
    "sg:city":"Southaven",
    "sg:classifiers":[
        {
            "category":"Banks & Credit Unions",
            "subcategory":"Bank",
            "type":"Services"
        }
    ],
    "sg:phone":"+1 662 342 1882",
    "sg:postcode":"38671",
    "sg:province":"MS",
    "sg:tags":[
        "loan",
        "real estate"
    ],
    "wof:name":"Alliance Capital Mortgage LLC",
    "wof:placetype":"venue"
},
  "geometry": {"coordinates":[-89.98868,34.968236],"type":"Point"}
}