{
  "type": "Feature",
  "properties": {
    "iso:country":"US",
    "sg:address":"528 Main St",
    "sg:city":"Philadelphia",
    "sg:classifiers":[
        {
            "category":"Insurance",
            "subcategory":"Insurance Agent",
            "type":"Services"
        }
    ],
    "sg:phone":"+1 601 656 4401",
    "sg:postcode":"39350",
    "sg:province":"MS",
    "wof:name":"Philadelphia Security Ins",
    "wof:placetype":"venue"
},
  "geometry": {"coordinates":[-89.10836999999999,32.77095],"type":"Point"}
}