{
  "type": "Feature",
  "properties": {
    "addr:full":"321 Goodman Rd W Southaven MS 38671",
    "addr:housenumber":"321",
    "addr:postcode":"38671",
    "addr:street":"Goodman Rd W",
    "iso:country":"US",
    "sg:address":"321 Goodman Rd W",
    "sg:city":"Southaven",
    "sg:classifiers":[
        {
            "category":"Restaurant",
            "type":"Food & Drink"
        }
    ],
    "sg:menulink":"http://www.allmenus.com/ms/southaven/96667-ihop/menu/",
    "sg:phone":"+1 662 349 1020",
    "sg:postcode":"38671",
    "sg:province":"MS",
    "sg:tags":[
        "sandwich",
        "salad",
        "burger",
        "soup",
        "american",
        "steakhouse",
        "wrap"
    ],
    "wof:name":"IHOP",
    "wof:placetype":"venue"
},
  "geometry": {"coordinates":[-89.993126,34.962669],"type":"Point"}
}