{
  "type": "Feature",
  "properties": {
    "addr:full":"9659 Goodman Rd Olive Branch MS 38654",
    "addr:housenumber":"9659",
    "addr:postcode":"38654",
    "addr:street":"Goodman Rd",
    "iso:country":"US",
    "sg:address":"9659 Goodman Rd",
    "sg:city":"Olive Branch",
    "sg:classifiers":[
        {
            "category":"Health Services",
            "subcategory":"Chiropractor",
            "type":"Services"
        }
    ],
    "sg:phone":"+1 662 895 2501",
    "sg:postcode":"38654",
    "sg:province":"MS",
    "wof:name":"De Sutter Chiropractic Clinic",
    "wof:placetype":"venue"
},
  "geometry": {"coordinates":[-89.819461,34.962105],"type":"Point"}
}