{
  "type": "Feature",
  "properties": {
    "iso:country":"US",
    "sg:address":"706 S Central Ave",
    "sg:city":"New Albany",
    "sg:classifiers":[
        {
            "category":"Social Services",
            "subcategory":"Child Care",
            "type":"Services"
        }
    ],
    "sg:phone":"+1 662 539 0408",
    "sg:postcode":"38652",
    "sg:province":"MS",
    "sg:tags":[
        "kindergarten",
        "academic",
        "school"
    ],
    "wof:name":"Rainbow Learning Ctr Inc",
    "wof:placetype":"venue"
},
  "geometry": {"coordinates":[-89.013774,34.483501],"type":"Point"}
}