{
  "type": "Feature",
  "properties": {
    "iso:country":"US",
    "sg:address":"368 Hwy 481",
    "sg:city":"Pelahatchie",
    "sg:classifiers":[
        {
            "category":"Utilities",
            "subcategory":"Water",
            "type":"Services"
        }
    ],
    "sg:phone":"+1 601 854 8729",
    "sg:postcode":"39145",
    "sg:province":"MS",
    "sg:tags":[
        "company",
        "sewage",
        "supply"
    ],
    "wof:name":"Leesburg Water Association",
    "wof:placetype":"venue"
},
  "geometry": {"coordinates":[-89.797179,32.440032],"type":"Point"}
}