{
  "type": "Feature",
  "properties": {
    "iso:country":"US",
    "sg:address":"935 Grand Ave",
    "sg:city":"Yazoo City",
    "sg:classifiers":[
        {
            "category":"Food & Beverages",
            "subcategory":"Groceries & Convenience Stores",
            "type":"Retail Goods"
        }
    ],
    "sg:phone":"+1 662 746 9065",
    "sg:postcode":"39194",
    "sg:province":"MS",
    "wof:name":"Easy & Quick Stop",
    "wof:placetype":"venue"
},
  "geometry": {"coordinates":[-90.40258900000001,32.860123],"type":"Point"}
}