{
  "type": "Feature",
  "properties": {
    "addr:full":"555 Hwy 80 E Pearl MS 39208",
    "addr:housenumber":"555",
    "addr:postcode":"39208",
    "addr:street":"Hwy 80 E",
    "iso:country":"US",
    "sg:address":"555 Hwy 80 E",
    "sg:city":"Pearl",
    "sg:classifiers":[
        {
            "category":"Autos & Motor Vehicles",
            "subcategory":"Auto Supplies",
            "type":"Retail Goods"
        }
    ],
    "sg:phone":"+1 601 932 0706",
    "sg:postcode":"39208",
    "sg:province":"MS",
    "sg:tags":[
        "tire"
    ],
    "wof:name":"Southern Tire Sales",
    "wof:placetype":"venue"
},
  "geometry": {"coordinates":[-90.171434,32.280353],"type":"Point"}
}