{
  "type": "Feature",
  "properties": {
    "iso:country":"US",
    "sg:address":"6566 Pine Springs Rd",
    "sg:city":"Meridian",
    "sg:classifiers":[
        {
            "category":"Organizations",
            "subcategory":"Religious Organization",
            "type":"Services"
        }
    ],
    "sg:phone":"+1 601 737 5573",
    "sg:postcode":"39305",
    "sg:province":"MS",
    "sg:tags":[
        "church"
    ],
    "wof:name":"Oak Grove Baptist Church",
    "wof:placetype":"venue"
},
  "geometry": {"coordinates":[-88.746584,32.434802],"type":"Point"}
}