{
  "type": "Feature",
  "properties": {
    "iso:country":"US",
    "sg:address":"3312 Goodman Rd E",
    "sg:city":"Southaven",
    "sg:classifiers":[
        {
            "category":"Insurance",
            "subcategory":"Insurance Agent",
            "type":"Services"
        }
    ],
    "sg:phone":"+1 662 349 8330",
    "sg:postcode":"38672",
    "sg:province":"MS",
    "sg:tags":[
        "accident"
    ],
    "wof:name":"Clay & Wright Insurance Inc",
    "wof:placetype":"venue"
},
  "geometry": {"coordinates":[-89.93097299999999,34.962479],"type":"Point"}
}