{
  "type": "Feature",
  "properties": {
    "addr:full":"106 W Jackson St Belzoni MS 39038",
    "addr:housenumber":"106",
    "addr:postcode":"39038",
    "addr:street":"W Jackson St",
    "iso:country":"US",
    "sg:address":"106 W Jackson St",
    "sg:city":"Belzoni",
    "sg:classifiers":[
        {
            "category":"Farming",
            "subcategory":"Farm",
            "type":"Manufacturing & Wholesale Goods"
        }
    ],
    "sg:phone":"+1 662 247 4466",
    "sg:postcode":"39038",
    "sg:province":"MS",
    "wof:name":"B & B Fish Farm",
    "wof:placetype":"venue"
},
  "geometry": {"coordinates":[-90.48939799999999,33.177688],"type":"Point"}
}