{
  "type": "Feature",
  "properties": {
    "addr:full":"439 N Jackson St Houston MS 38851",
    "addr:housenumber":"439",
    "addr:postcode":"38851",
    "addr:street":"N Jackson St",
    "iso:country":"US",
    "sg:address":"439 N Jackson St",
    "sg:city":"Houston",
    "sg:classifiers":[
        {
            "category":"Shopping",
            "subcategory":"Florist",
            "type":"Retail Goods"
        }
    ],
    "sg:phone":"+1 662 456 4411",
    "sg:postcode":"38851",
    "sg:province":"MS",
    "wof:name":"Blooming Heights",
    "wof:placetype":"venue"
},
  "geometry": {"coordinates":[-89.000365,33.900538],"type":"Point"}
}