{
  "type": "Feature",
  "properties": {
    "iso:country":"US",
    "sg:address":"205 South St",
    "sg:city":"Enterprise",
    "sg:classifiers":[
        {
            "category":"Home & Garden",
            "subcategory":"Hardware",
            "type":"Retail Goods"
        }
    ],
    "sg:phone":"+1 601 659 7047",
    "sg:postcode":"39330",
    "sg:province":"MS",
    "wof:name":"Solar Hardware Corp",
    "wof:placetype":"venue"
},
  "geometry": {"coordinates":[-88.83469599999999,32.165701],"type":"Point"}
}