{
  "type": "Feature",
  "properties": {
    "iso:country":"US",
    "sg:address":"6202 US Hwy 49",
    "sg:city":"Hattiesburg",
    "sg:classifiers":[
        {
            "category":"Personal",
            "subcategory":"Beauty Salon",
            "type":"Services"
        }
    ],
    "sg:phone":"+1 601 544 7191",
    "sg:postcode":"39401",
    "sg:province":"MS",
    "wof:name":"Robert E Douglas Hair Cutting",
    "wof:placetype":"venue"
},
  "geometry": {"coordinates":[-89.342308,31.353186],"type":"Point"}
}