{
  "type": "Feature",
  "properties": {
    "iso:country":"US",
    "sg:address":"630 Friars Point Rd",
    "sg:city":"Clarksdale",
    "sg:classifiers":[
        {
            "category":"Professional",
            "subcategory":"Business Services",
            "type":"Services"
        }
    ],
    "sg:phone":"+1 662 624 5500",
    "sg:postcode":"38614",
    "sg:province":"MS",
    "sg:tags":[
        "appraiser"
    ],
    "wof:name":"Peay Appraisal Svc",
    "wof:placetype":"venue"
},
  "geometry": {"coordinates":[-90.575282,34.211608],"type":"Point"}
}