{
  "type": "Feature",
  "properties": {
    "iso:country":"US",
    "sg:address":"812 Park Dr",
    "sg:city":"Oxford",
    "sg:classifiers":[
        {
            "category":"Professional",
            "subcategory":"Secretarial Services",
            "type":"Services"
        }
    ],
    "sg:phone":"+1 662 236 9093",
    "sg:postcode":"38655",
    "sg:province":"MS",
    "sg:tags":[
        "convention",
        "court",
        "reporter"
    ],
    "wof:name":"Database Realtime Reporting",
    "wof:placetype":"venue"
},
  "geometry": {"coordinates":[-89.499487,34.38507],"type":"Point"}
}