{
  "type": "Feature",
  "properties": {
    "iso:country":"US",
    "sg:address":"116 S Broadway St",
    "sg:city":"Greenville",
    "sg:classifiers":[
        {
            "category":"Personal",
            "subcategory":"Beauty Salon",
            "type":"Services"
        }
    ],
    "sg:phone":"+1 662 378 2890",
    "sg:postcode":"38701",
    "sg:province":"MS",
    "sg:tags":[
        "hair",
        "stylist"
    ],
    "wof:name":"Say's Beauty Salon",
    "wof:placetype":"venue"
},
  "geometry": {"coordinates":[-91.05889999999999,33.410074],"type":"Point"}
}