{
  "type": "Feature",
  "properties": {
    "iso:country":"US",
    "sg:address":"209 Traceside Dr",
    "sg:city":"Natchez",
    "sg:classifiers":[
        {
            "category":"Retail",
            "subcategory":"Auto Repair",
            "type":"Services"
        }
    ],
    "sg:phone":"+1 601 445 5598",
    "sg:postcode":"39120",
    "sg:province":"MS",
    "sg:tags":[
        "wrecker"
    ],
    "wof:name":"Natchez Towing Svc",
    "wof:placetype":"venue"
},
  "geometry": {"coordinates":[-91.320487,31.564646],"type":"Point"}
}