{
  "type": "Feature",
  "properties": {
    "iso:country":"US",
    "sg:address":"2934 N Hills St",
    "sg:city":"Meridian",
    "sg:classifiers":[
        {
            "category":"Food & Beverages",
            "subcategory":"Groceries & Convenience Stores",
            "type":"Retail Goods"
        }
    ],
    "sg:phone":"+1 601 482 5478",
    "sg:postcode":"39305",
    "sg:province":"MS",
    "wof:name":"Southern Family Markets",
    "wof:placetype":"venue"
},
  "geometry": {"coordinates":[-88.708017,32.408609],"type":"Point"}
}