{
  "type": "Feature",
  "properties": {
    "addr:full":"209 Commerce St Tupelo MS 38804",
    "addr:housenumber":"209",
    "addr:postcode":"38804",
    "addr:street":"Commerce St",
    "iso:country":"US",
    "sg:address":"209 Commerce St",
    "sg:city":"Tupelo",
    "sg:classifiers":[
        {
            "category":"Banks & Credit Unions",
            "subcategory":"Bank",
            "type":"Services"
        }
    ],
    "sg:phone":"+1 662 842 1312",
    "sg:postcode":"38804",
    "sg:province":"MS",
    "sg:tags":[
        "financing"
    ],
    "wof:name":"Republic Finance Inc",
    "wof:placetype":"venue"
},
  "geometry": {"coordinates":[-88.701719,34.258065],"type":"Point"}
}