{
  "type": "Feature",
  "properties": {
    "iso:country":"US",
    "sg:address":"430 Security Sq",
    "sg:city":"Gulfport",
    "sg:classifiers":[
        {
            "category":"Health Services",
            "subcategory":"Doctor",
            "type":"Services"
        }
    ],
    "sg:phone":"+1 228 896 5413",
    "sg:postcode":"39507",
    "sg:province":"MS",
    "wof:name":"Jeffery S Leblanc DDS",
    "wof:placetype":"venue"
},
  "geometry": {"coordinates":[-89.043046,30.386258],"type":"Point"}
}