{
  "type": "Feature",
  "properties": {
    "iso:country":"US",
    "sg:address":"900 S Thomas St",
    "sg:city":"Tupelo",
    "sg:classifiers":[
        {
            "category":"Organizations",
            "subcategory":"Religious Organization",
            "type":"Services"
        }
    ],
    "sg:phone":"+1 662 842 5454",
    "sg:postcode":"38801",
    "sg:province":"MS",
    "wof:name":"First Untd Pentecostal Church",
    "wof:placetype":"venue"
},
  "geometry": {"coordinates":[-88.746348,34.247657],"type":"Point"}
}