{
  "type": "Feature",
  "properties": {
    "iso:country":"US",
    "sg:address":"821 Harrison St",
    "sg:city":"Tupelo",
    "sg:classifiers":[
        {
            "category":"Manufacturing",
            "subcategory":"Printing",
            "type":"Manufacturing & Wholesale Goods"
        }
    ],
    "sg:phone":"+1 662 842 4481",
    "sg:postcode":"38801",
    "sg:province":"MS",
    "sg:tags":[
        "printer"
    ],
    "wof:name":"Sparks Printing & Graphics Co",
    "wof:placetype":"venue"
},
  "geometry": {"coordinates":[-88.71768400000001,34.245163],"type":"Point"}
}