{
  "type": "Feature",
  "properties": {
    "iso:country":"US",
    "sg:address":"409 Washington Ave",
    "sg:city":"Greenville",
    "sg:classifiers":[
        {
            "category":"Professional",
            "subcategory":"Computer Services",
            "type":"Services"
        }
    ],
    "sg:phone":"+1 662 334 3793",
    "sg:postcode":"38701",
    "sg:province":"MS",
    "wof:name":"Office & Computer Svc",
    "wof:placetype":"venue"
},
  "geometry": {"coordinates":[-91.060985,33.411372],"type":"Point"}
}