{
  "type": "Feature",
  "properties": {
    "iso:country":"US",
    "sg:address":"1256 Hwy 98 E",
    "sg:city":"Columbia",
    "sg:classifiers":[
        {
            "category":"Manufacturing",
            "subcategory":"Tools & Machinery",
            "type":"Manufacturing & Wholesale Goods"
        }
    ],
    "sg:phone":"+1 601 736 1783",
    "sg:postcode":"39429",
    "sg:province":"MS",
    "sg:tags":[
        "engine",
        "machine",
        "industrial",
        "diesel",
        "shop"
    ],
    "wof:name":"Columbia Diesel Castings",
    "wof:placetype":"venue"
},
  "geometry": {"coordinates":[-89.79787399999999,31.247193],"type":"Point"}
}