{
  "type": "Feature",
  "properties": {
    "iso:country":"US",
    "sg:address":"108 Salem-Cato Rd",
    "sg:city":"Brandon",
    "sg:classifiers":[
        {
            "category":"Building & Trades",
            "subcategory":"Electrical",
            "type":"Services"
        }
    ],
    "sg:phone":"+1 601 824 4453",
    "sg:postcode":"39042",
    "sg:province":"MS",
    "sg:tags":[
        "electrical",
        "contractor"
    ],
    "wof:name":"J&J Electrical Cont",
    "wof:placetype":"venue"
},
  "geometry": {"coordinates":[-89.86972900000001,32.120173],"type":"Point"}
}