{
  "type": "Feature",
  "properties": {
    "iso:country":"US",
    "sg:address":"8080 US Hwy 49",
    "sg:city":"Gulfport",
    "sg:classifiers":[
        {
            "category":"Shopping",
            "subcategory":"Computers & Home Electronics",
            "type":"Retail Goods"
        }
    ],
    "sg:phone":"+1 228 864 1988",
    "sg:postcode":"39501",
    "sg:province":"MS",
    "sg:tags":[
        "automotive",
        "repair"
    ],
    "wof:name":"Empress Audio",
    "wof:placetype":"venue"
},
  "geometry": {"coordinates":[-89.092688,30.402085],"type":"Point"}
}