{
  "type": "Feature",
  "properties": {
    "addr:full":"608 Yellow Jacket Dr Starkville MS 39759",
    "addr:housenumber":"608",
    "addr:postcode":"39759",
    "addr:street":"Yellow Jacket Dr",
    "iso:country":"US",
    "sg:address":"608 Yellow Jacket Dr",
    "sg:city":"Starkville",
    "sg:classifiers":[
        {
            "category":"Communications",
            "subcategory":"Radio Station",
            "type":"Services"
        }
    ],
    "sg:phone":"+1 662 338 5424",
    "sg:postcode":"39759",
    "sg:province":"MS",
    "sg:tags":[
        "broadcast"
    ],
    "wof:name":"Urban Radio Broadcasting",
    "wof:placetype":"venue"
},
  "geometry": {"coordinates":[-88.818758,33.451841],"type":"Point"}
}