{
  "type": "Feature",
  "properties": {
    "iso:country":"US",
    "sg:address":"2525 Hwy 82 E",
    "sg:city":"Greenville",
    "sg:classifiers":[
        {
            "category":"Restaurant",
            "type":"Food & Drink"
        }
    ],
    "sg:phone":"+1 662 332 3799",
    "sg:postcode":"38703",
    "sg:province":"MS",
    "wof:name":"Anna' Casey's Steak & Seafood",
    "wof:placetype":"venue"
},
  "geometry": {"coordinates":[-91.019318,33.39977],"type":"Point"}
}