{
  "type": "Feature",
  "properties": {
    "iso:country":"US",
    "sg:address":"3325 Barb Ave",
    "sg:city":"Pascagoula",
    "sg:classifiers":[
        {
            "category":"Retail",
            "subcategory":"Auto Repair",
            "type":"Services"
        }
    ],
    "sg:phone":"+1 228 762 4177",
    "sg:postcode":"39581",
    "sg:province":"MS",
    "sg:tags":[
        "general"
    ],
    "wof:name":"Krebs Auto Repair",
    "wof:placetype":"venue"
},
  "geometry": {"coordinates":[-88.52606400000001,30.367663],"type":"Point"}
}