{
  "type": "Feature",
  "properties": {
    "iso:country":"US",
    "sg:address":"1163 Woodlawn St",
    "sg:city":"Tupelo",
    "sg:classifiers":[
        {
            "category":"Utilities",
            "subcategory":"Cable",
            "type":"Services"
        }
    ],
    "sg:phone":"+1 662 620 7490",
    "sg:postcode":"38804",
    "sg:province":"MS",
    "sg:tags":[
        "television"
    ],
    "wof:name":"Cabletime",
    "wof:placetype":"venue"
},
  "geometry": {"coordinates":[-88.72239399999999,34.265851],"type":"Point"}
}