{
  "type": "Feature",
  "properties": {
    "addr:full":"3346 E Tate Rd Coldwater MS 38668",
    "addr:housenumber":"3346",
    "addr:postcode":"38668",
    "addr:street":"E Tate Rd",
    "iso:country":"US",
    "sg:address":"3346 E Tate Rd",
    "sg:city":"Coldwater",
    "sg:classifiers":[
        {
            "category":"Farming",
            "subcategory":"Dairy Farm",
            "type":"Manufacturing & Wholesale Goods"
        }
    ],
    "sg:phone":"+1 662 562 4894",
    "sg:postcode":"38668",
    "sg:province":"MS",
    "wof:name":"Three T Farm LLC",
    "wof:placetype":"venue"
},
  "geometry": {"coordinates":[-89.889588,34.641143],"type":"Point"}
}