{
  "type": "Feature",
  "properties": {
    "iso:country":"US",
    "sg:address":"4669 Redwood Rd",
    "sg:city":"Vicksburg",
    "sg:classifiers":[
        {
            "category":"Organizations",
            "subcategory":"Religious Organization",
            "type":"Services"
        }
    ],
    "sg:phone":"+1 601 883 2144",
    "sg:postcode":"39183",
    "sg:province":"MS",
    "sg:tags":[
        "church"
    ],
    "wof:name":"Ridgeway Baptist Church",
    "wof:placetype":"venue"
},
  "geometry": {"coordinates":[-90.74107600000001,32.452345],"type":"Point"}
}