{
  "type": "Feature",
  "properties": {
    "iso:country":"US",
    "sg:address":"3970 White Oak Rd",
    "sg:city":"Tunica",
    "sg:classifiers":[
        {
            "category":"Utilities",
            "subcategory":"Electric",
            "type":"Services"
        }
    ],
    "sg:phone":"+1 662 363 2931",
    "sg:postcode":"38676",
    "sg:province":"MS",
    "sg:tags":[
        "company"
    ],
    "wof:name":"Coahoma Electric Power Assn",
    "wof:placetype":"venue"
},
  "geometry": {"coordinates":[-90.358358,34.683949],"type":"Point"}
}