{
  "type": "Feature",
  "properties": {
    "iso:country":"US",
    "sg:address":"5113 Raymond Ave",
    "sg:city":"Verona",
    "sg:classifiers":[
        {
            "category":"Manufacturing",
            "subcategory":"Metals",
            "type":"Manufacturing & Wholesale Goods"
        }
    ],
    "sg:phone":"+1 662 566 1123",
    "sg:postcode":"38879",
    "sg:province":"MS",
    "sg:tags":[
        "hardware"
    ],
    "wof:name":"Leggett & Platt Inc",
    "wof:placetype":"venue"
},
  "geometry": {"coordinates":[-88.720012,34.192922],"type":"Point"}
}