{
  "type": "Feature",
  "properties": {
    "addr:full":"6644 Gary Rd Byram MS 39272",
    "addr:housenumber":"6644",
    "addr:postcode":"39272",
    "addr:street":"Gary Rd",
    "iso:country":"US",
    "sg:address":"6644 Gary Rd",
    "sg:city":"Byram",
    "sg:classifiers":[
        {
            "category":"Organizations",
            "subcategory":"Religious Organization",
            "type":"Services"
        }
    ],
    "sg:phone":"+1 601 371 8300",
    "sg:postcode":"39272",
    "sg:province":"MS",
    "sg:tags":[
        "church"
    ],
    "wof:name":"Pentecostal Holiness Church",
    "wof:placetype":"venue"
},
  "geometry": {"coordinates":[-90.29843099999999,32.198365],"type":"Point"}
}