{
  "type": "Feature",
  "properties": {
    "addr:full":"5300 Diamondhead Cir Diamondhead MS 39525",
    "addr:housenumber":"5300",
    "addr:postcode":"39525",
    "addr:street":"Diamondhead Cir",
    "iso:country":"US",
    "sg:address":"5300 Diamondhead Cir",
    "sg:city":"Diamondhead",
    "sg:classifiers":[
        {
            "category":"Shopping",
            "subcategory":"Bicycles & Sporting Goods",
            "type":"Retail Goods"
        }
    ],
    "sg:phone":"+1 228 255 5030",
    "sg:postcode":"39525",
    "sg:province":"MS",
    "sg:tags":[
        "equipment",
        "lesson",
        "tennis"
    ],
    "wof:name":"Tennis World",
    "wof:placetype":"venue"
},
  "geometry": {"coordinates":[-89.37901599999999,30.381033],"type":"Point"}
}