{
  "type": "Feature",
  "properties": {
    "iso:country":"US",
    "sg:address":"354 Trace Rd",
    "sg:city":"Laurel",
    "sg:classifiers":[
        {
            "category":"Health Services",
            "subcategory":"Nursing And Care Facility",
            "type":"Services"
        }
    ],
    "sg:phone":"+1 601 425 5599",
    "sg:postcode":"39443",
    "sg:province":"MS",
    "sg:tags":[
        "intermediate"
    ],
    "wof:name":"Extra Care",
    "wof:placetype":"venue"
},
  "geometry": {"coordinates":[-89.16802199999999,31.769704],"type":"Point"}
}