{
  "type": "Feature",
  "properties": {
    "iso:country":"US",
    "sg:address":"2609 Catalpa Ave",
    "sg:city":"Pascagoula",
    "sg:classifiers":[
        {
            "category":"Professional",
            "subcategory":"Computer Services",
            "type":"Services"
        }
    ],
    "sg:phone":"+1 228 769 1441",
    "sg:postcode":"39567",
    "sg:province":"MS",
    "sg:tags":[
        "website",
        "design"
    ],
    "wof:name":"CMC Professional Svc",
    "wof:placetype":"venue"
},
  "geometry": {"coordinates":[-88.53809200000001,30.38016],"type":"Point"}
}