{
  "type": "Feature",
  "properties": {
    "iso:country":"US",
    "sg:address":"1815 Nail Rd W",
    "sg:city":"Horn Lake",
    "sg:classifiers":[
        {
            "category":"Restaurant",
            "type":"Food & Drink"
        }
    ],
    "sg:phone":"+1 662 342 6727",
    "sg:postcode":"38637",
    "sg:province":"MS",
    "sg:website":"www.htponders.com",
    "wof:name":"H T Ponder's",
    "wof:placetype":"venue"
},
  "geometry": {"coordinates":[-90.022126,34.948043],"type":"Point"}
}