{
  "type": "Feature",
  "properties": {
    "iso:country":"US",
    "sg:address":"2894 Raymond Bolton Rd",
    "sg:city":"Raymond",
    "sg:classifiers":[
        {
            "category":"Education",
            "subcategory":"School",
            "type":"Public Place"
        }
    ],
    "sg:phone":"+1 601 857 5568",
    "sg:postcode":"39154",
    "sg:province":"MS",
    "sg:website":"www.centralhinds.com",
    "wof:name":"Central Hinds Academy Inc",
    "wof:placetype":"venue"
},
  "geometry": {"coordinates":[-90.448318,32.283042],"type":"Point"}
}