{
  "type": "Feature",
  "properties": {
    "iso:country":"US",
    "sg:address":"2599 Linwood Rd",
    "sg:city":"Vaughan",
    "sg:classifiers":[
        {
            "category":"Farming",
            "subcategory":"Farm & Veterinary Services",
            "type":"Manufacturing & Wholesale Goods"
        }
    ],
    "sg:phone":"+1 662 673 2229",
    "sg:postcode":"39179",
    "sg:province":"MS",
    "sg:tags":[
        "gin",
        "cotton"
    ],
    "wof:name":"Linwood Gin Co",
    "wof:placetype":"venue"
},
  "geometry": {"coordinates":[-90.141623,32.783588],"type":"Point"}
}