{
  "type": "Feature",
  "properties": {
    "iso:country":"US",
    "sg:address":"1010 Azalea Dr",
    "sg:city":"Waynesboro",
    "sg:classifiers":[
        {
            "category":"Banks & Credit Unions",
            "subcategory":"Bank",
            "type":"Services"
        }
    ],
    "sg:phone":"+1 601 735 4391",
    "sg:postcode":"39367",
    "sg:province":"MS",
    "wof:name":"Great Southern National Bank",
    "wof:placetype":"venue"
},
  "geometry": {"coordinates":[-88.639781,31.679376],"type":"Point"}
}