{
  "type": "Feature",
  "properties": {
    "addr:full":"1553 E County Line Rd Jackson MS 39211",
    "addr:housenumber":"1553",
    "addr:postcode":"39211",
    "addr:street":"E County Line Rd",
    "iso:country":"US",
    "sg:address":"1553 E County Line Rd",
    "sg:city":"Jackson",
    "sg:classifiers":[
        {
            "category":"Professional",
            "subcategory":"Engineering",
            "type":"Services"
        }
    ],
    "sg:phone":"+1 601 957 7666",
    "sg:postcode":"39211",
    "sg:province":"MS",
    "sg:tags":[
        "construction",
        "management",
        "architectural"
    ],
    "wof:name":"URS",
    "wof:placetype":"venue"
},
  "geometry": {"coordinates":[-90.124258,32.399387],"type":"Point"}
}