{
  "type": "Feature",
  "properties": {
    "iso:country":"US",
    "sg:address":"704 Co Rd 300",
    "sg:city":"Shannon",
    "sg:phone":"+1 662 767 3847",
    "sg:postcode":"38868",
    "sg:province":"MS",
    "sg:tags":[
        "farm",
        "soybean"
    ],
    "wof:name":"Ricky Mask",
    "wof:placetype":"venue"
},
  "geometry": {"coordinates":[-88.78231599999999,34.118805],"type":"Point"}
}