{
  "type": "Feature",
  "properties": {
    "addr:full":"4919 N State St Jackson MS 39206",
    "addr:housenumber":"4919",
    "addr:postcode":"39206",
    "addr:street":"N State St",
    "iso:country":"US",
    "sg:address":"4919 N State St",
    "sg:city":"Jackson",
    "sg:classifiers":[
        {
            "category":"Personal",
            "subcategory":"Beauty Salon",
            "type":"Services"
        }
    ],
    "sg:phone":"+1 601 981 8996",
    "sg:postcode":"39206",
    "sg:province":"MS",
    "wof:name":"C & C Hair Designs",
    "wof:placetype":"venue"
},
  "geometry": {"coordinates":[-90.16988499999999,32.366145],"type":"Point"}
}