{
  "type": "Feature",
  "properties": {
    "addr:full":"201 Methodist Blvd Hattiesburg MS 39402",
    "addr:housenumber":"201",
    "addr:postcode":"39402",
    "addr:street":"Methodist Blvd",
    "iso:country":"US",
    "sg:address":"201 Methodist Blvd",
    "sg:city":"Hattiesburg",
    "sg:classifiers":[
        {
            "category":"Professional",
            "subcategory":"Business Services",
            "type":"Services"
        }
    ],
    "sg:phone":"+1 601 450 3417",
    "sg:postcode":"39402",
    "sg:province":"MS",
    "sg:tags":[
        "transcribing",
        "disc"
    ],
    "wof:name":"E Scribe Transcriptions",
    "wof:placetype":"venue"
},
  "geometry": {"coordinates":[-89.370863,31.327561],"type":"Point"}
}