{
  "type": "Feature",
  "properties": {
    "iso:country":"US",
    "sg:address":"600 Marquette Rd",
    "sg:city":"Brandon",
    "sg:classifiers":[
        {
            "category":"Social Services",
            "type":"Services"
        }
    ],
    "sg:phone":"+1 601 824 5848",
    "sg:postcode":"39042",
    "sg:province":"MS",
    "sg:tags":[
        "organization",
        "welfare"
    ],
    "wof:name":"Ms Children's Advocacy Ctr",
    "wof:placetype":"venue"
},
  "geometry": {"coordinates":[-90.004318,32.280665],"type":"Point"}
}