{
  "type": "Feature",
  "properties": {
    "iso:country":"US",
    "sg:address":"206 Pine Park Dr",
    "sg:city":"Pearl",
    "sg:classifiers":[
        {
            "category":"Wholesale",
            "subcategory":"Electrical",
            "type":"Manufacturing & Wholesale Goods"
        }
    ],
    "sg:phone":"+1 601 664 0003",
    "sg:postcode":"39208",
    "sg:province":"MS",
    "sg:tags":[
        "control",
        "security",
        "system"
    ],
    "wof:name":"Maximum Security Products",
    "wof:placetype":"venue"
},
  "geometry": {"coordinates":[-90.13220099999999,32.269156],"type":"Point"}
}