{
  "type": "Feature",
  "properties": {
    "iso:country":"US",
    "sg:address":"13 W Reynolds St",
    "sg:city":"Pontotoc",
    "sg:classifiers":[
        {
            "category":"Social Services",
            "type":"Services"
        }
    ],
    "sg:phone":"+1 662 489 4848",
    "sg:postcode":"38863",
    "sg:province":"MS",
    "sg:tags":[
        "counseling"
    ],
    "wof:name":"Courageous Changes Counseling",
    "wof:placetype":"venue"
},
  "geometry": {"coordinates":[-88.999833,34.249053],"type":"Point"}
}