{
  "type": "Feature",
  "properties": {
    "addr:full":"302 Rosa Ave Hattiesburg MS 39401",
    "addr:housenumber":"302",
    "addr:postcode":"39401",
    "addr:street":"Rosa Ave",
    "iso:country":"US",
    "sg:address":"302 Rosa Ave",
    "sg:city":"Hattiesburg",
    "sg:classifiers":[
        {
            "category":"Wholesale",
            "subcategory":"Home Furnishings",
            "type":"Manufacturing & Wholesale Goods"
        }
    ],
    "sg:phone":"+1 601 544 5924",
    "sg:postcode":"39401",
    "sg:province":"MS",
    "wof:name":"Dimensions Plus",
    "wof:placetype":"venue"
},
  "geometry": {"coordinates":[-89.29321,31.313591],"type":"Point"}
}