{
  "type": "Feature",
  "properties": {
    "iso:country":"US",
    "sg:address":"1218 Hwy 12 W",
    "sg:city":"Starkville",
    "sg:classifiers":[
        {
            "category":"Food & Beverages",
            "subcategory":"Groceries & Convenience Stores",
            "type":"Retail Goods"
        }
    ],
    "sg:phone":"+1 662 323 9839",
    "sg:postcode":"39759",
    "sg:province":"MS",
    "sg:tags":[
        "grocer"
    ],
    "wof:name":"New Lite Grocery & Deli",
    "wof:placetype":"venue"
},
  "geometry": {"coordinates":[-88.855986,33.439466],"type":"Point"}
}