{
  "type": "Feature",
  "properties": {
    "addr:full":"359 Airport Rd Newton MS 39345",
    "addr:housenumber":"359",
    "addr:postcode":"39345",
    "addr:street":"Airport Rd",
    "iso:country":"US",
    "sg:address":"359 Airport Rd",
    "sg:city":"Newton",
    "sg:classifiers":[
        {
            "category":"Personal",
            "subcategory":"Beauty Salon",
            "type":"Services"
        }
    ],
    "sg:phone":"+1 601 683 2406",
    "sg:postcode":"39345",
    "sg:province":"MS",
    "wof:name":"Jo's Beauty & Body Massage",
    "wof:placetype":"venue"
},
  "geometry": {"coordinates":[-89.129806,32.317528],"type":"Point"}
}