{
  "type": "Feature",
  "properties": {
    "addr:full":"909 E Dinkins St Canton MS 39046",
    "addr:housenumber":"909",
    "addr:postcode":"39046",
    "addr:street":"E Dinkins St",
    "iso:country":"US",
    "sg:address":"909 E Dinkins St",
    "sg:city":"Canton",
    "sg:classifiers":[
        {
            "category":"Social Services",
            "subcategory":"Child Care",
            "type":"Services"
        }
    ],
    "sg:phone":"+1 601 859 0042",
    "sg:postcode":"39046",
    "sg:province":"MS",
    "sg:tags":[
        "day"
    ],
    "wof:name":"Honey Pot",
    "wof:placetype":"venue"
},
  "geometry": {"coordinates":[-90.012277,32.604089],"type":"Point"}
}