{
  "type": "Feature",
  "properties": {
    "iso:country":"US",
    "sg:address":"107 W Central Ave",
    "sg:city":"Petal",
    "sg:classifiers":[
        {
            "category":"Banks & Credit Unions",
            "subcategory":"Bank",
            "type":"Services"
        }
    ],
    "sg:phone":"+1 601 450 4352",
    "sg:postcode":"39465",
    "sg:province":"MS",
    "sg:tags":[
        "cashing",
        "check"
    ],
    "wof:name":"Check Of Mississippi Inc",
    "wof:placetype":"venue"
},
  "geometry": {"coordinates":[-89.265877,31.346607],"type":"Point"}
}