{
  "type": "Feature",
  "properties": {
    "iso:country":"US",
    "sg:address":"2550 Flowood Dr",
    "sg:city":"Flowood",
    "sg:classifiers":[
        {
            "category":"Health Services",
            "subcategory":"Doctor",
            "type":"Services"
        }
    ],
    "sg:phone":"+1 601 933 9521",
    "sg:postcode":"39232",
    "sg:province":"MS",
    "sg:tags":[
        "physician",
        "surgeon"
    ],
    "wof:name":"Anesthesia Consultants",
    "wof:placetype":"venue"
},
  "geometry": {"coordinates":[-90.10992899999999,32.323093],"type":"Point"}
}