{
  "type": "Feature",
  "properties": {
    "iso:country":"US",
    "sg:address":"308 E 3rd St",
    "sg:city":"Laurel",
    "sg:classifiers":[
        {
            "category":"Retail",
            "subcategory":"Repair Shop",
            "type":"Services"
        }
    ],
    "sg:phone":"+1 601 649 3984",
    "sg:postcode":"39440",
    "sg:province":"MS",
    "sg:tags":[
        "refrigeration"
    ],
    "wof:name":"Keys AC Heat",
    "wof:placetype":"venue"
},
  "geometry": {"coordinates":[-89.12403399999999,31.691969],"type":"Point"}
}