{
  "type": "Feature",
  "properties": {
    "addr:full":"140 Progress Rd Poplarville MS 39470",
    "addr:housenumber":"140",
    "addr:postcode":"39470",
    "addr:street":"Progress Rd",
    "iso:country":"US",
    "sg:address":"140 Progress Rd",
    "sg:city":"Poplarville",
    "sg:classifiers":[
        {
            "category":"Manufacturing",
            "subcategory":"Wood Products",
            "type":"Manufacturing & Wholesale Goods"
        }
    ],
    "sg:phone":"+1 601 795 4548",
    "sg:postcode":"39470",
    "sg:province":"MS",
    "sg:tags":[
        "pallet",
        "skid"
    ],
    "wof:name":"Burkhalter Forestry Co",
    "wof:placetype":"venue"
},
  "geometry": {"coordinates":[-89.501836,30.811226],"type":"Point"}
}