{
  "type": "Feature",
  "properties": {
    "addr:full":"611 Dixie Ave Mendenhall MS 39114",
    "addr:housenumber":"611",
    "addr:postcode":"39114",
    "addr:street":"Dixie Ave",
    "iso:country":"US",
    "sg:address":"611 Dixie Ave",
    "sg:city":"Mendenhall",
    "sg:classifiers":[
        {
            "category":"Social Services",
            "subcategory":"Child Care",
            "type":"Services"
        }
    ],
    "sg:phone":"+1 601 847 0551",
    "sg:postcode":"39114",
    "sg:province":"MS",
    "wof:name":"Nazareth Bapt Chr Day Care",
    "wof:placetype":"venue"
},
  "geometry": {"coordinates":[-89.878364,31.960543],"type":"Point"}
}