{
  "type": "Feature",
  "properties": {
    "iso:country":"US",
    "sg:address":"5731 Old Canton Rd",
    "sg:city":"Jackson",
    "sg:classifiers":[
        {
            "category":"Personal",
            "subcategory":"Beauty Salon",
            "type":"Services"
        }
    ],
    "sg:phone":"+1 601 956 2855",
    "sg:postcode":"39211",
    "sg:province":"MS",
    "wof:name":"Charles Victors Hair Mgmt",
    "wof:placetype":"venue"
},
  "geometry": {"coordinates":[-90.122659,32.377521],"type":"Point"}
}