{
  "type": "Feature",
  "properties": {
    "iso:country":"US",
    "sg:address":"2680 Sellers Dr",
    "sg:city":"Meridian",
    "sg:classifiers":[
        {
            "category":"Building & Trades",
            "subcategory":"Plumbing",
            "type":"Services"
        }
    ],
    "sg:phone":"+1 601 482 8529",
    "sg:postcode":"39301",
    "sg:province":"MS",
    "sg:tags":[
        "conditioning",
        "air",
        "system",
        "contractor"
    ],
    "wof:name":"Service Co",
    "wof:placetype":"venue"
},
  "geometry": {"coordinates":[-88.66727899999999,32.384736],"type":"Point"}
}