{
  "type": "Feature",
  "properties": {
    "iso:country":"US",
    "sg:address":"11348 Whitmoore Pl",
    "sg:city":"Gulfport",
    "sg:classifiers":[
        {
            "category":"Retail",
            "subcategory":"Repair Shop",
            "type":"Services"
        }
    ],
    "sg:phone":"+1 228 832 7441",
    "sg:postcode":"39503",
    "sg:province":"MS",
    "sg:tags":[
        "upholsterer"
    ],
    "wof:name":"B & D Upholstery",
    "wof:placetype":"venue"
},
  "geometry": {"coordinates":[-89.17424,30.451305],"type":"Point"}
}