{
  "type": "Feature",
  "properties": {
    "addr:full":"4955 Douglas Dr Olive Branch MS 38654",
    "addr:housenumber":"4955",
    "addr:postcode":"38654",
    "addr:street":"Douglas Dr",
    "iso:country":"US",
    "sg:address":"4955 Douglas Dr",
    "sg:city":"Olive Branch",
    "sg:classifiers":[
        {
            "category":"Home & Garden",
            "subcategory":"Building Materials",
            "type":"Retail Goods"
        },
        {
            "category":"Manufacturing",
            "subcategory":"Glass & Minerals",
            "type":"Manufacturing & Wholesale Goods"
        }
    ],
    "sg:phone":"+1 662 536 0054",
    "sg:postcode":"38654",
    "sg:province":"MS",
    "sg:tags":[
        "product",
        "leaded",
        "mfg"
    ],
    "wof:name":"A Glass Creations",
    "wof:placetype":"venue"
},
  "geometry": {"coordinates":[-89.902349,34.97501],"type":"Point"}
}