{
  "type": "Feature",
  "properties": {
    "addr:full":"116 N Court St Sumner MS 38965",
    "addr:housenumber":"116",
    "addr:postcode":"38965",
    "addr:street":"N Court St",
    "iso:country":"US",
    "sg:address":"116 N Court St",
    "sg:city":"Sumner",
    "sg:classifiers":[
        {
            "category":"Insurance",
            "subcategory":"Insurance Agent",
            "type":"Services"
        }
    ],
    "sg:phone":"+1 662 375 8091",
    "sg:postcode":"38965",
    "sg:province":"MS",
    "wof:name":"Bourne Insurance",
    "wof:placetype":"venue"
},
  "geometry": {"coordinates":[-89.630976,34.161509],"type":"Point"}
}