{
  "type": "Feature",
  "properties": {
    "addr:full":"1482 Green Gable Dr Terry MS 39170",
    "addr:housenumber":"1482",
    "addr:postcode":"39170",
    "addr:street":"Green Gable Dr Terry",
    "iso:country":"US",
    "sg:address":"1482 Green Gable Dr",
    "sg:city":"Terry",
    "sg:classifiers":[
        {
            "category":"Building & Trades",
            "subcategory":"Electrical",
            "type":"Services"
        }
    ],
    "sg:phone":"+1 601 878 9207",
    "sg:postcode":"39170",
    "sg:province":"MS",
    "sg:tags":[
        "electrical",
        "contractor"
    ],
    "wof:name":"Mayfield Electrical Service Co",
    "wof:placetype":"venue"
},
  "geometry": {"coordinates":[-90.314972,32.108098],"type":"Point"}
}