{
  "type": "Feature",
  "properties": {
    "addr:full":"4266 Popps Ferry Rd Diberville MS 39540",
    "addr:housenumber":"4266",
    "addr:postcode":"39540",
    "addr:street":"Popps Ferry Rd",
    "iso:country":"US",
    "sg:address":"4266 Popps Ferry Rd",
    "sg:city":"Diberville",
    "sg:classifiers":[
        {
            "category":"Autos & Motor Vehicles",
            "subcategory":"Automobile Sales",
            "type":"Retail Goods"
        }
    ],
    "sg:phone":"+1 228 396 1976",
    "sg:postcode":"39540",
    "sg:province":"MS",
    "sg:tags":[
        "car",
        "dealer"
    ],
    "wof:name":"Colonial Auto Sales",
    "wof:placetype":"venue"
},
  "geometry": {"coordinates":[-88.907994,30.444431],"type":"Point"}
}