{
  "type": "Feature",
  "properties": {
    "iso:country":"US",
    "sg:address":"168 George Mann Rd",
    "sg:city":"Holly Springs",
    "sg:classifiers":[
        {
            "category":"Wholesale",
            "subcategory":"Jewelry",
            "type":"Manufacturing & Wholesale Goods"
        }
    ],
    "sg:phone":"+1 662 551 1636",
    "sg:postcode":"38659",
    "sg:province":"MS",
    "sg:tags":[
        "stone"
    ],
    "wof:name":"Authentic S Amercn Gems LLC",
    "wof:placetype":"venue"
},
  "geometry": {"coordinates":[-89.369711,34.693853],"type":"Point"}
}