{
  "type": "Feature",
  "properties": {
    "iso:country":"US",
    "sg:address":"1306 Bienville Blvd",
    "sg:city":"Ocean Springs",
    "sg:classifiers":[
        {
            "category":"Real Estate",
            "subcategory":"Real Estate Agent",
            "type":"Services"
        }
    ],
    "sg:phone":"+1 228 818 5100",
    "sg:postcode":"39564",
    "sg:province":"MS",
    "wof:name":"American Dream Real Estate",
    "wof:placetype":"venue"
},
  "geometry": {"coordinates":[-88.822154,30.415956],"type":"Point"}
}