{
  "type": "Feature",
  "properties": {
    "addr:full":"825 N Flag Chapel Rd Jackson MS 39209",
    "addr:housenumber":"825",
    "addr:postcode":"39209",
    "addr:street":"N Flag Chapel Rd",
    "iso:country":"US",
    "sg:address":"825 N Flag Chapel Rd",
    "sg:city":"Jackson",
    "sg:classifiers":[
        {
            "category":"Organizations",
            "subcategory":"Religious Organization",
            "type":"Services"
        }
    ],
    "sg:phone":"+1 601 922 7065",
    "sg:postcode":"39209",
    "sg:province":"MS",
    "sg:tags":[
        "church"
    ],
    "wof:name":"Sunshine Baptist Church",
    "wof:placetype":"venue"
},
  "geometry": {"coordinates":[-90.26569600000001,32.353865],"type":"Point"}
}