{
  "type": "Feature",
  "properties": {
    "addr:full":"3001 Goodman Rd W Horn Lake MS 38637",
    "addr:housenumber":"3001",
    "addr:postcode":"38637",
    "addr:street":"Goodman Rd W Horn Lake",
    "iso:country":"US",
    "sg:address":"3001 Goodman Rd W",
    "sg:city":"Horn Lake",
    "sg:classifiers":[
        {
            "category":"Retail",
            "subcategory":"Laundry & Dry Cleaning",
            "type":"Services"
        }
    ],
    "sg:phone":"+1 662 342 4999",
    "sg:postcode":"38637",
    "sg:province":"MS",
    "sg:tags":[
        "cleaners"
    ],
    "wof:name":"Tidy Cleaners",
    "wof:placetype":"venue"
},
  "geometry": {"coordinates":[-90.04684899999999,34.962633],"type":"Point"}
}