{
  "type": "Feature",
  "properties": {
    "addr:full":"1855 Lakeland Dr Jackson MS 39216",
    "addr:housenumber":"1855",
    "addr:postcode":"39216",
    "addr:street":"Lakeland Dr",
    "iso:country":"US",
    "sg:address":"1855 Lakeland Dr",
    "sg:city":"Jackson",
    "sg:classifiers":[
        {
            "category":"Education",
            "subcategory":"Vocational School",
            "type":"Public Place"
        }
    ],
    "sg:phone":"+1 601 914 4500",
    "sg:postcode":"39216",
    "sg:province":"MS",
    "sg:tags":[
        "training",
        "computer"
    ],
    "wof:name":"New Horizons Computer Learning",
    "wof:placetype":"venue"
},
  "geometry": {"coordinates":[-90.139017,32.333867],"type":"Point"}
}