{
  "type": "Feature",
  "properties": {
    "addr:full":"594 Fort Hill Rd Grenada MS 38901",
    "addr:housenumber":"594",
    "addr:postcode":"38901",
    "addr:street":"Fort Hill Rd",
    "iso:country":"US",
    "sg:address":"594 Fort Hill Rd",
    "sg:city":"Grenada",
    "sg:classifiers":[
        {
            "category":"Utilities",
            "subcategory":"Telephone",
            "type":"Services"
        }
    ],
    "sg:phone":"+1 662 226 2769",
    "sg:postcode":"38901",
    "sg:province":"MS",
    "sg:tags":[
        "communications"
    ],
    "wof:name":"AT&T",
    "wof:placetype":"venue"
},
  "geometry": {"coordinates":[-89.753263,33.770177],"type":"Point"}
}