{
  "type": "Feature",
  "properties": {
    "iso:country":"US",
    "sg:address":"1520 Carl McAllister Dr",
    "sg:city":"Raymond",
    "sg:classifiers":[
        {
            "category":"Freight",
            "type":"Transportation"
        }
    ],
    "sg:phone":"+1 601 373 4729",
    "sg:postcode":"39154",
    "sg:province":"MS",
    "sg:tags":[
        "operator",
        "trucking"
    ],
    "wof:name":"Rollin Big Trucking Inc",
    "wof:placetype":"venue"
},
  "geometry": {"coordinates":[-90.344962,32.228864],"type":"Point"}
}