{
  "type": "Feature",
  "properties": {
    "addr:full":"404 Spring St Waynesboro MS 39367",
    "addr:housenumber":"404",
    "addr:postcode":"39367",
    "addr:street":"Spring St",
    "iso:country":"US",
    "sg:address":"404 Spring St",
    "sg:city":"Waynesboro",
    "sg:classifiers":[
        {
            "category":"Organizations",
            "subcategory":"Religious Organization",
            "type":"Services"
        }
    ],
    "sg:phone":"+1 601 735 3337",
    "sg:postcode":"39367",
    "sg:province":"MS",
    "sg:tags":[
        "church"
    ],
    "wof:name":"Mt Carmel United Methodist Chr",
    "wof:placetype":"venue"
},
  "geometry": {"coordinates":[-88.63869,31.670621],"type":"Point"}
}