{
  "type": "Feature",
  "properties": {
    "addr:full":"1032 N State St Clarksdale MS 38614",
    "addr:housenumber":"1032",
    "addr:postcode":"38614",
    "addr:street":"N State St",
    "iso:country":"US",
    "sg:address":"1032 N State St",
    "sg:city":"Clarksdale",
    "sg:classifiers":[
        {
            "category":"Shopping",
            "subcategory":"Department Store",
            "type":"Retail Goods"
        }
    ],
    "sg:phone":"+1 662 624 2648",
    "sg:postcode":"38614",
    "sg:province":"MS",
    "sg:tags":[
        "shop"
    ],
    "wof:name":"Family Dollar Store",
    "wof:placetype":"venue"
},
  "geometry": {"coordinates":[-90.561685,34.195532],"type":"Point"}
}