{
  "type": "Feature",
  "properties": {
    "iso:country":"US",
    "sg:address":"2415 A St",
    "sg:city":"Meridian",
    "sg:classifiers":[
        {
            "category":"Shopping",
            "subcategory":"Optical Goods",
            "type":"Retail Goods"
        }
    ],
    "sg:phone":"+1 601 693 6374",
    "sg:postcode":"39301",
    "sg:province":"MS",
    "sg:tags":[
        "optician"
    ],
    "wof:name":"Grayson's Optical",
    "wof:placetype":"venue"
},
  "geometry": {"coordinates":[-88.699083,32.360048],"type":"Point"}
}