{
  "type": "Feature",
  "properties": {
    "addr:full":"131 McTyere Ave Jackson MS 39202",
    "addr:housenumber":"131",
    "addr:postcode":"39202",
    "addr:street":"Mctyere Ave",
    "iso:country":"US",
    "sg:address":"131 McTyere Ave",
    "sg:city":"Jackson",
    "sg:classifiers":[
        {
            "category":"Shopping",
            "subcategory":"Luggage & Leather Goods",
            "type":"Retail Goods"
        }
    ],
    "sg:phone":"+1 601 354 3127",
    "sg:postcode":"39202",
    "sg:province":"MS",
    "wof:name":"Mori Luggage & Gifts",
    "wof:placetype":"venue"
},
  "geometry": {"coordinates":[-90.18566300000001,32.320387],"type":"Point"}
}