{
  "type": "Feature",
  "properties": {
    "iso:country":"US",
    "sg:address":"809 Holland Ave",
    "sg:city":"Philadelphia",
    "sg:classifiers":[
        {
            "category":"Shopping",
            "subcategory":"Gifts & Souvenirs",
            "type":"Retail Goods"
        }
    ],
    "sg:phone":"+1 601 389 1199",
    "sg:postcode":"39350",
    "sg:province":"MS",
    "sg:tags":[
        "shop"
    ],
    "wof:name":"Custom Frame & Gift",
    "wof:placetype":"venue"
},
  "geometry": {"coordinates":[-89.10563999999999,32.760327],"type":"Point"}
}