{
  "type": "Feature",
  "properties": {
    "addr:full":"1448 N Main St Columbia MS 39429",
    "addr:housenumber":"1448",
    "addr:postcode":"39429",
    "addr:street":"N Main St",
    "iso:country":"US",
    "sg:address":"1448 N Main St",
    "sg:city":"Columbia",
    "sg:classifiers":[
        {
            "category":"Health Services",
            "subcategory":"Nursing And Care Facility",
            "type":"Services"
        }
    ],
    "sg:phone":"+1 601 736 8143",
    "sg:postcode":"39429",
    "sg:province":"MS",
    "sg:tags":[
        "home",
        "retirement",
        "community"
    ],
    "wof:name":"Haven House",
    "wof:placetype":"venue"
},
  "geometry": {"coordinates":[-89.840001,31.263068],"type":"Point"}
}