{
  "type": "Feature",
  "properties": {
    "iso:country":"US",
    "sg:address":"2318 Pass Rd",
    "sg:city":"Biloxi",
    "sg:classifiers":[
        {
            "category":"Real Estate",
            "subcategory":"Real Estate Agent",
            "type":"Services"
        }
    ],
    "sg:phone":"+1 228 388 7188",
    "sg:postcode":"39531",
    "sg:province":"MS",
    "wof:name":"Gulf States Real Estate",
    "wof:placetype":"venue"
},
  "geometry": {"coordinates":[-88.970609,30.402521],"type":"Point"}
}