{
  "type": "Feature",
  "properties": {
    "addr:full":"2485 W Capitol St Jackson MS 39209",
    "addr:housenumber":"2485",
    "addr:postcode":"39209",
    "addr:street":"W Capitol St",
    "iso:country":"US",
    "sg:address":"2485 W Capitol St",
    "sg:city":"Jackson",
    "sg:classifiers":[
        {
            "category":"Organizations",
            "subcategory":"Religious Organization",
            "type":"Services"
        }
    ],
    "sg:phone":"+1 601 352 1680",
    "sg:postcode":"39209",
    "sg:province":"MS",
    "sg:tags":[
        "church"
    ],
    "wof:name":"Greater True Vine 1",
    "wof:placetype":"venue"
},
  "geometry": {"coordinates":[-90.21854,32.316614],"type":"Point"}
}