{
  "type": "Feature",
  "properties": {
    "iso:country":"US",
    "sg:address":"14070 Dedeaux Rd",
    "sg:city":"Gulfport",
    "sg:classifiers":[
        {
            "category":"Health Services",
            "subcategory":"Doctor",
            "type":"Services"
        }
    ],
    "sg:phone":"+1 228 832 1951",
    "sg:postcode":"39503",
    "sg:province":"MS",
    "wof:name":"Ross L Buntyn DDS",
    "wof:placetype":"venue"
},
  "geometry": {"coordinates":[-89.072124,30.449573],"type":"Point"}
}