{
  "type": "Feature",
  "properties": {
    "iso:country":"US",
    "sg:address":"309 W Church St",
    "sg:city":"Greenwood",
    "sg:classifiers":[
        {
            "category":"Retail",
            "subcategory":"Laundry & Dry Cleaning",
            "type":"Services"
        }
    ],
    "sg:phone":"+1 662 453 6531",
    "sg:postcode":"38930",
    "sg:province":"MS",
    "sg:tags":[
        "cleaners"
    ],
    "wof:name":"Delta Steam Laundry Inc",
    "wof:placetype":"venue"
},
  "geometry": {"coordinates":[-90.183279,33.518215],"type":"Point"}
}