{
  "type": "Feature",
  "properties": {
    "addr:full":"1200 N Gloster St Tupelo MS 38804",
    "addr:housenumber":"1200",
    "addr:postcode":"38804",
    "addr:street":"N Gloster St",
    "iso:country":"US",
    "sg:address":"1200 N Gloster St",
    "sg:city":"Tupelo",
    "sg:classifiers":[
        {
            "category":"Health Services",
            "subcategory":"Doctor",
            "type":"Services"
        }
    ],
    "sg:phone":"+1 662 840 0990",
    "sg:postcode":"38804",
    "sg:province":"MS",
    "sg:tags":[
        "physician",
        "surgeon"
    ],
    "wof:name":"Jones Family Medical Clinic",
    "wof:placetype":"venue"
},
  "geometry": {"coordinates":[-88.71548,34.278901],"type":"Point"}
}