{
  "type": "Feature",
  "properties": {
    "iso:country":"US",
    "sg:address":"1725 Dorchester Dr",
    "sg:city":"Southaven",
    "sg:classifiers":[
        {
            "category":"Real Estate",
            "subcategory":"Real Estate Services",
            "type":"Services"
        },
        {
            "category":"Real Estate",
            "subcategory":"Real Estate Operator",
            "type":"Services"
        }
    ],
    "sg:phone":"+1 662 393 8560",
    "sg:postcode":"38671",
    "sg:province":"MS",
    "sg:tags":[
        "vacancy",
        "apartment",
        "rental",
        "finder",
        "listing"
    ],
    "wof:name":"Dorchester Place Apartments",
    "wof:placetype":"venue"
},
  "geometry": {"coordinates":[-90.02081200000001,34.969597],"type":"Point"}
}