{
  "type": "Feature",
  "properties": {
    "addr:full":"111 E Church St Newton MS 39345",
    "addr:housenumber":"111",
    "addr:postcode":"39345",
    "addr:street":"E Church St",
    "iso:country":"US",
    "sg:address":"111 E Church St",
    "sg:city":"Newton",
    "sg:classifiers":[
        {
            "category":"Government",
            "subcategory":"Post Office",
            "type":"Public Place"
        }
    ],
    "sg:phone":"+1 601 683 2751",
    "sg:postcode":"39345",
    "sg:province":"MS",
    "wof:name":"US Post Office",
    "wof:placetype":"venue"
},
  "geometry": {"coordinates":[-89.162954,32.32161],"type":"Point"}
}