{
  "type": "Feature",
  "properties": {
    "addr:full":"324 Courthouse Rd Gulfport MS 39507",
    "addr:housenumber":"324",
    "addr:postcode":"39507",
    "addr:street":"Courthouse Rd",
    "iso:country":"US",
    "sg:address":"324 Courthouse Rd",
    "sg:city":"Gulfport",
    "sg:classifiers":[
        {
            "category":"Real Estate",
            "subcategory":"Real Estate Agent",
            "type":"Services"
        }
    ],
    "sg:phone":"+1 228 896 8518",
    "sg:postcode":"39507",
    "sg:province":"MS",
    "sg:tags":[
        "appraiser"
    ],
    "wof:name":"Gulf Appraisal Group",
    "wof:placetype":"venue"
},
  "geometry": {"coordinates":[-89.043942,30.382116],"type":"Point"}
}