{
  "type": "Feature",
  "properties": {
    "addr:full":"190 Churchwell Dr Lucedale MS 39452",
    "addr:housenumber":"190",
    "addr:postcode":"39452",
    "addr:street":"Churchwell Dr Lucedale",
    "iso:country":"US",
    "sg:address":"190 Churchwell Dr",
    "sg:city":"Lucedale",
    "sg:classifiers":[
        {
            "category":"Wholesale",
            "subcategory":"Non-durable Goods",
            "type":"Manufacturing & Wholesale Goods"
        },
        {
            "category":"Shopping",
            "subcategory":"Gifts & Souvenirs",
            "type":"Retail Goods"
        }
    ],
    "sg:phone":"+1 601 947 0123",
    "sg:postcode":"39452",
    "sg:province":"MS",
    "sg:tags":[
        "shop"
    ],
    "wof:name":"Taylor Made Baskets and Gifts",
    "wof:placetype":"venue"
},
  "geometry": {"coordinates":[-88.531768,30.799788],"type":"Point"}
}