{
  "type": "Feature",
  "properties": {
    "iso:country":"US",
    "sg:address":"801 Ridgewood Rd",
    "sg:city":"Ridgeland",
    "sg:classifiers":[
        {
            "category":"Travel",
            "subcategory":"Hotels & Motels",
            "type":"Entertainment"
        }
    ],
    "sg:phone":"+1 601 206 9190",
    "sg:postcode":"39157",
    "sg:province":"MS",
    "wof:name":"Staybridge",
    "wof:placetype":"venue"
},
  "geometry": {"coordinates":[-90.140862,32.411249],"type":"Point"}
}