{
  "type": "Feature",
  "properties": {
    "addr:full":"2941 Terry Rd Jackson MS 39212",
    "addr:housenumber":"2941",
    "addr:postcode":"39212",
    "addr:street":"Terry Rd",
    "iso:country":"US",
    "sg:address":"2941 Terry Rd",
    "sg:city":"Jackson",
    "sg:classifiers":[
        {
            "category":"Personal",
            "subcategory":"Beauty Salon",
            "type":"Services"
        }
    ],
    "sg:phone":"+1 601 373 0131",
    "sg:postcode":"39212",
    "sg:province":"MS",
    "sg:tags":[
        "shop"
    ],
    "wof:name":"Alice Borders",
    "wof:placetype":"venue"
},
  "geometry": {"coordinates":[-90.22035099999999,32.262075],"type":"Point"}
}