{
  "type": "Feature",
  "properties": {
    "addr:full":"405 Fairway Dr Pass Christian MS 39571",
    "addr:housenumber":"405",
    "addr:postcode":"39571",
    "addr:street":"Fairway Dr",
    "iso:country":"US",
    "sg:address":"405 Fairway Dr",
    "sg:city":"Pass Christian",
    "sg:classifiers":[
        {
            "category":"Home & Garden",
            "subcategory":"Hardware",
            "type":"Retail Goods"
        }
    ],
    "sg:phone":"+1 228 452 0077",
    "sg:postcode":"39571",
    "sg:province":"MS",
    "wof:name":"Ace Hardware",
    "wof:placetype":"venue"
},
  "geometry": {"coordinates":[-89.28196199999999,30.329657],"type":"Point"}
}