{
  "type": "Feature",
  "properties": {
    "addr:full":"102 Raymond Rd Jackson MS 39204",
    "addr:housenumber":"102",
    "addr:postcode":"39204",
    "addr:street":"Raymond Rd",
    "iso:country":"US",
    "sg:address":"102 Raymond Rd",
    "sg:city":"Jackson",
    "sg:classifiers":[
        {
            "category":"Retail",
            "subcategory":"Auto Repair",
            "type":"Services"
        }
    ],
    "sg:phone":"+1 601 373 4642",
    "sg:postcode":"39204",
    "sg:province":"MS",
    "sg:tags":[
        "body",
        "automobile",
        "painting"
    ],
    "wof:name":"Capitol Body Shop Towing",
    "wof:placetype":"venue"
},
  "geometry": {"coordinates":[-90.209447,32.28297],"type":"Point"}
}