{
  "type": "Feature",
  "properties": {
    "iso:country":"US",
    "sg:address":"2017 20th Ave",
    "sg:city":"Gulfport",
    "sg:classifiers":[
        {
            "category":"Professional",
            "subcategory":"Lawyer & Legal Services",
            "type":"Services"
        }
    ],
    "sg:phone":"+1 228 864 3489",
    "sg:postcode":"39501",
    "sg:province":"MS",
    "sg:tags":[
        "attorney"
    ],
    "sg:website":"www.lawyergulfport.com",
    "wof:name":"William A Pate",
    "wof:placetype":"venue"
},
  "geometry": {"coordinates":[-89.08614300000001,30.375448],"type":"Point"}
}