{
  "type": "Feature",
  "properties": {
    "addr:full":"119 N Oak St Raymond MS 39154",
    "addr:housenumber":"119",
    "addr:postcode":"39154",
    "addr:street":"N Oak St",
    "iso:country":"US",
    "sg:address":"119 N Oak St",
    "sg:city":"Raymond",
    "sg:classifiers":[
        {
            "category":"Insurance",
            "subcategory":"Insurance Agent",
            "type":"Services"
        }
    ],
    "sg:phone":"+1 601 857 0765",
    "sg:postcode":"39154",
    "sg:province":"MS",
    "wof:name":"Mutual Of Omaha Insurance Co",
    "wof:placetype":"venue"
},
  "geometry": {"coordinates":[-90.42173099999999,32.262055],"type":"Point"}
}