{
  "type": "Feature",
  "properties": {
    "iso:country":"US",
    "sg:address":"630 Anela St",
    "sg:city":"Diamondhead",
    "sg:classifiers":[
        {
            "category":"Professional",
            "type":"Services"
        }
    ],
    "sg:phone":"+1 228 255 7699",
    "sg:postcode":"39525",
    "sg:province":"MS",
    "wof:name":"Albert W Small",
    "wof:placetype":"venue"
},
  "geometry": {"coordinates":[-89.38139099999999,30.387597],"type":"Point"}
}