{
  "type": "Feature",
  "properties": {
    "iso:country":"US",
    "sg:address":"148 Oak St",
    "sg:city":"Greenville",
    "sg:classifiers":[
        {
            "category":"Building & Trades",
            "subcategory":"Construction",
            "type":"Services"
        }
    ],
    "sg:phone":"+1 662 334 6002",
    "sg:postcode":"38701",
    "sg:province":"MS",
    "sg:tags":[
        "siding",
        "contractor"
    ],
    "wof:name":"Custom Siding Co",
    "wof:placetype":"venue"
},
  "geometry": {"coordinates":[-91.074145,33.366267],"type":"Point"}
}