{
  "type": "Feature",
  "properties": {
    "iso:country":"US",
    "sg:address":"5630 Terry Rd",
    "sg:city":"Byram",
    "sg:classifiers":[
        {
            "category":"Manufacturing",
            "subcategory":"Printing",
            "type":"Manufacturing & Wholesale Goods"
        }
    ],
    "sg:phone":"+1 601 376 9004",
    "sg:postcode":"39272",
    "sg:province":"MS",
    "sg:tags":[
        "screen"
    ],
    "wof:name":"Gator Grafix Inc",
    "wof:placetype":"venue"
},
  "geometry": {"coordinates":[-90.28038100000001,32.171945],"type":"Point"}
}