{
  "type": "Feature",
  "properties": {
    "addr:full":"2400 Robinson St Jackson MS 39209",
    "addr:housenumber":"2400",
    "addr:postcode":"39209",
    "addr:street":"Robinson St",
    "iso:country":"US",
    "sg:address":"2400 Robinson St",
    "sg:city":"Jackson",
    "sg:classifiers":[
        {
            "category":"Education",
            "subcategory":"School",
            "type":"Public Place"
        }
    ],
    "sg:phone":"+1 601 960 5393",
    "sg:postcode":"39209",
    "sg:province":"MS",
    "wof:name":"Provine Senior High School",
    "wof:placetype":"venue"
},
  "geometry": {"coordinates":[-90.226624,32.305375],"type":"Point"}
}