{
  "type": "Feature",
  "properties": {
    "iso:country":"US",
    "sg:address":"404 S Beauchamp Ave",
    "sg:city":"Greenville",
    "sg:classifiers":[
        {
            "category":"Retail",
            "subcategory":"Auto Repair",
            "type":"Services"
        }
    ],
    "sg:phone":"+1 662 335 8222",
    "sg:postcode":"38703",
    "sg:province":"MS",
    "sg:tags":[
        "body"
    ],
    "wof:name":"Chatman Auto Upholstery",
    "wof:placetype":"venue"
},
  "geometry": {"coordinates":[-91.01954600000001,33.402811],"type":"Point"}
}