{
  "type": "Feature",
  "properties": {
    "iso:country":"US",
    "sg:address":"4735 Old Canton Rd",
    "sg:city":"Jackson",
    "sg:classifiers":[
        {
            "category":"Professional",
            "subcategory":"Lawyer & Legal Services",
            "type":"Services"
        }
    ],
    "sg:phone":"+1 601 366 4343",
    "sg:postcode":"39211",
    "sg:province":"MS",
    "sg:tags":[
        "attorney"
    ],
    "wof:name":"Wilkins Stephens & Tipton Pa",
    "wof:placetype":"venue"
},
  "geometry": {"coordinates":[-90.14621,32.362867],"type":"Point"}
}