{
  "type": "Feature",
  "properties": {
    "iso:country":"US",
    "sg:address":"5772 US Hwy 11",
    "sg:city":"Purvis",
    "sg:classifiers":[
        {
            "category":"Restaurant",
            "type":"Food & Drink"
        }
    ],
    "sg:phone":"+1 601 794 8007",
    "sg:postcode":"39475",
    "sg:province":"MS",
    "wof:name":"Movie Star Restaurant/Catering",
    "wof:placetype":"venue"
},
  "geometry": {"coordinates":[-89.40293800000001,31.146297],"type":"Point"}
}