{
  "type": "Feature",
  "properties": {
    "addr:full":"845 N Cherry St Magnolia MS 39652",
    "addr:housenumber":"845",
    "addr:postcode":"39652",
    "addr:street":"N Cherry St",
    "iso:country":"US",
    "sg:address":"845 N Cherry St",
    "sg:city":"Magnolia",
    "sg:classifiers":[
        {
            "category":"Organizations",
            "subcategory":"Religious Organization",
            "type":"Services"
        }
    ],
    "sg:phone":"+1 601 783 3702",
    "sg:postcode":"39652",
    "sg:province":"MS",
    "sg:tags":[
        "church"
    ],
    "wof:name":"Rose Hill Baptist Church",
    "wof:placetype":"venue"
},
  "geometry": {"coordinates":[-90.45518199999999,31.154734],"type":"Point"}
}