{
  "type": "Feature",
  "properties": {
    "iso:country":"US",
    "sg:address":"1020 Hickory Ridge Dr",
    "sg:city":"Kosciusko",
    "sg:classifiers":[
        {
            "category":"Wholesale",
            "subcategory":"Groceries",
            "type":"Manufacturing & Wholesale Goods"
        }
    ],
    "sg:phone":"+1 662 289 7506",
    "sg:postcode":"39090",
    "sg:province":"MS",
    "wof:name":"Spot Cash Specialty Co Inc",
    "wof:placetype":"venue"
},
  "geometry": {"coordinates":[-89.57429399999999,33.051167],"type":"Point"}
}