{
  "type": "Feature",
  "properties": {
    "iso:country":"US",
    "sg:address":"214 S State St",
    "sg:city":"Jackson",
    "sg:classifiers":[
        {
            "category":"Banks & Credit Unions",
            "subcategory":"Financial Services",
            "type":"Services"
        }
    ],
    "sg:phone":"+1 601 634 1030",
    "sg:postcode":"39201",
    "sg:province":"MS",
    "sg:tags":[
        "investor"
    ],
    "wof:name":"Southaven Townhouse",
    "wof:placetype":"venue"
},
  "geometry": {"coordinates":[-90.18077700000001,32.297266],"type":"Point"}
}