{
  "type": "Feature",
  "properties": {
    "addr:full":"2113 Alex Ave Pascagoula MS 39567",
    "addr:housenumber":"2113",
    "addr:postcode":"39567",
    "addr:street":"Alex Ave",
    "iso:country":"US",
    "sg:address":"2113 Alex Ave",
    "sg:city":"Pascagoula",
    "sg:classifiers":[
        {
            "category":"Real Estate",
            "subcategory":"Real Estate Agent",
            "type":"Services"
        }
    ],
    "sg:phone":"+1 228 762 6181",
    "sg:postcode":"39567",
    "sg:province":"MS",
    "sg:tags":[
        "authorities",
        "housing"
    ],
    "wof:name":"Housing Authority",
    "wof:placetype":"venue"
},
  "geometry": {"coordinates":[-88.542008,30.374113],"type":"Point"}
}