{
  "type": "Feature",
  "properties": {
    "iso:country":"US",
    "sg:address":"300 Ragsdale Rd",
    "sg:city":"Canton",
    "sg:classifiers":[
        {
            "category":"Professional",
            "subcategory":"Engineering",
            "type":"Services"
        }
    ],
    "sg:phone":"+1 601 407 1775",
    "sg:postcode":"39094",
    "sg:province":"MS",
    "sg:tags":[
        "engineer"
    ],
    "wof:name":"Florstore Engineering Inc",
    "wof:placetype":"venue"
},
  "geometry": {"coordinates":[-89.643959,32.640664],"type":"Point"}
}