{
  "type": "Feature",
  "properties": {
    "iso:country":"US",
    "sg:address":"1760 Oak Ridge Rd",
    "sg:city":"Vicksburg",
    "sg:classifiers":[
        {
            "category":"Food & Beverages",
            "subcategory":"Groceries & Convenience Stores",
            "type":"Retail Goods"
        }
    ],
    "sg:phone":"+1 601 638 0195",
    "sg:postcode":"39180",
    "sg:province":"MS",
    "wof:name":"Moak Petroleum",
    "wof:placetype":"venue"
},
  "geometry": {"coordinates":[-90.79406,32.40014],"type":"Point"}
}