{
  "type": "Feature",
  "properties": {
    "iso:country":"US",
    "sg:address":"195 E Railroad Ave N",
    "sg:city":"Magnolia",
    "sg:classifiers":[
        {
            "category":"Shopping",
            "subcategory":"Clothing, Apparel, & Fashions",
            "type":"Retail Goods"
        }
    ],
    "sg:phone":"+1 601 783 5564",
    "sg:postcode":"39652",
    "sg:province":"MS",
    "wof:name":"Rials Boutique",
    "wof:placetype":"venue"
},
  "geometry": {"coordinates":[-90.45790100000001,31.143149],"type":"Point"}
}