{
  "type": "Feature",
  "properties": {
    "iso:country":"US",
    "sg:address":"7638 Co Rd 280",
    "sg:city":"Vossburg",
    "sg:classifiers":[
        {
            "category":"Organizations",
            "subcategory":"Religious Organization",
            "type":"Services"
        }
    ],
    "sg:phone":"+1 601 776 3527",
    "sg:postcode":"39366",
    "sg:province":"MS",
    "sg:tags":[
        "church"
    ],
    "wof:name":"Knights Valley Baptist Church",
    "wof:placetype":"venue"
},
  "geometry": {"coordinates":[-88.85213899999999,31.945909],"type":"Point"}
}