{
  "type": "Feature",
  "properties": {
    "addr:full":"3005 Hwy 82 E Greenville MS 38703",
    "addr:housenumber":"3005",
    "addr:postcode":"38703",
    "addr:street":"Hwy 82 E",
    "iso:country":"US",
    "sg:address":"3005 Hwy 82 E",
    "sg:city":"Greenville",
    "sg:classifiers":[
        {
            "category":"Autos & Motor Vehicles",
            "subcategory":"Automobile Sales",
            "type":"Retail Goods"
        }
    ],
    "sg:phone":"+1 662 332 8135",
    "sg:postcode":"38703",
    "sg:province":"MS",
    "sg:tags":[
        "car",
        "dealer"
    ],
    "wof:name":"Callender Motors",
    "wof:placetype":"venue"
},
  "geometry": {"coordinates":[-91.014134,33.399905],"type":"Point"}
}