{
  "type": "Feature",
  "properties": {
    "iso:country":"US",
    "sg:address":"1167 Silver Dr",
    "sg:city":"Osyka",
    "sg:classifiers":[
        {
            "category":"Farming",
            "subcategory":"Poultry Farm",
            "type":"Manufacturing & Wholesale Goods"
        }
    ],
    "sg:phone":"+1 601 542 5622",
    "sg:postcode":"39657",
    "sg:province":"MS",
    "sg:tags":[
        "chicken"
    ],
    "wof:name":"Dillion Chicken Ranch",
    "wof:placetype":"venue"
},
  "geometry": {"coordinates":[-90.30364,31.008969],"type":"Point"}
}