{
  "type": "Feature",
  "properties": {
    "iso:country":"US",
    "sg:address":"6 Overby St",
    "sg:city":"Brandon",
    "sg:classifiers":[
        {
            "category":"Wholesale",
            "subcategory":"Tobacco Products",
            "type":"Manufacturing & Wholesale Goods"
        },
        {
            "category":"Shopping",
            "subcategory":"Tobacco",
            "type":"Retail Goods"
        }
    ],
    "sg:phone":"+1 601 824 0507",
    "sg:postcode":"39042",
    "sg:province":"MS",
    "sg:tags":[
        "cigarette",
        "cigar",
        "dealer"
    ],
    "wof:name":"Mack's Tobacco Shop",
    "wof:placetype":"venue"
},
  "geometry": {"coordinates":[-89.993927,32.273989],"type":"Point"}
}