{
  "type": "Feature",
  "properties": {
    "iso:country":"US",
    "sg:address":"1819 Quinn St",
    "sg:city":"Hattiesburg",
    "sg:classifiers":[
        {
            "category":"Social Services",
            "type":"Services"
        }
    ],
    "sg:phone":"+1 601 584 9540",
    "sg:postcode":"39401",
    "sg:province":"MS",
    "sg:tags":[
        "clinic",
        "specialty",
        "outpatient"
    ],
    "wof:name":"Personal Growth Center",
    "wof:placetype":"venue"
},
  "geometry": {"coordinates":[-89.31883000000001,31.328414],"type":"Point"}
}