{
  "type": "Feature",
  "properties": {
    "iso:country":"US",
    "sg:address":"123 Doyle St",
    "sg:city":"Poplarville",
    "sg:phone":"+1 601 795 6125",
    "sg:postcode":"39470",
    "sg:province":"MS",
    "sg:tags":[
        "product",
        "petroleum"
    ],
    "wof:name":"Pine Belt Oil Co",
    "wof:placetype":"venue"
},
  "geometry": {"coordinates":[-89.53463600000001,30.839523],"type":"Point"}
}