{
  "type": "Feature",
  "properties": {
    "addr:full":"13780 Vidalia Rd Pass Christian MS 39571",
    "addr:housenumber":"13780",
    "addr:postcode":"39571",
    "addr:street":"Vidalia Rd",
    "iso:country":"US",
    "sg:address":"13780 Vidalia Rd",
    "sg:city":"Pass Christian",
    "sg:classifiers":[
        {
            "category":"Real Estate",
            "subcategory":"Real Estate Operator",
            "type":"Services"
        }
    ],
    "sg:phone":"+1 228 255 7858",
    "sg:postcode":"39571",
    "sg:province":"MS",
    "sg:tags":[
        "mobile",
        "home",
        "community"
    ],
    "wof:name":"Vidalia Estates Mobile Home",
    "wof:placetype":"venue"
},
  "geometry": {"coordinates":[-89.336252,30.494336],"type":"Point"}
}