{
  "type": "Feature",
  "properties": {
    "addr:full":"11490 Old Hwy 61 Robinsonville MS 38664",
    "addr:housenumber":"11490",
    "addr:postcode":"38664",
    "addr:street":"Old Hwy 61",
    "iso:country":"US",
    "sg:address":"11490 Old Hwy 61",
    "sg:city":"Robinsonville",
    "sg:classifiers":[
        {
            "category":"Banks & Credit Unions",
            "subcategory":"Bank",
            "type":"Services"
        }
    ],
    "sg:phone":"+1 662 363 5015",
    "sg:postcode":"38664",
    "sg:province":"MS",
    "wof:name":"First Security Bank",
    "wof:placetype":"venue"
},
  "geometry": {"coordinates":[-90.314638,34.819239],"type":"Point"}
}