{
  "type": "Feature",
  "properties": {
    "iso:country":"US",
    "sg:address":"1400 Ellis Ave",
    "sg:city":"Jackson",
    "sg:classifiers":[
        {
            "category":"Shopping",
            "subcategory":"Gifts & Souvenirs",
            "type":"Retail Goods"
        },
        {
            "category":"Banks & Credit Unions",
            "subcategory":"Bank",
            "type":"Services"
        }
    ],
    "sg:phone":"+1 601 664 1200",
    "sg:postcode":"39204",
    "sg:province":"MS",
    "sg:tags":[
        "loan"
    ],
    "wof:name":"Hallmark Credit Corp",
    "wof:placetype":"venue"
},
  "geometry": {"coordinates":[-90.227752,32.293209],"type":"Point"}
}