{
  "type": "Feature",
  "properties": {
    "iso:country":"US",
    "sg:address":"950 Bonita Dr",
    "sg:city":"Meridian",
    "sg:classifiers":[
        {
            "category":"Organizations",
            "subcategory":"Religious Organization",
            "type":"Services"
        }
    ],
    "sg:phone":"+1 601 482 8750",
    "sg:postcode":"39301",
    "sg:province":"MS",
    "wof:name":"Calvary Hill Baptist Church",
    "wof:placetype":"venue"
},
  "geometry": {"coordinates":[-88.647961,32.370771],"type":"Point"}
}