{
  "type": "Feature",
  "properties": {
    "iso:country":"US",
    "sg:address":"30225 Johnson Mill Rd",
    "sg:city":"Nettleton",
    "sg:classifiers":[
        {
            "category":"Mining & Drilling",
            "type":"Manufacturing & Wholesale Goods"
        }
    ],
    "sg:phone":"+1 662 256 8218",
    "sg:postcode":"38858",
    "sg:province":"MS",
    "sg:tags":[
        "exploration"
    ],
    "wof:name":"Double E Farms",
    "wof:placetype":"venue"
},
  "geometry": {"coordinates":[-88.57865,34.02215],"type":"Point"}
}