{
  "type": "Feature",
  "properties": {
    "iso:country":"US",
    "sg:address":"1500 W Pine St",
    "sg:city":"Hattiesburg",
    "sg:classifiers":[
        {
            "category":"Autos & Motor Vehicles",
            "subcategory":"Automobile Sales",
            "type":"Retail Goods"
        }
    ],
    "sg:phone":"+1 601 544 3385",
    "sg:postcode":"39401",
    "sg:province":"MS",
    "sg:tags":[
        "car",
        "dealer"
    ],
    "wof:name":"Courtesy Motors Inc",
    "wof:placetype":"venue"
},
  "geometry": {"coordinates":[-89.30842699999999,31.3109],"type":"Point"}
}