{
  "type": "Feature",
  "properties": {
    "iso:country":"US",
    "sg:address":"2935 US Hwy 51",
    "sg:city":"Canton",
    "sg:classifiers":[
        {
            "category":"Government",
            "subcategory":"Jail",
            "type":"Public Place"
        }
    ],
    "sg:phone":"+1 601 859 5801",
    "sg:postcode":"39046",
    "sg:province":"MS",
    "sg:tags":[
        "county",
        "govt",
        "institution"
    ],
    "wof:name":"Madison County Jail",
    "wof:placetype":"venue"
},
  "geometry": {"coordinates":[-90.056406,32.567499],"type":"Point"}
}