{
  "type": "Feature",
  "properties": {
    "addr:full":"5438 I- 55 N Jackson MS 39211",
    "addr:housenumber":"5438;55 n",
    "addr:postcode":"39211",
    "addr:street":"I",
    "iso:country":"US",
    "sg:address":"5438 I- 55 N",
    "sg:city":"Jackson",
    "sg:classifiers":[
        {
            "category":"Insurance",
            "subcategory":"Insurance Agent",
            "type":"Services"
        }
    ],
    "sg:phone":"+1 601 957 7610",
    "sg:postcode":"39211",
    "sg:province":"MS",
    "sg:tags":[
        "agency"
    ],
    "wof:name":"Allstate",
    "wof:placetype":"venue"
},
  "geometry": {"coordinates":[-90.147853,32.374558],"type":"Point"}
}