{
  "type": "Feature",
  "properties": {
    "iso:country":"US",
    "sg:address":"2239 N Flag Chapel Rd",
    "sg:city":"Jackson",
    "sg:classifiers":[
        {
            "category":"Organizations",
            "subcategory":"Religious Organization",
            "type":"Services"
        }
    ],
    "sg:phone":"+1 601 922 9050",
    "sg:postcode":"39209",
    "sg:province":"MS",
    "wof:name":"Green Pastures Baptist Church",
    "wof:placetype":"venue"
},
  "geometry": {"coordinates":[-90.26579599999999,32.366073],"type":"Point"}
}