{
  "type": "Feature",
  "properties": {
    "iso:country":"US",
    "sg:address":"1025 Government St",
    "sg:city":"Ocean Springs",
    "sg:classifiers":[
        {
            "category":"Shopping",
            "subcategory":"Florist",
            "type":"Retail Goods"
        }
    ],
    "sg:phone":"+1 228 875 6109",
    "sg:postcode":"39564",
    "sg:province":"MS",
    "wof:name":"Lady Di's",
    "wof:placetype":"venue"
},
  "geometry": {"coordinates":[-88.82692,30.413674],"type":"Point"}
}