{
  "type": "Feature",
  "properties": {
    "addr:full":"938 S Green St Tupelo MS 38804",
    "addr:housenumber":"938",
    "addr:postcode":"38804",
    "addr:street":"S Green St",
    "iso:country":"US",
    "sg:address":"938 S Green St",
    "sg:city":"Tupelo",
    "sg:classifiers":[
        {
            "category":"Home & Garden",
            "subcategory":"Furniture",
            "type":"Retail Goods"
        }
    ],
    "sg:phone":"+1 662 680 6877",
    "sg:postcode":"38804",
    "sg:province":"MS",
    "sg:tags":[
        "equipment",
        "kitchen",
        "cabinet"
    ],
    "sg:website":"www.creativecountertops.com",
    "wof:name":"Creative Countertops",
    "wof:placetype":"venue"
},
  "geometry": {"coordinates":[-88.706996,34.249108],"type":"Point"}
}