{
  "type": "Feature",
  "properties": {
    "addr:full":"1984 Cliff Gookin Blvd Tupelo MS 38801",
    "addr:housenumber":"1984",
    "addr:postcode":"38801",
    "addr:street":"Cliff Gookin Blvd",
    "iso:country":"US",
    "sg:address":"1984 Cliff Gookin Blvd",
    "sg:city":"Tupelo",
    "sg:classifiers":[
        {
            "category":"Organizations",
            "subcategory":"Religious Organization",
            "type":"Services"
        }
    ],
    "sg:phone":"+1 662 620 0784",
    "sg:postcode":"38801",
    "sg:province":"MS",
    "sg:tags":[
        "church"
    ],
    "sg:website":"www.wordoflifechurch.com",
    "wof:name":"Word Of Life Church",
    "wof:placetype":"venue"
},
  "geometry": {"coordinates":[-88.764095,34.233942],"type":"Point"}
}