{
  "type": "Feature",
  "properties": {
    "iso:country":"US",
    "sg:address":"5943 Kennebrew Rd",
    "sg:city":"Jackson",
    "sg:classifiers":[
        {
            "category":"Professional",
            "subcategory":"Business Services",
            "type":"Services"
        }
    ],
    "sg:phone":"+1 601 981 3160",
    "sg:postcode":"39209",
    "sg:province":"MS",
    "wof:name":"Pat Pennington",
    "wof:placetype":"venue"
},
  "geometry": {"coordinates":[-90.300178,32.480344],"type":"Point"}
}