{
  "type": "Feature",
  "properties": {
    "iso:country":"US",
    "sg:address":"500 S College St",
    "sg:city":"Brandon",
    "sg:classifiers":[
        {
            "category":"Organizations",
            "subcategory":"Religious Organization",
            "type":"Services"
        }
    ],
    "sg:phone":"+1 601 825 8551",
    "sg:postcode":"39042",
    "sg:province":"MS",
    "sg:tags":[
        "church"
    ],
    "sg:website":"www.brandoncog.com",
    "wof:name":"Brandon Church Of God",
    "wof:placetype":"venue"
},
  "geometry": {"coordinates":[-89.989261,32.261621],"type":"Point"}
}