{
  "type": "Feature",
  "properties": {
    "addr:full":"926 I- 20 Frontage Rd N Jackson MS 39201",
    "addr:housenumber":"926",
    "addr:postcode":"39201",
    "addr:street":"I 20 Frontage Rd N",
    "iso:country":"US",
    "sg:address":"926 I- 20 Frontage Rd N",
    "sg:city":"Jackson",
    "sg:classifiers":[
        {
            "category":"Wholesale",
            "subcategory":"Auto Parts",
            "type":"Manufacturing & Wholesale Goods"
        }
    ],
    "sg:phone":"+1 601 353 2624",
    "sg:postcode":"39201",
    "sg:province":"MS",
    "sg:tags":[
        "tire"
    ],
    "sg:website":"www.heafnet.com",
    "wof:name":"American Tire Distributors",
    "wof:placetype":"venue"
},
  "geometry": {"coordinates":[-90.208845,32.281641],"type":"Point"}
}