{
  "type": "Feature",
  "properties": {
    "addr:full":"317 Oak St Greenwood MS 38930",
    "addr:housenumber":"317",
    "addr:postcode":"38930",
    "addr:street":"Oak St",
    "iso:country":"US",
    "sg:address":"317 Oak St",
    "sg:city":"Greenwood",
    "sg:classifiers":[
        {
            "category":"Personal",
            "subcategory":"Beauty Salon",
            "type":"Services"
        }
    ],
    "sg:phone":"+1 662 455 1225",
    "sg:postcode":"38930",
    "sg:province":"MS",
    "sg:tags":[
        "shop"
    ],
    "wof:name":"Twice Is Nice Styling Salon",
    "wof:placetype":"venue"
},
  "geometry": {"coordinates":[-90.171003,33.516517],"type":"Point"}
}