{
  "type": "Feature",
  "properties": {
    "addr:full":"445 Captain Gloster Dr Gloster MS 39638",
    "addr:housenumber":"445",
    "addr:postcode":"39638",
    "addr:street":"Captain Gloster Dr Gloster",
    "iso:country":"US",
    "sg:address":"445 Captain Gloster Dr",
    "sg:city":"Gloster",
    "sg:classifiers":[
        {
            "category":"Food & Beverages",
            "subcategory":"Groceries & Convenience Stores",
            "type":"Retail Goods"
        }
    ],
    "sg:phone":"+1 601 225 4507",
    "sg:postcode":"39638",
    "sg:province":"MS",
    "sg:tags":[
        "grocer"
    ],
    "wof:name":"Corbanville Grocery",
    "wof:placetype":"venue"
},
  "geometry": {"coordinates":[-91.00231599999999,31.200316],"type":"Point"}
}