{
  "type": "Feature",
  "properties": {
    "addr:full":"571 Old Hwy 45 S Corinth MS 38834",
    "addr:housenumber":"571",
    "addr:postcode":"38834",
    "addr:street":"Old Hwy 45 S Corinth",
    "iso:country":"US",
    "sg:address":"571 Old Hwy 45 S",
    "sg:city":"Corinth",
    "sg:classifiers":[
        {
            "category":"Education",
            "subcategory":"School",
            "type":"Public Place"
        }
    ],
    "sg:phone":"+1 662 286 6593",
    "sg:postcode":"38834",
    "sg:province":"MS",
    "wof:name":"Alcorn School District",
    "wof:placetype":"venue"
},
  "geometry": {"coordinates":[-88.545523,34.923639],"type":"Point"}
}