{
  "type": "Feature",
  "properties": {
    "addr:full":"428 24th Ave N Columbus MS 39705",
    "addr:housenumber":"428",
    "addr:postcode":"39705",
    "addr:street":"24Th Ave N",
    "iso:country":"US",
    "sg:address":"428 24th Ave N",
    "sg:city":"Columbus",
    "sg:classifiers":[
        {
            "category":"Insurance",
            "subcategory":"Insurance Agent",
            "type":"Services"
        }
    ],
    "sg:phone":"+1 662 327 1671",
    "sg:postcode":"39705",
    "sg:province":"MS",
    "wof:name":"State Farm Insurance",
    "wof:placetype":"venue"
},
  "geometry": {"coordinates":[-88.42909899999999,33.521669],"type":"Point"}
}