{
  "type": "Feature",
  "properties": {
    "iso:country":"US",
    "sg:address":"200 Clinton Blvd",
    "sg:city":"Clinton",
    "sg:classifiers":[
        {
            "category":"Food & Beverages",
            "subcategory":"Groceries & Convenience Stores",
            "type":"Retail Goods"
        }
    ],
    "sg:phone":"+1 601 924 3572",
    "sg:postcode":"39056",
    "sg:province":"MS",
    "sg:tags":[
        "supermarket"
    ],
    "wof:name":"Jitney Premier 70",
    "wof:placetype":"venue"
},
  "geometry": {"coordinates":[-90.31362300000001,32.334905],"type":"Point"}
}