{
  "type": "Feature",
  "properties": {
    "addr:full":"907 Rutherford Dr Jackson MS 39206",
    "addr:housenumber":"907",
    "addr:postcode":"39206",
    "addr:street":"Rutherford Dr",
    "iso:country":"US",
    "sg:address":"907 Rutherford Dr",
    "sg:city":"Jackson",
    "sg:classifiers":[
        {
            "category":"Real Estate",
            "subcategory":"Real Estate Agent",
            "type":"Services"
        }
    ],
    "sg:phone":"+1 601 981 5174",
    "sg:postcode":"39206",
    "sg:province":"MS",
    "wof:name":"Falcon Realty Inc",
    "wof:placetype":"venue"
},
  "geometry": {"coordinates":[-90.18804,32.391129],"type":"Point"}
}