{
  "type": "Feature",
  "properties": {
    "iso:country":"US",
    "sg:address":"5404 Hurley Wade Rd",
    "sg:city":"Moss Point",
    "sg:classifiers":[
        {
            "category":"Education",
            "subcategory":"School",
            "type":"Public Place"
        }
    ],
    "sg:phone":"+1 228 588 7009",
    "sg:postcode":"39562",
    "sg:province":"MS",
    "wof:name":"East Central Middle School",
    "wof:placetype":"venue"
},
  "geometry": {"coordinates":[-88.51731100000001,30.659335],"type":"Point"}
}