{
  "type": "Feature",
  "properties": {
    "iso:country":"US",
    "sg:address":"905 N Montgomery St",
    "sg:city":"Starkville",
    "sg:classifiers":[
        {
            "category":"Real Estate",
            "subcategory":"Real Estate Agent",
            "type":"Services"
        }
    ],
    "sg:phone":"+1 662 323 3461",
    "sg:postcode":"39759",
    "sg:province":"MS",
    "wof:name":"Boardtown Village",
    "wof:placetype":"venue"
},
  "geometry": {"coordinates":[-88.81035900000001,33.478193],"type":"Point"}
}