{
  "type": "Feature",
  "properties": {
    "iso:country":"US",
    "sg:address":"25 Pond Meadow Rd",
    "sg:city":"Natchez",
    "sg:classifiers":[
        {
            "category":"Restaurant",
            "type":"Food & Drink"
        }
    ],
    "sg:phone":"+1 601 445 9868",
    "sg:postcode":"39120",
    "sg:province":"MS",
    "sg:tags":[
        "eating"
    ],
    "wof:name":"McDonalds",
    "wof:placetype":"venue"
},
  "geometry": {"coordinates":[-91.33598600000001,31.499365],"type":"Point"}
}