{
  "type": "Feature",
  "properties": {
    "iso:country":"US",
    "sg:address":"109 Millsaps Dr",
    "sg:city":"Hattiesburg",
    "sg:classifiers":[
        {
            "category":"Health Services",
            "subcategory":"Doctor",
            "type":"Services"
        }
    ],
    "sg:phone":"+1 601 268 1234",
    "sg:postcode":"39402",
    "sg:province":"MS",
    "sg:tags":[
        "dentist"
    ],
    "wof:name":"R Conner Bills Pediatric",
    "wof:placetype":"venue"
},
  "geometry": {"coordinates":[-89.370431,31.323675],"type":"Point"}
}