{
  "type": "Feature",
  "properties": {
    "addr:full":"6370 Cole Rd Ridgeland MS 39157",
    "addr:housenumber":"6370",
    "addr:postcode":"39157",
    "addr:street":"Cole Rd",
    "iso:country":"US",
    "sg:address":"6370 Cole Rd",
    "sg:city":"Ridgeland",
    "sg:classifiers":[
        {
            "category":"Home & Garden",
            "subcategory":"Building Materials",
            "type":"Retail Goods"
        }
    ],
    "sg:phone":"+1 601 956 9544",
    "sg:postcode":"39157",
    "sg:province":"MS",
    "sg:tags":[
        "windows"
    ],
    "sg:website":"www.jfday.com",
    "wof:name":"Pella Window Store",
    "wof:placetype":"venue"
},
  "geometry": {"coordinates":[-90.178764,32.400665],"type":"Point"}
}