{
  "type": "Feature",
  "properties": {
    "iso:country":"US",
    "sg:address":"1224 Booker St",
    "sg:city":"Jackson",
    "sg:classifiers":[
        {
            "category":"Professional",
            "subcategory":"Business Services",
            "type":"Services"
        }
    ],
    "sg:phone":"+1 601 353 3054",
    "sg:postcode":"39204",
    "sg:province":"MS",
    "sg:tags":[
        "notary",
        "public"
    ],
    "wof:name":"Blonda Y Mack Notary Public",
    "wof:placetype":"venue"
},
  "geometry": {"coordinates":[-90.206785,32.289956],"type":"Point"}
}