{
  "type": "Feature",
  "properties": {
    "iso:country":"US",
    "sg:address":"793 N President St",
    "sg:city":"Jackson",
    "sg:classifiers":[
        {
            "category":"Organizations",
            "subcategory":"Non-profit Organization",
            "type":"Services"
        }
    ],
    "sg:phone":"+1 601 353 2741",
    "sg:postcode":"39202",
    "sg:province":"MS",
    "wof:name":"Mississippi Supervisor Mgzn",
    "wof:placetype":"venue"
},
  "geometry": {"coordinates":[-90.17994,32.308902],"type":"Point"}
}