{
  "type": "Feature",
  "properties": {
    "iso:country":"US",
    "sg:address":"210 N Main St",
    "sg:city":"Calhoun City",
    "sg:classifiers":[
        {
            "category":"Building & Trades",
            "subcategory":"Pest Control",
            "type":"Services"
        }
    ],
    "sg:phone":"+1 662 628 6837",
    "sg:postcode":"38916",
    "sg:province":"MS",
    "wof:name":"Tri-State Termite & Pest Contr",
    "wof:placetype":"venue"
},
  "geometry": {"coordinates":[-89.315197,33.869664],"type":"Point"}
}