{
  "type": "Feature",
  "properties": {
    "addr:full":"2995 Bienville Blvd Ocean Springs MS 39564",
    "addr:housenumber":"2995",
    "addr:postcode":"39564",
    "addr:street":"Bienville Blvd",
    "iso:country":"US",
    "sg:address":"2995 Bienville Blvd",
    "sg:city":"Ocean Springs",
    "sg:classifiers":[
        {
            "category":"Food & Beverages",
            "subcategory":"Groceries & Convenience Stores",
            "type":"Retail Goods"
        }
    ],
    "sg:phone":"+1 228 818 5639",
    "sg:postcode":"39564",
    "sg:province":"MS",
    "wof:name":"Fast Trac",
    "wof:placetype":"venue"
},
  "geometry": {"coordinates":[-88.786018,30.412885],"type":"Point"}
}