{
  "type": "Feature",
  "properties": {
    "iso:country":"US",
    "sg:address":"402 1st Ave NE",
    "sg:city":"Magee",
    "sg:classifiers":[
        {
            "category":"Organizations",
            "subcategory":"Religious Organization",
            "type":"Services"
        }
    ],
    "sg:phone":"+1 601 849 6231",
    "sg:postcode":"39111",
    "sg:province":"MS",
    "sg:tags":[
        "church"
    ],
    "wof:name":"New Covenant Worship Ctr",
    "wof:placetype":"venue"
},
  "geometry": {"coordinates":[-89.731336,31.877266],"type":"Point"}
}