{
  "type": "Feature",
  "properties": {
    "iso:country":"US",
    "sg:address":"124 N Main St",
    "sg:city":"Sardis",
    "sg:classifiers":[
        {
            "category":"Shopping",
            "subcategory":"Clothing, Apparel, & Fashions",
            "type":"Retail Goods"
        }
    ],
    "sg:phone":"+1 662 487 1654",
    "sg:postcode":"38666",
    "sg:province":"MS",
    "sg:tags":[
        "t"
    ],
    "wof:name":"Tshirts & More & Sweeties Tax",
    "wof:placetype":"venue"
},
  "geometry": {"coordinates":[-89.916141,34.437968],"type":"Point"}
}