{
  "type": "Feature",
  "properties": {
    "addr:full":"3615 Hospital St Pascagoula MS 39581",
    "addr:housenumber":"3615",
    "addr:postcode":"39581",
    "addr:street":"Hospital St",
    "iso:country":"US",
    "sg:address":"3615 Hospital St",
    "sg:city":"Pascagoula",
    "sg:classifiers":[
        {
            "category":"Health Services",
            "subcategory":"Doctor",
            "type":"Services"
        }
    ],
    "sg:phone":"+1 228 202 8236",
    "sg:postcode":"39581",
    "sg:province":"MS",
    "sg:tags":[
        "physician",
        "surgeon"
    ],
    "wof:name":"Suncoast Pain Management",
    "wof:placetype":"venue"
},
  "geometry": {"coordinates":[-88.53367,30.370739],"type":"Point"}
}