{
  "type": "Feature",
  "properties": {
    "iso:country":"US",
    "sg:address":"822 S West St",
    "sg:city":"Jackson",
    "sg:classifiers":[
        {
            "category":"Retail",
            "subcategory":"Auto Repair",
            "type":"Services"
        }
    ],
    "sg:phone":"+1 601 969 0044",
    "sg:postcode":"39201",
    "sg:province":"MS",
    "sg:tags":[
        "automobile",
        "customizing"
    ],
    "wof:name":"Street Toyz Customs",
    "wof:placetype":"venue"
},
  "geometry": {"coordinates":[-90.18599399999999,32.289835],"type":"Point"}
}