{
  "type": "Feature",
  "properties": {
    "addr:full":"3125 Hwy 39 N Meridian MS 39301",
    "addr:housenumber":"3125",
    "addr:postcode":"39301",
    "addr:street":"Hwy 39 N",
    "iso:country":"US",
    "sg:address":"3125 Hwy 39 N",
    "sg:city":"Meridian",
    "sg:classifiers":[
        {
            "category":"Professional",
            "subcategory":"Accounting & Tax Preparation",
            "type":"Services"
        }
    ],
    "sg:phone":"+1 601 485 8305",
    "sg:postcode":"39301",
    "sg:province":"MS",
    "wof:name":"Shirley Anigie CPA",
    "wof:placetype":"venue"
},
  "geometry": {"coordinates":[-88.682839,32.391349],"type":"Point"}
}