{
  "type": "Feature",
  "properties": {
    "addr:full":"9826 Sweethome Rd Holcomb MS 38940",
    "addr:postcode":"9826;38940",
    "addr:street":"Sweethome Rd",
    "iso:country":"US",
    "sg:address":"9826 Sweethome Rd",
    "sg:city":"Holcomb",
    "sg:classifiers":[
        {
            "category":"Organizations",
            "subcategory":"Community Association",
            "type":"Services"
        }
    ],
    "sg:phone":"+1 662 226 3814",
    "sg:postcode":"38940",
    "sg:province":"MS",
    "wof:name":"Grenada Youth League Inc",
    "wof:placetype":"venue"
},
  "geometry": {"coordinates":[-89.948994,33.701864],"type":"Point"}
}