{
  "type": "Feature",
  "properties": {
    "addr:full":"215 Franklin St Natchez MS 39120",
    "addr:housenumber":"215",
    "addr:postcode":"39120",
    "addr:street":"Franklin St",
    "iso:country":"US",
    "sg:address":"215 Franklin St",
    "sg:city":"Natchez",
    "sg:classifiers":[
        {
            "category":"Professional",
            "subcategory":"Business Services",
            "type":"Services"
        }
    ],
    "sg:phone":"+1 601 445 4155",
    "sg:postcode":"39120",
    "sg:province":"MS",
    "sg:tags":[
        "convention",
        "meeting",
        "facility"
    ],
    "wof:name":"Natchez Community Ctr",
    "wof:placetype":"venue"
},
  "geometry": {"coordinates":[-91.404375,31.562369],"type":"Point"}
}