{
  "type": "Feature",
  "properties": {
    "iso:country":"US",
    "sg:address":"9597 Old Hwy 61",
    "sg:city":"Robinsonville",
    "sg:classifiers":[
        {
            "category":"Real Estate",
            "subcategory":"Developer",
            "type":"Services"
        }
    ],
    "sg:phone":"+1 662 363 9800",
    "sg:postcode":"38664",
    "sg:province":"MS",
    "wof:name":"Robinsville Development Co",
    "wof:placetype":"venue"
},
  "geometry": {"coordinates":[-90.332061,34.796828],"type":"Point"}
}