{
  "type": "Feature",
  "properties": {
    "addr:full":"3419 Bienville Blvd Ocean Springs MS 39564",
    "addr:housenumber":"3419",
    "addr:postcode":"39564",
    "addr:street":"Bienville Blvd",
    "iso:country":"US",
    "sg:address":"3419 Bienville Blvd",
    "sg:city":"Ocean Springs",
    "sg:classifiers":[
        {
            "category":"Travel",
            "subcategory":"Hotels & Motels",
            "type":"Entertainment"
        },
        {
            "category":"Real Estate",
            "subcategory":"Real Estate Operator",
            "type":"Services"
        }
    ],
    "sg:phone":"+1 228 875 5881",
    "sg:postcode":"39564",
    "sg:province":"MS",
    "sg:tags":[
        "building",
        "operation",
        "apartment"
    ],
    "wof:name":"Twin Pines Motel",
    "wof:placetype":"venue"
},
  "geometry": {"coordinates":[-88.77722199999999,30.412125],"type":"Point"}
}