{
  "type": "Feature",
  "properties": {
    "iso:country":"US",
    "sg:address":"224 Co Rd 137",
    "sg:city":"Okolona",
    "sg:classifiers":[
        {
            "category":"Retail",
            "subcategory":"Repair Shop",
            "type":"Services"
        },
        {
            "category":"Building & Trades",
            "subcategory":"Construction",
            "type":"Services"
        }
    ],
    "sg:phone":"+1 662 447 2289",
    "sg:postcode":"38860",
    "sg:province":"MS",
    "sg:tags":[
        "welding"
    ],
    "wof:name":"Chickasaw Fabrication LLC",
    "wof:placetype":"venue"
},
  "geometry": {"coordinates":[-88.80714399999999,34.045557],"type":"Point"}
}