{
  "type": "Feature",
  "properties": {
    "addr:full":"1307 Hwy 13 S Columbia MS 39429",
    "addr:housenumber":"1307",
    "addr:postcode":"39429",
    "addr:street":"Hwy 13 S",
    "iso:country":"US",
    "sg:address":"1307 Hwy 13 S",
    "sg:city":"Columbia",
    "sg:classifiers":[
        {
            "category":"Shopping",
            "subcategory":"Department Store",
            "type":"Retail Goods"
        }
    ],
    "sg:phone":"+1 601 736 8060",
    "sg:postcode":"39429",
    "sg:province":"MS",
    "sg:tags":[
        "shop"
    ],
    "wof:name":"Dollar General",
    "wof:placetype":"venue"
},
  "geometry": {"coordinates":[-89.808052,31.210921],"type":"Point"}
}