{
  "type": "Feature",
  "properties": {
    "addr:full":"1135 W Main St Tupelo MS 38801",
    "addr:housenumber":"1135",
    "addr:postcode":"38801",
    "addr:street":"W Main St",
    "iso:country":"US",
    "sg:address":"1135 W Main St",
    "sg:city":"Tupelo",
    "sg:classifiers":[
        {
            "category":"Professional",
            "subcategory":"Accounting & Tax Preparation",
            "type":"Services"
        }
    ],
    "sg:phone":"+1 662 841 1434",
    "sg:postcode":"38801",
    "sg:province":"MS",
    "sg:tags":[
        "return"
    ],
    "wof:name":"Alford Tax Services",
    "wof:placetype":"venue"
},
  "geometry": {"coordinates":[-88.723275,34.257069],"type":"Point"}
}