{
  "type": "Feature",
  "properties": {
    "addr:full":"2888 S Liberty St Canton MS 39046",
    "addr:housenumber":"2888",
    "addr:postcode":"39046",
    "addr:street":"S Liberty St",
    "iso:country":"US",
    "sg:address":"2888 S Liberty St",
    "sg:city":"Canton",
    "sg:classifiers":[
        {
            "category":"Building & Trades",
            "subcategory":"Landscaping Services",
            "type":"Services"
        }
    ],
    "sg:phone":"+1 601 859 9974",
    "sg:postcode":"39046",
    "sg:province":"MS",
    "wof:name":"Designscape Inc",
    "wof:placetype":"venue"
},
  "geometry": {"coordinates":[-90.054328,32.571564],"type":"Point"}
}