{
  "type": "Feature",
  "properties": {
    "iso:country":"US",
    "sg:address":"127 Hillside Dr",
    "sg:city":"Hazlehurst",
    "sg:classifiers":[
        {
            "category":"Shopping",
            "subcategory":"Clothing, Apparel, & Fashions",
            "type":"Retail Goods"
        }
    ],
    "sg:phone":"+1 601 894 4252",
    "sg:postcode":"39083",
    "sg:province":"MS",
    "wof:name":"Smith Company",
    "wof:placetype":"venue"
},
  "geometry": {"coordinates":[-90.38632,31.873524],"type":"Point"}
}