{
  "type": "Feature",
  "properties": {
    "addr:full":"1413 W Main St Tupelo MS 38801",
    "addr:housenumber":"1413",
    "addr:postcode":"38801",
    "addr:street":"W Main St",
    "iso:country":"US",
    "sg:address":"1413 W Main St",
    "sg:city":"Tupelo",
    "sg:classifiers":[
        {
            "category":"Banks & Credit Unions",
            "subcategory":"Bank",
            "type":"Services"
        }
    ],
    "sg:phone":"+1 662 690 6650",
    "sg:postcode":"38801",
    "sg:province":"MS",
    "sg:tags":[
        "banker",
        "mortgage"
    ],
    "wof:name":"Wells Fargo",
    "wof:placetype":"venue"
},
  "geometry": {"coordinates":[-88.729353,34.256092],"type":"Point"}
}