{
  "type": "Feature",
  "properties": {
    "addr:full":"2756 Bienville Blvd Ocean Springs MS 39564",
    "addr:housenumber":"2756",
    "addr:postcode":"39564",
    "addr:street":"Bienville Blvd",
    "iso:country":"US",
    "sg:address":"2756 Bienville Blvd",
    "sg:city":"Ocean Springs",
    "sg:classifiers":[
        {
            "category":"Personal",
            "subcategory":"Beauty Salon",
            "type":"Services"
        }
    ],
    "sg:phone":"+1 228 872 3923",
    "sg:postcode":"39564",
    "sg:province":"MS",
    "sg:tags":[
        "shop"
    ],
    "wof:name":"Magic Touch Beauty Salon",
    "wof:placetype":"venue"
},
  "geometry": {"coordinates":[-88.795153,30.414403],"type":"Point"}
}