{
  "type": "Feature",
  "properties": {
    "addr:full":"1312 22nd Ave Hts Meridian MS 39301",
    "addr:housenumber":"1312",
    "addr:postcode":"39301",
    "addr:street":"22Nd Ave",
    "iso:country":"US",
    "sg:address":"1312 22nd Ave Hts",
    "sg:city":"Meridian",
    "sg:classifiers":[
        {
            "category":"Shopping",
            "type":"Retail Goods"
        },
        {
            "category":"Wholesale",
            "subcategory":"Electrical",
            "type":"Manufacturing & Wholesale Goods"
        }
    ],
    "sg:phone":"+1 601 482 8661",
    "sg:postcode":"39301",
    "sg:province":"MS",
    "sg:tags":[
        "alarm",
        "burglar",
        "system",
        "merchandise"
    ],
    "wof:name":"Telephone Tech Meridian",
    "wof:placetype":"venue"
},
  "geometry": {"coordinates":[-88.68872399999999,32.350673],"type":"Point"}
}