{
  "type": "Feature",
  "properties": {
    "iso:country":"US",
    "sg:address":"1059 E County Line Rd",
    "sg:city":"Jackson",
    "sg:classifiers":[
        {
            "category":"Social Services",
            "subcategory":"Child Care",
            "type":"Services"
        }
    ],
    "sg:phone":"+1 601 956 7788",
    "sg:postcode":"39211",
    "sg:province":"MS",
    "wof:name":"Kid's World Furniture",
    "wof:placetype":"venue"
},
  "geometry": {"coordinates":[-90.14282300000001,32.399648],"type":"Point"}
}