{
  "type": "Feature",
  "properties": {
    "iso:country":"US",
    "sg:address":"3127 Greenfield Rd",
    "sg:city":"Jackson",
    "sg:classifiers":[
        {
            "category":"Professional",
            "type":"Services"
        }
    ],
    "sg:phone":"+1 601 936 7745",
    "sg:postcode":"39208",
    "sg:province":"MS",
    "sg:tags":[
        "establishment"
    ],
    "wof:name":"Frierdich & Frierdich",
    "wof:placetype":"venue"
},
  "geometry": {"coordinates":[-90.037266,32.268944],"type":"Point"}
}