{
  "type": "Feature",
  "properties": {
    "iso:country":"US",
    "sg:address":"15317 Big Ridge Rd",
    "sg:city":"Biloxi",
    "sg:classifiers":[
        {
            "category":"Building & Trades",
            "subcategory":"Cleaning & Sanitation",
            "type":"Services"
        }
    ],
    "sg:phone":"+1 228 396 0238",
    "sg:postcode":"39532",
    "sg:province":"MS",
    "sg:tags":[
        "maintenance"
    ],
    "wof:name":"Murphy Housing Maintenance",
    "wof:placetype":"venue"
},
  "geometry": {"coordinates":[-88.86463000000001,30.450234],"type":"Point"}
}