{
  "type": "Feature",
  "properties": {
    "iso:country":"US",
    "sg:address":"221 Main St",
    "sg:city":"Mccomb",
    "sg:classifiers":[
        {
            "category":"Professional",
            "subcategory":"Lawyer & Legal Services",
            "type":"Services"
        }
    ],
    "sg:phone":"+1 601 684 0578",
    "sg:postcode":"39648",
    "sg:province":"MS",
    "sg:tags":[
        "attorney"
    ],
    "wof:name":"Central Southwest Ms Legal Svc",
    "wof:placetype":"venue"
},
  "geometry": {"coordinates":[-90.452427,31.243881],"type":"Point"}
}