{
  "type": "Feature",
  "properties": {
    "addr:full":"14220 US Hwy 49 Gulfport MS 39503",
    "addr:housenumber":"14220",
    "addr:postcode":"39503",
    "addr:street":"Us Hwy 49",
    "iso:country":"US",
    "sg:address":"14220 US Hwy 49",
    "sg:city":"Gulfport",
    "sg:classifiers":[
        {
            "category":"Manufacturing",
            "subcategory":"Tools & Machinery",
            "type":"Manufacturing & Wholesale Goods"
        }
    ],
    "sg:phone":"+1 228 832 0992",
    "sg:postcode":"39503",
    "sg:province":"MS",
    "sg:tags":[
        "ind",
        "general"
    ],
    "sg:website":"www.keithhuber.com",
    "wof:name":"Keith Huber Inc",
    "wof:placetype":"venue"
},
  "geometry": {"coordinates":[-89.10514999999999,30.492981],"type":"Point"}
}