{
  "type": "Feature",
  "properties": {
    "iso:country":"US",
    "sg:address":"2818 Hwy 471",
    "sg:city":"Brandon",
    "sg:classifiers":[
        {
            "category":"Autos & Motor Vehicles",
            "subcategory":"Automobile Sales",
            "type":"Retail Goods"
        }
    ],
    "sg:phone":"+1 601 829 9983",
    "sg:postcode":"39047",
    "sg:province":"MS",
    "sg:tags":[
        "car",
        "dealer"
    ],
    "wof:name":"Fannin Auto Sales Inc",
    "wof:placetype":"venue"
},
  "geometry": {"coordinates":[-89.956633,32.417417],"type":"Point"}
}