{
  "type": "Feature",
  "properties": {
    "addr:full":"861 Bilglade Dr Biloxi MS 39532",
    "addr:housenumber":"861",
    "addr:postcode":"39532",
    "addr:street":"Bilglade Dr",
    "iso:country":"US",
    "sg:address":"861 Bilglade Dr",
    "sg:city":"Biloxi",
    "sg:classifiers":[
        {
            "category":"Building & Trades",
            "subcategory":"Landscaping Services",
            "type":"Services"
        }
    ],
    "sg:phone":"+1 228 388 8257",
    "sg:postcode":"39532",
    "sg:province":"MS",
    "wof:name":"Sunset Lawn Care Maintenance",
    "wof:placetype":"venue"
},
  "geometry": {"coordinates":[-88.97178099999999,30.432822],"type":"Point"}
}