{
  "type": "Feature",
  "properties": {
    "iso:country":"US",
    "sg:address":"1217 Flagg Ave",
    "sg:city":"Tunica",
    "sg:classifiers":[
        {
            "category":"Shopping",
            "subcategory":"Bicycles & Sporting Goods",
            "type":"Retail Goods"
        }
    ],
    "sg:phone":"+1 662 363 3946",
    "sg:postcode":"38676",
    "sg:province":"MS",
    "sg:tags":[
        "bait",
        "fishing"
    ],
    "wof:name":"Larry Etta Davis",
    "wof:placetype":"venue"
},
  "geometry": {"coordinates":[-90.376628,34.703181],"type":"Point"}
}