{
  "type": "Feature",
  "properties": {
    "iso:country":"US",
    "sg:address":"31 Co Rd 827",
    "sg:city":"Blue Mountain",
    "sg:classifiers":[
        {
            "category":"Mining & Drilling",
            "type":"Manufacturing & Wholesale Goods"
        }
    ],
    "sg:phone":"+1 662 685 4066",
    "sg:postcode":"38610",
    "sg:province":"MS",
    "sg:tags":[
        "contractor"
    ],
    "wof:name":"Wommack Trucking",
    "wof:placetype":"venue"
},
  "geometry": {"coordinates":[-89.02430200000001,34.649074],"type":"Point"}
}