{
  "type": "Feature",
  "properties": {
    "iso:country":"US",
    "sg:address":"231 Frontage Rd",
    "sg:city":"Picayune",
    "sg:classifiers":[
        {
            "category":"Wholesale",
            "subcategory":"Machinery & Supplies",
            "type":"Manufacturing & Wholesale Goods"
        }
    ],
    "sg:phone":"+1 601 749 9280",
    "sg:postcode":"39466",
    "sg:province":"MS",
    "sg:tags":[
        "salon",
        "beauty"
    ],
    "wof:name":"Sally Beauty Supply",
    "wof:placetype":"venue"
},
  "geometry": {"coordinates":[-89.665345,30.510714],"type":"Point"}
}