{
  "type": "Feature",
  "properties": {
    "addr:full":"199 Copeland Rd Forest MS 39074",
    "addr:housenumber":"199",
    "addr:postcode":"39074",
    "addr:street":"Copeland Rd",
    "iso:country":"US",
    "sg:address":"199 Copeland Rd",
    "sg:city":"Forest",
    "sg:classifiers":[
        {
            "category":"Communications",
            "type":"Services"
        }
    ],
    "sg:phone":"+1 601 469 0637",
    "sg:postcode":"39074",
    "sg:province":"MS",
    "wof:name":"USA Mobility Inc",
    "wof:placetype":"venue"
},
  "geometry": {"coordinates":[-89.547831,32.340663],"type":"Point"}
}