{
  "type": "Feature",
  "properties": {
    "iso:country":"US",
    "sg:address":"827 S Main St",
    "sg:city":"Greenville",
    "sg:classifiers":[
        {
            "category":"Manufacturing",
            "subcategory":"Lumber",
            "type":"Manufacturing & Wholesale Goods"
        }
    ],
    "sg:phone":"+1 662 332 9190",
    "sg:postcode":"38701",
    "sg:province":"MS",
    "sg:tags":[
        "forester"
    ],
    "wof:name":"L C White Forest Consultant",
    "wof:placetype":"venue"
},
  "geometry": {"coordinates":[-91.053612,33.395405],"type":"Point"}
}