{
  "type": "Feature",
  "properties": {
    "iso:country":"US",
    "sg:address":"331 W College Ave",
    "sg:city":"Wiggins",
    "sg:classifiers":[
        {
            "category":"Organizations",
            "subcategory":"Religious Organization",
            "type":"Services"
        }
    ],
    "sg:phone":"+1 601 928 3904",
    "sg:postcode":"39577",
    "sg:province":"MS",
    "sg:tags":[
        "church"
    ],
    "wof:name":"Presbyterian Church",
    "wof:placetype":"venue"
},
  "geometry": {"coordinates":[-89.141176,30.859135],"type":"Point"}
}