{
  "type": "Feature",
  "properties": {
    "iso:country":"US",
    "sg:address":"20502 Hill Top Rd",
    "sg:city":"Saucier",
    "sg:classifiers":[
        {
            "category":"Building & Trades",
            "subcategory":"Construction",
            "type":"Services"
        }
    ],
    "sg:phone":"+1 228 832 8562",
    "sg:postcode":"39574",
    "sg:province":"MS",
    "sg:tags":[
        "remodeling"
    ],
    "wof:name":"Walker Construction",
    "wof:placetype":"venue"
},
  "geometry": {"coordinates":[-89.12323600000001,30.582444],"type":"Point"}
}