{
  "type": "Feature",
  "properties": {
    "iso:country":"US",
    "sg:address":"531 Central Ave",
    "sg:city":"Laurel",
    "sg:classifiers":[
        {
            "category":"Insurance",
            "subcategory":"Insurance Agent",
            "type":"Services"
        }
    ],
    "sg:phone":"+1 601 649 0266",
    "sg:postcode":"39440",
    "sg:province":"MS",
    "sg:tags":[
        "consulting",
        "financial"
    ],
    "wof:name":"Davis Financial Services",
    "wof:placetype":"venue"
},
  "geometry": {"coordinates":[-89.132734,31.69345],"type":"Point"}
}