{
  "type": "Feature",
  "properties": {
    "addr:full":"616 Fulton St Greenwood MS 38930",
    "addr:housenumber":"616",
    "addr:postcode":"38930",
    "addr:street":"Fulton St",
    "iso:country":"US",
    "sg:address":"616 Fulton St",
    "sg:city":"Greenwood",
    "sg:classifiers":[
        {
            "category":"Building & Trades",
            "subcategory":"Construction",
            "type":"Services"
        }
    ],
    "sg:phone":"+1 662 455 3049",
    "sg:postcode":"38930",
    "sg:province":"MS",
    "sg:tags":[
        "painter"
    ],
    "wof:name":"Martin's Mc Arthur Painting",
    "wof:placetype":"venue"
},
  "geometry": {"coordinates":[-90.182641,33.516075],"type":"Point"}
}