{
  "type": "Feature",
  "properties": {
    "addr:full":"119 E 2nd St Pass Christian MS 39571",
    "addr:housenumber":"119",
    "addr:postcode":"39571",
    "addr:street":"E 2Nd St",
    "iso:country":"US",
    "sg:address":"119 E 2nd St",
    "sg:city":"Pass Christian",
    "sg:classifiers":[
        {
            "category":"Home & Garden",
            "subcategory":"Garden Supply",
            "type":"Retail Goods"
        }
    ],
    "sg:phone":"+1 228 452 3137",
    "sg:postcode":"39571",
    "sg:province":"MS",
    "sg:tags":[
        "center"
    ],
    "wof:name":"Rain Tree Ctr",
    "wof:placetype":"venue"
},
  "geometry": {"coordinates":[-89.247122,30.31589],"type":"Point"}
}