{
  "type": "Feature",
  "properties": {
    "addr:full":"6791 S Siwell Rd Jackson MS 39272",
    "addr:housenumber":"6791",
    "addr:postcode":"39272",
    "addr:street":"S Siwell Rd",
    "iso:country":"US",
    "sg:address":"6791 S Siwell Rd",
    "sg:city":"Jackson",
    "sg:classifiers":[
        {
            "category":"Real Estate",
            "subcategory":"Real Estate Agent",
            "type":"Services"
        }
    ],
    "sg:phone":"+1 601 371 7500",
    "sg:postcode":"39272",
    "sg:province":"MS",
    "wof:name":"R E Max Properties",
    "wof:placetype":"venue"
},
  "geometry": {"coordinates":[-90.28921,32.202791],"type":"Point"}
}