{
  "type": "Feature",
  "properties": {
    "iso:country":"US",
    "sg:address":"4300 15th St",
    "sg:city":"Gulfport",
    "sg:classifiers":[
        {
            "category":"Shopping",
            "subcategory":"Pharmacy",
            "type":"Retail Goods"
        }
    ],
    "sg:phone":"+1 228 864 3514",
    "sg:postcode":"39501",
    "sg:province":"MS",
    "sg:tags":[
        "drug",
        "store"
    ],
    "wof:name":"Sartins",
    "wof:placetype":"venue"
},
  "geometry": {"coordinates":[-89.113647,30.369232],"type":"Point"}
}