{
  "type": "Feature",
  "properties": {
    "iso:country":"US",
    "sg:address":"627 W Porter St",
    "sg:city":"Jackson",
    "sg:classifiers":[
        {
            "category":"Education",
            "subcategory":"College",
            "type":"Public Place"
        }
    ],
    "sg:phone":"+1 601 969 9399",
    "sg:postcode":"39204",
    "sg:province":"MS",
    "sg:tags":[
        "academic",
        "school"
    ],
    "wof:name":"Emmanuel College Of Ministries",
    "wof:placetype":"venue"
},
  "geometry": {"coordinates":[-90.19788800000001,32.288337],"type":"Point"}
}