{
  "type": "Feature",
  "properties": {
    "addr:full":"210 W Front St Hattiesburg MS 39401",
    "addr:housenumber":"210",
    "addr:postcode":"39401",
    "addr:street":"W Front St",
    "iso:country":"US",
    "sg:address":"210 W Front St",
    "sg:city":"Hattiesburg",
    "sg:classifiers":[
        {
            "category":"Professional",
            "subcategory":"Research",
            "type":"Services"
        }
    ],
    "sg:phone":"+1 601 544 1477",
    "sg:postcode":"39401",
    "sg:province":"MS",
    "sg:tags":[
        "environmental",
        "ecological"
    ],
    "wof:name":"Apex Environmental Conslnt Inc",
    "wof:placetype":"venue"
},
  "geometry": {"coordinates":[-89.29093,31.325216],"type":"Point"}
}