{
  "type": "Feature",
  "properties": {
    "iso:country":"US",
    "sg:address":"12200 Dedeaux Rd",
    "sg:city":"Gulfport",
    "sg:classifiers":[
        {
            "category":"Education",
            "subcategory":"School",
            "type":"Public Place"
        }
    ],
    "sg:phone":"+1 228 832 4585",
    "sg:postcode":"39503",
    "sg:province":"MS",
    "sg:website":"www.bbcgulfport.org",
    "wof:name":"Christian Collegiate Academy",
    "wof:placetype":"venue"
},
  "geometry": {"coordinates":[-89.038025,30.449806],"type":"Point"}
}