{
  "type": "Feature",
  "properties": {
    "iso:country":"US",
    "sg:address":"1076 E County Line Rd",
    "sg:city":"Ridgeland",
    "sg:classifiers":[
        {
            "category":"Banks & Credit Unions",
            "subcategory":"Bank",
            "type":"Services"
        }
    ],
    "sg:phone":"+1 601 957 7006",
    "sg:postcode":"39157",
    "sg:province":"MS",
    "sg:tags":[
        "loan"
    ],
    "wof:name":"Title Cash",
    "wof:placetype":"venue"
},
  "geometry": {"coordinates":[-90.136527,32.399549],"type":"Point"}
}