{
  "type": "Feature",
  "properties": {
    "iso:country":"US",
    "sg:address":"123 Co Rd 1810",
    "sg:city":"Tupelo",
    "sg:classifiers":[
        {
            "category":"Shopping",
            "subcategory":"Crafts & Fabrics",
            "type":"Retail Goods"
        }
    ],
    "sg:phone":"+1 662 844 4654",
    "sg:postcode":"38866",
    "sg:province":"MS",
    "sg:tags":[
        "monogram"
    ],
    "sg:website":"www.punching.net",
    "wof:name":"Monogram Magic",
    "wof:placetype":"venue"
},
  "geometry": {"coordinates":[-88.732676,34.340885],"type":"Point"}
}