{
  "type": "Feature",
  "properties": {
    "iso:country":"US",
    "sg:address":"131 Buck Temple Rd",
    "sg:city":"Laurel",
    "sg:classifiers":[
        {
            "category":"Building & Trades",
            "subcategory":"Plumbing",
            "type":"Services"
        }
    ],
    "sg:phone":"+1 601 426 6797",
    "sg:postcode":"39443",
    "sg:province":"MS",
    "sg:tags":[
        "mechanical",
        "contractor"
    ],
    "wof:name":"S & S Air Conditioning & Htg",
    "wof:placetype":"venue"
},
  "geometry": {"coordinates":[-89.11063799999999,31.755395],"type":"Point"}
}