{
  "type": "Feature",
  "properties": {
    "iso:country":"US",
    "sg:address":"2123 Government St",
    "sg:city":"Ocean Springs",
    "sg:classifiers":[
        {
            "category":"Health Services",
            "subcategory":"Doctor",
            "type":"Services"
        }
    ],
    "sg:phone":"+1 228 872 2411",
    "sg:postcode":"39564",
    "sg:province":"MS",
    "sg:tags":[
        "medical"
    ],
    "wof:name":"Segarra J T MD Facp PA",
    "wof:placetype":"venue"
},
  "geometry": {"coordinates":[-88.812905,30.413649],"type":"Point"}
}