{
  "type": "Feature",
  "properties": {
    "addr:full":"4541 Bright Rd Hernando MS 38632",
    "addr:housenumber":"4541",
    "addr:postcode":"38632",
    "addr:street":"Bright Rd",
    "iso:country":"US",
    "sg:address":"4541 Bright Rd",
    "sg:city":"Hernando",
    "sg:classifiers":[
        {
            "category":"Organizations",
            "subcategory":"Religious Organization",
            "type":"Services"
        }
    ],
    "sg:phone":"+1 662 429 7990",
    "sg:postcode":"38632",
    "sg:province":"MS",
    "sg:tags":[
        "church"
    ],
    "wof:name":"Enon Springs Church",
    "wof:placetype":"venue"
},
  "geometry": {"coordinates":[-89.906076,34.846027],"type":"Point"}
}