{
  "type": "Feature",
  "properties": {
    "addr:full":"236 Greensview Dr Brandon MS 39047",
    "addr:housenumber":"236",
    "addr:postcode":"39047",
    "addr:street":"Greensview Dr",
    "iso:country":"US",
    "sg:address":"236 Greensview Dr",
    "sg:city":"Brandon",
    "sg:classifiers":[
        {
            "category":"Real Estate",
            "subcategory":"Real Estate Agent",
            "type":"Services"
        }
    ],
    "sg:phone":"+1 601 992 6777",
    "sg:postcode":"39047",
    "sg:province":"MS",
    "sg:tags":[
        "appraiser"
    ],
    "wof:name":"Michael Maloney Appraiser",
    "wof:placetype":"venue"
},
  "geometry": {"coordinates":[-89.992135,32.344951],"type":"Point"}
}