{
  "type": "Feature",
  "properties": {
    "iso:country":"US",
    "sg:address":"106 E McLaurin St",
    "sg:city":"Sardis",
    "sg:classifiers":[
        {
            "category":"Organizations",
            "subcategory":"Religious Organization",
            "type":"Services"
        }
    ],
    "sg:phone":"+1 662 487 1091",
    "sg:postcode":"38666",
    "sg:province":"MS",
    "sg:tags":[
        "church"
    ],
    "wof:name":"Sardis Presbyterian Church",
    "wof:placetype":"venue"
},
  "geometry": {"coordinates":[-89.91606899999999,34.433869],"type":"Point"}
}