{
  "type": "Feature",
  "properties": {
    "iso:country":"US",
    "sg:address":"5060 Cedar St",
    "sg:city":"Meridian",
    "sg:classifiers":[
        {
            "category":"Professional",
            "subcategory":"Computer Services",
            "type":"Services"
        }
    ],
    "sg:phone":"+1 601 938 4636",
    "sg:postcode":"39307",
    "sg:province":"MS",
    "sg:tags":[
        "related"
    ],
    "wof:name":"Howse Mapping and Gis",
    "wof:placetype":"venue"
},
  "geometry": {"coordinates":[-88.780646,32.412453],"type":"Point"}
}