{
  "type": "Feature",
  "properties": {
    "iso:country":"US",
    "sg:address":"216 Demetz Ave",
    "sg:city":"Pass Christian",
    "sg:classifiers":[
        {
            "category":"Retail",
            "subcategory":"Repair Shop",
            "type":"Services"
        }
    ],
    "sg:phone":"+1 228 452 1831",
    "sg:postcode":"39571",
    "sg:province":"MS",
    "wof:name":"A A Coast Rooter",
    "wof:placetype":"venue"
},
  "geometry": {"coordinates":[-89.2497,30.317261],"type":"Point"}
}