{
  "type": "Feature",
  "properties": {
    "addr:full":"316 W Commerce St Hernando MS 38632",
    "addr:housenumber":"316",
    "addr:postcode":"38632",
    "addr:street":"W Commerce St",
    "iso:country":"US",
    "sg:address":"316 W Commerce St",
    "sg:city":"Hernando",
    "sg:classifiers":[
        {
            "category":"Organizations",
            "subcategory":"Professional Association",
            "type":"Services"
        }
    ],
    "sg:phone":"+1 662 449 2883",
    "sg:postcode":"38632",
    "sg:province":"MS",
    "wof:name":"United Way Of The Mid South",
    "wof:placetype":"venue"
},
  "geometry": {"coordinates":[-89.99494300000001,34.823617],"type":"Point"}
}