{
  "type": "Feature",
  "properties": {
    "iso:country":"US",
    "sg:address":"336 Crossgates Blvd",
    "sg:city":"Brandon",
    "sg:classifiers":[
        {
            "category":"Health Services",
            "subcategory":"Hospital",
            "type":"Services"
        }
    ],
    "sg:phone":"+1 601 824 8175",
    "sg:postcode":"39042",
    "sg:province":"MS",
    "wof:name":"Rankin Medical Ctr",
    "wof:placetype":"venue"
},
  "geometry": {"coordinates":[-90.035887,32.287698],"type":"Point"}
}