{
  "type": "Feature",
  "properties": {
    "iso:country":"US",
    "sg:address":"152 Teagarden Rd",
    "sg:city":"Gulfport",
    "sg:classifiers":[
        {
            "category":"Restaurant",
            "type":"Food & Drink"
        }
    ],
    "sg:phone":"+1 228 897 7772",
    "sg:postcode":"39507",
    "sg:province":"MS",
    "sg:tags":[
        "shop",
        "coffee"
    ],
    "wof:name":"Tea Garden",
    "wof:placetype":"venue"
},
  "geometry": {"coordinates":[-89.035499,30.381357],"type":"Point"}
}