{
  "type": "Feature",
  "properties": {
    "addr:full":"2214 4th St Meridian MS 39301",
    "addr:housenumber":"2214",
    "addr:postcode":"39301",
    "addr:street":"4Th St",
    "iso:country":"US",
    "sg:address":"2214 4th St",
    "sg:city":"Meridian",
    "sg:classifiers":[
        {
            "category":"Health Services",
            "subcategory":"Hospital",
            "type":"Services"
        }
    ],
    "sg:phone":"+1 601 483 4821",
    "sg:postcode":"39301",
    "sg:province":"MS",
    "sg:tags":[
        "psychiatric"
    ],
    "wof:name":"Weems Children Youth Outreach",
    "wof:placetype":"venue"
},
  "geometry": {"coordinates":[-88.69956999999999,32.363364],"type":"Point"}
}