{
  "type": "Feature",
  "properties": {
    "iso:country":"US",
    "sg:address":"145 Old Hwy 45",
    "sg:city":"Booneville",
    "sg:classifiers":[
        {
            "category":"Home & Garden",
            "subcategory":"Carpets & Floor Coverings",
            "type":"Retail Goods"
        }
    ],
    "sg:phone":"+1 662 728 4955",
    "sg:postcode":"38829",
    "sg:province":"MS",
    "sg:tags":[
        "dealer",
        "rug"
    ],
    "wof:name":"Perry's Carpet Outlet",
    "wof:placetype":"venue"
},
  "geometry": {"coordinates":[-88.55683500000001,34.697865],"type":"Point"}
}