{
  "type": "Feature",
  "properties": {
    "addr:full":"2111 Hwy 15 N Pontotoc MS 38863",
    "addr:housenumber":"2111",
    "addr:postcode":"38863",
    "addr:street":"Hwy 15 N",
    "iso:country":"US",
    "sg:address":"2111 Hwy 15 N",
    "sg:city":"Pontotoc",
    "sg:classifiers":[
        {
            "category":"Manufacturing",
            "subcategory":"Printing",
            "type":"Manufacturing & Wholesale Goods"
        }
    ],
    "sg:phone":"+1 662 489 2741",
    "sg:postcode":"38863",
    "sg:province":"MS",
    "sg:tags":[
        "screen",
        "commercial"
    ],
    "wof:name":"Image Screen Printing Inc",
    "wof:placetype":"venue"
},
  "geometry": {"coordinates":[-89.024745,34.276882],"type":"Point"}
}