{
  "type": "Feature",
  "properties": {
    "iso:country":"US",
    "sg:address":"7464 Winchester Rd",
    "sg:city":"Memphis",
    "sg:classifiers":[
        {
            "category":"Wholesale",
            "subcategory":"Tobacco Products",
            "type":"Manufacturing & Wholesale Goods"
        }
    ],
    "sg:phone":"+1 901 754 0351",
    "sg:postcode":"38125",
    "sg:province":"MS",
    "sg:tags":[
        "cigarette",
        "cigar",
        "dealer"
    ],
    "wof:name":"Tobacco Superstore",
    "wof:placetype":"venue"
},
  "geometry": {"coordinates":[-89.81743400000001,35.050324],"type":"Point"}
}