{
  "type": "Feature",
  "properties": {
    "iso:country":"US",
    "sg:address":"414 Mulberry St",
    "sg:city":"Vaiden",
    "sg:classifiers":[
        {
            "category":"Social Services",
            "subcategory":"Child Care",
            "type":"Services"
        }
    ],
    "sg:phone":"+1 662 464 9250",
    "sg:postcode":"39176",
    "sg:province":"MS",
    "wof:name":"Happy Kids Christian Day Care",
    "wof:placetype":"venue"
},
  "geometry": {"coordinates":[-89.74362000000001,33.331346],"type":"Point"}
}