{
  "type": "Feature",
  "properties": {
    "iso:country":"US",
    "sg:address":"1218 Main St",
    "sg:city":"Columbus",
    "sg:classifiers":[
        {
            "category":"Building & Trades",
            "subcategory":"Construction",
            "type":"Services"
        }
    ],
    "sg:phone":"+1 662 328 6658",
    "sg:postcode":"39701",
    "sg:province":"MS",
    "sg:tags":[
        "contractor"
    ],
    "wof:name":"S Pierce",
    "wof:placetype":"venue"
},
  "geometry": {"coordinates":[-88.418606,33.496397],"type":"Point"}
}