{
  "type": "Feature",
  "properties": {
    "addr:full":"2431 East St Hernando MS 38632",
    "addr:housenumber":"2431",
    "addr:postcode":"38632",
    "addr:street":"East St",
    "iso:country":"US",
    "sg:address":"2431 East St",
    "sg:city":"Hernando",
    "sg:classifiers":[
        {
            "category":"Retail",
            "subcategory":"Auto Repair",
            "type":"Services"
        }
    ],
    "sg:phone":"+1 662 429 0909",
    "sg:postcode":"38632",
    "sg:province":"MS",
    "sg:tags":[
        "body",
        "automobile",
        "painting"
    ],
    "wof:name":"Jordan's Body Shop",
    "wof:placetype":"venue"
},
  "geometry": {"coordinates":[-89.99314200000001,34.824695],"type":"Point"}
}