{
  "type": "Feature",
  "properties": {
    "addr:full":"2567 US Hwy 98 Smithdale MS 39664",
    "addr:housenumber":"2567",
    "addr:postcode":"39664",
    "addr:street":"Us Hwy 98",
    "iso:country":"US",
    "sg:address":"2567 US Hwy 98",
    "sg:city":"Smithdale",
    "sg:classifiers":[
        {
            "category":"Farming",
            "subcategory":"Poultry Farm",
            "type":"Manufacturing & Wholesale Goods"
        }
    ],
    "sg:phone":"+1 601 567 2483",
    "sg:postcode":"39664",
    "sg:province":"MS",
    "sg:tags":[
        "hatchery"
    ],
    "wof:name":"Circle J Farms Inc",
    "wof:placetype":"venue"
},
  "geometry": {"coordinates":[-90.63333799999999,31.363467],"type":"Point"}
}