{
  "type": "Feature",
  "properties": {
    "addr:full":"201 Easthaven Dr Clinton MS 39056",
    "addr:housenumber":"201",
    "addr:postcode":"39056",
    "addr:street":"Easthaven Dr",
    "iso:country":"US",
    "sg:address":"201 Easthaven Dr",
    "sg:city":"Clinton",
    "sg:classifiers":[
        {
            "category":"Education",
            "subcategory":"School",
            "type":"Public Place"
        }
    ],
    "sg:phone":"+1 601 924 7261",
    "sg:postcode":"39056",
    "sg:province":"MS",
    "wof:name":"Eastside Elementary School",
    "wof:placetype":"venue"
},
  "geometry": {"coordinates":[-90.301872,32.330535],"type":"Point"}
}