{
  "type": "Feature",
  "properties": {
    "addr:full":"15315 Hwy 24 W Woodville MS 39669",
    "addr:housenumber":"15315",
    "addr:postcode":"39669",
    "addr:street":"Hwy 24 W",
    "iso:country":"US",
    "sg:address":"15315 Hwy 24 W",
    "sg:city":"Woodville",
    "sg:classifiers":[
        {
            "category":"Organizations",
            "subcategory":"Religious Organization",
            "type":"Services"
        }
    ],
    "sg:phone":"+1 601 888 7005",
    "sg:postcode":"39669",
    "sg:province":"MS",
    "sg:tags":[
        "church"
    ],
    "wof:name":"Rosehill Baptist Church",
    "wof:placetype":"venue"
},
  "geometry": {"coordinates":[-91.50767,31.147126],"type":"Point"}
}