{
  "type": "Feature",
  "properties": {
    "addr:full":"7219 Winchester Rd Memphis MS 38125",
    "addr:housenumber":"7219",
    "addr:postcode":"38125",
    "addr:street":"Winchester Rd",
    "iso:country":"US",
    "sg:address":"7219 Winchester Rd",
    "sg:city":"Memphis",
    "sg:classifiers":[
        {
            "category":"Personal",
            "type":"Services"
        }
    ],
    "sg:phone":"+1 901 624 1101",
    "sg:postcode":"38125",
    "sg:province":"MS",
    "sg:tags":[
        "medical"
    ],
    "wof:name":"Rayudu S RAO MD PHD",
    "wof:placetype":"venue"
},
  "geometry": {"coordinates":[-89.819423,35.049448],"type":"Point"}
}