{
  "type": "Feature",
  "properties": {
    "iso:country":"US",
    "sg:address":"20272 State Hwy 53",
    "sg:city":"Gulfport",
    "sg:classifiers":[
        {
            "category":"Retail",
            "subcategory":"Repair Shop",
            "type":"Services"
        }
    ],
    "sg:phone":"+1 228 832 8544",
    "sg:postcode":"39503",
    "sg:province":"MS",
    "wof:name":"Vinyl Lady",
    "wof:placetype":"venue"
},
  "geometry": {"coordinates":[-89.174266,30.516512],"type":"Point"}
}