{
  "type": "Feature",
  "properties": {
    "addr:full":"505 S Main St Picayune MS 39466",
    "addr:housenumber":"505",
    "addr:postcode":"39466",
    "addr:street":"S Main St",
    "iso:country":"US",
    "sg:address":"505 S Main St",
    "sg:city":"Picayune",
    "sg:classifiers":[
        {
            "category":"Retail",
            "subcategory":"Repair Shop",
            "type":"Services"
        }
    ],
    "sg:phone":"+1 601 798 4020",
    "sg:postcode":"39466",
    "sg:province":"MS",
    "sg:tags":[
        "lock",
        "locksmith"
    ],
    "wof:name":"Pro Lock Jock Inc",
    "wof:placetype":"venue"
},
  "geometry": {"coordinates":[-89.683615,30.518462],"type":"Point"}
}