{
  "type": "Feature",
  "properties": {
    "iso:country":"US",
    "sg:address":"1929 Spillway Rd",
    "sg:city":"Brandon",
    "sg:classifiers":[
        {
            "category":"Real Estate",
            "subcategory":"Real Estate Agent",
            "type":"Services"
        }
    ],
    "sg:phone":"+1 601 992 5094",
    "sg:postcode":"39047",
    "sg:province":"MS",
    "wof:name":"Meeler Real Estate",
    "wof:placetype":"venue"
},
  "geometry": {"coordinates":[-90.034678,32.379748],"type":"Point"}
}