{
  "type": "Feature",
  "properties": {
    "iso:country":"US",
    "sg:address":"9104 Heather Ln",
    "sg:city":"Moss Point",
    "sg:classifiers":[
        {
            "category":"Building & Trades",
            "subcategory":"Plumbing",
            "type":"Services"
        }
    ],
    "sg:phone":"+1 228 475 1916",
    "sg:postcode":"39581",
    "sg:province":"MS",
    "sg:tags":[
        "contractor"
    ],
    "wof:name":"Staton Service Co",
    "wof:placetype":"venue"
},
  "geometry": {"coordinates":[-88.420402,30.474503],"type":"Point"}
}