{
  "type": "Feature",
  "properties": {
    "iso:country":"US",
    "sg:address":"676 Bryant Ln",
    "sg:city":"Belden",
    "sg:classifiers":[
        {
            "category":"Building & Trades",
            "subcategory":"Construction",
            "type":"Services"
        }
    ],
    "sg:phone":"+1 662 690 6608",
    "sg:postcode":"38826",
    "sg:province":"MS",
    "sg:tags":[
        "house"
    ],
    "wof:name":"B&B Construction",
    "wof:placetype":"venue"
},
  "geometry": {"coordinates":[-88.87568,34.31508],"type":"Point"}
}