{
  "type": "Feature",
  "properties": {
    "iso:country":"US",
    "sg:address":"810 S West St",
    "sg:city":"Jackson",
    "sg:classifiers":[
        {
            "category":"Home & Garden",
            "subcategory":"Building Materials",
            "type":"Retail Goods"
        }
    ],
    "sg:phone":"+1 601 353 4432",
    "sg:postcode":"39201",
    "sg:province":"MS",
    "sg:tags":[
        "glass",
        "window",
        "plate"
    ],
    "wof:name":"Mid-State Glass Co",
    "wof:placetype":"venue"
},
  "geometry": {"coordinates":[-90.18604000000001,32.289663],"type":"Point"}
}