{
  "type": "Feature",
  "properties": {
    "iso:country":"US",
    "sg:address":"100 S Main St",
    "sg:city":"Swan Lake",
    "sg:classifiers":[
        {
            "category":"Farming",
            "subcategory":"Farm & Veterinary Services",
            "type":"Manufacturing & Wholesale Goods"
        }
    ],
    "sg:phone":"+1 662 375 8946",
    "sg:postcode":"38901",
    "sg:province":"MS",
    "sg:tags":[
        "aerial",
        "applicator"
    ],
    "wof:name":"Flautt Flying Svc",
    "wof:placetype":"venue"
},
  "geometry": {"coordinates":[-89.80213000000001,33.784502],"type":"Point"}
}