{
  "type": "Feature",
  "properties": {
    "iso:country":"US",
    "sg:address":"1920 E Main St",
    "sg:city":"Tupelo",
    "sg:classifiers":[
        {
            "category":"Manufacturing",
            "subcategory":"Paper Products",
            "type":"Manufacturing & Wholesale Goods"
        }
    ],
    "sg:phone":"+1 662 842 1862",
    "sg:postcode":"38804",
    "sg:province":"MS",
    "sg:tags":[
        "corrugated",
        "solid",
        "fiber",
        "box"
    ],
    "wof:name":"Gibson Corrugated",
    "wof:placetype":"venue"
},
  "geometry": {"coordinates":[-88.658767,34.257911],"type":"Point"}
}