{
  "type": "Feature",
  "properties": {
    "iso:country":"US",
    "sg:address":"125 Rouser Rd",
    "sg:city":"Ridgeland",
    "sg:classifiers":[
        {
            "category":"Autos & Motor Vehicles",
            "subcategory":"Automobile Sales",
            "type":"Retail Goods"
        }
    ],
    "sg:phone":"+1 601 503 3724",
    "sg:postcode":"39157",
    "sg:province":"MS",
    "sg:tags":[
        "new",
        "used",
        "car"
    ],
    "wof:name":"Diplomatic Luxury Auto Sales",
    "wof:placetype":"venue"
},
  "geometry": {"coordinates":[-90.23504699999999,32.407177],"type":"Point"}
}