{
  "type": "Feature",
  "properties": {
    "iso:country":"US",
    "sg:address":"30054 Lake Monroe Rd",
    "sg:city":"Aberdeen",
    "sg:classifiers":[
        {
            "category":"Organizations",
            "subcategory":"Religious Organization",
            "type":"Services"
        }
    ],
    "sg:phone":"+1 662 256 2037",
    "sg:postcode":"39730",
    "sg:province":"MS",
    "sg:tags":[
        "church"
    ],
    "wof:name":"North Mississippi Worship Ctr",
    "wof:placetype":"venue"
},
  "geometry": {"coordinates":[-88.58188699999999,33.977151],"type":"Point"}
}