{
  "type": "Feature",
  "properties": {
    "addr:full":"6121 US Hwy 49 Hattiesburg MS 39401",
    "addr:housenumber":"6121",
    "addr:postcode":"39401",
    "addr:street":"Us Hwy 49",
    "iso:country":"US",
    "sg:address":"6121 US Hwy 49",
    "sg:city":"Hattiesburg",
    "sg:classifiers":[
        {
            "category":"Restaurant",
            "type":"Food & Drink"
        }
    ],
    "sg:phone":"+1 601 264 8438",
    "sg:postcode":"39401",
    "sg:province":"MS",
    "wof:name":"Shoney's",
    "wof:placetype":"venue"
},
  "geometry": {"coordinates":[-89.341137,31.352003],"type":"Point"}
}