{
  "type": "Feature",
  "properties": {
    "iso:country":"US",
    "sg:address":"1155 Taylor Thurston Rd",
    "sg:city":"Columbus",
    "sg:classifiers":[
        {
            "category":"Organizations",
            "subcategory":"Religious Organization",
            "type":"Services"
        }
    ],
    "sg:phone":"+1 662 328 5546",
    "sg:postcode":"39701",
    "sg:province":"MS",
    "sg:tags":[
        "church"
    ],
    "wof:name":"Oak Grove Mb Church",
    "wof:placetype":"venue"
},
  "geometry": {"coordinates":[-88.545491,33.48832],"type":"Point"}
}