{
  "type": "Feature",
  "properties": {
    "iso:country":"US",
    "sg:address":"204 Kenneth St",
    "sg:city":"Greenwood",
    "sg:classifiers":[
        {
            "category":"Restaurant",
            "type":"Food & Drink"
        }
    ],
    "sg:phone":"+1 662 455 9402",
    "sg:postcode":"38930",
    "sg:province":"MS",
    "sg:tags":[
        "eating"
    ],
    "wof:name":"Q-Balls Bar-B-Que",
    "wof:placetype":"venue"
},
  "geometry": {"coordinates":[-90.175543,33.530284],"type":"Point"}
}