{
  "type": "Feature",
  "properties": {
    "iso:country":"US",
    "sg:address":"1089 Collins St",
    "sg:city":"Tunica",
    "sg:classifiers":[
        {
            "category":"Restaurant",
            "type":"Food & Drink"
        }
    ],
    "sg:phone":"+1 662 363 2011",
    "sg:postcode":"38676",
    "sg:province":"MS",
    "wof:name":"Old Sub Hot Wings & Things",
    "wof:placetype":"venue"
},
  "geometry": {"coordinates":[-90.37703999999999,34.705253],"type":"Point"}
}