{
  "type": "Feature",
  "properties": {
    "iso:country":"US",
    "sg:address":"6644 State Hwy 7",
    "sg:city":"Holcomb",
    "sg:classifiers":[
        {
            "category":"Shopping",
            "subcategory":"Bicycles & Sporting Goods",
            "type":"Retail Goods"
        }
    ],
    "sg:phone":"+1 662 227 1250",
    "sg:postcode":"38940",
    "sg:province":"MS",
    "wof:name":"Ace Hunting Supply",
    "wof:placetype":"venue"
},
  "geometry": {"coordinates":[-89.99780199999999,33.754816],"type":"Point"}
}