{
  "type": "Feature",
  "properties": {
    "iso:country":"US",
    "sg:address":"5024 Perrett Rd",
    "sg:city":"Hazlehurst",
    "sg:classifiers":[
        {
            "category":"Organizations",
            "subcategory":"Religious Organization",
            "type":"Services"
        }
    ],
    "sg:phone":"+1 601 894 8200",
    "sg:postcode":"39083",
    "sg:province":"MS",
    "sg:tags":[
        "church"
    ],
    "wof:name":"St Peter Rescue Mission Church",
    "wof:placetype":"venue"
},
  "geometry": {"coordinates":[-90.33786499999999,31.846565],"type":"Point"}
}