{
  "type": "Feature",
  "properties": {
    "iso:country":"US",
    "sg:address":"2701 N 14th Ave",
    "sg:city":"Columbus",
    "sg:classifiers":[
        {
            "category":"Personal",
            "subcategory":"Beauty Salon",
            "type":"Services"
        }
    ],
    "sg:phone":"+1 662 245 1279",
    "sg:postcode":"39701",
    "sg:province":"MS",
    "sg:tags":[
        "shop"
    ],
    "wof:name":"Frozen Paradise Beauty Salon",
    "wof:placetype":"venue"
},
  "geometry": {"coordinates":[-88.40279099999999,33.51088],"type":"Point"}
}