{
  "type": "Feature",
  "properties": {
    "iso:country":"US",
    "sg:address":"1497 Clear Creek Church Rd",
    "sg:city":"Lumberton",
    "sg:classifiers":[
        {
            "category":"Mining & Drilling",
            "type":"Manufacturing & Wholesale Goods"
        }
    ],
    "sg:phone":"+1 601 796 4921",
    "sg:postcode":"39455",
    "sg:province":"MS",
    "sg:tags":[
        "operator",
        "production",
        "gas",
        "oil"
    ],
    "wof:name":"Texas Petroleum Investment Co",
    "wof:placetype":"venue"
},
  "geometry": {"coordinates":[-89.655402,31.062921],"type":"Point"}
}