{
  "type": "Feature",
  "properties": {
    "iso:country":"US",
    "sg:address":"4619 Main St",
    "sg:city":"Moss Point",
    "sg:classifiers":[
        {
            "category":"Banks & Credit Unions",
            "subcategory":"Bank",
            "type":"Services"
        }
    ],
    "sg:phone":"+1 228 762 3311",
    "sg:postcode":"39563",
    "sg:province":"MS",
    "wof:name":"Merchants & Marine Bank",
    "wof:placetype":"venue"
},
  "geometry": {"coordinates":[-88.53894699999999,30.407382],"type":"Point"}
}