{
  "type": "Feature",
  "properties": {
    "addr:full":"241 Hwy 1 S Greenville MS 38701",
    "addr:housenumber":"241",
    "addr:postcode":"38701",
    "addr:street":"Hwy 1 S",
    "iso:country":"US",
    "sg:address":"241 Hwy 1 S",
    "sg:city":"Greenville",
    "sg:classifiers":[
        {
            "category":"Retail",
            "subcategory":"Car Wash",
            "type":"Services"
        }
    ],
    "sg:phone":"+1 662 335 3899",
    "sg:postcode":"38701",
    "sg:province":"MS",
    "sg:tags":[
        "carwash",
        "floor",
        "covering"
    ],
    "wof:name":"Selmon Sales Retail Shop",
    "wof:placetype":"venue"
},
  "geometry": {"coordinates":[-91.037987,33.404699],"type":"Point"}
}