{
  "type": "Feature",
  "properties": {
    "iso:country":"US",
    "sg:address":"680 Hwy 41 N",
    "sg:city":"Okolona",
    "sg:classifiers":[
        {
            "category":"Freight",
            "type":"Transportation"
        }
    ],
    "sg:phone":"+1 662 447 3386",
    "sg:postcode":"38860",
    "sg:province":"MS",
    "sg:tags":[
        "grain",
        "elevator"
    ],
    "wof:name":"Cargill",
    "wof:placetype":"venue"
},
  "geometry": {"coordinates":[-88.792856,34.025424],"type":"Point"}
}