{
  "type": "Feature",
  "properties": {
    "iso:country":"US",
    "sg:address":"5842 Terry Rd",
    "sg:city":"Byram",
    "sg:classifiers":[
        {
            "category":"Recreation",
            "subcategory":"Arcade",
            "type":"Entertainment"
        }
    ],
    "sg:phone":"+1 601 371 1000",
    "sg:postcode":"39272",
    "sg:province":"MS",
    "sg:tags":[
        "amusement",
        "devices"
    ],
    "wof:name":"Green Games",
    "wof:placetype":"venue"
},
  "geometry": {"coordinates":[-90.28939,32.165459],"type":"Point"}
}