{
  "type": "Feature",
  "properties": {
    "iso:country":"US",
    "sg:address":"509 Lakepointe Ln",
    "sg:city":"Madison",
    "sg:classifiers":[
        {
            "category":"Farming",
            "subcategory":"Farm",
            "type":"Manufacturing & Wholesale Goods"
        }
    ],
    "sg:phone":"+1 601 853 0372",
    "sg:postcode":"39110",
    "sg:province":"MS",
    "sg:tags":[
        "crop",
        "general"
    ],
    "wof:name":"Gold Medal Farms Inc",
    "wof:placetype":"venue"
},
  "geometry": {"coordinates":[-90.07310699999999,32.460993],"type":"Point"}
}