{
  "type": "Feature",
  "properties": {
    "iso:country":"US",
    "sg:address":"1903 Mission 66",
    "sg:city":"Vicksburg",
    "sg:classifiers":[
        {
            "category":"Travel",
            "subcategory":"Travel Agent",
            "type":"Entertainment"
        }
    ],
    "sg:phone":"+1 601 636 2121",
    "sg:postcode":"39180",
    "sg:province":"MS",
    "sg:tags":[
        "passenger",
        "charter",
        "agency",
        "tr",
        "bus"
    ],
    "wof:name":"A I-American Intl Trvl",
    "wof:placetype":"venue"
},
  "geometry": {"coordinates":[-90.8642,32.338294],"type":"Point"}
}