{
  "type": "Feature",
  "properties": {
    "iso:country":"US",
    "sg:address":"120 S Court St",
    "sg:city":"Cleveland",
    "sg:classifiers":[
        {
            "category":"Professional",
            "subcategory":"Lawyer & Legal Services",
            "type":"Services"
        }
    ],
    "sg:phone":"+1 662 846 6564",
    "sg:postcode":"38732",
    "sg:province":"MS",
    "sg:tags":[
        "attorney"
    ],
    "wof:name":"L Paul Kossman",
    "wof:placetype":"venue"
},
  "geometry": {"coordinates":[-90.722746,33.74431],"type":"Point"}
}