{
  "type": "Feature",
  "properties": {
    "addr:full":"2959 Willie Moore Rd Verona MS 38801",
    "addr:housenumber":"2959",
    "addr:postcode":"38801",
    "addr:street":"Willie Moore Rd",
    "iso:country":"US",
    "sg:address":"2959 Willie Moore Rd",
    "sg:city":"Verona",
    "sg:classifiers":[
        {
            "category":"Personal",
            "subcategory":"Beauty Salon",
            "type":"Services"
        }
    ],
    "sg:phone":"+1 662 566 1358",
    "sg:postcode":"38801",
    "sg:province":"MS",
    "wof:name":"Walking In Faith Hair Design",
    "wof:placetype":"venue"
},
  "geometry": {"coordinates":[-88.755032,34.209706],"type":"Point"}
}