{
  "type": "Feature",
  "properties": {
    "iso:country":"US",
    "sg:address":"6863 N Hamilton Cir",
    "sg:city":"Olive Branch",
    "sg:classifiers":[
        {
            "category":"Building & Trades",
            "subcategory":"Construction",
            "type":"Services"
        }
    ],
    "sg:phone":"+1 662 895 7129",
    "sg:postcode":"38654",
    "sg:province":"MS",
    "sg:tags":[
        "personal",
        "house"
    ],
    "wof:name":"Durhams Construction",
    "wof:placetype":"venue"
},
  "geometry": {"coordinates":[-89.872274,34.969276],"type":"Point"}
}