{
  "type": "Feature",
  "properties": {
    "iso:country":"US",
    "sg:address":"149 Fox Run Dr",
    "sg:city":"Raymond",
    "sg:classifiers":[
        {
            "category":"Wholesale",
            "subcategory":"Non-durable Goods",
            "type":"Manufacturing & Wholesale Goods"
        }
    ],
    "sg:phone":"+1 601 857 8529",
    "sg:postcode":"39154",
    "sg:province":"MS",
    "sg:tags":[
        "gen",
        "merchandise"
    ],
    "wof:name":"S & L Collectibles",
    "wof:placetype":"venue"
},
  "geometry": {"coordinates":[-90.389809,32.206968],"type":"Point"}
}