{
  "type": "Feature",
  "properties": {
    "iso:country":"US",
    "sg:address":"6640 Hwy 72",
    "sg:city":"Walnut",
    "sg:classifiers":[
        {
            "category":"Restaurant",
            "type":"Food & Drink"
        }
    ],
    "sg:phone":"+1 662 223 4219",
    "sg:postcode":"38683",
    "sg:province":"MS",
    "sg:tags":[
        "eating"
    ],
    "wof:name":"Burgers & Stuff",
    "wof:placetype":"venue"
},
  "geometry": {"coordinates":[-88.902717,34.952252],"type":"Point"}
}