{
  "type": "Feature",
  "properties": {
    "addr:full":"2935 Potterchitto Rd Newton MS 39345",
    "addr:housenumber":"2935",
    "addr:postcode":"39345",
    "addr:street":"Potterchitto Rd",
    "iso:country":"US",
    "sg:address":"2935 Potterchitto Rd",
    "sg:city":"Newton",
    "sg:classifiers":[
        {
            "category":"Farming",
            "subcategory":"Farm",
            "type":"Manufacturing & Wholesale Goods"
        }
    ],
    "sg:phone":"+1 601 683 2290",
    "sg:postcode":"39345",
    "sg:province":"MS",
    "wof:name":"Poplar Springs Farm",
    "wof:placetype":"venue"
},
  "geometry": {"coordinates":[-89.079583,32.305289],"type":"Point"}
}