{
  "type": "Feature",
  "properties": {
    "iso:country":"US",
    "sg:address":"1473 Memorial Dr",
    "sg:city":"Cleveland",
    "sg:classifiers":[
        {
            "category":"Professional",
            "subcategory":"Business Services",
            "type":"Services"
        }
    ],
    "sg:phone":"+1 662 846 6442",
    "sg:postcode":"38732",
    "sg:province":"MS",
    "sg:tags":[
        "consultant",
        "coach"
    ],
    "wof:name":"Baughman Agricultural Consulting Service",
    "wof:placetype":"venue"
},
  "geometry": {"coordinates":[-90.727352,33.718955],"type":"Point"}
}