{
  "type": "Feature",
  "properties": {
    "iso:country":"US",
    "sg:address":"14224 Browns Ferry Rd",
    "sg:city":"Sarah",
    "sg:classifiers":[
        {
            "category":"Wholesale",
            "subcategory":"Construction Materials",
            "type":"Manufacturing & Wholesale Goods"
        },
        {
            "category":"Manufacturing",
            "subcategory":"Lumber",
            "type":"Manufacturing & Wholesale Goods"
        }
    ],
    "sg:phone":"+1 662 382 7649",
    "sg:postcode":"38665",
    "sg:province":"MS",
    "sg:tags":[
        "timberland",
        "company",
        "logging",
        "timber"
    ],
    "wof:name":"Barber's Timber & Logging Co",
    "wof:placetype":"venue"
},
  "geometry": {"coordinates":[-90.17491800000001,34.570784],"type":"Point"}
}