{
  "type": "Feature",
  "properties": {
    "addr:full":"221 Morris St Itta Bena MS 38941",
    "addr:housenumber":"221",
    "addr:postcode":"38941",
    "addr:street":"Morris St",
    "iso:country":"US",
    "sg:address":"221 Morris St",
    "sg:city":"Itta Bena",
    "sg:classifiers":[
        {
            "category":"Restaurant",
            "type":"Food & Drink"
        }
    ],
    "sg:phone":"+1 662 254 7909",
    "sg:postcode":"38941",
    "sg:province":"MS",
    "wof:name":"Christ Temple Kitchen",
    "wof:placetype":"venue"
},
  "geometry": {"coordinates":[-90.33045199999999,33.494667],"type":"Point"}
}