{
  "type": "Feature",
  "properties": {
    "addr:full":"5962 Baxter Dr Jackson MS 39211",
    "addr:housenumber":"5962",
    "addr:postcode":"39211",
    "addr:street":"Baxter Dr",
    "iso:country":"US",
    "sg:address":"5962 Baxter Dr",
    "sg:city":"Jackson",
    "sg:classifiers":[
        {
            "category":"Home & Garden",
            "subcategory":"Mobile Homes",
            "type":"Retail Goods"
        }
    ],
    "sg:phone":"+1 601 957 1720",
    "sg:postcode":"39211",
    "sg:province":"MS",
    "wof:name":"HK&d Dream Homes LLC",
    "wof:placetype":"venue"
},
  "geometry": {"coordinates":[-90.122297,32.38951],"type":"Point"}
}