{
  "type": "Feature",
  "properties": {
    "iso:country":"US",
    "sg:address":"3900 Lakeland Dr",
    "sg:city":"Flowood",
    "sg:classifiers":[
        {
            "category":"Professional",
            "subcategory":"Management & Consulting",
            "type":"Services"
        }
    ],
    "sg:phone":"+1 601 420 0141",
    "sg:postcode":"39232",
    "sg:province":"MS",
    "sg:tags":[
        "consultant",
        "medical"
    ],
    "wof:name":"Performax",
    "wof:placetype":"venue"
},
  "geometry": {"coordinates":[-90.084644,32.339209],"type":"Point"}
}