{
  "type": "Feature",
  "properties": {
    "addr:full":"47 New St Natchez MS 39120",
    "addr:housenumber":"47",
    "addr:postcode":"39120",
    "addr:street":"New St",
    "iso:country":"US",
    "sg:address":"47 New St",
    "sg:city":"Natchez",
    "sg:classifiers":[
        {
            "category":"Travel",
            "subcategory":"Hotels & Motels",
            "type":"Entertainment"
        }
    ],
    "sg:phone":"+1 601 446 6526",
    "sg:postcode":"39120",
    "sg:province":"MS",
    "sg:tags":[
        "breakfast",
        "accommodation",
        "bed"
    ],
    "wof:name":"Riverview",
    "wof:placetype":"venue"
},
  "geometry": {"coordinates":[-91.395946,31.570233],"type":"Point"}
}