{
  "type": "Feature",
  "properties": {
    "iso:country":"US",
    "sg:address":"15 Northtown Dr",
    "sg:city":"Jackson",
    "sg:classifiers":[
        {
            "category":"Real Estate",
            "subcategory":"Real Estate Agent",
            "type":"Services"
        }
    ],
    "sg:phone":"+1 601 957 3001",
    "sg:postcode":"39211",
    "sg:province":"MS",
    "sg:tags":[
        "management"
    ],
    "wof:name":"Orkin Property Management",
    "wof:placetype":"venue"
},
  "geometry": {"coordinates":[-90.11308200000001,32.385886],"type":"Point"}
}