{
  "type": "Feature",
  "properties": {
    "addr:full":"1115 Hwy 45 N West Point MS 39773",
    "addr:housenumber":"1115",
    "addr:postcode":"39773",
    "addr:street":"Hwy 45 N",
    "iso:country":"US",
    "sg:address":"1115 Hwy 45 N",
    "sg:city":"West Point",
    "sg:classifiers":[
        {
            "category":"Restaurant",
            "type":"Food & Drink"
        }
    ],
    "sg:phone":"+1 662 494 0006",
    "sg:postcode":"39773",
    "sg:province":"MS",
    "wof:name":"Tin Lizzie Cafe",
    "wof:placetype":"venue"
},
  "geometry": {"coordinates":[-88.65906,33.622799],"type":"Point"}
}