{
  "type": "Feature",
  "properties": {
    "iso:country":"US",
    "sg:address":"55 Sgt Prentiss Dr",
    "sg:city":"Natchez",
    "sg:classifiers":[
        {
            "category":"Wholesale",
            "subcategory":"Machinery & Supplies",
            "type":"Manufacturing & Wholesale Goods"
        }
    ],
    "sg:phone":"+1 601 442 6254",
    "sg:postcode":"39120",
    "sg:province":"MS",
    "sg:tags":[
        "salon",
        "beauty"
    ],
    "wof:name":"Sally Beauty Supply",
    "wof:placetype":"venue"
},
  "geometry": {"coordinates":[-91.381755,31.533219],"type":"Point"}
}