{
  "type": "Feature",
  "properties": {
    "iso:country":"US",
    "sg:address":"2330 Hwy 82 W",
    "sg:city":"Greenwood",
    "sg:classifiers":[
        {
            "category":"Shopping",
            "subcategory":"Shoes",
            "type":"Retail Goods"
        }
    ],
    "sg:phone":"+1 662 455 7362",
    "sg:postcode":"38930",
    "sg:province":"MS",
    "wof:name":"Hibbett Sporting Goods Inc",
    "wof:placetype":"venue"
},
  "geometry": {"coordinates":[-90.23276,33.530278],"type":"Point"}
}