{
  "type": "Feature",
  "properties": {
    "iso:country":"US",
    "sg:address":"1706 Bienville Blvd",
    "sg:city":"Ocean Springs",
    "sg:classifiers":[
        {
            "category":"Restaurant",
            "type":"Food & Drink"
        }
    ],
    "sg:phone":"+1 228 875 1925",
    "sg:postcode":"39564",
    "sg:province":"MS",
    "wof:name":"Jocelyn's",
    "wof:placetype":"venue"
},
  "geometry": {"coordinates":[-88.81511399999999,30.416154],"type":"Point"}
}