{
  "type": "Feature",
  "properties": {
    "iso:country":"US",
    "sg:address":"645 Rio St",
    "sg:city":"Jackson",
    "sg:classifiers":[
        {
            "category":"Real Estate",
            "subcategory":"Real Estate Operator",
            "type":"Services"
        }
    ],
    "sg:phone":"+1 601 949 3428",
    "sg:postcode":"39202",
    "sg:province":"MS",
    "sg:tags":[
        "apartment"
    ],
    "wof:name":"Rio Apartments",
    "wof:placetype":"venue"
},
  "geometry": {"coordinates":[-90.175252,32.306492],"type":"Point"}
}