{
  "type": "Feature",
  "properties": {
    "iso:country":"US",
    "sg:address":"406 Front St",
    "sg:city":"Richton",
    "sg:classifiers":[
        {
            "category":"Health Services",
            "subcategory":"Doctor",
            "type":"Services"
        }
    ],
    "sg:phone":"+1 601 788 6381",
    "sg:postcode":"39476",
    "sg:province":"MS",
    "sg:tags":[
        "physician",
        "surgeon"
    ],
    "wof:name":"William E Moak MD",
    "wof:placetype":"venue"
},
  "geometry": {"coordinates":[-88.93556599999999,31.353371],"type":"Point"}
}