{
  "type": "Feature",
  "properties": {
    "iso:country":"US",
    "sg:address":"519 N 13th Ave",
    "sg:city":"Laurel",
    "sg:classifiers":[
        {
            "category":"Manufacturing",
            "subcategory":"Tools & Machinery",
            "type":"Manufacturing & Wholesale Goods"
        }
    ],
    "sg:phone":"+1 601 649 1317",
    "sg:postcode":"39440",
    "sg:province":"MS",
    "sg:tags":[
        "conductive",
        "wiring",
        "devices",
        "mfg"
    ],
    "wof:name":"Robinson Electric Supply Co",
    "wof:placetype":"venue"
},
  "geometry": {"coordinates":[-89.142635,31.695415],"type":"Point"}
}