{
  "type": "Feature",
  "properties": {
    "iso:country":"US",
    "sg:address":"23167 Saucier Fairley Rd",
    "sg:city":"Saucier",
    "sg:classifiers":[
        {
            "category":"Building & Trades",
            "subcategory":"Construction",
            "type":"Services"
        }
    ],
    "sg:phone":"+1 228 832 1677",
    "sg:postcode":"39574",
    "sg:province":"MS",
    "sg:tags":[
        "contractor"
    ],
    "wof:name":"Gulf Sandblasting & Painting",
    "wof:placetype":"venue"
},
  "geometry": {"coordinates":[-89.117724,30.619448],"type":"Point"}
}