{
  "type": "Feature",
  "properties": {
    "iso:country":"US",
    "sg:address":"849 Hwy 45 N",
    "sg:city":"West Point",
    "sg:classifiers":[
        {
            "category":"Freight",
            "type":"Transportation"
        }
    ],
    "sg:phone":"+1 662 494 9000",
    "sg:postcode":"39773",
    "sg:province":"MS",
    "sg:tags":[
        "commercial",
        "storage",
        "special"
    ],
    "wof:name":"S & W Mini Storage",
    "wof:placetype":"venue"
},
  "geometry": {"coordinates":[-88.659069,33.618014],"type":"Point"}
}