{
  "type": "Feature",
  "properties": {
    "addr:full":"1076 Hwy 98 E Mccomb MS 39648",
    "addr:housenumber":"1076",
    "addr:postcode":"39648",
    "addr:street":"Hwy 98 E Mccomb",
    "iso:country":"US",
    "sg:address":"1076 Hwy 98 E",
    "sg:city":"Mccomb",
    "sg:classifiers":[
        {
            "category":"Freight",
            "type":"Transportation"
        }
    ],
    "sg:phone":"+1 601 833 2699",
    "sg:postcode":"39648",
    "sg:province":"MS",
    "sg:tags":[
        "commercial",
        "storage"
    ],
    "wof:name":"Space Place Mini Storage",
    "wof:placetype":"venue"
},
  "geometry": {"coordinates":[-90.43124899999999,31.227846],"type":"Point"}
}