{
  "type": "Feature",
  "properties": {
    "iso:country":"US",
    "sg:address":"2375 Oakley Rd",
    "sg:city":"Raymond",
    "sg:classifiers":[
        {
            "category":"Government",
            "subcategory":"Jail",
            "type":"Public Place"
        }
    ],
    "sg:phone":"+1 601 857 8031",
    "sg:postcode":"39154",
    "sg:province":"MS",
    "sg:tags":[
        "correctional",
        "institution"
    ],
    "wof:name":"Mycc Unit 2 Administration",
    "wof:placetype":"venue"
},
  "geometry": {"coordinates":[-90.50366699999999,32.219842],"type":"Point"}
}