{
  "type": "Feature",
  "properties": {
    "iso:country":"US",
    "sg:address":"300 Cahal St",
    "sg:city":"Hattiesburg",
    "sg:classifiers":[
        {
            "category":"Health Services",
            "subcategory":"Nursing And Care Facility",
            "type":"Services"
        }
    ],
    "sg:phone":"+1 601 544 5300",
    "sg:postcode":"39401",
    "sg:province":"MS",
    "sg:tags":[
        "home",
        "for",
        "elderly"
    ],
    "wof:name":"Conva Rest Nursing Home",
    "wof:placetype":"venue"
},
  "geometry": {"coordinates":[-89.324646,31.344068],"type":"Point"}
}