{
  "type": "Feature",
  "properties": {
    "iso:country":"US",
    "sg:address":"1651 Hwy 1 S",
    "sg:city":"Greenville",
    "sg:classifiers":[
        {
            "category":"Utilities",
            "subcategory":"Mobile Phone",
            "type":"Services"
        }
    ],
    "sg:phone":"+1 662 335 2088",
    "sg:postcode":"38701",
    "sg:province":"MS",
    "sg:tags":[
        "telephone",
        "cellular"
    ],
    "wof:name":"Cingular Wireless",
    "wof:placetype":"venue"
},
  "geometry": {"coordinates":[-91.039625,33.376491],"type":"Point"}
}