{
  "type": "Feature",
  "properties": {
    "addr:full":"502 E Bankhead St New Albany MS 38652",
    "addr:housenumber":"502",
    "addr:postcode":"38652",
    "addr:street":"E Bankhead St",
    "iso:country":"US",
    "sg:address":"502 E Bankhead St",
    "sg:city":"New Albany",
    "sg:classifiers":[
        {
            "category":"Insurance",
            "subcategory":"Insurance Agent",
            "type":"Services"
        }
    ],
    "sg:phone":"+1 662 538 9800",
    "sg:postcode":"38652",
    "sg:province":"MS",
    "wof:name":"Shelter Insurance",
    "wof:placetype":"venue"
},
  "geometry": {"coordinates":[-89.00270999999999,34.488437],"type":"Point"}
}