{
  "type": "Feature",
  "properties": {
    "iso:country":"US",
    "sg:address":"263 Coffee St",
    "sg:city":"Pontotoc",
    "sg:classifiers":[
        {
            "category":"Manufacturing",
            "subcategory":"Furniture",
            "type":"Manufacturing & Wholesale Goods"
        }
    ],
    "sg:phone":"+1 662 489 4242",
    "sg:postcode":"38863",
    "sg:province":"MS",
    "wof:name":"Miss-Eaton Corp",
    "wof:placetype":"venue"
},
  "geometry": {"coordinates":[-89.010177,34.245992],"type":"Point"}
}