{
  "type": "Feature",
  "properties": {
    "addr:full":"4315 Industrial Dr Jackson MS 39209",
    "addr:housenumber":"4315",
    "addr:postcode":"39209",
    "addr:street":"Industrial Dr",
    "iso:country":"US",
    "sg:address":"4315 Industrial Dr",
    "sg:city":"Jackson",
    "sg:classifiers":[
        {
            "category":"Freight",
            "type":"Transportation"
        }
    ],
    "sg:phone":"+1 601 352 2529",
    "sg:postcode":"39209",
    "sg:province":"MS",
    "sg:tags":[
        "trucking"
    ],
    "wof:name":"TCW Inc",
    "wof:placetype":"venue"
},
  "geometry": {"coordinates":[-90.24024199999999,32.340274],"type":"Point"}
}