{
  "type": "Feature",
  "properties": {
    "iso:country":"US",
    "sg:address":"3645 Hwy 80 W",
    "sg:city":"Jackson",
    "sg:classifiers":[
        {
            "category":"Shopping",
            "subcategory":"Clothing, Apparel, & Fashions",
            "type":"Retail Goods"
        }
    ],
    "sg:phone":"+1 601 969 5161",
    "sg:postcode":"39209",
    "sg:province":"MS",
    "sg:tags":[
        "furnishing"
    ],
    "wof:name":"Napoly",
    "wof:placetype":"venue"
},
  "geometry": {"coordinates":[-90.249695,32.30196],"type":"Point"}
}