{
  "type": "Feature",
  "properties": {
    "addr:full":"2388 Hwy 98 E Columbia MS 39429",
    "addr:housenumber":"2388",
    "addr:postcode":"39429",
    "addr:street":"Hwy 98 E",
    "iso:country":"US",
    "sg:address":"2388 Hwy 98 E",
    "sg:city":"Columbia",
    "sg:phone":"+1 601 731 6420",
    "sg:postcode":"39429",
    "sg:province":"MS",
    "sg:tags":[
        "distributor",
        "oil"
    ],
    "wof:name":"Steel Sales & Rentals",
    "wof:placetype":"venue"
},
  "geometry": {"coordinates":[-89.70891899999999,31.268359],"type":"Point"}
}