{
  "type": "Feature",
  "properties": {
    "addr:full":"315 Lavelle Dr Gulfport MS 39503",
    "addr:housenumber":"315",
    "addr:postcode":"39503",
    "addr:street":"Lavelle Dr",
    "iso:country":"US",
    "sg:address":"315 Lavelle Dr",
    "sg:city":"Gulfport",
    "sg:classifiers":[
        {
            "category":"Wholesale",
            "subcategory":"Electrical",
            "type":"Manufacturing & Wholesale Goods"
        }
    ],
    "sg:phone":"+1 228 831 8844",
    "sg:postcode":"39503",
    "sg:province":"MS",
    "sg:tags":[
        "control",
        "security",
        "system"
    ],
    "wof:name":"Coastwide Security",
    "wof:placetype":"venue"
},
  "geometry": {"coordinates":[-89.075362,30.460699],"type":"Point"}
}