{
  "type": "Feature",
  "properties": {
    "iso:country":"US",
    "sg:address":"7340 Greenbrook Pkwy",
    "sg:city":"Southaven",
    "sg:classifiers":[
        {
            "category":"Organizations",
            "subcategory":"Religious Organization",
            "type":"Services"
        }
    ],
    "sg:phone":"+1 662 393 8991",
    "sg:postcode":"38671",
    "sg:province":"MS",
    "wof:name":"Phoenix Chapel AME Church",
    "wof:placetype":"venue"
},
  "geometry": {"coordinates":[-89.98034800000001,34.967933],"type":"Point"}
}