{
  "type": "Feature",
  "properties": {
    "addr:full":"1624 N Green St Tupelo MS 38804",
    "addr:housenumber":"1624",
    "addr:postcode":"38804",
    "addr:street":"N Green St",
    "iso:country":"US",
    "sg:address":"1624 N Green St",
    "sg:city":"Tupelo",
    "sg:classifiers":[
        {
            "category":"Real Estate",
            "subcategory":"Real Estate Agent",
            "type":"Services"
        }
    ],
    "sg:phone":"+1 662 841 0006",
    "sg:postcode":"38804",
    "sg:province":"MS",
    "sg:tags":[
        "authorities",
        "housing"
    ],
    "wof:name":"Tupelo Housing Authority",
    "wof:placetype":"venue"
},
  "geometry": {"coordinates":[-88.709661,34.281165],"type":"Point"}
}