{
  "type": "Feature",
  "properties": {
    "iso:country":"US",
    "sg:address":"216 Courtenay Ave",
    "sg:city":"Pass Christian",
    "sg:classifiers":[
        {
            "category":"Personal",
            "subcategory":"Beauty Salon",
            "type":"Services"
        }
    ],
    "sg:phone":"+1 228 452 4390",
    "sg:postcode":"39571",
    "sg:province":"MS",
    "sg:tags":[
        "shop"
    ],
    "wof:name":"Magnolia Hair Studio",
    "wof:placetype":"venue"
},
  "geometry": {"coordinates":[-89.228443,30.324856],"type":"Point"}
}