{
  "type": "Feature",
  "properties": {
    "iso:country":"US",
    "sg:address":"116 Skyland Dr",
    "sg:city":"Meridian",
    "sg:classifiers":[
        {
            "category":"Communications",
            "subcategory":"Radio Station",
            "type":"Services"
        }
    ],
    "sg:phone":"+1 601 693 0112",
    "sg:postcode":"39301",
    "sg:province":"MS",
    "sg:tags":[
        "company",
        "broadcasting"
    ],
    "wof:name":"WSLY",
    "wof:placetype":"venue"
},
  "geometry": {"coordinates":[-88.686511,32.326665],"type":"Point"}
}