{
  "type": "Feature",
  "properties": {
    "iso:country":"US",
    "sg:address":"5040 State Hwy 1",
    "sg:city":"Rosedale",
    "sg:classifiers":[
        {
            "category":"Social Services",
            "type":"Services"
        }
    ],
    "sg:phone":"+1 662 759 6637",
    "sg:postcode":"38769",
    "sg:province":"MS",
    "sg:tags":[
        "youth",
        "organization",
        "center"
    ],
    "wof:name":"Rosedale Mobile Headstart",
    "wof:placetype":"venue"
},
  "geometry": {"coordinates":[-91.027646,33.850717],"type":"Point"}
}