{
  "type": "Feature",
  "properties": {
    "iso:country":"US",
    "sg:address":"8608 Hwy 178",
    "sg:city":"Olive Branch",
    "sg:classifiers":[
        {
            "category":"Food & Beverages",
            "subcategory":"Groceries & Convenience Stores",
            "type":"Retail Goods"
        }
    ],
    "sg:phone":"+1 662 893 8184",
    "sg:postcode":"38654",
    "sg:province":"MS",
    "sg:tags":[
        "grocer"
    ],
    "wof:name":"Penny Wise",
    "wof:placetype":"venue"
},
  "geometry": {"coordinates":[-89.83474699999999,34.968582],"type":"Point"}
}