{
  "type": "Feature",
  "properties": {
    "iso:country":"US",
    "sg:address":"103 N Church St",
    "sg:city":"Charleston",
    "sg:classifiers":[
        {
            "category":"Food & Beverages",
            "subcategory":"Liquor & Beverages",
            "type":"Retail Goods"
        }
    ],
    "sg:phone":"+1 662 647 3106",
    "sg:postcode":"38921",
    "sg:province":"MS",
    "wof:name":"City Package Store",
    "wof:placetype":"venue"
},
  "geometry": {"coordinates":[-90.059399,34.007636],"type":"Point"}
}