{
  "type": "Feature",
  "properties": {
    "addr:full":"410 5th Ave Hattiesburg MS 39401",
    "addr:housenumber":"410",
    "addr:postcode":"39401",
    "addr:street":"5Th Ave",
    "iso:country":"US",
    "sg:address":"410 5th Ave",
    "sg:city":"Hattiesburg",
    "sg:classifiers":[
        {
            "category":"Building & Trades",
            "subcategory":"Cleaning & Sanitation",
            "type":"Services"
        }
    ],
    "sg:phone":"+1 601 545 3779",
    "sg:postcode":"39401",
    "sg:province":"MS",
    "sg:tags":[
        "fireplace",
        "chimney"
    ],
    "wof:name":"Harvison Chimney Sweep Co",
    "wof:placetype":"venue"
},
  "geometry": {"coordinates":[-89.301844,31.322689],"type":"Point"}
}