{
  "type": "Feature",
  "properties": {
    "iso:country":"US",
    "sg:address":"1139 Reo-Lane Rd",
    "sg:city":"Magnolia",
    "sg:classifiers":[
        {
            "category":"Social Services",
            "subcategory":"Child Care",
            "type":"Services"
        }
    ],
    "sg:phone":"+1 601 783 5803",
    "sg:postcode":"39652",
    "sg:province":"MS",
    "sg:tags":[
        "day"
    ],
    "wof:name":"Magnolia Headstart Center",
    "wof:placetype":"venue"
},
  "geometry": {"coordinates":[-90.45909899999999,31.162139],"type":"Point"}
}