{
  "type": "Feature",
  "properties": {
    "iso:country":"US",
    "sg:address":"809 Hwy 98 E",
    "sg:city":"Columbia",
    "sg:classifiers":[
        {
            "category":"Restaurant",
            "type":"Food & Drink"
        }
    ],
    "sg:phone":"+1 601 736 4221",
    "sg:postcode":"39429",
    "sg:province":"MS",
    "sg:website":"www.hardees.com",
    "wof:name":"Hardee's",
    "wof:placetype":"venue"
},
  "geometry": {"coordinates":[-89.817753,31.238912],"type":"Point"}
}