{
  "type": "Feature",
  "properties": {
    "iso:country":"US",
    "sg:address":"313 N Magnolia St",
    "sg:city":"Laurel",
    "sg:classifiers":[
        {
            "category":"Restaurant",
            "type":"Food & Drink"
        }
    ],
    "sg:phone":"+1 601 426 2100",
    "sg:postcode":"39440",
    "sg:province":"MS",
    "sg:tags":[
        "personal",
        "eating"
    ],
    "wof:name":"Cafe La Fleur",
    "wof:placetype":"venue"
},
  "geometry": {"coordinates":[-89.129745,31.692783],"type":"Point"}
}