{
  "type": "Feature",
  "properties": {
    "addr:full":"2653 Hwy 471 Brandon MS 39047",
    "addr:housenumber":"2653",
    "addr:postcode":"39047",
    "addr:street":"Hwy 471",
    "iso:country":"US",
    "sg:address":"2653 Hwy 471",
    "sg:city":"Brandon",
    "sg:classifiers":[
        {
            "category":"Utilities",
            "subcategory":"Water",
            "type":"Services"
        }
    ],
    "sg:phone":"+1 601 829 3343",
    "sg:postcode":"39047",
    "sg:province":"MS",
    "sg:tags":[
        "company",
        "sewage"
    ],
    "wof:name":"Fannin Water Assn",
    "wof:placetype":"venue"
},
  "geometry": {"coordinates":[-89.957284,32.411729],"type":"Point"}
}