{
  "type": "Feature",
  "properties": {
    "iso:country":"US",
    "sg:address":"800 Live Oak Dr",
    "sg:city":"Clinton",
    "sg:classifiers":[
        {
            "category":"Wholesale",
            "subcategory":"Machinery & Supplies",
            "type":"Manufacturing & Wholesale Goods"
        }
    ],
    "sg:phone":"+1 601 924 5028",
    "sg:postcode":"39056",
    "sg:province":"MS",
    "sg:tags":[
        "spraying",
        "equipment"
    ],
    "wof:name":"Bob Lowe Distributors",
    "wof:placetype":"venue"
},
  "geometry": {"coordinates":[-90.31660100000001,32.349643],"type":"Point"}
}