{
  "type": "Feature",
  "properties": {
    "iso:country":"US",
    "sg:address":"422 W Canal St",
    "sg:city":"Picayune",
    "sg:classifiers":[
        {
            "category":"Shopping",
            "subcategory":"Bicycles & Sporting Goods",
            "type":"Retail Goods"
        }
    ],
    "sg:phone":"+1 601 749 4823",
    "sg:postcode":"39466",
    "sg:province":"MS",
    "wof:name":"Instant Replay Sports Picayune",
    "wof:placetype":"venue"
},
  "geometry": {"coordinates":[-89.684533,30.526945],"type":"Point"}
}