{
  "type": "Feature",
  "properties": {
    "addr:full":"10004 Saracennia Rd Moss Point MS 39562",
    "addr:housenumber":"10004",
    "addr:postcode":"39562",
    "addr:street":"Saracennia Rd",
    "iso:country":"US",
    "sg:address":"10004 Saracennia Rd",
    "sg:city":"Moss Point",
    "sg:classifiers":[
        {
            "category":"Food & Beverages",
            "subcategory":"Fruits & Vegetables",
            "type":"Retail Goods"
        }
    ],
    "sg:phone":"+1 228 475 8553",
    "sg:postcode":"39562",
    "sg:province":"MS",
    "wof:name":"B & D Produce",
    "wof:placetype":"venue"
},
  "geometry": {"coordinates":[-88.50312099999999,30.487444],"type":"Point"}
}