{
  "type": "Feature",
  "properties": {
    "addr:full":"3113 Crestwood Dr Laurel MS 39440",
    "addr:housenumber":"3113",
    "addr:postcode":"39440",
    "addr:street":"Crestwood Dr",
    "iso:country":"US",
    "sg:address":"3113 Crestwood Dr",
    "sg:city":"Laurel",
    "sg:classifiers":[
        {
            "category":"Wholesale",
            "subcategory":"Machinery & Supplies",
            "type":"Manufacturing & Wholesale Goods"
        }
    ],
    "sg:phone":"+1 601 426 3204",
    "sg:postcode":"39440",
    "sg:province":"MS",
    "sg:tags":[
        "equipment",
        "industrial"
    ],
    "wof:name":"Mississippi Engine Company",
    "wof:placetype":"venue"
},
  "geometry": {"coordinates":[-89.143074,31.729109],"type":"Point"}
}