{
  "type": "Feature",
  "properties": {
    "iso:country":"US",
    "sg:address":"96 State Hwy 537",
    "sg:city":"Laurel",
    "sg:classifiers":[
        {
            "category":"Food & Beverages",
            "subcategory":"Specialty",
            "type":"Retail Goods"
        }
    ],
    "sg:phone":"+1 601 425 2966",
    "sg:postcode":"39443",
    "sg:province":"MS",
    "wof:name":"Wholesale Distributors",
    "wof:placetype":"venue"
},
  "geometry": {"coordinates":[-89.186902,31.808632],"type":"Point"}
}