{
  "type": "Feature",
  "properties": {
    "iso:country":"US",
    "sg:address":"3932 Flowood Dr",
    "sg:city":"Jackson",
    "sg:classifiers":[
        {
            "category":"Social Services",
            "subcategory":"Child Care",
            "type":"Services"
        }
    ],
    "sg:phone":"+1 601 932 7711",
    "sg:postcode":"39232",
    "sg:province":"MS",
    "sg:tags":[
        "day"
    ],
    "wof:name":"Kids Stop Preschool Inc",
    "wof:placetype":"venue"
},
  "geometry": {"coordinates":[-90.06057699999999,32.34661],"type":"Point"}
}