{
  "type": "Feature",
  "properties": {
    "addr:full":"5582 Blythe Rd Lake Cormorant MS 38641",
    "addr:housenumber":"5582",
    "addr:postcode":"38641",
    "addr:street":"Blythe Rd",
    "iso:country":"US",
    "sg:address":"5582 Blythe Rd",
    "sg:city":"Lake Cormorant",
    "sg:classifiers":[
        {
            "category":"Recreation",
            "type":"Entertainment"
        }
    ],
    "sg:phone":"+1 662 781 1112",
    "sg:postcode":"38641",
    "sg:province":"MS",
    "sg:tags":[
        "karate",
        "judo",
        "instr"
    ],
    "wof:name":"Mid-South Institute Of Self",
    "wof:placetype":"venue"
},
  "geometry": {"coordinates":[-90.20207499999999,34.942019],"type":"Point"}
}