{
  "type": "Feature",
  "properties": {
    "iso:country":"US",
    "sg:address":"225 North St",
    "sg:city":"Cleveland",
    "sg:classifiers":[
        {
            "category":"Food & Beverages",
            "subcategory":"Fruits & Vegetables",
            "type":"Retail Goods"
        }
    ],
    "sg:phone":"+1 662 846 0291",
    "sg:postcode":"38732",
    "sg:province":"MS",
    "sg:tags":[
        "produce"
    ],
    "wof:name":"Cleveland Fruit Market",
    "wof:placetype":"venue"
},
  "geometry": {"coordinates":[-90.717721,33.744496],"type":"Point"}
}