{
  "type": "Feature",
  "properties": {
    "iso:country":"US",
    "sg:address":"834 Hwy 12 W",
    "sg:city":"Starkville",
    "sg:classifiers":[
        {
            "category":"Professional",
            "subcategory":"Advertising",
            "type":"Services"
        }
    ],
    "sg:phone":"+1 662 338 5077",
    "sg:postcode":"39759",
    "sg:province":"MS",
    "sg:tags":[
        "mailing",
        "shipping"
    ],
    "wof:name":"UPS Store",
    "wof:placetype":"venue"
},
  "geometry": {"coordinates":[-88.83953,33.448597],"type":"Point"}
}