{
  "type": "Feature",
  "properties": {
    "addr:full":"140 E Jackson St Ridgeland MS 39157",
    "addr:housenumber":"140",
    "addr:postcode":"39157",
    "addr:street":"E Jackson St",
    "iso:country":"US",
    "sg:address":"140 E Jackson St",
    "sg:city":"Ridgeland",
    "sg:classifiers":[
        {
            "category":"Professional",
            "subcategory":"Management & Consulting",
            "type":"Services"
        }
    ],
    "sg:phone":"+1 601 856 8783",
    "sg:postcode":"39157",
    "sg:province":"MS",
    "sg:tags":[
        "retail",
        "direct",
        "sales"
    ],
    "wof:name":"Classic Designs",
    "wof:placetype":"venue"
},
  "geometry": {"coordinates":[-90.12809300000001,32.428704],"type":"Point"}
}