{
  "type": "Feature",
  "properties": {
    "addr:full":"1107 Westhaven Blvd Jackson MS 39209",
    "addr:housenumber":"1107",
    "addr:postcode":"39209",
    "addr:street":"Westhaven Blvd",
    "iso:country":"US",
    "sg:address":"1107 Westhaven Blvd",
    "sg:city":"Jackson",
    "sg:classifiers":[
        {
            "category":"Organizations",
            "subcategory":"Religious Organization",
            "type":"Services"
        }
    ],
    "sg:phone":"+1 601 922 7973",
    "sg:postcode":"39209",
    "sg:province":"MS",
    "sg:tags":[
        "church"
    ],
    "wof:name":"Faith Way Baptist Church",
    "wof:placetype":"venue"
},
  "geometry": {"coordinates":[-90.27005800000001,32.314158],"type":"Point"}
}