{
  "type": "Feature",
  "properties": {
    "iso:country":"US",
    "sg:address":"427 Liberty Rd",
    "sg:city":"Natchez",
    "sg:classifiers":[
        {
            "category":"Retail",
            "subcategory":"Laundry & Dry Cleaning",
            "type":"Services"
        }
    ],
    "sg:phone":"+1 601 445 0266",
    "sg:postcode":"39120",
    "sg:province":"MS",
    "wof:name":"HP Holmes Steam Clean",
    "wof:placetype":"venue"
},
  "geometry": {"coordinates":[-91.365075,31.543482],"type":"Point"}
}