{
  "type": "Feature",
  "properties": {
    "iso:country":"US",
    "sg:address":"160 W Center St",
    "sg:city":"Canton",
    "sg:classifiers":[
        {
            "category":"Organizations",
            "subcategory":"Religious Organization",
            "type":"Services"
        }
    ],
    "sg:phone":"+1 601 859 5708",
    "sg:postcode":"39046",
    "sg:province":"MS",
    "wof:name":"In His Steps Ministries",
    "wof:placetype":"venue"
},
  "geometry": {"coordinates":[-90.03560899999999,32.613928],"type":"Point"}
}