{
  "type": "Feature",
  "properties": {
    "iso:country":"US",
    "sg:address":"900 S Roach St",
    "sg:city":"Jackson",
    "sg:classifiers":[
        {
            "category":"Autos & Motor Vehicles",
            "subcategory":"Automobile Sales",
            "type":"Retail Goods"
        }
    ],
    "sg:phone":"+1 601 969 7245",
    "sg:postcode":"39201",
    "sg:province":"MS",
    "sg:tags":[
        "used"
    ],
    "wof:name":"Bittersweet Auto Sales",
    "wof:placetype":"venue"
},
  "geometry": {"coordinates":[-90.18971500000001,32.290145],"type":"Point"}
}