{
  "type": "Feature",
  "properties": {
    "iso:country":"US",
    "sg:address":"302 Porter St",
    "sg:city":"Ocean Springs",
    "sg:classifiers":[
        {
            "category":"Health Services",
            "subcategory":"Doctor",
            "type":"Services"
        }
    ],
    "sg:phone":"+1 228 875 4604",
    "sg:postcode":"39564",
    "sg:province":"MS",
    "sg:tags":[
        "medical"
    ],
    "wof:name":"Gene Janus DDS",
    "wof:placetype":"venue"
},
  "geometry": {"coordinates":[-88.83796599999999,30.412974],"type":"Point"}
}