{
  "type": "Feature",
  "properties": {
    "iso:country":"US",
    "sg:address":"145 Rust Ave",
    "sg:city":"Holly Springs",
    "sg:classifiers":[
        {
            "category":"Autos & Motor Vehicles",
            "subcategory":"Auto Supplies",
            "type":"Retail Goods"
        }
    ],
    "sg:phone":"+1 662 252 1070",
    "sg:postcode":"38635",
    "sg:province":"MS",
    "wof:name":"A J & Associates",
    "wof:placetype":"venue"
},
  "geometry": {"coordinates":[-89.447377,34.774157],"type":"Point"}
}