{
  "type": "Feature",
  "properties": {
    "iso:country":"US",
    "sg:address":"906 Co Rd 416",
    "sg:city":"Woodland",
    "sg:classifiers":[
        {
            "category":"Organizations",
            "subcategory":"Religious Organization",
            "type":"Services"
        }
    ],
    "sg:phone":"+1 662 456 4714",
    "sg:postcode":"39776",
    "sg:province":"MS",
    "sg:tags":[
        "church"
    ],
    "wof:name":"Pleasant Ridge Baptist Church",
    "wof:placetype":"venue"
},
  "geometry": {"coordinates":[-89.056817,33.82457],"type":"Point"}
}