{
  "type": "Feature",
  "properties": {
    "iso:country":"US",
    "sg:address":"3845 Meadow Ln",
    "sg:city":"Jackson",
    "sg:classifiers":[
        {
            "category":"Insurance",
            "subcategory":"Hazard Insurance",
            "type":"Services"
        }
    ],
    "sg:phone":"+1 601 825 1077",
    "sg:postcode":"39212",
    "sg:province":"MS",
    "sg:tags":[
        "bond"
    ],
    "wof:name":"Liberty Bail Bonds & Legal Svc",
    "wof:placetype":"venue"
},
  "geometry": {"coordinates":[-90.235489,32.243617],"type":"Point"}
}