{
  "type": "Feature",
  "properties": {
    "iso:country":"US",
    "sg:address":"3820 W Railroad St",
    "sg:city":"Gulfport",
    "sg:classifiers":[
        {
            "category":"Retail",
            "subcategory":"Auto Repair",
            "type":"Services"
        }
    ],
    "sg:phone":"+1 228 864 3715",
    "sg:postcode":"39501",
    "sg:province":"MS",
    "sg:tags":[
        "repairing",
        "automobile"
    ],
    "wof:name":"Ronnie's Automotive & Towing",
    "wof:placetype":"venue"
},
  "geometry": {"coordinates":[-89.108056,30.365284],"type":"Point"}
}