{
  "type": "Feature",
  "properties": {
    "iso:country":"US",
    "sg:address":"2623 Pass Rd",
    "sg:city":"Biloxi",
    "sg:classifiers":[
        {
            "category":"Real Estate",
            "subcategory":"Real Estate Agent",
            "type":"Services"
        }
    ],
    "sg:phone":"+1 228 385 9981",
    "sg:postcode":"39531",
    "sg:province":"MS",
    "sg:tags":[
        "finding",
        "apartment",
        "rental"
    ],
    "sg:website":"www.apartmentguide.com",
    "wof:name":"Apartment Guide",
    "wof:placetype":"venue"
},
  "geometry": {"coordinates":[-88.989876,30.400546],"type":"Point"}
}