{
  "type": "Feature",
  "properties": {
    "addr:full":"849 E Northside Dr Clinton MS 39056",
    "addr:housenumber":"849",
    "addr:postcode":"39056",
    "addr:street":"E Northside Dr",
    "iso:country":"US",
    "sg:address":"849 E Northside Dr",
    "sg:city":"Clinton",
    "sg:classifiers":[
        {
            "category":"Restaurant",
            "type":"Food & Drink"
        }
    ],
    "sg:menulink":"http://www.allmenus.com/ms/raymond/199548-sonic/menu/",
    "sg:phone":"+1 601 924 7136",
    "sg:postcode":"39056",
    "sg:province":"MS",
    "sg:tags":[
        "burger",
        "american"
    ],
    "wof:name":"Sonic",
    "wof:placetype":"venue"
},
  "geometry": {"coordinates":[-90.314308,32.347737],"type":"Point"}
}