{
  "type": "Feature",
  "properties": {
    "iso:country":"US",
    "sg:address":"1405 Hwy 25 S",
    "sg:city":"Amory",
    "sg:classifiers":[
        {
            "category":"Personal",
            "subcategory":"Beauty Salon",
            "type":"Services"
        }
    ],
    "sg:phone":"+1 662 256 3251",
    "sg:postcode":"38821",
    "sg:province":"MS",
    "wof:name":"Cool Cuts",
    "wof:placetype":"venue"
},
  "geometry": {"coordinates":[-88.489621,33.96982],"type":"Point"}
}