{
  "type": "Feature",
  "properties": {
    "iso:country":"US",
    "sg:address":"1100 Grove St",
    "sg:city":"Vicksburg",
    "sg:classifiers":[
        {
            "category":"Government",
            "subcategory":"Jail",
            "type":"Public Place"
        }
    ],
    "sg:phone":"+1 601 630 8003",
    "sg:postcode":"39183",
    "sg:province":"MS",
    "sg:tags":[
        "correctional",
        "institution"
    ],
    "wof:name":"Detention Center",
    "wof:placetype":"venue"
},
  "geometry": {"coordinates":[-90.87705,32.351479],"type":"Point"}
}