{
  "type": "Feature",
  "properties": {
    "addr:full":"11351 Fenton Dr Biloxi MS 39532",
    "addr:housenumber":"11351",
    "addr:postcode":"39532",
    "addr:street":"Fenton Dr",
    "iso:country":"US",
    "sg:address":"11351 Fenton Dr",
    "sg:city":"Biloxi",
    "sg:classifiers":[
        {
            "category":"Freight",
            "type":"Transportation"
        }
    ],
    "sg:phone":"+1 228 497 9980",
    "sg:postcode":"39532",
    "sg:province":"MS",
    "sg:tags":[
        "delivery"
    ],
    "wof:name":"Tele-Pcs Delivery Company",
    "wof:placetype":"venue"
},
  "geometry": {"coordinates":[-88.93900499999999,30.453098],"type":"Point"}
}