{
  "type": "Feature",
  "properties": {
    "addr:full":"148 US Hwy 84 Brookhaven MS 39601",
    "addr:housenumber":"148",
    "addr:postcode":"39601",
    "addr:street":"Us Hwy 84",
    "iso:country":"US",
    "sg:address":"148 US Hwy 84",
    "sg:city":"Brookhaven",
    "sg:classifiers":[
        {
            "category":"Autos & Motor Vehicles",
            "subcategory":"Fuel & Gas Station",
            "type":"Retail Goods"
        }
    ],
    "sg:phone":"+1 601 833 5300",
    "sg:postcode":"39601",
    "sg:province":"MS",
    "sg:tags":[
        "store"
    ],
    "wof:name":"Chevron",
    "wof:placetype":"venue"
},
  "geometry": {"coordinates":[-90.467415,31.547161],"type":"Point"}
}