{
  "type": "Feature",
  "properties": {
    "addr:full":"1622 Pass Rd Biloxi MS 39531",
    "addr:housenumber":"1622",
    "addr:postcode":"39531",
    "addr:street":"Pass Rd",
    "iso:country":"US",
    "sg:address":"1622 Pass Rd",
    "sg:city":"Biloxi",
    "sg:classifiers":[
        {
            "category":"Personal",
            "type":"Services"
        }
    ],
    "sg:phone":"+1 228 435 7436",
    "sg:postcode":"39531",
    "sg:province":"MS",
    "wof:name":"California Tatoo",
    "wof:placetype":"venue"
},
  "geometry": {"coordinates":[-88.93418,30.402654],"type":"Point"}
}