{
  "type": "Feature",
  "properties": {
    "iso:country":"US",
    "sg:address":"128 W Cherokee St",
    "sg:city":"Brookhaven",
    "sg:classifiers":[
        {
            "category":"Personal",
            "subcategory":"Beauty Salon",
            "type":"Services"
        }
    ],
    "sg:phone":"+1 601 835 0204",
    "sg:postcode":"39601",
    "sg:province":"MS",
    "wof:name":"Unity One Hair Salon",
    "wof:placetype":"venue"
},
  "geometry": {"coordinates":[-90.443133,31.578468],"type":"Point"}
}