{
  "type": "Feature",
  "properties": {
    "addr:full":"2811 Hwy 178 Tupelo MS 38804",
    "addr:housenumber":"2811",
    "addr:postcode":"38804",
    "addr:street":"Hwy 178",
    "iso:country":"US",
    "sg:address":"2811 Hwy 178",
    "sg:city":"Tupelo",
    "sg:classifiers":[
        {
            "category":"Home & Garden",
            "subcategory":"Furniture",
            "type":"Retail Goods"
        }
    ],
    "sg:phone":"+1 662 842 4188",
    "sg:postcode":"38804",
    "sg:province":"MS",
    "sg:tags":[
        "picture",
        "lamp",
        "mirror"
    ],
    "wof:name":"Towery Furniture Company Inc",
    "wof:placetype":"venue"
},
  "geometry": {"coordinates":[-88.626317,34.265664],"type":"Point"}
}