{
  "type": "Feature",
  "properties": {
    "iso:country":"US",
    "sg:address":"2461 5th St N",
    "sg:city":"Columbus",
    "sg:classifiers":[
        {
            "category":"Health Services",
            "subcategory":"Medical Lab",
            "type":"Services"
        }
    ],
    "sg:phone":"+1 662 329 1317",
    "sg:postcode":"39705",
    "sg:province":"MS",
    "sg:tags":[
        "laboratory"
    ],
    "wof:name":"Medical Pathology Lab",
    "wof:placetype":"venue"
},
  "geometry": {"coordinates":[-88.42907700000001,33.523076],"type":"Point"}
}