{
  "type": "Feature",
  "properties": {
    "addr:full":"14 Dunn Rd Poplarville MS 39470",
    "addr:housenumber":"14",
    "addr:postcode":"39470",
    "addr:street":"Dunn Rd",
    "iso:country":"US",
    "sg:address":"14 Dunn Rd",
    "sg:city":"Poplarville",
    "sg:classifiers":[
        {
            "category":"Bars & Pubs",
            "type":"Food & Drink"
        }
    ],
    "sg:phone":"+1 601 403 8400",
    "sg:postcode":"39470",
    "sg:province":"MS",
    "sg:tags":[
        "drinking"
    ],
    "wof:name":"Barstool Memories",
    "wof:placetype":"venue"
},
  "geometry": {"coordinates":[-89.56755800000001,30.883112],"type":"Point"}
}