{
  "type": "Feature",
  "properties": {
    "iso:country":"US",
    "sg:address":"109 W Pine Ave",
    "sg:city":"Wiggins",
    "sg:classifiers":[
        {
            "category":"Banks & Credit Unions",
            "subcategory":"Bank",
            "type":"Services"
        }
    ],
    "sg:phone":"+1 601 928 5233",
    "sg:postcode":"39577",
    "sg:province":"MS",
    "wof:name":"Bank Of Wiggins",
    "wof:placetype":"venue"
},
  "geometry": {"coordinates":[-89.13945099999999,30.857875],"type":"Point"}
}