{
  "type": "Feature",
  "properties": {
    "iso:country":"US",
    "sg:address":"118 Service Dr",
    "sg:city":"Brandon",
    "sg:classifiers":[
        {
            "category":"Shopping",
            "subcategory":"Used Merchandise",
            "type":"Retail Goods"
        }
    ],
    "sg:phone":"+1 601 824 1223",
    "sg:postcode":"39042",
    "sg:province":"MS",
    "sg:tags":[
        "book",
        "rare",
        "dealer"
    ],
    "wof:name":"Book Rack Brandon",
    "wof:placetype":"venue"
},
  "geometry": {"coordinates":[-90.028745,32.283648],"type":"Point"}
}