{
  "type": "Feature",
  "properties": {
    "addr:full":"101 S Lafayette St Starkville MS 39759",
    "addr:housenumber":"101",
    "addr:postcode":"39759",
    "addr:street":"S Lafayette St",
    "iso:country":"US",
    "sg:address":"101 S Lafayette St",
    "sg:city":"Starkville",
    "sg:classifiers":[
        {
            "category":"Manufacturing",
            "subcategory":"Printing",
            "type":"Manufacturing & Wholesale Goods"
        }
    ],
    "sg:phone":"+1 662 323 2424",
    "sg:postcode":"39759",
    "sg:province":"MS",
    "sg:tags":[
        "newspaper"
    ],
    "wof:name":"Commercial Dispatch",
    "wof:placetype":"venue"
},
  "geometry": {"coordinates":[-88.815198,33.463827],"type":"Point"}
}