{
  "type": "Feature",
  "properties": {
    "iso:country":"US",
    "sg:address":"7300 S Siwell Rd",
    "sg:city":"Jackson",
    "sg:classifiers":[
        {
            "category":"Health Services",
            "subcategory":"Doctor",
            "type":"Services"
        }
    ],
    "sg:phone":"+1 601 373 1234",
    "sg:postcode":"39272",
    "sg:province":"MS",
    "sg:tags":[
        "medical"
    ],
    "wof:name":"Mea Medical Clinic",
    "wof:placetype":"venue"
},
  "geometry": {"coordinates":[-90.265348,32.189217],"type":"Point"}
}