{
  "type": "Feature",
  "properties": {
    "iso:country":"US",
    "sg:address":"5446 Windsor Cir",
    "sg:city":"Meridian",
    "sg:classifiers":[
        {
            "category":"Building & Trades",
            "subcategory":"Construction",
            "type":"Services"
        }
    ],
    "sg:phone":"+1 601 681 8334",
    "sg:postcode":"39305",
    "sg:province":"MS",
    "sg:tags":[
        "hanging",
        "contractor"
    ],
    "wof:name":"Hover Bill Pntg & Wallcovering",
    "wof:placetype":"venue"
},
  "geometry": {"coordinates":[-88.734206,32.446243],"type":"Point"}
}