{
  "type": "Feature",
  "properties": {
    "addr:full":"107 Fairland Pl Clarksdale MS 38614",
    "addr:housenumber":"107",
    "addr:postcode":"38614",
    "addr:street":"Fairland Pl",
    "iso:country":"US",
    "sg:address":"107 Fairland Pl",
    "sg:city":"Clarksdale",
    "sg:classifiers":[
        {
            "category":"Autos & Motor Vehicles",
            "subcategory":"Automobile Sales",
            "type":"Retail Goods"
        }
    ],
    "sg:phone":"+1 662 624 6633",
    "sg:postcode":"38614",
    "sg:province":"MS",
    "sg:tags":[
        "dealers-used",
        "car",
        "used",
        "cars-wholesale"
    ],
    "wof:name":"A-1",
    "wof:placetype":"venue"
},
  "geometry": {"coordinates":[-90.567346,34.204315],"type":"Point"}
}