{
  "type": "Feature",
  "properties": {
    "iso:country":"US",
    "sg:address":"7534 Windsong Dr",
    "sg:city":"Memphis",
    "sg:classifiers":[
        {
            "category":"Professional",
            "subcategory":"Business Services",
            "type":"Services"
        }
    ],
    "sg:phone":"+1 901 758 1215",
    "sg:postcode":"38125",
    "sg:province":"MS",
    "wof:name":"Anns Custom Sewing",
    "wof:placetype":"venue"
},
  "geometry": {"coordinates":[-89.811469,35.025075],"type":"Point"}
}