{
  "type": "Feature",
  "properties": {
    "iso:country":"US",
    "sg:address":"3276 Goodman Rd E",
    "sg:city":"Southaven",
    "sg:classifiers":[
        {
            "category":"Real Estate",
            "subcategory":"Real Estate Agent",
            "type":"Services"
        }
    ],
    "sg:phone":"+1 662 349 0039",
    "sg:postcode":"38672",
    "sg:province":"MS",
    "sg:website":"www.1stchoicems.com",
    "wof:name":"First Choice Realty",
    "wof:placetype":"venue"
},
  "geometry": {"coordinates":[-89.931493,34.962483],"type":"Point"}
}