{
  "type": "Feature",
  "properties": {
    "iso:country":"US",
    "sg:address":"115 N Broadway St",
    "sg:city":"Tupelo",
    "sg:classifiers":[
        {
            "category":"Professional",
            "subcategory":"Lawyer & Legal Services",
            "type":"Services"
        }
    ],
    "sg:phone":"+1 662 620 7938",
    "sg:postcode":"38804",
    "sg:province":"MS",
    "sg:tags":[
        "attorney"
    ],
    "sg:website":"www.claytonlaw.net",
    "wof:name":"Clayton O'Donnell Walsh",
    "wof:placetype":"venue"
},
  "geometry": {"coordinates":[-88.705466,34.258146],"type":"Point"}
}