{
  "type": "Feature",
  "properties": {
    "iso:country":"US",
    "sg:address":"134 Oak St",
    "sg:city":"Biloxi",
    "sg:classifiers":[
        {
            "category":"Manufacturing",
            "subcategory":"Tools & Machinery",
            "type":"Manufacturing & Wholesale Goods"
        }
    ],
    "sg:phone":"+1 228 374 5210",
    "sg:postcode":"39530",
    "sg:province":"MS",
    "sg:tags":[
        "engine",
        "repair",
        "internal",
        "combustion",
        "mfg"
    ],
    "wof:name":"Biloxi Marine Diesel",
    "wof:placetype":"venue"
},
  "geometry": {"coordinates":[-88.86761,30.394628],"type":"Point"}
}