{
  "type": "Feature",
  "properties": {
    "iso:country":"US",
    "sg:address":"1078 Old Yorkville Rd S",
    "sg:city":"Columbus",
    "sg:classifiers":[
        {
            "category":"Shopping",
            "type":"Retail Goods"
        }
    ],
    "sg:phone":"+1 662 328 3748",
    "sg:postcode":"39702",
    "sg:province":"MS",
    "sg:tags":[
        "wedding",
        "supply"
    ],
    "wof:name":"Hide Away Hall",
    "wof:placetype":"venue"
},
  "geometry": {"coordinates":[-88.305249,33.429518],"type":"Point"}
}