{
  "type": "Feature",
  "properties": {
    "iso:country":"US",
    "sg:address":"5119 Mitchell Rd",
    "sg:city":"Long Beach",
    "sg:classifiers":[
        {
            "category":"Professional",
            "type":"Services"
        }
    ],
    "sg:phone":"+1 228 864 7938",
    "sg:postcode":"39560",
    "sg:province":"MS",
    "wof:name":"Cass Service Solutions",
    "wof:placetype":"venue"
},
  "geometry": {"coordinates":[-89.17868199999999,30.362771],"type":"Point"}
}