{
  "type": "Feature",
  "properties": {
    "iso:country":"US",
    "sg:address":"760 Highway 49 S",
    "sg:city":"Richland",
    "sg:classifiers":[
        {
            "category":"Restaurant",
            "type":"Food & Drink"
        }
    ],
    "sg:menulink":"http://www.allmenus.com/ms/florence/133095-subway/menu/",
    "sg:phone":"+1 601 936 4138",
    "sg:postcode":"39218",
    "sg:province":"MS",
    "sg:tags":[
        "american",
        "sandwich"
    ],
    "wof:name":"Subway",
    "wof:placetype":"venue"
},
  "geometry": {"coordinates":[-90.160431,32.229977],"type":"Point"}
}