{
  "type": "Feature",
  "properties": {
    "iso:country":"US",
    "sg:address":"538 Division St",
    "sg:city":"Biloxi",
    "sg:classifiers":[
        {
            "category":"Restaurant",
            "type":"Food & Drink"
        }
    ],
    "sg:phone":"+1 228 374 2069",
    "sg:postcode":"39530",
    "sg:province":"MS",
    "wof:name":"Song Long Restaurant",
    "wof:placetype":"venue"
},
  "geometry": {"coordinates":[-88.87866200000001,30.403274],"type":"Point"}
}