{
  "type": "Feature",
  "properties": {
    "iso:country":"US",
    "sg:address":"8980 College St",
    "sg:city":"Olive Branch",
    "sg:classifiers":[
        {
            "category":"Shopping",
            "subcategory":"Beauty & Cosmetics",
            "type":"Retail Goods"
        }
    ],
    "sg:phone":"+1 662 890 3810",
    "sg:postcode":"38654",
    "sg:province":"MS",
    "sg:tags":[
        "merchandise"
    ],
    "wof:name":"Merle Norman Cosmetics",
    "wof:placetype":"venue"
},
  "geometry": {"coordinates":[-89.842517,34.960712],"type":"Point"}
}