{
  "type": "Feature",
  "properties": {
    "addr:full":"315 Highland Dr N Tupelo MS 38801",
    "addr:housenumber":"315",
    "addr:postcode":"38801",
    "addr:street":"Highland Dr N",
    "iso:country":"US",
    "sg:address":"315 Highland Dr N",
    "sg:city":"Tupelo",
    "sg:classifiers":[
        {
            "category":"Freight",
            "type":"Transportation"
        }
    ],
    "sg:phone":"+1 662 844 3607",
    "sg:postcode":"38801",
    "sg:province":"MS",
    "sg:tags":[
        "trucking"
    ],
    "wof:name":"Frank's Inc",
    "wof:placetype":"venue"
},
  "geometry": {"coordinates":[-88.72962699999999,34.257986],"type":"Point"}
}