{
  "type": "Feature",
  "properties": {
    "iso:country":"US",
    "sg:address":"1305 22nd Ave",
    "sg:city":"Meridian",
    "sg:classifiers":[
        {
            "category":"Banks & Credit Unions",
            "subcategory":"Bank",
            "type":"Services"
        }
    ],
    "sg:phone":"+1 601 484 5800",
    "sg:postcode":"39301",
    "sg:province":"MS",
    "sg:tags":[
        "commercial"
    ],
    "wof:name":"Commercial Bank",
    "wof:placetype":"venue"
},
  "geometry": {"coordinates":[-88.700523,32.370742],"type":"Point"}
}