{
  "type": "Feature",
  "properties": {
    "addr:full":"105 N Washington St Starkville MS 39759",
    "addr:housenumber":"105",
    "addr:postcode":"39759",
    "addr:street":"N Washington St",
    "iso:country":"US",
    "sg:address":"105 N Washington St",
    "sg:city":"Starkville",
    "sg:classifiers":[
        {
            "category":"Government",
            "subcategory":"Office",
            "type":"Public Place"
        }
    ],
    "sg:phone":"+1 662 323 2839",
    "sg:postcode":"39759",
    "sg:province":"MS",
    "wof:name":"Okitbbeha Food Svc",
    "wof:placetype":"venue"
},
  "geometry": {"coordinates":[-88.816554,33.464837],"type":"Point"}
}