{
  "type": "Feature",
  "properties": {
    "iso:country":"US",
    "sg:address":"321 E Fox Ave",
    "sg:city":"Eupora",
    "sg:classifiers":[
        {
            "category":"Retail",
            "subcategory":"Auto Repair",
            "type":"Services"
        }
    ],
    "sg:phone":"+1 662 258 2717",
    "sg:postcode":"39744",
    "sg:province":"MS",
    "sg:tags":[
        "general"
    ],
    "wof:name":"Jerrys Auto Repair",
    "wof:placetype":"venue"
},
  "geometry": {"coordinates":[-89.260897,33.541958],"type":"Point"}
}