{
  "type": "Feature",
  "properties": {
    "iso:country":"US",
    "sg:address":"219 Hwy 42",
    "sg:city":"Petal",
    "sg:classifiers":[
        {
            "category":"Professional",
            "subcategory":"Advertising",
            "type":"Services"
        }
    ],
    "sg:phone":"+1 601 544 4306",
    "sg:postcode":"39465",
    "sg:province":"MS",
    "sg:tags":[
        "mail",
        "direct"
    ],
    "wof:name":"Mailing Place",
    "wof:placetype":"venue"
},
  "geometry": {"coordinates":[-89.25761300000001,31.346707],"type":"Point"}
}