{
  "type": "Feature",
  "properties": {
    "addr:full":"1506 University Ave Oxford MS 38655",
    "addr:housenumber":"1506",
    "addr:postcode":"38655",
    "addr:street":"University Ave",
    "iso:country":"US",
    "sg:address":"1506 University Ave",
    "sg:city":"Oxford",
    "sg:classifiers":[
        {
            "category":"Restaurant",
            "type":"Food & Drink"
        }
    ],
    "sg:menulink":"http://www.allmenus.com/ms/hickory-flat/72894-pizza-hut/menu/",
    "sg:phone":"+1 662 236 2005",
    "sg:postcode":"38655",
    "sg:province":"MS",
    "sg:tags":[
        "american",
        "pizza"
    ],
    "wof:name":"Pizza Hut",
    "wof:placetype":"venue"
},
  "geometry": {"coordinates":[-89.51634799999999,34.363652],"type":"Point"}
}