{
  "type": "Feature",
  "properties": {
    "addr:full":"100 Fisher Ferry Rd Vicksburg MS 39180",
    "addr:housenumber":"100",
    "addr:postcode":"39180",
    "addr:street":"Fisher Ferry Rd",
    "iso:country":"US",
    "sg:address":"100 Fisher Ferry Rd",
    "sg:city":"Vicksburg",
    "sg:classifiers":[
        {
            "category":"Social Services",
            "subcategory":"Child Care",
            "type":"Services"
        }
    ],
    "sg:phone":"+1 601 638 0992",
    "sg:postcode":"39180",
    "sg:province":"MS",
    "sg:tags":[
        "day"
    ],
    "wof:name":"Kid's Connection",
    "wof:placetype":"venue"
},
  "geometry": {"coordinates":[-90.869068,32.291629],"type":"Point"}
}