{
  "type": "Feature",
  "properties": {
    "iso:country":"US",
    "sg:address":"1710 Magnolia Rd",
    "sg:city":"Corinth",
    "sg:classifiers":[
        {
            "category":"Real Estate",
            "subcategory":"Real Estate Agent",
            "type":"Services"
        }
    ],
    "sg:phone":"+1 662 287 0241",
    "sg:postcode":"38834",
    "sg:province":"MS",
    "sg:tags":[
        "appraiser",
        "business"
    ],
    "wof:name":"Brewster Appraisal Service",
    "wof:placetype":"venue"
},
  "geometry": {"coordinates":[-88.505414,34.947094],"type":"Point"}
}