{
  "type": "Feature",
  "properties": {
    "iso:country":"US",
    "sg:address":"99 Co Rd 218",
    "sg:city":"Glen",
    "sg:classifiers":[
        {
            "category":"Building & Trades",
            "subcategory":"Construction",
            "type":"Services"
        }
    ],
    "sg:phone":"+1 662 287 4910",
    "sg:postcode":"38846",
    "sg:province":"MS",
    "sg:tags":[
        "contractor"
    ],
    "wof:name":"Roberts Insulation Co LLC",
    "wof:placetype":"venue"
},
  "geometry": {"coordinates":[-88.43994499999999,34.884336],"type":"Point"}
}