{
  "type": "Feature",
  "properties": {
    "iso:country":"US",
    "sg:address":"1197 Pontocola Rd",
    "sg:city":"Pontotoc",
    "sg:classifiers":[
        {
            "category":"Retail",
            "subcategory":"Repair Shop",
            "type":"Services"
        }
    ],
    "sg:phone":"+1 662 231 6144",
    "sg:postcode":"38863",
    "sg:province":"MS",
    "sg:tags":[
        "lock",
        "locksmith"
    ],
    "wof:name":"AAA-Mike's Unlocking",
    "wof:placetype":"venue"
},
  "geometry": {"coordinates":[-88.900682,34.162071],"type":"Point"}
}