{
  "type": "Feature",
  "properties": {
    "addr:full":"148 Becknell St Pearl MS 39208",
    "addr:housenumber":"148",
    "addr:postcode":"39208",
    "addr:street":"Becknell St",
    "iso:country":"US",
    "sg:address":"148 Becknell St",
    "sg:city":"Pearl",
    "sg:classifiers":[
        {
            "category":"Manufacturing",
            "subcategory":"Tools & Machinery",
            "type":"Manufacturing & Wholesale Goods"
        }
    ],
    "sg:phone":"+1 601 939 6062",
    "sg:postcode":"39208",
    "sg:province":"MS",
    "sg:tags":[
        "air",
        "parts",
        "conditioning",
        "supply"
    ],
    "wof:name":"Hallmark Hermetic Co Inc",
    "wof:placetype":"venue"
},
  "geometry": {"coordinates":[-90.149321,32.264155],"type":"Point"}
}