{
  "type": "Feature",
  "properties": {
    "iso:country":"US",
    "sg:address":"3222 Hwy 13 S",
    "sg:city":"Columbia",
    "sg:classifiers":[
        {
            "category":"Food & Beverages",
            "subcategory":"Groceries & Convenience Stores",
            "type":"Retail Goods"
        }
    ],
    "sg:phone":"+1 601 736 8270",
    "sg:postcode":"39429",
    "sg:province":"MS",
    "wof:name":"Country Store",
    "wof:placetype":"venue"
},
  "geometry": {"coordinates":[-89.694918,31.134329],"type":"Point"}
}