{
  "type": "Feature",
  "properties": {
    "addr:full":"508 Colonial Cir Jackson MS 39211",
    "addr:housenumber":"508",
    "addr:postcode":"39211",
    "addr:street":"Colonial Cir",
    "iso:country":"US",
    "sg:address":"508 Colonial Cir",
    "sg:city":"Jackson",
    "sg:classifiers":[
        {
            "category":"Manufacturing",
            "subcategory":"Printing",
            "type":"Manufacturing & Wholesale Goods"
        }
    ],
    "sg:phone":"+1 601 956 2264",
    "sg:postcode":"39211",
    "sg:province":"MS",
    "sg:tags":[
        "publishing"
    ],
    "wof:name":"23",
    "wof:placetype":"venue"
},
  "geometry": {"coordinates":[-90.13014699999999,32.384407],"type":"Point"}
}