{
  "type": "Feature",
  "properties": {
    "iso:country":"US",
    "sg:address":"2018 Bienville Blvd",
    "sg:city":"Ocean Springs",
    "sg:classifiers":[
        {
            "category":"Restaurant",
            "type":"Food & Drink"
        }
    ],
    "sg:phone":"+1 228 818 5331",
    "sg:postcode":"39564",
    "sg:province":"MS",
    "sg:tags":[
        "shop",
        "coffee"
    ],
    "wof:name":"Java Joe'z Coffee",
    "wof:placetype":"venue"
},
  "geometry": {"coordinates":[-88.807351,30.416197],"type":"Point"}
}