{
  "type": "Feature",
  "properties": {
    "iso:country":"US",
    "sg:address":"200 5th Ave",
    "sg:city":"Mccomb",
    "sg:classifiers":[
        {
            "category":"Shopping",
            "subcategory":"Used Merchandise",
            "type":"Retail Goods"
        },
        {
            "category":"Social Services",
            "type":"Services"
        }
    ],
    "sg:phone":"+1 601 250 1588",
    "sg:postcode":"39648",
    "sg:province":"MS",
    "sg:tags":[
        "flea",
        "market"
    ],
    "wof:name":"Yes Society",
    "wof:placetype":"venue"
},
  "geometry": {"coordinates":[-90.45291899999999,31.240979],"type":"Point"}
}