{
  "type": "Feature",
  "properties": {
    "addr:full":"420 5th St West Point MS 39773",
    "addr:housenumber":"420",
    "addr:postcode":"39773",
    "addr:street":"5Th St",
    "iso:country":"US",
    "sg:address":"420 5th St",
    "sg:city":"West Point",
    "sg:classifiers":[
        {
            "category":"Organizations",
            "subcategory":"Religious Organization",
            "type":"Services"
        }
    ],
    "sg:phone":"+1 662 494 2093",
    "sg:postcode":"39773",
    "sg:province":"MS",
    "wof:name":"Saint Mtthew Tmple Chrch God C",
    "wof:placetype":"venue"
},
  "geometry": {"coordinates":[-88.64403900000001,33.612409],"type":"Point"}
}