{
  "type": "Feature",
  "properties": {
    "iso:country":"US",
    "sg:address":"2909 26th Ave",
    "sg:city":"Gulfport",
    "sg:classifiers":[
        {
            "category":"Government",
            "subcategory":"Office",
            "type":"Public Place"
        }
    ],
    "sg:phone":"+1 228 863 6272",
    "sg:postcode":"39501",
    "sg:province":"MS",
    "sg:website":"www.mrha8.org",
    "wof:name":"Mississippi Regional Housing",
    "wof:placetype":"venue"
},
  "geometry": {"coordinates":[-89.09469799999999,30.386498],"type":"Point"}
}