{
  "type": "Feature",
  "properties": {
    "addr:full":"451 Main St Meadville MS 39669",
    "addr:housenumber":"451",
    "addr:postcode":"39669",
    "addr:street":"Main St",
    "iso:country":"US",
    "sg:address":"451 Main St",
    "sg:city":"Meadville",
    "sg:classifiers":[
        {
            "category":"Shopping",
            "subcategory":"Gifts & Souvenirs",
            "type":"Retail Goods"
        }
    ],
    "sg:phone":"+1 601 384 5595",
    "sg:postcode":"39669",
    "sg:province":"MS",
    "sg:tags":[
        "shop"
    ],
    "wof:name":"Gina's Hidden Treasures Inc",
    "wof:placetype":"venue"
},
  "geometry": {"coordinates":[-91.297719,31.104009],"type":"Point"}
}