{
  "type": "Feature",
  "properties": {
    "iso:country":"US",
    "sg:address":"1197 Hwy 25",
    "sg:city":"Tishomingo",
    "sg:classifiers":[
        {
            "category":"Personal",
            "subcategory":"Beauty Salon",
            "type":"Services"
        }
    ],
    "sg:phone":"+1 662 438 6301",
    "sg:postcode":"38873",
    "sg:province":"MS",
    "wof:name":"Jennifer's Hair Fashions",
    "wof:placetype":"venue"
},
  "geometry": {"coordinates":[-88.22799999999999,34.623778],"type":"Point"}
}