{
  "type": "Feature",
  "properties": {
    "iso:country":"US",
    "sg:address":"14 Pass Rd",
    "sg:city":"Gulfport",
    "sg:classifiers":[
        {
            "category":"Autos & Motor Vehicles",
            "subcategory":"Recreational Vehicle Sales",
            "type":"Retail Goods"
        }
    ],
    "sg:phone":"+1 228 863 6700",
    "sg:postcode":"39507",
    "sg:province":"MS",
    "sg:tags":[
        "canopy",
        "shell",
        "truck",
        "cap"
    ],
    "wof:name":"Topper World Of Gulfport",
    "wof:placetype":"venue"
},
  "geometry": {"coordinates":[-89.04604500000001,30.393692],"type":"Point"}
}