{
  "type": "Feature",
  "properties": {
    "addr:full":"406 Old Rice Rd Madison MS 39110",
    "addr:housenumber":"406",
    "addr:postcode":"39110",
    "addr:street":"Old Rice Rd",
    "iso:country":"US",
    "sg:address":"406 Old Rice Rd",
    "sg:city":"Madison",
    "sg:classifiers":[
        {
            "category":"Recreation",
            "type":"Entertainment"
        }
    ],
    "sg:phone":"+1 601 856 6281",
    "sg:postcode":"39110",
    "sg:province":"MS",
    "sg:tags":[
        "club",
        "membership"
    ],
    "wof:name":"J R Byrd Hunting Club",
    "wof:placetype":"venue"
},
  "geometry": {"coordinates":[-90.062618,32.472182],"type":"Point"}
}