{
  "type": "Feature",
  "properties": {
    "iso:country":"US",
    "sg:address":"1103 S Clifton St",
    "sg:city":"Fulton",
    "sg:classifiers":[
        {
            "category":"Personal",
            "subcategory":"Beauty Salon",
            "type":"Services"
        }
    ],
    "sg:phone":"+1 662 862 4520",
    "sg:postcode":"38843",
    "sg:province":"MS",
    "sg:tags":[
        "shop"
    ],
    "wof:name":"Wandas Beauty Salon",
    "wof:placetype":"venue"
},
  "geometry": {"coordinates":[-88.407549,34.260021],"type":"Point"}
}