{
  "type": "Feature",
  "properties": {
    "addr:full":"3214 Pascagoula St Pascagoula MS 39567",
    "addr:housenumber":"3214",
    "addr:postcode":"39567",
    "addr:street":"Pascagoula St",
    "iso:country":"US",
    "sg:address":"3214 Pascagoula St",
    "sg:city":"Pascagoula",
    "sg:classifiers":[
        {
            "category":"Education",
            "subcategory":"Library",
            "type":"Public Place"
        }
    ],
    "sg:phone":"+1 228 769 3059",
    "sg:postcode":"39567",
    "sg:province":"MS",
    "wof:name":"Jackson-George Regional Libr",
    "wof:placetype":"venue"
},
  "geometry": {"coordinates":[-88.556584,30.36603],"type":"Point"}
}