{
  "type": "Feature",
  "properties": {
    "addr:full":"2950 Co Rd 410 Ripley MS 38629",
    "addr:housenumber":"2950;410",
    "addr:postcode":"38629",
    "addr:street":"Co Rd",
    "iso:country":"US",
    "sg:address":"2950 Co Rd 410",
    "sg:city":"Ripley",
    "sg:classifiers":[
        {
            "category":"Organizations",
            "subcategory":"Religious Organization",
            "type":"Services"
        }
    ],
    "sg:phone":"+1 662 837 7932",
    "sg:postcode":"38629",
    "sg:province":"MS",
    "sg:tags":[
        "church"
    ],
    "wof:name":"New Life Pentecostal Church",
    "wof:placetype":"venue"
},
  "geometry": {"coordinates":[-88.935143,34.807551],"type":"Point"}
}