{
  "type": "Feature",
  "properties": {
    "iso:country":"US",
    "sg:address":"2245 Hwy 15 N",
    "sg:city":"Pontotoc",
    "sg:classifiers":[
        {
            "category":"Sports & Exercise",
            "subcategory":"Gym",
            "type":"Entertainment"
        }
    ],
    "sg:phone":"+1 662 489 2204",
    "sg:postcode":"38863",
    "sg:province":"MS",
    "sg:tags":[
        "club",
        "health",
        "studio",
        "gymnasium"
    ],
    "wof:name":"Fit America Fitness Equipment",
    "wof:placetype":"venue"
},
  "geometry": {"coordinates":[-89.025019,34.279134],"type":"Point"}
}