{
  "type": "Feature",
  "properties": {
    "iso:country":"US",
    "sg:address":"1163 Old Pearl Rd",
    "sg:city":"Florence",
    "sg:classifiers":[
        {
            "category":"Retail",
            "subcategory":"Repair Shop",
            "type":"Services"
        }
    ],
    "sg:phone":"+1 601 845 5483",
    "sg:postcode":"39073",
    "sg:province":"MS",
    "sg:tags":[
        "welding"
    ],
    "wof:name":"S & C Welding & Mach Works Inc",
    "wof:placetype":"venue"
},
  "geometry": {"coordinates":[-90.198043,32.025534],"type":"Point"}
}