{
  "type": "Feature",
  "properties": {
    "iso:country":"US",
    "sg:address":"1520 W Capitol St",
    "sg:city":"Jackson",
    "sg:classifiers":[
        {
            "category":"Government",
            "subcategory":"Office",
            "type":"Public Place"
        }
    ],
    "sg:phone":"+1 601 961 7589",
    "sg:postcode":"39203",
    "sg:province":"MS",
    "sg:tags":[
        "federal",
        "affairs",
        "govt",
        "admin"
    ],
    "wof:name":"US Veterans Employment Svc",
    "wof:placetype":"venue"
},
  "geometry": {"coordinates":[-90.206756,32.311099],"type":"Point"}
}