{
  "type": "Feature",
  "properties": {
    "addr:full":"1488 Belk Blvd Oxford MS 38655",
    "addr:housenumber":"1488",
    "addr:postcode":"38655",
    "addr:street":"Belk Blvd",
    "iso:country":"US",
    "sg:address":"1488 Belk Blvd",
    "sg:city":"Oxford",
    "sg:classifiers":[
        {
            "category":"Health Services",
            "subcategory":"Nursing And Care Facility",
            "type":"Services"
        }
    ],
    "sg:phone":"+1 662 234 8244",
    "sg:postcode":"38655",
    "sg:province":"MS",
    "sg:tags":[
        "skilled",
        "intermediate"
    ],
    "wof:name":"Hermitage Gardens Of Oxford",
    "wof:placetype":"venue"
},
  "geometry": {"coordinates":[-89.513527,34.345726],"type":"Point"}
}