{
  "type": "Feature",
  "properties": {
    "iso:country":"US",
    "sg:address":"55 Sgt Prentiss Dr",
    "sg:city":"Natchez",
    "sg:classifiers":[
        {
            "category":"Retail",
            "subcategory":"Laundry & Dry Cleaning",
            "type":"Services"
        }
    ],
    "sg:phone":"+1 601 442 6926",
    "sg:postcode":"39120",
    "sg:province":"MS",
    "sg:tags":[
        "cleaners"
    ],
    "wof:name":"Jaco Inc",
    "wof:placetype":"venue"
},
  "geometry": {"coordinates":[-91.381755,31.533219],"type":"Point"}
}