{
  "type": "Feature",
  "properties": {
    "iso:country":"US",
    "sg:address":"200 Walnut Ave",
    "sg:city":"Eupora",
    "sg:classifiers":[
        {
            "category":"Health Services",
            "subcategory":"Nursing And Care Facility",
            "type":"Services"
        }
    ],
    "sg:phone":"+1 662 258 8293",
    "sg:postcode":"39744",
    "sg:province":"MS",
    "sg:tags":[
        "home",
        "convalescent"
    ],
    "sg:website":"www.beverlycorp.com",
    "wof:name":"Beverly Healthcare",
    "wof:placetype":"venue"
},
  "geometry": {"coordinates":[-89.263672,33.532759],"type":"Point"}
}