{
  "type": "Feature",
  "properties": {
    "addr:full":"421 W Peace St Canton MS 39046",
    "addr:housenumber":"421",
    "addr:postcode":"39046",
    "addr:street":"W Peace St",
    "iso:country":"US",
    "sg:address":"421 W Peace St",
    "sg:city":"Canton",
    "sg:classifiers":[
        {
            "category":"Insurance",
            "subcategory":"Insurance Agent",
            "type":"Services"
        }
    ],
    "sg:phone":"+1 601 859 2627",
    "sg:postcode":"39046",
    "sg:province":"MS",
    "wof:name":"Lacy & Assoc Insurance",
    "wof:placetype":"venue"
},
  "geometry": {"coordinates":[-90.040363,32.612503],"type":"Point"}
}