{
  "type": "Feature",
  "properties": {
    "iso:country":"US",
    "sg:address":"8320 Hwy 15 S",
    "sg:city":"Pontotoc",
    "sg:classifiers":[
        {
            "category":"Government",
            "subcategory":"Office",
            "type":"Public Place"
        }
    ],
    "sg:phone":"+1 662 489 5211",
    "sg:postcode":"38863",
    "sg:province":"MS",
    "wof:name":"Swine Unit",
    "wof:placetype":"venue"
},
  "geometry": {"coordinates":[-89.00371800000001,34.137749],"type":"Point"}
}