{
  "type": "Feature",
  "properties": {
    "iso:country":"US",
    "sg:address":"2689 Hwy 19 S",
    "sg:city":"Meridian",
    "sg:classifiers":[
        {
            "category":"Manufacturing",
            "subcategory":"Furniture",
            "type":"Manufacturing & Wholesale Goods"
        }
    ],
    "sg:phone":"+1 601 484 6003",
    "sg:postcode":"39301",
    "sg:province":"MS",
    "sg:tags":[
        "upholstered",
        "household",
        "mfg"
    ],
    "wof:name":"Boykin Bros Awng & Upholstory",
    "wof:placetype":"venue"
},
  "geometry": {"coordinates":[-88.554852,32.321972],"type":"Point"}
}