{
  "type": "Feature",
  "properties": {
    "iso:country":"US",
    "sg:address":"1201 Gunter Rd",
    "sg:city":"Florence",
    "sg:classifiers":[
        {
            "category":"Health Services",
            "subcategory":"Nursing And Care Facility",
            "type":"Services"
        }
    ],
    "sg:phone":"+1 601 939 6371",
    "sg:postcode":"39073",
    "sg:province":"MS",
    "sg:tags":[
        "home",
        "rest"
    ],
    "wof:name":"Briar Hill Rest Home Inc",
    "wof:placetype":"venue"
},
  "geometry": {"coordinates":[-90.12393400000001,32.181318],"type":"Point"}
}