{
  "type": "Feature",
  "properties": {
    "iso:country":"US",
    "sg:address":"204 James St",
    "sg:city":"Long Beach",
    "sg:classifiers":[
        {
            "category":"Professional",
            "type":"Services"
        }
    ],
    "sg:phone":"+1 228 863 1101",
    "sg:postcode":"39560",
    "sg:province":"MS",
    "wof:name":"Hallwrite C",
    "wof:placetype":"venue"
},
  "geometry": {"coordinates":[-89.137992,30.361224],"type":"Point"}
}