{
  "type": "Feature",
  "properties": {
    "iso:country":"US",
    "sg:address":"8835 Commerce Dr",
    "sg:city":"Southaven",
    "sg:classifiers":[
        {
            "category":"Retail",
            "subcategory":"Driving School",
            "type":"Services"
        },
        {
            "category":"Autos & Motor Vehicles",
            "subcategory":"Motorcycle Sales",
            "type":"Retail Goods"
        }
    ],
    "sg:phone":"+1 662 393 7780",
    "sg:postcode":"38671",
    "sg:province":"MS",
    "sg:tags":[
        "scooters-parts",
        "instruction",
        "supply"
    ],
    "wof:name":"Motosport Inc",
    "wof:placetype":"venue"
},
  "geometry": {"coordinates":[-89.967049,34.988974],"type":"Point"}
}