{
  "type": "Feature",
  "properties": {
    "iso:country":"US",
    "sg:address":"120 Commerce St",
    "sg:city":"West Point",
    "sg:classifiers":[
        {
            "category":"Home & Garden",
            "subcategory":"Hardware",
            "type":"Retail Goods"
        }
    ],
    "sg:phone":"+1 662 494 5783",
    "sg:postcode":"39773",
    "sg:province":"MS",
    "wof:name":"Kellogg Hardware & Appliance",
    "wof:placetype":"venue"
},
  "geometry": {"coordinates":[-88.648591,33.606881],"type":"Point"}
}