{
  "type": "Feature",
  "properties": {
    "iso:country":"US",
    "sg:address":"102 Proprietors Pt",
    "sg:city":"Madison",
    "sg:classifiers":[
        {
            "category":"Professional",
            "subcategory":"Art Services",
            "type":"Services"
        }
    ],
    "sg:phone":"+1 601 898 8828",
    "sg:postcode":"39110",
    "sg:province":"MS",
    "sg:tags":[
        "photographer"
    ],
    "wof:name":"Kirkpatrick Photography",
    "wof:placetype":"venue"
},
  "geometry": {"coordinates":[-90.133214,32.486986],"type":"Point"}
}