{
  "type": "Feature",
  "properties": {
    "iso:country":"US",
    "sg:address":"1574 Hwy 98 E",
    "sg:city":"Columbia",
    "sg:classifiers":[
        {
            "category":"Professional",
            "subcategory":"Engineering",
            "type":"Services"
        }
    ],
    "sg:phone":"+1 601 731 2600",
    "sg:postcode":"39429",
    "sg:province":"MS",
    "sg:tags":[
        "engineer"
    ],
    "sg:website":"www.dunganeng.com",
    "wof:name":"Dungan Engineering Pa",
    "wof:placetype":"venue"
},
  "geometry": {"coordinates":[-89.779673,31.254631],"type":"Point"}
}