{
  "type": "Feature",
  "properties": {
    "iso:country":"US",
    "sg:address":"709 Smythe St",
    "sg:city":"Kosciusko",
    "sg:classifiers":[
        {
            "category":"Restaurant",
            "type":"Food & Drink"
        }
    ],
    "sg:phone":"+1 662 289 5075",
    "sg:postcode":"39090",
    "sg:province":"MS",
    "sg:tags":[
        "eating"
    ],
    "wof:name":"P P Birdhouses",
    "wof:placetype":"venue"
},
  "geometry": {"coordinates":[-89.577094,33.047839],"type":"Point"}
}