{
  "type": "Feature",
  "properties": {
    "iso:country":"US",
    "sg:address":"4913 Kreole Ave",
    "sg:city":"Kreole",
    "sg:classifiers":[
        {
            "category":"Government",
            "subcategory":"Post Office",
            "type":"Public Place"
        }
    ],
    "sg:phone":"+1 228 000 1111",
    "sg:postcode":"39563",
    "sg:province":"MS",
    "wof:name":"US Post Office",
    "wof:placetype":"venue"
},
  "geometry": {"coordinates":[-88.494602,30.411433],"type":"Point"}
}