{
  "type": "Feature",
  "properties": {
    "iso:country":"US",
    "sg:address":"1127 Openwood St",
    "sg:city":"Vicksburg",
    "sg:classifiers":[
        {
            "category":"Professional",
            "subcategory":"Business Services",
            "type":"Services"
        }
    ],
    "sg:phone":"+1 601 634 0641",
    "sg:postcode":"39183",
    "sg:province":"MS",
    "wof:name":"Carson Bail Bonding",
    "wof:placetype":"venue"
},
  "geometry": {"coordinates":[-90.875924,32.35303],"type":"Point"}
}