{
  "type": "Feature",
  "properties": {
    "addr:full":"5795 Terry Rd Byram MS 39272",
    "addr:housenumber":"5795",
    "addr:postcode":"39272",
    "addr:street":"Terry Rd",
    "iso:country":"US",
    "sg:address":"5795 Terry Rd",
    "sg:city":"Byram",
    "sg:classifiers":[
        {
            "category":"Restaurant",
            "type":"Food & Drink"
        }
    ],
    "sg:phone":"+1 601 371 3202",
    "sg:postcode":"39272",
    "sg:province":"MS",
    "wof:name":"Dragon Garden",
    "wof:placetype":"venue"
},
  "geometry": {"coordinates":[-90.289641,32.165164],"type":"Point"}
}