{
  "type": "Feature",
  "properties": {
    "iso:country":"US",
    "sg:address":"907 Hwy 82 W",
    "sg:city":"Greenwood",
    "sg:classifiers":[
        {
            "category":"Health Services",
            "subcategory":"Health Practitioner",
            "type":"Services"
        }
    ],
    "sg:phone":"+1 662 459 7294",
    "sg:postcode":"38930",
    "sg:province":"MS",
    "wof:name":"HealthSouth",
    "wof:placetype":"venue"
},
  "geometry": {"coordinates":[-90.204915,33.524454],"type":"Point"}
}