{
  "type": "Feature",
  "properties": {
    "iso:country":"US",
    "sg:address":"804 State Hwy 35",
    "sg:city":"Carthage",
    "sg:classifiers":[
        {
            "category":"Food & Beverages",
            "subcategory":"Groceries & Convenience Stores",
            "type":"Retail Goods"
        }
    ],
    "sg:phone":"+1 601 267 7817",
    "sg:postcode":"39051",
    "sg:province":"MS",
    "wof:name":"Fortune Mart",
    "wof:placetype":"venue"
},
  "geometry": {"coordinates":[-89.530844,32.718107],"type":"Point"}
}