{
  "type": "Feature",
  "properties": {
    "addr:full":"1237 Vine St Jackson MS 39202",
    "addr:housenumber":"1237",
    "addr:postcode":"39202",
    "addr:street":"Vine St",
    "iso:country":"US",
    "sg:address":"1237 Vine St",
    "sg:city":"Jackson",
    "sg:classifiers":[
        {
            "category":"Manufacturing",
            "subcategory":"Tools & Machinery",
            "type":"Manufacturing & Wholesale Goods"
        }
    ],
    "sg:phone":"+1 601 355 6485",
    "sg:postcode":"39202",
    "sg:province":"MS",
    "sg:tags":[
        "lighting",
        "fixture"
    ],
    "sg:website":"www.lithonia.com",
    "wof:name":"Cook Hartwell Mfg Rep & Wrhse",
    "wof:placetype":"venue"
},
  "geometry": {"coordinates":[-90.16952999999999,32.305179],"type":"Point"}
}