{
  "type": "Feature",
  "properties": {
    "iso:country":"US",
    "sg:address":"20 Dickens Ct",
    "sg:city":"Jackson",
    "sg:classifiers":[
        {
            "category":"Local Transit",
            "type":"Transportation"
        }
    ],
    "sg:phone":"+1 601 956 2535",
    "sg:postcode":"39206",
    "sg:province":"MS",
    "wof:name":"Brown Transportation",
    "wof:placetype":"venue"
},
  "geometry": {"coordinates":[-90.169552,32.386277],"type":"Point"}
}