{
  "type": "Feature",
  "properties": {
    "addr:full":"4300 Popps Ferry Rd Biloxi MS 39540",
    "addr:housenumber":"4300",
    "addr:postcode":"39540",
    "addr:street":"Popps Ferry Rd",
    "iso:country":"US",
    "sg:address":"4300 Popps Ferry Rd",
    "sg:city":"Biloxi",
    "sg:classifiers":[
        {
            "category":"Building & Trades",
            "subcategory":"Construction",
            "type":"Services"
        }
    ],
    "sg:phone":"+1 228 392 3359",
    "sg:postcode":"39540",
    "sg:province":"MS",
    "sg:tags":[
        "metal",
        "contractor"
    ],
    "wof:name":"Southeastern Erectors Inc",
    "wof:placetype":"venue"
},
  "geometry": {"coordinates":[-88.911571,30.443431],"type":"Point"}
}