{
  "type": "Feature",
  "properties": {
    "iso:country":"US",
    "sg:address":"5275 Terry Rd",
    "sg:city":"Jackson",
    "sg:classifiers":[
        {
            "category":"Organizations",
            "subcategory":"Religious Organization",
            "type":"Services"
        }
    ],
    "sg:phone":"+1 601 372 7812",
    "sg:postcode":"39212",
    "sg:province":"MS",
    "sg:tags":[
        "church"
    ],
    "wof:name":"Griffith Mem Baptst Church",
    "wof:placetype":"venue"
},
  "geometry": {"coordinates":[-90.268688,32.179431],"type":"Point"}
}