{
  "type": "Feature",
  "properties": {
    "iso:country":"US",
    "sg:address":"620 Delaware Ave",
    "sg:city":"Mccomb",
    "sg:classifiers":[
        {
            "category":"Insurance",
            "subcategory":"Insurance Agent",
            "type":"Services"
        }
    ],
    "sg:phone":"+1 601 249 2900",
    "sg:postcode":"39648",
    "sg:province":"MS",
    "wof:name":"Allstate Insurance",
    "wof:placetype":"venue"
},
  "geometry": {"coordinates":[-90.458995,31.246131],"type":"Point"}
}