{
  "type": "Feature",
  "properties": {
    "iso:country":"US",
    "sg:address":"165 Rollingwood Dr",
    "sg:city":"Lucedale",
    "sg:classifiers":[
        {
            "category":"Building & Trades",
            "subcategory":"Landscaping Services",
            "type":"Services"
        }
    ],
    "sg:phone":"+1 601 947 8064",
    "sg:postcode":"39426",
    "sg:province":"MS",
    "wof:name":"Pro Lawn Maintenance",
    "wof:placetype":"venue"
},
  "geometry": {"coordinates":[-89.636683,30.572054],"type":"Point"}
}