{
  "type": "Feature",
  "properties": {
    "iso:country":"US",
    "sg:address":"4311 Hospital St",
    "sg:city":"Pascagoula",
    "sg:classifiers":[
        {
            "category":"Education",
            "subcategory":"School",
            "type":"Public Place"
        }
    ],
    "sg:phone":"+1 228 762 1457",
    "sg:postcode":"39567",
    "sg:province":"MS",
    "sg:tags":[
        "executive"
    ],
    "wof:name":"Jackson Cnty Exceptional Schl",
    "wof:placetype":"venue"
},
  "geometry": {"coordinates":[-88.53479,30.373335],"type":"Point"}
}