{
  "type": "Feature",
  "properties": {
    "iso:country":"US",
    "sg:address":"412 US Hwy 49",
    "sg:city":"Wiggins",
    "sg:classifiers":[
        {
            "category":"Food & Beverages",
            "subcategory":"Fruits & Vegetables",
            "type":"Retail Goods"
        }
    ],
    "sg:phone":"+1 601 928 1930",
    "sg:postcode":"39577",
    "sg:province":"MS",
    "sg:tags":[
        "produce"
    ],
    "wof:name":"Swing City",
    "wof:placetype":"venue"
},
  "geometry": {"coordinates":[-89.162397,30.861522],"type":"Point"}
}