{
  "type": "Feature",
  "properties": {
    "addr:full":"107 Jefferson St Natchez MS 39120",
    "addr:housenumber":"107",
    "addr:postcode":"39120",
    "addr:street":"Jefferson St",
    "iso:country":"US",
    "sg:address":"107 Jefferson St",
    "sg:city":"Natchez",
    "sg:classifiers":[
        {
            "category":"Shopping",
            "subcategory":"Clothing, Apparel, & Fashions",
            "type":"Retail Goods"
        }
    ],
    "sg:phone":"+1 601 445 6018",
    "sg:postcode":"39120",
    "sg:province":"MS",
    "sg:tags":[
        "wear"
    ],
    "wof:name":"Four Korners",
    "wof:placetype":"venue"
},
  "geometry": {"coordinates":[-91.404432,31.563752],"type":"Point"}
}