{
  "type": "Feature",
  "properties": {
    "iso:country":"US",
    "sg:address":"986 Magnolia St",
    "sg:city":"Tunica",
    "sg:classifiers":[
        {
            "category":"Manufacturing",
            "subcategory":"Printing",
            "type":"Manufacturing & Wholesale Goods"
        }
    ],
    "sg:phone":"+1 662 363 1511",
    "sg:postcode":"38676",
    "sg:province":"MS",
    "sg:tags":[
        "newspaper"
    ],
    "wof:name":"Tunica Times",
    "wof:placetype":"venue"
},
  "geometry": {"coordinates":[-90.381529,34.687793],"type":"Point"}
}