{
  "type": "Feature",
  "properties": {
    "iso:country":"US",
    "sg:address":"123 S Industrial Rd",
    "sg:city":"Tupelo",
    "sg:classifiers":[
        {
            "category":"Restaurant",
            "type":"Food & Drink"
        }
    ],
    "sg:phone":"+1 662 844 7399",
    "sg:postcode":"38801",
    "sg:province":"MS",
    "sg:tags":[
        "eating"
    ],
    "wof:name":"Las Margaritas",
    "wof:placetype":"venue"
},
  "geometry": {"coordinates":[-88.720572,34.256896],"type":"Point"}
}