{
  "type": "Feature",
  "properties": {
    "iso:country":"US",
    "sg:address":"747 Cooper Rd",
    "sg:city":"Jackson",
    "sg:classifiers":[
        {
            "category":"Personal",
            "subcategory":"Beauty Salon",
            "type":"Services"
        }
    ],
    "sg:phone":"+1 601 371 1965",
    "sg:postcode":"39212",
    "sg:province":"MS",
    "wof:name":"Mary's Salon",
    "wof:placetype":"venue"
},
  "geometry": {"coordinates":[-90.24614800000001,32.253783],"type":"Point"}
}