{
  "type": "Feature",
  "properties": {
    "addr:full":"2301 Hewes Ave Gulfport MS 39507",
    "addr:housenumber":"2301",
    "addr:postcode":"39507",
    "addr:street":"Hewes Ave",
    "iso:country":"US",
    "sg:address":"2301 Hewes Ave",
    "sg:city":"Gulfport",
    "sg:classifiers":[
        {
            "category":"Retail",
            "subcategory":"Auto Repair",
            "type":"Services"
        }
    ],
    "sg:phone":"+1 228 865 0600",
    "sg:postcode":"39507",
    "sg:province":"MS",
    "sg:tags":[
        "general",
        "supply"
    ],
    "wof:name":"Gulf Coast Auto Air",
    "wof:placetype":"venue"
},
  "geometry": {"coordinates":[-89.060423,30.380325],"type":"Point"}
}