{
  "type": "Feature",
  "properties": {
    "iso:country":"US",
    "sg:address":"314 Washington St",
    "sg:city":"Okolona",
    "sg:classifiers":[
        {
            "category":"Social Services",
            "subcategory":"Child Care",
            "type":"Services"
        }
    ],
    "sg:phone":"+1 662 447 3271",
    "sg:postcode":"38860",
    "sg:province":"MS",
    "sg:tags":[
        "day"
    ],
    "wof:name":"Armstrongs Kiddie Care",
    "wof:placetype":"venue"
},
  "geometry": {"coordinates":[-88.751863,34.008915],"type":"Point"}
}