{
  "type": "Feature",
  "properties": {
    "iso:country":"US",
    "sg:address":"4306 Halls Ferry Rd",
    "sg:city":"Vicksburg",
    "sg:classifiers":[
        {
            "category":"Autos & Motor Vehicles",
            "subcategory":"Fuel & Gas Station",
            "type":"Retail Goods"
        }
    ],
    "sg:phone":"+1 601 638 7114",
    "sg:postcode":"39180",
    "sg:province":"MS",
    "sg:tags":[
        "oil"
    ],
    "wof:name":"Jr's Chevron",
    "wof:placetype":"venue"
},
  "geometry": {"coordinates":[-90.86702,32.291759],"type":"Point"}
}