{
  "type": "Feature",
  "properties": {
    "addr:full":"105 Pluck Rd Belzoni MS 39038",
    "addr:housenumber":"105",
    "addr:postcode":"39038",
    "addr:street":"Pluck Rd",
    "iso:country":"US",
    "sg:address":"105 Pluck Rd",
    "sg:city":"Belzoni",
    "sg:classifiers":[
        {
            "category":"Wholesale",
            "subcategory":"Durable Goods & Equipment",
            "type":"Manufacturing & Wholesale Goods"
        }
    ],
    "sg:phone":"+1 662 247 2866",
    "sg:postcode":"39038",
    "sg:province":"MS",
    "sg:tags":[
        "exporter"
    ],
    "wof:name":"Floor Care Co",
    "wof:placetype":"venue"
},
  "geometry": {"coordinates":[-90.503277,33.167412],"type":"Point"}
}