{
  "type": "Feature",
  "properties": {
    "addr:full":"822 Longwood Pl Pearl MS 39208",
    "addr:housenumber":"822",
    "addr:postcode":"39208",
    "addr:street":"Longwood Pl",
    "iso:country":"US",
    "sg:address":"822 Longwood Pl",
    "sg:city":"Pearl",
    "sg:classifiers":[
        {
            "category":"Building & Trades",
            "subcategory":"Plumbing",
            "type":"Services"
        }
    ],
    "sg:phone":"+1 601 939 9290",
    "sg:postcode":"39208",
    "sg:province":"MS",
    "sg:tags":[
        "contractor"
    ],
    "wof:name":"Chaney Mechanical",
    "wof:placetype":"venue"
},
  "geometry": {"coordinates":[-90.04149700000001,32.307454],"type":"Point"}
}