{
  "type": "Feature",
  "properties": {
    "iso:country":"US",
    "sg:address":"3 Highland Park Ct",
    "sg:city":"Jackson",
    "sg:classifiers":[
        {
            "category":"Farming",
            "subcategory":"Farm",
            "type":"Manufacturing & Wholesale Goods"
        }
    ],
    "sg:phone":"+1 601 987 4000",
    "sg:postcode":"39211",
    "sg:province":"MS",
    "sg:tags":[
        "crop",
        "general"
    ],
    "wof:name":"P&G Farm Properties LLC",
    "wof:placetype":"venue"
},
  "geometry": {"coordinates":[-90.149475,32.351379],"type":"Point"}
}