{
  "type": "Feature",
  "properties": {
    "iso:country":"US",
    "sg:address":"1940 Hwy 19 N",
    "sg:city":"Meridian",
    "sg:classifiers":[
        {
            "category":"Retail",
            "subcategory":"Auto Repair",
            "type":"Services"
        }
    ],
    "sg:phone":"+1 601 483 0345",
    "sg:postcode":"39307",
    "sg:province":"MS",
    "sg:tags":[
        "repairing",
        "automobile",
        "general"
    ],
    "wof:name":"Express Care Auto Center",
    "wof:placetype":"venue"
},
  "geometry": {"coordinates":[-88.742485,32.37329],"type":"Point"}
}