{
  "type": "Feature",
  "properties": {
    "addr:full":"489 Luckney Rd Brandon MS 39042",
    "addr:housenumber":"489",
    "addr:postcode":"39042",
    "addr:street":"Luckney Rd",
    "iso:country":"US",
    "sg:address":"489 Luckney Rd",
    "sg:city":"Brandon",
    "sg:classifiers":[
        {
            "category":"Organizations",
            "subcategory":"Professional Association",
            "type":"Services"
        }
    ],
    "sg:phone":"+1 601 824 9726",
    "sg:postcode":"39042",
    "sg:province":"MS",
    "wof:name":"Taylorsville Water Association",
    "wof:placetype":"venue"
},
  "geometry": {"coordinates":[-90.01584200000001,32.311282],"type":"Point"}
}