{
  "type": "Feature",
  "properties": {
    "addr:full":"2247 Mill Creek Rd Laurel MS 39443",
    "addr:housenumber":"2247",
    "addr:postcode":"39443",
    "addr:street":"Mill Creek Rd",
    "iso:country":"US",
    "sg:address":"2247 Mill Creek Rd",
    "sg:city":"Laurel",
    "sg:classifiers":[
        {
            "category":"Social Services",
            "subcategory":"Child Care",
            "type":"Services"
        }
    ],
    "sg:phone":"+1 601 428 4292",
    "sg:postcode":"39443",
    "sg:province":"MS",
    "wof:name":"Mill Creek Church Of God Daycr",
    "wof:placetype":"venue"
},
  "geometry": {"coordinates":[-88.96070899999999,31.69486],"type":"Point"}
}