{
  "type": "Feature",
  "properties": {
    "iso:country":"US",
    "sg:address":"4120 Dogwood Dr",
    "sg:city":"Jackson",
    "sg:classifiers":[
        {
            "category":"Professional",
            "subcategory":"Business Services",
            "type":"Services"
        }
    ],
    "sg:phone":"+1 601 982 1415",
    "sg:postcode":"39211",
    "sg:province":"MS",
    "wof:name":"Legend Enterprises",
    "wof:placetype":"venue"
},
  "geometry": {"coordinates":[-90.132341,32.347833],"type":"Point"}
}