{
  "type": "Feature",
  "properties": {
    "addr:full":"6767 US Hwy 49 Hattiesburg MS 39402",
    "addr:housenumber":"6767",
    "addr:postcode":"39402",
    "addr:street":"Us Hwy 49",
    "iso:country":"US",
    "sg:address":"6767 US Hwy 49",
    "sg:city":"Hattiesburg",
    "sg:classifiers":[
        {
            "category":"Retail",
            "subcategory":"Auto Rental",
            "type":"Services"
        }
    ],
    "sg:phone":"+1 601 264 1940",
    "sg:postcode":"39402",
    "sg:province":"MS",
    "sg:tags":[
        "renting",
        "automobile"
    ],
    "wof:name":"A Plus Car Rental",
    "wof:placetype":"venue"
},
  "geometry": {"coordinates":[-89.350786,31.361217],"type":"Point"}
}