{
  "type": "Feature",
  "properties": {
    "iso:country":"US",
    "sg:address":"1474 US Hwy 61",
    "sg:city":"Tunica",
    "sg:classifiers":[
        {
            "category":"Autos & Motor Vehicles",
            "subcategory":"Fuel & Gas Station",
            "type":"Retail Goods"
        }
    ],
    "sg:phone":"+1 662 363 2731",
    "sg:postcode":"38676",
    "sg:province":"MS",
    "sg:tags":[
        "oil"
    ],
    "wof:name":"Highway 61 Gulf",
    "wof:placetype":"venue"
},
  "geometry": {"coordinates":[-90.37561100000001,34.691304],"type":"Point"}
}