{
  "type": "Feature",
  "properties": {
    "iso:country":"US",
    "sg:address":"1050 E Peace St",
    "sg:city":"Canton",
    "sg:classifiers":[
        {
            "category":"Food & Beverages",
            "subcategory":"Groceries & Convenience Stores",
            "type":"Retail Goods"
        }
    ],
    "sg:phone":"+1 601 855 9321",
    "sg:postcode":"39046",
    "sg:province":"MS",
    "wof:name":"Save-A-Lot",
    "wof:placetype":"venue"
},
  "geometry": {"coordinates":[-90.011341,32.612167],"type":"Point"}
}