{
  "type": "Feature",
  "properties": {
    "addr:full":"3202 53rd Ave Gulfport MS 39501",
    "addr:housenumber":"3202",
    "addr:postcode":"39501",
    "addr:street":"53Rd Ave",
    "iso:country":"US",
    "sg:address":"3202 53rd Ave",
    "sg:city":"Gulfport",
    "sg:classifiers":[
        {
            "category":"Building & Trades",
            "subcategory":"Landscaping Services",
            "type":"Services"
        }
    ],
    "sg:phone":"+1 228 867 2060",
    "sg:postcode":"39501",
    "sg:province":"MS",
    "sg:tags":[
        "tree"
    ],
    "wof:name":"Acorn Tree Svc",
    "wof:placetype":"venue"
},
  "geometry": {"coordinates":[-89.12501,30.38867],"type":"Point"}
}