{
  "type": "Feature",
  "properties": {
    "addr:full":"68 Northeast Rd Laurel MS 39443",
    "addr:housenumber":"68",
    "addr:postcode":"39443",
    "addr:street":"Northeast Rd",
    "iso:country":"US",
    "sg:address":"68 Northeast Rd",
    "sg:city":"Laurel",
    "sg:classifiers":[
        {
            "category":"Education",
            "subcategory":"School",
            "type":"Public Place"
        }
    ],
    "sg:phone":"+1 601 425 2347",
    "sg:postcode":"39443",
    "sg:province":"MS",
    "wof:name":"Northeast Jones Jr & Sr High",
    "wof:placetype":"venue"
},
  "geometry": {"coordinates":[-89.07824599999999,31.659631],"type":"Point"}
}