{
  "type": "Feature",
  "properties": {
    "iso:country":"US",
    "sg:address":"3537 Bienville Blvd",
    "sg:city":"Ocean Springs",
    "sg:classifiers":[
        {
            "category":"Building & Trades",
            "subcategory":"Construction",
            "type":"Services"
        }
    ],
    "sg:phone":"+1 228 818 5399",
    "sg:postcode":"39564",
    "sg:province":"MS",
    "sg:tags":[
        "tile",
        "dealer"
    ],
    "wof:name":"Steve Nall Tile & Installation",
    "wof:placetype":"venue"
},
  "geometry": {"coordinates":[-88.77340100000001,30.411505],"type":"Point"}
}