{
  "type": "Feature",
  "properties": {
    "addr:full":"100 N Lafayette St Starkville MS 39759",
    "addr:housenumber":"100",
    "addr:postcode":"39759",
    "addr:street":"N Lafayette St",
    "iso:country":"US",
    "sg:address":"100 N Lafayette St",
    "sg:city":"Starkville",
    "sg:classifiers":[
        {
            "category":"Social Services",
            "type":"Services"
        }
    ],
    "sg:phone":"+1 662 323 4433",
    "sg:postcode":"39759",
    "sg:province":"MS",
    "wof:name":"I Care Counseling Service Inc",
    "wof:placetype":"venue"
},
  "geometry": {"coordinates":[-88.815208,33.4649],"type":"Point"}
}