{
  "type": "Feature",
  "properties": {
    "iso:country":"US",
    "sg:address":"603 US Hwy 90",
    "sg:city":"Bay Saint Louis",
    "sg:classifiers":[
        {
            "category":"Building & Trades",
            "subcategory":"Equipment Rental",
            "type":"Services"
        }
    ],
    "sg:phone":"+1 228 466 4441",
    "sg:postcode":"39520",
    "sg:province":"MS",
    "wof:name":"Babers Leasing",
    "wof:placetype":"venue"
},
  "geometry": {"coordinates":[-89.344967,30.317646],"type":"Point"}
}