{
  "type": "Feature",
  "properties": {
    "addr:full":"102 21st St Mccomb MS 39648",
    "addr:housenumber":"102",
    "addr:postcode":"39648",
    "addr:street":"21St St",
    "iso:country":"US",
    "sg:address":"102 21st St",
    "sg:city":"Mccomb",
    "sg:classifiers":[
        {
            "category":"Personal",
            "subcategory":"Beauty Salon",
            "type":"Services"
        }
    ],
    "sg:phone":"+1 601 249 3205",
    "sg:postcode":"39648",
    "sg:province":"MS",
    "sg:tags":[
        "shop"
    ],
    "wof:name":"Styles Unlimited",
    "wof:placetype":"venue"
},
  "geometry": {"coordinates":[-90.450841,31.237283],"type":"Point"}
}