{
  "type": "Feature",
  "properties": {
    "iso:country":"US",
    "sg:address":"313 Concord Dr",
    "sg:city":"Clinton",
    "sg:classifiers":[
        {
            "category":"Professional",
            "subcategory":"Business Services",
            "type":"Services"
        }
    ],
    "sg:phone":"+1 601 924 4372",
    "sg:postcode":"39056",
    "sg:province":"MS",
    "wof:name":"Right Away Technology Inc",
    "wof:placetype":"venue"
},
  "geometry": {"coordinates":[-90.345349,32.315377],"type":"Point"}
}