{
  "type": "Feature",
  "properties": {
    "addr:full":"338 Crawford St Biloxi MS 39530",
    "addr:housenumber":"338",
    "addr:postcode":"39530",
    "addr:street":"Crawford St",
    "iso:country":"US",
    "sg:address":"338 Crawford St",
    "sg:city":"Biloxi",
    "sg:classifiers":[
        {
            "category":"Building & Trades",
            "subcategory":"Construction",
            "type":"Services"
        }
    ],
    "sg:phone":"+1 228 435 2015",
    "sg:postcode":"39530",
    "sg:province":"MS",
    "sg:tags":[
        "painter"
    ],
    "wof:name":"Biloxi Painting & Drywall",
    "wof:placetype":"venue"
},
  "geometry": {"coordinates":[-88.87044899999999,30.405449],"type":"Point"}
}