{
  "type": "Feature",
  "properties": {
    "addr:full":"12472 Dedeaux Rd Gulfport MS 39503",
    "addr:housenumber":"12472",
    "addr:postcode":"39503",
    "addr:street":"Dedeaux Rd",
    "iso:country":"US",
    "sg:address":"12472 Dedeaux Rd",
    "sg:city":"Gulfport",
    "sg:classifiers":[
        {
            "category":"Organizations",
            "subcategory":"Religious Organization",
            "type":"Services"
        }
    ],
    "sg:phone":"+1 228 832 5849",
    "sg:postcode":"39503",
    "sg:province":"MS",
    "sg:tags":[
        "church"
    ],
    "sg:website":"www.ramsaymemorialumc.2itb.com",
    "wof:name":"Ramsay Memorial United Meth",
    "wof:placetype":"venue"
},
  "geometry": {"coordinates":[-89.050023,30.449767],"type":"Point"}
}