{
  "type": "Feature",
  "properties": {
    "addr:full":"204 S Brooks Ave Boyle MS 38730",
    "addr:housenumber":"204",
    "addr:postcode":"38730",
    "addr:street":"S Brooks Ave",
    "iso:country":"US",
    "sg:address":"204 S Brooks Ave",
    "sg:city":"Boyle",
    "sg:classifiers":[
        {
            "category":"Building & Trades",
            "subcategory":"Construction",
            "type":"Services"
        }
    ],
    "sg:phone":"+1 662 846 6133",
    "sg:postcode":"38730",
    "sg:province":"MS",
    "sg:tags":[
        "roofing",
        "contractor"
    ],
    "wof:name":"Clinton Powell Roofing & Const",
    "wof:placetype":"venue"
},
  "geometry": {"coordinates":[-90.728309,33.703304],"type":"Point"}
}