{
  "type": "Feature",
  "properties": {
    "iso:country":"US",
    "sg:address":"303 Lakeside Dr",
    "sg:city":"Brandon",
    "sg:classifiers":[
        {
            "category":"Real Estate",
            "subcategory":"Real Estate Agent",
            "type":"Services"
        }
    ],
    "sg:phone":"+1 601 992 0892",
    "sg:postcode":"39047",
    "sg:province":"MS",
    "wof:name":"Merck Team Realty Inc",
    "wof:placetype":"venue"
},
  "geometry": {"coordinates":[-90.032031,32.381721],"type":"Point"}
}