{
  "type": "Feature",
  "properties": {
    "addr:full":"3680 Terry Rd Jackson MS 39212",
    "addr:housenumber":"3680",
    "addr:postcode":"39212",
    "addr:street":"Terry Rd",
    "iso:country":"US",
    "sg:address":"3680 Terry Rd",
    "sg:city":"Jackson",
    "sg:classifiers":[
        {
            "category":"Government",
            "subcategory":"Fire Station",
            "type":"Public Place"
        }
    ],
    "sg:phone":"+1 601 960 2111",
    "sg:postcode":"39212",
    "sg:province":"MS",
    "sg:tags":[
        "protection"
    ],
    "wof:name":"Jackson Fire Department",
    "wof:placetype":"venue"
},
  "geometry": {"coordinates":[-90.234503,32.234848],"type":"Point"}
}