{
  "type": "Feature",
  "properties": {
    "iso:country":"US",
    "sg:address":"9911 Janice Brooklyn Rd",
    "sg:city":"Brooklyn",
    "sg:classifiers":[
        {
            "category":"Government",
            "subcategory":"Fire Station",
            "type":"Public Place"
        }
    ],
    "sg:phone":"+1 601 598 2300",
    "sg:postcode":"39425",
    "sg:province":"MS",
    "sg:tags":[
        "protection"
    ],
    "wof:name":"Janice Fire House",
    "wof:placetype":"venue"
},
  "geometry": {"coordinates":[-89.06388800000001,31.034056],"type":"Point"}
}