{
  "type": "Feature",
  "properties": {
    "iso:country":"US",
    "sg:address":"1404 Old Aberdeen Rd",
    "sg:city":"Columbus",
    "sg:classifiers":[
        {
            "category":"Shopping",
            "subcategory":"Computers & Home Electronics",
            "type":"Retail Goods"
        }
    ],
    "sg:phone":"+1 662 327 5824",
    "sg:postcode":"39705",
    "sg:province":"MS",
    "sg:tags":[
        "equipment",
        "electronic",
        "supply"
    ],
    "wof:name":"Radio Shack",
    "wof:placetype":"venue"
},
  "geometry": {"coordinates":[-88.433204,33.517549],"type":"Point"}
}