{
  "type": "Feature",
  "properties": {
    "iso:country":"US",
    "sg:address":"1400 Clayton Ave",
    "sg:city":"Tupelo",
    "sg:classifiers":[
        {
            "category":"Organizations",
            "subcategory":"Religious Organization",
            "type":"Services"
        }
    ],
    "sg:phone":"+1 662 842 6522",
    "sg:postcode":"38804",
    "sg:province":"MS",
    "wof:name":"Saint Luke Untd Methdst Church",
    "wof:placetype":"venue"
},
  "geometry": {"coordinates":[-88.725515,34.276288],"type":"Point"}
}