{
  "type": "Feature",
  "properties": {
    "iso:country":"US",
    "sg:address":"113 Dover Ct",
    "sg:city":"Starkville",
    "sg:classifiers":[
        {
            "category":"Retail",
            "subcategory":"Auto Repair",
            "type":"Services"
        }
    ],
    "sg:phone":"+1 662 323 0004",
    "sg:postcode":"39759",
    "sg:province":"MS",
    "sg:tags":[
        "glass",
        "replacement"
    ],
    "wof:name":"Windshield Doctor",
    "wof:placetype":"venue"
},
  "geometry": {"coordinates":[-88.818201,33.422803],"type":"Point"}
}