{
  "type": "Feature",
  "properties": {
    "iso:country":"US",
    "sg:address":"4526 Office Park Dr",
    "sg:city":"Jackson",
    "sg:classifiers":[
        {
            "category":"Building & Trades",
            "subcategory":"Construction",
            "type":"Services"
        }
    ],
    "sg:phone":"+1 601 982 7788",
    "sg:postcode":"39206",
    "sg:province":"MS",
    "sg:tags":[
        "general",
        "contractor"
    ],
    "wof:name":"ERS",
    "wof:placetype":"venue"
},
  "geometry": {"coordinates":[-90.15367500000001,32.355331],"type":"Point"}
}