{
  "type": "Feature",
  "properties": {
    "addr:full":"2945 Randolph St Jackson MS 39213",
    "addr:housenumber":"2945",
    "addr:postcode":"39213",
    "addr:street":"Randolph St",
    "iso:country":"US",
    "sg:address":"2945 Randolph St",
    "sg:city":"Jackson",
    "sg:classifiers":[
        {
            "category":"Organizations",
            "subcategory":"Religious Organization",
            "type":"Services"
        }
    ],
    "sg:phone":"+1 601 362 8395",
    "sg:postcode":"39213",
    "sg:province":"MS",
    "sg:tags":[
        "church"
    ],
    "wof:name":"Virden Grove Baptist Church",
    "wof:placetype":"venue"
},
  "geometry": {"coordinates":[-90.19008700000001,32.339292],"type":"Point"}
}