{
  "type": "Feature",
  "properties": {
    "iso:country":"US",
    "sg:address":"313 S 40th Ave",
    "sg:city":"Hattiesburg",
    "sg:classifiers":[
        {
            "category":"Health Services",
            "subcategory":"Doctor",
            "type":"Services"
        }
    ],
    "sg:phone":"+1 601 264 5100",
    "sg:postcode":"39402",
    "sg:province":"MS",
    "sg:tags":[
        "dentist"
    ],
    "wof:name":"First Dental",
    "wof:placetype":"venue"
},
  "geometry": {"coordinates":[-89.347999,31.322107],"type":"Point"}
}