{
  "type": "Feature",
  "properties": {
    "iso:country":"US",
    "sg:address":"28 Lake Rd",
    "sg:city":"Dennis",
    "sg:classifiers":[
        {
            "category":"Building & Trades",
            "subcategory":"Landscaping Services",
            "type":"Services"
        }
    ],
    "sg:phone":"+1 662 454 9587",
    "sg:postcode":"38843",
    "sg:province":"MS",
    "sg:tags":[
        "lawn",
        "maintenance",
        "grounds"
    ],
    "wof:name":"R & D Maintenance Svc Inc",
    "wof:placetype":"venue"
},
  "geometry": {"coordinates":[-88.39963,34.262385],"type":"Point"}
}