{
  "type": "Feature",
  "properties": {
    "iso:country":"US",
    "sg:address":"112 Pine Ridge Cir",
    "sg:city":"Brandon",
    "sg:classifiers":[
        {
            "category":"Professional",
            "subcategory":"Management & Consulting",
            "type":"Services"
        }
    ],
    "sg:phone":"+1 601 829 0431",
    "sg:postcode":"39047",
    "sg:province":"MS",
    "wof:name":"Al W Goodman",
    "wof:placetype":"venue"
},
  "geometry": {"coordinates":[-89.957635,32.395201],"type":"Point"}
}