{
  "type": "Feature",
  "properties": {
    "iso:country":"US",
    "sg:address":"710 James St",
    "sg:city":"Hattiesburg",
    "sg:classifiers":[
        {
            "category":"Retail",
            "subcategory":"Car Wash",
            "type":"Services"
        }
    ],
    "sg:phone":"+1 601 544 6789",
    "sg:postcode":"39401",
    "sg:province":"MS",
    "sg:tags":[
        "polishing",
        "carwash",
        "washing"
    ],
    "wof:name":"Fine Point Detail & Accessorie",
    "wof:placetype":"venue"
},
  "geometry": {"coordinates":[-89.28505,31.316535],"type":"Point"}
}