{
  "type": "Feature",
  "properties": {
    "iso:country":"US",
    "sg:address":"101 Mimosa St",
    "sg:city":"Booneville",
    "sg:classifiers":[
        {
            "category":"Health Services",
            "subcategory":"Doctor",
            "type":"Services"
        }
    ],
    "sg:phone":"+1 662 728 8171",
    "sg:postcode":"38829",
    "sg:province":"MS",
    "sg:tags":[
        "dentist"
    ],
    "wof:name":"Goodwin & Austin Family Dnstry",
    "wof:placetype":"venue"
},
  "geometry": {"coordinates":[-88.554412,34.655803],"type":"Point"}
}