{
  "type": "Feature",
  "properties": {
    "iso:country":"US",
    "sg:address":"14881 John Clark Rd",
    "sg:city":"Gulfport",
    "sg:classifiers":[
        {
            "category":"Wholesale",
            "subcategory":"Construction Materials",
            "type":"Manufacturing & Wholesale Goods"
        }
    ],
    "sg:phone":"+1 228 297 9897",
    "sg:postcode":"39503",
    "sg:province":"MS",
    "sg:tags":[
        "fence"
    ],
    "wof:name":"Custom Fencing",
    "wof:placetype":"venue"
},
  "geometry": {"coordinates":[-89.15156,30.491569],"type":"Point"}
}