{
  "type": "Feature",
  "properties": {
    "iso:country":"US",
    "sg:address":"2900 Hwy 39 N",
    "sg:city":"Meridian",
    "sg:classifiers":[
        {
            "category":"Autos & Motor Vehicles",
            "subcategory":"Automobile Sales",
            "type":"Retail Goods"
        }
    ],
    "sg:phone":"+1 601 485 1620",
    "sg:postcode":"39301",
    "sg:province":"MS",
    "sg:tags":[
        "car",
        "dealer"
    ],
    "sg:website":"www.johnsontoyota.com",
    "wof:name":"John O'Neil Johnson Toyota",
    "wof:placetype":"venue"
},
  "geometry": {"coordinates":[-88.68524499999999,32.386581],"type":"Point"}
}