{
  "type": "Feature",
  "properties": {
    "iso:country":"US",
    "sg:address":"401 Arrow Dr",
    "sg:city":"Clinton",
    "sg:classifiers":[
        {
            "category":"Education",
            "subcategory":"School",
            "type":"Public Place"
        }
    ],
    "sg:phone":"+1 601 924 5656",
    "sg:postcode":"39056",
    "sg:province":"MS",
    "wof:name":"Clinton High School",
    "wof:placetype":"venue"
},
  "geometry": {"coordinates":[-90.31230499999999,32.362248],"type":"Point"}
}