{
  "type": "Feature",
  "properties": {
    "iso:country":"US",
    "sg:address":"111 Kaiser Lake Rd",
    "sg:city":"Natchez",
    "sg:classifiers":[
        {
            "category":"Freight",
            "type":"Transportation"
        }
    ],
    "sg:phone":"+1 601 445 0508",
    "sg:postcode":"39120",
    "sg:province":"MS",
    "sg:tags":[
        "distance",
        "without",
        "storage",
        "long",
        "trucking"
    ],
    "wof:name":"Jay Dee Transport Inc",
    "wof:placetype":"venue"
},
  "geometry": {"coordinates":[-91.27037,31.579819],"type":"Point"}
}