{
  "type": "Feature",
  "properties": {
    "addr:full":"271 Mill Ln Centreville MS 39631",
    "addr:housenumber":"271",
    "addr:postcode":"39631",
    "addr:street":"Mill Ln",
    "iso:country":"US",
    "sg:address":"271 Mill Ln",
    "sg:city":"Centreville",
    "sg:classifiers":[
        {
            "category":"Museum",
            "type":"Entertainment"
        }
    ],
    "sg:phone":"+1 601 888 6788",
    "sg:postcode":"39631",
    "sg:province":"MS",
    "sg:tags":[
        "gallery"
    ],
    "wof:name":"UDC",
    "wof:placetype":"venue"
},
  "geometry": {"coordinates":[-91.098833,31.085657],"type":"Point"}
}