{
  "type": "Feature",
  "properties": {
    "iso:country":"US",
    "sg:address":"1220 Jefferson Ave",
    "sg:city":"Oxford",
    "sg:classifiers":[
        {
            "category":"Professional",
            "subcategory":"Business Services",
            "type":"Services"
        }
    ],
    "sg:phone":"+1 662 234 1444",
    "sg:postcode":"38655",
    "sg:province":"MS",
    "sg:tags":[
        "interior",
        "design",
        "furniture"
    ],
    "wof:name":"Inside Oxford Inc",
    "wof:placetype":"venue"
},
  "geometry": {"coordinates":[-89.51805899999999,34.368537],"type":"Point"}
}