{
  "type": "Feature",
  "properties": {
    "iso:country":"US",
    "sg:address":"520 E Pine Ave",
    "sg:city":"Wiggins",
    "sg:classifiers":[
        {
            "category":"Organizations",
            "subcategory":"Religious Organization",
            "type":"Services"
        }
    ],
    "sg:phone":"+1 601 928 4880",
    "sg:postcode":"39577",
    "sg:province":"MS",
    "sg:tags":[
        "church"
    ],
    "wof:name":"First United Methodist Church",
    "wof:placetype":"venue"
},
  "geometry": {"coordinates":[-89.132381,30.857724],"type":"Point"}
}