{
  "type": "Feature",
  "properties": {
    "iso:country":"US",
    "sg:address":"2060 Jerry Clower Blvd",
    "sg:city":"Yazoo City",
    "sg:classifiers":[
        {
            "category":"Retail",
            "subcategory":"Laundry & Dry Cleaning",
            "type":"Services"
        }
    ],
    "sg:phone":"+1 662 716 3005",
    "sg:postcode":"39194",
    "sg:province":"MS",
    "sg:tags":[
        "power"
    ],
    "wof:name":"Sunset Cleaners",
    "wof:placetype":"venue"
},
  "geometry": {"coordinates":[-90.388319,32.886127],"type":"Point"}
}