{
  "type": "Feature",
  "properties": {
    "iso:country":"US",
    "sg:address":"225 Martin Luther King Jr Dr",
    "sg:city":"Batesville",
    "sg:classifiers":[
        {
            "category":"Retail",
            "subcategory":"Auto Repair",
            "type":"Services"
        }
    ],
    "sg:phone":"+1 662 563 7500",
    "sg:postcode":"38606",
    "sg:province":"MS",
    "sg:tags":[
        "truck"
    ],
    "wof:name":"Unitech Auto Tire Truck Svc",
    "wof:placetype":"venue"
},
  "geometry": {"coordinates":[-89.964748,34.323564],"type":"Point"}
}