{
  "type": "Feature",
  "properties": {
    "iso:country":"US",
    "sg:address":"3709 W Main St",
    "sg:city":"Tupelo",
    "sg:classifiers":[
        {
            "category":"Home & Garden",
            "subcategory":"Carpets & Floor Coverings",
            "type":"Retail Goods"
        }
    ],
    "sg:phone":"+1 662 844 1165",
    "sg:postcode":"38801",
    "sg:province":"MS",
    "sg:tags":[
        "installs"
    ],
    "wof:name":"Montgomery Car Wash",
    "wof:placetype":"venue"
},
  "geometry": {"coordinates":[-88.767476,34.250064],"type":"Point"}
}