{
  "type": "Feature",
  "properties": {
    "addr:full":"713 E North St Pass Christian MS 39571",
    "addr:housenumber":"713",
    "addr:postcode":"39571",
    "addr:street":"E North St",
    "iso:country":"US",
    "sg:address":"713 E North St",
    "sg:city":"Pass Christian",
    "sg:classifiers":[
        {
            "category":"Building & Trades",
            "subcategory":"Construction",
            "type":"Services"
        }
    ],
    "sg:phone":"+1 228 452 0804",
    "sg:postcode":"39571",
    "sg:province":"MS",
    "sg:tags":[
        "heavy"
    ],
    "wof:name":"Matthews Marine Inc",
    "wof:placetype":"venue"
},
  "geometry": {"coordinates":[-89.22888399999999,30.3329],"type":"Point"}
}