{
  "type": "Feature",
  "properties": {
    "iso:country":"US",
    "sg:address":"511 Red Oak Dr",
    "sg:city":"Gulfport",
    "sg:classifiers":[
        {
            "category":"Real Estate",
            "subcategory":"Architect",
            "type":"Services"
        }
    ],
    "sg:phone":"+1 228 896 3805",
    "sg:postcode":"39507",
    "sg:province":"MS",
    "wof:name":"Don D Leopard",
    "wof:placetype":"venue"
},
  "geometry": {"coordinates":[-89.008807,30.398083],"type":"Point"}
}