{
  "type": "Feature",
  "properties": {
    "iso:country":"US",
    "sg:address":"961 Hwy 80 E",
    "sg:city":"Clinton",
    "sg:classifiers":[
        {
            "category":"Shopping",
            "subcategory":"Computers & Home Electronics",
            "type":"Retail Goods"
        }
    ],
    "sg:phone":"+1 601 925 5650",
    "sg:postcode":"39056",
    "sg:province":"MS",
    "sg:tags":[
        "equipment",
        "dealer"
    ],
    "wof:name":"Bridges For Learning",
    "wof:placetype":"venue"
},
  "geometry": {"coordinates":[-90.29689,32.32506],"type":"Point"}
}