{
  "type": "Feature",
  "properties": {
    "iso:country":"US",
    "sg:address":"745 W Madison St",
    "sg:city":"Houston",
    "sg:classifiers":[
        {
            "category":"Autos & Motor Vehicles",
            "subcategory":"Auto Supplies",
            "type":"Retail Goods"
        }
    ],
    "sg:phone":"+1 662 456 4350",
    "sg:postcode":"38851",
    "sg:province":"MS",
    "sg:tags":[
        "tire"
    ],
    "wof:name":"Wofford Tire Co",
    "wof:placetype":"venue"
},
  "geometry": {"coordinates":[-89.02393600000001,33.894494],"type":"Point"}
}