{
  "type": "Feature",
  "properties": {
    "addr:full":"426 Ridgewood Dr Vicksburg MS 39180",
    "addr:housenumber":"426",
    "addr:postcode":"39180",
    "addr:street":"Ridgewood Dr",
    "iso:country":"US",
    "sg:address":"426 Ridgewood Dr",
    "sg:city":"Vicksburg",
    "sg:classifiers":[
        {
            "category":"Professional",
            "type":"Services"
        }
    ],
    "sg:phone":"+1 601 636 6826",
    "sg:postcode":"39180",
    "sg:province":"MS",
    "wof:name":"L&W Services Inc",
    "wof:placetype":"venue"
},
  "geometry": {"coordinates":[-90.83763399999999,32.319459],"type":"Point"}
}