{
  "type": "Feature",
  "properties": {
    "iso:country":"US",
    "sg:address":"5882 US Hwy 11",
    "sg:city":"Purvis",
    "sg:classifiers":[
        {
            "category":"Wholesale",
            "subcategory":"Farm Supplies",
            "type":"Manufacturing & Wholesale Goods"
        }
    ],
    "sg:phone":"+1 601 794 6079",
    "sg:postcode":"39475",
    "sg:province":"MS",
    "sg:tags":[
        "feed"
    ],
    "wof:name":"Fowler Feed & Seed",
    "wof:placetype":"venue"
},
  "geometry": {"coordinates":[-89.40548,31.138992],"type":"Point"}
}