{
  "type": "Feature",
  "properties": {
    "iso:country":"US",
    "sg:address":"257 Temple Rd",
    "sg:city":"Petal",
    "sg:classifiers":[
        {
            "category":"Communications",
            "type":"Services"
        }
    ],
    "sg:phone":"+1 601 544 3158",
    "sg:postcode":"39465",
    "sg:province":"MS",
    "wof:name":"Spectra Site Communications",
    "wof:placetype":"venue"
},
  "geometry": {"coordinates":[-89.16494,31.346453],"type":"Point"}
}