{
  "type": "Feature",
  "properties": {
    "iso:country":"US",
    "sg:address":"824 E Main St",
    "sg:city":"Fulton",
    "sg:classifiers":[
        {
            "category":"Organizations",
            "subcategory":"Religious Organization",
            "type":"Services"
        }
    ],
    "sg:phone":"+1 662 862 4506",
    "sg:postcode":"38843",
    "sg:province":"MS",
    "sg:tags":[
        "church"
    ],
    "wof:name":"Fulton Free Will Baptist Chr",
    "wof:placetype":"venue"
},
  "geometry": {"coordinates":[-88.3866,34.274262],"type":"Point"}
}