{
  "type": "Feature",
  "properties": {
    "iso:country":"US",
    "sg:address":"103 Grosvenor Pl",
    "sg:city":"Waveland",
    "sg:classifiers":[
        {
            "category":"Building & Trades",
            "subcategory":"Construction",
            "type":"Services"
        }
    ],
    "sg:phone":"+1 228 463 9017",
    "sg:postcode":"39576",
    "sg:province":"MS",
    "sg:tags":[
        "house"
    ],
    "wof:name":"Benchmark Construction",
    "wof:placetype":"venue"
},
  "geometry": {"coordinates":[-89.362562,30.290254],"type":"Point"}
}