{
  "type": "Feature",
  "properties": {
    "addr:full":"14436 Hudson Krohn Rd Biloxi MS 39532",
    "addr:housenumber":"14436",
    "addr:postcode":"39532",
    "addr:street":"Hudson Krohn Rd",
    "iso:country":"US",
    "sg:address":"14436 Hudson Krohn Rd",
    "sg:city":"Biloxi",
    "sg:classifiers":[
        {
            "category":"Organizations",
            "subcategory":"Religious Organization",
            "type":"Services"
        }
    ],
    "sg:phone":"+1 228 392 3532",
    "sg:postcode":"39532",
    "sg:province":"MS",
    "wof:name":"Prince Of Peace Baptist Church",
    "wof:placetype":"venue"
},
  "geometry": {"coordinates":[-88.944863,30.500832],"type":"Point"}
}