{
  "type": "Feature",
  "properties": {
    "iso:country":"US",
    "sg:address":"407 Battleground Dr",
    "sg:city":"Iuka",
    "sg:classifiers":[
        {
            "category":"Home & Garden",
            "subcategory":"Furniture",
            "type":"Retail Goods"
        }
    ],
    "sg:phone":"+1 662 423 6809",
    "sg:postcode":"38852",
    "sg:province":"MS",
    "wof:name":"Iuka Furniture Outlet",
    "wof:placetype":"venue"
},
  "geometry": {"coordinates":[-88.19872700000001,34.810573],"type":"Point"}
}