{
  "type": "Feature",
  "properties": {
    "iso:country":"US",
    "sg:address":"1863 Popps Ferry Rd",
    "sg:city":"Biloxi",
    "sg:classifiers":[
        {
            "category":"Insurance",
            "subcategory":"Insurance Agent",
            "type":"Services"
        }
    ],
    "sg:phone":"+1 228 388 6646",
    "sg:postcode":"39532",
    "sg:province":"MS",
    "wof:name":"State Farm Insurance",
    "wof:placetype":"venue"
},
  "geometry": {"coordinates":[-88.944727,30.442517],"type":"Point"}
}