{
  "type": "Feature",
  "properties": {
    "addr:full":"310 E Main St Tchula MS 39169",
    "addr:housenumber":"310",
    "addr:postcode":"39169",
    "addr:street":"E Main St",
    "iso:country":"US",
    "sg:address":"310 E Main St",
    "sg:city":"Tchula",
    "sg:classifiers":[
        {
            "category":"Organizations",
            "subcategory":"Religious Organization",
            "type":"Services"
        }
    ],
    "sg:phone":"+1 662 235 5462",
    "sg:postcode":"39169",
    "sg:province":"MS",
    "sg:tags":[
        "church"
    ],
    "wof:name":"First Baptist Church",
    "wof:placetype":"venue"
},
  "geometry": {"coordinates":[-90.217809,33.179873],"type":"Point"}
}