{
  "type": "Feature",
  "properties": {
    "iso:country":"US",
    "sg:address":"400 Main St",
    "sg:city":"Walnut",
    "sg:classifiers":[
        {
            "category":"Professional",
            "subcategory":"Accounting & Tax Preparation",
            "type":"Services"
        }
    ],
    "sg:phone":"+1 662 223 5318",
    "sg:postcode":"38683",
    "sg:province":"MS",
    "sg:tags":[
        "return",
        "filing"
    ],
    "wof:name":"Phillips Tax Svc",
    "wof:placetype":"venue"
},
  "geometry": {"coordinates":[-88.900566,34.942787],"type":"Point"}
}