{
  "type": "Feature",
  "properties": {
    "addr:full":"118 Caldwell Dr Hazlehurst MS 39083",
    "addr:housenumber":"118",
    "addr:postcode":"39083",
    "addr:street":"Caldwell Dr Hazlehurst",
    "iso:country":"US",
    "sg:address":"118 Caldwell Dr",
    "sg:city":"Hazlehurst",
    "sg:classifiers":[
        {
            "category":"Insurance",
            "subcategory":"Insurance Agent",
            "type":"Services"
        }
    ],
    "sg:phone":"+1 601 894 8113",
    "sg:postcode":"39083",
    "sg:province":"MS",
    "wof:name":"Mitchell Insurance",
    "wof:placetype":"venue"
},
  "geometry": {"coordinates":[-90.396163,31.860336],"type":"Point"}
}