{
  "type": "Feature",
  "properties": {
    "addr:full":"2080 Smithtown Rd Tylertown MS 39666",
    "addr:postcode":"2080;39666",
    "addr:street":"Smithtown Rd",
    "iso:country":"US",
    "sg:address":"2080 Smithtown Rd",
    "sg:city":"Tylertown",
    "sg:classifiers":[
        {
            "category":"Professional",
            "subcategory":"Management & Consulting",
            "type":"Services"
        }
    ],
    "sg:phone":"+1 601 684 9207",
    "sg:postcode":"39666",
    "sg:province":"MS",
    "sg:tags":[
        "retail",
        "direct",
        "sales"
    ],
    "wof:name":"3ds",
    "wof:placetype":"venue"
},
  "geometry": {"coordinates":[-90.2732,31.23867],"type":"Point"}
}