{
  "type": "Feature",
  "properties": {
    "addr:full":"6341 Ridgewood Rd Horn Lake MS 38637",
    "addr:housenumber":"6341",
    "addr:postcode":"38637",
    "addr:street":"Ridgewood Rd",
    "iso:country":"US",
    "sg:address":"6341 Ridgewood Rd",
    "sg:city":"Horn Lake",
    "sg:classifiers":[
        {
            "category":"Social Services",
            "type":"Services"
        }
    ],
    "sg:phone":"+1 662 393 4654",
    "sg:postcode":"38637",
    "sg:province":"MS",
    "sg:tags":[
        "individual",
        "family"
    ],
    "wof:name":"Desoto Families First Parent",
    "wof:placetype":"venue"
},
  "geometry": {"coordinates":[-90.040126,34.954722],"type":"Point"}
}