{
  "type": "Feature",
  "properties": {
    "addr:full":"51 Pebble Hill Dr Brandon MS 39042",
    "addr:housenumber":"51",
    "addr:postcode":"39042",
    "addr:street":"Pebble Hill Dr",
    "iso:country":"US",
    "sg:address":"51 Pebble Hill Dr",
    "sg:city":"Brandon",
    "sg:classifiers":[
        {
            "category":"Banks & Credit Unions",
            "subcategory":"Financial Services",
            "type":"Services"
        }
    ],
    "sg:phone":"+1 601 825 8691",
    "sg:postcode":"39042",
    "sg:province":"MS",
    "sg:tags":[
        "trust",
        "management"
    ],
    "wof:name":"Barrentine Partners LLP",
    "wof:placetype":"venue"
},
  "geometry": {"coordinates":[-90.019567,32.296662],"type":"Point"}
}