{
  "type": "Feature",
  "properties": {
    "addr:full":"636 US Hwy 90 Waveland MS 39576",
    "addr:housenumber":"636",
    "addr:postcode":"39576",
    "addr:street":"Us Hwy 90",
    "iso:country":"US",
    "sg:address":"636 US Hwy 90",
    "sg:city":"Waveland",
    "sg:classifiers":[
        {
            "category":"Manufacturing",
            "subcategory":"Chemicals & Compounds",
            "type":"Manufacturing & Wholesale Goods"
        }
    ],
    "sg:phone":"+1 228 466 0966",
    "sg:postcode":"39576",
    "sg:province":"MS",
    "sg:tags":[
        "plastic"
    ],
    "wof:name":"Mississippi Polymer",
    "wof:placetype":"venue"
},
  "geometry": {"coordinates":[-89.395326,30.300416],"type":"Point"}
}