{
  "type": "Feature",
  "properties": {
    "addr:full":"2371 Trafalgar Dr Biloxi MS 39531",
    "addr:housenumber":"2371",
    "addr:postcode":"39531",
    "addr:street":"Trafalgar Dr",
    "iso:country":"US",
    "sg:address":"2371 Trafalgar Dr",
    "sg:city":"Biloxi",
    "sg:classifiers":[
        {
            "category":"Wholesale",
            "subcategory":"Machinery & Supplies",
            "type":"Manufacturing & Wholesale Goods"
        }
    ],
    "sg:phone":"+1 228 385 2847",
    "sg:postcode":"39531",
    "sg:province":"MS",
    "sg:tags":[
        "equipment"
    ],
    "wof:name":"O E Barron",
    "wof:placetype":"venue"
},
  "geometry": {"coordinates":[-88.974541,30.405621],"type":"Point"}
}