{
  "type": "Feature",
  "properties": {
    "iso:country":"US",
    "sg:address":"1201 Ocean View Dr",
    "sg:city":"Gulfport",
    "sg:classifiers":[
        {
            "category":"Professional",
            "subcategory":"Research",
            "type":"Services"
        }
    ],
    "sg:phone":"+1 228 896 7155",
    "sg:postcode":"39507",
    "sg:province":"MS",
    "sg:tags":[
        "environmental",
        "ecological"
    ],
    "wof:name":"Envirosync",
    "wof:placetype":"venue"
},
  "geometry": {"coordinates":[-89.028401,30.383833],"type":"Point"}
}