{
  "type": "Feature",
  "properties": {
    "iso:country":"US",
    "sg:address":"4915 I- 55 N",
    "sg:city":"Jackson",
    "sg:classifiers":[
        {
            "category":"Banks & Credit Unions",
            "subcategory":"Bank",
            "type":"Services"
        }
    ],
    "sg:phone":"+1 601 362 3095",
    "sg:postcode":"39206",
    "sg:province":"MS",
    "sg:tags":[
        "mortgage"
    ],
    "wof:name":"Plaza Mortgage",
    "wof:placetype":"venue"
},
  "geometry": {"coordinates":[-90.150882,32.363079],"type":"Point"}
}