{
  "type": "Feature",
  "properties": {
    "iso:country":"US",
    "sg:address":"1900 Hwy 80 W",
    "sg:city":"Jackson",
    "sg:classifiers":[
        {
            "category":"Shopping",
            "type":"Retail Goods"
        }
    ],
    "sg:phone":"+1 601 969 6888",
    "sg:postcode":"39204",
    "sg:province":"MS",
    "sg:tags":[
        "cosmetic",
        "perfume"
    ],
    "wof:name":"AAA Cosmetics",
    "wof:placetype":"venue"
},
  "geometry": {"coordinates":[-90.21692899999999,32.287719],"type":"Point"}
}