{
  "type": "Feature",
  "properties": {
    "iso:country":"US",
    "sg:address":"1815 Hwy 82 W",
    "sg:city":"Greenwood",
    "sg:classifiers":[
        {
            "category":"Travel",
            "subcategory":"Hotels & Motels",
            "type":"Entertainment"
        }
    ],
    "sg:phone":"+1 662 455 7985",
    "sg:postcode":"38930",
    "sg:province":"MS",
    "wof:name":"Hampton Inn Of Greenwood",
    "wof:placetype":"venue"
},
  "geometry": {"coordinates":[-90.215678,33.526973],"type":"Point"}
}