{
  "type": "Feature",
  "properties": {
    "addr:full":"1724 Bailey Ave Jackson MS 39203",
    "addr:housenumber":"1724",
    "addr:postcode":"39203",
    "addr:street":"Bailey Ave",
    "iso:country":"US",
    "sg:address":"1724 Bailey Ave",
    "sg:city":"Jackson",
    "sg:classifiers":[
        {
            "category":"Home & Garden",
            "subcategory":"Furniture",
            "type":"Retail Goods"
        }
    ],
    "sg:phone":"+1 601 355 2869",
    "sg:postcode":"39203",
    "sg:province":"MS",
    "wof:name":"Bob's Furniture",
    "wof:placetype":"venue"
},
  "geometry": {"coordinates":[-90.194154,32.322091],"type":"Point"}
}