{
  "type": "Feature",
  "properties": {
    "iso:country":"US",
    "sg:address":"3121 Halls Ferry Rd",
    "sg:city":"Vicksburg",
    "sg:classifiers":[
        {
            "category":"Restaurant",
            "type":"Food & Drink"
        }
    ],
    "sg:menulink":"http://www.allmenus.com/ms/vicksburg/190970-burger-king/menu/",
    "sg:phone":"+1 601 638 7294",
    "sg:postcode":"39180",
    "sg:province":"MS",
    "sg:tags":[
        "burger",
        "american"
    ],
    "wof:name":"Burger King",
    "wof:placetype":"venue"
},
  "geometry": {"coordinates":[-90.876605,32.323734],"type":"Point"}
}