{
  "type": "Feature",
  "properties": {
    "iso:country":"US",
    "sg:address":"101 Cypress St",
    "sg:city":"Quitman",
    "sg:classifiers":[
        {
            "category":"Wholesale",
            "subcategory":"Machinery & Supplies",
            "type":"Manufacturing & Wholesale Goods"
        }
    ],
    "sg:phone":"+1 601 776 6888",
    "sg:postcode":"39355",
    "sg:province":"MS",
    "sg:tags":[
        "salon",
        "beauty"
    ],
    "wof:name":"Lisa's Beauty Supply",
    "wof:placetype":"venue"
},
  "geometry": {"coordinates":[-88.72928899999999,32.04688],"type":"Point"}
}