{
  "type": "Feature",
  "properties": {
    "addr:full":"409 Grandview Ct Jackson MS 39208",
    "addr:housenumber":"409",
    "addr:postcode":"39208",
    "addr:street":"Grandview Ct",
    "iso:country":"US",
    "sg:address":"409 Grandview Ct",
    "sg:city":"Jackson",
    "sg:classifiers":[
        {
            "category":"Professional",
            "subcategory":"Business Services",
            "type":"Services"
        }
    ],
    "sg:phone":"+1 601 936 0975",
    "sg:postcode":"39208",
    "sg:province":"MS",
    "sg:tags":[
        "paging",
        "signaling"
    ],
    "wof:name":"Arch Paging",
    "wof:placetype":"venue"
},
  "geometry": {"coordinates":[-90.051582,32.254085],"type":"Point"}
}