{
  "type": "Feature",
  "properties": {
    "iso:country":"US",
    "sg:address":"40 Blackwell Rd",
    "sg:city":"Picayune",
    "sg:classifiers":[
        {
            "category":"Arts & Performance",
            "subcategory":"Theater",
            "type":"Entertainment"
        }
    ],
    "sg:phone":"+1 601 749 9890",
    "sg:postcode":"39466",
    "sg:province":"MS",
    "sg:tags":[
        "group"
    ],
    "wof:name":"Country Music By Dianne",
    "wof:placetype":"venue"
},
  "geometry": {"coordinates":[-89.784828,30.566908],"type":"Point"}
}