{
  "type": "Feature",
  "properties": {
    "addr:full":"1633 Wiltshire Blvd Biloxi MS 39531",
    "addr:housenumber":"1633",
    "addr:postcode":"39531",
    "addr:street":"Wiltshire Blvd",
    "iso:country":"US",
    "sg:address":"1633 Wiltshire Blvd",
    "sg:city":"Biloxi",
    "sg:classifiers":[
        {
            "category":"Organizations",
            "subcategory":"Professional Association",
            "type":"Services"
        }
    ],
    "sg:phone":"+1 228 432 7228",
    "sg:postcode":"39531",
    "sg:province":"MS",
    "wof:name":"National Society Daughter",
    "wof:placetype":"venue"
},
  "geometry": {"coordinates":[-88.93464299999999,30.406683],"type":"Point"}
}