{
  "type": "Feature",
  "properties": {
    "addr:full":"1900 N West St Jackson MS 39202",
    "addr:housenumber":"1900",
    "addr:postcode":"39202",
    "addr:street":"N West St",
    "iso:country":"US",
    "sg:address":"1900 N West St",
    "sg:city":"Jackson",
    "sg:classifiers":[
        {
            "category":"Social Services",
            "type":"Services"
        }
    ],
    "sg:phone":"+1 601 352 7784",
    "sg:postcode":"39202",
    "sg:province":"MS",
    "sg:tags":[
        "organization",
        "welfare"
    ],
    "sg:website":"www.mchscares.org",
    "wof:name":"Mississippi Children Home",
    "wof:placetype":"venue"
},
  "geometry": {"coordinates":[-90.182165,32.32452],"type":"Point"}
}