{
  "type": "Feature",
  "properties": {
    "addr:full":"2611 Ingalls Ave Pascagoula MS 39567",
    "addr:housenumber":"2611",
    "addr:postcode":"39567",
    "addr:street":"Ingalls Ave",
    "iso:country":"US",
    "sg:address":"2611 Ingalls Ave",
    "sg:city":"Pascagoula",
    "sg:classifiers":[
        {
            "category":"Education",
            "subcategory":"School",
            "type":"Public Place"
        }
    ],
    "sg:phone":"+1 228 938 6431",
    "sg:postcode":"39567",
    "sg:province":"MS",
    "sg:tags":[
        "executive"
    ],
    "wof:name":"Eastlawn Elementary School",
    "wof:placetype":"venue"
},
  "geometry": {"coordinates":[-88.535963,30.354915],"type":"Point"}
}