{
  "type": "Feature",
  "properties": {
    "iso:country":"US",
    "sg:address":"4309 Shenandoah Rd",
    "sg:city":"Vicksburg",
    "sg:classifiers":[
        {
            "category":"Manufacturing",
            "subcategory":"Tools & Machinery",
            "type":"Manufacturing & Wholesale Goods"
        }
    ],
    "sg:phone":"+1 601 634 1813",
    "sg:postcode":"39180",
    "sg:province":"MS",
    "sg:tags":[
        "devices",
        "mfg"
    ],
    "wof:name":"Civil Tek Inc",
    "wof:placetype":"venue"
},
  "geometry": {"coordinates":[-90.861757,32.248109],"type":"Point"}
}