{
  "type": "Feature",
  "properties": {
    "iso:country":"US",
    "sg:address":"2504 River Bluffs Dr",
    "sg:city":"Ocean Springs",
    "sg:classifiers":[
        {
            "category":"Home & Garden",
            "subcategory":"Furniture",
            "type":"Retail Goods"
        }
    ],
    "sg:phone":"+1 228 826 4579",
    "sg:postcode":"39565",
    "sg:province":"MS",
    "wof:name":"Restonic Mattress Gallery Inc",
    "wof:placetype":"venue"
},
  "geometry": {"coordinates":[-88.648731,30.590437],"type":"Point"}
}