{
  "type": "Feature",
  "properties": {
    "iso:country":"US",
    "sg:address":"2050 Lawrence Blvd",
    "sg:city":"Biloxi",
    "sg:classifiers":[
        {
            "category":"Government",
            "subcategory":"Office",
            "type":"Public Place"
        }
    ],
    "sg:phone":"+1 228 388 9301",
    "sg:postcode":"39531",
    "sg:province":"MS",
    "wof:name":"Retardation Office",
    "wof:placetype":"venue"
},
  "geometry": {"coordinates":[-88.95711300000001,30.400801],"type":"Point"}
}