{
  "type": "Feature",
  "properties": {
    "addr:full":"115 Village Dr Brandon MS 39047",
    "addr:housenumber":"115",
    "addr:postcode":"39047",
    "addr:street":"Village Dr",
    "iso:country":"US",
    "sg:address":"115 Village Dr",
    "sg:city":"Brandon",
    "sg:classifiers":[
        {
            "category":"Home & Garden",
            "subcategory":"Carpets & Floor Coverings",
            "type":"Retail Goods"
        }
    ],
    "sg:phone":"+1 601 992 1171",
    "sg:postcode":"39047",
    "sg:province":"MS",
    "sg:tags":[
        "material"
    ],
    "wof:name":"Bud Milners Flooring & Design",
    "wof:placetype":"venue"
},
  "geometry": {"coordinates":[-89.95034099999999,32.41519],"type":"Point"}
}