{
  "type": "Feature",
  "properties": {
    "iso:country":"US",
    "sg:address":"1245 N Lehmberg Rd",
    "sg:city":"Columbus",
    "sg:classifiers":[
        {
            "category":"Professional",
            "type":"Services"
        }
    ],
    "sg:phone":"+1 662 241 4405",
    "sg:postcode":"39702",
    "sg:province":"MS",
    "wof:name":"P E Lamoreaux & Associates",
    "wof:placetype":"venue"
},
  "geometry": {"coordinates":[-88.36372900000001,33.51954],"type":"Point"}
}