{
  "type": "Feature",
  "properties": {
    "iso:country":"US",
    "sg:address":"1151 N State St",
    "sg:city":"Jackson",
    "sg:classifiers":[
        {
            "category":"Health Services",
            "subcategory":"Clinic",
            "type":"Services"
        }
    ],
    "sg:phone":"+1 601 968 0894",
    "sg:postcode":"39202",
    "sg:province":"MS",
    "sg:tags":[
        "specialty",
        "outpatient"
    ],
    "wof:name":"Gulf States Physical Medicine",
    "wof:placetype":"venue"
},
  "geometry": {"coordinates":[-90.178231,32.31351],"type":"Point"}
}