{
  "type": "Feature",
  "properties": {
    "iso:country":"US",
    "sg:address":"421 S Church St",
    "sg:city":"Okolona",
    "sg:classifiers":[
        {
            "category":"Freight",
            "type":"Transportation"
        }
    ],
    "sg:phone":"+1 662 447 3076",
    "sg:postcode":"38860",
    "sg:province":"MS",
    "sg:tags":[
        "delivery"
    ],
    "wof:name":"D S & J Trucking",
    "wof:placetype":"venue"
},
  "geometry": {"coordinates":[-88.755309,33.993281],"type":"Point"}
}