{
  "type": "Feature",
  "properties": {
    "iso:country":"US",
    "sg:address":"114 Sycamore Way",
    "sg:city":"Florence",
    "sg:classifiers":[
        {
            "category":"Social Services",
            "type":"Services"
        }
    ],
    "sg:phone":"+1 601 845 1645",
    "sg:postcode":"39073",
    "sg:province":"MS",
    "sg:tags":[
        "notification",
        "emergency"
    ],
    "wof:name":"Ms State Oil & Gas Board Field",
    "wof:placetype":"venue"
},
  "geometry": {"coordinates":[-90.14836699999999,32.161377],"type":"Point"}
}