{
  "type": "Feature",
  "properties": {
    "addr:full":"314 W South St Hollandale MS 38748",
    "addr:housenumber":"314",
    "addr:postcode":"38748",
    "addr:street":"W South St",
    "iso:country":"US",
    "sg:address":"314 W South St",
    "sg:city":"Hollandale",
    "sg:classifiers":[
        {
            "category":"Organizations",
            "subcategory":"Religious Organization",
            "type":"Services"
        }
    ],
    "sg:phone":"+1 662 827 2200",
    "sg:postcode":"38748",
    "sg:province":"MS",
    "sg:tags":[
        "church"
    ],
    "wof:name":"New Bethel MB Church",
    "wof:placetype":"venue"
},
  "geometry": {"coordinates":[-90.85661899999999,33.167108],"type":"Point"}
}