{
  "type": "Feature",
  "properties": {
    "iso:country":"US",
    "sg:address":"2989 Steens Vernon Rd",
    "sg:city":"Steens",
    "sg:classifiers":[
        {
            "category":"Bars & Pubs",
            "type":"Food & Drink"
        }
    ],
    "sg:phone":"+1 662 328 8280",
    "sg:postcode":"39766",
    "sg:province":"MS",
    "wof:name":"Double D's",
    "wof:placetype":"venue"
},
  "geometry": {"coordinates":[-88.281954,33.585369],"type":"Point"}
}