{
  "type": "Feature",
  "properties": {
    "iso:country":"US",
    "sg:address":"516 Nakoma Dr",
    "sg:city":"Jackson",
    "sg:classifiers":[
        {
            "category":"Utilities",
            "subcategory":"Mobile Phone",
            "type":"Services"
        }
    ],
    "sg:phone":"+1 601 982 8565",
    "sg:postcode":"39206",
    "sg:province":"MS",
    "sg:tags":[
        "communication",
        "radiotelephone",
        "merchandise"
    ],
    "wof:name":"Northtowne Wireless",
    "wof:placetype":"venue"
},
  "geometry": {"coordinates":[-90.182226,32.37152],"type":"Point"}
}