{
  "type": "Feature",
  "properties": {
    "addr:full":"101 Oakhurst Dr Clinton MS 39056",
    "addr:housenumber":"101",
    "addr:postcode":"39056",
    "addr:street":"Oakhurst Dr",
    "iso:country":"US",
    "sg:address":"101 Oakhurst Dr",
    "sg:city":"Clinton",
    "sg:classifiers":[
        {
            "category":"Recreation",
            "type":"Entertainment"
        }
    ],
    "sg:phone":"+1 601 924 6355",
    "sg:postcode":"39056",
    "sg:province":"MS",
    "sg:tags":[
        "skating",
        "rink"
    ],
    "wof:name":"Funtime Skateland Of Clinton",
    "wof:placetype":"venue"
},
  "geometry": {"coordinates":[-90.32379899999999,32.368539],"type":"Point"}
}