{
  "type": "Feature",
  "properties": {
    "addr:full":"326 Stateline Rd W Southaven MS 38671",
    "addr:housenumber":"326",
    "addr:postcode":"38671",
    "addr:street":"Stateline Rd W",
    "iso:country":"US",
    "sg:address":"326 Stateline Rd W",
    "sg:city":"Southaven",
    "sg:classifiers":[
        {
            "category":"Shopping",
            "subcategory":"Shoes",
            "type":"Retail Goods"
        }
    ],
    "sg:phone":"+1 662 393 0481",
    "sg:postcode":"38671",
    "sg:province":"MS",
    "wof:name":"Payless Shoe Source",
    "wof:placetype":"venue"
},
  "geometry": {"coordinates":[-89.994877,34.991924],"type":"Point"}
}