{
  "type": "Feature",
  "properties": {
    "iso:country":"US",
    "sg:address":"1836 Sycamore Trl NE",
    "sg:city":"Brookhaven",
    "sg:classifiers":[
        {
            "category":"Personal",
            "subcategory":"Beauty Salon",
            "type":"Services"
        }
    ],
    "sg:phone":"+1 601 835 4196",
    "sg:postcode":"39601",
    "sg:province":"MS",
    "sg:tags":[
        "shop"
    ],
    "wof:name":"Stephs Hair Salon",
    "wof:placetype":"venue"
},
  "geometry": {"coordinates":[-90.37626899999999,31.56869],"type":"Point"}
}