{
  "type": "Feature",
  "properties": {
    "addr:full":"2608 13th St Gulfport MS 39501",
    "addr:housenumber":"2608",
    "addr:postcode":"39501",
    "addr:street":"13Th St",
    "iso:country":"US",
    "sg:address":"2608 13th St",
    "sg:city":"Gulfport",
    "sg:classifiers":[
        {
            "category":"Organizations",
            "subcategory":"Non-profit Organization",
            "type":"Services"
        }
    ],
    "sg:phone":"+1 228 868 9324",
    "sg:postcode":"39501",
    "sg:province":"MS",
    "wof:name":"Gulf Coast Women's Ctr",
    "wof:placetype":"venue"
},
  "geometry": {"coordinates":[-89.094634,30.367199],"type":"Point"}
}