{
  "type": "Feature",
  "properties": {
    "addr:full":"11 County Lake Denham Rd Waynesboro MS 39367",
    "addr:housenumber":"11",
    "addr:postcode":"39367",
    "addr:street":"County Lake Denham Rd",
    "iso:country":"US",
    "sg:address":"11 County Lake Denham Rd",
    "sg:city":"Waynesboro",
    "sg:classifiers":[
        {
            "category":"Restaurant",
            "type":"Food & Drink"
        }
    ],
    "sg:phone":"+1 601 735 1972",
    "sg:postcode":"39367",
    "sg:province":"MS",
    "wof:name":"Mc Ilwain's Catfish & Stkhse",
    "wof:placetype":"venue"
},
  "geometry": {"coordinates":[-88.601674,31.681271],"type":"Point"}
}