{
  "type": "Feature",
  "properties": {
    "addr:full":"1300 Beaumont-Brooklyn Rd Beaumont MS 39423",
    "addr:housenumber":"1300",
    "addr:postcode":"39423",
    "addr:street":"Beaumont-Brooklyn Rd",
    "iso:country":"US",
    "sg:address":"1300 Beaumont-Brooklyn Rd",
    "sg:city":"Beaumont",
    "sg:classifiers":[
        {
            "category":"Education",
            "subcategory":"School",
            "type":"Public Place"
        }
    ],
    "sg:phone":"+1 601 784 3393",
    "sg:postcode":"39423",
    "sg:province":"MS",
    "sg:tags":[
        "elementary"
    ],
    "wof:name":"Beaumont Elementary School",
    "wof:placetype":"venue"
},
  "geometry": {"coordinates":[-88.92949,31.15869],"type":"Point"}
}