{
  "type": "Feature",
  "properties": {
    "iso:country":"US",
    "sg:address":"1418 Government St",
    "sg:city":"Ocean Springs",
    "sg:classifiers":[
        {
            "category":"Organizations",
            "subcategory":"Religious Organization",
            "type":"Services"
        }
    ],
    "sg:phone":"+1 228 875 4823",
    "sg:postcode":"39564",
    "sg:province":"MS",
    "wof:name":"St James Methodist Church",
    "wof:placetype":"venue"
},
  "geometry": {"coordinates":[-88.822585,30.413529],"type":"Point"}
}