{
  "type": "Feature",
  "properties": {
    "addr:full":"7064 Hwy 51 N Horn Lake MS 38637",
    "addr:housenumber":"7064",
    "addr:postcode":"38637",
    "addr:street":"Hwy 51 N Horn Lake",
    "iso:country":"US",
    "sg:address":"7064 Hwy 51 N",
    "sg:city":"Horn Lake",
    "sg:classifiers":[
        {
            "category":"Shopping",
            "type":"Retail Goods"
        }
    ],
    "sg:phone":"+1 662 253 2000",
    "sg:postcode":"38637",
    "sg:province":"MS",
    "sg:tags":[
        "equipment",
        "telephone",
        "supply"
    ],
    "wof:name":"Caymus Communications",
    "wof:placetype":"venue"
},
  "geometry": {"coordinates":[-90.016378,34.964185],"type":"Point"}
}