{
  "type": "Feature",
  "properties": {
    "addr:full":"601 S Industrial Pkwy Yazoo City MS 39194",
    "addr:housenumber":"601",
    "addr:postcode":"39194",
    "addr:street":"S Industrial Pkwy",
    "iso:country":"US",
    "sg:address":"601 S Industrial Pkwy",
    "sg:city":"Yazoo City",
    "sg:classifiers":[
        {
            "category":"Food & Beverages",
            "subcategory":"Groceries & Convenience Stores",
            "type":"Retail Goods"
        }
    ],
    "sg:phone":"+1 662 746 1902",
    "sg:postcode":"39194",
    "sg:province":"MS",
    "wof:name":"Industrial Parkway Super Store",
    "wof:placetype":"venue"
},
  "geometry": {"coordinates":[-90.43388899999999,32.845169],"type":"Point"}
}