{
  "type": "Feature",
  "properties": {
    "iso:country":"US",
    "sg:address":"129 Executive Dr",
    "sg:city":"Madison",
    "sg:classifiers":[
        {
            "category":"Professional",
            "type":"Services"
        }
    ],
    "sg:phone":"+1 601 853 9307",
    "sg:postcode":"39110",
    "sg:province":"MS",
    "sg:tags":[
        "establishment"
    ],
    "wof:name":"Regional Office-Outback",
    "wof:placetype":"venue"
},
  "geometry": {"coordinates":[-90.116688,32.444562],"type":"Point"}
}