{
  "type": "Feature",
  "properties": {
    "iso:country":"US",
    "sg:address":"1450 Wiggins Rd",
    "sg:city":"Jackson",
    "sg:classifiers":[
        {
            "category":"Social Services",
            "subcategory":"Child Care",
            "type":"Services"
        },
        {
            "category":"Education",
            "subcategory":"School",
            "type":"Public Place"
        }
    ],
    "sg:phone":"+1 601 960 2400",
    "sg:postcode":"39209",
    "sg:province":"MS",
    "sg:tags":[
        "day"
    ],
    "wof:name":"Westside Day Care Center",
    "wof:placetype":"venue"
},
  "geometry": {"coordinates":[-90.282949,32.309008],"type":"Point"}
}