{
  "type": "Feature",
  "properties": {
    "iso:country":"US",
    "sg:address":"120 Ridge Dr",
    "sg:city":"Flowood",
    "sg:classifiers":[
        {
            "category":"Building & Trades",
            "subcategory":"Construction",
            "type":"Services"
        }
    ],
    "sg:phone":"+1 601 992 8475",
    "sg:postcode":"39216",
    "sg:province":"MS",
    "sg:tags":[
        "home",
        "improvement"
    ],
    "wof:name":"Lowe's Home Imprvmt Of Flowood",
    "wof:placetype":"venue"
},
  "geometry": {"coordinates":[-90.16699199999999,32.339857],"type":"Point"}
}