{
  "type": "Feature",
  "properties": {
    "iso:country":"US",
    "sg:address":"460 W Bridge St",
    "sg:city":"Yazoo City",
    "sg:classifiers":[
        {
            "category":"Retail",
            "subcategory":"Animal Services",
            "type":"Services"
        }
    ],
    "sg:phone":"+1 662 746 5121",
    "sg:postcode":"39194",
    "sg:province":"MS",
    "wof:name":"Animal Shelter",
    "wof:placetype":"venue"
},
  "geometry": {"coordinates":[-90.41945200000001,32.845479],"type":"Point"}
}