{
  "type": "Feature",
  "properties": {
    "iso:country":"US",
    "sg:address":"1757 Terry Rd",
    "sg:city":"Jackson",
    "sg:classifiers":[
        {
            "category":"Shopping",
            "type":"Retail Goods"
        }
    ],
    "sg:phone":"+1 601 371 2134",
    "sg:postcode":"39204",
    "sg:province":"MS",
    "sg:tags":[
        "typewriter"
    ],
    "wof:name":"Quality Office Svc & Supplies",
    "wof:placetype":"venue"
},
  "geometry": {"coordinates":[-90.207441,32.284641],"type":"Point"}
}