{
  "type": "Feature",
  "properties": {
    "iso:country":"US",
    "sg:address":"6791 S Siwell Rd",
    "sg:city":"Byram",
    "sg:classifiers":[
        {
            "category":"Banks & Credit Unions",
            "subcategory":"Bank",
            "type":"Services"
        }
    ],
    "sg:phone":"+1 601 372 6160",
    "sg:postcode":"39272",
    "sg:province":"MS",
    "sg:tags":[
        "mortgage",
        "loan",
        "broker",
        "real estate"
    ],
    "wof:name":"Diversified Mortgage Corp",
    "wof:placetype":"venue"
},
  "geometry": {"coordinates":[-90.28921,32.202791],"type":"Point"}
}