{
  "type": "Feature",
  "properties": {
    "addr:full":"40200 Holloway Rd Hamilton MS 39746",
    "addr:housenumber":"40200",
    "addr:postcode":"39746",
    "addr:street":"Holloway Rd",
    "iso:country":"US",
    "sg:address":"40200 Holloway Rd",
    "sg:city":"Hamilton",
    "sg:classifiers":[
        {
            "category":"Manufacturing",
            "subcategory":"Signs",
            "type":"Manufacturing & Wholesale Goods"
        }
    ],
    "sg:phone":"+1 662 343 8399",
    "sg:postcode":"39746",
    "sg:province":"MS",
    "wof:name":"Computer Graphics By Connie",
    "wof:placetype":"venue"
},
  "geometry": {"coordinates":[-88.42674599999999,33.725165],"type":"Point"}
}