{
  "type": "Feature",
  "properties": {
    "iso:country":"US",
    "sg:address":"612 35th St",
    "sg:city":"Gulfport",
    "sg:classifiers":[
        {
            "category":"Building & Trades",
            "subcategory":"Construction",
            "type":"Services"
        }
    ],
    "sg:phone":"+1 228 863 9003",
    "sg:postcode":"39501",
    "sg:province":"MS",
    "sg:tags":[
        "heavy",
        "concrete",
        "contractor"
    ],
    "wof:name":"Blanchard Construction Inc",
    "wof:placetype":"venue"
},
  "geometry": {"coordinates":[-89.06259900000001,30.3925],"type":"Point"}
}