{
  "type": "Feature",
  "properties": {
    "iso:country":"US",
    "sg:address":"3219 Nathan Hale Ave",
    "sg:city":"Pascagoula",
    "sg:classifiers":[
        {
            "category":"Health Services",
            "subcategory":"Clinic",
            "type":"Services"
        }
    ],
    "sg:phone":"+1 228 769 8332",
    "sg:postcode":"39581",
    "sg:province":"MS",
    "sg:tags":[
        "specialty",
        "outpatient"
    ],
    "wof:name":"Teen Challenge Of Mississippi",
    "wof:placetype":"venue"
},
  "geometry": {"coordinates":[-88.52947,30.374409],"type":"Point"}
}