{
  "type": "Feature",
  "properties": {
    "iso:country":"US",
    "sg:address":"208 E Maud Ave",
    "sg:city":"Mendenhall",
    "sg:classifiers":[
        {
            "category":"Building & Trades",
            "subcategory":"Landscaping Services",
            "type":"Services"
        }
    ],
    "sg:phone":"+1 601 847 9916",
    "sg:postcode":"39114",
    "sg:province":"MS",
    "sg:tags":[
        "tree"
    ],
    "wof:name":"Tip Top Tree Svc",
    "wof:placetype":"venue"
},
  "geometry": {"coordinates":[-89.86803,31.96141],"type":"Point"}
}