{
  "type": "Feature",
  "properties": {
    "addr:full":"501 Russell Ave Long Beach MS 39560",
    "addr:housenumber":"501",
    "addr:postcode":"39560",
    "addr:street":"Russell Ave",
    "iso:country":"US",
    "sg:address":"501 Russell Ave",
    "sg:city":"Long Beach",
    "sg:classifiers":[
        {
            "category":"Manufacturing",
            "subcategory":"Printing",
            "type":"Manufacturing & Wholesale Goods"
        }
    ],
    "sg:phone":"+1 228 863 6177",
    "sg:postcode":"39560",
    "sg:province":"MS",
    "sg:tags":[
        "publisher"
    ],
    "sg:website":"www.mathispublishers.com",
    "wof:name":"Mathis Publishers",
    "wof:placetype":"venue"
},
  "geometry": {"coordinates":[-89.15396800000001,30.343766],"type":"Point"}
}