{
  "type": "Feature",
  "properties": {
    "iso:country":"US",
    "sg:address":"60 Lott Loop Rd",
    "sg:city":"Hattiesburg",
    "sg:classifiers":[
        {
            "category":"Building & Trades",
            "subcategory":"Construction",
            "type":"Services"
        }
    ],
    "sg:phone":"+1 601 582 2464",
    "sg:postcode":"39401",
    "sg:province":"MS",
    "sg:tags":[
        "hanging",
        "contractor"
    ],
    "wof:name":"Ryals Painting Tracy A",
    "wof:placetype":"venue"
},
  "geometry": {"coordinates":[-89.27938399999999,31.230646],"type":"Point"}
}