{
  "type": "Feature",
  "properties": {
    "iso:country":"US",
    "sg:address":"101 S Industrial Rd",
    "sg:city":"Tupelo",
    "sg:classifiers":[
        {
            "category":"Health Services",
            "subcategory":"Clinic",
            "type":"Services"
        }
    ],
    "sg:phone":"+1 662 841 2900",
    "sg:postcode":"38801",
    "sg:province":"MS",
    "sg:tags":[
        "home"
    ],
    "sg:website":"www.helpathome.com",
    "wof:name":"Oxford Health Care",
    "wof:placetype":"venue"
},
  "geometry": {"coordinates":[-88.720626,34.25728],"type":"Point"}
}