{
  "type": "Feature",
  "properties": {
    "iso:country":"US",
    "sg:address":"4250 State Hwy 12",
    "sg:city":"Hollandale",
    "sg:classifiers":[
        {
            "category":"Building & Trades",
            "subcategory":"Construction",
            "type":"Services"
        }
    ],
    "sg:phone":"+1 662 827 5188",
    "sg:postcode":"38748",
    "sg:province":"MS",
    "sg:tags":[
        "general",
        "contractor"
    ],
    "wof:name":"Malouf Construction",
    "wof:placetype":"venue"
},
  "geometry": {"coordinates":[-90.711755,33.184528],"type":"Point"}
}