{
  "type": "Feature",
  "properties": {
    "iso:country":"US",
    "sg:address":"15235 Oneal Rd",
    "sg:city":"Gulfport",
    "sg:classifiers":[
        {
            "category":"Real Estate",
            "subcategory":"Developer",
            "type":"Services"
        }
    ],
    "sg:phone":"+1 228 822 1600",
    "sg:postcode":"39503",
    "sg:province":"MS",
    "sg:tags":[
        "building",
        "mgr",
        "apt",
        "agent",
        "subdivider"
    ],
    "wof:name":"Creekwood North Apartments",
    "wof:placetype":"venue"
},
  "geometry": {"coordinates":[-89.093633,30.470611],"type":"Point"}
}