{
  "type": "Feature",
  "properties": {
    "iso:country":"US",
    "sg:address":"1711 University Ave",
    "sg:city":"Oxford",
    "sg:classifiers":[
        {
            "category":"Personal",
            "subcategory":"Beauty Salon",
            "type":"Services"
        }
    ],
    "sg:phone":"+1 662 234 8282",
    "sg:postcode":"38655",
    "sg:province":"MS",
    "wof:name":"Continental Hair Styles",
    "wof:placetype":"venue"
},
  "geometry": {"coordinates":[-89.513155,34.363228],"type":"Point"}
}