{
  "type": "Feature",
  "properties": {
    "iso:country":"US",
    "sg:address":"3880 Gautier Vancleave Rd",
    "sg:city":"Gautier",
    "sg:classifiers":[
        {
            "category":"Shopping",
            "type":"Retail Goods"
        }
    ],
    "sg:phone":"+1 228 522 0048",
    "sg:postcode":"39553",
    "sg:province":"MS",
    "sg:tags":[
        "cosmetic",
        "perfume"
    ],
    "wof:name":"Merle Norman Cosmetics",
    "wof:placetype":"venue"
},
  "geometry": {"coordinates":[-88.652438,30.39742],"type":"Point"}
}