{
  "type": "Feature",
  "properties": {
    "iso:country":"US",
    "sg:address":"45 Allendale Rd",
    "sg:city":"Indianola",
    "sg:phone":"+1 662 887 4632",
    "sg:postcode":"38751",
    "sg:province":"MS",
    "sg:tags":[
        "wheat",
        "farm",
        "catfish",
        "soybean",
        "rice",
        "cotton"
    ],
    "wof:name":"Tindall Francis Lorrain",
    "wof:placetype":"venue"
},
  "geometry": {"coordinates":[-90.705682,33.410531],"type":"Point"}
}