{
  "type": "Feature",
  "properties": {
    "addr:full":"5220 Elmore Rd Southaven MS 38671",
    "addr:housenumber":"5220",
    "addr:postcode":"38671",
    "addr:street":"Elmore Rd",
    "iso:country":"US",
    "sg:address":"5220 Elmore Rd",
    "sg:city":"Southaven",
    "sg:classifiers":[
        {
            "category":"Home & Garden",
            "subcategory":"Furniture",
            "type":"Retail Goods"
        }
    ],
    "sg:phone":"+1 662 393 8139",
    "sg:postcode":"38671",
    "sg:province":"MS",
    "sg:tags":[
        "bedding"
    ],
    "wof:name":"Home Expressions",
    "wof:placetype":"venue"
},
  "geometry": {"coordinates":[-89.98106799999999,34.934772],"type":"Point"}
}