{
  "type": "Feature",
  "properties": {
    "addr:full":"1910 Hwy 19 N Meridian MS 39307",
    "addr:housenumber":"1910",
    "addr:postcode":"39307",
    "addr:street":"Hwy 19 N",
    "iso:country":"US",
    "sg:address":"1910 Hwy 19 N",
    "sg:city":"Meridian",
    "sg:classifiers":[
        {
            "category":"Restaurant",
            "type":"Food & Drink"
        }
    ],
    "sg:phone":"+1 601 693 0100",
    "sg:postcode":"39307",
    "sg:province":"MS",
    "sg:website":"www.luigis.us",
    "wof:name":"Luigi's New York Style Pizza",
    "wof:placetype":"venue"
},
  "geometry": {"coordinates":[-88.742876,32.373907],"type":"Point"}
}