{
  "type": "Feature",
  "properties": {
    "iso:country":"US",
    "sg:address":"225 S Washington Ave",
    "sg:city":"Greenville",
    "sg:classifiers":[
        {
            "category":"Health Services",
            "subcategory":"Clinic",
            "type":"Services"
        }
    ],
    "sg:phone":"+1 662 332 4373",
    "sg:postcode":"38701",
    "sg:province":"MS",
    "sg:tags":[
        "home",
        "care"
    ],
    "wof:name":"Continual Care Home Hlth Care",
    "wof:placetype":"venue"
},
  "geometry": {"coordinates":[-91.051615,33.405641],"type":"Point"}
}