{
  "type": "Feature",
  "properties": {
    "iso:country":"US",
    "sg:address":"3296 Hwy 80 W",
    "sg:city":"Jackson",
    "sg:classifiers":[
        {
            "category":"Restaurant",
            "type":"Food & Drink"
        }
    ],
    "sg:phone":"+1 601 353 0134",
    "sg:postcode":"39204",
    "sg:province":"MS",
    "sg:tags":[
        "eating"
    ],
    "wof:name":"KFC",
    "wof:placetype":"venue"
},
  "geometry": {"coordinates":[-90.237336,32.2961],"type":"Point"}
}