{
  "type": "Feature",
  "properties": {
    "iso:country":"US",
    "sg:address":"4710 W Beach Blvd",
    "sg:city":"Gulfport",
    "sg:classifiers":[
        {
            "category":"Real Estate",
            "subcategory":"Real Estate Operator",
            "type":"Services"
        }
    ],
    "sg:phone":"+1 228 864 5337",
    "sg:postcode":"39501",
    "sg:province":"MS",
    "sg:tags":[
        "condominium"
    ],
    "wof:name":"Acadian Village Condominiums",
    "wof:placetype":"venue"
},
  "geometry": {"coordinates":[-89.11926699999999,30.356662],"type":"Point"}
}