{
  "type": "Feature",
  "properties": {
    "iso:country":"US",
    "sg:address":"9262 Hwy 15 S",
    "sg:city":"Pontotoc",
    "sg:classifiers":[
        {
            "category":"Government",
            "subcategory":"Fire Station",
            "type":"Public Place"
        }
    ],
    "sg:phone":"+1 662 489 1428",
    "sg:postcode":"38863",
    "sg:province":"MS",
    "sg:tags":[
        "protection"
    ],
    "wof:name":"Beckham Volunteer Fire Dept",
    "wof:placetype":"venue"
},
  "geometry": {"coordinates":[-89.00131500000001,34.123501],"type":"Point"}
}