{
  "type": "Feature",
  "properties": {
    "iso:country":"US",
    "sg:address":"429 Cedar St",
    "sg:city":"Greenville",
    "sg:classifiers":[
        {
            "category":"Social Services",
            "subcategory":"Child Care",
            "type":"Services"
        }
    ],
    "sg:phone":"+1 662 334 9194",
    "sg:postcode":"38701",
    "sg:province":"MS",
    "sg:tags":[
        "day"
    ],
    "wof:name":"Ole Mother Hubbard Day CA",
    "wof:placetype":"venue"
},
  "geometry": {"coordinates":[-91.045361,33.40232],"type":"Point"}
}