{
  "type": "Feature",
  "properties": {
    "iso:country":"US",
    "sg:address":"655 Courthouse Rd",
    "sg:city":"Gulfport",
    "sg:classifiers":[
        {
            "category":"Autos & Motor Vehicles",
            "subcategory":"Auto Supplies",
            "type":"Retail Goods"
        }
    ],
    "sg:phone":"+1 228 897 1423",
    "sg:postcode":"39507",
    "sg:province":"MS",
    "wof:name":"Firestone",
    "wof:placetype":"venue"
},
  "geometry": {"coordinates":[-89.044382,30.392956],"type":"Point"}
}