{
  "type": "Feature",
  "properties": {
    "iso:country":"US",
    "sg:address":"25 Price Rd",
    "sg:city":"Perkinston",
    "sg:classifiers":[
        {
            "category":"Retail",
            "subcategory":"Animal Services",
            "type":"Services"
        }
    ],
    "sg:phone":"+1 601 928 5577",
    "sg:postcode":"39573",
    "sg:province":"MS",
    "sg:tags":[
        "breeder",
        "horse"
    ],
    "wof:name":"Stone Oak Farm",
    "wof:placetype":"venue"
},
  "geometry": {"coordinates":[-89.1283,30.790509],"type":"Point"}
}