{
  "type": "Feature",
  "properties": {
    "iso:country":"US",
    "sg:address":"431 N 2nd St",
    "sg:city":"Booneville",
    "sg:classifiers":[
        {
            "category":"Banks & Credit Unions",
            "subcategory":"Bank",
            "type":"Services"
        }
    ],
    "sg:phone":"+1 662 728 2233",
    "sg:postcode":"38829",
    "sg:province":"MS",
    "sg:tags":[
        "cashing",
        "agency",
        "check"
    ],
    "wof:name":"Family Check Advance",
    "wof:placetype":"venue"
},
  "geometry": {"coordinates":[-88.566473,34.662465],"type":"Point"}
}