{
  "type": "Feature",
  "properties": {
    "addr:full":"531 Central Ave Laurel MS 39440",
    "addr:housenumber":"531",
    "addr:postcode":"39440",
    "addr:street":"Central Ave",
    "iso:country":"US",
    "sg:address":"531 Central Ave",
    "sg:city":"Laurel",
    "sg:classifiers":[
        {
            "category":"Home & Garden",
            "subcategory":"Building Materials",
            "type":"Retail Goods"
        }
    ],
    "sg:phone":"+1 601 649 5755",
    "sg:postcode":"39440",
    "sg:province":"MS",
    "wof:name":"Low Grade Lumber",
    "wof:placetype":"venue"
},
  "geometry": {"coordinates":[-89.132734,31.69345],"type":"Point"}
}