{
  "type": "Feature",
  "properties": {
    "iso:country":"US",
    "sg:address":"2001 Veterans Blvd",
    "sg:city":"Mccomb",
    "sg:classifiers":[
        {
            "category":"Restaurant",
            "type":"Food & Drink"
        }
    ],
    "sg:menulink":"http://www.allmenus.com/ms/summit/158741-arbys/menu/",
    "sg:phone":"+1 601 250 6691",
    "sg:postcode":"39648",
    "sg:province":"MS",
    "sg:tags":[
        "burger",
        "american"
    ],
    "wof:name":"Arby's",
    "wof:placetype":"venue"
},
  "geometry": {"coordinates":[-90.480101,31.259635],"type":"Point"}
}