{
  "type": "Feature",
  "properties": {
    "iso:country":"US",
    "sg:address":"212 E Jefferson St",
    "sg:city":"Ripley",
    "sg:classifiers":[
        {
            "category":"Organizations",
            "subcategory":"Membership Organization",
            "type":"Services"
        },
        {
            "category":"Organizations",
            "subcategory":"Professional Association",
            "type":"Services"
        }
    ],
    "sg:phone":"+1 662 512 0226",
    "sg:postcode":"38663",
    "sg:province":"MS",
    "wof:name":"Ripley Main Street Association",
    "wof:placetype":"venue"
},
  "geometry": {"coordinates":[-88.948179,34.730417],"type":"Point"}
}