{
  "type": "Feature",
  "properties": {
    "iso:country":"US",
    "sg:address":"3227 Audubon Dr",
    "sg:city":"Laurel",
    "sg:classifiers":[
        {
            "category":"Health Services",
            "subcategory":"Hospital",
            "type":"Services"
        }
    ],
    "sg:phone":"+1 601 425 9322",
    "sg:postcode":"39440",
    "sg:province":"MS",
    "sg:tags":[
        "mental"
    ],
    "sg:website":"www.pbmhr.com",
    "wof:name":"Laurel Children's Ctr",
    "wof:placetype":"venue"
},
  "geometry": {"coordinates":[-89.139301,31.729898],"type":"Point"}
}