{
  "type": "Feature",
  "properties": {
    "addr:full":"827 US Hwy 90 Bay St Louis MS 39520",
    "addr:housenumber":"827",
    "addr:postcode":"39520",
    "addr:street":"Us Hwy 90",
    "iso:country":"US",
    "sg:address":"827 US Hwy 90",
    "sg:city":"Bay St Louis",
    "sg:classifiers":[
        {
            "category":"Professional",
            "subcategory":"Lawyer & Legal Services",
            "type":"Services"
        }
    ],
    "sg:phone":"+1 228 467 3422",
    "sg:postcode":"39520",
    "sg:province":"MS",
    "sg:tags":[
        "attorney"
    ],
    "wof:name":"Southern Title Co Inc",
    "wof:placetype":"venue"
},
  "geometry": {"coordinates":[-89.35248799999999,30.315067],"type":"Point"}
}