{
  "type": "Feature",
  "properties": {
    "iso:country":"US",
    "sg:address":"613 Magnolia Tree Dr",
    "sg:city":"Gautier",
    "sg:classifiers":[
        {
            "category":"Social Services",
            "subcategory":"Child Care",
            "type":"Services"
        }
    ],
    "sg:phone":"+1 228 497 4434",
    "sg:postcode":"39553",
    "sg:province":"MS",
    "wof:name":"Libby Center Inc",
    "wof:placetype":"venue"
},
  "geometry": {"coordinates":[-88.61849599999999,30.384015],"type":"Point"}
}