{
  "type": "Feature",
  "properties": {
    "addr:full":"152 E College Ave Holly Springs MS 38635",
    "addr:housenumber":"152",
    "addr:postcode":"38635",
    "addr:street":"E College Ave",
    "iso:country":"US",
    "sg:address":"152 E College Ave",
    "sg:city":"Holly Springs",
    "sg:classifiers":[
        {
            "category":"Restaurant",
            "type":"Food & Drink"
        }
    ],
    "sg:phone":"+1 662 252 1589",
    "sg:postcode":"38635",
    "sg:province":"MS",
    "sg:tags":[
        "eating"
    ],
    "wof:name":"Canton Chinese Restaurant",
    "wof:placetype":"venue"
},
  "geometry": {"coordinates":[-89.447638,34.76852],"type":"Point"}
}