{
  "type": "Feature",
  "properties": {
    "addr:full":"176 Whisper Lake Blvd Madison MS 39110",
    "addr:housenumber":"176",
    "addr:postcode":"39110",
    "addr:street":"Whisper Lake Blvd",
    "iso:country":"US",
    "sg:address":"176 Whisper Lake Blvd",
    "sg:city":"Madison",
    "sg:classifiers":[
        {
            "category":"Professional",
            "subcategory":"Management & Consulting",
            "type":"Services"
        }
    ],
    "sg:phone":"+1 601 898 0116",
    "sg:postcode":"39110",
    "sg:province":"MS",
    "sg:tags":[
        "supply"
    ],
    "wof:name":"MESSLLC",
    "wof:placetype":"venue"
},
  "geometry": {"coordinates":[-90.19176299999999,32.498979],"type":"Point"}
}