{
  "type": "Feature",
  "properties": {
    "iso:country":"US",
    "sg:address":"1396 S Veterans Blvd",
    "sg:city":"Tupelo",
    "sg:classifiers":[
        {
            "category":"Freight",
            "type":"Transportation"
        }
    ],
    "sg:phone":"+1 662 844 5840",
    "sg:postcode":"38801",
    "sg:province":"MS",
    "sg:tags":[
        "commercial",
        "storage"
    ],
    "wof:name":"Davis Property Management",
    "wof:placetype":"venue"
},
  "geometry": {"coordinates":[-88.684988,34.23601],"type":"Point"}
}