{
  "type": "Feature",
  "properties": {
    "addr:full":"4611 Terry Rd Jackson MS 39212",
    "addr:housenumber":"4611",
    "addr:postcode":"39212",
    "addr:street":"Terry Rd",
    "iso:country":"US",
    "sg:address":"4611 Terry Rd",
    "sg:city":"Jackson",
    "sg:classifiers":[
        {
            "category":"Personal",
            "subcategory":"Barber",
            "type":"Services"
        }
    ],
    "sg:phone":"+1 601 371 4443",
    "sg:postcode":"39212",
    "sg:province":"MS",
    "sg:tags":[
        "shop"
    ],
    "wof:name":"Heads Up Family Hair Care",
    "wof:placetype":"venue"
},
  "geometry": {"coordinates":[-90.252017,32.195548],"type":"Point"}
}