{
  "type": "Feature",
  "properties": {
    "iso:country":"US",
    "sg:address":"1491 US Hwy 61",
    "sg:city":"Woodville",
    "sg:classifiers":[
        {
            "category":"Government",
            "subcategory":"Office",
            "type":"Public Place"
        }
    ],
    "sg:phone":"+1 601 888 6429",
    "sg:postcode":"39669",
    "sg:province":"MS",
    "wof:name":"Wilkinson County Tire Waste",
    "wof:placetype":"venue"
},
  "geometry": {"coordinates":[-91.30519099999999,31.083804],"type":"Point"}
}