{
  "type": "Feature",
  "properties": {
    "addr:full":"2895 W 4th St Hattiesburg MS 39401",
    "addr:housenumber":"2895",
    "addr:postcode":"39401",
    "addr:street":"W 4Th St",
    "iso:country":"US",
    "sg:address":"2895 W 4th St",
    "sg:city":"Hattiesburg",
    "sg:classifiers":[
        {
            "category":"Shopping",
            "subcategory":"Bicycles & Sporting Goods",
            "type":"Retail Goods"
        }
    ],
    "sg:phone":"+1 601 450 5247",
    "sg:postcode":"39401",
    "sg:province":"MS",
    "wof:name":"Longleaf Trace Trail Manager",
    "wof:placetype":"venue"
},
  "geometry": {"coordinates":[-89.329936,31.33205],"type":"Point"}
}