{
  "type": "Feature",
  "properties": {
    "addr:full":"4253 Robinson St Jackson MS 39209",
    "addr:housenumber":"4253",
    "addr:postcode":"39209",
    "addr:street":"Robinson St",
    "iso:country":"US",
    "sg:address":"4253 Robinson St",
    "sg:city":"Jackson",
    "sg:classifiers":[
        {
            "category":"Retail",
            "subcategory":"Portrait Studio",
            "type":"Services"
        }
    ],
    "sg:phone":"+1 601 922 7600",
    "sg:postcode":"39209",
    "sg:province":"MS",
    "sg:tags":[
        "photo"
    ],
    "wof:name":"Olan Mills Studios",
    "wof:placetype":"venue"
},
  "geometry": {"coordinates":[-90.257094,32.301137],"type":"Point"}
}