{
  "type": "Feature",
  "properties": {
    "iso:country":"US",
    "sg:address":"409 W Oak St",
    "sg:city":"Laurel",
    "sg:classifiers":[
        {
            "category":"Insurance",
            "subcategory":"Insurance Agent",
            "type":"Services"
        }
    ],
    "sg:phone":"+1 601 428 4393",
    "sg:postcode":"39440",
    "sg:province":"MS",
    "wof:name":"G Carey Hauenstein & Assoc",
    "wof:placetype":"venue"
},
  "geometry": {"coordinates":[-89.130951,31.693403],"type":"Point"}
}