{
  "type": "Feature",
  "properties": {
    "iso:country":"US",
    "sg:address":"60021 Cotton Gin Port Rd",
    "sg:city":"Amory",
    "sg:classifiers":[
        {
            "category":"Professional",
            "subcategory":"Secretarial Services",
            "type":"Services"
        }
    ],
    "sg:phone":"+1 662 256 9990",
    "sg:postcode":"38821",
    "sg:province":"MS",
    "sg:tags":[
        "convention",
        "court",
        "reporter"
    ],
    "wof:name":"Maharrey Court Reporting",
    "wof:placetype":"venue"
},
  "geometry": {"coordinates":[-88.51402400000001,33.957612],"type":"Point"}
}