{
  "type": "Feature",
  "properties": {
    "iso:country":"US",
    "sg:address":"422 US Hwy 61 Bus",
    "sg:city":"Natchez",
    "sg:classifiers":[
        {
            "category":"Autos & Motor Vehicles",
            "subcategory":"Fuel & Gas Station",
            "type":"Retail Goods"
        }
    ],
    "sg:phone":"+1 601 446 6432",
    "sg:postcode":"39120",
    "sg:province":"MS",
    "sg:tags":[
        "station",
        "gasoline"
    ],
    "wof:name":"Docks Uhaul",
    "wof:placetype":"venue"
},
  "geometry": {"coordinates":[-91.40222300000001,31.554492],"type":"Point"}
}