{
  "type": "Feature",
  "properties": {
    "iso:country":"US",
    "sg:address":"801 Station St",
    "sg:city":"Waynesboro",
    "sg:classifiers":[
        {
            "category":"Shopping",
            "subcategory":"Discount & Variety Stores",
            "type":"Retail Goods"
        }
    ],
    "sg:phone":"+1 601 671 3757",
    "sg:postcode":"39367",
    "sg:province":"MS",
    "sg:tags":[
        "merchandise",
        "general"
    ],
    "wof:name":"Dollarama",
    "wof:placetype":"venue"
},
  "geometry": {"coordinates":[-88.647222,31.676267],"type":"Point"}
}