{
  "type": "Feature",
  "properties": {
    "iso:country":"US",
    "sg:address":"209 N Stone Ave",
    "sg:city":"Greenwood",
    "sg:classifiers":[
        {
            "category":"Organizations",
            "subcategory":"Religious Organization",
            "type":"Services"
        }
    ],
    "sg:phone":"+1 662 455 9679",
    "sg:postcode":"38930",
    "sg:province":"MS",
    "wof:name":"Salvation Army",
    "wof:placetype":"venue"
},
  "geometry": {"coordinates":[-90.167278,33.519216],"type":"Point"}
}