{
  "type": "Feature",
  "properties": {
    "addr:full":"2120 S Pat Harrison Dr Crystal Springs MS 39059",
    "addr:housenumber":"2120",
    "addr:postcode":"39059",
    "addr:street":"S Pat Harrison Dr",
    "iso:country":"US",
    "sg:address":"2120 S Pat Harrison Dr",
    "sg:city":"Crystal Springs",
    "sg:classifiers":[
        {
            "category":"Retail",
            "subcategory":"Repair Shop",
            "type":"Services"
        }
    ],
    "sg:phone":"+1 601 892 0545",
    "sg:postcode":"39059",
    "sg:province":"MS",
    "sg:tags":[
        "television",
        "radio"
    ],
    "wof:name":"Thomas TV & Electronics Repair",
    "wof:placetype":"venue"
},
  "geometry": {"coordinates":[-90.372389,31.969619],"type":"Point"}
}