{
  "type": "Feature",
  "properties": {
    "iso:country":"US",
    "sg:address":"2167 Stateline Rd W",
    "sg:city":"Southaven",
    "sg:classifiers":[
        {
            "category":"Retail",
            "subcategory":"Repair Shop",
            "type":"Services"
        }
    ],
    "sg:phone":"+1 662 342 3821",
    "sg:postcode":"38671",
    "sg:province":"MS",
    "sg:tags":[
        "electrical"
    ],
    "wof:name":"All Major Appliance",
    "wof:placetype":"venue"
},
  "geometry": {"coordinates":[-90.02888,34.99176],"type":"Point"}
}