{
  "type": "Feature",
  "properties": {
    "iso:country":"US",
    "sg:address":"1720 Read Rd",
    "sg:city":"Picayune",
    "sg:classifiers":[
        {
            "category":"Organizations",
            "subcategory":"Religious Organization",
            "type":"Services"
        }
    ],
    "sg:phone":"+1 601 798 7481",
    "sg:postcode":"39466",
    "sg:province":"MS",
    "sg:tags":[
        "church"
    ],
    "wof:name":"Church Of Jesus Christ Of Lds",
    "wof:placetype":"venue"
},
  "geometry": {"coordinates":[-89.662553,30.543028],"type":"Point"}
}