{
  "type": "Feature",
  "properties": {
    "iso:country":"US",
    "sg:address":"908 Poplar Rd",
    "sg:city":"Starkville",
    "sg:classifiers":[
        {
            "category":"Wholesale",
            "subcategory":"Construction Materials",
            "type":"Manufacturing & Wholesale Goods"
        }
    ],
    "sg:phone":"+1 662 320 4400",
    "sg:postcode":"39759",
    "sg:province":"MS",
    "sg:tags":[
        "fence"
    ],
    "wof:name":"Hester Fence Co",
    "wof:placetype":"venue"
},
  "geometry": {"coordinates":[-88.829999,33.448754],"type":"Point"}
}