{
  "type": "Feature",
  "properties": {
    "addr:full":"1113 US Hwy 61 Port Gibson MS 39150",
    "addr:housenumber":"1113",
    "addr:postcode":"39150",
    "addr:street":"Us Hwy 61 Port Gibson",
    "iso:country":"US",
    "sg:address":"1113 US Hwy 61",
    "sg:city":"Port Gibson",
    "sg:classifiers":[
        {
            "category":"Food & Beverages",
            "subcategory":"Meat & Fish",
            "type":"Retail Goods"
        },
        {
            "category":"Restaurant",
            "type":"Food & Drink"
        }
    ],
    "sg:phone":"+1 601 437 4009",
    "sg:postcode":"39150",
    "sg:province":"MS",
    "wof:name":"61 Fish Market & Restaurant",
    "wof:placetype":"venue"
},
  "geometry": {"coordinates":[-90.983846,31.955713],"type":"Point"}
}