{
  "type": "Feature",
  "properties": {
    "addr:full":"2021 US Hwy 11 N Picayune MS 39466",
    "addr:housenumber":"2021",
    "addr:postcode":"39466",
    "addr:street":"Us Hwy 11 N",
    "iso:country":"US",
    "sg:address":"2021 US Hwy 11 N",
    "sg:city":"Picayune",
    "sg:classifiers":[
        {
            "category":"Retail",
            "subcategory":"Laundry & Dry Cleaning",
            "type":"Services"
        }
    ],
    "sg:phone":"+1 601 798 3288",
    "sg:postcode":"39466",
    "sg:province":"MS",
    "sg:tags":[
        "cleaners"
    ],
    "wof:name":"Handy Cleaners",
    "wof:placetype":"venue"
},
  "geometry": {"coordinates":[-89.66510100000001,30.559136],"type":"Point"}
}