{
  "type": "Feature",
  "properties": {
    "addr:full":"6639 Edmonton St Horn Lake MS 38637",
    "addr:housenumber":"6639",
    "addr:postcode":"38637",
    "addr:street":"Edmonton St",
    "iso:country":"US",
    "sg:address":"6639 Edmonton St",
    "sg:city":"Horn Lake",
    "sg:classifiers":[
        {
            "category":"Personal",
            "type":"Services"
        }
    ],
    "sg:phone":"+1 662 342 9202",
    "sg:postcode":"38637",
    "sg:province":"MS",
    "sg:tags":[
        "therapist",
        "massage"
    ],
    "wof:name":"Nature's Grace Massage",
    "wof:placetype":"venue"
},
  "geometry": {"coordinates":[-90.06744999999999,34.959516],"type":"Point"}
}