{
  "type": "Feature",
  "properties": {
    "iso:country":"US",
    "sg:address":"4958 Forest Hill Irene Rd",
    "sg:city":"Memphis",
    "sg:classifiers":[
        {
            "category":"Farming",
            "subcategory":"Farm",
            "type":"Manufacturing & Wholesale Goods"
        }
    ],
    "sg:phone":"+1 901 754 7554",
    "sg:postcode":"38125",
    "sg:province":"MS",
    "sg:tags":[
        "crop",
        "general"
    ],
    "wof:name":"Desoto Farms LLC",
    "wof:placetype":"venue"
},
  "geometry": {"coordinates":[-89.759615,35.006029],"type":"Point"}
}