{
  "type": "Feature",
  "properties": {
    "iso:country":"US",
    "sg:address":"342 2nd St",
    "sg:city":"Belmont",
    "sg:classifiers":[
        {
            "category":"Banks & Credit Unions",
            "subcategory":"Bank",
            "type":"Services"
        }
    ],
    "sg:phone":"+1 662 454 0001",
    "sg:postcode":"38827",
    "sg:province":"AL",
    "wof:name":"Spirit Bank",
    "wof:placetype":"venue"
},
  "geometry": {"coordinates":[-88.2075,34.507785],"type":"Point"}
}