{
  "type": "Feature",
  "properties": {
    "iso:country":"US",
    "sg:address":"520 George St",
    "sg:city":"Jackson",
    "sg:classifiers":[
        {
            "category":"Organizations",
            "subcategory":"Non-profit Organization",
            "type":"Services"
        }
    ],
    "sg:phone":"+1 601 969 1200",
    "sg:postcode":"39202",
    "sg:province":"MS",
    "wof:name":"Mississippi Center-Public Plcy",
    "wof:placetype":"venue"
},
  "geometry": {"coordinates":[-90.180661,32.30618],"type":"Point"}
}