{
  "type": "Feature",
  "properties": {
    "iso:country":"US",
    "sg:address":"3655 US Hwy 51",
    "sg:city":"Senatobia",
    "sg:classifiers":[
        {
            "category":"Shopping",
            "subcategory":"Florist",
            "type":"Retail Goods"
        }
    ],
    "sg:phone":"+1 662 562 7777",
    "sg:postcode":"38668",
    "sg:province":"MS",
    "wof:name":"Ever Blooms",
    "wof:placetype":"venue"
},
  "geometry": {"coordinates":[-89.968486,34.618986],"type":"Point"}
}