{
  "type": "Feature",
  "properties": {
    "iso:country":"US",
    "sg:address":"4045 Hwy 19 S",
    "sg:city":"Meridian",
    "sg:classifiers":[
        {
            "category":"Building & Trades",
            "subcategory":"Construction",
            "type":"Services"
        }
    ],
    "sg:phone":"+1 601 644 3305",
    "sg:postcode":"39301",
    "sg:province":"MS",
    "sg:tags":[
        "residential",
        "general",
        "contractor"
    ],
    "wof:name":"Mike Holloman's Construction",
    "wof:placetype":"venue"
},
  "geometry": {"coordinates":[-88.501332,32.291543],"type":"Point"}
}