{
  "type": "Feature",
  "properties": {
    "iso:country":"US",
    "sg:address":"1104 Iberville Dr",
    "sg:city":"Ocean Springs",
    "sg:classifiers":[
        {
            "category":"Professional",
            "subcategory":"Engineering",
            "type":"Services"
        }
    ],
    "sg:phone":"+1 228 324 2272",
    "sg:postcode":"39564",
    "sg:province":"MS",
    "sg:tags":[
        "engineer"
    ],
    "wof:name":"Soil Testing Engineers",
    "wof:placetype":"venue"
},
  "geometry": {"coordinates":[-88.823807,30.417634],"type":"Point"}
}