{
  "type": "Feature",
  "properties": {
    "addr:full":"10534 Shore Cove Biloxi MS 39532",
    "addr:housenumber":"10534",
    "addr:postcode":"39532",
    "addr:street":"Shore Cove",
    "iso:country":"US",
    "sg:address":"10534 Shore Cove",
    "sg:city":"Biloxi",
    "sg:classifiers":[
        {
            "category":"Personal",
            "subcategory":"Barber",
            "type":"Services"
        }
    ],
    "sg:phone":"+1 228 354 8962",
    "sg:postcode":"39532",
    "sg:province":"MS",
    "wof:name":"Patricia Southard",
    "wof:placetype":"venue"
},
  "geometry": {"coordinates":[-89.005976,30.439492],"type":"Point"}
}