{
  "type": "Feature",
  "properties": {
    "iso:country":"US",
    "sg:address":"305 W Moody St",
    "sg:city":"Poplarville",
    "sg:classifiers":[
        {
            "category":"Health Services",
            "subcategory":"Hospital",
            "type":"Services"
        }
    ],
    "sg:phone":"+1 601 795 4543",
    "sg:postcode":"39470",
    "sg:province":"MS",
    "wof:name":"Pearl River County Hospital",
    "wof:placetype":"venue"
},
  "geometry": {"coordinates":[-89.54135100000001,30.857177],"type":"Point"}
}