{
  "type": "Feature",
  "properties": {
    "addr:full":"620 Washington Ave Greenville MS 38701",
    "addr:housenumber":"620",
    "addr:postcode":"38701",
    "addr:street":"Washington Ave",
    "iso:country":"US",
    "sg:address":"620 Washington Ave",
    "sg:city":"Greenville",
    "sg:classifiers":[
        {
            "category":"Shopping",
            "subcategory":"Discount & Variety Stores",
            "type":"Retail Goods"
        }
    ],
    "sg:phone":"+1 662 332 0173",
    "sg:postcode":"38701",
    "sg:province":"MS",
    "sg:tags":[
        "merchandise",
        "general"
    ],
    "wof:name":"Freds",
    "wof:placetype":"venue"
},
  "geometry": {"coordinates":[-91.058481,33.410128],"type":"Point"}
}