{
  "type": "Feature",
  "properties": {
    "addr:full":"289 Petty Rd Golden MS 38847",
    "addr:housenumber":"289",
    "addr:postcode":"38847",
    "addr:street":"Petty Rd",
    "iso:country":"US",
    "sg:address":"289 Petty Rd",
    "sg:city":"Golden",
    "sg:classifiers":[
        {
            "category":"Home & Garden",
            "subcategory":"Furniture",
            "type":"Retail Goods"
        }
    ],
    "sg:phone":"+1 662 676 8716",
    "sg:postcode":"38847",
    "sg:province":"MS",
    "wof:name":"Magnolia Bay Furniture Mf",
    "wof:placetype":"venue"
},
  "geometry": {"coordinates":[-88.19820199999999,34.395731],"type":"Point"}
}