{
  "type": "Feature",
  "properties": {
    "addr:full":"157 Beacon St Laurel MS 39440",
    "addr:housenumber":"157",
    "addr:postcode":"39440",
    "addr:street":"Beacon St",
    "iso:country":"US",
    "sg:address":"157 Beacon St",
    "sg:city":"Laurel",
    "sg:classifiers":[
        {
            "category":"Building & Trades",
            "subcategory":"Equipment Rental",
            "type":"Services"
        }
    ],
    "sg:phone":"+1 601 649 3403",
    "sg:postcode":"39440",
    "sg:province":"MS",
    "sg:tags":[
        "television"
    ],
    "wof:name":"E-Z Pay Rentals",
    "wof:placetype":"venue"
},
  "geometry": {"coordinates":[-89.133476,31.690795],"type":"Point"}
}