{
  "type": "Feature",
  "properties": {
    "iso:country":"US",
    "sg:address":"4820 Courthouse Rd",
    "sg:city":"Gulfport",
    "sg:classifiers":[
        {
            "category":"Banks & Credit Unions",
            "subcategory":"Investment Brokerage",
            "type":"Services"
        }
    ],
    "sg:phone":"+1 228 896 5558",
    "sg:postcode":"39507",
    "sg:province":"MS",
    "sg:tags":[
        "security"
    ],
    "wof:name":"Pass Christian Investors Inc",
    "wof:placetype":"venue"
},
  "geometry": {"coordinates":[-89.043646,30.413219],"type":"Point"}
}