{
  "type": "Feature",
  "properties": {
    "addr:full":"4515 Popps Ferry Rd Biloxi MS 39540",
    "addr:housenumber":"4515",
    "addr:postcode":"39540",
    "addr:street":"Popps Ferry Rd",
    "iso:country":"US",
    "sg:address":"4515 Popps Ferry Rd",
    "sg:city":"Biloxi",
    "sg:classifiers":[
        {
            "category":"Shopping",
            "subcategory":"Bicycles & Sporting Goods",
            "type":"Retail Goods"
        }
    ],
    "sg:phone":"+1 228 392 0355",
    "sg:postcode":"39540",
    "sg:province":"MS",
    "sg:tags":[
        "equipment",
        "hunting"
    ],
    "wof:name":"Cooks Guns Shop",
    "wof:placetype":"venue"
},
  "geometry": {"coordinates":[-88.916708,30.443127],"type":"Point"}
}