{
  "type": "Feature",
  "properties": {
    "addr:full":"1150 W Woodrow Wilson Ave Jackson MS 39213",
    "addr:housenumber":"1150",
    "addr:postcode":"39213",
    "addr:street":"W Woodrow Wilson Ave",
    "iso:country":"US",
    "sg:address":"1150 W Woodrow Wilson Ave",
    "sg:city":"Jackson",
    "sg:classifiers":[
        {
            "category":"Education",
            "subcategory":"School",
            "type":"Public Place"
        }
    ],
    "sg:phone":"+1 601 353 2750",
    "sg:postcode":"39213",
    "sg:province":"MS",
    "wof:name":"B W Abney Learning Ctr",
    "wof:placetype":"venue"
},
  "geometry": {"coordinates":[-90.21520700000001,32.324445],"type":"Point"}
}