{
  "type": "Feature",
  "properties": {
    "iso:country":"US",
    "sg:address":"13430 Dedeaux Rd",
    "sg:city":"Gulfport",
    "sg:classifiers":[
        {
            "category":"Retail",
            "subcategory":"Veterinary Services",
            "type":"Services"
        }
    ],
    "sg:phone":"+1 228 832 7188",
    "sg:postcode":"39503",
    "sg:province":"MS",
    "sg:tags":[
        "veterinarian",
        "animal"
    ],
    "wof:name":"Town & Cntry Veterinary Clinic",
    "wof:placetype":"venue"
},
  "geometry": {"coordinates":[-89.065849,30.449625],"type":"Point"}
}