{
  "type": "Feature",
  "properties": {
    "addr:full":"359 Co Rd 1371 Booneville MS 38829",
    "addr:housenumber":"359",
    "addr:postcode":"1371;38829",
    "addr:street":"Co Rd",
    "iso:country":"US",
    "sg:address":"359 Co Rd 1371",
    "sg:city":"Booneville",
    "sg:classifiers":[
        {
            "category":"Organizations",
            "subcategory":"Religious Organization",
            "type":"Services"
        }
    ],
    "sg:phone":"+1 662 720 1221",
    "sg:postcode":"38829",
    "sg:province":"MS",
    "wof:name":"Mount Olive Church of God",
    "wof:placetype":"venue"
},
  "geometry": {"coordinates":[-88.451307,34.717017],"type":"Point"}
}