{
  "type": "Feature",
  "properties": {
    "iso:country":"US",
    "sg:address":"227 E Lakeside Dr",
    "sg:city":"Hattiesburg",
    "sg:classifiers":[
        {
            "category":"Food & Beverages",
            "subcategory":"Groceries & Convenience Stores",
            "type":"Retail Goods"
        }
    ],
    "sg:phone":"+1 601 264 1877",
    "sg:postcode":"39402",
    "sg:province":"MS",
    "wof:name":"Mass Market Solutions Inc",
    "wof:placetype":"venue"
},
  "geometry": {"coordinates":[-89.36968299999999,31.303064],"type":"Point"}
}