{
  "type": "Feature",
  "properties": {
    "iso:country":"US",
    "sg:address":"459 Co Rd 241",
    "sg:city":"Vossburg",
    "sg:classifiers":[
        {
            "category":"Insurance",
            "subcategory":"Hazard Insurance",
            "type":"Services"
        }
    ],
    "sg:phone":"+1 601 787 4492",
    "sg:postcode":"39366",
    "sg:province":"MS",
    "sg:tags":[
        "bond"
    ],
    "wof:name":"D C Bail Bonding",
    "wof:placetype":"venue"
},
  "geometry": {"coordinates":[-88.894338,31.919852],"type":"Point"}
}