{
  "type": "Feature",
  "properties": {
    "iso:country":"US",
    "sg:address":"558 First South St",
    "sg:city":"Woodville",
    "sg:classifiers":[
        {
            "category":"Health Services",
            "subcategory":"Health Practitioner",
            "type":"Services"
        }
    ],
    "sg:phone":"+1 601 888 7944",
    "sg:postcode":"39669",
    "sg:province":"MS",
    "sg:tags":[
        "therapist",
        "physical"
    ],
    "wof:name":"Premier Physical Therapy",
    "wof:placetype":"venue"
},
  "geometry": {"coordinates":[-91.298086,31.102306],"type":"Point"}
}