{
  "type": "Feature",
  "properties": {
    "addr:full":"405 E Van Dorn Ave Holly Springs MS 38635",
    "addr:housenumber":"405",
    "addr:postcode":"38635",
    "addr:street":"E Van Dorn Ave",
    "iso:country":"US",
    "sg:address":"405 E Van Dorn Ave",
    "sg:city":"Holly Springs",
    "sg:classifiers":[
        {
            "category":"Restaurant",
            "type":"Food & Drink"
        }
    ],
    "sg:phone":"+1 662 252 5533",
    "sg:postcode":"38635",
    "sg:province":"MS",
    "wof:name":"Hot Wings Haven",
    "wof:placetype":"venue"
},
  "geometry": {"coordinates":[-89.435469,34.767571],"type":"Point"}
}