{
  "type": "Feature",
  "properties": {
    "iso:country":"US",
    "sg:address":"13243 County Farm Rd",
    "sg:city":"Gulfport",
    "sg:classifiers":[
        {
            "category":"Government",
            "subcategory":"Fire Station",
            "type":"Public Place"
        }
    ],
    "sg:phone":"+1 228 539 4414",
    "sg:postcode":"39503",
    "sg:province":"MS",
    "sg:tags":[
        "department"
    ],
    "wof:name":"Harrison County Fire Svc",
    "wof:placetype":"venue"
},
  "geometry": {"coordinates":[-89.187687,30.476459],"type":"Point"}
}