{
  "type": "Feature",
  "properties": {
    "iso:country":"US",
    "sg:address":"516 N Magnolia St",
    "sg:city":"Laurel",
    "sg:classifiers":[
        {
            "category":"Insurance",
            "subcategory":"Insurance Agent",
            "type":"Services"
        }
    ],
    "sg:phone":"+1 601 649 7431",
    "sg:postcode":"39440",
    "sg:province":"MS",
    "wof:name":"Terry Insurance",
    "wof:placetype":"venue"
},
  "geometry": {"coordinates":[-89.128241,31.695309],"type":"Point"}
}