{
  "type": "Feature",
  "properties": {
    "iso:country":"US",
    "sg:address":"1620 Old Hwy 12",
    "sg:city":"Starkville",
    "sg:classifiers":[
        {
            "category":"Building & Trades",
            "subcategory":"Construction",
            "type":"Services"
        }
    ],
    "sg:phone":"+1 662 324 2500",
    "sg:postcode":"39759",
    "sg:province":"MS",
    "sg:tags":[
        "general",
        "contractor"
    ],
    "wof:name":"Sam Oswalt & Son Inc",
    "wof:placetype":"venue"
},
  "geometry": {"coordinates":[-88.890457,33.433314],"type":"Point"}
}