{
  "type": "Feature",
  "properties": {
    "addr:full":"2718 Bartlett Ave Pascagoula MS 39567",
    "addr:housenumber":"2718",
    "addr:postcode":"39567",
    "addr:street":"Bartlett Ave",
    "iso:country":"US",
    "sg:address":"2718 Bartlett Ave",
    "sg:city":"Pascagoula",
    "sg:classifiers":[
        {
            "category":"Building & Trades",
            "subcategory":"Construction",
            "type":"Services"
        }
    ],
    "sg:phone":"+1 228 202 8094",
    "sg:postcode":"39567",
    "sg:province":"MS",
    "sg:tags":[
        "general",
        "contractor"
    ],
    "wof:name":"Charter Construction Group",
    "wof:placetype":"venue"
},
  "geometry": {"coordinates":[-88.535016,30.366242],"type":"Point"}
}