{
  "type": "Feature",
  "properties": {
    "addr:full":"1110 Irvin Farve Rd Pass Christian MS 39571",
    "addr:housenumber":"1110",
    "addr:postcode":"39571",
    "addr:street":"Irvin Farve Rd",
    "iso:country":"US",
    "sg:address":"1110 Irvin Farve Rd",
    "sg:city":"Pass Christian",
    "sg:classifiers":[
        {
            "category":"Building & Trades",
            "subcategory":"Construction",
            "type":"Services"
        }
    ],
    "sg:phone":"+1 228 255 9727",
    "sg:postcode":"39571",
    "sg:province":"MS",
    "sg:tags":[
        "excavation",
        "contractor"
    ],
    "wof:name":"Petes Backhoe Service",
    "wof:placetype":"venue"
},
  "geometry": {"coordinates":[-89.351251,30.412734],"type":"Point"}
}