{
  "type": "Feature",
  "properties": {
    "iso:country":"US",
    "sg:address":"1020 S Colorado St",
    "sg:city":"Greenville",
    "sg:classifiers":[
        {
            "category":"Organizations",
            "subcategory":"Religious Organization",
            "type":"Services"
        }
    ],
    "sg:phone":"+1 662 332 2952",
    "sg:postcode":"38703",
    "sg:province":"MS",
    "wof:name":"Grace United Methodist Church",
    "wof:placetype":"venue"
},
  "geometry": {"coordinates":[-91.03012,33.39323],"type":"Point"}
}