{
  "type": "Feature",
  "properties": {
    "iso:country":"US",
    "sg:address":"1324 Moss St",
    "sg:city":"Columbus",
    "sg:classifiers":[
        {
            "category":"Personal",
            "subcategory":"Beauty Salon",
            "type":"Services"
        }
    ],
    "sg:phone":"+1 662 327 1842",
    "sg:postcode":"39701",
    "sg:province":"MS",
    "sg:tags":[
        "shop"
    ],
    "wof:name":"You & Mrs Jones Salon Beauty",
    "wof:placetype":"venue"
},
  "geometry": {"coordinates":[-88.401022,33.510322],"type":"Point"}
}