{
  "type": "Feature",
  "properties": {
    "addr:full":"2085 Lakeland Dr Jackson MS 39216",
    "addr:housenumber":"2085",
    "addr:postcode":"39216",
    "addr:street":"Lakeland Dr",
    "iso:country":"US",
    "sg:address":"2085 Lakeland Dr",
    "sg:city":"Jackson",
    "sg:classifiers":[
        {
            "category":"Restaurant",
            "type":"Food & Drink"
        }
    ],
    "sg:phone":"+1 601 982 9004",
    "sg:postcode":"39216",
    "sg:province":"MS",
    "wof:name":"Penn's Fish House Inc",
    "wof:placetype":"venue"
},
  "geometry": {"coordinates":[-90.132178,32.332436],"type":"Point"}
}