{
  "type": "Feature",
  "properties": {
    "addr:full":"2715 Bullis Ave Gulfport MS 39501",
    "addr:housenumber":"2715",
    "addr:postcode":"39501",
    "addr:street":"Bullis Ave",
    "iso:country":"US",
    "sg:address":"2715 Bullis Ave",
    "sg:city":"Gulfport",
    "sg:classifiers":[
        {
            "category":"Professional",
            "subcategory":"Employment Agencies",
            "type":"Services"
        }
    ],
    "sg:phone":"+1 228 868 9191",
    "sg:postcode":"39501",
    "sg:province":"MS",
    "sg:tags":[
        "opportunity"
    ],
    "wof:name":"Spherion",
    "wof:placetype":"venue"
},
  "geometry": {"coordinates":[-89.07445199999999,30.384048],"type":"Point"}
}