{
  "type": "Feature",
  "properties": {
    "iso:country":"US",
    "sg:address":"179 Whitfield Rd",
    "sg:city":"Ovett",
    "sg:classifiers":[
        {
            "category":"Manufacturing",
            "subcategory":"Lumber",
            "type":"Manufacturing & Wholesale Goods"
        }
    ],
    "sg:phone":"+1 601 344 7285",
    "sg:postcode":"39464",
    "sg:province":"MS",
    "sg:tags":[
        "operation",
        "timber",
        "tract"
    ],
    "wof:name":"Knight Hall",
    "wof:placetype":"venue"
},
  "geometry": {"coordinates":[-88.942831,31.358178],"type":"Point"}
}