{
  "type": "Feature",
  "properties": {
    "iso:country":"US",
    "sg:address":"1050 Bill Strong Cir",
    "sg:city":"Edwards",
    "sg:classifiers":[
        {
            "category":"Food & Beverages",
            "subcategory":"Specialty",
            "type":"Retail Goods"
        }
    ],
    "sg:phone":"+1 601 885 9010",
    "sg:postcode":"39066",
    "sg:province":"MS",
    "sg:tags":[
        "health",
        "diet"
    ],
    "wof:name":"Hundred Natural Herbs Sales",
    "wof:placetype":"venue"
},
  "geometry": {"coordinates":[-90.616722,32.226966],"type":"Point"}
}