{
  "type": "Feature",
  "properties": {
    "iso:country":"US",
    "sg:address":"1217 McRaven Rd",
    "sg:city":"Clinton",
    "sg:classifiers":[
        {
            "category":"Home & Garden",
            "subcategory":"Building Materials",
            "type":"Retail Goods"
        }
    ],
    "sg:phone":"+1 601 922 0211",
    "sg:postcode":"39056",
    "sg:province":"MS",
    "sg:tags":[
        "shutter"
    ],
    "wof:name":"Old Town Wood Specialties",
    "wof:placetype":"venue"
},
  "geometry": {"coordinates":[-90.350194,32.299961],"type":"Point"}
}