{
  "type": "Feature",
  "properties": {
    "iso:country":"US",
    "sg:address":"60012 Little Rd",
    "sg:city":"Smithville",
    "sg:classifiers":[
        {
            "category":"Retail",
            "subcategory":"Auto Repair",
            "type":"Services"
        }
    ],
    "sg:phone":"+1 662 651 4979",
    "sg:postcode":"38870",
    "sg:province":"MS",
    "sg:tags":[
        "repairing",
        "automobile"
    ],
    "wof:name":"Tim's Repair Svc",
    "wof:placetype":"venue"
},
  "geometry": {"coordinates":[-88.365984,34.029552],"type":"Point"}
}