{
  "type": "Feature",
  "properties": {
    "addr:full":"708 Dunbar Ave Bay St Louis MS 39520",
    "addr:housenumber":"708",
    "addr:postcode":"39520",
    "addr:street":"Dunbar Ave",
    "iso:country":"US",
    "sg:address":"708 Dunbar Ave",
    "sg:city":"Bay St Louis",
    "sg:classifiers":[
        {
            "category":"Social Services",
            "type":"Services"
        }
    ],
    "sg:phone":"+1 228 467 7277",
    "sg:postcode":"39520",
    "sg:province":"MS",
    "sg:tags":[
        "organization",
        "welfare"
    ],
    "wof:name":"Goodwill Industries",
    "wof:placetype":"venue"
},
  "geometry": {"coordinates":[-89.337294,30.321226],"type":"Point"}
}