{
  "type": "Feature",
  "properties": {
    "iso:country":"US",
    "sg:address":"220 Woodlawn Dr",
    "sg:city":"Oxford",
    "sg:classifiers":[
        {
            "category":"Mining & Drilling",
            "type":"Manufacturing & Wholesale Goods"
        }
    ],
    "sg:phone":"+1 662 281 8589",
    "sg:postcode":"38655",
    "sg:province":"MS",
    "sg:tags":[
        "exploration"
    ],
    "wof:name":"Rpl Exploration Inc",
    "wof:placetype":"venue"
},
  "geometry": {"coordinates":[-89.57557300000001,34.364984],"type":"Point"}
}