{
  "type": "Feature",
  "properties": {
    "iso:country":"US",
    "sg:address":"111 W Shaw Ave",
    "sg:city":"Drew",
    "sg:classifiers":[
        {
            "category":"Professional",
            "subcategory":"Accounting & Tax Preparation",
            "type":"Services"
        }
    ],
    "sg:phone":"+1 662 745 6145",
    "sg:postcode":"38737",
    "sg:province":"MS",
    "wof:name":"Ricky Panel",
    "wof:placetype":"venue"
},
  "geometry": {"coordinates":[-90.529264,33.810023],"type":"Point"}
}