{
  "type": "Feature",
  "properties": {
    "addr:full":"305 N Court Ave Louisville MS 39339",
    "addr:housenumber":"305",
    "addr:postcode":"39339",
    "addr:street":"N Court Ave",
    "iso:country":"US",
    "sg:address":"305 N Court Ave",
    "sg:city":"Louisville",
    "sg:classifiers":[
        {
            "category":"Personal",
            "subcategory":"Beauty Salon",
            "type":"Services"
        }
    ],
    "sg:phone":"+1 662 773 5603",
    "sg:postcode":"39339",
    "sg:province":"MS",
    "sg:tags":[
        "shop"
    ],
    "wof:name":"Mark I Styling Studio",
    "wof:placetype":"venue"
},
  "geometry": {"coordinates":[-89.054205,33.127296],"type":"Point"}
}