{
  "type": "Feature",
  "properties": {
    "iso:country":"US",
    "sg:address":"1200 E Pass Rd",
    "sg:city":"Gulfport",
    "sg:classifiers":[
        {
            "category":"Insurance",
            "subcategory":"Insurance Agent",
            "type":"Services"
        }
    ],
    "sg:phone":"+1 228 896 7554",
    "sg:postcode":"39507",
    "sg:province":"MS",
    "wof:name":"Allstate",
    "wof:placetype":"venue"
},
  "geometry": {"coordinates":[-89.028385,30.39836],"type":"Point"}
}