{
  "type": "Feature",
  "properties": {
    "iso:country":"US",
    "sg:address":"605 N Rodgers Ave",
    "sg:city":"Louisville",
    "sg:classifiers":[
        {
            "category":"Building & Trades",
            "subcategory":"Construction",
            "type":"Services"
        }
    ],
    "sg:phone":"+1 662 773 9518",
    "sg:postcode":"39339",
    "sg:province":"MS",
    "sg:tags":[
        "house",
        "apartment",
        "ope"
    ],
    "wof:name":"De Shaz Apartments",
    "wof:placetype":"venue"
},
  "geometry": {"coordinates":[-89.051062,33.131812],"type":"Point"}
}