{
  "type": "Feature",
  "properties": {
    "addr:full":"368 Old Hwy 49 Wiggins MS 39577",
    "addr:housenumber":"368",
    "addr:postcode":"39577",
    "addr:street":"Old Hwy 49",
    "iso:country":"US",
    "sg:address":"368 Old Hwy 49",
    "sg:city":"Wiggins",
    "sg:classifiers":[
        {
            "category":"Building & Trades",
            "subcategory":"Construction",
            "type":"Services"
        }
    ],
    "sg:phone":"+1 601 928 7291",
    "sg:postcode":"39577",
    "sg:province":"MS",
    "sg:tags":[
        "water",
        "well",
        "drilling"
    ],
    "wof:name":"Dale's Water Well Svc & Repair",
    "wof:placetype":"venue"
},
  "geometry": {"coordinates":[-89.126154,30.815674],"type":"Point"}
}