{
  "type": "Feature",
  "properties": {
    "iso:country":"US",
    "sg:address":"2734 Washington St",
    "sg:city":"Vicksburg",
    "sg:classifiers":[
        {
            "category":"Organizations",
            "subcategory":"Non-profit Organization",
            "type":"Services"
        },
        {
            "category":"Insurance",
            "subcategory":"Health Insurance",
            "type":"Services"
        }
    ],
    "sg:phone":"+1 601 638 6136",
    "sg:postcode":"39180",
    "sg:province":"MS",
    "sg:tags":[
        "plan"
    ],
    "sg:website":"www.dom.com",
    "wof:name":"Mississippi Regional Medicaid",
    "wof:placetype":"venue"
},
  "geometry": {"coordinates":[-90.88771199999999,32.333754],"type":"Point"}
}