{
  "type": "Feature",
  "properties": {
    "iso:country":"US",
    "sg:address":"13220 Goffville Rd",
    "sg:city":"Ocean Springs",
    "sg:classifiers":[
        {
            "category":"Real Estate",
            "subcategory":"Real Estate Agent",
            "type":"Services"
        }
    ],
    "sg:phone":"+1 228 875 8362",
    "sg:postcode":"39564",
    "sg:province":"MS",
    "sg:tags":[
        "acct",
        "broker"
    ],
    "wof:name":"Southern Relty SLS&srvc Incnc",
    "wof:placetype":"venue"
},
  "geometry": {"coordinates":[-88.83071700000001,30.447554],"type":"Point"}
}