{
  "type": "Feature",
  "properties": {
    "iso:country":"US",
    "sg:address":"110 US Hwy 11 S",
    "sg:city":"Picayune",
    "sg:classifiers":[
        {
            "category":"Insurance",
            "subcategory":"Insurance Agent",
            "type":"Services"
        }
    ],
    "sg:phone":"+1 601 798 4861",
    "sg:postcode":"39466",
    "sg:province":"MS",
    "wof:name":"Thigpen Insurance",
    "wof:placetype":"venue"
},
  "geometry": {"coordinates":[-89.679992,30.525709],"type":"Point"}
}