{
  "type": "Feature",
  "properties": {
    "iso:country":"US",
    "sg:address":"3477 Deasonville Rd",
    "sg:city":"Vaughan",
    "sg:classifiers":[
        {
            "category":"Organizations",
            "subcategory":"Religious Organization",
            "type":"Services"
        }
    ],
    "sg:phone":"+1 662 673 0051",
    "sg:postcode":"39179",
    "sg:province":"MS",
    "sg:tags":[
        "church"
    ],
    "wof:name":"Bell's Chapel Missionary",
    "wof:placetype":"venue"
},
  "geometry": {"coordinates":[-90.095157,32.788084],"type":"Point"}
}