{
  "type": "Feature",
  "properties": {
    "iso:country":"US",
    "sg:address":"5858 Ridgewood Rd",
    "sg:city":"Jackson",
    "sg:classifiers":[
        {
            "category":"Health Services",
            "subcategory":"Doctor",
            "type":"Services"
        }
    ],
    "sg:phone":"+1 601 956 2944",
    "sg:postcode":"39211",
    "sg:province":"MS",
    "wof:name":"Pat Welsh DDS",
    "wof:placetype":"venue"
},
  "geometry": {"coordinates":[-90.141831,32.387624],"type":"Point"}
}