{
  "type": "Feature",
  "properties": {
    "iso:country":"US",
    "sg:address":"1012 W Union St",
    "sg:city":"Greenville",
    "sg:classifiers":[
        {
            "category":"Place Of Worship",
            "subcategory":"Church",
            "type":"Public Place"
        },
        {
            "category":"Place Of Worship",
            "type":"Public Place"
        },
        {
            "category":"Organizations",
            "subcategory":"Religious Organization",
            "type":"Services"
        }
    ],
    "sg:phone":"+1 662 332 5637",
    "sg:postcode":"38701",
    "sg:province":"MS",
    "sg:tags":[
        "god",
        "churches-church",
        "christ",
        "churches-pentecostal"
    ],
    "wof:name":"Lily Of The Vly Ch God In Chri",
    "wof:placetype":"venue"
},
  "geometry": {"coordinates":[-91.046796,33.413697],"type":"Point"}
}