{
  "type": "Feature",
  "properties": {
    "iso:country":"US",
    "sg:address":"120 N Front St",
    "sg:city":"Senatobia",
    "sg:classifiers":[
        {
            "category":"Professional",
            "subcategory":"Lawyer & Legal Services",
            "type":"Services"
        }
    ],
    "sg:phone":"+1 662 562 4477",
    "sg:postcode":"38668",
    "sg:province":"MS",
    "sg:tags":[
        "attorney",
        "law",
        "disability",
        "security",
        "social"
    ],
    "wof:name":"Wilson Joe Morgan Attorney",
    "wof:placetype":"venue"
},
  "geometry": {"coordinates":[-89.964792,34.619767],"type":"Point"}
}