{
  "type": "Feature",
  "properties": {
    "addr:full":"270 Matagorda Rd Coahoma MS 38617",
    "addr:housenumber":"270",
    "addr:postcode":"38617",
    "addr:street":"Matagorda Rd",
    "iso:country":"US",
    "sg:address":"270 Matagorda Rd",
    "sg:city":"Coahoma",
    "sg:classifiers":[
        {
            "category":"Organizations",
            "subcategory":"Community Association",
            "type":"Services"
        }
    ],
    "sg:phone":"+1 662 358 4563",
    "sg:postcode":"38617",
    "sg:province":"MS",
    "wof:name":"Coahoma Opportunity",
    "wof:placetype":"venue"
},
  "geometry": {"coordinates":[-90.45010000000001,34.395554],"type":"Point"}
}