{
  "type": "Feature",
  "properties": {
    "iso:country":"US",
    "sg:address":"237 Short Columbia St",
    "sg:city":"Hattiesburg",
    "sg:classifiers":[
        {
            "category":"Personal",
            "subcategory":"Beauty Salon",
            "type":"Services"
        }
    ],
    "sg:phone":"+1 601 545 2271",
    "sg:postcode":"39401",
    "sg:province":"MS",
    "sg:tags":[
        "shop"
    ],
    "wof:name":"New Innovations Phase II",
    "wof:placetype":"venue"
},
  "geometry": {"coordinates":[-89.30744799999999,31.335022],"type":"Point"}
}