{
  "type": "Feature",
  "properties": {
    "iso:country":"US",
    "sg:address":"1000 Turtle Creek Dr",
    "sg:city":"Hattiesburg",
    "sg:classifiers":[
        {
            "category":"Manufacturing",
            "subcategory":"Chemicals & Compounds",
            "type":"Manufacturing & Wholesale Goods"
        },
        {
            "category":"Personal",
            "subcategory":"Beauty Salon",
            "type":"Services"
        }
    ],
    "sg:phone":"+1 601 261 0551",
    "sg:postcode":"39402",
    "sg:province":"MS",
    "sg:tags":[
        "preparation",
        "toilet",
        "manicuring",
        "mfg"
    ],
    "wof:name":"Nailshop",
    "wof:placetype":"venue"
},
  "geometry": {"coordinates":[-89.3762,31.330083],"type":"Point"}
}