{
  "type": "Feature",
  "properties": {
    "iso:country":"US",
    "sg:address":"2136 Kirk Rd",
    "sg:city":"Yazoo City",
    "sg:classifiers":[
        {
            "category":"Building & Trades",
            "subcategory":"Construction",
            "type":"Services"
        }
    ],
    "sg:phone":"+1 662 746 7752",
    "sg:postcode":"39194",
    "sg:province":"MS",
    "sg:tags":[
        "residential"
    ],
    "wof:name":"Jerry Dunn Building",
    "wof:placetype":"venue"
},
  "geometry": {"coordinates":[-90.356629,32.734158],"type":"Point"}
}