{
  "type": "Feature",
  "properties": {
    "iso:country":"US",
    "sg:address":"239 S Railroad Blvd",
    "sg:city":"Mc Comb",
    "sg:classifiers":[
        {
            "category":"Railroad",
            "type":"Transportation"
        }
    ],
    "sg:phone":"+1 601 684 9080",
    "sg:postcode":"39648",
    "sg:province":"MS",
    "sg:tags":[
        "operator",
        "line"
    ],
    "wof:name":"Mid American Distribution Ctrs",
    "wof:placetype":"venue"
},
  "geometry": {"coordinates":[-90.451139,31.242164],"type":"Point"}
}