{
  "type": "Feature",
  "properties": {
    "iso:country":"US",
    "sg:address":"2010 N Lamar St",
    "sg:city":"Jackson",
    "sg:classifiers":[
        {
            "category":"Retail",
            "subcategory":"Repair Shop",
            "type":"Services"
        }
    ],
    "sg:phone":"+1 601 352 1886",
    "sg:postcode":"39202",
    "sg:province":"MS",
    "sg:tags":[
        "equipment",
        "dental",
        "appliance",
        "lab"
    ],
    "wof:name":"Powers Repair",
    "wof:placetype":"venue"
},
  "geometry": {"coordinates":[-90.18423300000001,32.320346],"type":"Point"}
}