{
  "type": "Feature",
  "properties": {
    "addr:full":"17413 Landon Rd Gulfport MS 39503",
    "addr:housenumber":"17413",
    "addr:postcode":"39503",
    "addr:street":"Landon Rd",
    "iso:country":"US",
    "sg:address":"17413 Landon Rd",
    "sg:city":"Gulfport",
    "sg:classifiers":[
        {
            "category":"Building & Trades",
            "subcategory":"Equipment Rental",
            "type":"Services"
        }
    ],
    "sg:phone":"+1 228 831 9070",
    "sg:postcode":"39503",
    "sg:province":"MS",
    "sg:tags":[
        "store",
        "general"
    ],
    "wof:name":"Family Market",
    "wof:placetype":"venue"
},
  "geometry": {"coordinates":[-89.13086699999999,30.438283],"type":"Point"}
}