{
  "type": "Feature",
  "properties": {
    "iso:country":"US",
    "sg:address":"213 S Main St",
    "sg:city":"Calhoun City",
    "sg:classifiers":[
        {
            "category":"Autos & Motor Vehicles",
            "subcategory":"Automobile Sales",
            "type":"Retail Goods"
        }
    ],
    "sg:phone":"+1 662 628 5166",
    "sg:postcode":"38916",
    "sg:province":"MS",
    "sg:tags":[
        "car",
        "dealer"
    ],
    "wof:name":"Hawkins Motor Co",
    "wof:placetype":"venue"
},
  "geometry": {"coordinates":[-89.311424,33.853828],"type":"Point"}
}