{
  "type": "Feature",
  "properties": {
    "iso:country":"US",
    "sg:address":"318 Commerce St",
    "sg:city":"Gulfport",
    "sg:classifiers":[
        {
            "category":"Organizations",
            "subcategory":"Religious Organization",
            "type":"Services"
        }
    ],
    "sg:phone":"+1 228 896 6944",
    "sg:postcode":"39507",
    "sg:province":"MS",
    "wof:name":"Jehovahs Witnesses East",
    "wof:placetype":"venue"
},
  "geometry": {"coordinates":[-89.046147,30.398281],"type":"Point"}
}