{
  "type": "Feature",
  "properties": {
    "iso:country":"US",
    "sg:address":"6360 Cole Rd",
    "sg:city":"Ridgeland",
    "sg:classifiers":[
        {
            "category":"Wholesale",
            "subcategory":"Hardware",
            "type":"Manufacturing & Wholesale Goods"
        }
    ],
    "sg:phone":"+1 601 977 9779",
    "sg:postcode":"39157",
    "sg:province":"MS",
    "sg:tags":[
        "stapler",
        "tacker",
        "staple"
    ],
    "wof:name":"Fastening Solutions Inc",
    "wof:placetype":"venue"
},
  "geometry": {"coordinates":[-90.17875600000001,32.400665],"type":"Point"}
}