{
  "type": "Feature",
  "properties": {
    "addr:full":"469 Cleveland St Greenville MS 38701",
    "addr:housenumber":"469",
    "addr:postcode":"38701",
    "addr:street":"Cleveland St",
    "iso:country":"US",
    "sg:address":"469 Cleveland St",
    "sg:city":"Greenville",
    "sg:classifiers":[
        {
            "category":"Food & Beverages",
            "subcategory":"Candy",
            "type":"Retail Goods"
        }
    ],
    "sg:phone":"+1 662 332 8509",
    "sg:postcode":"38701",
    "sg:province":"MS",
    "sg:tags":[
        "confectionery"
    ],
    "wof:name":"Candyland",
    "wof:placetype":"venue"
},
  "geometry": {"coordinates":[-91.046295,33.41212],"type":"Point"}
}