{
  "type": "Feature",
  "properties": {
    "iso:country":"US",
    "sg:address":"130 Shelby Speights Dr",
    "sg:city":"Purvis",
    "sg:classifiers":[
        {
            "category":"Professional",
            "subcategory":"Lawyer & Legal Services",
            "type":"Services"
        }
    ],
    "sg:phone":"+1 601 794 2445",
    "sg:postcode":"39475",
    "sg:province":"MS",
    "sg:tags":[
        "attorney"
    ],
    "wof:name":"Mc Farland & Mc Farland",
    "wof:placetype":"venue"
},
  "geometry": {"coordinates":[-89.418347,31.143343],"type":"Point"}
}