{
  "type": "Feature",
  "properties": {
    "iso:country":"US",
    "sg:address":"107 Cedarwood Pt",
    "sg:city":"Pass Christian",
    "sg:classifiers":[
        {
            "category":"Manufacturing",
            "subcategory":"Textiles",
            "type":"Manufacturing & Wholesale Goods"
        }
    ],
    "sg:phone":"+1 228 452 4520",
    "sg:postcode":"39571",
    "sg:province":"MS",
    "sg:tags":[
        "finishing",
        "plant",
        "cotton"
    ],
    "wof:name":"Suns of Beaches",
    "wof:placetype":"venue"
},
  "geometry": {"coordinates":[-89.28457299999999,30.327014],"type":"Point"}
}