{
  "type": "Feature",
  "properties": {
    "addr:full":"415 Hwy 49 S Richland MS 39218",
    "addr:housenumber":"415",
    "addr:postcode":"39218",
    "addr:street":"Hwy 49 S",
    "iso:country":"US",
    "sg:address":"415 Hwy 49 S",
    "sg:city":"Richland",
    "sg:classifiers":[
        {
            "category":"Autos & Motor Vehicles",
            "subcategory":"Fuel & Gas Station",
            "type":"Retail Goods"
        }
    ],
    "sg:phone":"+1 601 939 7672",
    "sg:postcode":"39218",
    "sg:province":"MS",
    "sg:tags":[
        "plaza",
        "truck",
        "stops"
    ],
    "wof:name":"Delta Travel Ctr",
    "wof:placetype":"venue"
},
  "geometry": {"coordinates":[-90.13683899999999,32.183568],"type":"Point"}
}