{
  "type": "Feature",
  "properties": {
    "addr:full":"1416 Old Brandon Rd Jackson MS 39232",
    "addr:housenumber":"1416",
    "addr:postcode":"39232",
    "addr:street":"Old Brandon Rd",
    "iso:country":"US",
    "sg:address":"1416 Old Brandon Rd",
    "sg:city":"Jackson",
    "sg:classifiers":[
        {
            "category":"Building & Trades",
            "subcategory":"Construction",
            "type":"Services"
        }
    ],
    "sg:phone":"+1 601 932 0071",
    "sg:postcode":"39232",
    "sg:province":"MS",
    "sg:tags":[
        "wall",
        "modular"
    ],
    "wof:name":"ABS Services Inc",
    "wof:placetype":"venue"
},
  "geometry": {"coordinates":[-90.157394,32.281431],"type":"Point"}
}