{
  "type": "Feature",
  "properties": {
    "iso:country":"US",
    "sg:address":"107 Water Tank Rd",
    "sg:city":"Brandon",
    "sg:classifiers":[
        {
            "category":"Wholesale",
            "subcategory":"Electrical",
            "type":"Manufacturing & Wholesale Goods"
        }
    ],
    "sg:phone":"+1 601 919 3664",
    "sg:postcode":"39073",
    "sg:province":"MS",
    "sg:tags":[
        "control",
        "security",
        "system"
    ],
    "wof:name":"Metro Security & Alarm Svc",
    "wof:placetype":"venue"
},
  "geometry": {"coordinates":[-90.061989,32.179238],"type":"Point"}
}