{
  "type": "Feature",
  "properties": {
    "iso:country":"US",
    "sg:address":"102 Camelia Way",
    "sg:city":"Brandon",
    "sg:classifiers":[
        {
            "category":"Professional",
            "type":"Services"
        }
    ],
    "sg:phone":"+1 601 992 1096",
    "sg:postcode":"39047",
    "sg:province":"MS",
    "wof:name":"Southern Forest Products",
    "wof:placetype":"venue"
},
  "geometry": {"coordinates":[-90.008219,32.372147],"type":"Point"}
}