{
  "type": "Feature",
  "properties": {
    "addr:full":"3705 N West St Jackson MS 39216",
    "addr:housenumber":"3705",
    "addr:postcode":"39216",
    "addr:street":"N West St",
    "iso:country":"US",
    "sg:address":"3705 N West St",
    "sg:city":"Jackson",
    "sg:classifiers":[
        {
            "category":"Shopping",
            "subcategory":"Used Merchandise",
            "type":"Retail Goods"
        }
    ],
    "sg:phone":"+1 601 713 2274",
    "sg:postcode":"39216",
    "sg:province":"MS",
    "sg:tags":[
        "pawnbroker"
    ],
    "wof:name":"Top Dollar Pawn Gun & Car",
    "wof:placetype":"venue"
},
  "geometry": {"coordinates":[-90.181938,32.340012],"type":"Point"}
}