{
  "type": "Feature",
  "properties": {
    "addr:full":"3160 Co Rd 615 Ripley MS 38663",
    "addr:housenumber":"3160;615",
    "addr:postcode":"38663",
    "addr:street":"Co Rd",
    "iso:country":"US",
    "sg:address":"3160 Co Rd 615",
    "sg:city":"Ripley",
    "sg:classifiers":[
        {
            "category":"Retail",
            "subcategory":"Repair Shop",
            "type":"Services"
        }
    ],
    "sg:phone":"+1 662 837 3862",
    "sg:postcode":"38663",
    "sg:province":"MS",
    "sg:tags":[
        "air",
        "conditioning",
        "heating"
    ],
    "wof:name":"Hopkins Heating & Air Service",
    "wof:placetype":"venue"
},
  "geometry": {"coordinates":[-88.800394,34.696697],"type":"Point"}
}