{
  "type": "Feature",
  "properties": {
    "iso:country":"US",
    "sg:address":"1109 Stark Rd",
    "sg:city":"Starkville",
    "sg:classifiers":[
        {
            "category":"Personal",
            "subcategory":"Barber",
            "type":"Services"
        }
    ],
    "sg:phone":"+1 662 323 0771",
    "sg:postcode":"39759",
    "sg:province":"MS",
    "sg:tags":[
        "shop"
    ],
    "wof:name":"Loyd & Co",
    "wof:placetype":"venue"
},
  "geometry": {"coordinates":[-88.845429,33.45515],"type":"Point"}
}