{
  "type": "Feature",
  "properties": {
    "addr:full":"239 US Hwy 90 Bay St Louis MS 39520",
    "addr:housenumber":"239",
    "addr:postcode":"39520",
    "addr:street":"Us Hwy 90",
    "iso:country":"US",
    "sg:address":"239 US Hwy 90",
    "sg:city":"Bay St Louis",
    "sg:classifiers":[
        {
            "category":"Utilities",
            "subcategory":"Electric",
            "type":"Services"
        }
    ],
    "sg:phone":"+1 228 467 3741",
    "sg:postcode":"39520",
    "sg:province":"MS",
    "sg:tags":[
        "company"
    ],
    "wof:name":"M S Power Co Bayou Lacroix Sub",
    "wof:placetype":"venue"
},
  "geometry": {"coordinates":[-89.331801,30.320008],"type":"Point"}
}