{
  "type": "Feature",
  "properties": {
    "iso:country":"US",
    "sg:address":"1030 Hwy 471",
    "sg:city":"Brandon",
    "sg:classifiers":[
        {
            "category":"Building & Trades",
            "subcategory":"Construction",
            "type":"Services"
        }
    ],
    "sg:phone":"+1 601 824 3424",
    "sg:postcode":"39042",
    "sg:province":"MS",
    "sg:tags":[
        "home",
        "builder"
    ],
    "wof:name":"Southern Tradition Homes LLC",
    "wof:placetype":"venue"
},
  "geometry": {"coordinates":[-89.99483499999999,32.300436],"type":"Point"}
}