{
  "type": "Feature",
  "properties": {
    "iso:country":"US",
    "sg:address":"513 Bank St",
    "sg:city":"Union",
    "sg:classifiers":[
        {
            "category":"Retail",
            "subcategory":"Repair Shop",
            "type":"Services"
        }
    ],
    "sg:phone":"+1 601 774 5661",
    "sg:postcode":"39365",
    "sg:province":"MS",
    "sg:tags":[
        "repairing",
        "lawn",
        "mower"
    ],
    "wof:name":"Finley Repair Svc",
    "wof:placetype":"venue"
},
  "geometry": {"coordinates":[-89.12027500000001,32.569138],"type":"Point"}
}