{
  "type": "Feature",
  "properties": {
    "addr:full":"5036 State Hwy 547 Port Gibson MS 39150",
    "addr:housenumber":"5036",
    "addr:postcode":"39150",
    "addr:street":"State Hwy 547 Port Gibson",
    "iso:country":"US",
    "sg:address":"5036 State Hwy 547",
    "sg:city":"Port Gibson",
    "sg:classifiers":[
        {
            "category":"Professional",
            "subcategory":"Business Services",
            "type":"Services"
        }
    ],
    "sg:phone":"+1 601 437 9226",
    "sg:postcode":"39150",
    "sg:province":"MS",
    "sg:tags":[
        "recording",
        "record",
        "studio",
        "label"
    ],
    "wof:name":"Mars LLC",
    "wof:placetype":"venue"
},
  "geometry": {"coordinates":[-90.931207,31.916969],"type":"Point"}
}