{
  "type": "Feature",
  "properties": {
    "iso:country":"US",
    "sg:address":"4850 Moon Lake Rd",
    "sg:city":"Coahoma",
    "sg:classifiers":[
        {
            "category":"Food & Beverages",
            "subcategory":"Groceries & Convenience Stores",
            "type":"Retail Goods"
        }
    ],
    "sg:phone":"+1 662 337 2732",
    "sg:postcode":"38617",
    "sg:province":"MS",
    "wof:name":"Bmw Pit Stop",
    "wof:placetype":"venue"
},
  "geometry": {"coordinates":[-90.556229,34.460232],"type":"Point"}
}