{
  "type": "Feature",
  "properties": {
    "addr:full":"466 Hog Chain Dr SE Bogue Chitto MS 39629",
    "addr:housenumber":"466",
    "addr:postcode":"39629",
    "addr:street":"Hog Chain Dr Se;Chitto",
    "iso:country":"US",
    "sg:address":"466 Hog Chain Dr SE",
    "sg:city":"Bogue Chitto",
    "sg:classifiers":[
        {
            "category":"Shopping",
            "subcategory":"Used Merchandise",
            "type":"Retail Goods"
        }
    ],
    "sg:phone":"+1 601 833 2920",
    "sg:postcode":"39629",
    "sg:province":"MS",
    "sg:tags":[
        "repair"
    ],
    "wof:name":"Pawn Plus",
    "wof:placetype":"venue"
},
  "geometry": {"coordinates":[-90.43933,31.527639],"type":"Point"}
}