{
  "type": "Feature",
  "properties": {
    "iso:country":"US",
    "sg:address":"1436 Hair St",
    "sg:city":"Jackson",
    "sg:classifiers":[
        {
            "category":"Organizations",
            "subcategory":"Religious Organization",
            "type":"Services"
        }
    ],
    "sg:phone":"+1 601 355 0744",
    "sg:postcode":"39204",
    "sg:province":"MS",
    "sg:tags":[
        "church"
    ],
    "wof:name":"Love Outreach Evan Pentecostal",
    "wof:placetype":"venue"
},
  "geometry": {"coordinates":[-90.20962900000001,32.288661],"type":"Point"}
}