{
  "type": "Feature",
  "properties": {
    "iso:country":"US",
    "sg:address":"614 Bay Haven Cove",
    "sg:city":"Biloxi",
    "sg:classifiers":[
        {
            "category":"Government",
            "subcategory":"Office",
            "type":"Public Place"
        }
    ],
    "sg:phone":"+1 228 388 8762",
    "sg:postcode":"39532",
    "sg:province":"MS",
    "sg:tags":[
        "executive"
    ],
    "wof:name":"Integrity Care Management Inc",
    "wof:placetype":"venue"
},
  "geometry": {"coordinates":[-88.959658,30.424961],"type":"Point"}
}