{
  "type": "Feature",
  "properties": {
    "iso:country":"US",
    "sg:address":"110 College St",
    "sg:city":"Batesville",
    "sg:classifiers":[
        {
            "category":"Education",
            "subcategory":"School",
            "type":"Public Place"
        }
    ],
    "sg:phone":"+1 662 563 4596",
    "sg:postcode":"38606",
    "sg:province":"MS",
    "wof:name":"Batesville Elementary School",
    "wof:placetype":"venue"
},
  "geometry": {"coordinates":[-89.95184999999999,34.317579],"type":"Point"}
}