{
  "type": "Feature",
  "properties": {
    "addr:full":"803 Hwy 98 E Columbia MS 39429",
    "addr:housenumber":"803",
    "addr:postcode":"39429",
    "addr:street":"Hwy 98 E",
    "iso:country":"US",
    "sg:address":"803 Hwy 98 E",
    "sg:city":"Columbia",
    "sg:classifiers":[
        {
            "category":"Shopping",
            "subcategory":"Clothing, Apparel, & Fashions",
            "type":"Retail Goods"
        }
    ],
    "sg:phone":"+1 601 736 1300",
    "sg:postcode":"39429",
    "sg:province":"MS",
    "wof:name":"Cato",
    "wof:placetype":"venue"
},
  "geometry": {"coordinates":[-89.81762000000001,31.238975],"type":"Point"}
}