{
  "type": "Feature",
  "properties": {
    "addr:full":"228 Timbermill Dr Madison MS 39110",
    "addr:housenumber":"228",
    "addr:postcode":"39110",
    "addr:street":"Timbermill Dr",
    "iso:country":"US",
    "sg:address":"228 Timbermill Dr",
    "sg:city":"Madison",
    "sg:classifiers":[
        {
            "category":"Building & Trades",
            "subcategory":"Plumbing",
            "type":"Services"
        }
    ],
    "sg:phone":"+1 601 856 0078",
    "sg:postcode":"39110",
    "sg:province":"MS",
    "sg:tags":[
        "contractor"
    ],
    "wof:name":"Johnny Rowland",
    "wof:placetype":"venue"
},
  "geometry": {"coordinates":[-90.100438,32.458374],"type":"Point"}
}