{
  "type": "Feature",
  "properties": {
    "iso:country":"US",
    "sg:address":"1305 S Broadway St",
    "sg:city":"Shelby",
    "sg:classifiers":[
        {
            "category":"Food & Beverages",
            "subcategory":"Groceries & Convenience Stores",
            "type":"Retail Goods"
        }
    ],
    "sg:phone":"+1 662 398 7788",
    "sg:postcode":"38774",
    "sg:province":"MS",
    "wof:name":"Super Saver",
    "wof:placetype":"venue"
},
  "geometry": {"coordinates":[-90.767916,33.949064],"type":"Point"}
}