{
  "type": "Feature",
  "properties": {
    "iso:country":"US",
    "sg:address":"1004 N Jackson St",
    "sg:city":"Starkville",
    "sg:classifiers":[
        {
            "category":"Communications",
            "subcategory":"Film & Video Production",
            "type":"Services"
        }
    ],
    "sg:phone":"+1 662 324 2489",
    "sg:postcode":"39759",
    "sg:province":"MS",
    "sg:tags":[
        "motion",
        "picture"
    ],
    "wof:name":"Broadcast Media",
    "wof:placetype":"venue"
},
  "geometry": {"coordinates":[-88.81464099999999,33.481922],"type":"Point"}
}