{
  "type": "Feature",
  "properties": {
    "iso:country":"US",
    "sg:address":"3707 Hwy 72 W",
    "sg:city":"Corinth",
    "sg:classifiers":[
        {
            "category":"Building & Trades",
            "subcategory":"Plumbing",
            "type":"Services"
        }
    ],
    "sg:phone":"+1 662 286 5613",
    "sg:postcode":"38834",
    "sg:province":"MS",
    "sg:tags":[
        "sheet",
        "work",
        "metal",
        "contractor"
    ],
    "wof:name":"Meyers Sheet Metal",
    "wof:placetype":"venue"
},
  "geometry": {"coordinates":[-88.563756,34.930924],"type":"Point"}
}