{
  "type": "Feature",
  "properties": {
    "iso:country":"US",
    "sg:address":"94 Co Rd 283",
    "sg:city":"Iuka",
    "sg:classifiers":[
        {
            "category":"Organizations",
            "subcategory":"Religious Organization",
            "type":"Services"
        }
    ],
    "sg:phone":"+1 662 423 5153",
    "sg:postcode":"38852",
    "sg:province":"MS",
    "sg:tags":[
        "church"
    ],
    "wof:name":"New Salem Baptist Church",
    "wof:placetype":"venue"
},
  "geometry": {"coordinates":[-88.259794,34.882137],"type":"Point"}
}