{
  "type": "Feature",
  "properties": {
    "addr:full":"8960 College St Olive Branch MS 38654",
    "addr:housenumber":"8960",
    "addr:postcode":"38654",
    "addr:street":"College St",
    "iso:country":"US",
    "sg:address":"8960 College St",
    "sg:city":"Olive Branch",
    "sg:classifiers":[
        {
            "category":"Banks & Credit Unions",
            "subcategory":"Investment Brokerage",
            "type":"Services"
        }
    ],
    "sg:phone":"+1 662 890 5688",
    "sg:postcode":"38654",
    "sg:province":"MS",
    "sg:tags":[
        "security"
    ],
    "wof:name":"Edward Jones Co",
    "wof:placetype":"venue"
},
  "geometry": {"coordinates":[-89.84209799999999,34.95908],"type":"Point"}
}