{
  "type": "Feature",
  "properties": {
    "iso:country":"US",
    "sg:address":"124 Mc Comb Ave",
    "sg:city":"Port Gibson",
    "sg:classifiers":[
        {
            "category":"Education",
            "subcategory":"School",
            "type":"Public Place"
        }
    ],
    "sg:phone":"+1 601 437 4292",
    "sg:postcode":"39150",
    "sg:province":"MS",
    "sg:website":"www.chamberlain-hunt.com",
    "wof:name":"Chamberlain Hunt Academy",
    "wof:placetype":"venue"
},
  "geometry": {"coordinates":[-90.98748500000001,31.946762],"type":"Point"}
}