{
  "type": "Feature",
  "properties": {
    "iso:country":"US",
    "sg:address":"110 Stenson Loop",
    "sg:city":"Vicksburg",
    "sg:classifiers":[
        {
            "category":"Building & Trades",
            "subcategory":"Construction",
            "type":"Services"
        }
    ],
    "sg:phone":"+1 601 634 1529",
    "sg:postcode":"39180",
    "sg:province":"MS",
    "sg:tags":[
        "contractor"
    ],
    "wof:name":"RE Barnes Contractors Inc",
    "wof:placetype":"venue"
},
  "geometry": {"coordinates":[-90.816849,32.325737],"type":"Point"}
}