{
  "type": "Feature",
  "properties": {
    "iso:country":"US",
    "sg:address":"80 Eunice Bonner Rd",
    "sg:city":"Waynesboro",
    "sg:classifiers":[
        {
            "category":"Organizations",
            "subcategory":"Religious Organization",
            "type":"Services"
        }
    ],
    "sg:phone":"+1 601 671 4010",
    "sg:postcode":"39367",
    "sg:province":"MS",
    "sg:tags":[
        "church"
    ],
    "wof:name":"Windchester Church-God",
    "wof:placetype":"venue"
},
  "geometry": {"coordinates":[-88.57064699999999,31.627981],"type":"Point"}
}