{
  "type": "Feature",
  "properties": {
    "addr:full":"845 N Magnolia Dr Wiggins MS 39577",
    "addr:housenumber":"845",
    "addr:postcode":"39577",
    "addr:street":"N Magnolia Dr",
    "iso:country":"US",
    "sg:address":"845 N Magnolia Dr",
    "sg:city":"Wiggins",
    "sg:classifiers":[
        {
            "category":"Organizations",
            "subcategory":"Religious Organization",
            "type":"Services"
        }
    ],
    "sg:phone":"+1 601 928 2394",
    "sg:postcode":"39577",
    "sg:province":"MS",
    "sg:tags":[
        "church"
    ],
    "wof:name":"Church Of God Worship Ctr",
    "wof:placetype":"venue"
},
  "geometry": {"coordinates":[-89.14717899999999,30.8688],"type":"Point"}
}