{
  "type": "Feature",
  "properties": {
    "addr:full":"1330 Adams Ln Edwards MS 39066",
    "addr:housenumber":"1330",
    "addr:postcode":"39066",
    "addr:street":"Adams Ln",
    "iso:country":"US",
    "sg:address":"1330 Adams Ln",
    "sg:city":"Edwards",
    "sg:classifiers":[
        {
            "category":"Farming",
            "subcategory":"Farm & Veterinary Services",
            "type":"Manufacturing & Wholesale Goods"
        }
    ],
    "sg:phone":"+1 601 852 4774",
    "sg:postcode":"39066",
    "sg:province":"MS",
    "sg:tags":[
        "breeder",
        "livestock"
    ],
    "wof:name":"Cal Maine Breeder Adams Lane",
    "wof:placetype":"venue"
},
  "geometry": {"coordinates":[-90.563177,32.300812],"type":"Point"}
}