{
  "type": "Feature",
  "properties": {
    "iso:country":"US",
    "sg:address":"134 W Ridgeland Ave",
    "sg:city":"Ridgeland",
    "sg:classifiers":[
        {
            "category":"Autos & Motor Vehicles",
            "subcategory":"Auto Supplies",
            "type":"Retail Goods"
        }
    ],
    "sg:phone":"+1 601 856 8141",
    "sg:postcode":"39157",
    "sg:province":"MS",
    "sg:tags":[
        "tire"
    ],
    "wof:name":"Kelly's Tire & Repair Svc",
    "wof:placetype":"venue"
},
  "geometry": {"coordinates":[-90.125848,32.436074],"type":"Point"}
}