{
  "type": "Feature",
  "properties": {
    "iso:country":"US",
    "sg:address":"201 Fairground St",
    "sg:city":"Winona",
    "sg:classifiers":[
        {
            "category":"Real Estate",
            "subcategory":"Real Estate Operator",
            "type":"Services"
        }
    ],
    "sg:phone":"+1 662 283 2986",
    "sg:postcode":"38967",
    "sg:province":"MS",
    "sg:tags":[
        "property",
        "lessor"
    ],
    "wof:name":"Bailey Brothers Building LLC",
    "wof:placetype":"venue"
},
  "geometry": {"coordinates":[-89.734148,33.485874],"type":"Point"}
}