{
  "type": "Feature",
  "properties": {
    "addr:full":"2975 Forest Glen Cove Horn Lake MS 38637",
    "addr:housenumber":"2975",
    "addr:postcode":"38637",
    "addr:street":"Forest Glen Cove Horn Lake",
    "iso:country":"US",
    "sg:address":"2975 Forest Glen Cove",
    "sg:city":"Horn Lake",
    "sg:classifiers":[
        {
            "category":"Building & Trades",
            "subcategory":"Plumbing",
            "type":"Services"
        }
    ],
    "sg:phone":"+1 662 342 4958",
    "sg:postcode":"38637",
    "sg:province":"MS",
    "sg:tags":[
        "air",
        "heating",
        "conditioning",
        "contractor"
    ],
    "wof:name":"Don Caldwell Co",
    "wof:placetype":"venue"
},
  "geometry": {"coordinates":[-90.04307300000001,34.955696],"type":"Point"}
}