{
  "type": "Feature",
  "properties": {
    "addr:full":"204 S Church St Okolona MS 38860",
    "addr:housenumber":"204",
    "addr:postcode":"38860",
    "addr:street":"S Church St",
    "iso:country":"US",
    "sg:address":"204 S Church St",
    "sg:city":"Okolona",
    "sg:classifiers":[
        {
            "category":"Food & Beverages",
            "subcategory":"Groceries & Convenience Stores",
            "type":"Retail Goods"
        }
    ],
    "sg:phone":"+1 662 447 3915",
    "sg:postcode":"38860",
    "sg:province":"MS",
    "wof:name":"Supervalu Inc",
    "wof:placetype":"venue"
},
  "geometry": {"coordinates":[-88.755292,34.001594],"type":"Point"}
}