{
  "type": "Feature",
  "properties": {
    "addr:full":"101 S Washington St Starkville MS 39759",
    "addr:housenumber":"101",
    "addr:postcode":"39759",
    "addr:street":"S Washington St",
    "iso:country":"US",
    "sg:address":"101 S Washington St",
    "sg:city":"Starkville",
    "sg:classifiers":[
        {
            "category":"Insurance",
            "subcategory":"Insurance Agent",
            "type":"Services"
        }
    ],
    "sg:phone":"+1 662 323 2797",
    "sg:postcode":"39759",
    "sg:province":"MS",
    "sg:tags":[
        "management"
    ],
    "wof:name":"Alfa Insurance 416",
    "wof:placetype":"venue"
},
  "geometry": {"coordinates":[-88.816474,33.463827],"type":"Point"}
}