{
  "type": "Feature",
  "properties": {
    "iso:country":"US",
    "sg:address":"23 55th St",
    "sg:city":"Gulfport",
    "sg:classifiers":[
        {
            "category":"Building & Trades",
            "subcategory":"Landscaping Services",
            "type":"Services"
        }
    ],
    "sg:phone":"+1 228 864 8009",
    "sg:postcode":"39507",
    "sg:province":"MS",
    "sg:tags":[
        "landscape",
        "contractor"
    ],
    "wof:name":"Davidson Landscaping",
    "wof:placetype":"venue"
},
  "geometry": {"coordinates":[-89.05076099999999,30.423392],"type":"Point"}
}