{
  "type": "Feature",
  "properties": {
    "iso:country":"US",
    "sg:address":"1052 Mary Dr",
    "sg:city":"Mccomb",
    "sg:classifiers":[
        {
            "category":"Organizations",
            "subcategory":"Religious Organization",
            "type":"Services"
        }
    ],
    "sg:phone":"+1 601 684 2169",
    "sg:postcode":"39648",
    "sg:province":"MS",
    "sg:tags":[
        "church"
    ],
    "wof:name":"Mount Vernon Baptist Church",
    "wof:placetype":"venue"
},
  "geometry": {"coordinates":[-90.458663,31.219885],"type":"Point"}
}