{
  "type": "Feature",
  "properties": {
    "iso:country":"US",
    "sg:address":"334 US Hwy 90",
    "sg:city":"Waveland",
    "sg:classifiers":[
        {
            "category":"Restaurant",
            "type":"Food & Drink"
        }
    ],
    "sg:phone":"+1 228 463 1557",
    "sg:postcode":"39576",
    "sg:province":"MS",
    "sg:tags":[
        "eating"
    ],
    "wof:name":"Yun Long Buffet",
    "wof:placetype":"venue"
},
  "geometry": {"coordinates":[-89.377652,30.306437],"type":"Point"}
}