{
  "type": "Feature",
  "properties": {
    "addr:full":"550 Progress Rd Prentiss MS 39470",
    "addr:housenumber":"550",
    "addr:postcode":"39470",
    "addr:street":"Progress Rd",
    "iso:country":"US",
    "sg:address":"550 Progress Rd",
    "sg:city":"Prentiss",
    "sg:classifiers":[
        {
            "category":"Social Services",
            "type":"Services"
        }
    ],
    "sg:phone":"+1 601 792 9204",
    "sg:postcode":"39470",
    "sg:province":"MS",
    "wof:name":"Crossroad Christian Recovery",
    "wof:placetype":"venue"
},
  "geometry": {"coordinates":[-89.470536,30.806943],"type":"Point"}
}