{
  "type": "Feature",
  "properties": {
    "iso:country":"US",
    "sg:address":"981 W 3rd St",
    "sg:city":"Forest",
    "sg:classifiers":[
        {
            "category":"Restaurant",
            "type":"Food & Drink"
        }
    ],
    "sg:phone":"+1 601 469 2467",
    "sg:postcode":"39074",
    "sg:province":"MS",
    "wof:name":"Marin's Mexican Restaurant",
    "wof:placetype":"venue"
},
  "geometry": {"coordinates":[-89.486591,32.365382],"type":"Point"}
}