{
  "type": "Feature",
  "properties": {
    "addr:full":"508 Elks Lake Rd Hattiesburg MS 39401",
    "addr:housenumber":"508",
    "addr:postcode":"39401",
    "addr:street":"Elks Lake Rd",
    "iso:country":"US",
    "sg:address":"508 Elks Lake Rd",
    "sg:city":"Hattiesburg",
    "sg:classifiers":[
        {
            "category":"Shopping",
            "subcategory":"Department Store",
            "type":"Retail Goods"
        }
    ],
    "sg:phone":"+1 601 582 7009",
    "sg:postcode":"39401",
    "sg:province":"MS",
    "wof:name":"Dollar General",
    "wof:placetype":"venue"
},
  "geometry": {"coordinates":[-89.30212299999999,31.235579],"type":"Point"}
}