{
  "type": "Feature",
  "properties": {
    "iso:country":"US",
    "sg:address":"2404 N 5th Ave",
    "sg:city":"Laurel",
    "sg:classifiers":[
        {
            "category":"Retail",
            "subcategory":"Laundry & Dry Cleaning",
            "type":"Services"
        }
    ],
    "sg:phone":"+1 601 649 5582",
    "sg:postcode":"39440",
    "sg:province":"MS",
    "wof:name":"Fifth Avenue Laundromat",
    "wof:placetype":"venue"
},
  "geometry": {"coordinates":[-89.13071600000001,31.721323],"type":"Point"}
}