{
  "type": "Feature",
  "properties": {
    "iso:country":"US",
    "sg:address":"3609 Lyles Dr",
    "sg:city":"Oxford",
    "sg:classifiers":[
        {
            "category":"Professional",
            "subcategory":"Business Services",
            "type":"Services"
        }
    ],
    "sg:phone":"+1 662 234 0000",
    "sg:postcode":"38655",
    "sg:province":"MS",
    "wof:name":"C & G Partnership",
    "wof:placetype":"venue"
},
  "geometry": {"coordinates":[-89.512154,34.338344],"type":"Point"}
}