{
  "type": "Feature",
  "properties": {
    "addr:full":"1428 Vicksburg Dr Southaven MS 38671",
    "addr:housenumber":"1428",
    "addr:postcode":"38671",
    "addr:street":"Vicksburg Dr",
    "iso:country":"US",
    "sg:address":"1428 Vicksburg Dr",
    "sg:city":"Southaven",
    "sg:classifiers":[
        {
            "category":"Building & Trades",
            "subcategory":"Construction",
            "type":"Services"
        }
    ],
    "sg:phone":"+1 662 342 5804",
    "sg:postcode":"38671",
    "sg:province":"MS",
    "sg:tags":[
        "house"
    ],
    "wof:name":"Mid South Log Homes",
    "wof:placetype":"venue"
},
  "geometry": {"coordinates":[-90.015078,34.992842],"type":"Point"}
}