{
  "type": "Feature",
  "properties": {
    "iso:country":"US",
    "sg:address":"3465 Laurel Dr",
    "sg:city":"Horn Lake",
    "sg:classifiers":[
        {
            "category":"Manufacturing",
            "subcategory":"Printing",
            "type":"Manufacturing & Wholesale Goods"
        }
    ],
    "sg:phone":"+1 662 393 6396",
    "sg:postcode":"38637",
    "sg:province":"MS",
    "sg:tags":[
        "lithographic",
        "commercial"
    ],
    "wof:name":"Express Copy & Printing Center",
    "wof:placetype":"venue"
},
  "geometry": {"coordinates":[-90.050523,34.948532],"type":"Point"}
}