{
  "type": "Feature",
  "properties": {
    "addr:full":"905 Hackberry Ln Canton MS 39046",
    "addr:housenumber":"905",
    "addr:postcode":"39046",
    "addr:street":"Hackberry Ln",
    "iso:country":"US",
    "sg:address":"905 Hackberry Ln",
    "sg:city":"Canton",
    "sg:classifiers":[
        {
            "category":"Professional",
            "subcategory":"Management & Consulting",
            "type":"Services"
        }
    ],
    "sg:phone":"+1 601 853 8537",
    "sg:postcode":"39046",
    "sg:province":"MS",
    "sg:tags":[
        "real estate"
    ],
    "wof:name":"Warnock Real Estate LLC",
    "wof:placetype":"venue"
},
  "geometry": {"coordinates":[-90.034183,32.522841],"type":"Point"}
}