{
  "type": "Feature",
  "properties": {
    "iso:country":"US",
    "sg:address":"24 Work Ln",
    "sg:city":"Ellisville",
    "sg:classifiers":[
        {
            "category":"Building & Trades",
            "subcategory":"Plumbing",
            "type":"Services"
        }
    ],
    "sg:phone":"+1 601 649 0189",
    "sg:postcode":"39437",
    "sg:province":"MS",
    "sg:tags":[
        "contractor"
    ],
    "wof:name":"Purvis Plumbing Co",
    "wof:placetype":"venue"
},
  "geometry": {"coordinates":[-89.0873,31.57793],"type":"Point"}
}