{
  "type": "Feature",
  "properties": {
    "iso:country":"US",
    "sg:address":"736 E 15th St",
    "sg:city":"Yazoo City",
    "sg:classifiers":[
        {
            "category":"Shopping",
            "subcategory":"Discount & Variety Stores",
            "type":"Retail Goods"
        }
    ],
    "sg:phone":"+1 662 746 1914",
    "sg:postcode":"39194",
    "sg:province":"MS",
    "wof:name":"Family Dollar Store",
    "wof:placetype":"venue"
},
  "geometry": {"coordinates":[-90.396764,32.864789],"type":"Point"}
}