{
  "type": "Feature",
  "properties": {
    "iso:country":"US",
    "sg:address":"2666 Hardy Billups Rd",
    "sg:city":"Columbus",
    "sg:classifiers":[
        {
            "category":"Shopping",
            "subcategory":"Computers & Home Electronics",
            "type":"Retail Goods"
        }
    ],
    "sg:phone":"+1 662 328 5707",
    "sg:postcode":"39701",
    "sg:province":"MS",
    "wof:name":"Oxitek",
    "wof:placetype":"venue"
},
  "geometry": {"coordinates":[-88.58635200000001,33.389657],"type":"Point"}
}