{
  "type": "Feature",
  "properties": {
    "iso:country":"US",
    "sg:address":"5673 Hwy 18 W",
    "sg:city":"Jackson",
    "sg:classifiers":[
        {
            "category":"Food & Beverages",
            "subcategory":"Groceries & Convenience Stores",
            "type":"Retail Goods"
        }
    ],
    "sg:phone":"+1 601 923 1563",
    "sg:postcode":"39209",
    "sg:province":"MS",
    "wof:name":"Expressway 63",
    "wof:placetype":"venue"
},
  "geometry": {"coordinates":[-90.28227800000001,32.277353],"type":"Point"}
}