{
  "type": "Feature",
  "properties": {
    "iso:country":"US",
    "sg:address":"4910 Kendall Ave",
    "sg:city":"Gulfport",
    "sg:classifiers":[
        {
            "category":"Real Estate",
            "subcategory":"Real Estate Agent",
            "type":"Services"
        }
    ],
    "sg:phone":"+1 228 214 0014",
    "sg:postcode":"39507",
    "sg:province":"MS",
    "wof:name":"Royce Hill Real Estate",
    "wof:placetype":"venue"
},
  "geometry": {"coordinates":[-89.045863,30.413465],"type":"Point"}
}