{
  "type": "Feature",
  "properties": {
    "iso:country":"US",
    "sg:address":"12000 Mobile Ave",
    "sg:city":"Gulfport",
    "sg:classifiers":[
        {
            "category":"Professional",
            "subcategory":"Testing Lab",
            "type":"Services"
        }
    ],
    "sg:phone":"+1 228 831 0600",
    "sg:postcode":"39503",
    "sg:province":"MS",
    "sg:tags":[
        "laboratory"
    ],
    "wof:name":"Examination Management Svc",
    "wof:placetype":"venue"
},
  "geometry": {"coordinates":[-89.099378,30.458441],"type":"Point"}
}