{
  "type": "Feature",
  "properties": {
    "iso:country":"US",
    "sg:address":"402 Central Ave",
    "sg:city":"Laurel",
    "sg:classifiers":[
        {
            "category":"Government",
            "subcategory":"Court House",
            "type":"Public Place"
        }
    ],
    "sg:phone":"+1 601 428 3137",
    "sg:postcode":"39440",
    "sg:province":"MS",
    "sg:tags":[
        "county"
    ],
    "wof:name":"Jones County Justice Court",
    "wof:placetype":"venue"
},
  "geometry": {"coordinates":[-89.131038,31.692326],"type":"Point"}
}