{
  "type": "Feature",
  "properties": {
    "addr:full":"520 Smith Rd NE Mantachie MS 38847",
    "addr:housenumber":"520",
    "addr:postcode":"38847",
    "addr:street":"Smith Rd Ne",
    "iso:country":"US",
    "sg:address":"520 Smith Rd NE",
    "sg:city":"Mantachie",
    "sg:classifiers":[
        {
            "category":"Government",
            "subcategory":"Office",
            "type":"Public Place"
        }
    ],
    "sg:phone":"+1 662 282 7030",
    "sg:postcode":"38847",
    "sg:province":"MS",
    "sg:tags":[
        "govt",
        "state",
        "utility"
    ],
    "wof:name":"Oil & Gas Board",
    "wof:placetype":"venue"
},
  "geometry": {"coordinates":[-88.20429300000001,34.447295],"type":"Point"}
}