{
  "type": "Feature",
  "properties": {
    "iso:country":"US",
    "sg:address":"100 Westwood Ave",
    "sg:city":"Lexington",
    "sg:classifiers":[
        {
            "category":"Social Services",
            "type":"Services"
        }
    ],
    "sg:phone":"+1 662 834 2437",
    "sg:postcode":"39095",
    "sg:province":"MS",
    "sg:tags":[
        "organization",
        "welfare"
    ],
    "wof:name":"Central Mississippi Inc",
    "wof:placetype":"venue"
},
  "geometry": {"coordinates":[-90.06326199999999,33.113906],"type":"Point"}
}