{
  "type": "Feature",
  "properties": {
    "iso:country":"US",
    "sg:address":"94 Pinecrest Rd",
    "sg:city":"Columbus",
    "sg:classifiers":[
        {
            "category":"Shopping",
            "subcategory":"Computers & Home Electronics",
            "type":"Retail Goods"
        }
    ],
    "sg:phone":"+1 662 329 1946",
    "sg:postcode":"39705",
    "sg:province":"MS",
    "sg:tags":[
        "repair"
    ],
    "wof:name":"Electronic Hospital",
    "wof:placetype":"venue"
},
  "geometry": {"coordinates":[-88.406614,33.535077],"type":"Point"}
}