{
  "type": "Feature",
  "properties": {
    "addr:full":"3221 Players Club Pkwy Memphis MS 38125",
    "addr:housenumber":"3221",
    "addr:postcode":"38125",
    "addr:street":"Players Club Pkwy",
    "iso:country":"US",
    "sg:address":"3221 Players Club Pkwy",
    "sg:city":"Memphis",
    "sg:classifiers":[
        {
            "category":"Education",
            "subcategory":"Special Training",
            "type":"Public Place"
        }
    ],
    "sg:phone":"+1 901 507 9969",
    "sg:postcode":"38125",
    "sg:province":"MS",
    "sg:tags":[
        "aircraft",
        "school"
    ],
    "sg:website":"www.erau.edu",
    "wof:name":"Embry-Riddle Aeronautical Univ",
    "wof:placetype":"venue"
},
  "geometry": {"coordinates":[-89.79047300000001,35.061568],"type":"Point"}
}