{
  "type": "Feature",
  "properties": {
    "iso:country":"US",
    "sg:address":"1001 Hwy 49 S",
    "sg:city":"Jackson",
    "sg:classifiers":[
        {
            "category":"Banks & Credit Unions",
            "subcategory":"Bank",
            "type":"Services"
        }
    ],
    "sg:phone":"+1 601 939 0011",
    "sg:postcode":"39218",
    "sg:province":"MS",
    "sg:tags":[
        "national",
        "commercial"
    ],
    "wof:name":"Trustmark National Bank",
    "wof:placetype":"venue"
},
  "geometry": {"coordinates":[-90.11536599999999,32.149617],"type":"Point"}
}