{
  "type": "Feature",
  "properties": {
    "iso:country":"US",
    "sg:address":"424 US Hwy 90",
    "sg:city":"Gautier",
    "sg:classifiers":[
        {
            "category":"Professional",
            "subcategory":"Computer Services",
            "type":"Services"
        }
    ],
    "sg:phone":"+1 228 497 3936",
    "sg:postcode":"39553",
    "sg:province":"MS",
    "sg:tags":[
        "home",
        "consulting",
        "page",
        "dev",
        "internet"
    ],
    "wof:name":"L-3 Communications",
    "wof:placetype":"venue"
},
  "geometry": {"coordinates":[-88.614876,30.384517],"type":"Point"}
}