{
  "type": "Feature",
  "properties": {
    "addr:full":"236 Co Rd 1205 Plantersville MS 38862",
    "addr:housenumber":"236",
    "addr:postcode":"1205;38862",
    "addr:street":"Co Rd",
    "iso:country":"US",
    "sg:address":"236 Co Rd 1205",
    "sg:city":"Plantersville",
    "sg:classifiers":[
        {
            "category":"Personal",
            "subcategory":"Barber",
            "type":"Services"
        }
    ],
    "sg:phone":"+1 662 963 3558",
    "sg:postcode":"38862",
    "sg:province":"MS",
    "sg:tags":[
        "shop"
    ],
    "wof:name":"Barber Farms",
    "wof:placetype":"venue"
},
  "geometry": {"coordinates":[-88.578017,34.170359],"type":"Point"}
}