{
  "type": "Feature",
  "properties": {
    "iso:country":"US",
    "sg:address":"205 US Hwy 98",
    "sg:city":"New Augusta",
    "sg:classifiers":[
        {
            "category":"Freight",
            "type":"Transportation"
        }
    ],
    "sg:phone":"+1 601 964 8343",
    "sg:postcode":"39462",
    "sg:province":"MS",
    "sg:tags":[
        "hauling",
        "trucking"
    ],
    "wof:name":"CCC Trucking",
    "wof:placetype":"venue"
},
  "geometry": {"coordinates":[-89.027479,31.200863],"type":"Point"}
}