{
  "type": "Feature",
  "properties": {
    "addr:full":"1401 Kmart Plaza Dr Yazoo City MS 39194",
    "addr:housenumber":"1401",
    "addr:postcode":"39194",
    "addr:street":"Kmart Plaza Dr",
    "iso:country":"US",
    "sg:address":"1401 Kmart Plaza Dr",
    "sg:city":"Yazoo City",
    "sg:classifiers":[
        {
            "category":"Personal",
            "subcategory":"Beauty Salon",
            "type":"Services"
        }
    ],
    "sg:phone":"+1 662 746 6117",
    "sg:postcode":"39194",
    "sg:province":"MS",
    "wof:name":"Dian's Decision's Beauty Salon",
    "wof:placetype":"venue"
},
  "geometry": {"coordinates":[-90.395844,32.862566],"type":"Point"}
}