{
  "type": "Feature",
  "properties": {
    "addr:full":"3874 Hwy 12 W Sturgis MS 39769",
    "addr:housenumber":"3874",
    "addr:postcode":"39769",
    "addr:street":"Hwy 12 W",
    "iso:country":"US",
    "sg:address":"3874 Hwy 12 W",
    "sg:city":"Sturgis",
    "sg:classifiers":[
        {
            "category":"Shopping",
            "subcategory":"Gifts & Souvenirs",
            "type":"Retail Goods"
        }
    ],
    "sg:phone":"+1 662 465 6008",
    "sg:postcode":"39769",
    "sg:province":"MS",
    "sg:tags":[
        "shop"
    ],
    "wof:name":"Merchandise Warehouse",
    "wof:placetype":"venue"
},
  "geometry": {"coordinates":[-89.050212,33.343183],"type":"Point"}
}