{
  "type": "Feature",
  "properties": {
    "iso:country":"US",
    "sg:address":"102 Westover Dr",
    "sg:city":"Hattiesburg",
    "sg:classifiers":[
        {
            "category":"Retail",
            "subcategory":"Car Wash",
            "type":"Services"
        }
    ],
    "sg:phone":"+1 601 264 2701",
    "sg:postcode":"39402",
    "sg:province":"MS",
    "sg:tags":[
        "automobile",
        "detail",
        "clean"
    ],
    "wof:name":"Ultimate Car Wash & Quick Lube",
    "wof:placetype":"venue"
},
  "geometry": {"coordinates":[-89.356315,31.321953],"type":"Point"}
}