{
  "type": "Feature",
  "properties": {
    "addr:full":"11324 River Oaks Dr Biloxi MS 39532",
    "addr:housenumber":"11324",
    "addr:postcode":"39532",
    "addr:street":"River Oaks Dr",
    "iso:country":"US",
    "sg:address":"11324 River Oaks Dr",
    "sg:city":"Biloxi",
    "sg:classifiers":[
        {
            "category":"Professional",
            "subcategory":"Computer Services",
            "type":"Services"
        }
    ],
    "sg:phone":"+1 228 396 5547",
    "sg:postcode":"39532",
    "sg:province":"MS",
    "sg:tags":[
        "datum"
    ],
    "wof:name":"Chanee Waters",
    "wof:placetype":"venue"
},
  "geometry": {"coordinates":[-88.98784499999999,30.452921],"type":"Point"}
}