{
  "type": "Feature",
  "properties": {
    "addr:full":"13167 Bethel Rd Saucier MS 39574",
    "addr:housenumber":"13167",
    "addr:postcode":"39574",
    "addr:street":"Bethel Rd",
    "iso:country":"US",
    "sg:address":"13167 Bethel Rd",
    "sg:city":"Saucier",
    "sg:classifiers":[
        {
            "category":"Professional",
            "subcategory":"Research",
            "type":"Services"
        }
    ],
    "sg:phone":"+1 228 328 2200",
    "sg:postcode":"39574",
    "sg:province":"MS",
    "sg:tags":[
        "environmental",
        "ecological"
    ],
    "wof:name":"Onyx Industrial Svc Corp",
    "wof:placetype":"venue"
},
  "geometry": {"coordinates":[-89.05936800000001,30.640627],"type":"Point"}
}