{
  "type": "Feature",
  "properties": {
    "iso:country":"US",
    "sg:address":"1092 Monterey Rd",
    "sg:city":"Pearl",
    "sg:classifiers":[
        {
            "category":"Building & Trades",
            "subcategory":"Electrical",
            "type":"Services"
        }
    ],
    "sg:phone":"+1 601 939 8818",
    "sg:postcode":"39208",
    "sg:province":"MS",
    "sg:tags":[
        "electrical",
        "contractor"
    ],
    "wof:name":"Terrell Electric Co Inc",
    "wof:placetype":"venue"
},
  "geometry": {"coordinates":[-90.096,32.197308],"type":"Point"}
}