{
  "type": "Feature",
  "properties": {
    "iso:country":"US",
    "sg:address":"200 E Bankhead St",
    "sg:city":"New Albany",
    "sg:classifiers":[
        {
            "category":"Organizations",
            "subcategory":"Religious Organization",
            "type":"Services"
        }
    ],
    "sg:phone":"+1 662 534 5812",
    "sg:postcode":"38652",
    "sg:province":"MS",
    "wof:name":"First Baptist Church",
    "wof:placetype":"venue"
},
  "geometry": {"coordinates":[-89.0067,34.492715],"type":"Point"}
}