{
  "type": "Feature",
  "properties": {
    "addr:full":"717 Walthall St Greenwood MS 38930",
    "addr:housenumber":"717",
    "addr:postcode":"38930",
    "addr:street":"Walthall St",
    "iso:country":"US",
    "sg:address":"717 Walthall St",
    "sg:city":"Greenwood",
    "sg:classifiers":[
        {
            "category":"Organizations",
            "subcategory":"Religious Organization",
            "type":"Services"
        }
    ],
    "sg:phone":"+1 662 455 4745",
    "sg:postcode":"38930",
    "sg:province":"MS",
    "sg:tags":[
        "church"
    ],
    "wof:name":"Turner Chapel AME Church",
    "wof:placetype":"venue"
},
  "geometry": {"coordinates":[-90.178664,33.515705],"type":"Point"}
}