{
  "type": "Feature",
  "properties": {
    "iso:country":"US",
    "sg:address":"1800 Stateline Rd E",
    "sg:city":"Southaven",
    "sg:classifiers":[
        {
            "category":"Professional",
            "subcategory":"Advertising",
            "type":"Services"
        }
    ],
    "sg:phone":"+1 662 393 3840",
    "sg:postcode":"38671",
    "sg:province":"MS",
    "wof:name":"Memphis Shoppers Guide & News",
    "wof:placetype":"venue"
},
  "geometry": {"coordinates":[-89.95487,34.991675],"type":"Point"}
}