{
  "type": "Feature",
  "properties": {
    "iso:country":"US",
    "sg:address":"382 Peps Point Rd",
    "sg:city":"Hattiesburg",
    "sg:classifiers":[
        {
            "category":"Recreation",
            "subcategory":"Amusement Park",
            "type":"Entertainment"
        }
    ],
    "sg:phone":"+1 601 582 8461",
    "sg:postcode":"39401",
    "sg:province":"MS",
    "wof:name":"Pep's Point Water Park",
    "wof:placetype":"venue"
},
  "geometry": {"coordinates":[-89.370283,31.408582],"type":"Point"}
}