{
  "type": "Feature",
  "properties": {
    "iso:country":"US",
    "sg:address":"282 Co Rd 457",
    "sg:city":"Calhoun City",
    "sg:classifiers":[
        {
            "category":"Professional",
            "type":"Services"
        }
    ],
    "sg:phone":"+1 662 628 6500",
    "sg:postcode":"38916",
    "sg:province":"MS",
    "sg:tags":[
        "establishment"
    ],
    "wof:name":"Doler Brothers",
    "wof:placetype":"venue"
},
  "geometry": {"coordinates":[-89.31489500000001,33.809205],"type":"Point"}
}