{
  "type": "Feature",
  "properties": {
    "iso:country":"US",
    "sg:address":"410 City Ave S",
    "sg:city":"Ripley",
    "sg:classifiers":[
        {
            "category":"Retail",
            "subcategory":"Auto Repair",
            "type":"Services"
        }
    ],
    "sg:phone":"+1 662 512 0270",
    "sg:postcode":"38663",
    "sg:province":"MS",
    "sg:tags":[
        "repairing",
        "automotive",
        "automobile",
        "general"
    ],
    "wof:name":"Carpenter's Garage",
    "wof:placetype":"venue"
},
  "geometry": {"coordinates":[-88.94632,34.728136],"type":"Point"}
}