{
  "type": "Feature",
  "properties": {
    "iso:country":"US",
    "sg:address":"2715 Belvedere Dr",
    "sg:city":"Jackson",
    "sg:classifiers":[
        {
            "category":"Organizations",
            "subcategory":"Religious Organization",
            "type":"Services"
        }
    ],
    "sg:phone":"+1 601 346 4974",
    "sg:postcode":"39212",
    "sg:province":"MS",
    "sg:tags":[
        "church"
    ],
    "sg:website":"www.newhorizonministries.com",
    "wof:name":"New Horizon Church",
    "wof:placetype":"venue"
},
  "geometry": {"coordinates":[-90.22740899999999,32.266339],"type":"Point"}
}