{
  "type": "Feature",
  "properties": {
    "iso:country":"US",
    "sg:address":"1702 US Hwy 11 N",
    "sg:city":"Picayune",
    "sg:classifiers":[
        {
            "category":"Restaurant",
            "type":"Food & Drink"
        }
    ],
    "sg:phone":"+1 601 799 3507",
    "sg:postcode":"39466",
    "sg:province":"MS",
    "sg:tags":[
        "pizza"
    ],
    "wof:name":"Godfather's Pizza",
    "wof:placetype":"venue"
},
  "geometry": {"coordinates":[-89.66797099999999,30.549038],"type":"Point"}
}