{
  "type": "Feature",
  "properties": {
    "addr:full":"148 Hwy 51 N Batesville MS 38606",
    "addr:housenumber":"148",
    "addr:postcode":"38606",
    "addr:street":"Hwy 51 N",
    "iso:country":"US",
    "sg:address":"148 Hwy 51 N",
    "sg:city":"Batesville",
    "sg:classifiers":[
        {
            "category":"Government",
            "subcategory":"Office",
            "type":"Public Place"
        }
    ],
    "sg:phone":"+1 662 563 4271",
    "sg:postcode":"38606",
    "sg:province":"MS",
    "wof:name":"Highway Laboratory",
    "wof:placetype":"venue"
},
  "geometry": {"coordinates":[-89.943743,34.314136],"type":"Point"}
}