{
  "type": "Feature",
  "properties": {
    "iso:country":"US",
    "sg:address":"2013 Stateline Rd W",
    "sg:city":"Southaven",
    "sg:classifiers":[
        {
            "category":"Food & Beverages",
            "subcategory":"Specialty",
            "type":"Retail Goods"
        }
    ],
    "sg:phone":"+1 662 280 3230",
    "sg:postcode":"38671",
    "sg:province":"MS",
    "wof:name":"GNC",
    "wof:placetype":"venue"
},
  "geometry": {"coordinates":[-90.026025,34.991768],"type":"Point"}
}