{
  "type": "Feature",
  "properties": {
    "iso:country":"US",
    "sg:address":"4205 Indian Springs Rd",
    "sg:city":"Laurel",
    "sg:classifiers":[
        {
            "category":"Wholesale",
            "subcategory":"Groceries",
            "type":"Manufacturing & Wholesale Goods"
        }
    ],
    "sg:phone":"+1 601 428 0979",
    "sg:postcode":"39443",
    "sg:province":"MS",
    "wof:name":"Tony Chacheres Creole Fo",
    "wof:placetype":"venue"
},
  "geometry": {"coordinates":[-89.19878799999999,31.666157],"type":"Point"}
}