{
  "type": "Feature",
  "properties": {
    "addr:full":"8740 Dunn Ln Olive Branch MS 38654",
    "addr:housenumber":"8740",
    "addr:postcode":"38654",
    "addr:street":"Dunn Ln",
    "iso:country":"US",
    "sg:address":"8740 Dunn Ln",
    "sg:city":"Olive Branch",
    "sg:classifiers":[
        {
            "category":"Arts & Performance",
            "subcategory":"Theater",
            "type":"Entertainment"
        }
    ],
    "sg:phone":"+1 662 893 8217",
    "sg:postcode":"38654",
    "sg:province":"MS",
    "sg:tags":[
        "group"
    ],
    "wof:name":"Paul & Lucy Wood",
    "wof:placetype":"venue"
},
  "geometry": {"coordinates":[-89.834855,34.908756],"type":"Point"}
}