{
  "type": "Feature",
  "properties": {
    "iso:country":"US",
    "sg:address":"2400 S Gloster St",
    "sg:city":"Tupelo",
    "sg:classifiers":[
        {
            "category":"Retail",
            "subcategory":"Animal Services",
            "type":"Services"
        }
    ],
    "sg:phone":"+1 662 841 6500",
    "sg:postcode":"38801",
    "sg:province":"MS",
    "sg:tags":[
        "shelter"
    ],
    "wof:name":"Tupelo Lee Humane Society",
    "wof:placetype":"venue"
},
  "geometry": {"coordinates":[-88.719993,34.211038],"type":"Point"}
}