{
  "type": "Feature",
  "properties": {
    "iso:country":"US",
    "sg:address":"4648 Van Winkle Park Dr",
    "sg:city":"Jackson",
    "sg:classifiers":[
        {
            "category":"Professional",
            "subcategory":"Advertising",
            "type":"Services"
        }
    ],
    "sg:phone":"+1 601 922 2200",
    "sg:postcode":"39209",
    "sg:province":"MS",
    "sg:tags":[
        "outdoor",
        "spec",
        "mfg"
    ],
    "wof:name":"Signs Inc",
    "wof:placetype":"venue"
},
  "geometry": {"coordinates":[-90.264021,32.304664],"type":"Point"}
}