{
  "type": "Feature",
  "properties": {
    "addr:full":"5511 Telephone Rd Pascagoula MS 39567",
    "addr:housenumber":"5511",
    "addr:postcode":"39567",
    "addr:street":"Telephone Rd",
    "iso:country":"US",
    "sg:address":"5511 Telephone Rd",
    "sg:city":"Pascagoula",
    "sg:classifiers":[
        {
            "category":"Social Services",
            "subcategory":"Child Care",
            "type":"Services"
        }
    ],
    "sg:phone":"+1 228 762 8200",
    "sg:postcode":"39567",
    "sg:province":"MS",
    "sg:tags":[
        "day"
    ],
    "wof:name":"Precious Beginnings Child Dev",
    "wof:placetype":"venue"
},
  "geometry": {"coordinates":[-88.53493,30.386951],"type":"Point"}
}