{
  "type": "Feature",
  "properties": {
    "addr:full":"10556 US Hwy 49 Gulfport MS 39503",
    "addr:housenumber":"10556",
    "addr:postcode":"39503",
    "addr:street":"Us Hwy 49",
    "iso:country":"US",
    "sg:address":"10556 US Hwy 49",
    "sg:city":"Gulfport",
    "sg:classifiers":[
        {
            "category":"Autos & Motor Vehicles",
            "subcategory":"Fuel & Gas Station",
            "type":"Retail Goods"
        }
    ],
    "sg:phone":"+1 228 831 1002",
    "sg:postcode":"39503",
    "sg:province":"MS",
    "sg:tags":[
        "oil"
    ],
    "wof:name":"Chevron",
    "wof:placetype":"venue"
},
  "geometry": {"coordinates":[-89.097971,30.441505],"type":"Point"}
}