{
  "type": "Feature",
  "properties": {
    "addr:full":"120 Twelve Oaks Rd Canton MS 39046",
    "addr:housenumber":"120",
    "addr:postcode":"39046",
    "addr:street":"Twelve Oaks Rd",
    "iso:country":"US",
    "sg:address":"120 Twelve Oaks Rd",
    "sg:city":"Canton",
    "sg:classifiers":[
        {
            "category":"Building & Trades",
            "subcategory":"Construction",
            "type":"Services"
        }
    ],
    "sg:phone":"+1 601 201 2849",
    "sg:postcode":"39046",
    "sg:province":"MS",
    "sg:tags":[
        "house"
    ],
    "wof:name":"Simon Remodeling",
    "wof:placetype":"venue"
},
  "geometry": {"coordinates":[-90.040623,32.495151],"type":"Point"}
}