{
  "type": "Feature",
  "properties": {
    "addr:full":"5002 Pointset Ave Bay St Louis MS 39520",
    "addr:housenumber":"5002",
    "addr:postcode":"39520",
    "addr:street":"Pointset Ave",
    "iso:country":"US",
    "sg:address":"5002 Pointset Ave",
    "sg:city":"Bay St Louis",
    "sg:classifiers":[
        {
            "category":"Professional",
            "type":"Services"
        }
    ],
    "sg:phone":"+1 228 466 4520",
    "sg:postcode":"39520",
    "sg:province":"MS",
    "sg:tags":[
        "establishment"
    ],
    "wof:name":"Pointset Lift Station",
    "wof:placetype":"venue"
},
  "geometry": {"coordinates":[-89.419595,30.25621],"type":"Point"}
}