{
  "type": "Feature",
  "properties": {
    "iso:country":"US",
    "sg:address":"710 Esplanade Dr",
    "sg:city":"Ridgeland",
    "sg:classifiers":[
        {
            "category":"Arts & Performance",
            "subcategory":"Theater",
            "type":"Entertainment"
        }
    ],
    "sg:phone":"+1 601 201 4887",
    "sg:postcode":"39157",
    "sg:province":"MS",
    "sg:tags":[
        "group"
    ],
    "wof:name":"Joanne Parks",
    "wof:placetype":"venue"
},
  "geometry": {"coordinates":[-90.109472,32.418724],"type":"Point"}
}