{
  "type": "Feature",
  "properties": {
    "iso:country":"US",
    "sg:address":"133 E Commerce St",
    "sg:city":"Hernando",
    "sg:classifiers":[
        {
            "category":"Shopping",
            "subcategory":"Stationery & Office Supplies",
            "type":"Retail Goods"
        }
    ],
    "sg:phone":"+1 662 429 9073",
    "sg:postcode":"38632",
    "sg:province":"MS",
    "sg:tags":[
        "album",
        "scrapbook"
    ],
    "wof:name":"Scrapbook Corner",
    "wof:placetype":"venue"
},
  "geometry": {"coordinates":[-89.988497,34.823525],"type":"Point"}
}