{
  "type": "Feature",
  "properties": {
    "iso:country":"US",
    "sg:address":"108 US Hwy 49W",
    "sg:city":"Belzoni",
    "sg:classifiers":[
        {
            "category":"Restaurant",
            "type":"Food & Drink"
        }
    ],
    "sg:phone":"+1 662 247 4009",
    "sg:postcode":"39038",
    "sg:province":"MS",
    "wof:name":"Los Molcajetes Mexican Rstrnt",
    "wof:placetype":"venue"
},
  "geometry": {"coordinates":[-90.49892199999999,33.16656],"type":"Point"}
}