{
  "type": "Feature",
  "properties": {
    "iso:country":"US",
    "sg:address":"615 W Congress St",
    "sg:city":"Brookhaven",
    "sg:classifiers":[
        {
            "category":"Personal",
            "subcategory":"Beauty Salon",
            "type":"Services"
        }
    ],
    "sg:phone":"+1 601 833 7364",
    "sg:postcode":"39601",
    "sg:province":"MS",
    "sg:tags":[
        "shop"
    ],
    "wof:name":"Westside Beauty Salon",
    "wof:placetype":"venue"
},
  "geometry": {"coordinates":[-90.44967,31.58318],"type":"Point"}
}