{
  "type": "Feature",
  "properties": {
    "iso:country":"US",
    "sg:address":"13012 Jim Byrd Rd",
    "sg:city":"Biloxi",
    "sg:classifiers":[
        {
            "category":"Building & Trades",
            "subcategory":"Construction",
            "type":"Services"
        }
    ],
    "sg:phone":"+1 228 392 8877",
    "sg:postcode":"39532",
    "sg:province":"MS",
    "sg:tags":[
        "nonresidential",
        "demolition",
        "contractor"
    ],
    "wof:name":"W T Firth Construction Inc",
    "wof:placetype":"venue"
},
  "geometry": {"coordinates":[-88.972072,30.474138],"type":"Point"}
}