{
  "type": "Feature",
  "properties": {
    "iso:country":"US",
    "sg:address":"10060 Hwy 178",
    "sg:city":"Olive Branch",
    "sg:classifiers":[
        {
            "category":"Home & Garden",
            "subcategory":"Building Materials",
            "type":"Retail Goods"
        }
    ],
    "sg:phone":"+1 662 890 9518",
    "sg:postcode":"38654",
    "sg:province":"MS",
    "sg:tags":[
        "windows"
    ],
    "wof:name":"Olive Branch Window & Door",
    "wof:placetype":"venue"
},
  "geometry": {"coordinates":[-89.812772,34.951001],"type":"Point"}
}