{
  "type": "Feature",
  "properties": {
    "iso:country":"US",
    "sg:address":"2149 Swinnea Rd",
    "sg:city":"Nesbit",
    "sg:classifiers":[
        {
            "category":"Building & Trades",
            "subcategory":"Construction",
            "type":"Services"
        }
    ],
    "sg:phone":"+1 662 342 5788",
    "sg:postcode":"38651",
    "sg:province":"MS",
    "sg:tags":[
        "general",
        "contractor"
    ],
    "wof:name":"Rodgers & Assoc",
    "wof:placetype":"venue"
},
  "geometry": {"coordinates":[-89.97240499999999,34.891554],"type":"Point"}
}