{
  "type": "Feature",
  "properties": {
    "iso:country":"US",
    "sg:address":"800 Highway 45 N",
    "sg:city":"West Point",
    "sg:classifiers":[
        {
            "category":"Restaurant",
            "type":"Food & Drink"
        }
    ],
    "sg:menulink":"http://www.allmenus.com/ms/una/72869-pizza-hut/menu/",
    "sg:phone":"+1 662 494 2404",
    "sg:postcode":"39773",
    "sg:province":"MS",
    "sg:tags":[
        "american",
        "pizza"
    ],
    "wof:name":"Pizza Hut",
    "wof:placetype":"venue"
},
  "geometry": {"coordinates":[-88.658889,33.61751],"type":"Point"}
}