{
  "type": "Feature",
  "properties": {
    "iso:country":"US",
    "sg:address":"1125 E McDowell Rd",
    "sg:city":"Jackson",
    "sg:classifiers":[
        {
            "category":"Retail",
            "subcategory":"Auto Repair",
            "type":"Services"
        }
    ],
    "sg:phone":"+1 601 352 7005",
    "sg:postcode":"39204",
    "sg:province":"MS",
    "sg:tags":[
        "body",
        "automobile",
        "painting"
    ],
    "wof:name":"F & R Auto Body & Painting",
    "wof:placetype":"venue"
},
  "geometry": {"coordinates":[-90.19842800000001,32.268237],"type":"Point"}
}