{
  "type": "Feature",
  "properties": {
    "iso:country":"US",
    "sg:address":"839 US Hwy 11",
    "sg:city":"Petal",
    "sg:classifiers":[
        {
            "category":"Real Estate",
            "subcategory":"Real Estate Agent",
            "type":"Services"
        }
    ],
    "sg:phone":"+1 601 545 2795",
    "sg:postcode":"39465",
    "sg:province":"MS",
    "wof:name":"Tyler Properties",
    "wof:placetype":"venue"
},
  "geometry": {"coordinates":[-89.272527,31.348511],"type":"Point"}
}