{
  "type": "Feature",
  "properties": {
    "iso:country":"US",
    "sg:address":"66 Nicole Dr",
    "sg:city":"Vicksburg",
    "sg:classifiers":[
        {
            "category":"Professional",
            "subcategory":"Business Services",
            "type":"Services"
        }
    ],
    "sg:phone":"+1 601 636 2505",
    "sg:postcode":"39180",
    "sg:province":"MS",
    "wof:name":"Hall Automotive",
    "wof:placetype":"venue"
},
  "geometry": {"coordinates":[-90.76716999999999,32.350209],"type":"Point"}
}