{
  "type": "Feature",
  "properties": {
    "addr:full":"600 Hwy 32 W Houlka MS 38850",
    "addr:housenumber":"600",
    "addr:postcode":"38850",
    "addr:street":"Hwy 32 W Houlka",
    "iso:country":"US",
    "sg:address":"600 Hwy 32 W",
    "sg:city":"Houlka",
    "sg:classifiers":[
        {
            "category":"Home & Garden",
            "subcategory":"Household Appliances",
            "type":"Retail Goods"
        }
    ],
    "sg:phone":"+1 662 568 7041",
    "sg:postcode":"38850",
    "sg:province":"MS",
    "wof:name":"Houlka Appliance",
    "wof:placetype":"venue"
},
  "geometry": {"coordinates":[-89.028537,34.038281],"type":"Point"}
}