{
  "type": "Feature",
  "properties": {
    "addr:full":"340 Lee Dr Clarksdale MS 38614",
    "addr:housenumber":"340",
    "addr:postcode":"38614",
    "addr:street":"Lee Dr Clarksdale",
    "iso:country":"US",
    "sg:address":"340 Lee Dr",
    "sg:city":"Clarksdale",
    "sg:classifiers":[
        {
            "category":"Building & Trades",
            "subcategory":"Construction",
            "type":"Services"
        }
    ],
    "sg:phone":"+1 662 627 4410",
    "sg:postcode":"38614",
    "sg:province":"MS",
    "sg:tags":[
        "excavation",
        "concrete",
        "contractor"
    ],
    "wof:name":"Tim Gore Inc",
    "wof:placetype":"venue"
},
  "geometry": {"coordinates":[-90.56681,34.218617],"type":"Point"}
}