{
  "type": "Feature",
  "properties": {
    "iso:country":"US",
    "sg:address":"220 Depot St",
    "sg:city":"Woodville",
    "sg:classifiers":[
        {
            "category":"Personal",
            "subcategory":"Beauty Salon",
            "type":"Services"
        }
    ],
    "sg:phone":"+1 601 888 3772",
    "sg:postcode":"39669",
    "sg:province":"MS",
    "wof:name":"Trinity Touch",
    "wof:placetype":"venue"
},
  "geometry": {"coordinates":[-91.29862900000001,31.103094],"type":"Point"}
}