{
  "type": "Feature",
  "properties": {
    "addr:full":"3061 Oak Grove Rd Hattiesburg MS 39402",
    "addr:housenumber":"3061",
    "addr:postcode":"39402",
    "addr:street":"Oak Grove Rd",
    "iso:country":"US",
    "sg:address":"3061 Oak Grove Rd",
    "sg:city":"Hattiesburg",
    "sg:classifiers":[
        {
            "category":"Airline",
            "type":"Transportation"
        }
    ],
    "sg:phone":"+1 601 264 3752",
    "sg:postcode":"39402",
    "sg:province":"MS",
    "sg:tags":[
        "scheduled",
        "air"
    ],
    "wof:name":"Burks Aviation Inc",
    "wof:placetype":"venue"
},
  "geometry": {"coordinates":[-89.39432100000001,31.289715],"type":"Point"}
}