{
  "type": "Feature",
  "properties": {
    "iso:country":"US",
    "sg:address":"11471 Ashton Ln W",
    "sg:city":"Gulfport",
    "sg:classifiers":[
        {
            "category":"Building & Trades",
            "subcategory":"Construction",
            "type":"Services"
        }
    ],
    "sg:phone":"+1 228 669 7335",
    "sg:postcode":"39532",
    "sg:province":"MS",
    "sg:tags":[
        "house"
    ],
    "wof:name":"Hughes Properties",
    "wof:placetype":"venue"
},
  "geometry": {"coordinates":[-89.01767599999999,30.454977],"type":"Point"}
}