{
  "type": "Feature",
  "properties": {
    "iso:country":"US",
    "sg:address":"116 E Canal St",
    "sg:city":"Picayune",
    "sg:classifiers":[
        {
            "category":"Insurance",
            "subcategory":"Insurance Agent",
            "type":"Services"
        }
    ],
    "sg:phone":"+1 601 799 1758",
    "sg:postcode":"39466",
    "sg:province":"MS",
    "wof:name":"Seal Insurance Inc",
    "wof:placetype":"venue"
},
  "geometry": {"coordinates":[-89.679748,30.525686],"type":"Point"}
}