{
  "type": "Feature",
  "properties": {
    "iso:country":"US",
    "sg:address":"746 Fairway Trl",
    "sg:city":"Hernando",
    "sg:classifiers":[
        {
            "category":"Government",
            "subcategory":"Police Station",
            "type":"Public Place"
        }
    ],
    "sg:phone":"+1 662 429 7775",
    "sg:postcode":"38632",
    "sg:province":"MS",
    "sg:tags":[
        "investigator"
    ],
    "wof:name":"Rice Investigative Service",
    "wof:placetype":"venue"
},
  "geometry": {"coordinates":[-89.976456,34.851222],"type":"Point"}
}