{
  "type": "Feature",
  "properties": {
    "iso:country":"US",
    "sg:address":"928 Pine Bluff Rd",
    "sg:city":"Newton",
    "sg:classifiers":[
        {
            "category":"Professional",
            "subcategory":"Management & Consulting",
            "type":"Services"
        }
    ],
    "sg:phone":"+1 601 683 3982",
    "sg:postcode":"39345",
    "sg:province":"MS",
    "sg:tags":[
        "retail",
        "direct",
        "sales"
    ],
    "wof:name":"Carroll Enterprises",
    "wof:placetype":"venue"
},
  "geometry": {"coordinates":[-89.16628799999999,32.339778],"type":"Point"}
}