{
  "type": "Feature",
  "properties": {
    "iso:country":"US",
    "sg:address":"806 S Church Ave",
    "sg:city":"Louisville",
    "sg:classifiers":[
        {
            "category":"Professional",
            "subcategory":"Accounting & Tax Preparation",
            "type":"Services"
        }
    ],
    "sg:phone":"+1 662 773 4262",
    "sg:postcode":"39339",
    "sg:province":"MS",
    "sg:tags":[
        "accountant"
    ],
    "wof:name":"Joe H Hodge CPA",
    "wof:placetype":"venue"
},
  "geometry": {"coordinates":[-89.05529300000001,33.11303],"type":"Point"}
}