{
  "type": "Feature",
  "properties": {
    "addr:full":"204 N 13th Ave Laurel MS 39440",
    "addr:housenumber":"204",
    "addr:postcode":"39440",
    "addr:street":"N 13Th Ave",
    "iso:country":"US",
    "sg:address":"204 N 13th Ave",
    "sg:city":"Laurel",
    "sg:classifiers":[
        {
            "category":"Personal",
            "subcategory":"Beauty Salon",
            "type":"Services"
        }
    ],
    "sg:phone":"+1 601 428 4016",
    "sg:postcode":"39440",
    "sg:province":"MS",
    "wof:name":"Wavelengths",
    "wof:placetype":"venue"
},
  "geometry": {"coordinates":[-89.14278400000001,31.691838],"type":"Point"}
}