{
  "type": "Feature",
  "properties": {
    "addr:full":"2152 Jackson Ave W Oxford MS 38655",
    "addr:housenumber":"2152",
    "addr:postcode":"38655",
    "addr:street":"Jackson Ave W",
    "iso:country":"US",
    "sg:address":"2152 Jackson Ave W",
    "sg:city":"Oxford",
    "sg:classifiers":[
        {
            "category":"Banks & Credit Unions",
            "subcategory":"Bank",
            "type":"Services"
        }
    ],
    "sg:phone":"+1 662 236 3040",
    "sg:postcode":"38655",
    "sg:province":"MS",
    "sg:tags":[
        "cashing",
        "check"
    ],
    "wof:name":"Rapid Cash & Tax Svc",
    "wof:placetype":"venue"
},
  "geometry": {"coordinates":[-89.560061,34.362829],"type":"Point"}
}