{
  "type": "Feature",
  "properties": {
    "addr:full":"1411 Stonehedge Dr Southaven MS 38671",
    "addr:housenumber":"1411",
    "addr:postcode":"38671",
    "addr:street":"Stonehedge Dr",
    "iso:country":"US",
    "sg:address":"1411 Stonehedge Dr",
    "sg:city":"Southaven",
    "sg:classifiers":[
        {
            "category":"Real Estate",
            "subcategory":"Real Estate Agent",
            "type":"Services"
        },
        {
            "category":"Professional",
            "subcategory":"Business Services",
            "type":"Services"
        }
    ],
    "sg:phone":"+1 662 349 1500",
    "sg:postcode":"38671",
    "sg:province":"MS",
    "sg:tags":[
        "inspection"
    ],
    "wof:name":"Mitchell's Home Inspection",
    "wof:placetype":"venue"
},
  "geometry": {"coordinates":[-89.96440200000001,34.955957],"type":"Point"}
}