{
  "type": "Feature",
  "properties": {
    "iso:country":"US",
    "sg:address":"654 Cross St",
    "sg:city":"Laurel",
    "sg:classifiers":[
        {
            "category":"Autos & Motor Vehicles",
            "subcategory":"Automobile Sales",
            "type":"Retail Goods"
        }
    ],
    "sg:phone":"+1 601 428 7604",
    "sg:postcode":"39440",
    "sg:province":"MS",
    "sg:tags":[
        "car",
        "dealer"
    ],
    "wof:name":"Ray Auto Sales",
    "wof:placetype":"venue"
},
  "geometry": {"coordinates":[-89.123158,31.696754],"type":"Point"}
}