{
  "type": "Feature",
  "properties": {
    "iso:country":"US",
    "sg:address":"125 Main St",
    "sg:city":"Bay Saint Louis",
    "sg:classifiers":[
        {
            "category":"Shopping",
            "subcategory":"Used Merchandise",
            "type":"Retail Goods"
        }
    ],
    "sg:phone":"+1 228 467 4665",
    "sg:postcode":"39520",
    "sg:province":"MS",
    "wof:name":"Charters Antiques",
    "wof:placetype":"venue"
},
  "geometry": {"coordinates":[-89.32632700000001,30.310676],"type":"Point"}
}