{
  "type": "Feature",
  "properties": {
    "addr:full":"129 N Street Dr Brookhaven MS 39601",
    "addr:housenumber":"129",
    "addr:postcode":"39601",
    "addr:street":"N Street Dr",
    "iso:country":"US",
    "sg:address":"129 N Street Dr",
    "sg:city":"Brookhaven",
    "sg:classifiers":[
        {
            "category":"Retail",
            "subcategory":"Repair Shop",
            "type":"Services"
        }
    ],
    "sg:phone":"+1 601 835 1432",
    "sg:postcode":"39601",
    "sg:province":"MS",
    "wof:name":"James McGhee",
    "wof:placetype":"venue"
},
  "geometry": {"coordinates":[-90.43586000000001,31.602959],"type":"Point"}
}