{
  "type": "Feature",
  "properties": {
    "iso:country":"US",
    "sg:address":"1781 Nesbit Rd",
    "sg:city":"Nesbit",
    "sg:classifiers":[
        {
            "category":"Professional",
            "subcategory":"Business Services",
            "type":"Services"
        }
    ],
    "sg:phone":"+1 662 429 0168",
    "sg:postcode":"38651",
    "sg:province":"MS",
    "wof:name":"Wiley Enterprises Inc",
    "wof:placetype":"venue"
},
  "geometry": {"coordinates":[-90.020478,34.889686],"type":"Point"}
}