{
  "type": "Feature",
  "properties": {
    "addr:full":"2417 Hwy 80 E Pearl MS 39208",
    "addr:housenumber":"2417",
    "addr:postcode":"39208",
    "addr:street":"Hwy 80 E",
    "iso:country":"US",
    "sg:address":"2417 Hwy 80 E",
    "sg:city":"Pearl",
    "sg:classifiers":[
        {
            "category":"Professional",
            "subcategory":"Advertising",
            "type":"Services"
        },
        {
            "category":"Shopping",
            "subcategory":"Bicycles & Sporting Goods",
            "type":"Retail Goods"
        }
    ],
    "sg:phone":"+1 601 939 9558",
    "sg:postcode":"39208",
    "sg:province":"MS",
    "sg:tags":[
        "outdoor",
        "gun",
        "gunsmith"
    ],
    "wof:name":"Great Southern Firearms Inc",
    "wof:placetype":"venue"
},
  "geometry": {"coordinates":[-90.133675,32.280462],"type":"Point"}
}