{
  "type": "Feature",
  "properties": {
    "iso:country":"US",
    "sg:address":"110 C and S Rd",
    "sg:city":"Kokomo",
    "sg:classifiers":[
        {
            "category":"Freight",
            "type":"Transportation"
        }
    ],
    "sg:phone":"+1 601 736 5576",
    "sg:postcode":"39643",
    "sg:province":"MS",
    "sg:tags":[
        "operator",
        "trucking"
    ],
    "wof:name":"Star-Rite Products Inc",
    "wof:placetype":"venue"
},
  "geometry": {"coordinates":[-89.94576000000001,31.214724],"type":"Point"}
}