{
  "type": "Feature",
  "properties": {
    "iso:country":"US",
    "sg:address":"409 W Cypress St",
    "sg:city":"Charleston",
    "sg:classifiers":[
        {
            "category":"Professional",
            "subcategory":"Detective & Security Services",
            "type":"Services"
        }
    ],
    "sg:phone":"+1 662 647 5070",
    "sg:postcode":"38921",
    "sg:province":"MS",
    "sg:tags":[
        "criminologist"
    ],
    "wof:name":"Corrections Management Svc",
    "wof:placetype":"venue"
},
  "geometry": {"coordinates":[-90.063254,34.005036],"type":"Point"}
}