{
  "type": "Feature",
  "properties": {
    "addr:full":"105 S Main St Yazoo City MS 39194",
    "addr:housenumber":"105",
    "addr:postcode":"39194",
    "addr:street":"S Main St",
    "iso:country":"US",
    "sg:address":"105 S Main St",
    "sg:city":"Yazoo City",
    "sg:classifiers":[
        {
            "category":"Banks & Credit Unions",
            "subcategory":"Investment Brokerage",
            "type":"Services"
        }
    ],
    "sg:phone":"+1 662 746 5255",
    "sg:postcode":"39194",
    "sg:province":"MS",
    "sg:tags":[
        "security"
    ],
    "wof:name":"Mc Graw Life & Health Svc",
    "wof:placetype":"venue"
},
  "geometry": {"coordinates":[-90.416556,32.843393],"type":"Point"}
}