{
  "type": "Feature",
  "properties": {
    "iso:country":"US",
    "sg:address":"7060 302 Industrial Dr",
    "sg:city":"Southaven",
    "sg:classifiers":[
        {
            "category":"Real Estate",
            "subcategory":"Real Estate Agent",
            "type":"Services"
        }
    ],
    "sg:phone":"+1 662 349 7973",
    "sg:postcode":"38671",
    "sg:province":"MS",
    "sg:tags":[
        "inspection"
    ],
    "wof:name":"Ameri Spec Home Inspection Svc",
    "wof:placetype":"venue"
},
  "geometry": {"coordinates":[-89.926765,34.335685],"type":"Point"}
}