{
  "type": "Feature",
  "properties": {
    "iso:country":"US",
    "sg:address":"4204 Ridgemont Dr",
    "sg:city":"Tupelo",
    "sg:classifiers":[
        {
            "category":"Wholesale",
            "subcategory":"Machinery & Supplies",
            "type":"Manufacturing & Wholesale Goods"
        }
    ],
    "sg:phone":"+1 662 620 0889",
    "sg:postcode":"38826",
    "sg:province":"MS",
    "sg:tags":[
        "equipment",
        "conveyor",
        "conveying"
    ],
    "wof:name":"Hewitt Robins",
    "wof:placetype":"venue"
},
  "geometry": {"coordinates":[-88.77922100000001,34.294232],"type":"Point"}
}