{
  "type": "Feature",
  "properties": {
    "iso:country":"US",
    "sg:address":"205 Pine St",
    "sg:city":"Mc Comb",
    "sg:classifiers":[
        {
            "category":"Building & Trades",
            "subcategory":"Construction",
            "type":"Services"
        }
    ],
    "sg:phone":"+1 601 249 2808",
    "sg:postcode":"39648",
    "sg:province":"MS",
    "sg:tags":[
        "remodeling",
        "general"
    ],
    "wof:name":"Johnny Turner Construction",
    "wof:placetype":"venue"
},
  "geometry": {"coordinates":[-90.45303699999999,31.260334],"type":"Point"}
}