{
  "type": "Feature",
  "properties": {
    "iso:country":"US",
    "sg:address":"4521 Broadmeadow St",
    "sg:city":"Jackson",
    "sg:classifiers":[
        {
            "category":"Education",
            "subcategory":"School",
            "type":"Public Place"
        }
    ],
    "sg:phone":"+1 601 987 3504",
    "sg:postcode":"39206",
    "sg:province":"MS",
    "wof:name":"Boyd Elementary School",
    "wof:placetype":"venue"
},
  "geometry": {"coordinates":[-90.16522500000001,32.35534],"type":"Point"}
}