{
  "type": "Feature",
  "properties": {
    "addr:full":"505 Apache Dr Mccomb MS 39648",
    "addr:housenumber":"505",
    "addr:postcode":"39648",
    "addr:street":"Apache Dr",
    "iso:country":"US",
    "sg:address":"505 Apache Dr",
    "sg:city":"Mccomb",
    "sg:classifiers":[
        {
            "category":"Building & Trades",
            "subcategory":"Construction",
            "type":"Services"
        }
    ],
    "sg:phone":"+1 601 684 1841",
    "sg:postcode":"39648",
    "sg:province":"MS",
    "sg:tags":[
        "home",
        "builder"
    ],
    "wof:name":"Jim Walter Homes Inc",
    "wof:placetype":"venue"
},
  "geometry": {"coordinates":[-90.480063,31.254021],"type":"Point"}
}