{
  "type": "Feature",
  "properties": {
    "iso:country":"US",
    "sg:address":"814 E Sunflower Rd",
    "sg:city":"Cleveland",
    "sg:classifiers":[
        {
            "category":"Insurance",
            "subcategory":"Insurance Agent",
            "type":"Services"
        }
    ],
    "sg:phone":"+1 662 843 4727",
    "sg:postcode":"38732",
    "sg:province":"MS",
    "wof:name":"New York Life Insurance Co",
    "wof:placetype":"venue"
},
  "geometry": {"coordinates":[-90.71052299999999,33.747295],"type":"Point"}
}