{
  "type": "Feature",
  "properties": {
    "iso:country":"US",
    "sg:address":"106 Hickory Ln",
    "sg:city":"Pontotoc",
    "sg:classifiers":[
        {
            "category":"Food & Beverages",
            "subcategory":"Groceries & Convenience Stores",
            "type":"Retail Goods"
        }
    ],
    "sg:phone":"+1 662 489 7964",
    "sg:postcode":"38863",
    "sg:province":"MS",
    "wof:name":"Marks Quick Stop",
    "wof:placetype":"venue"
},
  "geometry": {"coordinates":[-89.07832999999999,34.227192],"type":"Point"}
}