{
  "type": "Feature",
  "properties": {
    "addr:full":"1743 Hwy 15 N Pontotoc MS 38863",
    "addr:housenumber":"1743",
    "addr:postcode":"38863",
    "addr:street":"Hwy 15 N",
    "iso:country":"US",
    "sg:address":"1743 Hwy 15 N",
    "sg:city":"Pontotoc",
    "sg:classifiers":[
        {
            "category":"Government",
            "subcategory":"Office",
            "type":"Public Place"
        }
    ],
    "sg:phone":"+1 601 955 0803",
    "sg:postcode":"38863",
    "sg:province":"MS",
    "sg:tags":[
        "federal",
        "security"
    ],
    "wof:name":"National Guard Recruiter",
    "wof:placetype":"venue"
},
  "geometry": {"coordinates":[-89.023719,34.273771],"type":"Point"}
}