{
  "type": "Feature",
  "properties": {
    "addr:full":"5555 Hwy 18 W Jackson MS 39209",
    "addr:housenumber":"5555",
    "addr:postcode":"39209",
    "addr:street":"Hwy 18 W",
    "iso:country":"US",
    "sg:address":"5555 Hwy 18 W",
    "sg:city":"Jackson",
    "sg:classifiers":[
        {
            "category":"Food & Beverages",
            "subcategory":"Groceries & Convenience Stores",
            "type":"Retail Goods"
        }
    ],
    "sg:phone":"+1 601 922 2721",
    "sg:postcode":"39209",
    "sg:province":"MS",
    "sg:tags":[
        "grocer"
    ],
    "wof:name":"Mac's Convenience Store",
    "wof:placetype":"venue"
},
  "geometry": {"coordinates":[-90.281047,32.278872],"type":"Point"}
}