{
  "type": "Feature",
  "properties": {
    "addr:full":"17441 C J Dellie Rd Saucier MS 39574",
    "addr:housenumber":"17441",
    "addr:postcode":"39574",
    "addr:street":"C J Dellie Rd",
    "iso:country":"US",
    "sg:address":"17441 C J Dellie Rd",
    "sg:city":"Saucier",
    "sg:classifiers":[
        {
            "category":"Building & Trades",
            "subcategory":"Landscaping Services",
            "type":"Services"
        }
    ],
    "sg:phone":"+1 228 392 3806",
    "sg:postcode":"39574",
    "sg:province":"MS",
    "wof:name":"Durhams Tree Service",
    "wof:placetype":"venue"
},
  "geometry": {"coordinates":[-88.932794,30.543072],"type":"Point"}
}