{
  "type": "Feature",
  "properties": {
    "addr:full":"2700 Co Rd 402 Corinth MS 38834",
    "addr:housenumber":"2700",
    "addr:postcode":"38834",
    "addr:street":"Co Rd 402",
    "iso:country":"US",
    "sg:address":"2700 Co Rd 402",
    "sg:city":"Corinth",
    "sg:classifiers":[
        {
            "category":"Organizations",
            "subcategory":"Labor Organization",
            "type":"Services"
        }
    ],
    "sg:phone":"+1 662 287 3863",
    "sg:postcode":"38834",
    "sg:province":"MS",
    "wof:name":"United Steelworkers Of America",
    "wof:placetype":"venue"
},
  "geometry": {"coordinates":[-88.523444,34.904824],"type":"Point"}
}