{
  "type": "Feature",
  "properties": {
    "addr:full":"1063 Loop Rd Lake MS 39092",
    "addr:housenumber":"1063",
    "addr:postcode":"39092",
    "addr:street":"Loop Rd",
    "iso:country":"US",
    "sg:address":"1063 Loop Rd",
    "sg:city":"Lake",
    "sg:classifiers":[
        {
            "category":"Building & Trades",
            "subcategory":"Construction",
            "type":"Services"
        }
    ],
    "sg:phone":"+1 601 536 2445",
    "sg:postcode":"39092",
    "sg:province":"MS",
    "sg:tags":[
        "concrete",
        "contractor"
    ],
    "wof:name":"Sessums Concrete Finishing",
    "wof:placetype":"venue"
},
  "geometry": {"coordinates":[-89.416211,32.318566],"type":"Point"}
}