{
  "type": "Feature",
  "properties": {
    "iso:country":"US",
    "sg:address":"207 S Davis Ave",
    "sg:city":"Cleveland",
    "sg:classifiers":[
        {
            "category":"Shopping",
            "type":"Retail Goods"
        }
    ],
    "sg:phone":"+1 662 843 8612",
    "sg:postcode":"38732",
    "sg:province":"MS",
    "sg:tags":[
        "cosmetic",
        "perfume"
    ],
    "wof:name":"Dream Hair & Beauty Supply",
    "wof:placetype":"venue"
},
  "geometry": {"coordinates":[-90.715723,33.741982],"type":"Point"}
}