{
  "type": "Feature",
  "properties": {
    "addr:full":"317 Highland Blvd Natchez MS 39120",
    "addr:housenumber":"317",
    "addr:postcode":"39120",
    "addr:street":"Highland Blvd",
    "iso:country":"US",
    "sg:address":"317 Highland Blvd",
    "sg:city":"Natchez",
    "sg:classifiers":[
        {
            "category":"Shopping",
            "subcategory":"Computers & Home Electronics",
            "type":"Retail Goods"
        }
    ],
    "sg:phone":"+1 601 446 8598",
    "sg:postcode":"39120",
    "sg:province":"MS",
    "sg:tags":[
        "equipment",
        "dealer"
    ],
    "wof:name":"D & L Allgood Custom Computer",
    "wof:placetype":"venue"
},
  "geometry": {"coordinates":[-91.39765,31.521179],"type":"Point"}
}