{
  "type": "Feature",
  "properties": {
    "iso:country":"US",
    "sg:address":"126 W Main St",
    "sg:city":"West Point",
    "sg:classifiers":[
        {
            "category":"Shopping",
            "type":"Retail Goods"
        },
        {
            "category":"Museum",
            "type":"Entertainment"
        }
    ],
    "sg:phone":"+1 662 494 1900",
    "sg:postcode":"39773",
    "sg:province":"MS",
    "sg:tags":[
        "picture",
        "frame",
        "gallery"
    ],
    "wof:name":"Davis Framing and Gallery",
    "wof:placetype":"venue"
},
  "geometry": {"coordinates":[-88.65083,33.607025],"type":"Point"}
}