{
  "type": "Feature",
  "properties": {
    "addr:full":"301 Stateline Rd W Southaven MS 38671",
    "addr:housenumber":"301",
    "addr:postcode":"38671",
    "addr:street":"Stateline Rd W",
    "iso:country":"US",
    "sg:address":"301 Stateline Rd W",
    "sg:city":"Southaven",
    "sg:classifiers":[
        {
            "category":"Autos & Motor Vehicles",
            "subcategory":"Auto Supplies",
            "type":"Retail Goods"
        }
    ],
    "sg:phone":"+1 662 342 6021",
    "sg:postcode":"38671",
    "sg:province":"MS",
    "sg:tags":[
        "tire"
    ],
    "wof:name":"Goodyear",
    "wof:placetype":"venue"
},
  "geometry": {"coordinates":[-89.994209,34.991773],"type":"Point"}
}