{
  "type": "Feature",
  "properties": {
    "addr:full":"2411 32nd St Gulfport MS 39501",
    "addr:housenumber":"2411",
    "addr:postcode":"39501",
    "addr:street":"32Nd St",
    "iso:country":"US",
    "sg:address":"2411 32nd St",
    "sg:city":"Gulfport",
    "sg:classifiers":[
        {
            "category":"Organizations",
            "subcategory":"Labor Organization",
            "type":"Services"
        }
    ],
    "sg:phone":"+1 228 863 4705",
    "sg:postcode":"39501",
    "sg:province":"MS",
    "wof:name":"IBEW",
    "wof:placetype":"venue"
},
  "geometry": {"coordinates":[-89.093034,30.389038],"type":"Point"}
}