{
  "type": "Feature",
  "properties": {
    "addr:full":"514 Washington Ave Ocean Springs MS 39564",
    "addr:housenumber":"514",
    "addr:postcode":"39564",
    "addr:street":"Washington Ave",
    "iso:country":"US",
    "sg:address":"514 Washington Ave",
    "sg:city":"Ocean Springs",
    "sg:classifiers":[
        {
            "category":"Social Services",
            "type":"Services"
        }
    ],
    "sg:phone":"+1 228 872 3653",
    "sg:postcode":"39564",
    "sg:province":"MS",
    "sg:tags":[
        "senior",
        "citizen"
    ],
    "wof:name":"Ocean Springs Senior Citizens",
    "wof:placetype":"venue"
},
  "geometry": {"coordinates":[-88.82780099999999,30.410304],"type":"Point"}
}