{
  "type": "Feature",
  "properties": {
    "iso:country":"US",
    "sg:address":"4030 Barnes Rd",
    "sg:city":"Crystal Springs",
    "sg:classifiers":[
        {
            "category":"Professional",
            "subcategory":"Engineering",
            "type":"Services"
        }
    ],
    "sg:phone":"+1 601 892 6388",
    "sg:postcode":"39059",
    "sg:province":"MS",
    "wof:name":"Julius Cooke Jr",
    "wof:placetype":"venue"
},
  "geometry": {"coordinates":[-90.28895300000001,32.02816],"type":"Point"}
}