{
  "type": "Feature",
  "properties": {
    "addr:full":"3103 Audubon Dr Laurel MS 39440",
    "addr:housenumber":"3103",
    "addr:postcode":"39440",
    "addr:street":"Audubon Dr",
    "iso:country":"US",
    "sg:address":"3103 Audubon Dr",
    "sg:city":"Laurel",
    "sg:classifiers":[
        {
            "category":"Personal",
            "type":"Services"
        }
    ],
    "sg:phone":"+1 601 649 7805",
    "sg:postcode":"39440",
    "sg:province":"MS",
    "wof:name":"Tropical Rayz",
    "wof:placetype":"venue"
},
  "geometry": {"coordinates":[-89.138869,31.729217],"type":"Point"}
}