{
  "type": "Feature",
  "properties": {
    "addr:full":"16438 Sweet Carolyn Dr Biloxi MS 39532",
    "addr:housenumber":"16438",
    "addr:postcode":"39532",
    "addr:street":"Sweet Carolyn Dr",
    "iso:country":"US",
    "sg:address":"16438 Sweet Carolyn Dr",
    "sg:city":"Biloxi",
    "sg:classifiers":[
        {
            "category":"Building & Trades",
            "subcategory":"Construction",
            "type":"Services"
        }
    ],
    "sg:phone":"+1 228 392 6883",
    "sg:postcode":"39532",
    "sg:province":"MS",
    "sg:tags":[
        "contractor"
    ],
    "wof:name":"Shoemaker Drywall",
    "wof:placetype":"venue"
},
  "geometry": {"coordinates":[-89.028935,30.526615],"type":"Point"}
}