{
  "type": "Feature",
  "properties": {
    "iso:country":"US",
    "sg:address":"714 Washington Ave",
    "sg:city":"Ocean Springs",
    "sg:classifiers":[
        {
            "category":"Shopping",
            "type":"Retail Goods"
        }
    ],
    "sg:phone":"+1 228 875 1166",
    "sg:postcode":"39564",
    "sg:province":"MS",
    "sg:tags":[
        "picture",
        "frame"
    ],
    "wof:name":"Whistle Stop Framing Gallery",
    "wof:placetype":"venue"
},
  "geometry": {"coordinates":[-88.82770600000001,30.413496],"type":"Point"}
}