{
  "type": "Feature",
  "properties": {
    "addr:full":"124 Kings Ridge Dr Brandon MS 39047",
    "addr:housenumber":"124",
    "addr:postcode":"39047",
    "addr:street":"Kings Ridge Dr",
    "iso:country":"US",
    "sg:address":"124 Kings Ridge Dr",
    "sg:city":"Brandon",
    "sg:classifiers":[
        {
            "category":"Professional",
            "subcategory":"Accounting & Tax Preparation",
            "type":"Services"
        }
    ],
    "sg:phone":"+1 601 992 4535",
    "sg:postcode":"39047",
    "sg:province":"MS",
    "sg:tags":[
        "payroll"
    ],
    "wof:name":"Payroll Benefits Group",
    "wof:placetype":"venue"
},
  "geometry": {"coordinates":[-90.034442,32.390512],"type":"Point"}
}