{
  "type": "Feature",
  "properties": {
    "iso:country":"US",
    "sg:address":"1215 N Main St",
    "sg:city":"Ripley",
    "sg:classifiers":[
        {
            "category":"Organizations",
            "subcategory":"Religious Organization",
            "type":"Services"
        }
    ],
    "sg:phone":"+1 662 837 7498",
    "sg:postcode":"38663",
    "sg:province":"MS",
    "wof:name":"North Ripley Baptist Church",
    "wof:placetype":"venue"
},
  "geometry": {"coordinates":[-88.945776,34.744662],"type":"Point"}
}