{
  "type": "Feature",
  "properties": {
    "iso:country":"US",
    "sg:address":"100 W Harrison St",
    "sg:city":"Ruleville",
    "sg:classifiers":[
        {
            "category":"Insurance",
            "subcategory":"Hazard Insurance",
            "type":"Services"
        }
    ],
    "sg:phone":"+1 662 756 2005",
    "sg:postcode":"38771",
    "sg:province":"MS",
    "sg:tags":[
        "bond"
    ],
    "wof:name":"Interstate Bail Bonds",
    "wof:placetype":"venue"
},
  "geometry": {"coordinates":[-90.551603,33.728491],"type":"Point"}
}