{
  "type": "Feature",
  "properties": {
    "iso:country":"US",
    "sg:address":"306 Maple St",
    "sg:city":"Mound Bayou",
    "sg:classifiers":[
        {
            "category":"Shopping",
            "subcategory":"Computers & Home Electronics",
            "type":"Retail Goods"
        }
    ],
    "sg:phone":"+1 662 741 2065",
    "sg:postcode":"38732",
    "sg:province":"MS",
    "sg:tags":[
        "television",
        "radio"
    ],
    "wof:name":"Robert's TV Svc",
    "wof:placetype":"venue"
},
  "geometry": {"coordinates":[-90.73687700000001,33.741786],"type":"Point"}
}