{
  "type": "Feature",
  "properties": {
    "addr:full":"607 W 2nd St Clarksdale MS 38614",
    "addr:housenumber":"607",
    "addr:postcode":"38614",
    "addr:street":"W 2Nd St",
    "iso:country":"US",
    "sg:address":"607 W 2nd St",
    "sg:city":"Clarksdale",
    "sg:classifiers":[
        {
            "category":"Airline",
            "type":"Transportation"
        }
    ],
    "sg:phone":"+1 662 624 5902",
    "sg:postcode":"38614",
    "sg:province":"MS",
    "sg:tags":[
        "nonscheduled",
        "air"
    ],
    "wof:name":"Specialty Air Charter",
    "wof:placetype":"venue"
},
  "geometry": {"coordinates":[-90.588955,34.200823],"type":"Point"}
}