{
  "type": "Feature",
  "properties": {
    "addr:full":"2318 Hwy 80 E Jackson MS 39208",
    "addr:housenumber":"2318",
    "addr:postcode":"39208",
    "addr:street":"Hwy 80 E",
    "iso:country":"US",
    "sg:address":"2318 Hwy 80 E",
    "sg:city":"Jackson",
    "sg:classifiers":[
        {
            "category":"Home & Garden",
            "subcategory":"Mobile Homes",
            "type":"Retail Goods"
        }
    ],
    "sg:phone":"+1 601 939 0461",
    "sg:postcode":"39208",
    "sg:province":"MS",
    "wof:name":"Clayton Homes",
    "wof:placetype":"venue"
},
  "geometry": {"coordinates":[-90.13451499999999,32.280177],"type":"Point"}
}