{
  "type": "Feature",
  "properties": {
    "iso:country":"US",
    "sg:address":"2800 33rd St",
    "sg:city":"Gulfport",
    "sg:classifiers":[
        {
            "category":"Professional",
            "subcategory":"Business Services",
            "type":"Services"
        }
    ],
    "sg:phone":"+1 228 864 1465",
    "sg:postcode":"39501",
    "sg:province":"MS",
    "sg:tags":[
        "packaging"
    ],
    "wof:name":"Craters & Freighters",
    "wof:placetype":"venue"
},
  "geometry": {"coordinates":[-89.097981,30.390249],"type":"Point"}
}