{
  "type": "Feature",
  "properties": {
    "iso:country":"US",
    "sg:address":"279 Kokomo Rd",
    "sg:city":"Kokomo",
    "sg:classifiers":[
        {
            "category":"Organizations",
            "subcategory":"Religious Organization",
            "type":"Services"
        }
    ],
    "sg:phone":"+1 601 736 8338",
    "sg:postcode":"39643",
    "sg:province":"MS",
    "sg:tags":[
        "church"
    ],
    "wof:name":"New Damascus Baptist Church",
    "wof:placetype":"venue"
},
  "geometry": {"coordinates":[-90.004446,31.211792],"type":"Point"}
}