{
  "type": "Feature",
  "properties": {
    "iso:country":"US",
    "sg:address":"753 Glencross Dr",
    "sg:city":"Jackson",
    "sg:classifiers":[
        {
            "category":"Real Estate",
            "subcategory":"Real Estate Operator",
            "type":"Services"
        }
    ],
    "sg:phone":"+1 601 957 1449",
    "sg:postcode":"39206",
    "sg:province":"MS",
    "sg:tags":[
        "apartment"
    ],
    "wof:name":"Willow Point Townhomes",
    "wof:placetype":"venue"
},
  "geometry": {"coordinates":[-90.162584,32.392434],"type":"Point"}
}