{
  "type": "Feature",
  "properties": {
    "iso:country":"US",
    "sg:address":"1609 Carsley Rd",
    "sg:city":"Jackson",
    "sg:classifiers":[
        {
            "category":"Recreation",
            "type":"Entertainment"
        }
    ],
    "sg:phone":"+1 601 924 3140",
    "sg:postcode":"39209",
    "sg:province":"MS",
    "sg:tags":[
        "stable"
    ],
    "wof:name":"Dancing Hooves Stable",
    "wof:placetype":"venue"
},
  "geometry": {"coordinates":[-90.372569,32.457724],"type":"Point"}
}