{
  "type": "Feature",
  "properties": {
    "iso:country":"US",
    "sg:address":"1001 N Main St",
    "sg:city":"Hattiesburg",
    "sg:classifiers":[
        {
            "category":"Shopping",
            "subcategory":"Florist",
            "type":"Retail Goods"
        }
    ],
    "sg:phone":"+1 601 583 1181",
    "sg:postcode":"39401",
    "sg:province":"MS",
    "wof:name":"Mc Cray's Florist",
    "wof:placetype":"venue"
},
  "geometry": {"coordinates":[-89.296893,31.332493],"type":"Point"}
}