{
  "type": "Feature",
  "properties": {
    "iso:country":"US",
    "sg:address":"148 W Cherry St",
    "sg:city":"Ackerman",
    "sg:classifiers":[
        {
            "category":"Social Services",
            "subcategory":"Job Training",
            "type":"Services"
        }
    ],
    "sg:phone":"+1 662 285 3612",
    "sg:postcode":"39735",
    "sg:province":"MS",
    "sg:tags":[
        "rehabilitation"
    ],
    "wof:name":"Trinity Rehab",
    "wof:placetype":"venue"
},
  "geometry": {"coordinates":[-89.176823,33.312602],"type":"Point"}
}