{
  "type": "Feature",
  "properties": {
    "addr:full":"4525 Long Creek Rd Memphis MS 38125",
    "addr:housenumber":"4525",
    "addr:postcode":"38125",
    "addr:street":"Long Creek Rd",
    "iso:country":"US",
    "sg:address":"4525 Long Creek Rd",
    "sg:city":"Memphis",
    "sg:classifiers":[
        {
            "category":"Freight",
            "type":"Transportation"
        }
    ],
    "sg:phone":"+1 901 758 1438",
    "sg:postcode":"38125",
    "sg:province":"MS",
    "sg:tags":[
        "operator",
        "local",
        "trucking"
    ],
    "wof:name":"Tr T Trucking",
    "wof:placetype":"venue"
},
  "geometry": {"coordinates":[-89.807964,35.024908],"type":"Point"}
}