{
  "type": "Feature",
  "properties": {
    "iso:country":"US",
    "sg:address":"52 Gulledge Dr",
    "sg:city":"Collins",
    "sg:classifiers":[
        {
            "category":"Freight",
            "type":"Transportation"
        }
    ],
    "sg:phone":"+1 601 722 3996",
    "sg:postcode":"39428",
    "sg:province":"MS",
    "sg:tags":[
        "operator",
        "local",
        "trucking"
    ],
    "wof:name":"L&L Trucking",
    "wof:placetype":"venue"
},
  "geometry": {"coordinates":[-89.574395,31.548488],"type":"Point"}
}