{
  "type": "Feature",
  "properties": {
    "iso:country":"US",
    "sg:address":"1811 Ray St",
    "sg:city":"Ocean Springs",
    "sg:classifiers":[
        {
            "category":"Real Estate",
            "subcategory":"Architect",
            "type":"Services"
        }
    ],
    "sg:phone":"+1 228 875 7606",
    "sg:postcode":"39564",
    "sg:province":"MS",
    "wof:name":"Bargas & Associates Architects",
    "wof:placetype":"venue"
},
  "geometry": {"coordinates":[-88.817167,30.421127],"type":"Point"}
}