{
  "type": "Feature",
  "properties": {
    "iso:country":"US",
    "sg:address":"1109 Lower Woodville Rd",
    "sg:city":"Natchez",
    "sg:classifiers":[
        {
            "category":"Wholesale",
            "subcategory":"Groceries",
            "type":"Manufacturing & Wholesale Goods"
        }
    ],
    "sg:phone":"+1 601 442 2767",
    "sg:postcode":"39120",
    "sg:province":"MS",
    "sg:tags":[
        "food",
        "product"
    ],
    "wof:name":"White Apple Farms",
    "wof:placetype":"venue"
},
  "geometry": {"coordinates":[-91.397362,31.412889],"type":"Point"}
}