{
  "type": "Feature",
  "properties": {
    "addr:full":"247 N Woodland Dr Forest MS 39074",
    "addr:housenumber":"247",
    "addr:postcode":"39074",
    "addr:street":"N Woodland Dr",
    "iso:country":"US",
    "sg:address":"247 N Woodland Dr",
    "sg:city":"Forest",
    "sg:classifiers":[
        {
            "category":"Banks & Credit Unions",
            "subcategory":"Bank",
            "type":"Services"
        }
    ],
    "sg:phone":"+1 601 469 3424",
    "sg:postcode":"39074",
    "sg:province":"MS",
    "wof:name":"Citizens Bank",
    "wof:placetype":"venue"
},
  "geometry": {"coordinates":[-89.473215,32.374701],"type":"Point"}
}