{
  "type": "Feature",
  "properties": {
    "addr:full":"291 Sunflower Ave Clarksdale MS 38614",
    "addr:housenumber":"291",
    "addr:postcode":"38614",
    "addr:street":"Sunflower Ave",
    "iso:country":"US",
    "sg:address":"291 Sunflower Ave",
    "sg:city":"Clarksdale",
    "sg:classifiers":[
        {
            "category":"Education",
            "subcategory":"Special Training",
            "type":"Public Place"
        }
    ],
    "sg:phone":"+1 662 627 4070",
    "sg:postcode":"38614",
    "sg:province":"MS",
    "sg:tags":[
        "educational"
    ],
    "wof:name":"Delta Blues Education Fund",
    "wof:placetype":"venue"
},
  "geometry": {"coordinates":[-90.57496500000001,34.19988],"type":"Point"}
}