{
  "type": "Feature",
  "properties": {
    "iso:country":"US",
    "sg:address":"105 W Bankhead St",
    "sg:city":"New Albany",
    "sg:classifiers":[
        {
            "category":"Manufacturing",
            "subcategory":"Printing",
            "type":"Manufacturing & Wholesale Goods"
        }
    ],
    "sg:phone":"+1 662 534 8714",
    "sg:postcode":"38652",
    "sg:province":"MS",
    "sg:tags":[
        "printer"
    ],
    "wof:name":"Network Printing",
    "wof:placetype":"venue"
},
  "geometry": {"coordinates":[-89.010687,34.494938],"type":"Point"}
}