{
  "type": "Feature",
  "properties": {
    "addr:full":"527 Front Beach Dr Ocean Springs MS 39564",
    "addr:housenumber":"527",
    "addr:postcode":"39564",
    "addr:street":"Front Beach Dr",
    "iso:country":"US",
    "sg:address":"527 Front Beach Dr",
    "sg:city":"Ocean Springs",
    "sg:classifiers":[
        {
            "category":"Organizations",
            "subcategory":"Professional Association",
            "type":"Services"
        }
    ],
    "sg:phone":"+1 228 872 2035",
    "sg:postcode":"39564",
    "sg:province":"MS",
    "wof:name":"Gulf Oaks Townhomes Assn",
    "wof:placetype":"venue"
},
  "geometry": {"coordinates":[-88.826341,30.403724],"type":"Point"}
}