{
  "type": "Feature",
  "properties": {
    "addr:full":"120 Plaza Dr Hattiesburg MS 39402",
    "addr:housenumber":"120",
    "addr:postcode":"39402",
    "addr:street":"Plaza Dr",
    "iso:country":"US",
    "sg:address":"120 Plaza Dr",
    "sg:city":"Hattiesburg",
    "sg:classifiers":[
        {
            "category":"Real Estate",
            "subcategory":"Real Estate Agent",
            "type":"Services"
        }
    ],
    "sg:phone":"+1 601 264 0047",
    "sg:postcode":"39402",
    "sg:province":"MS",
    "wof:name":"Coldwell Banker",
    "wof:placetype":"venue"
},
  "geometry": {"coordinates":[-89.35459299999999,31.328082],"type":"Point"}
}