{
  "type": "Feature",
  "properties": {
    "addr:full":"5959 I- 55 N Jackson MS 39213",
    "addr:housenumber":"5959;55 n",
    "addr:postcode":"39213",
    "addr:street":"I",
    "iso:country":"US",
    "sg:address":"5959 I- 55 N",
    "sg:city":"Jackson",
    "sg:classifiers":[
        {
            "category":"Social Services",
            "subcategory":"Job Training",
            "type":"Services"
        }
    ],
    "sg:phone":"+1 601 961 7931",
    "sg:postcode":"39213",
    "sg:province":"MS",
    "sg:tags":[
        "rehab",
        "government"
    ],
    "wof:name":"Job Service",
    "wof:placetype":"venue"
},
  "geometry": {"coordinates":[-90.14636299999999,32.38411],"type":"Point"}
}