{
  "type": "Feature",
  "properties": {
    "iso:country":"US",
    "sg:address":"3105 Hwy 82 E",
    "sg:city":"Greenville",
    "sg:classifiers":[
        {
            "category":"Restaurant",
            "type":"Food & Drink"
        }
    ],
    "sg:phone":"+1 662 335 1920",
    "sg:postcode":"38703",
    "sg:province":"MS",
    "wof:name":"How Joy Restaurant & Lounge",
    "wof:placetype":"venue"
},
  "geometry": {"coordinates":[-91.01549799999999,33.399874],"type":"Point"}
}