{
  "type": "Feature",
  "properties": {
    "addr:full":"407 S State St Jackson MS 39201",
    "addr:housenumber":"407",
    "addr:postcode":"39201",
    "addr:street":"S State St",
    "iso:country":"US",
    "sg:address":"407 S State St",
    "sg:city":"Jackson",
    "sg:classifiers":[
        {
            "category":"Professional",
            "subcategory":"Lawyer & Legal Services",
            "type":"Services"
        }
    ],
    "sg:phone":"+1 601 355 0955",
    "sg:postcode":"39201",
    "sg:province":"MS",
    "sg:tags":[
        "attorney"
    ],
    "sg:website":"www.jrwlaw.com",
    "wof:name":"John Robert White",
    "wof:placetype":"venue"
},
  "geometry": {"coordinates":[-90.18129500000001,32.295194],"type":"Point"}
}