{
  "type": "Feature",
  "properties": {
    "iso:country":"US",
    "sg:address":"945 N Theobald St",
    "sg:city":"Greenville",
    "sg:classifiers":[
        {
            "category":"Social Services",
            "subcategory":"Child Care",
            "type":"Services"
        }
    ],
    "sg:phone":"+1 662 334 4745",
    "sg:postcode":"38701",
    "sg:province":"MS",
    "wof:name":"Our Playmates Child Dev",
    "wof:placetype":"venue"
},
  "geometry": {"coordinates":[-91.040143,33.425886],"type":"Point"}
}