{
  "type": "Feature",
  "properties": {
    "iso:country":"US",
    "sg:address":"523 Berwick Dr",
    "sg:city":"Brandon",
    "sg:classifiers":[
        {
            "category":"Retail",
            "subcategory":"Auto Repair",
            "type":"Services"
        }
    ],
    "sg:phone":"+1 601 992 8149",
    "sg:postcode":"39047",
    "sg:province":"MS",
    "sg:tags":[
        "body"
    ],
    "wof:name":"Franks Customs & Collision",
    "wof:placetype":"venue"
},
  "geometry": {"coordinates":[-90.00744299999999,32.340551],"type":"Point"}
}