{
  "type": "Feature",
  "properties": {
    "iso:country":"US",
    "sg:address":"100 2nd Ave",
    "sg:city":"Kosciusko",
    "sg:classifiers":[
        {
            "category":"Government",
            "subcategory":"Office",
            "type":"Public Place"
        }
    ],
    "sg:phone":"+1 662 289 4711",
    "sg:postcode":"39090",
    "sg:province":"MS",
    "sg:tags":[
        "county",
        "taxation"
    ],
    "wof:name":"Attala County Tax Collector",
    "wof:placetype":"venue"
},
  "geometry": {"coordinates":[-89.59052699999999,33.066794],"type":"Point"}
}