{
  "type": "Feature",
  "properties": {
    "iso:country":"US",
    "sg:address":"210 W Jefferson St",
    "sg:city":"Yazoo City",
    "sg:classifiers":[
        {
            "category":"Wholesale",
            "subcategory":"Groceries",
            "type":"Manufacturing & Wholesale Goods"
        }
    ],
    "sg:phone":"+1 662 746 8000",
    "sg:postcode":"39194",
    "sg:province":"MS",
    "wof:name":"A G Sales Inc",
    "wof:placetype":"venue"
},
  "geometry": {"coordinates":[-90.41458299999999,32.846553],"type":"Point"}
}