{
  "type": "Feature",
  "properties": {
    "iso:country":"US",
    "sg:address":"1600 Shirley Ave",
    "sg:city":"Jackson",
    "sg:classifiers":[
        {
            "category":"Bars & Pubs",
            "type":"Food & Drink"
        }
    ],
    "sg:phone":"+1 601 949 8439",
    "sg:postcode":"39204",
    "sg:province":"MS",
    "sg:tags":[
        "drinking"
    ],
    "wof:name":"Ruths Lounge",
    "wof:placetype":"venue"
},
  "geometry": {"coordinates":[-90.214113,32.294606],"type":"Point"}
}