{
  "type": "Feature",
  "properties": {
    "addr:full":"2870 19th St Gulfport MS 39501",
    "addr:housenumber":"2870",
    "addr:postcode":"39501",
    "addr:street":"19Th St",
    "iso:country":"US",
    "sg:address":"2870 19th St",
    "sg:city":"Gulfport",
    "sg:classifiers":[
        {
            "category":"Building & Trades",
            "subcategory":"Construction",
            "type":"Services"
        }
    ],
    "sg:phone":"+1 228 863 8200",
    "sg:postcode":"39501",
    "sg:province":"MS",
    "sg:tags":[
        "general",
        "contractor"
    ],
    "wof:name":"Seaport Contractors Inc",
    "wof:placetype":"venue"
},
  "geometry": {"coordinates":[-89.095837,30.373526],"type":"Point"}
}