{
  "type": "Feature",
  "properties": {
    "iso:country":"US",
    "sg:address":"5404 State Hwy 604",
    "sg:city":"Pearlington",
    "sg:classifiers":[
        {
            "category":"Organizations",
            "subcategory":"Religious Organization",
            "type":"Services"
        }
    ],
    "sg:phone":"+1 228 533 0780",
    "sg:postcode":"39572",
    "sg:province":"MS",
    "wof:name":"Holmes Chpel Untd Mthdst Chrch",
    "wof:placetype":"venue"
},
  "geometry": {"coordinates":[-89.612695,30.249143],"type":"Point"}
}