{
  "type": "Feature",
  "properties": {
    "iso:country":"US",
    "sg:address":"5815 US Hwy 11",
    "sg:city":"Purvis",
    "sg:classifiers":[
        {
            "category":"Food & Beverages",
            "subcategory":"Groceries & Convenience Stores",
            "type":"Retail Goods"
        }
    ],
    "sg:phone":"+1 601 794 5428",
    "sg:postcode":"39475",
    "sg:province":"MS",
    "wof:name":"Mac's Mini-Mart",
    "wof:placetype":"venue"
},
  "geometry": {"coordinates":[-89.405357,31.143373],"type":"Point"}
}