{
  "type": "Feature",
  "properties": {
    "iso:country":"US",
    "sg:address":"1231 Curtis Dr",
    "sg:city":"Iuka",
    "sg:classifiers":[
        {
            "category":"Professional",
            "subcategory":"Lawyer & Legal Services",
            "type":"Services"
        }
    ],
    "sg:phone":"+1 662 423 1006",
    "sg:postcode":"38852",
    "sg:province":"MS",
    "sg:tags":[
        "attorney"
    ],
    "wof:name":"Segars & Holley",
    "wof:placetype":"venue"
},
  "geometry": {"coordinates":[-88.203137,34.803533],"type":"Point"}
}