{
  "type": "Feature",
  "properties": {
    "addr:full":"302 E Monroe Ave Okolona MS 38860",
    "addr:housenumber":"302",
    "addr:postcode":"38860",
    "addr:street":"E Monroe Ave",
    "iso:country":"US",
    "sg:address":"302 E Monroe Ave",
    "sg:city":"Okolona",
    "sg:classifiers":[
        {
            "category":"Food & Beverages",
            "subcategory":"Groceries & Convenience Stores",
            "type":"Retail Goods"
        }
    ],
    "sg:phone":"+1 662 447 2810",
    "sg:postcode":"38860",
    "sg:province":"MS",
    "wof:name":"Cody's Quick Mart",
    "wof:placetype":"venue"
},
  "geometry": {"coordinates":[-88.73992800000001,34.001747],"type":"Point"}
}