{
  "type": "Feature",
  "properties": {
    "iso:country":"US",
    "sg:address":"207 3rd Ave N",
    "sg:city":"Amory",
    "sg:classifiers":[
        {
            "category":"Shopping",
            "subcategory":"Pharmacy",
            "type":"Retail Goods"
        }
    ],
    "sg:phone":"+1 662 257 9885",
    "sg:postcode":"38821",
    "sg:province":"MS",
    "sg:tags":[
        "pharmaceutical",
        "consultant"
    ],
    "wof:name":"Pro Temp",
    "wof:placetype":"venue"
},
  "geometry": {"coordinates":[-88.489988,33.988085],"type":"Point"}
}