{
  "type": "Feature",
  "properties": {
    "addr:full":"710 Farmer St Port Gibson MS 39150",
    "addr:housenumber":"710",
    "addr:postcode":"39150",
    "addr:street":"Farmer St",
    "iso:country":"US",
    "sg:address":"710 Farmer St",
    "sg:city":"Port Gibson",
    "sg:classifiers":[
        {
            "category":"Shopping",
            "subcategory":"Florist",
            "type":"Retail Goods"
        }
    ],
    "sg:phone":"+1 601 437 3905",
    "sg:postcode":"39150",
    "sg:province":"MS",
    "wof:name":"Creations By Beau",
    "wof:placetype":"venue"
},
  "geometry": {"coordinates":[-90.983401,31.959795],"type":"Point"}
}