{
  "type": "Feature",
  "properties": {
    "iso:country":"US",
    "sg:address":"19 Bailey Dr",
    "sg:city":"Olive Branch",
    "sg:classifiers":[
        {
            "category":"Restaurant",
            "type":"Food & Drink"
        }
    ],
    "sg:phone":"+1 662 224 1111",
    "sg:postcode":"38611",
    "sg:province":"MS",
    "sg:tags":[
        "eating"
    ],
    "wof:name":"Kudzu Corner Inc",
    "wof:placetype":"venue"
},
  "geometry": {"coordinates":[-89.713229,34.956358],"type":"Point"}
}