{
  "type": "Feature",
  "properties": {
    "addr:full":"1775 N Washington St Vicksburg MS 39183",
    "addr:housenumber":"1775",
    "addr:postcode":"39183",
    "addr:street":"N Washington St",
    "iso:country":"US",
    "sg:address":"1775 N Washington St",
    "sg:city":"Vicksburg",
    "sg:classifiers":[
        {
            "category":"Restaurant",
            "type":"Food & Drink"
        }
    ],
    "sg:phone":"+1 601 638 0542",
    "sg:postcode":"39183",
    "sg:province":"MS",
    "sg:tags":[
        "eating"
    ],
    "wof:name":"Waring Oil Company",
    "wof:placetype":"venue"
},
  "geometry": {"coordinates":[-90.869642,32.377222],"type":"Point"}
}