{
  "type": "Feature",
  "properties": {
    "iso:country":"US",
    "sg:address":"120 Selma Estates Rd",
    "sg:city":"Natchez",
    "sg:classifiers":[
        {
            "category":"Social Services",
            "subcategory":"Adult Care",
            "type":"Services"
        },
        {
            "category":"Social Services",
            "subcategory":"Child Care",
            "type":"Services"
        }
    ],
    "sg:phone":"+1 601 446 7601",
    "sg:postcode":"39120",
    "sg:province":"MS",
    "sg:tags":[
        "residential",
        "sitting"
    ],
    "wof:name":"Professional Sitting Service",
    "wof:placetype":"venue"
},
  "geometry": {"coordinates":[-91.279678,31.597446],"type":"Point"}
}