{
  "type": "Feature",
  "properties": {
    "iso:country":"US",
    "sg:address":"720 North St",
    "sg:city":"Jackson",
    "sg:classifiers":[
        {
            "category":"Retail",
            "subcategory":"Portrait Studio",
            "type":"Services"
        }
    ],
    "sg:phone":"+1 601 969 1919",
    "sg:postcode":"39202",
    "sg:province":"MS",
    "sg:tags":[
        "photo"
    ],
    "wof:name":"Horrells Studios",
    "wof:placetype":"venue"
},
  "geometry": {"coordinates":[-90.176993,32.309489],"type":"Point"}
}