{
  "type": "Feature",
  "properties": {
    "addr:full":"52 Clipper Rd Hattiesburg MS 39402",
    "addr:housenumber":"52",
    "addr:postcode":"39402",
    "addr:street":"Clipper Rd",
    "iso:country":"US",
    "sg:address":"52 Clipper Rd",
    "sg:city":"Hattiesburg",
    "sg:classifiers":[
        {
            "category":"Autos & Motor Vehicles",
            "subcategory":"Automobile Sales",
            "type":"Retail Goods"
        }
    ],
    "sg:phone":"+1 601 264 7284",
    "sg:postcode":"39402",
    "sg:province":"MS",
    "sg:tags":[
        "used"
    ],
    "wof:name":"Enterprise Resource Group LLC",
    "wof:placetype":"venue"
},
  "geometry": {"coordinates":[-89.421077,31.323509],"type":"Point"}
}