{
  "type": "Feature",
  "properties": {
    "iso:country":"US",
    "sg:address":"5426 Hwy 39 N",
    "sg:city":"Meridian",
    "sg:classifiers":[
        {
            "category":"Organizations",
            "subcategory":"Religious Organization",
            "type":"Services"
        }
    ],
    "sg:phone":"+1 601 482 2229",
    "sg:postcode":"39305",
    "sg:province":"MS",
    "wof:name":"Broadmoor Baptist Church",
    "wof:placetype":"venue"
},
  "geometry": {"coordinates":[-88.678166,32.416518],"type":"Point"}
}