{
  "type": "Feature",
  "properties": {
    "iso:country":"US",
    "sg:address":"517 Greenhead Cir",
    "sg:city":"Brandon",
    "sg:classifiers":[
        {
            "category":"Building & Trades",
            "subcategory":"Plumbing",
            "type":"Services"
        },
        {
            "category":"Home & Garden",
            "subcategory":"Garden Supply",
            "type":"Retail Goods"
        }
    ],
    "sg:phone":"+1 601 992 0675",
    "sg:postcode":"39047",
    "sg:province":"MS",
    "sg:tags":[
        "sprinkler",
        "contractor"
    ],
    "wof:name":"Trenchless Irrigation LLC",
    "wof:placetype":"venue"
},
  "geometry": {"coordinates":[-90.01823,32.41497],"type":"Point"}
}