{
  "type": "Feature",
  "properties": {
    "iso:country":"US",
    "sg:address":"323 Cowart St",
    "sg:city":"Lucedale",
    "sg:classifiers":[
        {
            "category":"Government",
            "subcategory":"Office",
            "type":"Public Place"
        }
    ],
    "sg:phone":"+1 601 947 2751",
    "sg:postcode":"39452",
    "sg:province":"MS",
    "sg:tags":[
        "state",
        "security"
    ],
    "wof:name":"National Guard",
    "wof:placetype":"venue"
},
  "geometry": {"coordinates":[-88.592584,30.910265],"type":"Point"}
}