{
  "type": "Feature",
  "properties": {
    "addr:full":"1205 Worthington Dr Southaven MS 38671",
    "addr:housenumber":"1205",
    "addr:postcode":"38671",
    "addr:street":"Worthington Dr",
    "iso:country":"US",
    "sg:address":"1205 Worthington Dr",
    "sg:city":"Southaven",
    "sg:classifiers":[
        {
            "category":"Shopping",
            "subcategory":"Pets & Pet Supplies",
            "type":"Retail Goods"
        }
    ],
    "sg:phone":"+1 662 536 4364",
    "sg:postcode":"38671",
    "sg:province":"MS",
    "sg:tags":[
        "furnishing",
        "dog",
        "store",
        "cat"
    ],
    "wof:name":"Desoto Pet Sitters",
    "wof:placetype":"venue"
},
  "geometry": {"coordinates":[-89.968563,34.950298],"type":"Point"}
}