{
  "type": "Feature",
  "properties": {
    "iso:country":"US",
    "sg:address":"920 Cedar Lake Rd",
    "sg:city":"Biloxi",
    "sg:classifiers":[
        {
            "category":"Building & Trades",
            "subcategory":"Construction",
            "type":"Services"
        }
    ],
    "sg:phone":"+1 228 392 6569",
    "sg:postcode":"39532",
    "sg:province":"MS",
    "sg:tags":[
        "general",
        "contractor"
    ],
    "wof:name":"F & F Construction Inc",
    "wof:placetype":"venue"
},
  "geometry": {"coordinates":[-88.933904,30.442721],"type":"Point"}
}