{
  "type": "Feature",
  "properties": {
    "iso:country":"US",
    "sg:address":"920 Gates Rd",
    "sg:city":"Columbia",
    "sg:classifiers":[
        {
            "category":"Building & Trades",
            "subcategory":"Construction",
            "type":"Services"
        }
    ],
    "sg:phone":"+1 601 736 2118",
    "sg:postcode":"39429",
    "sg:province":"MS",
    "sg:tags":[
        "tile",
        "dealer",
        "contractor"
    ],
    "wof:name":"Williamson Jessie Ceramic Tile",
    "wof:placetype":"venue"
},
  "geometry": {"coordinates":[-89.753773,31.343809],"type":"Point"}
}