{
  "type": "Feature",
  "properties": {
    "iso:country":"US",
    "sg:address":"1027 Azalea Dr",
    "sg:city":"Waynesboro",
    "sg:classifiers":[
        {
            "category":"Insurance",
            "subcategory":"Insurance Agent",
            "type":"Services"
        }
    ],
    "sg:phone":"+1 601 735 1166",
    "sg:postcode":"39367",
    "sg:province":"MS",
    "wof:name":"State Farm Insurance",
    "wof:placetype":"venue"
},
  "geometry": {"coordinates":[-88.63822500000001,31.680665],"type":"Point"}
}