{
  "type": "Feature",
  "properties": {
    "iso:country":"US",
    "sg:address":"409 Hale St",
    "sg:city":"Macon",
    "sg:classifiers":[
        {
            "category":"Farming",
            "subcategory":"Orchard",
            "type":"Manufacturing & Wholesale Goods"
        }
    ],
    "sg:phone":"+1 662 726 5919",
    "sg:postcode":"39341",
    "sg:province":"MS",
    "sg:tags":[
        "fruit",
        "tree"
    ],
    "wof:name":"Cooper Peaches",
    "wof:placetype":"venue"
},
  "geometry": {"coordinates":[-88.565555,33.113645],"type":"Point"}
}