{
  "type": "Feature",
  "properties": {
    "iso:country":"US",
    "sg:address":"220 Yazoo Ave",
    "sg:city":"Clarksdale",
    "sg:classifiers":[
        {
            "category":"Restaurant",
            "type":"Food & Drink"
        }
    ],
    "sg:phone":"+1 662 621 2284",
    "sg:postcode":"38614",
    "sg:province":"MS",
    "wof:name":"Den",
    "wof:placetype":"venue"
},
  "geometry": {"coordinates":[-90.573633,34.202613],"type":"Point"}
}