{
  "type": "Feature",
  "properties": {
    "iso:country":"US",
    "sg:address":"369 W Northside Dr",
    "sg:city":"Jackson",
    "sg:phone":"+1 601 364 5000",
    "sg:postcode":"39206",
    "sg:province":"MS",
    "wof:name":"T'beaux's Iii Crawfish & Seafood Llc",
    "wof:placetype":"venue"
},
  "geometry": {"coordinates":[-90.18292599999999,32.355692],"type":"Point"}
}