{
  "type": "Feature",
  "properties": {
    "addr:full":"400 Hospital Rd Starkville MS 39759",
    "addr:housenumber":"400",
    "addr:postcode":"39759",
    "addr:street":"Hospital Rd",
    "iso:country":"US",
    "sg:address":"400 Hospital Rd",
    "sg:city":"Starkville",
    "sg:classifiers":[
        {
            "category":"Sports & Exercise",
            "subcategory":"Gym",
            "type":"Entertainment"
        }
    ],
    "sg:phone":"+1 662 323 9355",
    "sg:postcode":"39759",
    "sg:province":"MS",
    "sg:tags":[
        "club",
        "health",
        "studio",
        "gymnasium"
    ],
    "sg:website":"www.och.org",
    "wof:name":"Wellness Connection",
    "wof:placetype":"venue"
},
  "geometry": {"coordinates":[-88.82031499999999,33.474953],"type":"Point"}
}