{
  "type": "Feature",
  "properties": {
    "iso:country":"US",
    "sg:address":"109 Evans Ridge Dr",
    "sg:city":"Brandon",
    "sg:classifiers":[
        {
            "category":"Building & Trades",
            "subcategory":"Plumbing",
            "type":"Services"
        }
    ],
    "sg:phone":"+1 601 829 3893",
    "sg:postcode":"39047",
    "sg:province":"MS",
    "sg:tags":[
        "plumbing",
        "contractor"
    ],
    "wof:name":"Hobson Plumbing & Heating Co",
    "wof:placetype":"venue"
},
  "geometry": {"coordinates":[-89.946326,32.40743],"type":"Point"}
}