{
  "type": "Feature",
  "properties": {
    "addr:full":"1414 Jackson Ave W Oxford MS 38655",
    "addr:housenumber":"1414",
    "addr:postcode":"38655",
    "addr:street":"Jackson Ave W",
    "iso:country":"US",
    "sg:address":"1414 Jackson Ave W",
    "sg:city":"Oxford",
    "sg:classifiers":[
        {
            "category":"Restaurant",
            "type":"Food & Drink"
        }
    ],
    "sg:phone":"+1 662 234 1210",
    "sg:postcode":"38655",
    "sg:province":"MS",
    "wof:name":"Moe's Southwest Grill",
    "wof:placetype":"venue"
},
  "geometry": {"coordinates":[-89.548891,34.367265],"type":"Point"}
}