{
  "type": "Feature",
  "properties": {
    "iso:country":"US",
    "sg:address":"109 S Monroe St",
    "sg:city":"Calhoun City",
    "sg:classifiers":[
        {
            "category":"Retail",
            "subcategory":"Funeral Services",
            "type":"Services"
        }
    ],
    "sg:phone":"+1 662 628 5177",
    "sg:postcode":"38916",
    "sg:province":"MS",
    "sg:tags":[
        "director"
    ],
    "wof:name":"Pryor Funeral Home",
    "wof:placetype":"venue"
},
  "geometry": {"coordinates":[-89.312752,33.854581],"type":"Point"}
}