{
  "type": "Feature",
  "properties": {
    "iso:country":"US",
    "sg:address":"515 N Broadway St",
    "sg:city":"Greenville",
    "sg:classifiers":[
        {
            "category":"Restaurant",
            "type":"Food & Drink"
        }
    ],
    "sg:phone":"+1 662 334 4906",
    "sg:postcode":"38701",
    "sg:province":"MS",
    "sg:tags":[
        "style",
        "family"
    ],
    "wof:name":"Doris's Restaurant",
    "wof:placetype":"venue"
},
  "geometry": {"coordinates":[-91.06325,33.404575],"type":"Point"}
}