{
  "type": "Feature",
  "properties": {
    "iso:country":"US",
    "sg:address":"223 S Main St",
    "sg:city":"Sardis",
    "sg:classifiers":[
        {
            "category":"Home & Garden",
            "subcategory":"Garden Supply",
            "type":"Retail Goods"
        }
    ],
    "sg:phone":"+1 662 487 2619",
    "sg:postcode":"38666",
    "sg:province":"MS",
    "sg:tags":[
        "bulb",
        "seed"
    ],
    "wof:name":"White Deli & Gas",
    "wof:placetype":"venue"
},
  "geometry": {"coordinates":[-89.916312,34.435292],"type":"Point"}
}