{
  "type": "Feature",
  "properties": {
    "addr:full":"20 Hegwood Dr Richton MS 39476",
    "addr:housenumber":"20",
    "addr:postcode":"39476",
    "addr:street":"Hegwood Dr Richton",
    "iso:country":"US",
    "sg:address":"20 Hegwood Dr",
    "sg:city":"Richton",
    "sg:classifiers":[
        {
            "category":"Personal",
            "subcategory":"Beauty Salon",
            "type":"Services"
        }
    ],
    "sg:phone":"+1 601 788 9285",
    "sg:postcode":"39476",
    "sg:province":"MS",
    "wof:name":"Hair Etc",
    "wof:placetype":"venue"
},
  "geometry": {"coordinates":[-88.958877,31.365087],"type":"Point"}
}