{
  "type": "Feature",
  "properties": {
    "addr:full":"5125 Main St Lucedale MS 39452",
    "addr:housenumber":"5125",
    "addr:postcode":"39452",
    "addr:street":"Main St",
    "iso:country":"US",
    "sg:address":"5125 Main St",
    "sg:city":"Lucedale",
    "sg:classifiers":[
        {
            "category":"Restaurant",
            "type":"Food & Drink"
        }
    ],
    "sg:phone":"+1 601 947 9393",
    "sg:postcode":"39452",
    "sg:province":"MS",
    "wof:name":"Station",
    "wof:placetype":"venue"
},
  "geometry": {"coordinates":[-88.589938,30.924726],"type":"Point"}
}