{
  "type": "Feature",
  "properties": {
    "iso:country":"US",
    "sg:address":"1926 First Commercial Dr N",
    "sg:city":"Southaven",
    "sg:classifiers":[
        {
            "category":"Building & Trades",
            "subcategory":"Pest Control",
            "type":"Services"
        }
    ],
    "sg:phone":"+1 662 357 0192",
    "sg:postcode":"38671",
    "sg:province":"MS",
    "wof:name":"North Ms Pest Control",
    "wof:placetype":"venue"
},
  "geometry": {"coordinates":[-90.02148,34.990003],"type":"Point"}
}