{
  "type": "Feature",
  "properties": {
    "addr:full":"237 Lee Dr Clarksdale MS 38614",
    "addr:housenumber":"237",
    "addr:postcode":"38614",
    "addr:street":"Lee Dr Clarksdale",
    "iso:country":"US",
    "sg:address":"237 Lee Dr",
    "sg:city":"Clarksdale",
    "sg:classifiers":[
        {
            "category":"Organizations",
            "subcategory":"Religious Organization",
            "type":"Services"
        }
    ],
    "sg:phone":"+1 662 627 1076",
    "sg:postcode":"38614",
    "sg:province":"MS",
    "sg:tags":[
        "church"
    ],
    "wof:name":"New Beginning Ministry",
    "wof:placetype":"venue"
},
  "geometry": {"coordinates":[-90.564919,34.218803],"type":"Point"}
}