{
  "type": "Feature",
  "properties": {
    "iso:country":"US",
    "sg:address":"3325 8th St",
    "sg:city":"Meridian",
    "sg:classifiers":[
        {
            "category":"Restaurant",
            "type":"Food & Drink"
        }
    ],
    "sg:menulink":"http://www.allmenus.com/ms/meridian/13149-churchs-chicken/menu/",
    "sg:phone":"+1 601 485 5811",
    "sg:postcode":"39301",
    "sg:province":"MS",
    "sg:tags":[
        "chicken",
        "wing"
    ],
    "wof:name":"Church's Chicken",
    "wof:placetype":"venue"
},
  "geometry": {"coordinates":[-88.71127799999999,32.364883],"type":"Point"}
}