{
  "type": "Feature",
  "properties": {
    "iso:country":"US",
    "sg:address":"1120 Broad St",
    "sg:city":"Columbia",
    "sg:classifiers":[
        {
            "category":"Organizations",
            "subcategory":"Religious Organization",
            "type":"Services"
        }
    ],
    "sg:phone":"+1 601 444 9861",
    "sg:postcode":"39429",
    "sg:province":"MS",
    "sg:tags":[
        "church"
    ],
    "wof:name":"Columbia Church Of Christ",
    "wof:placetype":"venue"
},
  "geometry": {"coordinates":[-89.82001700000001,31.250564],"type":"Point"}
}