{
  "type": "Feature",
  "properties": {
    "iso:country":"US",
    "sg:address":"90 Hickory St",
    "sg:city":"Clarksdale",
    "sg:classifiers":[
        {
            "category":"Shopping",
            "subcategory":"Bicycles & Sporting Goods",
            "type":"Retail Goods"
        }
    ],
    "sg:phone":"+1 662 624 6090",
    "sg:postcode":"38614",
    "sg:province":"MS",
    "sg:tags":[
        "re",
        "clothing"
    ],
    "wof:name":"Campassi Sporting Goods",
    "wof:placetype":"venue"
},
  "geometry": {"coordinates":[-90.57312899999999,34.191569],"type":"Point"}
}