{
  "type": "Feature",
  "properties": {
    "addr:full":"151 Industrial Dr Ashland MS 38606",
    "addr:housenumber":"151",
    "addr:postcode":"38606",
    "addr:street":"Industrial Dr",
    "iso:country":"US",
    "sg:address":"151 Industrial Dr",
    "sg:city":"Ashland",
    "sg:classifiers":[
        {
            "category":"Wholesale",
            "subcategory":"Auto Parts",
            "type":"Manufacturing & Wholesale Goods"
        }
    ],
    "sg:phone":"+1 662 224 8972",
    "sg:postcode":"38606",
    "sg:province":"MS",
    "sg:tags":[
        "automobile",
        "supply",
        "vehicle",
        "motor",
        "mfg"
    ],
    "sg:website":"www.tciauto.com",
    "wof:name":"T C I Automotive",
    "wof:placetype":"venue"
},
  "geometry": {"coordinates":[-89.92869399999999,34.336273],"type":"Point"}
}