{
  "type": "Feature",
  "properties": {
    "iso:country":"US",
    "sg:address":"3580 Robinson St",
    "sg:city":"Jackson",
    "sg:classifiers":[
        {
            "category":"Retail",
            "subcategory":"Funeral Services",
            "type":"Services"
        }
    ],
    "sg:phone":"+1 601 922 3666",
    "sg:postcode":"39209",
    "sg:province":"MS",
    "sg:tags":[
        "director"
    ],
    "sg:website":"www.whmfh.com",
    "wof:name":"Westhaven Memorial Funeral Hm",
    "wof:placetype":"venue"
},
  "geometry": {"coordinates":[-90.24451000000001,32.30644],"type":"Point"}
}