{
  "type": "Feature",
  "properties": {
    "iso:country":"US",
    "sg:address":"200 N Frontage Rd",
    "sg:city":"Meridian",
    "sg:classifiers":[
        {
            "category":"Professional",
            "type":"Services"
        }
    ],
    "sg:phone":"+1 601 483 2275",
    "sg:postcode":"39301",
    "sg:province":"MS",
    "sg:tags":[
        "establishment"
    ],
    "wof:name":"Ethridge Isuzu",
    "wof:placetype":"venue"
},
  "geometry": {"coordinates":[-88.676312,32.363884],"type":"Point"}
}