{
  "type": "Feature",
  "properties": {
    "iso:country":"US",
    "sg:address":"1310 Brooks Dr",
    "sg:city":"Clarksdale",
    "sg:classifiers":[
        {
            "category":"Wholesale",
            "subcategory":"Electrical",
            "type":"Manufacturing & Wholesale Goods"
        }
    ],
    "sg:phone":"+1 662 627 3949",
    "sg:postcode":"38614",
    "sg:province":"MS",
    "sg:tags":[
        "alarm",
        "burglar",
        "system"
    ],
    "wof:name":"Dixon Security & Satellite",
    "wof:placetype":"venue"
},
  "geometry": {"coordinates":[-90.598883,34.204058],"type":"Point"}
}