{
  "type": "Feature",
  "properties": {
    "iso:country":"US",
    "sg:address":"1015 E Northside Dr",
    "sg:city":"Jackson",
    "sg:classifiers":[
        {
            "category":"Professional",
            "subcategory":"Business Services",
            "type":"Services"
        }
    ],
    "sg:phone":"+1 601 362 1100",
    "sg:postcode":"39213",
    "sg:province":"MS",
    "wof:name":"Visions Of Love",
    "wof:placetype":"venue"
},
  "geometry": {"coordinates":[-90.193907,32.355818],"type":"Point"}
}