{
  "type": "Feature",
  "properties": {
    "iso:country":"US",
    "sg:address":"208 Meadowbrook Rd",
    "sg:city":"Jackson",
    "sg:classifiers":[
        {
            "category":"Shopping",
            "subcategory":"Discount & Variety Stores",
            "type":"Retail Goods"
        }
    ],
    "sg:phone":"+1 601 362 5239",
    "sg:postcode":"39206",
    "sg:province":"MS",
    "sg:tags":[
        "salvage",
        "merchandise",
        "general"
    ],
    "wof:name":"Merchandise Warehouse",
    "wof:placetype":"venue"
},
  "geometry": {"coordinates":[-90.175495,32.350268],"type":"Point"}
}