{
  "type": "Feature",
  "properties": {
    "iso:country":"US",
    "sg:address":"650 Depot St",
    "sg:city":"Woodville",
    "sg:classifiers":[
        {
            "category":"Building & Trades",
            "subcategory":"Construction",
            "type":"Services"
        }
    ],
    "sg:phone":"+1 601 888 6165",
    "sg:postcode":"39669",
    "sg:province":"MS",
    "sg:tags":[
        "general",
        "contractor"
    ],
    "wof:name":"T & B Construction",
    "wof:placetype":"venue"
},
  "geometry": {"coordinates":[-91.29679899999999,31.0983],"type":"Point"}
}