{
  "type": "Feature",
  "properties": {
    "iso:country":"US",
    "sg:address":"478 Springridge Rd",
    "sg:city":"Clinton",
    "sg:classifiers":[
        {
            "category":"Freight",
            "type":"Transportation"
        }
    ],
    "sg:phone":"+1 601 924 5837",
    "sg:postcode":"39056",
    "sg:province":"MS",
    "sg:tags":[
        "warehouse",
        "merchandise"
    ],
    "wof:name":"Storagemax Clinton",
    "wof:placetype":"venue"
},
  "geometry": {"coordinates":[-90.326927,32.332264],"type":"Point"}
}