{
  "type": "Feature",
  "properties": {
    "iso:country":"US",
    "sg:address":"20360 Hwy 6 E",
    "sg:city":"Batesville",
    "sg:classifiers":[
        {
            "category":"Wholesale",
            "subcategory":"Construction Materials",
            "type":"Manufacturing & Wholesale Goods"
        },
        {
            "category":"Manufacturing",
            "subcategory":"Glass & Minerals",
            "type":"Manufacturing & Wholesale Goods"
        }
    ],
    "sg:phone":"+1 662 561 0014",
    "sg:postcode":"38606",
    "sg:province":"MS",
    "sg:tags":[
        "granite",
        "product",
        "marble"
    ],
    "wof:name":"Darby Natural Stone Inc",
    "wof:placetype":"venue"
},
  "geometry": {"coordinates":[-89.86894700000001,34.312953],"type":"Point"}
}