{
  "type": "Feature",
  "properties": {
    "addr:full":"11240 US Hwy 49 Gulfport MS 39503",
    "addr:housenumber":"11240",
    "addr:postcode":"39503",
    "addr:street":"Us Hwy 49",
    "iso:country":"US",
    "sg:address":"11240 US Hwy 49",
    "sg:city":"Gulfport",
    "sg:classifiers":[
        {
            "category":"Restaurant",
            "type":"Food & Drink"
        }
    ],
    "sg:phone":"+1 228 832 8580",
    "sg:postcode":"39503",
    "sg:province":"MS",
    "sg:tags":[
        "eating"
    ],
    "wof:name":"Subway",
    "wof:placetype":"venue"
},
  "geometry": {"coordinates":[-89.098252,30.442291],"type":"Point"}
}