{
  "type": "Feature",
  "properties": {
    "iso:country":"US",
    "sg:address":"501 Jacinto Rd",
    "sg:city":"Booneville",
    "sg:classifiers":[
        {
            "category":"Autos & Motor Vehicles",
            "subcategory":"Automobile Sales",
            "type":"Retail Goods"
        }
    ],
    "sg:phone":"+1 662 728 0308",
    "sg:postcode":"38829",
    "sg:province":"MS",
    "sg:tags":[
        "car",
        "dealer"
    ],
    "wof:name":"Barrett Used Cars",
    "wof:placetype":"venue"
},
  "geometry": {"coordinates":[-88.544319,34.661228],"type":"Point"}
}