{
  "type": "Feature",
  "properties": {
    "addr:full":"3645 Hwy 80 W Jackson MS 39209",
    "addr:housenumber":"3645",
    "addr:postcode":"39209",
    "addr:street":"Hwy 80 W",
    "iso:country":"US",
    "sg:address":"3645 Hwy 80 W",
    "sg:city":"Jackson",
    "sg:classifiers":[
        {
            "category":"Professional",
            "type":"Services"
        }
    ],
    "sg:phone":"+1 601 969 0868",
    "sg:postcode":"39209",
    "sg:province":"MS",
    "sg:tags":[
        "establishment"
    ],
    "wof:name":"W B X K L P",
    "wof:placetype":"venue"
},
  "geometry": {"coordinates":[-90.249695,32.30196],"type":"Point"}
}