{
  "type": "Feature",
  "properties": {
    "iso:country":"US",
    "sg:address":"109 Van Voris St",
    "sg:city":"Batesville",
    "sg:classifiers":[
        {
            "category":"Health Services",
            "subcategory":"Doctor",
            "type":"Services"
        }
    ],
    "sg:phone":"+1 662 563 8631",
    "sg:postcode":"38606",
    "sg:province":"MS",
    "sg:tags":[
        "physician",
        "surgeon"
    ],
    "wof:name":"Edward A Steward MD",
    "wof:placetype":"venue"
},
  "geometry": {"coordinates":[-89.95614,34.315553],"type":"Point"}
}