{
  "type": "Feature",
  "properties": {
    "iso:country":"US",
    "sg:address":"6093 N Railroad Ave",
    "sg:city":"Bay St Louis",
    "sg:classifiers":[
        {
            "category":"Railroad",
            "type":"Transportation"
        }
    ],
    "sg:phone":"+1 228 466 0793",
    "sg:postcode":"39576",
    "sg:province":"MS",
    "wof:name":"North Railroad Lift Station",
    "wof:placetype":"venue"
},
  "geometry": {"coordinates":[-89.416133,30.265925],"type":"Point"}
}