{
  "type": "Feature",
  "properties": {
    "iso:country":"US",
    "sg:address":"162 Stephen Lyon Rd",
    "sg:city":"Shaw",
    "sg:classifiers":[
        {
            "category":"Food & Beverages",
            "subcategory":"Groceries & Convenience Stores",
            "type":"Retail Goods"
        }
    ],
    "sg:phone":"+1 662 887 2784",
    "sg:postcode":"38773",
    "sg:province":"MS",
    "wof:name":"Stephensville Mini Mart Inc",
    "wof:placetype":"venue"
},
  "geometry": {"coordinates":[-90.67159700000001,33.563077],"type":"Point"}
}