{
  "type": "Feature",
  "properties": {
    "iso:country":"US",
    "sg:address":"507 Colonial Cir",
    "sg:city":"Starkville",
    "sg:classifiers":[
        {
            "category":"Professional",
            "subcategory":"Engineering",
            "type":"Services"
        }
    ],
    "sg:phone":"+1 662 324 1787",
    "sg:postcode":"39759",
    "sg:province":"MS",
    "wof:name":"Usati Utility Engineering Tech",
    "wof:placetype":"venue"
},
  "geometry": {"coordinates":[-88.814168,33.429702],"type":"Point"}
}