{
  "type": "Feature",
  "properties": {
    "iso:country":"US",
    "sg:address":"256 Oral Church Rd",
    "sg:city":"Tylertown",
    "sg:classifiers":[
        {
            "category":"Organizations",
            "subcategory":"Religious Organization",
            "type":"Services"
        }
    ],
    "sg:phone":"+1 601 876 5319",
    "sg:postcode":"39667",
    "sg:province":"MS",
    "wof:name":"Oral Baptist Church Parsonage",
    "wof:placetype":"venue"
},
  "geometry": {"coordinates":[-90.03536099999999,31.078073],"type":"Point"}
}