{
  "type": "Feature",
  "properties": {
    "iso:country":"US",
    "sg:address":"305 Jamaica Dr",
    "sg:city":"Ocean Springs",
    "sg:classifiers":[
        {
            "category":"Professional",
            "type":"Services"
        }
    ],
    "sg:phone":"+1 228 872 0973",
    "sg:postcode":"39564",
    "sg:province":"MS",
    "wof:name":"Schultz Rockey",
    "wof:placetype":"venue"
},
  "geometry": {"coordinates":[-88.793758,30.404619],"type":"Point"}
}