{
  "type": "Feature",
  "properties": {
    "iso:country":"US",
    "sg:address":"956 Eastport Rd",
    "sg:city":"Iuka",
    "sg:classifiers":[
        {
            "category":"Shopping",
            "subcategory":"Bicycles & Sporting Goods",
            "type":"Retail Goods"
        }
    ],
    "sg:phone":"+1 662 423 6416",
    "sg:postcode":"38852",
    "sg:province":"MS",
    "sg:tags":[
        "tackle",
        "fishing"
    ],
    "wof:name":"Ledbetter Fish Market",
    "wof:placetype":"venue"
},
  "geometry": {"coordinates":[-88.10736199999999,34.883612],"type":"Point"}
}