{
  "type": "Feature",
  "properties": {
    "addr:full":"203 Valley Vista Dr Jackson MS 39211",
    "addr:housenumber":"203",
    "addr:postcode":"39211",
    "addr:street":"Valley Vista Dr",
    "iso:country":"US",
    "sg:address":"203 Valley Vista Dr",
    "sg:city":"Jackson",
    "sg:classifiers":[
        {
            "category":"Education",
            "subcategory":"Dance Studio",
            "type":"Public Place"
        }
    ],
    "sg:phone":"+1 601 206 9279",
    "sg:postcode":"39211",
    "sg:province":"MS",
    "wof:name":"Academy of Ballet",
    "wof:placetype":"venue"
},
  "geometry": {"coordinates":[-90.118523,32.373889],"type":"Point"}
}