{
  "type": "Feature",
  "properties": {
    "iso:country":"US",
    "sg:address":"725 Old Jackson Rd",
    "sg:city":"Canton",
    "sg:classifiers":[
        {
            "category":"Organizations",
            "subcategory":"Religious Organization",
            "type":"Services"
        }
    ],
    "sg:phone":"+1 601 859 8811",
    "sg:postcode":"39046",
    "sg:province":"MS",
    "sg:tags":[
        "church"
    ],
    "wof:name":"Harvey Chapel Missionary Bapt",
    "wof:placetype":"venue"
},
  "geometry": {"coordinates":[-90.08908599999999,32.560736],"type":"Point"}
}