{
  "type": "Feature",
  "properties": {
    "addr:full":"701 US Hwy 90 Waveland MS 39576",
    "addr:housenumber":"701",
    "addr:postcode":"39576",
    "addr:street":"Us Hwy 90",
    "iso:country":"US",
    "sg:address":"701 US Hwy 90",
    "sg:city":"Waveland",
    "sg:classifiers":[
        {
            "category":"Banks & Credit Unions",
            "subcategory":"Bank",
            "type":"Services"
        }
    ],
    "sg:phone":"+1 228 466 5959",
    "sg:postcode":"39576",
    "sg:province":"MS",
    "sg:tags":[
        "state"
    ],
    "sg:website":"www.hancockbank.com",
    "wof:name":"Hancock Bank",
    "wof:placetype":"venue"
},
  "geometry": {"coordinates":[-89.397419,30.299477],"type":"Point"}
}