{
  "type": "Feature",
  "properties": {
    "iso:country":"US",
    "sg:address":"296 T Smith Rd",
    "sg:city":"Hattiesburg",
    "sg:classifiers":[
        {
            "category":"Real Estate",
            "subcategory":"Surveying",
            "type":"Services"
        }
    ],
    "sg:phone":"+1 601 584 1050",
    "sg:postcode":"39401",
    "sg:province":"MS",
    "sg:tags":[
        "surveyor"
    ],
    "wof:name":"David A Tant Surveying Mapping",
    "wof:placetype":"venue"
},
  "geometry": {"coordinates":[-89.343608,31.405062],"type":"Point"}
}