{
  "type": "Feature",
  "properties": {
    "iso:country":"US",
    "sg:address":"4416 Chicot St",
    "sg:city":"Pascagoula",
    "sg:classifiers":[
        {
            "category":"Shopping",
            "subcategory":"Discount & Variety Stores",
            "type":"Retail Goods"
        }
    ],
    "sg:phone":"+1 228 769 0579",
    "sg:postcode":"39581",
    "sg:province":"MS",
    "wof:name":"Dollar General",
    "wof:placetype":"venue"
},
  "geometry": {"coordinates":[-88.525007,30.37909],"type":"Point"}
}