{
  "type": "Feature",
  "properties": {
    "iso:country":"US",
    "sg:address":"10120 Factory Shops Blvd",
    "sg:city":"Gulfport",
    "sg:classifiers":[
        {
            "category":"Shopping",
            "type":"Retail Goods"
        }
    ],
    "sg:phone":"+1 228 822 0512",
    "sg:postcode":"39503",
    "sg:province":"MS",
    "sg:tags":[
        "factory",
        "outlet"
    ],
    "wof:name":"Bon Worth",
    "wof:placetype":"venue"
},
  "geometry": {"coordinates":[-89.096563,30.427456],"type":"Point"}
}