{
  "type": "Feature",
  "properties": {
    "iso:country":"US",
    "sg:address":"24 S Main St",
    "sg:city":"Pontotoc",
    "sg:classifiers":[
        {
            "category":"Personal",
            "subcategory":"Beauty Salon",
            "type":"Services"
        }
    ],
    "sg:phone":"+1 662 489 2050",
    "sg:postcode":"38863",
    "sg:province":"MS",
    "sg:tags":[
        "shop"
    ],
    "wof:name":"Cut Ups",
    "wof:placetype":"venue"
},
  "geometry": {"coordinates":[-88.999101,34.248601],"type":"Point"}
}