{
  "type": "Feature",
  "properties": {
    "iso:country":"US",
    "sg:address":"6214 US Hwy 49",
    "sg:city":"Hattiesburg",
    "sg:classifiers":[
        {
            "category":"Social Services",
            "subcategory":"Child Care",
            "type":"Services"
        }
    ],
    "sg:phone":"+1 601 582 7474",
    "sg:postcode":"39401",
    "sg:province":"MS",
    "wof:name":"Noah's Ark Childcare Ctr",
    "wof:placetype":"venue"
},
  "geometry": {"coordinates":[-89.3421,31.352973],"type":"Point"}
}