{
  "type": "Feature",
  "properties": {
    "iso:country":"US",
    "sg:address":"1491 Canton Mart Rd",
    "sg:city":"Jackson",
    "sg:classifiers":[
        {
            "category":"Professional",
            "subcategory":"Business Services",
            "type":"Services"
        }
    ],
    "sg:phone":"+1 601 956 9060",
    "sg:postcode":"39211",
    "sg:province":"MS",
    "sg:tags":[
        "interior",
        "consultant",
        "design",
        "decorator"
    ],
    "wof:name":"Mc Donald-Harris Interior Dsgn",
    "wof:placetype":"venue"
},
  "geometry": {"coordinates":[-90.14899800000001,32.366629],"type":"Point"}
}