{
  "type": "Feature",
  "properties": {
    "iso:country":"US",
    "sg:address":"4408 Will O Run Dr",
    "sg:city":"Jackson",
    "sg:classifiers":[
        {
            "category":"Wholesale",
            "subcategory":"Vending Machines",
            "type":"Manufacturing & Wholesale Goods"
        }
    ],
    "sg:phone":"+1 601 373 3914",
    "sg:postcode":"39212",
    "sg:province":"MS",
    "wof:name":"Evans Vending",
    "wof:placetype":"venue"
},
  "geometry": {"coordinates":[-90.295984,32.252911],"type":"Point"}
}