{
  "type": "Feature",
  "properties": {
    "iso:country":"US",
    "sg:address":"5204 Nantuckett Dr",
    "sg:city":"Jackson",
    "sg:classifiers":[
        {
            "category":"Wholesale",
            "subcategory":"Vending Machines",
            "type":"Manufacturing & Wholesale Goods"
        }
    ],
    "sg:phone":"+1 601 922 6922",
    "sg:postcode":"39209",
    "sg:province":"MS",
    "sg:tags":[
        "operator"
    ],
    "wof:name":"Quinns Vending",
    "wof:placetype":"venue"
},
  "geometry": {"coordinates":[-90.26464,32.336247],"type":"Point"}
}