{
  "type": "Feature",
  "properties": {
    "iso:country":"US",
    "sg:address":"1501 Adeline St",
    "sg:city":"Hattiesburg",
    "sg:classifiers":[
        {
            "category":"Professional",
            "subcategory":"Computer Services",
            "type":"Services"
        }
    ],
    "sg:phone":"+1 601 579 9321",
    "sg:postcode":"39401",
    "sg:province":"MS",
    "sg:tags":[
        "repair"
    ],
    "wof:name":"Greg's Computer Svc",
    "wof:placetype":"venue"
},
  "geometry": {"coordinates":[-89.313107,31.317365],"type":"Point"}
}