{
  "type": "Feature",
  "properties": {
    "addr:full":"25059 Hwy 51 Crystal Springs MS 39059",
    "addr:housenumber":"25059",
    "addr:postcode":"39059",
    "addr:street":"Hwy 51",
    "iso:country":"US",
    "sg:address":"25059 Hwy 51",
    "sg:city":"Crystal Springs",
    "sg:classifiers":[
        {
            "category":"Autos & Motor Vehicles",
            "subcategory":"Auto Supplies",
            "type":"Retail Goods"
        }
    ],
    "sg:phone":"+1 601 892 4412",
    "sg:postcode":"39059",
    "sg:province":"MS",
    "wof:name":"NAPA Auto Parts",
    "wof:placetype":"venue"
},
  "geometry": {"coordinates":[-90.358661,32.003011],"type":"Point"}
}