{
  "type": "Feature",
  "properties": {
    "iso:country":"US",
    "sg:address":"1018 19th St",
    "sg:city":"Meridian",
    "sg:classifiers":[
        {
            "category":"Retail",
            "subcategory":"Self-service Laundry",
            "type":"Services"
        }
    ],
    "sg:phone":"+1 601 485 9440",
    "sg:postcode":"39301",
    "sg:province":"MS",
    "sg:tags":[
        "coin"
    ],
    "wof:name":"Suds Laundromat Eastside",
    "wof:placetype":"venue"
},
  "geometry": {"coordinates":[-88.68910200000001,32.376685],"type":"Point"}
}