{
  "type": "Feature",
  "properties": {
    "iso:country":"US",
    "sg:address":"100 Pelahatchie Shore Dr",
    "sg:city":"Brandon",
    "sg:classifiers":[
        {
            "category":"Freight",
            "type":"Transportation"
        }
    ],
    "sg:phone":"+1 601 992 2055",
    "sg:postcode":"39047",
    "sg:province":"MS",
    "sg:tags":[
        "commercial",
        "storage",
        "general"
    ],
    "wof:name":"Reservoir Mini- Storage Inc",
    "wof:placetype":"venue"
},
  "geometry": {"coordinates":[-90.037762,32.384544],"type":"Point"}
}