{
  "type": "Feature",
  "properties": {
    "iso:country":"US",
    "sg:address":"119 Sherwood Cir",
    "sg:city":"Ocean Springs",
    "sg:classifiers":[
        {
            "category":"Professional",
            "type":"Services"
        }
    ],
    "sg:phone":"+1 228 872 0949",
    "sg:postcode":"39564",
    "sg:province":"MS",
    "wof:name":"Hurricane Protection Services",
    "wof:placetype":"venue"
},
  "geometry": {"coordinates":[-88.80516299999999,30.409476],"type":"Point"}
}