{
  "type": "Feature",
  "properties": {
    "iso:country":"US",
    "sg:address":"245 Excell Dr",
    "sg:city":"Pearl",
    "sg:classifiers":[
        {
            "category":"Wholesale",
            "subcategory":"Machinery & Supplies",
            "type":"Manufacturing & Wholesale Goods"
        }
    ],
    "sg:phone":"+1 601 932 4037",
    "sg:postcode":"39208",
    "sg:province":"MS",
    "sg:tags":[
        "equipment",
        "safety",
        "clothing"
    ],
    "wof:name":"Care Safety LLC",
    "wof:placetype":"venue"
},
  "geometry": {"coordinates":[-90.06141700000001,32.283775],"type":"Point"}
}