{
  "type": "Feature",
  "properties": {
    "addr:full":"7936 Carter's Rd Moss Point MS 39562",
    "addr:housenumber":"7936",
    "addr:postcode":"39562",
    "addr:street":"Carter'S Rd",
    "iso:country":"US",
    "sg:address":"7936 Carter's Rd",
    "sg:city":"Moss Point",
    "sg:classifiers":[
        {
            "category":"Organizations",
            "subcategory":"Religious Organization",
            "type":"Services"
        }
    ],
    "sg:phone":"+1 228 588 6827",
    "sg:postcode":"39562",
    "sg:province":"MS",
    "wof:name":"Pascagoula Baptist Church",
    "wof:placetype":"venue"
},
  "geometry": {"coordinates":[-88.48041499999999,30.560029],"type":"Point"}
}