{
  "type": "Feature",
  "properties": {
    "iso:country":"US",
    "sg:address":"1345 Ellisville Blvd",
    "sg:city":"Laurel",
    "sg:classifiers":[
        {
            "category":"Building & Trades",
            "subcategory":"Construction",
            "type":"Services"
        }
    ],
    "sg:phone":"+1 601 649 3121",
    "sg:postcode":"39440",
    "sg:province":"MS",
    "sg:tags":[
        "fence",
        "contractor"
    ],
    "wof:name":"Fenceworks",
    "wof:placetype":"venue"
},
  "geometry": {"coordinates":[-89.147474,31.670006],"type":"Point"}
}