{
  "type": "Feature",
  "properties": {
    "addr:full":"1266 Magnolia St Tunica MS 38676",
    "addr:housenumber":"1266",
    "addr:postcode":"38676",
    "addr:street":"Magnolia St",
    "iso:country":"US",
    "sg:address":"1266 Magnolia St",
    "sg:city":"Tunica",
    "sg:classifiers":[
        {
            "category":"Real Estate",
            "subcategory":"Architect",
            "type":"Services"
        }
    ],
    "sg:phone":"+1 662 363 1811",
    "sg:postcode":"38676",
    "sg:province":"MS",
    "wof:name":"Wenzel & Assoc",
    "wof:placetype":"venue"
},
  "geometry": {"coordinates":[-90.376684,34.687335],"type":"Point"}
}