{
  "type": "Feature",
  "properties": {
    "iso:country":"US",
    "sg:address":"119 Davis Ave",
    "sg:city":"Pass Christian",
    "sg:classifiers":[
        {
            "category":"Food & Beverages",
            "subcategory":"Liquor & Beverages",
            "type":"Retail Goods"
        }
    ],
    "sg:phone":"+1 228 452 7676",
    "sg:postcode":"39571",
    "sg:province":"MS",
    "sg:tags":[
        "alcoholic"
    ],
    "wof:name":"Keg",
    "wof:placetype":"venue"
},
  "geometry": {"coordinates":[-89.242507,30.317371],"type":"Point"}
}