{
  "type": "Feature",
  "properties": {
    "iso:country":"US",
    "sg:address":"1900 14th St",
    "sg:city":"Pascagoula",
    "sg:classifiers":[
        {
            "category":"Food & Beverages",
            "subcategory":"Groceries & Convenience Stores",
            "type":"Retail Goods"
        }
    ],
    "sg:phone":"+1 228 769 0100",
    "sg:postcode":"39567",
    "sg:province":"MS",
    "wof:name":"Gas & Save",
    "wof:placetype":"venue"
},
  "geometry": {"coordinates":[-88.539281,30.35599],"type":"Point"}
}