{
  "type": "Feature",
  "properties": {
    "iso:country":"US",
    "sg:address":"718 Hwy 80 E",
    "sg:city":"Flowood",
    "sg:classifiers":[
        {
            "category":"Professional",
            "type":"Services"
        }
    ],
    "sg:phone":"+1 601 664 0089",
    "sg:postcode":"39208",
    "sg:province":"MS",
    "sg:tags":[
        "establishment"
    ],
    "wof:name":"J Ms",
    "wof:placetype":"venue"
},
  "geometry": {"coordinates":[-90.168993,32.27984],"type":"Point"}
}