{
  "type": "Feature",
  "properties": {
    "iso:country":"US",
    "sg:address":"80 Annandale Pkwy",
    "sg:city":"Madison",
    "sg:classifiers":[
        {
            "category":"Travel",
            "subcategory":"Travel Agent",
            "type":"Entertainment"
        }
    ],
    "sg:phone":"+1 601 898 4653",
    "sg:postcode":"39110",
    "sg:province":"MS",
    "sg:tags":[
        "tours",
        "promoter"
    ],
    "wof:name":"Southern Farm Bureau Classic",
    "wof:placetype":"venue"
},
  "geometry": {"coordinates":[-90.18194800000001,32.494264],"type":"Point"}
}