{
  "type": "Feature",
  "properties": {
    "iso:country":"US",
    "sg:address":"152 G E Ohr St",
    "sg:city":"Biloxi",
    "sg:classifiers":[
        {
            "category":"Restaurant",
            "type":"Food & Drink"
        }
    ],
    "sg:menulink":"http://www.allmenus.com/ms/diberville/132952-subway/menu/",
    "sg:phone":"+1 228 435 7827",
    "sg:postcode":"39530",
    "sg:province":"MS",
    "sg:tags":[
        "american",
        "sandwich"
    ],
    "wof:name":"Subway",
    "wof:placetype":"venue"
},
  "geometry": {"coordinates":[-88.88810700000001,30.395814],"type":"Point"}
}