{
  "type": "Feature",
  "properties": {
    "iso:country":"US",
    "sg:address":"204 W Paulding Rd",
    "sg:city":"Ellisville",
    "sg:classifiers":[
        {
            "category":"Utilities",
            "subcategory":"Telephone",
            "type":"Services"
        }
    ],
    "sg:phone":"+1 601 319 3950",
    "sg:postcode":"39437",
    "sg:province":"MS",
    "sg:tags":[
        "communications"
    ],
    "wof:name":"Barter Shop",
    "wof:placetype":"venue"
},
  "geometry": {"coordinates":[-89.192286,31.61213],"type":"Point"}
}