{
  "type": "Feature",
  "properties": {
    "addr:full":"7760 Hwy 72 Walnut MS 38683",
    "addr:housenumber":"7760",
    "addr:postcode":"38683",
    "addr:street":"Hwy 72",
    "iso:country":"US",
    "sg:address":"7760 Hwy 72",
    "sg:city":"Walnut",
    "sg:classifiers":[
        {
            "category":"Communications",
            "subcategory":"Radio Station",
            "type":"Services"
        }
    ],
    "sg:phone":"+1 662 223 4071",
    "sg:postcode":"38683",
    "sg:province":"MS",
    "sg:tags":[
        "company",
        "broadcasting"
    ],
    "sg:website":"www.wlrcradio.com",
    "wof:name":"WLRC",
    "wof:placetype":"venue"
},
  "geometry": {"coordinates":[-88.879606,34.952546],"type":"Point"}
}