{
  "type": "Feature",
  "properties": {
    "iso:country":"US",
    "sg:address":"5390 Park Place Dr",
    "sg:city":"Horn Lake",
    "sg:classifiers":[
        {
            "category":"Building & Trades",
            "subcategory":"Construction",
            "type":"Services"
        }
    ],
    "sg:phone":"+1 662 342 2436",
    "sg:postcode":"38637",
    "sg:province":"MS",
    "sg:tags":[
        "house"
    ],
    "wof:name":"Faulkner Construction",
    "wof:placetype":"venue"
},
  "geometry": {"coordinates":[-90.027072,34.93809],"type":"Point"}
}