{
  "type": "Feature",
  "properties": {
    "iso:country":"US",
    "sg:address":"522 E Railroad St",
    "sg:city":"Long Beach",
    "sg:classifiers":[
        {
            "category":"Manufacturing",
            "subcategory":"Tools & Machinery",
            "type":"Manufacturing & Wholesale Goods"
        }
    ],
    "sg:phone":"+1 228 575 3100",
    "sg:postcode":"39560",
    "sg:province":"MS",
    "sg:tags":[
        "machine",
        "mfr",
        "teller",
        "automated"
    ],
    "wof:name":"Triton Systems of Delaware",
    "wof:placetype":"venue"
},
  "geometry": {"coordinates":[-89.14176399999999,30.354074],"type":"Point"}
}