{
  "type": "Feature",
  "properties": {
    "iso:country":"US",
    "sg:address":"4675 Hwy 178 E",
    "sg:city":"Fulton",
    "sg:classifiers":[
        {
            "category":"Freight",
            "type":"Transportation"
        }
    ],
    "sg:phone":"+1 662 862 9297",
    "sg:postcode":"38843",
    "sg:province":"MS",
    "sg:tags":[
        "commercial",
        "storage"
    ],
    "wof:name":"T & W Rental Inc",
    "wof:placetype":"venue"
},
  "geometry": {"coordinates":[-88.359891,34.276694],"type":"Point"}
}