{
  "type": "Feature",
  "properties": {
    "iso:country":"US",
    "sg:address":"999 N Halstead Rd",
    "sg:city":"Ocean Springs",
    "sg:classifiers":[
        {
            "category":"Health Services",
            "subcategory":"Doctor",
            "type":"Services"
        }
    ],
    "sg:phone":"+1 228 875 0780",
    "sg:postcode":"39564",
    "sg:province":"MS",
    "sg:tags":[
        "physician",
        "surgeon"
    ],
    "wof:name":"Gulf Coast Children's Clinic",
    "wof:placetype":"venue"
},
  "geometry": {"coordinates":[-88.799734,30.414903],"type":"Point"}
}