{
  "type": "Feature",
  "properties": {
    "iso:country":"US",
    "sg:address":"2010 Chicot St",
    "sg:city":"Pascagoula",
    "sg:classifiers":[
        {
            "category":"Manufacturing",
            "subcategory":"Printing",
            "type":"Manufacturing & Wholesale Goods"
        }
    ],
    "sg:phone":"+1 228 327 9392",
    "sg:postcode":"39581",
    "sg:province":"MS",
    "sg:tags":[
        "mfg"
    ],
    "wof:name":"Scrap Book Gallery",
    "wof:placetype":"venue"
},
  "geometry": {"coordinates":[-88.525628,30.355257],"type":"Point"}
}