{
  "type": "Feature",
  "properties": {
    "addr:full":"1575 Dancy Blvd Horn Lake MS 38637",
    "addr:housenumber":"1575",
    "addr:postcode":"38637",
    "addr:street":"Dancy Blvd Horn Lake",
    "iso:country":"US",
    "sg:address":"1575 Dancy Blvd",
    "sg:city":"Horn Lake",
    "sg:classifiers":[
        {
            "category":"Wholesale",
            "subcategory":"Hardware",
            "type":"Manufacturing & Wholesale Goods"
        }
    ],
    "sg:phone":"+1 662 393 6001",
    "sg:postcode":"38637",
    "sg:province":"MS",
    "wof:name":"C C Dickson Co",
    "wof:placetype":"venue"
},
  "geometry": {"coordinates":[-90.018366,34.959985],"type":"Point"}
}