{
  "type": "Feature",
  "properties": {
    "iso:country":"US",
    "sg:address":"423 Security Sq",
    "sg:city":"Gulfport",
    "sg:classifiers":[
        {
            "category":"Health Services",
            "subcategory":"Doctor",
            "type":"Services"
        }
    ],
    "sg:phone":"+1 228 896 1440",
    "sg:postcode":"39507",
    "sg:province":"MS",
    "sg:tags":[
        "dentist"
    ],
    "wof:name":"Ronald S Bourgeois DDS",
    "wof:placetype":"venue"
},
  "geometry": {"coordinates":[-89.04294299999999,30.386421],"type":"Point"}
}