{
  "type": "Feature",
  "properties": {
    "iso:country":"US",
    "sg:address":"955 Atlanta St",
    "sg:city":"Pearl",
    "sg:classifiers":[
        {
            "category":"Freight",
            "type":"Transportation"
        }
    ],
    "sg:phone":"+1 601 932 0738",
    "sg:postcode":"39208",
    "sg:province":"MS",
    "sg:tags":[
        "operator",
        "local",
        "trucking"
    ],
    "wof:name":"Dunson Trucking",
    "wof:placetype":"venue"
},
  "geometry": {"coordinates":[-90.101428,32.252594],"type":"Point"}
}