{
  "type": "Feature",
  "properties": {
    "addr:full":"7957 Highway 51 N Southaven MS 38671",
    "addr:housenumber":"7957",
    "addr:postcode":"38671",
    "addr:street":"Highway 51 N",
    "iso:country":"US",
    "sg:address":"7957 Highway 51 N",
    "sg:city":"Southaven",
    "sg:phone":"+1 662 393 6498",
    "sg:postcode":"38671",
    "sg:province":"MS",
    "wof:name":"Dabbs Gun & Pawn",
    "wof:placetype":"venue"
},
  "geometry": {"coordinates":[-90.015944,34.976756],"type":"Point"}
}