{
  "type": "Feature",
  "properties": {
    "addr:full":"211 Industrial Dr Ridgeland MS 39157",
    "addr:housenumber":"211",
    "addr:postcode":"39157",
    "addr:street":"Industrial Dr",
    "iso:country":"US",
    "sg:address":"211 Industrial Dr",
    "sg:city":"Ridgeland",
    "sg:classifiers":[
        {
            "category":"Wholesale",
            "subcategory":"Machinery & Supplies",
            "type":"Manufacturing & Wholesale Goods"
        }
    ],
    "sg:phone":"+1 601 605 1555",
    "sg:postcode":"39157",
    "sg:province":"MS",
    "sg:tags":[
        "machine",
        "new",
        "tool",
        "used"
    ],
    "wof:name":"Machine Tools Inc",
    "wof:placetype":"venue"
},
  "geometry": {"coordinates":[-90.141006,32.421896],"type":"Point"}
}