{
  "type": "Feature",
  "properties": {
    "iso:country":"US",
    "sg:address":"306 Barney Banks Rd",
    "sg:city":"Pinola",
    "sg:classifiers":[
        {
            "category":"Building & Trades",
            "subcategory":"Construction",
            "type":"Services"
        }
    ],
    "sg:phone":"+1 601 847 3541",
    "sg:postcode":"39149",
    "sg:province":"MS",
    "sg:tags":[
        "excavation",
        "contractor"
    ],
    "wof:name":"Banks Digging Service",
    "wof:placetype":"venue"
},
  "geometry": {"coordinates":[-90.029382,31.890265],"type":"Point"}
}