{
  "type": "Feature",
  "properties": {
    "iso:country":"US",
    "sg:address":"1010 S West St",
    "sg:city":"Jackson",
    "sg:classifiers":[
        {
            "category":"Retail",
            "subcategory":"Auto Repair",
            "type":"Services"
        }
    ],
    "sg:phone":"+1 601 352 7196",
    "sg:postcode":"39201",
    "sg:province":"MS",
    "sg:tags":[
        "automotive"
    ],
    "wof:name":"Mid-South Accessories",
    "wof:placetype":"venue"
},
  "geometry": {"coordinates":[-90.18649600000001,32.287534],"type":"Point"}
}