{
  "type": "Feature",
  "properties": {
    "iso:country":"US",
    "sg:address":"220 S Broadway St",
    "sg:city":"Greenville",
    "sg:classifiers":[
        {
            "category":"Social Services",
            "type":"Services"
        }
    ],
    "sg:phone":"+1 662 332 8819",
    "sg:postcode":"38701",
    "sg:province":"MS",
    "sg:tags":[
        "organization",
        "welfare"
    ],
    "wof:name":"Southern Aids Comission Inc",
    "wof:placetype":"venue"
},
  "geometry": {"coordinates":[-91.05988499999999,33.408553],"type":"Point"}
}