{
  "type": "Feature",
  "properties": {
    "iso:country":"US",
    "sg:address":"6413 US Hwy 98",
    "sg:city":"Hattiesburg",
    "sg:classifiers":[
        {
            "category":"Personal",
            "subcategory":"Tanning Parlor",
            "type":"Services"
        },
        {
            "category":"Personal",
            "type":"Services"
        }
    ],
    "sg:phone":"+1 601 579 9800",
    "sg:postcode":"39402",
    "sg:province":"MS",
    "sg:tags":[
        "salon"
    ],
    "wof:name":"Endless Summer",
    "wof:placetype":"venue"
},
  "geometry": {"coordinates":[-89.408697,31.317777],"type":"Point"}
}