{
  "type": "Feature",
  "properties": {
    "addr:full":"2802 Bienville Blvd Ocean Springs MS 39564",
    "addr:housenumber":"2802",
    "addr:postcode":"39564",
    "addr:street":"Bienville Blvd",
    "iso:country":"US",
    "sg:address":"2802 Bienville Blvd",
    "sg:city":"Ocean Springs",
    "sg:classifiers":[
        {
            "category":"Banks & Credit Unions",
            "subcategory":"Bank",
            "type":"Services"
        }
    ],
    "sg:phone":"+1 228 872 2800",
    "sg:postcode":"39564",
    "sg:province":"MS",
    "wof:name":"Merchants & Marine Bank",
    "wof:placetype":"venue"
},
  "geometry": {"coordinates":[-88.791861,30.413867],"type":"Point"}
}