{
  "type": "Feature",
  "properties": {
    "iso:country":"US",
    "sg:address":"600 Franklin Dr",
    "sg:city":"Houston",
    "sg:classifiers":[
        {
            "category":"Manufacturing",
            "subcategory":"Furniture",
            "type":"Manufacturing & Wholesale Goods"
        }
    ],
    "sg:phone":"+1 662 456 5771",
    "sg:postcode":"38851",
    "sg:province":"MS",
    "sg:website":"www.franklincorp.com",
    "wof:name":"Franklin Corp",
    "wof:placetype":"venue"
},
  "geometry": {"coordinates":[-89.01360099999999,33.914699],"type":"Point"}
}