{
  "type": "Feature",
  "properties": {
    "iso:country":"US",
    "sg:address":"324 Porter Dr",
    "sg:city":"Clarksdale",
    "sg:classifiers":[
        {
            "category":"Farming",
            "subcategory":"Farm",
            "type":"Manufacturing & Wholesale Goods"
        }
    ],
    "sg:phone":"+1 662 624 2112",
    "sg:postcode":"38614",
    "sg:province":"MS",
    "sg:tags":[
        "crop",
        "general"
    ],
    "wof:name":"Ancona Farms",
    "wof:placetype":"venue"
},
  "geometry": {"coordinates":[-90.58170200000001,34.22625],"type":"Point"}
}