{
  "type": "Feature",
  "properties": {
    "addr:full":"212 N 1st St Brookhaven MS 39601",
    "addr:housenumber":"212",
    "addr:postcode":"39601",
    "addr:street":"N 1St St",
    "iso:country":"US",
    "sg:address":"212 N 1st St",
    "sg:city":"Brookhaven",
    "sg:classifiers":[
        {
            "category":"Government",
            "subcategory":"Office",
            "type":"Public Place"
        }
    ],
    "sg:phone":"+1 601 833 9324",
    "sg:postcode":"39601",
    "sg:province":"MS",
    "sg:tags":[
        "federal"
    ],
    "wof:name":"Natural Resources Conservation",
    "wof:placetype":"venue"
},
  "geometry": {"coordinates":[-90.439831,31.58148],"type":"Point"}
}