{
  "type": "Feature",
  "properties": {
    "iso:country":"US",
    "sg:address":"1020 Starnes Rd",
    "sg:city":"Mccomb",
    "sg:classifiers":[
        {
            "category":"Retail",
            "subcategory":"Laundry & Dry Cleaning",
            "type":"Services"
        }
    ],
    "sg:phone":"+1 601 684 5420",
    "sg:postcode":"39648",
    "sg:province":"MS",
    "sg:tags":[
        "cleaners",
        "rug",
        "carpet"
    ],
    "wof:name":"Dave's Carpet Cleaning",
    "wof:placetype":"venue"
},
  "geometry": {"coordinates":[-90.44435,31.22616],"type":"Point"}
}