{
  "type": "Feature",
  "properties": {
    "iso:country":"US",
    "sg:address":"202 Pine St",
    "sg:city":"New Augusta",
    "sg:classifiers":[
        {
            "category":"Banks & Credit Unions",
            "subcategory":"Bank",
            "type":"Services"
        }
    ],
    "sg:phone":"+1 601 964 8852",
    "sg:postcode":"39462",
    "sg:province":"MS",
    "wof:name":"Richton Bank & Trust",
    "wof:placetype":"venue"
},
  "geometry": {"coordinates":[-89.034434,31.20187],"type":"Point"}
}