{
  "type": "Feature",
  "properties": {
    "iso:country":"US",
    "sg:address":"170 Isola St",
    "sg:city":"Cleveland",
    "sg:classifiers":[
        {
            "category":"Building & Trades",
            "subcategory":"Construction",
            "type":"Services"
        }
    ],
    "sg:phone":"+1 662 846 8985",
    "sg:postcode":"38732",
    "sg:province":"MS",
    "sg:tags":[
        "residential"
    ],
    "wof:name":"Co Op One",
    "wof:placetype":"venue"
},
  "geometry": {"coordinates":[-90.729569,33.769456],"type":"Point"}
}