{
  "type": "Feature",
  "properties": {
    "addr:full":"105 Red Maple Trl Petal MS 39465",
    "addr:housenumber":"105",
    "addr:postcode":"39465",
    "addr:street":"Red Maple Trl",
    "iso:country":"US",
    "sg:address":"105 Red Maple Trl",
    "sg:city":"Petal",
    "sg:classifiers":[
        {
            "category":"Building & Trades",
            "subcategory":"Construction",
            "type":"Services"
        }
    ],
    "sg:phone":"+1 601 544 7319",
    "sg:postcode":"39465",
    "sg:province":"MS",
    "sg:tags":[
        "designer",
        "dealer",
        "pool",
        "swimming"
    ],
    "wof:name":"Blue Dolphin Pool Svc",
    "wof:placetype":"venue"
},
  "geometry": {"coordinates":[-89.19704400000001,31.339046],"type":"Point"}
}