{
  "type": "Feature",
  "properties": {
    "iso:country":"US",
    "sg:address":"430 Old Richton Rd",
    "sg:city":"Petal",
    "sg:classifiers":[
        {
            "category":"Professional",
            "subcategory":"Engineering",
            "type":"Services"
        }
    ],
    "sg:phone":"+1 601 582 8283",
    "sg:postcode":"39465",
    "sg:province":"MS",
    "sg:tags":[
        "engineer"
    ],
    "wof:name":"Pittman Engineers Inc",
    "wof:placetype":"venue"
},
  "geometry": {"coordinates":[-89.255695,31.350463],"type":"Point"}
}