{
  "type": "Feature",
  "properties": {
    "iso:country":"US",
    "sg:address":"200 N 6th St",
    "sg:city":"Columbus",
    "sg:classifiers":[
        {
            "category":"Professional",
            "subcategory":"Lawyer & Legal Services",
            "type":"Services"
        }
    ],
    "sg:phone":"+1 662 244 8824",
    "sg:postcode":"39701",
    "sg:province":"MS",
    "sg:tags":[
        "attorney"
    ],
    "wof:name":"Kullman Firm",
    "wof:placetype":"venue"
},
  "geometry": {"coordinates":[-88.42733,33.497529],"type":"Point"}
}