{
  "type": "Feature",
  "properties": {
    "addr:full":"3519 Rita Dr Jackson MS 39213",
    "addr:housenumber":"3519",
    "addr:postcode":"39213",
    "addr:street":"Rita Dr",
    "iso:country":"US",
    "sg:address":"3519 Rita Dr",
    "sg:city":"Jackson",
    "sg:classifiers":[
        {
            "category":"Professional",
            "subcategory":"Management & Consulting",
            "type":"Services"
        }
    ],
    "sg:phone":"+1 601 982 1466",
    "sg:postcode":"39213",
    "sg:province":"MS",
    "wof:name":"Independent Business Inc",
    "wof:placetype":"venue"
},
  "geometry": {"coordinates":[-90.23494700000001,32.351237],"type":"Point"}
}