{
  "type": "Feature",
  "properties": {
    "iso:country":"US",
    "sg:address":"1011 Mount Olive Rd",
    "sg:city":"Starkville",
    "sg:classifiers":[
        {
            "category":"Organizations",
            "subcategory":"Religious Organization",
            "type":"Services"
        }
    ],
    "sg:phone":"+1 662 323 9173",
    "sg:postcode":"39759",
    "sg:province":"MS",
    "sg:tags":[
        "church"
    ],
    "wof:name":"Mount Olivet Baptist Church",
    "wof:placetype":"venue"
},
  "geometry": {"coordinates":[-88.77580399999999,33.374064],"type":"Point"}
}