{
  "type": "Feature",
  "properties": {
    "addr:full":"3054 Old Hwy 11 Purvis MS 39475",
    "addr:housenumber":"3054",
    "addr:postcode":"39475",
    "addr:street":"Old Hwy 11",
    "iso:country":"US",
    "sg:address":"3054 Old Hwy 11",
    "sg:city":"Purvis",
    "sg:classifiers":[
        {
            "category":"Government",
            "subcategory":"Office",
            "type":"Public Place"
        }
    ],
    "sg:phone":"+1 601 794 6663",
    "sg:postcode":"39475",
    "sg:province":"MS",
    "sg:tags":[
        "county",
        "program"
    ],
    "wof:name":"Lamar County Sanitation",
    "wof:placetype":"venue"
},
  "geometry": {"coordinates":[-89.419269,31.167111],"type":"Point"}
}