{
  "type": "Feature",
  "properties": {
    "iso:country":"US",
    "sg:address":"7711 US Hwy 78",
    "sg:city":"Olive Branch",
    "sg:classifiers":[
        {
            "category":"Building & Trades",
            "subcategory":"Landscaping Services",
            "type":"Services"
        }
    ],
    "sg:phone":"+1 662 890 3173",
    "sg:postcode":"38654",
    "sg:province":"MS",
    "wof:name":"Knox Landscaping",
    "wof:placetype":"venue"
},
  "geometry": {"coordinates":[-89.852859,34.962205],"type":"Point"}
}