{
  "type": "Feature",
  "properties": {
    "addr:full":"3201 D Ave Gulfport MS 39507",
    "addr:housenumber":"3201",
    "addr:postcode":"39507",
    "addr:street":"D Ave",
    "iso:country":"US",
    "sg:address":"3201 D Ave",
    "sg:city":"Gulfport",
    "sg:classifiers":[
        {
            "category":"Social Services",
            "type":"Services"
        }
    ],
    "sg:phone":"+1 228 868 8686",
    "sg:postcode":"39507",
    "sg:province":"MS",
    "wof:name":"Center Fr The Prvntn of Chld A",
    "wof:placetype":"venue"
},
  "geometry": {"coordinates":[-89.056743,30.389476],"type":"Point"}
}