{
  "type": "Feature",
  "properties": {
    "iso:country":"US",
    "sg:address":"4050 Sidlehill Dr",
    "sg:city":"Olive Branch",
    "sg:classifiers":[
        {
            "category":"Building & Trades",
            "subcategory":"Construction",
            "type":"Services"
        }
    ],
    "sg:phone":"+1 662 890 5787",
    "sg:postcode":"38654",
    "sg:province":"MS",
    "sg:tags":[
        "home",
        "builder"
    ],
    "wof:name":"Faxon Gillis Homes",
    "wof:placetype":"venue"
},
  "geometry": {"coordinates":[-89.80189799999999,34.922068],"type":"Point"}
}