{
  "type": "Feature",
  "properties": {
    "iso:country":"US",
    "sg:address":"1011 Old Hwy 61",
    "sg:city":"Tunica",
    "sg:classifiers":[
        {
            "category":"Travel",
            "subcategory":"Hotels & Motels",
            "type":"Entertainment"
        }
    ],
    "sg:phone":"+1 662 363 2932",
    "sg:postcode":"38676",
    "sg:province":"MS",
    "wof:name":"Tunica Motel",
    "wof:placetype":"venue"
},
  "geometry": {"coordinates":[-90.38291700000001,34.685639],"type":"Point"}
}