{
  "type": "Feature",
  "properties": {
    "addr:full":"1027 Mount Vernon Rd Columbus MS 39702",
    "addr:housenumber":"1027",
    "addr:postcode":"39702",
    "addr:street":"Mount Vernon Rd",
    "iso:country":"US",
    "sg:address":"1027 Mount Vernon Rd",
    "sg:city":"Columbus",
    "sg:classifiers":[
        {
            "category":"Building & Trades",
            "subcategory":"Construction",
            "type":"Services"
        }
    ],
    "sg:phone":"+1 662 328 7531",
    "sg:postcode":"39702",
    "sg:province":"MS",
    "sg:tags":[
        "house"
    ],
    "wof:name":"WA & Phillip Caldwell",
    "wof:placetype":"venue"
},
  "geometry": {"coordinates":[-88.313647,33.484886],"type":"Point"}
}