{
  "type": "Feature",
  "properties": {
    "iso:country":"US",
    "sg:address":"1426 Brookhaven Dr",
    "sg:city":"Southaven",
    "sg:classifiers":[
        {
            "category":"Manufacturing",
            "subcategory":"Metals",
            "type":"Manufacturing & Wholesale Goods"
        }
    ],
    "sg:phone":"+1 662 280 9002",
    "sg:postcode":"38671",
    "sg:province":"MS",
    "sg:tags":[
        "metalwork",
        "sheet",
        "mfg"
    ],
    "wof:name":"G & E Sheet Metal Enterprise",
    "wof:placetype":"venue"
},
  "geometry": {"coordinates":[-90.014635,34.981975],"type":"Point"}
}