{
  "type": "Feature",
  "properties": {
    "iso:country":"US",
    "sg:address":"2567 Pine Tree Rd",
    "sg:city":"Hernando",
    "sg:classifiers":[
        {
            "category":"Building & Trades",
            "subcategory":"Construction",
            "type":"Services"
        }
    ],
    "sg:phone":"+1 662 429 6821",
    "sg:postcode":"38632",
    "sg:province":"MS",
    "sg:tags":[
        "carpentry",
        "contractor"
    ],
    "wof:name":"Thomas Earl Trim",
    "wof:placetype":"venue"
},
  "geometry": {"coordinates":[-90.04272899999999,34.853474],"type":"Point"}
}