{
  "type": "Feature",
  "properties": {
    "iso:country":"US",
    "sg:address":"4235 Space Center Dr",
    "sg:city":"Jackson",
    "sg:classifiers":[
        {
            "category":"Wholesale",
            "subcategory":"Machinery & Supplies",
            "type":"Manufacturing & Wholesale Goods"
        }
    ],
    "sg:phone":"+1 601 714 4266",
    "sg:postcode":"39209",
    "sg:province":"MS",
    "sg:tags":[
        "equipment",
        "layer",
        "carpet"
    ],
    "wof:name":"Viking Distributors Inc",
    "wof:placetype":"venue"
},
  "geometry": {"coordinates":[-90.240262,32.339767],"type":"Point"}
}