{
  "type": "Feature",
  "properties": {
    "iso:country":"US",
    "sg:address":"2609 C St",
    "sg:city":"Meridian",
    "sg:classifiers":[
        {
            "category":"Organizations",
            "subcategory":"Religious Organization",
            "type":"Services"
        }
    ],
    "sg:phone":"+1 601 693 4254",
    "sg:postcode":"39301",
    "sg:province":"MS",
    "sg:tags":[
        "church"
    ],
    "wof:name":"Hawkins Memorial United Meth",
    "wof:placetype":"venue"
},
  "geometry": {"coordinates":[-88.69992000000001,32.35733],"type":"Point"}
}