{
  "type": "Feature",
  "properties": {
    "iso:country":"US",
    "sg:address":"4628 Goldfinch Dr",
    "sg:city":"Gulfport",
    "sg:classifiers":[
        {
            "category":"Professional",
            "subcategory":"Detective & Security Services",
            "type":"Services"
        }
    ],
    "sg:phone":"+1 228 868 3986",
    "sg:postcode":"39501",
    "sg:province":"MS",
    "sg:tags":[
        "car"
    ],
    "wof:name":"Fitzgerald Security Inc",
    "wof:placetype":"venue"
},
  "geometry": {"coordinates":[-89.106638,30.400324],"type":"Point"}
}