{
  "type": "Feature",
  "properties": {
    "addr:full":"271 Memorial Church Rd Richton MS 39476",
    "addr:housenumber":"271",
    "addr:postcode":"39476",
    "addr:street":"Church Rd",
    "iso:country":"US",
    "sg:address":"271 Memorial Church Rd",
    "sg:city":"Richton",
    "sg:classifiers":[
        {
            "category":"Organizations",
            "subcategory":"Religious Organization",
            "type":"Services"
        }
    ],
    "sg:phone":"+1 601 964 3775",
    "sg:postcode":"39476",
    "sg:province":"MS",
    "wof:name":"Memorial Baptist Parsonage",
    "wof:placetype":"venue"
},
  "geometry": {"coordinates":[-89.109561,31.257949],"type":"Point"}
}