{
  "type": "Feature",
  "properties": {
    "iso:country":"US",
    "sg:address":"1892 Colonial Hills Dr",
    "sg:city":"Southaven",
    "sg:classifiers":[
        {
            "category":"Building & Trades",
            "subcategory":"Construction",
            "type":"Services"
        }
    ],
    "sg:phone":"+1 662 280 2810",
    "sg:postcode":"38671",
    "sg:province":"MS",
    "sg:tags":[
        "house"
    ],
    "wof:name":"Bridges Maintenance Contr",
    "wof:placetype":"venue"
},
  "geometry": {"coordinates":[-90.023003,34.978327],"type":"Point"}
}