{
  "type": "Feature",
  "properties": {
    "iso:country":"US",
    "sg:address":"1389 US Hwy 61",
    "sg:city":"Lake Cormorant",
    "sg:classifiers":[
        {
            "category":"Shopping",
            "subcategory":"Used Merchandise",
            "type":"Retail Goods"
        }
    ],
    "sg:phone":"+1 662 781 8400",
    "sg:postcode":"38641",
    "sg:province":"MS",
    "wof:name":"Kellers Pawn Shop Inc",
    "wof:placetype":"venue"
},
  "geometry": {"coordinates":[-90.2264,34.87741],"type":"Point"}
}