{
  "type": "Feature",
  "properties": {
    "addr:full":"104 21st St Mccomb MS 39648",
    "addr:housenumber":"104",
    "addr:postcode":"39648",
    "addr:street":"21St St",
    "iso:country":"US",
    "sg:address":"104 21st St",
    "sg:city":"Mccomb",
    "sg:classifiers":[
        {
            "category":"Shopping",
            "subcategory":"Jewelry",
            "type":"Retail Goods"
        }
    ],
    "sg:phone":"+1 601 684 4994",
    "sg:postcode":"39648",
    "sg:province":"MS",
    "sg:tags":[
        "jeweler"
    ],
    "wof:name":"Deb's Outlet",
    "wof:placetype":"venue"
},
  "geometry": {"coordinates":[-90.45085400000001,31.23727],"type":"Point"}
}