{
  "type": "Feature",
  "properties": {
    "iso:country":"US",
    "sg:address":"200 Crawford St",
    "sg:city":"Madison",
    "sg:classifiers":[
        {
            "category":"Education",
            "subcategory":"School",
            "type":"Public Place"
        }
    ],
    "sg:phone":"+1 601 605 0054",
    "sg:postcode":"39110",
    "sg:province":"MS",
    "wof:name":"Rosa Scott Middle School",
    "wof:placetype":"venue"
},
  "geometry": {"coordinates":[-90.123572,32.462365],"type":"Point"}
}