{
  "type": "Feature",
  "properties": {
    "iso:country":"US",
    "sg:address":"104 Thomas St",
    "sg:city":"Batesville",
    "sg:classifiers":[
        {
            "category":"Retail",
            "subcategory":"Laundry & Dry Cleaning",
            "type":"Services"
        }
    ],
    "sg:phone":"+1 662 563 9739",
    "sg:postcode":"38606",
    "sg:province":"MS",
    "sg:tags":[
        "cleaners"
    ],
    "wof:name":"Smith Cleaners",
    "wof:placetype":"venue"
},
  "geometry": {"coordinates":[-89.95309,34.316252],"type":"Point"}
}