{
  "type": "Feature",
  "properties": {
    "iso:country":"US",
    "sg:address":"307 Market St",
    "sg:city":"Natchez",
    "sg:classifiers":[
        {
            "category":"Professional",
            "subcategory":"Lawyer & Legal Services",
            "type":"Services"
        }
    ],
    "sg:phone":"+1 601 446 7590",
    "sg:postcode":"39120",
    "sg:province":"MS",
    "wof:name":"Mississippi Center For Legal",
    "wof:placetype":"venue"
},
  "geometry": {"coordinates":[-91.404776,31.560344],"type":"Point"}
}