{
  "type": "Feature",
  "properties": {
    "addr:full":"100 3rd Ave Sherman MS 38869",
    "addr:housenumber":"100",
    "addr:postcode":"38869",
    "addr:street":"3Rd Ave",
    "iso:country":"US",
    "sg:address":"100 3rd Ave",
    "sg:city":"Sherman",
    "sg:classifiers":[
        {
            "category":"Building & Trades",
            "subcategory":"Landscaping Services",
            "type":"Services"
        }
    ],
    "sg:phone":"+1 662 840 8846",
    "sg:postcode":"38869",
    "sg:province":"MS",
    "sg:tags":[
        "tree"
    ],
    "wof:name":"A & B Tree Svc",
    "wof:placetype":"venue"
},
  "geometry": {"coordinates":[-88.841054,34.362715],"type":"Point"}
}