{
  "type": "Feature",
  "properties": {
    "iso:country":"US",
    "sg:address":"1525 24th St",
    "sg:city":"Meridian",
    "sg:classifiers":[
        {
            "category":"Organizations",
            "subcategory":"Religious Organization",
            "type":"Services"
        }
    ],
    "sg:phone":"+1 601 483 6130",
    "sg:postcode":"39301",
    "sg:province":"MS",
    "wof:name":"New Era Baptist Church",
    "wof:placetype":"venue"
},
  "geometry": {"coordinates":[-88.69482600000001,32.382879],"type":"Point"}
}