{
  "type": "Feature",
  "properties": {
    "iso:country":"US",
    "sg:address":"155 Oak Dr",
    "sg:city":"Pelahatchie",
    "sg:classifiers":[
        {
            "category":"Building & Trades",
            "subcategory":"Construction",
            "type":"Services"
        }
    ],
    "sg:phone":"+1 601 854 5377",
    "sg:postcode":"39145",
    "sg:province":"MS",
    "sg:tags":[
        "house"
    ],
    "wof:name":"Walker Construction Co Inc",
    "wof:placetype":"venue"
},
  "geometry": {"coordinates":[-89.815935,32.341874],"type":"Point"}
}