{
  "type": "Feature",
  "properties": {
    "addr:full":"23 Blackwell Dr Waynesboro MS 39367",
    "addr:housenumber":"23",
    "addr:postcode":"39367",
    "addr:street":"Blackwell Dr",
    "iso:country":"US",
    "sg:address":"23 Blackwell Dr",
    "sg:city":"Waynesboro",
    "sg:classifiers":[
        {
            "category":"Wholesale",
            "subcategory":"Construction Materials",
            "type":"Manufacturing & Wholesale Goods"
        }
    ],
    "sg:phone":"+1 601 735 3908",
    "sg:postcode":"39367",
    "sg:province":"MS",
    "wof:name":"T&B Timber Svc Inc",
    "wof:placetype":"venue"
},
  "geometry": {"coordinates":[-88.708688,31.52464],"type":"Point"}
}