{
  "type": "Feature",
  "properties": {
    "iso:country":"US",
    "sg:address":"213 Smith Rd",
    "sg:city":"Louisville",
    "sg:classifiers":[
        {
            "category":"Travel",
            "subcategory":"Hotels & Motels",
            "type":"Entertainment"
        }
    ],
    "sg:phone":"+1 662 773 7853",
    "sg:postcode":"39339",
    "sg:province":"MS",
    "sg:website":"www.ltok.com",
    "wof:name":"Lake Tiak-O-Khata",
    "wof:placetype":"venue"
},
  "geometry": {"coordinates":[-89.01103000000001,33.05019],"type":"Point"}
}