{
  "type": "Feature",
  "properties": {
    "iso:country":"US",
    "sg:address":"118 Nehi Cir",
    "sg:city":"Mccomb",
    "sg:classifiers":[
        {
            "category":"Building & Trades",
            "subcategory":"Plumbing",
            "type":"Services"
        }
    ],
    "sg:phone":"+1 601 684 2072",
    "sg:postcode":"39648",
    "sg:province":"MS",
    "sg:tags":[
        "heating",
        "contractor",
        "air",
        "system",
        "conditioning"
    ],
    "wof:name":"Comfort Air Inc",
    "wof:placetype":"venue"
},
  "geometry": {"coordinates":[-90.45031,31.231659],"type":"Point"}
}