{
  "type": "Feature",
  "properties": {
    "iso:country":"US",
    "sg:address":"3200 US Hwy 11 N",
    "sg:city":"Picayune",
    "sg:classifiers":[
        {
            "category":"Wholesale",
            "subcategory":"Farm Supplies",
            "type":"Manufacturing & Wholesale Goods"
        }
    ],
    "sg:phone":"+1 601 798 3242",
    "sg:postcode":"39466",
    "sg:province":"MS",
    "wof:name":"Stewart's Home & Garden Ctr",
    "wof:placetype":"venue"
},
  "geometry": {"coordinates":[-89.65985999999999,30.597835],"type":"Point"}
}