{
  "type": "Feature",
  "properties": {
    "iso:country":"US",
    "sg:address":"6240 Lauderdale Toomsuba Rd",
    "sg:city":"Toomsuba",
    "sg:classifiers":[
        {
            "category":"Organizations",
            "subcategory":"Non-profit Organization",
            "type":"Services"
        }
    ],
    "sg:phone":"+1 601 632 1929",
    "sg:postcode":"39364",
    "sg:province":"MS",
    "wof:name":"Toomsuba Water System",
    "wof:placetype":"venue"
},
  "geometry": {"coordinates":[-88.512107,32.426938],"type":"Point"}
}