{
  "type": "Feature",
  "properties": {
    "iso:country":"US",
    "sg:address":"107 Mimosa St",
    "sg:city":"Booneville",
    "sg:classifiers":[
        {
            "category":"Personal",
            "subcategory":"Beauty Salon",
            "type":"Services"
        }
    ],
    "sg:phone":"+1 662 728 6074",
    "sg:postcode":"38829",
    "sg:province":"MS",
    "sg:tags":[
        "shop",
        "barber"
    ],
    "wof:name":"A-Cut Above",
    "wof:placetype":"venue"
},
  "geometry": {"coordinates":[-88.554491,34.655694],"type":"Point"}
}