{
  "type": "Feature",
  "properties": {
    "iso:country":"US",
    "sg:address":"16350 State Hwy 603",
    "sg:city":"Kiln",
    "sg:classifiers":[
        {
            "category":"Autos & Motor Vehicles",
            "subcategory":"Automobile Sales",
            "type":"Retail Goods"
        }
    ],
    "sg:phone":"+1 228 586 0080",
    "sg:postcode":"39556",
    "sg:province":"MS",
    "sg:tags":[
        "car",
        "dealer"
    ],
    "wof:name":"ATS Auto Sales",
    "wof:placetype":"venue"
},
  "geometry": {"coordinates":[-89.44139199999999,30.406399],"type":"Point"}
}