{
  "type": "Feature",
  "properties": {
    "addr:full":"33 Jr Merrill Old Hwy 45 Rd S Buckatunna MS 39322",
    "addr:housenumber":"33",
    "addr:postcode":"39322",
    "addr:street":"Jr Merrill Old Hwy 45 Rd S Buckatunna",
    "iso:country":"US",
    "sg:address":"33 Jr Merrill Old Hwy 45 Rd S",
    "sg:city":"Buckatunna",
    "sg:classifiers":[
        {
            "category":"Organizations",
            "subcategory":"Religious Organization",
            "type":"Services"
        }
    ],
    "sg:phone":"+1 601 648 2707",
    "sg:postcode":"39322",
    "sg:province":"MS",
    "sg:tags":[
        "church"
    ],
    "wof:name":"Sweet Pilgrim Missionary Bapt",
    "wof:placetype":"venue"
},
  "geometry": {"coordinates":[-88.522464,31.531199],"type":"Point"}
}