{
  "type": "Feature",
  "properties": {
    "addr:full":"2137 Oak Grove Rd Hattiesburg MS 39402",
    "addr:housenumber":"2137",
    "addr:postcode":"39402",
    "addr:street":"Oak Grove Rd",
    "iso:country":"US",
    "sg:address":"2137 Oak Grove Rd",
    "sg:city":"Hattiesburg",
    "sg:classifiers":[
        {
            "category":"Personal",
            "subcategory":"Beauty Salon",
            "type":"Services"
        }
    ],
    "sg:phone":"+1 601 264 2467",
    "sg:postcode":"39402",
    "sg:province":"MS",
    "sg:tags":[
        "shop"
    ],
    "wof:name":"Magnolia Hair Designs",
    "wof:placetype":"venue"
},
  "geometry": {"coordinates":[-89.361688,31.318606],"type":"Point"}
}