{
  "type": "Feature",
  "properties": {
    "addr:full":"11505 Independence Rd Moss Point MS 39562",
    "addr:housenumber":"11505",
    "addr:postcode":"39562",
    "addr:street":"Independence Rd",
    "iso:country":"US",
    "sg:address":"11505 Independence Rd",
    "sg:city":"Moss Point",
    "sg:classifiers":[
        {
            "category":"Organizations",
            "subcategory":"Religious Organization",
            "type":"Services"
        }
    ],
    "sg:phone":"+1 228 475 3471",
    "sg:postcode":"39562",
    "sg:province":"MS",
    "wof:name":"Franklin Creek Baptist Church",
    "wof:placetype":"venue"
},
  "geometry": {"coordinates":[-88.419372,30.472681],"type":"Point"}
}