{
  "type": "Feature",
  "properties": {
    "addr:full":"1008 George Edward Rd Mccomb MS 39648",
    "addr:housenumber":"1008",
    "addr:postcode":"39648",
    "addr:street":"George Edward Rd",
    "iso:country":"US",
    "sg:address":"1008 George Edward Rd",
    "sg:city":"Mccomb",
    "sg:classifiers":[
        {
            "category":"Retail",
            "subcategory":"Auto Repair",
            "type":"Services"
        }
    ],
    "sg:phone":"+1 601 276 2181",
    "sg:postcode":"39648",
    "sg:province":"MS",
    "sg:tags":[
        "repairing",
        "automobile"
    ],
    "wof:name":"Topline",
    "wof:placetype":"venue"
},
  "geometry": {"coordinates":[-90.47560900000001,31.269027],"type":"Point"}
}