{
  "type": "Feature",
  "properties": {
    "iso:country":"US",
    "sg:address":"282 Eisenhower Dr",
    "sg:city":"Biloxi",
    "sg:classifiers":[
        {
            "category":"Personal",
            "subcategory":"Beauty Salon",
            "type":"Services"
        }
    ],
    "sg:phone":"+1 228 388 3443",
    "sg:postcode":"39531",
    "sg:province":"MS",
    "sg:tags":[
        "shop"
    ],
    "wof:name":"Sassy Nails",
    "wof:placetype":"venue"
},
  "geometry": {"coordinates":[-88.99322600000001,30.399278],"type":"Point"}
}