{
  "type": "Feature",
  "properties": {
    "iso:country":"US",
    "sg:address":"1002 Hwy 13",
    "sg:city":"Wiggins",
    "sg:classifiers":[
        {
            "category":"Food & Beverages",
            "subcategory":"Groceries & Convenience Stores",
            "type":"Retail Goods"
        }
    ],
    "sg:phone":"+1 601 928 5090",
    "sg:postcode":"39577",
    "sg:province":"MS",
    "sg:tags":[
        "grocer"
    ],
    "wof:name":"Double D Grocery & Deli",
    "wof:placetype":"venue"
},
  "geometry": {"coordinates":[-89.259142,30.987128],"type":"Point"}
}