{
  "type": "Feature",
  "properties": {
    "iso:country":"US",
    "sg:address":"1940 48th Ave",
    "sg:city":"Gulfport",
    "sg:classifiers":[
        {
            "category":"Shopping",
            "subcategory":"Jewelry",
            "type":"Retail Goods"
        }
    ],
    "sg:phone":"+1 228 864 5010",
    "sg:postcode":"39501",
    "sg:province":"MS",
    "wof:name":"Starling Sales & Service",
    "wof:placetype":"venue"
},
  "geometry": {"coordinates":[-89.118239,30.374003],"type":"Point"}
}