{
  "type": "Feature",
  "properties": {
    "iso:country":"US",
    "sg:address":"691 US Hwy 84",
    "sg:city":"Brookhaven",
    "sg:classifiers":[
        {
            "category":"Organizations",
            "subcategory":"Religious Organization",
            "type":"Services"
        }
    ],
    "sg:phone":"+1 601 833 8717",
    "sg:postcode":"39601",
    "sg:province":"MS",
    "wof:name":"New Prospect Baptist Church",
    "wof:placetype":"venue"
},
  "geometry": {"coordinates":[-90.519943,31.530505],"type":"Point"}
}