{
  "type": "Feature",
  "properties": {
    "addr:full":"1528 Pratt Ave Gulfport MS 39501",
    "addr:housenumber":"1528",
    "addr:postcode":"39501",
    "addr:street":"Pratt Ave",
    "iso:country":"US",
    "sg:address":"1528 Pratt Ave",
    "sg:city":"Gulfport",
    "sg:classifiers":[
        {
            "category":"Real Estate",
            "subcategory":"Real Estate Agent",
            "type":"Services"
        }
    ],
    "sg:phone":"+1 228 863 1845",
    "sg:postcode":"39501",
    "sg:province":"MS",
    "wof:name":"R T Mc Cool Real Estate Inc",
    "wof:placetype":"venue"
},
  "geometry": {"coordinates":[-89.07984,30.371137],"type":"Point"}
}