{
  "type": "Feature",
  "properties": {
    "addr:full":"1804 Yazoo Ave Greenwood MS 38930",
    "addr:housenumber":"1804",
    "addr:postcode":"38930",
    "addr:street":"Yazoo Ave",
    "iso:country":"US",
    "sg:address":"1804 Yazoo Ave",
    "sg:city":"Greenwood",
    "sg:classifiers":[
        {
            "category":"Retail",
            "subcategory":"Repair Shop",
            "type":"Services"
        }
    ],
    "sg:phone":"+1 662 451 5910",
    "sg:postcode":"38930",
    "sg:province":"MS",
    "sg:tags":[
        "scooter",
        "motorcycle",
        "motor"
    ],
    "wof:name":"Paul's Atv Repair",
    "wof:placetype":"venue"
},
  "geometry": {"coordinates":[-90.20243499999999,33.515287],"type":"Point"}
}