{
  "type": "Feature",
  "properties": {
    "addr:full":"530 W Central Ave Wiggins MS 39577",
    "addr:housenumber":"530",
    "addr:postcode":"39577",
    "addr:street":"W Central Ave",
    "iso:country":"US",
    "sg:address":"530 W Central Ave",
    "sg:city":"Wiggins",
    "sg:classifiers":[
        {
            "category":"Shopping",
            "subcategory":"Computers & Home Electronics",
            "type":"Retail Goods"
        }
    ],
    "sg:phone":"+1 601 928 3441",
    "sg:postcode":"39577",
    "sg:province":"MS",
    "sg:tags":[
        "equipment",
        "electronic",
        "supply"
    ],
    "wof:name":"Radio Shack",
    "wof:placetype":"venue"
},
  "geometry": {"coordinates":[-89.142591,30.851751],"type":"Point"}
}