{
  "type": "Feature",
  "properties": {
    "iso:country":"US",
    "sg:address":"124 Hunter's Cove",
    "sg:city":"Madison",
    "sg:classifiers":[
        {
            "category":"Shopping",
            "type":"Retail Goods"
        }
    ],
    "sg:phone":"+1 601 853 3942",
    "sg:postcode":"39110",
    "sg:province":"MS",
    "sg:tags":[
        "toy",
        "sales",
        "furniture"
    ],
    "wof:name":"Madison Toy Co",
    "wof:placetype":"venue"
},
  "geometry": {"coordinates":[-90.130083,32.533395],"type":"Point"}
}