{
  "type": "Feature",
  "properties": {
    "addr:full":"1516 Gardner Blvd Columbus MS 39702",
    "addr:housenumber":"1516",
    "addr:postcode":"39702",
    "addr:street":"Gardner Blvd",
    "iso:country":"US",
    "sg:address":"1516 Gardner Blvd",
    "sg:city":"Columbus",
    "sg:classifiers":[
        {
            "category":"Shopping",
            "subcategory":"Computers & Home Electronics",
            "type":"Retail Goods"
        }
    ],
    "sg:phone":"+1 662 244 8308",
    "sg:postcode":"39702",
    "sg:province":"MS",
    "wof:name":"Street Sounds",
    "wof:placetype":"venue"
},
  "geometry": {"coordinates":[-88.38955300000001,33.511627],"type":"Point"}
}