{
  "type": "Feature",
  "properties": {
    "iso:country":"US",
    "sg:address":"801 N Broad St",
    "sg:city":"Leland",
    "sg:classifiers":[
        {
            "category":"Government",
            "subcategory":"Office",
            "type":"Public Place"
        }
    ],
    "sg:phone":"+1 662 686 9306",
    "sg:postcode":"38756",
    "sg:province":"MS",
    "sg:tags":[
        "city",
        "program",
        "health"
    ],
    "wof:name":"Leland Health Dept",
    "wof:placetype":"venue"
},
  "geometry": {"coordinates":[-90.89367300000001,33.409701],"type":"Point"}
}