{
  "type": "Feature",
  "properties": {
    "addr:full":"3348 N Liberty St Canton MS 39046",
    "addr:housenumber":"3348",
    "addr:postcode":"39046",
    "addr:street":"N Liberty St",
    "iso:country":"US",
    "sg:address":"3348 N Liberty St",
    "sg:city":"Canton",
    "sg:classifiers":[
        {
            "category":"Health Services",
            "subcategory":"Health Practitioner",
            "type":"Services"
        }
    ],
    "sg:phone":"+1 601 859 8842",
    "sg:postcode":"39046",
    "sg:province":"MS",
    "sg:tags":[
        "psychologist"
    ],
    "wof:name":"Nelson R Cauthen Jr PHD",
    "wof:placetype":"venue"
},
  "geometry": {"coordinates":[-90.034864,32.612824],"type":"Point"}
}