{
  "type": "Feature",
  "properties": {
    "iso:country":"US",
    "sg:address":"1013 Co Rd 53",
    "sg:city":"Myrtle",
    "sg:classifiers":[
        {
            "category":"Building & Trades",
            "subcategory":"Construction",
            "type":"Services"
        }
    ],
    "sg:phone":"+1 662 988 2260",
    "sg:postcode":"38650",
    "sg:province":"MS",
    "sg:tags":[
        "contractor"
    ],
    "wof:name":"Kizer Contractors Inc",
    "wof:placetype":"venue"
},
  "geometry": {"coordinates":[-89.12298800000001,34.525096],"type":"Point"}
}