{
  "type": "Feature",
  "properties": {
    "addr:full":"1775 N Washington St Vicksburg MS 39183",
    "addr:housenumber":"1775",
    "addr:postcode":"39183",
    "addr:street":"N Washington St",
    "iso:country":"US",
    "sg:address":"1775 N Washington St",
    "sg:city":"Vicksburg",
    "sg:classifiers":[
        {
            "category":"Autos & Motor Vehicles",
            "subcategory":"Fuel & Gas Station",
            "type":"Retail Goods"
        }
    ],
    "sg:phone":"+1 601 638 8380",
    "sg:postcode":"39183",
    "sg:province":"MS",
    "wof:name":"Texaco",
    "wof:placetype":"venue"
},
  "geometry": {"coordinates":[-90.869642,32.377222],"type":"Point"}
}