{
  "type": "Feature",
  "properties": {
    "iso:country":"US",
    "sg:address":"105 Olympia Fields",
    "sg:city":"Jackson",
    "sg:classifiers":[
        {
            "category":"Real Estate",
            "subcategory":"Real Estate Operator",
            "type":"Services"
        }
    ],
    "sg:phone":"+1 601 956 8475",
    "sg:postcode":"39211",
    "sg:province":"MS",
    "sg:tags":[
        "building",
        "nonresidential"
    ],
    "wof:name":"Geiger Properties",
    "wof:placetype":"venue"
},
  "geometry": {"coordinates":[-90.103874,32.397624],"type":"Point"}
}