{
  "type": "Feature",
  "properties": {
    "iso:country":"US",
    "sg:address":"1100 E Peace St",
    "sg:city":"Canton",
    "sg:classifiers":[
        {
            "category":"Autos & Motor Vehicles",
            "subcategory":"Fuel & Gas Station",
            "type":"Retail Goods"
        }
    ],
    "sg:phone":"+1 601 859 8433",
    "sg:postcode":"39046",
    "sg:province":"MS",
    "sg:tags":[
        "station",
        "gasoline",
        "oil"
    ],
    "wof:name":"Speedy Oil & Lube Inc",
    "wof:placetype":"venue"
},
  "geometry": {"coordinates":[-90.010498,32.61199],"type":"Point"}
}