{
  "type": "Feature",
  "properties": {
    "iso:country":"US",
    "sg:address":"426 Rd 1581",
    "sg:city":"Tupelo",
    "sg:phone":"+1 662 844 7978",
    "sg:postcode":"38804",
    "sg:province":"MS",
    "sg:tags":[
        "farm",
        "soybean"
    ],
    "wof:name":"Shumpert Farm",
    "wof:placetype":"venue"
},
  "geometry": {"coordinates":[-88.54832399999999,34.198683],"type":"Point"}
}