{
  "type": "Feature",
  "properties": {
    "addr:full":"224 Canal St Mccomb MS 39648",
    "addr:housenumber":"224",
    "addr:postcode":"39648",
    "addr:street":"Canal St",
    "iso:country":"US",
    "sg:address":"224 Canal St",
    "sg:city":"Mccomb",
    "sg:classifiers":[
        {
            "category":"Autos & Motor Vehicles",
            "subcategory":"Fuel & Gas Station",
            "type":"Retail Goods"
        }
    ],
    "sg:phone":"+1 601 684 0096",
    "sg:postcode":"39648",
    "sg:province":"MS",
    "sg:tags":[
        "oil"
    ],
    "wof:name":"Shell",
    "wof:placetype":"venue"
},
  "geometry": {"coordinates":[-90.4521,31.242453],"type":"Point"}
}