{
  "type": "Feature",
  "properties": {
    "iso:country":"US",
    "sg:address":"8880 Germantown Rd",
    "sg:city":"Olive Branch",
    "sg:classifiers":[
        {
            "category":"Real Estate",
            "subcategory":"Real Estate Agent",
            "type":"Services"
        }
    ],
    "sg:phone":"+1 662 895 7163",
    "sg:postcode":"38654",
    "sg:province":"MS",
    "wof:name":"Eschelon Realty",
    "wof:placetype":"venue"
},
  "geometry": {"coordinates":[-89.83051500000001,34.988944],"type":"Point"}
}