{
  "type": "Feature",
  "properties": {
    "iso:country":"US",
    "sg:address":"2225 Denny Ave",
    "sg:city":"Pascagoula",
    "sg:classifiers":[
        {
            "category":"Autos & Motor Vehicles",
            "subcategory":"Auto Supplies",
            "type":"Retail Goods"
        }
    ],
    "sg:phone":"+1 228 769 2774",
    "sg:postcode":"39567",
    "sg:province":"MS",
    "sg:tags":[
        "tire"
    ],
    "wof:name":"Perkins Tire & Polaris",
    "wof:placetype":"venue"
},
  "geometry": {"coordinates":[-88.54166600000001,30.370738],"type":"Point"}
}