{
  "type": "Feature",
  "properties": {
    "addr:full":"160 Broadway St Clinton MS 39056",
    "addr:housenumber":"160",
    "addr:postcode":"39056",
    "addr:street":"Broadway St",
    "iso:country":"US",
    "sg:address":"160 Broadway St",
    "sg:city":"Clinton",
    "sg:classifiers":[
        {
            "category":"Freight",
            "type":"Transportation"
        }
    ],
    "sg:phone":"+1 601 924 1572",
    "sg:postcode":"39056",
    "sg:province":"MS",
    "sg:tags":[
        "commercial",
        "storage"
    ],
    "wof:name":"Dixie Self Storage",
    "wof:placetype":"venue"
},
  "geometry": {"coordinates":[-90.324479,32.330703],"type":"Point"}
}