{
  "type": "Feature",
  "properties": {
    "iso:country":"US",
    "sg:address":"343 Old Hwy 49 W",
    "sg:city":"Brooklyn",
    "sg:classifiers":[
        {
            "category":"Professional",
            "type":"Services"
        }
    ],
    "sg:phone":"+1 601 583 9838",
    "sg:postcode":"39425",
    "sg:province":"MS",
    "sg:tags":[
        "establishment"
    ],
    "wof:name":"Walley C W & Sons Inc",
    "wof:placetype":"venue"
},
  "geometry": {"coordinates":[-89.20182,31.071769],"type":"Point"}
}