{
  "type": "Feature",
  "properties": {
    "iso:country":"US",
    "sg:address":"3043 State Hwy 492",
    "sg:city":"Conehatta",
    "sg:classifiers":[
        {
            "category":"Building & Trades",
            "subcategory":"Construction",
            "type":"Services"
        }
    ],
    "sg:phone":"+1 601 774 8620",
    "sg:postcode":"39057",
    "sg:province":"MS",
    "sg:tags":[
        "house"
    ],
    "wof:name":"Hulon Hillman Contractor",
    "wof:placetype":"venue"
},
  "geometry": {"coordinates":[-89.290896,32.554935],"type":"Point"}
}