{
  "type": "Feature",
  "properties": {
    "addr:full":"506 Howard Ave Biloxi MS 39530",
    "addr:housenumber":"506",
    "addr:postcode":"39530",
    "addr:street":"Howard Ave",
    "iso:country":"US",
    "sg:address":"506 Howard Ave",
    "sg:city":"Biloxi",
    "sg:classifiers":[
        {
            "category":"Real Estate",
            "subcategory":"Real Estate Agent",
            "type":"Services"
        }
    ],
    "sg:phone":"+1 228 374 2859",
    "sg:postcode":"39530",
    "sg:province":"MS",
    "wof:name":"Jordan Development LLC",
    "wof:placetype":"venue"
},
  "geometry": {"coordinates":[-88.87688300000001,30.396708],"type":"Point"}
}