{
  "type": "Feature",
  "properties": {
    "iso:country":"US",
    "sg:address":"16172 Hwy 51",
    "sg:city":"Hazlehurst",
    "sg:classifiers":[
        {
            "category":"Home & Garden",
            "subcategory":"Hardware",
            "type":"Retail Goods"
        }
    ],
    "sg:phone":"+1 601 894 5335",
    "sg:postcode":"39083",
    "sg:province":"MS",
    "wof:name":"JB Entps - Hazlehurst LLC",
    "wof:placetype":"venue"
},
  "geometry": {"coordinates":[-90.40016199999999,31.882285],"type":"Point"}
}