{
  "type": "Feature",
  "properties": {
    "addr:full":"800 Avery Blvd N Ridgeland MS 39157",
    "addr:housenumber":"800",
    "addr:postcode":"39157",
    "addr:street":"Avery Blvd N",
    "iso:country":"US",
    "sg:address":"800 Avery Blvd N",
    "sg:city":"Ridgeland",
    "sg:classifiers":[
        {
            "category":"Social Services",
            "type":"Services"
        }
    ],
    "sg:phone":"+1 601 672 9156",
    "sg:postcode":"39157",
    "sg:province":"MS",
    "sg:tags":[
        "professional",
        "counselor"
    ],
    "wof:name":"Connie Girffin",
    "wof:placetype":"venue"
},
  "geometry": {"coordinates":[-90.115571,32.40406],"type":"Point"}
}