{
  "type": "Feature",
  "properties": {
    "iso:country":"US",
    "sg:address":"910 Robinson St",
    "sg:city":"Waynesboro",
    "sg:classifiers":[
        {
            "category":"Personal",
            "subcategory":"Barber",
            "type":"Services"
        }
    ],
    "sg:phone":"+1 601 735 9895",
    "sg:postcode":"39367",
    "sg:province":"MS",
    "wof:name":"A & J Barber Shop",
    "wof:placetype":"venue"
},
  "geometry": {"coordinates":[-88.643461,31.681041],"type":"Point"}
}