{
  "type": "Feature",
  "properties": {
    "addr:full":"308 E Sunflower Rd Cleveland MS 38732",
    "addr:housenumber":"308",
    "addr:postcode":"38732",
    "addr:street":"E Sunflower Rd",
    "iso:country":"US",
    "sg:address":"308 E Sunflower Rd",
    "sg:city":"Cleveland",
    "sg:classifiers":[
        {
            "category":"Banks & Credit Unions",
            "subcategory":"Bank",
            "type":"Services"
        }
    ],
    "sg:phone":"+1 662 843 4231",
    "sg:postcode":"38732",
    "sg:province":"MS",
    "sg:website":"www.mfbank.com",
    "wof:name":"Merchants & Farmers Bank",
    "wof:placetype":"venue"
},
  "geometry": {"coordinates":[-90.71978900000001,33.747371],"type":"Point"}
}