{
  "type": "Feature",
  "properties": {
    "addr:full":"188 Pine Ln Mendenhall MS 39114",
    "addr:housenumber":"188",
    "addr:postcode":"39114",
    "addr:street":"Pine Ln",
    "iso:country":"US",
    "sg:address":"188 Pine Ln",
    "sg:city":"Mendenhall",
    "sg:classifiers":[
        {
            "category":"Professional",
            "subcategory":"Detective & Security Services",
            "type":"Services"
        }
    ],
    "sg:phone":"+1 601 847 4008",
    "sg:postcode":"39114",
    "sg:province":"MS",
    "sg:tags":[
        "car"
    ],
    "wof:name":"Investigative Services Miss",
    "wof:placetype":"venue"
},
  "geometry": {"coordinates":[-89.877627,31.94312],"type":"Point"}
}