{
  "type": "Feature",
  "properties": {
    "iso:country":"US",
    "sg:address":"6718 State Hwy 63",
    "sg:city":"Moss Point",
    "sg:classifiers":[
        {
            "category":"Autos & Motor Vehicles",
            "subcategory":"Fuel & Gas Station",
            "type":"Retail Goods"
        }
    ],
    "sg:phone":"+1 228 474 0004",
    "sg:postcode":"39563",
    "sg:province":"MS",
    "sg:tags":[
        "oil"
    ],
    "wof:name":"Chevron",
    "wof:placetype":"venue"
},
  "geometry": {"coordinates":[-88.527821,30.440108],"type":"Point"}
}