{
  "type": "Feature",
  "properties": {
    "iso:country":"US",
    "sg:address":"3405 Co Rd 100",
    "sg:city":"Corinth",
    "sg:classifiers":[
        {
            "category":"Shopping",
            "subcategory":"Discount & Variety Stores",
            "type":"Retail Goods"
        }
    ],
    "sg:phone":"+1 662 287 1556",
    "sg:postcode":"38834",
    "sg:province":"MS",
    "sg:tags":[
        "merchandise",
        "g",
        "general"
    ],
    "wof:name":"Candle Nutt The",
    "wof:placetype":"venue"
},
  "geometry": {"coordinates":[-88.45295900000001,34.946737],"type":"Point"}
}