{
  "type": "Feature",
  "properties": {
    "addr:full":"5960 Getwell Rd Southaven MS 38672",
    "addr:postcode":"5960;38672",
    "addr:street":"Getwell Rd",
    "iso:country":"US",
    "sg:address":"5960 Getwell Rd",
    "sg:city":"Southaven",
    "sg:classifiers":[
        {
            "category":"Home & Garden",
            "subcategory":"Furniture",
            "type":"Retail Goods"
        }
    ],
    "sg:phone":"+1 662 893 3663",
    "sg:postcode":"38672",
    "sg:province":"MS",
    "sg:tags":[
        "store"
    ],
    "wof:name":"Robert Madison Home Furnishings",
    "wof:placetype":"venue"
},
  "geometry": {"coordinates":[-89.93675500000001,34.947345],"type":"Point"}
}