{
  "type": "Feature",
  "properties": {
    "iso:country":"US",
    "sg:address":"15444 Dedeaux Rd",
    "sg:city":"Gulfport",
    "sg:classifiers":[
        {
            "category":"Health Services",
            "subcategory":"Doctor",
            "type":"Services"
        }
    ],
    "sg:phone":"+1 228 832 9038",
    "sg:postcode":"39503",
    "sg:province":"MS",
    "sg:tags":[
        "clinic"
    ],
    "wof:name":"Primary Care Medical Ctr",
    "wof:placetype":"venue"
},
  "geometry": {"coordinates":[-89.10229200000001,30.44957],"type":"Point"}
}