{
  "type": "Feature",
  "properties": {
    "iso:country":"US",
    "sg:address":"16 Hillcrest Dr",
    "sg:city":"Hattiesburg",
    "sg:classifiers":[
        {
            "category":"Building & Trades",
            "subcategory":"Construction",
            "type":"Services"
        }
    ],
    "sg:phone":"+1 601 264 9800",
    "sg:postcode":"39402",
    "sg:province":"MS",
    "sg:tags":[
        "dwelling",
        "family",
        "builder",
        "general",
        "home",
        "contractor"
    ],
    "wof:name":"Stafford Construction Co Inc",
    "wof:placetype":"venue"
},
  "geometry": {"coordinates":[-89.371843,31.317553],"type":"Point"}
}