{
  "type": "Feature",
  "properties": {
    "iso:country":"US",
    "sg:address":"2624 N 13th St",
    "sg:city":"Ocean Springs",
    "sg:classifiers":[
        {
            "category":"Building & Trades",
            "subcategory":"Electrical",
            "type":"Services"
        }
    ],
    "sg:phone":"+1 228 872 1354",
    "sg:postcode":"39564",
    "sg:province":"MS",
    "sg:tags":[
        "electrical",
        "contractor"
    ],
    "wof:name":"Guice Electric",
    "wof:placetype":"venue"
},
  "geometry": {"coordinates":[-88.75314899999999,30.379592],"type":"Point"}
}