{
  "type": "Feature",
  "properties": {
    "iso:country":"US",
    "sg:address":"268 Atkins St",
    "sg:city":"Philadelphia",
    "sg:classifiers":[
        {
            "category":"Social Services",
            "subcategory":"Job Training",
            "type":"Services"
        }
    ],
    "sg:phone":"+1 601 656 9767",
    "sg:postcode":"39350",
    "sg:province":"MS",
    "sg:tags":[
        "employment"
    ],
    "wof:name":"Experience Works",
    "wof:placetype":"venue"
},
  "geometry": {"coordinates":[-89.11662699999999,32.779716],"type":"Point"}
}