{
  "type": "Feature",
  "properties": {
    "iso:country":"US",
    "sg:address":"2702 Flowood Dr",
    "sg:city":"Flowood",
    "sg:classifiers":[
        {
            "category":"Wholesale",
            "subcategory":"Office Equipment",
            "type":"Manufacturing & Wholesale Goods"
        }
    ],
    "sg:phone":"+1 601 932 0340",
    "sg:postcode":"39232",
    "sg:province":"MS",
    "sg:tags":[
        "machine",
        "duplicating",
        "copying"
    ],
    "wof:name":"Approved Document Svc",
    "wof:placetype":"venue"
},
  "geometry": {"coordinates":[-90.107574,32.323682],"type":"Point"}
}