{
  "type": "Feature",
  "properties": {
    "addr:full":"9902 State Hwy 43 N Poplarville MS 39470",
    "addr:housenumber":"9902",
    "addr:postcode":"39470",
    "addr:street":"State Hwy 43 N",
    "iso:country":"US",
    "sg:address":"9902 State Hwy 43 N",
    "sg:city":"Poplarville",
    "sg:classifiers":[
        {
            "category":"Retail",
            "subcategory":"Animal Services",
            "type":"Services"
        }
    ],
    "sg:phone":"+1 601 795 0255",
    "sg:postcode":"39470",
    "sg:province":"MS",
    "wof:name":"Scheyd Pine Oaks Farm",
    "wof:placetype":"venue"
},
  "geometry": {"coordinates":[-89.70970199999999,30.916522],"type":"Point"}
}