{
  "type": "Feature",
  "properties": {
    "iso:country":"US",
    "sg:address":"304 Park Dr",
    "sg:city":"Biloxi",
    "sg:classifiers":[
        {
            "category":"Professional",
            "subcategory":"Accounting & Tax Preparation",
            "type":"Services"
        }
    ],
    "sg:phone":"+1 228 388 6590",
    "sg:postcode":"39531",
    "sg:province":"MS",
    "sg:tags":[
        "bookkeeping",
        "general"
    ],
    "wof:name":"The Accounting Alternative",
    "wof:placetype":"venue"
},
  "geometry": {"coordinates":[-88.9623,30.409499],"type":"Point"}
}