{
  "type": "Feature",
  "properties": {
    "iso:country":"US",
    "sg:address":"2453 Palestine Rd",
    "sg:city":"Raymond",
    "sg:classifiers":[
        {
            "category":"Organizations",
            "subcategory":"Religious Organization",
            "type":"Services"
        }
    ],
    "sg:phone":"+1 601 857 0005",
    "sg:postcode":"39154",
    "sg:province":"MS",
    "sg:tags":[
        "church"
    ],
    "wof:name":"Highpointe Baptist Church",
    "wof:placetype":"venue"
},
  "geometry": {"coordinates":[-90.41742600000001,32.190466],"type":"Point"}
}