{
  "type": "Feature",
  "properties": {
    "addr:full":"4254 Hwy 373 Columbus MS 39705",
    "addr:housenumber":"4254",
    "addr:postcode":"39705",
    "addr:street":"Hwy 373",
    "iso:country":"US",
    "sg:address":"4254 Hwy 373",
    "sg:city":"Columbus",
    "sg:classifiers":[
        {
            "category":"Building & Trades",
            "subcategory":"Equipment Rental",
            "type":"Services"
        }
    ],
    "sg:phone":"+1 662 434 6665",
    "sg:postcode":"39705",
    "sg:province":"MS",
    "wof:name":"Express Video",
    "wof:placetype":"venue"
},
  "geometry": {"coordinates":[-88.45659499999999,33.660581],"type":"Point"}
}