{
  "type": "Feature",
  "properties": {
    "addr:full":"12 River Bend Pl Flowood MS 39232",
    "addr:housenumber":"12",
    "addr:postcode":"39232",
    "addr:street":"River Bend Pl",
    "iso:country":"US",
    "sg:address":"12 River Bend Pl",
    "sg:city":"Flowood",
    "sg:classifiers":[
        {
            "category":"Health Services",
            "subcategory":"Clinic",
            "type":"Services"
        }
    ],
    "sg:phone":"+1 601 933 1000",
    "sg:postcode":"39232",
    "sg:province":"MS",
    "sg:tags":[
        "banks",
        "tissue",
        "organ"
    ],
    "sg:website":"www.msora.org",
    "wof:name":"Mississippi Organ Recovery",
    "wof:placetype":"venue"
},
  "geometry": {"coordinates":[-90.125382,32.327268],"type":"Point"}
}