{
  "type": "Feature",
  "properties": {
    "addr:full":"114 E Canal St Picayune MS 39466",
    "addr:housenumber":"114",
    "addr:postcode":"39466",
    "addr:street":"E Canal St",
    "iso:country":"US",
    "sg:address":"114 E Canal St",
    "sg:city":"Picayune",
    "sg:classifiers":[
        {
            "category":"Insurance",
            "subcategory":"Insurance Agent",
            "type":"Services"
        }
    ],
    "sg:phone":"+1 601 749 8078",
    "sg:postcode":"39466",
    "sg:province":"MS",
    "wof:name":"First National Insurance",
    "wof:placetype":"venue"
},
  "geometry": {"coordinates":[-89.679767,30.52569],"type":"Point"}
}