{
  "type": "Feature",
  "properties": {
    "iso:country":"US",
    "sg:address":"3825 Ridgewood Rd",
    "sg:city":"Jackson",
    "sg:classifiers":[
        {
            "category":"Organizations",
            "subcategory":"Professional Association",
            "type":"Services"
        }
    ],
    "sg:phone":"+1 601 432 6539",
    "sg:postcode":"39211",
    "sg:province":"MS",
    "sg:tags":[
        "foundation",
        "television",
        "radio"
    ],
    "wof:name":"Foundation For Publc Broadcast",
    "wof:placetype":"venue"
},
  "geometry": {"coordinates":[-90.141974,32.339954],"type":"Point"}
}