{
  "type": "Feature",
  "properties": {
    "addr:full":"321 Devereaux Dr Natchez MS 39120",
    "addr:housenumber":"321",
    "addr:postcode":"39120",
    "addr:street":"Devereaux Dr",
    "iso:country":"US",
    "sg:address":"321 Devereaux Dr",
    "sg:city":"Natchez",
    "sg:classifiers":[
        {
            "category":"Retail",
            "subcategory":"Auto Rental",
            "type":"Services"
        }
    ],
    "sg:phone":"+1 601 445 8910",
    "sg:postcode":"39120",
    "sg:province":"MS",
    "sg:tags":[
        "renting",
        "automobile"
    ],
    "wof:name":"U-Save Auto Rental",
    "wof:placetype":"venue"
},
  "geometry": {"coordinates":[-91.362737,31.560783],"type":"Point"}
}