{
  "type": "Feature",
  "properties": {
    "iso:country":"US",
    "sg:address":"801 Hwy 45 N",
    "sg:city":"Columbus",
    "sg:classifiers":[
        {
            "category":"Professional",
            "subcategory":"Accounting & Tax Preparation",
            "type":"Services"
        }
    ],
    "sg:phone":"+1 662 329 8778",
    "sg:postcode":"39701",
    "sg:province":"MS",
    "sg:tags":[
        "accountant"
    ],
    "wof:name":"Tacs",
    "wof:placetype":"venue"
},
  "geometry": {"coordinates":[-88.435326,33.520896],"type":"Point"}
}