{
  "type": "Feature",
  "properties": {
    "iso:country":"US",
    "sg:address":"305 Veterans Memorial Blvd S",
    "sg:city":"Eupora",
    "sg:classifiers":[
        {
            "category":"Manufacturing",
            "subcategory":"Building Materials",
            "type":"Manufacturing & Wholesale Goods"
        },
        {
            "category":"Home & Garden",
            "subcategory":"Furniture",
            "type":"Retail Goods"
        }
    ],
    "sg:phone":"+1 662 258 2617",
    "sg:postcode":"39744",
    "sg:province":"MS",
    "sg:tags":[
        "wood",
        "household",
        "cabinet",
        "kitchen",
        "mfg"
    ],
    "wof:name":"Britton Industries LLC",
    "wof:placetype":"venue"
},
  "geometry": {"coordinates":[-89.266981,33.538493],"type":"Point"}
}