{
  "type": "Feature",
  "properties": {
    "iso:country":"US",
    "sg:address":"311 W Eastport St",
    "sg:city":"Iuka",
    "sg:classifiers":[
        {
            "category":"Communications",
            "subcategory":"Radio Station",
            "type":"Services"
        }
    ],
    "sg:phone":"+1 662 423 2369",
    "sg:postcode":"38852",
    "sg:province":"MS",
    "sg:tags":[
        "company",
        "broadcasting"
    ],
    "wof:name":"WFXO",
    "wof:placetype":"venue"
},
  "geometry": {"coordinates":[-88.19309699999999,34.812507],"type":"Point"}
}