{
  "type": "Feature",
  "properties": {
    "addr:full":"103 Grants Ferry Rd Brandon MS 39047",
    "addr:housenumber":"103",
    "addr:postcode":"39047",
    "addr:street":"Grants Ferry Rd",
    "iso:country":"US",
    "sg:address":"103 Grants Ferry Rd",
    "sg:city":"Brandon",
    "sg:classifiers":[
        {
            "category":"Food & Beverages",
            "subcategory":"Groceries & Convenience Stores",
            "type":"Retail Goods"
        }
    ],
    "sg:phone":"+1 601 992 5385",
    "sg:postcode":"39047",
    "sg:province":"MS",
    "wof:name":"Super Stop",
    "wof:placetype":"venue"
},
  "geometry": {"coordinates":[-90.017104,32.371342],"type":"Point"}
}