{
  "type": "Feature",
  "properties": {
    "iso:country":"US",
    "sg:address":"1902 Valley St",
    "sg:city":"Jackson",
    "sg:classifiers":[
        {
            "category":"Manufacturing",
            "subcategory":"Tools & Machinery",
            "type":"Manufacturing & Wholesale Goods"
        }
    ],
    "sg:phone":"+1 601 948 1900",
    "sg:postcode":"39204",
    "sg:province":"MS",
    "sg:tags":[
        "machine",
        "shop"
    ],
    "wof:name":"Amerimac Manufacturing Corp",
    "wof:placetype":"venue"
},
  "geometry": {"coordinates":[-90.21555600000001,32.289449],"type":"Point"}
}