{
  "type": "Feature",
  "properties": {
    "addr:full":"2728 Sharon Ln Greenville MS 38701",
    "addr:housenumber":"2728",
    "addr:postcode":"38701",
    "addr:street":"Sharon Ln",
    "iso:country":"US",
    "sg:address":"2728 Sharon Ln",
    "sg:city":"Greenville",
    "sg:classifiers":[
        {
            "category":"Real Estate",
            "subcategory":"Real Estate Operator",
            "type":"Services"
        }
    ],
    "sg:phone":"+1 662 335 8666",
    "sg:postcode":"38701",
    "sg:province":"MS",
    "sg:tags":[
        "apartment",
        "agent"
    ],
    "wof:name":"Bayou Estates",
    "wof:placetype":"venue"
},
  "geometry": {"coordinates":[-91.088284,33.341555],"type":"Point"}
}