{
  "type": "Feature",
  "properties": {
    "iso:country":"US",
    "sg:address":"116 Lundy Ln",
    "sg:city":"Hattiesburg",
    "sg:classifiers":[
        {
            "category":"Wholesale",
            "subcategory":"Hardware",
            "type":"Manufacturing & Wholesale Goods"
        }
    ],
    "sg:phone":"+1 601 264 6680",
    "sg:postcode":"39401",
    "sg:province":"MS",
    "sg:tags":[
        "plumbing",
        "merchandise"
    ],
    "wof:name":"Noland Company",
    "wof:placetype":"venue"
},
  "geometry": {"coordinates":[-89.351068,31.327349],"type":"Point"}
}