{
  "type": "Feature",
  "properties": {
    "addr:full":"674 Hwy 30 Tishomingo MS 38873",
    "addr:housenumber":"674",
    "addr:postcode":"38873",
    "addr:street":"Hwy 30 Tishomingo",
    "iso:country":"US",
    "sg:address":"674 Hwy 30",
    "sg:city":"Tishomingo",
    "sg:classifiers":[
        {
            "category":"Farming",
            "subcategory":"Farm",
            "type":"Manufacturing & Wholesale Goods"
        }
    ],
    "sg:phone":"+1 662 438 6522",
    "sg:postcode":"38873",
    "sg:province":"MS",
    "sg:tags":[
        "crop",
        "general"
    ],
    "wof:name":"Lowell Long",
    "wof:placetype":"venue"
},
  "geometry": {"coordinates":[-88.230909,34.648609],"type":"Point"}
}