{
  "type": "Feature",
  "properties": {
    "addr:full":"7915 Winchester Rd Memphis MS 38125",
    "addr:housenumber":"7915",
    "addr:postcode":"38125",
    "addr:street":"Winchester Rd",
    "iso:country":"US",
    "sg:address":"7915 Winchester Rd",
    "sg:city":"Memphis",
    "sg:classifiers":[
        {
            "category":"Wholesale",
            "subcategory":"Machinery & Supplies",
            "type":"Manufacturing & Wholesale Goods"
        }
    ],
    "sg:phone":"+1 901 757 9570",
    "sg:postcode":"38125",
    "sg:province":"MS",
    "sg:tags":[
        "salon",
        "beauty"
    ],
    "wof:name":"Heil Beauty Systems",
    "wof:placetype":"venue"
},
  "geometry": {"coordinates":[-89.80047999999999,35.048715],"type":"Point"}
}