{
  "type": "Feature",
  "properties": {
    "iso:country":"US",
    "sg:address":"118 N 6th St",
    "sg:city":"Mccomb",
    "sg:classifiers":[
        {
            "category":"Professional",
            "subcategory":"Employment Agencies",
            "type":"Services"
        }
    ],
    "sg:phone":"+1 601 250 0800",
    "sg:postcode":"39648",
    "sg:province":"MS",
    "sg:tags":[
        "opportunity"
    ],
    "wof:name":"Temp South Inc",
    "wof:placetype":"venue"
},
  "geometry": {"coordinates":[-90.456909,31.246455],"type":"Point"}
}