{
  "type": "Feature",
  "properties": {
    "iso:country":"US",
    "sg:address":"401 E 9th St",
    "sg:city":"Yazoo City",
    "sg:classifiers":[
        {
            "category":"Health Services",
            "subcategory":"Nursing And Care Facility",
            "type":"Services"
        }
    ],
    "sg:phone":"+1 662 746 4621",
    "sg:postcode":"39194",
    "sg:province":"MS",
    "sg:tags":[
        "skilled"
    ],
    "wof:name":"Martha Coker Convalescent Home",
    "wof:placetype":"venue"
},
  "geometry": {"coordinates":[-90.40441,32.859569],"type":"Point"}
}