{
  "type": "Feature",
  "properties": {
    "iso:country":"US",
    "sg:address":"925 George Washington Ave",
    "sg:city":"Canton",
    "sg:classifiers":[
        {
            "category":"Organizations",
            "subcategory":"Religious Organization",
            "type":"Services"
        }
    ],
    "sg:phone":"+1 601 859 5515",
    "sg:postcode":"39046",
    "sg:province":"MS",
    "wof:name":"Pleasant Grn Chrch Chrst Holns",
    "wof:placetype":"venue"
},
  "geometry": {"coordinates":[-90.048288,32.618451],"type":"Point"}
}