{
  "type": "Feature",
  "properties": {
    "addr:full":"802 S Cass St Corinth MS 38834",
    "addr:housenumber":"802",
    "addr:postcode":"38834",
    "addr:street":"S Cass St",
    "iso:country":"US",
    "sg:address":"802 S Cass St",
    "sg:city":"Corinth",
    "sg:classifiers":[
        {
            "category":"Shopping",
            "subcategory":"Books",
            "type":"Retail Goods"
        }
    ],
    "sg:phone":"+1 662 286 2335",
    "sg:postcode":"38834",
    "sg:province":"MS",
    "sg:tags":[
        "bookstore"
    ],
    "wof:name":"Books-A-Million",
    "wof:placetype":"venue"
},
  "geometry": {"coordinates":[-88.51803200000001,34.925475],"type":"Point"}
}