{
  "type": "Feature",
  "properties": {
    "addr:full":"721 Magnolia Dr Tupelo MS 38804",
    "addr:housenumber":"721",
    "addr:postcode":"38804",
    "addr:street":"Magnolia Dr",
    "iso:country":"US",
    "sg:address":"721 Magnolia Dr",
    "sg:city":"Tupelo",
    "sg:classifiers":[
        {
            "category":"Professional",
            "subcategory":"Engineering",
            "type":"Services"
        }
    ],
    "sg:phone":"+1 662 842 4349",
    "sg:postcode":"38804",
    "sg:province":"MS",
    "wof:name":"Container Engineering Corp",
    "wof:placetype":"venue"
},
  "geometry": {"coordinates":[-88.719331,34.269823],"type":"Point"}
}