{
  "type": "Feature",
  "properties": {
    "addr:full":"325 Hwy 12 E Kosciusko MS 39090",
    "addr:housenumber":"325",
    "addr:postcode":"39090",
    "addr:street":"Hwy 12 E",
    "iso:country":"US",
    "sg:address":"325 Hwy 12 E",
    "sg:city":"Kosciusko",
    "sg:classifiers":[
        {
            "category":"Parking",
            "type":"Transportation"
        }
    ],
    "sg:phone":"+1 662 289 1482",
    "sg:postcode":"39090",
    "sg:province":"MS",
    "sg:tags":[
        "garage"
    ],
    "wof:name":"County Of Attala",
    "wof:placetype":"venue"
},
  "geometry": {"coordinates":[-89.58562000000001,33.065863],"type":"Point"}
}