{
  "type": "Feature",
  "properties": {
    "iso:country":"US",
    "sg:address":"5989 Woodall Ln",
    "sg:city":"Liberty",
    "sg:classifiers":[
        {
            "category":"Farming",
            "subcategory":"Orchard",
            "type":"Manufacturing & Wholesale Goods"
        }
    ],
    "sg:phone":"+1 601 657 4720",
    "sg:postcode":"39645",
    "sg:province":"MS",
    "sg:tags":[
        "fruit",
        "tree"
    ],
    "wof:name":"Pin Oak Orchard",
    "wof:placetype":"venue"
},
  "geometry": {"coordinates":[-90.68408100000001,31.160776],"type":"Point"}
}