{
  "type": "Feature",
  "properties": {
    "addr:full":"3120 S Liberty St Canton MS 39046",
    "addr:housenumber":"3120",
    "addr:postcode":"39046",
    "addr:street":"S Liberty St",
    "iso:country":"US",
    "sg:address":"3120 S Liberty St",
    "sg:city":"Canton",
    "sg:classifiers":[
        {
            "category":"Government",
            "subcategory":"Office",
            "type":"Public Place"
        }
    ],
    "sg:phone":"+1 601 859 5747",
    "sg:postcode":"39046",
    "sg:province":"MS",
    "wof:name":"Madison County Meals On Wheels",
    "wof:placetype":"venue"
},
  "geometry": {"coordinates":[-90.03505699999999,32.60159],"type":"Point"}
}