{
  "type": "Feature",
  "properties": {
    "addr:full":"501 1st St S Columbus MS 39701",
    "addr:housenumber":"501",
    "addr:postcode":"39701",
    "addr:street":"1St St S",
    "iso:country":"US",
    "sg:address":"501 1st St S",
    "sg:city":"Columbus",
    "sg:classifiers":[
        {
            "category":"Professional",
            "subcategory":"Lawyer & Legal Services",
            "type":"Services"
        }
    ],
    "sg:phone":"+1 662 329 2231",
    "sg:postcode":"39701",
    "sg:province":"MS",
    "sg:tags":[
        "attorney"
    ],
    "wof:name":"Burdine Richard Law Office",
    "wof:placetype":"venue"
},
  "geometry": {"coordinates":[-88.43239,33.49057],"type":"Point"}
}