{
  "type": "Feature",
  "properties": {
    "addr:full":"5796 US Hwy 11 Purvis MS 39475",
    "addr:housenumber":"5796",
    "addr:postcode":"39475",
    "addr:street":"Us Hwy 11",
    "iso:country":"US",
    "sg:address":"5796 US Hwy 11",
    "sg:city":"Purvis",
    "sg:classifiers":[
        {
            "category":"Restaurant",
            "type":"Food & Drink"
        }
    ],
    "sg:phone":"+1 601 794 5511",
    "sg:postcode":"39475",
    "sg:province":"MS",
    "wof:name":"Subway Sandwiches & Salads",
    "wof:placetype":"venue"
},
  "geometry": {"coordinates":[-89.40441300000001,31.14443],"type":"Point"}
}