{
  "type": "Feature",
  "properties": {
    "addr:full":"145 W Brewer Ln Columbus MS 39701",
    "addr:housenumber":"145",
    "addr:postcode":"39701",
    "addr:street":"W Brewer Ln",
    "iso:country":"US",
    "sg:address":"145 W Brewer Ln",
    "sg:city":"Columbus",
    "sg:classifiers":[
        {
            "category":"Personal",
            "subcategory":"Beauty Salon",
            "type":"Services"
        }
    ],
    "sg:phone":"+1 662 244 8899",
    "sg:postcode":"39701",
    "sg:province":"MS",
    "wof:name":"Shirley Hair Care Scene",
    "wof:placetype":"venue"
},
  "geometry": {"coordinates":[-88.42638700000001,33.316141],"type":"Point"}
}