{
  "type": "Feature",
  "properties": {
    "iso:country":"US",
    "sg:address":"1804 Government St",
    "sg:city":"Ocean Springs",
    "sg:classifiers":[
        {
            "category":"Building & Trades",
            "subcategory":"Construction",
            "type":"Services"
        }
    ],
    "sg:phone":"+1 228 818 2455",
    "sg:postcode":"39564",
    "sg:province":"MS",
    "sg:tags":[
        "home",
        "builder"
    ],
    "wof:name":"Westminster Homes LLC",
    "wof:placetype":"venue"
},
  "geometry": {"coordinates":[-88.817036,30.413512],"type":"Point"}
}