{
  "type": "Feature",
  "properties": {
    "iso:country":"US",
    "sg:address":"2391 Lakeland Dr",
    "sg:city":"Flowood",
    "sg:classifiers":[
        {
            "category":"Food & Beverages",
            "subcategory":"Groceries & Convenience Stores",
            "type":"Retail Goods"
        }
    ],
    "sg:phone":"+1 601 939 6797",
    "sg:postcode":"39232",
    "sg:province":"MS",
    "wof:name":"Pantry",
    "wof:placetype":"venue"
},
  "geometry": {"coordinates":[-90.101185,32.333703],"type":"Point"}
}