{
  "type": "Feature",
  "properties": {
    "addr:full":"266 Dogwood Pl Flowood MS 39232",
    "addr:housenumber":"266",
    "addr:postcode":"39232",
    "addr:street":"Dogwood Pl",
    "iso:country":"US",
    "sg:address":"266 Dogwood Pl",
    "sg:city":"Flowood",
    "sg:classifiers":[
        {
            "category":"Wholesale",
            "subcategory":"Hardware",
            "type":"Manufacturing & Wholesale Goods"
        }
    ],
    "sg:phone":"+1 601 919 9942",
    "sg:postcode":"39232",
    "sg:province":"MS",
    "sg:tags":[
        "equipment",
        "energy",
        "solar"
    ],
    "wof:name":"Solar Nail",
    "wof:placetype":"venue"
},
  "geometry": {"coordinates":[-90.05095300000001,32.337846],"type":"Point"}
}