{
  "type": "Feature",
  "properties": {
    "addr:full":"118 Service Dr Brandon MS 39042",
    "addr:housenumber":"118",
    "addr:postcode":"39042",
    "addr:street":"Service Dr",
    "iso:country":"US",
    "sg:address":"118 Service Dr",
    "sg:city":"Brandon",
    "sg:classifiers":[
        {
            "category":"Personal",
            "subcategory":"Beauty Salon",
            "type":"Services"
        }
    ],
    "sg:phone":"+1 601 824 7413",
    "sg:postcode":"39042",
    "sg:province":"MS",
    "sg:tags":[
        "shop"
    ],
    "wof:name":"Looking Glass Salon",
    "wof:placetype":"venue"
},
  "geometry": {"coordinates":[-90.028745,32.283648],"type":"Point"}
}