{
  "type": "Feature",
  "properties": {
    "addr:full":"1512 25th Ave Meridian MS 39301",
    "addr:housenumber":"1512",
    "addr:postcode":"39301",
    "addr:street":"25Th Ave",
    "iso:country":"US",
    "sg:address":"1512 25th Ave",
    "sg:city":"Meridian",
    "sg:classifiers":[
        {
            "category":"Recreation",
            "type":"Entertainment"
        }
    ],
    "sg:phone":"+1 601 483 4710",
    "sg:postcode":"39301",
    "sg:province":"MS",
    "sg:tags":[
        "dance"
    ],
    "wof:name":"McCraw Suzie School of Dance",
    "wof:placetype":"venue"
},
  "geometry": {"coordinates":[-88.703616,32.372975],"type":"Point"}
}