{
  "type": "Feature",
  "properties": {
    "addr:full":"210 White Blvd Mccomb MS 39648",
    "addr:housenumber":"210",
    "addr:postcode":"39648",
    "addr:street":"White Blvd",
    "iso:country":"US",
    "sg:address":"210 White Blvd",
    "sg:city":"Mccomb",
    "sg:classifiers":[
        {
            "category":"Home & Garden",
            "subcategory":"Mobile Homes",
            "type":"Retail Goods"
        }
    ],
    "sg:phone":"+1 601 249 4882",
    "sg:postcode":"39648",
    "sg:province":"MS",
    "wof:name":"Bills Manufactured Homes Inc",
    "wof:placetype":"venue"
},
  "geometry": {"coordinates":[-90.44195999999999,31.231589],"type":"Point"}
}