{
  "type": "Feature",
  "properties": {
    "iso:country":"US",
    "sg:address":"200 S Jackson St",
    "sg:city":"Crystal Springs",
    "sg:classifiers":[
        {
            "category":"Education",
            "subcategory":"Library",
            "type":"Public Place"
        }
    ],
    "sg:phone":"+1 601 892 3205",
    "sg:postcode":"39059",
    "sg:province":"MS",
    "wof:name":"Crystal Springs Library",
    "wof:placetype":"venue"
},
  "geometry": {"coordinates":[-90.35737899999999,31.98603],"type":"Point"}
}