{
  "type": "Feature",
  "properties": {
    "addr:full":"1496 Old Aberdeen Rd Columbus MS 39705",
    "addr:housenumber":"1496",
    "addr:postcode":"39705",
    "addr:street":"Old Aberdeen Rd",
    "iso:country":"US",
    "sg:address":"1496 Old Aberdeen Rd",
    "sg:city":"Columbus",
    "sg:classifiers":[
        {
            "category":"Cinema",
            "subcategory":"Movie Rental",
            "type":"Entertainment"
        }
    ],
    "sg:phone":"+1 662 241 5126",
    "sg:postcode":"39705",
    "sg:province":"MS",
    "sg:tags":[
        "leasing",
        "video",
        "disc",
        "tape"
    ],
    "sg:website":"www.hollywoodvideo.com",
    "wof:name":"Hollywood Video",
    "wof:placetype":"venue"
},
  "geometry": {"coordinates":[-88.433193,33.51719],"type":"Point"}
}