{
  "type": "Feature",
  "properties": {
    "iso:country":"US",
    "sg:address":"8575 Hwy 51 N",
    "sg:city":"Southaven",
    "sg:classifiers":[
        {
            "category":"Retail",
            "subcategory":"Laundry & Dry Cleaning",
            "type":"Services"
        }
    ],
    "sg:phone":"+1 662 393 3535",
    "sg:postcode":"38671",
    "sg:province":"MS",
    "sg:tags":[
        "drycleaning",
        "plant",
        "cleaners"
    ],
    "wof:name":"Zing Parker Cleaners",
    "wof:placetype":"venue"
},
  "geometry": {"coordinates":[-90.01737,34.985735],"type":"Point"}
}