{
  "type": "Feature",
  "properties": {
    "iso:country":"US",
    "sg:address":"921 Maple Ave",
    "sg:city":"Heidelberg",
    "sg:classifiers":[
        {
            "category":"Social Services",
            "subcategory":"Child Care",
            "type":"Services"
        }
    ],
    "sg:phone":"+1 601 787 4638",
    "sg:postcode":"39439",
    "sg:province":"MS",
    "sg:tags":[
        "kindergarten",
        "academic",
        "school"
    ],
    "wof:name":"East Jasper Head Start",
    "wof:placetype":"venue"
},
  "geometry": {"coordinates":[-88.98796299999999,31.895809],"type":"Point"}
}