{
  "type": "Feature",
  "properties": {
    "addr:full":"1349 Cliff Gookin Blvd Tupelo MS 38801",
    "addr:housenumber":"1349",
    "addr:postcode":"38801",
    "addr:street":"Cliff Gookin Blvd",
    "iso:country":"US",
    "sg:address":"1349 Cliff Gookin Blvd",
    "sg:city":"Tupelo",
    "sg:classifiers":[
        {
            "category":"Manufacturing",
            "subcategory":"Printing",
            "type":"Manufacturing & Wholesale Goods"
        }
    ],
    "sg:phone":"+1 662 842 2725",
    "sg:postcode":"38801",
    "sg:province":"MS",
    "sg:tags":[
        "label"
    ],
    "sg:website":"www.weatherallprinting.com",
    "wof:name":"Pro Graphics",
    "wof:placetype":"venue"
},
  "geometry": {"coordinates":[-88.747827,34.224185],"type":"Point"}
}