{
  "type": "Feature",
  "properties": {
    "iso:country":"US",
    "sg:address":"30 Sgt Prentiss Dr",
    "sg:city":"Natchez",
    "sg:classifiers":[
        {
            "category":"Retail",
            "subcategory":"Laundry & Dry Cleaning",
            "type":"Services"
        }
    ],
    "sg:phone":"+1 601 442 8420",
    "sg:postcode":"39120",
    "sg:province":"MS",
    "sg:tags":[
        "drycleaning",
        "plant",
        "power",
        "cleaners"
    ],
    "wof:name":"Grace Cleaners and Laundry",
    "wof:placetype":"venue"
},
  "geometry": {"coordinates":[-91.38967100000001,31.522893],"type":"Point"}
}