{
  "type": "Feature",
  "properties": {
    "iso:country":"US",
    "sg:address":"4289 Hwy 9 S",
    "sg:city":"Pontotoc",
    "sg:classifiers":[
        {
            "category":"Manufacturing",
            "subcategory":"Furniture",
            "type":"Manufacturing & Wholesale Goods"
        }
    ],
    "sg:phone":"+1 662 489 2299",
    "sg:postcode":"38863",
    "sg:province":"MS",
    "wof:name":"R & M Furniture",
    "wof:placetype":"venue"
},
  "geometry": {"coordinates":[-89.08998,34.235967],"type":"Point"}
}