{
  "type": "Feature",
  "properties": {
    "addr:full":"1336 Highway 42 Petal MS 39465",
    "addr:housenumber":"1336",
    "addr:postcode":"39465",
    "addr:street":"Highway 42",
    "iso:country":"US",
    "sg:address":"1336 Highway 42",
    "sg:city":"Petal",
    "sg:classifiers":[
        {
            "category":"Health Services",
            "subcategory":"Dentist",
            "type":"Services"
        }
    ],
    "sg:phone":"+1 601 450 3371",
    "sg:postcode":"39465",
    "sg:province":"MS",
    "sg:website":"http://www.reynoldfamilydentistry.com",
    "wof:name":"Reynolds Family Dental Clinc",
    "wof:placetype":"venue"
},
  "geometry": {"coordinates":[-89.19063199999999,31.350719],"type":"Point"}
}