{
  "type": "Feature",
  "properties": {
    "iso:country":"US",
    "sg:address":"1672 Hwy 1 S",
    "sg:city":"Greenville",
    "sg:classifiers":[
        {
            "category":"Restaurant",
            "type":"Food & Drink"
        }
    ],
    "sg:phone":"+1 662 334 3018",
    "sg:postcode":"38701",
    "sg:province":"MS",
    "sg:tags":[
        "eating"
    ],
    "wof:name":"Noble Food Service Inc",
    "wof:placetype":"venue"
},
  "geometry": {"coordinates":[-91.039541,33.37551],"type":"Point"}
}