{
  "type": "Feature",
  "properties": {
    "iso:country":"US",
    "sg:address":"1214 Zentwood Rd",
    "sg:city":"Tupelo",
    "sg:classifiers":[
        {
            "category":"Insurance",
            "subcategory":"Insurance Agent",
            "type":"Services"
        }
    ],
    "sg:phone":"+1 662 680 7192",
    "sg:postcode":"38801",
    "sg:province":"MS",
    "wof:name":"Howling Wolf Creek Hunt Club",
    "wof:placetype":"venue"
},
  "geometry": {"coordinates":[-88.733058,34.232607],"type":"Point"}
}