{
  "type": "Feature",
  "properties": {
    "iso:country":"US",
    "sg:address":"835 S Wheatley St",
    "sg:city":"Ridgeland",
    "sg:classifiers":[
        {
            "category":"Restaurant",
            "type":"Food & Drink"
        }
    ],
    "sg:menulink":"http://www.allmenus.com/ms/mannsdale/72849-pizza-hut/menu/",
    "sg:phone":"+1 601 956 1000",
    "sg:postcode":"39157",
    "sg:province":"MS",
    "sg:tags":[
        "american",
        "pizza"
    ],
    "wof:name":"Pizza Hut",
    "wof:placetype":"venue"
},
  "geometry": {"coordinates":[-90.132141,32.40114],"type":"Point"}
}