{
  "type": "Feature",
  "properties": {
    "iso:country":"US",
    "sg:address":"187 Stateline Rd E",
    "sg:city":"Southaven",
    "sg:classifiers":[
        {
            "category":"Professional",
            "subcategory":"Accounting & Tax Preparation",
            "type":"Services"
        }
    ],
    "sg:phone":"+1 662 393 2200",
    "sg:postcode":"38671",
    "sg:province":"MS",
    "sg:tags":[
        "payroll"
    ],
    "wof:name":"Taxing Solutions LLC",
    "wof:placetype":"venue"
},
  "geometry": {"coordinates":[-89.985687,34.991745],"type":"Point"}
}