{
  "type": "Feature",
  "properties": {
    "iso:country":"US",
    "sg:address":"1903 Pass Rd",
    "sg:city":"Biloxi",
    "sg:classifiers":[
        {
            "category":"Real Estate",
            "subcategory":"Real Estate Agent",
            "type":"Services"
        }
    ],
    "sg:phone":"+1 228 388 6621",
    "sg:postcode":"39531",
    "sg:province":"MS",
    "wof:name":"Oak View Real Estate Rentals",
    "wof:placetype":"venue"
},
  "geometry": {"coordinates":[-88.953569,30.402711],"type":"Point"}
}