{
  "type": "Feature",
  "properties": {
    "iso:country":"US",
    "sg:address":"267 Byrnes Cir",
    "sg:city":"Columbus",
    "sg:classifiers":[
        {
            "category":"Organizations",
            "subcategory":"Religious Organization",
            "type":"Services"
        }
    ],
    "sg:phone":"+1 662 329 4823",
    "sg:postcode":"39701",
    "sg:province":"MS",
    "sg:tags":[
        "church"
    ],
    "wof:name":"Spirit Of Prayer Holiness Chr",
    "wof:placetype":"venue"
},
  "geometry": {"coordinates":[-88.399666,33.504403],"type":"Point"}
}