{
  "type": "Feature",
  "properties": {
    "iso:country":"US",
    "sg:address":"338 Bracey Rd",
    "sg:city":"Kokomo",
    "sg:classifiers":[
        {
            "category":"Personal",
            "type":"Services"
        }
    ],
    "sg:phone":"+1 601 736 4199",
    "sg:postcode":"39643",
    "sg:province":"MS",
    "wof:name":"Partyjumpers LLC",
    "wof:placetype":"venue"
},
  "geometry": {"coordinates":[-90.013991,31.296814],"type":"Point"}
}