{
  "type": "Feature",
  "properties": {
    "iso:country":"US",
    "sg:address":"766 Hwy 468",
    "sg:city":"Brandon",
    "sg:classifiers":[
        {
            "category":"Food & Beverages",
            "subcategory":"Groceries & Convenience Stores",
            "type":"Retail Goods"
        }
    ],
    "sg:phone":"+1 601 591 0988",
    "sg:postcode":"39042",
    "sg:province":"MS",
    "sg:tags":[
        "grocer"
    ],
    "wof:name":"Allens Food Store Inc",
    "wof:placetype":"venue"
},
  "geometry": {"coordinates":[-90.035174,32.225229],"type":"Point"}
}