{
  "type": "Feature",
  "properties": {
    "addr:full":"741 Gather Johnson Rd Magee MS 39111",
    "addr:housenumber":"741",
    "addr:postcode":"39111",
    "addr:street":"Gather Johnson Rd",
    "iso:country":"US",
    "sg:address":"741 Gather Johnson Rd",
    "sg:city":"Magee",
    "sg:classifiers":[
        {
            "category":"Real Estate",
            "subcategory":"Surveying",
            "type":"Services"
        }
    ],
    "sg:phone":"+1 601 849 9279",
    "sg:postcode":"39111",
    "sg:province":"MS",
    "wof:name":"Warren Brothers Survey",
    "wof:placetype":"venue"
},
  "geometry": {"coordinates":[-89.6703,31.952309],"type":"Point"}
}