{
  "type": "Feature",
  "properties": {
    "iso:country":"US",
    "sg:address":"55 Belisle Dr",
    "sg:city":"Southaven",
    "sg:classifiers":[
        {
            "category":"Insurance",
            "subcategory":"Insurance Agent",
            "type":"Services"
        }
    ],
    "sg:phone":"+1 662 536 3597",
    "sg:postcode":"38671",
    "sg:province":"MS",
    "wof:name":"Proactive Insurance Adjusters",
    "wof:placetype":"venue"
},
  "geometry": {"coordinates":[-89.988653,34.939752],"type":"Point"}
}