{
  "type": "Feature",
  "properties": {
    "iso:country":"US",
    "sg:address":"5244 Hwy 42",
    "sg:city":"Hattiesburg",
    "sg:classifiers":[
        {
            "category":"Professional",
            "type":"Services"
        }
    ],
    "sg:phone":"+1 601 583 8691",
    "sg:postcode":"39401",
    "sg:province":"MS",
    "wof:name":"Bo's Towing Svc",
    "wof:placetype":"venue"
},
  "geometry": {"coordinates":[-89.33531000000001,31.348105],"type":"Point"}
}