{
  "type": "Feature",
  "properties": {
    "addr:full":"517 E Leake St Clinton MS 39056",
    "addr:housenumber":"517",
    "addr:postcode":"39056",
    "addr:street":"E Leake St",
    "iso:country":"US",
    "sg:address":"517 E Leake St",
    "sg:city":"Clinton",
    "sg:classifiers":[
        {
            "category":"Building & Trades",
            "subcategory":"Construction",
            "type":"Services"
        }
    ],
    "sg:phone":"+1 601 932 5913",
    "sg:postcode":"39056",
    "sg:province":"MS",
    "sg:tags":[
        "hanging",
        "contractor"
    ],
    "wof:name":"Paper Works",
    "wof:placetype":"venue"
},
  "geometry": {"coordinates":[-90.320888,32.340448],"type":"Point"}
}