{
  "type": "Feature",
  "properties": {
    "iso:country":"US",
    "sg:address":"513 Highway 45 N",
    "sg:city":"Booneville",
    "sg:classifiers":[
        {
            "category":"Restaurant",
            "type":"Food & Drink"
        }
    ],
    "sg:menulink":"http://www.allmenus.com/ms/booneville/183196-kfc---kentucky-fried-chicken/menu/",
    "sg:phone":"+1 601 728 3135",
    "sg:postcode":"38829",
    "sg:province":"MS",
    "sg:tags":[
        "american",
        "chicken"
    ],
    "wof:name":"KFC - Kentucky Fried Chicken",
    "wof:placetype":"venue"
},
  "geometry": {"coordinates":[-88.555115,34.700343],"type":"Point"}
}