{
  "type": "Feature",
  "properties": {
    "addr:full":"4623 Meadow Ridge Dr Jackson MS 39206",
    "addr:housenumber":"4623",
    "addr:postcode":"39206",
    "addr:street":"Meadow Ridge Dr",
    "iso:country":"US",
    "sg:address":"4623 Meadow Ridge Dr",
    "sg:city":"Jackson",
    "sg:classifiers":[
        {
            "category":"Education",
            "subcategory":"Special Training",
            "type":"Public Place"
        }
    ],
    "sg:phone":"+1 601 987 0140",
    "sg:postcode":"39206",
    "sg:province":"MS",
    "wof:name":"Geissenger Studio of Music",
    "wof:placetype":"venue"
},
  "geometry": {"coordinates":[-90.167483,32.358224],"type":"Point"}
}