{
  "type": "Feature",
  "properties": {
    "iso:country":"US",
    "sg:address":"15412 Lemoyne Blvd",
    "sg:city":"Biloxi",
    "sg:classifiers":[
        {
            "category":"Food & Beverages",
            "subcategory":"Groceries & Convenience Stores",
            "type":"Retail Goods"
        }
    ],
    "sg:phone":"+1 228 392 0070",
    "sg:postcode":"39532",
    "sg:province":"MS",
    "wof:name":"Saint Martin Qwik Market",
    "wof:placetype":"venue"
},
  "geometry": {"coordinates":[-88.867959,30.443102],"type":"Point"}
}