{
  "type": "Feature",
  "properties": {
    "addr:full":"1074 Hwy 51 Mccomb MS 39648",
    "addr:housenumber":"1074",
    "addr:postcode":"39648",
    "addr:street":"Hwy 51",
    "iso:country":"US",
    "sg:address":"1074 Hwy 51",
    "sg:city":"Mccomb",
    "sg:classifiers":[
        {
            "category":"Building & Trades",
            "subcategory":"Plumbing",
            "type":"Services"
        }
    ],
    "sg:phone":"+1 601 684 4774",
    "sg:postcode":"39648",
    "sg:province":"MS",
    "sg:tags":[
        "plumbing",
        "contractor"
    ],
    "wof:name":"Marsalis Mechanical Contrs Inc",
    "wof:placetype":"venue"
},
  "geometry": {"coordinates":[-90.451515,31.231197],"type":"Point"}
}