{
  "type": "Feature",
  "properties": {
    "addr:full":"307 Courthouse Rd Gulfport MS 39507",
    "addr:housenumber":"307",
    "addr:postcode":"39507",
    "addr:street":"Courthouse Rd",
    "iso:country":"US",
    "sg:address":"307 Courthouse Rd",
    "sg:city":"Gulfport",
    "sg:classifiers":[
        {
            "category":"Wholesale",
            "subcategory":"Stationery",
            "type":"Manufacturing & Wholesale Goods"
        }
    ],
    "sg:phone":"+1 228 864 1770",
    "sg:postcode":"39507",
    "sg:province":"MS",
    "sg:tags":[
        "product",
        "paper"
    ],
    "wof:name":"Newell Paper Co",
    "wof:placetype":"venue"
},
  "geometry": {"coordinates":[-89.04409200000001,30.382145],"type":"Point"}
}