{
  "type": "Feature",
  "properties": {
    "iso:country":"US",
    "sg:address":"11337 Gould Rd",
    "sg:city":"Gulfport",
    "sg:classifiers":[
        {
            "category":"Real Estate",
            "subcategory":"Real Estate Operator",
            "type":"Services"
        }
    ],
    "sg:phone":"+1 228 832 3708",
    "sg:postcode":"39503",
    "sg:province":"MS",
    "sg:tags":[
        "apartment"
    ],
    "wof:name":"Sand Hill Village Apartment",
    "wof:placetype":"venue"
},
  "geometry": {"coordinates":[-89.022943,30.451656],"type":"Point"}
}