{
  "type": "Feature",
  "properties": {
    "addr:full":"7083 Commerce Dr Olive Branch MS 38654",
    "addr:housenumber":"7083",
    "addr:postcode":"38654",
    "addr:street":"Commerce Dr",
    "iso:country":"US",
    "sg:address":"7083 Commerce Dr",
    "sg:city":"Olive Branch",
    "sg:classifiers":[
        {
            "category":"Retail",
            "subcategory":"Auto Repair",
            "type":"Services"
        }
    ],
    "sg:phone":"+1 662 890 4625",
    "sg:postcode":"38654",
    "sg:province":"MS",
    "sg:tags":[
        "repairing",
        "automobile"
    ],
    "wof:name":"Muffler Express",
    "wof:placetype":"venue"
},
  "geometry": {"coordinates":[-89.85623099999999,34.965199],"type":"Point"}
}