{
  "type": "Feature",
  "properties": {
    "iso:country":"US",
    "sg:address":"114 Hwy 30 E",
    "sg:city":"Oxford",
    "sg:classifiers":[
        {
            "category":"Professional",
            "subcategory":"Accounting & Tax Preparation",
            "type":"Services"
        }
    ],
    "sg:phone":"+1 662 234 5224",
    "sg:postcode":"38655",
    "sg:province":"MS",
    "sg:tags":[
        "accountant"
    ],
    "wof:name":"Kerry G King CPA",
    "wof:placetype":"venue"
},
  "geometry": {"coordinates":[-89.472548,34.385975],"type":"Point"}
}