{
  "type": "Feature",
  "properties": {
    "iso:country":"US",
    "sg:address":"1640 S Gallatin St",
    "sg:city":"Jackson",
    "sg:classifiers":[
        {
            "category":"Wholesale",
            "subcategory":"Machinery & Supplies",
            "type":"Manufacturing & Wholesale Goods"
        }
    ],
    "sg:phone":"+1 601 948 5103",
    "sg:postcode":"39201",
    "sg:province":"MS",
    "sg:tags":[
        "compressor",
        "gas"
    ],
    "wof:name":"Dixie Compressor Systems Inc",
    "wof:placetype":"venue"
},
  "geometry": {"coordinates":[-90.192955,32.281777],"type":"Point"}
}