{
  "type": "Feature",
  "properties": {
    "iso:country":"US",
    "sg:address":"4 Old Prentiss Hwy W",
    "sg:city":"Natchez",
    "sg:classifiers":[
        {
            "category":"Personal",
            "subcategory":"Beauty Salon",
            "type":"Services"
        }
    ],
    "sg:phone":"+1 601 442 8787",
    "sg:postcode":"39120",
    "sg:province":"MS",
    "wof:name":"Judy's Hair Salon",
    "wof:placetype":"venue"
},
  "geometry": {"coordinates":[-91.38633,31.51755],"type":"Point"}
}