{
  "type": "Feature",
  "properties": {
    "iso:country":"US",
    "sg:address":"365 Allstate Dr",
    "sg:city":"Jackson",
    "sg:classifiers":[
        {
            "category":"Building & Trades",
            "subcategory":"Cleaning & Sanitation",
            "type":"Services"
        }
    ],
    "sg:phone":"+1 601 918 8408",
    "sg:postcode":"39211",
    "sg:province":"MS",
    "sg:tags":[
        "janitorial",
        "sales"
    ],
    "wof:name":"B-Enterprise Omniclean Jantr",
    "wof:placetype":"venue"
},
  "geometry": {"coordinates":[-90.11919399999999,32.372167],"type":"Point"}
}