{
  "type": "Feature",
  "properties": {
    "iso:country":"US",
    "sg:address":"1360 Nesbit Rd",
    "sg:city":"Hernando",
    "sg:classifiers":[
        {
            "category":"Education",
            "subcategory":"School",
            "type":"Public Place"
        }
    ],
    "sg:phone":"+1 662 429 8424",
    "sg:postcode":"38651",
    "sg:province":"MS",
    "wof:name":"St Michaels Community Home",
    "wof:placetype":"venue"
},
  "geometry": {"coordinates":[-90.01625,34.887415],"type":"Point"}
}