{
  "type": "Feature",
  "properties": {
    "addr:full":"12186 US Hwy 49 Gulfport MS 39503",
    "addr:housenumber":"12186",
    "addr:postcode":"39503",
    "addr:street":"Us Hwy 49",
    "iso:country":"US",
    "sg:address":"12186 US Hwy 49",
    "sg:city":"Gulfport",
    "sg:classifiers":[
        {
            "category":"Cinema",
            "subcategory":"Movie Rental",
            "type":"Entertainment"
        }
    ],
    "sg:phone":"+1 228 832 9010",
    "sg:postcode":"39503",
    "sg:province":"MS",
    "sg:tags":[
        "video",
        "tape"
    ],
    "wof:name":"Video USA 45",
    "wof:placetype":"venue"
},
  "geometry": {"coordinates":[-89.10139700000001,30.463592],"type":"Point"}
}