{
  "type": "Feature",
  "properties": {
    "iso:country":"US",
    "sg:address":"116 N 2nd St",
    "sg:city":"Wiggins",
    "sg:classifiers":[
        {
            "category":"Shopping",
            "subcategory":"Department Store",
            "type":"Retail Goods"
        }
    ],
    "sg:phone":"+1 601 928 5051",
    "sg:postcode":"39577",
    "sg:province":"MS",
    "wof:name":"Freds",
    "wof:placetype":"venue"
},
  "geometry": {"coordinates":[-89.13572499999999,30.86014],"type":"Point"}
}