{
  "type": "Feature",
  "properties": {
    "addr:full":"989 Townsend Dr SE Brookhaven MS 39601",
    "addr:housenumber":"989",
    "addr:postcode":"39601",
    "addr:street":"Townsend Dr Se",
    "iso:country":"US",
    "sg:address":"989 Townsend Dr SE",
    "sg:city":"Brookhaven",
    "sg:classifiers":[
        {
            "category":"Organizations",
            "subcategory":"Religious Organization",
            "type":"Services"
        }
    ],
    "sg:phone":"+1 601 833 2169",
    "sg:postcode":"39601",
    "sg:province":"MS",
    "sg:tags":[
        "church"
    ],
    "wof:name":"Harmony Baptist Church",
    "wof:placetype":"venue"
},
  "geometry": {"coordinates":[-90.269498,31.502832],"type":"Point"}
}