{
  "type": "Feature",
  "properties": {
    "iso:country":"US",
    "sg:address":"494 W Bankhead St",
    "sg:city":"New Albany",
    "sg:classifiers":[
        {
            "category":"Sports & Exercise",
            "subcategory":"Gym",
            "type":"Entertainment"
        }
    ],
    "sg:phone":"+1 662 539 6001",
    "sg:postcode":"38652",
    "sg:province":"MS",
    "sg:tags":[
        "club",
        "health",
        "studio",
        "gymnasium"
    ],
    "wof:name":"Curves For Women",
    "wof:placetype":"venue"
},
  "geometry": {"coordinates":[-89.01984400000001,34.496309],"type":"Point"}
}