{
  "type": "Feature",
  "properties": {
    "iso:country":"US",
    "sg:address":"110 W Jackson St",
    "sg:city":"Belzoni",
    "sg:classifiers":[
        {
            "category":"Shopping",
            "subcategory":"Bicycles & Sporting Goods",
            "type":"Retail Goods"
        }
    ],
    "sg:phone":"+1 662 247 2845",
    "sg:postcode":"39038",
    "sg:province":"MS",
    "sg:tags":[
        "beverage",
        "alcoholic"
    ],
    "wof:name":"Hoop Store Inc",
    "wof:placetype":"venue"
},
  "geometry": {"coordinates":[-90.489789,33.177605],"type":"Point"}
}