{
  "type": "Feature",
  "properties": {
    "iso:country":"US",
    "sg:address":"194 Mandarin Dr",
    "sg:city":"Brandon",
    "sg:classifiers":[
        {
            "category":"Building & Trades",
            "subcategory":"Pest Control",
            "type":"Services"
        }
    ],
    "sg:phone":"+1 601 829 4299",
    "sg:postcode":"39047",
    "sg:province":"MS",
    "wof:name":"Pro Maintenance Inc",
    "wof:placetype":"venue"
},
  "geometry": {"coordinates":[-90.01974800000001,32.414745],"type":"Point"}
}