{
  "type": "Feature",
  "properties": {
    "iso:country":"US",
    "sg:address":"3405 Barb Ave",
    "sg:city":"Pascagoula",
    "sg:classifiers":[
        {
            "category":"Retail",
            "subcategory":"Auto Repair",
            "type":"Services"
        }
    ],
    "sg:phone":"+1 228 762 2558",
    "sg:postcode":"39581",
    "sg:province":"MS",
    "sg:tags":[
        "general"
    ],
    "wof:name":"Krebes Auto Repair",
    "wof:placetype":"venue"
},
  "geometry": {"coordinates":[-88.52676200000001,30.367668],"type":"Point"}
}