{
  "type": "Feature",
  "properties": {
    "addr:full":"1102 N 2nd St Booneville MS 38829",
    "addr:housenumber":"1102",
    "addr:postcode":"38829",
    "addr:street":"N 2Nd St",
    "iso:country":"US",
    "sg:address":"1102 N 2nd St",
    "sg:city":"Booneville",
    "sg:classifiers":[
        {
            "category":"Banks & Credit Unions",
            "subcategory":"Bank",
            "type":"Services"
        }
    ],
    "sg:phone":"+1 601 728 9467",
    "sg:postcode":"38829",
    "sg:province":"MS",
    "sg:tags":[
        "national",
        "commercial"
    ],
    "wof:name":"Deposit Guaranty National Bank",
    "wof:placetype":"venue"
},
  "geometry": {"coordinates":[-88.560343,34.680207],"type":"Point"}
}