{
  "type": "Feature",
  "properties": {
    "addr:full":"1783 Hwy 503 Paulding MS 39348",
    "addr:housenumber":"1783",
    "addr:postcode":"39348",
    "addr:street":"Hwy 503 Paulding",
    "iso:country":"US",
    "sg:address":"1783 Hwy 503",
    "sg:city":"Paulding",
    "sg:classifiers":[
        {
            "category":"Government",
            "subcategory":"Post Office",
            "type":"Public Place"
        }
    ],
    "sg:phone":"+1 601 727 9850",
    "sg:postcode":"39348",
    "sg:province":"MS",
    "wof:name":"US Post Office",
    "wof:placetype":"venue"
},
  "geometry": {"coordinates":[-89.03473,32.0394],"type":"Point"}
}