{
  "type": "Feature",
  "properties": {
    "addr:full":"12330 Ashley Dr Gulfport MS 39503",
    "addr:housenumber":"12330",
    "addr:postcode":"39503",
    "addr:street":"Ashley Dr",
    "iso:country":"US",
    "sg:address":"12330 Ashley Dr",
    "sg:city":"Gulfport",
    "sg:classifiers":[
        {
            "category":"Health Services",
            "subcategory":"Doctor",
            "type":"Services"
        }
    ],
    "sg:phone":"+1 228 831 1572",
    "sg:postcode":"39503",
    "sg:province":"MS",
    "sg:tags":[
        "clinic"
    ],
    "wof:name":"Orange Grove Family Medical",
    "wof:placetype":"venue"
},
  "geometry": {"coordinates":[-89.09990999999999,30.461949],"type":"Point"}
}