{
  "type": "Feature",
  "properties": {
    "iso:country":"US",
    "sg:address":"1550 Hwy 35 S",
    "sg:city":"Forest",
    "sg:classifiers":[
        {
            "category":"Professional",
            "type":"Services"
        }
    ],
    "sg:phone":"+1 601 469 2029",
    "sg:postcode":"39074",
    "sg:province":"MS",
    "sg:tags":[
        "establishment"
    ],
    "wof:name":"Atxtree",
    "wof:placetype":"venue"
},
  "geometry": {"coordinates":[-89.483296,32.339804],"type":"Point"}
}