{
  "type": "Feature",
  "properties": {
    "addr:full":"3188 E Northside Dr Jackson MS 39213",
    "addr:housenumber":"3188",
    "addr:postcode":"39213",
    "addr:street":"E Northside Dr",
    "iso:country":"US",
    "sg:address":"3188 E Northside Dr",
    "sg:city":"Jackson",
    "sg:classifiers":[
        {
            "category":"Banks & Credit Unions",
            "subcategory":"Bank",
            "type":"Services"
        }
    ],
    "sg:phone":"+1 601 982 1047",
    "sg:postcode":"39213",
    "sg:province":"MS",
    "sg:tags":[
        "depository",
        "banking",
        "check",
        "cashing"
    ],
    "wof:name":"Express Check Advance",
    "wof:placetype":"venue"
},
  "geometry": {"coordinates":[-90.22747099999999,32.356086],"type":"Point"}
}