{
  "type": "Feature",
  "properties": {
    "iso:country":"US",
    "sg:address":"33 Avery Cir",
    "sg:city":"Jackson",
    "sg:classifiers":[
        {
            "category":"Professional",
            "type":"Services"
        }
    ],
    "sg:phone":"+1 601 956 3065",
    "sg:postcode":"39211",
    "sg:province":"MS",
    "wof:name":"Go Services Inc",
    "wof:placetype":"venue"
},
  "geometry": {"coordinates":[-90.115427,32.39722],"type":"Point"}
}