{
  "type": "Feature",
  "properties": {
    "addr:full":"11 Cedar Ln Natchez MS 39120",
    "addr:housenumber":"11",
    "addr:postcode":"39120",
    "addr:street":"Cedar Ln",
    "iso:country":"US",
    "sg:address":"11 Cedar Ln",
    "sg:city":"Natchez",
    "sg:classifiers":[
        {
            "category":"Government",
            "subcategory":"Office",
            "type":"Public Place"
        }
    ],
    "sg:phone":"+1 601 445 9062",
    "sg:postcode":"39120",
    "sg:province":"MS",
    "sg:tags":[
        "govt",
        "city"
    ],
    "wof:name":"Natchez Water Works Plant",
    "wof:placetype":"venue"
},
  "geometry": {"coordinates":[-91.341289,31.587567],"type":"Point"}
}