{
  "type": "Feature",
  "properties": {
    "addr:full":"1513 N Magnolia Dr Wiggins MS 39577",
    "addr:housenumber":"1513",
    "addr:postcode":"39577",
    "addr:street":"N Magnolia Dr",
    "iso:country":"US",
    "sg:address":"1513 N Magnolia Dr",
    "sg:city":"Wiggins",
    "sg:classifiers":[
        {
            "category":"Manufacturing",
            "subcategory":"Wood Products",
            "type":"Manufacturing & Wholesale Goods"
        }
    ],
    "sg:phone":"+1 601 928 7026",
    "sg:postcode":"39577",
    "sg:province":"MS",
    "wof:name":"Carpenter's Pole & Piling",
    "wof:placetype":"venue"
},
  "geometry": {"coordinates":[-89.161311,30.879668],"type":"Point"}
}