{
  "type": "Feature",
  "properties": {
    "iso:country":"US",
    "sg:address":"5348 Old Byram Rd",
    "sg:city":"Byram",
    "sg:classifiers":[
        {
            "category":"Building & Trades",
            "subcategory":"Plumbing",
            "type":"Services"
        }
    ],
    "sg:phone":"+1 601 371 7273",
    "sg:postcode":"39272",
    "sg:province":"MS",
    "sg:tags":[
        "plumbing",
        "contractor"
    ],
    "wof:name":"B's Plumbing Svc",
    "wof:placetype":"venue"
},
  "geometry": {"coordinates":[-90.23657,32.195535],"type":"Point"}
}