{
  "type": "Feature",
  "properties": {
    "iso:country":"US",
    "sg:address":"3600 Bluecutt Rd",
    "sg:city":"Columbus",
    "sg:classifiers":[
        {
            "category":"Professional",
            "subcategory":"Detective & Security Services",
            "type":"Services"
        }
    ],
    "sg:phone":"+1 662 328 4100",
    "sg:postcode":"39705",
    "sg:province":"MS",
    "sg:tags":[
        "guard",
        "patrol"
    ],
    "sg:website":"www.geminisecurityinc.com",
    "wof:name":"Gemini Security Inc",
    "wof:placetype":"venue"
},
  "geometry": {"coordinates":[-88.416616,33.517075],"type":"Point"}
}