{
  "type": "Feature",
  "properties": {
    "iso:country":"US",
    "sg:address":"5901 Hwy 569 N",
    "sg:city":"Smithdale",
    "sg:classifiers":[
        {
            "category":"Organizations",
            "subcategory":"Religious Organization",
            "type":"Services"
        }
    ],
    "sg:phone":"+1 601 567 9700",
    "sg:postcode":"39664",
    "sg:province":"MS",
    "sg:tags":[
        "church"
    ],
    "wof:name":"Goodhope FWB",
    "wof:placetype":"venue"
},
  "geometry": {"coordinates":[-90.692229,31.273653],"type":"Point"}
}