{
  "type": "Feature",
  "properties": {
    "iso:country":"US",
    "sg:address":"214 George St",
    "sg:city":"Greenwood",
    "sg:classifiers":[
        {
            "category":"Insurance",
            "subcategory":"Insurance Agent",
            "type":"Services"
        }
    ],
    "sg:phone":"+1 662 453 1111",
    "sg:postcode":"38930",
    "sg:province":"MS",
    "wof:name":"Clark Insurance",
    "wof:placetype":"venue"
},
  "geometry": {"coordinates":[-90.179239,33.521007],"type":"Point"}
}