{
  "type": "Feature",
  "properties": {
    "iso:country":"US",
    "sg:address":"334 First Hopewell Rd",
    "sg:city":"Sumrall",
    "sg:classifiers":[
        {
            "category":"Building & Trades",
            "subcategory":"Construction",
            "type":"Services"
        }
    ],
    "sg:phone":"+1 601 584 9090",
    "sg:postcode":"39482",
    "sg:province":"MS",
    "sg:tags":[
        "residential"
    ],
    "wof:name":"Able Consturction Services",
    "wof:placetype":"venue"
},
  "geometry": {"coordinates":[-89.657342,31.338721],"type":"Point"}
}