{
  "type": "Feature",
  "properties": {
    "iso:country":"US",
    "sg:address":"3002 Market St",
    "sg:city":"Pascagoula",
    "sg:classifiers":[
        {
            "category":"Food & Beverages",
            "subcategory":"Liquor & Beverages",
            "type":"Retail Goods"
        }
    ],
    "sg:phone":"+1 228 762 3874",
    "sg:postcode":"39567",
    "sg:province":"MS",
    "wof:name":"Liquors Unlimited",
    "wof:placetype":"venue"
},
  "geometry": {"coordinates":[-88.548458,30.365087],"type":"Point"}
}