{
  "type": "Feature",
  "properties": {
    "iso:country":"US",
    "sg:address":"1391 W Jackson St",
    "sg:city":"Tupelo",
    "sg:classifiers":[
        {
            "category":"Food & Beverages",
            "subcategory":"Groceries & Convenience Stores",
            "type":"Retail Goods"
        }
    ],
    "sg:phone":"+1 662 844 1594",
    "sg:postcode":"38801",
    "sg:province":"MS",
    "wof:name":"Chevron One Stop 5",
    "wof:placetype":"venue"
},
  "geometry": {"coordinates":[-88.734898,34.264714],"type":"Point"}
}