{
  "type": "Feature",
  "properties": {
    "iso:country":"US",
    "sg:address":"3405 Pemberton Square Blvd",
    "sg:city":"Vicksburg",
    "sg:classifiers":[
        {
            "category":"Food & Beverages",
            "subcategory":"Groceries & Convenience Stores",
            "type":"Retail Goods"
        },
        {
            "category":"Shopping",
            "subcategory":"Pharmacy",
            "type":"Retail Goods"
        }
    ],
    "sg:phone":"+1 601 638 3251",
    "sg:postcode":"39180",
    "sg:province":"MS",
    "sg:tags":[
        "prod",
        "mfg"
    ],
    "wof:name":"Kroger",
    "wof:placetype":"venue"
},
  "geometry": {"coordinates":[-90.88060900000001,32.31442],"type":"Point"}
}