{
  "type": "Feature",
  "properties": {
    "addr:full":"1729 S Azalea Dr Wiggins MS 39577",
    "addr:housenumber":"1729",
    "addr:postcode":"39577",
    "addr:street":"S Azalea Dr",
    "iso:country":"US",
    "sg:address":"1729 S Azalea Dr",
    "sg:city":"Wiggins",
    "sg:classifiers":[
        {
            "category":"Autos & Motor Vehicles",
            "subcategory":"Auto Supplies",
            "type":"Retail Goods"
        }
    ],
    "sg:phone":"+1 601 928 4674",
    "sg:postcode":"39577",
    "sg:province":"MS",
    "sg:tags":[
        "parts"
    ],
    "wof:name":"Parts Place",
    "wof:placetype":"venue"
},
  "geometry": {"coordinates":[-89.13681099999999,30.830937],"type":"Point"}
}