{
  "type": "Feature",
  "properties": {
    "iso:country":"US",
    "sg:address":"3173 Greenfield Rd",
    "sg:city":"Pearl",
    "sg:classifiers":[
        {
            "category":"Wholesale",
            "subcategory":"Auto Parts",
            "type":"Manufacturing & Wholesale Goods"
        }
    ],
    "sg:phone":"+1 601 420 8500",
    "sg:postcode":"39208",
    "sg:province":"MS",
    "sg:tags":[
        "automotive",
        "repair",
        "tire",
        "supply"
    ],
    "wof:name":"Tech Tire Supply",
    "wof:placetype":"venue"
},
  "geometry": {"coordinates":[-90.036232,32.274954],"type":"Point"}
}