{
  "type": "Feature",
  "properties": {
    "iso:country":"US",
    "sg:address":"215 S Pearl St",
    "sg:city":"Natchez",
    "sg:classifiers":[
        {
            "category":"Travel",
            "subcategory":"Travel Agent",
            "type":"Entertainment"
        },
        {
            "category":"Organizations",
            "subcategory":"Community Association",
            "type":"Services"
        }
    ],
    "sg:phone":"+1 601 443 9065",
    "sg:postcode":"39120",
    "sg:province":"MS",
    "sg:tags":[
        "club",
        "operator",
        "tour",
        "membership"
    ],
    "wof:name":"Natchez Garden Club Inc",
    "wof:placetype":"venue"
},
  "geometry": {"coordinates":[-91.40424400000001,31.559],"type":"Point"}
}