{
  "type": "Feature",
  "properties": {
    "iso:country":"US",
    "sg:address":"45 River Bend Dr",
    "sg:city":"Brandon",
    "sg:classifiers":[
        {
            "category":"Building & Trades",
            "subcategory":"Plumbing",
            "type":"Services"
        }
    ],
    "sg:phone":"+1 601 591 5642",
    "sg:postcode":"39042",
    "sg:province":"MS",
    "sg:tags":[
        "contractor"
    ],
    "wof:name":"Southern Air",
    "wof:placetype":"venue"
},
  "geometry": {"coordinates":[-90.01505899999999,32.328379],"type":"Point"}
}