{
  "type": "Feature",
  "properties": {
    "iso:country":"US",
    "sg:address":"1000 Turtle Creek Dr",
    "sg:city":"Hattiesburg",
    "sg:classifiers":[
        {
            "category":"Shopping",
            "subcategory":"Clothing, Apparel, & Fashions",
            "type":"Retail Goods"
        }
    ],
    "sg:phone":"+1 601 268 9410",
    "sg:postcode":"39402",
    "sg:province":"MS",
    "wof:name":"Limited The",
    "wof:placetype":"venue"
},
  "geometry": {"coordinates":[-89.3762,31.330083],"type":"Point"}
}