{
  "type": "Feature",
  "properties": {
    "addr:full":"449 Ash Washington Rd Columbus MS 39743",
    "addr:housenumber":"449",
    "addr:postcode":"39743",
    "addr:street":"Ash Washington Rd",
    "iso:country":"US",
    "sg:address":"449 Ash Washington Rd",
    "sg:city":"Columbus",
    "sg:classifiers":[
        {
            "category":"Building & Trades",
            "subcategory":"Construction",
            "type":"Services"
        }
    ],
    "sg:phone":"+1 662 425 8700",
    "sg:postcode":"39743",
    "sg:province":"MS",
    "sg:tags":[
        "general",
        "contractor"
    ],
    "wof:name":"R&H Remodeling Services Inc",
    "wof:placetype":"venue"
},
  "geometry": {"coordinates":[-88.58953700000001,33.356658],"type":"Point"}
}