{
  "type": "Feature",
  "properties": {
    "addr:full":"375 N Ruby Ave Ruleville MS 38771",
    "addr:housenumber":"375",
    "addr:postcode":"38771",
    "addr:street":"N Ruby Ave",
    "iso:country":"US",
    "sg:address":"375 N Ruby Ave",
    "sg:city":"Ruleville",
    "sg:classifiers":[
        {
            "category":"Health Services",
            "subcategory":"Doctor",
            "type":"Services"
        }
    ],
    "sg:phone":"+1 662 756 2249",
    "sg:postcode":"38771",
    "sg:province":"MS",
    "sg:tags":[
        "medical"
    ],
    "wof:name":"Greenvlle Nrosugical Clinic PA",
    "wof:placetype":"venue"
},
  "geometry": {"coordinates":[-90.548885,33.731027],"type":"Point"}
}