{
  "type": "Feature",
  "properties": {
    "iso:country":"US",
    "sg:address":"650 E Peace St",
    "sg:city":"Canton",
    "sg:classifiers":[
        {
            "category":"Utilities",
            "subcategory":"Water",
            "type":"Services"
        }
    ],
    "sg:phone":"+1 601 859 2810",
    "sg:postcode":"39046",
    "sg:province":"MS",
    "sg:tags":[
        "company",
        "sewage"
    ],
    "wof:name":"East Madison Water Assn",
    "wof:placetype":"venue"
},
  "geometry": {"coordinates":[-90.017929,32.613024],"type":"Point"}
}