{
  "type": "Feature",
  "properties": {
    "iso:country":"US",
    "sg:address":"404 Lake Ave",
    "sg:city":"Pascagoula",
    "sg:classifiers":[
        {
            "category":"Food & Beverages",
            "subcategory":"Meat & Fish",
            "type":"Retail Goods"
        }
    ],
    "sg:phone":"+1 228 762 6852",
    "sg:postcode":"39567",
    "sg:province":"MS",
    "sg:tags":[
        "seafood"
    ],
    "wof:name":"O'Sullivan & Son's Seafood Co",
    "wof:placetype":"venue"
},
  "geometry": {"coordinates":[-88.560221,30.377616],"type":"Point"}
}