{
  "type": "Feature",
  "properties": {
    "iso:country":"US",
    "sg:address":"8110 Camp Creek Rd",
    "sg:city":"Olive Branch",
    "sg:classifiers":[
        {
            "category":"Retail",
            "subcategory":"Auto Rental",
            "type":"Services"
        }
    ],
    "sg:phone":"+1 662 890 3710",
    "sg:postcode":"38654",
    "sg:province":"MS",
    "sg:tags":[
        "renting",
        "truck",
        "leasing"
    ],
    "wof:name":"Hertz Corp",
    "wof:placetype":"venue"
},
  "geometry": {"coordinates":[-89.83723999999999,34.969133],"type":"Point"}
}