{
  "type": "Feature",
  "properties": {
    "addr:full":"3103 Hwy 82 E Greenville MS 38703",
    "addr:housenumber":"3103",
    "addr:postcode":"38703",
    "addr:street":"Hwy 82 E",
    "iso:country":"US",
    "sg:address":"3103 Hwy 82 E",
    "sg:city":"Greenville",
    "sg:classifiers":[
        {
            "category":"Wholesale",
            "subcategory":"Groceries",
            "type":"Manufacturing & Wholesale Goods"
        }
    ],
    "sg:phone":"+1 662 390 9960",
    "sg:postcode":"38703",
    "sg:province":"MS",
    "sg:tags":[
        "baker"
    ],
    "wof:name":"Flowers Baking Co",
    "wof:placetype":"venue"
},
  "geometry": {"coordinates":[-91.01547100000001,33.399874],"type":"Point"}
}