{
  "type": "Feature",
  "properties": {
    "addr:full":"407 Jeff Davis Ave Long Beach MS 39560",
    "addr:housenumber":"407",
    "addr:postcode":"39560",
    "addr:street":"Jeff Davis Ave",
    "iso:country":"US",
    "sg:address":"407 Jeff Davis Ave",
    "sg:city":"Long Beach",
    "sg:classifiers":[
        {
            "category":"Professional",
            "subcategory":"Lawyer & Legal Services",
            "type":"Services"
        }
    ],
    "sg:phone":"+1 228 864 7443",
    "sg:postcode":"39560",
    "sg:province":"MS",
    "sg:tags":[
        "attorney"
    ],
    "wof:name":"Bryan J Vonder Bruegge",
    "wof:placetype":"venue"
},
  "geometry": {"coordinates":[-89.14907100000001,30.346902],"type":"Point"}
}