{
  "type": "Feature",
  "properties": {
    "iso:country":"US",
    "sg:address":"112 W Washington St",
    "sg:city":"Houston",
    "sg:classifiers":[
        {
            "category":"Professional",
            "subcategory":"Lawyer & Legal Services",
            "type":"Services"
        }
    ],
    "sg:phone":"+1 662 456 3794",
    "sg:postcode":"38851",
    "sg:province":"MS",
    "sg:tags":[
        "attorney"
    ],
    "wof:name":"Richard G Bennett",
    "wof:placetype":"venue"
},
  "geometry": {"coordinates":[-89.001137,33.897715],"type":"Point"}
}