{
  "type": "Feature",
  "properties": {
    "iso:country":"US",
    "sg:address":"2730 Bienville Blvd",
    "sg:city":"Ocean Springs",
    "sg:classifiers":[
        {
            "category":"Freight",
            "type":"Transportation"
        }
    ],
    "sg:phone":"+1 228 875 3214",
    "sg:postcode":"39564",
    "sg:province":"MS",
    "sg:tags":[
        "mover"
    ],
    "wof:name":"Ocean Springs Transfer & Stge",
    "wof:placetype":"venue"
},
  "geometry": {"coordinates":[-88.794276,30.41425],"type":"Point"}
}