{
  "type": "Feature",
  "properties": {
    "addr:full":"7920 Eureka Rd Courtland MS 38620",
    "addr:housenumber":"7920",
    "addr:postcode":"38620",
    "addr:street":"Eureka Rd",
    "iso:country":"US",
    "sg:address":"7920 Eureka Rd",
    "sg:city":"Courtland",
    "sg:classifiers":[
        {
            "category":"Government",
            "subcategory":"Office",
            "type":"Public Place"
        }
    ],
    "sg:phone":"+1 662 563 9892",
    "sg:postcode":"38620",
    "sg:province":"MS",
    "sg:tags":[
        "federal",
        "program"
    ],
    "wof:name":"US Agricultural Dept",
    "wof:placetype":"venue"
},
  "geometry": {"coordinates":[-89.85996799999999,34.243919],"type":"Point"}
}