{
  "type": "Feature",
  "properties": {
    "iso:country":"US",
    "sg:address":"3001 St Charles St",
    "sg:city":"Jackson",
    "sg:classifiers":[
        {
            "category":"Organizations",
            "subcategory":"Religious Organization",
            "type":"Services"
        }
    ],
    "sg:phone":"+1 601 944 9557",
    "sg:postcode":"39209",
    "sg:province":"MS",
    "wof:name":"Rising Sun Mssnary Bptst Chrch",
    "wof:placetype":"venue"
},
  "geometry": {"coordinates":[-90.231944,32.312483],"type":"Point"}
}