{
  "type": "Feature",
  "properties": {
    "iso:country":"US",
    "sg:address":"4235 Chalice Dr",
    "sg:city":"Southaven",
    "sg:classifiers":[
        {
            "category":"Professional",
            "subcategory":"Business Services",
            "type":"Services"
        }
    ],
    "sg:phone":"+1 662 449 3085",
    "sg:postcode":"38672",
    "sg:province":"MS",
    "wof:name":"Childers Enterprises LLC",
    "wof:placetype":"venue"
},
  "geometry": {"coordinates":[-89.9423,34.922011],"type":"Point"}
}