{
  "type": "Feature",
  "properties": {
    "iso:country":"US",
    "sg:address":"4100 Monarch St",
    "sg:city":"Moss Point",
    "sg:classifiers":[
        {
            "category":"Organizations",
            "subcategory":"Religious Organization",
            "type":"Services"
        }
    ],
    "sg:phone":"+1 228 475 8240",
    "sg:postcode":"39563",
    "sg:province":"MS",
    "sg:tags":[
        "church"
    ],
    "wof:name":"St John Missionary Baptist",
    "wof:placetype":"venue"
},
  "geometry": {"coordinates":[-88.54245899999999,30.401812],"type":"Point"}
}