{
  "type": "Feature",
  "properties": {
    "iso:country":"US",
    "sg:address":"3354 N Liberty St",
    "sg:city":"Canton",
    "sg:classifiers":[
        {
            "category":"Insurance",
            "subcategory":"Insurance Agent",
            "type":"Services"
        }
    ],
    "sg:phone":"+1 601 859 3414",
    "sg:postcode":"39046",
    "sg:province":"MS",
    "wof:name":"Roberts Insurance Inc",
    "wof:placetype":"venue"
},
  "geometry": {"coordinates":[-90.034863,32.612694],"type":"Point"}
}