{
  "type": "Feature",
  "properties": {
    "iso:country":"US",
    "sg:address":"2214 9th St",
    "sg:city":"Meridian",
    "sg:classifiers":[
        {
            "category":"Personal",
            "subcategory":"Beauty Salon",
            "type":"Services"
        }
    ],
    "sg:phone":"+1 601 485 6002",
    "sg:postcode":"39301",
    "sg:province":"MS",
    "wof:name":"Studio 601",
    "wof:placetype":"venue"
},
  "geometry": {"coordinates":[-88.701367,32.366034],"type":"Point"}
}