{
  "type": "Feature",
  "properties": {
    "iso:country":"US",
    "sg:address":"94 Main St",
    "sg:city":"Belmont",
    "sg:classifiers":[
        {
            "category":"Government",
            "subcategory":"Office",
            "type":"Public Place"
        }
    ],
    "sg:phone":"+1 662 454 3381",
    "sg:postcode":"38827",
    "sg:province":"AL",
    "sg:tags":[
        "executive"
    ],
    "wof:name":"City Hall",
    "wof:placetype":"venue"
},
  "geometry": {"coordinates":[-88.20925099999999,34.508847],"type":"Point"}
}