{
  "type": "Feature",
  "properties": {
    "addr:full":"205 N 1st St Booneville MS 38829",
    "addr:housenumber":"205",
    "addr:postcode":"38829",
    "addr:street":"N 1St St",
    "iso:country":"US",
    "sg:address":"205 N 1st St",
    "sg:city":"Booneville",
    "sg:classifiers":[
        {
            "category":"Retail",
            "subcategory":"Repair Shop",
            "type":"Services"
        }
    ],
    "sg:phone":"+1 662 728 6187",
    "sg:postcode":"38829",
    "sg:province":"MS",
    "sg:tags":[
        "armature",
        "rewinding"
    ],
    "wof:name":"Eaton Electric Motor Repair",
    "wof:placetype":"venue"
},
  "geometry": {"coordinates":[-88.564677,34.658923],"type":"Point"}
}