{
  "type": "Feature",
  "properties": {
    "iso:country":"US",
    "sg:address":"24 Co Rd 7481",
    "sg:city":"Baldwyn",
    "sg:phone":"+1 662 728 1445",
    "sg:postcode":"38824",
    "sg:province":"MS",
    "sg:tags":[
        "wheat",
        "farm",
        "corn",
        "crop",
        "field",
        "soybean"
    ],
    "wof:name":"Randy Vandevander",
    "wof:placetype":"venue"
},
  "geometry": {"coordinates":[-88.68338799999999,34.606513],"type":"Point"}
}