{
  "type": "Feature",
  "properties": {
    "addr:full":"121 S Walnut St Greenville MS 38701",
    "addr:housenumber":"121",
    "addr:postcode":"38701",
    "addr:street":"S Walnut St",
    "iso:country":"US",
    "sg:address":"121 S Walnut St",
    "sg:city":"Greenville",
    "sg:classifiers":[
        {
            "category":"Shopping",
            "subcategory":"Musical Instruments",
            "type":"Retail Goods"
        }
    ],
    "sg:phone":"+1 662 378 9002",
    "sg:postcode":"38701",
    "sg:province":"MS",
    "wof:name":"Brim's Music Shop",
    "wof:placetype":"venue"
},
  "geometry": {"coordinates":[-91.06412,33.412864],"type":"Point"}
}