{
  "type": "Feature",
  "properties": {
    "addr:full":"6767 S Siwell Rd Jackson MS 39272",
    "addr:housenumber":"6767",
    "addr:postcode":"39272",
    "addr:street":"S Siwell Rd",
    "iso:country":"US",
    "sg:address":"6767 S Siwell Rd",
    "sg:city":"Jackson",
    "sg:classifiers":[
        {
            "category":"Professional",
            "subcategory":"Accounting & Tax Preparation",
            "type":"Services"
        }
    ],
    "sg:phone":"+1 601 373 0073",
    "sg:postcode":"39272",
    "sg:province":"MS",
    "sg:tags":[
        "accountant"
    ],
    "wof:name":"Smith & Co",
    "wof:placetype":"venue"
},
  "geometry": {"coordinates":[-90.29277999999999,32.20295],"type":"Point"}
}