{
  "type": "Feature",
  "properties": {
    "addr:full":"210 Diamond D Lake Rd Brandon MS 39042",
    "addr:housenumber":"210;d",
    "addr:postcode":"39042",
    "addr:street":"Diamond;Lake Rd",
    "iso:country":"US",
    "sg:address":"210 Diamond D Lake Rd",
    "sg:city":"Brandon",
    "sg:classifiers":[
        {
            "category":"Farming",
            "subcategory":"Livestock Farm",
            "type":"Manufacturing & Wholesale Goods"
        }
    ],
    "sg:phone":"+1 601 546 2280",
    "sg:postcode":"39042",
    "sg:province":"MS",
    "sg:tags":[
        "beef",
        "feedlot",
        "cattle"
    ],
    "wof:name":"Diamomd D Farms",
    "wof:placetype":"venue"
},
  "geometry": {"coordinates":[-89.77744,32.17689],"type":"Point"}
}