{
  "type": "Feature",
  "properties": {
    "iso:country":"US",
    "sg:address":"168 John F Kennedy St",
    "sg:city":"Lucedale",
    "sg:classifiers":[
        {
            "category":"Social Services",
            "subcategory":"Child Care",
            "type":"Services"
        }
    ],
    "sg:phone":"+1 601 947 3294",
    "sg:postcode":"39452",
    "sg:province":"MS",
    "sg:tags":[
        "day"
    ],
    "wof:name":"Homechild Care",
    "wof:placetype":"venue"
},
  "geometry": {"coordinates":[-88.600131,30.915386],"type":"Point"}
}