{
  "type": "Feature",
  "properties": {
    "addr:full":"212 Debuys Rd Biloxi MS 39531",
    "addr:housenumber":"212",
    "addr:postcode":"39531",
    "addr:street":"Debuys Rd",
    "iso:country":"US",
    "sg:address":"212 Debuys Rd",
    "sg:city":"Biloxi",
    "sg:classifiers":[
        {
            "category":"Professional",
            "subcategory":"Advertising",
            "type":"Services"
        }
    ],
    "sg:phone":"+1 228 388 6000",
    "sg:postcode":"39531",
    "sg:province":"MS",
    "wof:name":"WCPR",
    "wof:placetype":"venue"
},
  "geometry": {"coordinates":[-89.001223,30.394209],"type":"Point"}
}