{
  "type": "Feature",
  "properties": {
    "addr:full":"1002 22nd St Pascagoula MS 39581",
    "addr:housenumber":"1002",
    "addr:postcode":"39581",
    "addr:street":"22Nd St",
    "iso:country":"US",
    "sg:address":"1002 22nd St",
    "sg:city":"Pascagoula",
    "sg:classifiers":[
        {
            "category":"Freight",
            "type":"Transportation"
        }
    ],
    "sg:phone":"+1 228 769 9269",
    "sg:postcode":"39581",
    "sg:province":"MS",
    "sg:tags":[
        "operator",
        "local",
        "trucking"
    ],
    "wof:name":"Sherman & Sherman Trucking",
    "wof:placetype":"venue"
},
  "geometry": {"coordinates":[-88.528498,30.349797],"type":"Point"}
}