{
  "type": "Feature",
  "properties": {
    "iso:country":"US",
    "sg:address":"6 Burgetown Rd",
    "sg:city":"Carriere",
    "sg:classifiers":[
        {
            "category":"Cinema",
            "subcategory":"Movie Rental",
            "type":"Entertainment"
        }
    ],
    "sg:phone":"+1 601 749 7944",
    "sg:postcode":"39426",
    "sg:province":"MS",
    "sg:tags":[
        "video"
    ],
    "wof:name":"PRC Video",
    "wof:placetype":"venue"
},
  "geometry": {"coordinates":[-89.656986,30.610497],"type":"Point"}
}