{
  "type": "Feature",
  "properties": {
    "iso:country":"US",
    "sg:address":"6069 Cricket Rd",
    "sg:city":"Meridian",
    "sg:classifiers":[
        {
            "category":"Building & Trades",
            "subcategory":"Construction",
            "type":"Services"
        }
    ],
    "sg:phone":"+1 601 693 6428",
    "sg:postcode":"39305",
    "sg:province":"MS",
    "sg:tags":[
        "contractor"
    ],
    "wof:name":"Odom Pressure Washing",
    "wof:placetype":"venue"
},
  "geometry": {"coordinates":[-88.78204599999999,32.424282],"type":"Point"}
}