{
  "type": "Feature",
  "properties": {
    "addr:full":"6890 Hwy 305 N Olive Branch MS 38654",
    "addr:housenumber":"6890",
    "addr:postcode":"38654",
    "addr:street":"Hwy 305 N",
    "iso:country":"US",
    "sg:address":"6890 Hwy 305 N",
    "sg:city":"Olive Branch",
    "sg:classifiers":[
        {
            "category":"Banks & Credit Unions",
            "subcategory":"Bank",
            "type":"Services"
        }
    ],
    "sg:phone":"+1 662 893 5003",
    "sg:postcode":"38654",
    "sg:province":"MS",
    "wof:name":"Peoples Bank & Trust Co",
    "wof:placetype":"venue"
},
  "geometry": {"coordinates":[-89.830313,34.960141],"type":"Point"}
}