{
  "type": "Feature",
  "properties": {
    "addr:full":"13096 Williams Rd Gulfport MS 39503",
    "addr:housenumber":"13096",
    "addr:postcode":"39503",
    "addr:street":"Williams Rd",
    "iso:country":"US",
    "sg:address":"13096 Williams Rd",
    "sg:city":"Gulfport",
    "sg:classifiers":[
        {
            "category":"Building & Trades",
            "subcategory":"Pest Control",
            "type":"Services"
        }
    ],
    "sg:phone":"+1 228 832 5521",
    "sg:postcode":"39503",
    "sg:province":"MS",
    "wof:name":"Calhoun Pest Control",
    "wof:placetype":"venue"
},
  "geometry": {"coordinates":[-89.065376,30.471549],"type":"Point"}
}