{
  "type": "Feature",
  "properties": {
    "iso:country":"US",
    "sg:address":"5430 Executive Pl",
    "sg:city":"Jackson",
    "sg:classifiers":[
        {
            "category":"Arena",
            "subcategory":"Sports Club",
            "type":"Entertainment"
        }
    ],
    "sg:phone":"+1 601 982 5198",
    "sg:postcode":"39206",
    "sg:province":"MS",
    "sg:tags":[
        "soccer"
    ],
    "wof:name":"Mississippi Youth Soccer Assn",
    "wof:placetype":"venue"
},
  "geometry": {"coordinates":[-90.15122100000001,32.370255],"type":"Point"}
}