{
  "type": "Feature",
  "properties": {
    "addr:full":"274 Dogwood Pl Flowood MS 39232",
    "addr:housenumber":"274",
    "addr:postcode":"39232",
    "addr:street":"Dogwood Pl",
    "iso:country":"US",
    "sg:address":"274 Dogwood Pl",
    "sg:city":"Flowood",
    "sg:classifiers":[
        {
            "category":"Restaurant",
            "type":"Food & Drink"
        }
    ],
    "sg:phone":"+1 601 992 2554",
    "sg:postcode":"39232",
    "sg:province":"MS",
    "sg:tags":[
        "eating"
    ],
    "wof:name":"Chick-Fil-A",
    "wof:placetype":"venue"
},
  "geometry": {"coordinates":[-90.05067099999999,32.336349],"type":"Point"}
}