{
  "type": "Feature",
  "properties": {
    "iso:country":"US",
    "sg:address":"1010 E Northside Dr",
    "sg:city":"Jackson",
    "sg:classifiers":[
        {
            "category":"Home & Garden",
            "subcategory":"Furniture",
            "type":"Retail Goods"
        }
    ],
    "sg:phone":"+1 601 366 0335",
    "sg:postcode":"39206",
    "sg:province":"MS",
    "sg:tags":[
        "house",
        "furnishing"
    ],
    "wof:name":"Batte Furniture & Interiors",
    "wof:placetype":"venue"
},
  "geometry": {"coordinates":[-90.154713,32.355865],"type":"Point"}
}