{
  "type": "Feature",
  "properties": {
    "iso:country":"US",
    "sg:address":"1907 Popps Ferry Rd",
    "sg:city":"Biloxi",
    "sg:classifiers":[
        {
            "category":"Organizations",
            "subcategory":"Religious Organization",
            "type":"Services"
        }
    ],
    "sg:phone":"+1 228 385 1001",
    "sg:postcode":"39532",
    "sg:province":"MS",
    "sg:tags":[
        "church"
    ],
    "sg:website":"www.fpcofbiloxi.com",
    "wof:name":"First Pentecostal Church",
    "wof:placetype":"venue"
},
  "geometry": {"coordinates":[-88.95012699999999,30.441662],"type":"Point"}
}