{
  "type": "Feature",
  "properties": {
    "iso:country":"US",
    "sg:address":"4167 Hwy 9 S",
    "sg:city":"Pontotoc",
    "sg:classifiers":[
        {
            "category":"Wholesale",
            "subcategory":"Machinery & Supplies",
            "type":"Manufacturing & Wholesale Goods"
        }
    ],
    "sg:phone":"+1 662 489 8100",
    "sg:postcode":"38863",
    "sg:province":"MS",
    "sg:tags":[
        "industrial"
    ],
    "sg:website":"www.bryantsales.com",
    "wof:name":"Bryant Sales & Supply",
    "wof:placetype":"venue"
},
  "geometry": {"coordinates":[-89.088054,34.236735],"type":"Point"}
}