{
  "type": "Feature",
  "properties": {
    "addr:full":"104 E Quiver Rd Sunflower MS 38778",
    "addr:housenumber":"104",
    "addr:postcode":"38778",
    "addr:street":"E Quiver Rd",
    "iso:country":"US",
    "sg:address":"104 E Quiver Rd",
    "sg:city":"Sunflower",
    "sg:classifiers":[
        {
            "category":"Autos & Motor Vehicles",
            "subcategory":"Fuel & Gas Station",
            "type":"Retail Goods"
        }
    ],
    "sg:phone":"+1 662 569 3256",
    "sg:postcode":"38778",
    "sg:province":"MS",
    "sg:tags":[
        "oil"
    ],
    "wof:name":"Abneys Amoco",
    "wof:placetype":"venue"
},
  "geometry": {"coordinates":[-90.51327499999999,33.734006],"type":"Point"}
}