{
  "type": "Feature",
  "properties": {
    "iso:country":"US",
    "sg:address":"307 Clinton Blvd",
    "sg:city":"Clinton",
    "sg:classifiers":[
        {
            "category":"Food & Beverages",
            "subcategory":"Groceries & Convenience Stores",
            "type":"Retail Goods"
        },
        {
            "category":"Food & Beverages",
            "subcategory":"Specialty",
            "type":"Retail Goods"
        }
    ],
    "sg:phone":"+1 601 924 1800",
    "sg:postcode":"39056",
    "sg:province":"MS",
    "sg:tags":[
        "grocer"
    ],
    "wof:name":"Sweet & Sour",
    "wof:placetype":"venue"
},
  "geometry": {"coordinates":[-90.310119,32.334856],"type":"Point"}
}