{
  "type": "Feature",
  "properties": {
    "addr:full":"7011 Beatline Rd Long Beach MS 39560",
    "addr:housenumber":"7011",
    "addr:postcode":"39560",
    "addr:street":"Beatline Rd",
    "iso:country":"US",
    "sg:address":"7011 Beatline Rd",
    "sg:city":"Long Beach",
    "sg:classifiers":[
        {
            "category":"Food & Beverages",
            "subcategory":"Groceries & Convenience Stores",
            "type":"Retail Goods"
        }
    ],
    "sg:phone":"+1 228 871 5100",
    "sg:postcode":"39560",
    "sg:province":"MS",
    "wof:name":"Beatline Chevron At 28th",
    "wof:placetype":"venue"
},
  "geometry": {"coordinates":[-89.187189,30.383979],"type":"Point"}
}