{
  "type": "Feature",
  "properties": {
    "addr:full":"840 Hwy 51 S Hernando MS 38632",
    "addr:housenumber":"840",
    "addr:postcode":"38632",
    "addr:street":"Hwy 51 S",
    "iso:country":"US",
    "sg:address":"840 Hwy 51 S",
    "sg:city":"Hernando",
    "sg:classifiers":[
        {
            "category":"Government",
            "subcategory":"Office",
            "type":"Public Place"
        }
    ],
    "sg:phone":"+1 662 429 8687",
    "sg:postcode":"38632",
    "sg:province":"MS",
    "sg:tags":[
        "federal",
        "program"
    ],
    "wof:name":"US Agricultural Dept",
    "wof:placetype":"venue"
},
  "geometry": {"coordinates":[-89.99502099999999,34.84658],"type":"Point"}
}