{
  "type": "Feature",
  "properties": {
    "iso:country":"US",
    "sg:address":"344 Crossgates Blvd",
    "sg:city":"Brandon",
    "sg:classifiers":[
        {
            "category":"Health Services",
            "subcategory":"Doctor",
            "type":"Services"
        }
    ],
    "sg:phone":"+1 601 825 6372",
    "sg:postcode":"39042",
    "sg:province":"MS",
    "sg:tags":[
        "dentist"
    ],
    "wof:name":"Family Dental Care Inc",
    "wof:placetype":"venue"
},
  "geometry": {"coordinates":[-90.035888,32.287415],"type":"Point"}
}