{
  "type": "Feature",
  "properties": {
    "addr:full":"101 Thornhill Dr Hattiesburg MS 39402",
    "addr:housenumber":"101",
    "addr:postcode":"39402",
    "addr:street":"Thornhill Dr",
    "iso:country":"US",
    "sg:address":"101 Thornhill Dr",
    "sg:city":"Hattiesburg",
    "sg:classifiers":[
        {
            "category":"Restaurant",
            "type":"Food & Drink"
        }
    ],
    "sg:phone":"+1 601 264 4758",
    "sg:postcode":"39402",
    "sg:province":"MS",
    "wof:name":"Ward's",
    "wof:placetype":"venue"
},
  "geometry": {"coordinates":[-89.35165499999999,31.327427],"type":"Point"}
}