{
  "type": "Feature",
  "properties": {
    "iso:country":"US",
    "sg:address":"237 Co Rd 1101",
    "sg:city":"Booneville",
    "sg:classifiers":[
        {
            "category":"Utilities",
            "subcategory":"Water",
            "type":"Services"
        }
    ],
    "sg:phone":"+1 662 728 4003",
    "sg:postcode":"38829",
    "sg:province":"MS",
    "sg:tags":[
        "company",
        "management",
        "sewage",
        "supply"
    ],
    "wof:name":"New Candler Water Association",
    "wof:placetype":"venue"
},
  "geometry": {"coordinates":[-88.507729,34.692771],"type":"Point"}
}