{
  "type": "Feature",
  "properties": {
    "iso:country":"US",
    "sg:address":"422 Sol Colston Rd",
    "sg:city":"Finger",
    "sg:classifiers":[
        {
            "category":"Freight",
            "type":"Transportation"
        }
    ],
    "sg:phone":"+1 731 934 4047",
    "sg:postcode":"38334",
    "sg:province":"MS",
    "sg:tags":[
        "operator",
        "local",
        "trucking"
    ],
    "wof:name":"Barnes Trucking",
    "wof:placetype":"venue"
},
  "geometry": {"coordinates":[-88.64735899999999,35.342428],"type":"Point"}
}