{
  "type": "Feature",
  "properties": {
    "iso:country":"US",
    "sg:address":"2403 Eden St",
    "sg:city":"Pascagoula",
    "sg:classifiers":[
        {
            "category":"Real Estate",
            "subcategory":"Real Estate Operator",
            "type":"Services"
        }
    ],
    "sg:phone":"+1 228 762 2057",
    "sg:postcode":"39581",
    "sg:province":"MS",
    "sg:tags":[
        "apartment"
    ],
    "wof:name":"Edenwood Apartments",
    "wof:placetype":"venue"
},
  "geometry": {"coordinates":[-88.530731,30.359919],"type":"Point"}
}