{
  "type": "Feature",
  "properties": {
    "addr:full":"400 High St Jackson MS 39201",
    "addr:housenumber":"400",
    "addr:postcode":"39201",
    "addr:street":"High St",
    "iso:country":"US",
    "sg:address":"400 High St",
    "sg:city":"Jackson",
    "sg:classifiers":[
        {
            "category":"Manufacturing",
            "subcategory":"Printing",
            "type":"Manufacturing & Wholesale Goods"
        }
    ],
    "sg:phone":"+1 601 353 3119",
    "sg:postcode":"39201",
    "sg:province":"MS",
    "sg:tags":[
        "newspaper"
    ],
    "wof:name":"Northeast Miss Daily Journal",
    "wof:placetype":"venue"
},
  "geometry": {"coordinates":[-90.181927,32.30493],"type":"Point"}
}