{
  "type": "Feature",
  "properties": {
    "iso:country":"US",
    "sg:address":"910 Sawmill Rd",
    "sg:city":"Laurel",
    "sg:classifiers":[
        {
            "category":"Restaurant",
            "type":"Food & Drink"
        }
    ],
    "sg:menulink":"http://www.allmenus.com/ms/laurel/180116-chick-fil-a/menu/",
    "sg:phone":"+1 601 428 1196",
    "sg:postcode":"39440",
    "sg:province":"MS",
    "sg:tags":[
        "wrap",
        "soup",
        "american",
        "sandwich",
        "salad"
    ],
    "wof:name":"Chick-fil-A",
    "wof:placetype":"venue"
},
  "geometry": {"coordinates":[-89.13734100000001,31.693552],"type":"Point"}
}