{
  "type": "Feature",
  "properties": {
    "iso:country":"US",
    "sg:address":"274 Evanston Rd",
    "sg:city":"Lucedale",
    "sg:classifiers":[
        {
            "category":"Manufacturing",
            "subcategory":"Metals",
            "type":"Manufacturing & Wholesale Goods"
        }
    ],
    "sg:phone":"+1 601 947 7210",
    "sg:postcode":"39452",
    "sg:province":"MS",
    "sg:tags":[
        "shop",
        "plate",
        "work",
        "fabricated"
    ],
    "sg:website":"www.at-v.com",
    "wof:name":"American Tank & Vessel Co",
    "wof:placetype":"venue"
},
  "geometry": {"coordinates":[-88.555583,30.913895],"type":"Point"}
}