{
  "type": "Feature",
  "properties": {
    "addr:full":"1619 Highland Dr Amory MS 38821",
    "addr:housenumber":"1619",
    "addr:postcode":"38821",
    "addr:street":"Highland Dr",
    "iso:country":"US",
    "sg:address":"1619 Highland Dr",
    "sg:city":"Amory",
    "sg:classifiers":[
        {
            "category":"Social Services",
            "subcategory":"Job Training",
            "type":"Services"
        }
    ],
    "sg:phone":"+1 662 256 2618",
    "sg:postcode":"38821",
    "sg:province":"MS",
    "sg:tags":[
        "rehab",
        "government"
    ],
    "wof:name":"Employment Security Commission",
    "wof:placetype":"venue"
},
  "geometry": {"coordinates":[-88.480372,34.003524],"type":"Point"}
}