{
  "type": "Feature",
  "properties": {
    "addr:full":"106 N Canal St Natchez MS 39120",
    "addr:housenumber":"106",
    "addr:postcode":"39120",
    "addr:street":"N Canal St",
    "iso:country":"US",
    "sg:address":"106 N Canal St",
    "sg:city":"Natchez",
    "sg:classifiers":[
        {
            "category":"Food & Beverages",
            "subcategory":"Candy",
            "type":"Retail Goods"
        }
    ],
    "sg:phone":"+1 601 446 5354",
    "sg:postcode":"39120",
    "sg:province":"MS",
    "sg:tags":[
        "confectionery"
    ],
    "wof:name":"Old South Trading Post",
    "wof:placetype":"venue"
},
  "geometry": {"coordinates":[-91.4049,31.562087],"type":"Point"}
}