{
  "type": "Feature",
  "properties": {
    "iso:country":"US",
    "sg:address":"254 Green Ave",
    "sg:city":"Drew",
    "sg:classifiers":[
        {
            "category":"Personal",
            "subcategory":"Beauty Salon",
            "type":"Services"
        }
    ],
    "sg:phone":"+1 662 745 6647",
    "sg:postcode":"38737",
    "sg:province":"MS",
    "sg:tags":[
        "shop"
    ],
    "wof:name":"Beauty Den",
    "wof:placetype":"venue"
},
  "geometry": {"coordinates":[-90.53507500000001,33.807982],"type":"Point"}
}