{
  "type": "Feature",
  "properties": {
    "iso:country":"US",
    "sg:address":"2528 Lawndale Dr",
    "sg:city":"Tupelo",
    "sg:classifiers":[
        {
            "category":"Retail",
            "subcategory":"Laundry & Dry Cleaning",
            "type":"Services"
        }
    ],
    "sg:phone":"+1 662 841 0580",
    "sg:postcode":"38801",
    "sg:province":"MS",
    "sg:tags":[
        "drycleaning",
        "plant",
        "agent",
        "garment"
    ],
    "wof:name":"Vogue Village Cleaners",
    "wof:placetype":"venue"
},
  "geometry": {"coordinates":[-88.72878300000001,34.225523],"type":"Point"}
}