{
  "type": "Feature",
  "properties": {
    "iso:country":"US",
    "sg:address":"744 Winter St",
    "sg:city":"Lucedale",
    "sg:classifiers":[
        {
            "category":"Insurance",
            "subcategory":"Insurance Agent",
            "type":"Services"
        }
    ],
    "sg:phone":"+1 601 947 6660",
    "sg:postcode":"39452",
    "sg:province":"MS",
    "wof:name":"Alfa Insurance Corp",
    "wof:placetype":"venue"
},
  "geometry": {"coordinates":[-88.59270600000001,30.91939],"type":"Point"}
}