{
  "type": "Feature",
  "properties": {
    "addr:full":"166 E Cherokee St Brookhaven MS 39601",
    "addr:housenumber":"166",
    "addr:postcode":"39601",
    "addr:street":"E Cherokee St",
    "iso:country":"US",
    "sg:address":"166 E Cherokee St",
    "sg:city":"Brookhaven",
    "sg:classifiers":[
        {
            "category":"Education",
            "subcategory":"School",
            "type":"Public Place"
        }
    ],
    "sg:phone":"+1 601 645 0008",
    "sg:postcode":"39601",
    "sg:province":"MS",
    "wof:name":"William Winas Middle School",
    "wof:placetype":"venue"
},
  "geometry": {"coordinates":[-90.44179200000001,31.577912],"type":"Point"}
}