{
  "type": "Feature",
  "properties": {
    "iso:country":"US",
    "sg:address":"2300 11th St",
    "sg:city":"Meridian",
    "sg:classifiers":[
        {
            "category":"Organizations",
            "subcategory":"Professional Association",
            "type":"Services"
        }
    ],
    "sg:phone":"+1 601 693 1465",
    "sg:postcode":"39301",
    "sg:province":"MS",
    "wof:name":"Scottish Rite Bodies",
    "wof:placetype":"venue"
},
  "geometry": {"coordinates":[-88.702591,32.367764],"type":"Point"}
}