{
  "type": "Feature",
  "properties": {
    "addr:full":"5395 I- 55 N Jackson MS 39206",
    "addr:housenumber":"5395;55 n",
    "addr:postcode":"39206",
    "addr:street":"I",
    "iso:country":"US",
    "sg:address":"5395 I- 55 N",
    "sg:city":"Jackson",
    "sg:classifiers":[
        {
            "category":"Wholesale",
            "subcategory":"Auto Parts",
            "type":"Manufacturing & Wholesale Goods"
        }
    ],
    "sg:phone":"+1 601 982 4607",
    "sg:postcode":"39206",
    "sg:province":"MS",
    "sg:tags":[
        "automobile",
        "supply"
    ],
    "wof:name":"North Jackson Parts Div",
    "wof:placetype":"venue"
},
  "geometry": {"coordinates":[-90.14901999999999,32.372761],"type":"Point"}
}