{
  "type": "Feature",
  "properties": {
    "iso:country":"US",
    "sg:address":"2408 S Gloster St",
    "sg:city":"Tupelo",
    "sg:classifiers":[
        {
            "category":"Home & Garden",
            "subcategory":"Mobile Homes",
            "type":"Retail Goods"
        }
    ],
    "sg:phone":"+1 662 842 1804",
    "sg:postcode":"38801",
    "sg:province":"MS",
    "wof:name":"Windhams Mobile Homes Inc",
    "wof:placetype":"venue"
},
  "geometry": {"coordinates":[-88.71999700000001,34.210946],"type":"Point"}
}