{
  "type": "Feature",
  "properties": {
    "addr:full":"2404 E Lincoln Rd SE Brookhaven MS 39601",
    "addr:housenumber":"2404",
    "addr:postcode":"39601",
    "addr:street":"E Lincoln Rd Se",
    "iso:country":"US",
    "sg:address":"2404 E Lincoln Rd SE",
    "sg:city":"Brookhaven",
    "sg:classifiers":[
        {
            "category":"Food & Beverages",
            "subcategory":"Groceries & Convenience Stores",
            "type":"Retail Goods"
        }
    ],
    "sg:phone":"+1 601 833 1473",
    "sg:postcode":"39601",
    "sg:province":"MS",
    "wof:name":"Martin's Grocery & Grill Inc",
    "wof:placetype":"venue"
},
  "geometry": {"coordinates":[-90.345664,31.510061],"type":"Point"}
}