{
  "type": "Feature",
  "properties": {
    "iso:country":"US",
    "sg:address":"323 W Canal St",
    "sg:city":"Picayune",
    "sg:classifiers":[
        {
            "category":"Personal",
            "subcategory":"Beauty Salon",
            "type":"Services"
        }
    ],
    "sg:phone":"+1 601 798 9417",
    "sg:postcode":"39466",
    "sg:province":"MS",
    "sg:tags":[
        "shop"
    ],
    "wof:name":"B & B Renewed Attitudes",
    "wof:placetype":"venue"
},
  "geometry": {"coordinates":[-89.68403499999999,30.526699],"type":"Point"}
}