{
  "type": "Feature",
  "properties": {
    "addr:full":"3669 Highway 61 N Ste A Tunica MS 38676",
    "addr:housenumber":"3669",
    "addr:postcode":"38676",
    "addr:street":"Highway 61 N Ste A Tunica",
    "iso:country":"US",
    "sg:address":"3669 Highway 61 N Ste A",
    "sg:city":"Tunica",
    "sg:classifiers":[
        {
            "category":"Restaurant",
            "type":"Food & Drink"
        }
    ],
    "sg:phone":"+1 662 357 0102",
    "sg:postcode":"38676",
    "sg:province":"MS",
    "sg:tags":[
        "style",
        "mexican",
        "family"
    ],
    "wof:name":"Mexico Grill",
    "wof:placetype":"venue"
},
  "geometry": {"coordinates":[-90.368472,34.722386],"type":"Point"}
}