{
  "type": "Feature",
  "properties": {
    "addr:full":"332 N Heard St Senatobia MS 38668",
    "addr:housenumber":"332",
    "addr:postcode":"38668",
    "addr:street":"N Heard St",
    "iso:country":"US",
    "sg:address":"332 N Heard St",
    "sg:city":"Senatobia",
    "sg:classifiers":[
        {
            "category":"Restaurant",
            "type":"Food & Drink"
        }
    ],
    "sg:menulink":"http://www.allmenus.com/ms/crossroad/199511-sonic/menu/",
    "sg:phone":"+1 662 562 5641",
    "sg:postcode":"38668",
    "sg:province":"MS",
    "sg:tags":[
        "burger",
        "american"
    ],
    "wof:name":"Sonic",
    "wof:placetype":"venue"
},
  "geometry": {"coordinates":[-89.959782,34.623967],"type":"Point"}
}