{
  "type": "Feature",
  "properties": {
    "iso:country":"US",
    "sg:address":"111 Court St",
    "sg:city":"Bay St Louis",
    "sg:classifiers":[
        {
            "category":"Government",
            "subcategory":"Office",
            "type":"Public Place"
        }
    ],
    "sg:phone":"+1 228 467 9060",
    "sg:postcode":"39520",
    "sg:province":"MS",
    "sg:tags":[
        "village"
    ],
    "wof:name":"Bay St Louis Business License",
    "wof:placetype":"venue"
},
  "geometry": {"coordinates":[-89.327384,30.310119],"type":"Point"}
}