{
  "type": "Feature",
  "properties": {
    "addr:full":"4725 Dubarry Ln Jackson MS 39209",
    "addr:housenumber":"4725",
    "addr:postcode":"39209",
    "addr:street":"Dubarry Ln",
    "iso:country":"US",
    "sg:address":"4725 Dubarry Ln",
    "sg:city":"Jackson",
    "sg:classifiers":[
        {
            "category":"Manufacturing",
            "subcategory":"Chemicals & Compounds",
            "type":"Manufacturing & Wholesale Goods"
        }
    ],
    "sg:phone":"+1 601 922 4522",
    "sg:postcode":"39209",
    "sg:province":"MS",
    "sg:tags":[
        "cleaning"
    ],
    "wof:name":"Carpet Solutions",
    "wof:placetype":"venue"
},
  "geometry": {"coordinates":[-90.252154,32.31663],"type":"Point"}
}