{
  "type": "Feature",
  "properties": {
    "addr:full":"3109 20th St Gulfport MS 39501",
    "addr:housenumber":"3109",
    "addr:postcode":"39501",
    "addr:street":"20Th St",
    "iso:country":"US",
    "sg:address":"3109 20th St",
    "sg:city":"Gulfport",
    "sg:classifiers":[
        {
            "category":"Retail",
            "subcategory":"Self-service Laundry",
            "type":"Services"
        }
    ],
    "sg:phone":"+1 228 864 4118",
    "sg:postcode":"39501",
    "sg:province":"MS",
    "wof:name":"Neighborhood Laundry",
    "wof:placetype":"venue"
},
  "geometry": {"coordinates":[-89.09961800000001,30.374488],"type":"Point"}
}