{
  "type": "Feature",
  "properties": {
    "addr:full":"625 Northview Dr Laurel MS 39440",
    "addr:housenumber":"625",
    "addr:postcode":"39440",
    "addr:street":"Northview Dr",
    "iso:country":"US",
    "sg:address":"625 Northview Dr",
    "sg:city":"Laurel",
    "sg:classifiers":[
        {
            "category":"Social Services",
            "subcategory":"Adult Care",
            "type":"Services"
        }
    ],
    "sg:phone":"+1 601 426 3782",
    "sg:postcode":"39440",
    "sg:province":"MS",
    "sg:tags":[
        "home",
        "residential"
    ],
    "wof:name":"Northview Care Ctr",
    "wof:placetype":"venue"
},
  "geometry": {"coordinates":[-89.134096,31.729783],"type":"Point"}
}