{
  "type": "Feature",
  "properties": {
    "iso:country":"US",
    "sg:address":"616 S 9th St",
    "sg:city":"Greenville",
    "sg:classifiers":[
        {
            "category":"Personal",
            "subcategory":"Beauty Salon",
            "type":"Services"
        }
    ],
    "sg:phone":"+1 662 332 1051",
    "sg:postcode":"38703",
    "sg:province":"MS",
    "wof:name":"Creative Cuts & Styles",
    "wof:placetype":"venue"
},
  "geometry": {"coordinates":[-91.03476499999999,33.399398],"type":"Point"}
}