{
  "type": "Feature",
  "properties": {
    "iso:country":"US",
    "sg:address":"599 N 1st St",
    "sg:city":"Rolling Fork",
    "sg:classifiers":[
        {
            "category":"Farming",
            "subcategory":"Farm",
            "type":"Manufacturing & Wholesale Goods"
        }
    ],
    "sg:phone":"+1 662 873 4054",
    "sg:postcode":"39159",
    "sg:province":"MS",
    "wof:name":"Carter Brothers Farms",
    "wof:placetype":"venue"
},
  "geometry": {"coordinates":[-90.87925199999999,32.907414],"type":"Point"}
}