{
  "type": "Feature",
  "properties": {
    "iso:country":"US",
    "sg:address":"1007 Rock Hill Rd",
    "sg:city":"Sardis",
    "sg:classifiers":[
        {
            "category":"Wholesale",
            "subcategory":"Durable Goods & Equipment",
            "type":"Manufacturing & Wholesale Goods"
        }
    ],
    "sg:phone":"+1 662 487 0030",
    "sg:postcode":"38666",
    "sg:province":"MS",
    "wof:name":"P and J Wholesale",
    "wof:placetype":"venue"
},
  "geometry": {"coordinates":[-89.978869,34.398736],"type":"Point"}
}