{
  "type": "Feature",
  "properties": {
    "addr:full":"5044 Raymond Ave Verona MS 38801",
    "addr:housenumber":"5044",
    "addr:postcode":"38801",
    "addr:street":"Raymond Ave",
    "iso:country":"US",
    "sg:address":"5044 Raymond Ave",
    "sg:city":"Verona",
    "sg:classifiers":[
        {
            "category":"Manufacturing",
            "subcategory":"Printing",
            "type":"Manufacturing & Wholesale Goods"
        }
    ],
    "sg:phone":"+1 662 566 2578",
    "sg:postcode":"38801",
    "sg:province":"MS",
    "sg:tags":[
        "screen"
    ],
    "sg:website":"www.southeastco.com",
    "wof:name":"Southeast Co",
    "wof:placetype":"venue"
},
  "geometry": {"coordinates":[-88.71986699999999,34.193572],"type":"Point"}
}