{
  "type": "Feature",
  "properties": {
    "addr:full":"2102 5th St N Columbus MS 39705",
    "addr:housenumber":"2102",
    "addr:postcode":"39705",
    "addr:street":"5Th St N",
    "iso:country":"US",
    "sg:address":"2102 5th St N",
    "sg:city":"Columbus",
    "sg:classifiers":[
        {
            "category":"Health Services",
            "subcategory":"Doctor",
            "type":"Services"
        }
    ],
    "sg:phone":"+1 662 329 1393",
    "sg:postcode":"39705",
    "sg:province":"MS",
    "sg:tags":[
        "physician",
        "surgeon"
    ],
    "wof:name":"Columbus Ob/Gyn Clinic",
    "wof:placetype":"venue"
},
  "geometry": {"coordinates":[-88.4289,33.518229],"type":"Point"}
}