{
  "type": "Feature",
  "properties": {
    "addr:full":"201 Alabama St Columbus MS 39702",
    "addr:housenumber":"201",
    "addr:postcode":"39702",
    "addr:street":"Alabama St",
    "iso:country":"US",
    "sg:address":"201 Alabama St",
    "sg:city":"Columbus",
    "sg:classifiers":[
        {
            "category":"Bars & Pubs",
            "type":"Food & Drink"
        }
    ],
    "sg:phone":"+1 662 327 9878",
    "sg:postcode":"39702",
    "sg:province":"MS",
    "sg:tags":[
        "club",
        "night"
    ],
    "wof:name":"Gateway Lounge",
    "wof:placetype":"venue"
},
  "geometry": {"coordinates":[-88.38494900000001,33.49615],"type":"Point"}
}