{
  "type": "Feature",
  "properties": {
    "iso:country":"US",
    "sg:address":"226 Pompano Dr",
    "sg:city":"Hattiesburg",
    "sg:classifiers":[
        {
            "category":"Recreation",
            "type":"Entertainment"
        }
    ],
    "sg:phone":"+1 601 264 9760",
    "sg:postcode":"39402",
    "sg:province":"MS",
    "sg:tags":[
        "parachute",
        "training",
        "air",
        "hot",
        "balloon"
    ],
    "wof:name":"C B I",
    "wof:placetype":"venue"
},
  "geometry": {"coordinates":[-89.428629,31.326077],"type":"Point"}
}