{
  "type": "Feature",
  "properties": {
    "iso:country":"US",
    "sg:address":"65 Hwy 48 E",
    "sg:city":"Tylertown",
    "sg:classifiers":[
        {
            "category":"Farming",
            "subcategory":"Livestock Farm",
            "type":"Manufacturing & Wholesale Goods"
        }
    ],
    "sg:phone":"+1 601 876 5107",
    "sg:postcode":"39667",
    "sg:province":"MS",
    "sg:tags":[
        "beef",
        "feedlot",
        "cattle"
    ],
    "wof:name":"C S Brahmens",
    "wof:placetype":"venue"
},
  "geometry": {"coordinates":[-90.11909,31.10857],"type":"Point"}
}