{
  "type": "Feature",
  "properties": {
    "iso:country":"US",
    "sg:address":"1036 S McRaven Rd",
    "sg:city":"Jackson",
    "sg:classifiers":[
        {
            "category":"Organizations",
            "subcategory":"Religious Organization",
            "type":"Services"
        }
    ],
    "sg:phone":"+1 601 922 1155",
    "sg:postcode":"39209",
    "sg:province":"MS",
    "sg:tags":[
        "church"
    ],
    "wof:name":"Mc Raven Hill Christian Flwshp",
    "wof:placetype":"venue"
},
  "geometry": {"coordinates":[-90.32263399999999,32.294379],"type":"Point"}
}