{
  "type": "Feature",
  "properties": {
    "iso:country":"US",
    "sg:address":"1650 S Veterans Blvd",
    "sg:city":"Tupelo",
    "sg:classifiers":[
        {
            "category":"Organizations",
            "subcategory":"Religious Organization",
            "type":"Services"
        }
    ],
    "sg:phone":"+1 662 842 4932",
    "sg:postcode":"38804",
    "sg:province":"MS",
    "wof:name":"Tupelo Free Will Baptst Church",
    "wof:placetype":"venue"
},
  "geometry": {"coordinates":[-88.68501999999999,34.232698],"type":"Point"}
}