{
  "type": "Feature",
  "properties": {
    "addr:full":"562 US Hwy 51 Ridgeland MS 39157",
    "addr:housenumber":"562",
    "addr:postcode":"39157",
    "addr:street":"Us Hwy 51",
    "iso:country":"US",
    "sg:address":"562 US Hwy 51",
    "sg:city":"Ridgeland",
    "sg:classifiers":[
        {
            "category":"Manufacturing",
            "subcategory":"Printing",
            "type":"Manufacturing & Wholesale Goods"
        }
    ],
    "sg:phone":"+1 601 607 7002",
    "sg:postcode":"39157",
    "sg:province":"MS",
    "sg:tags":[
        "business",
        "form",
        "system"
    ],
    "wof:name":"Standard Register Co",
    "wof:placetype":"venue"
},
  "geometry": {"coordinates":[-90.12805899999999,32.429907],"type":"Point"}
}