{
  "type": "Feature",
  "properties": {
    "iso:country":"US",
    "sg:address":"3008 Papania Ln",
    "sg:city":"Gulfport",
    "sg:classifiers":[
        {
            "category":"Manufacturing",
            "subcategory":"Apparel",
            "type":"Manufacturing & Wholesale Goods"
        },
        {
            "category":"Wholesale",
            "subcategory":"Non-durable Goods",
            "type":"Manufacturing & Wholesale Goods"
        }
    ],
    "sg:phone":"+1 228 864 1802",
    "sg:postcode":"39501",
    "sg:province":"MS",
    "sg:tags":[
        "flag",
        "banner",
        "advertising",
        "specialty"
    ],
    "wof:name":"Papania Advertising Specs",
    "wof:placetype":"venue"
},
  "geometry": {"coordinates":[-89.11270399999999,30.386298],"type":"Point"}
}