{
  "type": "Feature",
  "properties": {
    "iso:country":"US",
    "sg:address":"807 US Hwy 82 W",
    "sg:city":"Indianola",
    "sg:classifiers":[
        {
            "category":"Manufacturing",
            "subcategory":"Printing",
            "type":"Manufacturing & Wholesale Goods"
        }
    ],
    "sg:phone":"+1 662 887 7840",
    "sg:postcode":"38751",
    "sg:province":"MS",
    "sg:tags":[
        "stationery",
        "on",
        "printer",
        "site",
        "retail"
    ],
    "sg:website":"www.hometownprinting.com",
    "wof:name":"Hometown Printing Company",
    "wof:placetype":"venue"
},
  "geometry": {"coordinates":[-90.662277,33.457547],"type":"Point"}
}