{
  "type": "Feature",
  "properties": {
    "iso:country":"US",
    "sg:address":"775 N Congress St",
    "sg:city":"Jackson",
    "sg:classifiers":[
        {
            "category":"Professional",
            "subcategory":"Lawyer & Legal Services",
            "type":"Services"
        }
    ],
    "sg:phone":"+1 601 354 2121",
    "sg:postcode":"39202",
    "sg:province":"MS",
    "sg:tags":[
        "attorney"
    ],
    "sg:website":"www.prjmlaw.com",
    "wof:name":"Pigott Reeves Johnson & Minor",
    "wof:placetype":"venue"
},
  "geometry": {"coordinates":[-90.181428,32.307643],"type":"Point"}
}