{
  "type": "Feature",
  "properties": {
    "addr:full":"510 Dumas Ave Hattiesburg MS 39401",
    "addr:housenumber":"510",
    "addr:postcode":"39401",
    "addr:street":"Dumas Ave",
    "iso:country":"US",
    "sg:address":"510 Dumas Ave",
    "sg:city":"Hattiesburg",
    "sg:classifiers":[
        {
            "category":"Organizations",
            "subcategory":"Religious Organization",
            "type":"Services"
        }
    ],
    "sg:phone":"+1 601 583 2405",
    "sg:postcode":"39401",
    "sg:province":"MS",
    "wof:name":"Sweet Pilgrim Baptist Church",
    "wof:placetype":"venue"
},
  "geometry": {"coordinates":[-89.30169100000001,31.309782],"type":"Point"}
}