{
  "type": "Feature",
  "properties": {
    "addr:full":"1914 24th Ave Gulfport MS 39501",
    "addr:housenumber":"1914",
    "addr:postcode":"39501",
    "addr:street":"24Th Ave",
    "iso:country":"US",
    "sg:address":"1914 24th Ave",
    "sg:city":"Gulfport",
    "sg:classifiers":[
        {
            "category":"Professional",
            "subcategory":"Lawyer & Legal Services",
            "type":"Services"
        }
    ],
    "sg:phone":"+1 228 864 4357",
    "sg:postcode":"39501",
    "sg:province":"MS",
    "sg:tags":[
        "attorney"
    ],
    "wof:name":"Gerard F Smith",
    "wof:placetype":"venue"
},
  "geometry": {"coordinates":[-89.091514,30.374409],"type":"Point"}
}