{
  "type": "Feature",
  "properties": {
    "iso:country":"US",
    "sg:address":"11451 White Star Rd",
    "sg:city":"Biloxi",
    "sg:classifiers":[
        {
            "category":"Sports & Exercise",
            "subcategory":"Race Track",
            "type":"Entertainment"
        }
    ],
    "sg:phone":"+1 228 392 7803",
    "sg:postcode":"39532",
    "sg:province":"MS",
    "sg:tags":[
        "operation",
        "racing",
        "or"
    ],
    "wof:name":"Fox Family Racing Inc",
    "wof:placetype":"venue"
},
  "geometry": {"coordinates":[-89.032921,30.529582],"type":"Point"}
}