{
  "type": "Feature",
  "properties": {
    "iso:country":"US",
    "sg:address":"3525 Boone St",
    "sg:city":"Moss Point",
    "sg:classifiers":[
        {
            "category":"Restaurant",
            "type":"Food & Drink"
        }
    ],
    "sg:phone":"+1 228 474 2414",
    "sg:postcode":"39563",
    "sg:province":"MS",
    "wof:name":"LA Paloma",
    "wof:placetype":"venue"
},
  "geometry": {"coordinates":[-88.509576,30.391657],"type":"Point"}
}