{
  "type": "Feature",
  "properties": {
    "iso:country":"US",
    "sg:address":"1535 Hwy 45 N",
    "sg:city":"Columbus",
    "sg:classifiers":[
        {
            "category":"Restaurant",
            "type":"Food & Drink"
        }
    ],
    "sg:phone":"+1 662 329 1126",
    "sg:postcode":"39705",
    "sg:province":"MS",
    "wof:name":"Popeyes Chicken & Biscuits",
    "wof:placetype":"venue"
},
  "geometry": {"coordinates":[-88.436476,33.527341],"type":"Point"}
}