{
  "type": "Feature",
  "properties": {
    "iso:country":"US",
    "sg:address":"418 Cherokee Dr",
    "sg:city":"Oxford",
    "sg:classifiers":[
        {
            "category":"Social Services",
            "type":"Services"
        }
    ],
    "sg:phone":"+1 662 236 4993",
    "sg:postcode":"38655",
    "sg:province":"MS",
    "sg:tags":[
        "counseling"
    ],
    "wof:name":"Counseling Services Of Oxford",
    "wof:placetype":"venue"
},
  "geometry": {"coordinates":[-89.51471100000001,34.378119],"type":"Point"}
}