{
  "type": "Feature",
  "properties": {
    "iso:country":"US",
    "sg:address":"805 W Woodrow Wilson Ave",
    "sg:city":"Jackson",
    "sg:classifiers":[
        {
            "category":"Retail",
            "subcategory":"Auto Repair",
            "type":"Services"
        }
    ],
    "sg:phone":"+1 601 352 3900",
    "sg:postcode":"39213",
    "sg:province":"MS",
    "sg:tags":[
        "body",
        "automobile",
        "painting"
    ],
    "wof:name":"Triple C Auto Body Shop",
    "wof:placetype":"venue"
},
  "geometry": {"coordinates":[-90.20132099999999,32.326704],"type":"Point"}
}