{
  "type": "Feature",
  "properties": {
    "iso:country":"US",
    "sg:address":"104 Laurel St",
    "sg:city":"Mccomb",
    "sg:classifiers":[
        {
            "category":"Personal",
            "type":"Services"
        },
        {
            "category":"Personal",
            "subcategory":"Tattoo Parlor",
            "type":"Services"
        }
    ],
    "sg:phone":"+1 601 684 9100",
    "sg:postcode":"39648",
    "sg:province":"MS",
    "sg:tags":[
        "tattooing"
    ],
    "wof:name":"Tattoo's Unlimited",
    "wof:placetype":"venue"
},
  "geometry": {"coordinates":[-90.464876,31.248806],"type":"Point"}
}