{
  "type": "Feature",
  "properties": {
    "iso:country":"US",
    "sg:address":"2865 Hwy 51 S",
    "sg:city":"Hernando",
    "sg:classifiers":[
        {
            "category":"Social Services",
            "type":"Services"
        }
    ],
    "sg:phone":"+1 662 429 1389",
    "sg:postcode":"38632",
    "sg:province":"MS",
    "sg:tags":[
        "probation"
    ],
    "wof:name":"De Soto Cnty Probation Office",
    "wof:placetype":"venue"
},
  "geometry": {"coordinates":[-89.99412100000001,34.818228],"type":"Point"}
}