{
  "type": "Feature",
  "properties": {
    "iso:country":"US",
    "sg:address":"122 S Broadway St",
    "sg:city":"Mccomb",
    "sg:classifiers":[
        {
            "category":"Home & Garden",
            "subcategory":"Garden Supply",
            "type":"Retail Goods"
        }
    ],
    "sg:phone":"+1 601 684 1651",
    "sg:postcode":"39648",
    "sg:province":"MS",
    "sg:tags":[
        "nurseryman"
    ],
    "wof:name":"Pike County Cooperative Aal",
    "wof:placetype":"venue"
},
  "geometry": {"coordinates":[-90.453395,31.243145],"type":"Point"}
}