{
  "type": "Feature",
  "properties": {
    "iso:country":"US",
    "sg:address":"919 Ferncliff Cove",
    "sg:city":"Southaven",
    "sg:classifiers":[
        {
            "category":"Professional",
            "subcategory":"Lawyer & Legal Services",
            "type":"Services"
        }
    ],
    "sg:phone":"+1 662 393 8542",
    "sg:postcode":"38671",
    "sg:province":"MS",
    "sg:tags":[
        "attorney"
    ],
    "wof:name":"Davis Law Firm",
    "wof:placetype":"venue"
},
  "geometry": {"coordinates":[-90.00696000000001,34.988599],"type":"Point"}
}