{
  "type": "Feature",
  "properties": {
    "iso:country":"US",
    "sg:address":"501 Battleground Dr",
    "sg:city":"Iuka",
    "sg:classifiers":[
        {
            "category":"Freight",
            "type":"Transportation"
        }
    ],
    "sg:phone":"+1 662 423 5022",
    "sg:postcode":"38852",
    "sg:province":"MS",
    "sg:tags":[
        "commercial",
        "storage"
    ],
    "wof:name":"Iuka Mini Storage",
    "wof:placetype":"venue"
},
  "geometry": {"coordinates":[-88.199163,34.809725],"type":"Point"}
}