{
  "type": "Feature",
  "properties": {
    "iso:country":"US",
    "sg:address":"102 Lakeway Dr",
    "sg:city":"Oxford",
    "sg:classifiers":[
        {
            "category":"Professional",
            "subcategory":"Management & Consulting",
            "type":"Services"
        }
    ],
    "sg:phone":"+1 662 236 2266",
    "sg:postcode":"38655",
    "sg:province":"MS",
    "sg:tags":[
        "business"
    ],
    "wof:name":"Kishk Consulting",
    "wof:placetype":"venue"
},
  "geometry": {"coordinates":[-89.554227,34.390462],"type":"Point"}
}