{
  "type": "Feature",
  "properties": {
    "iso:country":"US",
    "sg:address":"40 Morning Dew Rd",
    "sg:city":"Laurel",
    "sg:classifiers":[
        {
            "category":"Mining & Drilling",
            "type":"Manufacturing & Wholesale Goods"
        }
    ],
    "sg:phone":"+1 601 428 5114",
    "sg:postcode":"39443",
    "sg:province":"MS",
    "sg:tags":[
        "perforating",
        "well",
        "oil",
        "logging"
    ],
    "sg:website":"www.perfolog.com",
    "wof:name":"Perf-O-Log Svc Inc",
    "wof:placetype":"venue"
},
  "geometry": {"coordinates":[-89.08768600000001,31.638302],"type":"Point"}
}