{
  "type": "Feature",
  "properties": {
    "addr:full":"1092 Airport Fernwood Rd Mccomb MS 39648",
    "addr:housenumber":"1092",
    "addr:postcode":"39648",
    "addr:street":"Airport Fernwood Rd",
    "iso:country":"US",
    "sg:address":"1092 Airport Fernwood Rd",
    "sg:city":"Mccomb",
    "sg:classifiers":[
        {
            "category":"Wholesale",
            "subcategory":"Machinery & Supplies",
            "type":"Manufacturing & Wholesale Goods"
        }
    ],
    "sg:phone":"+1 601 684 9962",
    "sg:postcode":"39648",
    "sg:province":"MS",
    "sg:tags":[
        "equipment",
        "log",
        "splitting"
    ],
    "sg:website":"www.dmequipment.com",
    "wof:name":"D-M Equipment Co",
    "wof:placetype":"venue"
},
  "geometry": {"coordinates":[-90.491083,31.18918],"type":"Point"}
}