{
  "type": "Feature",
  "properties": {
    "iso:country":"US",
    "sg:address":"100 W Main St",
    "sg:city":"New Albany",
    "sg:classifiers":[
        {
            "category":"Professional",
            "subcategory":"Lawyer & Legal Services",
            "type":"Services"
        }
    ],
    "sg:phone":"+1 662 534 6333",
    "sg:postcode":"38652",
    "sg:province":"MS",
    "sg:tags":[
        "attorney"
    ],
    "wof:name":"Regan S Russell Law Office",
    "wof:placetype":"venue"
},
  "geometry": {"coordinates":[-89.00999,34.493738],"type":"Point"}
}