{
  "type": "Feature",
  "properties": {
    "addr:full":"188 Main St Biloxi MS 39530",
    "addr:housenumber":"188",
    "addr:postcode":"39530",
    "addr:street":"Main St",
    "iso:country":"US",
    "sg:address":"188 Main St",
    "sg:city":"Biloxi",
    "sg:classifiers":[
        {
            "category":"Social Services",
            "type":"Services"
        }
    ],
    "sg:phone":"+1 228 435 5433",
    "sg:postcode":"39530",
    "sg:province":"MS",
    "sg:tags":[
        "organization",
        "welfare"
    ],
    "sg:website":"www.lifeofms.com",
    "wof:name":"Life",
    "wof:placetype":"venue"
},
  "geometry": {"coordinates":[-88.885537,30.397908],"type":"Point"}
}