{
  "type": "Feature",
  "properties": {
    "addr:full":"315 S Main St Picayune MS 39466",
    "addr:housenumber":"315",
    "addr:postcode":"39466",
    "addr:street":"S Main St",
    "iso:country":"US",
    "sg:address":"315 S Main St",
    "sg:city":"Picayune",
    "sg:classifiers":[
        {
            "category":"Insurance",
            "subcategory":"Hazard Insurance",
            "type":"Services"
        }
    ],
    "sg:phone":"+1 601 749 2338",
    "sg:postcode":"39466",
    "sg:province":"MS",
    "sg:tags":[
        "bond"
    ],
    "wof:name":"Instant Bail Bonding",
    "wof:placetype":"venue"
},
  "geometry": {"coordinates":[-89.68220599999999,30.523828],"type":"Point"}
}