{
  "type": "Feature",
  "properties": {
    "iso:country":"US",
    "sg:address":"909 Central St",
    "sg:city":"Water Valley",
    "sg:classifiers":[
        {
            "category":"Freight",
            "type":"Transportation"
        }
    ],
    "sg:phone":"+1 662 473 2656",
    "sg:postcode":"38965",
    "sg:province":"MS",
    "sg:tags":[
        "special"
    ],
    "wof:name":"J & B Rentals",
    "wof:placetype":"venue"
},
  "geometry": {"coordinates":[-89.62993899999999,34.158331],"type":"Point"}
}