{
  "type": "Feature",
  "properties": {
    "iso:country":"US",
    "sg:address":"1215 Military Rd",
    "sg:city":"Columbus",
    "sg:classifiers":[
        {
            "category":"Building & Trades",
            "subcategory":"Construction",
            "type":"Services"
        }
    ],
    "sg:phone":"+1 662 328 7235",
    "sg:postcode":"39701",
    "sg:province":"MS",
    "sg:tags":[
        "restoration",
        "cleaning",
        "patio",
        "deck"
    ],
    "wof:name":"Hill's Pressure Washing Svc",
    "wof:placetype":"venue"
},
  "geometry": {"coordinates":[-88.41927200000001,33.50775],"type":"Point"}
}