{
  "type": "Feature",
  "properties": {
    "addr:full":"601 US Hwy 90 Bay St Louis MS 39520",
    "addr:housenumber":"601",
    "addr:postcode":"39520",
    "addr:street":"Us Hwy 90",
    "iso:country":"US",
    "sg:address":"601 US Hwy 90",
    "sg:city":"Bay St Louis",
    "sg:classifiers":[
        {
            "category":"Banks & Credit Unions",
            "subcategory":"Bank",
            "type":"Services"
        }
    ],
    "sg:phone":"+1 228 466 5933",
    "sg:postcode":"39520",
    "sg:province":"MS",
    "sg:tags":[
        "state"
    ],
    "wof:name":"Hancock Bank",
    "wof:placetype":"venue"
},
  "geometry": {"coordinates":[-89.34502500000001,30.317542],"type":"Point"}
}