{
  "type": "Feature",
  "properties": {
    "iso:country":"US",
    "sg:address":"2384 Carrollton Rd",
    "sg:city":"Grenada",
    "sg:classifiers":[
        {
            "category":"Organizations",
            "subcategory":"Religious Organization",
            "type":"Services"
        }
    ],
    "sg:phone":"+1 662 226 3900",
    "sg:postcode":"38901",
    "sg:province":"MS",
    "sg:tags":[
        "church"
    ],
    "wof:name":"Family Life Ctr",
    "wof:placetype":"venue"
},
  "geometry": {"coordinates":[-89.80886099999999,33.755071],"type":"Point"}
}