{
  "type": "Feature",
  "properties": {
    "addr:full":"11186 McAlpine St Diberville MS 39540",
    "addr:housenumber":"11186",
    "addr:postcode":"39540",
    "addr:street":"Mcalpine St",
    "iso:country":"US",
    "sg:address":"11186 McAlpine St",
    "sg:city":"Diberville",
    "sg:classifiers":[
        {
            "category":"Shopping",
            "type":"Retail Goods"
        }
    ],
    "sg:phone":"+1 228 392 8674",
    "sg:postcode":"39540",
    "sg:province":"MS",
    "sg:tags":[
        "typewriter"
    ],
    "wof:name":"Seacoast Business Machines",
    "wof:placetype":"venue"
},
  "geometry": {"coordinates":[-88.90014499999999,30.44808],"type":"Point"}
}