{
  "type": "Feature",
  "properties": {
    "iso:country":"US",
    "sg:address":"53 Holcomb Carroll Rd",
    "sg:city":"Carriere",
    "sg:classifiers":[
        {
            "category":"Building & Trades",
            "subcategory":"Construction",
            "type":"Services"
        }
    ],
    "sg:phone":"+1 601 799 1844",
    "sg:postcode":"39426",
    "sg:province":"MS",
    "sg:tags":[
        "house"
    ],
    "wof:name":"Cagle Construction",
    "wof:placetype":"venue"
},
  "geometry": {"coordinates":[-89.676497,30.631507],"type":"Point"}
}