{
  "type": "Feature",
  "properties": {
    "addr:full":"450 Stateline Rd E Southaven MS 38671",
    "addr:housenumber":"450",
    "addr:postcode":"38671",
    "addr:street":"Stateline Rd E",
    "iso:country":"US",
    "sg:address":"450 Stateline Rd E",
    "sg:city":"Southaven",
    "sg:classifiers":[
        {
            "category":"Banks & Credit Unions",
            "subcategory":"Bank",
            "type":"Services"
        }
    ],
    "sg:phone":"+1 662 280 1139",
    "sg:postcode":"38671",
    "sg:province":"MS",
    "sg:tags":[
        "cashing",
        "personal",
        "check",
        "institution"
    ],
    "wof:name":"Advance America",
    "wof:placetype":"venue"
},
  "geometry": {"coordinates":[-89.978202,34.991888],"type":"Point"}
}