{
  "type": "Feature",
  "properties": {
    "addr:full":"519 S Gloster St Tupelo MS 38801",
    "addr:housenumber":"519",
    "addr:postcode":"38801",
    "addr:street":"S Gloster St",
    "iso:country":"US",
    "sg:address":"519 S Gloster St",
    "sg:city":"Tupelo",
    "sg:classifiers":[
        {
            "category":"Personal",
            "subcategory":"Barber",
            "type":"Services"
        }
    ],
    "sg:phone":"+1 662 841 2276",
    "sg:postcode":"38801",
    "sg:province":"MS",
    "sg:tags":[
        "shop"
    ],
    "wof:name":"Larry's Barber Shop",
    "wof:placetype":"venue"
},
  "geometry": {"coordinates":[-88.71658600000001,34.249913],"type":"Point"}
}