{
  "type": "Feature",
  "properties": {
    "addr:full":"2153 Main St Ethel MS 39074",
    "addr:housenumber":"2153",
    "addr:postcode":"39074",
    "addr:street":"Main St",
    "iso:country":"US",
    "sg:address":"2153 Main St",
    "sg:city":"Ethel",
    "sg:classifiers":[
        {
            "category":"Food & Beverages",
            "subcategory":"Groceries & Convenience Stores",
            "type":"Retail Goods"
        }
    ],
    "sg:phone":"+1 662 674 5034",
    "sg:postcode":"39074",
    "sg:province":"MS",
    "wof:name":"Dotsons Grocery",
    "wof:placetype":"venue"
},
  "geometry": {"coordinates":[-89.47366700000001,32.349],"type":"Point"}
}