{
  "type": "Feature",
  "properties": {
    "iso:country":"US",
    "sg:address":"405 Maryland Ave",
    "sg:city":"Mccomb",
    "sg:classifiers":[
        {
            "category":"Government",
            "subcategory":"Office",
            "type":"Public Place"
        }
    ],
    "sg:phone":"+1 601 684 9503",
    "sg:postcode":"39648",
    "sg:province":"MS",
    "wof:name":"Section 8 Housing",
    "wof:placetype":"venue"
},
  "geometry": {"coordinates":[-90.455271,31.246015],"type":"Point"}
}