{
  "type": "Feature",
  "properties": {
    "addr:full":"426 Delmar Ave Ruleville MS 38771",
    "addr:housenumber":"426",
    "addr:postcode":"38771",
    "addr:street":"Delmar Ave",
    "iso:country":"US",
    "sg:address":"426 Delmar Ave",
    "sg:city":"Ruleville",
    "sg:classifiers":[
        {
            "category":"Organizations",
            "subcategory":"Religious Organization",
            "type":"Services"
        }
    ],
    "sg:phone":"+1 662 756 2573",
    "sg:postcode":"38771",
    "sg:province":"MS",
    "sg:tags":[
        "church"
    ],
    "wof:name":"Church Of Christ Of Ruleville",
    "wof:placetype":"venue"
},
  "geometry": {"coordinates":[-90.547923,33.728826],"type":"Point"}
}