{
  "type": "Feature",
  "properties": {
    "addr:full":"819 Larson St Jackson MS 39202",
    "addr:housenumber":"819",
    "addr:postcode":"39202",
    "addr:street":"Larson St",
    "iso:country":"US",
    "sg:address":"819 Larson St",
    "sg:city":"Jackson",
    "sg:classifiers":[
        {
            "category":"Manufacturing",
            "subcategory":"Tools & Machinery",
            "type":"Manufacturing & Wholesale Goods"
        }
    ],
    "sg:phone":"+1 601 944 0880",
    "sg:postcode":"39202",
    "sg:province":"MS",
    "sg:tags":[
        "equipment",
        "irrigation",
        "system"
    ],
    "wof:name":"Keeling Co",
    "wof:placetype":"venue"
},
  "geometry": {"coordinates":[-90.167241,32.309399],"type":"Point"}
}