{
  "type": "Feature",
  "properties": {
    "iso:country":"US",
    "sg:address":"209 N 2nd St",
    "sg:city":"Baldwyn",
    "sg:classifiers":[
        {
            "category":"Shopping",
            "subcategory":"Discount & Variety Stores",
            "type":"Retail Goods"
        },
        {
            "category":"Shopping",
            "subcategory":"Department Store",
            "type":"Retail Goods"
        }
    ],
    "sg:phone":"+1 662 365 5144",
    "sg:postcode":"38824",
    "sg:province":"MS",
    "sg:tags":[
        "shop"
    ],
    "wof:name":"Family Dollar Stores",
    "wof:placetype":"venue"
},
  "geometry": {"coordinates":[-88.632958,34.510843],"type":"Point"}
}