{
  "type": "Feature",
  "properties": {
    "iso:country":"US",
    "sg:address":"2525 Lincoln Rd",
    "sg:city":"Hattiesburg",
    "sg:classifiers":[
        {
            "category":"Shopping",
            "subcategory":"Books",
            "type":"Retail Goods"
        }
    ],
    "sg:phone":"+1 601 268 7675",
    "sg:postcode":"39402",
    "sg:province":"MS",
    "sg:tags":[
        "comic"
    ],
    "wof:name":"Comics & Stuff",
    "wof:placetype":"venue"
},
  "geometry": {"coordinates":[-89.32849899999999,31.304177],"type":"Point"}
}