{
  "type": "Feature",
  "properties": {
    "iso:country":"US",
    "sg:address":"322 Laughlin Rd",
    "sg:city":"Cleveland",
    "sg:classifiers":[
        {
            "category":"Freight",
            "type":"Transportation"
        }
    ],
    "sg:phone":"+1 662 843 1965",
    "sg:postcode":"38732",
    "sg:province":"MS",
    "wof:name":"Dry Bayou Transports Inc",
    "wof:placetype":"venue"
},
  "geometry": {"coordinates":[-90.730439,33.718581],"type":"Point"}
}