{
  "type": "Feature",
  "properties": {
    "addr:full":"311 S Parkway St Corinth MS 38834",
    "addr:housenumber":"311",
    "addr:postcode":"38834",
    "addr:street":"S Parkway St",
    "iso:country":"US",
    "sg:address":"311 S Parkway St",
    "sg:city":"Corinth",
    "sg:classifiers":[
        {
            "category":"Professional",
            "subcategory":"Computer Services",
            "type":"Services"
        }
    ],
    "sg:phone":"+1 301 469 0304",
    "sg:postcode":"38834",
    "sg:province":"MS",
    "sg:tags":[
        "system",
        "integration"
    ],
    "wof:name":"Mississippi Science Engrg Tech",
    "wof:placetype":"venue"
},
  "geometry": {"coordinates":[-88.50569,34.925962],"type":"Point"}
}