{
  "type": "Feature",
  "properties": {
    "iso:country":"US",
    "sg:address":"214 S Bolivar Ave",
    "sg:city":"Cleveland",
    "sg:classifiers":[
        {
            "category":"Manufacturing",
            "subcategory":"Paper Products",
            "type":"Manufacturing & Wholesale Goods"
        },
        {
            "category":"Travel",
            "subcategory":"Hotels & Motels",
            "type":"Entertainment"
        }
    ],
    "sg:phone":"+1 662 843 9913",
    "sg:postcode":"38732",
    "sg:province":"MS",
    "sg:tags":[
        "operation"
    ],
    "wof:name":"Molly's Bed & Breakfast",
    "wof:placetype":"venue"
},
  "geometry": {"coordinates":[-90.72509700000001,33.742851],"type":"Point"}
}