{
  "type": "Feature",
  "properties": {
    "iso:country":"US",
    "sg:address":"243 Delta Ave",
    "sg:city":"Clarksdale",
    "sg:classifiers":[
        {
            "category":"Professional",
            "type":"Services"
        }
    ],
    "sg:phone":"+1 662 621 2427",
    "sg:postcode":"38614",
    "sg:province":"MS",
    "sg:tags":[
        "establishment"
    ],
    "wof:name":"Pop's",
    "wof:placetype":"venue"
},
  "geometry": {"coordinates":[-90.574844,34.201774],"type":"Point"}
}