{
  "type": "Feature",
  "properties": {
    "addr:full":"4101 Gautier Vancleave Rd Gautier MS 39553",
    "addr:housenumber":"4101",
    "addr:postcode":"39553",
    "addr:street":"Gautier Vancleave Rd",
    "iso:country":"US",
    "sg:address":"4101 Gautier Vancleave Rd",
    "sg:city":"Gautier",
    "sg:classifiers":[
        {
            "category":"Professional",
            "subcategory":"Management & Consulting",
            "type":"Services"
        }
    ],
    "sg:phone":"+1 228 497 6966",
    "sg:postcode":"39553",
    "sg:province":"MS",
    "sg:tags":[
        "consultant"
    ],
    "sg:website":"www.marcgold.com",
    "wof:name":"Marc Gold & Assoc",
    "wof:placetype":"venue"
},
  "geometry": {"coordinates":[-88.65454200000001,30.402281],"type":"Point"}
}