{
  "type": "Feature",
  "properties": {
    "iso:country":"US",
    "sg:address":"717 Bienville Blvd",
    "sg:city":"Ocean Springs",
    "sg:classifiers":[
        {
            "category":"Recreation",
            "type":"Entertainment"
        }
    ],
    "sg:phone":"+1 228 872 7223",
    "sg:postcode":"39564",
    "sg:province":"MS",
    "sg:tags":[
        "amusement"
    ],
    "wof:name":"USA Patriot Motor Sports",
    "wof:placetype":"venue"
},
  "geometry": {"coordinates":[-88.832303,30.416088],"type":"Point"}
}