{
  "type": "Feature",
  "properties": {
    "iso:country":"US",
    "sg:address":"1013 State Hwy 550",
    "sg:city":"Brookhaven",
    "sg:classifiers":[
        {
            "category":"Home & Garden",
            "subcategory":"Building Materials",
            "type":"Retail Goods"
        }
    ],
    "sg:phone":"+1 601 823 6202",
    "sg:postcode":"39601",
    "sg:province":"MS",
    "sg:tags":[
        "glass",
        "window",
        "plate"
    ],
    "wof:name":"Skates Glass LLC",
    "wof:placetype":"venue"
},
  "geometry": {"coordinates":[-90.421305,31.574427],"type":"Point"}
}