{
  "type": "Feature",
  "properties": {
    "iso:country":"US",
    "sg:address":"112 N Madison St",
    "sg:city":"Tupelo",
    "sg:classifiers":[
        {
            "category":"Banks & Credit Unions",
            "subcategory":"Investment Brokerage",
            "type":"Services"
        }
    ],
    "sg:phone":"+1 662 844 4600",
    "sg:postcode":"38804",
    "sg:province":"MS",
    "sg:tags":[
        "stock",
        "bond"
    ],
    "wof:name":"Morgan Stanley",
    "wof:placetype":"venue"
},
  "geometry": {"coordinates":[-88.711179,34.257976],"type":"Point"}
}