{
  "type": "Feature",
  "properties": {
    "iso:country":"US",
    "sg:address":"4848 E Main St",
    "sg:city":"Flora",
    "sg:classifiers":[
        {
            "category":"Professional",
            "subcategory":"Lawyer & Legal Services",
            "type":"Services"
        }
    ],
    "sg:phone":"+1 601 879 3532",
    "sg:postcode":"39071",
    "sg:province":"MS",
    "sg:tags":[
        "attorney"
    ],
    "wof:name":"Hazel Cunningham",
    "wof:placetype":"venue"
},
  "geometry": {"coordinates":[-90.310754,32.54282],"type":"Point"}
}