{
  "type": "Feature",
  "properties": {
    "addr:full":"5054 N State St Jackson MS 39206",
    "addr:housenumber":"5054",
    "addr:postcode":"39206",
    "addr:street":"N State St",
    "iso:country":"US",
    "sg:address":"5054 N State St",
    "sg:city":"Jackson",
    "sg:classifiers":[
        {
            "category":"Shopping",
            "subcategory":"Clothing, Apparel, & Fashions",
            "type":"Retail Goods"
        }
    ],
    "sg:phone":"+1 601 982 4194",
    "sg:postcode":"39206",
    "sg:province":"MS",
    "sg:tags":[
        "alteration"
    ],
    "wof:name":"Janice's Creative Sewing",
    "wof:placetype":"venue"
},
  "geometry": {"coordinates":[-90.17064000000001,32.364382],"type":"Point"}
}