{
  "type": "Feature",
  "properties": {
    "addr:full":"21312 State Line Rd Moss Point MS 39562",
    "addr:housenumber":"21312",
    "addr:postcode":"39562",
    "addr:street":"State Line Rd",
    "iso:country":"US",
    "sg:address":"21312 State Line Rd",
    "sg:city":"Moss Point",
    "sg:classifiers":[
        {
            "category":"Banks & Credit Unions",
            "subcategory":"Bank",
            "type":"Services"
        }
    ],
    "sg:phone":"+1 228 588 2281",
    "sg:postcode":"39562",
    "sg:province":"MS",
    "sg:tags":[
        "institution",
        "business"
    ],
    "wof:name":"Arena Investments LLC",
    "wof:placetype":"venue"
},
  "geometry": {"coordinates":[-88.411828,30.666903],"type":"Point"}
}