{
  "type": "Feature",
  "properties": {
    "addr:full":"138 Cedar Ridge Rd Raymond MS 39154",
    "addr:housenumber":"138",
    "addr:postcode":"39154",
    "addr:street":"Cedar Ridge Rd",
    "iso:country":"US",
    "sg:address":"138 Cedar Ridge Rd",
    "sg:city":"Raymond",
    "sg:classifiers":[
        {
            "category":"Wholesale",
            "subcategory":"Office Equipment",
            "type":"Manufacturing & Wholesale Goods"
        }
    ],
    "sg:phone":"+1 601 857 8689",
    "sg:postcode":"39154",
    "sg:province":"MS",
    "sg:tags":[
        "machine",
        "duplicating",
        "copying"
    ],
    "wof:name":"Office Products Co",
    "wof:placetype":"venue"
},
  "geometry": {"coordinates":[-90.445103,32.223182],"type":"Point"}
}