{
  "type": "Feature",
  "properties": {
    "addr:full":"406 Liberty Rd Natchez MS 39120",
    "addr:housenumber":"406",
    "addr:postcode":"39120",
    "addr:street":"Liberty Rd",
    "iso:country":"US",
    "sg:address":"406 Liberty Rd",
    "sg:city":"Natchez",
    "sg:classifiers":[
        {
            "category":"Manufacturing",
            "subcategory":"Tools & Machinery",
            "type":"Manufacturing & Wholesale Goods"
        }
    ],
    "sg:phone":"+1 601 445 0040",
    "sg:postcode":"39120",
    "sg:province":"MS",
    "sg:tags":[
        "water",
        "well",
        "drilling"
    ],
    "wof:name":"Rayborn Inc",
    "wof:placetype":"venue"
},
  "geometry": {"coordinates":[-91.366114,31.543844],"type":"Point"}
}