{
  "type": "Feature",
  "properties": {
    "iso:country":"US",
    "sg:address":"200 Arlington Loop",
    "sg:city":"Beaumont",
    "sg:classifiers":[
        {
            "category":"Organizations",
            "subcategory":"Professional Association",
            "type":"Services"
        }
    ],
    "sg:phone":"+1 601 784 3776",
    "sg:postcode":"39423",
    "sg:province":"MS",
    "wof:name":"Arlington Water Assn",
    "wof:placetype":"venue"
},
  "geometry": {"coordinates":[-88.87492899999999,31.20814],"type":"Point"}
}