{
  "type": "Feature",
  "properties": {
    "iso:country":"US",
    "sg:address":"515 S 2nd Ave",
    "sg:city":"Columbus",
    "sg:classifiers":[
        {
            "category":"Government",
            "subcategory":"Fire Station",
            "type":"Public Place"
        }
    ],
    "sg:phone":"+1 662 329 5110",
    "sg:postcode":"39701",
    "sg:province":"MS",
    "sg:tags":[
        "department"
    ],
    "wof:name":"Lowndes County Fire Dept",
    "wof:placetype":"venue"
},
  "geometry": {"coordinates":[-88.426839,33.494177],"type":"Point"}
}