{
  "type": "Feature",
  "properties": {
    "iso:country":"US",
    "sg:address":"8226 Mississippi Ave",
    "sg:city":"Gulfport",
    "sg:classifiers":[
        {
            "category":"Organizations",
            "subcategory":"Religious Organization",
            "type":"Services"
        }
    ],
    "sg:phone":"+1 228 864 8856",
    "sg:postcode":"39501",
    "sg:province":"MS",
    "sg:tags":[
        "church"
    ],
    "wof:name":"Full Gospel Holiness Church",
    "wof:placetype":"venue"
},
  "geometry": {"coordinates":[-89.091117,30.404363],"type":"Point"}
}