{
  "type": "Feature",
  "properties": {
    "iso:country":"US",
    "sg:address":"263 Co Rd 147",
    "sg:city":"Verona",
    "sg:classifiers":[
        {
            "category":"Restaurant",
            "type":"Food & Drink"
        }
    ],
    "sg:phone":"+1 662 566 2555",
    "sg:postcode":"38873",
    "sg:province":"MS",
    "sg:tags":[
        "out"
    ],
    "wof:name":"Johnny's Dairy Bar",
    "wof:placetype":"venue"
},
  "geometry": {"coordinates":[-88.23799,34.70117],"type":"Point"}
}