{
  "type": "Feature",
  "properties": {
    "iso:country":"US",
    "sg:address":"4500 I- 55 N",
    "sg:city":"Jackson",
    "sg:classifiers":[
        {
            "category":"Social Services",
            "type":"Services"
        }
    ],
    "sg:phone":"+1 601 982 5943",
    "sg:postcode":"39211",
    "sg:province":"MS",
    "sg:tags":[
        "counseling"
    ],
    "wof:name":"John Owen Recovery Conslnts",
    "wof:placetype":"venue"
},
  "geometry": {"coordinates":[-90.15299899999999,32.350564],"type":"Point"}
}