{
  "type": "Feature",
  "properties": {
    "addr:full":"5837 White Ridge Cir W Olive Branch MS 38654",
    "addr:housenumber":"5837",
    "addr:postcode":"38654",
    "addr:street":"White Ridge Cir W",
    "iso:country":"US",
    "sg:address":"5837 White Ridge Cir W",
    "sg:city":"Olive Branch",
    "sg:classifiers":[
        {
            "category":"Real Estate",
            "subcategory":"Real Estate Agent",
            "type":"Services"
        }
    ],
    "sg:phone":"+1 662 893 0249",
    "sg:postcode":"38654",
    "sg:province":"MS",
    "sg:tags":[
        "finding",
        "apartment",
        "rental"
    ],
    "wof:name":"Corporate Quarters",
    "wof:placetype":"venue"
},
  "geometry": {"coordinates":[-89.814493,34.945208],"type":"Point"}
}