{
  "type": "Feature",
  "properties": {
    "addr:full":"429 Azalea Dr Waynesboro MS 39367",
    "addr:housenumber":"429",
    "addr:postcode":"39367",
    "addr:street":"Azalea Dr",
    "iso:country":"US",
    "sg:address":"429 Azalea Dr",
    "sg:city":"Waynesboro",
    "sg:classifiers":[
        {
            "category":"Personal",
            "subcategory":"Beauty Salon",
            "type":"Services"
        }
    ],
    "sg:phone":"+1 601 671 8881",
    "sg:postcode":"39367",
    "sg:province":"MS",
    "sg:tags":[
        "shop"
    ],
    "wof:name":"Beauty Zone",
    "wof:placetype":"venue"
},
  "geometry": {"coordinates":[-88.65263299999999,31.671313],"type":"Point"}
}