{
  "type": "Feature",
  "properties": {
    "iso:country":"US",
    "sg:address":"1769 Hwy 25 S",
    "sg:city":"Starkville",
    "sg:classifiers":[
        {
            "category":"Social Services",
            "type":"Services"
        }
    ],
    "sg:phone":"+1 662 338 9070",
    "sg:postcode":"39759",
    "sg:province":"MS",
    "sg:tags":[
        "organization",
        "welfare"
    ],
    "wof:name":"Veterans Of Foreign Wars 5573",
    "wof:placetype":"venue"
},
  "geometry": {"coordinates":[-88.841539,33.415524],"type":"Point"}
}