{
  "type": "Feature",
  "properties": {
    "addr:full":"104 Depot St Lexington MS 39095",
    "addr:housenumber":"104",
    "addr:postcode":"39095",
    "addr:street":"Depot St",
    "iso:country":"US",
    "sg:address":"104 Depot St",
    "sg:city":"Lexington",
    "sg:classifiers":[
        {
            "category":"Shopping",
            "subcategory":"Music",
            "type":"Retail Goods"
        }
    ],
    "sg:phone":"+1 662 834 0101",
    "sg:postcode":"39095",
    "sg:province":"MS",
    "wof:name":"Life Music",
    "wof:placetype":"venue"
},
  "geometry": {"coordinates":[-90.052222,33.112864],"type":"Point"}
}