{
  "type": "Feature",
  "properties": {
    "addr:full":"1090 E McDowell Rd Jackson MS 39204",
    "addr:housenumber":"1090",
    "addr:postcode":"39204",
    "addr:street":"E Mcdowell Rd",
    "iso:country":"US",
    "sg:address":"1090 E McDowell Rd",
    "sg:city":"Jackson",
    "sg:classifiers":[
        {
            "category":"Freight",
            "type":"Transportation"
        }
    ],
    "sg:phone":"+1 601 969 5848",
    "sg:postcode":"39204",
    "sg:province":"MS",
    "sg:tags":[
        "trucking"
    ],
    "sg:website":"www.usfdugan.com",
    "wof:name":"USF Dugan Inc",
    "wof:placetype":"venue"
},
  "geometry": {"coordinates":[-90.19751100000001,32.268305],"type":"Point"}
}