{
  "type": "Feature",
  "properties": {
    "iso:country":"US",
    "sg:address":"12056 Cedar Lake Rd",
    "sg:city":"Biloxi",
    "sg:classifiers":[
        {
            "category":"Shopping",
            "subcategory":"Bicycles & Sporting Goods",
            "type":"Retail Goods"
        }
    ],
    "sg:phone":"+1 228 392 0852",
    "sg:postcode":"39532",
    "sg:province":"MS",
    "wof:name":"Lil Joes Cedar Lk Fishing Camp",
    "wof:placetype":"venue"
},
  "geometry": {"coordinates":[-88.93885400000001,30.458599],"type":"Point"}
}