{
  "type": "Feature",
  "properties": {
    "iso:country":"US",
    "sg:address":"430 Earle St",
    "sg:city":"Jackson",
    "sg:classifiers":[
        {
            "category":"Health Services",
            "subcategory":"Nursing And Care Facility",
            "type":"Services"
        }
    ],
    "sg:phone":"+1 601 352 6161",
    "sg:postcode":"39203",
    "sg:province":"MS",
    "sg:tags":[
        "home",
        "retirement",
        "community"
    ],
    "wof:name":"Izora's Personal Care Home",
    "wof:placetype":"venue"
},
  "geometry": {"coordinates":[-90.193957,32.295925],"type":"Point"}
}