{
  "type": "Feature",
  "properties": {
    "addr:full":"20015 Red Dr Aberdeen MS 39730",
    "addr:housenumber":"20015",
    "addr:postcode":"39730",
    "addr:street":"Red Dr",
    "iso:country":"US",
    "sg:address":"20015 Red Dr",
    "sg:city":"Aberdeen",
    "sg:classifiers":[
        {
            "category":"Building & Trades",
            "subcategory":"Plumbing",
            "type":"Services"
        }
    ],
    "sg:phone":"+1 662 319 9022",
    "sg:postcode":"39730",
    "sg:province":"MS",
    "sg:tags":[
        "plumbing",
        "contractor"
    ],
    "wof:name":"Red's Handyman",
    "wof:placetype":"venue"
},
  "geometry": {"coordinates":[-88.659566,33.916643],"type":"Point"}
}