{
  "type": "Feature",
  "properties": {
    "iso:country":"US",
    "sg:address":"3449 Hwy 6",
    "sg:city":"Plantersville",
    "sg:classifiers":[
        {
            "category":"Building & Trades",
            "subcategory":"Construction",
            "type":"Services"
        },
        {
            "category":"Home & Garden",
            "subcategory":"Furniture",
            "type":"Retail Goods"
        }
    ],
    "sg:phone":"+1 662 844 1368",
    "sg:postcode":"38862",
    "sg:province":"MS",
    "sg:tags":[
        "household",
        "appliance",
        "maker",
        "cabinet"
    ],
    "wof:name":"Pettigrew Cabinet's Inc",
    "wof:placetype":"venue"
},
  "geometry": {"coordinates":[-88.64858700000001,34.162847],"type":"Point"}
}