{
  "type": "Feature",
  "properties": {
    "iso:country":"US",
    "sg:address":"1131 Richburg Rd",
    "sg:city":"Hattiesburg",
    "sg:classifiers":[
        {
            "category":"Organizations",
            "subcategory":"Religious Organization",
            "type":"Services"
        }
    ],
    "sg:phone":"+1 601 264 0593",
    "sg:postcode":"39402",
    "sg:province":"MS",
    "sg:tags":[
        "church"
    ],
    "sg:website":"www.gracetemple.com",
    "wof:name":"Grace Temple",
    "wof:placetype":"venue"
},
  "geometry": {"coordinates":[-89.335694,31.285607],"type":"Point"}
}