{
  "type": "Feature",
  "properties": {
    "iso:country":"US",
    "sg:address":"912 Robinson St",
    "sg:city":"Waynesboro",
    "sg:classifiers":[
        {
            "category":"Shopping",
            "subcategory":"Department Store",
            "type":"Retail Goods"
        }
    ],
    "sg:phone":"+1 601 735 0670",
    "sg:postcode":"39367",
    "sg:province":"MS",
    "wof:name":"Hudsons Inc",
    "wof:placetype":"venue"
},
  "geometry": {"coordinates":[-88.64357699999999,31.680997],"type":"Point"}
}