{
  "type": "Feature",
  "properties": {
    "iso:country":"US",
    "sg:address":"221 Clinton Blvd",
    "sg:city":"Clinton",
    "sg:classifiers":[
        {
            "category":"Autos & Motor Vehicles",
            "subcategory":"Fuel & Gas Station",
            "type":"Retail Goods"
        }
    ],
    "sg:phone":"+1 601 924 4749",
    "sg:postcode":"39056",
    "sg:province":"MS",
    "sg:tags":[
        "station",
        "gasoline"
    ],
    "wof:name":"Chevron",
    "wof:placetype":"venue"
},
  "geometry": {"coordinates":[-90.314302,32.335012],"type":"Point"}
}