{
  "type": "Feature",
  "properties": {
    "addr:full":"524 Main St Philadelphia MS 39350",
    "addr:housenumber":"524",
    "addr:postcode":"39350",
    "addr:street":"Main St",
    "iso:country":"US",
    "sg:address":"524 Main St",
    "sg:city":"Philadelphia",
    "sg:classifiers":[
        {
            "category":"Shopping",
            "subcategory":"Stationery & Office Supplies",
            "type":"Retail Goods"
        }
    ],
    "sg:phone":"+1 601 656 3546",
    "sg:postcode":"39350",
    "sg:province":"MS",
    "wof:name":"Curtis Office Supply",
    "wof:placetype":"venue"
},
  "geometry": {"coordinates":[-89.108924,32.770875],"type":"Point"}
}