{
  "type": "Feature",
  "properties": {
    "iso:country":"US",
    "sg:address":"1317 24th Ave",
    "sg:city":"Gulfport",
    "sg:classifiers":[
        {
            "category":"Restaurant",
            "type":"Food & Drink"
        }
    ],
    "sg:phone":"+1 228 864 3848",
    "sg:postcode":"39501",
    "sg:province":"MS",
    "sg:tags":[
        "barbecue"
    ],
    "wof:name":"Dirty South Bbq & Gumbo",
    "wof:placetype":"venue"
},
  "geometry": {"coordinates":[-89.091487,30.367155],"type":"Point"}
}