{
  "type": "Feature",
  "properties": {
    "addr:full":"1900 Denny Ave Pascagoula MS 39567",
    "addr:postcode":"1900;39567",
    "addr:street":"Denny Ave",
    "iso:country":"US",
    "sg:address":"1900 Denny Ave",
    "sg:city":"Pascagoula",
    "sg:classifiers":[
        {
            "category":"Home & Garden",
            "subcategory":"Furniture",
            "type":"Retail Goods"
        }
    ],
    "sg:phone":"+1 228 769 7006",
    "sg:postcode":"39567",
    "sg:province":"MS",
    "sg:tags":[
        "mattress"
    ],
    "wof:name":"Sleep King",
    "wof:placetype":"venue"
},
  "geometry": {"coordinates":[-88.54234,30.3708],"type":"Point"}
}