{
  "type": "Feature",
  "properties": {
    "iso:country":"US",
    "sg:address":"888 Hwy 16 W",
    "sg:city":"Holly Bluff",
    "sg:classifiers":[
        {
            "category":"Banks & Credit Unions",
            "subcategory":"Bank",
            "type":"Services"
        }
    ],
    "sg:phone":"+1 662 828 3231",
    "sg:postcode":"39088",
    "sg:province":"MS",
    "wof:name":"Bank Plus",
    "wof:placetype":"venue"
},
  "geometry": {"coordinates":[-90.70907,32.821469],"type":"Point"}
}