{
  "type": "Feature",
  "properties": {
    "iso:country":"US",
    "sg:address":"2809 Denny Ave",
    "sg:city":"Pascagoula",
    "sg:classifiers":[
        {
            "category":"Local Transit",
            "type":"Transportation"
        }
    ],
    "sg:phone":"+1 228 769 7095",
    "sg:postcode":"39581",
    "sg:province":"MS",
    "sg:tags":[
        "passenger"
    ],
    "wof:name":"Acadian Ambulance & A Med Svcs",
    "wof:placetype":"venue"
},
  "geometry": {"coordinates":[-88.532681,30.374625],"type":"Point"}
}