{
  "type": "Feature",
  "properties": {
    "iso:country":"US",
    "sg:address":"203 8th St",
    "sg:city":"Leland",
    "sg:classifiers":[
        {
            "category":"Personal",
            "subcategory":"Beauty Salon",
            "type":"Services"
        }
    ],
    "sg:phone":"+1 662 686 2466",
    "sg:postcode":"38725",
    "sg:province":"MS",
    "sg:tags":[
        "shop"
    ],
    "wof:name":"Rosetta's Beauty Box",
    "wof:placetype":"venue"
},
  "geometry": {"coordinates":[-91.0068,33.647997],"type":"Point"}
}