{
  "type": "Feature",
  "properties": {
    "addr:full":"3275 State Hwy 371 N Mantachie MS 38876",
    "addr:housenumber":"3275",
    "addr:postcode":"38876",
    "addr:street":"State Hwy 371 N",
    "iso:country":"US",
    "sg:address":"3275 State Hwy 371 N",
    "sg:city":"Mantachie",
    "sg:classifiers":[
        {
            "category":"Food & Beverages",
            "subcategory":"Groceries & Convenience Stores",
            "type":"Retail Goods"
        }
    ],
    "sg:phone":"+1 662 282 4642",
    "sg:postcode":"38876",
    "sg:province":"MS",
    "sg:tags":[
        "grocer"
    ],
    "wof:name":"Mantachie Foods",
    "wof:placetype":"venue"
},
  "geometry": {"coordinates":[-88.493099,34.31714],"type":"Point"}
}