{
  "type": "Feature",
  "properties": {
    "addr:full":"711 Old Richton Rd Petal MS 39465",
    "addr:housenumber":"711",
    "addr:postcode":"39465",
    "addr:street":"Old Richton Rd",
    "iso:country":"US",
    "sg:address":"711 Old Richton Rd",
    "sg:city":"Petal",
    "sg:classifiers":[
        {
            "category":"Organizations",
            "subcategory":"Religious Organization",
            "type":"Services"
        }
    ],
    "sg:phone":"+1 601 582 2450",
    "sg:postcode":"39465",
    "sg:province":"MS",
    "sg:tags":[
        "church"
    ],
    "wof:name":"Green's Creek Baptist Church",
    "wof:placetype":"venue"
},
  "geometry": {"coordinates":[-89.248728,31.356764],"type":"Point"}
}