{
  "type": "Feature",
  "properties": {
    "iso:country":"US",
    "sg:address":"115 Pow Wow Trl",
    "sg:city":"Tupelo",
    "sg:classifiers":[
        {
            "category":"Retail",
            "subcategory":"Portrait Studio",
            "type":"Services"
        }
    ],
    "sg:phone":"+1 662 840 1465",
    "sg:postcode":"38804",
    "sg:province":"MS",
    "sg:tags":[
        "photo"
    ],
    "wof:name":"Luanne Burnett Photography",
    "wof:placetype":"venue"
},
  "geometry": {"coordinates":[-88.63802800000001,34.324925],"type":"Point"}
}