{
  "type": "Feature",
  "properties": {
    "iso:country":"US",
    "sg:address":"225 E Jackson St",
    "sg:city":"Ridgeland",
    "sg:classifiers":[
        {
            "category":"Building & Trades",
            "subcategory":"Construction",
            "type":"Services"
        }
    ],
    "sg:phone":"+1 601 853 6894",
    "sg:postcode":"39157",
    "sg:province":"MS",
    "sg:tags":[
        "house"
    ],
    "wof:name":"Huddleston Construction G",
    "wof:placetype":"venue"
},
  "geometry": {"coordinates":[-90.126344,32.428538],"type":"Point"}
}