{
  "type": "Feature",
  "properties": {
    "addr:full":"1408 Old Aberdeen Rd Columbus MS 39705",
    "addr:housenumber":"1408",
    "addr:postcode":"39705",
    "addr:street":"Old Aberdeen Rd",
    "iso:country":"US",
    "sg:address":"1408 Old Aberdeen Rd",
    "sg:city":"Columbus",
    "sg:classifiers":[
        {
            "category":"Shopping",
            "subcategory":"Department Store",
            "type":"Retail Goods"
        }
    ],
    "sg:phone":"+1 662 328 1160",
    "sg:postcode":"39705",
    "sg:province":"MS",
    "sg:tags":[
        "shop"
    ],
    "wof:name":"Dollar Tree",
    "wof:placetype":"venue"
},
  "geometry": {"coordinates":[-88.433204,33.517533],"type":"Point"}
}