{
  "type": "Feature",
  "properties": {
    "iso:country":"US",
    "sg:address":"2343 Getwell Rd",
    "sg:city":"Nesbit",
    "sg:classifiers":[
        {
            "category":"Organizations",
            "subcategory":"Membership Organization",
            "type":"Services"
        }
    ],
    "sg:phone":"+1 662 429 0094",
    "sg:postcode":"38651",
    "sg:province":"MS",
    "wof:name":"American Ex Prisoners of War",
    "wof:placetype":"venue"
},
  "geometry": {"coordinates":[-89.937062,34.894981],"type":"Point"}
}