{
  "type": "Feature",
  "properties": {
    "iso:country":"US",
    "sg:address":"2049 Goodman Rd W",
    "sg:city":"Horn Lake",
    "sg:classifiers":[
        {
            "category":"Banks & Credit Unions",
            "subcategory":"Bank",
            "type":"Services"
        }
    ],
    "sg:phone":"+1 662 280 4660",
    "sg:postcode":"38637",
    "sg:province":"MS",
    "sg:tags":[
        "cashing",
        "check"
    ],
    "wof:name":"Cash Depot",
    "wof:placetype":"venue"
},
  "geometry": {"coordinates":[-90.02504999999999,34.962575],"type":"Point"}
}