{
  "type": "Feature",
  "properties": {
    "iso:country":"US",
    "sg:address":"3535 Stateline Rd W",
    "sg:city":"Southaven",
    "sg:classifiers":[
        {
            "category":"Wholesale",
            "subcategory":"Toys & Hobbies",
            "type":"Manufacturing & Wholesale Goods"
        }
    ],
    "sg:phone":"+1 662 393 2397",
    "sg:postcode":"38671",
    "sg:province":"MS",
    "sg:tags":[
        "firework"
    ],
    "wof:name":"American Fireworks",
    "wof:placetype":"venue"
},
  "geometry": {"coordinates":[-90.049825,34.991739],"type":"Point"}
}