{
  "type": "Feature",
  "properties": {
    "addr:full":"2560 Hwy 51 S Hernando MS 38632",
    "addr:housenumber":"2560",
    "addr:postcode":"38632",
    "addr:street":"Hwy 51 S",
    "iso:country":"US",
    "sg:address":"2560 Hwy 51 S",
    "sg:city":"Hernando",
    "sg:classifiers":[
        {
            "category":"Banks & Credit Unions",
            "subcategory":"Investment Brokerage",
            "type":"Services"
        }
    ],
    "sg:phone":"+1 662 449 0410",
    "sg:postcode":"38632",
    "sg:province":"MS",
    "sg:tags":[
        "security"
    ],
    "sg:website":"www.edwardjones.com",
    "wof:name":"Edward Jones Co",
    "wof:placetype":"venue"
},
  "geometry": {"coordinates":[-89.994039,34.822774],"type":"Point"}
}