{
  "type": "Feature",
  "properties": {
    "iso:country":"US",
    "sg:address":"89 Jeff St",
    "sg:city":"Oxford",
    "sg:classifiers":[
        {
            "category":"Organizations",
            "subcategory":"Professional Association",
            "type":"Services"
        }
    ],
    "sg:phone":"+1 662 234 5228",
    "sg:postcode":"38655",
    "sg:province":"MS",
    "sg:tags":[
        "medical"
    ],
    "wof:name":"Mississppi Ostopathic Med Assn",
    "wof:placetype":"venue"
},
  "geometry": {"coordinates":[-89.493657,34.354569],"type":"Point"}
}