{
  "type": "Feature",
  "properties": {
    "addr:full":"4436 Hwy 301 S Hernando MS 38632",
    "addr:housenumber":"4436",
    "addr:postcode":"38632",
    "addr:street":"Hwy 301 S",
    "iso:country":"US",
    "sg:address":"4436 Hwy 301 S",
    "sg:city":"Hernando",
    "sg:classifiers":[
        {
            "category":"Organizations",
            "subcategory":"Religious Organization",
            "type":"Services"
        }
    ],
    "sg:phone":"+1 662 429 9648",
    "sg:postcode":"38632",
    "sg:province":"MS",
    "sg:tags":[
        "church"
    ],
    "wof:name":"Pleasant Grove CME Church",
    "wof:placetype":"venue"
},
  "geometry": {"coordinates":[-90.148242,34.794913],"type":"Point"}
}