{
  "type": "Feature",
  "properties": {
    "addr:full":"616 University Dr Starkville MS 39759",
    "addr:housenumber":"616",
    "addr:postcode":"39759",
    "addr:street":"University Dr",
    "iso:country":"US",
    "sg:address":"616 University Dr",
    "sg:city":"Starkville",
    "sg:classifiers":[
        {
            "category":"Shopping",
            "subcategory":"Discount & Variety Stores",
            "type":"Retail Goods"
        }
    ],
    "sg:phone":"+1 662 324 5005",
    "sg:postcode":"39759",
    "sg:province":"MS",
    "wof:name":"Dollar General",
    "wof:placetype":"venue"
},
  "geometry": {"coordinates":[-88.80348499999999,33.461371],"type":"Point"}
}