{
  "type": "Feature",
  "properties": {
    "iso:country":"US",
    "sg:address":"101 Holly Ln",
    "sg:city":"Mayersville",
    "sg:classifiers":[
        {
            "category":"Food & Beverages",
            "subcategory":"Groceries & Convenience Stores",
            "type":"Retail Goods"
        }
    ],
    "sg:phone":"+1 662 873 6030",
    "sg:postcode":"39113",
    "sg:province":"MS",
    "sg:tags":[
        "grocer"
    ],
    "wof:name":"Tony's Grocery",
    "wof:placetype":"venue"
},
  "geometry": {"coordinates":[-91.052233,32.904246],"type":"Point"}
}