{
  "type": "Feature",
  "properties": {
    "addr:full":"224 S 13th Ave Laurel MS 39440",
    "addr:housenumber":"224",
    "addr:postcode":"39440",
    "addr:street":"S 13Th Ave",
    "iso:country":"US",
    "sg:address":"224 S 13th Ave",
    "sg:city":"Laurel",
    "sg:classifiers":[
        {
            "category":"Banks & Credit Unions",
            "subcategory":"Investment Brokerage",
            "type":"Services"
        }
    ],
    "sg:phone":"+1 601 649 8146",
    "sg:postcode":"39440",
    "sg:province":"MS",
    "sg:tags":[
        "advisory",
        "planning",
        "insurance",
        "retirement"
    ],
    "wof:name":"Mc Craw & Assoc",
    "wof:placetype":"venue"
},
  "geometry": {"coordinates":[-89.142765,31.687627],"type":"Point"}
}