{
  "type": "Feature",
  "properties": {
    "iso:country":"US",
    "sg:address":"83 Bridge Lake Rd",
    "sg:city":"Carriere",
    "sg:classifiers":[
        {
            "category":"Retail",
            "subcategory":"Repair Shop",
            "type":"Services"
        }
    ],
    "sg:phone":"+1 601 749 8749",
    "sg:postcode":"39426",
    "sg:province":"MS",
    "sg:tags":[
        "taxidermist"
    ],
    "wof:name":"Old River Taxidermy",
    "wof:placetype":"venue"
},
  "geometry": {"coordinates":[-89.801402,30.680821],"type":"Point"}
}