{
  "type": "Feature",
  "properties": {
    "iso:country":"US",
    "sg:address":"734 S Magnolia Dr",
    "sg:city":"Wiggins",
    "sg:classifiers":[
        {
            "category":"Food & Beverages",
            "subcategory":"Groceries & Convenience Stores",
            "type":"Retail Goods"
        }
    ],
    "sg:phone":"+1 601 928 4483",
    "sg:postcode":"39577",
    "sg:province":"MS",
    "sg:tags":[
        "grocer"
    ],
    "wof:name":"Super Savers Discount Salvage",
    "wof:placetype":"venue"
},
  "geometry": {"coordinates":[-89.138322,30.849255],"type":"Point"}
}