{
  "type": "Feature",
  "properties": {
    "addr:full":"5204 Hwy 26 W Lucedale MS 39452",
    "addr:housenumber":"5204",
    "addr:postcode":"39452",
    "addr:street":"Hwy 26 W Lucedale",
    "iso:country":"US",
    "sg:address":"5204 Hwy 26 W",
    "sg:city":"Lucedale",
    "sg:classifiers":[
        {
            "category":"Education",
            "subcategory":"School",
            "type":"Public Place"
        }
    ],
    "sg:phone":"+1 601 945 2933",
    "sg:postcode":"39452",
    "sg:province":"MS",
    "wof:name":"Benndale Elementary School",
    "wof:placetype":"venue"
},
  "geometry": {"coordinates":[-88.801215,30.872703],"type":"Point"}
}