{
  "type": "Feature",
  "properties": {
    "addr:full":"134 Richardson Dr Jackson MS 39209",
    "addr:housenumber":"134",
    "addr:postcode":"39209",
    "addr:street":"Richardson Dr",
    "iso:country":"US",
    "sg:address":"134 Richardson Dr",
    "sg:city":"Jackson",
    "sg:classifiers":[
        {
            "category":"Wholesale",
            "subcategory":"Chemicals & Plastics",
            "type":"Manufacturing & Wholesale Goods"
        }
    ],
    "sg:phone":"+1 601 922 7568",
    "sg:postcode":"39209",
    "sg:province":"MS",
    "wof:name":"Pride Inc",
    "wof:placetype":"venue"
},
  "geometry": {"coordinates":[-90.253,32.353963],"type":"Point"}
}