{
  "type": "Feature",
  "properties": {
    "iso:country":"US",
    "sg:address":"140 Progress Rd",
    "sg:city":"Prentiss",
    "sg:classifiers":[
        {
            "category":"Personal",
            "subcategory":"Barber",
            "type":"Services"
        }
    ],
    "sg:phone":"+1 601 792 9116",
    "sg:postcode":"39470",
    "sg:province":"MS",
    "wof:name":"Mr D's",
    "wof:placetype":"venue"
},
  "geometry": {"coordinates":[-89.501836,30.811226],"type":"Point"}
}