{
  "type": "Feature",
  "properties": {
    "iso:country":"US",
    "sg:address":"132 Commerce St",
    "sg:city":"West Point",
    "sg:classifiers":[
        {
            "category":"Personal",
            "subcategory":"Beauty Salon",
            "type":"Services"
        }
    ],
    "sg:phone":"+1 662 494 1115",
    "sg:postcode":"39773",
    "sg:province":"MS",
    "wof:name":"Positive Image Hair Salon",
    "wof:placetype":"venue"
},
  "geometry": {"coordinates":[-88.64854099999999,33.606741],"type":"Point"}
}