{
  "type": "Feature",
  "properties": {
    "addr:full":"121 W Market St Greenwood MS 38930",
    "addr:housenumber":"121",
    "addr:postcode":"38930",
    "addr:street":"W Market St",
    "iso:country":"US",
    "sg:address":"121 W Market St",
    "sg:city":"Greenwood",
    "sg:classifiers":[
        {
            "category":"Insurance",
            "subcategory":"Insurance Agent",
            "type":"Services"
        }
    ],
    "sg:phone":"+1 662 455 6999",
    "sg:postcode":"38930",
    "sg:province":"MS",
    "wof:name":"Singleton & Naaman Insurance",
    "wof:placetype":"venue"
},
  "geometry": {"coordinates":[-90.18167099999999,33.52057],"type":"Point"}
}