{
  "type": "Feature",
  "properties": {
    "addr:full":"1704 Kelly Ave Gulfport MS 39501",
    "addr:housenumber":"1704",
    "addr:postcode":"39501",
    "addr:street":"Kelly Ave",
    "iso:country":"US",
    "sg:address":"1704 Kelly Ave",
    "sg:city":"Gulfport",
    "sg:classifiers":[
        {
            "category":"Retail",
            "subcategory":"Auto Repair",
            "type":"Services"
        }
    ],
    "sg:phone":"+1 228 863 9634",
    "sg:postcode":"39501",
    "sg:province":"MS",
    "sg:tags":[
        "repairing",
        "automobile",
        "maintenance",
        "general"
    ],
    "wof:name":"Progressive Automotive Inc",
    "wof:placetype":"venue"
},
  "geometry": {"coordinates":[-89.072204,30.374913],"type":"Point"}
}