{
  "type": "Feature",
  "properties": {
    "iso:country":"US",
    "sg:address":"5722 Old Hwy 61",
    "sg:city":"Tunica",
    "sg:classifiers":[
        {
            "category":"Farming",
            "subcategory":"Farm",
            "type":"Manufacturing & Wholesale Goods"
        }
    ],
    "sg:phone":"+1 662 363 9646",
    "sg:postcode":"38676",
    "sg:province":"MS",
    "sg:tags":[
        "crop",
        "general"
    ],
    "wof:name":"Limerick Farms",
    "wof:placetype":"venue"
},
  "geometry": {"coordinates":[-90.357152,34.746998],"type":"Point"}
}