{
  "type": "Feature",
  "properties": {
    "iso:country":"US",
    "sg:address":"114 Co Rd 420",
    "sg:city":"Calhoun City",
    "sg:classifiers":[
        {
            "category":"Organizations",
            "subcategory":"Religious Organization",
            "type":"Services"
        }
    ],
    "sg:phone":"+1 662 628 5701",
    "sg:postcode":"38916",
    "sg:province":"MS",
    "wof:name":"Duncan Hill Baptist Church",
    "wof:placetype":"venue"
},
  "geometry": {"coordinates":[-89.256838,33.860326],"type":"Point"}
}