{
  "type": "Feature",
  "properties": {
    "addr:full":"727 Terry Rd Jackson MS 39203",
    "addr:housenumber":"727",
    "addr:postcode":"39203",
    "addr:street":"Terry Rd",
    "iso:country":"US",
    "sg:address":"727 Terry Rd",
    "sg:city":"Jackson",
    "sg:classifiers":[
        {
            "category":"Retail",
            "subcategory":"Auto Repair",
            "type":"Services"
        }
    ],
    "sg:phone":"+1 601 355 3166",
    "sg:postcode":"39203",
    "sg:province":"MS",
    "sg:tags":[
        "transmission"
    ],
    "wof:name":"A-1 Transmissions Inc",
    "wof:placetype":"venue"
},
  "geometry": {"coordinates":[-90.19833199999999,32.295418],"type":"Point"}
}