{
  "type": "Feature",
  "properties": {
    "addr:full":"1660 Jefferson Davis Cove Nesbit MS 38651",
    "addr:housenumber":"1660",
    "addr:postcode":"38651",
    "addr:street":"Jefferson Davis Cove",
    "iso:country":"US",
    "sg:address":"1660 Jefferson Davis Cove",
    "sg:city":"Nesbit",
    "sg:classifiers":[
        {
            "category":"Professional",
            "subcategory":"Detective & Security Services",
            "type":"Services"
        }
    ],
    "sg:phone":"+1 662 429 3333",
    "sg:postcode":"38651",
    "sg:province":"MS",
    "sg:tags":[
        "guard",
        "patrol"
    ],
    "wof:name":"Allstar Security Co",
    "wof:placetype":"venue"
},
  "geometry": {"coordinates":[-90.00559,34.882832],"type":"Point"}
}