{
  "type": "Feature",
  "properties": {
    "addr:full":"520 W Presley Blvd Mccomb MS 39648",
    "addr:housenumber":"520",
    "addr:postcode":"39648",
    "addr:street":"W Presley Blvd",
    "iso:country":"US",
    "sg:address":"520 W Presley Blvd",
    "sg:city":"Mccomb",
    "sg:classifiers":[
        {
            "category":"Autos & Motor Vehicles",
            "subcategory":"Automobile Sales",
            "type":"Retail Goods"
        },
        {
            "category":"Wholesale",
            "subcategory":"Auto Parts",
            "type":"Manufacturing & Wholesale Goods"
        }
    ],
    "sg:phone":"+1 601 684 0990",
    "sg:postcode":"39648",
    "sg:province":"MS",
    "sg:tags":[
        "used",
        "automotive",
        "general",
        "r",
        "car",
        "salvage",
        "dealer"
    ],
    "wof:name":"Presley Cars & Parts",
    "wof:placetype":"venue"
},
  "geometry": {"coordinates":[-90.461552,31.227026],"type":"Point"}
}