{
  "type": "Feature",
  "properties": {
    "addr:full":"10452 Hwy 494 Meridian MS 39305",
    "addr:housenumber":"10452",
    "addr:postcode":"39305",
    "addr:street":"Hwy 494",
    "iso:country":"US",
    "sg:address":"10452 Hwy 494",
    "sg:city":"Meridian",
    "sg:classifiers":[
        {
            "category":"Food & Beverages",
            "subcategory":"Bakery",
            "type":"Retail Goods"
        }
    ],
    "sg:phone":"+1 601 483 3396",
    "sg:postcode":"39305",
    "sg:province":"MS",
    "sg:tags":[
        "baker"
    ],
    "wof:name":"King Bakery Deb's Fountain",
    "wof:placetype":"venue"
},
  "geometry": {"coordinates":[-88.796464,32.435242],"type":"Point"}
}