{
  "type": "Feature",
  "properties": {
    "iso:country":"US",
    "sg:address":"13185 Three Rivers Rd",
    "sg:city":"Gulfport",
    "sg:classifiers":[
        {
            "category":"Building & Trades",
            "subcategory":"Construction",
            "type":"Services"
        }
    ],
    "sg:phone":"+1 228 832 1856",
    "sg:postcode":"39503",
    "sg:province":"MS",
    "sg:tags":[
        "house",
        "builder",
        "home"
    ],
    "wof:name":"Price's Contracting Inc",
    "wof:placetype":"venue"
},
  "geometry": {"coordinates":[-89.06970699999999,30.475145],"type":"Point"}
}