{
  "type": "Feature",
  "properties": {
    "iso:country":"US",
    "sg:address":"1001 Felts Ln",
    "sg:city":"Crystal Springs",
    "sg:classifiers":[
        {
            "category":"Wholesale",
            "subcategory":"Vending Machines",
            "type":"Manufacturing & Wholesale Goods"
        }
    ],
    "sg:phone":"+1 601 892 2289",
    "sg:postcode":"39059",
    "sg:province":"MS",
    "sg:tags":[
        "retail"
    ],
    "wof:name":"TS Vending Machine",
    "wof:placetype":"venue"
},
  "geometry": {"coordinates":[-90.44112699999999,31.98386],"type":"Point"}
}