{
  "type": "Feature",
  "properties": {
    "iso:country":"US",
    "sg:address":"207 W Central Ave",
    "sg:city":"Petal",
    "sg:classifiers":[
        {
            "category":"Autos & Motor Vehicles",
            "subcategory":"Auto Supplies",
            "type":"Retail Goods"
        }
    ],
    "sg:phone":"+1 601 544 0144",
    "sg:postcode":"39465",
    "sg:province":"MS",
    "sg:tags":[
        "automobile",
        "parts"
    ],
    "wof:name":"Nobles Auto Parts Inc",
    "wof:placetype":"venue"
},
  "geometry": {"coordinates":[-89.270228,31.34669],"type":"Point"}
}