{
  "type": "Feature",
  "properties": {
    "iso:country":"US",
    "sg:address":"2499 Old Hernando Rd",
    "sg:city":"Holly Springs",
    "sg:classifiers":[
        {
            "category":"Professional",
            "subcategory":"Lawyer & Legal Services",
            "type":"Services"
        }
    ],
    "sg:phone":"+1 662 252 5474",
    "sg:postcode":"38635",
    "sg:province":"MS",
    "wof:name":"Bell McHlle Prpaid Legal Svcs",
    "wof:placetype":"venue"
},
  "geometry": {"coordinates":[-89.500924,34.779282],"type":"Point"}
}