{
  "type": "Feature",
  "properties": {
    "addr:full":"203 Main St Natchez MS 39120",
    "addr:housenumber":"203",
    "addr:postcode":"39120",
    "addr:street":"Main St",
    "iso:country":"US",
    "sg:address":"203 Main St",
    "sg:city":"Natchez",
    "sg:classifiers":[
        {
            "category":"Banks & Credit Unions",
            "subcategory":"Bank",
            "type":"Services"
        }
    ],
    "sg:phone":"+1 601 445 7041",
    "sg:postcode":"39120",
    "sg:province":"MS",
    "wof:name":"United Mississippt Bank",
    "wof:placetype":"venue"
},
  "geometry": {"coordinates":[-91.405247,31.561616],"type":"Point"}
}