{
  "type": "Feature",
  "properties": {
    "iso:country":"US",
    "sg:address":"55 Kimes Cove",
    "sg:city":"Sardis",
    "sg:classifiers":[
        {
            "category":"Food & Beverages",
            "subcategory":"Groceries & Convenience Stores",
            "type":"Retail Goods"
        }
    ],
    "sg:phone":"+1 662 526 1969",
    "sg:postcode":"38666",
    "sg:province":"MS",
    "wof:name":"Sportsman's One Stop",
    "wof:placetype":"venue"
},
  "geometry": {"coordinates":[-89.831836,34.423178],"type":"Point"}
}