{
  "type": "Feature",
  "properties": {
    "iso:country":"US",
    "sg:address":"550 W Government St",
    "sg:city":"Brandon",
    "sg:classifiers":[
        {
            "category":"Retail",
            "subcategory":"Veterinary Services",
            "type":"Services"
        }
    ],
    "sg:phone":"+1 601 825 2915",
    "sg:postcode":"39042",
    "sg:province":"MS",
    "wof:name":"Luckett Animal Clinic",
    "wof:placetype":"venue"
},
  "geometry": {"coordinates":[-89.994021,32.274206],"type":"Point"}
}