{
  "type": "Feature",
  "properties": {
    "iso:country":"US",
    "sg:address":"2525 US Hwy 90",
    "sg:city":"Gautier",
    "sg:classifiers":[
        {
            "category":"Food & Beverages",
            "subcategory":"Groceries & Convenience Stores",
            "type":"Retail Goods"
        }
    ],
    "sg:phone":"+1 228 497 4884",
    "sg:postcode":"39553",
    "sg:province":"MS",
    "sg:tags":[
        "grocer"
    ],
    "wof:name":"Jerry Lee's Grocery Inc",
    "wof:placetype":"venue"
},
  "geometry": {"coordinates":[-88.648974,30.391207],"type":"Point"}
}