{
  "type": "Feature",
  "properties": {
    "iso:country":"US",
    "sg:address":"6409 Washington Ave",
    "sg:city":"Ocean Springs",
    "sg:classifiers":[
        {
            "category":"Home & Garden",
            "subcategory":"Building Materials",
            "type":"Retail Goods"
        }
    ],
    "sg:phone":"+1 228 875 1840",
    "sg:postcode":"39564",
    "sg:province":"MS",
    "sg:tags":[
        "paint"
    ],
    "wof:name":"Sherwin-Williams Paints",
    "wof:placetype":"venue"
},
  "geometry": {"coordinates":[-88.830513,30.435384],"type":"Point"}
}