{
  "type": "Feature",
  "properties": {
    "addr:full":"9075 Valley Grove Ln Southaven MS 38672",
    "addr:housenumber":"9075",
    "addr:postcode":"38672",
    "addr:street":"Valley Grove Ln",
    "iso:country":"US",
    "sg:address":"9075 Valley Grove Ln",
    "sg:city":"Southaven",
    "sg:classifiers":[
        {
            "category":"Wholesale",
            "subcategory":"Auto Parts",
            "type":"Manufacturing & Wholesale Goods"
        }
    ],
    "sg:phone":"+1 662 393 8663",
    "sg:postcode":"38672",
    "sg:province":"MS",
    "wof:name":"Snap-On Tools",
    "wof:placetype":"venue"
},
  "geometry": {"coordinates":[-89.949004,34.992943],"type":"Point"}
}