{
  "type": "Feature",
  "properties": {
    "addr:full":"1308 Levee St Vicksburg MS 39180",
    "addr:housenumber":"1308",
    "addr:postcode":"39180",
    "addr:street":"Levee St",
    "iso:country":"US",
    "sg:address":"1308 Levee St",
    "sg:city":"Vicksburg",
    "sg:classifiers":[
        {
            "category":"Shopping",
            "subcategory":"Bicycles & Sporting Goods",
            "type":"Retail Goods"
        }
    ],
    "sg:phone":"+1 601 638 7137",
    "sg:postcode":"39180",
    "sg:province":"MS",
    "wof:name":"Surplus City USA Inc",
    "wof:placetype":"venue"
},
  "geometry": {"coordinates":[-90.884608,32.349388],"type":"Point"}
}