{
  "type": "Feature",
  "properties": {
    "iso:country":"US",
    "sg:address":"50041 Beaver Rd",
    "sg:city":"Aberdeen",
    "sg:classifiers":[
        {
            "category":"Building & Trades",
            "subcategory":"Construction",
            "type":"Services"
        }
    ],
    "sg:phone":"+1 662 369 3433",
    "sg:postcode":"39730",
    "sg:province":"MS",
    "sg:tags":[
        "house"
    ],
    "wof:name":"Kennedy Construction",
    "wof:placetype":"venue"
},
  "geometry": {"coordinates":[-88.50837199999999,33.84308],"type":"Point"}
}