{
  "type": "Feature",
  "properties": {
    "iso:country":"US",
    "sg:address":"102 Bus Park Dr",
    "sg:city":"Ridgeland",
    "sg:classifiers":[
        {
            "category":"Professional",
            "type":"Services"
        }
    ],
    "sg:phone":"+1 601 956 6488",
    "sg:postcode":"39157",
    "sg:province":"MS",
    "sg:tags":[
        "establishment"
    ],
    "wof:name":"WLIN",
    "wof:placetype":"venue"
},
  "geometry": {"coordinates":[-90.177967,32.405975],"type":"Point"}
}