{
  "type": "Feature",
  "properties": {
    "iso:country":"US",
    "sg:address":"202 E Railroad St",
    "sg:city":"Long Beach",
    "sg:classifiers":[
        {
            "category":"Health Services",
            "subcategory":"Optometrist",
            "type":"Services"
        }
    ],
    "sg:phone":"+1 228 868 2020",
    "sg:postcode":"39560",
    "sg:province":"MS",
    "sg:website":"www.edringtonoptical.com",
    "wof:name":"Edrington Optical",
    "wof:placetype":"venue"
},
  "geometry": {"coordinates":[-89.146604,30.352489],"type":"Point"}
}