{
  "type": "Feature",
  "properties": {
    "addr:full":"503 W Main St Fulton MS 38843",
    "addr:housenumber":"503",
    "addr:postcode":"38843",
    "addr:street":"W Main St",
    "iso:country":"US",
    "sg:address":"503 W Main St",
    "sg:city":"Fulton",
    "sg:classifiers":[
        {
            "category":"Building & Trades",
            "subcategory":"Plumbing",
            "type":"Services"
        }
    ],
    "sg:phone":"+1 662 862 9397",
    "sg:postcode":"38843",
    "sg:province":"MS",
    "sg:tags":[
        "air",
        "heating",
        "conditioning",
        "contractor"
    ],
    "wof:name":"Fulton Heating & Cooling Inc",
    "wof:placetype":"venue"
},
  "geometry": {"coordinates":[-88.411113,34.27378],"type":"Point"}
}