{
  "type": "Feature",
  "properties": {
    "addr:full":"5315 I- 55 N Jackson MS 39206",
    "addr:housenumber":"5315;55 n",
    "addr:postcode":"39206",
    "addr:street":"I",
    "iso:country":"US",
    "sg:address":"5315 I- 55 N",
    "sg:city":"Jackson",
    "sg:classifiers":[
        {
            "category":"Restaurant",
            "type":"Food & Drink"
        }
    ],
    "sg:phone":"+1 601 362 7000",
    "sg:postcode":"39206",
    "sg:province":"MS",
    "sg:tags":[
        "eating"
    ],
    "wof:name":"Peking Chinese Restaurant",
    "wof:placetype":"venue"
},
  "geometry": {"coordinates":[-90.149404,32.370725],"type":"Point"}
}