{
  "type": "Feature",
  "properties": {
    "iso:country":"US",
    "sg:address":"1385 State Hwy 29",
    "sg:city":"Ellisville",
    "sg:classifiers":[
        {
            "category":"Communications",
            "subcategory":"Radio Station",
            "type":"Services"
        }
    ],
    "sg:phone":"+1 601 477 2105",
    "sg:postcode":"39437",
    "sg:province":"MS",
    "sg:tags":[
        "company",
        "broadcasting"
    ],
    "wof:name":"Comulus Broadcasting",
    "wof:placetype":"venue"
},
  "geometry": {"coordinates":[-89.21944000000001,31.633778],"type":"Point"}
}