{
  "type": "Feature",
  "properties": {
    "iso:country":"US",
    "sg:address":"317 Lake Como Rd",
    "sg:city":"Laurel",
    "sg:classifiers":[
        {
            "category":"Freight",
            "type":"Transportation"
        }
    ],
    "sg:phone":"+1 601 498 3579",
    "sg:postcode":"39441",
    "sg:province":"MS",
    "sg:tags":[
        "operator",
        "local",
        "trucking"
    ],
    "wof:name":"Jerry Akerman Trucking",
    "wof:placetype":"venue"
},
  "geometry": {"coordinates":[-89.122024,31.771743],"type":"Point"}
}