{
  "type": "Feature",
  "properties": {
    "addr:full":"1315 N Jefferson St Jackson MS 39202",
    "addr:housenumber":"1315",
    "addr:postcode":"39202",
    "addr:street":"N Jefferson St",
    "iso:country":"US",
    "sg:address":"1315 N Jefferson St",
    "sg:city":"Jackson",
    "sg:classifiers":[
        {
            "category":"Social Services",
            "type":"Services"
        }
    ],
    "sg:phone":"+1 601 949 2522",
    "sg:postcode":"39202",
    "sg:province":"MS",
    "sg:tags":[
        "professional",
        "counselor"
    ],
    "wof:name":"Fairman Group Inc",
    "wof:placetype":"venue"
},
  "geometry": {"coordinates":[-90.175344,32.315894],"type":"Point"}
}