{
  "type": "Feature",
  "properties": {
    "addr:full":"39 Johns Ln Richton MS 39476",
    "addr:housenumber":"39",
    "addr:postcode":"39476",
    "addr:street":"Johns Ln",
    "iso:country":"US",
    "sg:address":"39 Johns Ln",
    "sg:city":"Richton",
    "sg:classifiers":[
        {
            "category":"Insurance",
            "subcategory":"Insurance Agent",
            "type":"Services"
        }
    ],
    "sg:phone":"+1 601 989 2443",
    "sg:postcode":"39476",
    "sg:province":"MS",
    "wof:name":"Pulliam Insurance Plans Inc",
    "wof:placetype":"venue"
},
  "geometry": {"coordinates":[-88.75111699999999,31.381068],"type":"Point"}
}