{
  "type": "Feature",
  "properties": {
    "iso:country":"US",
    "sg:address":"602 Wallace Dr",
    "sg:city":"Edwards",
    "sg:classifiers":[
        {
            "category":"Restaurant",
            "type":"Food & Drink"
        }
    ],
    "sg:phone":"+1 601 852 2278",
    "sg:postcode":"39066",
    "sg:province":"MS",
    "wof:name":"Mr Biggs Restaurant",
    "wof:placetype":"venue"
},
  "geometry": {"coordinates":[-90.59771000000001,32.336926],"type":"Point"}
}