{
  "type": "Feature",
  "properties": {
    "addr:full":"14021 Banbury Cove Gulfport MS 39503",
    "addr:housenumber":"14021",
    "addr:postcode":"39503",
    "addr:street":"Banbury Cove",
    "iso:country":"US",
    "sg:address":"14021 Banbury Cove",
    "sg:city":"Gulfport",
    "sg:classifiers":[
        {
            "category":"Professional",
            "type":"Services"
        }
    ],
    "sg:phone":"+1 228 539 5588",
    "sg:postcode":"39503",
    "sg:province":"MS",
    "wof:name":"Complete Instrument Comp Inc",
    "wof:placetype":"venue"
},
  "geometry": {"coordinates":[-89.11093700000001,30.48603],"type":"Point"}
}