{
  "type": "Feature",
  "properties": {
    "iso:country":"US",
    "sg:address":"250 Hwy 12 W",
    "sg:city":"Kosciusko",
    "sg:classifiers":[
        {
            "category":"Wholesale",
            "subcategory":"Electrical",
            "type":"Manufacturing & Wholesale Goods"
        }
    ],
    "sg:phone":"+1 662 289 4461",
    "sg:postcode":"39090",
    "sg:province":"MS",
    "sg:tags":[
        "equipment",
        "electric",
        "supply"
    ],
    "wof:name":"Timberland Supply Co Inc",
    "wof:placetype":"venue"
},
  "geometry": {"coordinates":[-89.601404,33.063574],"type":"Point"}
}