{
  "type": "Feature",
  "properties": {
    "iso:country":"US",
    "sg:address":"102 Cross St",
    "sg:city":"Natchez",
    "sg:classifiers":[
        {
            "category":"Shopping",
            "subcategory":"Jewelry",
            "type":"Retail Goods"
        }
    ],
    "sg:phone":"+1 601 442 7074",
    "sg:postcode":"39120",
    "sg:province":"MS",
    "wof:name":"Lea Ju Designs",
    "wof:placetype":"venue"
},
  "geometry": {"coordinates":[-91.357282,31.568841],"type":"Point"}
}