{
  "type": "Feature",
  "properties": {
    "iso:country":"US",
    "sg:address":"1203 US Hwy 90",
    "sg:city":"Bay St Louis",
    "sg:classifiers":[
        {
            "category":"Organizations",
            "subcategory":"Religious Organization",
            "type":"Services"
        }
    ],
    "sg:phone":"+1 228 467 0529",
    "sg:postcode":"39520",
    "sg:province":"MS",
    "sg:tags":[
        "church"
    ],
    "wof:name":"Central Baptist Church",
    "wof:placetype":"venue"
},
  "geometry": {"coordinates":[-89.365909,30.310243],"type":"Point"}
}