{
  "type": "Feature",
  "properties": {
    "iso:country":"US",
    "sg:address":"2108 Crossbridge Blvd",
    "sg:city":"Jackson",
    "sg:classifiers":[
        {
            "category":"Social Services",
            "type":"Services"
        }
    ],
    "sg:phone":"+1 601 372 5374",
    "sg:postcode":"39272",
    "sg:province":"MS",
    "wof:name":"Lisa B Yazdani",
    "wof:placetype":"venue"
},
  "geometry": {"coordinates":[-90.29121499999999,32.200714],"type":"Point"}
}