{
  "type": "Feature",
  "properties": {
    "iso:country":"US",
    "sg:address":"176 Country Heritage Rd",
    "sg:city":"Poplarville",
    "sg:classifiers":[
        {
            "category":"Building & Trades",
            "subcategory":"Electrical",
            "type":"Services"
        }
    ],
    "sg:phone":"+1 601 795 4425",
    "sg:postcode":"39470",
    "sg:province":"MS",
    "sg:tags":[
        "electrical",
        "electric",
        "contractor"
    ],
    "wof:name":"Roger's Electric",
    "wof:placetype":"venue"
},
  "geometry": {"coordinates":[-89.486993,30.841023],"type":"Point"}
}