{
  "type": "Feature",
  "properties": {
    "iso:country":"US",
    "sg:address":"100 W Canal St",
    "sg:city":"Picayune",
    "sg:classifiers":[
        {
            "category":"Organizations",
            "subcategory":"Professional Association",
            "type":"Services"
        }
    ],
    "sg:phone":"+1 601 799 3070",
    "sg:postcode":"39466",
    "sg:province":"MS",
    "wof:name":"Picayune Main Street/Downtown",
    "wof:placetype":"venue"
},
  "geometry": {"coordinates":[-89.682014,30.52639],"type":"Point"}
}