{
  "type": "Feature",
  "properties": {
    "iso:country":"US",
    "sg:address":"689 Hwy 25",
    "sg:city":"Dennis",
    "sg:classifiers":[
        {
            "category":"Organizations",
            "subcategory":"Religious Organization",
            "type":"Services"
        }
    ],
    "sg:phone":"+1 662 454 7310",
    "sg:postcode":"38838",
    "sg:province":"MS",
    "wof:name":"Liberty Church Of Christ",
    "wof:placetype":"venue"
},
  "geometry": {"coordinates":[-88.224591,34.555261],"type":"Point"}
}