{
  "type": "Feature",
  "properties": {
    "iso:country":"US",
    "sg:address":"33 Sgt Prentiss Dr",
    "sg:city":"Natchez",
    "sg:classifiers":[
        {
            "category":"Shopping",
            "subcategory":"Music",
            "type":"Retail Goods"
        },
        {
            "category":"Cinema",
            "subcategory":"Movie Rental",
            "type":"Entertainment"
        }
    ],
    "sg:phone":"+1 601 442 8811",
    "sg:postcode":"39120",
    "sg:province":"MS",
    "sg:tags":[
        "video",
        "disc",
        "tape",
        "cassette"
    ],
    "wof:name":"Southgate Video",
    "wof:placetype":"venue"
},
  "geometry": {"coordinates":[-91.388842,31.521596],"type":"Point"}
}