{
  "type": "Feature",
  "properties": {
    "addr:full":"1621 Hwy 15 N Laurel MS 39440",
    "addr:housenumber":"1621",
    "addr:postcode":"39440",
    "addr:street":"Hwy 15 N",
    "iso:country":"US",
    "sg:address":"1621 Hwy 15 N",
    "sg:city":"Laurel",
    "sg:classifiers":[
        {
            "category":"Professional",
            "subcategory":"Accounting & Tax Preparation",
            "type":"Services"
        }
    ],
    "sg:phone":"+1 601 428 4310",
    "sg:postcode":"39440",
    "sg:province":"MS",
    "sg:tags":[
        "return",
        "filing"
    ],
    "wof:name":"Jackson Hewitt Tax Svc",
    "wof:placetype":"venue"
},
  "geometry": {"coordinates":[-89.148545,31.708869],"type":"Point"}
}