{
  "type": "Feature",
  "properties": {
    "iso:country":"US",
    "sg:address":"2025 Longwood Cove",
    "sg:city":"Pearl",
    "sg:classifiers":[
        {
            "category":"Home & Garden",
            "subcategory":"Home Furnishings",
            "type":"Retail Goods"
        }
    ],
    "sg:phone":"+1 601 932 4855",
    "sg:postcode":"39208",
    "sg:province":"MS",
    "sg:tags":[
        "mirror"
    ],
    "wof:name":"Custom Mirrors & Shower Doors",
    "wof:placetype":"venue"
},
  "geometry": {"coordinates":[-90.043975,32.311844],"type":"Point"}
}