{
  "type": "Feature",
  "properties": {
    "iso:country":"US",
    "sg:address":"212 Sandy St",
    "sg:city":"Pass Christian",
    "sg:classifiers":[
        {
            "category":"Real Estate",
            "subcategory":"Real Estate Operator",
            "type":"Services"
        }
    ],
    "sg:phone":"+1 228 452 2203",
    "sg:postcode":"39576",
    "sg:province":"MS",
    "wof:name":"Montignet Properties",
    "wof:placetype":"venue"
},
  "geometry": {"coordinates":[-89.38295599999999,30.279587],"type":"Point"}
}