{
  "type": "Feature",
  "properties": {
    "iso:country":"US",
    "sg:address":"8068 Buckingham Dr",
    "sg:city":"Southaven",
    "sg:classifiers":[
        {
            "category":"Manufacturing",
            "subcategory":"Tools & Machinery",
            "type":"Manufacturing & Wholesale Goods"
        }
    ],
    "sg:phone":"+1 662 342 0555",
    "sg:postcode":"38671",
    "sg:province":"MS",
    "sg:tags":[
        "equipment",
        "printing",
        "mfg"
    ],
    "wof:name":"Ray Brooks Enterprises",
    "wof:placetype":"venue"
},
  "geometry": {"coordinates":[-90.003702,34.980078],"type":"Point"}
}