{
  "type": "Feature",
  "properties": {
    "iso:country":"US",
    "sg:address":"401 W Main St",
    "sg:city":"Charleston",
    "sg:classifiers":[
        {
            "category":"Retail",
            "subcategory":"Auto Repair",
            "type":"Services"
        }
    ],
    "sg:phone":"+1 662 647 8440",
    "sg:postcode":"38921",
    "sg:province":"MS",
    "sg:tags":[
        "repairing",
        "automobile"
    ],
    "wof:name":"Sayle Service Ctr",
    "wof:placetype":"venue"
},
  "geometry": {"coordinates":[-90.06268900000001,34.007187],"type":"Point"}
}