{
  "type": "Feature",
  "properties": {
    "iso:country":"US",
    "sg:address":"118 W Washington St",
    "sg:city":"Kosciusko",
    "sg:classifiers":[
        {
            "category":"Government",
            "subcategory":"Court House",
            "type":"Public Place"
        }
    ],
    "sg:phone":"+1 662 289 1135",
    "sg:postcode":"39090",
    "sg:province":"MS",
    "wof:name":"Circuit Courthouse",
    "wof:placetype":"venue"
},
  "geometry": {"coordinates":[-89.590681,33.058651],"type":"Point"}
}