{
  "type": "Feature",
  "properties": {
    "iso:country":"US",
    "sg:address":"8 Woodstone Dr",
    "sg:city":"Hattiesburg",
    "sg:classifiers":[
        {
            "category":"Manufacturing",
            "subcategory":"Printing",
            "type":"Manufacturing & Wholesale Goods"
        }
    ],
    "sg:phone":"+1 601 296 1555",
    "sg:postcode":"39402",
    "sg:province":"MS",
    "sg:tags":[
        "printer",
        "form"
    ],
    "wof:name":"Moore Business Forms & Systems",
    "wof:placetype":"venue"
},
  "geometry": {"coordinates":[-89.417047,31.313447],"type":"Point"}
}