{
  "type": "Feature",
  "properties": {
    "addr:full":"1026 Stateline Rd W Southaven MS 38671",
    "addr:housenumber":"1026",
    "addr:postcode":"38671",
    "addr:street":"Stateline Rd W",
    "iso:country":"US",
    "sg:address":"1026 Stateline Rd W",
    "sg:city":"Southaven",
    "sg:classifiers":[
        {
            "category":"Professional",
            "subcategory":"Accounting & Tax Preparation",
            "type":"Services"
        }
    ],
    "sg:phone":"+1 662 342 6968",
    "sg:postcode":"38671",
    "sg:province":"MS",
    "sg:tags":[
        "center",
        "payment",
        "for",
        "provider"
    ],
    "wof:name":"Entergy",
    "wof:placetype":"venue"
},
  "geometry": {"coordinates":[-90.008303,34.991929],"type":"Point"}
}