{
  "type": "Feature",
  "properties": {
    "addr:full":"204 Mallory Ct Madison MS 39110",
    "addr:housenumber":"204",
    "addr:postcode":"39110",
    "addr:street":"Mallory Ct",
    "iso:country":"US",
    "sg:address":"204 Mallory Ct",
    "sg:city":"Madison",
    "sg:classifiers":[
        {
            "category":"Professional",
            "subcategory":"Management & Consulting",
            "type":"Services"
        }
    ],
    "sg:phone":"+1 601 856 2779",
    "sg:postcode":"39110",
    "sg:province":"MS",
    "sg:tags":[
        "consultant",
        "educational"
    ],
    "wof:name":"Education & Training Conslnts",
    "wof:placetype":"venue"
},
  "geometry": {"coordinates":[-90.14107799999999,32.487544],"type":"Point"}
}