{
  "type": "Feature",
  "properties": {
    "iso:country":"US",
    "sg:address":"431 N 16th St",
    "sg:city":"Oxford",
    "sg:classifiers":[
        {
            "category":"Organizations",
            "subcategory":"Religious Organization",
            "type":"Services"
        }
    ],
    "sg:phone":"+1 662 234 2503",
    "sg:postcode":"38655",
    "sg:province":"MS",
    "sg:tags":[
        "church"
    ],
    "wof:name":"St Andrews United Methodist",
    "wof:placetype":"venue"
},
  "geometry": {"coordinates":[-89.51384899999999,34.368246],"type":"Point"}
}