{
  "type": "Feature",
  "properties": {
    "iso:country":"US",
    "sg:address":"1812 Market St",
    "sg:city":"Pascagoula",
    "sg:classifiers":[
        {
            "category":"Home & Garden",
            "subcategory":"Hardware",
            "type":"Retail Goods"
        }
    ],
    "sg:phone":"+1 228 762 7850",
    "sg:postcode":"39567",
    "sg:province":"MS",
    "sg:tags":[
        "tool",
        "used"
    ],
    "wof:name":"Gibson Tool Repair Svc Inc",
    "wof:placetype":"venue"
},
  "geometry": {"coordinates":[-88.548383,30.353706],"type":"Point"}
}