{
  "type": "Feature",
  "properties": {
    "iso:country":"US",
    "sg:address":"1409 Aston Ave",
    "sg:city":"Mc Comb",
    "sg:classifiers":[
        {
            "category":"Building & Trades",
            "subcategory":"Equipment Rental",
            "type":"Services"
        }
    ],
    "sg:phone":"+1 601 249 2692",
    "sg:postcode":"39648",
    "sg:province":"MS",
    "sg:tags":[
        "medical"
    ],
    "wof:name":"Ammed",
    "wof:placetype":"venue"
},
  "geometry": {"coordinates":[-90.469596,31.250442],"type":"Point"}
}