{
  "type": "Feature",
  "properties": {
    "iso:country":"US",
    "sg:address":"8565 Hwy 45 N",
    "sg:city":"Meridian",
    "sg:classifiers":[
        {
            "category":"Organizations",
            "subcategory":"Religious Organization",
            "type":"Services"
        }
    ],
    "sg:phone":"+1 601 679 8870",
    "sg:postcode":"39305",
    "sg:province":"MS",
    "sg:tags":[
        "church"
    ],
    "wof:name":"Northeast Baptist Church",
    "wof:placetype":"venue"
},
  "geometry": {"coordinates":[-88.601575,32.478143],"type":"Point"}
}