{
  "type": "Feature",
  "properties": {
    "addr:full":"205 E Northside Dr Jackson MS 39206",
    "addr:housenumber":"205",
    "addr:postcode":"39206",
    "addr:street":"E Northside Dr",
    "iso:country":"US",
    "sg:address":"205 E Northside Dr",
    "sg:city":"Jackson",
    "sg:classifiers":[
        {
            "category":"Autos & Motor Vehicles",
            "subcategory":"Auto Supplies",
            "type":"Retail Goods"
        }
    ],
    "sg:phone":"+1 601 713 3679",
    "sg:postcode":"39206",
    "sg:province":"MS",
    "sg:tags":[
        "home"
    ],
    "wof:name":"Advanced Auto Parts",
    "wof:placetype":"venue"
},
  "geometry": {"coordinates":[-90.17986399999999,32.355589],"type":"Point"}
}