{
  "type": "Feature",
  "properties": {
    "iso:country":"US",
    "sg:address":"1500 Terry Rd",
    "sg:city":"Jackson",
    "sg:classifiers":[
        {
            "category":"Shopping",
            "subcategory":"Used Merchandise",
            "type":"Retail Goods"
        }
    ],
    "sg:phone":"+1 601 352 5252",
    "sg:postcode":"39204",
    "sg:province":"MS",
    "sg:tags":[
        "pawnbroker"
    ],
    "wof:name":"Terry Road Pawn Shop",
    "wof:placetype":"venue"
},
  "geometry": {"coordinates":[-90.20462999999999,32.287701],"type":"Point"}
}