{
  "type": "Feature",
  "properties": {
    "iso:country":"US",
    "sg:address":"1141 Mount Vernon Rd",
    "sg:city":"Columbus",
    "sg:classifiers":[
        {
            "category":"Wholesale",
            "subcategory":"Electrical",
            "type":"Manufacturing & Wholesale Goods"
        }
    ],
    "sg:phone":"+1 662 327 4960",
    "sg:postcode":"39702",
    "sg:province":"MS",
    "sg:tags":[
        "equipment"
    ],
    "wof:name":"Pro Alarm Audio Engrg LLC",
    "wof:placetype":"venue"
},
  "geometry": {"coordinates":[-88.315848,33.484895],"type":"Point"}
}