{
  "type": "Feature",
  "properties": {
    "iso:country":"US",
    "sg:address":"2335 Dulaney Rd",
    "sg:city":"Terry",
    "sg:classifiers":[
        {
            "category":"Retail",
            "subcategory":"Repair Shop",
            "type":"Services"
        }
    ],
    "sg:phone":"+1 601 878 9658",
    "sg:postcode":"39170",
    "sg:province":"MS",
    "sg:tags":[
        "taxidermist"
    ],
    "wof:name":"Dan Heasley Taxidermy",
    "wof:placetype":"venue"
},
  "geometry": {"coordinates":[-90.389381,32.122572],"type":"Point"}
}