{
  "type": "Feature",
  "properties": {
    "addr:full":"401 Roberts Dr Pearl MS 39208",
    "addr:housenumber":"401",
    "addr:postcode":"39208",
    "addr:street":"Roberts Dr",
    "iso:country":"US",
    "sg:address":"401 Roberts Dr",
    "sg:city":"Pearl",
    "sg:classifiers":[
        {
            "category":"Retail",
            "subcategory":"Repair Shop",
            "type":"Services"
        }
    ],
    "sg:phone":"+1 601 932 1107",
    "sg:postcode":"39208",
    "sg:province":"MS",
    "wof:name":"Copy Tech",
    "wof:placetype":"venue"
},
  "geometry": {"coordinates":[-90.131032,32.280306],"type":"Point"}
}