{
  "type": "Feature",
  "properties": {
    "addr:full":"121 N Jackson St Starkville MS 39759",
    "addr:housenumber":"121",
    "addr:postcode":"39759",
    "addr:street":"N Jackson St",
    "iso:country":"US",
    "sg:address":"121 N Jackson St",
    "sg:city":"Starkville",
    "sg:classifiers":[
        {
            "category":"Professional",
            "subcategory":"Lawyer & Legal Services",
            "type":"Services"
        }
    ],
    "sg:phone":"+1 662 323 1912",
    "sg:postcode":"39759",
    "sg:province":"MS",
    "sg:tags":[
        "attorney"
    ],
    "wof:name":"Ward & Rogers",
    "wof:placetype":"venue"
},
  "geometry": {"coordinates":[-88.813987,33.464443],"type":"Point"}
}