{
  "type": "Feature",
  "properties": {
    "addr:full":"2004 Hwy 82 W Greenwood MS 38930",
    "addr:housenumber":"2004",
    "addr:postcode":"38930",
    "addr:street":"Hwy 82 W",
    "iso:country":"US",
    "sg:address":"2004 Hwy 82 W",
    "sg:city":"Greenwood",
    "sg:classifiers":[
        {
            "category":"Insurance",
            "subcategory":"Insurance Agent",
            "type":"Services"
        }
    ],
    "sg:phone":"+1 662 453 0060",
    "sg:postcode":"38930",
    "sg:province":"MS",
    "wof:name":"Allstate",
    "wof:placetype":"venue"
},
  "geometry": {"coordinates":[-90.223063,33.528401],"type":"Point"}
}