{
  "type": "Feature",
  "properties": {
    "iso:country":"US",
    "sg:address":"207 N Columbus Ave",
    "sg:city":"Louisville",
    "sg:classifiers":[
        {
            "category":"Local Transit",
            "type":"Transportation"
        }
    ],
    "sg:phone":"+1 662 773 3444",
    "sg:postcode":"39339",
    "sg:province":"MS",
    "sg:tags":[
        "ambulance"
    ],
    "wof:name":"Emergystat Inc",
    "wof:placetype":"venue"
},
  "geometry": {"coordinates":[-89.05307000000001,33.12532],"type":"Point"}
}