{
  "type": "Feature",
  "properties": {
    "iso:country":"US",
    "sg:address":"904 E Main St",
    "sg:city":"Tupelo",
    "sg:classifiers":[
        {
            "category":"Professional",
            "subcategory":"Business Services",
            "type":"Services"
        },
        {
            "category":"Insurance",
            "subcategory":"Insurance Agent",
            "type":"Services"
        }
    ],
    "sg:phone":"+1 662 844 5307",
    "sg:postcode":"38804",
    "sg:province":"MS",
    "wof:name":"Northwestern Mutual Financial",
    "wof:placetype":"venue"
},
  "geometry": {"coordinates":[-88.68287100000001,34.257395],"type":"Point"}
}