{
  "type": "Feature",
  "properties": {
    "iso:country":"US",
    "sg:address":"1000 Shady Grove Rd",
    "sg:city":"Pontotoc",
    "sg:classifiers":[
        {
            "category":"Organizations",
            "subcategory":"Religious Organization",
            "type":"Services"
        }
    ],
    "sg:phone":"+1 662 489 7842",
    "sg:postcode":"38863",
    "sg:province":"MS",
    "sg:tags":[
        "church"
    ],
    "wof:name":"Shady Grove Baptist Church",
    "wof:placetype":"venue"
},
  "geometry": {"coordinates":[-89.110618,34.372423],"type":"Point"}
}