{
  "type": "Feature",
  "properties": {
    "iso:country":"US",
    "sg:address":"209 W Adams St",
    "sg:city":"Kosciusko",
    "sg:classifiers":[
        {
            "category":"Government",
            "subcategory":"Fire Station",
            "type":"Public Place"
        }
    ],
    "sg:phone":"+1 662 289 2311",
    "sg:postcode":"39090",
    "sg:province":"MS",
    "sg:tags":[
        "department"
    ],
    "wof:name":"Kosciusko Fire Dept",
    "wof:placetype":"venue"
},
  "geometry": {"coordinates":[-89.591995,33.059469],"type":"Point"}
}