{
  "type": "Feature",
  "properties": {
    "addr:full":"2226 Tv Rd Jackson MS 39209",
    "addr:housenumber":"2226",
    "addr:postcode":"39209",
    "addr:street":"Tv Rd",
    "iso:country":"US",
    "sg:address":"2226 Tv Rd",
    "sg:city":"Jackson",
    "sg:classifiers":[
        {
            "category":"Organizations",
            "subcategory":"Religious Organization",
            "type":"Services"
        }
    ],
    "sg:phone":"+1 601 922 9193",
    "sg:postcode":"39209",
    "sg:province":"MS",
    "wof:name":"New Life Apostolic Church Inc",
    "wof:placetype":"venue"
},
  "geometry": {"coordinates":[-90.28278899999999,32.283398],"type":"Point"}
}