{
  "type": "Feature",
  "properties": {
    "iso:country":"US",
    "sg:address":"678 Lebanon Rd",
    "sg:city":"Potts Camp",
    "sg:classifiers":[
        {
            "category":"Building & Trades",
            "subcategory":"Cleaning & Sanitation",
            "type":"Services"
        }
    ],
    "sg:phone":"+1 662 333 7176",
    "sg:postcode":"38659",
    "sg:province":"MS",
    "sg:tags":[
        "maintenance"
    ],
    "wof:name":"Shannon Cleaning Service",
    "wof:placetype":"venue"
},
  "geometry": {"coordinates":[-89.367024,34.610235],"type":"Point"}
}