{
  "type": "Feature",
  "properties": {
    "addr:full":"4509 B Pl Meridian MS 39301",
    "addr:housenumber":"4509",
    "addr:postcode":"39301",
    "addr:street":"B Pl",
    "iso:country":"US",
    "sg:address":"4509 B Pl",
    "sg:city":"Meridian",
    "sg:classifiers":[
        {
            "category":"Shopping",
            "subcategory":"Gifts & Souvenirs",
            "type":"Retail Goods"
        }
    ],
    "sg:phone":"+1 601 483 3197",
    "sg:postcode":"39301",
    "sg:province":"MS",
    "wof:name":"Lil t Enterprises",
    "wof:placetype":"venue"
},
  "geometry": {"coordinates":[-88.673913,32.405798],"type":"Point"}
}