{
  "type": "Feature",
  "properties": {
    "addr:full":"509 E Capitol St Jackson MS 39201",
    "addr:housenumber":"509",
    "addr:postcode":"39201",
    "addr:street":"E Capitol St",
    "iso:country":"US",
    "sg:address":"509 E Capitol St",
    "sg:city":"Jackson",
    "sg:classifiers":[
        {
            "category":"Education",
            "subcategory":"College",
            "type":"Public Place"
        }
    ],
    "sg:phone":"+1 601 354 6480",
    "sg:postcode":"39201",
    "sg:province":"MS",
    "sg:tags":[
        "academic",
        "school"
    ],
    "wof:name":"MSU School Of Architecture",
    "wof:placetype":"venue"
},
  "geometry": {"coordinates":[-90.18054100000001,32.299228],"type":"Point"}
}