{
  "type": "Feature",
  "properties": {
    "iso:country":"US",
    "sg:address":"423 Dukes Ave",
    "sg:city":"Columbia",
    "sg:classifiers":[
        {
            "category":"Organizations",
            "subcategory":"Religious Organization",
            "type":"Services"
        }
    ],
    "sg:phone":"+1 601 736 2312",
    "sg:postcode":"39429",
    "sg:province":"MS",
    "wof:name":"William Chap Church God Christ",
    "wof:placetype":"venue"
},
  "geometry": {"coordinates":[-89.828411,31.262705],"type":"Point"}
}