{
  "type": "Feature",
  "properties": {
    "addr:full":"101 Redd Loop Rd Natchez MS 39120",
    "addr:housenumber":"101",
    "addr:postcode":"39120",
    "addr:street":"Redd Loop Rd",
    "iso:country":"US",
    "sg:address":"101 Redd Loop Rd",
    "sg:city":"Natchez",
    "sg:classifiers":[
        {
            "category":"Shopping",
            "subcategory":"Hobbies, Toys, & Games",
            "type":"Retail Goods"
        }
    ],
    "sg:phone":"+1 601 442 2045",
    "sg:postcode":"39120",
    "sg:province":"MS",
    "sg:tags":[
        "model",
        "supply"
    ],
    "wof:name":"Trey's Hobby Shop",
    "wof:placetype":"venue"
},
  "geometry": {"coordinates":[-91.33407699999999,31.571096],"type":"Point"}
}