{
  "type": "Feature",
  "properties": {
    "iso:country":"US",
    "sg:address":"4604 Womack Dr",
    "sg:city":"Jackson",
    "sg:classifiers":[
        {
            "category":"Building & Trades",
            "subcategory":"Plumbing",
            "type":"Services"
        }
    ],
    "sg:phone":"+1 601 353 3774",
    "sg:postcode":"39209",
    "sg:province":"MS",
    "sg:tags":[
        "mechanical",
        "contractor"
    ],
    "wof:name":"Gipson Mechanical Contrs Inc",
    "wof:placetype":"venue"
},
  "geometry": {"coordinates":[-90.254092,32.355117],"type":"Point"}
}