{
  "type": "Feature",
  "properties": {
    "addr:full":"1404 Hatley Rd Amory MS 38821",
    "addr:housenumber":"1404",
    "addr:postcode":"38821",
    "addr:street":"Hatley Rd",
    "iso:country":"US",
    "sg:address":"1404 Hatley Rd",
    "sg:city":"Amory",
    "sg:classifiers":[
        {
            "category":"Building & Trades",
            "subcategory":"Equipment Rental",
            "type":"Services"
        }
    ],
    "sg:phone":"+1 662 256 2333",
    "sg:postcode":"38821",
    "sg:province":"MS",
    "wof:name":"Busy B Rental",
    "wof:placetype":"venue"
},
  "geometry": {"coordinates":[-88.460294,33.98619],"type":"Point"}
}