{
  "type": "Feature",
  "properties": {
    "addr:full":"331 W 3rd St Forest MS 39074",
    "addr:housenumber":"331",
    "addr:postcode":"39074",
    "addr:street":"W 3Rd St",
    "iso:country":"US",
    "sg:address":"331 W 3rd St",
    "sg:city":"Forest",
    "sg:classifiers":[
        {
            "category":"Autos & Motor Vehicles",
            "subcategory":"Auto Supplies",
            "type":"Retail Goods"
        }
    ],
    "sg:phone":"+1 601 469 0722",
    "sg:postcode":"39074",
    "sg:province":"MS",
    "sg:tags":[
        "parts",
        "accessory"
    ],
    "wof:name":"Autozone",
    "wof:placetype":"venue"
},
  "geometry": {"coordinates":[-89.47759600000001,32.364271],"type":"Point"}
}