{
  "type": "Feature",
  "properties": {
    "iso:country":"US",
    "sg:address":"307 S Washington Ave",
    "sg:city":"Greenville",
    "sg:classifiers":[
        {
            "category":"Personal",
            "type":"Services"
        }
    ],
    "sg:phone":"+1 662 820 6809",
    "sg:postcode":"38701",
    "sg:province":"MS",
    "sg:tags":[
        "therapist",
        "massage"
    ],
    "wof:name":"Robert Jordan",
    "wof:placetype":"venue"
},
  "geometry": {"coordinates":[-91.051644,33.404656],"type":"Point"}
}