{
  "type": "Feature",
  "properties": {
    "addr:full":"803 1st St Cleveland MS 38732",
    "addr:housenumber":"803",
    "addr:postcode":"38732",
    "addr:street":"1St St",
    "iso:country":"US",
    "sg:address":"803 1st St",
    "sg:city":"Cleveland",
    "sg:classifiers":[
        {
            "category":"Health Services",
            "subcategory":"Doctor",
            "type":"Services"
        }
    ],
    "sg:phone":"+1 662 843 2721",
    "sg:postcode":"38732",
    "sg:province":"MS",
    "sg:tags":[
        "medical"
    ],
    "wof:name":"Family Medical Clinic",
    "wof:placetype":"venue"
},
  "geometry": {"coordinates":[-90.711029,33.74888],"type":"Point"}
}