{
  "type": "Feature",
  "properties": {
    "iso:country":"US",
    "sg:address":"2702 25th Ave",
    "sg:city":"Gulfport",
    "sg:classifiers":[
        {
            "category":"Home & Garden",
            "subcategory":"Furniture",
            "type":"Retail Goods"
        }
    ],
    "sg:phone":"+1 228 864 1430",
    "sg:postcode":"39501",
    "sg:province":"MS",
    "sg:tags":[
        "household"
    ],
    "wof:name":"Broadus L S Furniture Co",
    "wof:placetype":"venue"
},
  "geometry": {"coordinates":[-89.09297100000001,30.38399],"type":"Point"}
}