{
  "type": "Feature",
  "properties": {
    "addr:full":"1610 Twin Oaks Dr Clinton MS 39056",
    "addr:housenumber":"1610",
    "addr:postcode":"39056",
    "addr:street":"Twin Oaks Dr",
    "iso:country":"US",
    "sg:address":"1610 Twin Oaks Dr",
    "sg:city":"Clinton",
    "sg:classifiers":[
        {
            "category":"Freight",
            "type":"Transportation"
        }
    ],
    "sg:phone":"+1 601 924 2224",
    "sg:postcode":"39056",
    "sg:province":"MS",
    "sg:tags":[
        "operator",
        "trucking"
    ],
    "wof:name":"Russell Trucking Inc",
    "wof:placetype":"venue"
},
  "geometry": {"coordinates":[-90.29901099999999,32.348874],"type":"Point"}
}