{
  "type": "Feature",
  "properties": {
    "iso:country":"US",
    "sg:address":"505 23rd Ave",
    "sg:city":"Meridian",
    "sg:classifiers":[
        {
            "category":"Personal",
            "subcategory":"Beauty Salon",
            "type":"Services"
        }
    ],
    "sg:phone":"+1 601 483 9519",
    "sg:postcode":"39301",
    "sg:province":"MS",
    "wof:name":"Hair Studio",
    "wof:placetype":"venue"
},
  "geometry": {"coordinates":[-88.701458,32.363829],"type":"Point"}
}