{
  "type": "Feature",
  "properties": {
    "iso:country":"US",
    "sg:address":"118 N Hayden St",
    "sg:city":"Belzoni",
    "sg:classifiers":[
        {
            "category":"Real Estate",
            "subcategory":"Real Estate Agent",
            "type":"Services"
        }
    ],
    "sg:phone":"+1 662 247 2431",
    "sg:postcode":"39038",
    "sg:province":"MS",
    "sg:tags":[
        "management"
    ],
    "wof:name":"Turner Rentals",
    "wof:placetype":"venue"
},
  "geometry": {"coordinates":[-90.488625,33.190804],"type":"Point"}
}