{
  "type": "Feature",
  "properties": {
    "addr:full":"305 Conehatta Rd Union MS 39365",
    "addr:housenumber":"305",
    "addr:postcode":"39365",
    "addr:street":"Conehatta Rd",
    "iso:country":"US",
    "sg:address":"305 Conehatta Rd",
    "sg:city":"Union",
    "sg:classifiers":[
        {
            "category":"Real Estate",
            "subcategory":"Real Estate Agent",
            "type":"Services"
        }
    ],
    "sg:phone":"+1 601 774 9108",
    "sg:postcode":"39365",
    "sg:province":"MS",
    "wof:name":"T & T Properties",
    "wof:placetype":"venue"
},
  "geometry": {"coordinates":[-89.122816,32.568605],"type":"Point"}
}