{
  "type": "Feature",
  "properties": {
    "iso:country":"US",
    "sg:address":"5765 Polk Ln",
    "sg:city":"Olive Branch",
    "sg:classifiers":[
        {
            "category":"Building & Trades",
            "subcategory":"Plumbing",
            "type":"Services"
        }
    ],
    "sg:phone":"+1 662 895 5357",
    "sg:postcode":"38654",
    "sg:province":"MS",
    "sg:tags":[
        "contractor"
    ],
    "wof:name":"Foust Plumbing Co",
    "wof:placetype":"venue"
},
  "geometry": {"coordinates":[-89.777475,34.947305],"type":"Point"}
}