{
  "type": "Feature",
  "properties": {
    "iso:country":"US",
    "sg:address":"134 Kirkwood Dr",
    "sg:city":"Clinton",
    "sg:classifiers":[
        {
            "category":"Building & Trades",
            "subcategory":"Construction",
            "type":"Services"
        }
    ],
    "sg:phone":"+1 601 924 5556",
    "sg:postcode":"39056",
    "sg:province":"MS",
    "sg:tags":[
        "home",
        "builder"
    ],
    "wof:name":"Kirkland Real Estate",
    "wof:placetype":"venue"
},
  "geometry": {"coordinates":[-90.338753,32.316377],"type":"Point"}
}