{
  "type": "Feature",
  "properties": {
    "addr:full":"11455 Holly Bluff Cir Biloxi MS 39532",
    "addr:housenumber":"11455",
    "addr:postcode":"39532",
    "addr:street":"Holly Bluff Cir",
    "iso:country":"US",
    "sg:address":"11455 Holly Bluff Cir",
    "sg:city":"Biloxi",
    "sg:classifiers":[
        {
            "category":"Real Estate",
            "subcategory":"Architect",
            "type":"Services"
        }
    ],
    "sg:phone":"+1 228 396 1855",
    "sg:postcode":"39532",
    "sg:province":"MS",
    "sg:tags":[
        "architectural"
    ],
    "wof:name":"Denmark Design Inc",
    "wof:placetype":"venue"
},
  "geometry": {"coordinates":[-88.932575,30.455093],"type":"Point"}
}