{
  "type": "Feature",
  "properties": {
    "addr:full":"203 Maid Marian Rd Starkville MS 39759",
    "addr:housenumber":"203",
    "addr:postcode":"39759",
    "addr:street":"Maid Marian Rd",
    "iso:country":"US",
    "sg:address":"203 Maid Marian Rd",
    "sg:city":"Starkville",
    "sg:classifiers":[
        {
            "category":"Manufacturing",
            "subcategory":"Printing",
            "type":"Manufacturing & Wholesale Goods"
        }
    ],
    "sg:phone":"+1 662 324 1040",
    "sg:postcode":"39759",
    "sg:province":"MS",
    "sg:tags":[
        "periodical"
    ],
    "wof:name":"Centcom Ltd",
    "wof:placetype":"venue"
},
  "geometry": {"coordinates":[-88.80362700000001,33.444758],"type":"Point"}
}