{
  "type": "Feature",
  "properties": {
    "addr:full":"308 Steens Vernon Rd Steens MS 39766",
    "addr:housenumber":"308",
    "addr:postcode":"39766",
    "addr:street":"Steens Vernon Rd",
    "iso:country":"US",
    "sg:address":"308 Steens Vernon Rd",
    "sg:city":"Steens",
    "sg:classifiers":[
        {
            "category":"Home & Garden",
            "subcategory":"Furniture",
            "type":"Retail Goods"
        }
    ],
    "sg:phone":"+1 662 328 5075",
    "sg:postcode":"39766",
    "sg:province":"MS",
    "sg:tags":[
        "builder",
        "custom"
    ],
    "wof:name":"Riverbend Furniture & Millwork",
    "wof:placetype":"venue"
},
  "geometry": {"coordinates":[-88.315929,33.56357],"type":"Point"}
}