{
  "type": "Feature",
  "properties": {
    "addr:full":"411 W Main St West Point MS 39773",
    "addr:housenumber":"411",
    "addr:postcode":"39773",
    "addr:street":"W Main St",
    "iso:country":"US",
    "sg:address":"411 W Main St",
    "sg:city":"West Point",
    "sg:classifiers":[
        {
            "category":"Shopping",
            "subcategory":"Clothing, Apparel, & Fashions",
            "type":"Retail Goods"
        }
    ],
    "sg:phone":"+1 662 494 0307",
    "sg:postcode":"39773",
    "sg:province":"MS",
    "wof:name":"M'Ladys Accessories",
    "wof:placetype":"venue"
},
  "geometry": {"coordinates":[-88.65545299999999,33.607185],"type":"Point"}
}