{
  "type": "Feature",
  "properties": {
    "iso:country":"US",
    "sg:address":"3785 Nesbit Rd",
    "sg:city":"Nesbit",
    "sg:classifiers":[
        {
            "category":"Building & Trades",
            "subcategory":"Construction",
            "type":"Services"
        }
    ],
    "sg:phone":"+1 662 429 1847",
    "sg:postcode":"38651",
    "sg:province":"MS",
    "wof:name":"Billy Lawrence Grading",
    "wof:placetype":"venue"
},
  "geometry": {"coordinates":[-90.056292,34.889695],"type":"Point"}
}