{
  "type": "Feature",
  "properties": {
    "iso:country":"US",
    "sg:address":"105 Alabama St",
    "sg:city":"Columbus",
    "sg:classifiers":[
        {
            "category":"Insurance",
            "subcategory":"Insurance Agent",
            "type":"Services"
        }
    ],
    "sg:phone":"+1 662 328 5701",
    "sg:postcode":"39702",
    "sg:province":"MS",
    "wof:name":"State Farm Insurance",
    "wof:placetype":"venue"
},
  "geometry": {"coordinates":[-88.389118,33.496948],"type":"Point"}
}