{
  "type": "Feature",
  "properties": {
    "addr:full":"203 N Cleveland Ave Long Beach MS 39560",
    "addr:housenumber":"203",
    "addr:postcode":"39560",
    "addr:street":"N Cleveland Ave",
    "iso:country":"US",
    "sg:address":"203 N Cleveland Ave",
    "sg:city":"Long Beach",
    "sg:classifiers":[
        {
            "category":"Real Estate",
            "subcategory":"Real Estate Operator",
            "type":"Services"
        }
    ],
    "sg:phone":"+1 228 864 7371",
    "sg:postcode":"39560",
    "sg:province":"MS",
    "sg:tags":[
        "building",
        "apartment"
    ],
    "wof:name":"Lynd Company",
    "wof:placetype":"venue"
},
  "geometry": {"coordinates":[-89.147063,30.353256],"type":"Point"}
}