{
  "type": "Feature",
  "properties": {
    "addr:full":"1626 24th Ave Gulfport MS 39501",
    "addr:housenumber":"1626",
    "addr:postcode":"39501",
    "addr:street":"24Th Ave",
    "iso:country":"US",
    "sg:address":"1626 24th Ave",
    "sg:city":"Gulfport",
    "sg:classifiers":[
        {
            "category":"Health Services",
            "subcategory":"Doctor",
            "type":"Services"
        }
    ],
    "sg:phone":"+1 228 864 4501",
    "sg:postcode":"39501",
    "sg:province":"MS",
    "sg:tags":[
        "physician",
        "surgeon"
    ],
    "wof:name":"Gulfcoast Radiation Oncology",
    "wof:placetype":"venue"
},
  "geometry": {"coordinates":[-89.091454,30.371288],"type":"Point"}
}