{
  "type": "Feature",
  "properties": {
    "iso:country":"US",
    "sg:address":"2040 Johnston Chapel Rd",
    "sg:city":"Summit",
    "sg:classifiers":[
        {
            "category":"Wholesale",
            "subcategory":"Plants",
            "type":"Manufacturing & Wholesale Goods"
        }
    ],
    "sg:phone":"+1 601 276 2794",
    "sg:postcode":"39666",
    "sg:province":"MS",
    "sg:tags":[
        "nursery",
        "tree"
    ],
    "wof:name":"Williamson Nursery",
    "wof:placetype":"venue"
},
  "geometry": {"coordinates":[-90.509815,31.320943],"type":"Point"}
}