{
  "type": "Feature",
  "properties": {
    "addr:full":"620 S 28th Ave Hattiesburg MS 39402",
    "addr:housenumber":"620",
    "addr:postcode":"39402",
    "addr:street":"S 28Th Ave",
    "iso:country":"US",
    "sg:address":"620 S 28th Ave",
    "sg:city":"Hattiesburg",
    "sg:classifiers":[
        {
            "category":"Real Estate",
            "subcategory":"Real Estate Operator",
            "type":"Services"
        }
    ],
    "sg:phone":"+1 601 268 6173",
    "sg:postcode":"39402",
    "sg:province":"MS",
    "sg:tags":[
        "building",
        "apartment"
    ],
    "wof:name":"South Miss",
    "wof:placetype":"venue"
},
  "geometry": {"coordinates":[-89.331163,31.313368],"type":"Point"}
}