{
  "type": "Feature",
  "properties": {
    "iso:country":"US",
    "sg:address":"236 Starlyn Ln",
    "sg:city":"New Albany",
    "sg:classifiers":[
        {
            "category":"Health Services",
            "subcategory":"Doctor",
            "type":"Services"
        }
    ],
    "sg:phone":"+1 662 534 4121",
    "sg:postcode":"38652",
    "sg:province":"MS",
    "sg:tags":[
        "physician",
        "surgeon"
    ],
    "wof:name":"Advanced Obstetrics & Gynclgy",
    "wof:placetype":"venue"
},
  "geometry": {"coordinates":[-89.035623,34.496125],"type":"Point"}
}