{
  "type": "Feature",
  "properties": {
    "iso:country":"US",
    "sg:address":"6745 S Siwell Rd",
    "sg:city":"Byram",
    "sg:classifiers":[
        {
            "category":"Restaurant",
            "type":"Food & Drink"
        }
    ],
    "sg:phone":"+1 601 371 0101",
    "sg:postcode":"39212",
    "sg:province":"MS",
    "sg:tags":[
        "parlor",
        "ice",
        "cream"
    ],
    "wof:name":"Bop's Frozen Custards Of Byram",
    "wof:placetype":"venue"
},
  "geometry": {"coordinates":[-90.295678,32.205757],"type":"Point"}
}