{
  "type": "Feature",
  "properties": {
    "addr:full":"420 Russell Ave Ocean Springs MS 39564",
    "addr:housenumber":"420",
    "addr:postcode":"39564",
    "addr:street":"Russell Ave",
    "iso:country":"US",
    "sg:address":"420 Russell Ave",
    "sg:city":"Ocean Springs",
    "sg:classifiers":[
        {
            "category":"Restaurant",
            "type":"Food & Drink"
        }
    ],
    "sg:phone":"+1 228 872 3637",
    "sg:postcode":"39564",
    "sg:province":"MS",
    "sg:tags":[
        "eating"
    ],
    "wof:name":"Ice Inc",
    "wof:placetype":"venue"
},
  "geometry": {"coordinates":[-88.824552,30.410071],"type":"Point"}
}