{
  "type": "Feature",
  "properties": {
    "iso:country":"US",
    "sg:address":"1000 Cliff Gookin Blvd",
    "sg:city":"Tupelo",
    "sg:classifiers":[
        {
            "category":"Restaurant",
            "type":"Food & Drink"
        }
    ],
    "sg:phone":"+1 662 840 3900",
    "sg:postcode":"38801",
    "sg:province":"MS",
    "sg:tags":[
        "pizza"
    ],
    "wof:name":"Hutstuff Pizzeria",
    "wof:placetype":"venue"
},
  "geometry": {"coordinates":[-88.73213199999999,34.223566],"type":"Point"}
}