{
  "type": "Feature",
  "properties": {
    "iso:country":"US",
    "sg:address":"801 Desoto Cove",
    "sg:city":"Horn Lake",
    "sg:classifiers":[
        {
            "category":"Restaurant",
            "type":"Food & Drink"
        }
    ],
    "sg:phone":"+1 901 848 7902",
    "sg:postcode":"38637",
    "sg:province":"MS",
    "sg:tags":[
        "fast"
    ],
    "wof:name":"Simexim Inc",
    "wof:placetype":"venue"
},
  "geometry": {"coordinates":[-90.00111699999999,34.966825],"type":"Point"}
}