{
  "type": "Feature",
  "properties": {
    "iso:country":"US",
    "sg:address":"1243 Langley Ave",
    "sg:city":"Jackson",
    "sg:classifiers":[
        {
            "category":"Building & Trades",
            "subcategory":"Construction",
            "type":"Services"
        }
    ],
    "sg:phone":"+1 601 353 3744",
    "sg:postcode":"39204",
    "sg:province":"MS",
    "sg:tags":[
        "general",
        "contractor"
    ],
    "wof:name":"W H Scott Construction Co",
    "wof:placetype":"venue"
},
  "geometry": {"coordinates":[-90.195948,32.286602],"type":"Point"}
}