{
  "type": "Feature",
  "properties": {
    "iso:country":"US",
    "sg:address":"4361 Hwy 9 S",
    "sg:city":"Pontotoc",
    "sg:classifiers":[
        {
            "category":"Home & Garden",
            "subcategory":"Furniture",
            "type":"Retail Goods"
        }
    ],
    "sg:phone":"+1 662 456 9204",
    "sg:postcode":"38863",
    "sg:province":"MS",
    "wof:name":"Houston Furniture Supply Inc",
    "wof:placetype":"venue"
},
  "geometry": {"coordinates":[-89.091104,34.235485],"type":"Point"}
}