{
  "type": "Feature",
  "properties": {
    "iso:country":"US",
    "sg:address":"1367 Ross Cir",
    "sg:city":"Jackson",
    "sg:classifiers":[
        {
            "category":"Government",
            "subcategory":"Fire Station",
            "type":"Public Place"
        }
    ],
    "sg:phone":"+1 601 982 8761",
    "sg:postcode":"39209",
    "sg:province":"MS",
    "sg:tags":[
        "department"
    ],
    "wof:name":"Maclean Volunteer Fire Dept",
    "wof:placetype":"venue"
},
  "geometry": {"coordinates":[-90.279883,32.42393],"type":"Point"}
}