{
  "type": "Feature",
  "properties": {
    "iso:country":"US",
    "sg:address":"237 E Amite St",
    "sg:city":"Jackson",
    "sg:classifiers":[
        {
            "category":"Manufacturing",
            "subcategory":"Printing",
            "type":"Manufacturing & Wholesale Goods"
        }
    ],
    "sg:phone":"+1 601 969 3581",
    "sg:postcode":"39201",
    "sg:province":"MS",
    "sg:tags":[
        "newspaper"
    ],
    "wof:name":"Mississippi Catholic",
    "wof:placetype":"venue"
},
  "geometry": {"coordinates":[-90.184566,32.300903],"type":"Point"}
}