{
  "type": "Feature",
  "properties": {
    "addr:full":"234 Co Rd 333 Heidelberg MS 39439",
    "addr:housenumber":"234",
    "addr:postcode":"333;39439",
    "addr:street":"Co Rd",
    "iso:country":"US",
    "sg:address":"234 Co Rd 333",
    "sg:city":"Heidelberg",
    "sg:classifiers":[
        {
            "category":"Organizations",
            "subcategory":"Religious Organization",
            "type":"Services"
        }
    ],
    "sg:phone":"+1 601 787 2176",
    "sg:postcode":"39439",
    "sg:province":"MS",
    "wof:name":"Wesley Chapel AME Church",
    "wof:placetype":"venue"
},
  "geometry": {"coordinates":[-89.03688699999999,31.848081],"type":"Point"}
}