{
  "type": "Feature",
  "properties": {
    "iso:country":"US",
    "sg:address":"2152 Baywood Dr",
    "sg:city":"Biloxi",
    "sg:classifiers":[
        {
            "category":"Professional",
            "subcategory":"Business Services",
            "type":"Services"
        }
    ],
    "sg:phone":"+1 228 388 0057",
    "sg:postcode":"39532",
    "sg:province":"MS",
    "wof:name":"United Services LLC",
    "wof:placetype":"venue"
},
  "geometry": {"coordinates":[-88.96439700000001,30.435166],"type":"Point"}
}