{
  "type": "Feature",
  "properties": {
    "iso:country":"US",
    "sg:address":"709 Mc Kinley St",
    "sg:city":"Clarksdale",
    "sg:classifiers":[
        {
            "category":"Social Services",
            "subcategory":"Child Care",
            "type":"Services"
        }
    ],
    "sg:phone":"+1 662 621 1039",
    "sg:postcode":"38614",
    "sg:province":"MS",
    "sg:tags":[
        "day"
    ],
    "wof:name":"Helping Hands Childcare Center",
    "wof:placetype":"venue"
},
  "geometry": {"coordinates":[-90.559782,34.197266],"type":"Point"}
}