{
  "type": "Feature",
  "properties": {
    "iso:country":"US",
    "sg:address":"2666 Learned Rd",
    "sg:city":"Raymond",
    "sg:classifiers":[
        {
            "category":"Organizations",
            "subcategory":"Religious Organization",
            "type":"Services"
        }
    ],
    "sg:phone":"+1 601 885 6314",
    "sg:postcode":"39154",
    "sg:province":"MS",
    "wof:name":"Salem Baptist Church",
    "wof:placetype":"venue"
},
  "geometry": {"coordinates":[-90.54294400000001,32.17756],"type":"Point"}
}