{
  "type": "Feature",
  "properties": {
    "iso:country":"US",
    "sg:address":"1075 Carsley Rd",
    "sg:city":"Jackson",
    "sg:classifiers":[
        {
            "category":"Wholesale",
            "subcategory":"Construction Materials",
            "type":"Manufacturing & Wholesale Goods"
        }
    ],
    "sg:phone":"+1 601 924 0094",
    "sg:postcode":"39209",
    "sg:province":"MS",
    "sg:tags":[
        "fence"
    ],
    "wof:name":"Gatekeeper Inc",
    "wof:placetype":"venue"
},
  "geometry": {"coordinates":[-90.374844,32.451116],"type":"Point"}
}