{
  "type": "Feature",
  "properties": {
    "addr:full":"224 Commerce Dr Brandon MS 39042",
    "addr:housenumber":"224",
    "addr:postcode":"39042",
    "addr:street":"Commerce Dr",
    "iso:country":"US",
    "sg:address":"224 Commerce Dr",
    "sg:city":"Brandon",
    "sg:classifiers":[
        {
            "category":"Organizations",
            "subcategory":"Non-profit Organization",
            "type":"Services"
        }
    ],
    "sg:phone":"+1 601 824 7020",
    "sg:postcode":"39042",
    "sg:province":"MS",
    "sg:tags":[
        "social"
    ],
    "wof:name":"Baptist Home Health Services",
    "wof:placetype":"venue"
},
  "geometry": {"coordinates":[-90.02697000000001,32.282002],"type":"Point"}
}