{
  "type": "Feature",
  "properties": {
    "iso:country":"US",
    "sg:address":"3330 S Liberty St",
    "sg:city":"Canton",
    "sg:classifiers":[
        {
            "category":"Health Services",
            "subcategory":"Clinic",
            "type":"Services"
        }
    ],
    "sg:phone":"+1 601 855 0045",
    "sg:postcode":"39046",
    "sg:province":"MS",
    "sg:tags":[
        "home"
    ],
    "wof:name":"Sta-Home Health Agency",
    "wof:placetype":"venue"
},
  "geometry": {"coordinates":[-90.03497400000001,32.611827],"type":"Point"}
}