{
  "type": "Feature",
  "properties": {
    "iso:country":"US",
    "sg:address":"4432 State Blvd",
    "sg:city":"Meridian",
    "sg:classifiers":[
        {
            "category":"Travel",
            "subcategory":"Hotels & Motels",
            "type":"Entertainment"
        }
    ],
    "sg:phone":"+1 601 485 8235",
    "sg:postcode":"39307",
    "sg:province":"MS",
    "sg:tags":[
        "breakfast",
        "operation",
        "bed",
        "accommodation"
    ],
    "wof:name":"Lion and Harp Bed & Breakfast",
    "wof:placetype":"venue"
},
  "geometry": {"coordinates":[-88.73532,32.406221],"type":"Point"}
}