{
  "type": "Feature",
  "properties": {
    "iso:country":"US",
    "sg:address":"363 Courthouse Rd",
    "sg:city":"Gulfport",
    "sg:classifiers":[
        {
            "category":"Government",
            "subcategory":"Post Office",
            "type":"Public Place"
        }
    ],
    "sg:phone":"+1 228 896 3826",
    "sg:postcode":"39507",
    "sg:province":"MS",
    "sg:tags":[
        "postal",
        "us"
    ],
    "wof:name":"US Post Office",
    "wof:placetype":"venue"
},
  "geometry": {"coordinates":[-89.044107,30.3854],"type":"Point"}
}