{
  "type": "Feature",
  "properties": {
    "addr:full":"211 Broad St New Albany MS 38652",
    "addr:housenumber":"211",
    "addr:postcode":"38652",
    "addr:street":"Broad St",
    "iso:country":"US",
    "sg:address":"211 Broad St",
    "sg:city":"New Albany",
    "sg:classifiers":[
        {
            "category":"Restaurant",
            "type":"Food & Drink"
        }
    ],
    "sg:menulink":"http://www.allmenus.com/ms/graham/132986-subway/menu/",
    "sg:phone":"+1 662 534 7607",
    "sg:postcode":"38652",
    "sg:province":"MS",
    "sg:tags":[
        "american",
        "sandwich"
    ],
    "wof:name":"Subway",
    "wof:placetype":"venue"
},
  "geometry": {"coordinates":[-89.00315399999999,34.49666],"type":"Point"}
}