{
  "type": "Feature",
  "properties": {
    "iso:country":"US",
    "sg:address":"1909 Hwy 45 N",
    "sg:city":"Columbus",
    "sg:classifiers":[
        {
            "category":"Retail",
            "subcategory":"Animal Services",
            "type":"Services"
        }
    ],
    "sg:phone":"+1 662 245 0452",
    "sg:postcode":"39705",
    "sg:province":"MS",
    "sg:tags":[
        "pet",
        "grooming",
        "washing"
    ],
    "wof:name":"Sassy Pups",
    "wof:placetype":"venue"
},
  "geometry": {"coordinates":[-88.437172,33.531248],"type":"Point"}
}