{
  "type": "Feature",
  "properties": {
    "iso:country":"US",
    "sg:address":"3198 Russell Camp Rd",
    "sg:city":"Meridian",
    "sg:classifiers":[
        {
            "category":"Retail",
            "subcategory":"Auto Repair",
            "type":"Services"
        }
    ],
    "sg:phone":"+1 601 644 3486",
    "sg:postcode":"39301",
    "sg:province":"MS",
    "sg:tags":[
        "general"
    ],
    "wof:name":"Joness Body Shop",
    "wof:placetype":"venue"
},
  "geometry": {"coordinates":[-88.537227,32.287318],"type":"Point"}
}