{
  "type": "Feature",
  "properties": {
    "addr:full":"412 N Gate Rd Hattiesburg MS 39401",
    "addr:housenumber":"412",
    "addr:postcode":"39401",
    "addr:street":"N Gate Rd",
    "iso:country":"US",
    "sg:address":"412 N Gate Rd",
    "sg:city":"Hattiesburg",
    "sg:classifiers":[
        {
            "category":"Building & Trades",
            "subcategory":"Construction",
            "type":"Services"
        }
    ],
    "sg:phone":"+1 601 584 1078",
    "sg:postcode":"39401",
    "sg:province":"MS",
    "sg:tags":[
        "general",
        "contractor"
    ],
    "wof:name":"Gottfried Construction",
    "wof:placetype":"venue"
},
  "geometry": {"coordinates":[-89.23906700000001,31.231083],"type":"Point"}
}