{
  "type": "Feature",
  "properties": {
    "addr:full":"1138 Cloverdale Dr Greenville MS 38701",
    "addr:housenumber":"1138",
    "addr:postcode":"38701",
    "addr:street":"Cloverdale Dr",
    "iso:country":"US",
    "sg:address":"1138 Cloverdale Dr",
    "sg:city":"Greenville",
    "sg:classifiers":[
        {
            "category":"Professional",
            "subcategory":"Business Services",
            "type":"Services"
        }
    ],
    "sg:phone":"+1 662 335 2270",
    "sg:postcode":"38701",
    "sg:province":"MS",
    "sg:tags":[
        "consultant",
        "coach"
    ],
    "wof:name":"Transition Consultants",
    "wof:placetype":"venue"
},
  "geometry": {"coordinates":[-91.03407300000001,33.347279],"type":"Point"}
}