{
  "type": "Feature",
  "properties": {
    "addr:full":"2707 US Hwy 90 Gautier MS 39553",
    "addr:housenumber":"2707",
    "addr:postcode":"39553",
    "addr:street":"Us Hwy 90",
    "iso:country":"US",
    "sg:address":"2707 US Hwy 90",
    "sg:city":"Gautier",
    "sg:classifiers":[
        {
            "category":"Organizations",
            "subcategory":"Religious Organization",
            "type":"Services"
        }
    ],
    "sg:phone":"+1 228 522 1980",
    "sg:postcode":"39553",
    "sg:province":"MS",
    "sg:tags":[
        "church"
    ],
    "wof:name":"Refuge",
    "wof:placetype":"venue"
},
  "geometry": {"coordinates":[-88.65189599999999,30.391726],"type":"Point"}
}