{
  "type": "Feature",
  "properties": {
    "addr:full":"205 Bardwell Ave Mc Comb MS 39648",
    "addr:housenumber":"205",
    "addr:postcode":"39648",
    "addr:street":"Bardwell Ave Mc Comb",
    "iso:country":"US",
    "sg:address":"205 Bardwell Ave",
    "sg:city":"Mc Comb",
    "sg:classifiers":[
        {
            "category":"Organizations",
            "subcategory":"Religious Organization",
            "type":"Services"
        }
    ],
    "sg:phone":"+1 601 684 6996",
    "sg:postcode":"39648",
    "sg:province":"MS",
    "wof:name":"New Harvest Church of God",
    "wof:placetype":"venue"
},
  "geometry": {"coordinates":[-90.45244599999999,31.228285],"type":"Point"}
}