{
  "type": "Feature",
  "properties": {
    "iso:country":"US",
    "sg:address":"714 Jackson Ave E",
    "sg:city":"Oxford",
    "sg:classifiers":[
        {
            "category":"Banks & Credit Unions",
            "subcategory":"Bank",
            "type":"Services"
        }
    ],
    "sg:phone":"+1 662 234 8617",
    "sg:postcode":"38655",
    "sg:province":"MS",
    "sg:tags":[
        "commercial"
    ],
    "wof:name":"Commonwealth Savingshares",
    "wof:placetype":"venue"
},
  "geometry": {"coordinates":[-89.52214600000001,34.367259],"type":"Point"}
}