{
  "type": "Feature",
  "properties": {
    "iso:country":"US",
    "sg:address":"244 Hosey Rd",
    "sg:city":"Magee",
    "sg:classifiers":[
        {
            "category":"Professional",
            "type":"Services"
        }
    ],
    "sg:phone":"+1 601 867 3915",
    "sg:postcode":"39111",
    "sg:province":"MS",
    "sg:tags":[
        "establishment"
    ],
    "wof:name":"SRS",
    "wof:placetype":"venue"
},
  "geometry": {"coordinates":[-89.67421,31.964508],"type":"Point"}
}