{
  "type": "Feature",
  "properties": {
    "iso:country":"US",
    "sg:address":"1400 24th Ave",
    "sg:city":"Gulfport",
    "sg:classifiers":[
        {
            "category":"Government",
            "subcategory":"Office",
            "type":"Public Place"
        }
    ],
    "sg:phone":"+1 228 864 0254",
    "sg:postcode":"39501",
    "sg:province":"MS",
    "sg:tags":[
        "state"
    ],
    "sg:website":"www.sos.state.ms.us",
    "wof:name":"Secretary Of State",
    "wof:placetype":"venue"
},
  "geometry": {"coordinates":[-89.091499,30.369262],"type":"Point"}
}