{
  "type": "Feature",
  "properties": {
    "iso:country":"US",
    "sg:address":"1170 Hwy 49 S",
    "sg:city":"Jackson",
    "sg:classifiers":[
        {
            "category":"Restaurant",
            "type":"Food & Drink"
        }
    ],
    "sg:phone":"+1 601 932 7580",
    "sg:postcode":"39218",
    "sg:province":"MS",
    "sg:tags":[
        "eating"
    ],
    "wof:name":"Taco Bell",
    "wof:placetype":"venue"
},
  "geometry": {"coordinates":[-90.113899,32.149002],"type":"Point"}
}