{
  "type": "Feature",
  "properties": {
    "addr:full":"1606 Chickasaw St Greenwood MS 38930",
    "addr:housenumber":"1606",
    "addr:postcode":"38930",
    "addr:street":"Chickasaw St",
    "iso:country":"US",
    "sg:address":"1606 Chickasaw St",
    "sg:city":"Greenwood",
    "sg:classifiers":[
        {
            "category":"Professional",
            "subcategory":"Management & Consulting",
            "type":"Services"
        }
    ],
    "sg:phone":"+1 662 453 3645",
    "sg:postcode":"38930",
    "sg:province":"MS",
    "wof:name":"AFA Recovery Network",
    "wof:placetype":"venue"
},
  "geometry": {"coordinates":[-90.210615,33.527844],"type":"Point"}
}