{
  "type": "Feature",
  "properties": {
    "addr:full":"816 Mayes St W Jackson MS 39213",
    "addr:housenumber":"816",
    "addr:postcode":"39213",
    "addr:street":"Mayes St W",
    "iso:country":"US",
    "sg:address":"816 Mayes St W",
    "sg:city":"Jackson",
    "sg:classifiers":[
        {
            "category":"Food & Beverages",
            "subcategory":"Groceries & Convenience Stores",
            "type":"Retail Goods"
        }
    ],
    "sg:phone":"+1 601 982 2727",
    "sg:postcode":"39213",
    "sg:province":"MS",
    "sg:tags":[
        "grocer"
    ],
    "wof:name":"Mickey's Fairway Supermarket",
    "wof:placetype":"venue"
},
  "geometry": {"coordinates":[-90.19178599999999,32.345033],"type":"Point"}
}