{
  "type": "Feature",
  "properties": {
    "iso:country":"US",
    "sg:address":"11130 Canal Rd",
    "sg:city":"Gulfport",
    "sg:classifiers":[
        {
            "category":"Building & Trades",
            "subcategory":"Construction",
            "type":"Services"
        }
    ],
    "sg:phone":"+1 228 832 1526",
    "sg:postcode":"39503",
    "sg:province":"MS",
    "sg:tags":[
        "painter"
    ],
    "sg:website":"www.industrialcorrosion.com",
    "wof:name":"Industrial Corrosion Control",
    "wof:placetype":"venue"
},
  "geometry": {"coordinates":[-89.13676,30.443027],"type":"Point"}
}