{
  "type": "Feature",
  "properties": {
    "addr:full":"919 Hwy 82 W Greenwood MS 38930",
    "addr:housenumber":"919",
    "addr:postcode":"38930",
    "addr:street":"Hwy 82 W",
    "iso:country":"US",
    "sg:address":"919 Hwy 82 W",
    "sg:city":"Greenwood",
    "sg:classifiers":[
        {
            "category":"Restaurant",
            "type":"Food & Drink"
        }
    ],
    "sg:phone":"+1 601 455 3030",
    "sg:postcode":"38930",
    "sg:province":"MS",
    "sg:tags":[
        "pizza"
    ],
    "wof:name":"Domino's Pizza",
    "wof:placetype":"venue"
},
  "geometry": {"coordinates":[-90.204943,33.524373],"type":"Point"}
}