{
  "type": "Feature",
  "properties": {
    "addr:full":"1626 E Pass Rd Gulfport MS 39507",
    "addr:housenumber":"1626",
    "addr:postcode":"39507",
    "addr:street":"E Pass Rd",
    "iso:country":"US",
    "sg:address":"1626 E Pass Rd",
    "sg:city":"Gulfport",
    "sg:classifiers":[
        {
            "category":"Health Services",
            "subcategory":"Doctor",
            "type":"Services"
        }
    ],
    "sg:phone":"+1 228 896 4084",
    "sg:postcode":"39507",
    "sg:province":"MS",
    "sg:tags":[
        "dentist"
    ],
    "wof:name":"Emery L Edwards DDS",
    "wof:placetype":"venue"
},
  "geometry": {"coordinates":[-89.02087899999999,30.400095],"type":"Point"}
}