{
  "type": "Feature",
  "properties": {
    "addr:full":"2319 Crestwood Dr Tupelo MS 38801",
    "addr:housenumber":"2319",
    "addr:postcode":"38801",
    "addr:street":"Crestwood Dr",
    "iso:country":"US",
    "sg:address":"2319 Crestwood Dr",
    "sg:city":"Tupelo",
    "sg:classifiers":[
        {
            "category":"Professional",
            "subcategory":"Management & Consulting",
            "type":"Services"
        }
    ],
    "sg:phone":"+1 662 840 7601",
    "sg:postcode":"38801",
    "sg:province":"MS",
    "sg:tags":[
        "business"
    ],
    "wof:name":"Holley Consulting Service",
    "wof:placetype":"venue"
},
  "geometry": {"coordinates":[-88.740955,34.243688],"type":"Point"}
}