{
  "type": "Feature",
  "properties": {
    "iso:country":"US",
    "sg:address":"36 Academy Dr",
    "sg:city":"Hattiesburg",
    "sg:classifiers":[
        {
            "category":"Government",
            "subcategory":"Office",
            "type":"Public Place"
        }
    ],
    "sg:phone":"+1 601 582 3234",
    "sg:postcode":"39401",
    "sg:province":"MS",
    "sg:tags":[
        "national",
        "security"
    ],
    "wof:name":"Reserve Center",
    "wof:placetype":"venue"
},
  "geometry": {"coordinates":[-89.258053,31.270327],"type":"Point"}
}