{
  "type": "Feature",
  "properties": {
    "addr:full":"528 Alabama St Columbus MS 39702",
    "addr:housenumber":"528",
    "addr:postcode":"39702",
    "addr:street":"Alabama St",
    "iso:country":"US",
    "sg:address":"528 Alabama St",
    "sg:city":"Columbus",
    "sg:classifiers":[
        {
            "category":"Shopping",
            "subcategory":"Computers & Home Electronics",
            "type":"Retail Goods"
        }
    ],
    "sg:phone":"+1 662 327 0781",
    "sg:postcode":"39702",
    "sg:province":"MS",
    "sg:tags":[
        "equipment",
        "electronic",
        "supply"
    ],
    "wof:name":"Kellum Distributors",
    "wof:placetype":"venue"
},
  "geometry": {"coordinates":[-88.37447,33.494193],"type":"Point"}
}