{
  "type": "Feature",
  "properties": {
    "iso:country":"US",
    "sg:address":"459 Old Yorkville Rd",
    "sg:city":"Columbus",
    "sg:classifiers":[
        {
            "category":"Organizations",
            "subcategory":"Religious Organization",
            "type":"Services"
        }
    ],
    "sg:phone":"+1 662 328 6024",
    "sg:postcode":"39702",
    "sg:province":"MS",
    "wof:name":"Friendship Baptist Church",
    "wof:placetype":"venue"
},
  "geometry": {"coordinates":[-88.315189,33.451287],"type":"Point"}
}