{
  "type": "Feature",
  "properties": {
    "addr:full":"6738 US Hwy 49 Hattiesburg MS 39402",
    "addr:housenumber":"6738",
    "addr:postcode":"39402",
    "addr:street":"Us Hwy 49",
    "iso:country":"US",
    "sg:address":"6738 US Hwy 49",
    "sg:city":"Hattiesburg",
    "sg:classifiers":[
        {
            "category":"Restaurant",
            "type":"Food & Drink"
        }
    ],
    "sg:phone":"+1 601 261 3993",
    "sg:postcode":"39402",
    "sg:province":"MS",
    "sg:website":"www.wendys.com",
    "wof:name":"Wendy's",
    "wof:placetype":"venue"
},
  "geometry": {"coordinates":[-89.34915100000001,31.359528],"type":"Point"}
}