{
  "type": "Feature",
  "properties": {
    "iso:country":"US",
    "sg:address":"3817 Montrose Cir",
    "sg:city":"Jackson",
    "sg:classifiers":[
        {
            "category":"Real Estate",
            "subcategory":"Developer",
            "type":"Services"
        }
    ],
    "sg:phone":"+1 601 981 4498",
    "sg:postcode":"39216",
    "sg:province":"MS",
    "wof:name":"Harrow Development Corporation",
    "wof:placetype":"venue"
},
  "geometry": {"coordinates":[-90.162092,32.34055],"type":"Point"}
}