{
  "type": "Feature",
  "properties": {
    "iso:country":"US",
    "sg:address":"8411 Hwy 178",
    "sg:city":"Olive Branch",
    "sg:classifiers":[
        {
            "category":"Retail",
            "subcategory":"Repair Shop",
            "type":"Services"
        },
        {
            "category":"Home & Garden",
            "subcategory":"Garden Supply",
            "type":"Retail Goods"
        }
    ],
    "sg:phone":"+1 662 895 7372",
    "sg:postcode":"38654",
    "sg:province":"MS",
    "sg:tags":[
        "lawn",
        "mower",
        "power",
        "mfg"
    ],
    "wof:name":"Olive Branch Small Engine Rpr",
    "wof:placetype":"venue"
},
  "geometry": {"coordinates":[-89.84463599999999,34.974827],"type":"Point"}
}