{
  "type": "Feature",
  "properties": {
    "iso:country":"US",
    "sg:address":"500 Rasco Rd W",
    "sg:city":"Southaven",
    "sg:classifiers":[
        {
            "category":"Real Estate",
            "subcategory":"Real Estate Operator",
            "type":"Services"
        }
    ],
    "sg:phone":"+1 662 393 8900",
    "sg:postcode":"38671",
    "sg:province":"MS",
    "sg:tags":[
        "building",
        "apartment"
    ],
    "wof:name":"Foxhaven Community Inc",
    "wof:placetype":"venue"
},
  "geometry": {"coordinates":[-89.9982,34.977337],"type":"Point"}
}