{
  "type": "Feature",
  "properties": {
    "iso:country":"US",
    "sg:address":"785 Commerce St",
    "sg:city":"Jackson",
    "sg:classifiers":[
        {
            "category":"Wholesale",
            "subcategory":"Groceries",
            "type":"Manufacturing & Wholesale Goods"
        }
    ],
    "sg:phone":"+1 601 352 0737",
    "sg:postcode":"39201",
    "sg:province":"MS",
    "sg:tags":[
        "food",
        "broker"
    ],
    "wof:name":"Budd Mayer Co Of Jackson Inc",
    "wof:placetype":"venue"
},
  "geometry": {"coordinates":[-90.180712,32.291193],"type":"Point"}
}