{
  "type": "Feature",
  "properties": {
    "addr:full":"350 Gilchrist Dr Jackson MS 39208",
    "addr:housenumber":"350",
    "addr:postcode":"39208",
    "addr:street":"Gilchrist Dr",
    "iso:country":"US",
    "sg:address":"350 Gilchrist Dr",
    "sg:city":"Jackson",
    "sg:classifiers":[
        {
            "category":"Food & Beverages",
            "subcategory":"Groceries & Convenience Stores",
            "type":"Retail Goods"
        }
    ],
    "sg:phone":"+1 601 932 3949",
    "sg:postcode":"39208",
    "sg:province":"MS",
    "wof:name":"Super Stop",
    "wof:placetype":"venue"
},
  "geometry": {"coordinates":[-90.071658,32.274615],"type":"Point"}
}