{
  "type": "Feature",
  "properties": {
    "iso:country":"US",
    "sg:address":"2408 Martin Luther King Jr Dr",
    "sg:city":"Jackson",
    "sg:classifiers":[
        {
            "category":"Retail",
            "subcategory":"Auto Repair",
            "type":"Services"
        }
    ],
    "sg:phone":"+1 601 354 9301",
    "sg:postcode":"39213",
    "sg:province":"MS",
    "sg:tags":[
        "repairing",
        "automobile",
        "body"
    ],
    "wof:name":"Mc Elroy's Auto Repair Shop",
    "wof:placetype":"venue"
},
  "geometry": {"coordinates":[-90.204643,32.327117],"type":"Point"}
}