{
  "type": "Feature",
  "properties": {
    "iso:country":"US",
    "sg:address":"3082 Union Rd SE",
    "sg:city":"Brookhaven",
    "sg:classifiers":[
        {
            "category":"Freight",
            "type":"Transportation"
        }
    ],
    "sg:phone":"+1 601 833 1018",
    "sg:postcode":"39601",
    "sg:province":"MS",
    "sg:tags":[
        "operator",
        "local",
        "trucking"
    ],
    "wof:name":"Prestridge Trucking",
    "wof:placetype":"venue"
},
  "geometry": {"coordinates":[-90.30417799999999,31.502984],"type":"Point"}
}