{
  "type": "Feature",
  "properties": {
    "addr:full":"548 E Rosemary Rd Cleveland MS 38732",
    "addr:housenumber":"548",
    "addr:postcode":"38732",
    "addr:street":"E Rosemary Rd",
    "iso:country":"US",
    "sg:address":"548 E Rosemary Rd",
    "sg:city":"Cleveland",
    "sg:classifiers":[
        {
            "category":"Health Services",
            "subcategory":"Doctor",
            "type":"Services"
        }
    ],
    "sg:phone":"+1 662 846 5032",
    "sg:postcode":"38732",
    "sg:province":"MS",
    "sg:tags":[
        "clinic"
    ],
    "wof:name":"Bethany Medical Clinic",
    "wof:placetype":"venue"
},
  "geometry": {"coordinates":[-90.71385600000001,33.762184],"type":"Point"}
}