{
  "type": "Feature",
  "properties": {
    "addr:full":"1407 Strong Ave Greenwood MS 38930",
    "addr:housenumber":"1407",
    "addr:postcode":"38930",
    "addr:street":"Strong Ave",
    "iso:country":"US",
    "sg:address":"1407 Strong Ave",
    "sg:city":"Greenwood",
    "sg:classifiers":[
        {
            "category":"Health Services",
            "subcategory":"Doctor",
            "type":"Services"
        }
    ],
    "sg:phone":"+1 662 459 2586",
    "sg:postcode":"38930",
    "sg:province":"MS",
    "sg:tags":[
        "physician",
        "surgeon"
    ],
    "wof:name":"Greenwood Neurological Surgery",
    "wof:placetype":"venue"
},
  "geometry": {"coordinates":[-90.198306,33.517173],"type":"Point"}
}