{
  "type": "Feature",
  "properties": {
    "addr:full":"109 W Pine Ave Mendenhall MS 39114",
    "addr:housenumber":"109",
    "addr:postcode":"39114",
    "addr:street":"W Pine Ave",
    "iso:country":"US",
    "sg:address":"109 W Pine Ave",
    "sg:city":"Mendenhall",
    "sg:classifiers":[
        {
            "category":"Government",
            "subcategory":"Office",
            "type":"Public Place"
        }
    ],
    "sg:phone":"+1 601 847 4081",
    "sg:postcode":"39114",
    "sg:province":"MS",
    "wof:name":"Social Services",
    "wof:placetype":"venue"
},
  "geometry": {"coordinates":[-89.86968899999999,31.963269],"type":"Point"}
}