{
  "type": "Feature",
  "properties": {
    "iso:country":"US",
    "sg:address":"141 Arrowhead Trl",
    "sg:city":"Brandon",
    "sg:classifiers":[
        {
            "category":"Banks & Credit Unions",
            "subcategory":"Financial Services",
            "type":"Services"
        }
    ],
    "sg:phone":"+1 601 992 9644",
    "sg:postcode":"39047",
    "sg:province":"MS",
    "sg:tags":[
        "investor"
    ],
    "wof:name":"Cornerstone Capital Corp",
    "wof:placetype":"venue"
},
  "geometry": {"coordinates":[-90.016307,32.377377],"type":"Point"}
}