{
  "type": "Feature",
  "properties": {
    "iso:country":"US",
    "sg:address":"331 Williamson Ave",
    "sg:city":"Philadelphia",
    "sg:classifiers":[
        {
            "category":"Personal",
            "subcategory":"Beauty Salon",
            "type":"Services"
        }
    ],
    "sg:phone":"+1 601 663 4255",
    "sg:postcode":"39350",
    "sg:province":"MS",
    "wof:name":"Erica's Barber & Beauty Salon",
    "wof:placetype":"venue"
},
  "geometry": {"coordinates":[-89.085707,32.767502],"type":"Point"}
}