{
  "type": "Feature",
  "properties": {
    "addr:full":"2864 McGuffee Rd Clinton MS 39056",
    "addr:housenumber":"2864",
    "addr:postcode":"39056",
    "addr:street":"Mcguffee Rd",
    "iso:country":"US",
    "sg:address":"2864 McGuffee Rd",
    "sg:city":"Clinton",
    "sg:classifiers":[
        {
            "category":"Building & Trades",
            "subcategory":"Construction",
            "type":"Services"
        }
    ],
    "sg:phone":"+1 601 924 9671",
    "sg:postcode":"39056",
    "sg:province":"MS",
    "sg:tags":[
        "contractor"
    ],
    "wof:name":"Claxton Drywall",
    "wof:placetype":"venue"
},
  "geometry": {"coordinates":[-90.374,32.429166],"type":"Point"}
}