{
  "type": "Feature",
  "properties": {
    "addr:full":"495 Lebanon Rd Laurel MS 39443",
    "addr:housenumber":"495",
    "addr:postcode":"39443",
    "addr:street":"Lebanon Rd",
    "iso:country":"US",
    "sg:address":"495 Lebanon Rd",
    "sg:city":"Laurel",
    "sg:classifiers":[
        {
            "category":"Freight",
            "type":"Transportation"
        }
    ],
    "sg:phone":"+1 601 729 2414",
    "sg:postcode":"39443",
    "sg:province":"MS",
    "sg:tags":[
        "operator",
        "local",
        "trucking"
    ],
    "wof:name":"Jefcoat Trucking",
    "wof:placetype":"venue"
},
  "geometry": {"coordinates":[-89.232079,31.714507],"type":"Point"}
}