{
  "type": "Feature",
  "properties": {
    "iso:country":"US",
    "sg:address":"31 Gussy Nobles Rd",
    "sg:city":"Sumrall",
    "sg:classifiers":[
        {
            "category":"Retail",
            "subcategory":"Repair Shop",
            "type":"Services"
        }
    ],
    "sg:phone":"+1 601 268 1166",
    "sg:postcode":"39482",
    "sg:province":"MS",
    "sg:tags":[
        "lock",
        "locksmith"
    ],
    "wof:name":"Lamar Lock & Key",
    "wof:placetype":"venue"
},
  "geometry": {"coordinates":[-89.51215000000001,31.264391],"type":"Point"}
}