{
  "type": "Feature",
  "properties": {
    "addr:full":"200 W Front St Hattiesburg MS 39401",
    "addr:housenumber":"200",
    "addr:postcode":"39401",
    "addr:street":"W Front St",
    "iso:country":"US",
    "sg:address":"200 W Front St",
    "sg:city":"Hattiesburg",
    "sg:classifiers":[
        {
            "category":"Professional",
            "subcategory":"Engineering",
            "type":"Services"
        }
    ],
    "sg:phone":"+1 601 582 4249",
    "sg:postcode":"39401",
    "sg:province":"MS",
    "wof:name":"David Sheley",
    "wof:placetype":"venue"
},
  "geometry": {"coordinates":[-89.29104599999999,31.325207],"type":"Point"}
}