{
  "type": "Feature",
  "properties": {
    "addr:full":"4303 8th St Meridian MS 39307",
    "addr:housenumber":"4303",
    "addr:postcode":"39307",
    "addr:street":"8Th St",
    "iso:country":"US",
    "sg:address":"4303 8th St",
    "sg:city":"Meridian",
    "sg:classifiers":[
        {
            "category":"Shopping",
            "subcategory":"Department Store",
            "type":"Retail Goods"
        }
    ],
    "sg:phone":"+1 601 482 5202",
    "sg:postcode":"39307",
    "sg:province":"MS",
    "sg:tags":[
        "shop"
    ],
    "wof:name":"Fred's Store",
    "wof:placetype":"venue"
},
  "geometry": {"coordinates":[-88.72066700000001,32.364604],"type":"Point"}
}