{
  "type": "Feature",
  "properties": {
    "addr:full":"6889 Paxton Rd Vicksburg MS 39180",
    "addr:housenumber":"6889",
    "addr:postcode":"39180",
    "addr:street":"Paxton Rd",
    "iso:country":"US",
    "sg:address":"6889 Paxton Rd",
    "sg:city":"Vicksburg",
    "sg:classifiers":[
        {
            "category":"Building & Trades",
            "subcategory":"Construction",
            "type":"Services"
        }
    ],
    "sg:phone":"+1 601 638 9890",
    "sg:postcode":"39180",
    "sg:province":"MS",
    "sg:tags":[
        "general",
        "contractor"
    ],
    "wof:name":"Lampkin Construction",
    "wof:placetype":"venue"
},
  "geometry": {"coordinates":[-90.828155,32.341011],"type":"Point"}
}