{
  "type": "Feature",
  "properties": {
    "addr:full":"319 E Church St Ackerman MS 39735",
    "addr:housenumber":"319",
    "addr:postcode":"39735",
    "addr:street":"E Church St",
    "iso:country":"US",
    "sg:address":"319 E Church St",
    "sg:city":"Ackerman",
    "sg:classifiers":[
        {
            "category":"Education",
            "subcategory":"Junior College",
            "type":"Public Place"
        }
    ],
    "sg:phone":"+1 662 285 4150",
    "sg:postcode":"39735",
    "sg:province":"MS",
    "sg:tags":[
        "technical",
        "institute"
    ],
    "sg:website":"www.choctaw.k12.ms.us",
    "wof:name":"Choctaw County Career & Tech",
    "wof:placetype":"venue"
},
  "geometry": {"coordinates":[-89.16335599999999,33.31014],"type":"Point"}
}