{
  "type": "Feature",
  "properties": {
    "iso:country":"US",
    "sg:address":"1061 S Raceway Rd",
    "sg:city":"Greenville",
    "sg:classifiers":[
        {
            "category":"Retail",
            "subcategory":"Laundry & Dry Cleaning",
            "type":"Services"
        }
    ],
    "sg:phone":"+1 662 335 7791",
    "sg:postcode":"38703",
    "sg:province":"MS",
    "sg:tags":[
        "cleaners",
        "rug",
        "carpet"
    ],
    "wof:name":"Baxter Professional Cleaning",
    "wof:placetype":"venue"
},
  "geometry": {"coordinates":[-91.00633500000001,33.388315],"type":"Point"}
}