{
  "type": "Feature",
  "properties": {
    "addr:full":"11555 Cedar Lake Rd Biloxi MS 39532",
    "addr:housenumber":"11555",
    "addr:postcode":"39532",
    "addr:street":"Cedar Lake Rd",
    "iso:country":"US",
    "sg:address":"11555 Cedar Lake Rd",
    "sg:city":"Biloxi",
    "sg:classifiers":[
        {
            "category":"Social Services",
            "subcategory":"Child Care",
            "type":"Services"
        }
    ],
    "sg:phone":"+1 228 392 4227",
    "sg:postcode":"39532",
    "sg:province":"MS",
    "wof:name":"Cedar Lake Christian Pre-Schl",
    "wof:placetype":"venue"
},
  "geometry": {"coordinates":[-88.938669,30.455096],"type":"Point"}
}