{
  "type": "Feature",
  "properties": {
    "iso:country":"US",
    "sg:address":"201 Poplar St",
    "sg:city":"Florence",
    "sg:classifiers":[
        {
            "category":"Retail",
            "subcategory":"Auto Repair",
            "type":"Services"
        }
    ],
    "sg:phone":"+1 601 939 6096",
    "sg:postcode":"39073",
    "sg:province":"MS",
    "sg:tags":[
        "general"
    ],
    "wof:name":"S Waggoner Auto Repair",
    "wof:placetype":"venue"
},
  "geometry": {"coordinates":[-90.04016300000001,32.184222],"type":"Point"}
}