{
  "type": "Feature",
  "properties": {
    "iso:country":"US",
    "sg:address":"7712 Old Canton Rd",
    "sg:city":"Madison",
    "sg:classifiers":[
        {
            "category":"Health Services",
            "subcategory":"Doctor",
            "type":"Services"
        }
    ],
    "sg:phone":"+1 601 856 2290",
    "sg:postcode":"39110",
    "sg:province":"MS",
    "sg:tags":[
        "medical"
    ],
    "wof:name":"Compass Family Medicine",
    "wof:placetype":"venue"
},
  "geometry": {"coordinates":[-90.10669900000001,32.458749],"type":"Point"}
}