{
  "type": "Feature",
  "properties": {
    "iso:country":"US",
    "sg:address":"910 Sawmill Rd",
    "sg:city":"Laurel",
    "sg:classifiers":[
        {
            "category":"Professional",
            "subcategory":"Accounting & Tax Preparation",
            "type":"Services"
        }
    ],
    "sg:phone":"+1 601 428 1062",
    "sg:postcode":"39440",
    "sg:province":"MS",
    "sg:tags":[
        "return",
        "filing"
    ],
    "wof:name":"Jackson Hewitt Tax Svc",
    "wof:placetype":"venue"
},
  "geometry": {"coordinates":[-89.133538,31.69349],"type":"Point"}
}