{
  "type": "Feature",
  "properties": {
    "addr:full":"503 E Park Ave Greenwood MS 38930",
    "addr:housenumber":"503",
    "addr:postcode":"38930",
    "addr:street":"E Park Ave",
    "iso:country":"US",
    "sg:address":"503 E Park Ave",
    "sg:city":"Greenwood",
    "sg:classifiers":[
        {
            "category":"Social Services",
            "type":"Services"
        }
    ],
    "sg:phone":"+1 662 455 2095",
    "sg:postcode":"38930",
    "sg:province":"MS",
    "sg:tags":[
        "probation"
    ],
    "wof:name":"Parole Office",
    "wof:placetype":"venue"
},
  "geometry": {"coordinates":[-90.182745,33.535539],"type":"Point"}
}