{
  "type": "Feature",
  "properties": {
    "iso:country":"US",
    "sg:address":"403 Broad St",
    "sg:city":"Columbia",
    "sg:classifiers":[
        {
            "category":"Travel",
            "subcategory":"Hotels & Motels",
            "type":"Entertainment"
        }
    ],
    "sg:phone":"+1 601 731 5222",
    "sg:postcode":"39429",
    "sg:province":"MS",
    "sg:tags":[
        "operation"
    ],
    "wof:name":"Corner Oaks Bed & Breakfast",
    "wof:placetype":"venue"
},
  "geometry": {"coordinates":[-89.830507,31.250868],"type":"Point"}
}