{
  "type": "Feature",
  "properties": {
    "iso:country":"US",
    "sg:address":"6394 Quail Lake Dr",
    "sg:city":"Jackson",
    "sg:classifiers":[
        {
            "category":"Communications",
            "subcategory":"Film & Video Production",
            "type":"Services"
        }
    ],
    "sg:phone":"+1 601 954 9118",
    "sg:postcode":"39206",
    "sg:province":"MS",
    "sg:tags":[
        "motion"
    ],
    "wof:name":"Nivek Revluc Productions Inc",
    "wof:placetype":"venue"
},
  "geometry": {"coordinates":[-90.164855,32.395968],"type":"Point"}
}