{
  "type": "Feature",
  "properties": {
    "iso:country":"US",
    "sg:address":"302 8th Ave SE",
    "sg:city":"Magee",
    "sg:classifiers":[
        {
            "category":"Insurance",
            "subcategory":"Insurance Agent",
            "type":"Services"
        }
    ],
    "sg:phone":"+1 601 849 5031",
    "sg:postcode":"39111",
    "sg:province":"MS",
    "sg:tags":[
        "funeral"
    ],
    "wof:name":"Colonial Chapel Funeral Home",
    "wof:placetype":"venue"
},
  "geometry": {"coordinates":[-89.723035,31.87133],"type":"Point"}
}