{
  "type": "Feature",
  "properties": {
    "iso:country":"US",
    "sg:address":"1 S Timber St",
    "sg:city":"Brandon",
    "sg:classifiers":[
        {
            "category":"Real Estate",
            "subcategory":"Surveying",
            "type":"Services"
        }
    ],
    "sg:phone":"+1 601 591 1077",
    "sg:postcode":"39042",
    "sg:province":"MS",
    "sg:tags":[
        "surveyor"
    ],
    "wof:name":"Benchmark Engineering Srvyng",
    "wof:placetype":"venue"
},
  "geometry": {"coordinates":[-89.986282,32.271822],"type":"Point"}
}