{
  "type": "Feature",
  "properties": {
    "addr:full":"814 Hwy 82 W Greenwood MS 38930",
    "addr:housenumber":"814",
    "addr:postcode":"38930",
    "addr:street":"Hwy 82 W",
    "iso:country":"US",
    "sg:address":"814 Hwy 82 W",
    "sg:city":"Greenwood",
    "sg:classifiers":[
        {
            "category":"Food & Beverages",
            "subcategory":"Groceries & Convenience Stores",
            "type":"Retail Goods"
        }
    ],
    "sg:phone":"+1 662 455 3100",
    "sg:postcode":"38930",
    "sg:province":"MS",
    "wof:name":"Double Quick",
    "wof:placetype":"venue"
},
  "geometry": {"coordinates":[-90.192435,33.507163],"type":"Point"}
}