{
  "type": "Feature",
  "properties": {
    "iso:country":"US",
    "sg:address":"204 W George E Allen Dr",
    "sg:city":"Booneville",
    "sg:classifiers":[
        {
            "category":"Organizations",
            "subcategory":"Religious Organization",
            "type":"Services"
        }
    ],
    "sg:phone":"+1 662 728 4047",
    "sg:postcode":"38829",
    "sg:province":"MS",
    "sg:tags":[
        "church"
    ],
    "wof:name":"Church Of Jesus Christ Of Lds",
    "wof:placetype":"venue"
},
  "geometry": {"coordinates":[-88.560681,34.669028],"type":"Point"}
}