{
  "type": "Feature",
  "properties": {
    "iso:country":"US",
    "sg:address":"406 Dogwood Lake Dr",
    "sg:city":"Vicksburg",
    "sg:classifiers":[
        {
            "category":"Building & Trades",
            "subcategory":"Construction",
            "type":"Services"
        }
    ],
    "sg:phone":"+1 601 634 8717",
    "sg:postcode":"39183",
    "sg:province":"MS",
    "sg:tags":[
        "tile",
        "dealer"
    ],
    "wof:name":"Estes Tile & Marble",
    "wof:placetype":"venue"
},
  "geometry": {"coordinates":[-90.693163,32.375177],"type":"Point"}
}