{
  "type": "Feature",
  "properties": {
    "iso:country":"US",
    "sg:address":"7080 Hwy 51 N",
    "sg:city":"Horn Lake",
    "sg:classifiers":[
        {
            "category":"Restaurant",
            "type":"Food & Drink"
        }
    ],
    "sg:phone":"+1 662 342 9865",
    "sg:postcode":"38637",
    "sg:province":"MS",
    "wof:name":"Conestoga's Bull Frog Corner",
    "wof:placetype":"venue"
},
  "geometry": {"coordinates":[-90.01638699999999,34.964002],"type":"Point"}
}