{
  "type": "Feature",
  "properties": {
    "addr:full":"802 Sussex St Ridgeland MS 39157",
    "addr:housenumber":"802",
    "addr:postcode":"39157",
    "addr:street":"Sussex St",
    "iso:country":"US",
    "sg:address":"802 Sussex St",
    "sg:city":"Ridgeland",
    "sg:classifiers":[
        {
            "category":"Shopping",
            "type":"Retail Goods"
        }
    ],
    "sg:phone":"+1 601 899 9330",
    "sg:postcode":"39157",
    "sg:province":"MS",
    "sg:tags":[
        "equipment",
        "telephone",
        "supply"
    ],
    "wof:name":"Telcom Express",
    "wof:placetype":"venue"
},
  "geometry": {"coordinates":[-90.102557,32.409905],"type":"Point"}
}