{
  "type": "Feature",
  "properties": {
    "iso:country":"US",
    "sg:address":"415 Highland Dr",
    "sg:city":"Indianola",
    "sg:classifiers":[
        {
            "category":"Retail",
            "subcategory":"Repair Shop",
            "type":"Services"
        }
    ],
    "sg:phone":"+1 662 887 1752",
    "sg:postcode":"38751",
    "sg:province":"MS",
    "sg:tags":[
        "electrical",
        "contractor"
    ],
    "wof:name":"Davis Electrical & Mechanical",
    "wof:placetype":"venue"
},
  "geometry": {"coordinates":[-90.63945099999999,33.456732],"type":"Point"}
}