{
  "type": "Feature",
  "properties": {
    "iso:country":"US",
    "sg:address":"304 Hwy 42",
    "sg:city":"Petal",
    "sg:classifiers":[
        {
            "category":"Insurance",
            "subcategory":"Insurance Agent",
            "type":"Services"
        }
    ],
    "sg:phone":"+1 601 544 9303",
    "sg:postcode":"39465",
    "sg:province":"MS",
    "wof:name":"David M Smith Insurance",
    "wof:placetype":"venue"
},
  "geometry": {"coordinates":[-89.25608,31.346626],"type":"Point"}
}