{
  "type": "Feature",
  "properties": {
    "addr:full":"124 Baker Ln Brandon MS 39047",
    "addr:housenumber":"124",
    "addr:postcode":"39047",
    "addr:street":"Baker Ln",
    "iso:country":"US",
    "sg:address":"124 Baker Ln",
    "sg:city":"Brandon",
    "sg:classifiers":[
        {
            "category":"Building & Trades",
            "subcategory":"Construction",
            "type":"Services"
        }
    ],
    "sg:phone":"+1 601 829 4100",
    "sg:postcode":"39047",
    "sg:province":"MS",
    "sg:tags":[
        "pole",
        "line",
        "contractor"
    ],
    "sg:website":"www.bbecon.com",
    "wof:name":"B & B Electrical Contractors",
    "wof:placetype":"venue"
},
  "geometry": {"coordinates":[-89.964792,32.356772],"type":"Point"}
}