{
  "type": "Feature",
  "properties": {
    "iso:country":"US",
    "sg:address":"10185 D Ave",
    "sg:city":"Bay Saint Louis",
    "sg:classifiers":[
        {
            "category":"Professional",
            "subcategory":"Management & Consulting",
            "type":"Services"
        }
    ],
    "sg:phone":"+1 228 463 9787",
    "sg:postcode":"39520",
    "sg:province":"MS",
    "wof:name":"M D Hamilton Inc",
    "wof:placetype":"venue"
},
  "geometry": {"coordinates":[-89.400352,30.320701],"type":"Point"}
}