{
  "type": "Feature",
  "properties": {
    "iso:country":"US",
    "sg:address":"5261 Greenway Dr Exd",
    "sg:city":"Jackson",
    "sg:classifiers":[
        {
            "category":"Wholesale",
            "subcategory":"Non-durable Goods",
            "type":"Manufacturing & Wholesale Goods"
        }
    ],
    "sg:phone":"+1 601 922 2277",
    "sg:postcode":"39204",
    "sg:province":"MS",
    "sg:tags":[
        "agency",
        "advertising"
    ],
    "wof:name":"Jackson Specialty Advg LLC",
    "wof:placetype":"venue"
},
  "geometry": {"coordinates":[-90.283112,32.292613],"type":"Point"}
}