{
  "type": "Feature",
  "properties": {
    "addr:full":"428 Mable St Hattiesburg MS 39401",
    "addr:housenumber":"428",
    "addr:postcode":"39401",
    "addr:street":"Mable St",
    "iso:country":"US",
    "sg:address":"428 Mable St",
    "sg:city":"Hattiesburg",
    "sg:classifiers":[
        {
            "category":"Manufacturing",
            "subcategory":"Glass & Minerals",
            "type":"Manufacturing & Wholesale Goods"
        }
    ],
    "sg:phone":"+1 601 583 9287",
    "sg:postcode":"39401",
    "sg:province":"MS",
    "sg:tags":[
        "product",
        "mfg"
    ],
    "wof:name":"Glass Medic",
    "wof:placetype":"venue"
},
  "geometry": {"coordinates":[-89.30293899999999,31.331023],"type":"Point"}
}