{
  "type": "Feature",
  "properties": {
    "addr:full":"231 W Main St Forest MS 39074",
    "addr:housenumber":"231",
    "addr:postcode":"39074",
    "addr:street":"W Main St",
    "iso:country":"US",
    "sg:address":"231 W Main St",
    "sg:city":"Forest",
    "sg:classifiers":[
        {
            "category":"Professional",
            "subcategory":"Lawyer & Legal Services",
            "type":"Services"
        }
    ],
    "sg:phone":"+1 601 469 3992",
    "sg:postcode":"39074",
    "sg:province":"MS",
    "sg:tags":[
        "attorney"
    ],
    "wof:name":"Rick B Clark Pa",
    "wof:placetype":"venue"
},
  "geometry": {"coordinates":[-89.474701,32.362687],"type":"Point"}
}