{
  "type": "Feature",
  "properties": {
    "iso:country":"US",
    "sg:address":"513 Central Ave",
    "sg:city":"Laurel",
    "sg:classifiers":[
        {
            "category":"Professional",
            "subcategory":"Art Services",
            "type":"Services"
        }
    ],
    "sg:phone":"+1 601 426 9729",
    "sg:postcode":"39440",
    "sg:province":"MS",
    "sg:tags":[
        "photo",
        "photography",
        "commercial",
        "studio",
        "portrait"
    ],
    "wof:name":"Cameo Portaits Inc",
    "wof:placetype":"venue"
},
  "geometry": {"coordinates":[-89.132891,31.693524],"type":"Point"}
}