{
  "type": "Feature",
  "properties": {
    "iso:country":"US",
    "sg:address":"3104 N 5th Ave",
    "sg:city":"Laurel",
    "sg:classifiers":[
        {
            "category":"Retail",
            "subcategory":"Repair Shop",
            "type":"Services"
        }
    ],
    "sg:phone":"+1 601 649 5581",
    "sg:postcode":"39440",
    "sg:province":"MS",
    "sg:tags":[
        "repairing",
        "organs"
    ],
    "wof:name":"Pipe Organ Specialties Inc",
    "wof:placetype":"venue"
},
  "geometry": {"coordinates":[-89.130576,31.729706],"type":"Point"}
}