{
  "type": "Feature",
  "properties": {
    "iso:country":"US",
    "sg:address":"8516 Hwy 182 E",
    "sg:city":"Columbus",
    "sg:classifiers":[
        {
            "category":"Retail",
            "subcategory":"Auto Repair",
            "type":"Services"
        }
    ],
    "sg:phone":"+1 662 328 3124",
    "sg:postcode":"39702",
    "sg:province":"MS",
    "sg:tags":[
        "shop",
        "convenience",
        "brake",
        "muffler",
        "tanning",
        "store"
    ],
    "wof:name":"Country Village Tackle Shop",
    "wof:placetype":"venue"
},
  "geometry": {"coordinates":[-88.282768,33.491128],"type":"Point"}
}