{
  "type": "Feature",
  "properties": {
    "iso:country":"US",
    "sg:address":"732 Mount Olive Rd",
    "sg:city":"Starkville",
    "sg:classifiers":[
        {
            "category":"Manufacturing",
            "subcategory":"Printing",
            "type":"Manufacturing & Wholesale Goods"
        }
    ],
    "sg:phone":"+1 662 323 8175",
    "sg:postcode":"39759",
    "sg:province":"MS",
    "sg:tags":[
        "printer"
    ],
    "wof:name":"Country Home Printing",
    "wof:placetype":"venue"
},
  "geometry": {"coordinates":[-88.800755,33.374032],"type":"Point"}
}