{
  "type": "Feature",
  "properties": {
    "iso:country":"US",
    "sg:address":"529 Delaware Ave",
    "sg:city":"Mccomb",
    "sg:classifiers":[
        {
            "category":"Professional",
            "subcategory":"Lawyer & Legal Services",
            "type":"Services"
        }
    ],
    "sg:phone":"+1 601 684 7780",
    "sg:postcode":"39648",
    "sg:province":"MS",
    "sg:tags":[
        "attorney"
    ],
    "wof:name":"Edwin L Bean Jr",
    "wof:placetype":"venue"
},
  "geometry": {"coordinates":[-90.456593,31.245138],"type":"Point"}
}