{
  "type": "Feature",
  "properties": {
    "iso:country":"US",
    "sg:address":"905 Division St",
    "sg:city":"Biloxi",
    "sg:classifiers":[
        {
            "category":"Social Services",
            "type":"Services"
        }
    ],
    "sg:phone":"+1 228 432 7947",
    "sg:postcode":"39530",
    "sg:province":"MS",
    "sg:tags":[
        "info",
        "program",
        "referral"
    ],
    "wof:name":"Interfaith Hospitality Network",
    "wof:placetype":"venue"
},
  "geometry": {"coordinates":[-88.892618,30.403102],"type":"Point"}
}