{
  "type": "Feature",
  "properties": {
    "addr:full":"307 Ratliff St Lucedale MS 39452",
    "addr:housenumber":"307",
    "addr:postcode":"39452",
    "addr:street":"Ratliff St",
    "iso:country":"US",
    "sg:address":"307 Ratliff St",
    "sg:city":"Lucedale",
    "sg:classifiers":[
        {
            "category":"Professional",
            "subcategory":"Engineering",
            "type":"Services"
        }
    ],
    "sg:phone":"+1 601 947 4499",
    "sg:postcode":"39452",
    "sg:province":"MS",
    "sg:tags":[
        "engineer"
    ],
    "wof:name":"W Engineering",
    "wof:placetype":"venue"
},
  "geometry": {"coordinates":[-88.589439,30.922979],"type":"Point"}
}