{
  "type": "Feature",
  "properties": {
    "addr:full":"1024 Washington Ave Greenville MS 38701",
    "addr:housenumber":"1024",
    "addr:postcode":"38701",
    "addr:street":"Washington Ave",
    "iso:country":"US",
    "sg:address":"1024 Washington Ave",
    "sg:city":"Greenville",
    "sg:classifiers":[
        {
            "category":"Building & Trades",
            "subcategory":"Construction",
            "type":"Services"
        }
    ],
    "sg:phone":"+1 662 378 9362",
    "sg:postcode":"38701",
    "sg:province":"MS",
    "sg:tags":[
        "marine",
        "co"
    ],
    "wof:name":"Newsouth Marine Builders LLC",
    "wof:placetype":"venue"
},
  "geometry": {"coordinates":[-91.052224,33.406638],"type":"Point"}
}