{
  "type": "Feature",
  "properties": {
    "iso:country":"US",
    "sg:address":"1208 E Hardy St",
    "sg:city":"Hattiesburg",
    "sg:classifiers":[
        {
            "category":"Organizations",
            "subcategory":"Religious Organization",
            "type":"Services"
        }
    ],
    "sg:phone":"+1 601 544 8485",
    "sg:postcode":"39401",
    "sg:province":"MS",
    "sg:tags":[
        "church"
    ],
    "wof:name":"Victory Christian Church",
    "wof:placetype":"venue"
},
  "geometry": {"coordinates":[-89.278536,31.325119],"type":"Point"}
}