{
  "type": "Feature",
  "properties": {
    "iso:country":"US",
    "sg:address":"4299 Barren Brook Dr",
    "sg:city":"Memphis",
    "sg:classifiers":[
        {
            "category":"Professional",
            "subcategory":"Computer Services",
            "type":"Services"
        }
    ],
    "sg:phone":"+1 901 756 9582",
    "sg:postcode":"38125",
    "sg:province":"MS",
    "sg:tags":[
        "datum"
    ],
    "wof:name":"Macroburst LLC",
    "wof:placetype":"venue"
},
  "geometry": {"coordinates":[-89.790842,35.0309],"type":"Point"}
}