{
  "type": "Feature",
  "properties": {
    "iso:country":"US",
    "sg:address":"1100 Co Rd 992",
    "sg:city":"Iuka",
    "sg:classifiers":[
        {
            "category":"Manufacturing",
            "subcategory":"Printing",
            "type":"Manufacturing & Wholesale Goods"
        }
    ],
    "sg:phone":"+1 662 423 2778",
    "sg:postcode":"38852",
    "sg:province":"MS",
    "sg:tags":[
        "commercial"
    ],
    "wof:name":"Custom Graphics",
    "wof:placetype":"venue"
},
  "geometry": {"coordinates":[-88.198329,34.776738],"type":"Point"}
}