{
  "type": "Feature",
  "properties": {
    "iso:country":"US",
    "sg:address":"450 Highland Dr",
    "sg:city":"Yazoo City",
    "sg:classifiers":[
        {
            "category":"Farming",
            "subcategory":"Farm",
            "type":"Manufacturing & Wholesale Goods"
        }
    ],
    "sg:phone":"+1 662 746 1804",
    "sg:postcode":"39194",
    "sg:province":"MS",
    "sg:tags":[
        "crop",
        "general"
    ],
    "wof:name":"Michael Mc Cain",
    "wof:placetype":"venue"
},
  "geometry": {"coordinates":[-90.407366,32.836673],"type":"Point"}
}