{
  "type": "Feature",
  "properties": {
    "iso:country":"US",
    "sg:address":"491 Hibiscus Dr",
    "sg:city":"Bay Saint Louis",
    "sg:classifiers":[
        {
            "category":"Building & Trades",
            "subcategory":"Construction",
            "type":"Services"
        }
    ],
    "sg:phone":"+1 228 467 3418",
    "sg:postcode":"39520",
    "sg:province":"MS",
    "sg:tags":[
        "residential"
    ],
    "wof:name":"Bay Marine Construction",
    "wof:placetype":"venue"
},
  "geometry": {"coordinates":[-89.382187,30.325769],"type":"Point"}
}