{
  "type": "Feature",
  "properties": {
    "addr:full":"544 Co Rd 102 Oxford MS 38655",
    "addr:housenumber":"544;102",
    "addr:postcode":"38655",
    "addr:street":"Co Rd",
    "iso:country":"US",
    "sg:address":"544 Co Rd 102",
    "sg:city":"Oxford",
    "sg:classifiers":[
        {
            "category":"Building & Trades",
            "subcategory":"Plumbing",
            "type":"Services"
        }
    ],
    "sg:phone":"+1 662 281 1231",
    "sg:postcode":"38655",
    "sg:province":"MS",
    "sg:tags":[
        "heating",
        "contractor"
    ],
    "wof:name":"Franklin's Heating & Air Cond",
    "wof:placetype":"venue"
},
  "geometry": {"coordinates":[-89.60897799999999,34.4578],"type":"Point"}
}