{
  "type": "Feature",
  "properties": {
    "iso:country":"US",
    "sg:address":"1332 Rasco Rd W",
    "sg:city":"Southaven",
    "sg:classifiers":[
        {
            "category":"Restaurant",
            "type":"Food & Drink"
        }
    ],
    "sg:phone":"+1 662 342 7200",
    "sg:postcode":"38671",
    "sg:province":"MS",
    "sg:tags":[
        "eating"
    ],
    "wof:name":"Sunshine Catering",
    "wof:placetype":"venue"
},
  "geometry": {"coordinates":[-90.013113,34.977426],"type":"Point"}
}