{
  "type": "Feature",
  "properties": {
    "iso:country":"US",
    "sg:address":"609 E Commerce St",
    "sg:city":"Aberdeen",
    "sg:classifiers":[
        {
            "category":"Building & Trades",
            "subcategory":"Electrical",
            "type":"Services"
        }
    ],
    "sg:phone":"+1 662 369 2609",
    "sg:postcode":"39730",
    "sg:province":"MS",
    "sg:tags":[
        "electric",
        "contractor"
    ],
    "wof:name":"Roberts Electric Svc",
    "wof:placetype":"venue"
},
  "geometry": {"coordinates":[-88.53701700000001,33.823583],"type":"Point"}
}