{
  "type": "Feature",
  "properties": {
    "addr:full":"1308 N Pearl St Iuka MS 38852",
    "addr:housenumber":"1308",
    "addr:postcode":"38852",
    "addr:street":"N Pearl St",
    "iso:country":"US",
    "sg:address":"1308 N Pearl St",
    "sg:city":"Iuka",
    "sg:classifiers":[
        {
            "category":"Health Services",
            "subcategory":"Nursing And Care Facility",
            "type":"Services"
        }
    ],
    "sg:phone":"+1 662 424 0023",
    "sg:postcode":"38852",
    "sg:province":"MS",
    "sg:tags":[
        "skilled"
    ],
    "wof:name":"Southern Magnolia Estates",
    "wof:placetype":"venue"
},
  "geometry": {"coordinates":[-88.18946800000001,34.827957],"type":"Point"}
}