{
  "type": "Feature",
  "properties": {
    "iso:country":"US",
    "sg:address":"12481 Glascock Dr",
    "sg:city":"Gulfport",
    "sg:classifiers":[
        {
            "category":"Manufacturing",
            "subcategory":"Glass & Minerals",
            "type":"Manufacturing & Wholesale Goods"
        }
    ],
    "sg:phone":"+1 228 314 8000",
    "sg:postcode":"39503",
    "sg:province":"MS",
    "sg:tags":[
        "fabricator",
        "fiber"
    ],
    "sg:website":"www.seemanncomposites.com",
    "wof:name":"Seemann Composites Inc",
    "wof:placetype":"venue"
},
  "geometry": {"coordinates":[-89.05216299999999,30.429783],"type":"Point"}
}