{
  "type": "Feature",
  "properties": {
    "iso:country":"US",
    "sg:address":"105 Veterans Memorial Blvd N",
    "sg:city":"Eupora",
    "sg:classifiers":[
        {
            "category":"Personal",
            "subcategory":"Barber",
            "type":"Services"
        }
    ],
    "sg:phone":"+1 662 258 6716",
    "sg:postcode":"39744",
    "sg:province":"MS",
    "wof:name":"Ellen's Barber Shop",
    "wof:placetype":"venue"
},
  "geometry": {"coordinates":[-89.267399,33.542063],"type":"Point"}
}