{
  "type": "Feature",
  "properties": {
    "iso:country":"US",
    "sg:address":"6445 US Hwy 49",
    "sg:city":"Hattiesburg",
    "sg:classifiers":[
        {
            "category":"Insurance",
            "subcategory":"Insurance Agent",
            "type":"Services"
        }
    ],
    "sg:phone":"+1 601 264 3668",
    "sg:postcode":"39401",
    "sg:province":"MS",
    "wof:name":"Forest County Farm Bur Insur",
    "wof:placetype":"venue"
},
  "geometry": {"coordinates":[-89.34469199999999,31.355161],"type":"Point"}
}