{
  "type": "Feature",
  "properties": {
    "iso:country":"US",
    "sg:address":"911 64th Ave",
    "sg:city":"Meridian",
    "sg:classifiers":[
        {
            "category":"Social Services",
            "subcategory":"Child Care",
            "type":"Services"
        }
    ],
    "sg:phone":"+1 601 482 8575",
    "sg:postcode":"39307",
    "sg:province":"MS",
    "sg:tags":[
        "day"
    ],
    "wof:name":"Great Start Learning Center",
    "wof:placetype":"venue"
},
  "geometry": {"coordinates":[-88.74349599999999,32.364833],"type":"Point"}
}