{
  "type": "Feature",
  "properties": {
    "addr:full":"102 Ridgemont Cir Booneville MS 38829",
    "addr:housenumber":"102",
    "addr:postcode":"38829",
    "addr:street":"Ridgemont Cir",
    "iso:country":"US",
    "sg:address":"102 Ridgemont Cir",
    "sg:city":"Booneville",
    "sg:classifiers":[
        {
            "category":"Health Services",
            "subcategory":"Clinic",
            "type":"Services"
        }
    ],
    "sg:phone":"+1 662 720 7050",
    "sg:postcode":"38829",
    "sg:province":"MS",
    "sg:tags":[
        "specialty",
        "outpatient"
    ],
    "wof:name":"Caring Hands Rehab",
    "wof:placetype":"venue"
},
  "geometry": {"coordinates":[-88.56675,34.696408],"type":"Point"}
}