{
  "type": "Feature",
  "properties": {
    "iso:country":"US",
    "sg:address":"7254 Stennis Airport Rd",
    "sg:city":"Kiln",
    "sg:classifiers":[
        {
            "category":"Airport",
            "type":"Transportation"
        }
    ],
    "sg:phone":"+1 228 467 3466",
    "sg:postcode":"39556",
    "sg:province":"MS",
    "wof:name":"Phillips Aviation Inc",
    "wof:placetype":"venue"
},
  "geometry": {"coordinates":[-89.442564,30.373272],"type":"Point"}
}