{
  "type": "Feature",
  "properties": {
    "iso:country":"US",
    "sg:address":"705 N Davis Ave",
    "sg:city":"Cleveland",
    "sg:classifiers":[
        {
            "category":"Wholesale",
            "subcategory":"Electrical",
            "type":"Manufacturing & Wholesale Goods"
        }
    ],
    "sg:phone":"+1 662 843 3465",
    "sg:postcode":"38732",
    "sg:province":"MS",
    "sg:tags":[
        "communication",
        "radio",
        "system"
    ],
    "wof:name":"Modern Communications Inc",
    "wof:placetype":"venue"
},
  "geometry": {"coordinates":[-90.715906,33.755967],"type":"Point"}
}