{
  "type": "Feature",
  "properties": {
    "iso:country":"US",
    "sg:address":"1865 S Main St",
    "sg:city":"Greenville",
    "sg:classifiers":[
        {
            "category":"Place Of Worship",
            "subcategory":"Church",
            "type":"Public Place"
        },
        {
            "category":"Place Of Worship",
            "type":"Public Place"
        }
    ],
    "sg:phone":"+1 662 334 3893",
    "sg:postcode":"38701",
    "sg:province":"MS",
    "sg:tags":[
        "churches-interdenominational",
        "churches-various",
        "denomination"
    ],
    "wof:name":"Chruch Of The Open Doors",
    "wof:placetype":"venue"
},
  "geometry": {"coordinates":[-91.058791,33.371755],"type":"Point"}
}