{
  "type": "Feature",
  "properties": {
    "addr:full":"345 Marie Dr Florence MS 39073",
    "addr:housenumber":"345",
    "addr:postcode":"39073",
    "addr:street":"Marie Dr",
    "iso:country":"US",
    "sg:address":"345 Marie Dr",
    "sg:city":"Florence",
    "sg:classifiers":[
        {
            "category":"Food & Beverages",
            "subcategory":"Groceries & Convenience Stores",
            "type":"Retail Goods"
        }
    ],
    "sg:phone":"+1 601 932 6807",
    "sg:postcode":"39073",
    "sg:province":"MS",
    "sg:tags":[
        "grocer"
    ],
    "wof:name":"Griffin Grocery",
    "wof:placetype":"venue"
},
  "geometry": {"coordinates":[-90.153361,32.203055],"type":"Point"}
}