{
  "type": "Feature",
  "properties": {
    "addr:full":"2625 Old Hwy 51 Terry MS 39170",
    "addr:housenumber":"2625",
    "addr:postcode":"39170",
    "addr:street":"Old Hwy 51 Terry",
    "iso:country":"US",
    "sg:address":"2625 Old Hwy 51",
    "sg:city":"Terry",
    "sg:classifiers":[
        {
            "category":"Education",
            "subcategory":"Vocational School",
            "type":"Public Place"
        }
    ],
    "sg:phone":"+1 601 878 0011",
    "sg:postcode":"39170",
    "sg:province":"MS",
    "wof:name":"Equipment Operator Training",
    "wof:placetype":"venue"
},
  "geometry": {"coordinates":[-90.301042,32.107511],"type":"Point"}
}