{
  "type": "Feature",
  "properties": {
    "iso:country":"US",
    "sg:address":"14561 Hwy 15 N",
    "sg:city":"Philadelphia",
    "sg:classifiers":[
        {
            "category":"Retail",
            "subcategory":"Auto Repair",
            "type":"Services"
        }
    ],
    "sg:phone":"+1 601 656 8942",
    "sg:postcode":"39350",
    "sg:province":"MS",
    "sg:tags":[
        "general"
    ],
    "wof:name":"Popes Automotive Repair",
    "wof:placetype":"venue"
},
  "geometry": {"coordinates":[-89.094866,32.863849],"type":"Point"}
}