{
  "type": "Feature",
  "properties": {
    "addr:full":"1440 Hwy 80 W Jackson MS 39204",
    "addr:housenumber":"1440",
    "addr:postcode":"39204",
    "addr:street":"Hwy 80 W",
    "iso:country":"US",
    "sg:address":"1440 Hwy 80 W",
    "sg:city":"Jackson",
    "sg:classifiers":[
        {
            "category":"Shopping",
            "subcategory":"Clothing, Apparel, & Fashions",
            "type":"Retail Goods"
        }
    ],
    "sg:phone":"+1 601 948 2923",
    "sg:postcode":"39204",
    "sg:province":"MS",
    "sg:tags":[
        "salvage",
        "surplus",
        "merchandise"
    ],
    "wof:name":"Gipson's Warehouse Food Prods",
    "wof:placetype":"venue"
},
  "geometry": {"coordinates":[-90.21028,32.286743],"type":"Point"}
}