{
  "type": "Feature",
  "properties": {
    "iso:country":"US",
    "sg:address":"1847 US Hwy 82 W",
    "sg:city":"Indianola",
    "sg:classifiers":[
        {
            "category":"Wholesale",
            "subcategory":"Auto Parts",
            "type":"Manufacturing & Wholesale Goods"
        }
    ],
    "sg:phone":"+1 662 887 4015",
    "sg:postcode":"38751",
    "sg:province":"MS",
    "sg:tags":[
        "automobile",
        "rebuilt"
    ],
    "wof:name":"Cobb's Salvage",
    "wof:placetype":"venue"
},
  "geometry": {"coordinates":[-90.739676,33.438246],"type":"Point"}
}