{
  "type": "Feature",
  "properties": {
    "iso:country":"US",
    "sg:address":"4860 Bethel Rd",
    "sg:city":"Olive Branch",
    "sg:classifiers":[
        {
            "category":"Professional",
            "subcategory":"Accounting & Tax Preparation",
            "type":"Services"
        }
    ],
    "sg:phone":"+1 662 890 9411",
    "sg:postcode":"38654",
    "sg:province":"MS",
    "sg:tags":[
        "return",
        "filing"
    ],
    "wof:name":"Crittle Financial Inc",
    "wof:placetype":"venue"
},
  "geometry": {"coordinates":[-89.79481800000001,34.923658],"type":"Point"}
}