{
  "type": "Feature",
  "properties": {
    "iso:country":"US",
    "sg:address":"7588 Hwy 178",
    "sg:city":"Olive Branch",
    "sg:classifiers":[
        {
            "category":"Building & Trades",
            "subcategory":"Plumbing",
            "type":"Services"
        }
    ],
    "sg:phone":"+1 662 890 7451",
    "sg:postcode":"38654",
    "sg:province":"MS",
    "sg:tags":[
        "contractor"
    ],
    "wof:name":"Creasie Plumbing",
    "wof:placetype":"venue"
},
  "geometry": {"coordinates":[-89.85437400000001,34.980334],"type":"Point"}
}