{
  "type": "Feature",
  "properties": {
    "iso:country":"US",
    "sg:address":"203 Poplar St",
    "sg:city":"Plantersville",
    "sg:classifiers":[
        {
            "category":"Organizations",
            "subcategory":"Religious Organization",
            "type":"Services"
        }
    ],
    "sg:phone":"+1 662 844 0856",
    "sg:postcode":"38862",
    "sg:province":"MS",
    "wof:name":"New Chapel Untd Methdst Church",
    "wof:placetype":"venue"
},
  "geometry": {"coordinates":[-88.674791,34.213625],"type":"Point"}
}