{
  "type": "Feature",
  "properties": {
    "addr:full":"3205 Hewes Ave Gulfport MS 39507",
    "addr:housenumber":"3205",
    "addr:postcode":"39507",
    "addr:street":"Hewes Ave",
    "iso:country":"US",
    "sg:address":"3205 Hewes Ave",
    "sg:city":"Gulfport",
    "sg:classifiers":[
        {
            "category":"Restaurant",
            "type":"Food & Drink"
        }
    ],
    "sg:phone":"+1 228 863 7030",
    "sg:postcode":"39507",
    "sg:province":"MS",
    "sg:tags":[
        "eating"
    ],
    "wof:name":"Uncle Ralph's Paragon Cafe",
    "wof:placetype":"venue"
},
  "geometry": {"coordinates":[-89.06103400000001,30.390345],"type":"Point"}
}