{
  "type": "Feature",
  "properties": {
    "iso:country":"US",
    "sg:address":"207 Howard St",
    "sg:city":"Greenwood",
    "sg:classifiers":[
        {
            "category":"Personal",
            "subcategory":"Beauty Salon",
            "type":"Services"
        }
    ],
    "sg:phone":"+1 662 453 8808",
    "sg:postcode":"38930",
    "sg:province":"MS",
    "sg:tags":[
        "shop"
    ],
    "wof:name":"Beauty Den",
    "wof:placetype":"venue"
},
  "geometry": {"coordinates":[-90.18257199999999,33.520417],"type":"Point"}
}