{
  "type": "Feature",
  "properties": {
    "addr:full":"107 Main St Purvis MS 39475",
    "addr:housenumber":"107",
    "addr:postcode":"39475",
    "addr:street":"Main St",
    "iso:country":"US",
    "sg:address":"107 Main St",
    "sg:city":"Purvis",
    "sg:classifiers":[
        {
            "category":"Freight",
            "type":"Transportation"
        }
    ],
    "sg:phone":"+1 601 794 2661",
    "sg:postcode":"39475",
    "sg:province":"MS",
    "sg:tags":[
        "terminal"
    ],
    "wof:name":"R & R Trucking Incorporated",
    "wof:placetype":"venue"
},
  "geometry": {"coordinates":[-89.41244500000001,31.144007],"type":"Point"}
}