{
  "type": "Feature",
  "properties": {
    "addr:full":"222 E Railroad Ave Crystal Springs MS 39059",
    "addr:housenumber":"222",
    "addr:postcode":"39059",
    "addr:street":"E Railroad Ave",
    "iso:country":"US",
    "sg:address":"222 E Railroad Ave",
    "sg:city":"Crystal Springs",
    "sg:classifiers":[
        {
            "category":"Recreation",
            "type":"Entertainment"
        }
    ],
    "sg:phone":"+1 601 892 0237",
    "sg:postcode":"39059",
    "sg:province":"MS",
    "sg:tags":[
        "instruction",
        "yoga"
    ],
    "wof:name":"Studio",
    "wof:placetype":"venue"
},
  "geometry": {"coordinates":[-90.35847800000001,31.986295],"type":"Point"}
}