{
  "type": "Feature",
  "properties": {
    "iso:country":"US",
    "sg:address":"221 Parks Rd",
    "sg:city":"Jackson",
    "sg:classifiers":[
        {
            "category":"Freight",
            "type":"Transportation"
        }
    ],
    "sg:phone":"+1 601 372 6704",
    "sg:postcode":"39212",
    "sg:province":"MS",
    "sg:tags":[
        "operator",
        "local",
        "trucking"
    ],
    "wof:name":"Dickerson Trucking",
    "wof:placetype":"venue"
},
  "geometry": {"coordinates":[-90.32671499999999,32.236505],"type":"Point"}
}