{
  "type": "Feature",
  "properties": {
    "iso:country":"US",
    "sg:address":"942 Berwood Dr",
    "sg:city":"Jackson",
    "sg:classifiers":[
        {
            "category":"Building & Trades",
            "subcategory":"Plumbing",
            "type":"Services"
        }
    ],
    "sg:phone":"+1 601 362 7330",
    "sg:postcode":"39206",
    "sg:province":"MS",
    "sg:tags":[
        "contractor"
    ],
    "wof:name":"Johnny Young Plumbing",
    "wof:placetype":"venue"
},
  "geometry": {"coordinates":[-90.191732,32.363727],"type":"Point"}
}