{
  "type": "Feature",
  "properties": {
    "iso:country":"US",
    "sg:address":"4315 30th St",
    "sg:city":"Meridian",
    "sg:classifiers":[
        {
            "category":"Organizations",
            "subcategory":"Religious Organization",
            "type":"Services"
        }
    ],
    "sg:phone":"+1 601 693 7062",
    "sg:postcode":"39307",
    "sg:province":"MS",
    "wof:name":"McSwain Theodis Rev",
    "wof:placetype":"venue"
},
  "geometry": {"coordinates":[-88.722183,32.38868],"type":"Point"}
}