{
  "type": "Feature",
  "properties": {
    "iso:country":"US",
    "sg:address":"218 Cain Ridge Rd",
    "sg:city":"Vicksburg",
    "sg:classifiers":[
        {
            "category":"Retail",
            "subcategory":"Repair Shop",
            "type":"Services"
        }
    ],
    "sg:phone":"+1 601 636 7810",
    "sg:postcode":"39180",
    "sg:province":"MS",
    "sg:tags":[
        "electrical"
    ],
    "wof:name":"Kens Appliance Repair",
    "wof:placetype":"venue"
},
  "geometry": {"coordinates":[-90.881102,32.305227],"type":"Point"}
}