{
  "type": "Feature",
  "properties": {
    "iso:country":"US",
    "sg:address":"528 Klondyke Rd",
    "sg:city":"Long Beach",
    "sg:classifiers":[
        {
            "category":"Organizations",
            "subcategory":"Religious Organization",
            "type":"Services"
        }
    ],
    "sg:phone":"+1 228 214 0111",
    "sg:postcode":"39560",
    "sg:province":"MS",
    "sg:tags":[
        "church"
    ],
    "wof:name":"Unity Center",
    "wof:placetype":"venue"
},
  "geometry": {"coordinates":[-89.153237,30.365776],"type":"Point"}
}