{
  "type": "Feature",
  "properties": {
    "addr:full":"9180 Crestwyn Hills Dr Memphis MS 38125",
    "addr:housenumber":"9180",
    "addr:postcode":"38125",
    "addr:street":"Crestwyn Hills Dr",
    "iso:country":"US",
    "sg:address":"9180 Crestwyn Hills Dr",
    "sg:city":"Memphis",
    "sg:classifiers":[
        {
            "category":"Wholesale",
            "subcategory":"Furniture",
            "type":"Manufacturing & Wholesale Goods"
        }
    ],
    "sg:phone":"+1 901 756 9619",
    "sg:postcode":"38125",
    "sg:province":"MS",
    "sg:tags":[
        "chair"
    ],
    "wof:name":"Miss Eaton Inc",
    "wof:placetype":"venue"
},
  "geometry": {"coordinates":[-89.75882799999999,35.044552],"type":"Point"}
}