{
  "type": "Feature",
  "properties": {
    "iso:country":"US",
    "sg:address":"647 S Theobald St",
    "sg:city":"Greenville",
    "sg:classifiers":[
        {
            "category":"Personal",
            "subcategory":"Beauty Salon",
            "type":"Services"
        }
    ],
    "sg:phone":"+1 662 332 5751",
    "sg:postcode":"38701",
    "sg:province":"MS",
    "sg:tags":[
        "shop"
    ],
    "wof:name":"Integrity Hair Salon",
    "wof:placetype":"venue"
},
  "geometry": {"coordinates":[-91.063035,33.402098],"type":"Point"}
}