{
  "type": "Feature",
  "properties": {
    "iso:country":"US",
    "sg:address":"103 E Floyce St",
    "sg:city":"Ruleville",
    "sg:classifiers":[
        {
            "category":"Insurance",
            "subcategory":"Insurance Agent",
            "type":"Services"
        }
    ],
    "sg:phone":"+1 662 756 4998",
    "sg:postcode":"38771",
    "sg:province":"MS",
    "wof:name":"Farm Bureau Insurance",
    "wof:placetype":"venue"
},
  "geometry": {"coordinates":[-90.551807,33.726016],"type":"Point"}
}