{
  "type": "Feature",
  "properties": {
    "addr:full":"1700 W Government St Brandon MS 39042",
    "addr:housenumber":"1700",
    "addr:postcode":"39042",
    "addr:street":"W Government St",
    "iso:country":"US",
    "sg:address":"1700 W Government St",
    "sg:city":"Brandon",
    "sg:phone":"+1 601 825 9281",
    "sg:postcode":"39042",
    "sg:province":"MS",
    "sg:tags":[
        "product",
        "petroleum"
    ],
    "wof:name":"Star Enterprise",
    "wof:placetype":"venue"
},
  "geometry": {"coordinates":[-90.008072,32.282758],"type":"Point"}
}