{
  "type": "Feature",
  "properties": {
    "iso:country":"US",
    "sg:address":"3800 Bailey Ave",
    "sg:city":"Jackson",
    "sg:classifiers":[
        {
            "category":"Real Estate",
            "subcategory":"Real Estate Operator",
            "type":"Services"
        }
    ],
    "sg:phone":"+1 601 362 3036",
    "sg:postcode":"39213",
    "sg:province":"MS",
    "sg:tags":[
        "building",
        "apartment"
    ],
    "wof:name":"Hunnington Terrace Apartments",
    "wof:placetype":"venue"
},
  "geometry": {"coordinates":[-90.19257,32.354024],"type":"Point"}
}