{
  "type": "Feature",
  "properties": {
    "iso:country":"US",
    "sg:address":"117 Woodsong Way",
    "sg:city":"Madison",
    "sg:classifiers":[
        {
            "category":"Professional",
            "subcategory":"Management & Consulting",
            "type":"Services"
        }
    ],
    "sg:phone":"+1 601 898 1465",
    "sg:postcode":"39110",
    "sg:province":"MS",
    "wof:name":"Howell Barry L Sales Rep Ad S",
    "wof:placetype":"venue"
},
  "geometry": {"coordinates":[-90.099205,32.470812],"type":"Point"}
}