{
  "type": "Feature",
  "properties": {
    "iso:country":"US",
    "sg:address":"4623 Hanging Moss Rd",
    "sg:city":"Jackson",
    "sg:classifiers":[
        {
            "category":"Social Services",
            "subcategory":"Child Care",
            "type":"Services"
        }
    ],
    "sg:phone":"+1 601 713 2551",
    "sg:postcode":"39206",
    "sg:province":"MS",
    "wof:name":"Whole Life Christian Preschool",
    "wof:placetype":"venue"
},
  "geometry": {"coordinates":[-90.179841,32.369555],"type":"Point"}
}