{
  "type": "Feature",
  "properties": {
    "addr:full":"101 E Harrington St Houston MS 38851",
    "addr:housenumber":"101",
    "addr:postcode":"38851",
    "addr:street":"E Harrington St",
    "iso:country":"US",
    "sg:address":"101 E Harrington St",
    "sg:city":"Houston",
    "sg:classifiers":[
        {
            "category":"Insurance",
            "subcategory":"Insurance Agent",
            "type":"Services"
        }
    ],
    "sg:phone":"+1 662 456 3338",
    "sg:postcode":"38851",
    "sg:province":"MS",
    "wof:name":"Wallace Norman Insurance",
    "wof:placetype":"venue"
},
  "geometry": {"coordinates":[-89.000169,33.895793],"type":"Point"}
}