{
  "type": "Feature",
  "properties": {
    "iso:country":"US",
    "sg:address":"501 W Laurel Ave",
    "sg:city":"Hattiesburg",
    "sg:classifiers":[
        {
            "category":"Wholesale",
            "subcategory":"Hardware",
            "type":"Manufacturing & Wholesale Goods"
        }
    ],
    "sg:phone":"+1 601 582 3571",
    "sg:postcode":"39401",
    "sg:province":"MS",
    "sg:tags":[
        "plumbing",
        "fixture",
        "supply"
    ],
    "wof:name":"Mc Elhaney Plumbing & Hardware",
    "wof:placetype":"venue"
},
  "geometry": {"coordinates":[-89.289232,31.323183],"type":"Point"}
}