{
  "type": "Feature",
  "properties": {
    "iso:country":"US",
    "sg:address":"1766 Old Leland Rd",
    "sg:city":"Greenville",
    "sg:classifiers":[
        {
            "category":"Real Estate",
            "subcategory":"Real Estate Operator",
            "type":"Services"
        }
    ],
    "sg:phone":"+1 662 335 4909",
    "sg:postcode":"38703",
    "sg:province":"MS",
    "sg:tags":[
        "retirement",
        "hotel",
        "apartment"
    ],
    "wof:name":"Mc Farland Estates",
    "wof:placetype":"venue"
},
  "geometry": {"coordinates":[-91.03482700000001,33.416428],"type":"Point"}
}