{
  "type": "Feature",
  "properties": {
    "iso:country":"US",
    "sg:address":"1044 Lake Jackson Rd",
    "sg:city":"Glen Allan",
    "sg:classifiers":[
        {
            "category":"Farming",
            "subcategory":"Farm",
            "type":"Manufacturing & Wholesale Goods"
        }
    ],
    "sg:phone":"+1 662 827 5810",
    "sg:postcode":"38744",
    "sg:province":"MS",
    "sg:tags":[
        "crop",
        "general"
    ],
    "wof:name":"Howard New & Sons",
    "wof:placetype":"venue"
},
  "geometry": {"coordinates":[-91.080653,33.063351],"type":"Point"}
}