{
  "type": "Feature",
  "properties": {
    "addr:full":"3102 Donniebrook Ln Moss Point MS 39562",
    "addr:housenumber":"3102",
    "addr:postcode":"39562",
    "addr:street":"Donniebrook Ln",
    "iso:country":"US",
    "sg:address":"3102 Donniebrook Ln",
    "sg:city":"Moss Point",
    "sg:classifiers":[
        {
            "category":"Manufacturing",
            "subcategory":"Textiles",
            "type":"Manufacturing & Wholesale Goods"
        }
    ],
    "sg:phone":"+1 228 475 2503",
    "sg:postcode":"39562",
    "sg:province":"MS",
    "sg:tags":[
        "coated",
        "fabric",
        "mfg"
    ],
    "wof:name":"Poly Dynamics LLC",
    "wof:placetype":"venue"
},
  "geometry": {"coordinates":[-88.55707,30.495881],"type":"Point"}
}