{
  "type": "Feature",
  "properties": {
    "iso:country":"US",
    "sg:address":"1823 N 3rd Ave",
    "sg:city":"Columbus",
    "sg:classifiers":[
        {
            "category":"Shopping",
            "subcategory":"Used Merchandise",
            "type":"Retail Goods"
        }
    ],
    "sg:phone":"+1 662 327 6693",
    "sg:postcode":"39701",
    "sg:province":"MS",
    "sg:tags":[
        "furniture"
    ],
    "wof:name":"Watts Furniture Co",
    "wof:placetype":"venue"
},
  "geometry": {"coordinates":[-88.41218600000001,33.499757],"type":"Point"}
}