{
  "type": "Feature",
  "properties": {
    "addr:full":"1511 Eckford St Tupelo MS 38801",
    "addr:housenumber":"1511",
    "addr:postcode":"38801",
    "addr:street":"Eckford St",
    "iso:country":"US",
    "sg:address":"1511 Eckford St",
    "sg:city":"Tupelo",
    "sg:classifiers":[
        {
            "category":"Personal",
            "subcategory":"Beauty Salon",
            "type":"Services"
        }
    ],
    "sg:phone":"+1 662 840 9028",
    "sg:postcode":"38801",
    "sg:province":"MS",
    "sg:tags":[
        "shop"
    ],
    "wof:name":"Adkins Hair & Skin Salon",
    "wof:placetype":"venue"
},
  "geometry": {"coordinates":[-88.731751,34.256777],"type":"Point"}
}