{
  "type": "Feature",
  "properties": {
    "iso:country":"US",
    "sg:address":"2147 Mill St Exn",
    "sg:city":"Lucedale",
    "sg:classifiers":[
        {
            "category":"Organizations",
            "subcategory":"Religious Organization",
            "type":"Services"
        }
    ],
    "sg:phone":"+1 601 947 1478",
    "sg:postcode":"39452",
    "sg:province":"MS",
    "sg:tags":[
        "church"
    ],
    "wof:name":"Bethel Baptist Church Lucedale",
    "wof:placetype":"venue"
},
  "geometry": {"coordinates":[-88.58795499999999,30.907432],"type":"Point"}
}