{
  "type": "Feature",
  "properties": {
    "iso:country":"US",
    "sg:address":"4822 State Hwy 22",
    "sg:city":"Flora",
    "sg:classifiers":[
        {
            "category":"Restaurant",
            "type":"Food & Drink"
        }
    ],
    "sg:phone":"+1 601 879 3701",
    "sg:postcode":"39071",
    "sg:province":"MS",
    "wof:name":"G G's Diner",
    "wof:placetype":"venue"
},
  "geometry": {"coordinates":[-90.310293,32.542978],"type":"Point"}
}