{
  "type": "Feature",
  "properties": {
    "iso:country":"US",
    "sg:address":"4801 Mc Innis Ave",
    "sg:city":"Moss Point",
    "sg:classifiers":[
        {
            "category":"Building & Trades",
            "subcategory":"Construction",
            "type":"Services"
        }
    ],
    "sg:phone":"+1 228 475 7002",
    "sg:postcode":"39563",
    "sg:province":"MS",
    "sg:tags":[
        "contractor"
    ],
    "wof:name":"Rose Contracting LLC",
    "wof:placetype":"venue"
},
  "geometry": {"coordinates":[-88.510232,30.398798],"type":"Point"}
}