{
  "type": "Feature",
  "properties": {
    "iso:country":"US",
    "sg:address":"562 Marson Trigg Rd",
    "sg:city":"Seminary",
    "sg:classifiers":[
        {
            "category":"Farming",
            "subcategory":"Livestock Farm",
            "type":"Manufacturing & Wholesale Goods"
        }
    ],
    "sg:phone":"+1 601 722 3352",
    "sg:postcode":"39479",
    "sg:province":"MS",
    "sg:tags":[
        "feedlot",
        "field",
        "crop",
        "beef",
        "cattle"
    ],
    "wof:name":"Trigg Marson",
    "wof:placetype":"venue"
},
  "geometry": {"coordinates":[-89.498923,31.477902],"type":"Point"}
}