{
  "type": "Feature",
  "properties": {
    "addr:full":"4393 Union Ave Nettleton MS 38858",
    "addr:housenumber":"4393",
    "addr:postcode":"38858",
    "addr:street":"Union Ave",
    "iso:country":"US",
    "sg:address":"4393 Union Ave",
    "sg:city":"Nettleton",
    "sg:classifiers":[
        {
            "category":"Organizations",
            "subcategory":"Religious Organization",
            "type":"Services"
        }
    ],
    "sg:phone":"+1 662 963 7289",
    "sg:postcode":"38858",
    "sg:province":"MS",
    "sg:tags":[
        "church"
    ],
    "wof:name":"Palenstine United Methodist",
    "wof:placetype":"venue"
},
  "geometry": {"coordinates":[-88.62239099999999,34.101116],"type":"Point"}
}