{
  "type": "Feature",
  "properties": {
    "iso:country":"US",
    "sg:address":"316 S President St",
    "sg:city":"Jackson",
    "sg:classifiers":[
        {
            "category":"Government",
            "subcategory":"Office",
            "type":"Public Place"
        }
    ],
    "sg:phone":"+1 601 878 5583",
    "sg:postcode":"39201",
    "sg:province":"MS",
    "sg:tags":[
        "county"
    ],
    "wof:name":"Hinds County Board-Supervisors",
    "wof:placetype":"venue"
},
  "geometry": {"coordinates":[-90.182233,32.296444],"type":"Point"}
}