{
  "type": "Feature",
  "properties": {
    "addr:full":"3425 Marydell St Jackson MS 39213",
    "addr:housenumber":"3425",
    "addr:postcode":"39213",
    "addr:street":"Marydell St",
    "iso:country":"US",
    "sg:address":"3425 Marydell St",
    "sg:city":"Jackson",
    "sg:classifiers":[
        {
            "category":"Organizations",
            "subcategory":"Religious Organization",
            "type":"Services"
        }
    ],
    "sg:phone":"+1 601 981 8569",
    "sg:postcode":"39213",
    "sg:province":"MS",
    "sg:tags":[
        "church"
    ],
    "wof:name":"New Jerusalem Church Of God",
    "wof:placetype":"venue"
},
  "geometry": {"coordinates":[-90.21102500000001,32.33932],"type":"Point"}
}