{
  "type": "Feature",
  "properties": {
    "addr:full":"5735 Cedar Lake Dr N Walls MS 38680",
    "addr:housenumber":"5735",
    "addr:postcode":"38680",
    "addr:street":"Cedar Lake Dr N Walls",
    "iso:country":"US",
    "sg:address":"5735 Cedar Lake Dr N",
    "sg:city":"Walls",
    "sg:classifiers":[
        {
            "category":"Retail",
            "subcategory":"Auto Rental",
            "type":"Services"
        }
    ],
    "sg:phone":"+1 662 781 0286",
    "sg:postcode":"38680",
    "sg:province":"MS",
    "sg:tags":[
        "passenger",
        "leasing",
        "car"
    ],
    "wof:name":"Barnett Group Leasing LLC",
    "wof:placetype":"venue"
},
  "geometry": {"coordinates":[-90.092491,34.986622],"type":"Point"}
}