{
  "type": "Feature",
  "properties": {
    "iso:country":"US",
    "sg:address":"924 S Gloster St",
    "sg:city":"Tupelo",
    "sg:classifiers":[
        {
            "category":"Personal",
            "subcategory":"Beauty Salon",
            "type":"Services"
        }
    ],
    "sg:phone":"+1 662 844 2300",
    "sg:postcode":"38801",
    "sg:province":"MS",
    "sg:tags":[
        "shop"
    ],
    "wof:name":"Shear Genius",
    "wof:placetype":"venue"
},
  "geometry": {"coordinates":[-88.71798,34.240231],"type":"Point"}
}