{
  "type": "Feature",
  "properties": {
    "iso:country":"US",
    "sg:address":"63 Shoreline Ln",
    "sg:city":"Gulfport",
    "sg:classifiers":[
        {
            "category":"Building & Trades",
            "subcategory":"Construction",
            "type":"Services"
        }
    ],
    "sg:phone":"+1 228 896 6680",
    "sg:postcode":"39503",
    "sg:province":"MS",
    "sg:tags":[
        "industrial"
    ],
    "wof:name":"Warehouse Partners Inc",
    "wof:placetype":"venue"
},
  "geometry": {"coordinates":[-89.03500699999999,30.412696],"type":"Point"}
}