{
  "type": "Feature",
  "properties": {
    "iso:country":"US",
    "sg:address":"1115 City Ave N",
    "sg:city":"Ripley",
    "sg:classifiers":[
        {
            "category":"Food & Beverages",
            "subcategory":"Groceries & Convenience Stores",
            "type":"Retail Goods"
        }
    ],
    "sg:phone":"+1 662 837 7121",
    "sg:postcode":"38663",
    "sg:province":"MS",
    "sg:tags":[
        "grocer"
    ],
    "wof:name":"Chapman's Big Red Foods",
    "wof:placetype":"venue"
},
  "geometry": {"coordinates":[-88.94945800000001,34.740596],"type":"Point"}
}