{
  "type": "Feature",
  "properties": {
    "iso:country":"US",
    "sg:address":"617 E Lee St",
    "sg:city":"Sardis",
    "sg:classifiers":[
        {
            "category":"Local Transit",
            "type":"Transportation"
        }
    ],
    "sg:phone":"+1 662 487 3004",
    "sg:postcode":"38666",
    "sg:province":"MS",
    "sg:tags":[
        "passenger"
    ],
    "wof:name":"Emergystat Ambulance",
    "wof:placetype":"venue"
},
  "geometry": {"coordinates":[-89.892338,34.43725],"type":"Point"}
}