{
  "type": "Feature",
  "properties": {
    "iso:country":"US",
    "sg:address":"2 Medical Park Cir",
    "sg:city":"Fulton",
    "sg:classifiers":[
        {
            "category":"Health Services",
            "subcategory":"Clinic",
            "type":"Services"
        }
    ],
    "sg:phone":"+1 662 862 7403",
    "sg:postcode":"38801",
    "sg:province":"MS",
    "sg:tags":[
        "home"
    ],
    "wof:name":"North Mississippi Home Health",
    "wof:placetype":"venue"
},
  "geometry": {"coordinates":[-88.71473400000001,34.234564],"type":"Point"}
}