{
  "type": "Feature",
  "properties": {
    "iso:country":"US",
    "sg:address":"2403 N 3rd Ave",
    "sg:city":"Columbus",
    "sg:classifiers":[
        {
            "category":"Retail",
            "subcategory":"Auto Repair",
            "type":"Services"
        }
    ],
    "sg:phone":"+1 662 251 2936",
    "sg:postcode":"39701",
    "sg:province":"MS",
    "sg:tags":[
        "body",
        "automobile",
        "painting"
    ],
    "wof:name":"Hall's Body Shop & Wrecker Svc",
    "wof:placetype":"venue"
},
  "geometry": {"coordinates":[-88.40295,33.499854],"type":"Point"}
}