{
  "type": "Feature",
  "properties": {
    "iso:country":"US",
    "sg:address":"290 Allen Rd",
    "sg:city":"Columbia",
    "sg:classifiers":[
        {
            "category":"Farming",
            "subcategory":"Livestock Farm",
            "type":"Manufacturing & Wholesale Goods"
        }
    ],
    "sg:phone":"+1 601 736 6969",
    "sg:postcode":"39429",
    "sg:province":"MS",
    "sg:tags":[
        "beef",
        "feedlot",
        "cattle"
    ],
    "wof:name":"Milton Carson",
    "wof:placetype":"venue"
},
  "geometry": {"coordinates":[-89.77308499999999,31.410126],"type":"Point"}
}