{
  "type": "Feature",
  "properties": {
    "iso:country":"US",
    "sg:address":"144 Main St",
    "sg:city":"Bay St Louis",
    "sg:classifiers":[
        {
            "category":"Shopping",
            "type":"Retail Goods"
        }
    ],
    "sg:phone":"+1 228 467 7993",
    "sg:postcode":"39520",
    "sg:province":"MS",
    "sg:tags":[
        "picture",
        "frame",
        "merchandise"
    ],
    "wof:name":"Loft Studios",
    "wof:placetype":"venue"
},
  "geometry": {"coordinates":[-89.32593799999999,30.310403],"type":"Point"}
}