{
  "type": "Feature",
  "properties": {
    "iso:country":"US",
    "sg:address":"173 1st St",
    "sg:city":"Biloxi",
    "sg:classifiers":[
        {
            "category":"Recreation",
            "type":"Entertainment"
        }
    ],
    "sg:phone":"+1 228 435 1592",
    "sg:postcode":"39530",
    "sg:province":"MS",
    "sg:tags":[
        "water",
        "passenger",
        "transport"
    ],
    "wof:name":"Mississippi Hospitality",
    "wof:placetype":"venue"
},
  "geometry": {"coordinates":[-88.861192,30.393619],"type":"Point"}
}