{
  "type": "Feature",
  "properties": {
    "iso:country":"US",
    "sg:address":"108 N Main St",
    "sg:city":"Petal",
    "sg:classifiers":[
        {
            "category":"Health Services",
            "subcategory":"Doctor",
            "type":"Services"
        }
    ],
    "sg:phone":"+1 601 583 8726",
    "sg:postcode":"39465",
    "sg:province":"MS",
    "wof:name":"Barbara B Mauldin DDS",
    "wof:placetype":"venue"
},
  "geometry": {"coordinates":[-89.262997,31.347403],"type":"Point"}
}