{
  "type": "Feature",
  "properties": {
    "iso:country":"US",
    "sg:address":"2111 29th St",
    "sg:city":"Gulfport",
    "sg:classifiers":[
        {
            "category":"Wholesale",
            "subcategory":"Hardware",
            "type":"Manufacturing & Wholesale Goods"
        }
    ],
    "sg:phone":"+1 228 868 7358",
    "sg:postcode":"39501",
    "sg:province":"MS",
    "wof:name":"Solar Supply of Gulfport",
    "wof:placetype":"venue"
},
  "geometry": {"coordinates":[-89.08778,30.385275],"type":"Point"}
}