{
  "type": "Feature",
  "properties": {
    "addr:full":"111 N Main St Ripley MS 38663",
    "addr:housenumber":"111",
    "addr:postcode":"38663",
    "addr:street":"N Main St",
    "iso:country":"US",
    "sg:address":"111 N Main St",
    "sg:city":"Ripley",
    "sg:classifiers":[
        {
            "category":"Organizations",
            "subcategory":"Religious Organization",
            "type":"Services"
        }
    ],
    "sg:phone":"+1 662 837 3773",
    "sg:postcode":"38663",
    "sg:province":"MS",
    "sg:tags":[
        "church"
    ],
    "wof:name":"House Of Freedom Church",
    "wof:placetype":"venue"
},
  "geometry": {"coordinates":[-88.949164,34.730943],"type":"Point"}
}