{
  "type": "Feature",
  "properties": {
    "addr:full":"500 Madison St Clinton MS 39056",
    "addr:housenumber":"500",
    "addr:postcode":"39056",
    "addr:street":"Madison St",
    "iso:country":"US",
    "sg:address":"500 Madison St",
    "sg:city":"Clinton",
    "sg:classifiers":[
        {
            "category":"Manufacturing",
            "subcategory":"Printing",
            "type":"Manufacturing & Wholesale Goods"
        }
    ],
    "sg:phone":"+1 601 924 9193",
    "sg:postcode":"39056",
    "sg:province":"MS",
    "sg:tags":[
        "building",
        "operator",
        "apartment",
        "commercial"
    ],
    "wof:name":"Fondren George R Oil Gas Prpts",
    "wof:placetype":"venue"
},
  "geometry": {"coordinates":[-90.335855,32.337238],"type":"Point"}
}