{
  "type": "Feature",
  "properties": {
    "iso:country":"US",
    "sg:address":"2800 US Hwy 90",
    "sg:city":"Gautier",
    "sg:classifiers":[
        {
            "category":"Health Services",
            "subcategory":"Doctor",
            "type":"Services"
        }
    ],
    "sg:phone":"+1 228 497 6110",
    "sg:postcode":"39553",
    "sg:province":"MS",
    "sg:tags":[
        "dentist"
    ],
    "wof:name":"Dental Plaza",
    "wof:placetype":"venue"
},
  "geometry": {"coordinates":[-88.65346,30.392307],"type":"Point"}
}