{
  "type": "Feature",
  "properties": {
    "addr:full":"6620 Swinnea Rd Southaven MS 38671",
    "addr:postcode":"6620;38671",
    "addr:street":"Swinnea Rd",
    "iso:country":"US",
    "sg:address":"6620 Swinnea Rd",
    "sg:city":"Southaven",
    "sg:classifiers":[
        {
            "category":"Building & Trades",
            "subcategory":"Equipment Rental",
            "type":"Services"
        }
    ],
    "sg:phone":"+1 662 349 8344",
    "sg:postcode":"38671",
    "sg:province":"MS",
    "wof:name":"Bcs Rentals Inc",
    "wof:placetype":"venue"
},
  "geometry": {"coordinates":[-89.972077,34.957383],"type":"Point"}
}