{
  "type": "Feature",
  "properties": {
    "iso:country":"US",
    "sg:address":"3335 Pine Tar Aly",
    "sg:city":"Southaven",
    "sg:classifiers":[
        {
            "category":"Professional",
            "subcategory":"Management & Consulting",
            "type":"Services"
        }
    ],
    "sg:phone":"+1 662 890 3371",
    "sg:postcode":"38672",
    "sg:province":"MS",
    "sg:tags":[
        "fuel"
    ],
    "sg:website":"www.ssmsports.com",
    "wof:name":"Southeastern Sports Management",
    "wof:placetype":"venue"
},
  "geometry": {"coordinates":[-89.93153700000001,34.955916],"type":"Point"}
}