{
  "type": "Feature",
  "properties": {
    "addr:full":"922 McLean St Greenwood MS 38930",
    "addr:housenumber":"922",
    "addr:postcode":"38930",
    "addr:street":"Mclean St",
    "iso:country":"US",
    "sg:address":"922 McLean St",
    "sg:city":"Greenwood",
    "sg:classifiers":[
        {
            "category":"Local Transit",
            "type":"Transportation"
        }
    ],
    "sg:phone":"+1 662 429 5691",
    "sg:postcode":"38930",
    "sg:province":"MS",
    "wof:name":"VH4 Inc",
    "wof:placetype":"venue"
},
  "geometry": {"coordinates":[-90.164665,33.519151],"type":"Point"}
}