{
  "type": "Feature",
  "properties": {
    "addr:full":"119 Wesley Grant Rd Hattiesburg MS 39401",
    "addr:housenumber":"119",
    "addr:postcode":"39401",
    "addr:street":"Wesley Grant Rd",
    "iso:country":"US",
    "sg:address":"119 Wesley Grant Rd",
    "sg:city":"Hattiesburg",
    "sg:classifiers":[
        {
            "category":"Freight",
            "type":"Transportation"
        }
    ],
    "sg:phone":"+1 601 584 8757",
    "sg:postcode":"39401",
    "sg:province":"MS",
    "sg:tags":[
        "timber",
        "trucking"
    ],
    "wof:name":"T & T Repair",
    "wof:placetype":"venue"
},
  "geometry": {"coordinates":[-89.328033,31.379411],"type":"Point"}
}