{
  "type": "Feature",
  "properties": {
    "iso:country":"US",
    "sg:address":"2362 Long Creek Rd",
    "sg:city":"Meridian",
    "sg:classifiers":[
        {
            "category":"Education",
            "subcategory":"School",
            "type":"Public Place"
        }
    ],
    "sg:phone":"+1 601 483 5501",
    "sg:postcode":"39301",
    "sg:province":"MS",
    "sg:website":"www.ihigh.com",
    "wof:name":"Southeast High School",
    "wof:placetype":"venue"
},
  "geometry": {"coordinates":[-88.57305100000001,32.325879],"type":"Point"}
}