{
  "type": "Feature",
  "properties": {
    "addr:full":"216 Main St Mccomb MS 39648",
    "addr:housenumber":"216",
    "addr:postcode":"39648",
    "addr:street":"Main St",
    "iso:country":"US",
    "sg:address":"216 Main St",
    "sg:city":"Mccomb",
    "sg:classifiers":[
        {
            "category":"Shopping",
            "subcategory":"Hobbies, Toys, & Games",
            "type":"Retail Goods"
        }
    ],
    "sg:phone":"+1 601 250 0009",
    "sg:postcode":"39648",
    "sg:province":"MS",
    "sg:tags":[
        "supply"
    ],
    "wof:name":"Chibi's",
    "wof:placetype":"venue"
},
  "geometry": {"coordinates":[-90.452296,31.243747],"type":"Point"}
}