{
  "type": "Feature",
  "properties": {
    "iso:country":"US",
    "sg:address":"3512 N Shellrock Rd",
    "sg:city":"Jackson",
    "sg:classifiers":[
        {
            "category":"Organizations",
            "subcategory":"Religious Organization",
            "type":"Services"
        }
    ],
    "sg:phone":"+1 601 981 5646",
    "sg:postcode":"39213",
    "sg:province":"MS",
    "sg:tags":[
        "church"
    ],
    "wof:name":"Potter's House Fellowship Bapt",
    "wof:placetype":"venue"
},
  "geometry": {"coordinates":[-90.24883800000001,32.370456],"type":"Point"}
}