{
  "type": "Feature",
  "properties": {
    "iso:country":"US",
    "sg:address":"56 Airport Rd",
    "sg:city":"Lyon",
    "sg:classifiers":[
        {
            "category":"Farming",
            "subcategory":"Farm & Veterinary Services",
            "type":"Manufacturing & Wholesale Goods"
        }
    ],
    "sg:phone":"+1 662 627 5522",
    "sg:postcode":"38645",
    "sg:province":"MS",
    "sg:tags":[
        "crop"
    ],
    "wof:name":"Leist Air Service Inc",
    "wof:placetype":"venue"
},
  "geometry": {"coordinates":[-90.512308,34.290292],"type":"Point"}
}