{
  "type": "Feature",
  "properties": {
    "addr:full":"1414 Gibraltar Dr Jackson MS 39204",
    "addr:housenumber":"1414",
    "addr:postcode":"39204",
    "addr:street":"Gibraltar Dr",
    "iso:country":"US",
    "sg:address":"1414 Gibraltar Dr",
    "sg:city":"Jackson",
    "sg:classifiers":[
        {
            "category":"Freight",
            "type":"Transportation"
        }
    ],
    "sg:phone":"+1 601 372 5764",
    "sg:postcode":"39204",
    "sg:province":"MS",
    "sg:tags":[
        "commercial",
        "storage"
    ],
    "wof:name":"Uhaul Self Storage",
    "wof:placetype":"venue"
},
  "geometry": {"coordinates":[-90.232113,32.292886],"type":"Point"}
}