{
  "type": "Feature",
  "properties": {
    "iso:country":"US",
    "sg:address":"622 Bayview Ave",
    "sg:city":"Biloxi",
    "sg:classifiers":[
        {
            "category":"Government",
            "subcategory":"Office",
            "type":"Public Place"
        }
    ],
    "sg:phone":"+1 228 435 6121",
    "sg:postcode":"39530",
    "sg:province":"MS",
    "sg:tags":[
        "village"
    ],
    "sg:website":"www.biloxi.ms.us",
    "wof:name":"Old Brick House",
    "wof:placetype":"venue"
},
  "geometry": {"coordinates":[-88.881648,30.411967],"type":"Point"}
}