{
  "type": "Feature",
  "properties": {
    "iso:country":"US",
    "sg:address":"4960 Old Canton Rd",
    "sg:city":"Jackson",
    "sg:classifiers":[
        {
            "category":"Retail",
            "subcategory":"Veterinary Services",
            "type":"Services"
        }
    ],
    "sg:phone":"+1 601 956 6144",
    "sg:postcode":"39211",
    "sg:province":"MS",
    "sg:tags":[
        "hospital",
        "animal"
    ],
    "wof:name":"Canton Road Veterinary Hosp",
    "wof:placetype":"venue"
},
  "geometry": {"coordinates":[-90.141938,32.366723],"type":"Point"}
}