{
  "type": "Feature",
  "properties": {
    "iso:country":"US",
    "sg:address":"404 Main St",
    "sg:city":"Greenwood",
    "sg:classifiers":[
        {
            "category":"Government",
            "subcategory":"Fire Station",
            "type":"Public Place"
        }
    ],
    "sg:phone":"+1 662 455 7632",
    "sg:postcode":"38930",
    "sg:province":"MS",
    "sg:tags":[
        "department"
    ],
    "wof:name":"Greenwood City Fire Dept",
    "wof:placetype":"venue"
},
  "geometry": {"coordinates":[-90.180907,33.518386],"type":"Point"}
}