{
  "type": "Feature",
  "properties": {
    "iso:country":"US",
    "sg:address":"17 Co Rd 1083",
    "sg:city":"Oxford",
    "sg:classifiers":[
        {
            "category":"Building & Trades",
            "subcategory":"Construction",
            "type":"Services"
        }
    ],
    "sg:phone":"+1 662 236 6747",
    "sg:postcode":"38655",
    "sg:province":"MS",
    "sg:tags":[
        "resurfacing",
        "laying",
        "refinishing",
        "floor"
    ],
    "wof:name":"Darrell Daniels Ceramic Tile",
    "wof:placetype":"venue"
},
  "geometry": {"coordinates":[-89.699681,34.431405],"type":"Point"}
}