{
  "type": "Feature",
  "properties": {
    "iso:country":"US",
    "sg:address":"3549 Lower Centreville Rd",
    "sg:city":"Liberty",
    "sg:classifiers":[
        {
            "category":"Health Services",
            "subcategory":"Doctor",
            "type":"Services"
        }
    ],
    "sg:phone":"+1 601 657 4562",
    "sg:postcode":"39645",
    "sg:province":"MS",
    "sg:tags":[
        "medical"
    ],
    "wof:name":"Henry Lewis Dr",
    "wof:placetype":"venue"
},
  "geometry": {"coordinates":[-90.89730400000001,31.056577],"type":"Point"}
}