{
  "type": "Feature",
  "properties": {
    "addr:full":"7050 Malco Xing Memphis MS 38125",
    "addr:postcode":"7050;38125",
    "addr:street":"Malco Xing",
    "iso:country":"US",
    "sg:address":"7050 Malco Xing",
    "sg:city":"Memphis",
    "sg:classifiers":[
        {
            "category":"Personal",
            "subcategory":"Barber",
            "type":"Services"
        }
    ],
    "sg:phone":"+1 901 751 0090",
    "sg:postcode":"38125",
    "sg:province":"MS",
    "wof:name":"New Era",
    "wof:placetype":"venue"
},
  "geometry": {"coordinates":[-89.828169,35.047206],"type":"Point"}
}