{
  "type": "Feature",
  "properties": {
    "addr:full":"7460 Southwind Cove Memphis MS 38125",
    "addr:housenumber":"7460",
    "addr:postcode":"38125",
    "addr:street":"Southwind Cove",
    "iso:country":"US",
    "sg:address":"7460 Southwind Cove",
    "sg:city":"Memphis",
    "sg:classifiers":[
        {
            "category":"Building & Trades",
            "subcategory":"Cleaning & Sanitation",
            "type":"Services"
        }
    ],
    "sg:phone":"+1 901 754 2883",
    "sg:postcode":"38125",
    "sg:province":"MS",
    "sg:tags":[
        "maintenance"
    ],
    "wof:name":"Love Cleaning Services Lcs",
    "wof:placetype":"venue"
},
  "geometry": {"coordinates":[-89.81452899999999,35.021144],"type":"Point"}
}