{
  "type": "Feature",
  "properties": {
    "iso:country":"US",
    "sg:address":"207 Mable St",
    "sg:city":"Lucedale",
    "sg:classifiers":[
        {
            "category":"Organizations",
            "subcategory":"Religious Organization",
            "type":"Services"
        }
    ],
    "sg:phone":"+1 601 947 6158",
    "sg:postcode":"39452",
    "sg:province":"MS",
    "wof:name":"New Testament Church of God",
    "wof:placetype":"venue"
},
  "geometry": {"coordinates":[-88.597934,30.916359],"type":"Point"}
}