{
  "type": "Feature",
  "properties": {
    "addr:full":"423 Church St Hattiesburg MS 39452",
    "addr:housenumber":"423",
    "addr:postcode":"39452",
    "addr:street":"Church St",
    "iso:country":"US",
    "sg:address":"423 Church St",
    "sg:city":"Hattiesburg",
    "sg:classifiers":[
        {
            "category":"Government",
            "subcategory":"Post Office",
            "type":"Public Place"
        }
    ],
    "sg:phone":"+1 601 582 1819",
    "sg:postcode":"39452",
    "sg:province":"MS",
    "sg:tags":[
        "s",
        "postal",
        "u"
    ],
    "wof:name":"US Post Office",
    "wof:placetype":"venue"
},
  "geometry": {"coordinates":[-88.595387,30.919139],"type":"Point"}
}