{
  "type": "Feature",
  "properties": {
    "iso:country":"US",
    "sg:address":"318 E 18th St",
    "sg:city":"Laurel",
    "sg:classifiers":[
        {
            "category":"Banks & Credit Unions",
            "subcategory":"Bank",
            "type":"Services"
        }
    ],
    "sg:phone":"+1 601 399 0618",
    "sg:postcode":"39440",
    "sg:province":"MS",
    "sg:tags":[
        "loan",
        "real estate"
    ],
    "wof:name":"Premier Loan Svc Inc",
    "wof:placetype":"venue"
},
  "geometry": {"coordinates":[-89.122806,31.711273],"type":"Point"}
}