{
  "type": "Feature",
  "properties": {
    "iso:country":"US",
    "sg:address":"601 25th Ave",
    "sg:city":"Meridian",
    "sg:classifiers":[
        {
            "category":"Manufacturing",
            "subcategory":"Paper Products",
            "type":"Manufacturing & Wholesale Goods"
        }
    ],
    "sg:phone":"+1 601 693 1771",
    "sg:postcode":"39301",
    "sg:province":"MS",
    "sg:tags":[
        "converter"
    ],
    "sg:website":"www.specialtyroll.com",
    "wof:name":"Specialty Roll Products Inc",
    "wof:placetype":"venue"
},
  "geometry": {"coordinates":[-88.703508,32.363948],"type":"Point"}
}