{
  "type": "Feature",
  "properties": {
    "addr:full":"353 Humphrey Rd Poplarville MS 39470",
    "addr:housenumber":"353",
    "addr:postcode":"39470",
    "addr:street":"Humphrey Rd",
    "iso:country":"US",
    "sg:address":"353 Humphrey Rd",
    "sg:city":"Poplarville",
    "sg:classifiers":[
        {
            "category":"Building & Trades",
            "subcategory":"Construction",
            "type":"Services"
        }
    ],
    "sg:phone":"+1 601 772 9429",
    "sg:postcode":"39470",
    "sg:province":"MS",
    "sg:tags":[
        "contractor"
    ],
    "wof:name":"Playtime Pools",
    "wof:placetype":"venue"
},
  "geometry": {"coordinates":[-89.739699,30.832297],"type":"Point"}
}