{
  "type": "Feature",
  "properties": {
    "iso:country":"US",
    "sg:address":"5384 Haynes Dr",
    "sg:city":"Horn Lake",
    "sg:classifiers":[
        {
            "category":"Freight",
            "type":"Transportation"
        }
    ],
    "sg:phone":"+1 662 781 0984",
    "sg:postcode":"38637",
    "sg:province":"MS",
    "sg:tags":[
        "operator",
        "local",
        "trucking"
    ],
    "wof:name":"Hibbler Trucking",
    "wof:placetype":"venue"
},
  "geometry": {"coordinates":[-90.08513000000001,34.947149],"type":"Point"}
}