{
  "type": "Feature",
  "properties": {
    "addr:full":"481 US Hwy 90 Waveland MS 39576",
    "addr:housenumber":"481",
    "addr:postcode":"39576",
    "addr:street":"Us Hwy 90",
    "iso:country":"US",
    "sg:address":"481 US Hwy 90",
    "sg:city":"Waveland",
    "sg:classifiers":[
        {
            "category":"Banks & Credit Unions",
            "subcategory":"Bank",
            "type":"Services"
        }
    ],
    "sg:phone":"+1 228 463 9465",
    "sg:postcode":"39576",
    "sg:province":"MS",
    "sg:tags":[
        "federally",
        "chartered"
    ],
    "sg:website":"www.kfc.org",
    "wof:name":"Keesler Federal Credit Union",
    "wof:placetype":"venue"
},
  "geometry": {"coordinates":[-89.384912,30.303727],"type":"Point"}
}