{
  "type": "Feature",
  "properties": {
    "iso:country":"US",
    "sg:address":"211 W Main St",
    "sg:city":"Okolona",
    "sg:classifiers":[
        {
            "category":"Personal",
            "subcategory":"Beauty Salon",
            "type":"Services"
        }
    ],
    "sg:phone":"+1 662 447 2558",
    "sg:postcode":"38860",
    "sg:province":"MS",
    "sg:tags":[
        "shop"
    ],
    "wof:name":"Craigs Kurl & Post",
    "wof:placetype":"venue"
},
  "geometry": {"coordinates":[-88.748012,34.004216],"type":"Point"}
}