{
  "type": "Feature",
  "properties": {
    "iso:country":"US",
    "sg:address":"5006 Rollingwood Estates Dr",
    "sg:city":"Vicksburg",
    "sg:classifiers":[
        {
            "category":"Professional",
            "type":"Services"
        },
        {
            "category":"Professional",
            "subcategory":"Business Services",
            "type":"Services"
        }
    ],
    "sg:phone":"+1 601 259 4487",
    "sg:postcode":"39180",
    "sg:province":"MS",
    "sg:tags":[
        "establishment"
    ],
    "wof:name":"A Twj Group LLC",
    "wof:placetype":"venue"
},
  "geometry": {"coordinates":[-90.837317,32.293372],"type":"Point"}
}