{
  "type": "Feature",
  "properties": {
    "iso:country":"US",
    "sg:address":"9974 Lizelia Rd",
    "sg:city":"Meridian",
    "sg:classifiers":[
        {
            "category":"Autos & Motor Vehicles",
            "subcategory":"Motorcycle Sales",
            "type":"Retail Goods"
        }
    ],
    "sg:phone":"+1 601 679 7479",
    "sg:postcode":"39305",
    "sg:province":"MS",
    "sg:tags":[
        "car",
        "golf",
        "cart"
    ],
    "wof:name":"Clayton's Golf Carts Sales",
    "wof:placetype":"venue"
},
  "geometry": {"coordinates":[-88.63011899999999,32.532998],"type":"Point"}
}