{
  "type": "Feature",
  "properties": {
    "addr:full":"1556 Old Highway 61 S Tunica MS 38676",
    "addr:housenumber":"1556",
    "addr:postcode":"38676",
    "addr:street":"Old Highway 61 S Tunica",
    "iso:country":"US",
    "sg:address":"1556 Old Highway 61 S",
    "sg:city":"Tunica",
    "sg:classifiers":[
        {
            "category":"Shopping",
            "subcategory":"Antiques",
            "type":"Retail Goods"
        }
    ],
    "sg:phone":"+1 662 363 2565",
    "sg:postcode":"38676",
    "sg:province":"MS",
    "wof:name":"Main Street Market",
    "wof:placetype":"venue"
},
  "geometry": {"coordinates":[-90.38481899999999,34.67543],"type":"Point"}
}