{
  "type": "Feature",
  "properties": {
    "iso:country":"US",
    "sg:address":"108 W 7th Ave",
    "sg:city":"Petal",
    "sg:classifiers":[
        {
            "category":"Building & Trades",
            "subcategory":"Construction",
            "type":"Services"
        }
    ],
    "sg:phone":"+1 601 583 8344",
    "sg:postcode":"39465",
    "sg:province":"MS",
    "sg:tags":[
        "material",
        "contractor"
    ],
    "wof:name":"Palmer Fence Co",
    "wof:placetype":"venue"
},
  "geometry": {"coordinates":[-89.264273,31.339366],"type":"Point"}
}