{
  "type": "Feature",
  "properties": {
    "addr:full":"1211 Bayou Dr Indianola MS 38751",
    "addr:housenumber":"1211",
    "addr:postcode":"38751",
    "addr:street":"Bayou Dr",
    "iso:country":"US",
    "sg:address":"1211 Bayou Dr",
    "sg:city":"Indianola",
    "sg:classifiers":[
        {
            "category":"Professional",
            "subcategory":"Business Services",
            "type":"Services"
        }
    ],
    "sg:phone":"+1 662 887 2445",
    "sg:postcode":"38751",
    "sg:province":"MS",
    "wof:name":"Little Designs",
    "wof:placetype":"venue"
},
  "geometry": {"coordinates":[-90.627182,33.453935],"type":"Point"}
}