{
  "type": "Feature",
  "properties": {
    "iso:country":"US",
    "sg:address":"1691 Dancy Blvd",
    "sg:city":"Horn Lake",
    "sg:classifiers":[
        {
            "category":"Home & Garden",
            "subcategory":"Garden Supply",
            "type":"Retail Goods"
        }
    ],
    "sg:phone":"+1 662 342 5406",
    "sg:postcode":"38637",
    "sg:province":"MS",
    "sg:tags":[
        "engine"
    ],
    "wof:name":"Miller's Small Engines",
    "wof:placetype":"venue"
},
  "geometry": {"coordinates":[-90.021683,34.959985],"type":"Point"}
}