{
  "type": "Feature",
  "properties": {
    "iso:country":"US",
    "sg:address":"9160 Ashbury Ln",
    "sg:city":"Gulfport",
    "sg:classifiers":[
        {
            "category":"Building & Trades",
            "subcategory":"Construction",
            "type":"Services"
        }
    ],
    "sg:phone":"+1 228 896 1941",
    "sg:postcode":"39503",
    "sg:province":"MS",
    "sg:tags":[
        "house"
    ],
    "wof:name":"Dream Maker Homes LLC",
    "wof:placetype":"venue"
},
  "geometry": {"coordinates":[-89.03191,30.416766],"type":"Point"}
}