{
  "type": "Feature",
  "properties": {
    "addr:full":"274 Co Rd 215 University MS 38683",
    "addr:housenumber":"274;215",
    "addr:postcode":"38683",
    "addr:street":"Co Rd",
    "iso:country":"US",
    "sg:address":"274 Co Rd 215",
    "sg:city":"University",
    "sg:classifiers":[
        {
            "category":"Organizations",
            "subcategory":"Religious Organization",
            "type":"Services"
        }
    ],
    "sg:phone":"+1 662 232 8670",
    "sg:postcode":"38683",
    "sg:province":"MS",
    "sg:tags":[
        "church"
    ],
    "wof:name":"East St Peter Missionary Chr",
    "wof:placetype":"venue"
},
  "geometry": {"coordinates":[-88.894515,34.931206],"type":"Point"}
}