{
  "type": "Feature",
  "properties": {
    "iso:country":"US",
    "sg:address":"2112 Grenada Blvd",
    "sg:city":"Greenwood",
    "sg:classifiers":[
        {
            "category":"Food & Beverages",
            "subcategory":"Groceries & Convenience Stores",
            "type":"Retail Goods"
        }
    ],
    "sg:phone":"+1 662 453 3215",
    "sg:postcode":"38930",
    "sg:province":"MS",
    "wof:name":"Short Stop Inc",
    "wof:placetype":"venue"
},
  "geometry": {"coordinates":[-90.155845,33.522039],"type":"Point"}
}