{
  "type": "Feature",
  "properties": {
    "iso:country":"US",
    "sg:address":"511 Hathaway Dr",
    "sg:city":"Clinton",
    "sg:classifiers":[
        {
            "category":"Organizations",
            "subcategory":"Religious Organization",
            "type":"Services"
        }
    ],
    "sg:phone":"+1 601 924 6512",
    "sg:postcode":"39056",
    "sg:province":"MS",
    "wof:name":"Success Ministries",
    "wof:placetype":"venue"
},
  "geometry": {"coordinates":[-90.302173,32.329813],"type":"Point"}
}