{
  "type": "Feature",
  "properties": {
    "addr:full":"6241 Moreton Pl Ocean Springs MS 39564",
    "addr:housenumber":"6241",
    "addr:postcode":"39564",
    "addr:street":"Moreton Pl",
    "iso:country":"US",
    "sg:address":"6241 Moreton Pl",
    "sg:city":"Ocean Springs",
    "sg:classifiers":[
        {
            "category":"Building & Trades",
            "subcategory":"Construction",
            "type":"Services"
        }
    ],
    "sg:phone":"+1 228 872 8119",
    "sg:postcode":"39564",
    "sg:province":"MS",
    "sg:tags":[
        "house"
    ],
    "wof:name":"Afforfable Contractor Inc",
    "wof:placetype":"venue"
},
  "geometry": {"coordinates":[-88.814334,30.430819],"type":"Point"}
}