{
  "type": "Feature",
  "properties": {
    "iso:country":"US",
    "sg:address":"109 Bailey Ave",
    "sg:city":"Coffeeville",
    "sg:classifiers":[
        {
            "category":"Organizations",
            "subcategory":"Religious Organization",
            "type":"Services"
        }
    ],
    "sg:phone":"+1 662 675 8878",
    "sg:postcode":"38922",
    "sg:province":"MS",
    "sg:tags":[
        "church"
    ],
    "wof:name":"Coffeeville Church Of Christ",
    "wof:placetype":"venue"
},
  "geometry": {"coordinates":[-89.673789,33.980949],"type":"Point"}
}