{
  "type": "Feature",
  "properties": {
    "iso:country":"US",
    "sg:address":"600 US Hwy 51",
    "sg:city":"Ridgeland",
    "sg:classifiers":[
        {
            "category":"Retail",
            "subcategory":"Laundry & Dry Cleaning",
            "type":"Services"
        }
    ],
    "sg:phone":"+1 601 856 3581",
    "sg:postcode":"39157",
    "sg:province":"MS",
    "wof:name":"Sew Simple",
    "wof:placetype":"venue"
},
  "geometry": {"coordinates":[-90.12815399999999,32.429523],"type":"Point"}
}