{
  "type": "Feature",
  "properties": {
    "addr:full":"100 G T Thames Dr Starkville MS 39759",
    "addr:housenumber":"100",
    "addr:postcode":"39759",
    "addr:street":"G T Thames Dr",
    "iso:country":"US",
    "sg:address":"100 G T Thames Dr",
    "sg:city":"Starkville",
    "sg:classifiers":[
        {
            "category":"Health Services",
            "subcategory":"Doctor",
            "type":"Services"
        }
    ],
    "sg:phone":"+1 662 324 0700",
    "sg:postcode":"39759",
    "sg:province":"MS",
    "sg:tags":[
        "dentist"
    ],
    "wof:name":"Golden Triangle Dental Ctr",
    "wof:placetype":"venue"
},
  "geometry": {"coordinates":[-88.84809199999999,33.45001],"type":"Point"}
}