{
  "type": "Feature",
  "properties": {
    "addr:full":"102 Walthall St Greenwood MS 38930",
    "addr:housenumber":"102",
    "addr:postcode":"38930",
    "addr:street":"Walthall St",
    "iso:country":"US",
    "sg:address":"102 Walthall St",
    "sg:city":"Greenwood",
    "sg:classifiers":[
        {
            "category":"Shopping",
            "subcategory":"Used Merchandise",
            "type":"Retail Goods"
        }
    ],
    "sg:phone":"+1 662 453 5070",
    "sg:postcode":"38930",
    "sg:province":"MS",
    "sg:tags":[
        "antique"
    ],
    "wof:name":"Port Eliot",
    "wof:placetype":"venue"
},
  "geometry": {"coordinates":[-90.180592,33.521393],"type":"Point"}
}