{
  "type": "Feature",
  "properties": {
    "iso:country":"US",
    "sg:address":"105 Summer Ridge Dr",
    "sg:city":"Jackson",
    "sg:classifiers":[
        {
            "category":"Manufacturing",
            "subcategory":"Signs",
            "type":"Manufacturing & Wholesale Goods"
        },
        {
            "category":"Professional",
            "subcategory":"Business Services",
            "type":"Services"
        }
    ],
    "sg:phone":"+1 601 939 0586",
    "sg:postcode":"39208",
    "sg:province":"MS",
    "sg:tags":[
        "specialty",
        "mfg"
    ],
    "wof:name":"Outdoor Graphics Inc",
    "wof:placetype":"venue"
},
  "geometry": {"coordinates":[-90.048057,32.308066],"type":"Point"}
}