{
  "type": "Feature",
  "properties": {
    "iso:country":"US",
    "sg:address":"203 E College St",
    "sg:city":"Louisville",
    "sg:classifiers":[
        {
            "category":"Retail",
            "subcategory":"Self-service Laundry",
            "type":"Services"
        }
    ],
    "sg:phone":"+1 662 773 7715",
    "sg:postcode":"39339",
    "sg:province":"MS",
    "wof:name":"Sunshine Center",
    "wof:placetype":"venue"
},
  "geometry": {"coordinates":[-89.050675,33.126255],"type":"Point"}
}