{
  "type": "Feature",
  "properties": {
    "iso:country":"US",
    "sg:address":"50 Sunline Dr",
    "sg:city":"Brandon",
    "sg:classifiers":[
        {
            "category":"Wholesale",
            "subcategory":"Durable Goods & Equipment",
            "type":"Manufacturing & Wholesale Goods"
        }
    ],
    "sg:phone":"+1 601 825 3686",
    "sg:postcode":"39042",
    "sg:province":"MS",
    "sg:tags":[
        "representative",
        "manufacturer"
    ],
    "wof:name":"Burgess Sales",
    "wof:placetype":"venue"
},
  "geometry": {"coordinates":[-90.01666899999999,32.291919],"type":"Point"}
}