{
  "type": "Feature",
  "properties": {
    "iso:country":"US",
    "sg:address":"605 S 2nd Ave",
    "sg:city":"Columbus",
    "sg:classifiers":[
        {
            "category":"Professional",
            "subcategory":"Management & Consulting",
            "type":"Services"
        }
    ],
    "sg:phone":"+1 662 241 5666",
    "sg:postcode":"39701",
    "sg:province":"MS",
    "sg:tags":[
        "consultant",
        "business"
    ],
    "wof:name":"Ray Y Gildea Jr",
    "wof:placetype":"venue"
},
  "geometry": {"coordinates":[-88.425494,33.494366],"type":"Point"}
}