{
  "type": "Feature",
  "properties": {
    "addr:full":"1703 Old Mobile Ave Pascagoula MS 39567",
    "addr:housenumber":"1703",
    "addr:postcode":"39567",
    "addr:street":"Old Mobile Ave",
    "iso:country":"US",
    "sg:address":"1703 Old Mobile Ave",
    "sg:city":"Pascagoula",
    "sg:classifiers":[
        {
            "category":"Professional",
            "subcategory":"Employment Agencies",
            "type":"Services"
        }
    ],
    "sg:phone":"+1 228 762 9899",
    "sg:postcode":"39567",
    "sg:province":"MS",
    "sg:tags":[
        "opportunity"
    ],
    "wof:name":"Global Employment Svc",
    "wof:placetype":"venue"
},
  "geometry": {"coordinates":[-88.54427800000001,30.366605],"type":"Point"}
}