{
  "type": "Feature",
  "properties": {
    "iso:country":"US",
    "sg:address":"6908 Hwy 50 E",
    "sg:city":"Columbus",
    "sg:classifiers":[
        {
            "category":"Building & Trades",
            "subcategory":"Construction",
            "type":"Services"
        }
    ],
    "sg:phone":"+1 662 328 8521",
    "sg:postcode":"39702",
    "sg:province":"MS",
    "sg:tags":[
        "painter"
    ],
    "wof:name":"Williams Decorating Svc",
    "wof:placetype":"venue"
},
  "geometry": {"coordinates":[-88.30102100000001,33.534983],"type":"Point"}
}