{
  "type": "Feature",
  "properties": {
    "iso:country":"US",
    "sg:address":"120 Byram Dr",
    "sg:city":"Byram",
    "sg:classifiers":[
        {
            "category":"Freight",
            "type":"Transportation"
        }
    ],
    "sg:phone":"+1 601 373 0052",
    "sg:postcode":"39272",
    "sg:province":"MS",
    "sg:tags":[
        "warehouse"
    ],
    "wof:name":"Byram U Store Mini Warehouse",
    "wof:placetype":"venue"
},
  "geometry": {"coordinates":[-90.23049899999999,32.251219],"type":"Point"}
}