{
  "type": "Feature",
  "properties": {
    "iso:country":"US",
    "sg:address":"11475 Hwy 346",
    "sg:city":"Thaxton",
    "sg:classifiers":[
        {
            "category":"Real Estate",
            "subcategory":"Real Estate Operator",
            "type":"Services"
        }
    ],
    "sg:phone":"+1 662 489 2990",
    "sg:postcode":"38871",
    "sg:province":"MS",
    "sg:tags":[
        "property",
        "lessor"
    ],
    "wof:name":"Sunnett Stone",
    "wof:placetype":"venue"
},
  "geometry": {"coordinates":[-89.214826,34.338939],"type":"Point"}
}