{
  "type": "Feature",
  "properties": {
    "iso:country":"US",
    "sg:address":"172 W Santa Clair St",
    "sg:city":"Jackson",
    "sg:classifiers":[
        {
            "category":"Wholesale",
            "subcategory":"Machinery & Supplies",
            "type":"Manufacturing & Wholesale Goods"
        }
    ],
    "sg:phone":"+1 601 372 7233",
    "sg:postcode":"39212",
    "sg:province":"MS",
    "sg:tags":[
        "equipment",
        "establishment"
    ],
    "wof:name":"Rives Carpet Service",
    "wof:placetype":"venue"
},
  "geometry": {"coordinates":[-90.223574,32.260437],"type":"Point"}
}