{
  "type": "Feature",
  "properties": {
    "iso:country":"US",
    "sg:address":"109 Victor Rd",
    "sg:city":"Columbus",
    "sg:classifiers":[
        {
            "category":"Building & Trades",
            "subcategory":"Electrical",
            "type":"Services"
        }
    ],
    "sg:phone":"+1 662 434 6460",
    "sg:postcode":"39705",
    "sg:province":"MS",
    "sg:tags":[
        "electrical",
        "gen",
        "contractor"
    ],
    "wof:name":"Raymond Griffin Construction",
    "wof:placetype":"venue"
},
  "geometry": {"coordinates":[-88.42957699999999,33.604339],"type":"Point"}
}