{
  "type": "Feature",
  "properties": {
    "addr:full":"128 S 11th Ave Laurel MS 39440",
    "addr:housenumber":"128",
    "addr:postcode":"39440",
    "addr:street":"S 11Th Ave",
    "iso:country":"US",
    "sg:address":"128 S 11th Ave",
    "sg:city":"Laurel",
    "sg:classifiers":[
        {
            "category":"Health Services",
            "subcategory":"Doctor",
            "type":"Services"
        }
    ],
    "sg:phone":"+1 601 649 8732",
    "sg:postcode":"39440",
    "sg:province":"MS",
    "sg:tags":[
        "clinic"
    ],
    "wof:name":"Laurel Ent Surgical Clinic",
    "wof:placetype":"venue"
},
  "geometry": {"coordinates":[-89.140055,31.689174],"type":"Point"}
}