{
  "type": "Feature",
  "properties": {
    "iso:country":"US",
    "sg:address":"2893 State Hwy 178",
    "sg:city":"Holly Springs",
    "sg:classifiers":[
        {
            "category":"Shopping",
            "subcategory":"Clothing, Apparel, & Fashions",
            "type":"Retail Goods"
        }
    ],
    "sg:phone":"+1 662 252 1382",
    "sg:postcode":"38635",
    "sg:province":"MS",
    "sg:tags":[
        "some"
    ],
    "wof:name":"Sir Everett Cross Designs",
    "wof:placetype":"venue"
},
  "geometry": {"coordinates":[-89.519685,34.812337],"type":"Point"}
}