{
  "type": "Feature",
  "properties": {
    "iso:country":"US",
    "sg:address":"326 East St",
    "sg:city":"Macon",
    "sg:classifiers":[
        {
            "category":"Organizations",
            "subcategory":"Religious Organization",
            "type":"Services"
        }
    ],
    "sg:phone":"+1 601 687 6979",
    "sg:postcode":"39341",
    "sg:province":"MS",
    "sg:tags":[
        "church"
    ],
    "wof:name":"Congregation Church Of God",
    "wof:placetype":"venue"
},
  "geometry": {"coordinates":[-88.55787599999999,33.106597],"type":"Point"}
}