{
  "type": "Feature",
  "properties": {
    "iso:country":"US",
    "sg:address":"501 26th St",
    "sg:city":"Gulfport",
    "sg:classifiers":[
        {
            "category":"Social Services",
            "type":"Services"
        }
    ],
    "sg:phone":"+1 228 868 5762",
    "sg:postcode":"39507",
    "sg:province":"MS",
    "sg:tags":[
        "executive"
    ],
    "wof:name":"Katie Ptterson Booth Cmnty Ctr",
    "wof:placetype":"venue"
},
  "geometry": {"coordinates":[-89.05919799999999,30.382831],"type":"Point"}
}