{
  "type": "Feature",
  "properties": {
    "iso:country":"US",
    "sg:address":"826 Shell St",
    "sg:city":"Tupelo",
    "sg:classifiers":[
        {
            "category":"Building & Trades",
            "subcategory":"Construction",
            "type":"Services"
        }
    ],
    "sg:phone":"+1 662 690 6502",
    "sg:postcode":"38801",
    "sg:province":"MS",
    "sg:tags":[
        "fire",
        "restoration",
        "damage"
    ],
    "wof:name":"Servpro Of Tupelo",
    "wof:placetype":"venue"
},
  "geometry": {"coordinates":[-88.72127500000001,34.215704],"type":"Point"}
}