{
  "type": "Feature",
  "properties": {
    "iso:country":"US",
    "sg:address":"1835 Nelle St",
    "sg:city":"Tupelo",
    "sg:classifiers":[
        {
            "category":"Professional",
            "subcategory":"Business Services",
            "type":"Services"
        }
    ],
    "sg:phone":"+1 662 841 7858",
    "sg:postcode":"38801",
    "sg:province":"MS",
    "sg:tags":[
        "event"
    ],
    "wof:name":"Resource Marketing Inc",
    "wof:placetype":"venue"
},
  "geometry": {"coordinates":[-88.732518,34.259391],"type":"Point"}
}