{
  "type": "Feature",
  "properties": {
    "iso:country":"US",
    "sg:address":"105 Hwy 6 W",
    "sg:city":"Batesville",
    "sg:classifiers":[
        {
            "category":"Food & Beverages",
            "subcategory":"Groceries & Convenience Stores",
            "type":"Retail Goods"
        }
    ],
    "sg:phone":"+1 662 563 0338",
    "sg:postcode":"38606",
    "sg:province":"MS",
    "sg:tags":[
        "station",
        "gasoline"
    ],
    "wof:name":"Exxon",
    "wof:placetype":"venue"
},
  "geometry": {"coordinates":[-89.945099,34.311461],"type":"Point"}
}