{
  "type": "Feature",
  "properties": {
    "iso:country":"US",
    "sg:address":"2207 Hardy St",
    "sg:city":"Hattiesburg",
    "sg:classifiers":[
        {
            "category":"Health Services",
            "subcategory":"Clinic",
            "type":"Services"
        }
    ],
    "sg:phone":"+1 601 583 4327",
    "sg:postcode":"39401",
    "sg:province":"MS",
    "wof:name":"Audiology & Speech Assoc",
    "wof:placetype":"venue"
},
  "geometry": {"coordinates":[-89.325131,31.324764],"type":"Point"}
}