{
  "type": "Feature",
  "properties": {
    "addr:full":"315 E 4th St Long Beach MS 39560",
    "addr:housenumber":"315",
    "addr:postcode":"39560",
    "addr:street":"E 4Th St",
    "iso:country":"US",
    "sg:address":"315 E 4th St",
    "sg:city":"Long Beach",
    "sg:classifiers":[
        {
            "category":"Building & Trades",
            "subcategory":"Construction",
            "type":"Services"
        }
    ],
    "sg:phone":"+1 228 868 2267",
    "sg:postcode":"39560",
    "sg:province":"MS",
    "sg:tags":[
        "paving",
        "contractor"
    ],
    "wof:name":"Asphalt Maintenance Inc",
    "wof:placetype":"venue"
},
  "geometry": {"coordinates":[-89.142616,30.349927],"type":"Point"}
}