{
  "type": "Feature",
  "properties": {
    "addr:full":"154 Industrial Park Rd Lucedale MS 39452",
    "addr:housenumber":"154",
    "addr:postcode":"39452",
    "addr:street":"Industrial Park Rd",
    "iso:country":"US",
    "sg:address":"154 Industrial Park Rd",
    "sg:city":"Lucedale",
    "sg:classifiers":[
        {
            "category":"Government",
            "subcategory":"Jail",
            "type":"Public Place"
        }
    ],
    "sg:phone":"+1 601 947 9399",
    "sg:postcode":"39452",
    "sg:province":"MS",
    "sg:tags":[
        "correctional",
        "facility"
    ],
    "wof:name":"Regional Correctional Facility",
    "wof:placetype":"venue"
},
  "geometry": {"coordinates":[-88.587868,30.928936],"type":"Point"}
}