{
  "type": "Feature",
  "properties": {
    "addr:full":"112 Coachmans Rd Madison MS 39110",
    "addr:housenumber":"112",
    "addr:postcode":"39110",
    "addr:street":"Coachmans Rd",
    "iso:country":"US",
    "sg:address":"112 Coachmans Rd",
    "sg:city":"Madison",
    "sg:classifiers":[
        {
            "category":"Real Estate",
            "subcategory":"Real Estate Operator",
            "type":"Services"
        }
    ],
    "sg:phone":"+1 601 856 6249",
    "sg:postcode":"39110",
    "sg:province":"MS",
    "sg:tags":[
        "building",
        "nonresidential"
    ],
    "wof:name":"Jay Management Inc",
    "wof:placetype":"venue"
},
  "geometry": {"coordinates":[-90.073443,32.434725],"type":"Point"}
}