{
  "type": "Feature",
  "properties": {
    "iso:country":"US",
    "sg:address":"1533 Baldwin Ferry Rd",
    "sg:city":"Vicksburg",
    "sg:classifiers":[
        {
            "category":"Education",
            "subcategory":"School",
            "type":"Public Place"
        }
    ],
    "sg:phone":"+1 601 636 1966",
    "sg:postcode":"39180",
    "sg:province":"MS",
    "wof:name":"Vicksburg Junior High School",
    "wof:placetype":"venue"
},
  "geometry": {"coordinates":[-90.871347,32.345005],"type":"Point"}
}