{
  "type": "Feature",
  "properties": {
    "iso:country":"US",
    "sg:address":"308 Magnolia St",
    "sg:city":"Philadelphia",
    "sg:classifiers":[
        {
            "category":"Manufacturing",
            "subcategory":"Lumber",
            "type":"Manufacturing & Wholesale Goods"
        }
    ],
    "sg:phone":"+1 601 656 4041",
    "sg:postcode":"39350",
    "sg:province":"MS",
    "sg:tags":[
        "operation",
        "timber",
        "tract"
    ],
    "wof:name":"J E Pope L P",
    "wof:placetype":"venue"
},
  "geometry": {"coordinates":[-89.105093,32.785262],"type":"Point"}
}