{
  "type": "Feature",
  "properties": {
    "iso:country":"US",
    "sg:address":"303 Court St",
    "sg:city":"Vaiden",
    "sg:classifiers":[
        {
            "category":"Real Estate",
            "subcategory":"Real Estate Operator",
            "type":"Services"
        }
    ],
    "sg:phone":"+1 662 464 5655",
    "sg:postcode":"39176",
    "sg:province":"MS",
    "sg:tags":[
        "apartment"
    ],
    "wof:name":"Poplar Manor",
    "wof:placetype":"venue"
},
  "geometry": {"coordinates":[-89.739858,33.330345],"type":"Point"}
}