{
  "type": "Feature",
  "properties": {
    "iso:country":"US",
    "sg:address":"1882 Hwy 471",
    "sg:city":"Brandon",
    "sg:classifiers":[
        {
            "category":"Retail",
            "subcategory":"Auto Repair",
            "type":"Services"
        }
    ],
    "sg:phone":"+1 601 829 9185",
    "sg:postcode":"39047",
    "sg:province":"MS",
    "sg:tags":[
        "body",
        "automobile",
        "painting"
    ],
    "wof:name":"Precision Collision Repair",
    "wof:placetype":"venue"
},
  "geometry": {"coordinates":[-89.9665,32.368611],"type":"Point"}
}