{
  "type": "Feature",
  "properties": {
    "iso:country":"US",
    "sg:address":"701 N Davis Ave",
    "sg:city":"Cleveland",
    "sg:classifiers":[
        {
            "category":"Home & Garden",
            "subcategory":"Furniture",
            "type":"Retail Goods"
        }
    ],
    "sg:phone":"+1 662 843 2946",
    "sg:postcode":"38732",
    "sg:province":"MS",
    "wof:name":"Hollowell Furniture-Cleveland",
    "wof:placetype":"venue"
},
  "geometry": {"coordinates":[-90.71583099999999,33.75604],"type":"Point"}
}