{
  "type": "Feature",
  "properties": {
    "addr:full":"348 1st St Flora MS 39071",
    "addr:housenumber":"348",
    "addr:postcode":"39071",
    "addr:street":"1St St",
    "iso:country":"US",
    "sg:address":"348 1st St",
    "sg:city":"Flora",
    "sg:classifiers":[
        {
            "category":"Building & Trades",
            "subcategory":"Construction",
            "type":"Services"
        }
    ],
    "sg:phone":"+1 601 879 8207",
    "sg:postcode":"39071",
    "sg:province":"MS",
    "sg:tags":[
        "general",
        "contractor"
    ],
    "wof:name":"Dunlap Construction",
    "wof:placetype":"venue"
},
  "geometry": {"coordinates":[-90.31291899999999,32.543363],"type":"Point"}
}