{
  "type": "Feature",
  "properties": {
    "addr:full":"115 Richardson Rd Louisville MS 39339",
    "addr:housenumber":"115",
    "addr:postcode":"39339",
    "addr:street":"Richardson Rd",
    "iso:country":"US",
    "sg:address":"115 Richardson Rd",
    "sg:city":"Louisville",
    "sg:classifiers":[
        {
            "category":"Organizations",
            "subcategory":"Religious Organization",
            "type":"Services"
        }
    ],
    "sg:phone":"+1 662 773 9228",
    "sg:postcode":"39339",
    "sg:province":"MS",
    "wof:name":"Mike Allday",
    "wof:placetype":"venue"
},
  "geometry": {"coordinates":[-89.04257200000001,33.139149],"type":"Point"}
}