{
  "type": "Feature",
  "properties": {
    "addr:full":"210 Maudedith Ln Clinton MS 39056",
    "addr:housenumber":"210",
    "addr:postcode":"39056",
    "addr:street":"Maudedith Ln",
    "iso:country":"US",
    "sg:address":"210 Maudedith Ln",
    "sg:city":"Clinton",
    "sg:classifiers":[
        {
            "category":"Shopping",
            "type":"Retail Goods"
        }
    ],
    "sg:phone":"+1 601 924 4184",
    "sg:postcode":"39056",
    "sg:province":"MS",
    "sg:tags":[
        "a",
        "lock",
        "alarm",
        "safe",
        "operates",
        "as",
        "key"
    ],
    "wof:name":"Mississippi Safe and Lock Inc",
    "wof:placetype":"venue"
},
  "geometry": {"coordinates":[-90.338292,32.341502],"type":"Point"}
}