{
  "type": "Feature",
  "properties": {
    "iso:country":"US",
    "sg:address":"100 Airport Rd",
    "sg:city":"Marks",
    "sg:classifiers":[
        {
            "category":"Government",
            "subcategory":"Office",
            "type":"Public Place"
        }
    ],
    "sg:phone":"+1 662 326 8587",
    "sg:postcode":"38663",
    "sg:province":"MS",
    "wof:name":"Road Shop",
    "wof:placetype":"venue"
},
  "geometry": {"coordinates":[-89.013042,34.730977],"type":"Point"}
}