{
  "type": "Feature",
  "properties": {
    "addr:full":"7895 Highway 51 N Southaven MS 38671",
    "addr:housenumber":"7895",
    "addr:postcode":"38671",
    "addr:street":"Highway 51 N",
    "iso:country":"US",
    "sg:address":"7895 Highway 51 N",
    "sg:city":"Southaven",
    "sg:classifiers":[
        {
            "category":"Utilities",
            "subcategory":"Natural Gas",
            "type":"Services"
        }
    ],
    "sg:phone":"+1 601 342 9852",
    "sg:postcode":"38671",
    "sg:province":"MS",
    "wof:name":"Atmos Energy Corp",
    "wof:placetype":"venue"
},
  "geometry": {"coordinates":[-90.01600000000001,34.975602],"type":"Point"}
}