{
  "type": "Feature",
  "properties": {
    "iso:country":"US",
    "sg:address":"5185 Nail Rd",
    "sg:city":"Olive Branch",
    "sg:classifiers":[
        {
            "category":"Professional",
            "subcategory":"Management & Consulting",
            "type":"Services"
        }
    ],
    "sg:phone":"+1 662 895 6738",
    "sg:postcode":"38654",
    "sg:province":"MS",
    "wof:name":"Comprehensive Health Care Inc",
    "wof:placetype":"venue"
},
  "geometry": {"coordinates":[-89.896973,34.947755],"type":"Point"}
}