{
  "type": "Feature",
  "properties": {
    "iso:country":"US",
    "sg:address":"15317 Parkwood Dr N",
    "sg:city":"Gulfport",
    "sg:classifiers":[
        {
            "category":"Retail",
            "subcategory":"Auto Repair",
            "type":"Services"
        }
    ],
    "sg:phone":"+1 228 831 1620",
    "sg:postcode":"39503",
    "sg:province":"MS",
    "sg:tags":[
        "general"
    ],
    "wof:name":"Wayne Mc Queen",
    "wof:placetype":"venue"
},
  "geometry": {"coordinates":[-89.096609,30.467275],"type":"Point"}
}