{
  "type": "Feature",
  "properties": {
    "iso:country":"US",
    "sg:address":"455 Shiloh Cemetery Rd",
    "sg:city":"Mantachie",
    "sg:classifiers":[
        {
            "category":"Wholesale",
            "subcategory":"Hardware",
            "type":"Manufacturing & Wholesale Goods"
        }
    ],
    "sg:phone":"+1 662 282 7080",
    "sg:postcode":"38855",
    "sg:province":"MS",
    "sg:tags":[
        "refrigerating"
    ],
    "wof:name":"Thompson Refrigeration Svc",
    "wof:placetype":"venue"
},
  "geometry": {"coordinates":[-88.54135100000001,34.32095],"type":"Point"}
}