{
  "type": "Feature",
  "properties": {
    "addr:full":"419 Haas St Vicksburg MS 39180",
    "addr:housenumber":"419",
    "addr:postcode":"39180",
    "addr:street":"Haas St",
    "iso:country":"US",
    "sg:address":"419 Haas St",
    "sg:city":"Vicksburg",
    "sg:classifiers":[
        {
            "category":"Insurance",
            "subcategory":"Hazard Insurance",
            "type":"Services"
        }
    ],
    "sg:phone":"+1 601 636 6119",
    "sg:postcode":"39180",
    "sg:province":"MS",
    "sg:tags":[
        "bond"
    ],
    "wof:name":"Phelps Bail Bond Svc",
    "wof:placetype":"venue"
},
  "geometry": {"coordinates":[-90.87192400000001,32.32274],"type":"Point"}
}