{
  "type": "Feature",
  "properties": {
    "iso:country":"US",
    "sg:address":"544 Julienne St",
    "sg:city":"Jackson",
    "sg:classifiers":[
        {
            "category":"Building & Trades",
            "subcategory":"Construction",
            "type":"Services"
        }
    ],
    "sg:phone":"+1 601 969 7961",
    "sg:postcode":"39201",
    "sg:province":"MS",
    "sg:tags":[
        "contractor"
    ],
    "wof:name":"Mitchell Building Systems",
    "wof:placetype":"venue"
},
  "geometry": {"coordinates":[-90.194295,32.281034],"type":"Point"}
}