{
  "type": "Feature",
  "properties": {
    "addr:full":"709 Webster St Corinth MS 38834",
    "addr:housenumber":"709",
    "addr:postcode":"38834",
    "addr:street":"Webster St",
    "iso:country":"US",
    "sg:address":"709 Webster St",
    "sg:city":"Corinth",
    "sg:classifiers":[
        {
            "category":"Personal",
            "subcategory":"Beauty Salon",
            "type":"Services"
        }
    ],
    "sg:phone":"+1 662 665 0024",
    "sg:postcode":"38834",
    "sg:province":"MS",
    "sg:tags":[
        "shop"
    ],
    "wof:name":"Tangles Hair Salon",
    "wof:placetype":"venue"
},
  "geometry": {"coordinates":[-88.517174,34.936411],"type":"Point"}
}