{
  "type": "Feature",
  "properties": {
    "iso:country":"US",
    "sg:address":"714 W Bankhead St",
    "sg:city":"New Albany",
    "sg:classifiers":[
        {
            "category":"Shopping",
            "subcategory":"Clothing, Apparel, & Fashions",
            "type":"Retail Goods"
        }
    ],
    "sg:phone":"+1 662 534 5009",
    "sg:postcode":"38652",
    "sg:province":"MS",
    "sg:tags":[
        "salvage",
        "surplus",
        "merchandise"
    ],
    "wof:name":"Kim's Salvage Store",
    "wof:placetype":"venue"
},
  "geometry": {"coordinates":[-89.025487,34.50081],"type":"Point"}
}