{
  "type": "Feature",
  "properties": {
    "addr:full":"1810 Military Rd Columbus MS 39701",
    "addr:housenumber":"1810",
    "addr:postcode":"39701",
    "addr:street":"Military Rd",
    "iso:country":"US",
    "sg:address":"1810 Military Rd",
    "sg:city":"Columbus",
    "sg:classifiers":[
        {
            "category":"Wholesale",
            "subcategory":"Machinery & Supplies",
            "type":"Manufacturing & Wholesale Goods"
        }
    ],
    "sg:phone":"+1 662 327 0774",
    "sg:postcode":"39701",
    "sg:province":"MS",
    "sg:tags":[
        "equipment",
        "establishment"
    ],
    "wof:name":"2-U Beauty & Fashions",
    "wof:placetype":"venue"
},
  "geometry": {"coordinates":[-88.416774,33.515865],"type":"Point"}
}