{
  "type": "Feature",
  "properties": {
    "addr:full":"403 Security Sq Gulfport MS 39507",
    "addr:housenumber":"403",
    "addr:postcode":"39507",
    "addr:street":"Security Sq",
    "iso:country":"US",
    "sg:address":"403 Security Sq",
    "sg:city":"Gulfport",
    "sg:classifiers":[
        {
            "category":"Insurance",
            "subcategory":"Insurance Agent",
            "type":"Services"
        }
    ],
    "sg:phone":"+1 228 896 3652",
    "sg:postcode":"39507",
    "sg:province":"MS",
    "wof:name":"State Farm Insurance",
    "wof:placetype":"venue"
},
  "geometry": {"coordinates":[-89.042784,30.386589],"type":"Point"}
}