{
  "type": "Feature",
  "properties": {
    "iso:country":"US",
    "sg:address":"21 Garner Rd",
    "sg:city":"Jayess",
    "sg:classifiers":[
        {
            "category":"Building & Trades",
            "subcategory":"Plumbing",
            "type":"Services"
        }
    ],
    "sg:phone":"+1 601 249 2159",
    "sg:postcode":"39641",
    "sg:province":"MS",
    "sg:tags":[
        "septic"
    ],
    "wof:name":"Garner Septic Tank Cleaning",
    "wof:placetype":"venue"
},
  "geometry": {"coordinates":[-90.22844600000001,31.332375],"type":"Point"}
}