{
  "type": "Feature",
  "properties": {
    "iso:country":"US",
    "sg:address":"109 Pembroke Pointe Dr",
    "sg:city":"Madison",
    "sg:classifiers":[
        {
            "category":"Building & Trades",
            "subcategory":"Construction",
            "type":"Services"
        }
    ],
    "sg:phone":"+1 601 856 7404",
    "sg:postcode":"39110",
    "sg:province":"MS",
    "sg:tags":[
        "warehouse",
        "prefabricated",
        "metal",
        "contractor"
    ],
    "wof:name":"Webb Construction Co Inc",
    "wof:placetype":"venue"
},
  "geometry": {"coordinates":[-90.152687,32.562137],"type":"Point"}
}