{
  "type": "Feature",
  "properties": {
    "iso:country":"US",
    "sg:address":"201 N Castle Dr",
    "sg:city":"Madison",
    "sg:classifiers":[
        {
            "category":"Real Estate",
            "subcategory":"Real Estate Agent",
            "type":"Services"
        }
    ],
    "sg:phone":"+1 601 853 0337",
    "sg:postcode":"39110",
    "sg:province":"MS",
    "sg:tags":[
        "appraiser"
    ],
    "wof:name":"Simpson Appraisal Group",
    "wof:placetype":"venue"
},
  "geometry": {"coordinates":[-90.15349999999999,32.462156],"type":"Point"}
}