{
  "type": "Feature",
  "properties": {
    "iso:country":"US",
    "sg:address":"114 Old Mobile Hwy",
    "sg:city":"Lucedale",
    "sg:classifiers":[
        {
            "category":"Organizations",
            "subcategory":"Religious Organization",
            "type":"Services"
        }
    ],
    "sg:phone":"+1 601 947 7633",
    "sg:postcode":"39452",
    "sg:province":"MS",
    "wof:name":"Antioch Missionary Baptist",
    "wof:placetype":"venue"
},
  "geometry": {"coordinates":[-88.554175,30.931043],"type":"Point"}
}