{
  "type": "Feature",
  "properties": {
    "addr:full":"15251 Debbie Cove Gulfport MS 39503",
    "addr:housenumber":"15251",
    "addr:postcode":"39503",
    "addr:street":"Debbie Cove",
    "iso:country":"US",
    "sg:address":"15251 Debbie Cove",
    "sg:city":"Gulfport",
    "sg:classifiers":[
        {
            "category":"Shopping",
            "subcategory":"Florist",
            "type":"Retail Goods"
        }
    ],
    "sg:phone":"+1 228 328 1980",
    "sg:postcode":"39503",
    "sg:province":"MS",
    "wof:name":"Party Perfect & Balloon",
    "wof:placetype":"venue"
},
  "geometry": {"coordinates":[-89.094055,30.463818],"type":"Point"}
}