{
  "type": "Feature",
  "properties": {
    "iso:country":"US",
    "sg:address":"1911 Wall Hill Rd",
    "sg:city":"Byhalia",
    "sg:classifiers":[
        {
            "category":"Food & Beverages",
            "subcategory":"Groceries & Convenience Stores",
            "type":"Retail Goods"
        }
    ],
    "sg:phone":"+1 662 564 9922",
    "sg:postcode":"38618",
    "sg:province":"MS",
    "wof:name":"Wall Hill Grocery",
    "wof:placetype":"venue"
},
  "geometry": {"coordinates":[-89.69098,34.713367],"type":"Point"}
}