{
  "type": "Feature",
  "properties": {
    "iso:country":"US",
    "sg:address":"1915 Mission 66",
    "sg:city":"Vicksburg",
    "sg:classifiers":[
        {
            "category":"Personal",
            "subcategory":"Beauty Salon",
            "type":"Services"
        }
    ],
    "sg:phone":"+1 601 638 3951",
    "sg:postcode":"39180",
    "sg:province":"MS",
    "wof:name":"Townhouse Hair Styling Salon",
    "wof:placetype":"venue"
},
  "geometry": {"coordinates":[-90.864199,32.338133],"type":"Point"}
}