{
  "type": "Feature",
  "properties": {
    "iso:country":"US",
    "sg:address":"315 Main St",
    "sg:city":"Natchez",
    "sg:classifiers":[
        {
            "category":"Restaurant",
            "type":"Food & Drink"
        }
    ],
    "sg:phone":"+1 601 446 9922",
    "sg:postcode":"39120",
    "sg:province":"MS",
    "sg:tags":[
        "eating"
    ],
    "wof:name":"Biscuits & Blues",
    "wof:placetype":"venue"
},
  "geometry": {"coordinates":[-91.404161,31.560877],"type":"Point"}
}