{
  "type": "Feature",
  "properties": {
    "iso:country":"US",
    "sg:address":"404 9th Ave S",
    "sg:city":"Amory",
    "sg:classifiers":[
        {
            "category":"Health Services",
            "subcategory":"Doctor",
            "type":"Services"
        }
    ],
    "sg:phone":"+1 662 257 9106",
    "sg:postcode":"38821",
    "sg:province":"MS",
    "sg:tags":[
        "physician",
        "surgeon"
    ],
    "wof:name":"Golden Triangle Neurology Clnc",
    "wof:placetype":"venue"
},
  "geometry": {"coordinates":[-88.478774,33.977533],"type":"Point"}
}