{
  "type": "Feature",
  "properties": {
    "iso:country":"US",
    "sg:address":"45 W Long St",
    "sg:city":"Abbeville",
    "sg:classifiers":[
        {
            "category":"Wholesale",
            "subcategory":"Construction Materials",
            "type":"Manufacturing & Wholesale Goods"
        },
        {
            "category":"Manufacturing",
            "subcategory":"Lumber",
            "type":"Manufacturing & Wholesale Goods"
        }
    ],
    "sg:phone":"+1 662 234 0904",
    "sg:postcode":"38601",
    "sg:province":"MS",
    "sg:tags":[
        "timberland",
        "company",
        "logging",
        "timber"
    ],
    "wof:name":"Timberland Harvesters Inc",
    "wof:placetype":"venue"
},
  "geometry": {"coordinates":[-89.51082100000001,34.502714],"type":"Point"}
}