{
  "type": "Feature",
  "properties": {
    "addr:full":"2167 Heucks Retreat Rd NE Brookhaven MS 39601",
    "addr:housenumber":"2167",
    "addr:postcode":"39601",
    "addr:street":"Heucks Retreat Rd Ne",
    "iso:country":"US",
    "sg:address":"2167 Heucks Retreat Rd NE",
    "sg:city":"Brookhaven",
    "sg:classifiers":[
        {
            "category":"Organizations",
            "subcategory":"Religious Organization",
            "type":"Services"
        }
    ],
    "sg:phone":"+1 601 835 1821",
    "sg:postcode":"39601",
    "sg:province":"MS",
    "wof:name":"Heucks Retreat Baptist Church",
    "wof:placetype":"venue"
},
  "geometry": {"coordinates":[-90.355222,31.62576],"type":"Point"}
}