{
  "type": "Feature",
  "properties": {
    "iso:country":"US",
    "sg:address":"8664 Bridgewood Dr",
    "sg:city":"Southaven",
    "sg:classifiers":[
        {
            "category":"Travel",
            "subcategory":"Travel Agent",
            "type":"Entertainment"
        }
    ],
    "sg:phone":"+1 662 393 2783",
    "sg:postcode":"38671",
    "sg:province":"MS",
    "sg:tags":[
        "agency",
        "bureau"
    ],
    "wof:name":"Blue Paradise Cruise",
    "wof:placetype":"venue"
},
  "geometry": {"coordinates":[-89.97500700000001,34.987102],"type":"Point"}
}