{
  "type": "Feature",
  "properties": {
    "iso:country":"US",
    "sg:address":"4364 Sharon Rd",
    "sg:city":"Laurel",
    "sg:classifiers":[
        {
            "category":"Restaurant",
            "type":"Food & Drink"
        }
    ],
    "sg:phone":"+1 601 428 2020",
    "sg:postcode":"39443",
    "sg:province":"MS",
    "wof:name":"Sam's Snac Shak",
    "wof:placetype":"venue"
},
  "geometry": {"coordinates":[-89.09875,31.79216],"type":"Point"}
}