{
  "type": "Feature",
  "properties": {
    "iso:country":"US",
    "sg:address":"1770 E Scott Rd",
    "sg:city":"Lake",
    "sg:classifiers":[
        {
            "category":"Education",
            "subcategory":"School",
            "type":"Public Place"
        }
    ],
    "sg:phone":"+1 601 775 3614",
    "sg:postcode":"39074",
    "sg:province":"MS",
    "wof:name":"Lake Middle School",
    "wof:placetype":"venue"
},
  "geometry": {"coordinates":[-89.356202,32.405938],"type":"Point"}
}