{
  "type": "Feature",
  "properties": {
    "iso:country":"US",
    "sg:address":"511 Pecan Cir",
    "sg:city":"Lucedale",
    "sg:classifiers":[
        {
            "category":"Building & Trades",
            "subcategory":"Construction",
            "type":"Services"
        }
    ],
    "sg:phone":"+1 601 766 3860",
    "sg:postcode":"39452",
    "sg:province":"MS",
    "sg:tags":[
        "contractor"
    ],
    "wof:name":"E C Builders",
    "wof:placetype":"venue"
},
  "geometry": {"coordinates":[-88.594382,30.912635],"type":"Point"}
}