{
  "type": "Feature",
  "properties": {
    "iso:country":"US",
    "sg:address":"379 Morgantown Rd",
    "sg:city":"Natchez",
    "sg:classifiers":[
        {
            "category":"Personal",
            "subcategory":"Beauty Salon",
            "type":"Services"
        }
    ],
    "sg:phone":"+1 601 442 9674",
    "sg:postcode":"39120",
    "sg:province":"MS",
    "sg:tags":[
        "shop"
    ],
    "wof:name":"Beauty Hut",
    "wof:placetype":"venue"
},
  "geometry": {"coordinates":[-91.30884500000001,31.585286],"type":"Point"}
}