{
  "type": "Feature",
  "properties": {
    "addr:full":"116 Woodgreen Dr Madison MS 39110",
    "addr:housenumber":"116",
    "addr:postcode":"39110",
    "addr:street":"Woodgreen Dr",
    "iso:country":"US",
    "sg:address":"116 Woodgreen Dr",
    "sg:city":"Madison",
    "sg:classifiers":[
        {
            "category":"Health Services",
            "subcategory":"Clinic",
            "type":"Services"
        }
    ],
    "sg:phone":"+1 601 368 3238",
    "sg:postcode":"39110",
    "sg:province":"MS",
    "wof:name":"Delta Health Solutions",
    "wof:placetype":"venue"
},
  "geometry": {"coordinates":[-90.137826,32.472884],"type":"Point"}
}