{
  "type": "Feature",
  "properties": {
    "addr:full":"709 Howard Ave Biloxi MS 39530",
    "addr:housenumber":"709",
    "addr:postcode":"39530",
    "addr:street":"Howard Ave",
    "iso:country":"US",
    "sg:address":"709 Howard Ave",
    "sg:city":"Biloxi",
    "sg:classifiers":[
        {
            "category":"Shopping",
            "subcategory":"Florist",
            "type":"Retail Goods"
        }
    ],
    "sg:phone":"+1 228 436 4791",
    "sg:postcode":"39530",
    "sg:province":"MS",
    "wof:name":"Kay's Flowers",
    "wof:placetype":"venue"
},
  "geometry": {"coordinates":[-88.88581600000001,30.396095],"type":"Point"}
}