{
  "type": "Feature",
  "properties": {
    "iso:country":"US",
    "sg:address":"866 S Ridge Rd",
    "sg:city":"Starkville",
    "sg:classifiers":[
        {
            "category":"Professional",
            "subcategory":"Management & Consulting",
            "type":"Services"
        }
    ],
    "sg:phone":"+1 662 323 2679",
    "sg:postcode":"39759",
    "sg:province":"MS",
    "sg:tags":[
        "business"
    ],
    "wof:name":"Duett Consulting",
    "wof:placetype":"venue"
},
  "geometry": {"coordinates":[-88.819154,33.384762],"type":"Point"}
}