{
  "type": "Feature",
  "properties": {
    "iso:country":"US",
    "sg:address":"223 Goodman Rd E",
    "sg:city":"Southaven",
    "sg:classifiers":[
        {
            "category":"Autos & Motor Vehicles",
            "subcategory":"Automobile Sales",
            "type":"Retail Goods"
        }
    ],
    "sg:phone":"+1 662 349 3700",
    "sg:postcode":"38671",
    "sg:province":"MS",
    "sg:tags":[
        "car",
        "dealer"
    ],
    "sg:website":"www.southlandchryslerjeep.com",
    "wof:name":"Southland Chrysler-Jeep Inc",
    "wof:placetype":"venue"
},
  "geometry": {"coordinates":[-89.98541299999999,34.962658],"type":"Point"}
}