{
  "type": "Feature",
  "properties": {
    "iso:country":"US",
    "sg:address":"2980 Davis Rd",
    "sg:city":"Terry",
    "sg:classifiers":[
        {
            "category":"Professional",
            "subcategory":"Computer Services",
            "type":"Services"
        }
    ],
    "sg:phone":"+1 601 373 0177",
    "sg:postcode":"39170",
    "sg:province":"MS",
    "wof:name":"Regie Networking Systems",
    "wof:placetype":"venue"
},
  "geometry": {"coordinates":[-90.29445200000001,32.203263],"type":"Point"}
}