{
  "type": "Feature",
  "properties": {
    "addr:full":"815 Hickory Ridge Dr Jackson MS 39206",
    "addr:housenumber":"815",
    "addr:postcode":"39206",
    "addr:street":"Hickory Ridge Dr",
    "iso:country":"US",
    "sg:address":"815 Hickory Ridge Dr",
    "sg:city":"Jackson",
    "sg:classifiers":[
        {
            "category":"Building & Trades",
            "subcategory":"Cleaning & Sanitation",
            "type":"Services"
        }
    ],
    "sg:phone":"+1 601 982 0959",
    "sg:postcode":"39206",
    "sg:province":"MS",
    "sg:tags":[
        "house"
    ],
    "wof:name":"Freshness Cleaning Svc",
    "wof:placetype":"venue"
},
  "geometry": {"coordinates":[-90.192537,32.357317],"type":"Point"}
}