{
  "type": "Feature",
  "properties": {
    "addr:full":"1305 Concart St Hattiesburg MS 39401",
    "addr:housenumber":"1305",
    "addr:postcode":"39401",
    "addr:street":"Concart St",
    "iso:country":"US",
    "sg:address":"1305 Concart St",
    "sg:city":"Hattiesburg",
    "sg:classifiers":[
        {
            "category":"Professional",
            "subcategory":"Engineering",
            "type":"Services"
        }
    ],
    "sg:phone":"+1 601 544 6166",
    "sg:postcode":"39401",
    "sg:province":"MS",
    "wof:name":"Microcon Inc",
    "wof:placetype":"venue"
},
  "geometry": {"coordinates":[-89.30967800000001,31.322964],"type":"Point"}
}