{
  "type": "Feature",
  "properties": {
    "addr:full":"158 Bails Rd Ripley MS 38663",
    "addr:housenumber":"158",
    "addr:postcode":"38663",
    "addr:street":"Bails Rd",
    "iso:country":"US",
    "sg:address":"158 Bails Rd",
    "sg:city":"Ripley",
    "sg:classifiers":[
        {
            "category":"Manufacturing",
            "subcategory":"Furniture",
            "type":"Manufacturing & Wholesale Goods"
        }
    ],
    "sg:phone":"+1 662 837 1003",
    "sg:postcode":"38663",
    "sg:province":"MS",
    "wof:name":"Kirkwood Industries Inc",
    "wof:placetype":"venue"
},
  "geometry": {"coordinates":[-88.959563,34.736054],"type":"Point"}
}