{
  "type": "Feature",
  "properties": {
    "iso:country":"US",
    "sg:address":"9264 Hwy 39 N",
    "sg:city":"Meridian",
    "sg:classifiers":[
        {
            "category":"Organizations",
            "subcategory":"Religious Organization",
            "type":"Services"
        }
    ],
    "sg:phone":"+1 601 681 6668",
    "sg:postcode":"39305",
    "sg:province":"MS",
    "wof:name":"Countryside Baptist Church",
    "wof:placetype":"venue"
},
  "geometry": {"coordinates":[-88.671046,32.50497],"type":"Point"}
}