{
  "type": "Feature",
  "properties": {
    "iso:country":"US",
    "sg:address":"2223 25th Ave",
    "sg:city":"Gulfport",
    "sg:classifiers":[
        {
            "category":"Autos & Motor Vehicles",
            "subcategory":"Auto Supplies",
            "type":"Retail Goods"
        }
    ],
    "sg:phone":"+1 228 863 0029",
    "sg:postcode":"39501",
    "sg:province":"MS",
    "sg:tags":[
        "automobile",
        "parts"
    ],
    "wof:name":"Autozone",
    "wof:placetype":"venue"
},
  "geometry": {"coordinates":[-89.093182,30.377629],"type":"Point"}
}