{
  "type": "Feature",
  "properties": {
    "iso:country":"US",
    "sg:address":"1180 Sandflat Rd",
    "sg:city":"Meridian",
    "sg:classifiers":[
        {
            "category":"Government",
            "subcategory":"Police Station",
            "type":"Public Place"
        }
    ],
    "sg:phone":"+1 601 484 6833",
    "sg:postcode":"39301",
    "sg:province":"MS",
    "sg:tags":[
        "department"
    ],
    "sg:website":"www.meridianms.org",
    "wof:name":"Meridian Police Firing Range",
    "wof:placetype":"venue"
},
  "geometry": {"coordinates":[-88.62636999999999,32.351221],"type":"Point"}
}