{
  "type": "Feature",
  "properties": {
    "iso:country":"US",
    "sg:address":"161 Main St",
    "sg:city":"Bay St Louis",
    "sg:classifiers":[
        {
            "category":"Government",
            "subcategory":"Office",
            "type":"Public Place"
        }
    ],
    "sg:phone":"+1 228 467 0130",
    "sg:postcode":"39520",
    "sg:province":"MS",
    "wof:name":"Hancock County Reappraisal",
    "wof:placetype":"venue"
},
  "geometry": {"coordinates":[-89.32832999999999,30.311252],"type":"Point"}
}