{
  "type": "Feature",
  "properties": {
    "addr:full":"1201 Ingalls Ave Pascagoula MS 39567",
    "addr:housenumber":"1201",
    "addr:postcode":"39567",
    "addr:street":"Ingalls Ave",
    "iso:country":"US",
    "sg:address":"1201 Ingalls Ave",
    "sg:city":"Pascagoula",
    "sg:classifiers":[
        {
            "category":"Sports & Exercise",
            "subcategory":"Gym",
            "type":"Entertainment"
        }
    ],
    "sg:phone":"+1 228 762 7200",
    "sg:postcode":"39567",
    "sg:province":"MS",
    "sg:tags":[
        "gymnasium"
    ],
    "wof:name":"Fitness Zone",
    "wof:placetype":"venue"
},
  "geometry": {"coordinates":[-88.55219700000001,30.354761],"type":"Point"}
}