{
  "type": "Feature",
  "properties": {
    "addr:full":"302 W Church St Booneville MS 38829",
    "addr:housenumber":"302",
    "addr:postcode":"38829",
    "addr:street":"W Church St",
    "iso:country":"US",
    "sg:address":"302 W Church St",
    "sg:city":"Booneville",
    "sg:classifiers":[
        {
            "category":"Utilities",
            "subcategory":"Electric",
            "type":"Services"
        }
    ],
    "sg:phone":"+1 662 728 4433",
    "sg:postcode":"38829",
    "sg:province":"MS",
    "sg:tags":[
        "company"
    ],
    "wof:name":"Prentiss County Electric Power",
    "wof:placetype":"venue"
},
  "geometry": {"coordinates":[-88.564087,34.656596],"type":"Point"}
}