{
  "type": "Feature",
  "properties": {
    "iso:country":"US",
    "sg:address":"1445 Main St",
    "sg:city":"Fayette",
    "sg:classifiers":[
        {
            "category":"Banks & Credit Unions",
            "subcategory":"Bank",
            "type":"Services"
        }
    ],
    "sg:phone":"+1 601 786 3191",
    "sg:postcode":"39069",
    "sg:province":"MS",
    "wof:name":"Jefferson Bank",
    "wof:placetype":"venue"
},
  "geometry": {"coordinates":[-91.058615,31.724437],"type":"Point"}
}