{
  "type": "Feature",
  "properties": {
    "iso:country":"US",
    "sg:address":"610 13th St",
    "sg:city":"Mc Comb",
    "sg:classifiers":[
        {
            "category":"Building & Trades",
            "subcategory":"Landscaping Services",
            "type":"Services"
        }
    ],
    "sg:phone":"+1 601 249 2769",
    "sg:postcode":"39648",
    "sg:province":"MS",
    "wof:name":"Browns Landscaping Lawn Svcs",
    "wof:placetype":"venue"
},
  "geometry": {"coordinates":[-90.470423,31.232919],"type":"Point"}
}