{
  "type": "Feature",
  "properties": {
    "iso:country":"US",
    "sg:address":"207 Old Richton Rd",
    "sg:city":"Petal",
    "sg:classifiers":[
        {
            "category":"Professional",
            "subcategory":"Lawyer & Legal Services",
            "type":"Services"
        }
    ],
    "sg:phone":"+1 601 544 8855",
    "sg:postcode":"39465",
    "sg:province":"MS",
    "sg:tags":[
        "attorney"
    ],
    "wof:name":"Glenn L White PLLC",
    "wof:placetype":"venue"
},
  "geometry": {"coordinates":[-89.258814,31.347808],"type":"Point"}
}