{
  "type": "Feature",
  "properties": {
    "addr:full":"102 Catalpa Dr Natchez MS 39120",
    "addr:housenumber":"102",
    "addr:postcode":"39120",
    "addr:street":"Catalpa Dr",
    "iso:country":"US",
    "sg:address":"102 Catalpa Dr",
    "sg:city":"Natchez",
    "sg:classifiers":[
        {
            "category":"Manufacturing",
            "subcategory":"Toys & Sporting Goods",
            "type":"Manufacturing & Wholesale Goods"
        }
    ],
    "sg:phone":"+1 601 442 4597",
    "sg:postcode":"39120",
    "sg:province":"MS",
    "sg:tags":[
        "polymer",
        "mfr",
        "paper",
        "clay",
        "doll"
    ],
    "wof:name":"Bonnies Babies & Ladies",
    "wof:placetype":"venue"
},
  "geometry": {"coordinates":[-91.38484099999999,31.517781],"type":"Point"}
}