{
  "type": "Feature",
  "properties": {
    "iso:country":"US",
    "sg:address":"829 Wright Rd",
    "sg:city":"Vicksburg",
    "sg:classifiers":[
        {
            "category":"Professional",
            "subcategory":"Advertising",
            "type":"Services"
        }
    ],
    "sg:phone":"+1 601 634 1634",
    "sg:postcode":"39180",
    "sg:province":"MS",
    "sg:tags":[
        "mail",
        "direct"
    ],
    "wof:name":"Gary Rickles",
    "wof:placetype":"venue"
},
  "geometry": {"coordinates":[-90.905646,32.157362],"type":"Point"}
}