{
  "type": "Feature",
  "properties": {
    "addr:full":"7307 Alexander Rd Olive Branch MS 38654",
    "addr:housenumber":"7307",
    "addr:postcode":"38654",
    "addr:street":"Alexander Rd",
    "iso:country":"US",
    "sg:address":"7307 Alexander Rd",
    "sg:city":"Olive Branch",
    "sg:classifiers":[
        {
            "category":"Building & Trades",
            "subcategory":"Construction",
            "type":"Services"
        }
    ],
    "sg:phone":"+1 662 893 7841",
    "sg:postcode":"38654",
    "sg:province":"MS",
    "sg:tags":[
        "general",
        "contractor"
    ],
    "wof:name":"Crossman Communities",
    "wof:placetype":"venue"
},
  "geometry": {"coordinates":[-89.81293100000001,34.968494],"type":"Point"}
}