{
  "type": "Feature",
  "properties": {
    "iso:country":"US",
    "sg:address":"1415 Broad St",
    "sg:city":"Columbia",
    "sg:classifiers":[
        {
            "category":"Real Estate",
            "subcategory":"Real Estate Operator",
            "type":"Services"
        }
    ],
    "sg:phone":"+1 601 736 8458",
    "sg:postcode":"39429",
    "sg:province":"MS",
    "sg:tags":[
        "building",
        "nonresidential"
    ],
    "wof:name":"Dungan Properties Inc",
    "wof:placetype":"venue"
},
  "geometry": {"coordinates":[-89.814629,31.249755],"type":"Point"}
}