{
  "type": "Feature",
  "properties": {
    "iso:country":"US",
    "sg:address":"564 N Forest Dr",
    "sg:city":"Gulfport",
    "sg:classifiers":[
        {
            "category":"Building & Trades",
            "subcategory":"Cleaning & Sanitation",
            "type":"Services"
        }
    ],
    "sg:phone":"+1 228 896 5903",
    "sg:postcode":"39507",
    "sg:province":"MS",
    "sg:tags":[
        "maintenance"
    ],
    "wof:name":"Huddleston Janitorial Service",
    "wof:placetype":"venue"
},
  "geometry": {"coordinates":[-89.03067299999999,30.394396],"type":"Point"}
}