{
  "type": "Feature",
  "properties": {
    "iso:country":"US",
    "sg:address":"232 E North St",
    "sg:city":"Pass Christian",
    "sg:classifiers":[
        {
            "category":"Personal",
            "subcategory":"Barber",
            "type":"Services"
        }
    ],
    "sg:phone":"+1 228 452 6166",
    "sg:postcode":"39571",
    "sg:province":"MS",
    "wof:name":"Cuttin Up Barber Shop",
    "wof:placetype":"venue"
},
  "geometry": {"coordinates":[-89.24660900000001,30.326988],"type":"Point"}
}