{
  "type": "Feature",
  "properties": {
    "iso:country":"US",
    "sg:address":"3105 Tarpon Dr",
    "sg:city":"Gautier",
    "sg:classifiers":[
        {
            "category":"Building & Trades",
            "subcategory":"Landscaping Services",
            "type":"Services"
        }
    ],
    "sg:phone":"+1 228 497 6107",
    "sg:postcode":"39553",
    "sg:province":"MS",
    "wof:name":"Tree Toppers",
    "wof:placetype":"venue"
},
  "geometry": {"coordinates":[-88.661171,30.364723],"type":"Point"}
}