{
  "type": "Feature",
  "properties": {
    "addr:full":"4955 N State St Jackson MS 39206",
    "addr:housenumber":"4955",
    "addr:postcode":"39206",
    "addr:street":"N State St",
    "iso:country":"US",
    "sg:address":"4955 N State St",
    "sg:city":"Jackson",
    "sg:classifiers":[
        {
            "category":"Personal",
            "subcategory":"Beauty Salon",
            "type":"Services"
        }
    ],
    "sg:phone":"+1 601 366 4477",
    "sg:postcode":"39206",
    "sg:province":"MS",
    "sg:tags":[
        "shop"
    ],
    "wof:name":"Nail Millennium",
    "wof:placetype":"venue"
},
  "geometry": {"coordinates":[-90.170131,32.365693],"type":"Point"}
}