{
  "type": "Feature",
  "properties": {
    "iso:country":"US",
    "sg:address":"155 S Hangar Dr",
    "sg:city":"Jackson",
    "sg:classifiers":[
        {
            "category":"Government",
            "subcategory":"Office",
            "type":"Public Place"
        }
    ],
    "sg:phone":"+1 601 939 3055",
    "sg:postcode":"39208",
    "sg:province":"MS",
    "sg:tags":[
        "state",
        "program"
    ],
    "wof:name":"Office-Air Transportation",
    "wof:placetype":"venue"
},
  "geometry": {"coordinates":[-90.07145,32.30541],"type":"Point"}
}