{
  "type": "Feature",
  "properties": {
    "iso:country":"US",
    "sg:address":"800 S Beech St",
    "sg:city":"Picayune",
    "sg:classifiers":[
        {
            "category":"Organizations",
            "subcategory":"Religious Organization",
            "type":"Services"
        }
    ],
    "sg:phone":"+1 601 749 0070",
    "sg:postcode":"39466",
    "sg:province":"MS",
    "wof:name":"Power Hse of Dlvrnce Mnistries",
    "wof:placetype":"venue"
},
  "geometry": {"coordinates":[-89.697913,30.518578],"type":"Point"}
}