{
  "type": "Feature",
  "properties": {
    "addr:full":"1527 University Ave Oxford MS 38655",
    "addr:housenumber":"1527",
    "addr:postcode":"38655",
    "addr:street":"University Ave",
    "iso:country":"US",
    "sg:address":"1527 University Ave",
    "sg:city":"Oxford",
    "sg:classifiers":[
        {
            "category":"Health Services",
            "subcategory":"Chiropractor",
            "type":"Services"
        }
    ],
    "sg:phone":"+1 662 236 6888",
    "sg:postcode":"38655",
    "sg:province":"MS",
    "wof:name":"Charles Wade DC",
    "wof:placetype":"venue"
},
  "geometry": {"coordinates":[-89.515604,34.363613],"type":"Point"}
}