{
  "type": "Feature",
  "properties": {
    "addr:full":"6805 MS-63 Moss Point MS 39563",
    "addr:housenumber":"6805",
    "addr:postcode":"39563",
    "addr:street":"Ms-63",
    "iso:country":"US",
    "sg:address":"6805 MS-63",
    "sg:city":"Moss Point",
    "sg:classifiers":[
        {
            "category":"Bars & Pubs",
            "type":"Food & Drink"
        }
    ],
    "sg:menulink":"http://www.allmenus.com/ms/coll-town/34368-cracker-barrel-old-country-store/menu/",
    "sg:phone":"+1 228 475 8856",
    "sg:postcode":"39563",
    "sg:province":"MS",
    "sg:tags":[
        "american",
        "southern"
    ],
    "wof:name":"Cracker Barrel Old Country Store",
    "wof:placetype":"venue"
},
  "geometry": {"coordinates":[-88.53272699999999,30.454893],"type":"Point"}
}