{
  "type": "Feature",
  "properties": {
    "addr:full":"1020 Island Rd Columbus MS 39701",
    "addr:housenumber":"1020",
    "addr:postcode":"39701",
    "addr:street":"Island Rd",
    "iso:country":"US",
    "sg:address":"1020 Island Rd",
    "sg:city":"Columbus",
    "sg:classifiers":[
        {
            "category":"Food & Beverages",
            "subcategory":"Groceries & Convenience Stores",
            "type":"Retail Goods"
        }
    ],
    "sg:phone":"+1 662 328 5471",
    "sg:postcode":"39701",
    "sg:province":"MS",
    "wof:name":"Sanders Oil Co",
    "wof:placetype":"venue"
},
  "geometry": {"coordinates":[-88.44835399999999,33.48866],"type":"Point"}
}