{
  "type": "Feature",
  "properties": {
    "iso:country":"US",
    "sg:address":"1140 Hwy 48 E",
    "sg:city":"Tylertown",
    "sg:classifiers":[
        {
            "category":"Farming",
            "subcategory":"Dairy Farm",
            "type":"Manufacturing & Wholesale Goods"
        }
    ],
    "sg:phone":"+1 601 876 4132",
    "sg:postcode":"39667",
    "sg:province":"MS",
    "wof:name":"Bill Morris",
    "wof:placetype":"venue"
},
  "geometry": {"coordinates":[-89.959431,31.074804],"type":"Point"}
}