{
  "type": "Feature",
  "properties": {
    "iso:country":"US",
    "sg:address":"2344 Clara Strengthford Rd",
    "sg:city":"Waynesboro",
    "sg:classifiers":[
        {
            "category":"Manufacturing",
            "subcategory":"Glass & Minerals",
            "type":"Manufacturing & Wholesale Goods"
        }
    ],
    "sg:phone":"+1 601 735 2933",
    "sg:postcode":"39367",
    "sg:province":"MS",
    "sg:tags":[
        "product",
        "mfg"
    ],
    "wof:name":"Wayne County Glass & Mirror",
    "wof:placetype":"venue"
},
  "geometry": {"coordinates":[-88.711089,31.587303],"type":"Point"}
}