{
  "type": "Feature",
  "properties": {
    "iso:country":"US",
    "sg:address":"878 Avery Blvd N",
    "sg:city":"Ridgeland",
    "sg:classifiers":[
        {
            "category":"Manufacturing",
            "subcategory":"Toys & Sporting Goods",
            "type":"Manufacturing & Wholesale Goods"
        }
    ],
    "sg:phone":"+1 601 899 9696",
    "sg:postcode":"39157",
    "sg:province":"MS",
    "sg:tags":[
        "athletic",
        "retailer"
    ],
    "wof:name":"Fleet Feet Sports",
    "wof:placetype":"venue"
},
  "geometry": {"coordinates":[-90.115521,32.403346],"type":"Point"}
}