{
  "type": "Feature",
  "properties": {
    "iso:country":"US",
    "sg:address":"1524 Co Rd 126",
    "sg:city":"New Albany",
    "sg:classifiers":[
        {
            "category":"Wholesale",
            "subcategory":"Petroleum",
            "type":"Manufacturing & Wholesale Goods"
        }
    ],
    "sg:phone":"+1 662 534 8426",
    "sg:postcode":"38652",
    "sg:province":"MS",
    "sg:tags":[
        "pipe",
        "line",
        "company"
    ],
    "wof:name":"Columbia Gulf Transmission Co",
    "wof:placetype":"venue"
},
  "geometry": {"coordinates":[-88.93033800000001,34.54731],"type":"Point"}
}