{
  "type": "Feature",
  "properties": {
    "iso:country":"US",
    "sg:address":"9444 US Hwy 49",
    "sg:city":"Gulfport",
    "sg:classifiers":[
        {
            "category":"Shopping",
            "subcategory":"Stationery & Office Supplies",
            "type":"Retail Goods"
        }
    ],
    "sg:phone":"+1 228 865 4393",
    "sg:postcode":"39503",
    "sg:province":"MS",
    "sg:website":"www.officemax.com",
    "wof:name":"Office Max",
    "wof:placetype":"venue"
},
  "geometry": {"coordinates":[-89.09232299999999,30.421478],"type":"Point"}
}