{
  "type": "Feature",
  "properties": {
    "addr:full":"401 W Lamar Ave Poplarville MS 39470",
    "addr:housenumber":"401",
    "addr:postcode":"39470",
    "addr:street":"W Lamar Ave",
    "iso:country":"US",
    "sg:address":"401 W Lamar Ave",
    "sg:city":"Poplarville",
    "sg:classifiers":[
        {
            "category":"Government",
            "subcategory":"Office",
            "type":"Public Place"
        }
    ],
    "sg:phone":"+1 601 795 4352",
    "sg:postcode":"39470",
    "sg:province":"MS",
    "wof:name":"Pearl River 4-H Office",
    "wof:placetype":"venue"
},
  "geometry": {"coordinates":[-89.54449700000001,30.851648],"type":"Point"}
}