{
  "type": "Feature",
  "properties": {
    "addr:full":"104 5th St Leland MS 38756",
    "addr:housenumber":"104",
    "addr:postcode":"38756",
    "addr:street":"5Th St",
    "iso:country":"US",
    "sg:address":"104 5th St",
    "sg:city":"Leland",
    "sg:classifiers":[
        {
            "category":"Taxi",
            "type":"Transportation"
        }
    ],
    "sg:phone":"+1 662 686 4910",
    "sg:postcode":"38756",
    "sg:province":"MS",
    "sg:tags":[
        "taxicab"
    ],
    "wof:name":"Leland City Cab Co",
    "wof:placetype":"venue"
},
  "geometry": {"coordinates":[-90.897576,33.407189],"type":"Point"}
}