{
  "type": "Feature",
  "properties": {
    "iso:country":"US",
    "sg:address":"7408 US Hwy 49",
    "sg:city":"Hattiesburg",
    "sg:classifiers":[
        {
            "category":"Home & Garden",
            "subcategory":"Mobile Homes",
            "type":"Retail Goods"
        }
    ],
    "sg:phone":"+1 601 264 8466",
    "sg:postcode":"39402",
    "sg:province":"MS",
    "sg:tags":[
        "parts"
    ],
    "wof:name":"A To Z Mobile Home & Parts Svc",
    "wof:placetype":"venue"
},
  "geometry": {"coordinates":[-89.38165499999999,31.393808],"type":"Point"}
}