{
  "type": "Feature",
  "properties": {
    "iso:country":"US",
    "sg:address":"702 N 30th Ave",
    "sg:city":"Hattiesburg",
    "sg:classifiers":[
        {
            "category":"Organizations",
            "subcategory":"Religious Organization",
            "type":"Services"
        }
    ],
    "sg:phone":"+1 601 264 1105",
    "sg:postcode":"39401",
    "sg:province":"MS",
    "sg:tags":[
        "church"
    ],
    "wof:name":"Christian Science Society",
    "wof:placetype":"venue"
},
  "geometry": {"coordinates":[-89.334411,31.339297],"type":"Point"}
}