{
  "type": "Feature",
  "properties": {
    "iso:country":"US",
    "sg:address":"2102 23rd Ave",
    "sg:city":"Gulfport",
    "sg:classifiers":[
        {
            "category":"Organizations",
            "subcategory":"Religious Organization",
            "type":"Services"
        }
    ],
    "sg:phone":"+1 228 868 0344",
    "sg:postcode":"39501",
    "sg:province":"MS",
    "wof:name":"Power Source Christian Center",
    "wof:placetype":"venue"
},
  "geometry": {"coordinates":[-89.090074,30.376696],"type":"Point"}
}