{
  "type": "Feature",
  "properties": {
    "addr:full":"622 Washington Ave Ocean Springs MS 39564",
    "addr:housenumber":"622",
    "addr:postcode":"39564",
    "addr:street":"Washington Ave",
    "iso:country":"US",
    "sg:address":"622 Washington Ave",
    "sg:city":"Ocean Springs",
    "sg:classifiers":[
        {
            "category":"Shopping",
            "subcategory":"Clothing, Apparel, & Fashions",
            "type":"Retail Goods"
        }
    ],
    "sg:phone":"+1 228 875 7008",
    "sg:postcode":"39564",
    "sg:province":"MS",
    "wof:name":"Bayou Belle",
    "wof:placetype":"venue"
},
  "geometry": {"coordinates":[-88.827709,30.412608],"type":"Point"}
}