{
  "type": "Feature",
  "properties": {
    "iso:country":"US",
    "sg:address":"677 Hodges Dr",
    "sg:city":"Mantachie",
    "sg:classifiers":[
        {
            "category":"Manufacturing",
            "subcategory":"Printing",
            "type":"Manufacturing & Wholesale Goods"
        }
    ],
    "sg:phone":"+1 662 282 7625",
    "sg:postcode":"38855",
    "sg:province":"MS",
    "sg:tags":[
        "commercial"
    ],
    "wof:name":"Mantachie Printing",
    "wof:placetype":"venue"
},
  "geometry": {"coordinates":[-88.49608600000001,34.316748],"type":"Point"}
}