{
  "type": "Feature",
  "properties": {
    "iso:country":"US",
    "sg:address":"412 Old Hwy 26 E",
    "sg:city":"Perkinston",
    "sg:classifiers":[
        {
            "category":"Professional",
            "subcategory":"Management & Consulting",
            "type":"Services"
        }
    ],
    "sg:phone":"+1 601 928 4949",
    "sg:postcode":"39573",
    "sg:province":"MS",
    "sg:tags":[
        "retail",
        "direct",
        "sales"
    ],
    "wof:name":"Premiere Design",
    "wof:placetype":"venue"
},
  "geometry": {"coordinates":[-88.88476,30.79499],"type":"Point"}
}