{
  "type": "Feature",
  "properties": {
    "iso:country":"US",
    "sg:address":"127 Pleasant St",
    "sg:city":"Brandon",
    "sg:classifiers":[
        {
            "category":"Education",
            "subcategory":"School",
            "type":"Public Place"
        }
    ],
    "sg:phone":"+1 601 825 6577",
    "sg:postcode":"39042",
    "sg:province":"MS",
    "wof:name":"Parent Center & Ropes Course",
    "wof:placetype":"venue"
},
  "geometry": {"coordinates":[-89.97727999999999,32.272221],"type":"Point"}
}