{
  "type": "Feature",
  "properties": {
    "iso:country":"US",
    "sg:address":"409 W Porter St",
    "sg:city":"Ridgeland",
    "sg:classifiers":[
        {
            "category":"Insurance",
            "subcategory":"Insurance Agent",
            "type":"Services"
        }
    ],
    "sg:phone":"+1 601 856 1228",
    "sg:postcode":"39157",
    "sg:province":"MS",
    "wof:name":"State Farm Insurance",
    "wof:placetype":"venue"
},
  "geometry": {"coordinates":[-90.13795,32.429734],"type":"Point"}
}