{
  "type": "Feature",
  "properties": {
    "iso:country":"US",
    "sg:address":"14108 Seaway Rd",
    "sg:city":"Gulfport",
    "sg:classifiers":[
        {
            "category":"Freight",
            "type":"Transportation"
        }
    ],
    "sg:phone":"+1 228 868 3333",
    "sg:postcode":"39503",
    "sg:province":"MS",
    "sg:tags":[
        "operator",
        "local",
        "trucking"
    ],
    "wof:name":"A1 Trucking Long Haul Inc",
    "wof:placetype":"venue"
},
  "geometry": {"coordinates":[-89.07359,30.434381],"type":"Point"}
}