{
  "type": "Feature",
  "properties": {
    "iso:country":"US",
    "sg:address":"505 Earle St",
    "sg:city":"Jackson",
    "sg:classifiers":[
        {
            "category":"Autos & Motor Vehicles",
            "subcategory":"Auto Supplies",
            "type":"Retail Goods"
        }
    ],
    "sg:phone":"+1 601 985 9222",
    "sg:postcode":"39203",
    "sg:province":"MS",
    "sg:tags":[
        "tire"
    ],
    "wof:name":"Air It Up New & Used Tires",
    "wof:placetype":"venue"
},
  "geometry": {"coordinates":[-90.19625499999999,32.295823],"type":"Point"}
}