{
  "type": "Feature",
  "properties": {
    "addr:full":"115 Northwest Plz Senatobia MS 38668",
    "addr:housenumber":"115",
    "addr:postcode":"38668",
    "addr:street":"Northwest Plz",
    "iso:country":"US",
    "sg:address":"115 Northwest Plz",
    "sg:city":"Senatobia",
    "sg:classifiers":[
        {
            "category":"Utilities",
            "subcategory":"Mobile Phone",
            "type":"Services"
        },
        {
            "category":"Shopping",
            "subcategory":"Mobile Phones",
            "type":"Retail Goods"
        },
        {
            "category":"Utilities",
            "subcategory":"Telephone",
            "type":"Services"
        },
        {
            "category":"Professional",
            "subcategory":"Computer Services",
            "type":"Services"
        }
    ],
    "sg:phone":"+1 662 562 6288",
    "sg:postcode":"38668",
    "sg:province":"MS",
    "sg:tags":[
        "telecommunication",
        "supply",
        "communication",
        "system",
        "wireless",
        "equipment",
        "cellular"
    ],
    "sg:website":"http://clickserve.dartsearch.net/link/click?lid=43000000308049899",
    "wof:name":"T-Mobile",
    "wof:placetype":"venue"
},
  "geometry": {"coordinates":[-89.968726,34.626671],"type":"Point"}
}