{
  "type": "Feature",
  "properties": {
    "addr:full":"10356 Shorecrest Rd Biloxi MS 39532",
    "addr:housenumber":"10356",
    "addr:postcode":"39532",
    "addr:street":"Shorecrest Rd",
    "iso:country":"US",
    "sg:address":"10356 Shorecrest Rd",
    "sg:city":"Biloxi",
    "sg:classifiers":[
        {
            "category":"Utilities",
            "subcategory":"Refuse",
            "type":"Services"
        }
    ],
    "sg:phone":"+1 228 392 7173",
    "sg:postcode":"39532",
    "sg:province":"MS",
    "sg:tags":[
        "system"
    ],
    "wof:name":"S&S Enterprises Inc",
    "wof:placetype":"venue"
},
  "geometry": {"coordinates":[-89.007352,30.436082],"type":"Point"}
}