{
  "type": "Feature",
  "properties": {
    "iso:country":"US",
    "sg:address":"776 W Cooper St",
    "sg:city":"Ripley",
    "sg:classifiers":[
        {
            "category":"Retail",
            "subcategory":"Auto Repair",
            "type":"Services"
        }
    ],
    "sg:phone":"+1 662 512 1979",
    "sg:postcode":"38663",
    "sg:province":"MS",
    "sg:tags":[
        "automotive"
    ],
    "wof:name":"West Ripley Auto Autmtc Trans",
    "wof:placetype":"venue"
},
  "geometry": {"coordinates":[-88.961252,34.736045],"type":"Point"}
}