{
  "type": "Feature",
  "properties": {
    "iso:country":"US",
    "sg:address":"1112 Lyles Ln",
    "sg:city":"Raymond",
    "sg:classifiers":[
        {
            "category":"Building & Trades",
            "subcategory":"Construction",
            "type":"Services"
        }
    ],
    "sg:phone":"+1 601 373 8605",
    "sg:postcode":"39154",
    "sg:province":"MS",
    "sg:tags":[
        "house"
    ],
    "wof:name":"James T Lyles Construction",
    "wof:placetype":"venue"
},
  "geometry": {"coordinates":[-90.332076,32.290883],"type":"Point"}
}