{
  "type": "Feature",
  "properties": {
    "addr:full":"4802 Harrison Cir Gulfport MS 39507",
    "addr:housenumber":"4802",
    "addr:postcode":"39507",
    "addr:street":"Harrison Cir",
    "iso:country":"US",
    "sg:address":"4802 Harrison Cir",
    "sg:city":"Gulfport",
    "sg:classifiers":[
        {
            "category":"Farming",
            "subcategory":"Livestock Farm",
            "type":"Manufacturing & Wholesale Goods"
        }
    ],
    "sg:phone":"+1 228 871 2211",
    "sg:postcode":"39507",
    "sg:province":"MS",
    "sg:tags":[
        "beef",
        "feedlot",
        "cattle"
    ],
    "wof:name":"Coyote Springs Farm",
    "wof:placetype":"venue"
},
  "geometry": {"coordinates":[-89.04996,30.40924],"type":"Point"}
}