{
  "type": "Feature",
  "properties": {
    "iso:country":"US",
    "sg:address":"150 Lexington Ave",
    "sg:city":"Jackson",
    "sg:classifiers":[
        {
            "category":"Building & Trades",
            "subcategory":"Construction",
            "type":"Services"
        }
    ],
    "sg:phone":"+1 601 353 3730",
    "sg:postcode":"39209",
    "sg:province":"MS",
    "sg:tags":[
        "general",
        "contractor"
    ],
    "wof:name":"H & H Construction",
    "wof:placetype":"venue"
},
  "geometry": {"coordinates":[-90.21887,32.315726],"type":"Point"}
}