{
  "type": "Feature",
  "properties": {
    "addr:full":"1975 Goodman Rd W Horn Lake MS 38637",
    "addr:housenumber":"1975",
    "addr:postcode":"38637",
    "addr:street":"Goodman Rd W Horn Lake",
    "iso:country":"US",
    "sg:address":"1975 Goodman Rd W",
    "sg:city":"Horn Lake",
    "sg:classifiers":[
        {
            "category":"Building & Trades",
            "subcategory":"Construction",
            "type":"Services"
        }
    ],
    "sg:phone":"+1 662 349 4829",
    "sg:postcode":"38637",
    "sg:province":"MS",
    "sg:tags":[
        "contractor"
    ],
    "wof:name":"Desoto County Pool & Spa",
    "wof:placetype":"venue"
},
  "geometry": {"coordinates":[-90.02381800000001,34.96257],"type":"Point"}
}