{
  "type": "Feature",
  "properties": {
    "iso:country":"US",
    "sg:address":"1900 Lincoln Rd",
    "sg:city":"Hattiesburg",
    "sg:classifiers":[
        {
            "category":"Restaurant",
            "type":"Food & Drink"
        }
    ],
    "sg:phone":"+1 601 296 0303",
    "sg:postcode":"39402",
    "sg:province":"MS",
    "sg:tags":[
        "grill",
        "bar"
    ],
    "wof:name":"Our Place Bar & Grill",
    "wof:placetype":"venue"
},
  "geometry": {"coordinates":[-89.317902,31.304023],"type":"Point"}
}