{
  "type": "Feature",
  "properties": {
    "addr:full":"121 S Industrial Rd Tupelo MS 38801",
    "addr:housenumber":"121",
    "addr:postcode":"38801",
    "addr:street":"S Industrial Rd",
    "iso:country":"US",
    "sg:address":"121 S Industrial Rd",
    "sg:city":"Tupelo",
    "sg:classifiers":[
        {
            "category":"Shopping",
            "type":"Retail Goods"
        }
    ],
    "sg:phone":"+1 662 844 5686",
    "sg:postcode":"38801",
    "sg:province":"MS",
    "sg:tags":[
        "church",
        "supply"
    ],
    "wof:name":"Christian Center",
    "wof:placetype":"venue"
},
  "geometry": {"coordinates":[-88.72058199999999,34.256929],"type":"Point"}
}