{
  "type": "Feature",
  "properties": {
    "iso:country":"US",
    "sg:address":"139 Richardson Rd",
    "sg:city":"Louisville",
    "sg:classifiers":[
        {
            "category":"Freight",
            "type":"Transportation"
        }
    ],
    "sg:phone":"+1 662 773 4339",
    "sg:postcode":"39339",
    "sg:province":"MS",
    "sg:tags":[
        "local",
        "storage",
        "trucking"
    ],
    "wof:name":"Dany W Misso",
    "wof:placetype":"venue"
},
  "geometry": {"coordinates":[-89.03652099999999,33.13918],"type":"Point"}
}