{
  "type": "Feature",
  "properties": {
    "addr:full":"295 Industrial Dr Jackson MS 39209",
    "addr:housenumber":"295",
    "addr:postcode":"39209",
    "addr:street":"Industrial Dr",
    "iso:country":"US",
    "sg:address":"295 Industrial Dr",
    "sg:city":"Jackson",
    "sg:classifiers":[
        {
            "category":"Wholesale",
            "subcategory":"Groceries",
            "type":"Manufacturing & Wholesale Goods"
        }
    ],
    "sg:phone":"+1 601 352 4426",
    "sg:postcode":"39209",
    "sg:province":"MS",
    "sg:tags":[
        "grocer"
    ],
    "wof:name":"Pilgrim's Food Systems",
    "wof:placetype":"venue"
},
  "geometry": {"coordinates":[-90.230718,32.330354],"type":"Point"}
}