{
  "type": "Feature",
  "properties": {
    "addr:full":"2719 Pass Rd Biloxi MS 39531",
    "addr:housenumber":"2719",
    "addr:postcode":"39531",
    "addr:street":"Pass Rd",
    "iso:country":"US",
    "sg:address":"2719 Pass Rd",
    "sg:city":"Biloxi",
    "sg:classifiers":[
        {
            "category":"Home & Garden",
            "subcategory":"Carpets & Floor Coverings",
            "type":"Retail Goods"
        }
    ],
    "sg:phone":"+1 228 388 7085",
    "sg:postcode":"39531",
    "sg:province":"MS",
    "wof:name":"Rhodes Carpetmax Flooring Ctr",
    "wof:placetype":"venue"
},
  "geometry": {"coordinates":[-88.99738499999999,30.40044],"type":"Point"}
}