{
  "type": "Feature",
  "properties": {
    "addr:full":"509 Walnut St Port Gibson MS 39150",
    "addr:housenumber":"509",
    "addr:postcode":"39150",
    "addr:street":"Walnut St",
    "iso:country":"US",
    "sg:address":"509 Walnut St",
    "sg:city":"Port Gibson",
    "sg:classifiers":[
        {
            "category":"Social Services",
            "subcategory":"Child Care",
            "type":"Services"
        }
    ],
    "sg:phone":"+1 601 437 3588",
    "sg:postcode":"39150",
    "sg:province":"MS",
    "wof:name":"All God's Children Nursery",
    "wof:placetype":"venue"
},
  "geometry": {"coordinates":[-90.98103,31.959234],"type":"Point"}
}