{
  "type": "Feature",
  "properties": {
    "addr:full":"10509 Lemoyne Blvd Diberville MS 39540",
    "addr:housenumber":"10509",
    "addr:postcode":"39540",
    "addr:street":"Lemoyne Blvd Diberville",
    "iso:country":"US",
    "sg:address":"10509 Lemoyne Blvd",
    "sg:city":"Diberville",
    "sg:classifiers":[
        {
            "category":"Building & Trades",
            "subcategory":"Equipment Rental",
            "type":"Services"
        }
    ],
    "sg:phone":"+1 228 392 7368",
    "sg:postcode":"39540",
    "sg:province":"MS",
    "sg:tags":[
        "contractor"
    ],
    "wof:name":"D'Iberville Equipment Rental",
    "wof:placetype":"venue"
},
  "geometry": {"coordinates":[-88.885834,30.437241],"type":"Point"}
}