{
  "type": "Feature",
  "properties": {
    "iso:country":"US",
    "sg:address":"5965 Westwind Dr",
    "sg:city":"Tupelo",
    "sg:classifiers":[
        {
            "category":"Insurance",
            "subcategory":"Insurance Agent",
            "type":"Services"
        }
    ],
    "sg:phone":"+1 662 844 0355",
    "sg:postcode":"38801",
    "sg:province":"MS",
    "wof:name":"Professional Health Care Svcs",
    "wof:placetype":"venue"
},
  "geometry": {"coordinates":[-88.80324,34.261282],"type":"Point"}
}