{
  "type": "Feature",
  "properties": {
    "addr:full":"218 S Thomas St Tupelo MS 38801",
    "addr:housenumber":"218",
    "addr:postcode":"38801",
    "addr:street":"S Thomas St",
    "iso:country":"US",
    "sg:address":"218 S Thomas St",
    "sg:city":"Tupelo",
    "sg:classifiers":[
        {
            "category":"Sports & Exercise",
            "subcategory":"Gym",
            "type":"Entertainment"
        }
    ],
    "sg:phone":"+1 662 841 1919",
    "sg:postcode":"38801",
    "sg:province":"MS",
    "sg:tags":[
        "club",
        "health",
        "studio",
        "gymnasium"
    ],
    "wof:name":"Curves For Women Fitness",
    "wof:placetype":"venue"
},
  "geometry": {"coordinates":[-88.74621500000001,34.253484],"type":"Point"}
}