{
  "type": "Feature",
  "properties": {
    "addr:full":"3042 Hwy 51 Mm Mccomb MS 39648",
    "addr:housenumber":"3042",
    "addr:postcode":"39648",
    "addr:street":"Hwy 51 Mm Mccomb",
    "iso:country":"US",
    "sg:address":"3042 Hwy 51 Mm",
    "sg:city":"Mccomb",
    "sg:classifiers":[
        {
            "category":"Restaurant",
            "type":"Food & Drink"
        }
    ],
    "sg:phone":"+1 601 250 0222",
    "sg:postcode":"39648",
    "sg:province":"MS",
    "wof:name":"Martey's Bar & Grill",
    "wof:placetype":"venue"
},
  "geometry": {"coordinates":[-90.454342,31.210974],"type":"Point"}
}