{
  "type": "Feature",
  "properties": {
    "addr:full":"3865 Goodman Rd E Southaven MS 38672",
    "addr:housenumber":"3865",
    "addr:postcode":"38672",
    "addr:street":"Goodman Rd E",
    "iso:country":"US",
    "sg:address":"3865 Goodman Rd E",
    "sg:city":"Southaven",
    "sg:classifiers":[
        {
            "category":"Building & Trades",
            "subcategory":"Construction",
            "type":"Services"
        }
    ],
    "sg:phone":"+1 662 890 9851",
    "sg:postcode":"38672",
    "sg:province":"MS",
    "sg:tags":[
        "designer",
        "dealer",
        "pool",
        "swimming"
    ],
    "wof:name":"Atlantis Pools",
    "wof:placetype":"venue"
},
  "geometry": {"coordinates":[-89.922135,34.962308],"type":"Point"}
}