{
  "type": "Feature",
  "properties": {
    "iso:country":"US",
    "sg:address":"2516 Old Hwy 24",
    "sg:city":"Hattiesburg",
    "sg:classifiers":[
        {
            "category":"Real Estate",
            "subcategory":"Real Estate Agent",
            "type":"Services"
        }
    ],
    "sg:phone":"+1 601 579 8240",
    "sg:postcode":"39402",
    "sg:province":"MS",
    "wof:name":"Assist 2 Sell",
    "wof:placetype":"venue"
},
  "geometry": {"coordinates":[-89.428528,31.282135],"type":"Point"}
}