{
  "type": "Feature",
  "properties": {
    "addr:full":"809 Hwy 35 S Forest MS 39074",
    "addr:housenumber":"809",
    "addr:postcode":"39074",
    "addr:street":"Hwy 35 S Forest",
    "iso:country":"US",
    "sg:address":"809 Hwy 35 S",
    "sg:city":"Forest",
    "sg:classifiers":[
        {
            "category":"Retail",
            "subcategory":"Animal Services",
            "type":"Services"
        }
    ],
    "sg:phone":"+1 601 469 4422",
    "sg:postcode":"39074",
    "sg:province":"MS",
    "wof:name":"Pretty Paws",
    "wof:placetype":"venue"
},
  "geometry": {"coordinates":[-89.480774,32.358103],"type":"Point"}
}