{
  "type": "Feature",
  "properties": {
    "iso:country":"US",
    "sg:address":"903 Susie B Ruffin Ave",
    "sg:city":"Laurel",
    "sg:classifiers":[
        {
            "category":"Shopping",
            "subcategory":"Florist",
            "type":"Retail Goods"
        }
    ],
    "sg:phone":"+1 601 649 6985",
    "sg:postcode":"39440",
    "sg:province":"MS",
    "wof:name":"Head To Toes Boutique & Flwrs",
    "wof:placetype":"venue"
},
  "geometry": {"coordinates":[-89.121944,31.700913],"type":"Point"}
}