{
  "type": "Feature",
  "properties": {
    "addr:full":"2554 Robinson St Jackson MS 39209",
    "addr:housenumber":"2554",
    "addr:postcode":"39209",
    "addr:street":"Robinson St",
    "iso:country":"US",
    "sg:address":"2554 Robinson St",
    "sg:city":"Jackson",
    "sg:classifiers":[
        {
            "category":"Shopping",
            "subcategory":"Clothing, Apparel, & Fashions",
            "type":"Retail Goods"
        }
    ],
    "sg:phone":"+1 601 352 5008",
    "sg:postcode":"39209",
    "sg:province":"MS",
    "wof:name":"Fashion Cents",
    "wof:placetype":"venue"
},
  "geometry": {"coordinates":[-90.22832200000001,32.30549],"type":"Point"}
}