{
  "type": "Feature",
  "properties": {
    "iso:country":"US",
    "sg:address":"712 N Main St",
    "sg:city":"Hattiesburg",
    "sg:classifiers":[
        {
            "category":"Organizations",
            "subcategory":"Religious Organization",
            "type":"Services"
        }
    ],
    "sg:phone":"+1 601 582 5557",
    "sg:postcode":"39401",
    "sg:province":"MS",
    "sg:tags":[
        "church"
    ],
    "sg:website":"www.mainst-umc.org",
    "wof:name":"Main Street United Methodist",
    "wof:placetype":"venue"
},
  "geometry": {"coordinates":[-89.292309,31.327995],"type":"Point"}
}