{
  "type": "Feature",
  "properties": {
    "iso:country":"US",
    "sg:address":"5724 Terry Rd",
    "sg:city":"Byram",
    "sg:classifiers":[
        {
            "category":"Autos & Motor Vehicles",
            "subcategory":"Fuel & Gas Station",
            "type":"Retail Goods"
        }
    ],
    "sg:phone":"+1 601 372 0432",
    "sg:postcode":"39272",
    "sg:province":"MS",
    "sg:tags":[
        "station",
        "gasoline",
        "oil"
    ],
    "wof:name":"Thornton Tire & Auto Service",
    "wof:placetype":"venue"
},
  "geometry": {"coordinates":[-90.28640799999999,32.168199],"type":"Point"}
}