{
  "type": "Feature",
  "properties": {
    "addr:full":"1825 6th St Meridian MS 39301",
    "addr:housenumber":"1825",
    "addr:postcode":"39301",
    "addr:street":"6Th St",
    "iso:country":"US",
    "sg:address":"1825 6th St",
    "sg:city":"Meridian",
    "sg:classifiers":[
        {
            "category":"Insurance",
            "subcategory":"Insurance Agent",
            "type":"Services"
        }
    ],
    "sg:phone":"+1 601 482 0034",
    "sg:postcode":"39301",
    "sg:province":"MS",
    "wof:name":"Jimmy Knight Insurance",
    "wof:placetype":"venue"
},
  "geometry": {"coordinates":[-88.6969,32.366548],"type":"Point"}
}