{
  "type": "Feature",
  "properties": {
    "iso:country":"US",
    "sg:address":"85 Sweet Beulah Rd",
    "sg:city":"Perkinston",
    "sg:classifiers":[
        {
            "category":"Organizations",
            "subcategory":"Religious Organization",
            "type":"Services"
        }
    ],
    "sg:phone":"+1 601 928 4681",
    "sg:postcode":"39573",
    "sg:province":"MS",
    "sg:tags":[
        "church"
    ],
    "wof:name":"Sweet Beulah Baptist Church",
    "wof:placetype":"venue"
},
  "geometry": {"coordinates":[-89.20105,30.79711],"type":"Point"}
}