{
  "type": "Feature",
  "properties": {
    "iso:country":"US",
    "sg:address":"2420 Terry Rd",
    "sg:city":"Jackson",
    "sg:classifiers":[
        {
            "category":"Banks & Credit Unions",
            "subcategory":"Bank",
            "type":"Services"
        }
    ],
    "sg:phone":"+1 601 372 0212",
    "sg:postcode":"39204",
    "sg:province":"MS",
    "sg:tags":[
        "broker",
        "mortgage"
    ],
    "wof:name":"Mortgage Loan Funding Inc",
    "wof:placetype":"venue"
},
  "geometry": {"coordinates":[-90.216093,32.273653],"type":"Point"}
}