{
  "type": "Feature",
  "properties": {
    "iso:country":"US",
    "sg:address":"104 N Murphree St",
    "sg:city":"Pittsboro",
    "sg:classifiers":[
        {
            "category":"Government",
            "subcategory":"Post Office",
            "type":"Public Place"
        }
    ],
    "sg:phone":"+1 662 983 2772",
    "sg:postcode":"38951",
    "sg:province":"MS",
    "wof:name":"US Post Office",
    "wof:placetype":"venue"
},
  "geometry": {"coordinates":[-89.343698,33.954949],"type":"Point"}
}