{
  "type": "Feature",
  "properties": {
    "addr:full":"609 Hwy 24 E Centreville MS 39631",
    "addr:housenumber":"609",
    "addr:postcode":"39631",
    "addr:street":"Hwy 24 E",
    "iso:country":"US",
    "sg:address":"609 Hwy 24 E",
    "sg:city":"Centreville",
    "sg:classifiers":[
        {
            "category":"Shopping",
            "subcategory":"Department Store",
            "type":"Retail Goods"
        }
    ],
    "sg:phone":"+1 601 645 6387",
    "sg:postcode":"39631",
    "sg:province":"MS",
    "sg:tags":[
        "shop"
    ],
    "wof:name":"Dollar General",
    "wof:placetype":"venue"
},
  "geometry": {"coordinates":[-91.28188,31.09797],"type":"Point"}
}