{
  "type": "Feature",
  "properties": {
    "iso:country":"US",
    "sg:address":"1245 42nd Ave",
    "sg:city":"Gulfport",
    "sg:classifiers":[
        {
            "category":"Health Services",
            "subcategory":"Doctor",
            "type":"Services"
        }
    ],
    "sg:phone":"+1 228 864 8049",
    "sg:postcode":"39501",
    "sg:province":"MS",
    "sg:tags":[
        "physician",
        "surgeon"
    ],
    "wof:name":"Tulane Dermatology Affiliates",
    "wof:placetype":"venue"
},
  "geometry": {"coordinates":[-89.11143,30.366554],"type":"Point"}
}