{
  "type": "Feature",
  "properties": {
    "iso:country":"US",
    "sg:address":"15260 State Hwy 513",
    "sg:city":"Enterprise",
    "sg:classifiers":[
        {
            "category":"Organizations",
            "subcategory":"Religious Organization",
            "type":"Services"
        }
    ],
    "sg:phone":"+1 601 659 7976",
    "sg:postcode":"39330",
    "sg:province":"MS",
    "sg:tags":[
        "church"
    ],
    "wof:name":"Magnolia United Methodist Chr",
    "wof:placetype":"venue"
},
  "geometry": {"coordinates":[-88.90269499999999,32.168483],"type":"Point"}
}