{
  "type": "Feature",
  "properties": {
    "iso:country":"US",
    "sg:address":"3103 5th Ave",
    "sg:city":"Gulfport",
    "sg:classifiers":[
        {
            "category":"Building & Trades",
            "subcategory":"Plumbing",
            "type":"Services"
        }
    ],
    "sg:phone":"+1 228 864 2122",
    "sg:postcode":"39501",
    "sg:province":"MS",
    "sg:tags":[
        "plumbing",
        "contractor"
    ],
    "wof:name":"Lindsay Plumbing",
    "wof:placetype":"venue"
},
  "geometry": {"coordinates":[-89.06627,30.388493],"type":"Point"}
}