{
  "type": "Feature",
  "properties": {
    "addr:full":"337 E Madison St Houston MS 38851",
    "addr:housenumber":"337",
    "addr:postcode":"38851",
    "addr:street":"E Madison St",
    "iso:country":"US",
    "sg:address":"337 E Madison St",
    "sg:city":"Houston",
    "sg:classifiers":[
        {
            "category":"Personal",
            "subcategory":"Barber",
            "type":"Services"
        }
    ],
    "sg:phone":"+1 662 456 7344",
    "sg:postcode":"38851",
    "sg:province":"MS",
    "wof:name":"Earp's Barber Shop",
    "wof:placetype":"venue"
},
  "geometry": {"coordinates":[-88.997668,33.896759],"type":"Point"}
}