{
  "type": "Feature",
  "properties": {
    "iso:country":"US",
    "sg:address":"213 N 1st St",
    "sg:city":"Wiggins",
    "sg:classifiers":[
        {
            "category":"Cinema",
            "subcategory":"Movie Rental",
            "type":"Entertainment"
        }
    ],
    "sg:phone":"+1 601 928 3816",
    "sg:postcode":"39577",
    "sg:province":"MS",
    "sg:tags":[
        "television",
        "video"
    ],
    "wof:name":"Central TV Video World",
    "wof:placetype":"venue"
},
  "geometry": {"coordinates":[-89.13775099999999,30.861418],"type":"Point"}
}