{
  "type": "Feature",
  "properties": {
    "iso:country":"US",
    "sg:address":"3169 Players Club Pkwy",
    "sg:city":"Memphis",
    "sg:classifiers":[
        {
            "category":"Shopping",
            "subcategory":"Computers & Home Electronics",
            "type":"Retail Goods"
        }
    ],
    "sg:phone":"+1 901 754 5223",
    "sg:postcode":"38125",
    "sg:province":"MS",
    "sg:tags":[
        "audio"
    ],
    "wof:name":"Visual Thunder",
    "wof:placetype":"venue"
},
  "geometry": {"coordinates":[-89.791377,35.061667],"type":"Point"}
}