{
  "type": "Feature",
  "properties": {
    "addr:full":"85 Goodman Rd W Southaven MS 38671",
    "addr:housenumber":"85",
    "addr:postcode":"38671",
    "addr:street":"Goodman Rd W",
    "iso:country":"US",
    "sg:address":"85 Goodman Rd W",
    "sg:city":"Southaven",
    "sg:classifiers":[
        {
            "category":"Wholesale",
            "subcategory":"Machinery & Supplies",
            "type":"Manufacturing & Wholesale Goods"
        }
    ],
    "sg:phone":"+1 662 349 1811",
    "sg:postcode":"38671",
    "sg:province":"MS",
    "sg:tags":[
        "salon",
        "beauty"
    ],
    "wof:name":"Sally Beauty Supply",
    "wof:placetype":"venue"
},
  "geometry": {"coordinates":[-89.991163,34.962607],"type":"Point"}
}