{
  "type": "Feature",
  "properties": {
    "addr:full":"3532 Hwy 15 N Laurel MS 39440",
    "addr:housenumber":"3532",
    "addr:postcode":"39440",
    "addr:street":"Hwy 15 N",
    "iso:country":"US",
    "sg:address":"3532 Hwy 15 N",
    "sg:city":"Laurel",
    "sg:classifiers":[
        {
            "category":"Personal",
            "subcategory":"Beauty Salon",
            "type":"Services"
        }
    ],
    "sg:phone":"+1 601 426 3736",
    "sg:postcode":"39440",
    "sg:province":"MS",
    "sg:tags":[
        "shop"
    ],
    "wof:name":"X Treme Tanning & Toning Salon",
    "wof:placetype":"venue"
},
  "geometry": {"coordinates":[-89.146686,31.731909],"type":"Point"}
}