{
  "type": "Feature",
  "properties": {
    "addr:full":"210 W Jefferson St Ripley MS 38663",
    "addr:housenumber":"210",
    "addr:postcode":"38663",
    "addr:street":"W Jefferson St",
    "iso:country":"US",
    "sg:address":"210 W Jefferson St",
    "sg:city":"Ripley",
    "sg:classifiers":[
        {
            "category":"Utilities",
            "subcategory":"Mobile Phone",
            "type":"Services"
        }
    ],
    "sg:phone":"+1 662 837 3030",
    "sg:postcode":"38663",
    "sg:province":"MS",
    "wof:name":"Cingular Wireless",
    "wof:placetype":"venue"
},
  "geometry": {"coordinates":[-88.951745,34.73038],"type":"Point"}
}