{
  "type": "Feature",
  "properties": {
    "iso:country":"US",
    "sg:address":"165 Herbert Trigg Rd",
    "sg:city":"Seminary",
    "sg:classifiers":[
        {
            "category":"Farming",
            "subcategory":"Livestock Farm",
            "type":"Manufacturing & Wholesale Goods"
        }
    ],
    "sg:phone":"+1 601 722 9081",
    "sg:postcode":"39479",
    "sg:province":"MS",
    "sg:tags":[
        "beef",
        "feedlot",
        "cattle"
    ],
    "wof:name":"Parker Ted R Farmer",
    "wof:placetype":"venue"
},
  "geometry": {"coordinates":[-89.500922,31.504047],"type":"Point"}
}