{
  "type": "Feature",
  "properties": {
    "addr:full":"2527 Hwy 496 Meridian MS 39301",
    "addr:housenumber":"2527",
    "addr:postcode":"39301",
    "addr:street":"Hwy 496",
    "iso:country":"US",
    "sg:address":"2527 Hwy 496",
    "sg:city":"Meridian",
    "sg:classifiers":[
        {
            "category":"Food & Beverages",
            "subcategory":"Groceries & Convenience Stores",
            "type":"Retail Goods"
        },
        {
            "category":"Shopping",
            "subcategory":"Discount & Variety Stores",
            "type":"Retail Goods"
        }
    ],
    "sg:phone":"+1 601 553 0505",
    "sg:postcode":"39301",
    "sg:province":"MS",
    "sg:tags":[
        "grocer",
        "merchandise",
        "general"
    ],
    "wof:name":"Poissos Country Store",
    "wof:placetype":"venue"
},
  "geometry": {"coordinates":[-88.566248,32.364841],"type":"Point"}
}