{
  "type": "Feature",
  "properties": {
    "addr:full":"118 S McCrary Rd Columbus MS 39702",
    "addr:housenumber":"118",
    "addr:postcode":"39702",
    "addr:street":"S Mccrary Rd",
    "iso:country":"US",
    "sg:address":"118 S McCrary Rd",
    "sg:city":"Columbus",
    "sg:classifiers":[
        {
            "category":"Wholesale",
            "subcategory":"Furniture",
            "type":"Manufacturing & Wholesale Goods"
        }
    ],
    "sg:phone":"+1 662 244 8894",
    "sg:postcode":"39702",
    "sg:province":"MS",
    "sg:website":"www.magnoliabusiness.com",
    "wof:name":"Magnolia Business Systems Inc",
    "wof:placetype":"venue"
},
  "geometry": {"coordinates":[-88.380475,33.494944],"type":"Point"}
}