{
  "type": "Feature",
  "properties": {
    "addr:full":"2430 Hwy 80 E Pearl MS 39208",
    "addr:housenumber":"2430",
    "addr:postcode":"39208",
    "addr:street":"Hwy 80 E",
    "iso:country":"US",
    "sg:address":"2430 Hwy 80 E",
    "sg:city":"Pearl",
    "sg:classifiers":[
        {
            "category":"Home & Garden",
            "subcategory":"Building Materials",
            "type":"Retail Goods"
        }
    ],
    "sg:phone":"+1 601 932 4999",
    "sg:postcode":"39208",
    "sg:province":"MS",
    "sg:tags":[
        "manufactured"
    ],
    "wof:name":"Home South Manufactured Hsing",
    "wof:placetype":"venue"
},
  "geometry": {"coordinates":[-90.13109900000001,32.280708],"type":"Point"}
}