{
  "type": "Feature",
  "properties": {
    "addr:full":"506 W Henry St Greenwood MS 38930",
    "addr:housenumber":"506",
    "addr:postcode":"38930",
    "addr:street":"W Henry St",
    "iso:country":"US",
    "sg:address":"506 W Henry St",
    "sg:city":"Greenwood",
    "sg:classifiers":[
        {
            "category":"Manufacturing",
            "subcategory":"Printing",
            "type":"Manufacturing & Wholesale Goods"
        }
    ],
    "sg:phone":"+1 662 453 0578",
    "sg:postcode":"38930",
    "sg:province":"MS",
    "sg:tags":[
        "lithographic",
        "commercial"
    ],
    "wof:name":"Williams Printing Service",
    "wof:placetype":"venue"
},
  "geometry": {"coordinates":[-90.184684,33.514843],"type":"Point"}
}