{
  "type": "Feature",
  "properties": {
    "iso:country":"US",
    "sg:address":"605 W Main St",
    "sg:city":"Tupelo",
    "sg:classifiers":[
        {
            "category":"Shopping",
            "subcategory":"Clothing, Apparel, & Fashions",
            "type":"Retail Goods"
        }
    ],
    "sg:phone":"+1 662 841 0850",
    "sg:postcode":"38804",
    "sg:province":"MS",
    "sg:tags":[
        "alteration"
    ],
    "wof:name":"Teri's Alterations",
    "wof:placetype":"venue"
},
  "geometry": {"coordinates":[-88.712608,34.257315],"type":"Point"}
}