{
  "type": "Feature",
  "properties": {
    "iso:country":"US",
    "sg:address":"129 Brickerton St",
    "sg:city":"Columbus",
    "sg:classifiers":[
        {
            "category":"Travel",
            "subcategory":"Hotels & Motels",
            "type":"Entertainment"
        }
    ],
    "sg:phone":"+1 662 327 9999",
    "sg:postcode":"39701",
    "sg:province":"MS",
    "sg:website":"www.wingateinns.com",
    "wof:name":"Wingate Inn",
    "wof:placetype":"venue"
},
  "geometry": {"coordinates":[-88.414688,33.517218],"type":"Point"}
}