{
  "type": "Feature",
  "properties": {
    "addr:full":"239 N Lamar St Jackson MS 39201",
    "addr:housenumber":"239",
    "addr:postcode":"39201",
    "addr:street":"N Lamar St",
    "iso:country":"US",
    "sg:address":"239 N Lamar St",
    "sg:city":"Jackson",
    "sg:classifiers":[
        {
            "category":"Organizations",
            "subcategory":"Membership Organization",
            "type":"Services"
        }
    ],
    "sg:phone":"+1 601 359 6030",
    "sg:postcode":"39201",
    "sg:province":"MS",
    "wof:name":"Arts Commission",
    "wof:placetype":"venue"
},
  "geometry": {"coordinates":[-90.185492,32.30214],"type":"Point"}
}