{
  "type": "Feature",
  "properties": {
    "iso:country":"US",
    "sg:address":"809 College Hill Rd",
    "sg:city":"Oxford",
    "sg:classifiers":[
        {
            "category":"Organizations",
            "subcategory":"Religious Organization",
            "type":"Services"
        }
    ],
    "sg:phone":"+1 662 234 3858",
    "sg:postcode":"38655",
    "sg:province":"MS",
    "sg:tags":[
        "church"
    ],
    "wof:name":"Spirit Of Excellence",
    "wof:placetype":"venue"
},
  "geometry": {"coordinates":[-89.54343,34.379656],"type":"Point"}
}