{
  "type": "Feature",
  "properties": {
    "iso:country":"US",
    "sg:address":"8945 Hamilton Rd",
    "sg:city":"Southaven",
    "sg:classifiers":[
        {
            "category":"Travel",
            "subcategory":"Hotels & Motels",
            "type":"Entertainment"
        }
    ],
    "sg:phone":"+1 662 393 4174",
    "sg:postcode":"38671",
    "sg:province":"MS",
    "wof:name":"Southern Inn & Suites",
    "wof:placetype":"venue"
},
  "geometry": {"coordinates":[-89.999306,34.990665],"type":"Point"}
}