{
  "type": "Feature",
  "properties": {
    "iso:country":"US",
    "sg:address":"3450 Mccracken Rd",
    "sg:city":"Hernando",
    "sg:classifiers":[
        {
            "category":"Utilities",
            "subcategory":"Mobile Phone",
            "type":"Services"
        },
        {
            "category":"Shopping",
            "subcategory":"Mobile Phones",
            "type":"Retail Goods"
        },
        {
            "category":"Utilities",
            "subcategory":"Telephone",
            "type":"Services"
        },
        {
            "category":"Manufacturing",
            "subcategory":"Electronics",
            "type":"Manufacturing & Wholesale Goods"
        }
    ],
    "sg:phone":"+1 662 429 8230",
    "sg:postcode":"38632",
    "sg:province":"MS",
    "sg:tags":[
        "telecommunications-equipment",
        "supply",
        "communication",
        "system",
        "wireless",
        "equipment",
        "cellular"
    ],
    "wof:name":"AT&T Wireless",
    "wof:placetype":"venue"
},
  "geometry": {"coordinates":[-89.971829,34.808518],"type":"Point"}
}