{
  "type": "Feature",
  "properties": {
    "addr:full":"980 Stateline Rd E Southaven MS 38671",
    "addr:housenumber":"980",
    "addr:postcode":"38671",
    "addr:street":"Stateline Rd E",
    "iso:country":"US",
    "sg:address":"980 Stateline Rd E",
    "sg:city":"Southaven",
    "sg:classifiers":[
        {
            "category":"Organizations",
            "subcategory":"Religious Organization",
            "type":"Services"
        }
    ],
    "sg:phone":"+1 662 342 6407",
    "sg:postcode":"38671",
    "sg:province":"MS",
    "sg:tags":[
        "church"
    ],
    "wof:name":"Brown Missionary Baptst Church",
    "wof:placetype":"venue"
},
  "geometry": {"coordinates":[-89.976618,34.991878],"type":"Point"}
}