{
  "type": "Feature",
  "properties": {
    "iso:country":"US",
    "sg:address":"721 Arlington St",
    "sg:city":"Jackson",
    "sg:classifiers":[
        {
            "category":"Real Estate",
            "subcategory":"Real Estate Agent",
            "type":"Services"
        }
    ],
    "sg:phone":"+1 601 352 1175",
    "sg:postcode":"39202",
    "sg:province":"MS",
    "wof:name":"Highland Properties",
    "wof:placetype":"venue"
},
  "geometry": {"coordinates":[-90.176694,32.31938],"type":"Point"}
}