{
  "type": "Feature",
  "properties": {
    "iso:country":"US",
    "sg:address":"1425 Lelia Dr",
    "sg:city":"Jackson",
    "sg:classifiers":[
        {
            "category":"Professional",
            "subcategory":"Lawyer & Legal Services",
            "type":"Services"
        }
    ],
    "sg:phone":"+1 601 362 1374",
    "sg:postcode":"39216",
    "sg:province":"MS",
    "sg:tags":[
        "attorney"
    ],
    "wof:name":"Smith & Smith Pllc",
    "wof:placetype":"venue"
},
  "geometry": {"coordinates":[-90.148719,32.332893],"type":"Point"}
}