{
  "type": "Feature",
  "properties": {
    "iso:country":"US",
    "sg:address":"600 Station St",
    "sg:city":"Waynesboro",
    "sg:classifiers":[
        {
            "category":"Autos & Motor Vehicles",
            "subcategory":"Auto Supplies",
            "type":"Retail Goods"
        }
    ],
    "sg:phone":"+1 601 671 0001",
    "sg:postcode":"39367",
    "sg:province":"MS",
    "sg:tags":[
        "battery"
    ],
    "wof:name":"J & B Batteries",
    "wof:placetype":"venue"
},
  "geometry": {"coordinates":[-88.64490000000001,31.673911],"type":"Point"}
}