{
  "type": "Feature",
  "properties": {
    "iso:country":"US",
    "sg:address":"647 Co Rd 157",
    "sg:city":"Coffeeville",
    "sg:classifiers":[
        {
            "category":"Freight",
            "type":"Transportation"
        }
    ],
    "sg:phone":"+1 662 675 2850",
    "sg:postcode":"38922",
    "sg:province":"MS",
    "sg:tags":[
        "trucking"
    ],
    "wof:name":"Cornerstone Trucking",
    "wof:placetype":"venue"
},
  "geometry": {"coordinates":[-89.72248,34.000982],"type":"Point"}
}