{
  "type": "Feature",
  "properties": {
    "iso:country":"US",
    "sg:address":"626 E Beach Blvd",
    "sg:city":"Long Beach",
    "sg:classifiers":[
        {
            "category":"Real Estate",
            "subcategory":"Real Estate Operator",
            "type":"Services"
        }
    ],
    "sg:phone":"+1 228 864 9719",
    "sg:postcode":"39560",
    "sg:province":"MS",
    "sg:tags":[
        "apartment"
    ],
    "wof:name":"Tiffany Gardens Apartments",
    "wof:placetype":"venue"
},
  "geometry": {"coordinates":[-89.13694599999999,30.350187],"type":"Point"}
}