{
  "type": "Feature",
  "properties": {
    "addr:full":"1990 S Frontage Rd Vicksburg MS 39180",
    "addr:housenumber":"1990",
    "addr:postcode":"39180",
    "addr:street":"S Frontage Rd",
    "iso:country":"US",
    "sg:address":"1990 S Frontage Rd",
    "sg:city":"Vicksburg",
    "sg:classifiers":[
        {
            "category":"Banks & Credit Unions",
            "subcategory":"Bank",
            "type":"Services"
        }
    ],
    "sg:phone":"+1 601 661 0240",
    "sg:postcode":"39180",
    "sg:province":"MS",
    "sg:tags":[
        "depository",
        "banking",
        "check",
        "cashing"
    ],
    "wof:name":"Express Check Advance",
    "wof:placetype":"venue"
},
  "geometry": {"coordinates":[-90.868233,32.322311],"type":"Point"}
}