{
  "type": "Feature",
  "properties": {
    "iso:country":"US",
    "sg:address":"506 Academy St",
    "sg:city":"Okolona",
    "sg:classifiers":[
        {
            "category":"Organizations",
            "subcategory":"Religious Organization",
            "type":"Services"
        }
    ],
    "sg:phone":"+1 662 447 3307",
    "sg:postcode":"38860",
    "sg:province":"MS",
    "sg:tags":[
        "church"
    ],
    "wof:name":"Jehovah Jireh CME Church",
    "wof:placetype":"venue"
},
  "geometry": {"coordinates":[-88.755375,34.010353],"type":"Point"}
}