{
  "type": "Feature",
  "properties": {
    "iso:country":"US",
    "sg:address":"4183 Middle Glading Rd",
    "sg:city":"Magnolia",
    "sg:classifiers":[
        {
            "category":"Health Services",
            "subcategory":"Medical Lab",
            "type":"Services"
        }
    ],
    "sg:phone":"+1 601 684 1621",
    "sg:postcode":"39652",
    "sg:province":"MS",
    "sg:tags":[
        "laboratory"
    ],
    "wof:name":"Jimmy Ross Dental Lab",
    "wof:placetype":"venue"
},
  "geometry": {"coordinates":[-90.60741899999999,31.166381],"type":"Point"}
}