{
  "type": "Feature",
  "properties": {
    "iso:country":"US",
    "sg:address":"2311 Belair St",
    "sg:city":"Pascagoula",
    "sg:classifiers":[
        {
            "category":"Wholesale",
            "subcategory":"Seafood",
            "type":"Manufacturing & Wholesale Goods"
        }
    ],
    "sg:phone":"+1 228 762 2922",
    "sg:postcode":"39567",
    "sg:province":"MS",
    "wof:name":"Phil Bryant Seafood",
    "wof:placetype":"venue"
},
  "geometry": {"coordinates":[-88.53563699999999,30.358954],"type":"Point"}
}