{
  "type": "Feature",
  "properties": {
    "iso:country":"US",
    "sg:address":"1410 May St",
    "sg:city":"Clarksdale",
    "sg:classifiers":[
        {
            "category":"Professional",
            "type":"Services"
        }
    ],
    "sg:phone":"+1 662 621 2525",
    "sg:postcode":"38614",
    "sg:province":"MS",
    "sg:tags":[
        "establishment"
    ],
    "wof:name":"Growth & Co Inc",
    "wof:placetype":"venue"
},
  "geometry": {"coordinates":[-90.60498699999999,34.205167],"type":"Point"}
}