{
  "type": "Feature",
  "properties": {
    "iso:country":"US",
    "sg:address":"208 Winterset Dr",
    "sg:city":"Starkville",
    "sg:classifiers":[
        {
            "category":"Insurance",
            "subcategory":"Hazard Insurance",
            "type":"Services"
        }
    ],
    "sg:phone":"+1 662 323 9111",
    "sg:postcode":"39759",
    "sg:province":"MS",
    "sg:tags":[
        "carrier"
    ],
    "wof:name":"Jaudon & Associates Insurance",
    "wof:placetype":"venue"
},
  "geometry": {"coordinates":[-88.819441,33.433917],"type":"Point"}
}