{
  "type": "Feature",
  "properties": {
    "iso:country":"US",
    "sg:address":"213 W Wiygul St",
    "sg:city":"Fulton",
    "sg:classifiers":[
        {
            "category":"Government",
            "subcategory":"Office",
            "type":"Public Place"
        }
    ],
    "sg:phone":"+1 662 862 7556",
    "sg:postcode":"38843",
    "sg:province":"MS",
    "sg:tags":[
        "city",
        "program"
    ],
    "wof:name":"Fulton Sanitation Dept",
    "wof:placetype":"venue"
},
  "geometry": {"coordinates":[-88.409076,34.272809],"type":"Point"}
}