{
  "type": "Feature",
  "properties": {
    "iso:country":"US",
    "sg:address":"302 E Franklin St",
    "sg:city":"Carthage",
    "sg:classifiers":[
        {
            "category":"Professional",
            "subcategory":"Business Services",
            "type":"Services"
        }
    ],
    "sg:phone":"+1 601 267 0749",
    "sg:postcode":"39051",
    "sg:province":"MS",
    "wof:name":"Etheridge Enterprises Inc",
    "wof:placetype":"venue"
},
  "geometry": {"coordinates":[-89.528316,32.738265],"type":"Point"}
}