{
  "type": "Feature",
  "properties": {
    "iso:country":"US",
    "sg:address":"1002 S 13th St",
    "sg:city":"Columbus",
    "sg:classifiers":[
        {
            "category":"Home & Garden",
            "subcategory":"Hardware",
            "type":"Retail Goods"
        }
    ],
    "sg:phone":"+1 662 328 8073",
    "sg:postcode":"39701",
    "sg:province":"MS",
    "wof:name":"Military Hardware & Garden Ctr",
    "wof:placetype":"venue"
},
  "geometry": {"coordinates":[-88.417444,33.485954],"type":"Point"}
}