{
  "type": "Feature",
  "properties": {
    "addr:full":"1973 Cliff Gookin Blvd Tupelo MS 38801",
    "addr:housenumber":"1973",
    "addr:postcode":"38801",
    "addr:street":"Cliff Gookin Blvd",
    "iso:country":"US",
    "sg:address":"1973 Cliff Gookin Blvd",
    "sg:city":"Tupelo",
    "sg:classifiers":[
        {
            "category":"Local Transit",
            "type":"Transportation"
        }
    ],
    "sg:phone":"+1 662 840 8888",
    "sg:postcode":"38801",
    "sg:province":"MS",
    "sg:tags":[
        "auto",
        "rental"
    ],
    "wof:name":"U-Save Auto Rental",
    "wof:placetype":"venue"
},
  "geometry": {"coordinates":[-88.76424900000001,34.233915],"type":"Point"}
}