{
  "type": "Feature",
  "properties": {
    "iso:country":"US",
    "sg:address":"420 W Sweet Potato St",
    "sg:city":"Vardaman",
    "sg:classifiers":[
        {
            "category":"Wholesale",
            "subcategory":"Fruits & Vegetables",
            "type":"Manufacturing & Wholesale Goods"
        }
    ],
    "sg:phone":"+1 662 682 9575",
    "sg:postcode":"38878",
    "sg:province":"MS",
    "wof:name":"SMP Southeast Marketing Inc",
    "wof:placetype":"venue"
},
  "geometry": {"coordinates":[-89.183397,33.875513],"type":"Point"}
}