{
  "type": "Feature",
  "properties": {
    "addr:full":"109 Lowe Cir Clinton MS 39056",
    "addr:housenumber":"109",
    "addr:postcode":"39056",
    "addr:street":"Lowe Cir",
    "iso:country":"US",
    "sg:address":"109 Lowe Cir",
    "sg:city":"Clinton",
    "sg:classifiers":[
        {
            "category":"Professional",
            "subcategory":"Art Services",
            "type":"Services"
        }
    ],
    "sg:phone":"+1 601 924 4520",
    "sg:postcode":"39056",
    "sg:province":"MS",
    "sg:tags":[
        "commercial",
        "design"
    ],
    "wof:name":"Lynn Reid",
    "wof:placetype":"venue"
},
  "geometry": {"coordinates":[-90.340037,32.321409],"type":"Point"}
}