{
  "type": "Feature",
  "properties": {
    "iso:country":"US",
    "sg:address":"12400 Lisa Dr",
    "sg:city":"Gulfport",
    "sg:classifiers":[
        {
            "category":"Wholesale",
            "subcategory":"Farm Supplies",
            "type":"Manufacturing & Wholesale Goods"
        }
    ],
    "sg:phone":"+1 228 831 0412",
    "sg:postcode":"39503",
    "sg:province":"MS",
    "sg:tags":[
        "erosion"
    ],
    "wof:name":"Coastal Hydrograss",
    "wof:placetype":"venue"
},
  "geometry": {"coordinates":[-89.212975,30.467251],"type":"Point"}
}