{
  "type": "Feature",
  "properties": {
    "addr:full":"19 Feltus St Natchez MS 39120",
    "addr:housenumber":"19",
    "addr:postcode":"39120",
    "addr:street":"Feltus St",
    "iso:country":"US",
    "sg:address":"19 Feltus St",
    "sg:city":"Natchez",
    "sg:classifiers":[
        {
            "category":"Autos & Motor Vehicles",
            "subcategory":"Automobile Sales",
            "type":"Retail Goods"
        }
    ],
    "sg:phone":"+1 601 445 8850",
    "sg:postcode":"39120",
    "sg:province":"MS",
    "sg:tags":[
        "truck"
    ],
    "wof:name":"Waters International Trucks",
    "wof:placetype":"venue"
},
  "geometry": {"coordinates":[-91.363764,31.546006],"type":"Point"}
}