{
  "type": "Feature",
  "properties": {
    "iso:country":"US",
    "sg:address":"16242 Crestview Dr",
    "sg:city":"Gulfport",
    "sg:classifiers":[
        {
            "category":"Building & Trades",
            "subcategory":"Pest Control",
            "type":"Services"
        }
    ],
    "sg:phone":"+1 228 832 2408",
    "sg:postcode":"39503",
    "sg:province":"MS",
    "wof:name":"Byrds Pest Control",
    "wof:placetype":"venue"
},
  "geometry": {"coordinates":[-89.110556,30.458187],"type":"Point"}
}