{
  "type": "Feature",
  "properties": {
    "addr:full":"324 Williamson Ave Philadelphia MS 39350",
    "addr:housenumber":"324",
    "addr:postcode":"39350",
    "addr:street":"Williamson Ave",
    "iso:country":"US",
    "sg:address":"324 Williamson Ave",
    "sg:city":"Philadelphia",
    "sg:classifiers":[
        {
            "category":"Building & Trades",
            "subcategory":"Plumbing",
            "type":"Services"
        }
    ],
    "sg:phone":"+1 601 656 4771",
    "sg:postcode":"39350",
    "sg:province":"MS",
    "sg:tags":[
        "conditioning",
        "air",
        "system",
        "contractor"
    ],
    "wof:name":"James Williamson Co",
    "wof:placetype":"venue"
},
  "geometry": {"coordinates":[-89.085555,32.76781],"type":"Point"}
}