{
  "type": "Feature",
  "properties": {
    "iso:country":"US",
    "sg:address":"9100 E Sandidge Rd",
    "sg:city":"Olive Branch",
    "sg:classifiers":[
        {
            "category":"Organizations",
            "subcategory":"Religious Organization",
            "type":"Services"
        }
    ],
    "sg:phone":"+1 662 895 5102",
    "sg:postcode":"38654",
    "sg:province":"MS",
    "wof:name":"Olive Branch Church Of Christ",
    "wof:placetype":"venue"
},
  "geometry": {"coordinates":[-89.828288,34.947793],"type":"Point"}
}