{
  "type": "Feature",
  "properties": {
    "addr:full":"1 Jones Rd Natchez MS 39120",
    "addr:housenumber":"1",
    "addr:postcode":"39120",
    "addr:street":"Jones Rd",
    "iso:country":"US",
    "sg:address":"1 Jones Rd",
    "sg:city":"Natchez",
    "sg:classifiers":[
        {
            "category":"Professional",
            "subcategory":"Detective & Security Services",
            "type":"Services"
        }
    ],
    "sg:phone":"+1 601 445 4300",
    "sg:postcode":"39120",
    "sg:province":"MS",
    "sg:tags":[
        "guard",
        "patrol"
    ],
    "wof:name":"Riverton Security Agency",
    "wof:placetype":"venue"
},
  "geometry": {"coordinates":[-91.28637999999999,31.557679],"type":"Point"}
}