{
  "type": "Feature",
  "properties": {
    "iso:country":"US",
    "sg:address":"119 Montague St",
    "sg:city":"Hattiesburg",
    "sg:classifiers":[
        {
            "category":"Professional",
            "subcategory":"Management & Consulting",
            "type":"Services"
        }
    ],
    "sg:phone":"+1 601 584 7988",
    "sg:postcode":"39401",
    "sg:province":"MS",
    "sg:tags":[
        "retail",
        "direct",
        "sales"
    ],
    "wof:name":"Simmons Sellers Inc",
    "wof:placetype":"venue"
},
  "geometry": {"coordinates":[-89.301019,31.334203],"type":"Point"}
}