{
  "type": "Feature",
  "properties": {
    "iso:country":"US",
    "sg:address":"422 S Gloster St",
    "sg:city":"Tupelo",
    "sg:classifiers":[
        {
            "category":"Banks & Credit Unions",
            "subcategory":"Bank",
            "type":"Services"
        }
    ],
    "sg:phone":"+1 662 844 4656",
    "sg:postcode":"38801",
    "sg:province":"MS",
    "sg:tags":[
        "cashing",
        "check"
    ],
    "wof:name":"Economy Check Advance",
    "wof:placetype":"venue"
},
  "geometry": {"coordinates":[-88.71614,34.251937],"type":"Point"}
}