{
  "type": "Feature",
  "properties": {
    "iso:country":"US",
    "sg:address":"2005 Church St",
    "sg:city":"Byhalia",
    "sg:phone":"+1 662 838 6197",
    "sg:postcode":"38611",
    "sg:province":"MS",
    "sg:tags":[
        "farm",
        "corn",
        "soybean"
    ],
    "wof:name":"Phillip Malone",
    "wof:placetype":"venue"
},
  "geometry": {"coordinates":[-89.67982000000001,34.868988],"type":"Point"}
}