{
  "type": "Feature",
  "properties": {
    "iso:country":"US",
    "sg:address":"172 Morgan Seal Rd",
    "sg:city":"Picayune",
    "sg:classifiers":[
        {
            "category":"Professional",
            "subcategory":"Business Services",
            "type":"Services"
        }
    ],
    "sg:phone":"+1 601 798 7907",
    "sg:postcode":"39466",
    "sg:province":"MS",
    "wof:name":"Instant Bail Bonding",
    "wof:placetype":"venue"
},
  "geometry": {"coordinates":[-89.78335199999999,30.557389],"type":"Point"}
}