{
  "type": "Feature",
  "properties": {
    "iso:country":"US",
    "sg:address":"152 Hwy 45 S",
    "sg:city":"West Point",
    "sg:classifiers":[
        {
            "category":"Autos & Motor Vehicles",
            "subcategory":"Automobile Sales",
            "type":"Retail Goods"
        }
    ],
    "sg:phone":"+1 662 494 5438",
    "sg:postcode":"39773",
    "sg:province":"MS",
    "sg:tags":[
        "car",
        "dealer"
    ],
    "wof:name":"Michhell Chevrolet",
    "wof:placetype":"venue"
},
  "geometry": {"coordinates":[-88.65899400000001,33.606321],"type":"Point"}
}