{
  "type": "Feature",
  "properties": {
    "iso:country":"US",
    "sg:address":"560 Division St",
    "sg:city":"Biloxi",
    "sg:classifiers":[
        {
            "category":"Restaurant",
            "type":"Food & Drink"
        }
    ],
    "sg:phone":"+1 228 374 5085",
    "sg:postcode":"39530",
    "sg:province":"MS",
    "wof:name":"Twin's Harbor LLC",
    "wof:placetype":"venue"
},
  "geometry": {"coordinates":[-88.87963999999999,30.403209],"type":"Point"}
}