{
  "type": "Feature",
  "properties": {
    "iso:country":"US",
    "sg:address":"34165 Hwy 25 N",
    "sg:city":"Golden",
    "sg:classifiers":[
        {
            "category":"Manufacturing",
            "subcategory":"Lumber",
            "type":"Manufacturing & Wholesale Goods"
        }
    ],
    "sg:phone":"+1 662 585 3417",
    "sg:postcode":"38847",
    "sg:province":"MS",
    "sg:tags":[
        "logging"
    ],
    "wof:name":"J T Horn Logging Inc",
    "wof:placetype":"venue"
},
  "geometry": {"coordinates":[-88.22447,34.457049],"type":"Point"}
}