{
  "type": "Feature",
  "properties": {
    "iso:country":"US",
    "sg:address":"28850 Hwy 25 N",
    "sg:city":"Golden",
    "sg:classifiers":[
        {
            "category":"Restaurant",
            "type":"Food & Drink"
        }
    ],
    "sg:phone":"+1 662 585 3796",
    "sg:postcode":"38847",
    "sg:province":"MS",
    "sg:tags":[
        "eating"
    ],
    "wof:name":"Reeves Fish & Steak House",
    "wof:placetype":"venue"
},
  "geometry": {"coordinates":[-88.292462,34.415975],"type":"Point"}
}