{
  "type": "Feature",
  "properties": {
    "iso:country":"US",
    "sg:address":"282 Maxie Dr",
    "sg:city":"Brandon",
    "sg:classifiers":[
        {
            "category":"Professional",
            "subcategory":"Accounting & Tax Preparation",
            "type":"Services"
        }
    ],
    "sg:phone":"+1 601 825 1310",
    "sg:postcode":"39042",
    "sg:province":"MS",
    "sg:tags":[
        "accountant"
    ],
    "wof:name":"Barlow Walker & Hill",
    "wof:placetype":"venue"
},
  "geometry": {"coordinates":[-90.00805699999999,32.280718],"type":"Point"}
}