{
  "type": "Feature",
  "properties": {
    "addr:full":"3017 E Reed Rd Greenville MS 38703",
    "addr:housenumber":"3017",
    "addr:postcode":"38703",
    "addr:street":"E Reed Rd",
    "iso:country":"US",
    "sg:address":"3017 E Reed Rd",
    "sg:city":"Greenville",
    "sg:classifiers":[
        {
            "category":"Government",
            "subcategory":"Office",
            "type":"Public Place"
        }
    ],
    "sg:phone":"+1 601 334 9472",
    "sg:postcode":"38703",
    "sg:province":"MS",
    "sg:tags":[
        "use",
        "land",
        "commodity",
        "related",
        "program",
        "administers"
    ],
    "wof:name":"Farm Service Agency",
    "wof:placetype":"venue"
},
  "geometry": {"coordinates":[-91.01000000000001,33.385687],"type":"Point"}
}