{
  "type": "Feature",
  "properties": {
    "addr:full":"1015 Rogers St Laurel MS 39440",
    "addr:housenumber":"1015",
    "addr:postcode":"39440",
    "addr:street":"Rogers St",
    "iso:country":"US",
    "sg:address":"1015 Rogers St",
    "sg:city":"Laurel",
    "sg:classifiers":[
        {
            "category":"Home & Garden",
            "subcategory":"Building Materials",
            "type":"Retail Goods"
        }
    ],
    "sg:phone":"+1 601 428 5602",
    "sg:postcode":"39440",
    "sg:province":"MS",
    "sg:tags":[
        "glass",
        "window",
        "plate"
    ],
    "wof:name":"City Glass Co",
    "wof:placetype":"venue"
},
  "geometry": {"coordinates":[-89.13831399999999,31.690402],"type":"Point"}
}