{
  "type": "Feature",
  "properties": {
    "iso:country":"US",
    "sg:address":"235 N 15th Ave",
    "sg:city":"Laurel",
    "sg:classifiers":[
        {
            "category":"Personal",
            "subcategory":"Beauty Salon",
            "type":"Services"
        }
    ],
    "sg:phone":"+1 601 649 6088",
    "sg:postcode":"39440",
    "sg:province":"MS",
    "sg:tags":[
        "shop"
    ],
    "wof:name":"Images Day Salon",
    "wof:placetype":"venue"
},
  "geometry": {"coordinates":[-89.145358,31.69181],"type":"Point"}
}