{
  "type": "Feature",
  "properties": {
    "iso:country":"US",
    "sg:address":"607 Mary Grove Church Rd",
    "sg:city":"Mendenhall",
    "sg:classifiers":[
        {
            "category":"Organizations",
            "subcategory":"Religious Organization",
            "type":"Services"
        }
    ],
    "sg:phone":"+1 601 849 3895",
    "sg:postcode":"39114",
    "sg:province":"MS",
    "wof:name":"Mary Grove Baptist Church",
    "wof:placetype":"venue"
},
  "geometry": {"coordinates":[-89.767077,31.922709],"type":"Point"}
}