{
  "type": "Feature",
  "properties": {
    "iso:country":"US",
    "sg:address":"8057 Longwood Dr",
    "sg:city":"Olive Branch",
    "sg:classifiers":[
        {
            "category":"Wholesale",
            "subcategory":"Farm Supplies",
            "type":"Manufacturing & Wholesale Goods"
        }
    ],
    "sg:phone":"+1 662 895 5687",
    "sg:postcode":"38654",
    "sg:province":"MS",
    "sg:tags":[
        "bean",
        "corn",
        "cotton"
    ],
    "wof:name":"Lyon Cattle Grain",
    "wof:placetype":"venue"
},
  "geometry": {"coordinates":[-89.830468,34.976911],"type":"Point"}
}