{
  "type": "Feature",
  "properties": {
    "iso:country":"US",
    "sg:address":"12504 State Hwy 57",
    "sg:city":"Ocean Springs",
    "sg:classifiers":[
        {
            "category":"Shopping",
            "subcategory":"Computers & Home Electronics",
            "type":"Retail Goods"
        }
    ],
    "sg:phone":"+1 228 826 9669",
    "sg:postcode":"39565",
    "sg:province":"MS",
    "sg:tags":[
        "equipment",
        "dealer"
    ],
    "wof:name":"Computer Store",
    "wof:placetype":"venue"
},
  "geometry": {"coordinates":[-88.68974300000001,30.525076],"type":"Point"}
}