{
  "type": "Feature",
  "properties": {
    "iso:country":"US",
    "sg:address":"609 Glassco St",
    "sg:city":"Cleveland",
    "sg:classifiers":[
        {
            "category":"Real Estate",
            "subcategory":"Real Estate Operator",
            "type":"Services"
        }
    ],
    "sg:phone":"+1 662 846 0784",
    "sg:postcode":"38732",
    "sg:province":"MS",
    "sg:tags":[
        "apartment"
    ],
    "wof:name":"South Central Village Apts",
    "wof:placetype":"venue"
},
  "geometry": {"coordinates":[-90.718547,33.729529],"type":"Point"}
}