{
  "type": "Feature",
  "properties": {
    "iso:country":"US",
    "sg:address":"4503 Methodist Farm Rd",
    "sg:city":"Jackson",
    "sg:classifiers":[
        {
            "category":"Manufacturing",
            "subcategory":"Motor Vehicles & Parts",
            "type":"Manufacturing & Wholesale Goods"
        }
    ],
    "sg:phone":"+1 601 981 7686",
    "sg:postcode":"39213",
    "sg:province":"MS",
    "sg:tags":[
        "automobile",
        "supply"
    ],
    "wof:name":"Quality Auto",
    "wof:placetype":"venue"
},
  "geometry": {"coordinates":[-90.22272100000001,32.35601],"type":"Point"}
}