{
  "type": "Feature",
  "properties": {
    "iso:country":"US",
    "sg:address":"746 Nelson St",
    "sg:city":"Greenville",
    "sg:classifiers":[
        {
            "category":"Personal",
            "subcategory":"Barber",
            "type":"Services"
        }
    ],
    "sg:phone":"+1 662 332 5155",
    "sg:postcode":"38701",
    "sg:province":"MS",
    "sg:tags":[
        "shop"
    ],
    "wof:name":"Unique Barber Shop",
    "wof:placetype":"venue"
},
  "geometry": {"coordinates":[-91.05305199999999,33.413643],"type":"Point"}
}