{
  "type": "Feature",
  "properties": {
    "addr:full":"307 N Main St Picayune MS 39466",
    "addr:housenumber":"307",
    "addr:postcode":"39466",
    "addr:street":"N Main St",
    "iso:country":"US",
    "sg:address":"307 N Main St",
    "sg:city":"Picayune",
    "sg:classifiers":[
        {
            "category":"Real Estate",
            "subcategory":"Real Estate Agent",
            "type":"Services"
        }
    ],
    "sg:phone":"+1 601 798 3493",
    "sg:postcode":"39466",
    "sg:province":"MS",
    "wof:name":"Magnolia Properties",
    "wof:placetype":"venue"
},
  "geometry": {"coordinates":[-89.680706,30.52726],"type":"Point"}
}