{
  "type": "Feature",
  "properties": {
    "iso:country":"US",
    "sg:address":"5220 Galaxie Dr",
    "sg:city":"Jackson",
    "sg:classifiers":[
        {
            "category":"Professional",
            "subcategory":"Business Services",
            "type":"Services"
        }
    ],
    "sg:phone":"+1 601 362 4321",
    "sg:postcode":"39206",
    "sg:province":"MS",
    "sg:tags":[
        "interior",
        "consultant",
        "design",
        "decorator"
    ],
    "wof:name":"Suburban Decorating",
    "wof:placetype":"venue"
},
  "geometry": {"coordinates":[-90.151782,32.369134],"type":"Point"}
}