{
  "type": "Feature",
  "properties": {
    "addr:full":"2847 Hwy 1 S Greenville MS 38701",
    "addr:housenumber":"2847",
    "addr:postcode":"38701",
    "addr:street":"Hwy 1 S",
    "iso:country":"US",
    "sg:address":"2847 Hwy 1 S",
    "sg:city":"Greenville",
    "sg:classifiers":[
        {
            "category":"Autos & Motor Vehicles",
            "subcategory":"Automobile Sales",
            "type":"Retail Goods"
        }
    ],
    "sg:phone":"+1 662 332 6640",
    "sg:postcode":"38701",
    "sg:province":"MS",
    "sg:tags":[
        "car",
        "used",
        "dealer"
    ],
    "wof:name":"Terry's Auto Sales",
    "wof:placetype":"venue"
},
  "geometry": {"coordinates":[-91.042439,33.341863],"type":"Point"}
}