{
  "type": "Feature",
  "properties": {
    "iso:country":"US",
    "sg:address":"9905 Hwy 433 S",
    "sg:city":"Benton",
    "sg:phone":"+1 662 673 2281",
    "sg:postcode":"39039",
    "sg:province":"MS",
    "sg:tags":[
        "farm",
        "soybean"
    ],
    "wof:name":"Clarence Vandevere",
    "wof:placetype":"venue"
},
  "geometry": {"coordinates":[-90.26112999999999,32.73133],"type":"Point"}
}