{
  "type": "Feature",
  "properties": {
    "addr:full":"5040 Hwy 3 Redwood MS 39156",
    "addr:housenumber":"5040",
    "addr:postcode":"39156",
    "addr:street":"Hwy 3",
    "iso:country":"US",
    "sg:address":"5040 Hwy 3",
    "sg:city":"Redwood",
    "sg:classifiers":[
        {
            "category":"Farming",
            "subcategory":"Farm",
            "type":"Manufacturing & Wholesale Goods"
        }
    ],
    "sg:phone":"+1 601 638 3660",
    "sg:postcode":"39156",
    "sg:province":"MS",
    "wof:name":"B N Simrall & Son Inc",
    "wof:placetype":"venue"
},
  "geometry": {"coordinates":[-90.75251900000001,32.537481],"type":"Point"}
}