{
  "type": "Feature",
  "properties": {
    "addr:full":"17670 Hwy 18 Raymond MS 39154",
    "addr:housenumber":"17670",
    "addr:postcode":"39154",
    "addr:street":"Hwy 18 Raymond",
    "iso:country":"US",
    "sg:address":"17670 Hwy 18",
    "sg:city":"Raymond",
    "sg:classifiers":[
        {
            "category":"Organizations",
            "subcategory":"Religious Organization",
            "type":"Services"
        }
    ],
    "sg:phone":"+1 601 857 2447",
    "sg:postcode":"39154",
    "sg:province":"MS",
    "sg:tags":[
        "church"
    ],
    "wof:name":"Eagle Ridge Community Church",
    "wof:placetype":"venue"
},
  "geometry": {"coordinates":[-90.46357399999999,32.217608],"type":"Point"}
}