{
  "type": "Feature",
  "properties": {
    "iso:country":"US",
    "sg:address":"228 N Main St",
    "sg:city":"Yazoo City",
    "sg:classifiers":[
        {
            "category":"Organizations",
            "subcategory":"Religious Organization",
            "type":"Services"
        }
    ],
    "sg:phone":"+1 662 746 1226",
    "sg:postcode":"39194",
    "sg:province":"MS",
    "sg:tags":[
        "clergy"
    ],
    "wof:name":"First Presbyterian Church",
    "wof:placetype":"venue"
},
  "geometry": {"coordinates":[-90.412817,32.848854],"type":"Point"}
}