{
  "type": "Feature",
  "properties": {
    "addr:full":"3969 State Hwy 53 Poplarville MS 39470",
    "addr:housenumber":"3969",
    "addr:postcode":"39470",
    "addr:street":"State Hwy 53",
    "iso:country":"US",
    "sg:address":"3969 State Hwy 53",
    "sg:city":"Poplarville",
    "sg:classifiers":[
        {
            "category":"Manufacturing",
            "subcategory":"Lumber",
            "type":"Manufacturing & Wholesale Goods"
        }
    ],
    "sg:phone":"+1 601 795 4912",
    "sg:postcode":"39470",
    "sg:province":"MS",
    "sg:tags":[
        "government"
    ],
    "wof:name":"Forestry Dept",
    "wof:placetype":"venue"
},
  "geometry": {"coordinates":[-89.498503,30.77799],"type":"Point"}
}