{
  "type": "Feature",
  "properties": {
    "addr:full":"307 W College St Booneville MS 38829",
    "addr:housenumber":"307",
    "addr:postcode":"38829",
    "addr:street":"W College St",
    "iso:country":"US",
    "sg:address":"307 W College St",
    "sg:city":"Booneville",
    "sg:classifiers":[
        {
            "category":"Insurance",
            "subcategory":"Insurance Agent",
            "type":"Services"
        }
    ],
    "sg:phone":"+1 662 728 9595",
    "sg:postcode":"38829",
    "sg:province":"MS",
    "wof:name":"State Farm Insurance",
    "wof:placetype":"venue"
},
  "geometry": {"coordinates":[-88.56467600000001,34.654422],"type":"Point"}
}