{
  "type": "Feature",
  "properties": {
    "addr:full":"8859 Goodman Rd Olive Branch MS 38654",
    "addr:housenumber":"8859",
    "addr:postcode":"38654",
    "addr:street":"Goodman Rd",
    "iso:country":"US",
    "sg:address":"8859 Goodman Rd",
    "sg:city":"Olive Branch",
    "sg:classifiers":[
        {
            "category":"Restaurant",
            "type":"Food & Drink"
        }
    ],
    "sg:menulink":"http://www.allmenus.com/ms/olive-branch/76318-dominos-pizza/menu/",
    "sg:phone":"+1 662 895 3005",
    "sg:postcode":"38654",
    "sg:province":"MS",
    "sg:tags":[
        "american",
        "wing",
        "pizza"
    ],
    "wof:name":"Domino's Pizza",
    "wof:placetype":"venue"
},
  "geometry": {"coordinates":[-89.83304699999999,34.962203],"type":"Point"}
}