{
  "type": "Feature",
  "properties": {
    "iso:country":"US",
    "sg:address":"1615 Tissington Dr",
    "sg:city":"Horn Lake",
    "sg:classifiers":[
        {
            "category":"Professional",
            "subcategory":"Detective & Security Services",
            "type":"Services"
        }
    ],
    "sg:phone":"+1 901 219 4144",
    "sg:postcode":"38637",
    "sg:province":"MS",
    "sg:tags":[
        "system"
    ],
    "wof:name":"Ionic Security",
    "wof:placetype":"venue"
},
  "geometry": {"coordinates":[-90.017989,34.941717],"type":"Point"}
}