{
  "type": "Feature",
  "properties": {
    "addr:full":"4045 Sumatra Rd Pearlington MS 39572",
    "addr:housenumber":"4045",
    "addr:postcode":"39572",
    "addr:street":"Sumatra Rd",
    "iso:country":"US",
    "sg:address":"4045 Sumatra Rd",
    "sg:city":"Pearlington",
    "sg:classifiers":[
        {
            "category":"Professional",
            "subcategory":"Management & Consulting",
            "type":"Services"
        }
    ],
    "sg:phone":"+1 228 533 7727",
    "sg:postcode":"39572",
    "sg:province":"MS",
    "sg:tags":[
        "training",
        "instruction",
        "safety"
    ],
    "wof:name":"Vk Safety",
    "wof:placetype":"venue"
},
  "geometry": {"coordinates":[-89.609526,30.237103],"type":"Point"}
}