{
  "type": "Feature",
  "properties": {
    "addr:full":"261 Co Rd 301 Oxford MS 38655",
    "addr:housenumber":"261;301",
    "addr:postcode":"38655",
    "addr:street":"Co Rd",
    "iso:country":"US",
    "sg:address":"261 Co Rd 301",
    "sg:city":"Oxford",
    "sg:classifiers":[
        {
            "category":"Recreation",
            "type":"Entertainment"
        }
    ],
    "sg:phone":"+1 662 236 3332",
    "sg:postcode":"38655",
    "sg:province":"MS",
    "sg:tags":[
        "personal"
    ],
    "wof:name":"Skate Place",
    "wof:placetype":"venue"
},
  "geometry": {"coordinates":[-89.52312000000001,34.317285],"type":"Point"}
}