{
  "type": "Feature",
  "properties": {
    "addr:full":"6145 Causeyville Rd Meridian MS 39301",
    "addr:housenumber":"6145",
    "addr:postcode":"39301",
    "addr:street":"Causeyville Rd",
    "iso:country":"US",
    "sg:address":"6145 Causeyville Rd",
    "sg:city":"Meridian",
    "sg:classifiers":[
        {
            "category":"Retail",
            "subcategory":"Auto Repair",
            "type":"Services"
        }
    ],
    "sg:phone":"+1 601 644 9972",
    "sg:postcode":"39301",
    "sg:province":"MS",
    "sg:tags":[
        "repairing",
        "automobile"
    ],
    "wof:name":"Spiller Automotive",
    "wof:placetype":"venue"
},
  "geometry": {"coordinates":[-88.56008300000001,32.25757],"type":"Point"}
}