{
  "type": "Feature",
  "properties": {
    "iso:country":"US",
    "sg:address":"1024 Washington Ave",
    "sg:city":"Greenville",
    "sg:classifiers":[
        {
            "category":"Professional",
            "subcategory":"Engineering",
            "type":"Services"
        }
    ],
    "sg:phone":"+1 662 378 8825",
    "sg:postcode":"38701",
    "sg:province":"MS",
    "sg:tags":[
        "architectural"
    ],
    "wof:name":"Oakman-Harvey Architects",
    "wof:placetype":"venue"
},
  "geometry": {"coordinates":[-91.052224,33.406638],"type":"Point"}
}