{
  "type": "Feature",
  "properties": {
    "iso:country":"US",
    "sg:address":"8195 Woolmarket Rd",
    "sg:city":"Biloxi",
    "sg:classifiers":[
        {
            "category":"Building & Trades",
            "subcategory":"Electrical",
            "type":"Services"
        },
        {
            "category":"Building & Trades",
            "subcategory":"Construction",
            "type":"Services"
        }
    ],
    "sg:phone":"+1 228 396 2888",
    "sg:postcode":"39532",
    "sg:province":"MS",
    "sg:tags":[
        "audit",
        "modem",
        "direct",
        "cable",
        "sales"
    ],
    "wof:name":"Cable Marketing & Installation",
    "wof:placetype":"venue"
},
  "geometry": {"coordinates":[-88.973094,30.469741],"type":"Point"}
}