{
  "type": "Feature",
  "properties": {
    "iso:country":"US",
    "sg:address":"709 Longview St",
    "sg:city":"Vicksburg",
    "sg:classifiers":[
        {
            "category":"Shopping",
            "subcategory":"Books",
            "type":"Retail Goods"
        }
    ],
    "sg:phone":"+1 601 636 8639",
    "sg:postcode":"39180",
    "sg:province":"MS",
    "wof:name":"Bookstore The",
    "wof:placetype":"venue"
},
  "geometry": {"coordinates":[-90.89017,32.295309],"type":"Point"}
}