{
  "type": "Feature",
  "properties": {
    "addr:full":"1289 Williams Lake Rd Bolton MS 39041",
    "addr:housenumber":"1289",
    "addr:postcode":"39041",
    "addr:street":"Williams Lake Rd",
    "iso:country":"US",
    "sg:address":"1289 Williams Lake Rd",
    "sg:city":"Bolton",
    "sg:classifiers":[
        {
            "category":"Organizations",
            "subcategory":"Religious Organization",
            "type":"Services"
        }
    ],
    "sg:phone":"+1 601 866 7646",
    "sg:postcode":"39041",
    "sg:province":"MS",
    "wof:name":"Church Of God In Christ",
    "wof:placetype":"venue"
},
  "geometry": {"coordinates":[-90.47188199999999,32.373163],"type":"Point"}
}