{
  "type": "Feature",
  "properties": {
    "iso:country":"US",
    "sg:address":"490 Livingston Vernon Rd",
    "sg:city":"Flora",
    "sg:classifiers":[
        {
            "category":"Food & Beverages",
            "subcategory":"Groceries & Convenience Stores",
            "type":"Retail Goods"
        }
    ],
    "sg:phone":"+1 601 879 3638",
    "sg:postcode":"39071",
    "sg:province":"MS",
    "sg:tags":[
        "grocer"
    ],
    "wof:name":"Kearney Park Grocery",
    "wof:placetype":"venue"
},
  "geometry": {"coordinates":[-90.31674700000001,32.589673],"type":"Point"}
}