{
  "type": "Feature",
  "properties": {
    "iso:country":"US",
    "sg:address":"400 Holland Ave",
    "sg:city":"Philadelphia",
    "sg:classifiers":[
        {
            "category":"Food & Beverages",
            "subcategory":"Groceries & Convenience Stores",
            "type":"Retail Goods"
        }
    ],
    "sg:phone":"+1 601 389 5400",
    "sg:postcode":"39350",
    "sg:province":"MS",
    "wof:name":"One Stop Discount Tobacco Inc",
    "wof:placetype":"venue"
},
  "geometry": {"coordinates":[-89.10615199999999,32.77171],"type":"Point"}
}