{
  "type": "Feature",
  "properties": {
    "iso:country":"US",
    "sg:address":"3023 Windwood Cir",
    "sg:city":"Jackson",
    "sg:classifiers":[
        {
            "category":"Retail",
            "subcategory":"Auto Repair",
            "type":"Services"
        }
    ],
    "sg:phone":"+1 601 992 6009",
    "sg:postcode":"39232",
    "sg:province":"MS",
    "sg:tags":[
        "general"
    ],
    "wof:name":"Auto Tech Inc",
    "wof:placetype":"venue"
},
  "geometry": {"coordinates":[-90.07051,32.347017],"type":"Point"}
}