{
  "type": "Feature",
  "properties": {
    "iso:country":"US",
    "sg:address":"1908 Hwy 45 N",
    "sg:city":"Columbus",
    "sg:classifiers":[
        {
            "category":"Shopping",
            "subcategory":"Used Merchandise",
            "type":"Retail Goods"
        }
    ],
    "sg:phone":"+1 662 329 3660",
    "sg:postcode":"39705",
    "sg:province":"MS",
    "sg:tags":[
        "antique"
    ],
    "wof:name":"Riverhill Antiques",
    "wof:placetype":"venue"
},
  "geometry": {"coordinates":[-88.43732,33.531225],"type":"Point"}
}