{
  "type": "Feature",
  "properties": {
    "iso:country":"US",
    "sg:address":"525 N Main St",
    "sg:city":"Hattiesburg",
    "sg:classifiers":[
        {
            "category":"Banks & Credit Unions",
            "subcategory":"Investment Brokerage",
            "type":"Services"
        }
    ],
    "sg:phone":"+1 601 544 8585",
    "sg:postcode":"39401",
    "sg:province":"MS",
    "sg:tags":[
        "advisory",
        "financial"
    ],
    "wof:name":"DCM Financial Partners LTD",
    "wof:placetype":"venue"
},
  "geometry": {"coordinates":[-89.289716,31.326574],"type":"Point"}
}