{
  "type": "Feature",
  "properties": {
    "iso:country":"US",
    "sg:address":"6165 N Chapel Hill Rd",
    "sg:city":"Bolton",
    "sg:classifiers":[
        {
            "category":"Building & Trades",
            "subcategory":"Plumbing",
            "type":"Services"
        }
    ],
    "sg:phone":"+1 601 866 2334",
    "sg:postcode":"39041",
    "sg:province":"MS",
    "sg:tags":[
        "conditioning",
        "air",
        "system",
        "contractor"
    ],
    "wof:name":"Bell's AC & Heating",
    "wof:placetype":"venue"
},
  "geometry": {"coordinates":[-90.48164300000001,32.329716],"type":"Point"}
}