{
  "type": "Feature",
  "properties": {
    "iso:country":"US",
    "sg:address":"1781 Main St",
    "sg:city":"Southaven",
    "sg:classifiers":[
        {
            "category":"Personal",
            "type":"Services"
        }
    ],
    "sg:phone":"+1 901 503 7307",
    "sg:postcode":"38671",
    "sg:province":"MS",
    "sg:tags":[
        "electrolysis"
    ],
    "wof:name":"Preferred Electrology South",
    "wof:placetype":"venue"
},
  "geometry": {"coordinates":[-90.020577,34.991773],"type":"Point"}
}