{
  "type": "Feature",
  "properties": {
    "iso:country":"US",
    "sg:address":"2885 McCullough Blvd",
    "sg:city":"Belden",
    "sg:classifiers":[
        {
            "category":"Banks & Credit Unions",
            "subcategory":"Investment Brokerage",
            "type":"Services"
        }
    ],
    "sg:phone":"+1 662 842 2625",
    "sg:postcode":"38826",
    "sg:province":"MS",
    "sg:tags":[
        "security"
    ],
    "wof:name":"Edward Jones Co",
    "wof:placetype":"venue"
},
  "geometry": {"coordinates":[-88.797349,34.32976],"type":"Point"}
}