{
  "type": "Feature",
  "properties": {
    "addr:full":"1514 S Lauderdale Ave Shelby MS 38774",
    "addr:housenumber":"1514",
    "addr:postcode":"38774",
    "addr:street":"S Lauderdale Ave",
    "iso:country":"US",
    "sg:address":"1514 S Lauderdale Ave",
    "sg:city":"Shelby",
    "sg:classifiers":[
        {
            "category":"Organizations",
            "subcategory":"Religious Organization",
            "type":"Services"
        }
    ],
    "sg:phone":"+1 662 398 7890",
    "sg:postcode":"38774",
    "sg:province":"MS",
    "sg:tags":[
        "church"
    ],
    "wof:name":"Christian Union Church",
    "wof:placetype":"venue"
},
  "geometry": {"coordinates":[-90.76476700000001,33.944221],"type":"Point"}
}