{
  "type": "Feature",
  "properties": {
    "iso:country":"US",
    "sg:address":"113 S Jefferson St",
    "sg:city":"Macon",
    "sg:classifiers":[
        {
            "category":"Shopping",
            "subcategory":"Clothing, Apparel, & Fashions",
            "type":"Retail Goods"
        }
    ],
    "sg:phone":"+1 662 726 9999",
    "sg:postcode":"39341",
    "sg:province":"MS",
    "wof:name":"R & T Flowers & Fashions",
    "wof:placetype":"venue"
},
  "geometry": {"coordinates":[-88.560363,33.109963],"type":"Point"}
}