{
  "type": "Feature",
  "properties": {
    "iso:country":"US",
    "sg:address":"2 Cemetery Rd",
    "sg:city":"Picayune",
    "sg:classifiers":[
        {
            "category":"Shopping",
            "subcategory":"Used Merchandise",
            "type":"Retail Goods"
        }
    ],
    "sg:phone":"+1 601 798 0350",
    "sg:postcode":"39429",
    "sg:province":"MS",
    "sg:tags":[
        "flea",
        "market"
    ],
    "wof:name":"Mc Neil Flea Market",
    "wof:placetype":"venue"
},
  "geometry": {"coordinates":[-89.794544,31.390787],"type":"Point"}
}