{
  "type": "Feature",
  "properties": {
    "addr:full":"401 N 4th St Baldwyn MS 38824",
    "addr:housenumber":"401",
    "addr:postcode":"38824",
    "addr:street":"N 4Th St",
    "iso:country":"US",
    "sg:address":"401 N 4th St",
    "sg:city":"Baldwyn",
    "sg:classifiers":[
        {
            "category":"Manufacturing",
            "subcategory":"Tools & Machinery",
            "type":"Manufacturing & Wholesale Goods"
        },
        {
            "category":"Wholesale",
            "subcategory":"Auto Parts",
            "type":"Manufacturing & Wholesale Goods"
        }
    ],
    "sg:phone":"+1 662 365 5291",
    "sg:postcode":"38824",
    "sg:province":"MS",
    "sg:tags":[
        "body",
        "shop",
        "automobile",
        "equipment"
    ],
    "wof:name":"Hill Auto Supply Inc",
    "wof:placetype":"venue"
},
  "geometry": {"coordinates":[-88.634019,34.513287],"type":"Point"}
}