{
  "type": "Feature",
  "properties": {
    "addr:full":"129 E Van Dorn Ave Holly Springs MS 38635",
    "addr:housenumber":"129",
    "addr:postcode":"38635",
    "addr:street":"E Van Dorn Ave",
    "iso:country":"US",
    "sg:address":"129 E Van Dorn Ave",
    "sg:city":"Holly Springs",
    "sg:classifiers":[
        {
            "category":"Real Estate",
            "subcategory":"Real Estate Agent",
            "type":"Services"
        }
    ],
    "sg:phone":"+1 662 252 5527",
    "sg:postcode":"38635",
    "sg:province":"MS",
    "wof:name":"Century 21",
    "wof:placetype":"venue"
},
  "geometry": {"coordinates":[-89.447435,34.767411],"type":"Point"}
}