{
  "type": "Feature",
  "properties": {
    "iso:country":"US",
    "sg:address":"5244 A Ave",
    "sg:city":"Long Beach",
    "sg:classifiers":[
        {
            "category":"Social Services",
            "subcategory":"Job Training",
            "type":"Services"
        }
    ],
    "sg:phone":"+1 228 864 3521",
    "sg:postcode":"39560",
    "sg:province":"MS",
    "wof:name":"Allied Entps Harrison Cnty",
    "wof:placetype":"venue"
},
  "geometry": {"coordinates":[-89.197778,30.36142],"type":"Point"}
}