{
  "type": "Feature",
  "properties": {
    "iso:country":"US",
    "sg:address":"129 Selby Dr",
    "sg:city":"Madison",
    "sg:classifiers":[
        {
            "category":"Shopping",
            "subcategory":"Clothing, Apparel, & Fashions",
            "type":"Retail Goods"
        }
    ],
    "sg:phone":"+1 601 853 8485",
    "sg:postcode":"39110",
    "sg:province":"MS",
    "sg:tags":[
        "custom"
    ],
    "wof:name":"Aldrich Custom Apparel",
    "wof:placetype":"venue"
},
  "geometry": {"coordinates":[-90.14997,32.459837],"type":"Point"}
}