{
  "type": "Feature",
  "properties": {
    "iso:country":"US",
    "sg:address":"1404 Ellisville Blvd",
    "sg:city":"Laurel",
    "sg:classifiers":[
        {
            "category":"Organizations",
            "subcategory":"Religious Organization",
            "type":"Services"
        }
    ],
    "sg:phone":"+1 601 649 2442",
    "sg:postcode":"39440",
    "sg:province":"MS",
    "sg:tags":[
        "church"
    ],
    "wof:name":"Hosanna Missionary Baptist Chr",
    "wof:placetype":"venue"
},
  "geometry": {"coordinates":[-89.148669,31.669467],"type":"Point"}
}