{
  "type": "Feature",
  "properties": {
    "iso:country":"US",
    "sg:address":"300 N 2nd St",
    "sg:city":"Brookhaven",
    "sg:classifiers":[
        {
            "category":"Government",
            "subcategory":"Court House",
            "type":"Public Place"
        }
    ],
    "sg:phone":"+1 601 833 6699",
    "sg:postcode":"39601",
    "sg:province":"MS",
    "sg:tags":[
        "county",
        "counsel"
    ],
    "wof:name":"Lincoln County Public Defender",
    "wof:placetype":"venue"
},
  "geometry": {"coordinates":[-90.43794,31.58252],"type":"Point"}
}