{
  "type": "Feature",
  "properties": {
    "iso:country":"US",
    "sg:address":"5031 Old Hwy 11",
    "sg:city":"Hattiesburg",
    "sg:classifiers":[
        {
            "category":"Wholesale",
            "subcategory":"Farm Supplies",
            "type":"Manufacturing & Wholesale Goods"
        }
    ],
    "sg:phone":"+1 601 268 2029",
    "sg:postcode":"39402",
    "sg:province":"MS",
    "wof:name":"Oak Grove Feed & Seed",
    "wof:placetype":"venue"
},
  "geometry": {"coordinates":[-89.411334,31.293011],"type":"Point"}
}