{
  "type": "Feature",
  "properties": {
    "addr:full":"3040 Indiana Ave Vicksburg MS 39180",
    "addr:housenumber":"3040",
    "addr:postcode":"39180",
    "addr:street":"Indiana Ave",
    "iso:country":"US",
    "sg:address":"3040 Indiana Ave",
    "sg:city":"Vicksburg",
    "sg:classifiers":[
        {
            "category":"Freight",
            "type":"Transportation"
        }
    ],
    "sg:phone":"+1 601 636 0083",
    "sg:postcode":"39180",
    "sg:province":"MS",
    "sg:tags":[
        "warehouse",
        "merchandise"
    ],
    "wof:name":"Centrex Self Storage",
    "wof:placetype":"venue"
},
  "geometry": {"coordinates":[-90.865084,32.331141],"type":"Point"}
}