{
  "type": "Feature",
  "properties": {
    "addr:full":"120 S Main St Newton MS 39345",
    "addr:housenumber":"120",
    "addr:postcode":"39345",
    "addr:street":"S Main St",
    "iso:country":"US",
    "sg:address":"120 S Main St",
    "sg:city":"Newton",
    "sg:classifiers":[
        {
            "category":"Manufacturing",
            "subcategory":"Printing",
            "type":"Manufacturing & Wholesale Goods"
        }
    ],
    "sg:phone":"+1 601 683 2001",
    "sg:postcode":"39345",
    "sg:province":"MS",
    "sg:tags":[
        "newspaper"
    ],
    "wof:name":"Newton Record Inc",
    "wof:placetype":"venue"
},
  "geometry": {"coordinates":[-89.16301900000001,32.321496],"type":"Point"}
}