{
  "type": "Feature",
  "properties": {
    "iso:country":"US",
    "sg:address":"1020 Grand Ave",
    "sg:city":"Meridian",
    "sg:phone":"+1 601 693 3401",
    "sg:postcode":"39301",
    "sg:province":"MS",
    "sg:tags":[
        "gas"
    ],
    "wof:name":"Mc Donald & Hill Inc",
    "wof:placetype":"venue"
},
  "geometry": {"coordinates":[-88.70131499999999,32.354041],"type":"Point"}
}