{
  "type": "Feature",
  "properties": {
    "addr:full":"2051 John E Lewis Dr Mc Comb MS 39648",
    "addr:housenumber":"2051",
    "addr:postcode":"39648",
    "addr:street":"John E Lewis Dr",
    "iso:country":"US",
    "sg:address":"2051 John E Lewis Dr",
    "sg:city":"Mc Comb",
    "sg:classifiers":[
        {
            "category":"Airline",
            "type":"Transportation"
        }
    ],
    "sg:phone":"+1 601 684 8950",
    "sg:postcode":"39648",
    "sg:province":"MS",
    "sg:tags":[
        "fuel",
        "sales"
    ],
    "wof:name":"Air Services of Mississippi",
    "wof:placetype":"venue"
},
  "geometry": {"coordinates":[-90.468289,31.175904],"type":"Point"}
}