{
  "type": "Feature",
  "properties": {
    "iso:country":"US",
    "sg:address":"714 Cooper Rd",
    "sg:city":"Magee",
    "sg:classifiers":[
        {
            "category":"Autos & Motor Vehicles",
            "subcategory":"Fuel & Gas Station",
            "type":"Retail Goods"
        }
    ],
    "sg:phone":"+1 601 849 3390",
    "sg:postcode":"39111",
    "sg:province":"MS",
    "sg:tags":[
        "oil"
    ],
    "wof:name":"Magee Cooperative Gas Station",
    "wof:placetype":"venue"
},
  "geometry": {"coordinates":[-89.72121300000001,31.924731],"type":"Point"}
}