{
  "type": "Feature",
  "properties": {
    "addr:full":"6780 US Hwy 49 Hattiesburg MS 39402",
    "addr:housenumber":"6780",
    "addr:postcode":"39402",
    "addr:street":"Us Hwy 49",
    "iso:country":"US",
    "sg:address":"6780 US Hwy 49",
    "sg:city":"Hattiesburg",
    "sg:classifiers":[
        {
            "category":"Restaurant",
            "type":"Food & Drink"
        }
    ],
    "sg:phone":"+1 601 268 7801",
    "sg:postcode":"39402",
    "sg:province":"MS",
    "wof:name":"Subway Sandwiches & Salads",
    "wof:placetype":"venue"
},
  "geometry": {"coordinates":[-89.35148599999999,31.362139],"type":"Point"}
}