{
  "type": "Feature",
  "properties": {
    "addr:full":"3215 37th Ct Meridian MS 39305",
    "addr:housenumber":"3215",
    "addr:postcode":"39305",
    "addr:street":"37Th Ct",
    "iso:country":"US",
    "sg:address":"3215 37th Ct",
    "sg:city":"Meridian",
    "sg:classifiers":[
        {
            "category":"Professional",
            "subcategory":"Computer Services",
            "type":"Services"
        }
    ],
    "sg:phone":"+1 601 483 4170",
    "sg:postcode":"39305",
    "sg:province":"MS",
    "sg:tags":[
        "related"
    ],
    "wof:name":"Knoble Systems",
    "wof:placetype":"venue"
},
  "geometry": {"coordinates":[-88.711687,32.396064],"type":"Point"}
}