{
  "type": "Feature",
  "properties": {
    "iso:country":"US",
    "sg:address":"300 Cherry St",
    "sg:city":"Marks",
    "sg:classifiers":[
        {
            "category":"Insurance",
            "subcategory":"Insurance Agent",
            "type":"Services"
        }
    ],
    "sg:phone":"+1 662 326 8878",
    "sg:postcode":"38614",
    "sg:province":"MS",
    "wof:name":"Tackett Agency Inc",
    "wof:placetype":"venue"
},
  "geometry": {"coordinates":[-90.58291699999999,34.198586],"type":"Point"}
}