{
  "type": "Feature",
  "properties": {
    "addr:full":"140 S Bayou Ave Boyle MS 38730",
    "addr:housenumber":"140",
    "addr:postcode":"38730",
    "addr:street":"S Bayou Ave",
    "iso:country":"US",
    "sg:address":"140 S Bayou Ave",
    "sg:city":"Boyle",
    "sg:classifiers":[
        {
            "category":"Real Estate",
            "subcategory":"Real Estate Operator",
            "type":"Services"
        }
    ],
    "sg:phone":"+1 662 843 6002",
    "sg:postcode":"38730",
    "sg:province":"MS",
    "sg:tags":[
        "apartment"
    ],
    "wof:name":"Pazaaz Apartments",
    "wof:placetype":"venue"
},
  "geometry": {"coordinates":[-90.72365499999999,33.701522],"type":"Point"}
}