{
  "type": "Feature",
  "properties": {
    "addr:full":"4830 Amoco Dr Moss Point MS 39563",
    "addr:housenumber":"4830",
    "addr:postcode":"39563",
    "addr:street":"Amoco Dr",
    "iso:country":"US",
    "sg:address":"4830 Amoco Dr",
    "sg:city":"Moss Point",
    "sg:classifiers":[
        {
            "category":"Travel",
            "subcategory":"Hotels & Motels",
            "type":"Entertainment"
        }
    ],
    "sg:phone":"+1 228 475 5000",
    "sg:postcode":"39563",
    "sg:province":"MS",
    "wof:name":"Best Western",
    "wof:placetype":"venue"
},
  "geometry": {"coordinates":[-88.52723899999999,30.4378],"type":"Point"}
}