{
  "type": "Feature",
  "properties": {
    "iso:country":"US",
    "sg:address":"3353 N Gloster St",
    "sg:city":"Tupelo",
    "sg:classifiers":[
        {
            "category":"Health Services",
            "subcategory":"Optometrist",
            "type":"Services"
        }
    ],
    "sg:phone":"+1 662 844 3555",
    "sg:postcode":"38804",
    "sg:province":"MS",
    "sg:tags":[
        "lens",
        "retail",
        "glasses",
        "contact"
    ],
    "wof:name":"Mothershed F H Dr",
    "wof:placetype":"venue"
},
  "geometry": {"coordinates":[-88.707536,34.302032],"type":"Point"}
}