{
  "type": "Feature",
  "properties": {
    "iso:country":"US",
    "sg:address":"4569 Fisher Ferry Rd",
    "sg:city":"Vicksburg",
    "sg:classifiers":[
        {
            "category":"Organizations",
            "subcategory":"Religious Organization",
            "type":"Services"
        }
    ],
    "sg:phone":"+1 601 636 4904",
    "sg:postcode":"39180",
    "sg:province":"MS",
    "sg:website":"www.goodrum-baptist.com",
    "wof:name":"Goodrum Baptist Church",
    "wof:placetype":"venue"
},
  "geometry": {"coordinates":[-90.84899799999999,32.246441],"type":"Point"}
}