{
  "type": "Feature",
  "properties": {
    "iso:country":"US",
    "sg:address":"101 Leon Davis Dr",
    "sg:city":"Fulton",
    "sg:classifiers":[
        {
            "category":"Restaurant",
            "type":"Food & Drink"
        }
    ],
    "sg:phone":"+1 662 862 2315",
    "sg:postcode":"38843",
    "sg:province":"MS",
    "wof:name":"Waterfront Restaurant",
    "wof:placetype":"venue"
},
  "geometry": {"coordinates":[-88.39321099999999,34.248753],"type":"Point"}
}