{
  "type": "Feature",
  "properties": {
    "addr:full":"7058 Hwy 51 N Horn Lake MS 38637",
    "addr:housenumber":"7058",
    "addr:postcode":"38637",
    "addr:street":"Hwy 51 N Horn Lake",
    "iso:country":"US",
    "sg:address":"7058 Hwy 51 N",
    "sg:city":"Horn Lake",
    "sg:classifiers":[
        {
            "category":"Professional",
            "subcategory":"Business Services",
            "type":"Services"
        }
    ],
    "sg:phone":"+1 662 280 3287",
    "sg:postcode":"38637",
    "sg:province":"MS",
    "sg:tags":[
        "packaging"
    ],
    "wof:name":"Parcel Plus",
    "wof:placetype":"venue"
},
  "geometry": {"coordinates":[-90.016375,34.964253],"type":"Point"}
}