{
  "type": "Feature",
  "properties": {
    "iso:country":"US",
    "sg:address":"2973 State Hwy 22",
    "sg:city":"Madison",
    "sg:classifiers":[
        {
            "category":"Real Estate",
            "subcategory":"Developer",
            "type":"Services"
        }
    ],
    "sg:phone":"+1 601 853 7552",
    "sg:postcode":"39110",
    "sg:province":"MS",
    "wof:name":"Robert N Stockett Sr",
    "wof:placetype":"venue"
},
  "geometry": {"coordinates":[-90.165184,32.567841],"type":"Point"}
}