{
  "type": "Feature",
  "properties": {
    "iso:country":"US",
    "sg:address":"219 S Main St",
    "sg:city":"Yazoo City",
    "sg:classifiers":[
        {
            "category":"Shopping",
            "type":"Retail Goods"
        }
    ],
    "sg:phone":"+1 662 716 7162",
    "sg:postcode":"39194",
    "sg:province":"MS",
    "sg:tags":[
        "merchandise"
    ],
    "wof:name":"Critters Pet Shop",
    "wof:placetype":"venue"
},
  "geometry": {"coordinates":[-90.416128,32.843744],"type":"Point"}
}