{
  "type": "Feature",
  "properties": {
    "addr:full":"642 E 15th St Yazoo City MS 39194",
    "addr:housenumber":"642",
    "addr:postcode":"39194",
    "addr:street":"E 15Th St",
    "iso:country":"US",
    "sg:address":"642 E 15th St",
    "sg:city":"Yazoo City",
    "sg:classifiers":[
        {
            "category":"Shopping",
            "subcategory":"Clothing, Apparel, & Fashions",
            "type":"Retail Goods"
        }
    ],
    "sg:phone":"+1 662 746 7000",
    "sg:postcode":"39194",
    "sg:province":"MS",
    "sg:tags":[
        "t"
    ],
    "wof:name":"Creations By Coleman",
    "wof:placetype":"venue"
},
  "geometry": {"coordinates":[-90.397245,32.864989],"type":"Point"}
}