{
  "type": "Feature",
  "properties": {
    "iso:country":"US",
    "sg:address":"150 Fuller Rd",
    "sg:city":"Meridian",
    "sg:classifiers":[
        {
            "category":"Professional",
            "subcategory":"Engineering",
            "type":"Services"
        }
    ],
    "sg:phone":"+1 601 679 5154",
    "sg:postcode":"39309",
    "sg:province":"MS",
    "wof:name":"Raytheon",
    "wof:placetype":"venue"
},
  "geometry": {"coordinates":[-88.606331,32.551511],"type":"Point"}
}