{
  "type": "Feature",
  "properties": {
    "addr:full":"3645 Hwy 80 W Jackson MS 39209",
    "addr:housenumber":"3645",
    "addr:postcode":"39209",
    "addr:street":"Hwy 80 W",
    "iso:country":"US",
    "sg:address":"3645 Hwy 80 W",
    "sg:city":"Jackson",
    "sg:classifiers":[
        {
            "category":"Shopping",
            "subcategory":"Clothing, Apparel, & Fashions",
            "type":"Retail Goods"
        }
    ],
    "sg:phone":"+1 601 949 4996",
    "sg:postcode":"39209",
    "sg:province":"MS",
    "sg:tags":[
        "furnishing"
    ],
    "wof:name":"Burkes",
    "wof:placetype":"venue"
},
  "geometry": {"coordinates":[-90.249695,32.30196],"type":"Point"}
}