{
  "type": "Feature",
  "properties": {
    "addr:full":"15173 Saint Charles St Gulfport MS 39503",
    "addr:housenumber":"15173",
    "addr:postcode":"39503",
    "addr:street":"Saint Charles St",
    "iso:country":"US",
    "sg:address":"15173 Saint Charles St",
    "sg:city":"Gulfport",
    "sg:classifiers":[
        {
            "category":"Shopping",
            "subcategory":"Beauty & Cosmetics",
            "type":"Retail Goods"
        }
    ],
    "sg:phone":"+1 228 832 5612",
    "sg:postcode":"39503",
    "sg:province":"MS",
    "sg:tags":[
        "merchandise"
    ],
    "wof:name":"Cosmetics By Levi",
    "wof:placetype":"venue"
},
  "geometry": {"coordinates":[-89.092212,30.458561],"type":"Point"}
}