{
  "type": "Feature",
  "properties": {
    "iso:country":"US",
    "sg:address":"9092 Goodman Rd",
    "sg:city":"Olive Branch",
    "sg:classifiers":[
        {
            "category":"Farming",
            "subcategory":"Nursery",
            "type":"Manufacturing & Wholesale Goods"
        }
    ],
    "sg:phone":"+1 662 890 4689",
    "sg:postcode":"38654",
    "sg:province":"MS",
    "sg:tags":[
        "ornamental",
        "greenhouse"
    ],
    "wof:name":"Polly's Greenhouse",
    "wof:placetype":"venue"
},
  "geometry": {"coordinates":[-89.829055,34.961935],"type":"Point"}
}