{
  "type": "Feature",
  "properties": {
    "addr:full":"2016 Bienville Blvd Ocean Springs MS 39564",
    "addr:housenumber":"2016",
    "addr:postcode":"39564",
    "addr:street":"Bienville Blvd",
    "iso:country":"US",
    "sg:address":"2016 Bienville Blvd",
    "sg:city":"Ocean Springs",
    "sg:classifiers":[
        {
            "category":"Professional",
            "subcategory":"Lawyer & Legal Services",
            "type":"Services"
        }
    ],
    "sg:phone":"+1 228 872 1993",
    "sg:postcode":"39564",
    "sg:province":"MS",
    "sg:tags":[
        "attorney"
    ],
    "wof:name":"Kenneth L Swarthout",
    "wof:placetype":"venue"
},
  "geometry": {"coordinates":[-88.807334,30.416197],"type":"Point"}
}