{
  "type": "Feature",
  "properties": {
    "addr:full":"1215 City Ave N Ripley MS 38663",
    "addr:housenumber":"1215",
    "addr:postcode":"38663",
    "addr:street":"City Ave N",
    "iso:country":"US",
    "sg:address":"1215 City Ave N",
    "sg:city":"Ripley",
    "sg:classifiers":[
        {
            "category":"Building & Trades",
            "subcategory":"Landscaping Services",
            "type":"Services"
        }
    ],
    "sg:phone":"+1 662 512 4042",
    "sg:postcode":"38663",
    "sg:province":"MS",
    "wof:name":"Money N Minutes",
    "wof:placetype":"venue"
},
  "geometry": {"coordinates":[-88.948252,34.742951],"type":"Point"}
}