{
  "type": "Feature",
  "properties": {
    "iso:country":"US",
    "sg:address":"802 2nd Ave",
    "sg:city":"Picayune",
    "sg:classifiers":[
        {
            "category":"Professional",
            "type":"Services"
        }
    ],
    "sg:phone":"+1 601 798 6068",
    "sg:postcode":"39466",
    "sg:province":"MS",
    "sg:tags":[
        "establishment"
    ],
    "wof:name":"Quick & Grice",
    "wof:placetype":"venue"
},
  "geometry": {"coordinates":[-89.68497000000001,30.533809],"type":"Point"}
}