{
  "type": "Feature",
  "properties": {
    "addr:full":"232 N Magnolia Dr Wiggins MS 39577",
    "addr:housenumber":"232",
    "addr:postcode":"39577",
    "addr:street":"N Magnolia Dr",
    "iso:country":"US",
    "sg:address":"232 N Magnolia Dr",
    "sg:city":"Wiggins",
    "sg:classifiers":[
        {
            "category":"Personal",
            "subcategory":"Beauty Salon",
            "type":"Services"
        }
    ],
    "sg:phone":"+1 601 928 4273",
    "sg:postcode":"39577",
    "sg:province":"MS",
    "wof:name":"Chris' One Stop Hair Shop",
    "wof:placetype":"venue"
},
  "geometry": {"coordinates":[-89.138542,30.861182],"type":"Point"}
}