{
  "type": "Feature",
  "properties": {
    "addr:full":"49 Co Rd 5131 Booneville MS 38829",
    "addr:housenumber":"49",
    "addr:postcode":"5131;38829",
    "addr:street":"Co Rd",
    "iso:country":"US",
    "sg:address":"49 Co Rd 5131",
    "sg:city":"Booneville",
    "sg:classifiers":[
        {
            "category":"Retail",
            "subcategory":"Repair Shop",
            "type":"Services"
        }
    ],
    "sg:phone":"+1 662 728 5108",
    "sg:postcode":"38829",
    "sg:province":"MS",
    "sg:tags":[
        "welding"
    ],
    "wof:name":"Mc Kissack Welding & Fab",
    "wof:placetype":"venue"
},
  "geometry": {"coordinates":[-88.563743,34.595843],"type":"Point"}
}