{
  "type": "Feature",
  "properties": {
    "iso:country":"US",
    "sg:address":"1792 Hwy 1 S",
    "sg:city":"Greenville",
    "sg:classifiers":[
        {
            "category":"Banks & Credit Unions",
            "subcategory":"Bank",
            "type":"Services"
        }
    ],
    "sg:phone":"+1 662 335 2395",
    "sg:postcode":"38701",
    "sg:province":"MS",
    "sg:tags":[
        "loan",
        "real estate"
    ],
    "wof:name":"Wells Fargo Financial Accptnce",
    "wof:placetype":"venue"
},
  "geometry": {"coordinates":[-91.039795,33.372218],"type":"Point"}
}