{
  "type": "Feature",
  "properties": {
    "iso:country":"US",
    "sg:address":"2815 25th St",
    "sg:city":"Meridian",
    "sg:classifiers":[
        {
            "category":"Education",
            "subcategory":"School",
            "type":"Public Place"
        }
    ],
    "sg:phone":"+1 601 484 4977",
    "sg:postcode":"39301",
    "sg:province":"MS",
    "wof:name":"Marion Park Complex",
    "wof:placetype":"venue"
},
  "geometry": {"coordinates":[-88.706745,32.383707],"type":"Point"}
}