{
  "type": "Feature",
  "properties": {
    "iso:country":"US",
    "sg:address":"183 Glenwood Dr",
    "sg:city":"Columbus",
    "sg:classifiers":[
        {
            "category":"Shopping",
            "subcategory":"Gifts & Souvenirs",
            "type":"Retail Goods"
        }
    ],
    "sg:phone":"+1 662 327 2475",
    "sg:postcode":"39705",
    "sg:province":"MS",
    "sg:tags":[
        "wear"
    ],
    "wof:name":"Lace Edge",
    "wof:placetype":"venue"
},
  "geometry": {"coordinates":[-88.40843,33.521409],"type":"Point"}
}