{
  "type": "Feature",
  "properties": {
    "addr:full":"2967 State Hwy 448 Shaw MS 38773",
    "addr:housenumber":"2967",
    "addr:postcode":"38773",
    "addr:street":"State Hwy 448",
    "iso:country":"US",
    "sg:address":"2967 State Hwy 448",
    "sg:city":"Shaw",
    "sg:classifiers":[
        {
            "category":"Organizations",
            "subcategory":"Religious Organization",
            "type":"Services"
        }
    ],
    "sg:phone":"+1 662 754 6494",
    "sg:postcode":"38773",
    "sg:province":"MS",
    "sg:tags":[
        "church"
    ],
    "wof:name":"Jehovah's Witnesses Shaw",
    "wof:placetype":"venue"
},
  "geometry": {"coordinates":[-90.79808800000001,33.604994],"type":"Point"}
}