{
  "type": "Feature",
  "properties": {
    "iso:country":"US",
    "sg:address":"212 W Court St",
    "sg:city":"Brookhaven",
    "sg:classifiers":[
        {
            "category":"Personal",
            "subcategory":"Beauty Salon",
            "type":"Services"
        }
    ],
    "sg:phone":"+1 601 823 1821",
    "sg:postcode":"39601",
    "sg:province":"MS",
    "sg:tags":[
        "shop"
    ],
    "wof:name":"Byrons Cuts & Styles",
    "wof:placetype":"venue"
},
  "geometry": {"coordinates":[-90.44515699999999,31.581824],"type":"Point"}
}