{
  "type": "Feature",
  "properties": {
    "iso:country":"US",
    "sg:address":"922 N Main St",
    "sg:city":"Columbia",
    "sg:classifiers":[
        {
            "category":"Food & Beverages",
            "subcategory":"Groceries & Convenience Stores",
            "type":"Retail Goods"
        }
    ],
    "sg:phone":"+1 601 736 4647",
    "sg:postcode":"39429",
    "sg:province":"MS",
    "wof:name":"Main Street Muffler Shop",
    "wof:placetype":"venue"
},
  "geometry": {"coordinates":[-89.835363,31.255493],"type":"Point"}
}