{
  "type": "Feature",
  "properties": {
    "addr:full":"296 Beauvoir Rd Biloxi MS 39531",
    "addr:housenumber":"296",
    "addr:postcode":"39531",
    "addr:street":"Beauvoir Rd",
    "iso:country":"US",
    "sg:address":"296 Beauvoir Rd",
    "sg:city":"Biloxi",
    "sg:classifiers":[
        {
            "category":"Cinema",
            "subcategory":"Movie Rental",
            "type":"Entertainment"
        }
    ],
    "sg:phone":"+1 228 388 0990",
    "sg:postcode":"39531",
    "sg:province":"MS",
    "sg:tags":[
        "video",
        "tape"
    ],
    "wof:name":"Blockbuster",
    "wof:placetype":"venue"
},
  "geometry": {"coordinates":[-88.972858,30.398513],"type":"Point"}
}