{
  "type": "Feature",
  "properties": {
    "iso:country":"US",
    "sg:address":"9659 Hwy 178",
    "sg:city":"Olive Branch",
    "sg:classifiers":[
        {
            "category":"Restaurant",
            "type":"Food & Drink"
        }
    ],
    "sg:phone":"+1 662 895 9494",
    "sg:postcode":"38654",
    "sg:province":"MS",
    "wof:name":"Olive Branch Catfish Co",
    "wof:placetype":"venue"
},
  "geometry": {"coordinates":[-89.81871,34.957121],"type":"Point"}
}