{
  "type": "Feature",
  "properties": {
    "addr:full":"2296 Salem Rd Lake MS 39092",
    "addr:housenumber":"2296",
    "addr:postcode":"39092",
    "addr:street":"Salem Rd",
    "iso:country":"US",
    "sg:address":"2296 Salem Rd",
    "sg:city":"Lake",
    "sg:classifiers":[
        {
            "category":"Organizations",
            "subcategory":"Religious Organization",
            "type":"Services"
        }
    ],
    "sg:phone":"+1 601 775 3081",
    "sg:postcode":"39092",
    "sg:province":"MS",
    "wof:name":"Salem Baptist Church",
    "wof:placetype":"venue"
},
  "geometry": {"coordinates":[-89.356893,32.417027],"type":"Point"}
}