{
  "type": "Feature",
  "properties": {
    "iso:country":"US",
    "sg:address":"81 Log Cabin Rd",
    "sg:city":"Roxie",
    "sg:classifiers":[
        {
            "category":"Building & Trades",
            "subcategory":"Electrical",
            "type":"Services"
        }
    ],
    "sg:phone":"+1 601 597 2344",
    "sg:postcode":"39667",
    "sg:province":"MS",
    "sg:tags":[
        "electric",
        "contractor"
    ],
    "wof:name":"Spear Electric LLC",
    "wof:placetype":"venue"
},
  "geometry": {"coordinates":[-90.12844,31.26664],"type":"Point"}
}