{
  "type": "Feature",
  "properties": {
    "iso:country":"US",
    "sg:address":"103 Mueller Rd",
    "sg:city":"Fulton",
    "sg:classifiers":[
        {
            "category":"Retail",
            "subcategory":"Auto Repair",
            "type":"Services"
        }
    ],
    "sg:phone":"+1 662 862 5880",
    "sg:postcode":"38843",
    "sg:province":"MS",
    "sg:tags":[
        "automotive",
        "fluid"
    ],
    "wof:name":"Champion Express Lube Inc",
    "wof:placetype":"venue"
},
  "geometry": {"coordinates":[-88.40427699999999,34.249601],"type":"Point"}
}