{
  "type": "Feature",
  "properties": {
    "addr:full":"250 S Industrial Pkwy Yazoo City MS 39194",
    "addr:housenumber":"250",
    "addr:postcode":"39194",
    "addr:street":"S Industrial Pkwy",
    "iso:country":"US",
    "sg:address":"250 S Industrial Pkwy",
    "sg:city":"Yazoo City",
    "sg:classifiers":[
        {
            "category":"Manufacturing",
            "subcategory":"Paper Products",
            "type":"Manufacturing & Wholesale Goods"
        }
    ],
    "sg:phone":"+1 662 746 8333",
    "sg:postcode":"39194",
    "sg:province":"MS",
    "sg:tags":[
        "pulp"
    ],
    "wof:name":"Fulgham Fiber",
    "wof:placetype":"venue"
},
  "geometry": {"coordinates":[-90.43222299999999,32.853727],"type":"Point"}
}