{
  "type": "Feature",
  "properties": {
    "addr:full":"200 5th St Biloxi MS 39530",
    "addr:housenumber":"200",
    "addr:postcode":"39530",
    "addr:street":"5Th St",
    "iso:country":"US",
    "sg:address":"200 5th St",
    "sg:city":"Biloxi",
    "sg:classifiers":[
        {
            "category":"Manufacturing",
            "subcategory":"Rubber & Plastics",
            "type":"Manufacturing & Wholesale Goods"
        }
    ],
    "sg:phone":"+1 228 374 1774",
    "sg:postcode":"39530",
    "sg:province":"MS",
    "sg:tags":[
        "fiberglass",
        "pipe",
        "mfg"
    ],
    "sg:website":"www.ershigs-biloxi.com",
    "wof:name":"Ershigs Inc",
    "wof:placetype":"venue"
},
  "geometry": {"coordinates":[-88.86344,30.401124],"type":"Point"}
}