{
  "type": "Feature",
  "properties": {
    "addr:full":"304 Barrington Cove Byram MS 39272",
    "addr:housenumber":"304",
    "addr:postcode":"39272",
    "addr:street":"Barrington Cove",
    "iso:country":"US",
    "sg:address":"304 Barrington Cove",
    "sg:city":"Byram",
    "sg:classifiers":[
        {
            "category":"Health Services",
            "subcategory":"Medical Lab",
            "type":"Services"
        }
    ],
    "sg:phone":"+1 601 373 1034",
    "sg:postcode":"39272",
    "sg:province":"MS",
    "sg:tags":[
        "detection",
        "equipment",
        "drug"
    ],
    "wof:name":"Ira Jane Hurst & Assoc",
    "wof:placetype":"venue"
},
  "geometry": {"coordinates":[-90.283112,32.213595],"type":"Point"}
}