{
  "type": "Feature",
  "properties": {
    "addr:full":"12008 Three Rivers Rd Gulfport MS 39503",
    "addr:housenumber":"12008",
    "addr:postcode":"39503",
    "addr:street":"Three Rivers Rd",
    "iso:country":"US",
    "sg:address":"12008 Three Rivers Rd",
    "sg:city":"Gulfport",
    "sg:classifiers":[
        {
            "category":"Retail",
            "subcategory":"Repair Shop",
            "type":"Services"
        }
    ],
    "sg:phone":"+1 228 832 7511",
    "sg:postcode":"39503",
    "sg:province":"MS",
    "sg:tags":[
        "electrical"
    ],
    "wof:name":"Bond Appliances & Parts",
    "wof:placetype":"venue"
},
  "geometry": {"coordinates":[-89.06958299999999,30.457106],"type":"Point"}
}