{
  "type": "Feature",
  "properties": {
    "addr:full":"17476 Dogwood Hills Dr Biloxi MS 39532",
    "addr:housenumber":"17476",
    "addr:postcode":"39532",
    "addr:street":"Dogwood Hills Dr",
    "iso:country":"US",
    "sg:address":"17476 Dogwood Hills Dr",
    "sg:city":"Biloxi",
    "sg:classifiers":[
        {
            "category":"Sports & Exercise",
            "subcategory":"Golf",
            "type":"Entertainment"
        }
    ],
    "sg:phone":"+1 228 392 9805",
    "sg:postcode":"39532",
    "sg:province":"MS",
    "sg:tags":[
        "course",
        "eating",
        "public",
        "se"
    ],
    "sg:website":"www.dogwoodhillsgolf.com",
    "wof:name":"Dogwood Hills Golf Club",
    "wof:placetype":"venue"
},
  "geometry": {"coordinates":[-89.005843,30.541067],"type":"Point"}
}