{
  "type": "Feature",
  "properties": {
    "addr:full":"3187 Enon Rd Louisville MS 39339",
    "addr:housenumber":"3187",
    "addr:postcode":"39339",
    "addr:street":"Enon Rd",
    "iso:country":"US",
    "sg:address":"3187 Enon Rd",
    "sg:city":"Louisville",
    "sg:classifiers":[
        {
            "category":"Organizations",
            "subcategory":"Religious Organization",
            "type":"Services"
        }
    ],
    "sg:phone":"+1 662 779 0253",
    "sg:postcode":"39339",
    "sg:province":"MS",
    "wof:name":"Mount Cnnie Mssion Bptst Chrch",
    "wof:placetype":"venue"
},
  "geometry": {"coordinates":[-89.02403700000001,33.042413],"type":"Point"}
}