{
  "type": "Feature",
  "properties": {
    "iso:country":"US",
    "sg:address":"831 Beechwood Ct",
    "sg:city":"Jackson",
    "sg:classifiers":[
        {
            "category":"Insurance",
            "subcategory":"Insurance Agent",
            "type":"Services"
        }
    ],
    "sg:phone":"+1 601 362 2919",
    "sg:postcode":"39206",
    "sg:province":"MS",
    "wof:name":"Myles Willie",
    "wof:placetype":"venue"
},
  "geometry": {"coordinates":[-90.185249,32.380754],"type":"Point"}
}