{
  "type": "Feature",
  "properties": {
    "iso:country":"US",
    "sg:address":"630 Morgan Dr",
    "sg:city":"Terry",
    "sg:classifiers":[
        {
            "category":"Government",
            "subcategory":"Office",
            "type":"Public Place"
        }
    ],
    "sg:phone":"+1 601 878 5056",
    "sg:postcode":"39170",
    "sg:province":"MS",
    "wof:name":"Terry Neighborhood Svc Ctr",
    "wof:placetype":"venue"
},
  "geometry": {"coordinates":[-90.29042,32.102129],"type":"Point"}
}