{
  "type": "Feature",
  "properties": {
    "iso:country":"US",
    "sg:address":"3745 Co Rd 211",
    "sg:city":"Coffeeville",
    "sg:classifiers":[
        {
            "category":"Farming",
            "subcategory":"Farm & Veterinary Services",
            "type":"Manufacturing & Wholesale Goods"
        }
    ],
    "sg:phone":"+1 662 675 8797",
    "sg:postcode":"38922",
    "sg:province":"MS",
    "sg:tags":[
        "gin",
        "cotton"
    ],
    "wof:name":"Yalobusha Gin",
    "wof:placetype":"venue"
},
  "geometry": {"coordinates":[-89.735921,34.012832],"type":"Point"}
}