{
  "type": "Feature",
  "properties": {
    "addr:full":"1926 First Commercial Dr N Southaven MS 38671",
    "addr:housenumber":"1926",
    "addr:postcode":"38671",
    "addr:street":"First Commercial Dr N",
    "iso:country":"US",
    "sg:address":"1926 First Commercial Dr N",
    "sg:city":"Southaven",
    "sg:classifiers":[
        {
            "category":"Wholesale",
            "subcategory":"Office Equipment",
            "type":"Manufacturing & Wholesale Goods"
        }
    ],
    "sg:phone":"+1 662 280 2455",
    "sg:postcode":"38671",
    "sg:province":"MS",
    "sg:tags":[
        "machine",
        "duplicating",
        "copying"
    ],
    "wof:name":"Copytech Copier & Fax Co",
    "wof:placetype":"venue"
},
  "geometry": {"coordinates":[-90.02148,34.990003],"type":"Point"}
}