{
  "type": "Feature",
  "properties": {
    "iso:country":"US",
    "sg:address":"1007 Hardy St",
    "sg:city":"Hattiesburg",
    "sg:classifiers":[
        {
            "category":"Professional",
            "subcategory":"Accounting & Tax Preparation",
            "type":"Services"
        }
    ],
    "sg:phone":"+1 601 582 2822",
    "sg:postcode":"39401",
    "sg:province":"MS",
    "sg:tags":[
        "return",
        "filing"
    ],
    "wof:name":"Econotax",
    "wof:placetype":"venue"
},
  "geometry": {"coordinates":[-89.307215,31.324809],"type":"Point"}
}