{
  "type": "Feature",
  "properties": {
    "addr:full":"713 S Starkville St Houston MS 38851",
    "addr:housenumber":"713",
    "addr:postcode":"38851",
    "addr:street":"S Starkville St",
    "iso:country":"US",
    "sg:address":"713 S Starkville St",
    "sg:city":"Houston",
    "sg:classifiers":[
        {
            "category":"Organizations",
            "subcategory":"Religious Organization",
            "type":"Services"
        }
    ],
    "sg:phone":"+1 662 456 9474",
    "sg:postcode":"38851",
    "sg:province":"MS",
    "sg:tags":[
        "church"
    ],
    "wof:name":"Cornerstone Church",
    "wof:placetype":"venue"
},
  "geometry": {"coordinates":[-88.98593700000001,33.884779],"type":"Point"}
}