{
  "type": "Feature",
  "properties": {
    "iso:country":"US",
    "sg:address":"140 Ollhoft Rd",
    "sg:city":"Meridian",
    "sg:classifiers":[
        {
            "category":"Real Estate",
            "subcategory":"Real Estate Operator",
            "type":"Services"
        }
    ],
    "sg:phone":"+1 601 681 9090",
    "sg:postcode":"39305",
    "sg:province":"MS",
    "sg:tags":[
        "building",
        "nonresidential"
    ],
    "wof:name":"H&B Southern Properties",
    "wof:placetype":"venue"
},
  "geometry": {"coordinates":[-88.66336699999999,32.51977],"type":"Point"}
}