{
  "type": "Feature",
  "properties": {
    "iso:country":"US",
    "sg:address":"204 E Water St",
    "sg:city":"Carthage",
    "sg:classifiers":[
        {
            "category":"Professional",
            "subcategory":"Computer Services",
            "type":"Services"
        }
    ],
    "sg:phone":"+1 601 267 5377",
    "sg:postcode":"39051",
    "sg:province":"MS",
    "sg:tags":[
        "internet"
    ],
    "wof:name":"Mississippi Internet",
    "wof:placetype":"venue"
},
  "geometry": {"coordinates":[-89.531718,32.735846],"type":"Point"}
}