{
  "type": "Feature",
  "properties": {
    "addr:full":"1240 Double Shovel Dr Hernando MS 38632",
    "addr:housenumber":"1240",
    "addr:postcode":"38632",
    "addr:street":"Double Shovel Dr",
    "iso:country":"US",
    "sg:address":"1240 Double Shovel Dr",
    "sg:city":"Hernando",
    "sg:classifiers":[
        {
            "category":"Building & Trades",
            "subcategory":"Construction",
            "type":"Services"
        },
        {
            "category":"Military Area",
            "subcategory":"Armory",
            "type":"Public Place"
        }
    ],
    "sg:phone":"+1 662 449 0141",
    "sg:postcode":"38632",
    "sg:province":"MS",
    "sg:tags":[
        "repair",
        "fence-sales",
        "fence",
        "contractor"
    ],
    "wof:name":"Master-Bilt Fence",
    "wof:placetype":"venue"
},
  "geometry": {"coordinates":[-89.965211,34.841341],"type":"Point"}
}