{
  "type": "Feature",
  "properties": {
    "iso:country":"US",
    "sg:address":"1515 E Canal St",
    "sg:city":"Picayune",
    "sg:classifiers":[
        {
            "category":"Home & Garden",
            "subcategory":"Building Materials",
            "type":"Retail Goods"
        }
    ],
    "sg:phone":"+1 601 798 8129",
    "sg:postcode":"39466",
    "sg:province":"MS",
    "sg:tags":[
        "lumber"
    ],
    "wof:name":"Great Southern",
    "wof:placetype":"venue"
},
  "geometry": {"coordinates":[-89.66188699999999,30.524228],"type":"Point"}
}