{
  "type": "Feature",
  "properties": {
    "addr:full":"130 Interstate Dr Jackson MS 39218",
    "addr:housenumber":"130",
    "addr:postcode":"39218",
    "addr:street":"Interstate Dr",
    "iso:country":"US",
    "sg:address":"130 Interstate Dr",
    "sg:city":"Jackson",
    "sg:classifiers":[
        {
            "category":"Wholesale",
            "subcategory":"Machinery & Supplies",
            "type":"Manufacturing & Wholesale Goods"
        }
    ],
    "sg:phone":"+1 601 939 8941",
    "sg:postcode":"39218",
    "sg:province":"MS",
    "sg:tags":[
        "mill",
        "paper"
    ],
    "wof:name":"Passons Specialized Svc",
    "wof:placetype":"venue"
},
  "geometry": {"coordinates":[-90.15887499999999,32.253092],"type":"Point"}
}