{
  "type": "Feature",
  "properties": {
    "iso:country":"US",
    "sg:address":"148 Triangle Dr",
    "sg:city":"Laurel",
    "sg:classifiers":[
        {
            "category":"Mining & Drilling",
            "type":"Manufacturing & Wholesale Goods"
        }
    ],
    "sg:phone":"+1 601 425 2473",
    "sg:postcode":"39443",
    "sg:province":"MS",
    "sg:tags":[
        "field",
        "oil"
    ],
    "wof:name":"Free State Tool Corp",
    "wof:placetype":"venue"
},
  "geometry": {"coordinates":[-89.09798000000001,31.65296],"type":"Point"}
}