{
  "type": "Feature",
  "properties": {
    "iso:country":"US",
    "sg:address":"141 W Peace St",
    "sg:city":"Canton",
    "sg:classifiers":[
        {
            "category":"Professional",
            "type":"Services"
        },
        {
            "category":"Shopping",
            "subcategory":"Gifts & Souvenirs",
            "type":"Retail Goods"
        }
    ],
    "sg:phone":"+1 601 859 9599",
    "sg:postcode":"39046",
    "sg:province":"MS",
    "sg:tags":[
        "shop"
    ],
    "wof:name":"Cotton Patch Original Inc",
    "wof:placetype":"venue"
},
  "geometry": {"coordinates":[-90.035849,32.612531],"type":"Point"}
}