{
  "type": "Feature",
  "properties": {
    "addr:full":"200 E Bay St Magnolia MS 39652",
    "addr:housenumber":"200",
    "addr:postcode":"39652",
    "addr:street":"E Bay St",
    "iso:country":"US",
    "sg:address":"200 E Bay St",
    "sg:city":"Magnolia",
    "sg:classifiers":[
        {
            "category":"Government",
            "subcategory":"Office",
            "type":"Public Place"
        }
    ],
    "sg:phone":"+1 601 783 6138",
    "sg:postcode":"39652",
    "sg:province":"MS",
    "wof:name":"Receiving Clerk Office",
    "wof:placetype":"venue"
},
  "geometry": {"coordinates":[-90.46012899999999,31.14398],"type":"Point"}
}