{
  "type": "Feature",
  "properties": {
    "addr:full":"990 Bolivar Rd Benoit MS 38725",
    "addr:housenumber":"990",
    "addr:postcode":"38725",
    "addr:street":"Bolivar Rd",
    "iso:country":"US",
    "sg:address":"990 Bolivar Rd",
    "sg:city":"Benoit",
    "sg:classifiers":[
        {
            "category":"Personal",
            "subcategory":"Beauty Salon",
            "type":"Services"
        }
    ],
    "sg:phone":"+1 662 742 0769",
    "sg:postcode":"38725",
    "sg:province":"MS",
    "wof:name":"Earlee Barnett",
    "wof:placetype":"venue"
},
  "geometry": {"coordinates":[-91.013623,33.65291],"type":"Point"}
}