{
  "type": "Feature",
  "properties": {
    "iso:country":"US",
    "sg:address":"100 M Price Rd",
    "sg:city":"Wiggins",
    "sg:classifiers":[
        {
            "category":"Wholesale",
            "subcategory":"Construction Materials",
            "type":"Manufacturing & Wholesale Goods"
        }
    ],
    "sg:phone":"+1 601 528 9007",
    "sg:postcode":"39573",
    "sg:province":"MS",
    "sg:tags":[
        "timberland",
        "company",
        "timber"
    ],
    "wof:name":"Stonnington Equine & Timber",
    "wof:placetype":"venue"
},
  "geometry": {"coordinates":[-89.095437,30.796865],"type":"Point"}
}