{
  "type": "Feature",
  "properties": {
    "iso:country":"US",
    "sg:address":"1000 Artesia Rd",
    "sg:city":"Starkville",
    "sg:classifiers":[
        {
            "category":"Building & Trades",
            "subcategory":"Landscaping Services",
            "type":"Services"
        }
    ],
    "sg:phone":"+1 662 323 5288",
    "sg:postcode":"39759",
    "sg:province":"MS",
    "sg:tags":[
        "interior",
        "industrial",
        "sanitation"
    ],
    "wof:name":"Guaranteed Green",
    "wof:placetype":"venue"
},
  "geometry": {"coordinates":[-88.776203,33.425894],"type":"Point"}
}