{
  "type": "Feature",
  "properties": {
    "addr:full":"4665 S McRaven Rd Jackson MS 39204",
    "addr:housenumber":"4665",
    "addr:postcode":"39204",
    "addr:street":"S Mcraven Rd",
    "iso:country":"US",
    "sg:address":"4665 S McRaven Rd",
    "sg:city":"Jackson",
    "sg:classifiers":[
        {
            "category":"Retail",
            "subcategory":"Auto Repair",
            "type":"Services"
        }
    ],
    "sg:phone":"+1 601 922 2266",
    "sg:postcode":"39204",
    "sg:province":"MS",
    "sg:tags":[
        "repairing",
        "automobile"
    ],
    "wof:name":"Keene's Volkswagen Specialist",
    "wof:placetype":"venue"
},
  "geometry": {"coordinates":[-90.26377100000001,32.297214],"type":"Point"}
}