{
  "type": "Feature",
  "properties": {
    "addr:full":"520 US Hwy 82 E Indianola MS 38751",
    "addr:housenumber":"520",
    "addr:postcode":"38751",
    "addr:street":"Us Hwy 82 E",
    "iso:country":"US",
    "sg:address":"520 US Hwy 82 E",
    "sg:city":"Indianola",
    "sg:classifiers":[
        {
            "category":"Restaurant",
            "type":"Food & Drink"
        }
    ],
    "sg:phone":"+1 662 887 2929",
    "sg:postcode":"38751",
    "sg:province":"MS",
    "wof:name":"Sonic Drive-In",
    "wof:placetype":"venue"
},
  "geometry": {"coordinates":[-90.644102,33.457958],"type":"Point"}
}