{
  "type": "Feature",
  "properties": {
    "addr:full":"102 S Dunn St Eupora MS 39744",
    "addr:housenumber":"102",
    "addr:postcode":"39744",
    "addr:street":"S Dunn St",
    "iso:country":"US",
    "sg:address":"102 S Dunn St",
    "sg:city":"Eupora",
    "sg:classifiers":[
        {
            "category":"Professional",
            "subcategory":"Management & Consulting",
            "type":"Services"
        }
    ],
    "sg:phone":"+1 662 258 7835",
    "sg:postcode":"39744",
    "sg:province":"MS",
    "sg:tags":[
        "development",
        "industrial"
    ],
    "wof:name":"Webster County Development",
    "wof:placetype":"venue"
},
  "geometry": {"coordinates":[-89.26873000000001,33.540824],"type":"Point"}
}