{
  "type": "Feature",
  "properties": {
    "addr:full":"8866 Hwy 16 E Benton MS 39039",
    "addr:housenumber":"8866",
    "addr:postcode":"39039",
    "addr:street":"Hwy 16 E",
    "iso:country":"US",
    "sg:address":"8866 Hwy 16 E",
    "sg:city":"Benton",
    "sg:classifiers":[
        {
            "category":"Organizations",
            "subcategory":"Religious Organization",
            "type":"Services"
        }
    ],
    "sg:phone":"+1 662 673 9176",
    "sg:postcode":"39039",
    "sg:province":"MS",
    "sg:tags":[
        "church"
    ],
    "wof:name":"Oak Grove A M E Church",
    "wof:placetype":"venue"
},
  "geometry": {"coordinates":[-90.23807499999999,32.811146],"type":"Point"}
}