{
  "type": "Feature",
  "properties": {
    "iso:country":"US",
    "sg:address":"3675 Hwy 4",
    "sg:city":"Sarah",
    "sg:classifiers":[
        {
            "category":"Food & Beverages",
            "subcategory":"Groceries & Convenience Stores",
            "type":"Retail Goods"
        }
    ],
    "sg:phone":"+1 662 562 5480",
    "sg:postcode":"38665",
    "sg:province":"MS",
    "sg:tags":[
        "grocer"
    ],
    "wof:name":"Hudspeth's Grocery",
    "wof:placetype":"venue"
},
  "geometry": {"coordinates":[-90.132794,34.612512],"type":"Point"}
}