{
  "type": "Feature",
  "properties": {
    "iso:country":"US",
    "sg:address":"1312 Hwy 80 W",
    "sg:city":"Jackson",
    "sg:classifiers":[
        {
            "category":"Bars & Pubs",
            "type":"Food & Drink"
        }
    ],
    "sg:phone":"+1 601 969 0366",
    "sg:postcode":"39204",
    "sg:province":"MS",
    "wof:name":"Tunes N More",
    "wof:placetype":"venue"
},
  "geometry": {"coordinates":[-90.206937,32.286305],"type":"Point"}
}