{
  "type": "Feature",
  "properties": {
    "addr:full":"617 Dunton Rd Clinton MS 39056",
    "addr:housenumber":"617",
    "addr:postcode":"39056",
    "addr:street":"Dunton Rd",
    "iso:country":"US",
    "sg:address":"617 Dunton Rd",
    "sg:city":"Clinton",
    "sg:classifiers":[
        {
            "category":"Government",
            "subcategory":"Office",
            "type":"Public Place"
        }
    ],
    "sg:phone":"+1 601 926 1104",
    "sg:postcode":"39056",
    "sg:province":"MS",
    "sg:tags":[
        "water",
        "solid",
        "waste",
        "management",
        "air"
    ],
    "wof:name":"Clinton Community Nature Ctr",
    "wof:placetype":"venue"
},
  "geometry": {"coordinates":[-90.320871,32.341663],"type":"Point"}
}