{
  "type": "Feature",
  "properties": {
    "iso:country":"US",
    "sg:address":"46 Sgt Prentiss Dr",
    "sg:city":"Natchez",
    "sg:classifiers":[
        {
            "category":"Health Services",
            "subcategory":"Doctor",
            "type":"Services"
        }
    ],
    "sg:phone":"+1 601 445 8667",
    "sg:postcode":"39120",
    "sg:province":"MS",
    "sg:tags":[
        "physician",
        "medical",
        "surgeon"
    ],
    "wof:name":"Geoffrey J Flattmann MD",
    "wof:placetype":"venue"
},
  "geometry": {"coordinates":[-91.388408,31.52074],"type":"Point"}
}