{
  "type": "Feature",
  "properties": {
    "iso:country":"US",
    "sg:address":"934 Industrial Park Rd NE",
    "sg:city":"Brookhaven",
    "sg:classifiers":[
        {
            "category":"Government",
            "subcategory":"Office",
            "type":"Public Place"
        }
    ],
    "sg:phone":"+1 601 833 3231",
    "sg:postcode":"39601",
    "sg:province":"MS",
    "sg:tags":[
        "state",
        "program"
    ],
    "wof:name":"Vocational Rehabilitation Svc",
    "wof:placetype":"venue"
},
  "geometry": {"coordinates":[-90.43034900000001,31.59933],"type":"Point"}
}