{
  "type": "Feature",
  "properties": {
    "iso:country":"US",
    "sg:address":"306 East Ave S",
    "sg:city":"Hollandale",
    "sg:classifiers":[
        {
            "category":"Government",
            "subcategory":"Office",
            "type":"Public Place"
        }
    ],
    "sg:phone":"+1 662 827 5626",
    "sg:postcode":"38748",
    "sg:province":"MS",
    "sg:tags":[
        "county",
        "program",
        "health"
    ],
    "wof:name":"Washington County Health Dept",
    "wof:placetype":"venue"
},
  "geometry": {"coordinates":[-90.85319800000001,33.166594],"type":"Point"}
}