{
  "type": "Feature",
  "properties": {
    "iso:country":"US",
    "sg:address":"104 Louis Wilson Dr",
    "sg:city":"Brandon",
    "sg:classifiers":[
        {
            "category":"Insurance",
            "subcategory":"Insurance Agent",
            "type":"Services"
        }
    ],
    "sg:phone":"+1 601 825 5056",
    "sg:postcode":"39042",
    "sg:province":"MS",
    "wof:name":"Farm Bureau Insurance",
    "wof:placetype":"venue"
},
  "geometry": {"coordinates":[-89.98157500000001,32.272877],"type":"Point"}
}