{
  "type": "Feature",
  "properties": {
    "addr:full":"8737 State Hwy 613 Moss Point MS 39562",
    "addr:housenumber":"8737",
    "addr:postcode":"39562",
    "addr:street":"State Hwy 613",
    "iso:country":"US",
    "sg:address":"8737 State Hwy 613",
    "sg:city":"Moss Point",
    "sg:classifiers":[
        {
            "category":"Insurance",
            "subcategory":"Insurance Agent",
            "type":"Services"
        }
    ],
    "sg:phone":"+1 228 475 8021",
    "sg:postcode":"39562",
    "sg:province":"MS",
    "wof:name":"Farm Bureau Insurance",
    "wof:placetype":"venue"
},
  "geometry": {"coordinates":[-88.54646700000001,30.471333],"type":"Point"}
}