{
  "type": "Feature",
  "properties": {
    "iso:country":"US",
    "sg:address":"698 Liberty Rd",
    "sg:city":"Natchez",
    "sg:classifiers":[
        {
            "category":"Utilities",
            "subcategory":"Refuse",
            "type":"Services"
        }
    ],
    "sg:phone":"+1 601 442 3094",
    "sg:postcode":"39120",
    "sg:province":"MS",
    "sg:tags":[
        "disposal",
        "waste"
    ],
    "wof:name":"Jsk Resources Inc",
    "wof:placetype":"venue"
},
  "geometry": {"coordinates":[-91.34688800000001,31.531536],"type":"Point"}
}