{
  "type": "Feature",
  "properties": {
    "iso:country":"US",
    "sg:address":"2159 Henry Hill Dr",
    "sg:city":"Jackson",
    "sg:classifiers":[
        {
            "category":"Banks & Credit Unions",
            "subcategory":"Bank",
            "type":"Services"
        }
    ],
    "sg:phone":"+1 601 923 8226",
    "sg:postcode":"39204",
    "sg:province":"MS",
    "sg:tags":[
        "mortgage",
        "loan",
        "broker",
        "real estate"
    ],
    "wof:name":"Transcontinental Lending Group",
    "wof:placetype":"venue"
},
  "geometry": {"coordinates":[-90.269375,32.291629],"type":"Point"}
}