{
  "type": "Feature",
  "properties": {
    "addr:full":"506 W Gertrude Ave Drew MS 38737",
    "addr:housenumber":"506",
    "addr:postcode":"38737",
    "addr:street":"W Gertrude Ave",
    "iso:country":"US",
    "sg:address":"506 W Gertrude Ave",
    "sg:city":"Drew",
    "sg:classifiers":[
        {
            "category":"Organizations",
            "subcategory":"Community Association",
            "type":"Services"
        }
    ],
    "sg:phone":"+1 662 745 8362",
    "sg:postcode":"38737",
    "sg:province":"MS",
    "wof:name":"Free & Accepted Masons Miss",
    "wof:placetype":"venue"
},
  "geometry": {"coordinates":[-90.540542,33.806034],"type":"Point"}
}