{
  "type": "Feature",
  "properties": {
    "iso:country":"US",
    "sg:address":"1901 17th Ave",
    "sg:city":"Meridian",
    "sg:classifiers":[
        {
            "category":"Organizations",
            "subcategory":"Religious Organization",
            "type":"Services"
        }
    ],
    "sg:phone":"+1 601 696 4940",
    "sg:postcode":"39301",
    "sg:province":"MS",
    "sg:tags":[
        "church"
    ],
    "wof:name":"Free Gospel Temple",
    "wof:placetype":"venue"
},
  "geometry": {"coordinates":[-88.69583,32.378006],"type":"Point"}
}