{
  "type": "Feature",
  "properties": {
    "iso:country":"US",
    "sg:address":"102 Pine Knoll Dr",
    "sg:city":"Ridgeland",
    "sg:classifiers":[
        {
            "category":"Restaurant",
            "type":"Food & Drink"
        }
    ],
    "sg:menulink":"http://www.allmenus.com/ms/madison/76295-dominos-pizza/menu/",
    "sg:phone":"+1 601 956 4900",
    "sg:postcode":"39157",
    "sg:province":"MS",
    "sg:tags":[
        "american",
        "wing",
        "pizza"
    ],
    "wof:name":"Domino's Pizza",
    "wof:placetype":"venue"
},
  "geometry": {"coordinates":[-90.10778999999999,32.402529],"type":"Point"}
}