{
  "type": "Feature",
  "properties": {
    "iso:country":"US",
    "sg:address":"4952 State Hwy 29",
    "sg:city":"Petal",
    "sg:classifiers":[
        {
            "category":"Building & Trades",
            "subcategory":"Construction",
            "type":"Services"
        }
    ],
    "sg:phone":"+1 601 545 8220",
    "sg:postcode":"39465",
    "sg:province":"MS",
    "sg:tags":[
        "contractor"
    ],
    "wof:name":"McCardle Forestry Service",
    "wof:placetype":"venue"
},
  "geometry": {"coordinates":[-89.11137600000001,31.364727],"type":"Point"}
}