{
  "type": "Feature",
  "properties": {
    "iso:country":"US",
    "sg:address":"9121 Lauderdale Toomsuba Rd",
    "sg:city":"Lauderdale",
    "sg:classifiers":[
        {
            "category":"Real Estate",
            "subcategory":"Developer",
            "type":"Services"
        },
        {
            "category":"Travel",
            "subcategory":"Hotels & Motels",
            "type":"Entertainment"
        }
    ],
    "sg:phone":"+1 601 632 4302",
    "sg:postcode":"39335",
    "sg:province":"MS",
    "sg:tags":[
        "resort"
    ],
    "wof:name":"Dalewood Shores Sales Office",
    "wof:placetype":"venue"
},
  "geometry": {"coordinates":[-88.516677,32.498996],"type":"Point"}
}