{
  "type": "Feature",
  "properties": {
    "addr:full":"1407 Hwy 278 E Amory MS 38821",
    "addr:housenumber":"1407",
    "addr:postcode":"38821",
    "addr:street":"Hwy 278 E Amory",
    "iso:country":"US",
    "sg:address":"1407 Hwy 278 E",
    "sg:city":"Amory",
    "sg:classifiers":[
        {
            "category":"Wholesale",
            "subcategory":"Electrical",
            "type":"Manufacturing & Wholesale Goods"
        }
    ],
    "sg:phone":"+1 662 256 7357",
    "sg:postcode":"38821",
    "sg:province":"MS",
    "sg:tags":[
        "communication",
        "radio",
        "system"
    ],
    "wof:name":"Precision Communications",
    "wof:placetype":"venue"
},
  "geometry": {"coordinates":[-88.46422099999999,33.971528],"type":"Point"}
}