{
  "type": "Feature",
  "properties": {
    "iso:country":"US",
    "sg:address":"2596 Robinson St",
    "sg:city":"Jackson",
    "sg:classifiers":[
        {
            "category":"Personal",
            "subcategory":"Beauty Salon",
            "type":"Services"
        }
    ],
    "sg:phone":"+1 601 944 1400",
    "sg:postcode":"39209",
    "sg:province":"MS",
    "sg:tags":[
        "manicuring"
    ],
    "wof:name":"Magic Nails",
    "wof:placetype":"venue"
},
  "geometry": {"coordinates":[-90.22784299999999,32.305508],"type":"Point"}
}