{
  "type": "Feature",
  "properties": {
    "iso:country":"US",
    "sg:address":"402 S Deer Creek Dr W",
    "sg:city":"Leland",
    "sg:classifiers":[
        {
            "category":"Education",
            "subcategory":"Junior College",
            "type":"Public Place"
        }
    ],
    "sg:phone":"+1 662 686 5025",
    "sg:postcode":"38756",
    "sg:province":"MS",
    "sg:tags":[
        "technical",
        "institute"
    ],
    "wof:name":"Leland Vocational Technical",
    "wof:placetype":"venue"
},
  "geometry": {"coordinates":[-90.90682700000001,33.408124],"type":"Point"}
}