{
  "type": "Feature",
  "properties": {
    "iso:country":"US",
    "sg:address":"5 Jones Rd",
    "sg:city":"Grenada",
    "sg:classifiers":[
        {
            "category":"Organizations",
            "subcategory":"Religious Organization",
            "type":"Services"
        }
    ],
    "sg:phone":"+1 662 294 0920",
    "sg:postcode":"38901",
    "sg:province":"MS",
    "wof:name":"Vine Life Fellowship Church",
    "wof:placetype":"venue"
},
  "geometry": {"coordinates":[-89.801717,33.75924],"type":"Point"}
}