{
  "type": "Feature",
  "properties": {
    "iso:country":"US",
    "sg:address":"267 Daryl Tisdale Rd",
    "sg:city":"Moselle",
    "sg:classifiers":[
        {
            "category":"Home & Garden",
            "subcategory":"Garden Supply",
            "type":"Retail Goods"
        }
    ],
    "sg:phone":"+1 601 752 2707",
    "sg:postcode":"39459",
    "sg:province":"MS",
    "sg:tags":[
        "nurseryman"
    ],
    "wof:name":"Crosby's Nursery",
    "wof:placetype":"venue"
},
  "geometry": {"coordinates":[-89.31935900000001,31.532069],"type":"Point"}
}