{
  "type": "Feature",
  "properties": {
    "iso:country":"US",
    "sg:address":"5135 Galaxie Dr",
    "sg:city":"Jackson",
    "sg:classifiers":[
        {
            "category":"Building & Trades",
            "subcategory":"Cleaning & Sanitation",
            "type":"Services"
        }
    ],
    "sg:phone":"+1 601 362 6211",
    "sg:postcode":"39206",
    "sg:province":"MS",
    "sg:tags":[
        "maintenance"
    ],
    "wof:name":"Dirt Be Gone Inc",
    "wof:placetype":"venue"
},
  "geometry": {"coordinates":[-90.15161500000001,32.36748],"type":"Point"}
}