{
  "type": "Feature",
  "properties": {
    "iso:country":"US",
    "sg:address":"729 Hwy 82 E",
    "sg:city":"Greenville",
    "sg:classifiers":[
        {
            "category":"Personal",
            "subcategory":"Shoe Repair & Shine",
            "type":"Services"
        }
    ],
    "sg:phone":"+1 662 378 9481",
    "sg:postcode":"38701",
    "sg:province":"MS",
    "sg:tags":[
        "repairing",
        "boot"
    ],
    "wof:name":"Dennis Shoe Repair & Clothing",
    "wof:placetype":"venue"
},
  "geometry": {"coordinates":[-91.041791,33.399464],"type":"Point"}
}