{
  "type": "Feature",
  "properties": {
    "iso:country":"US",
    "sg:address":"1320 Azalea Dr",
    "sg:city":"Waynesboro",
    "sg:classifiers":[
        {
            "category":"Shopping",
            "subcategory":"Shoes",
            "type":"Retail Goods"
        }
    ],
    "sg:phone":"+1 601 735 4263",
    "sg:postcode":"39367",
    "sg:province":"MS",
    "wof:name":"Hibbett Sporting Goods Inc",
    "wof:placetype":"venue"
},
  "geometry": {"coordinates":[-88.632898,31.684679],"type":"Point"}
}