{
  "type": "Feature",
  "properties": {
    "addr:full":"100 Felicity St Brandon MS 39042",
    "addr:housenumber":"100",
    "addr:postcode":"39042",
    "addr:street":"Felicity St",
    "iso:country":"US",
    "sg:address":"100 Felicity St",
    "sg:city":"Brandon",
    "sg:classifiers":[
        {
            "category":"Wholesale",
            "subcategory":"Machinery & Supplies",
            "type":"Manufacturing & Wholesale Goods"
        }
    ],
    "sg:phone":"+1 601 825 8446",
    "sg:postcode":"39042",
    "sg:province":"MS",
    "sg:tags":[
        "equipment",
        "industrial"
    ],
    "wof:name":"Hey Boy Corporation",
    "wof:placetype":"venue"
},
  "geometry": {"coordinates":[-89.988086,32.273137],"type":"Point"}
}