{
  "type": "Feature",
  "properties": {
    "iso:country":"US",
    "sg:address":"409 N 15th Ave",
    "sg:city":"Laurel",
    "sg:classifiers":[
        {
            "category":"Insurance",
            "subcategory":"Insurance Agent",
            "type":"Services"
        }
    ],
    "sg:phone":"+1 601 649 4280",
    "sg:postcode":"39440",
    "sg:province":"MS",
    "wof:name":"Walter's Insurance Agency",
    "wof:placetype":"venue"
},
  "geometry": {"coordinates":[-89.145346,31.694342],"type":"Point"}
}