{
  "type": "Feature",
  "properties": {
    "addr:full":"900 E County Line Rd Ridgeland MS 39157",
    "addr:housenumber":"900",
    "addr:postcode":"39157",
    "addr:street":"E County Line Rd",
    "iso:country":"US",
    "sg:address":"900 E County Line Rd",
    "sg:city":"Ridgeland",
    "sg:phone":"+1 601 956 0046",
    "sg:postcode":"39157",
    "sg:province":"MS",
    "wof:name":"Party City",
    "wof:placetype":"venue"
},
  "geometry": {"coordinates":[-90.140717,32.399502],"type":"Point"}
}