{
  "type": "Feature",
  "properties": {
    "addr:full":"221 Belle Pointe Madison MS 39110",
    "addr:housenumber":"221",
    "addr:postcode":"39110",
    "addr:street":"Belle Pointe",
    "iso:country":"US",
    "sg:address":"221 Belle Pointe",
    "sg:city":"Madison",
    "sg:classifiers":[
        {
            "category":"Real Estate",
            "subcategory":"Real Estate Operator",
            "type":"Services"
        }
    ],
    "sg:phone":"+1 601 853 7571",
    "sg:postcode":"39110",
    "sg:province":"MS",
    "sg:tags":[
        "building",
        "nonresidential"
    ],
    "wof:name":"Stonehouse Properties LLC",
    "wof:placetype":"venue"
},
  "geometry": {"coordinates":[-90.15249799999999,32.554881],"type":"Point"}
}