{
  "type": "Feature",
  "properties": {
    "addr:full":"311 Tuscaloosa Rd Columbus MS 39702",
    "addr:housenumber":"311",
    "addr:postcode":"39702",
    "addr:street":"Tuscaloosa Rd",
    "iso:country":"US",
    "sg:address":"311 Tuscaloosa Rd",
    "sg:city":"Columbus",
    "sg:classifiers":[
        {
            "category":"Organizations",
            "subcategory":"Religious Organization",
            "type":"Services"
        }
    ],
    "sg:phone":"+1 662 328 1750",
    "sg:postcode":"39702",
    "sg:province":"MS",
    "sg:tags":[
        "church"
    ],
    "wof:name":"First Pentecostal Church",
    "wof:placetype":"venue"
},
  "geometry": {"coordinates":[-88.38376,33.515658],"type":"Point"}
}