{
  "type": "Feature",
  "properties": {
    "addr:full":"1109 S Main St Petal MS 39465",
    "addr:housenumber":"1109",
    "addr:postcode":"39465",
    "addr:street":"S Main St",
    "iso:country":"US",
    "sg:address":"1109 S Main St",
    "sg:city":"Petal",
    "sg:classifiers":[
        {
            "category":"Freight",
            "type":"Transportation"
        }
    ],
    "sg:phone":"+1 601 545 8339",
    "sg:postcode":"39465",
    "sg:province":"MS",
    "sg:tags":[
        "commercial",
        "storage"
    ],
    "wof:name":"Desoto's Mini Storage",
    "wof:placetype":"venue"
},
  "geometry": {"coordinates":[-89.266498,31.326897],"type":"Point"}
}