{
  "type": "Feature",
  "properties": {
    "addr:full":"4046 Suzanne Dr Diberville MS 39540",
    "addr:housenumber":"4046",
    "addr:postcode":"39540",
    "addr:street":"Suzanne Dr",
    "iso:country":"US",
    "sg:address":"4046 Suzanne Dr",
    "sg:city":"Diberville",
    "sg:classifiers":[
        {
            "category":"Government",
            "subcategory":"Office",
            "type":"Public Place"
        }
    ],
    "sg:phone":"+1 228 396 5194",
    "sg:postcode":"39540",
    "sg:province":"MS",
    "sg:tags":[
        "state",
        "program",
        "health"
    ],
    "wof:name":"WIC Distribution Ctr",
    "wof:placetype":"venue"
},
  "geometry": {"coordinates":[-88.901751,30.440512],"type":"Point"}
}