{
  "type": "Feature",
  "properties": {
    "iso:country":"US",
    "sg:address":"6051 US Hwy 98",
    "sg:city":"Hattiesburg",
    "sg:classifiers":[
        {
            "category":"Building & Trades",
            "subcategory":"Construction",
            "type":"Services"
        }
    ],
    "sg:phone":"+1 601 264 1005",
    "sg:postcode":"39402",
    "sg:province":"MS",
    "sg:tags":[
        "designer",
        "dealer",
        "pool",
        "swimming"
    ],
    "wof:name":"Bill Jones Pool Construction",
    "wof:placetype":"venue"
},
  "geometry": {"coordinates":[-89.383005,31.321541],"type":"Point"}
}