{
  "type": "Feature",
  "properties": {
    "addr:full":"6227 Hwy 612 Lucedale MS 39452",
    "addr:housenumber":"6227",
    "addr:postcode":"39452",
    "addr:street":"Hwy 612 Lucedale",
    "iso:country":"US",
    "sg:address":"6227 Hwy 612",
    "sg:city":"Lucedale",
    "sg:classifiers":[
        {
            "category":"Real Estate",
            "subcategory":"Real Estate Agent",
            "type":"Services"
        }
    ],
    "sg:phone":"+1 601 947 7472",
    "sg:postcode":"39452",
    "sg:province":"MS",
    "wof:name":"H & W Inc",
    "wof:placetype":"venue"
},
  "geometry": {"coordinates":[-88.42379099999999,30.793788],"type":"Point"}
}