{
  "type": "Feature",
  "properties": {
    "iso:country":"US",
    "sg:address":"264 Pinebreeze Rd",
    "sg:city":"Columbus",
    "sg:classifiers":[
        {
            "category":"Professional",
            "subcategory":"Engineering",
            "type":"Services"
        }
    ],
    "sg:phone":"+1 662 241 5114",
    "sg:postcode":"39702",
    "sg:province":"MS",
    "sg:tags":[
        "consultant"
    ],
    "wof:name":"M & M Enterprises",
    "wof:placetype":"venue"
},
  "geometry": {"coordinates":[-88.331694,33.5232],"type":"Point"}
}