{
  "type": "Feature",
  "properties": {
    "iso:country":"US",
    "sg:address":"2991 State Hwy 8",
    "sg:city":"Cleveland",
    "sg:classifiers":[
        {
            "category":"Farming",
            "subcategory":"Farm",
            "type":"Manufacturing & Wholesale Goods"
        }
    ],
    "sg:phone":"+1 662 719 3450",
    "sg:postcode":"38732",
    "sg:province":"MS",
    "sg:tags":[
        "crop"
    ],
    "wof:name":"Icy Bayou Farms Partnership",
    "wof:placetype":"venue"
},
  "geometry": {"coordinates":[-90.79751899999999,33.764394],"type":"Point"}
}