{
  "type": "Feature",
  "properties": {
    "iso:country":"US",
    "sg:address":"610 N Bierdeman Rd",
    "sg:city":"Pearl",
    "sg:classifiers":[
        {
            "category":"Building & Trades",
            "subcategory":"Construction",
            "type":"Services"
        }
    ],
    "sg:phone":"+1 601 936 0091",
    "sg:postcode":"39208",
    "sg:province":"MS",
    "sg:tags":[
        "boring",
        "drilling",
        "contractor"
    ],
    "wof:name":"A-Mc Construction Drilling",
    "wof:placetype":"venue"
},
  "geometry": {"coordinates":[-90.12996800000001,32.282858],"type":"Point"}
}