{
  "type": "Feature",
  "properties": {
    "iso:country":"US",
    "sg:address":"2591 Brighton Cir",
    "sg:city":"Biloxi",
    "sg:classifiers":[
        {
            "category":"Travel",
            "subcategory":"Hotels & Motels",
            "type":"Entertainment"
        }
    ],
    "sg:phone":"+1 228 388 1656",
    "sg:postcode":"39531",
    "sg:province":"MS",
    "sg:tags":[
        "management"
    ],
    "sg:website":"www.hibiloxi.com",
    "wof:name":"Gulfshores Inc",
    "wof:placetype":"venue"
},
  "geometry": {"coordinates":[-88.985122,30.405119],"type":"Point"}
}