{
  "type": "Feature",
  "properties": {
    "iso:country":"US",
    "sg:address":"244 Cowart Holliday Rd",
    "sg:city":"Poplarville",
    "sg:classifiers":[
        {
            "category":"Freight",
            "type":"Transportation"
        }
    ],
    "sg:phone":"+1 601 795 6724",
    "sg:postcode":"39470",
    "sg:province":"MS",
    "sg:tags":[
        "operator",
        "local",
        "trucking"
    ],
    "wof:name":"Dns Trucking Inc",
    "wof:placetype":"venue"
},
  "geometry": {"coordinates":[-89.556382,30.796391],"type":"Point"}
}