{
  "type": "Feature",
  "properties": {
    "iso:country":"US",
    "sg:address":"346 Cameron St",
    "sg:city":"Jackson",
    "sg:phone":"+1 601 372 4582",
    "sg:postcode":"39212",
    "sg:province":"MS",
    "sg:tags":[
        "farm",
        "corn"
    ],
    "wof:name":"Roger Pettigrew",
    "wof:placetype":"venue"
},
  "geometry": {"coordinates":[-90.220461,32.24404],"type":"Point"}
}