{
  "type": "Feature",
  "properties": {
    "addr:full":"12514 Hwy 24 E Centreville MS 39631",
    "addr:housenumber":"12514",
    "addr:postcode":"39631",
    "addr:street":"Hwy 24 E",
    "iso:country":"US",
    "sg:address":"12514 Hwy 24 E",
    "sg:city":"Centreville",
    "sg:classifiers":[
        {
            "category":"Organizations",
            "subcategory":"Religious Organization",
            "type":"Services"
        }
    ],
    "sg:phone":"+1 601 645 5399",
    "sg:postcode":"39631",
    "sg:province":"MS",
    "wof:name":"Kingdom Hall Jhovahs Witnesses",
    "wof:placetype":"venue"
},
  "geometry": {"coordinates":[-91.087881,31.078058],"type":"Point"}
}