{
  "type": "Feature",
  "properties": {
    "iso:country":"US",
    "sg:address":"501 Pine St",
    "sg:city":"Picayune",
    "sg:classifiers":[
        {
            "category":"Professional",
            "subcategory":"Engineering",
            "type":"Services"
        }
    ],
    "sg:phone":"+1 601 798 9914",
    "sg:postcode":"39466",
    "sg:province":"MS",
    "wof:name":"Sea Probe",
    "wof:placetype":"venue"
},
  "geometry": {"coordinates":[-89.681839,30.531219],"type":"Point"}
}