{
  "type": "Feature",
  "properties": {
    "iso:country":"US",
    "sg:address":"898 Hwy 41 N",
    "sg:city":"Okolona",
    "sg:classifiers":[
        {
            "category":"Home & Garden",
            "subcategory":"Furniture",
            "type":"Retail Goods"
        }
    ],
    "sg:phone":"+1 662 447 3992",
    "sg:postcode":"38860",
    "sg:province":"MS",
    "wof:name":"Docs Matress Factory",
    "wof:placetype":"venue"
},
  "geometry": {"coordinates":[-88.810344,34.035522],"type":"Point"}
}