{
  "type": "Feature",
  "properties": {
    "iso:country":"US",
    "sg:address":"101 W 1st St",
    "sg:city":"Newton",
    "sg:classifiers":[
        {
            "category":"Building & Trades",
            "subcategory":"Plumbing",
            "type":"Services"
        }
    ],
    "sg:phone":"+1 601 683 6020",
    "sg:postcode":"39345",
    "sg:province":"MS",
    "sg:tags":[
        "plumbing",
        "contractor"
    ],
    "wof:name":"Usry's Tip Top Plumbing",
    "wof:placetype":"venue"
},
  "geometry": {"coordinates":[-89.164681,32.319327],"type":"Point"}
}