{
  "type": "Feature",
  "properties": {
    "iso:country":"US",
    "sg:address":"3200 Medgar Evers Blvd",
    "sg:city":"Jackson",
    "sg:classifiers":[
        {
            "category":"Shopping",
            "type":"Retail Goods"
        }
    ],
    "sg:phone":"+1 601 982 7112",
    "sg:postcode":"39213",
    "sg:province":"MS",
    "sg:tags":[
        "religious"
    ],
    "wof:name":"Bell's Robes & Worship Aids",
    "wof:placetype":"venue"
},
  "geometry": {"coordinates":[-90.250187,32.372552],"type":"Point"}
}