{
  "type": "Feature",
  "properties": {
    "iso:country":"US",
    "sg:address":"715 N 10th Ave",
    "sg:city":"Laurel",
    "sg:classifiers":[
        {
            "category":"Recreation",
            "type":"Entertainment"
        }
    ],
    "sg:phone":"+1 601 428 6452",
    "sg:postcode":"39440",
    "sg:province":"MS",
    "sg:tags":[
        "parks"
    ],
    "wof:name":"City Recreation",
    "wof:placetype":"venue"
},
  "geometry": {"coordinates":[-89.13855700000001,31.697812],"type":"Point"}
}