{
  "type": "Feature",
  "properties": {
    "iso:country":"US",
    "sg:address":"303 Pebble Brook Dr",
    "sg:city":"Clinton",
    "sg:classifiers":[
        {
            "category":"Real Estate",
            "subcategory":"Real Estate Operator",
            "type":"Services"
        }
    ],
    "sg:phone":"+1 601 924 4232",
    "sg:postcode":"39056",
    "sg:province":"MS",
    "sg:tags":[
        "building",
        "nonresidential"
    ],
    "wof:name":"Collins Properties of Clinton",
    "wof:placetype":"venue"
},
  "geometry": {"coordinates":[-90.331701,32.314677],"type":"Point"}
}