{
  "type": "Feature",
  "properties": {
    "addr:full":"109 Westside Cove Pearl MS 39208",
    "addr:housenumber":"109",
    "addr:postcode":"39208",
    "addr:street":"Westside Cove",
    "iso:country":"US",
    "sg:address":"109 Westside Cove",
    "sg:city":"Pearl",
    "sg:classifiers":[
        {
            "category":"Professional",
            "subcategory":"Computer Services",
            "type":"Services"
        }
    ],
    "sg:phone":"+1 601 932 3955",
    "sg:postcode":"39208",
    "sg:province":"MS",
    "sg:tags":[
        "wiring"
    ],
    "sg:website":"www.jsico.com",
    "wof:name":"James Self Inc",
    "wof:placetype":"venue"
},
  "geometry": {"coordinates":[-90.04451299999999,32.284748],"type":"Point"}
}