{
  "type": "Feature",
  "properties": {
    "addr:full":"1003 Bellevue Pl Jackson MS 39202",
    "addr:housenumber":"1003",
    "addr:postcode":"39202",
    "addr:street":"Bellevue Pl",
    "iso:country":"US",
    "sg:address":"1003 Bellevue Pl",
    "sg:city":"Jackson",
    "sg:classifiers":[
        {
            "category":"Professional",
            "subcategory":"Business Services",
            "type":"Services"
        }
    ],
    "sg:phone":"+1 601 948 5140",
    "sg:postcode":"39202",
    "sg:province":"MS",
    "sg:tags":[
        "transcribing",
        "disc"
    ],
    "wof:name":"Medical Office Outsourcing",
    "wof:placetype":"venue"
},
  "geometry": {"coordinates":[-90.17189999999999,32.30903],"type":"Point"}
}