{
  "type": "Feature",
  "properties": {
    "iso:country":"US",
    "sg:address":"2300 24th Ave",
    "sg:city":"Gulfport",
    "sg:classifiers":[
        {
            "category":"Professional",
            "subcategory":"Lawyer & Legal Services",
            "type":"Services"
        }
    ],
    "sg:phone":"+1 228 868 5667",
    "sg:postcode":"39501",
    "sg:province":"MS",
    "sg:tags":[
        "attorney"
    ],
    "wof:name":"David L Lord & Assoc",
    "wof:placetype":"venue"
},
  "geometry": {"coordinates":[-89.091673,30.37908],"type":"Point"}
}