{
  "type": "Feature",
  "properties": {
    "iso:country":"US",
    "sg:address":"882 N Lehmberg Rd",
    "sg:city":"Columbus",
    "sg:classifiers":[
        {
            "category":"Shopping",
            "subcategory":"Clothing, Apparel, & Fashions",
            "type":"Retail Goods"
        }
    ],
    "sg:phone":"+1 662 327 0805",
    "sg:postcode":"39702",
    "sg:province":"MS",
    "sg:tags":[
        "alteration"
    ],
    "wof:name":"Commerce Cleaners",
    "wof:placetype":"venue"
},
  "geometry": {"coordinates":[-88.36346899999999,33.5102],"type":"Point"}
}