{
  "type": "Feature",
  "properties": {
    "iso:country":"US",
    "sg:address":"6791 S Siwell Rd",
    "sg:city":"Byram",
    "sg:classifiers":[
        {
            "category":"Restaurant",
            "type":"Food & Drink"
        }
    ],
    "sg:phone":"+1 601 376 4677",
    "sg:postcode":"39272",
    "sg:province":"MS",
    "wof:name":"Mott's Backdoor Bbq",
    "wof:placetype":"venue"
},
  "geometry": {"coordinates":[-90.28921,32.202791],"type":"Point"}
}