{
  "type": "Feature",
  "properties": {
    "addr:full":"1269 Main St Fayette MS 39069",
    "addr:housenumber":"1269",
    "addr:postcode":"39069",
    "addr:street":"Main St",
    "iso:country":"US",
    "sg:address":"1269 Main St",
    "sg:city":"Fayette",
    "sg:classifiers":[
        {
            "category":"Government",
            "subcategory":"Office",
            "type":"Public Place"
        }
    ],
    "sg:phone":"+1 601 786 0311",
    "sg:postcode":"39069",
    "sg:province":"MS",
    "wof:name":"Jefferson County E911 Office",
    "wof:placetype":"venue"
},
  "geometry": {"coordinates":[-91.05870899999999,31.72254],"type":"Point"}
}