{
  "type": "Feature",
  "properties": {
    "addr:full":"2035 Old Industrial Rd Mc Comb MS 39648",
    "addr:housenumber":"2035",
    "addr:postcode":"39648",
    "addr:street":"Old Industrial Rd",
    "iso:country":"US",
    "sg:address":"2035 Old Industrial Rd",
    "sg:city":"Mc Comb",
    "sg:classifiers":[
        {
            "category":"Building & Trades",
            "subcategory":"Equipment Rental",
            "type":"Services"
        }
    ],
    "sg:phone":"+1 601 684 9516",
    "sg:postcode":"39648",
    "sg:province":"MS",
    "wof:name":"Amite Rental Ctr LLC",
    "wof:placetype":"venue"
},
  "geometry": {"coordinates":[-90.438244,31.205514],"type":"Point"}
}