{
  "type": "Feature",
  "properties": {
    "iso:country":"US",
    "sg:address":"17 Ivey Ln",
    "sg:city":"Picayune",
    "sg:classifiers":[
        {
            "category":"Utilities",
            "subcategory":"Mobile Phone",
            "type":"Services"
        }
    ],
    "sg:phone":"+1 601 215 0000",
    "sg:postcode":"39402",
    "sg:province":"MS",
    "sg:tags":[
        "telephone",
        "cellular"
    ],
    "wof:name":"Cellular XL",
    "wof:placetype":"venue"
},
  "geometry": {"coordinates":[-89.358914,31.270517],"type":"Point"}
}