{
  "type": "Feature",
  "properties": {
    "iso:country":"US",
    "sg:address":"6770 Co Rd 825",
    "sg:city":"Blue Mountain",
    "sg:classifiers":[
        {
            "category":"Building & Trades",
            "subcategory":"Pest Control",
            "type":"Services"
        }
    ],
    "sg:phone":"+1 662 685 9422",
    "sg:postcode":"38610",
    "sg:province":"MS",
    "wof:name":"Henderson Pest Control Inc",
    "wof:placetype":"venue"
},
  "geometry": {"coordinates":[-89.051367,34.656722],"type":"Point"}
}