{
  "type": "Feature",
  "properties": {
    "iso:country":"US",
    "sg:address":"50 Castlewoods Blvd",
    "sg:city":"Brandon",
    "sg:classifiers":[
        {
            "category":"Social Services",
            "subcategory":"Child Care",
            "type":"Services"
        }
    ],
    "sg:phone":"+1 601 919 9175",
    "sg:postcode":"39232",
    "sg:province":"MS",
    "wof:name":"Super Kids Learning Ctr",
    "wof:placetype":"venue"
},
  "geometry": {"coordinates":[-90.012084,32.35633],"type":"Point"}
}