{
  "type": "Feature",
  "properties": {
    "addr:full":"301 US Hwy 51 Pickens MS 39146",
    "addr:housenumber":"301",
    "addr:postcode":"39146",
    "addr:street":"Us Hwy 51",
    "iso:country":"US",
    "sg:address":"301 US Hwy 51",
    "sg:city":"Pickens",
    "sg:classifiers":[
        {
            "category":"Government",
            "subcategory":"Police Station",
            "type":"Public Place"
        }
    ],
    "sg:phone":"+1 662 468 9898",
    "sg:postcode":"39146",
    "sg:province":"MS",
    "sg:tags":[
        "department"
    ],
    "wof:name":"Pickens Police Dept",
    "wof:placetype":"venue"
},
  "geometry": {"coordinates":[-89.976198,32.872647],"type":"Point"}
}