{
  "type": "Feature",
  "properties": {
    "iso:country":"US",
    "sg:address":"792 Water St",
    "sg:city":"Biloxi",
    "sg:classifiers":[
        {
            "category":"Wholesale",
            "subcategory":"Electrical",
            "type":"Manufacturing & Wholesale Goods"
        }
    ],
    "sg:phone":"+1 228 432 7775",
    "sg:postcode":"39530",
    "sg:province":"MS",
    "sg:tags":[
        "control",
        "security",
        "system"
    ],
    "wof:name":"Southern Integrated Tech",
    "wof:placetype":"venue"
},
  "geometry": {"coordinates":[-88.888468,30.394802],"type":"Point"}
}