{
  "type": "Feature",
  "properties": {
    "iso:country":"US",
    "sg:address":"5146 York Rd",
    "sg:city":"Lauderdale",
    "sg:classifiers":[
        {
            "category":"Government",
            "subcategory":"Fire Station",
            "type":"Public Place"
        }
    ],
    "sg:phone":"+1 601 632 4432",
    "sg:postcode":"39335",
    "sg:province":"MS",
    "sg:tags":[
        "department"
    ],
    "wof:name":"Center Ridge Volunteer Fire",
    "wof:placetype":"venue"
},
  "geometry": {"coordinates":[-88.467102,32.543309],"type":"Point"}
}