{
  "type": "Feature",
  "properties": {
    "addr:full":"434 Airport Rd Natchez MS 39120",
    "addr:housenumber":"434",
    "addr:postcode":"39120",
    "addr:street":"Airport Rd",
    "iso:country":"US",
    "sg:address":"434 Airport Rd",
    "sg:city":"Natchez",
    "sg:classifiers":[
        {
            "category":"Airport",
            "type":"Transportation"
        }
    ],
    "sg:phone":"+1 601 442 5171",
    "sg:postcode":"39120",
    "sg:province":"MS",
    "wof:name":"Natchez Adams County Airport",
    "wof:placetype":"venue"
},
  "geometry": {"coordinates":[-91.28919399999999,31.615602],"type":"Point"}
}