{
  "type": "Feature",
  "properties": {
    "iso:country":"US",
    "sg:address":"303 Main St",
    "sg:city":"Union",
    "sg:classifiers":[
        {
            "category":"Restaurant",
            "type":"Food & Drink"
        }
    ],
    "sg:phone":"+1 601 774 9566",
    "sg:postcode":"39365",
    "sg:province":"MS",
    "sg:tags":[
        "barbecue"
    ],
    "wof:name":"Dave's Hotspot Barbeque",
    "wof:placetype":"venue"
},
  "geometry": {"coordinates":[-89.119721,32.572175],"type":"Point"}
}