{
  "type": "Feature",
  "properties": {
    "iso:country":"US",
    "sg:address":"385 Drew Merigold Rd",
    "sg:city":"Merigold",
    "sg:phone":"+1 662 745 2129",
    "sg:postcode":"38759",
    "sg:province":"MS",
    "sg:tags":[
        "farm",
        "rice",
        "soybean",
        "cotton"
    ],
    "wof:name":"A Tidmore",
    "wof:placetype":"venue"
},
  "geometry": {"coordinates":[-90.591543,33.81298],"type":"Point"}
}