{
  "type": "Feature",
  "properties": {
    "iso:country":"US",
    "sg:address":"4630 Magnolia St",
    "sg:city":"Moss Point",
    "sg:classifiers":[
        {
            "category":"Education",
            "subcategory":"School",
            "type":"Public Place"
        }
    ],
    "sg:phone":"+1 228 475 1429",
    "sg:postcode":"39563",
    "sg:province":"MS",
    "sg:website":"www.mp.k12.ms.us",
    "wof:name":"Magnolia Junior High School",
    "wof:placetype":"venue"
},
  "geometry": {"coordinates":[-88.547522,30.410505],"type":"Point"}
}