{
  "type": "Feature",
  "properties": {
    "iso:country":"US",
    "sg:address":"205 Bay Ave",
    "sg:city":"Richton",
    "sg:classifiers":[
        {
            "category":"Health Services",
            "subcategory":"Doctor",
            "type":"Services"
        }
    ],
    "sg:phone":"+1 601 788 9374",
    "sg:postcode":"39476",
    "sg:province":"MS",
    "sg:tags":[
        "dentist"
    ],
    "wof:name":"A Roddy Scarbrough DDS",
    "wof:placetype":"venue"
},
  "geometry": {"coordinates":[-88.938121,31.346991],"type":"Point"}
}