{
  "type": "Feature",
  "properties": {
    "iso:country":"US",
    "sg:address":"1085 Ted Thompson Rd",
    "sg:city":"Summit",
    "sg:classifiers":[
        {
            "category":"Building & Trades",
            "subcategory":"Construction",
            "type":"Services"
        }
    ],
    "sg:phone":"+1 601 684 5650",
    "sg:postcode":"39666",
    "sg:province":"MS",
    "sg:tags":[
        "carpentry",
        "contractor"
    ],
    "wof:name":"Gimmie Shelter General Contrs",
    "wof:placetype":"venue"
},
  "geometry": {"coordinates":[-90.320376,31.286214],"type":"Point"}
}