{
  "type": "Feature",
  "properties": {
    "addr:full":"60026 Industrial Dr Smithville MS 38821",
    "addr:housenumber":"60026",
    "addr:postcode":"38821",
    "addr:street":"Industrial Dr",
    "iso:country":"US",
    "sg:address":"60026 Industrial Dr",
    "sg:city":"Smithville",
    "sg:classifiers":[
        {
            "category":"Manufacturing",
            "subcategory":"Tools & Machinery",
            "type":"Manufacturing & Wholesale Goods"
        }
    ],
    "sg:phone":"+1 662 651 5438",
    "sg:postcode":"38821",
    "sg:province":"MS",
    "sg:tags":[
        "machine",
        "shop"
    ],
    "wof:name":"Maxey Millwright & Machine Inc",
    "wof:placetype":"venue"
},
  "geometry": {"coordinates":[-88.480909,33.968878],"type":"Point"}
}