{
  "type": "Feature",
  "properties": {
    "iso:country":"US",
    "sg:address":"419 S State St",
    "sg:city":"Jackson",
    "sg:classifiers":[
        {
            "category":"Professional",
            "subcategory":"Lawyer & Legal Services",
            "type":"Services"
        }
    ],
    "sg:phone":"+1 601 969 1900",
    "sg:postcode":"39201",
    "sg:province":"MS",
    "sg:tags":[
        "attorney"
    ],
    "wof:name":"William P Featherston Jr",
    "wof:placetype":"venue"
},
  "geometry": {"coordinates":[-90.18127800000001,32.295313],"type":"Point"}
}