{
  "type": "Feature",
  "properties": {
    "addr:full":"5455 Desoto Rd Horn Lake MS 38637",
    "addr:housenumber":"5455",
    "addr:postcode":"38637",
    "addr:street":"Desoto Rd",
    "iso:country":"US",
    "sg:address":"5455 Desoto Rd",
    "sg:city":"Horn Lake",
    "sg:classifiers":[
        {
            "category":"Professional",
            "type":"Services"
        }
    ],
    "sg:phone":"+1 662 781 0820",
    "sg:postcode":"38637",
    "sg:province":"MS",
    "sg:tags":[
        "establishment"
    ],
    "wof:name":"Mike's Desoto Road Auto",
    "wof:placetype":"venue"
},
  "geometry": {"coordinates":[-90.08701000000001,34.976981],"type":"Point"}
}