{
  "type": "Feature",
  "properties": {
    "iso:country":"US",
    "sg:address":"1224 65th Ave",
    "sg:city":"Meridian",
    "sg:classifiers":[
        {
            "category":"Organizations",
            "subcategory":"Religious Organization",
            "type":"Services"
        }
    ],
    "sg:phone":"+1 601 482 3283",
    "sg:postcode":"39307",
    "sg:province":"MS",
    "sg:tags":[
        "church"
    ],
    "sg:website":"www.excitingwestwood.faithweb.com",
    "wof:name":"Westwood Baptist Church",
    "wof:placetype":"venue"
},
  "geometry": {"coordinates":[-88.74466200000001,32.368794],"type":"Point"}
}