{
  "type": "Feature",
  "properties": {
    "addr:full":"112 N Broadway St Tupelo MS 38804",
    "addr:housenumber":"112",
    "addr:postcode":"38804",
    "addr:street":"N Broadway St",
    "iso:country":"US",
    "sg:address":"112 N Broadway St",
    "sg:city":"Tupelo",
    "sg:classifiers":[
        {
            "category":"Professional",
            "subcategory":"Lawyer & Legal Services",
            "type":"Services"
        }
    ],
    "sg:phone":"+1 662 844 0944",
    "sg:postcode":"38804",
    "sg:province":"MS",
    "wof:name":"Thorne Michael G",
    "wof:placetype":"venue"
},
  "geometry": {"coordinates":[-88.70531699999999,34.25817],"type":"Point"}
}