{
  "type": "Feature",
  "properties": {
    "iso:country":"US",
    "sg:address":"104 W Sunset Dr",
    "sg:city":"Brandon",
    "sg:classifiers":[
        {
            "category":"Insurance",
            "subcategory":"Insurance Agent",
            "type":"Services"
        }
    ],
    "sg:phone":"+1 601 824 4611",
    "sg:postcode":"39042",
    "sg:province":"MS",
    "wof:name":"Tebran Insurance Consultants",
    "wof:placetype":"venue"
},
  "geometry": {"coordinates":[-89.991905,32.265443],"type":"Point"}
}