{
  "type": "Feature",
  "properties": {
    "iso:country":"US",
    "sg:address":"118 N Meridian St",
    "sg:city":"Aberdeen",
    "sg:classifiers":[
        {
            "category":"Food & Beverages",
            "subcategory":"Groceries & Convenience Stores",
            "type":"Retail Goods"
        }
    ],
    "sg:phone":"+1 662 369 4813",
    "sg:postcode":"39730",
    "sg:province":"MS",
    "wof:name":"Big Star Grocery",
    "wof:placetype":"venue"
},
  "geometry": {"coordinates":[-88.54374900000001,33.825589],"type":"Point"}
}