{
  "type": "Feature",
  "properties": {
    "addr:full":"730 Lincoln Pl Clarksdale MS 38614",
    "addr:housenumber":"730",
    "addr:postcode":"38614",
    "addr:street":"Lincoln Pl",
    "iso:country":"US",
    "sg:address":"730 Lincoln Pl",
    "sg:city":"Clarksdale",
    "sg:classifiers":[
        {
            "category":"Travel",
            "subcategory":"Hotels & Motels",
            "type":"Entertainment"
        }
    ],
    "sg:phone":"+1 662 624 9900",
    "sg:postcode":"38614",
    "sg:province":"MS",
    "wof:name":"Hicks Motel",
    "wof:placetype":"venue"
},
  "geometry": {"coordinates":[-90.56227,34.196832],"type":"Point"}
}