{
  "type": "Feature",
  "properties": {
    "iso:country":"US",
    "sg:address":"416 Francis St",
    "sg:city":"Leakesville",
    "sg:classifiers":[
        {
            "category":"Professional",
            "subcategory":"Accounting & Tax Preparation",
            "type":"Services"
        }
    ],
    "sg:phone":"+1 601 394 5017",
    "sg:postcode":"39401",
    "sg:province":"MS",
    "sg:tags":[
        "accountant"
    ],
    "wof:name":"Cary E Williams CPA",
    "wof:placetype":"venue"
},
  "geometry": {"coordinates":[-89.30174100000001,31.311476],"type":"Point"}
}