{
  "type": "Feature",
  "properties": {
    "addr:full":"1213 Maria Ln Iuka MS 38852",
    "addr:housenumber":"1213",
    "addr:postcode":"38852",
    "addr:street":"Maria Ln",
    "iso:country":"US",
    "sg:address":"1213 Maria Ln",
    "sg:city":"Iuka",
    "sg:classifiers":[
        {
            "category":"Health Services",
            "subcategory":"Hospital",
            "type":"Services"
        }
    ],
    "sg:phone":"+1 662 423 3332",
    "sg:postcode":"38852",
    "sg:province":"MS",
    "sg:tags":[
        "mental"
    ],
    "wof:name":"Timber Hills Mental Health Svc",
    "wof:placetype":"venue"
},
  "geometry": {"coordinates":[-88.206992,34.806423],"type":"Point"}
}