{
  "type": "Feature",
  "properties": {
    "iso:country":"US",
    "sg:address":"210 W Main St",
    "sg:city":"Fulton",
    "sg:classifiers":[
        {
            "category":"Shopping",
            "subcategory":"Used Merchandise",
            "type":"Retail Goods"
        }
    ],
    "sg:phone":"+1 662 862 5111",
    "sg:postcode":"38843",
    "sg:province":"MS",
    "sg:tags":[
        "antique"
    ],
    "wof:name":"Courtsquare Antiques & Cllctbl",
    "wof:placetype":"venue"
},
  "geometry": {"coordinates":[-88.40896600000001,34.273707],"type":"Point"}
}