{
  "type": "Feature",
  "properties": {
    "addr:full":"310 Research Blvd Starkville MS 39759",
    "addr:housenumber":"310",
    "addr:postcode":"39759",
    "addr:street":"Research Blvd",
    "iso:country":"US",
    "sg:address":"310 Research Blvd",
    "sg:city":"Starkville",
    "sg:classifiers":[
        {
            "category":"Utilities",
            "subcategory":"Electric",
            "type":"Services"
        }
    ],
    "sg:phone":"+1 662 338 3160",
    "sg:postcode":"39759",
    "sg:province":"MS",
    "wof:name":"Tennessee Valley Authority",
    "wof:placetype":"venue"
},
  "geometry": {"coordinates":[-88.794489,33.472505],"type":"Point"}
}