{
  "type": "Feature",
  "properties": {
    "iso:country":"US",
    "sg:address":"216 Shenandoah Rd",
    "sg:city":"Brandon",
    "sg:classifiers":[
        {
            "category":"Building & Trades",
            "subcategory":"Construction",
            "type":"Services"
        }
    ],
    "sg:phone":"+1 601 992 4142",
    "sg:postcode":"39047",
    "sg:province":"MS",
    "sg:tags":[
        "house"
    ],
    "wof:name":"Alpha Inspection",
    "wof:placetype":"venue"
},
  "geometry": {"coordinates":[-90.02221299999999,32.369761],"type":"Point"}
}