{
  "type": "Feature",
  "properties": {
    "iso:country":"US",
    "sg:address":"214 N Harvey St",
    "sg:city":"Greenville",
    "sg:classifiers":[
        {
            "category":"Home & Garden",
            "subcategory":"Furniture",
            "type":"Retail Goods"
        }
    ],
    "sg:phone":"+1 662 335 7771",
    "sg:postcode":"38701",
    "sg:province":"MS",
    "sg:tags":[
        "mattress"
    ],
    "wof:name":"Griffin's Factory House Inc",
    "wof:placetype":"venue"
},
  "geometry": {"coordinates":[-91.05166199999999,33.41036],"type":"Point"}
}