{
  "type": "Feature",
  "properties": {
    "iso:country":"US",
    "sg:address":"1042 Holland Ave",
    "sg:city":"Philadelphia",
    "sg:classifiers":[
        {
            "category":"Professional",
            "subcategory":"Business Services",
            "type":"Services"
        }
    ],
    "sg:phone":"+1 601 656 9768",
    "sg:postcode":"39350",
    "sg:province":"MS",
    "sg:tags":[
        "auctioneer"
    ],
    "wof:name":"Deanco Auction Co",
    "wof:placetype":"venue"
},
  "geometry": {"coordinates":[-89.10047400000001,32.752676],"type":"Point"}
}