{
  "type": "Feature",
  "properties": {
    "iso:country":"US",
    "sg:address":"4527 Henderson Rd",
    "sg:city":"Byram",
    "sg:classifiers":[
        {
            "category":"Building & Trades",
            "subcategory":"Cleaning & Sanitation",
            "type":"Services"
        },
        {
            "category":"Building & Trades",
            "subcategory":"Plumbing",
            "type":"Services"
        }
    ],
    "sg:phone":"+1 601 371 1269",
    "sg:postcode":"39272",
    "sg:province":"MS",
    "sg:tags":[
        "repair",
        "maintenance",
        "septic"
    ],
    "wof:name":"Dier's Sanitation",
    "wof:placetype":"venue"
},
  "geometry": {"coordinates":[-90.27962599999999,32.208334],"type":"Point"}
}