{
  "type": "Feature",
  "properties": {
    "addr:full":"2600 Carsley Rd Jackson MS 39209",
    "addr:housenumber":"2600",
    "addr:postcode":"39209",
    "addr:street":"Carsley Rd",
    "iso:country":"US",
    "sg:address":"2600 Carsley Rd",
    "sg:city":"Jackson",
    "sg:classifiers":[
        {
            "category":"Farming",
            "subcategory":"Farm",
            "type":"Manufacturing & Wholesale Goods"
        }
    ],
    "sg:phone":"+1 601 925 0079",
    "sg:postcode":"39209",
    "sg:province":"MS",
    "wof:name":"Providence Hill Farm LLC",
    "wof:placetype":"venue"
},
  "geometry": {"coordinates":[-90.372827,32.474888],"type":"Point"}
}