{
  "type": "Feature",
  "properties": {
    "iso:country":"US",
    "sg:address":"722 China St",
    "sg:city":"Vicksburg",
    "sg:classifiers":[
        {
            "category":"Autos & Motor Vehicles",
            "subcategory":"Fuel & Gas Station",
            "type":"Retail Goods"
        }
    ],
    "sg:phone":"+1 601 636 6471",
    "sg:postcode":"39183",
    "sg:province":"MS",
    "sg:tags":[
        "station",
        "gasoline"
    ],
    "wof:name":"Warnock Service Center",
    "wof:placetype":"venue"
},
  "geometry": {"coordinates":[-90.881698,32.350981],"type":"Point"}
}