{
  "type": "Feature",
  "properties": {
    "addr:full":"900 Earl Frye Blvd Amory MS 38821",
    "addr:housenumber":"900",
    "addr:postcode":"38821",
    "addr:street":"Earl Frye Blvd",
    "iso:country":"US",
    "sg:address":"900 Earl Frye Blvd",
    "sg:city":"Amory",
    "sg:classifiers":[
        {
            "category":"Health Services",
            "subcategory":"Doctor",
            "type":"Services"
        }
    ],
    "sg:phone":"+1 662 256 9391",
    "sg:postcode":"38821",
    "sg:province":"MS",
    "sg:tags":[
        "clinic"
    ],
    "wof:name":"Physicians & Surgeons Clinic",
    "wof:placetype":"venue"
},
  "geometry": {"coordinates":[-88.477706,33.977913],"type":"Point"}
}