{
  "type": "Feature",
  "properties": {
    "iso:country":"US",
    "sg:address":"720 N Lehmberg Rd",
    "sg:city":"Columbus",
    "sg:classifiers":[
        {
            "category":"Building & Trades",
            "subcategory":"Pest Control",
            "type":"Services"
        }
    ],
    "sg:phone":"+1 662 329 2796",
    "sg:postcode":"39702",
    "sg:province":"MS",
    "wof:name":"James Price Termite Pest Cntrl",
    "wof:placetype":"venue"
},
  "geometry": {"coordinates":[-88.363382,33.506494],"type":"Point"}
}