{
  "type": "Feature",
  "properties": {
    "iso:country":"US",
    "sg:address":"511 Willow Court Dr",
    "sg:city":"Brandon",
    "sg:classifiers":[
        {
            "category":"Shopping",
            "subcategory":"Gifts & Souvenirs",
            "type":"Retail Goods"
        }
    ],
    "sg:phone":"+1 601 992 3883",
    "sg:postcode":"39047",
    "sg:province":"MS",
    "wof:name":"2 Busy Today",
    "wof:placetype":"venue"
},
  "geometry": {"coordinates":[-89.991411,32.345972],"type":"Point"}
}