{
  "type": "Feature",
  "properties": {
    "addr:full":"4192 Ward Pineview Rd Lucedale MS 39452",
    "addr:housenumber":"4192",
    "addr:postcode":"39452",
    "addr:street":"Ward Pineview Rd",
    "iso:country":"US",
    "sg:address":"4192 Ward Pineview Rd",
    "sg:city":"Lucedale",
    "sg:classifiers":[
        {
            "category":"Building & Trades",
            "subcategory":"Electrical",
            "type":"Services"
        }
    ],
    "sg:phone":"+1 601 766 3899",
    "sg:postcode":"39452",
    "sg:province":"MS",
    "sg:tags":[
        "electric",
        "contractor"
    ],
    "wof:name":"Nelson Electrical Svc",
    "wof:placetype":"venue"
},
  "geometry": {"coordinates":[-88.53436000000001,30.892374],"type":"Point"}
}