{
  "type": "Feature",
  "properties": {
    "addr:full":"9534 W Lauderdale Rd Collinsville MS 39325",
    "addr:housenumber":"9534",
    "addr:postcode":"39325",
    "addr:street":"W Lauderdale Rd",
    "iso:country":"US",
    "sg:address":"9534 W Lauderdale Rd",
    "sg:city":"Collinsville",
    "sg:classifiers":[
        {
            "category":"Travel",
            "subcategory":"Campground",
            "type":"Entertainment"
        }
    ],
    "sg:phone":"+1 601 626 8455",
    "sg:postcode":"39325",
    "sg:province":"MS",
    "sg:tags":[
        "attendant",
        "camp",
        "ground"
    ],
    "wof:name":"Johnnie Foreman",
    "wof:placetype":"venue"
},
  "geometry": {"coordinates":[-88.82631000000001,32.511434],"type":"Point"}
}