{
  "type": "Feature",
  "properties": {
    "iso:country":"US",
    "sg:address":"3911 Co Rd 301",
    "sg:city":"Tiplersville",
    "sg:phone":"+1 662 223 4390",
    "sg:postcode":"38674",
    "sg:province":"MS",
    "sg:tags":[
        "farm",
        "corn",
        "soybean"
    ],
    "wof:name":"Ned Patrick",
    "wof:placetype":"venue"
},
  "geometry": {"coordinates":[-88.96434600000001,34.887178],"type":"Point"}
}