{
  "type": "Feature",
  "properties": {
    "addr:full":"7224 Poplar Springs Dr Meridian MS 39305",
    "addr:housenumber":"7224",
    "addr:postcode":"39305",
    "addr:street":"Poplar Springs Dr",
    "iso:country":"US",
    "sg:address":"7224 Poplar Springs Dr",
    "sg:city":"Meridian",
    "sg:classifiers":[
        {
            "category":"Professional",
            "subcategory":"Lawyer & Legal Services",
            "type":"Services"
        }
    ],
    "sg:phone":"+1 601 693 6445",
    "sg:postcode":"39305",
    "sg:province":"MS",
    "sg:tags":[
        "attorney"
    ],
    "wof:name":"Maurice H Hall Jr",
    "wof:placetype":"venue"
},
  "geometry": {"coordinates":[-88.694609,32.435117],"type":"Point"}
}