{
  "type": "Feature",
  "properties": {
    "iso:country":"US",
    "sg:address":"5071 Austin Rd",
    "sg:city":"Lake Cormorant",
    "sg:classifiers":[
        {
            "category":"Wholesale",
            "subcategory":"Metals & Minerals",
            "type":"Manufacturing & Wholesale Goods"
        }
    ],
    "sg:phone":"+1 662 781 4000",
    "sg:postcode":"38641",
    "sg:province":"MS",
    "sg:tags":[
        "concrete",
        "reinforcement"
    ],
    "wof:name":"AASE Steel Erectors Inc",
    "wof:placetype":"venue"
},
  "geometry": {"coordinates":[-90.07947299999999,34.918701],"type":"Point"}
}