{
  "type": "Feature",
  "properties": {
    "iso:country":"US",
    "sg:address":"15451 Dedeaux Rd",
    "sg:city":"Gulfport",
    "sg:classifiers":[
        {
            "category":"Education",
            "subcategory":"School",
            "type":"Public Place"
        }
    ],
    "sg:phone":"+1 228 832 2701",
    "sg:postcode":"39503",
    "sg:province":"MS",
    "wof:name":"Harrison Centl Elementary Schl",
    "wof:placetype":"venue"
},
  "geometry": {"coordinates":[-89.1022,30.44942],"type":"Point"}
}