{
  "type": "Feature",
  "properties": {
    "iso:country":"US",
    "sg:address":"212 W Clark Ave",
    "sg:city":"Eupora",
    "sg:classifiers":[
        {
            "category":"Government",
            "subcategory":"Office",
            "type":"Public Place"
        }
    ],
    "sg:phone":"+1 662 258 6728",
    "sg:postcode":"39744",
    "sg:province":"MS",
    "wof:name":"Webster County Federal Program",
    "wof:placetype":"venue"
},
  "geometry": {"coordinates":[-89.273704,33.543137],"type":"Point"}
}