{
  "type": "Feature",
  "properties": {
    "iso:country":"US",
    "sg:address":"1280 Hwy 35 S",
    "sg:city":"Forest",
    "sg:classifiers":[
        {
            "category":"Travel",
            "subcategory":"Hotels & Motels",
            "type":"Entertainment"
        }
    ],
    "sg:phone":"+1 601 469 2500",
    "sg:postcode":"39074",
    "sg:province":"MS",
    "sg:tags":[
        "operation"
    ],
    "wof:name":"Days Inn",
    "wof:placetype":"venue"
},
  "geometry": {"coordinates":[-89.482508,32.344979],"type":"Point"}
}