{
  "type": "Feature",
  "properties": {
    "iso:country":"US",
    "sg:address":"235 Cedars School Cir",
    "sg:city":"Vicksburg",
    "sg:classifiers":[
        {
            "category":"Social Services",
            "subcategory":"Child Care",
            "type":"Services"
        }
    ],
    "sg:phone":"+1 601 636 1360",
    "sg:postcode":"39180",
    "sg:province":"MS",
    "wof:name":"Cedars Head Start Ctr",
    "wof:placetype":"venue"
},
  "geometry": {"coordinates":[-90.92979200000001,32.245386],"type":"Point"}
}