{
  "type": "Feature",
  "properties": {
    "iso:country":"US",
    "sg:address":"135 US Hwy 61 Bus",
    "sg:city":"Natchez",
    "sg:classifiers":[
        {
            "category":"Autos & Motor Vehicles",
            "subcategory":"Auto Supplies",
            "type":"Retail Goods"
        }
    ],
    "sg:phone":"+1 601 442 3061",
    "sg:postcode":"39120",
    "sg:province":"MS",
    "sg:tags":[
        "automobile",
        "stereo",
        "radio"
    ],
    "wof:name":"Naff's Audio-Video",
    "wof:placetype":"venue"
},
  "geometry": {"coordinates":[-91.38821,31.555419],"type":"Point"}
}