{
  "type": "Feature",
  "properties": {
    "addr:full":"3854 Chisholm Dr SW Summit MS 39666",
    "addr:housenumber":"3854",
    "addr:postcode":"39666",
    "addr:street":"Chisholm Dr Sw",
    "iso:country":"US",
    "sg:address":"3854 Chisholm Dr SW",
    "sg:city":"Summit",
    "sg:classifiers":[
        {
            "category":"Building & Trades",
            "subcategory":"Construction",
            "type":"Services"
        }
    ],
    "sg:phone":"+1 601 567 9924",
    "sg:postcode":"39666",
    "sg:province":"MS",
    "sg:tags":[
        "house",
        "family"
    ],
    "wof:name":"M 5 Works",
    "wof:placetype":"venue"
},
  "geometry": {"coordinates":[-90.557368,31.353936],"type":"Point"}
}