{
  "type": "Feature",
  "properties": {
    "iso:country":"US",
    "sg:address":"2140 Cedar Point Cv",
    "sg:city":"Southaven",
    "sg:classifiers":[
        {
            "category":"Government",
            "subcategory":"Police Station",
            "type":"Public Place"
        }
    ],
    "sg:phone":"+1 662 393 8476",
    "sg:postcode":"38671",
    "sg:province":"MS",
    "sg:tags":[
        "department"
    ],
    "wof:name":"Orlando Police Retirees Associ",
    "wof:placetype":"venue"
},
  "geometry": {"coordinates":[-90.02925,34.981544],"type":"Point"}
}