{
  "type": "Feature",
  "properties": {
    "iso:country":"US",
    "sg:address":"20763 Yankee Town Rd",
    "sg:city":"Saucier",
    "sg:classifiers":[
        {
            "category":"Freight",
            "type":"Transportation"
        }
    ],
    "sg:phone":"+1 228 832 0249",
    "sg:postcode":"39574",
    "sg:province":"MS",
    "sg:tags":[
        "trucking"
    ],
    "wof:name":"Louisiana Transportation",
    "wof:placetype":"venue"
},
  "geometry": {"coordinates":[-89.14487699999999,30.587785],"type":"Point"}
}