{
  "type": "Feature",
  "properties": {
    "iso:country":"US",
    "sg:address":"534 Whitfield Dr",
    "sg:city":"Hernando",
    "sg:classifiers":[
        {
            "category":"Building & Trades",
            "subcategory":"Plumbing",
            "type":"Services"
        }
    ],
    "sg:phone":"+1 662 429 1598",
    "sg:postcode":"38632",
    "sg:province":"MS",
    "sg:tags":[
        "contractor"
    ],
    "wof:name":"Bobbitt Mechanical Inc",
    "wof:placetype":"venue"
},
  "geometry": {"coordinates":[-89.998318,34.838994],"type":"Point"}
}