{
  "type": "Feature",
  "properties": {
    "iso:country":"US",
    "sg:address":"1920 S Frontage Rd",
    "sg:city":"Vicksburg",
    "sg:classifiers":[
        {
            "category":"Personal",
            "subcategory":"Tanning Parlor",
            "type":"Services"
        },
        {
            "category":"Personal",
            "type":"Services"
        }
    ],
    "sg:phone":"+1 601 619 6999",
    "sg:postcode":"39180",
    "sg:province":"MS",
    "sg:tags":[
        "salon"
    ],
    "wof:name":"Sunsational Tanning Salon Inc",
    "wof:placetype":"venue"
},
  "geometry": {"coordinates":[-90.868623,32.322196],"type":"Point"}
}