{
  "type": "Feature",
  "properties": {
    "addr:full":"2081 White Rd Florence MS 39073",
    "addr:housenumber":"2081",
    "addr:postcode":"39073",
    "addr:street":"White Rd",
    "iso:country":"US",
    "sg:address":"2081 White Rd",
    "sg:city":"Florence",
    "sg:classifiers":[
        {
            "category":"Organizations",
            "subcategory":"Religious Organization",
            "type":"Services"
        }
    ],
    "sg:phone":"+1 601 845 8251",
    "sg:postcode":"39073",
    "sg:province":"MS",
    "sg:tags":[
        "church"
    ],
    "wof:name":"Mount Zion Baptist Church",
    "wof:placetype":"venue"
},
  "geometry": {"coordinates":[-90.210362,32.066747],"type":"Point"}
}