{
  "type": "Feature",
  "properties": {
    "iso:country":"US",
    "sg:address":"3645 Hwy 80 W",
    "sg:city":"Jackson",
    "sg:classifiers":[
        {
            "category":"Home & Garden",
            "subcategory":"Garden Supply",
            "type":"Retail Goods"
        }
    ],
    "sg:phone":"+1 601 352 8152",
    "sg:postcode":"39209",
    "sg:province":"MS",
    "sg:tags":[
        "statuary"
    ],
    "wof:name":"Identity Pets",
    "wof:placetype":"venue"
},
  "geometry": {"coordinates":[-90.249695,32.30196],"type":"Point"}
}