{
  "type": "Feature",
  "properties": {
    "addr:full":"2309 Hwy 1 S Greenville MS 38701",
    "addr:housenumber":"2309",
    "addr:postcode":"38701",
    "addr:street":"Hwy 1 S",
    "iso:country":"US",
    "sg:address":"2309 Hwy 1 S",
    "sg:city":"Greenville",
    "sg:classifiers":[
        {
            "category":"Food & Beverages",
            "subcategory":"Liquor & Beverages",
            "type":"Retail Goods"
        }
    ],
    "sg:phone":"+1 662 378 8462",
    "sg:postcode":"38701",
    "sg:province":"MS",
    "wof:name":"Corner Liquor & Wine",
    "wof:placetype":"venue"
},
  "geometry": {"coordinates":[-91.04110799999999,33.357685],"type":"Point"}
}