{
  "type": "Feature",
  "properties": {
    "addr:full":"2671 Wire Rd E Perkinston MS 39573",
    "addr:housenumber":"2671",
    "addr:postcode":"39573",
    "addr:street":"Wire Rd E",
    "iso:country":"US",
    "sg:address":"2671 Wire Rd E",
    "sg:city":"Perkinston",
    "sg:classifiers":[
        {
            "category":"Real Estate",
            "subcategory":"Real Estate Agent",
            "type":"Services"
        },
        {
            "category":"Professional",
            "subcategory":"Management & Consulting",
            "type":"Services"
        }
    ],
    "sg:phone":"+1 601 928 4296",
    "sg:postcode":"39573",
    "sg:province":"MS",
    "sg:tags":[
        "fuel"
    ],
    "wof:name":"Red Creek Management Area",
    "wof:placetype":"venue"
},
  "geometry": {"coordinates":[-88.920686,30.729567],"type":"Point"}
}