{
  "type": "Feature",
  "properties": {
    "iso:country":"US",
    "sg:address":"800 Hwy 1 S",
    "sg:city":"Greenville",
    "sg:classifiers":[
        {
            "category":"Government",
            "subcategory":"Office",
            "type":"Public Place"
        }
    ],
    "sg:phone":"+1 662 332 7353",
    "sg:postcode":"38703",
    "sg:province":"MS",
    "sg:tags":[
        "armed",
        "force",
        "recruiting"
    ],
    "wof:name":"US Marine Corps Recruiting",
    "wof:placetype":"venue"
},
  "geometry": {"coordinates":[-91.0378,33.397526],"type":"Point"}
}