{
  "type": "Feature",
  "properties": {
    "iso:country":"US",
    "sg:address":"315 Co Rd 8301",
    "sg:city":"Rienzi",
    "sg:classifiers":[
        {
            "category":"Building & Trades",
            "subcategory":"Construction",
            "type":"Services"
        }
    ],
    "sg:phone":"+1 662 728 0268",
    "sg:postcode":"38865",
    "sg:province":"MS",
    "sg:tags":[
        "contractor"
    ],
    "wof:name":"Jimmy Lambert Welding",
    "wof:placetype":"venue"
},
  "geometry": {"coordinates":[-88.62785700000001,34.737297],"type":"Point"}
}