{
  "type": "Feature",
  "properties": {
    "iso:country":"US",
    "sg:address":"421 Pin Oak Dr",
    "sg:city":"Madison",
    "sg:classifiers":[
        {
            "category":"Professional",
            "subcategory":"Computer Services",
            "type":"Services"
        }
    ],
    "sg:phone":"+1 601 856 4129",
    "sg:postcode":"39110",
    "sg:province":"MS",
    "sg:tags":[
        "consultant",
        "designer",
        "datum",
        "system"
    ],
    "wof:name":"Data Technologies",
    "wof:placetype":"venue"
},
  "geometry": {"coordinates":[-90.115544,32.470669],"type":"Point"}
}