{
  "type": "Feature",
  "properties": {
    "addr:full":"1305 S Matubba St Aberdeen MS 39730",
    "addr:housenumber":"1305",
    "addr:postcode":"39730",
    "addr:street":"S Matubba St",
    "iso:country":"US",
    "sg:address":"1305 S Matubba St",
    "sg:city":"Aberdeen",
    "sg:classifiers":[
        {
            "category":"Manufacturing",
            "subcategory":"Furniture",
            "type":"Manufacturing & Wholesale Goods"
        }
    ],
    "sg:phone":"+1 662 369 2100",
    "sg:postcode":"39730",
    "sg:province":"MS",
    "wof:name":"Sit N Easy",
    "wof:placetype":"venue"
},
  "geometry": {"coordinates":[-88.552612,33.809996],"type":"Point"}
}