{
  "type": "Feature",
  "properties": {
    "addr:full":"814 S Theobald St Greenville MS 38701",
    "addr:housenumber":"814",
    "addr:postcode":"38701",
    "addr:street":"S Theobald St",
    "iso:country":"US",
    "sg:address":"814 S Theobald St",
    "sg:city":"Greenville",
    "sg:classifiers":[
        {
            "category":"Place Of Worship",
            "type":"Public Place"
        }
    ],
    "sg:phone":"+1 662 332 5695",
    "sg:postcode":"38701",
    "sg:province":"MS",
    "sg:tags":[
        "church"
    ],
    "wof:name":"Evans, E E Rev",
    "wof:placetype":"venue"
},
  "geometry": {"coordinates":[-91.064578,33.40014],"type":"Point"}
}