{
  "type": "Feature",
  "properties": {
    "iso:country":"US",
    "sg:address":"10061 Rodriguez St",
    "sg:city":"Diberville",
    "sg:classifiers":[
        {
            "category":"Retail",
            "subcategory":"Auto Repair",
            "type":"Services"
        }
    ],
    "sg:phone":"+1 228 392 7924",
    "sg:postcode":"39540",
    "sg:province":"MS",
    "sg:tags":[
        "repairing",
        "automobile"
    ],
    "wof:name":"A & W Auto",
    "wof:placetype":"venue"
},
  "geometry": {"coordinates":[-88.891724,30.42954],"type":"Point"}
}