{
  "type": "Feature",
  "properties": {
    "iso:country":"US",
    "sg:address":"120 N Jackson St",
    "sg:city":"Starkville",
    "sg:classifiers":[
        {
            "category":"Personal",
            "subcategory":"Beauty Salon",
            "type":"Services"
        },
        {
            "category":"Personal",
            "subcategory":"Barber",
            "type":"Services"
        }
    ],
    "sg:phone":"+1 662 324 2418",
    "sg:postcode":"39759",
    "sg:province":"MS",
    "sg:tags":[
        "shop"
    ],
    "wof:name":"H & M Beauty & Supply",
    "wof:placetype":"venue"
},
  "geometry": {"coordinates":[-88.81383700000001,33.464441],"type":"Point"}
}