{
  "type": "Feature",
  "properties": {
    "iso:country":"US",
    "sg:address":"845 South Plz",
    "sg:city":"Jackson",
    "sg:classifiers":[
        {
            "category":"Organizations",
            "subcategory":"Non-profit Organization",
            "type":"Services"
        }
    ],
    "sg:phone":"+1 601 346 6004",
    "sg:postcode":"39204",
    "sg:province":"MS",
    "sg:tags":[
        "information",
        "alcoholism",
        "treatment"
    ],
    "wof:name":"Jonah House",
    "wof:placetype":"venue"
},
  "geometry": {"coordinates":[-90.216459,32.282169],"type":"Point"}
}