{
  "type": "Feature",
  "properties": {
    "iso:country":"US",
    "sg:address":"121 Goshen Springs Ln",
    "sg:city":"Brandon",
    "sg:classifiers":[
        {
            "category":"Retail",
            "subcategory":"Repair Shop",
            "type":"Services"
        }
    ],
    "sg:phone":"+1 601 829 0198",
    "sg:postcode":"39047",
    "sg:province":"MS",
    "wof:name":"Good Clean Fun Inc",
    "wof:placetype":"venue"
},
  "geometry": {"coordinates":[-89.927739,32.488768],"type":"Point"}
}