{
  "type": "Feature",
  "properties": {
    "addr:full":"1913 Hwy 45 N Columbus MS 39705",
    "addr:housenumber":"1913",
    "addr:postcode":"39705",
    "addr:street":"Hwy 45 N",
    "iso:country":"US",
    "sg:address":"1913 Hwy 45 N",
    "sg:city":"Columbus",
    "sg:classifiers":[
        {
            "category":"Professional",
            "subcategory":"Accounting & Tax Preparation",
            "type":"Services"
        }
    ],
    "sg:phone":"+1 662 328 1323",
    "sg:postcode":"39705",
    "sg:province":"MS",
    "sg:tags":[
        "return",
        "filing"
    ],
    "wof:name":"H & R Block Tax Svc",
    "wof:placetype":"venue"
},
  "geometry": {"coordinates":[-88.437168,33.531221],"type":"Point"}
}