{
  "type": "Feature",
  "properties": {
    "iso:country":"US",
    "sg:address":"4 S Poplar St",
    "sg:city":"Foxworth",
    "sg:classifiers":[
        {
            "category":"Professional",
            "subcategory":"Research",
            "type":"Services"
        }
    ],
    "sg:phone":"+1 601 736 3500",
    "sg:postcode":"39483",
    "sg:province":"MS",
    "sg:tags":[
        "environmental",
        "ecological"
    ],
    "wof:name":"Walker-Hill Environmental Inc",
    "wof:placetype":"venue"
},
  "geometry": {"coordinates":[-89.868045,31.230788],"type":"Point"}
}