{
  "type": "Feature",
  "properties": {
    "iso:country":"US",
    "sg:address":"275 Azalea Ct",
    "sg:city":"Brandon",
    "sg:classifiers":[
        {
            "category":"Banks & Credit Unions",
            "subcategory":"Bank",
            "type":"Services"
        }
    ],
    "sg:phone":"+1 601 992 1910",
    "sg:postcode":"39047",
    "sg:province":"MS",
    "sg:tags":[
        "broker",
        "mortgage"
    ],
    "wof:name":"Mortgage Guaranty Corporation",
    "wof:placetype":"venue"
},
  "geometry": {"coordinates":[-90.003704,32.34997],"type":"Point"}
}