{
  "type": "Feature",
  "properties": {
    "addr:full":"638 Gulf Camp Rd Lumberton MS 39455",
    "addr:housenumber":"638",
    "addr:postcode":"39455",
    "addr:street":"Gulf Camp Rd",
    "iso:country":"US",
    "sg:address":"638 Gulf Camp Rd",
    "sg:city":"Lumberton",
    "sg:classifiers":[
        {
            "category":"Personal",
            "subcategory":"Beauty Salon",
            "type":"Services"
        }
    ],
    "sg:phone":"+1 601 796 2280",
    "sg:postcode":"39455",
    "sg:province":"MS",
    "sg:tags":[
        "shop"
    ],
    "wof:name":"Cindys Cutting Corner",
    "wof:placetype":"venue"
},
  "geometry": {"coordinates":[-89.597931,31.08356],"type":"Point"}
}