{
  "type": "Feature",
  "properties": {
    "iso:country":"US",
    "sg:address":"2123 S Azalea Dr",
    "sg:city":"Wiggins",
    "sg:classifiers":[
        {
            "category":"Retail",
            "subcategory":"Auto Repair",
            "type":"Services"
        }
    ],
    "sg:phone":"+1 601 928 2046",
    "sg:postcode":"39577",
    "sg:province":"MS",
    "sg:tags":[
        "body",
        "automobile",
        "painting"
    ],
    "wof:name":"Tim's Body Shop",
    "wof:placetype":"venue"
},
  "geometry": {"coordinates":[-89.136572,30.822918],"type":"Point"}
}