{
  "type": "Feature",
  "properties": {
    "iso:country":"US",
    "sg:address":"2961 Bienville Blvd",
    "sg:city":"Ocean Springs",
    "sg:classifiers":[
        {
            "category":"Restaurant",
            "type":"Food & Drink"
        }
    ],
    "sg:phone":"+1 228 818 9505",
    "sg:postcode":"39564",
    "sg:province":"MS",
    "sg:tags":[
        "parlor",
        "ice",
        "cream"
    ],
    "wof:name":"Hershey's Double Dip Ice Cream",
    "wof:placetype":"venue"
},
  "geometry": {"coordinates":[-88.789051,30.413822],"type":"Point"}
}