{
  "type": "Feature",
  "properties": {
    "iso:country":"US",
    "sg:address":"176 Goodman Rd W",
    "sg:city":"Southaven",
    "sg:classifiers":[
        {
            "category":"Health Services",
            "subcategory":"Clinic",
            "type":"Services"
        }
    ],
    "sg:phone":"+1 662 536 1020",
    "sg:postcode":"38671",
    "sg:province":"MS",
    "sg:website":"http://www.primeurgentmedicalclinic.com",
    "wof:name":"Urgent Medical Clinic",
    "wof:placetype":"venue"
},
  "geometry": {"coordinates":[-89.993296,34.962681],"type":"Point"}
}