{
  "type": "Feature",
  "properties": {
    "iso:country":"US",
    "sg:address":"304 US Hwy 90",
    "sg:city":"Waveland",
    "sg:classifiers":[
        {
            "category":"Shopping",
            "subcategory":"Used Merchandise",
            "type":"Retail Goods"
        }
    ],
    "sg:phone":"+1 228 467 6104",
    "sg:postcode":"39576",
    "sg:province":"MS",
    "sg:tags":[
        "shop",
        "consignment"
    ],
    "wof:name":"Just Looking",
    "wof:placetype":"venue"
},
  "geometry": {"coordinates":[-89.376671,30.30673],"type":"Point"}
}