{
  "type": "Feature",
  "properties": {
    "iso:country":"US",
    "sg:address":"5301 Diamondhead Cir",
    "sg:city":"Diamondhead",
    "sg:classifiers":[
        {
            "category":"Social Services",
            "subcategory":"Child Care",
            "type":"Services"
        }
    ],
    "sg:phone":"+1 228 255 7751",
    "sg:postcode":"39525",
    "sg:province":"MS",
    "sg:tags":[
        "kindergarten",
        "academic",
        "school"
    ],
    "wof:name":"Diamondhead Community School",
    "wof:placetype":"venue"
},
  "geometry": {"coordinates":[-89.37901599999999,30.381033],"type":"Point"}
}