{
  "type": "Feature",
  "properties": {
    "addr:full":"157 Salem Rd Foxworth MS 39466",
    "addr:housenumber":"157",
    "addr:postcode":"39466",
    "addr:street":"Salem Rd",
    "iso:country":"US",
    "sg:address":"157 Salem Rd",
    "sg:city":"Foxworth",
    "sg:classifiers":[
        {
            "category":"Building & Trades",
            "subcategory":"Construction",
            "type":"Services"
        }
    ],
    "sg:phone":"+1 601 736 9309",
    "sg:postcode":"39466",
    "sg:province":"MS",
    "sg:tags":[
        "hanging",
        "contractor"
    ],
    "wof:name":"McCraws Painting",
    "wof:placetype":"venue"
},
  "geometry": {"coordinates":[-89.59961699999999,30.508671],"type":"Point"}
}