{
  "type": "Feature",
  "properties": {
    "addr:full":"3835 Hillsdale Rd Olive Branch MS 38654",
    "addr:housenumber":"3835",
    "addr:postcode":"38654",
    "addr:street":"Hillsdale Rd",
    "iso:country":"US",
    "sg:address":"3835 Hillsdale Rd",
    "sg:city":"Olive Branch",
    "sg:classifiers":[
        {
            "category":"Professional",
            "subcategory":"Engineering",
            "type":"Services"
        }
    ],
    "sg:phone":"+1 662 895 9297",
    "sg:postcode":"38654",
    "sg:province":"MS",
    "wof:name":"Tech Wurkz",
    "wof:placetype":"venue"
},
  "geometry": {"coordinates":[-89.921948,34.97088],"type":"Point"}
}