{
  "type": "Feature",
  "properties": {
    "addr:full":"101 Forrest Lee Dr Booneville MS 38829",
    "addr:housenumber":"101",
    "addr:postcode":"38829",
    "addr:street":"Forrest Lee Dr",
    "iso:country":"US",
    "sg:address":"101 Forrest Lee Dr",
    "sg:city":"Booneville",
    "sg:classifiers":[
        {
            "category":"Autos & Motor Vehicles",
            "subcategory":"Automobile Sales",
            "type":"Retail Goods"
        }
    ],
    "sg:phone":"+1 662 728 6239",
    "sg:postcode":"38829",
    "sg:province":"MS",
    "sg:tags":[
        "used"
    ],
    "wof:name":"Davis Used Cars & Body Shop",
    "wof:placetype":"venue"
},
  "geometry": {"coordinates":[-88.549865,34.641425],"type":"Point"}
}