{
  "type": "Feature",
  "properties": {
    "iso:country":"US",
    "sg:address":"2008 University Ave",
    "sg:city":"Oxford",
    "sg:classifiers":[
        {
            "category":"Real Estate",
            "subcategory":"Developer",
            "type":"Services"
        }
    ],
    "sg:phone":"+1 662 236 5080",
    "sg:postcode":"38655",
    "sg:province":"MS",
    "wof:name":"Chartre Consulting LTD",
    "wof:placetype":"venue"
},
  "geometry": {"coordinates":[-89.505702,34.361908],"type":"Point"}
}