{
  "type": "Feature",
  "properties": {
    "iso:country":"US",
    "sg:address":"23539 Central Dr",
    "sg:city":"Saucier",
    "sg:classifiers":[
        {
            "category":"Shopping",
            "type":"Retail Goods"
        }
    ],
    "sg:phone":"+1 228 831 8882",
    "sg:postcode":"39574",
    "sg:province":"MS",
    "sg:tags":[
        "ice"
    ],
    "wof:name":"Icehouse",
    "wof:placetype":"venue"
},
  "geometry": {"coordinates":[-89.13220099999999,30.632562],"type":"Point"}
}