{
  "type": "Feature",
  "properties": {
    "addr:full":"212 N 1st St Lumberton MS 39455",
    "addr:housenumber":"212",
    "addr:postcode":"39455",
    "addr:street":"N 1St St",
    "iso:country":"US",
    "sg:address":"212 N 1st St",
    "sg:city":"Lumberton",
    "sg:classifiers":[
        {
            "category":"Government",
            "subcategory":"Office",
            "type":"Public Place"
        }
    ],
    "sg:phone":"+1 601 796 8317",
    "sg:postcode":"39455",
    "sg:province":"MS",
    "sg:tags":[
        "state",
        "security"
    ],
    "wof:name":"National Guard",
    "wof:placetype":"venue"
},
  "geometry": {"coordinates":[-89.448657,31.002135],"type":"Point"}
}