{
  "type": "Feature",
  "properties": {
    "iso:country":"US",
    "sg:address":"332 Hwy 45 S",
    "sg:city":"West Point",
    "sg:classifiers":[
        {
            "category":"Personal",
            "subcategory":"Beauty Salon",
            "type":"Services"
        }
    ],
    "sg:phone":"+1 662 494 6654",
    "sg:postcode":"39773",
    "sg:province":"MS",
    "sg:tags":[
        "shop"
    ],
    "wof:name":"Hair Designs Unlimited",
    "wof:placetype":"venue"
},
  "geometry": {"coordinates":[-88.658975,33.603889],"type":"Point"}
}