{
  "type": "Feature",
  "properties": {
    "iso:country":"US",
    "sg:address":"1133 Co Rd 277",
    "sg:city":"Quitman",
    "sg:classifiers":[
        {
            "category":"Professional",
            "type":"Services"
        }
    ],
    "sg:phone":"+1 601 776 2239",
    "sg:postcode":"39366",
    "sg:province":"MS",
    "sg:tags":[
        "establishment"
    ],
    "wof:name":"Valence Operating Co",
    "wof:placetype":"venue"
},
  "geometry": {"coordinates":[-88.838345,31.935481],"type":"Point"}
}