{
  "type": "Feature",
  "properties": {
    "addr:full":"5743 Old Canton Rd Jackson MS 39211",
    "addr:housenumber":"5743",
    "addr:postcode":"39211",
    "addr:street":"Old Canton Rd",
    "iso:country":"US",
    "sg:address":"5743 Old Canton Rd",
    "sg:city":"Jackson",
    "sg:classifiers":[
        {
            "category":"Personal",
            "subcategory":"Beauty Salon",
            "type":"Services"
        }
    ],
    "sg:phone":"+1 601 956 8161",
    "sg:postcode":"39211",
    "sg:province":"MS",
    "sg:tags":[
        "shop"
    ],
    "wof:name":"Raymond's",
    "wof:placetype":"venue"
},
  "geometry": {"coordinates":[-90.12320200000001,32.377015],"type":"Point"}
}