{
  "type": "Feature",
  "properties": {
    "iso:country":"US",
    "sg:address":"205 Bolton Brownsville Rd",
    "sg:city":"Bolton",
    "sg:classifiers":[
        {
            "category":"Retail",
            "subcategory":"Funeral Services",
            "type":"Services"
        }
    ],
    "sg:phone":"+1 601 866 7011",
    "sg:postcode":"39041",
    "sg:province":"MS",
    "sg:tags":[
        "director"
    ],
    "wof:name":"Bolton Funeral Home",
    "wof:placetype":"venue"
},
  "geometry": {"coordinates":[-90.46108599999999,32.351653],"type":"Point"}
}