{
  "type": "Feature",
  "properties": {
    "addr:full":"2550 Dean Rd Nesbit MS 38651",
    "addr:housenumber":"2550",
    "addr:postcode":"38651",
    "addr:street":"Dean Rd",
    "iso:country":"US",
    "sg:address":"2550 Dean Rd",
    "sg:city":"Nesbit",
    "sg:classifiers":[
        {
            "category":"Autos & Motor Vehicles",
            "subcategory":"Automobile Sales",
            "type":"Retail Goods"
        }
    ],
    "sg:phone":"+1 662 393 2133",
    "sg:postcode":"38651",
    "sg:province":"MS",
    "sg:tags":[
        "car",
        "dealer"
    ],
    "wof:name":"Auto Depot",
    "wof:placetype":"venue"
},
  "geometry": {"coordinates":[-90.03479,34.88101],"type":"Point"}
}