{
  "type": "Feature",
  "properties": {
    "addr:full":"301 Claiborne Ave Jackson MS 39209",
    "addr:housenumber":"301",
    "addr:postcode":"39209",
    "addr:street":"Claiborne Ave",
    "iso:country":"US",
    "sg:address":"301 Claiborne Ave",
    "sg:city":"Jackson",
    "sg:classifiers":[
        {
            "category":"Social Services",
            "subcategory":"Child Care",
            "type":"Services"
        }
    ],
    "sg:phone":"+1 601 353 8120",
    "sg:postcode":"39209",
    "sg:province":"MS",
    "wof:name":"Spirit Word Fellowship Daycare",
    "wof:placetype":"venue"
},
  "geometry": {"coordinates":[-90.22263100000001,32.314707],"type":"Point"}
}