{
  "type": "Feature",
  "properties": {
    "iso:country":"US",
    "sg:address":"710 Venture Dr",
    "sg:city":"Southaven",
    "sg:classifiers":[
        {
            "category":"Wholesale",
            "subcategory":"Electrical",
            "type":"Manufacturing & Wholesale Goods"
        }
    ],
    "sg:phone":"+1 662 393 6910",
    "sg:postcode":"38672",
    "sg:province":"MS",
    "sg:tags":[
        "electric",
        "motor"
    ],
    "sg:website":"www.usmotors.com",
    "wof:name":"Emerson Motor Technologies",
    "wof:placetype":"venue"
},
  "geometry": {"coordinates":[-90.00825500000001,34.925181],"type":"Point"}
}