{
  "type": "Feature",
  "properties": {
    "iso:country":"US",
    "sg:address":"203 N Newberger Ave",
    "sg:city":"Bruce",
    "sg:classifiers":[
        {
            "category":"Shopping",
            "subcategory":"Pharmacy",
            "type":"Retail Goods"
        }
    ],
    "sg:phone":"+1 662 983 4011",
    "sg:postcode":"38915",
    "sg:province":"MS",
    "wof:name":"Stepp-Saver Pharmacy",
    "wof:placetype":"venue"
},
  "geometry": {"coordinates":[-89.34717499999999,33.993414],"type":"Point"}
}