{
  "type": "Feature",
  "properties": {
    "iso:country":"US",
    "sg:address":"1001 S 4th Ave",
    "sg:city":"Laurel",
    "sg:classifiers":[
        {
            "category":"Manufacturing",
            "subcategory":"Wood Products",
            "type":"Manufacturing & Wholesale Goods"
        }
    ],
    "sg:phone":"+1 601 649 6000",
    "sg:postcode":"39440",
    "sg:province":"MS",
    "sg:tags":[
        "hardboard",
        "manufacturer"
    ],
    "sg:website":"www.masonite.com",
    "wof:name":"Masonite Corp",
    "wof:placetype":"venue"
},
  "geometry": {"coordinates":[-89.13060900000001,31.67956],"type":"Point"}
}