{
  "type": "Feature",
  "properties": {
    "addr:full":"1105 Grand Ave Lena MS 39094",
    "addr:housenumber":"1105",
    "addr:postcode":"39094",
    "addr:street":"Grand Ave",
    "iso:country":"US",
    "sg:address":"1105 Grand Ave",
    "sg:city":"Lena",
    "sg:classifiers":[
        {
            "category":"Restaurant",
            "type":"Food & Drink"
        }
    ],
    "sg:phone":"+1 601 654 3700",
    "sg:postcode":"39094",
    "sg:province":"MS",
    "sg:tags":[
        "eating"
    ],
    "wof:name":"Burger Hut",
    "wof:placetype":"venue"
},
  "geometry": {"coordinates":[-89.601247,32.589944],"type":"Point"}
}