{
  "type": "Feature",
  "properties": {
    "addr:full":"2078 Shady Lane Dr Jackson MS 39204",
    "addr:housenumber":"2078",
    "addr:postcode":"39204",
    "addr:street":"Shady Lane Dr",
    "iso:country":"US",
    "sg:address":"2078 Shady Lane Dr",
    "sg:city":"Jackson",
    "sg:classifiers":[
        {
            "category":"Building & Trades",
            "subcategory":"Construction",
            "type":"Services"
        }
    ],
    "sg:phone":"+1 601 372 6506",
    "sg:postcode":"39204",
    "sg:province":"MS",
    "sg:tags":[
        "residential"
    ],
    "wof:name":"J R Reed General Contractor",
    "wof:placetype":"venue"
},
  "geometry": {"coordinates":[-90.236906,32.27878],"type":"Point"}
}