{
  "type": "Feature",
  "properties": {
    "addr:full":"9117 Corporate Dr Southaven MS 38671",
    "addr:housenumber":"9117",
    "addr:postcode":"38671",
    "addr:street":"Corporate Dr",
    "iso:country":"US",
    "sg:address":"9117 Corporate Dr",
    "sg:city":"Southaven",
    "sg:classifiers":[
        {
            "category":"Retail",
            "subcategory":"Laundry & Dry Cleaning",
            "type":"Services"
        }
    ],
    "sg:phone":"+1 662 342 0897",
    "sg:postcode":"38671",
    "sg:province":"MS",
    "sg:tags":[
        "cleaners",
        "rug",
        "carpet"
    ],
    "wof:name":"Rainbow International Carpet",
    "wof:placetype":"venue"
},
  "geometry": {"coordinates":[-90.0288,34.993041],"type":"Point"}
}