{
  "type": "Feature",
  "properties": {
    "addr:full":"1153 Owens Rd Terry MS 39170",
    "addr:housenumber":"1153",
    "addr:postcode":"39170",
    "addr:street":"Owens Rd",
    "iso:country":"US",
    "sg:address":"1153 Owens Rd",
    "sg:city":"Terry",
    "sg:classifiers":[
        {
            "category":"Social Services",
            "type":"Services"
        }
    ],
    "sg:phone":"+1 601 857 8544",
    "sg:postcode":"39170",
    "sg:province":"MS",
    "sg:tags":[
        "mission"
    ],
    "wof:name":"Agricultural Mission Fndtn LTD",
    "wof:placetype":"venue"
},
  "geometry": {"coordinates":[-90.37492,32.188086],"type":"Point"}
}