{
  "type": "Feature",
  "properties": {
    "iso:country":"US",
    "sg:address":"309 Clinton Blvd",
    "sg:city":"Clinton",
    "sg:classifiers":[
        {
            "category":"Home & Garden",
            "subcategory":"Carpets & Floor Coverings",
            "type":"Retail Goods"
        }
    ],
    "sg:phone":"+1 601 924 4409",
    "sg:postcode":"39056",
    "sg:province":"MS",
    "sg:tags":[
        "material"
    ],
    "wof:name":"Clinton Floors & Interiors",
    "wof:placetype":"venue"
},
  "geometry": {"coordinates":[-90.310163,32.334858],"type":"Point"}
}