{
  "type": "Feature",
  "properties": {
    "iso:country":"US",
    "sg:address":"14086 Dedeaux Rd",
    "sg:city":"Gulfport",
    "sg:classifiers":[
        {
            "category":"Retail",
            "subcategory":"Veterinary Services",
            "type":"Services"
        }
    ],
    "sg:phone":"+1 228 832 6360",
    "sg:postcode":"39503",
    "sg:province":"MS",
    "sg:tags":[
        "veterinarian"
    ],
    "wof:name":"Animal Hospital Orange Grove",
    "wof:placetype":"venue"
},
  "geometry": {"coordinates":[-89.07252099999999,30.449569],"type":"Point"}
}