{
  "type": "Feature",
  "properties": {
    "iso:country":"US",
    "sg:address":"631 Hwy 45 S",
    "sg:city":"West Point",
    "sg:classifiers":[
        {
            "category":"Retail",
            "subcategory":"Auto Repair",
            "type":"Services"
        }
    ],
    "sg:phone":"+1 662 494 6001",
    "sg:postcode":"39773",
    "sg:province":"MS",
    "sg:tags":[
        "automobile",
        "electric",
        "automotive"
    ],
    "wof:name":"C & S Auto Electric",
    "wof:placetype":"venue"
},
  "geometry": {"coordinates":[-88.659131,33.599988],"type":"Point"}
}