{
  "type": "Feature",
  "properties": {
    "iso:country":"US",
    "sg:address":"712 E Beach Blvd",
    "sg:city":"Long Beach",
    "sg:classifiers":[
        {
            "category":"Organizations",
            "subcategory":"Religious Organization",
            "type":"Services"
        }
    ],
    "sg:phone":"+1 228 868 3774",
    "sg:postcode":"39560",
    "sg:province":"MS",
    "sg:tags":[
        "church"
    ],
    "wof:name":"St Thomas Office Of Religious",
    "wof:placetype":"venue"
},
  "geometry": {"coordinates":[-89.13933299999999,30.348762],"type":"Point"}
}