{
  "type": "Feature",
  "properties": {
    "iso:country":"US",
    "sg:address":"157 Grown Williams Rd",
    "sg:city":"Canton",
    "sg:classifiers":[
        {
            "category":"Building & Trades",
            "subcategory":"Plumbing",
            "type":"Services"
        }
    ],
    "sg:phone":"+1 601 859 7103",
    "sg:postcode":"39046",
    "sg:province":"MS",
    "sg:tags":[
        "contractor"
    ],
    "wof:name":"Griffens Concrete",
    "wof:placetype":"venue"
},
  "geometry": {"coordinates":[-89.781464,32.658938],"type":"Point"}
}