{
  "type": "Feature",
  "properties": {
    "iso:country":"US",
    "sg:address":"2340 E Pass Rd",
    "sg:city":"Gulfport",
    "sg:classifiers":[
        {
            "category":"Retail",
            "subcategory":"Repair Shop",
            "type":"Services"
        }
    ],
    "sg:phone":"+1 228 896 1584",
    "sg:postcode":"39507",
    "sg:province":"MS",
    "sg:tags":[
        "appliance"
    ],
    "wof:name":"S & H Appliance Repair",
    "wof:placetype":"venue"
},
  "geometry": {"coordinates":[-89.001514,30.400716],"type":"Point"}
}