{
  "type": "Feature",
  "properties": {
    "iso:country":"US",
    "sg:address":"317 Ralph Rawls Rd",
    "sg:city":"Hattiesburg",
    "sg:classifiers":[
        {
            "category":"Building & Trades",
            "subcategory":"Plumbing",
            "type":"Services"
        }
    ],
    "sg:phone":"+1 601 264 6219",
    "sg:postcode":"39402",
    "sg:province":"MS",
    "sg:tags":[
        "plumbing",
        "contractor"
    ],
    "wof:name":"Baggett Plumbing Co Inc",
    "wof:placetype":"venue"
},
  "geometry": {"coordinates":[-89.473167,31.339879],"type":"Point"}
}