{
  "type": "Feature",
  "properties": {
    "addr:full":"5147 Sunnyvale Dr Jackson MS 39211",
    "addr:housenumber":"5147",
    "addr:postcode":"39211",
    "addr:street":"Sunnyvale Dr",
    "iso:country":"US",
    "sg:address":"5147 Sunnyvale Dr",
    "sg:city":"Jackson",
    "sg:classifiers":[
        {
            "category":"Building & Trades",
            "subcategory":"Cleaning & Sanitation",
            "type":"Services"
        }
    ],
    "sg:phone":"+1 601 957 0662",
    "sg:postcode":"39211",
    "sg:province":"MS",
    "sg:tags":[
        "maintenance"
    ],
    "wof:name":"Andys Prof Win Clg LLC",
    "wof:placetype":"venue"
},
  "geometry": {"coordinates":[-90.124275,32.367838],"type":"Point"}
}