{
  "type": "Feature",
  "properties": {
    "iso:country":"US",
    "sg:address":"108 E Hill Dr",
    "sg:city":"Madison",
    "sg:classifiers":[
        {
            "category":"Personal",
            "type":"Services"
        }
    ],
    "sg:phone":"+1 601 605 8762",
    "sg:postcode":"39110",
    "sg:province":"MS",
    "wof:name":"Better Bodies",
    "wof:placetype":"venue"
},
  "geometry": {"coordinates":[-90.107659,32.455189],"type":"Point"}
}