{
  "type": "Feature",
  "properties": {
    "iso:country":"US",
    "sg:address":"103 Drexel Cir",
    "sg:city":"Clinton",
    "sg:classifiers":[
        {
            "category":"Professional",
            "subcategory":"Accounting & Tax Preparation",
            "type":"Services"
        }
    ],
    "sg:phone":"+1 601 924 4910",
    "sg:postcode":"39056",
    "sg:province":"MS",
    "sg:tags":[
        "accountant"
    ],
    "wof:name":"Roy L Horton CPA",
    "wof:placetype":"venue"
},
  "geometry": {"coordinates":[-90.33135799999999,32.302526],"type":"Point"}
}