{
  "type": "Feature",
  "properties": {
    "iso:country":"US",
    "sg:address":"3082 Bienville Blvd",
    "sg:city":"Ocean Springs",
    "sg:classifiers":[
        {
            "category":"Shopping",
            "subcategory":"Pharmacy",
            "type":"Retail Goods"
        }
    ],
    "sg:phone":"+1 228 872 2646",
    "sg:postcode":"39564",
    "sg:province":"MS",
    "sg:tags":[
        "photofinishing",
        "laboratory"
    ],
    "wof:name":"Rite Aid",
    "wof:placetype":"venue"
},
  "geometry": {"coordinates":[-88.785647,30.412857],"type":"Point"}
}