{
  "type": "Feature",
  "properties": {
    "addr:full":"544 Main St Bay St Louis MS 39520",
    "addr:housenumber":"544",
    "addr:postcode":"39520",
    "addr:street":"Main St",
    "iso:country":"US",
    "sg:address":"544 Main St",
    "sg:city":"Bay St Louis",
    "sg:classifiers":[
        {
            "category":"Professional",
            "subcategory":"Lawyer & Legal Services",
            "type":"Services"
        }
    ],
    "sg:phone":"+1 228 467 0006",
    "sg:postcode":"39520",
    "sg:province":"MS",
    "sg:tags":[
        "attorney"
    ],
    "wof:name":"Brehm Bell",
    "wof:placetype":"venue"
},
  "geometry": {"coordinates":[-89.34310499999999,30.315827],"type":"Point"}
}