{
  "type": "Feature",
  "properties": {
    "iso:country":"US",
    "sg:address":"4 Willow Pt",
    "sg:city":"Hattiesburg",
    "sg:classifiers":[
        {
            "category":"Personal",
            "type":"Services"
        }
    ],
    "sg:phone":"+1 601 261 5579",
    "sg:postcode":"39402",
    "sg:province":"MS",
    "sg:tags":[
        "program",
        "physical",
        "exercise",
        "fitness"
    ],
    "wof:name":"Quest Ladies Fitness",
    "wof:placetype":"venue"
},
  "geometry": {"coordinates":[-89.37308299999999,31.329338],"type":"Point"}
}