{
  "type": "Feature",
  "properties": {
    "addr:full":"1542 E Beach Blvd Gulfport MS 39501",
    "addr:housenumber":"1542",
    "addr:postcode":"39501",
    "addr:street":"E Beach Blvd",
    "iso:country":"US",
    "sg:address":"1542 E Beach Blvd",
    "sg:city":"Gulfport",
    "sg:classifiers":[
        {
            "category":"Professional",
            "subcategory":"Computer Services",
            "type":"Services"
        }
    ],
    "sg:phone":"+1 228 575 4503",
    "sg:postcode":"39501",
    "sg:province":"MS",
    "sg:tags":[
        "processing",
        "datum"
    ],
    "wof:name":"ADP",
    "wof:placetype":"venue"
},
  "geometry": {"coordinates":[-89.079222,30.370345],"type":"Point"}
}