{
  "type": "Feature",
  "properties": {
    "iso:country":"US",
    "sg:address":"105 Grand Blvd",
    "sg:city":"Greenwood",
    "sg:classifiers":[
        {
            "category":"Personal",
            "subcategory":"Beauty Salon",
            "type":"Services"
        }
    ],
    "sg:phone":"+1 662 455 2626",
    "sg:postcode":"38930",
    "sg:province":"MS",
    "sg:tags":[
        "shop"
    ],
    "wof:name":"Legends Hair & Nail Care",
    "wof:placetype":"venue"
},
  "geometry": {"coordinates":[-90.18597699999999,33.525693],"type":"Point"}
}