{
  "type": "Feature",
  "properties": {
    "iso:country":"US",
    "sg:address":"2303 13th St",
    "sg:city":"Meridian",
    "sg:classifiers":[
        {
            "category":"Personal",
            "subcategory":"Beauty Salon",
            "type":"Services"
        }
    ],
    "sg:phone":"+1 601 482 4463",
    "sg:postcode":"39301",
    "sg:province":"MS",
    "sg:tags":[
        "spa",
        "day"
    ],
    "wof:name":"Pampered Bodies Day Spa",
    "wof:placetype":"venue"
},
  "geometry": {"coordinates":[-88.702563,32.369809],"type":"Point"}
}