{
  "type": "Feature",
  "properties": {
    "addr:full":"110 S 2nd St Bay St Louis MS 39520",
    "addr:housenumber":"110",
    "addr:postcode":"39520",
    "addr:street":"S 2Nd St",
    "iso:country":"US",
    "sg:address":"110 S 2nd St",
    "sg:city":"Bay St Louis",
    "sg:classifiers":[
        {
            "category":"Shopping",
            "subcategory":"Used Merchandise",
            "type":"Retail Goods"
        },
        {
            "category":"Professional",
            "subcategory":"Business Services",
            "type":"Services"
        }
    ],
    "sg:phone":"+1 228 467 9890",
    "sg:postcode":"39520",
    "sg:province":"MS",
    "sg:tags":[
        "antique"
    ],
    "wof:name":"M Schon Antiques",
    "wof:placetype":"venue"
},
  "geometry": {"coordinates":[-89.328874,30.311422],"type":"Point"}
}