{
  "type": "Feature",
  "properties": {
    "iso:country":"US",
    "sg:address":"2737 Old Brandon Rd",
    "sg:city":"Jackson",
    "sg:classifiers":[
        {
            "category":"Organizations",
            "subcategory":"Labor Organization",
            "type":"Services"
        }
    ],
    "sg:phone":"+1 601 932 0480",
    "sg:postcode":"39208",
    "sg:province":"MS",
    "wof:name":"IUE",
    "wof:placetype":"venue"
},
  "geometry": {"coordinates":[-90.121728,32.278507],"type":"Point"}
}