{
  "type": "Feature",
  "properties": {
    "iso:country":"US",
    "sg:address":"3909 Halls Ferry Rd",
    "sg:city":"Vicksburg",
    "sg:classifiers":[
        {
            "category":"Shopping",
            "subcategory":"Discount & Variety Stores",
            "type":"Retail Goods"
        }
    ],
    "sg:phone":"+1 601 634 2377",
    "sg:postcode":"39180",
    "sg:province":"MS",
    "sg:tags":[
        "merchandise",
        "general"
    ],
    "wof:name":"Vicksburg Post Exchange",
    "wof:placetype":"venue"
},
  "geometry": {"coordinates":[-90.87334199999999,32.30195],"type":"Point"}
}