{
  "type": "Feature",
  "properties": {
    "iso:country":"US",
    "sg:address":"504 Cox Ave",
    "sg:city":"Hattiesburg",
    "sg:classifiers":[
        {
            "category":"Manufacturing",
            "subcategory":"Glass & Minerals",
            "type":"Manufacturing & Wholesale Goods"
        }
    ],
    "sg:phone":"+1 601 268 6703",
    "sg:postcode":"39402",
    "sg:province":"MS",
    "sg:tags":[
        "ready",
        "concrete",
        "mfg"
    ],
    "wof:name":"Central Ready Mix Corp",
    "wof:placetype":"venue"
},
  "geometry": {"coordinates":[-89.360478,31.311822],"type":"Point"}
}