{
  "type": "Feature",
  "properties": {
    "iso:country":"US",
    "sg:address":"100 S Oak Ave",
    "sg:city":"Ruleville",
    "sg:classifiers":[
        {
            "category":"Restaurant",
            "type":"Food & Drink"
        }
    ],
    "sg:phone":"+1 662 756 2868",
    "sg:postcode":"38771",
    "sg:province":"MS",
    "wof:name":"Ann's Catfish",
    "wof:placetype":"venue"
},
  "geometry": {"coordinates":[-90.546914,33.724422],"type":"Point"}
}