{
  "type": "Feature",
  "properties": {
    "iso:country":"US",
    "sg:address":"905 Spring St",
    "sg:city":"Waynesboro",
    "sg:classifiers":[
        {
            "category":"Arts & Performance",
            "subcategory":"Theater",
            "type":"Entertainment"
        }
    ],
    "sg:phone":"+1 601 735 5751",
    "sg:postcode":"39367",
    "sg:province":"MS",
    "sg:tags":[
        "musician"
    ],
    "wof:name":"Mc Rae's LLC",
    "wof:placetype":"venue"
},
  "geometry": {"coordinates":[-88.645769,31.677553],"type":"Point"}
}