{
  "type": "Feature",
  "properties": {
    "addr:full":"15416 Saint Charles St Gulfport MS 39503",
    "addr:housenumber":"15416",
    "addr:postcode":"39503",
    "addr:street":"Saint Charles St",
    "iso:country":"US",
    "sg:address":"15416 Saint Charles St",
    "sg:city":"Gulfport",
    "sg:classifiers":[
        {
            "category":"Shopping",
            "subcategory":"Florist",
            "type":"Retail Goods"
        }
    ],
    "sg:phone":"+1 228 832 5798",
    "sg:postcode":"39503",
    "sg:province":"MS",
    "wof:name":"Village Florist",
    "wof:placetype":"venue"
},
  "geometry": {"coordinates":[-89.10014200000001,30.458452],"type":"Point"}
}