{
  "type": "Feature",
  "properties": {
    "iso:country":"US",
    "sg:address":"5850 Goodman Rd",
    "sg:city":"Olive Branch",
    "sg:classifiers":[
        {
            "category":"Retail",
            "subcategory":"Veterinary Services",
            "type":"Services"
        }
    ],
    "sg:phone":"+1 662 895 4004",
    "sg:postcode":"38654",
    "sg:province":"MS",
    "sg:tags":[
        "hospital",
        "animal"
    ],
    "wof:name":"All Animal Hospital",
    "wof:placetype":"venue"
},
  "geometry": {"coordinates":[-89.88727799999999,34.962317],"type":"Point"}
}