{
  "type": "Feature",
  "properties": {
    "addr:full":"115 E Beach Blvd Pass Christian MS 39571",
    "addr:housenumber":"115",
    "addr:postcode":"39571",
    "addr:street":"E Beach Blvd",
    "iso:country":"US",
    "sg:address":"115 E Beach Blvd",
    "sg:city":"Pass Christian",
    "sg:classifiers":[
        {
            "category":"Restaurant",
            "type":"Food & Drink"
        }
    ],
    "sg:phone":"+1 228 452 0019",
    "sg:postcode":"39571",
    "sg:province":"MS",
    "wof:name":"Mc Donald's",
    "wof:placetype":"venue"
},
  "geometry": {"coordinates":[-89.242434,30.31568],"type":"Point"}
}