{
  "type": "Feature",
  "properties": {
    "iso:country":"US",
    "sg:address":"10319 Diberville Blvd",
    "sg:city":"Biloxi",
    "sg:classifiers":[
        {
            "category":"Food & Beverages",
            "subcategory":"Liquor & Beverages",
            "type":"Retail Goods"
        }
    ],
    "sg:phone":"+1 228 392 2620",
    "sg:postcode":"39540",
    "sg:province":"MS",
    "sg:tags":[
        "alcoholic"
    ],
    "wof:name":"O D Thrift Package Store",
    "wof:placetype":"venue"
},
  "geometry": {"coordinates":[-88.89263800000001,30.436377],"type":"Point"}
}