{
  "type": "Feature",
  "properties": {
    "iso:country":"US",
    "sg:address":"1601 Government St",
    "sg:city":"Ocean Springs",
    "sg:classifiers":[
        {
            "category":"Personal",
            "subcategory":"Beauty Salon",
            "type":"Services"
        }
    ],
    "sg:phone":"+1 228 875 2816",
    "sg:postcode":"39564",
    "sg:province":"MS",
    "sg:tags":[
        "shop"
    ],
    "wof:name":"Headlines For Hair",
    "wof:placetype":"venue"
},
  "geometry": {"coordinates":[-88.82071999999999,30.413672],"type":"Point"}
}