{
  "type": "Feature",
  "properties": {
    "addr:full":"816 18th Ave Meridian MS 39301",
    "addr:housenumber":"816",
    "addr:postcode":"39301",
    "addr:street":"18Th Ave",
    "iso:country":"US",
    "sg:address":"816 18th Ave",
    "sg:city":"Meridian",
    "sg:classifiers":[
        {
            "category":"Wholesale",
            "subcategory":"Groceries",
            "type":"Manufacturing & Wholesale Goods"
        }
    ],
    "sg:phone":"+1 601 483 6711",
    "sg:postcode":"39301",
    "sg:province":"MS",
    "sg:tags":[
        "baker"
    ],
    "wof:name":"Earthgrains Baking Co Inc",
    "wof:placetype":"venue"
},
  "geometry": {"coordinates":[-88.689199,32.357831],"type":"Point"}
}