{
  "type": "Feature",
  "properties": {
    "iso:country":"US",
    "sg:address":"8265 Hwy 178",
    "sg:city":"Olive Branch",
    "sg:classifiers":[
        {
            "category":"Building & Trades",
            "subcategory":"Construction",
            "type":"Services"
        }
    ],
    "sg:phone":"+1 662 895 1222",
    "sg:postcode":"38654",
    "sg:province":"MS",
    "sg:tags":[
        "nonresidential"
    ],
    "wof:name":"Seamer Tools Inc",
    "wof:placetype":"venue"
},
  "geometry": {"coordinates":[-89.842522,34.973554],"type":"Point"}
}