{
  "type": "Feature",
  "properties": {
    "addr:full":"1469 E Northside Dr Jackson MS 39213",
    "addr:housenumber":"1469",
    "addr:postcode":"39213",
    "addr:street":"E Northside Dr",
    "iso:country":"US",
    "sg:address":"1469 E Northside Dr",
    "sg:city":"Jackson",
    "sg:classifiers":[
        {
            "category":"Personal",
            "subcategory":"Beauty Salon",
            "type":"Services"
        }
    ],
    "sg:phone":"+1 601 366 4513",
    "sg:postcode":"39213",
    "sg:province":"MS",
    "sg:tags":[
        "shop"
    ],
    "wof:name":"Nu Visions",
    "wof:placetype":"venue"
},
  "geometry": {"coordinates":[-90.200183,32.355898],"type":"Point"}
}