{
  "type": "Feature",
  "properties": {
    "iso:country":"US",
    "sg:address":"1298 F O A Rd",
    "sg:city":"Jackson",
    "sg:classifiers":[
        {
            "category":"Organizations",
            "subcategory":"Non-profit Organization",
            "type":"Services"
        }
    ],
    "sg:phone":"+1 601 362 4275",
    "sg:postcode":"39209",
    "sg:province":"MS",
    "sg:tags":[
        "information",
        "alcoholism",
        "treatment"
    ],
    "wof:name":"Friends Of Alcoholics",
    "wof:placetype":"venue"
},
  "geometry": {"coordinates":[-90.30413799999999,32.450753],"type":"Point"}
}