{
  "type": "Feature",
  "properties": {
    "addr:full":"4591 Sycamore Rd Coldwater MS 38638",
    "addr:housenumber":"4591",
    "addr:postcode":"38638",
    "addr:street":"Sycamore Rd",
    "iso:country":"US",
    "sg:address":"4591 Sycamore Rd",
    "sg:city":"Coldwater",
    "sg:classifiers":[
        {
            "category":"Building & Trades",
            "subcategory":"Construction",
            "type":"Services"
        }
    ],
    "sg:phone":"+1 662 233 0103",
    "sg:postcode":"38638",
    "sg:province":"MS",
    "sg:tags":[
        "general",
        "contractor"
    ],
    "wof:name":"House Doctor Construction",
    "wof:placetype":"venue"
},
  "geometry": {"coordinates":[-89.776477,34.746671],"type":"Point"}
}