{
  "type": "Feature",
  "properties": {
    "addr:full":"6124 Brown St Jackson MS 39213",
    "addr:housenumber":"6124",
    "addr:postcode":"39213",
    "addr:street":"Brown St",
    "iso:country":"US",
    "sg:address":"6124 Brown St",
    "sg:city":"Jackson",
    "sg:classifiers":[
        {
            "category":"Professional",
            "subcategory":"Management & Consulting",
            "type":"Services"
        }
    ],
    "sg:phone":"+1 601 956 0028",
    "sg:postcode":"39213",
    "sg:province":"MS",
    "sg:tags":[
        "consultant",
        "educational"
    ],
    "wof:name":"Innovative Behaviorial Svc",
    "wof:placetype":"venue"
},
  "geometry": {"coordinates":[-90.20229999999999,32.328904],"type":"Point"}
}