{
  "type": "Feature",
  "properties": {
    "iso:country":"US",
    "sg:address":"317 Delta Ave",
    "sg:city":"Clarksdale",
    "sg:classifiers":[
        {
            "category":"Professional",
            "subcategory":"Business Services",
            "type":"Services"
        }
    ],
    "sg:phone":"+1 662 627 7778",
    "sg:postcode":"38614",
    "sg:province":"MS",
    "sg:tags":[
        "broadcast",
        "radio"
    ],
    "wof:name":"Studio 61 Recording",
    "wof:placetype":"venue"
},
  "geometry": {"coordinates":[-90.574275,34.20036],"type":"Point"}
}