{
  "type": "Feature",
  "properties": {
    "iso:country":"US",
    "sg:address":"732 Brabston Rd",
    "sg:city":"Vicksburg",
    "sg:classifiers":[
        {
            "category":"Recreation",
            "type":"Entertainment"
        },
        {
            "category":"Retail",
            "subcategory":"Animal Services",
            "type":"Services"
        }
    ],
    "sg:phone":"+1 601 634 1345",
    "sg:postcode":"39180",
    "sg:province":"MS",
    "sg:tags":[
        "stable"
    ],
    "wof:name":"Merit Hill Stables",
    "wof:placetype":"venue"
},
  "geometry": {"coordinates":[-90.65243599999999,32.351173],"type":"Point"}
}