{
  "type": "Feature",
  "properties": {
    "addr:full":"720 Center St West Point MS 39773",
    "addr:housenumber":"720",
    "addr:postcode":"39773",
    "addr:street":"Center St",
    "iso:country":"US",
    "sg:address":"720 Center St",
    "sg:city":"West Point",
    "sg:classifiers":[
        {
            "category":"Health Services",
            "subcategory":"Doctor",
            "type":"Services"
        }
    ],
    "sg:phone":"+1 662 494 1620",
    "sg:postcode":"39773",
    "sg:province":"MS",
    "sg:tags":[
        "physician",
        "surgeon",
        "medical"
    ],
    "wof:name":"Children's Clinic",
    "wof:placetype":"venue"
},
  "geometry": {"coordinates":[-88.642742,33.616164],"type":"Point"}
}