{
  "type": "Feature",
  "properties": {
    "iso:country":"US",
    "sg:address":"1404 Belleglade St",
    "sg:city":"Jackson",
    "sg:classifiers":[
        {
            "category":"Real Estate",
            "subcategory":"Real Estate Operator",
            "type":"Services"
        }
    ],
    "sg:phone":"+1 601 982 2919",
    "sg:postcode":"39211",
    "sg:province":"MS",
    "sg:tags":[
        "building",
        "nonresidential"
    ],
    "wof:name":"Fifty One Place Shopping Ctr",
    "wof:placetype":"venue"
},
  "geometry": {"coordinates":[-90.144008,32.354931],"type":"Point"}
}