{
  "type": "Feature",
  "properties": {
    "addr:full":"582 Goodman Rd E Southaven MS 38671",
    "addr:housenumber":"582",
    "addr:postcode":"38671",
    "addr:street":"Goodman Rd E",
    "iso:country":"US",
    "sg:address":"582 Goodman Rd E",
    "sg:city":"Southaven",
    "sg:classifiers":[
        {
            "category":"Banks & Credit Unions",
            "subcategory":"Bank",
            "type":"Services"
        }
    ],
    "sg:phone":"+1 662 349 1998",
    "sg:postcode":"38671",
    "sg:province":"MS",
    "sg:tags":[
        "cashing",
        "check"
    ],
    "wof:name":"X-Tra Cash",
    "wof:placetype":"venue"
},
  "geometry": {"coordinates":[-89.980289,34.96281],"type":"Point"}
}