{
  "type": "Feature",
  "properties": {
    "iso:country":"US",
    "sg:address":"549 Northside Dr",
    "sg:city":"Newton",
    "sg:classifiers":[
        {
            "category":"Food & Beverages",
            "subcategory":"Groceries & Convenience Stores",
            "type":"Retail Goods"
        }
    ],
    "sg:phone":"+1 601 683 0111",
    "sg:postcode":"39345",
    "sg:province":"MS",
    "wof:name":"Spanky's Food Mart",
    "wof:placetype":"venue"
},
  "geometry": {"coordinates":[-89.158615,32.331195],"type":"Point"}
}