{
  "type": "Feature",
  "properties": {
    "addr:full":"1173 Hopper Rd Lucedale MS 39452",
    "addr:housenumber":"1173",
    "addr:postcode":"39452",
    "addr:street":"Hopper Rd",
    "iso:country":"US",
    "sg:address":"1173 Hopper Rd",
    "sg:city":"Lucedale",
    "sg:classifiers":[
        {
            "category":"Home & Garden",
            "subcategory":"Garden Supply",
            "type":"Retail Goods"
        }
    ],
    "sg:phone":"+1 601 947 8454",
    "sg:postcode":"39452",
    "sg:province":"MS",
    "sg:tags":[
        "nurseryman"
    ],
    "wof:name":"Serenity Hill Nursery",
    "wof:placetype":"venue"
},
  "geometry": {"coordinates":[-88.515764,30.914529],"type":"Point"}
}