{
  "type": "Feature",
  "properties": {
    "iso:country":"US",
    "sg:address":"200 E Bay St",
    "sg:city":"Magnolia",
    "sg:classifiers":[
        {
            "category":"Government",
            "subcategory":"Office",
            "type":"Public Place"
        }
    ],
    "sg:phone":"+1 601 783 5289",
    "sg:postcode":"39652",
    "sg:province":"MS",
    "wof:name":"Pike County Accounting Dept",
    "wof:placetype":"venue"
},
  "geometry": {"coordinates":[-90.46012899999999,31.14398],"type":"Point"}
}