{
  "type": "Feature",
  "properties": {
    "iso:country":"US",
    "sg:address":"2060 Baldwin Rd S",
    "sg:city":"Hernando",
    "sg:classifiers":[
        {
            "category":"Organizations",
            "subcategory":"Religious Organization",
            "type":"Services"
        }
    ],
    "sg:phone":"+1 662 429 3738",
    "sg:postcode":"38632",
    "sg:province":"MS",
    "sg:tags":[
        "church"
    ],
    "wof:name":"Eudora First United Methodist",
    "wof:placetype":"venue"
},
  "geometry": {"coordinates":[-90.13133500000001,34.830043],"type":"Point"}
}