{
  "type": "Feature",
  "properties": {
    "iso:country":"US",
    "sg:address":"135 Lewis Dr",
    "sg:city":"Natchez",
    "sg:classifiers":[
        {
            "category":"Personal",
            "subcategory":"Beauty Salon",
            "type":"Services"
        }
    ],
    "sg:phone":"+1 601 442 9370",
    "sg:postcode":"39120",
    "sg:province":"MS",
    "wof:name":"Regis' Styling Salon",
    "wof:placetype":"venue"
},
  "geometry": {"coordinates":[-91.41027,31.527189],"type":"Point"}
}