{
  "type": "Feature",
  "properties": {
    "iso:country":"US",
    "sg:address":"345 E Commerce St",
    "sg:city":"Hernando",
    "sg:classifiers":[
        {
            "category":"Shopping",
            "subcategory":"Used Merchandise",
            "type":"Retail Goods"
        }
    ],
    "sg:phone":"+1 662 449 5544",
    "sg:postcode":"38632",
    "sg:province":"MS",
    "sg:tags":[
        "antique"
    ],
    "wof:name":"Southern Antiques",
    "wof:placetype":"venue"
},
  "geometry": {"coordinates":[-89.98417600000001,34.823641],"type":"Point"}
}