{
  "type": "Feature",
  "properties": {
    "iso:country":"US",
    "sg:address":"2408 4th Ave",
    "sg:city":"Meridian",
    "sg:classifiers":[
        {
            "category":"Insurance",
            "subcategory":"Insurance Agent",
            "type":"Services"
        }
    ],
    "sg:phone":"+1 601 483 6249",
    "sg:postcode":"39301",
    "sg:province":"MS",
    "wof:name":"Lauderdale County Farm Bureau",
    "wof:placetype":"venue"
},
  "geometry": {"coordinates":[-88.682485,32.384394],"type":"Point"}
}