{
  "type": "Feature",
  "properties": {
    "addr:full":"580 Klondyke Rd Long Beach MS 39560",
    "addr:housenumber":"580",
    "addr:postcode":"39560",
    "addr:street":"Klondyke Rd",
    "iso:country":"US",
    "sg:address":"580 Klondyke Rd",
    "sg:city":"Long Beach",
    "sg:classifiers":[
        {
            "category":"Retail",
            "subcategory":"Auto Rental",
            "type":"Services"
        }
    ],
    "sg:phone":"+1 228 864 5800",
    "sg:postcode":"39560",
    "sg:province":"MS",
    "sg:tags":[
        "renting",
        "leasing",
        "trailer"
    ],
    "wof:name":"U-Haul Co",
    "wof:placetype":"venue"
},
  "geometry": {"coordinates":[-89.153246,30.367922],"type":"Point"}
}