{
  "type": "Feature",
  "properties": {
    "iso:country":"US",
    "sg:address":"849 1st St NW",
    "sg:city":"Magee",
    "sg:classifiers":[
        {
            "category":"Real Estate",
            "subcategory":"Real Estate Operator",
            "type":"Services"
        }
    ],
    "sg:phone":"+1 601 849 6081",
    "sg:postcode":"39111",
    "sg:province":"MS",
    "sg:tags":[
        "apartment"
    ],
    "wof:name":"Azalea Apartments",
    "wof:placetype":"venue"
},
  "geometry": {"coordinates":[-89.73959499999999,31.874169],"type":"Point"}
}