{
  "type": "Feature",
  "properties": {
    "iso:country":"US",
    "sg:address":"530 Old Hwy 26 W",
    "sg:city":"Poplarville",
    "sg:classifiers":[
        {
            "category":"Government",
            "subcategory":"Office",
            "type":"Public Place"
        }
    ],
    "sg:phone":"+1 601 795 4099",
    "sg:postcode":"39470",
    "sg:province":"MS",
    "sg:tags":[
        "state",
        "program",
        "health"
    ],
    "wof:name":"Mental Health Dept",
    "wof:placetype":"venue"
},
  "geometry": {"coordinates":[-89.595178,30.821904],"type":"Point"}
}