{
  "type": "Feature",
  "properties": {
    "iso:country":"US",
    "sg:address":"13250 Hwy 4 E",
    "sg:city":"Ripley",
    "sg:classifiers":[
        {
            "category":"Autos & Motor Vehicles",
            "subcategory":"Automobile Sales",
            "type":"Retail Goods"
        }
    ],
    "sg:phone":"+1 662 837 3774",
    "sg:postcode":"38663",
    "sg:province":"MS",
    "sg:tags":[
        "used"
    ],
    "wof:name":"Randys Auto Sales",
    "wof:placetype":"venue"
},
  "geometry": {"coordinates":[-88.88861300000001,34.727112],"type":"Point"}
}