{
  "type": "Feature",
  "properties": {
    "iso:country":"US",
    "sg:address":"107 Poplar Flat Rd",
    "sg:city":"Louisville",
    "sg:classifiers":[
        {
            "category":"Organizations",
            "subcategory":"Religious Organization",
            "type":"Services"
        }
    ],
    "sg:phone":"+1 662 773 7716",
    "sg:postcode":"39339",
    "sg:province":"MS",
    "wof:name":"Poplar Flats Rd Baptst Church",
    "wof:placetype":"venue"
},
  "geometry": {"coordinates":[-89.07534,33.147383],"type":"Point"}
}