{
  "type": "Feature",
  "properties": {
    "iso:country":"US",
    "sg:address":"422 Antioch-Shiloh Rd",
    "sg:city":"Pelahatchie",
    "sg:classifiers":[
        {
            "category":"Building & Trades",
            "subcategory":"Construction",
            "type":"Services"
        }
    ],
    "sg:phone":"+1 601 546 2306",
    "sg:postcode":"39145",
    "sg:province":"MS",
    "sg:tags":[
        "nonresidential"
    ],
    "wof:name":"Quality Farm Construction",
    "wof:placetype":"venue"
},
  "geometry": {"coordinates":[-89.811362,32.220524],"type":"Point"}
}