{
  "type": "Feature",
  "properties": {
    "addr:full":"1157 Lewis St Greenville MS 38701",
    "addr:housenumber":"1157",
    "addr:postcode":"38701",
    "addr:street":"Lewis St",
    "iso:country":"US",
    "sg:address":"1157 Lewis St",
    "sg:city":"Greenville",
    "sg:classifiers":[
        {
            "category":"Marine",
            "type":"Transportation"
        }
    ],
    "sg:phone":"+1 662 335 4772",
    "sg:postcode":"38701",
    "sg:province":"MS",
    "sg:tags":[
        "towing"
    ],
    "wof:name":"William's Diesel Svc",
    "wof:placetype":"venue"
},
  "geometry": {"coordinates":[-91.058724,33.388917],"type":"Point"}
}