{
  "type": "Feature",
  "properties": {
    "iso:country":"US",
    "sg:address":"5544 Hwy 21",
    "sg:city":"Forest",
    "sg:classifiers":[
        {
            "category":"Wholesale",
            "subcategory":"Machinery & Supplies",
            "type":"Manufacturing & Wholesale Goods"
        },
        {
            "category":"Building & Trades",
            "subcategory":"Plumbing",
            "type":"Services"
        }
    ],
    "sg:phone":"+1 601 469 1105",
    "sg:postcode":"39074",
    "sg:province":"MS",
    "sg:tags":[
        "sprinkle",
        "sprinkler",
        "installs",
        "alarm",
        "system",
        "fire"
    ],
    "wof:name":"Specialty Fire Protection Inc",
    "wof:placetype":"venue"
},
  "geometry": {"coordinates":[-89.428952,32.448417],"type":"Point"}
}