{
  "type": "Feature",
  "properties": {
    "iso:country":"US",
    "sg:address":"737 N Main St",
    "sg:city":"Vardaman",
    "sg:classifiers":[
        {
            "category":"Organizations",
            "subcategory":"Religious Organization",
            "type":"Services"
        }
    ],
    "sg:phone":"+1 662 682 9828",
    "sg:postcode":"38878",
    "sg:province":"MS",
    "sg:tags":[
        "church"
    ],
    "wof:name":"Independent Full Gospel Church",
    "wof:placetype":"venue"
},
  "geometry": {"coordinates":[-89.177998,33.889071],"type":"Point"}
}