{
  "type": "Feature",
  "properties": {
    "iso:country":"US",
    "sg:address":"506 W 8th St",
    "sg:city":"Macon",
    "sg:classifiers":[
        {
            "category":"Freight",
            "type":"Transportation"
        }
    ],
    "sg:phone":"+1 662 726 4255",
    "sg:postcode":"39341",
    "sg:province":"MS",
    "wof:name":"American Power Source Inc",
    "wof:placetype":"venue"
},
  "geometry": {"coordinates":[-88.56666800000001,33.110237],"type":"Point"}
}