{
  "type": "Feature",
  "properties": {
    "iso:country":"US",
    "sg:address":"5705 Hwy 178 W",
    "sg:city":"Fulton",
    "sg:classifiers":[
        {
            "category":"Government",
            "subcategory":"Office",
            "type":"Public Place"
        }
    ],
    "sg:phone":"+1 662 862 2723",
    "sg:postcode":"38843",
    "sg:province":"MS",
    "sg:tags":[
        "state"
    ],
    "wof:name":"Wildlife Dept",
    "wof:placetype":"venue"
},
  "geometry": {"coordinates":[-88.446488,34.264324],"type":"Point"}
}