{
  "type": "Feature",
  "properties": {
    "iso:country":"US",
    "sg:address":"506 Jacinto Rd",
    "sg:city":"Booneville",
    "sg:classifiers":[
        {
            "category":"Wholesale",
            "subcategory":"Auto Parts",
            "type":"Manufacturing & Wholesale Goods"
        }
    ],
    "sg:phone":"+1 662 728 8882",
    "sg:postcode":"38829",
    "sg:province":"MS",
    "sg:tags":[
        "automobile",
        "rebuilt"
    ],
    "wof:name":"Big H Auto Salvage & Recycling",
    "wof:placetype":"venue"
},
  "geometry": {"coordinates":[-88.544251,34.661051],"type":"Point"}
}