{
  "type": "Feature",
  "properties": {
    "addr:full":"2161 McCullough Blvd Tupelo MS 38801",
    "addr:housenumber":"2161",
    "addr:postcode":"38801",
    "addr:street":"Mccullough Blvd",
    "iso:country":"US",
    "sg:address":"2161 McCullough Blvd",
    "sg:city":"Tupelo",
    "sg:classifiers":[
        {
            "category":"Shopping",
            "type":"Retail Goods"
        }
    ],
    "sg:phone":"+1 662 842 3767",
    "sg:postcode":"38801",
    "sg:province":"MS",
    "sg:tags":[
        "water",
        "equipment",
        "treatment"
    ],
    "wof:name":"Rainsoft Water Treatment",
    "wof:placetype":"venue"
},
  "geometry": {"coordinates":[-88.768653,34.296254],"type":"Point"}
}