{
  "type": "Feature",
  "properties": {
    "addr:full":"3512 US Hwy 90 Gautier MS 39553",
    "addr:housenumber":"3512",
    "addr:postcode":"39553",
    "addr:street":"Us Hwy 90",
    "iso:country":"US",
    "sg:address":"3512 US Hwy 90",
    "sg:city":"Gautier",
    "sg:classifiers":[
        {
            "category":"Retail",
            "subcategory":"Auto Repair",
            "type":"Services"
        }
    ],
    "sg:phone":"+1 228 497 4500",
    "sg:postcode":"39553",
    "sg:province":"MS",
    "sg:tags":[
        "body",
        "automobile",
        "painting"
    ],
    "wof:name":"Metal Creations Custom Auto",
    "wof:placetype":"venue"
},
  "geometry": {"coordinates":[-88.677228,30.395944],"type":"Point"}
}