{
  "type": "Feature",
  "properties": {
    "addr:full":"718 Parkwood Dr Long Beach MS 39560",
    "addr:housenumber":"718",
    "addr:postcode":"39560",
    "addr:street":"Parkwood Dr",
    "iso:country":"US",
    "sg:address":"718 Parkwood Dr",
    "sg:city":"Long Beach",
    "sg:classifiers":[
        {
            "category":"Food & Beverages",
            "subcategory":"Specialty",
            "type":"Retail Goods"
        }
    ],
    "sg:phone":"+1 228 867 9840",
    "sg:postcode":"39560",
    "sg:province":"MS",
    "sg:tags":[
        "health",
        "diet"
    ],
    "wof:name":"Work From Home",
    "wof:placetype":"venue"
},
  "geometry": {"coordinates":[-89.182357,30.356362],"type":"Point"}
}