{
  "type": "Feature",
  "properties": {
    "addr:full":"419 Azalea Dr Waynesboro MS 39367",
    "addr:housenumber":"419",
    "addr:postcode":"39367",
    "addr:street":"Azalea Dr",
    "iso:country":"US",
    "sg:address":"419 Azalea Dr",
    "sg:city":"Waynesboro",
    "sg:classifiers":[
        {
            "category":"Shopping",
            "subcategory":"Department Store",
            "type":"Retail Goods"
        }
    ],
    "sg:phone":"+1 601 735 5748",
    "sg:postcode":"39367",
    "sg:province":"MS",
    "sg:tags":[
        "shop"
    ],
    "wof:name":"Family Dollar Store",
    "wof:placetype":"venue"
},
  "geometry": {"coordinates":[-88.653076,31.671252],"type":"Point"}
}