{
  "type": "Feature",
  "properties": {
    "addr:full":"4413 US Hwy 51 Senatobia MS 38668",
    "addr:housenumber":"4413",
    "addr:postcode":"38668",
    "addr:street":"Us Hwy 51",
    "iso:country":"US",
    "sg:address":"4413 US Hwy 51",
    "sg:city":"Senatobia",
    "sg:classifiers":[
        {
            "category":"Banks & Credit Unions",
            "subcategory":"Bank",
            "type":"Services"
        }
    ],
    "sg:phone":"+1 662 562 5238",
    "sg:postcode":"38668",
    "sg:province":"MS",
    "sg:tags":[
        "loan"
    ],
    "wof:name":"Massey Loans Inc",
    "wof:placetype":"venue"
},
  "geometry": {"coordinates":[-89.968487,34.618876],"type":"Point"}
}