{
  "type": "Feature",
  "properties": {
    "iso:country":"US",
    "sg:address":"107 Pearson St",
    "sg:city":"Pass Christian",
    "sg:classifiers":[
        {
            "category":"Wholesale",
            "subcategory":"Sporting Goods",
            "type":"Manufacturing & Wholesale Goods"
        }
    ],
    "sg:phone":"+1 228 452 0054",
    "sg:postcode":"39571",
    "sg:province":"MS",
    "sg:tags":[
        "equipment",
        "pool",
        "swimming"
    ],
    "wof:name":"Transtec Inc",
    "wof:placetype":"venue"
},
  "geometry": {"coordinates":[-89.252036,30.326898],"type":"Point"}
}