{
  "type": "Feature",
  "properties": {
    "iso:country":"US",
    "sg:address":"26 Eastgate Dr",
    "sg:city":"Brandon",
    "sg:classifiers":[
        {
            "category":"Professional",
            "subcategory":"Lawyer & Legal Services",
            "type":"Services"
        }
    ],
    "sg:phone":"+1 601 825 7291",
    "sg:postcode":"39042",
    "sg:province":"MS",
    "sg:tags":[
        "attorney"
    ],
    "wof:name":"John Robbins II",
    "wof:placetype":"venue"
},
  "geometry": {"coordinates":[-90.00711200000001,32.294688],"type":"Point"}
}