{
  "type": "Feature",
  "properties": {
    "iso:country":"US",
    "sg:address":"300 Katie Ave",
    "sg:city":"Hattiesburg",
    "sg:classifiers":[
        {
            "category":"Food & Beverages",
            "subcategory":"Groceries & Convenience Stores",
            "type":"Retail Goods"
        }
    ],
    "sg:phone":"+1 601 582 8626",
    "sg:postcode":"39401",
    "sg:province":"MS",
    "wof:name":"Katie Avenue Plaza",
    "wof:placetype":"venue"
},
  "geometry": {"coordinates":[-89.293176,31.315721],"type":"Point"}
}