{
  "type": "Feature",
  "properties": {
    "iso:country":"US",
    "sg:address":"596 Beulah Grove Rd",
    "sg:city":"Pontotoc",
    "sg:classifiers":[
        {
            "category":"Freight",
            "type":"Transportation"
        }
    ],
    "sg:phone":"+1 662 489 1180",
    "sg:postcode":"38863",
    "sg:province":"MS",
    "sg:tags":[
        "operator",
        "local",
        "trucking"
    ],
    "wof:name":"Pontotoc Trucks Inc",
    "wof:placetype":"venue"
},
  "geometry": {"coordinates":[-89.053141,34.280317],"type":"Point"}
}