{
  "type": "Feature",
  "properties": {
    "iso:country":"US",
    "sg:address":"320 Williamson Ave",
    "sg:city":"Philadelphia",
    "sg:classifiers":[
        {
            "category":"Professional",
            "subcategory":"Engineering",
            "type":"Services"
        }
    ],
    "sg:phone":"+1 601 656 3711",
    "sg:postcode":"39350",
    "sg:province":"MS",
    "sg:tags":[
        "engineer"
    ],
    "wof:name":"Neshoba County Engineering",
    "wof:placetype":"venue"
},
  "geometry": {"coordinates":[-89.08562999999999,32.767913],"type":"Point"}
}