{
  "type": "Feature",
  "properties": {
    "addr:full":"25 S Liberty St Pontotoc MS 38863",
    "addr:housenumber":"25",
    "addr:postcode":"38863",
    "addr:street":"S Liberty St",
    "iso:country":"US",
    "sg:address":"25 S Liberty St",
    "sg:city":"Pontotoc",
    "sg:classifiers":[
        {
            "category":"Government",
            "subcategory":"Office",
            "type":"Public Place"
        }
    ],
    "sg:phone":"+1 662 489 1232",
    "sg:postcode":"38863",
    "sg:province":"MS",
    "sg:tags":[
        "state",
        "resource"
    ],
    "wof:name":"Human Services Dept",
    "wof:placetype":"venue"
},
  "geometry": {"coordinates":[-88.998318,34.248432],"type":"Point"}
}