{
  "type": "Feature",
  "properties": {
    "addr:full":"617 Hwy 1 N Greenville MS 38703",
    "addr:housenumber":"617",
    "addr:postcode":"38703",
    "addr:street":"Hwy 1 N",
    "iso:country":"US",
    "sg:address":"617 Hwy 1 N",
    "sg:city":"Greenville",
    "sg:classifiers":[
        {
            "category":"Social Services",
            "subcategory":"Child Care",
            "type":"Services"
        }
    ],
    "sg:phone":"+1 662 332 3232",
    "sg:postcode":"38703",
    "sg:province":"MS",
    "sg:tags":[
        "day"
    ],
    "wof:name":"Rocking Chair Daycare",
    "wof:placetype":"venue"
},
  "geometry": {"coordinates":[-91.037916,33.418105],"type":"Point"}
}