{
  "type": "Feature",
  "properties": {
    "iso:country":"US",
    "sg:address":"252 US Hwy 90",
    "sg:city":"Bay Saint Louis",
    "sg:classifiers":[
        {
            "category":"Health Services",
            "subcategory":"Doctor",
            "type":"Services"
        }
    ],
    "sg:phone":"+1 228 466 3977",
    "sg:postcode":"39520",
    "sg:province":"MS",
    "sg:tags":[
        "clinic",
        "medical"
    ],
    "wof:name":"Dawkins Craig A MD",
    "wof:placetype":"venue"
},
  "geometry": {"coordinates":[-89.336602,30.320024],"type":"Point"}
}