{
  "type": "Feature",
  "properties": {
    "addr:full":"38 Alton Gavin Rd Laurel MS 39443",
    "addr:housenumber":"38",
    "addr:postcode":"39443",
    "addr:street":"Alton Gavin Rd",
    "iso:country":"US",
    "sg:address":"38 Alton Gavin Rd",
    "sg:city":"Laurel",
    "sg:classifiers":[
        {
            "category":"Building & Trades",
            "subcategory":"Cleaning & Sanitation",
            "type":"Services"
        }
    ],
    "sg:phone":"+1 601 729 2070",
    "sg:postcode":"39443",
    "sg:province":"MS",
    "sg:tags":[
        "maintenance",
        "contractor"
    ],
    "wof:name":"Ole Time Chimney Sweeps",
    "wof:placetype":"venue"
},
  "geometry": {"coordinates":[-89.21384999999999,31.762218],"type":"Point"}
}