{
  "type": "Feature",
  "properties": {
    "iso:country":"US",
    "sg:address":"100 Industrial Park Rd",
    "sg:city":"Booneville",
    "sg:classifiers":[
        {
            "category":"Manufacturing",
            "subcategory":"Rubber & Plastics",
            "type":"Manufacturing & Wholesale Goods"
        }
    ],
    "sg:phone":"+1 662 728 7799",
    "sg:postcode":"38829",
    "sg:province":"MS",
    "sg:tags":[
        "product"
    ],
    "wof:name":"Homeland Vinyl Products",
    "wof:placetype":"venue"
},
  "geometry": {"coordinates":[-88.55153199999999,34.668932],"type":"Point"}
}