{
  "type": "Feature",
  "properties": {
    "iso:country":"US",
    "sg:address":"326 Audubon Cir",
    "sg:city":"Brandon",
    "sg:classifiers":[
        {
            "category":"Building & Trades",
            "subcategory":"Construction",
            "type":"Services"
        }
    ],
    "sg:phone":"+1 601 668 7182",
    "sg:postcode":"39047",
    "sg:province":"MS",
    "sg:tags":[
        "carpentry",
        "contractor"
    ],
    "wof:name":"Browning Cstm Cabinets & Trim",
    "wof:placetype":"venue"
},
  "geometry": {"coordinates":[-90.06316099999999,32.356784],"type":"Point"}
}