{
  "type": "Feature",
  "properties": {
    "iso:country":"US",
    "sg:address":"152 Main St",
    "sg:city":"Bay St Louis",
    "sg:classifiers":[
        {
            "category":"Government",
            "subcategory":"Office",
            "type":"Public Place"
        }
    ],
    "sg:phone":"+1 228 467 6012",
    "sg:postcode":"39520",
    "sg:province":"MS",
    "wof:name":"Hancock County Bookkeeping",
    "wof:placetype":"venue"
},
  "geometry": {"coordinates":[-89.327755,30.311085],"type":"Point"}
}