{
  "type": "Feature",
  "properties": {
    "iso:country":"US",
    "sg:address":"135 US Hwy 61",
    "sg:city":"Woodville",
    "sg:classifiers":[
        {
            "category":"Shopping",
            "subcategory":"Discount & Variety Stores",
            "type":"Retail Goods"
        }
    ],
    "sg:phone":"+1 601 888 1887",
    "sg:postcode":"39669",
    "sg:province":"MS",
    "wof:name":"Conveinent Store",
    "wof:placetype":"venue"
},
  "geometry": {"coordinates":[-91.292376,31.103332],"type":"Point"}
}