{
  "type": "Feature",
  "properties": {
    "iso:country":"US",
    "sg:address":"5711 Telephone Rd",
    "sg:city":"Pascagoula",
    "sg:classifiers":[
        {
            "category":"Personal",
            "subcategory":"Barber",
            "type":"Services"
        }
    ],
    "sg:phone":"+1 228 762 1808",
    "sg:postcode":"39567",
    "sg:province":"MS",
    "wof:name":"Trinity Barber & Style Ctr",
    "wof:placetype":"venue"
},
  "geometry": {"coordinates":[-88.535312,30.38881],"type":"Point"}
}