{
  "type": "Feature",
  "properties": {
    "addr:full":"10432 Hwy 494 Meridian MS 39305",
    "addr:housenumber":"10432",
    "addr:postcode":"39305",
    "addr:street":"Hwy 494",
    "iso:country":"US",
    "sg:address":"10432 Hwy 494",
    "sg:city":"Meridian",
    "sg:classifiers":[
        {
            "category":"Government",
            "subcategory":"Fire Station",
            "type":"Public Place"
        }
    ],
    "sg:phone":"+1 601 581 5000",
    "sg:postcode":"39305",
    "sg:province":"MS",
    "sg:tags":[
        "department"
    ],
    "wof:name":"Suqualena Volunteer Fire",
    "wof:placetype":"venue"
},
  "geometry": {"coordinates":[-88.793781,32.433805],"type":"Point"}
}