{
  "type": "Feature",
  "properties": {
    "iso:country":"US",
    "sg:address":"915 38th Ave",
    "sg:city":"Gulfport",
    "sg:classifiers":[
        {
            "category":"Food & Beverages",
            "subcategory":"Groceries & Convenience Stores",
            "type":"Retail Goods"
        }
    ],
    "sg:phone":"+1 228 863 9411",
    "sg:postcode":"39501",
    "sg:province":"MS",
    "wof:name":"Food For Life",
    "wof:placetype":"venue"
},
  "geometry": {"coordinates":[-89.10720999999999,30.363729],"type":"Point"}
}