{
  "type": "Feature",
  "properties": {
    "iso:country":"US",
    "sg:address":"3246 Hwy 51 S",
    "sg:city":"Hernando",
    "sg:classifiers":[
        {
            "category":"Social Services",
            "type":"Services"
        }
    ],
    "sg:phone":"+1 662 429 1327",
    "sg:postcode":"38632",
    "sg:province":"MS",
    "sg:tags":[
        "government"
    ],
    "wof:name":"De Soto County Youth Svc",
    "wof:placetype":"venue"
},
  "geometry": {"coordinates":[-89.99225199999999,34.8125],"type":"Point"}
}