{
  "type": "Feature",
  "properties": {
    "iso:country":"US",
    "sg:address":"5836 US Hwy 11",
    "sg:city":"Purvis",
    "sg:classifiers":[
        {
            "category":"Banks & Credit Unions",
            "subcategory":"Bank",
            "type":"Services"
        }
    ],
    "sg:phone":"+1 601 794 0044",
    "sg:postcode":"39475",
    "sg:province":"MS",
    "sg:tags":[
        "cashing",
        "check"
    ],
    "wof:name":"Ronnie Keller Advance Check",
    "wof:placetype":"venue"
},
  "geometry": {"coordinates":[-89.405528,31.141758],"type":"Point"}
}