{
  "type": "Feature",
  "properties": {
    "addr:full":"502 City Ave S Ripley MS 38663",
    "addr:housenumber":"502",
    "addr:postcode":"38663",
    "addr:street":"City Ave S",
    "iso:country":"US",
    "sg:address":"502 City Ave S",
    "sg:city":"Ripley",
    "sg:classifiers":[
        {
            "category":"Insurance",
            "subcategory":"Insurance Agent",
            "type":"Services"
        }
    ],
    "sg:phone":"+1 662 837 8874",
    "sg:postcode":"38663",
    "sg:province":"MS",
    "wof:name":"Ripley Insurance",
    "wof:placetype":"venue"
},
  "geometry": {"coordinates":[-88.94633,34.727576],"type":"Point"}
}