{
  "type": "Feature",
  "properties": {
    "iso:country":"US",
    "sg:address":"117 N Broadway St",
    "sg:city":"Mccomb",
    "sg:classifiers":[
        {
            "category":"Personal",
            "subcategory":"Barber",
            "type":"Services"
        }
    ],
    "sg:phone":"+1 601 684 4091",
    "sg:postcode":"39648",
    "sg:province":"MS",
    "wof:name":"Five Point Barber Shop",
    "wof:placetype":"venue"
},
  "geometry": {"coordinates":[-90.453942,31.244843],"type":"Point"}
}