{
  "type": "Feature",
  "properties": {
    "iso:country":"US",
    "sg:address":"179 Fellowship Rd",
    "sg:city":"Saltillo",
    "sg:classifiers":[
        {
            "category":"Government",
            "subcategory":"Office",
            "type":"Public Place"
        }
    ],
    "sg:phone":"+1 662 869 2107",
    "sg:postcode":"38866",
    "sg:province":"MS",
    "sg:tags":[
        "village"
    ],
    "wof:name":"Waste Water Plant",
    "wof:placetype":"venue"
},
  "geometry": {"coordinates":[-88.68012899999999,34.371508],"type":"Point"}
}