{
  "type": "Feature",
  "properties": {
    "iso:country":"US",
    "sg:address":"18045 Bond Rd",
    "sg:city":"Saucier",
    "sg:classifiers":[
        {
            "category":"Building & Trades",
            "subcategory":"Electrical",
            "type":"Services"
        }
    ],
    "sg:phone":"+1 228 832 8839",
    "sg:postcode":"39574",
    "sg:province":"MS",
    "sg:tags":[
        "electric",
        "contractor"
    ],
    "wof:name":"King Electric",
    "wof:placetype":"venue"
},
  "geometry": {"coordinates":[-89.138358,30.589928],"type":"Point"}
}