{
  "type": "Feature",
  "properties": {
    "iso:country":"US",
    "sg:address":"10 Dean Griner Dr",
    "sg:city":"Columbia",
    "sg:classifiers":[
        {
            "category":"Government",
            "subcategory":"Office",
            "type":"Public Place"
        }
    ],
    "sg:phone":"+1 601 736 2099",
    "sg:postcode":"39429",
    "sg:province":"MS",
    "wof:name":"Marion County Dist Supervisor",
    "wof:placetype":"venue"
},
  "geometry": {"coordinates":[-89.86028399999999,31.275695],"type":"Point"}
}