{
  "type": "Feature",
  "properties": {
    "iso:country":"US",
    "sg:address":"508 N Church Ave",
    "sg:city":"Louisville",
    "sg:classifiers":[
        {
            "category":"Retail",
            "subcategory":"Veterinary Services",
            "type":"Services"
        }
    ],
    "sg:phone":"+1 662 773 8188",
    "sg:postcode":"39339",
    "sg:province":"MS",
    "sg:tags":[
        "veterinarian"
    ],
    "wof:name":"Animal Medical-Surgical Clinic",
    "wof:placetype":"venue"
},
  "geometry": {"coordinates":[-89.05665399999999,33.133702],"type":"Point"}
}