{
  "type": "Feature",
  "properties": {
    "iso:country":"US",
    "sg:address":"5223 Ulmer Rd",
    "sg:city":"Beaumont",
    "sg:classifiers":[
        {
            "category":"Autos & Motor Vehicles",
            "subcategory":"Auto Supplies",
            "type":"Retail Goods"
        }
    ],
    "sg:phone":"+1 601 584 6551",
    "sg:postcode":"39423",
    "sg:province":"MS",
    "sg:tags":[
        "tire"
    ],
    "wof:name":"South Mississippi Tire",
    "wof:placetype":"venue"
},
  "geometry": {"coordinates":[-88.838396,31.196374],"type":"Point"}
}