{
  "type": "Feature",
  "properties": {
    "addr:full":"122 Col John Pitchford Pkwy Natchez MS 39120",
    "addr:housenumber":"122",
    "addr:postcode":"39120",
    "addr:street":"Col John Pitchford Pkwy Natchez",
    "iso:country":"US",
    "sg:address":"122 Col John Pitchford Pkwy",
    "sg:city":"Natchez",
    "sg:classifiers":[
        {
            "category":"Wholesale",
            "subcategory":"Petroleum",
            "type":"Manufacturing & Wholesale Goods"
        }
    ],
    "sg:phone":"+1 601 304 1280",
    "sg:postcode":"39120",
    "sg:province":"MS",
    "sg:tags":[
        "bulk",
        "station"
    ],
    "wof:name":"Kaiser Enterprises Inc",
    "wof:placetype":"venue"
},
  "geometry": {"coordinates":[-91.39159100000001,31.513838],"type":"Point"}
}