{
  "type": "Feature",
  "properties": {
    "addr:full":"1201 Grove St Vicksburg MS 39183",
    "addr:housenumber":"1201",
    "addr:postcode":"39183",
    "addr:street":"Grove St",
    "iso:country":"US",
    "sg:address":"1201 Grove St",
    "sg:city":"Vicksburg",
    "sg:classifiers":[
        {
            "category":"Organizations",
            "subcategory":"Religious Organization",
            "type":"Services"
        }
    ],
    "sg:phone":"+1 601 638 2500",
    "sg:postcode":"39183",
    "sg:province":"MS",
    "sg:tags":[
        "church"
    ],
    "sg:website":"www.wofcc-vicksburg.com",
    "wof:name":"Word Of Faith Christian Ctr",
    "wof:placetype":"venue"
},
  "geometry": {"coordinates":[-90.87588,32.351329],"type":"Point"}
}