{
  "type": "Feature",
  "properties": {
    "iso:country":"US",
    "sg:address":"129 Jack Pearson Rd",
    "sg:city":"Louisville",
    "sg:classifiers":[
        {
            "category":"Shopping",
            "subcategory":"Used Merchandise",
            "type":"Retail Goods"
        }
    ],
    "sg:phone":"+1 662 773 2366",
    "sg:postcode":"39339",
    "sg:province":"MS",
    "sg:tags":[
        "antique"
    ],
    "wof:name":"Britni's Antiques & Cllctbls",
    "wof:placetype":"venue"
},
  "geometry": {"coordinates":[-88.982472,33.103317],"type":"Point"}
}