{
  "type": "Feature",
  "properties": {
    "addr:full":"1670 Whitehouse Rd Iuka MS 38852",
    "addr:housenumber":"1670",
    "addr:postcode":"38852",
    "addr:street":"Whitehouse Rd",
    "iso:country":"US",
    "sg:address":"1670 Whitehouse Rd",
    "sg:city":"Iuka",
    "sg:classifiers":[
        {
            "category":"Health Services",
            "subcategory":"Nursing And Care Facility",
            "type":"Services"
        },
        {
            "category":"Social Services",
            "type":"Services"
        }
    ],
    "sg:phone":"+1 662 423 1194",
    "sg:postcode":"38852",
    "sg:province":"MS",
    "sg:tags":[
        "personal",
        "home",
        "intermediate"
    ],
    "wof:name":"Carrington House Inc",
    "wof:placetype":"venue"
},
  "geometry": {"coordinates":[-88.213174,34.821687],"type":"Point"}
}