{
  "type": "Feature",
  "properties": {
    "iso:country":"US",
    "sg:address":"201 Hwy 45 N",
    "sg:city":"Aberdeen",
    "sg:classifiers":[
        {
            "category":"Restaurant",
            "type":"Food & Drink"
        }
    ],
    "sg:phone":"+1 662 369 9886",
    "sg:postcode":"39730",
    "sg:province":"MS",
    "sg:tags":[
        "eating"
    ],
    "wof:name":"McDonalds",
    "wof:placetype":"venue"
},
  "geometry": {"coordinates":[-88.56155,33.829519],"type":"Point"}
}