{
  "type": "Feature",
  "properties": {
    "addr:full":"585 Tate Rd Natchez MS 39120",
    "addr:housenumber":"585",
    "addr:postcode":"39120",
    "addr:street":"Tate Rd",
    "iso:country":"US",
    "sg:address":"585 Tate Rd",
    "sg:city":"Natchez",
    "sg:classifiers":[
        {
            "category":"Organizations",
            "subcategory":"Religious Organization",
            "type":"Services"
        }
    ],
    "sg:phone":"+1 601 442 3289",
    "sg:postcode":"39120",
    "sg:province":"MS",
    "sg:tags":[
        "church"
    ],
    "wof:name":"St James AME Church",
    "wof:placetype":"venue"
},
  "geometry": {"coordinates":[-91.203275,31.626408],"type":"Point"}
}