{
  "type": "Feature",
  "properties": {
    "iso:country":"US",
    "sg:address":"217 W Pine St",
    "sg:city":"Hattiesburg",
    "sg:classifiers":[
        {
            "category":"Banks & Credit Unions",
            "subcategory":"Investment Brokerage",
            "type":"Services"
        }
    ],
    "sg:phone":"+1 601 583 1800",
    "sg:postcode":"39401",
    "sg:province":"MS",
    "sg:tags":[
        "security"
    ],
    "wof:name":"Mc Creery Securities Inc",
    "wof:placetype":"venue"
},
  "geometry": {"coordinates":[-89.29170499999999,31.325949],"type":"Point"}
}