{
  "type": "Feature",
  "properties": {
    "iso:country":"US",
    "sg:address":"6536 Old Canton Rd",
    "sg:city":"Ridgeland",
    "sg:classifiers":[
        {
            "category":"Banks & Credit Unions",
            "subcategory":"Bank",
            "type":"Services"
        }
    ],
    "sg:phone":"+1 601 957 5720",
    "sg:postcode":"39157",
    "sg:province":"MS",
    "wof:name":"M & F Bank",
    "wof:placetype":"venue"
},
  "geometry": {"coordinates":[-90.10852300000001,32.400778],"type":"Point"}
}