{
  "type": "Feature",
  "properties": {
    "iso:country":"US",
    "sg:address":"405 Fayard St",
    "sg:city":"Biloxi",
    "sg:classifiers":[
        {
            "category":"Building & Trades",
            "subcategory":"Construction",
            "type":"Services"
        }
    ],
    "sg:phone":"+1 228 432 7164",
    "sg:postcode":"39530",
    "sg:province":"MS",
    "sg:tags":[
        "sheet",
        "metal",
        "contractor"
    ],
    "wof:name":"Philip Dellenger Sheet Metal",
    "wof:placetype":"venue"
},
  "geometry": {"coordinates":[-88.89117400000001,30.408957],"type":"Point"}
}