{
  "type": "Feature",
  "properties": {
    "iso:country":"US",
    "sg:address":"313 Robin Dr",
    "sg:city":"Hattiesburg",
    "sg:classifiers":[
        {
            "category":"Real Estate",
            "subcategory":"Developer",
            "type":"Services"
        }
    ],
    "sg:phone":"+1 601 296 7938",
    "sg:postcode":"39402",
    "sg:province":"MS",
    "wof:name":"Kings Kids Development Center",
    "wof:placetype":"venue"
},
  "geometry": {"coordinates":[-89.361679,31.285259],"type":"Point"}
}