{
  "type": "Feature",
  "properties": {
    "addr:full":"307 Fox Run Rd Brandon MS 39042",
    "addr:housenumber":"307",
    "addr:postcode":"39042",
    "addr:street":"Fox Run Rd",
    "iso:country":"US",
    "sg:address":"307 Fox Run Rd",
    "sg:city":"Brandon",
    "sg:classifiers":[
        {
            "category":"Utilities",
            "subcategory":"Telephone",
            "type":"Services"
        }
    ],
    "sg:phone":"+1 601 829 1999",
    "sg:postcode":"39042",
    "sg:province":"MS",
    "sg:tags":[
        "communications",
        "cabling"
    ],
    "wof:name":"Integrated Cable Services LLC",
    "wof:placetype":"venue"
},
  "geometry": {"coordinates":[-89.950475,32.356612],"type":"Point"}
}