{
  "type": "Feature",
  "properties": {
    "iso:country":"US",
    "sg:address":"437 S Industrial Pkwy",
    "sg:city":"Yazoo City",
    "sg:classifiers":[
        {
            "category":"Manufacturing",
            "subcategory":"Textiles",
            "type":"Manufacturing & Wholesale Goods"
        }
    ],
    "sg:phone":"+1 662 746 4941",
    "sg:postcode":"39194",
    "sg:province":"MS",
    "sg:tags":[
        "cotton"
    ],
    "sg:website":"www.staplcotn.com",
    "wof:name":"Staplcotn",
    "wof:placetype":"venue"
},
  "geometry": {"coordinates":[-90.433756,32.848167],"type":"Point"}
}