{
  "type": "Feature",
  "properties": {
    "iso:country":"US",
    "sg:address":"9785 Wildcat Rd",
    "sg:city":"Collinsville",
    "sg:classifiers":[
        {
            "category":"Manufacturing",
            "subcategory":"Lumber",
            "type":"Manufacturing & Wholesale Goods"
        }
    ],
    "sg:phone":"+1 601 626 0056",
    "sg:postcode":"39325",
    "sg:province":"MS",
    "sg:tags":[
        "forestry",
        "forester"
    ],
    "wof:name":"Southern Natural Resource Inc",
    "wof:placetype":"venue"
},
  "geometry": {"coordinates":[-88.863758,32.524489],"type":"Point"}
}