{
  "type": "Feature",
  "properties": {
    "iso:country":"US",
    "sg:address":"1777 Old Mobile Ave",
    "sg:city":"Pascagoula",
    "sg:classifiers":[
        {
            "category":"Retail",
            "subcategory":"Repair Shop",
            "type":"Services"
        }
    ],
    "sg:phone":"+1 228 762 1258",
    "sg:postcode":"39567",
    "sg:province":"MS",
    "sg:tags":[
        "electrical"
    ],
    "wof:name":"Communications Engrg Svcs",
    "wof:placetype":"venue"
},
  "geometry": {"coordinates":[-88.544929,30.366418],"type":"Point"}
}