{
  "type": "Feature",
  "properties": {
    "iso:country":"US",
    "sg:address":"333 Port Access Rd",
    "sg:city":"Columbus",
    "sg:classifiers":[
        {
            "category":"Farming",
            "subcategory":"Farm",
            "type":"Manufacturing & Wholesale Goods"
        }
    ],
    "sg:phone":"+1 662 328 5617",
    "sg:postcode":"39701",
    "sg:province":"MS",
    "sg:tags":[
        "crop",
        "general"
    ],
    "wof:name":"P Steven Swedenburg",
    "wof:placetype":"venue"
},
  "geometry": {"coordinates":[-88.44082899999999,33.487099],"type":"Point"}
}