{
  "type": "Feature",
  "properties": {
    "iso:country":"US",
    "sg:address":"820 North St",
    "sg:city":"Jackson",
    "sg:classifiers":[
        {
            "category":"Professional",
            "subcategory":"Lawyer & Legal Services",
            "type":"Services"
        }
    ],
    "sg:phone":"+1 601 353 2460",
    "sg:postcode":"39202",
    "sg:province":"MS",
    "sg:tags":[
        "attorney"
    ],
    "wof:name":"Priester Law Firm",
    "wof:placetype":"venue"
},
  "geometry": {"coordinates":[-90.177269,32.307882],"type":"Point"}
}