{
  "type": "Feature",
  "properties": {
    "iso:country":"US",
    "sg:address":"3680 Sangani Blvd",
    "sg:city":"Diberville",
    "sg:classifiers":[
        {
            "category":"Social Services",
            "subcategory":"Job Training",
            "type":"Services"
        }
    ],
    "sg:phone":"+1 228 392 9995",
    "sg:postcode":"39532",
    "sg:province":"MS",
    "sg:tags":[
        "rehabilitation"
    ],
    "wof:name":"Healing Center",
    "wof:placetype":"venue"
},
  "geometry": {"coordinates":[-88.89882799999999,30.457886],"type":"Point"}
}