{
  "type": "Feature",
  "properties": {
    "iso:country":"US",
    "sg:address":"615 E Clay St",
    "sg:city":"Greenville",
    "sg:classifiers":[
        {
            "category":"Professional",
            "subcategory":"Accounting & Tax Preparation",
            "type":"Services"
        }
    ],
    "sg:phone":"+1 662 344 0770",
    "sg:postcode":"38701",
    "sg:province":"MS",
    "sg:tags":[
        "bookkeeping",
        "general"
    ],
    "wof:name":"L C's Bookkeeping & Scrtrl",
    "wof:placetype":"venue"
},
  "geometry": {"coordinates":[-91.059927,33.399433],"type":"Point"}
}