{
  "type": "Feature",
  "properties": {
    "addr:full":"115 Village Square Dr Brandon MS 39047",
    "addr:housenumber":"115",
    "addr:postcode":"39047",
    "addr:street":"Village Square Dr",
    "iso:country":"US",
    "sg:address":"115 Village Square Dr",
    "sg:city":"Brandon",
    "sg:classifiers":[
        {
            "category":"Shopping",
            "subcategory":"Tobacco",
            "type":"Retail Goods"
        }
    ],
    "sg:phone":"+1 601 992 2882",
    "sg:postcode":"39047",
    "sg:province":"MS",
    "sg:tags":[
        "cigarette",
        "cigar",
        "stand",
        "store",
        "dealer"
    ],
    "wof:name":"Tobacco Market",
    "wof:placetype":"venue"
},
  "geometry": {"coordinates":[-89.95034099999999,32.41519],"type":"Point"}
}