{
  "type": "Feature",
  "properties": {
    "addr:full":"1042 Goodman Rd E Southaven MS 38671",
    "addr:housenumber":"1042",
    "addr:postcode":"38671",
    "addr:street":"Goodman Rd E",
    "iso:country":"US",
    "sg:address":"1042 Goodman Rd E",
    "sg:city":"Southaven",
    "sg:classifiers":[
        {
            "category":"Shopping",
            "subcategory":"Bicycles & Sporting Goods",
            "type":"Retail Goods"
        }
    ],
    "sg:phone":"+1 662 349 0900",
    "sg:postcode":"38671",
    "sg:province":"MS",
    "wof:name":"Andrews Management Inc",
    "wof:placetype":"venue"
},
  "geometry": {"coordinates":[-89.971554,34.962693],"type":"Point"}
}