{
  "type": "Feature",
  "properties": {
    "iso:country":"US",
    "sg:address":"970 Division St",
    "sg:city":"Biloxi",
    "sg:classifiers":[
        {
            "category":"Professional",
            "subcategory":"Advertising",
            "type":"Services"
        }
    ],
    "sg:phone":"+1 228 432 1212",
    "sg:postcode":"39530",
    "sg:province":"MS",
    "sg:tags":[
        "counselor"
    ],
    "sg:website":"www.bbwagency.com",
    "wof:name":"Brown Baer Wilcox Agency",
    "wof:placetype":"venue"
},
  "geometry": {"coordinates":[-88.89722399999999,30.40324],"type":"Point"}
}