{
  "type": "Feature",
  "properties": {
    "iso:country":"US",
    "sg:address":"5625 Hwy 18 W",
    "sg:city":"Jackson",
    "sg:classifiers":[
        {
            "category":"Building & Trades",
            "subcategory":"Electrical",
            "type":"Services"
        }
    ],
    "sg:phone":"+1 601 372 0081",
    "sg:postcode":"39209",
    "sg:province":"MS",
    "sg:tags":[
        "electric",
        "contractor"
    ],
    "wof:name":"Luft Electric Inc",
    "wof:placetype":"venue"
},
  "geometry": {"coordinates":[-90.281834,32.277971],"type":"Point"}
}