{
  "type": "Feature",
  "properties": {
    "iso:country":"US",
    "sg:address":"44 John Hession Rd",
    "sg:city":"Hattiesburg",
    "sg:classifiers":[
        {
            "category":"Personal",
            "subcategory":"Beauty Salon",
            "type":"Services"
        }
    ],
    "sg:phone":"+1 601 545 2008",
    "sg:postcode":"39401",
    "sg:province":"MS",
    "wof:name":"Special Touch",
    "wof:placetype":"venue"
},
  "geometry": {"coordinates":[-89.29901099999999,31.167419],"type":"Point"}
}