{
  "type": "Feature",
  "properties": {
    "iso:country":"US",
    "sg:address":"518 Beulah Ave",
    "sg:city":"Tylertown",
    "sg:classifiers":[
        {
            "category":"Shopping",
            "subcategory":"Computers & Home Electronics",
            "type":"Retail Goods"
        }
    ],
    "sg:phone":"+1 601 876 3771",
    "sg:postcode":"39667",
    "sg:province":"MS",
    "sg:tags":[
        "repair",
        "satellite",
        "appliance",
        "system",
        "equipment"
    ],
    "wof:name":"Blackwells TV Inc",
    "wof:placetype":"venue"
},
  "geometry": {"coordinates":[-90.17012200000001,31.126629],"type":"Point"}
}