{
  "type": "Feature",
  "properties": {
    "iso:country":"US",
    "sg:address":"1109 Ingalls Ave",
    "sg:city":"Pascagoula",
    "sg:classifiers":[
        {
            "category":"Shopping",
            "subcategory":"Clothing, Apparel, & Fashions",
            "type":"Retail Goods"
        }
    ],
    "sg:phone":"+1 228 769 5170",
    "sg:postcode":"39567",
    "sg:province":"MS",
    "sg:tags":[
        "designer"
    ],
    "wof:name":"Deanna Bartee's Design Room",
    "wof:placetype":"venue"
},
  "geometry": {"coordinates":[-88.553737,30.354801],"type":"Point"}
}