{
  "type": "Feature",
  "properties": {
    "iso:country":"US",
    "sg:address":"5435 Casino Strip Resort Blvd",
    "sg:city":"Tunica",
    "sg:classifiers":[
        {
            "category":"Organizations",
            "subcategory":"Religious Organization",
            "type":"Services"
        }
    ],
    "sg:phone":"+1 662 363 2794",
    "sg:postcode":"38664",
    "sg:province":"MS",
    "sg:tags":[
        "church"
    ],
    "wof:name":"Mt Olive Missionary Baptist",
    "wof:placetype":"venue"
},
  "geometry": {"coordinates":[-90.345844,34.817216],"type":"Point"}
}