{
  "type": "Feature",
  "properties": {
    "addr:full":"2616 W Capitol St Jackson MS 39209",
    "addr:housenumber":"2616",
    "addr:postcode":"39209",
    "addr:street":"W Capitol St",
    "iso:country":"US",
    "sg:address":"2616 W Capitol St",
    "sg:city":"Jackson",
    "sg:classifiers":[
        {
            "category":"Social Services",
            "type":"Services"
        }
    ],
    "sg:phone":"+1 601 353 9933",
    "sg:postcode":"39209",
    "sg:province":"MS",
    "wof:name":"Victims of Police Pursuits",
    "wof:placetype":"venue"
},
  "geometry": {"coordinates":[-90.219128,32.316823],"type":"Point"}
}