{
  "type": "Feature",
  "properties": {
    "addr:full":"1101 State Hwy 8 Cleveland MS 38732",
    "addr:housenumber":"1101",
    "addr:postcode":"38732",
    "addr:street":"State Hwy 8",
    "iso:country":"US",
    "sg:address":"1101 State Hwy 8",
    "sg:city":"Cleveland",
    "sg:classifiers":[
        {
            "category":"Insurance",
            "subcategory":"Insurance Agent",
            "type":"Services"
        }
    ],
    "sg:phone":"+1 662 843 5938",
    "sg:postcode":"38732",
    "sg:province":"MS",
    "wof:name":"State Farm Insurance",
    "wof:placetype":"venue"
},
  "geometry": {"coordinates":[-90.74105299999999,33.748353],"type":"Point"}
}