{
  "type": "Feature",
  "properties": {
    "addr:full":"1755 McNeill McHenry Rd Perkinston MS 39573",
    "addr:housenumber":"1755",
    "addr:postcode":"39573",
    "addr:street":"Mcneill Mchenry Rd",
    "iso:country":"US",
    "sg:address":"1755 McNeill McHenry Rd",
    "sg:city":"Perkinston",
    "sg:classifiers":[
        {
            "category":"Restaurant",
            "type":"Food & Drink"
        }
    ],
    "sg:phone":"+1 601 928 5809",
    "sg:postcode":"39573",
    "sg:province":"MS",
    "sg:tags":[
        "eating"
    ],
    "wof:name":"Norton Company",
    "wof:placetype":"venue"
},
  "geometry": {"coordinates":[-89.34339,30.732366],"type":"Point"}
}