{
  "type": "Feature",
  "properties": {
    "addr:full":"5813 Pepper Chase Dr Southaven MS 38671",
    "addr:housenumber":"5813",
    "addr:postcode":"38671",
    "addr:street":"Pepper Chase Dr",
    "iso:country":"US",
    "sg:address":"5813 Pepper Chase Dr",
    "sg:city":"Southaven",
    "sg:classifiers":[
        {
            "category":"Government",
            "subcategory":"Office",
            "type":"Public Place"
        }
    ],
    "sg:phone":"+1 662 393 0511",
    "sg:postcode":"38671",
    "sg:province":"MS",
    "sg:tags":[
        "village"
    ],
    "wof:name":"Southaven Animal Shelter",
    "wof:placetype":"venue"
},
  "geometry": {"coordinates":[-89.996736,34.94335],"type":"Point"}
}