{
  "type": "Feature",
  "properties": {
    "iso:country":"US",
    "sg:address":"326 Main Ave N",
    "sg:city":"Magee",
    "sg:classifiers":[
        {
            "category":"Shopping",
            "subcategory":"Department Store",
            "type":"Retail Goods"
        }
    ],
    "sg:phone":"+1 601 849 5111",
    "sg:postcode":"39111",
    "sg:province":"MS",
    "sg:tags":[
        "shop"
    ],
    "wof:name":"Fred's Store",
    "wof:placetype":"venue"
},
  "geometry": {"coordinates":[-89.73245300000001,31.876042],"type":"Point"}
}