{
  "type": "Feature",
  "properties": {
    "addr:full":"4765 S McRaven Rd Jackson MS 39204",
    "addr:housenumber":"4765",
    "addr:postcode":"39204",
    "addr:street":"S Mcraven Rd",
    "iso:country":"US",
    "sg:address":"4765 S McRaven Rd",
    "sg:city":"Jackson",
    "sg:classifiers":[
        {
            "category":"Wholesale",
            "subcategory":"Groceries",
            "type":"Manufacturing & Wholesale Goods"
        }
    ],
    "sg:phone":"+1 601 366 3502",
    "sg:postcode":"39204",
    "sg:province":"MS",
    "sg:tags":[
        "baker"
    ],
    "wof:name":"Tiller Biscotti & Cookie Co",
    "wof:placetype":"venue"
},
  "geometry": {"coordinates":[-90.265624,32.297111],"type":"Point"}
}