{
  "type": "Feature",
  "properties": {
    "iso:country":"US",
    "sg:address":"1505 Genie Fairway",
    "sg:city":"Greenville",
    "sg:classifiers":[
        {
            "category":"Building & Trades",
            "subcategory":"Construction",
            "type":"Services"
        }
    ],
    "sg:phone":"+1 662 378 3761",
    "sg:postcode":"38701",
    "sg:province":"MS",
    "wof:name":"Floyd Construction & Dev Co",
    "wof:placetype":"venue"
},
  "geometry": {"coordinates":[-91.048767,33.381436],"type":"Point"}
}