{
  "type": "Feature",
  "properties": {
    "iso:country":"US",
    "sg:address":"1860 Popps Ferry Rd",
    "sg:city":"Biloxi",
    "sg:classifiers":[
        {
            "category":"Organizations",
            "subcategory":"Religious Organization",
            "type":"Services"
        }
    ],
    "sg:phone":"+1 228 388 3077",
    "sg:postcode":"39532",
    "sg:province":"MS",
    "wof:name":"Bell C Glennis Rev",
    "wof:placetype":"venue"
},
  "geometry": {"coordinates":[-88.939905,30.442636],"type":"Point"}
}