{
  "type": "Feature",
  "properties": {
    "iso:country":"US",
    "sg:address":"1848 Long Branch Rd",
    "sg:city":"West",
    "sg:classifiers":[
        {
            "category":"Organizations",
            "subcategory":"Religious Organization",
            "type":"Services"
        }
    ],
    "sg:phone":"+1 662 967 2519",
    "sg:postcode":"39192",
    "sg:province":"MS",
    "sg:tags":[
        "church"
    ],
    "wof:name":"Long Branch Missionary Baptist",
    "wof:placetype":"venue"
},
  "geometry": {"coordinates":[-89.850347,33.198707],"type":"Point"}
}