{
  "type": "Feature",
  "properties": {
    "addr:full":"3210 Hwy 80 W Jackson MS 39204",
    "addr:housenumber":"3210",
    "addr:postcode":"39204",
    "addr:street":"Hwy 80 W",
    "iso:country":"US",
    "sg:address":"3210 Hwy 80 W",
    "sg:city":"Jackson",
    "sg:classifiers":[
        {
            "category":"Food & Beverages",
            "subcategory":"Groceries & Convenience Stores",
            "type":"Retail Goods"
        }
    ],
    "sg:phone":"+1 601 353 0784",
    "sg:postcode":"39204",
    "sg:province":"MS",
    "wof:name":"Food Queen Mini Mart",
    "wof:placetype":"venue"
},
  "geometry": {"coordinates":[-90.238232,32.296532],"type":"Point"}
}