{
  "type": "Feature",
  "properties": {
    "iso:country":"US",
    "sg:address":"1935 McCullough Blvd",
    "sg:city":"Tupelo",
    "sg:classifiers":[
        {
            "category":"Restaurant",
            "type":"Food & Drink"
        }
    ],
    "sg:phone":"+1 662 841 2111",
    "sg:postcode":"38801",
    "sg:province":"MS",
    "sg:tags":[
        "pizza"
    ],
    "wof:name":"Mama Mias Pizza",
    "wof:placetype":"venue"
},
  "geometry": {"coordinates":[-88.75858599999999,34.29331],"type":"Point"}
}