{
  "type": "Feature",
  "properties": {
    "addr:full":"3634 Sykes Park Dr Jackson MS 39212",
    "addr:housenumber":"3634",
    "addr:postcode":"39212",
    "addr:street":"Sykes Park Dr",
    "iso:country":"US",
    "sg:address":"3634 Sykes Park Dr",
    "sg:city":"Jackson",
    "sg:classifiers":[
        {
            "category":"Manufacturing",
            "subcategory":"Lumber",
            "type":"Manufacturing & Wholesale Goods"
        }
    ],
    "sg:phone":"+1 601 372 3090",
    "sg:postcode":"39212",
    "sg:province":"MS",
    "sg:tags":[
        "operation",
        "timber",
        "tract"
    ],
    "wof:name":"Ainsworth Hurbert",
    "wof:placetype":"venue"
},
  "geometry": {"coordinates":[-90.238867,32.247813],"type":"Point"}
}