{
  "type": "Feature",
  "properties": {
    "iso:country":"US",
    "sg:address":"6 Riverview Dr",
    "sg:city":"Vicksburg",
    "sg:classifiers":[
        {
            "category":"Building & Trades",
            "subcategory":"Construction",
            "type":"Services"
        }
    ],
    "sg:phone":"+1 601 218 5900",
    "sg:postcode":"39180",
    "sg:province":"MS",
    "sg:tags":[
        "general",
        "contractor"
    ],
    "wof:name":"Lee Group Inc",
    "wof:placetype":"venue"
},
  "geometry": {"coordinates":[-90.91289,32.27723],"type":"Point"}
}