{
  "type": "Feature",
  "properties": {
    "addr:full":"345 N Church Ave Louisville MS 39339",
    "addr:housenumber":"345",
    "addr:postcode":"39339",
    "addr:street":"N Church Ave",
    "iso:country":"US",
    "sg:address":"345 N Church Ave",
    "sg:city":"Louisville",
    "sg:classifiers":[
        {
            "category":"Restaurant",
            "type":"Food & Drink"
        }
    ],
    "sg:menulink":"http://www.allmenus.com/ms/louisville/133119-subway/menu/",
    "sg:phone":"+1 662 773 3379",
    "sg:postcode":"39339",
    "sg:province":"MS",
    "sg:tags":[
        "american",
        "sandwich"
    ],
    "wof:name":"Subway",
    "wof:placetype":"venue"
},
  "geometry": {"coordinates":[-89.05556300000001,33.127216],"type":"Point"}
}