{
  "type": "Feature",
  "properties": {
    "iso:country":"US",
    "sg:address":"50 W Lakeview Dr",
    "sg:city":"Clinton",
    "sg:classifiers":[
        {
            "category":"Insurance",
            "subcategory":"Hazard Insurance",
            "type":"Services"
        }
    ],
    "sg:phone":"+1 601 925 4990",
    "sg:postcode":"39056",
    "sg:province":"MS",
    "sg:tags":[
        "bond"
    ],
    "wof:name":"Clinton Bail Bonds",
    "wof:placetype":"venue"
},
  "geometry": {"coordinates":[-90.31131999999999,32.333951],"type":"Point"}
}