{
  "type": "Feature",
  "properties": {
    "addr:full":"1407 Pass Rd Gulfport MS 39501",
    "addr:housenumber":"1407",
    "addr:postcode":"39501",
    "addr:street":"Pass Rd",
    "iso:country":"US",
    "sg:address":"1407 Pass Rd",
    "sg:city":"Gulfport",
    "sg:classifiers":[
        {
            "category":"Autos & Motor Vehicles",
            "subcategory":"Auto Supplies",
            "type":"Retail Goods"
        }
    ],
    "sg:phone":"+1 228 867 6300",
    "sg:postcode":"39501",
    "sg:province":"MS",
    "sg:tags":[
        "repair",
        "r",
        "general",
        "automotive"
    ],
    "wof:name":"Japtec",
    "wof:placetype":"venue"
},
  "geometry": {"coordinates":[-89.079027,30.381992],"type":"Point"}
}