{
  "type": "Feature",
  "properties": {
    "addr:full":"716 S 2nd Ave Columbus MS 39701",
    "addr:housenumber":"716",
    "addr:postcode":"39701",
    "addr:street":"S 2Nd Ave",
    "iso:country":"US",
    "sg:address":"716 S 2nd Ave",
    "sg:city":"Columbus",
    "sg:classifiers":[
        {
            "category":"Retail",
            "subcategory":"Funeral Services",
            "type":"Services"
        }
    ],
    "sg:phone":"+1 662 328 4432",
    "sg:postcode":"39701",
    "sg:province":"MS",
    "sg:tags":[
        "director"
    ],
    "wof:name":"Memorial Funeral Home Svc",
    "wof:placetype":"venue"
},
  "geometry": {"coordinates":[-88.424367,33.494351],"type":"Point"}
}