{
  "type": "Feature",
  "properties": {
    "addr:full":"210 N 3rd Ave Cleveland MS 38732",
    "addr:housenumber":"210",
    "addr:postcode":"38732",
    "addr:street":"N 3Rd Ave",
    "iso:country":"US",
    "sg:address":"210 N 3rd Ave",
    "sg:city":"Cleveland",
    "sg:classifiers":[
        {
            "category":"Wholesale",
            "subcategory":"Durable Goods & Equipment",
            "type":"Manufacturing & Wholesale Goods"
        }
    ],
    "sg:phone":"+1 662 846 6002",
    "sg:postcode":"38732",
    "sg:province":"MS",
    "wof:name":"Gift World",
    "wof:placetype":"venue"
},
  "geometry": {"coordinates":[-90.731337,33.747487],"type":"Point"}
}