{
  "type": "Feature",
  "properties": {
    "iso:country":"US",
    "sg:address":"830 Pass Rd",
    "sg:city":"Gulfport",
    "sg:classifiers":[
        {
            "category":"Home & Garden",
            "subcategory":"Hardware",
            "type":"Retail Goods"
        },
        {
            "category":"Retail",
            "subcategory":"Repair Shop",
            "type":"Services"
        }
    ],
    "sg:phone":"+1 228 863 7871",
    "sg:postcode":"39501",
    "sg:province":"MS",
    "sg:tags":[
        "communications",
        "screen"
    ],
    "wof:name":"Cole's Screen & Glass Shop",
    "wof:placetype":"venue"
},
  "geometry": {"coordinates":[-89.06719200000001,30.387013],"type":"Point"}
}