{
  "type": "Feature",
  "properties": {
    "iso:country":"US",
    "sg:address":"211 Commerce Dr",
    "sg:city":"Brandon",
    "sg:classifiers":[
        {
            "category":"Building & Trades",
            "subcategory":"Construction",
            "type":"Services"
        }
    ],
    "sg:phone":"+1 601 825 8967",
    "sg:postcode":"39042",
    "sg:province":"MS",
    "sg:tags":[
        "residential",
        "general",
        "contractor"
    ],
    "wof:name":"Tommy Thrash Construction Co",
    "wof:placetype":"venue"
},
  "geometry": {"coordinates":[-90.026819,32.281743],"type":"Point"}
}