{
  "type": "Feature",
  "properties": {
    "addr:full":"730 Ridgewood Rd Ridgeland MS 39157",
    "addr:housenumber":"730",
    "addr:postcode":"39157",
    "addr:street":"Ridgewood Rd",
    "iso:country":"US",
    "sg:address":"730 Ridgewood Rd",
    "sg:city":"Ridgeland",
    "sg:classifiers":[
        {
            "category":"Health Services",
            "subcategory":"Doctor",
            "type":"Services"
        }
    ],
    "sg:phone":"+1 601 957 1560",
    "sg:postcode":"39157",
    "sg:province":"MS",
    "sg:tags":[
        "physician",
        "surgeon"
    ],
    "wof:name":"Rankin Neurology",
    "wof:placetype":"venue"
},
  "geometry": {"coordinates":[-90.14061599999999,32.405331],"type":"Point"}
}