{
  "type": "Feature",
  "properties": {
    "addr:full":"604 E Waldron St Corinth TN 38834",
    "addr:housenumber":"604",
    "addr:postcode":"38834",
    "addr:street":"E Waldron St",
    "iso:country":"US",
    "sg:address":"604 E Waldron St",
    "sg:city":"Corinth",
    "sg:classifiers":[
        {
            "category":"Shopping",
            "subcategory":"Pharmacy",
            "type":"Retail Goods"
        }
    ],
    "sg:phone":"+1 662 286 3361",
    "sg:postcode":"38834",
    "sg:province":"TN",
    "wof:name":"Borroum's Drug Store",
    "wof:placetype":"venue"
},
  "geometry": {"coordinates":[-88.51952900000001,34.934738],"type":"Point"}
}