{
  "type": "Feature",
  "properties": {
    "addr:full":"1010 Rogers St Laurel MS 39440",
    "addr:housenumber":"1010",
    "addr:postcode":"39440",
    "addr:street":"Rogers St",
    "iso:country":"US",
    "sg:address":"1010 Rogers St",
    "sg:city":"Laurel",
    "sg:classifiers":[
        {
            "category":"Professional",
            "subcategory":"Lawyer & Legal Services",
            "type":"Services"
        }
    ],
    "sg:phone":"+1 601 428 1726",
    "sg:postcode":"39440",
    "sg:province":"MS",
    "wof:name":"Sam Creel & Associates",
    "wof:placetype":"venue"
},
  "geometry": {"coordinates":[-89.138136,31.690309],"type":"Point"}
}