{
  "type": "Feature",
  "properties": {
    "iso:country":"US",
    "sg:address":"1221 Taylor St",
    "sg:city":"Corinth",
    "sg:classifiers":[
        {
            "category":"Wholesale",
            "subcategory":"Durable Goods & Equipment",
            "type":"Manufacturing & Wholesale Goods"
        }
    ],
    "sg:phone":"+1 662 286 8326",
    "sg:postcode":"38834",
    "sg:province":"MS",
    "wof:name":"Michael Mm & Co",
    "wof:placetype":"venue"
},
  "geometry": {"coordinates":[-88.51718700000001,34.94131],"type":"Point"}
}