{
  "type": "Feature",
  "properties": {
    "iso:country":"US",
    "sg:address":"200 E Government St",
    "sg:city":"Brandon",
    "sg:classifiers":[
        {
            "category":"Insurance",
            "subcategory":"Hazard Insurance",
            "type":"Services"
        }
    ],
    "sg:phone":"+1 601 825 3010",
    "sg:postcode":"39042",
    "sg:province":"MS",
    "sg:tags":[
        "bond"
    ],
    "wof:name":"A-AAA Bonding Co",
    "wof:placetype":"venue"
},
  "geometry": {"coordinates":[-89.98624,32.273109],"type":"Point"}
}