{
  "type": "Feature",
  "properties": {
    "addr:full":"4864 State Hwy 589 Sumrall MS 39482",
    "addr:housenumber":"4864",
    "addr:postcode":"39482",
    "addr:street":"State Hwy 589 Sumrall",
    "iso:country":"US",
    "sg:address":"4864 State Hwy 589",
    "sg:city":"Sumrall",
    "sg:classifiers":[
        {
            "category":"Health Services",
            "subcategory":"Doctor",
            "type":"Services"
        }
    ],
    "sg:phone":"+1 601 758 0150",
    "sg:postcode":"39482",
    "sg:province":"MS",
    "sg:tags":[
        "dentist"
    ],
    "wof:name":"Sumrall Dental Clinic",
    "wof:placetype":"venue"
},
  "geometry": {"coordinates":[-89.545817,31.415665],"type":"Point"}
}