{
  "type": "Feature",
  "properties": {
    "addr:full":"904 Morningside St Jackson MS 39202",
    "addr:housenumber":"904",
    "addr:postcode":"39202",
    "addr:street":"Morningside St",
    "iso:country":"US",
    "sg:address":"904 Morningside St",
    "sg:city":"Jackson",
    "sg:classifiers":[
        {
            "category":"Real Estate",
            "subcategory":"Real Estate Operator",
            "type":"Services"
        }
    ],
    "sg:phone":"+1 601 355 0100",
    "sg:postcode":"39202",
    "sg:province":"MS",
    "sg:tags":[
        "apartment"
    ],
    "wof:name":"Nejam A Waddell Properties",
    "wof:placetype":"venue"
},
  "geometry": {"coordinates":[-90.173536,32.310922],"type":"Point"}
}