{
  "type": "Feature",
  "properties": {
    "addr:full":"27999 US Hwy 49E Minter City MS 38944",
    "addr:postcode":"27999;38944",
    "addr:street":"Us Hwy 49E",
    "iso:country":"US",
    "sg:address":"27999 US Hwy 49E",
    "sg:city":"Minter City",
    "sg:classifiers":[
        {
            "category":"Food & Beverages",
            "subcategory":"Groceries & Convenience Stores",
            "type":"Retail Goods"
        }
    ],
    "sg:phone":"+1 662 658 4644",
    "sg:postcode":"38944",
    "sg:province":"MS",
    "sg:tags":[
        "grocer"
    ],
    "wof:name":"Minter City Grocery",
    "wof:placetype":"venue"
},
  "geometry": {"coordinates":[-90.31496300000001,33.734089],"type":"Point"}
}