{
  "type": "Feature",
  "properties": {
    "iso:country":"US",
    "sg:address":"311 E Roane Ave",
    "sg:city":"Eupora",
    "sg:classifiers":[
        {
            "category":"Shopping",
            "subcategory":"Bicycles & Sporting Goods",
            "type":"Retail Goods"
        }
    ],
    "sg:phone":"+1 662 258 2848",
    "sg:postcode":"39744",
    "sg:province":"MS",
    "sg:tags":[
        "equipment",
        "archery",
        "supply"
    ],
    "wof:name":"Pounds Sporting Goods",
    "wof:placetype":"venue"
},
  "geometry": {"coordinates":[-89.26091599999999,33.540625],"type":"Point"}
}