{
  "type": "Feature",
  "properties": {
    "iso:country":"US",
    "sg:address":"6335 Autumn Oaks Dr",
    "sg:city":"Olive Branch",
    "sg:classifiers":[
        {
            "category":"Banks & Credit Unions",
            "subcategory":"Bank",
            "type":"Services"
        }
    ],
    "sg:phone":"+1 662 893 1978",
    "sg:postcode":"38654",
    "sg:province":"MS",
    "sg:tags":[
        "loan",
        "real estate"
    ],
    "wof:name":"Mass Mutual Mortgage Co",
    "wof:placetype":"venue"
},
  "geometry": {"coordinates":[-89.87641000000001,34.951829],"type":"Point"}
}