{
  "type": "Feature",
  "properties": {
    "iso:country":"US",
    "sg:address":"601 Klein St",
    "sg:city":"Vicksburg",
    "sg:classifiers":[
        {
            "category":"Travel",
            "subcategory":"Hotels & Motels",
            "type":"Entertainment"
        }
    ],
    "sg:phone":"+1 601 636 7421",
    "sg:postcode":"39180",
    "sg:province":"MS",
    "sg:tags":[
        "breakfast",
        "operation",
        "bed",
        "accommodation"
    ],
    "wof:name":"Corners The Bed & Breakfast",
    "wof:placetype":"venue"
},
  "geometry": {"coordinates":[-90.88517299999999,32.341282],"type":"Point"}
}