{
  "type": "Feature",
  "properties": {
    "addr:full":"20304 Egypt Rd Aberdeen MS 39730",
    "addr:postcode":"20304;39730",
    "addr:street":"Egypt Rd",
    "iso:country":"US",
    "sg:address":"20304 Egypt Rd",
    "sg:city":"Aberdeen",
    "sg:classifiers":[
        {
            "category":"Food & Beverages",
            "subcategory":"Groceries & Convenience Stores",
            "type":"Retail Goods"
        }
    ],
    "sg:phone":"+1 662 319 6560",
    "sg:postcode":"39730",
    "sg:province":"MS",
    "wof:name":"Foard's Grocery",
    "wof:placetype":"venue"
},
  "geometry": {"coordinates":[-88.67116900000001,33.885299],"type":"Point"}
}