{
  "type": "Feature",
  "properties": {
    "iso:country":"US",
    "sg:address":"1010 Bankhead Dr",
    "sg:city":"Belzoni",
    "sg:classifiers":[
        {
            "category":"Social Services",
            "subcategory":"Child Care",
            "type":"Services"
        }
    ],
    "sg:phone":"+1 662 247 2400",
    "sg:postcode":"39038",
    "sg:province":"MS",
    "wof:name":"We Care",
    "wof:placetype":"venue"
},
  "geometry": {"coordinates":[-90.499256,33.192278],"type":"Point"}
}