{
  "type": "Feature",
  "properties": {
    "iso:country":"US",
    "sg:address":"2009 Resca de la Palma St",
    "sg:city":"Pascagoula",
    "sg:classifiers":[
        {
            "category":"Building & Trades",
            "subcategory":"Construction",
            "type":"Services"
        }
    ],
    "sg:phone":"+1 228 762 1064",
    "sg:postcode":"39567",
    "sg:province":"MS",
    "sg:tags":[
        "maker",
        "cabinet"
    ],
    "wof:name":"S W Krebs Woodworking Co",
    "wof:placetype":"venue"
},
  "geometry": {"coordinates":[-88.552667,30.353326],"type":"Point"}
}