{
  "type": "Feature",
  "properties": {
    "iso:country":"US",
    "sg:address":"1097 Stark Rd",
    "sg:city":"Starkville",
    "sg:classifiers":[
        {
            "category":"Home & Garden",
            "subcategory":"Building Materials",
            "type":"Retail Goods"
        }
    ],
    "sg:phone":"+1 662 323 9300",
    "sg:postcode":"39759",
    "sg:province":"MS",
    "sg:tags":[
        "glass",
        "window",
        "plate"
    ],
    "wof:name":"City Glass Co",
    "wof:placetype":"venue"
},
  "geometry": {"coordinates":[-88.845465,33.458402],"type":"Point"}
}