{
  "type": "Feature",
  "properties": {
    "iso:country":"US",
    "sg:address":"3211 Peyton Rd",
    "sg:city":"Coldwater",
    "sg:classifiers":[
        {
            "category":"Manufacturing",
            "subcategory":"Tools & Machinery",
            "type":"Manufacturing & Wholesale Goods"
        }
    ],
    "sg:phone":"+1 662 622 5883",
    "sg:postcode":"38618",
    "sg:province":"MS",
    "sg:tags":[
        "die",
        "maker"
    ],
    "wof:name":"Magnolia State Die",
    "wof:placetype":"venue"
},
  "geometry": {"coordinates":[-89.94472399999999,34.669682],"type":"Point"}
}