{
  "type": "Feature",
  "properties": {
    "addr:full":"2325 Greenway Dr Gautier MS 39553",
    "addr:housenumber":"2325",
    "addr:postcode":"39553",
    "addr:street":"Greenway Dr",
    "iso:country":"US",
    "sg:address":"2325 Greenway Dr",
    "sg:city":"Gautier",
    "sg:classifiers":[
        {
            "category":"Real Estate",
            "subcategory":"Real Estate Operator",
            "type":"Services"
        }
    ],
    "sg:phone":"+1 228 497 9159",
    "sg:postcode":"39553",
    "sg:province":"MS",
    "sg:tags":[
        "building",
        "nonresidential"
    ],
    "wof:name":"Coast Line Properties LLC",
    "wof:placetype":"venue"
},
  "geometry": {"coordinates":[-88.64866499999999,30.415955],"type":"Point"}
}