{
  "type": "Feature",
  "properties": {
    "iso:country":"US",
    "sg:address":"70 Bovina Dr",
    "sg:city":"Vicksburg",
    "sg:classifiers":[
        {
            "category":"Organizations",
            "subcategory":"Religious Organization",
            "type":"Services"
        }
    ],
    "sg:phone":"+1 601 631 0720",
    "sg:postcode":"39180",
    "sg:province":"MS",
    "wof:name":"Bovina United Methodist Church",
    "wof:placetype":"venue"
},
  "geometry": {"coordinates":[-90.73589699999999,32.350631],"type":"Point"}
}