{
  "type": "Feature",
  "properties": {
    "iso:country":"US",
    "sg:address":"2001 Hwy 332",
    "sg:city":"Grenada",
    "sg:classifiers":[
        {
            "category":"Retail",
            "subcategory":"Auto Repair",
            "type":"Services"
        }
    ],
    "sg:phone":"+1 662 226 5438",
    "sg:postcode":"38901",
    "sg:province":"MS",
    "sg:tags":[
        "repairing",
        "automobile"
    ],
    "wof:name":"Sullivan's Import Repair",
    "wof:placetype":"venue"
},
  "geometry": {"coordinates":[-89.79297200000001,33.822495],"type":"Point"}
}