{
  "type": "Feature",
  "properties": {
    "iso:country":"US",
    "sg:address":"7550 Hwy 178",
    "sg:city":"Olive Branch",
    "sg:classifiers":[
        {
            "category":"Retail",
            "subcategory":"Auto Repair",
            "type":"Services"
        }
    ],
    "sg:phone":"+1 662 895 2508",
    "sg:postcode":"38654",
    "sg:province":"MS",
    "sg:tags":[
        "body"
    ],
    "wof:name":"Olive Branch Motors Inc",
    "wof:placetype":"venue"
},
  "geometry": {"coordinates":[-89.85380000000001,34.979976],"type":"Point"}
}