{
  "type": "Feature",
  "properties": {
    "iso:country":"US",
    "sg:address":"4400 Nail Rd",
    "sg:city":"Olive Branch",
    "sg:classifiers":[
        {
            "category":"Real Estate",
            "subcategory":"Real Estate Agent",
            "type":"Services"
        }
    ],
    "sg:phone":"+1 662 895 8439",
    "sg:postcode":"38654",
    "sg:province":"MS",
    "wof:name":"All American Realty",
    "wof:placetype":"venue"
},
  "geometry": {"coordinates":[-89.91124600000001,34.947865],"type":"Point"}
}