{
  "type": "Feature",
  "properties": {
    "iso:country":"US",
    "sg:address":"5466 Grafton St",
    "sg:city":"Jackson",
    "sg:classifiers":[
        {
            "category":"Manufacturing",
            "subcategory":"Apparel",
            "type":"Manufacturing & Wholesale Goods"
        }
    ],
    "sg:phone":"+1 601 981 0282",
    "sg:postcode":"39206",
    "sg:province":"MS",
    "wof:name":"Ser Cap",
    "wof:placetype":"venue"
},
  "geometry": {"coordinates":[-90.157653,32.375144],"type":"Point"}
}