{
  "type": "Feature",
  "properties": {
    "iso:country":"US",
    "sg:address":"2471 Old Highway 61 N",
    "sg:city":"Tunica",
    "sg:classifiers":[
        {
            "category":"Education",
            "subcategory":"Vocational School",
            "type":"Public Place"
        },
        {
            "category":"Education",
            "subcategory":"School",
            "type":"Public Place"
        }
    ],
    "sg:phone":"+1 662 363 2051",
    "sg:postcode":"38676",
    "sg:province":"MS",
    "sg:tags":[
        "business"
    ],
    "wof:name":"Tunica Vocatinal School",
    "wof:placetype":"venue"
},
  "geometry": {"coordinates":[-90.378843,34.705443],"type":"Point"}
}