{
  "type": "Feature",
  "properties": {
    "iso:country":"US",
    "sg:address":"169 Martha Robinson Rd",
    "sg:city":"Ellisville",
    "sg:classifiers":[
        {
            "category":"Building & Trades",
            "subcategory":"Plumbing",
            "type":"Services"
        }
    ],
    "sg:phone":"+1 601 425 5486",
    "sg:postcode":"39437",
    "sg:province":"MS",
    "sg:tags":[
        "conditioning",
        "air",
        "system",
        "contractor"
    ],
    "wof:name":"Russell's Heating AC & Appl",
    "wof:placetype":"venue"
},
  "geometry": {"coordinates":[-89.252987,31.651455],"type":"Point"}
}