{
  "type": "Feature",
  "properties": {
    "addr:full":"950 W Broad St Monticello MS 39654",
    "addr:housenumber":"950",
    "addr:postcode":"39654",
    "addr:street":"W Broad St",
    "iso:country":"US",
    "sg:address":"950 W Broad St",
    "sg:city":"Monticello",
    "sg:classifiers":[
        {
            "category":"Banks & Credit Unions",
            "subcategory":"Bank",
            "type":"Services"
        }
    ],
    "sg:phone":"+1 601 587 0883",
    "sg:postcode":"39654",
    "sg:province":"MS",
    "sg:tags":[
        "loan"
    ],
    "wof:name":"Lawrence County Finance Inc",
    "wof:placetype":"venue"
},
  "geometry": {"coordinates":[-90.11319399999999,31.557197],"type":"Point"}
}