{
  "type": "Feature",
  "properties": {
    "iso:country":"US",
    "sg:address":"502 Cemetery Rd",
    "sg:city":"North Carrollton",
    "sg:classifiers":[
        {
            "category":"Health Services",
            "subcategory":"Doctor",
            "type":"Services"
        }
    ],
    "sg:phone":"+1 662 237 6243",
    "sg:postcode":"38947",
    "sg:province":"MS",
    "sg:tags":[
        "dentist"
    ],
    "wof:name":"Sanders Dental Clinic",
    "wof:placetype":"venue"
},
  "geometry": {"coordinates":[-89.91323,33.522101],"type":"Point"}
}