{
  "type": "Feature",
  "properties": {
    "iso:country":"US",
    "sg:address":"303 N College St",
    "sg:city":"Booneville",
    "sg:classifiers":[
        {
            "category":"Home & Garden",
            "subcategory":"Garden Supply",
            "type":"Retail Goods"
        }
    ],
    "sg:phone":"+1 662 728 5800",
    "sg:postcode":"38829",
    "sg:province":"MS",
    "sg:tags":[
        "center"
    ],
    "wof:name":"Chittom Garden Ctr",
    "wof:placetype":"venue"
},
  "geometry": {"coordinates":[-88.560631,34.657422],"type":"Point"}
}