{
  "type": "Feature",
  "properties": {
    "iso:country":"US",
    "sg:address":"1106 N 2nd St",
    "sg:city":"Booneville",
    "sg:classifiers":[
        {
            "category":"Banks & Credit Unions",
            "subcategory":"Bank",
            "type":"Services"
        }
    ],
    "sg:phone":"+1 662 728 4484",
    "sg:postcode":"38829",
    "sg:province":"MS",
    "sg:tags":[
        "loan"
    ],
    "wof:name":"Booneville Financial Svc",
    "wof:placetype":"venue"
},
  "geometry": {"coordinates":[-88.56034200000001,34.680134],"type":"Point"}
}