{
  "type": "Feature",
  "properties": {
    "iso:country":"US",
    "sg:address":"1270 River Rd",
    "sg:city":"Tunica",
    "sg:classifiers":[
        {
            "category":"Building & Trades",
            "subcategory":"Cleaning & Sanitation",
            "type":"Services"
        }
    ],
    "sg:phone":"+1 662 363 2867",
    "sg:postcode":"38676",
    "sg:province":"MS",
    "sg:tags":[
        "house"
    ],
    "wof:name":"Courtesy Cleaning Co",
    "wof:placetype":"venue"
},
  "geometry": {"coordinates":[-90.376733,34.68951],"type":"Point"}
}