{
  "type": "Feature",
  "properties": {
    "iso:country":"US",
    "sg:address":"707 Airport Rd",
    "sg:city":"Houston",
    "sg:classifiers":[
        {
            "category":"Real Estate",
            "subcategory":"Real Estate Operator",
            "type":"Services"
        }
    ],
    "sg:phone":"+1 662 456 5830",
    "sg:postcode":"38851",
    "sg:province":"MS",
    "sg:tags":[
        "apartment"
    ],
    "wof:name":"Pine View Apartments",
    "wof:placetype":"venue"
},
  "geometry": {"coordinates":[-89.01711299999999,33.888041],"type":"Point"}
}