{
  "type": "Feature",
  "properties": {
    "addr:full":"2300 E Pass Rd Gulfport MS 39507",
    "addr:housenumber":"2300",
    "addr:postcode":"39507",
    "addr:street":"E Pass Rd",
    "iso:country":"US",
    "sg:address":"2300 E Pass Rd",
    "sg:city":"Gulfport",
    "sg:classifiers":[
        {
            "category":"Personal",
            "subcategory":"Beauty Salon",
            "type":"Services"
        }
    ],
    "sg:phone":"+1 228 897 2166",
    "sg:postcode":"39507",
    "sg:province":"MS",
    "sg:tags":[
        "shop"
    ],
    "wof:name":"Rochelle's Beauty Shop",
    "wof:placetype":"venue"
},
  "geometry": {"coordinates":[-89.00305299999999,30.400627],"type":"Point"}
}