{
  "type": "Feature",
  "properties": {
    "iso:country":"US",
    "sg:address":"13 Oakland School Rd",
    "sg:city":"Corinth",
    "sg:classifiers":[
        {
            "category":"Organizations",
            "subcategory":"Community Association",
            "type":"Services"
        }
    ],
    "sg:phone":"+1 662 286 2204",
    "sg:postcode":"38834",
    "sg:province":"MS",
    "sg:tags":[
        "club"
    ],
    "wof:name":"Hillandale Country Club Inc",
    "wof:placetype":"venue"
},
  "geometry": {"coordinates":[-88.484939,34.908933],"type":"Point"}
}