{
  "type": "Feature",
  "properties": {
    "iso:country":"US",
    "sg:address":"826 S Church Ave",
    "sg:city":"Louisville",
    "sg:classifiers":[
        {
            "category":"Manufacturing",
            "subcategory":"Chemicals & Compounds",
            "type":"Manufacturing & Wholesale Goods"
        }
    ],
    "sg:phone":"+1 662 779 1300",
    "sg:postcode":"39339",
    "sg:province":"MS",
    "sg:tags":[
        "resin"
    ],
    "wof:name":"Georgia-Pacific Resins Inc",
    "wof:placetype":"venue"
},
  "geometry": {"coordinates":[-89.055617,33.111244],"type":"Point"}
}