{
  "type": "Feature",
  "properties": {
    "addr:full":"67 Co Rd 514 Corinth MS 38834",
    "addr:housenumber":"67",
    "addr:postcode":"38834",
    "addr:street":"Co Rd 514",
    "iso:country":"US",
    "sg:address":"67 Co Rd 514",
    "sg:city":"Corinth",
    "sg:classifiers":[
        {
            "category":"Real Estate",
            "subcategory":"Real Estate Operator",
            "type":"Services"
        }
    ],
    "sg:phone":"+1 662 462 5506",
    "sg:postcode":"38834",
    "sg:province":"MS",
    "sg:tags":[
        "farm",
        "property",
        "lessor",
        "soybean"
    ],
    "wof:name":"Donnie Martin",
    "wof:placetype":"venue"
},
  "geometry": {"coordinates":[-88.642658,34.828894],"type":"Point"}
}