{
  "type": "Feature",
  "properties": {
    "addr:full":"7435 Goodman Rd Olive Branch MS 38654",
    "addr:housenumber":"7435",
    "addr:postcode":"38654",
    "addr:street":"Goodman Rd",
    "iso:country":"US",
    "sg:address":"7435 Goodman Rd",
    "sg:city":"Olive Branch",
    "sg:classifiers":[
        {
            "category":"Professional",
            "subcategory":"Accounting & Tax Preparation",
            "type":"Services"
        }
    ],
    "sg:phone":"+1 662 893 7266",
    "sg:postcode":"38654",
    "sg:province":"MS",
    "sg:tags":[
        "return",
        "filing"
    ],
    "wof:name":"H & R Block Tax Svc",
    "wof:placetype":"venue"
},
  "geometry": {"coordinates":[-89.85660300000001,34.962125],"type":"Point"}
}