{
  "type": "Feature",
  "properties": {
    "addr:full":"4074 Northview Dr Jackson MS 39206",
    "addr:housenumber":"4074",
    "addr:postcode":"39206",
    "addr:street":"Northview Dr",
    "iso:country":"US",
    "sg:address":"4074 Northview Dr",
    "sg:city":"Jackson",
    "sg:classifiers":[
        {
            "category":"Recreation",
            "type":"Entertainment"
        }
    ],
    "sg:phone":"+1 601 981 3321",
    "sg:postcode":"39206",
    "sg:province":"MS",
    "sg:tags":[
        "concessionaire"
    ],
    "wof:name":"World's Finest Food",
    "wof:placetype":"venue"
},
  "geometry": {"coordinates":[-90.176132,32.352744],"type":"Point"}
}