{
  "type": "Feature",
  "properties": {
    "iso:country":"US",
    "sg:address":"2784 US Hwy 61",
    "sg:city":"Tunica",
    "sg:classifiers":[
        {
            "category":"Wholesale",
            "subcategory":"Chemicals & Plastics",
            "type":"Manufacturing & Wholesale Goods"
        }
    ],
    "sg:phone":"+1 662 363 3592",
    "sg:postcode":"38676",
    "sg:province":"MS",
    "wof:name":"Agro Distribution",
    "wof:placetype":"venue"
},
  "geometry": {"coordinates":[-90.374436,34.711723],"type":"Point"}
}