{
  "type": "Feature",
  "properties": {
    "iso:country":"US",
    "sg:address":"618 Jefferson St",
    "sg:city":"Natchez",
    "sg:classifiers":[
        {
            "category":"Autos & Motor Vehicles",
            "subcategory":"Fuel & Gas Station",
            "type":"Retail Goods"
        }
    ],
    "sg:phone":"+1 601 442 8777",
    "sg:postcode":"39120",
    "sg:province":"MS",
    "sg:tags":[
        "oil"
    ],
    "wof:name":"Old Standard Svc Ctr",
    "wof:placetype":"venue"
},
  "geometry": {"coordinates":[-91.399826,31.560416],"type":"Point"}
}