{
  "type": "Feature",
  "properties": {
    "addr:full":"6 Crestwood Dr Vicksburg MS 39180",
    "addr:housenumber":"6",
    "addr:postcode":"39180",
    "addr:street":"Crestwood Dr",
    "iso:country":"US",
    "sg:address":"6 Crestwood Dr",
    "sg:city":"Vicksburg",
    "sg:classifiers":[
        {
            "category":"Freight",
            "type":"Transportation"
        }
    ],
    "sg:phone":"+1 601 636 4372",
    "sg:postcode":"39180",
    "sg:province":"MS",
    "sg:tags":[
        "operator",
        "local",
        "trucking"
    ],
    "wof:name":"Ace Delivery Co",
    "wof:placetype":"venue"
},
  "geometry": {"coordinates":[-90.86865,32.29417],"type":"Point"}
}