{
  "type": "Feature",
  "properties": {
    "addr:full":"300 Main St Natchez MS 39120",
    "addr:housenumber":"300",
    "addr:postcode":"39120",
    "addr:street":"Main St",
    "iso:country":"US",
    "sg:address":"300 Main St",
    "sg:city":"Natchez",
    "sg:classifiers":[
        {
            "category":"Professional",
            "subcategory":"Employment Agencies",
            "type":"Services"
        }
    ],
    "sg:phone":"+1 601 445 4960",
    "sg:postcode":"39120",
    "sg:province":"MS",
    "sg:tags":[
        "help",
        "contractor"
    ],
    "wof:name":"Southern Employer Inc",
    "wof:placetype":"venue"
},
  "geometry": {"coordinates":[-91.40433899999999,31.56093],"type":"Point"}
}