{
  "type": "Feature",
  "properties": {
    "addr:full":"2391 US Hwy 51 Canton MS 39046",
    "addr:housenumber":"2391",
    "addr:postcode":"39046",
    "addr:street":"Us Hwy 51",
    "iso:country":"US",
    "sg:address":"2391 US Hwy 51",
    "sg:city":"Canton",
    "sg:classifiers":[
        {
            "category":"Freight",
            "type":"Transportation"
        }
    ],
    "sg:phone":"+1 601 859 4144",
    "sg:postcode":"39046",
    "sg:province":"MS",
    "sg:tags":[
        "commercial",
        "storage"
    ],
    "wof:name":"LJP Rentals",
    "wof:placetype":"venue"
},
  "geometry": {"coordinates":[-90.024286,32.641224],"type":"Point"}
}