{
  "type": "Feature",
  "properties": {
    "iso:country":"US",
    "sg:address":"6171 Co Rd 690",
    "sg:city":"Quitman",
    "sg:classifiers":[
        {
            "category":"Wholesale",
            "subcategory":"Electrical",
            "type":"Manufacturing & Wholesale Goods"
        }
    ],
    "sg:phone":"+1 601 693 1720",
    "sg:postcode":"39355",
    "sg:province":"MS",
    "sg:tags":[
        "alarm",
        "burglar",
        "system"
    ],
    "wof:name":"Prime Alert Security Systems",
    "wof:placetype":"venue"
},
  "geometry": {"coordinates":[-88.60856699999999,31.972926],"type":"Point"}
}