{
  "type": "Feature",
  "properties": {
    "iso:country":"US",
    "sg:address":"101 Mills St",
    "sg:city":"Brookhaven",
    "sg:classifiers":[
        {
            "category":"Health Services",
            "subcategory":"Nursing And Care Facility",
            "type":"Services"
        }
    ],
    "sg:phone":"+1 601 833 5608",
    "sg:postcode":"39601",
    "sg:province":"MS",
    "sg:tags":[
        "home",
        "convalescent"
    ],
    "wof:name":"Haven Hall Healthcare Ctr",
    "wof:placetype":"venue"
},
  "geometry": {"coordinates":[-90.44206,31.588829],"type":"Point"}
}