{
  "type": "Feature",
  "properties": {
    "iso:country":"US",
    "sg:address":"308 Railroad Ave",
    "sg:city":"Quitman",
    "sg:classifiers":[
        {
            "category":"Social Services",
            "subcategory":"Child Care",
            "type":"Services"
        }
    ],
    "sg:phone":"+1 601 776 3335",
    "sg:postcode":"39355",
    "sg:province":"MS",
    "sg:tags":[
        "day"
    ],
    "wof:name":"Toddlers Depot",
    "wof:placetype":"venue"
},
  "geometry": {"coordinates":[-88.73043,32.035579],"type":"Point"}
}