{
  "type": "Feature",
  "properties": {
    "iso:country":"US",
    "sg:address":"4317 Lakeland Dr",
    "sg:city":"Flowood",
    "sg:classifiers":[
        {
            "category":"Professional",
            "subcategory":"Employment Agencies",
            "type":"Services"
        }
    ],
    "sg:phone":"+1 601 420 9278",
    "sg:postcode":"39232",
    "sg:province":"MS",
    "sg:tags":[
        "opportunity"
    ],
    "wof:name":"Ablest Staffing Svc",
    "wof:placetype":"venue"
},
  "geometry": {"coordinates":[-90.07947799999999,32.339025],"type":"Point"}
}