{
  "type": "Feature",
  "properties": {
    "iso:country":"US",
    "sg:address":"18 C E Morrison Ln",
    "sg:city":"Wiggins",
    "sg:classifiers":[
        {
            "category":"Building & Trades",
            "subcategory":"Construction",
            "type":"Services"
        }
    ],
    "sg:phone":"+1 601 928 5289",
    "sg:postcode":"39577",
    "sg:province":"MS",
    "sg:tags":[
        "house",
        "nonresidential"
    ],
    "wof:name":"Morrison and Sons Construction",
    "wof:placetype":"venue"
},
  "geometry": {"coordinates":[-89.251971,30.987085],"type":"Point"}
}