{
  "type": "Feature",
  "properties": {
    "iso:country":"US",
    "sg:address":"1062 Cochran Rd",
    "sg:city":"Belden",
    "sg:classifiers":[
        {
            "category":"Retail",
            "subcategory":"Repair Shop",
            "type":"Services"
        }
    ],
    "sg:phone":"+1 662 840 7930",
    "sg:postcode":"38826",
    "sg:province":"MS",
    "sg:tags":[
        "conveyor",
        "installation",
        "belt"
    ],
    "wof:name":"Bekt Tech Inc",
    "wof:placetype":"venue"
},
  "geometry": {"coordinates":[-88.845787,34.319204],"type":"Point"}
}