{
  "type": "Feature",
  "properties": {
    "iso:country":"US",
    "sg:address":"130 Hwy 45 S",
    "sg:city":"West Point",
    "sg:classifiers":[
        {
            "category":"Manufacturing",
            "subcategory":"Tools & Machinery",
            "type":"Manufacturing & Wholesale Goods"
        },
        {
            "category":"Wholesale",
            "subcategory":"Auto Parts",
            "type":"Manufacturing & Wholesale Goods"
        }
    ],
    "sg:phone":"+1 662 494 4543",
    "sg:postcode":"39773",
    "sg:province":"MS",
    "sg:tags":[
        "machine",
        "shop",
        "supply"
    ],
    "wof:name":"Jim's Auto Parts Inc",
    "wof:placetype":"venue"
},
  "geometry": {"coordinates":[-88.658991,33.606654],"type":"Point"}
}