{
  "type": "Feature",
  "properties": {
    "addr:full":"113 Westwood Dr Senatobia MS 38668",
    "addr:housenumber":"113",
    "addr:postcode":"38668",
    "addr:street":"Westwood Dr",
    "iso:country":"US",
    "sg:address":"113 Westwood Dr",
    "sg:city":"Senatobia",
    "sg:classifiers":[
        {
            "category":"Retail",
            "subcategory":"Repair Shop",
            "type":"Services"
        }
    ],
    "sg:phone":"+1 662 562 7314",
    "sg:postcode":"38668",
    "sg:province":"MS",
    "wof:name":"Windy Hill Farriers",
    "wof:placetype":"venue"
},
  "geometry": {"coordinates":[-89.996759,34.621916],"type":"Point"}
}