{
  "type": "Feature",
  "properties": {
    "iso:country":"US",
    "sg:address":"227 Devereaux Dr",
    "sg:city":"Natchez",
    "sg:classifiers":[
        {
            "category":"Restaurant",
            "type":"Food & Drink"
        }
    ],
    "sg:menulink":"http://www.allmenus.com/ms/roxie/72907-pizza-hut/menu/",
    "sg:phone":"+1 601 442 2221",
    "sg:postcode":"39120",
    "sg:province":"MS",
    "sg:tags":[
        "american",
        "pizza"
    ],
    "wof:name":"Pizza Hut",
    "wof:placetype":"venue"
},
  "geometry": {"coordinates":[-91.374044,31.55799],"type":"Point"}
}