{
  "type": "Feature",
  "properties": {
    "addr:full":"1243 S Gallatin St Jackson MS 39201",
    "addr:housenumber":"1243",
    "addr:postcode":"39201",
    "addr:street":"S Gallatin St",
    "iso:country":"US",
    "sg:address":"1243 S Gallatin St",
    "sg:city":"Jackson",
    "sg:classifiers":[
        {
            "category":"Manufacturing",
            "subcategory":"Metals",
            "type":"Manufacturing & Wholesale Goods"
        }
    ],
    "sg:phone":"+1 601 352 8207",
    "sg:postcode":"39201",
    "sg:province":"MS",
    "sg:tags":[
        "fabricator",
        "sheet"
    ],
    "wof:name":"Carl's Sheet Metal Shop",
    "wof:placetype":"venue"
},
  "geometry": {"coordinates":[-90.19295700000001,32.286857],"type":"Point"}
}