{
  "type": "Feature",
  "properties": {
    "iso:country":"US",
    "sg:address":"1442 Fire Station Rd",
    "sg:city":"Starkville",
    "sg:classifiers":[
        {
            "category":"Building & Trades",
            "subcategory":"Plumbing",
            "type":"Services"
        }
    ],
    "sg:phone":"+1 662 323 1543",
    "sg:postcode":"39759",
    "sg:province":"MS",
    "sg:tags":[
        "heating",
        "contractor"
    ],
    "wof:name":"Hollis Brothers Air Cond & Svc",
    "wof:placetype":"venue"
},
  "geometry": {"coordinates":[-88.818957,33.487459],"type":"Point"}
}