{
  "type": "Feature",
  "properties": {
    "addr:full":"3440 Halls Ferry Rd Vicksburg MS 39180",
    "addr:housenumber":"3440",
    "addr:postcode":"39180",
    "addr:street":"Halls Ferry Rd",
    "iso:country":"US",
    "sg:address":"3440 Halls Ferry Rd",
    "sg:city":"Vicksburg",
    "sg:classifiers":[
        {
            "category":"Shopping",
            "subcategory":"Used Merchandise",
            "type":"Retail Goods"
        },
        {
            "category":"Shopping",
            "subcategory":"Clothing, Apparel, & Fashions",
            "type":"Retail Goods"
        }
    ],
    "sg:phone":"+1 601 636 0832",
    "sg:postcode":"39180",
    "sg:province":"MS",
    "sg:tags":[
        "wear",
        "furniture"
    ],
    "wof:name":"Treasure Chest",
    "wof:placetype":"venue"
},
  "geometry": {"coordinates":[-90.876732,32.315873],"type":"Point"}
}