{
  "type": "Feature",
  "properties": {
    "addr:full":"1532 Liberty Rd Flowood MS 39232",
    "addr:housenumber":"1532",
    "addr:postcode":"39232",
    "addr:street":"Liberty Rd",
    "iso:country":"US",
    "sg:address":"1532 Liberty Rd",
    "sg:city":"Flowood",
    "sg:classifiers":[
        {
            "category":"Building & Trades",
            "subcategory":"Landscaping Services",
            "type":"Services"
        }
    ],
    "sg:phone":"+1 601 936 2559",
    "sg:postcode":"39232",
    "sg:province":"MS",
    "sg:tags":[
        "lawn",
        "maintenance",
        "grounds"
    ],
    "wof:name":"A Yard Of The Month",
    "wof:placetype":"venue"
},
  "geometry": {"coordinates":[-90.09165299999999,32.341769],"type":"Point"}
}