{
  "type": "Feature",
  "properties": {
    "addr:full":"3688 Veteran Memorial Dr Hattiesburg MS 39401",
    "addr:housenumber":"3688",
    "addr:postcode":"39401",
    "addr:street":"Veteran Memorial Dr",
    "iso:country":"US",
    "sg:address":"3688 Veteran Memorial Dr",
    "sg:city":"Hattiesburg",
    "sg:classifiers":[
        {
            "category":"Building & Trades",
            "subcategory":"Construction",
            "type":"Services"
        }
    ],
    "sg:phone":"+1 601 554 7525",
    "sg:postcode":"39401",
    "sg:province":"MS",
    "sg:tags":[
        "development",
        "medical",
        "center",
        "ho"
    ],
    "wof:name":"Southern Dev Resources LLC",
    "wof:placetype":"venue"
},
  "geometry": {"coordinates":[-89.330832,31.27115],"type":"Point"}
}