{
  "type": "Feature",
  "properties": {
    "addr:full":"875 Riverside Dr Jackson MS 39202",
    "addr:housenumber":"875",
    "addr:postcode":"39202",
    "addr:street":"Riverside Dr",
    "iso:country":"US",
    "sg:address":"875 Riverside Dr",
    "sg:city":"Jackson",
    "sg:classifiers":[
        {
            "category":"Social Services",
            "type":"Services"
        }
    ],
    "sg:phone":"+1 601 353 5442",
    "sg:postcode":"39202",
    "sg:province":"MS",
    "sg:tags":[
        "organization",
        "welfare"
    ],
    "sg:website":"www.mississippi-redcross.org",
    "wof:name":"American Red Cross",
    "wof:placetype":"venue"
},
  "geometry": {"coordinates":[-90.17546400000001,32.323343],"type":"Point"}
}