{
  "type": "Feature",
  "properties": {
    "addr:full":"132 Main St Raleigh MS 39120",
    "addr:housenumber":"132",
    "addr:postcode":"39120",
    "addr:street":"Main St",
    "iso:country":"US",
    "sg:address":"132 Main St",
    "sg:city":"Raleigh",
    "sg:classifiers":[
        {
            "category":"Shopping",
            "subcategory":"Florist",
            "type":"Retail Goods"
        }
    ],
    "sg:phone":"+1 601 782 4527",
    "sg:postcode":"39120",
    "sg:province":"MS",
    "wof:name":"Raleigh Flower & Gift Shop",
    "wof:placetype":"venue"
},
  "geometry": {"coordinates":[-91.405883,31.561869],"type":"Point"}
}