{
  "type": "Feature",
  "properties": {
    "iso:country":"US",
    "sg:address":"2111 25th Ave",
    "sg:city":"Gulfport",
    "sg:classifiers":[
        {
            "category":"Professional",
            "subcategory":"Lawyer & Legal Services",
            "type":"Services"
        }
    ],
    "sg:phone":"+1 228 865 0313",
    "sg:postcode":"39501",
    "sg:province":"MS",
    "sg:tags":[
        "attorney"
    ],
    "wof:name":"Michael W Crosby",
    "wof:placetype":"venue"
},
  "geometry": {"coordinates":[-89.093163,30.376587],"type":"Point"}
}