{
  "type": "Feature",
  "properties": {
    "addr:full":"224 W Railroad St Long Beach MS 39560",
    "addr:housenumber":"224",
    "addr:postcode":"39560",
    "addr:street":"W Railroad St",
    "iso:country":"US",
    "sg:address":"224 W Railroad St",
    "sg:city":"Long Beach",
    "sg:classifiers":[
        {
            "category":"Insurance",
            "subcategory":"Insurance Agent",
            "type":"Services"
        }
    ],
    "sg:phone":"+1 228 863 8535",
    "sg:postcode":"39560",
    "sg:province":"MS",
    "wof:name":"State Farm Insurance",
    "wof:placetype":"venue"
},
  "geometry": {"coordinates":[-89.15433299999999,30.349957],"type":"Point"}
}