{
  "type": "Feature",
  "properties": {
    "addr:full":"449 Co Rd 380 Calhoun City MS 38916",
    "addr:housenumber":"449;380",
    "addr:postcode":"38916",
    "addr:street":"Co Rd",
    "iso:country":"US",
    "sg:address":"449 Co Rd 380",
    "sg:city":"Calhoun City",
    "sg:classifiers":[
        {
            "category":"Freight",
            "type":"Transportation"
        }
    ],
    "sg:phone":"+1 662 637 2318",
    "sg:postcode":"38916",
    "sg:province":"MS",
    "sg:tags":[
        "operator",
        "local",
        "trucking"
    ],
    "wof:name":"C & C Trucking",
    "wof:placetype":"venue"
},
  "geometry": {"coordinates":[-89.443721,33.758174],"type":"Point"}
}