{
  "type": "Feature",
  "properties": {
    "iso:country":"US",
    "sg:address":"200 S Seashore Ave",
    "sg:city":"Long Beach",
    "sg:classifiers":[
        {
            "category":"Professional",
            "subcategory":"Engineering",
            "type":"Services"
        }
    ],
    "sg:phone":"+1 228 255 4544",
    "sg:postcode":"39560",
    "sg:province":"MS",
    "wof:name":"Lapitsky Industrial Cons",
    "wof:placetype":"venue"
},
  "geometry": {"coordinates":[-89.17457400000001,30.341179],"type":"Point"}
}