{
  "type": "Feature",
  "properties": {
    "iso:country":"US",
    "sg:address":"11367 Co Rd 511",
    "sg:city":"Quitman",
    "sg:classifiers":[
        {
            "category":"Organizations",
            "subcategory":"Religious Organization",
            "type":"Services"
        }
    ],
    "sg:phone":"+1 601 776 0308",
    "sg:postcode":"39355",
    "sg:province":"MS",
    "sg:tags":[
        "church"
    ],
    "wof:name":"Mt Pisgah Baptist Church",
    "wof:placetype":"venue"
},
  "geometry": {"coordinates":[-88.49020299999999,31.950861],"type":"Point"}
}