{
  "type": "Feature",
  "properties": {
    "iso:country":"US",
    "sg:address":"18473 Lake Ridge Dr",
    "sg:city":"Saucier",
    "sg:classifiers":[
        {
            "category":"Wholesale",
            "subcategory":"Construction Materials",
            "type":"Manufacturing & Wholesale Goods"
        },
        {
            "category":"Building & Trades",
            "subcategory":"Construction",
            "type":"Services"
        }
    ],
    "sg:phone":"+1 228 539 2778",
    "sg:postcode":"39574",
    "sg:province":"MS",
    "sg:tags":[
        "fence",
        "contractor"
    ],
    "wof:name":"American Fence & Deck Inc",
    "wof:placetype":"venue"
},
  "geometry": {"coordinates":[-89.17689300000001,30.55549],"type":"Point"}
}