{
  "type": "Feature",
  "properties": {
    "addr:full":"6174 Elmore Rd Southaven MS 38671",
    "addr:housenumber":"6174",
    "addr:postcode":"38671",
    "addr:street":"Elmore Rd",
    "iso:country":"US",
    "sg:address":"6174 Elmore Rd",
    "sg:city":"Southaven",
    "sg:classifiers":[
        {
            "category":"Building & Trades",
            "subcategory":"Landscaping Services",
            "type":"Services"
        }
    ],
    "sg:phone":"+1 662 349 0543",
    "sg:postcode":"38671",
    "sg:province":"MS",
    "wof:name":"Superior Lawn Care",
    "wof:placetype":"venue"
},
  "geometry": {"coordinates":[-89.980982,34.951249],"type":"Point"}
}