{
  "type": "Feature",
  "properties": {
    "addr:full":"311 Carroll Ave Bay St Louis MS 39520",
    "addr:housenumber":"311",
    "addr:postcode":"39520",
    "addr:street":"Carroll Ave",
    "iso:country":"US",
    "sg:address":"311 Carroll Ave",
    "sg:city":"Bay St Louis",
    "sg:classifiers":[
        {
            "category":"Professional",
            "subcategory":"Research",
            "type":"Services"
        },
        {
            "category":"Manufacturing",
            "subcategory":"Printing",
            "type":"Manufacturing & Wholesale Goods"
        }
    ],
    "sg:phone":"+1 228 467 7348",
    "sg:postcode":"39520",
    "sg:province":"MS",
    "sg:tags":[
        "publisher",
        "commercial",
        "nonphysical"
    ],
    "wof:name":"Richardson's Land Surveys",
    "wof:placetype":"venue"
},
  "geometry": {"coordinates":[-89.33293999999999,30.315814],"type":"Point"}
}