{
  "type": "Feature",
  "properties": {
    "addr:full":"41 Torbrook Cove Southaven MS 38671",
    "addr:housenumber":"41",
    "addr:postcode":"38671",
    "addr:street":"Torbrook Cove",
    "iso:country":"US",
    "sg:address":"41 Torbrook Cove",
    "sg:city":"Southaven",
    "sg:classifiers":[
        {
            "category":"Shopping",
            "subcategory":"Gifts & Souvenirs",
            "type":"Retail Goods"
        }
    ],
    "sg:phone":"+1 662 393 5000",
    "sg:postcode":"38671",
    "sg:province":"MS",
    "sg:tags":[
        "balloon",
        "artist"
    ],
    "wof:name":"Clown Around Town",
    "wof:placetype":"venue"
},
  "geometry": {"coordinates":[-89.9907,34.980643],"type":"Point"}
}