{
  "type": "Feature",
  "properties": {
    "addr:full":"833 Hwy 12 W Starkville MS 39759",
    "addr:housenumber":"833",
    "addr:postcode":"39759",
    "addr:street":"Hwy 12 W",
    "iso:country":"US",
    "sg:address":"833 Hwy 12 W",
    "sg:city":"Starkville",
    "sg:classifiers":[
        {
            "category":"Food & Beverages",
            "subcategory":"Groceries & Convenience Stores",
            "type":"Retail Goods"
        }
    ],
    "sg:phone":"+1 662 323 8201",
    "sg:postcode":"39759",
    "sg:province":"MS",
    "wof:name":"Sprint Mart",
    "wof:placetype":"venue"
},
  "geometry": {"coordinates":[-88.83953,33.448597],"type":"Point"}
}