{
  "type": "Feature",
  "properties": {
    "addr:full":"16236 McLean Rd Hurley MS 39567",
    "addr:housenumber":"16236",
    "addr:postcode":"39567",
    "addr:street":"Mclean Rd",
    "iso:country":"US",
    "sg:address":"16236 McLean Rd",
    "sg:city":"Hurley",
    "sg:classifiers":[
        {
            "category":"Organizations",
            "subcategory":"Religious Organization",
            "type":"Services"
        }
    ],
    "sg:phone":"+1 228 588 2151",
    "sg:postcode":"39567",
    "sg:province":"MS",
    "sg:tags":[
        "church"
    ],
    "wof:name":"Miracle Temple Holiness Church",
    "wof:placetype":"venue"
},
  "geometry": {"coordinates":[-88.55701500000001,30.579006],"type":"Point"}
}