{
  "type": "Feature",
  "properties": {
    "iso:country":"US",
    "sg:address":"694 Hwy 45 S",
    "sg:city":"State Line",
    "sg:classifiers":[
        {
            "category":"Restaurant",
            "type":"Food & Drink"
        }
    ],
    "sg:phone":"+1 601 848 7721",
    "sg:postcode":"39362",
    "sg:province":"MS",
    "wof:name":"Jordan's Fish Camp",
    "wof:placetype":"venue"
},
  "geometry": {"coordinates":[-88.49253400000001,31.493512],"type":"Point"}
}