{
  "type": "Feature",
  "properties": {
    "iso:country":"US",
    "sg:address":"6360 I- 55 N",
    "sg:city":"Jackson",
    "sg:classifiers":[
        {
            "category":"Professional",
            "subcategory":"Accounting & Tax Preparation",
            "type":"Services"
        }
    ],
    "sg:phone":"+1 601 956 6040",
    "sg:postcode":"39211",
    "sg:province":"MS",
    "sg:tags":[
        "accountant"
    ],
    "wof:name":"Collins & Corbin LTD",
    "wof:placetype":"venue"
},
  "geometry": {"coordinates":[-90.144276,32.398519],"type":"Point"}
}