{
  "type": "Feature",
  "properties": {
    "addr:full":"120 Kellis Store Rd Preston MS 39354",
    "addr:housenumber":"120",
    "addr:postcode":"39354",
    "addr:street":"Kellis Store Rd",
    "iso:country":"US",
    "sg:address":"120 Kellis Store Rd",
    "sg:city":"Preston",
    "sg:classifiers":[
        {
            "category":"Organizations",
            "subcategory":"Religious Organization",
            "type":"Services"
        }
    ],
    "sg:phone":"+1 601 677 3550",
    "sg:postcode":"39354",
    "sg:province":"MS",
    "wof:name":"United Methodist Church Inc",
    "wof:placetype":"venue"
},
  "geometry": {"coordinates":[-88.813186,32.85619],"type":"Point"}
}