{
  "type": "Feature",
  "properties": {
    "addr:full":"407 Court St Waynesboro MS 39367",
    "addr:housenumber":"407",
    "addr:postcode":"39367",
    "addr:street":"Court St",
    "iso:country":"US",
    "sg:address":"407 Court St",
    "sg:city":"Waynesboro",
    "sg:classifiers":[
        {
            "category":"Autos & Motor Vehicles",
            "subcategory":"Auto Supplies",
            "type":"Retail Goods"
        }
    ],
    "sg:phone":"+1 601 735 5795",
    "sg:postcode":"39367",
    "sg:province":"MS",
    "wof:name":"A & M Tire & Auto Service",
    "wof:placetype":"venue"
},
  "geometry": {"coordinates":[-88.65187,31.673003],"type":"Point"}
}