{
  "type": "Feature",
  "properties": {
    "iso:country":"US",
    "sg:address":"3831 Main St",
    "sg:city":"Moss Point",
    "sg:classifiers":[
        {
            "category":"Restaurant",
            "type":"Food & Drink"
        }
    ],
    "sg:menulink":"http://www.allmenus.com/ms/moss-point/13159-churchs-chicken/menu/",
    "sg:phone":"+1 228 475 8395",
    "sg:postcode":"39563",
    "sg:province":"MS",
    "sg:tags":[
        "chicken",
        "wing"
    ],
    "wof:name":"Church's Chicken",
    "wof:placetype":"venue"
},
  "geometry": {"coordinates":[-88.538121,30.396757],"type":"Point"}
}