{
  "type": "Feature",
  "properties": {
    "iso:country":"US",
    "sg:address":"2052 Old Industrial Rd",
    "sg:city":"Mccomb",
    "sg:classifiers":[
        {
            "category":"Organizations",
            "subcategory":"Religious Organization",
            "type":"Services"
        }
    ],
    "sg:phone":"+1 601 684 1797",
    "sg:postcode":"39648",
    "sg:province":"MS",
    "sg:tags":[
        "church"
    ],
    "wof:name":"True Gospel Missionary Baptist",
    "wof:placetype":"venue"
},
  "geometry": {"coordinates":[-90.43816,31.20687],"type":"Point"}
}