{
  "type": "Feature",
  "properties": {
    "iso:country":"US",
    "sg:address":"912 S 11th Ave",
    "sg:city":"Columbus",
    "sg:classifiers":[
        {
            "category":"Professional",
            "type":"Services"
        }
    ],
    "sg:phone":"+1 662 328 5722",
    "sg:postcode":"39701",
    "sg:province":"MS",
    "sg:tags":[
        "establishment"
    ],
    "wof:name":"Hutchinson Cottage",
    "wof:placetype":"venue"
},
  "geometry": {"coordinates":[-88.42116,33.485015],"type":"Point"}
}