{
  "type": "Feature",
  "properties": {
    "addr:full":"942 Moselle-Seminary Rd Moselle MS 39459",
    "addr:housenumber":"942",
    "addr:postcode":"39459",
    "addr:street":"Moselle-Seminary Rd",
    "iso:country":"US",
    "sg:address":"942 Moselle-Seminary Rd",
    "sg:city":"Moselle",
    "sg:classifiers":[
        {
            "category":"Organizations",
            "subcategory":"Religious Organization",
            "type":"Services"
        }
    ],
    "sg:phone":"+1 601 752 6366",
    "sg:postcode":"39459",
    "sg:province":"MS",
    "sg:tags":[
        "church"
    ],
    "wof:name":"Fairfield Baptist Church",
    "wof:placetype":"venue"
},
  "geometry": {"coordinates":[-89.354928,31.541382],"type":"Point"}
}