{
  "type": "Feature",
  "properties": {
    "addr:full":"325 Lynwood Cir Long Beach MS 39560",
    "addr:housenumber":"325",
    "addr:postcode":"39560",
    "addr:street":"Lynwood Cir",
    "iso:country":"US",
    "sg:address":"325 Lynwood Cir",
    "sg:city":"Long Beach",
    "sg:classifiers":[
        {
            "category":"Shopping",
            "subcategory":"Pharmacy",
            "type":"Retail Goods"
        }
    ],
    "sg:phone":"+1 228 864 4079",
    "sg:postcode":"39560",
    "sg:province":"MS",
    "sg:tags":[
        "drug",
        "store"
    ],
    "wof:name":"T D Drugs Inc",
    "wof:placetype":"venue"
},
  "geometry": {"coordinates":[-89.162982,30.357213],"type":"Point"}
}