{
  "type": "Feature",
  "properties": {
    "addr:full":"1 Main St Taylor MS 38620",
    "addr:housenumber":"1",
    "addr:postcode":"38620",
    "addr:street":"Main St",
    "iso:country":"US",
    "sg:address":"1 Main St",
    "sg:city":"Taylor",
    "sg:classifiers":[
        {
            "category":"Government",
            "subcategory":"Post Office",
            "type":"Public Place"
        }
    ],
    "sg:phone":"+1 662 234 1817",
    "sg:postcode":"38620",
    "sg:province":"MS",
    "wof:name":"US Post Office",
    "wof:placetype":"venue"
},
  "geometry": {"coordinates":[-89.950614,34.237686],"type":"Point"}
}