{
  "type": "Feature",
  "properties": {
    "iso:country":"US",
    "sg:address":"701 W Main St",
    "sg:city":"Tupelo",
    "sg:classifiers":[
        {
            "category":"Shopping",
            "subcategory":"Discount & Variety Stores",
            "type":"Retail Goods"
        },
        {
            "category":"Shopping",
            "subcategory":"Department Store",
            "type":"Retail Goods"
        }
    ],
    "sg:phone":"+1 662 841 2819",
    "sg:postcode":"38804",
    "sg:province":"MS",
    "sg:tags":[
        "shop"
    ],
    "wof:name":"Family Dollar Stores",
    "wof:placetype":"venue"
},
  "geometry": {"coordinates":[-88.71554999999999,34.257276],"type":"Point"}
}