{
  "type": "Feature",
  "properties": {
    "addr:full":"931 Hwy 80 E Clinton MS 39056",
    "addr:housenumber":"931",
    "addr:postcode":"39056",
    "addr:street":"Hwy 80 E",
    "iso:country":"US",
    "sg:address":"931 Hwy 80 E",
    "sg:city":"Clinton",
    "sg:classifiers":[
        {
            "category":"Recreation",
            "type":"Entertainment"
        }
    ],
    "sg:phone":"+1 601 924 6500",
    "sg:postcode":"39056",
    "sg:province":"MS",
    "sg:tags":[
        "skating",
        "rink"
    ],
    "wof:name":"Funtime Skateland Clinton Inc",
    "wof:placetype":"venue"
},
  "geometry": {"coordinates":[-90.297129,32.325134],"type":"Point"}
}