{
  "type": "Feature",
  "properties": {
    "addr:full":"51 Adams Dr Fulton MS 38843",
    "addr:housenumber":"51",
    "addr:postcode":"38843",
    "addr:street":"Adams Dr",
    "iso:country":"US",
    "sg:address":"51 Adams Dr",
    "sg:city":"Fulton",
    "sg:classifiers":[
        {
            "category":"Restaurant",
            "type":"Food & Drink"
        }
    ],
    "sg:menulink":"http://www.allmenus.com/ms/clay/211691-mcdonalds/menu/",
    "sg:phone":"+1 662 862 7696",
    "sg:postcode":"38843",
    "sg:province":"MS",
    "sg:tags":[
        "burger",
        "american"
    ],
    "wof:name":"McDonald's",
    "wof:placetype":"venue"
},
  "geometry": {"coordinates":[-88.32610099999999,34.31685],"type":"Point"}
}