{
  "type": "Feature",
  "properties": {
    "iso:country":"US",
    "sg:address":"7643 Hwy 178",
    "sg:city":"Olive Branch",
    "sg:classifiers":[
        {
            "category":"Local Transit",
            "type":"Transportation"
        }
    ],
    "sg:phone":"+1 662 890 1784",
    "sg:postcode":"38654",
    "sg:province":"MS",
    "wof:name":"C P Express",
    "wof:placetype":"venue"
},
  "geometry": {"coordinates":[-89.85630999999999,34.981009],"type":"Point"}
}