{
  "type": "Feature",
  "properties": {
    "addr:full":"1425 E Main St Tupelo MS 38804",
    "addr:housenumber":"1425",
    "addr:postcode":"38804",
    "addr:street":"E Main St",
    "iso:country":"US",
    "sg:address":"1425 E Main St",
    "sg:city":"Tupelo",
    "sg:classifiers":[
        {
            "category":"Shopping",
            "subcategory":"Gifts & Souvenirs",
            "type":"Retail Goods"
        }
    ],
    "sg:phone":"+1 662 690 6111",
    "sg:postcode":"38804",
    "sg:province":"MS",
    "sg:tags":[
        "collectible"
    ],
    "wof:name":"R & A Sports",
    "wof:placetype":"venue"
},
  "geometry": {"coordinates":[-88.67549,34.257591],"type":"Point"}
}