{
  "type": "Feature",
  "properties": {
    "iso:country":"US",
    "sg:address":"707 US Hwy 82 E",
    "sg:city":"Indianola",
    "sg:classifiers":[
        {
            "category":"Insurance",
            "subcategory":"Insurance Agent",
            "type":"Services"
        }
    ],
    "sg:phone":"+1 662 455 1009",
    "sg:postcode":"38751",
    "sg:province":"MS",
    "sg:tags":[
        "agency"
    ],
    "wof:name":"Direct General Insurance Co",
    "wof:placetype":"venue"
},
  "geometry": {"coordinates":[-90.64053,33.458086],"type":"Point"}
}