{
  "type": "Feature",
  "properties": {
    "iso:country":"US",
    "sg:address":"10179 Hwy 9 N",
    "sg:city":"Belden",
    "sg:classifiers":[
        {
            "category":"Shopping",
            "subcategory":"Clothing, Apparel, & Fashions",
            "type":"Retail Goods"
        }
    ],
    "sg:phone":"+1 662 620 1008",
    "sg:postcode":"38826",
    "sg:province":"MS",
    "sg:tags":[
        "salvage",
        "surplus",
        "merchandise"
    ],
    "wof:name":"Craig's Bargain Barn",
    "wof:placetype":"venue"
},
  "geometry": {"coordinates":[-88.876895,34.324186],"type":"Point"}
}