{
  "type": "Feature",
  "properties": {
    "iso:country":"US",
    "sg:address":"250 S Church St",
    "sg:city":"Florence",
    "sg:classifiers":[
        {
            "category":"Government",
            "subcategory":"Post Office",
            "type":"Public Place"
        }
    ],
    "sg:phone":"+1 601 845 3585",
    "sg:postcode":"39073",
    "sg:province":"MS",
    "wof:name":"US Post Office",
    "wof:placetype":"venue"
},
  "geometry": {"coordinates":[-90.13055799999999,32.14407],"type":"Point"}
}