{
  "type": "Feature",
  "properties": {
    "addr:full":"208 Alabama St Columbus MS 39702",
    "addr:housenumber":"208",
    "addr:postcode":"39702",
    "addr:street":"Alabama St",
    "iso:country":"US",
    "sg:address":"208 Alabama St",
    "sg:city":"Columbus",
    "sg:classifiers":[
        {
            "category":"Restaurant",
            "type":"Food & Drink"
        }
    ],
    "sg:menulink":"http://www.allmenus.com/ms/caledonia/183206-kfc---kentucky-fried-chicken/menu/",
    "sg:phone":"+1 601 638 2115",
    "sg:postcode":"39702",
    "sg:province":"MS",
    "sg:tags":[
        "american",
        "chicken"
    ],
    "wof:name":"KFC - Kentucky Fried Chicken",
    "wof:placetype":"venue"
},
  "geometry": {"coordinates":[-88.383121,33.495846],"type":"Point"}
}