{
  "type": "Feature",
  "properties": {
    "addr:full":"525 Nepanee Rd Leland MS 38756",
    "addr:housenumber":"525",
    "addr:postcode":"38756",
    "addr:street":"Nepanee Rd",
    "iso:country":"US",
    "sg:address":"525 Nepanee Rd",
    "sg:city":"Leland",
    "sg:classifiers":[
        {
            "category":"Farming",
            "subcategory":"Aquatic Farm",
            "type":"Manufacturing & Wholesale Goods"
        }
    ],
    "sg:phone":"+1 662 686 2894",
    "sg:postcode":"38756",
    "sg:province":"MS",
    "wof:name":"L & S Fish Farms Inc",
    "wof:placetype":"venue"
},
  "geometry": {"coordinates":[-90.870279,33.491642],"type":"Point"}
}