{
  "type": "Feature",
  "properties": {
    "iso:country":"US",
    "sg:address":"842 Commerce St",
    "sg:city":"Gulfport",
    "sg:classifiers":[
        {
            "category":"Government",
            "subcategory":"Office",
            "type":"Public Place"
        }
    ],
    "sg:phone":"+1 228 896 0055",
    "sg:postcode":"39507",
    "sg:province":"MS",
    "sg:website":"www.co.harrison.ms.us",
    "wof:name":"Harrison County Sand Beach",
    "wof:placetype":"venue"
},
  "geometry": {"coordinates":[-89.034791,30.398396],"type":"Point"}
}