{
  "type": "Feature",
  "properties": {
    "iso:country":"US",
    "sg:address":"4918 Finley St",
    "sg:city":"Gulfport",
    "sg:classifiers":[
        {
            "category":"Shopping",
            "subcategory":"Used Merchandise",
            "type":"Retail Goods"
        }
    ],
    "sg:phone":"+1 228 864 7440",
    "sg:postcode":"39501",
    "sg:province":"MS",
    "wof:name":"Grannys Antiques",
    "wof:placetype":"venue"
},
  "geometry": {"coordinates":[-89.12199099999999,30.356743],"type":"Point"}
}