{
  "type": "Feature",
  "properties": {
    "iso:country":"US",
    "sg:address":"1206 Poplar St",
    "sg:city":"Greenwood",
    "sg:classifiers":[
        {
            "category":"Professional",
            "subcategory":"Lawyer & Legal Services",
            "type":"Services"
        }
    ],
    "sg:phone":"+1 662 455 9999",
    "sg:postcode":"38930",
    "sg:province":"MS",
    "wof:name":"Rideout Law Office",
    "wof:placetype":"venue"
},
  "geometry": {"coordinates":[-90.189716,33.538236],"type":"Point"}
}