{
  "type": "Feature",
  "properties": {
    "addr:full":"3190 Robb St W Exd Summit MS 39666",
    "addr:housenumber":"3190",
    "addr:postcode":"39666",
    "addr:street":"Robb St W Exd",
    "iso:country":"US",
    "sg:address":"3190 Robb St W Exd",
    "sg:city":"Summit",
    "sg:classifiers":[
        {
            "category":"Social Services",
            "type":"Services"
        }
    ],
    "sg:phone":"+1 601 276 9291",
    "sg:postcode":"39666",
    "sg:province":"MS",
    "sg:tags":[
        "youth",
        "organization",
        "center"
    ],
    "wof:name":"Summit Dixie Youth Baseball",
    "wof:placetype":"venue"
},
  "geometry": {"coordinates":[-90.482606,31.284155],"type":"Point"}
}