{
  "type": "Feature",
  "properties": {
    "iso:country":"US",
    "sg:address":"7685 Hacks Cross Rd",
    "sg:city":"Olive Branch",
    "sg:classifiers":[
        {
            "category":"Personal",
            "subcategory":"Beauty Salon",
            "type":"Services"
        }
    ],
    "sg:phone":"+1 662 893 0930",
    "sg:postcode":"38654",
    "sg:province":"MS",
    "wof:name":"Braids & Fades",
    "wof:placetype":"venue"
},
  "geometry": {"coordinates":[-89.795241,34.97256],"type":"Point"}
}