{
  "type": "Feature",
  "properties": {
    "addr:full":"1115 Highway 82 E Greenville MS 38703",
    "addr:housenumber":"1115",
    "addr:postcode":"38703",
    "addr:street":"Highway 82 E",
    "iso:country":"US",
    "sg:address":"1115 Highway 82 E",
    "sg:city":"Greenville",
    "sg:classifiers":[
        {
            "category":"Professional",
            "type":"Services"
        },
        {
            "category":"Restaurant",
            "type":"Food & Drink"
        },
        {
            "category":"Fast Food",
            "type":"Food & Drink"
        }
    ],
    "sg:phone":"+1 662 335 5348",
    "sg:postcode":"38703",
    "sg:province":"MS",
    "sg:tags":[
        "delivery",
        "take",
        "pizza"
    ],
    "sg:website":"http://www.pizzahut.com",
    "wof:name":"Pizza Hut",
    "wof:placetype":"venue"
},
  "geometry": {"coordinates":[-91.037097,33.399543],"type":"Point"}
}