{
  "type": "Feature",
  "properties": {
    "addr:full":"241 W Oxford St Pontotoc MS 38863",
    "addr:housenumber":"241",
    "addr:postcode":"38863",
    "addr:street":"W Oxford St",
    "iso:country":"US",
    "sg:address":"241 W Oxford St",
    "sg:city":"Pontotoc",
    "sg:classifiers":[
        {
            "category":"Professional",
            "subcategory":"Accounting & Tax Preparation",
            "type":"Services"
        }
    ],
    "sg:phone":"+1 662 489 4828",
    "sg:postcode":"38863",
    "sg:province":"MS",
    "sg:tags":[
        "return",
        "filing"
    ],
    "wof:name":"H & R Block Tax Svc",
    "wof:placetype":"venue"
},
  "geometry": {"coordinates":[-89.01016799999999,34.254117],"type":"Point"}
}