{
  "type": "Feature",
  "properties": {
    "addr:full":"277 State Hwy 178 Holly Springs MS 38635",
    "addr:housenumber":"277",
    "addr:postcode":"38635",
    "addr:street":"State Hwy 178",
    "iso:country":"US",
    "sg:address":"277 State Hwy 178",
    "sg:city":"Holly Springs",
    "sg:classifiers":[
        {
            "category":"Utilities",
            "subcategory":"Mobile Phone",
            "type":"Services"
        }
    ],
    "sg:phone":"+1 662 252 1100",
    "sg:postcode":"38635",
    "sg:province":"MS",
    "sg:tags":[
        "cellular"
    ],
    "wof:name":"Cingular Wireless",
    "wof:placetype":"venue"
},
  "geometry": {"coordinates":[-89.443838,34.767387],"type":"Point"}
}