{
  "type": "Feature",
  "properties": {
    "iso:country":"US",
    "sg:address":"115 Patterson St",
    "sg:city":"Batesville",
    "sg:classifiers":[
        {
            "category":"Social Services",
            "subcategory":"Child Care",
            "type":"Services"
        }
    ],
    "sg:phone":"+1 662 578 0711",
    "sg:postcode":"38606",
    "sg:province":"MS",
    "wof:name":"Hoskins Learning Ctr Inc",
    "wof:placetype":"venue"
},
  "geometry": {"coordinates":[-89.967106,34.32149],"type":"Point"}
}