{
  "type": "Feature",
  "properties": {
    "iso:country":"US",
    "sg:address":"1808 Terry Rd",
    "sg:city":"Jackson",
    "sg:classifiers":[
        {
            "category":"Wholesale",
            "subcategory":"Machinery & Supplies",
            "type":"Manufacturing & Wholesale Goods"
        },
        {
            "category":"Shopping",
            "type":"Retail Goods"
        }
    ],
    "sg:phone":"+1 601 373 9212",
    "sg:postcode":"39204",
    "sg:province":"MS",
    "sg:tags":[
        "equipment",
        "establishment",
        "cosmetic",
        "perfume"
    ],
    "wof:name":"Carda' Beauty Supply",
    "wof:placetype":"venue"
},
  "geometry": {"coordinates":[-90.20966199999999,32.282444],"type":"Point"}
}