{
  "type": "Feature",
  "properties": {
    "addr:full":"2309 Pass Rd Gulfport MS 39501",
    "addr:housenumber":"2309",
    "addr:postcode":"39501",
    "addr:street":"Pass Rd",
    "iso:country":"US",
    "sg:address":"2309 Pass Rd",
    "sg:city":"Gulfport",
    "sg:classifiers":[
        {
            "category":"Banks & Credit Unions",
            "subcategory":"Bank",
            "type":"Services"
        }
    ],
    "sg:phone":"+1 228 863 5454",
    "sg:postcode":"39501",
    "sg:province":"MS",
    "sg:tags":[
        "cashing",
        "check"
    ],
    "wof:name":"Southeastern Cash Advance",
    "wof:placetype":"venue"
},
  "geometry": {"coordinates":[-89.0917,30.380311],"type":"Point"}
}