{
  "type": "Feature",
  "properties": {
    "addr:full":"105 Alabama St Columbus MS 39702",
    "addr:housenumber":"105",
    "addr:postcode":"39702",
    "addr:street":"Alabama St",
    "iso:country":"US",
    "sg:address":"105 Alabama St",
    "sg:city":"Columbus",
    "sg:classifiers":[
        {
            "category":"Shopping",
            "subcategory":"Jewelry",
            "type":"Retail Goods"
        }
    ],
    "sg:phone":"+1 662 328 2755",
    "sg:postcode":"39702",
    "sg:province":"MS",
    "sg:tags":[
        "food"
    ],
    "wof:name":"Fit Tree Health Foods",
    "wof:placetype":"venue"
},
  "geometry": {"coordinates":[-88.389118,33.496948],"type":"Point"}
}