{
  "type": "Feature",
  "properties": {
    "iso:country":"US",
    "sg:address":"305 W Eastport St",
    "sg:city":"Iuka",
    "sg:classifiers":[
        {
            "category":"Utilities",
            "subcategory":"Water",
            "type":"Services"
        }
    ],
    "sg:phone":"+1 662 424 0017",
    "sg:postcode":"38852",
    "sg:province":"MS",
    "sg:tags":[
        "company",
        "sewage"
    ],
    "wof:name":"Short Coleman Park Water Assn",
    "wof:placetype":"venue"
},
  "geometry": {"coordinates":[-88.19158400000001,34.812137],"type":"Point"}
}