{
  "type": "Feature",
  "properties": {
    "addr:full":"149 N Edison St Greenville MS 38701",
    "addr:housenumber":"149",
    "addr:postcode":"38701",
    "addr:street":"N Edison St",
    "iso:country":"US",
    "sg:address":"149 N Edison St",
    "sg:city":"Greenville",
    "sg:classifiers":[
        {
            "category":"Professional",
            "subcategory":"Lawyer & Legal Services",
            "type":"Services"
        }
    ],
    "sg:phone":"+1 662 378 2626",
    "sg:postcode":"38701",
    "sg:province":"MS",
    "sg:tags":[
        "attorney"
    ],
    "wof:name":"Dyer Dyer Jones & Danieels",
    "wof:placetype":"venue"
},
  "geometry": {"coordinates":[-91.05229,33.406892],"type":"Point"}
}