{
  "type": "Feature",
  "properties": {
    "iso:country":"US",
    "sg:address":"113 E Church St",
    "sg:city":"Quitman",
    "sg:classifiers":[
        {
            "category":"Government",
            "subcategory":"Office",
            "type":"Public Place"
        }
    ],
    "sg:phone":"+1 601 776 2256",
    "sg:postcode":"39355",
    "sg:province":"MS",
    "sg:tags":[
        "county",
        "safety",
        "order"
    ],
    "wof:name":"Clarke County Emergency Mgmt",
    "wof:placetype":"venue"
},
  "geometry": {"coordinates":[-88.724991,32.040184],"type":"Point"}
}