{
  "type": "Feature",
  "properties": {
    "addr:full":"205 Court St West Point MS 39773",
    "addr:housenumber":"205",
    "addr:postcode":"39773",
    "addr:street":"Court St",
    "iso:country":"US",
    "sg:address":"205 Court St",
    "sg:city":"West Point",
    "sg:classifiers":[
        {
            "category":"Government",
            "subcategory":"Court House",
            "type":"Public Place"
        }
    ],
    "sg:phone":"+1 662 494 3389",
    "sg:postcode":"39773",
    "sg:province":"MS",
    "sg:tags":[
        "county",
        "counsel"
    ],
    "wof:name":"Clay County District Attorney",
    "wof:placetype":"venue"
},
  "geometry": {"coordinates":[-88.649186,33.605872],"type":"Point"}
}