{
  "type": "Feature",
  "properties": {
    "addr:full":"145 Executive Dr Madison MS 39110",
    "addr:housenumber":"145",
    "addr:postcode":"39110",
    "addr:street":"Executive Dr",
    "iso:country":"US",
    "sg:address":"145 Executive Dr",
    "sg:city":"Madison",
    "sg:classifiers":[
        {
            "category":"Social Services",
            "type":"Services"
        }
    ],
    "sg:phone":"+1 601 856 7575",
    "sg:postcode":"39110",
    "sg:province":"MS",
    "sg:tags":[
        "organization",
        "welfare"
    ],
    "wof:name":"National Multiple Sclerosis",
    "wof:placetype":"venue"
},
  "geometry": {"coordinates":[-90.11671699999999,32.44452],"type":"Point"}
}