{
  "type": "Feature",
  "properties": {
    "addr:full":"1453 Co Rd 402 Houston MS 38851",
    "addr:housenumber":"1453",
    "addr:postcode":"38851",
    "addr:street":"Co Rd 402",
    "iso:country":"US",
    "sg:address":"1453 Co Rd 402",
    "sg:city":"Houston",
    "sg:classifiers":[
        {
            "category":"Organizations",
            "subcategory":"Religious Organization",
            "type":"Services"
        }
    ],
    "sg:phone":"+1 662 456 3815",
    "sg:postcode":"38851",
    "sg:province":"MS",
    "wof:name":"Pleasant Grove Baptist Church",
    "wof:placetype":"venue"
},
  "geometry": {"coordinates":[-88.843424,33.899604],"type":"Point"}
}