{
  "type": "Feature",
  "properties": {
    "iso:country":"US",
    "sg:address":"1201 Office Park Dr",
    "sg:city":"Oxford",
    "sg:classifiers":[
        {
            "category":"Professional",
            "subcategory":"Business Services",
            "type":"Services"
        },
        {
            "category":"Government",
            "subcategory":"Post Office",
            "type":"Public Place"
        }
    ],
    "sg:phone":"+1 662 513 9997",
    "sg:postcode":"38655",
    "sg:province":"MS",
    "sg:tags":[
        "delivery",
        "mail",
        "messenger",
        "shipping",
        "courier"
    ],
    "sg:website":"http://www.postalconnections.com",
    "wof:name":"Postal Connections",
    "wof:placetype":"venue"
},
  "geometry": {"coordinates":[-89.518108,34.33787],"type":"Point"}
}