{
  "type": "Feature",
  "properties": {
    "addr:full":"4182 Union Church Rd Magnolia MS 39652",
    "addr:housenumber":"4182",
    "addr:postcode":"39652",
    "addr:street":"Union Church Rd",
    "iso:country":"US",
    "sg:address":"4182 Union Church Rd",
    "sg:city":"Magnolia",
    "sg:classifiers":[
        {
            "category":"Organizations",
            "subcategory":"Religious Organization",
            "type":"Services"
        }
    ],
    "sg:phone":"+1 601 783 6409",
    "sg:postcode":"39652",
    "sg:province":"MS",
    "wof:name":"East Union Baptist Church",
    "wof:placetype":"venue"
},
  "geometry": {"coordinates":[-90.3831,31.14613],"type":"Point"}
}