{
  "type": "Feature",
  "properties": {
    "addr:full":"38 Co Rd 370 Iuka MS 38852",
    "addr:housenumber":"38",
    "addr:postcode":"370;38852",
    "addr:street":"Co Rd",
    "iso:country":"US",
    "sg:address":"38 Co Rd 370",
    "sg:city":"Iuka",
    "sg:classifiers":[
        {
            "category":"Manufacturing",
            "subcategory":"Metals",
            "type":"Manufacturing & Wholesale Goods"
        }
    ],
    "sg:phone":"+1 662 424 0115",
    "sg:postcode":"38852",
    "sg:province":"MS",
    "sg:tags":[
        "steel",
        "processing"
    ],
    "sg:website":"www.ferrousmetalprocessing.com",
    "wof:name":"Ferrous Metal Processing Co",
    "wof:placetype":"venue"
},
  "geometry": {"coordinates":[-88.239718,34.975733],"type":"Point"}
}