{
  "type": "Feature",
  "properties": {
    "iso:country":"US",
    "sg:address":"5809 Ridgewood Rd",
    "sg:city":"Jackson",
    "sg:classifiers":[
        {
            "category":"Autos & Motor Vehicles",
            "subcategory":"Auto Supplies",
            "type":"Retail Goods"
        }
    ],
    "sg:phone":"+1 601 991 2288",
    "sg:postcode":"39211",
    "sg:province":"MS",
    "sg:tags":[
        "automobile",
        "parts"
    ],
    "wof:name":"Advance Auto Parts Inc",
    "wof:placetype":"venue"
},
  "geometry": {"coordinates":[-90.141994,32.384883],"type":"Point"}
}