{
  "type": "Feature",
  "properties": {
    "addr:full":"124 Plummer Cir Jackson MS 39212",
    "addr:housenumber":"124",
    "addr:postcode":"39212",
    "addr:street":"Plummer Cir",
    "iso:country":"US",
    "sg:address":"124 Plummer Cir",
    "sg:city":"Jackson",
    "sg:classifiers":[
        {
            "category":"Social Services",
            "type":"Services"
        }
    ],
    "sg:phone":"+1 601 502 0575",
    "sg:postcode":"39212",
    "sg:province":"MS",
    "wof:name":"A New Beginning For At Risk Ch",
    "wof:placetype":"venue"
},
  "geometry": {"coordinates":[-90.274525,32.27031],"type":"Point"}
}