{
  "type": "Feature",
  "properties": {
    "addr:full":"2190 Iowa Blvd Vicksburg MS 39180",
    "addr:housenumber":"2190",
    "addr:postcode":"39180",
    "addr:street":"Iowa Blvd",
    "iso:country":"US",
    "sg:address":"2190 Iowa Blvd",
    "sg:city":"Vicksburg",
    "sg:classifiers":[
        {
            "category":"Utilities",
            "subcategory":"Mobile Phone",
            "type":"Services"
        }
    ],
    "sg:phone":"+1 601 638 0500",
    "sg:postcode":"39180",
    "sg:province":"MS",
    "sg:tags":[
        "telephone",
        "cellular"
    ],
    "wof:name":"Unitel",
    "wof:placetype":"venue"
},
  "geometry": {"coordinates":[-90.893157,32.307316],"type":"Point"}
}