{
  "type": "Feature",
  "properties": {
    "iso:country":"US",
    "sg:address":"959 Lake Harbour Dr",
    "sg:city":"Ridgeland",
    "sg:classifiers":[
        {
            "category":"Building & Trades",
            "subcategory":"Construction",
            "type":"Services"
        }
    ],
    "sg:phone":"+1 601 372 3635",
    "sg:postcode":"39157",
    "sg:province":"MS",
    "sg:tags":[
        "house"
    ],
    "wof:name":"David Lingle Homes Inc",
    "wof:placetype":"venue"
},
  "geometry": {"coordinates":[-90.094483,32.411968],"type":"Point"}
}