{
  "type": "Feature",
  "properties": {
    "addr:full":"400 Hillcrest Loop Petal MS 39465",
    "addr:housenumber":"400",
    "addr:postcode":"39465",
    "addr:street":"Hillcrest Loop",
    "iso:country":"US",
    "sg:address":"400 Hillcrest Loop",
    "sg:city":"Petal",
    "sg:classifiers":[
        {
            "category":"Education",
            "subcategory":"School",
            "type":"Public Place"
        }
    ],
    "sg:phone":"+1 601 584 7660",
    "sg:postcode":"39465",
    "sg:province":"MS",
    "wof:name":"W L Smith School",
    "wof:placetype":"venue"
},
  "geometry": {"coordinates":[-89.25846,31.335573],"type":"Point"}
}