{
  "type": "Feature",
  "properties": {
    "iso:country":"US",
    "sg:address":"2903 N State St",
    "sg:city":"Jackson",
    "sg:classifiers":[
        {
            "category":"Health Services",
            "subcategory":"Clinic",
            "type":"Services"
        }
    ],
    "sg:phone":"+1 601 366 2261",
    "sg:postcode":"39216",
    "sg:province":"MS",
    "sg:tags":[
        "information",
        "abortion",
        "specialty",
        "outpatient"
    ],
    "sg:website":"www.nwho.com",
    "wof:name":"Jackson Women's Health Orgnztn",
    "wof:placetype":"venue"
},
  "geometry": {"coordinates":[-90.176806,32.335315],"type":"Point"}
}