{
  "type": "Feature",
  "properties": {
    "iso:country":"US",
    "sg:address":"901 S Access Rd",
    "sg:city":"Fulton",
    "sg:classifiers":[
        {
            "category":"Government",
            "subcategory":"Office",
            "type":"Public Place"
        }
    ],
    "sg:phone":"+1 662 862 7431",
    "sg:postcode":"38843",
    "sg:province":"MS",
    "sg:tags":[
        "engineering"
    ],
    "wof:name":"US Army Corps Of Engineers",
    "wof:placetype":"venue"
},
  "geometry": {"coordinates":[-88.41755000000001,34.250625],"type":"Point"}
}