{
  "type": "Feature",
  "properties": {
    "iso:country":"US",
    "sg:address":"270 Power Dr",
    "sg:city":"Batesville",
    "sg:classifiers":[
        {
            "category":"Building & Trades",
            "subcategory":"Construction",
            "type":"Services"
        }
    ],
    "sg:phone":"+1 662 563 4551",
    "sg:postcode":"38606",
    "sg:province":"MS",
    "sg:tags":[
        "general",
        "contractor"
    ],
    "wof:name":"Mc Cain Builders Inc",
    "wof:placetype":"venue"
},
  "geometry": {"coordinates":[-89.923917,34.309403],"type":"Point"}
}