{
  "type": "Feature",
  "properties": {
    "iso:country":"US",
    "sg:address":"23506 State Hwy 53",
    "sg:city":"Gulfport",
    "sg:classifiers":[
        {
            "category":"Building & Trades",
            "subcategory":"Construction",
            "type":"Services"
        }
    ],
    "sg:phone":"+1 228 831 0134",
    "sg:postcode":"39503",
    "sg:province":"MS",
    "sg:tags":[
        "general",
        "contractor"
    ],
    "wof:name":"F & F Contracting",
    "wof:placetype":"venue"
},
  "geometry": {"coordinates":[-89.236412,30.534526],"type":"Point"}
}