{
  "type": "Feature",
  "properties": {
    "iso:country":"US",
    "sg:address":"1407 Goodman Rd W",
    "sg:city":"Horn Lake",
    "sg:classifiers":[
        {
            "category":"Personal",
            "subcategory":"Beauty Salon",
            "type":"Services"
        }
    ],
    "sg:phone":"+1 662 393 4444",
    "sg:postcode":"38637",
    "sg:province":"MS",
    "wof:name":"Hair Braiding",
    "wof:placetype":"venue"
},
  "geometry": {"coordinates":[-90.014595,34.962588],"type":"Point"}
}