{
  "type": "Feature",
  "properties": {
    "addr:full":"361 Edgewood Terrace Dr Jackson MS 39206",
    "addr:housenumber":"361",
    "addr:postcode":"39206",
    "addr:street":"Edgewood Terrace Dr",
    "iso:country":"US",
    "sg:address":"361 Edgewood Terrace Dr",
    "sg:city":"Jackson",
    "sg:classifiers":[
        {
            "category":"Restaurant",
            "type":"Food & Drink"
        }
    ],
    "sg:phone":"+1 601 982 2552",
    "sg:postcode":"39206",
    "sg:province":"MS",
    "wof:name":"KFC",
    "wof:placetype":"venue"
},
  "geometry": {"coordinates":[-90.156643,32.363681],"type":"Point"}
}