{
  "type": "Feature",
  "properties": {
    "iso:country":"US",
    "sg:address":"854 Kathy Smith St",
    "sg:city":"Brandon",
    "sg:classifiers":[
        {
            "category":"Freight",
            "type":"Transportation"
        }
    ],
    "sg:phone":"+1 601 825 0447",
    "sg:postcode":"39042",
    "sg:province":"MS",
    "sg:tags":[
        "operator",
        "local",
        "trucking"
    ],
    "wof:name":"Ben S Trucking",
    "wof:placetype":"venue"
},
  "geometry": {"coordinates":[-89.984486,32.189054],"type":"Point"}
}