{
  "type": "Feature",
  "properties": {
    "iso:country":"US",
    "sg:address":"2214 Metrocenter",
    "sg:city":"Jackson",
    "sg:classifiers":[
        {
            "category":"Restaurant",
            "type":"Food & Drink"
        }
    ],
    "sg:phone":"+1 601 355 0358",
    "sg:postcode":"39209",
    "sg:province":"MS",
    "wof:name":"Taco Bell",
    "wof:placetype":"venue"
},
  "geometry": {"coordinates":[-90.25502899999999,32.302753],"type":"Point"}
}