{
  "type": "Feature",
  "properties": {
    "addr:full":"2208 Arnold St Waveland MS 39576",
    "addr:housenumber":"2208",
    "addr:postcode":"39576",
    "addr:street":"Arnold St",
    "iso:country":"US",
    "sg:address":"2208 Arnold St",
    "sg:city":"Waveland",
    "sg:classifiers":[
        {
            "category":"Professional",
            "subcategory":"Business Services",
            "type":"Services"
        }
    ],
    "sg:phone":"+1 228 467 7418",
    "sg:postcode":"39576",
    "sg:province":"MS",
    "sg:tags":[
        "crane",
        "lift"
    ],
    "wof:name":"J & S Equipment Repair",
    "wof:placetype":"venue"
},
  "geometry": {"coordinates":[-89.372339,30.307035],"type":"Point"}
}