{
  "type": "Feature",
  "properties": {
    "addr:full":"4608 Hwy 49 W Yazoo City MS 39194",
    "addr:housenumber":"4608",
    "addr:postcode":"39194",
    "addr:street":"Hwy 49 W Yazoo",
    "iso:country":"US",
    "sg:address":"4608 Hwy 49 W",
    "sg:city":"Yazoo City",
    "sg:classifiers":[
        {
            "category":"Recreation",
            "type":"Entertainment"
        }
    ],
    "sg:phone":"+1 662 746 5992",
    "sg:postcode":"39194",
    "sg:province":"MS",
    "sg:tags":[
        "amusement"
    ],
    "wof:name":"Triad Nitrogen Inc",
    "wof:placetype":"venue"
},
  "geometry": {"coordinates":[-90.478722,32.875395],"type":"Point"}
}