{
  "type": "Feature",
  "properties": {
    "iso:country":"US",
    "sg:address":"420 Meadowbrook Rd",
    "sg:city":"Jackson",
    "sg:classifiers":[
        {
            "category":"Shopping",
            "subcategory":"Used Merchandise",
            "type":"Retail Goods"
        }
    ],
    "sg:phone":"+1 601 362 7707",
    "sg:postcode":"39206",
    "sg:province":"MS",
    "sg:tags":[
        "antique"
    ],
    "sg:website":"www.reavesorientalrugs.com",
    "wof:name":"Reaves' Oriental Rugs & Antqs",
    "wof:placetype":"venue"
},
  "geometry": {"coordinates":[-90.17362,32.350254],"type":"Point"}
}