{
  "type": "Feature",
  "properties": {
    "iso:country":"US",
    "sg:address":"100 Caldwell Dr",
    "sg:city":"Hazlehurst",
    "sg:classifiers":[
        {
            "category":"Government",
            "subcategory":"Office",
            "type":"Public Place"
        }
    ],
    "sg:phone":"+1 601 894 1856",
    "sg:postcode":"39083",
    "sg:province":"MS",
    "sg:tags":[
        "county",
        "program"
    ],
    "wof:name":"Solid Waste Collection",
    "wof:placetype":"venue"
},
  "geometry": {"coordinates":[-90.39633499999999,31.85972],"type":"Point"}
}