{
  "type": "Feature",
  "properties": {
    "iso:country":"US",
    "sg:address":"2619 S President Ave Exd",
    "sg:city":"Tupelo",
    "sg:classifiers":[
        {
            "category":"Home & Garden",
            "subcategory":"Furniture",
            "type":"Retail Goods"
        }
    ],
    "sg:phone":"+1 662 840 7899",
    "sg:postcode":"38801",
    "sg:province":"MS",
    "wof:name":"Infinity",
    "wof:placetype":"venue"
},
  "geometry": {"coordinates":[-88.723304,34.220977],"type":"Point"}
}