{
  "type": "Feature",
  "properties": {
    "iso:country":"US",
    "sg:address":"10638 Antioch Rd",
    "sg:city":"Lauderdale",
    "sg:classifiers":[
        {
            "category":"Organizations",
            "subcategory":"Religious Organization",
            "type":"Services"
        }
    ],
    "sg:phone":"+1 601 681 8500",
    "sg:postcode":"39335",
    "sg:province":"MS",
    "wof:name":"Antioch Baptist Church",
    "wof:placetype":"venue"
},
  "geometry": {"coordinates":[-88.641482,32.553274],"type":"Point"}
}