{
  "type": "Feature",
  "properties": {
    "iso:country":"US",
    "sg:address":"50 Allman St",
    "sg:city":"Lucedale",
    "sg:classifiers":[
        {
            "category":"Wholesale",
            "subcategory":"Tobacco Products",
            "type":"Manufacturing & Wholesale Goods"
        }
    ],
    "sg:phone":"+1 601 947 8186",
    "sg:postcode":"39452",
    "sg:province":"MS",
    "sg:tags":[
        "cigarette",
        "cigar",
        "dealer"
    ],
    "wof:name":"Wigley & Culp Inc",
    "wof:placetype":"venue"
},
  "geometry": {"coordinates":[-88.599813,30.909152],"type":"Point"}
}