{
  "type": "Feature",
  "properties": {
    "iso:country":"US",
    "sg:address":"9368 US Hwy 49",
    "sg:city":"Gulfport",
    "sg:classifiers":[
        {
            "category":"Shopping",
            "subcategory":"Shoes",
            "type":"Retail Goods"
        }
    ],
    "sg:phone":"+1 228 863 2212",
    "sg:postcode":"39503",
    "sg:province":"MS",
    "wof:name":"Payless Shoe Source",
    "wof:placetype":"venue"
},
  "geometry": {"coordinates":[-89.092376,30.427546],"type":"Point"}
}