{
  "type": "Feature",
  "properties": {
    "iso:country":"US",
    "sg:address":"1101 Rock Rd",
    "sg:city":"Mccomb",
    "sg:classifiers":[
        {
            "category":"Farming",
            "subcategory":"Farm",
            "type":"Manufacturing & Wholesale Goods"
        }
    ],
    "sg:phone":"+1 601 684 3089",
    "sg:postcode":"39669",
    "sg:province":"MS",
    "wof:name":"Rock House Farm",
    "wof:placetype":"venue"
},
  "geometry": {"coordinates":[-91.481318,31.18336],"type":"Point"}
}