{
  "type": "Feature",
  "properties": {
    "addr:full":"2323 Washington St Vicksburg MS 39183",
    "addr:housenumber":"2323",
    "addr:postcode":"39183",
    "addr:street":"Washington St",
    "iso:country":"US",
    "sg:address":"2323 Washington St",
    "sg:city":"Vicksburg",
    "sg:classifiers":[
        {
            "category":"Shopping",
            "subcategory":"Computers & Home Electronics",
            "type":"Retail Goods"
        }
    ],
    "sg:phone":"+1 601 638 2222",
    "sg:postcode":"39183",
    "sg:province":"MS",
    "sg:tags":[
        "tv",
        "repair"
    ],
    "wof:name":"Busby & Sons TV & Electronics",
    "wof:placetype":"venue"
},
  "geometry": {"coordinates":[-90.88536499999999,32.339603],"type":"Point"}
}