{
  "type": "Feature",
  "properties": {
    "iso:country":"US",
    "sg:address":"4410 W Aloha Dr",
    "sg:city":"Diamondhead",
    "sg:classifiers":[
        {
            "category":"Real Estate",
            "subcategory":"Real Estate Agent",
            "type":"Services"
        },
        {
            "category":"Building & Trades",
            "subcategory":"Construction",
            "type":"Services"
        }
    ],
    "sg:phone":"+1 228 255 8399",
    "sg:postcode":"39525",
    "sg:province":"MS",
    "sg:tags":[
        "house"
    ],
    "wof:name":"Diamondhead Home Sales Inc",
    "wof:placetype":"venue"
},
  "geometry": {"coordinates":[-89.376273,30.375642],"type":"Point"}
}