{
  "type": "Feature",
  "properties": {
    "iso:country":"US",
    "sg:address":"172 Co Rd 441",
    "sg:city":"Houston",
    "sg:classifiers":[
        {
            "category":"Freight",
            "type":"Transportation"
        }
    ],
    "sg:phone":"+1 662 456 5762",
    "sg:postcode":"38851",
    "sg:province":"MS",
    "sg:tags":[
        "operator",
        "local",
        "trucking"
    ],
    "wof:name":"Webster Trucking Inc",
    "wof:placetype":"venue"
},
  "geometry": {"coordinates":[-89.11675700000001,33.915883],"type":"Point"}
}