{
  "type": "Feature",
  "properties": {
    "iso:country":"US",
    "sg:address":"360 W Monticello St",
    "sg:city":"Brookhaven",
    "sg:classifiers":[
        {
            "category":"Shopping",
            "subcategory":"Pharmacy",
            "type":"Retail Goods"
        }
    ],
    "sg:phone":"+1 601 833 1922",
    "sg:postcode":"39601",
    "sg:province":"MS",
    "sg:tags":[
        "drug",
        "store"
    ],
    "wof:name":"Banes Drug Center",
    "wof:placetype":"venue"
},
  "geometry": {"coordinates":[-90.446865,31.580911],"type":"Point"}
}