{
  "type": "Feature",
  "properties": {
    "iso:country":"US",
    "sg:address":"16 Park Pl",
    "sg:city":"Hattiesburg",
    "sg:classifiers":[
        {
            "category":"Professional",
            "subcategory":"Lawyer & Legal Services",
            "type":"Services"
        }
    ],
    "sg:phone":"+1 601 268 9447",
    "sg:postcode":"39402",
    "sg:province":"MS",
    "sg:tags":[
        "attorney"
    ],
    "sg:website":"www.wilkesmchugh.com",
    "wof:name":"Wilkes & Mc Hugh",
    "wof:placetype":"venue"
},
  "geometry": {"coordinates":[-89.35875799999999,31.330243],"type":"Point"}
}