{
  "type": "Feature",
  "properties": {
    "addr:full":"101 Wallace St Tupelo MS 38804",
    "addr:housenumber":"101",
    "addr:postcode":"38804",
    "addr:street":"Wallace St",
    "iso:country":"US",
    "sg:address":"101 Wallace St",
    "sg:city":"Tupelo",
    "sg:classifiers":[
        {
            "category":"Railroad",
            "type":"Transportation"
        }
    ],
    "sg:phone":"+1 662 842 2417",
    "sg:postcode":"38804",
    "sg:province":"MS",
    "wof:name":"Kansas City Southern Railway",
    "wof:placetype":"venue"
},
  "geometry": {"coordinates":[-88.70714599999999,34.238188],"type":"Point"}
}