{
  "type": "Feature",
  "properties": {
    "iso:country":"US",
    "sg:address":"240 Maddox Rd",
    "sg:city":"Jackson",
    "sg:classifiers":[
        {
            "category":"Wholesale",
            "subcategory":"Toys & Hobbies",
            "type":"Manufacturing & Wholesale Goods"
        }
    ],
    "sg:phone":"+1 601 922 2365",
    "sg:postcode":"39212",
    "sg:province":"MS",
    "sg:tags":[
        "wholesaler"
    ],
    "wof:name":"A & A Wholesale",
    "wof:placetype":"venue"
},
  "geometry": {"coordinates":[-90.28454600000001,32.270866],"type":"Point"}
}