{
  "type": "Feature",
  "properties": {
    "addr:full":"104 Squaw Ln Booneville MS 38829",
    "addr:housenumber":"104",
    "addr:postcode":"38829",
    "addr:street":"Squaw Ln",
    "iso:country":"US",
    "sg:address":"104 Squaw Ln",
    "sg:city":"Booneville",
    "sg:classifiers":[
        {
            "category":"Restaurant",
            "type":"Food & Drink"
        }
    ],
    "sg:phone":"+1 662 728 8096",
    "sg:postcode":"38829",
    "sg:province":"MS",
    "sg:tags":[
        "eating",
        "merchandise"
    ],
    "wof:name":"Poor Boy Ice Inc",
    "wof:placetype":"venue"
},
  "geometry": {"coordinates":[-88.585857,34.650927],"type":"Point"}
}