{
  "type": "Feature",
  "properties": {
    "iso:country":"US",
    "sg:address":"423 Carrollton Ave",
    "sg:city":"Greenwood",
    "sg:classifiers":[
        {
            "category":"Restaurant",
            "type":"Food & Drink"
        }
    ],
    "sg:phone":"+1 662 453 6530",
    "sg:postcode":"38930",
    "sg:province":"MS",
    "sg:tags":[
        "eating"
    ],
    "wof:name":"Crystal Grill Inc",
    "wof:placetype":"venue"
},
  "geometry": {"coordinates":[-90.17725799999999,33.518008],"type":"Point"}
}