{
  "type": "Feature",
  "properties": {
    "iso:country":"US",
    "sg:address":"4800 McWillie Cir",
    "sg:city":"Jackson",
    "sg:classifiers":[
        {
            "category":"Building & Trades",
            "subcategory":"Electrical",
            "type":"Services"
        }
    ],
    "sg:phone":"+1 601 981 5889",
    "sg:postcode":"39206",
    "sg:province":"MS",
    "sg:tags":[
        "electric",
        "contractor"
    ],
    "wof:name":"Bennett Services",
    "wof:placetype":"venue"
},
  "geometry": {"coordinates":[-90.152731,32.364081],"type":"Point"}
}