{
  "type": "Feature",
  "properties": {
    "iso:country":"US",
    "sg:address":"715 S Jefferson St",
    "sg:city":"Jackson",
    "sg:classifiers":[
        {
            "category":"Communications",
            "subcategory":"Television Station",
            "type":"Services"
        }
    ],
    "sg:phone":"+1 601 948 3333",
    "sg:postcode":"39201",
    "sg:province":"MS",
    "sg:tags":[
        "broadcasting",
        "co"
    ],
    "sg:website":"www.wlbt.com",
    "wof:name":"Wlbt",
    "wof:placetype":"venue"
},
  "geometry": {"coordinates":[-90.179526,32.290358],"type":"Point"}
}