{
  "type": "Feature",
  "properties": {
    "addr:full":"400 State Hwy 330 Bruce MS 38915",
    "addr:housenumber":"400",
    "addr:postcode":"38915",
    "addr:street":"State Hwy 330",
    "iso:country":"US",
    "sg:address":"400 State Hwy 330",
    "sg:city":"Bruce",
    "sg:classifiers":[
        {
            "category":"Farming",
            "subcategory":"Farm & Veterinary Services",
            "type":"Manufacturing & Wholesale Goods"
        }
    ],
    "sg:phone":"+1 662 983 4665",
    "sg:postcode":"38915",
    "sg:province":"MS",
    "sg:tags":[
        "crop"
    ],
    "wof:name":"D C Aerial Services",
    "wof:placetype":"venue"
},
  "geometry": {"coordinates":[-89.461872,33.966884],"type":"Point"}
}