{
  "type": "Feature",
  "properties": {
    "iso:country":"US",
    "sg:address":"1409 E 2nd St",
    "sg:city":"Pass Christian",
    "sg:classifiers":[
        {
            "category":"Wholesale",
            "subcategory":"Seafood",
            "type":"Manufacturing & Wholesale Goods"
        }
    ],
    "sg:phone":"+1 228 452 2681",
    "sg:postcode":"39571",
    "sg:province":"MS",
    "wof:name":"Jerry Forte Seafood",
    "wof:placetype":"venue"
},
  "geometry": {"coordinates":[-89.19574299999999,30.334861],"type":"Point"}
}