{
  "type": "Feature",
  "properties": {
    "addr:full":"307 Beverly Ln Hattiesburg MS 39402",
    "addr:housenumber":"307",
    "addr:postcode":"39402",
    "addr:street":"Beverly Ln",
    "iso:country":"US",
    "sg:address":"307 Beverly Ln",
    "sg:city":"Hattiesburg",
    "sg:classifiers":[
        {
            "category":"Manufacturing",
            "subcategory":"Chemicals & Compounds",
            "type":"Manufacturing & Wholesale Goods"
        }
    ],
    "sg:phone":"+1 601 264 8903",
    "sg:postcode":"39402",
    "sg:province":"MS",
    "sg:tags":[
        "inorganic",
        "industrial",
        "mfg"
    ],
    "wof:name":"Blue Streak",
    "wof:placetype":"venue"
},
  "geometry": {"coordinates":[-89.34035299999999,31.316616],"type":"Point"}
}