{
  "type": "Feature",
  "properties": {
    "addr:full":"545 W Main St West Point MS 39773",
    "addr:housenumber":"545",
    "addr:postcode":"39773",
    "addr:street":"W Main St",
    "iso:country":"US",
    "sg:address":"545 W Main St",
    "sg:city":"West Point",
    "sg:classifiers":[
        {
            "category":"Shopping",
            "subcategory":"Pharmacy",
            "type":"Retail Goods"
        }
    ],
    "sg:phone":"+1 662 494 2535",
    "sg:postcode":"39773",
    "sg:province":"MS",
    "wof:name":"Plaza Drug Co",
    "wof:placetype":"venue"
},
  "geometry": {"coordinates":[-88.65607799999999,33.607187],"type":"Point"}
}