{
  "type": "Feature",
  "properties": {
    "iso:country":"US",
    "sg:address":"2103 25th Ave",
    "sg:city":"Gulfport",
    "sg:classifiers":[
        {
            "category":"Personal",
            "subcategory":"Beauty Salon",
            "type":"Services"
        }
    ],
    "sg:phone":"+1 228 822 9212",
    "sg:postcode":"39501",
    "sg:province":"MS",
    "sg:tags":[
        "shop"
    ],
    "wof:name":"Princess Nails",
    "wof:placetype":"venue"
},
  "geometry": {"coordinates":[-89.093163,30.376677],"type":"Point"}
}