{
  "type": "Feature",
  "properties": {
    "iso:country":"US",
    "sg:address":"3615 22nd St",
    "sg:city":"Gulfport",
    "sg:classifiers":[
        {
            "category":"Social Services",
            "type":"Services"
        }
    ],
    "sg:phone":"+1 228 865 1074",
    "sg:postcode":"39501",
    "sg:province":"MS",
    "wof:name":"Gulf Cast Trtmnt Chrstn Cnslin",
    "wof:placetype":"venue"
},
  "geometry": {"coordinates":[-89.10543199999999,30.376542],"type":"Point"}
}