{
  "type": "Feature",
  "properties": {
    "iso:country":"US",
    "sg:address":"4018 Katie St",
    "sg:city":"Moss Point",
    "sg:classifiers":[
        {
            "category":"Freight",
            "type":"Transportation"
        }
    ],
    "sg:phone":"+1 228 475 5865",
    "sg:postcode":"39563",
    "sg:province":"MS",
    "wof:name":"Taylors Transports",
    "wof:placetype":"venue"
},
  "geometry": {"coordinates":[-88.512326,30.402224],"type":"Point"}
}