{
  "type": "Feature",
  "properties": {
    "addr:full":"316 N Broad St Leland MS 38756",
    "addr:housenumber":"316",
    "addr:postcode":"38756",
    "addr:street":"N Broad St",
    "iso:country":"US",
    "sg:address":"316 N Broad St",
    "sg:city":"Leland",
    "sg:classifiers":[
        {
            "category":"Recreation",
            "type":"Entertainment"
        }
    ],
    "sg:phone":"+1 662 686 9636",
    "sg:postcode":"38756",
    "sg:province":"MS",
    "sg:tags":[
        "parks"
    ],
    "wof:name":"City Of Leland Park & Rcrtn",
    "wof:placetype":"venue"
},
  "geometry": {"coordinates":[-90.89762500000001,33.405211],"type":"Point"}
}