{
  "type": "Feature",
  "properties": {
    "addr:full":"2620 Green Tee Rd Verona MS 38801",
    "addr:housenumber":"2620",
    "addr:postcode":"38801",
    "addr:street":"Green Tee Rd",
    "iso:country":"US",
    "sg:address":"2620 Green Tee Rd",
    "sg:city":"Verona",
    "sg:classifiers":[
        {
            "category":"Food & Beverages",
            "subcategory":"Groceries & Convenience Stores",
            "type":"Retail Goods"
        }
    ],
    "sg:phone":"+1 662 566 8618",
    "sg:postcode":"38801",
    "sg:province":"MS",
    "sg:tags":[
        "grocer"
    ],
    "wof:name":"R & L Grocery",
    "wof:placetype":"venue"
},
  "geometry": {"coordinates":[-88.757372,34.206428],"type":"Point"}
}