{
  "type": "Feature",
  "properties": {
    "iso:country":"US",
    "sg:address":"200 N Main St",
    "sg:city":"Poplarville",
    "sg:classifiers":[
        {
            "category":"Autos & Motor Vehicles",
            "subcategory":"Fuel & Gas Station",
            "type":"Retail Goods"
        }
    ],
    "sg:phone":"+1 601 795 4385",
    "sg:postcode":"39470",
    "sg:province":"MS",
    "sg:tags":[
        "oil"
    ],
    "wof:name":"Quick & Grice",
    "wof:placetype":"venue"
},
  "geometry": {"coordinates":[-89.53567099999999,30.845722],"type":"Point"}
}