{
  "type": "Feature",
  "properties": {
    "addr:full":"367 Rd 1500 Belden MS 38826",
    "addr:housenumber":"367",
    "addr:postcode":"38826",
    "addr:street":"Rd 1500",
    "iso:country":"US",
    "sg:address":"367 Rd 1500",
    "sg:city":"Belden",
    "sg:classifiers":[
        {
            "category":"Building & Trades",
            "subcategory":"Construction",
            "type":"Services"
        }
    ],
    "sg:phone":"+1 662 842 8369",
    "sg:postcode":"38826",
    "sg:province":"MS",
    "sg:tags":[
        "hanging",
        "contractor"
    ],
    "wof:name":"Austra Line Master Painte",
    "wof:placetype":"venue"
},
  "geometry": {"coordinates":[-88.80041300000001,34.293617],"type":"Point"}
}