{
  "type": "Feature",
  "properties": {
    "iso:country":"US",
    "sg:address":"25401 Rosedale Church Rd",
    "sg:city":"Lucedale",
    "sg:classifiers":[
        {
            "category":"Building & Trades",
            "subcategory":"Construction",
            "type":"Services"
        }
    ],
    "sg:phone":"+1 228 588 9935",
    "sg:postcode":"39452",
    "sg:province":"MS",
    "sg:tags":[
        "tile",
        "contractor"
    ],
    "wof:name":"Dees Tile",
    "wof:placetype":"venue"
},
  "geometry": {"coordinates":[-88.526038,30.720461],"type":"Point"}
}