{
  "type": "Feature",
  "properties": {
    "iso:country":"US",
    "sg:address":"1701 Main St",
    "sg:city":"Columbus",
    "sg:classifiers":[
        {
            "category":"Home & Garden",
            "subcategory":"Building Materials",
            "type":"Retail Goods"
        }
    ],
    "sg:phone":"+1 662 328 4451",
    "sg:postcode":"39701",
    "sg:province":"MS",
    "sg:website":"www.newhomebuilding.net",
    "wof:name":"New Home Building Stores Inc",
    "wof:placetype":"venue"
},
  "geometry": {"coordinates":[-88.41310900000001,33.497189],"type":"Point"}
}