{
  "type": "Feature",
  "properties": {
    "addr:full":"1200 Hwy 469 S Florence MS 39073",
    "addr:housenumber":"1200",
    "addr:postcode":"39073",
    "addr:street":"Hwy 469 S",
    "iso:country":"US",
    "sg:address":"1200 Hwy 469 S",
    "sg:city":"Florence",
    "sg:classifiers":[
        {
            "category":"Government",
            "subcategory":"Fire Station",
            "type":"Public Place"
        }
    ],
    "sg:phone":"+1 601 845 0637",
    "sg:postcode":"39073",
    "sg:province":"MS",
    "sg:tags":[
        "department"
    ],
    "wof:name":"Mountain Creek Volunteer Fire",
    "wof:placetype":"venue"
},
  "geometry": {"coordinates":[-90.12854400000001,32.099494],"type":"Point"}
}