{
  "type": "Feature",
  "properties": {
    "addr:full":"796 Lake Harbour Dr Ridgeland MS 39157",
    "addr:housenumber":"796",
    "addr:postcode":"39157",
    "addr:street":"Lake Harbour Dr",
    "iso:country":"US",
    "sg:address":"796 Lake Harbour Dr",
    "sg:city":"Ridgeland",
    "sg:classifiers":[
        {
            "category":"Restaurant",
            "type":"Food & Drink"
        }
    ],
    "sg:phone":"+1 601 853 2255",
    "sg:postcode":"39157",
    "sg:province":"MS",
    "wof:name":"Subway Sandwiches & Salads",
    "wof:placetype":"venue"
},
  "geometry": {"coordinates":[-90.113232,32.41402],"type":"Point"}
}