{
  "type": "Feature",
  "properties": {
    "addr:full":"8473 Goodman Rd Olive Branch MS 38654",
    "addr:housenumber":"8473",
    "addr:postcode":"38654",
    "addr:street":"Goodman Rd",
    "iso:country":"US",
    "sg:address":"8473 Goodman Rd",
    "sg:city":"Olive Branch",
    "sg:classifiers":[
        {
            "category":"Home & Garden",
            "subcategory":"Building Materials",
            "type":"Retail Goods"
        }
    ],
    "sg:phone":"+1 662 895 0349",
    "sg:postcode":"38654",
    "sg:province":"MS",
    "sg:tags":[
        "paint"
    ],
    "wof:name":"PPG Porter Paints",
    "wof:placetype":"venue"
},
  "geometry": {"coordinates":[-89.841292,34.962117],"type":"Point"}
}