{
  "type": "Feature",
  "properties": {
    "iso:country":"US",
    "sg:address":"218 E Cherry St",
    "sg:city":"Shannon",
    "sg:classifiers":[
        {
            "category":"Education",
            "subcategory":"School",
            "type":"Public Place"
        }
    ],
    "sg:phone":"+1 662 767 9566",
    "sg:postcode":"38868",
    "sg:province":"MS",
    "wof:name":"Shannon High School",
    "wof:placetype":"venue"
},
  "geometry": {"coordinates":[-88.71476699999999,34.12391],"type":"Point"}
}