{
  "type": "Feature",
  "properties": {
    "iso:country":"US",
    "sg:address":"605 W Alexander St",
    "sg:city":"Greenville",
    "sg:classifiers":[
        {
            "category":"Banks & Credit Unions",
            "subcategory":"Bank",
            "type":"Services"
        }
    ],
    "sg:phone":"+1 662 332 4469",
    "sg:postcode":"38701",
    "sg:province":"MS",
    "sg:tags":[
        "loan",
        "institution",
        "business"
    ],
    "wof:name":"Quick Cash Inc",
    "wof:placetype":"venue"
},
  "geometry": {"coordinates":[-91.057351,33.41194],"type":"Point"}
}