{
  "type": "Feature",
  "properties": {
    "addr:full":"800 Cooper Rd Jackson MS 39212",
    "addr:housenumber":"800",
    "addr:postcode":"39212",
    "addr:street":"Cooper Rd",
    "iso:country":"US",
    "sg:address":"800 Cooper Rd",
    "sg:city":"Jackson",
    "sg:classifiers":[
        {
            "category":"Social Services",
            "subcategory":"Child Care",
            "type":"Services"
        }
    ],
    "sg:phone":"+1 601 371 3120",
    "sg:postcode":"39212",
    "sg:province":"MS",
    "wof:name":"Solomon Temple Child Care Ctr",
    "wof:placetype":"venue"
},
  "geometry": {"coordinates":[-90.247331,32.253867],"type":"Point"}
}