{
  "type": "Feature",
  "properties": {
    "iso:country":"US",
    "sg:address":"1167 Winnrose St",
    "sg:city":"Jackson",
    "sg:classifiers":[
        {
            "category":"Professional",
            "subcategory":"Lawyer & Legal Services",
            "type":"Services"
        }
    ],
    "sg:phone":"+1 601 956 2536",
    "sg:postcode":"39211",
    "sg:province":"MS",
    "wof:name":"R Steven Coleman JD",
    "wof:placetype":"venue"
},
  "geometry": {"coordinates":[-90.13967700000001,32.390781],"type":"Point"}
}