{
  "type": "Feature",
  "properties": {
    "iso:country":"US",
    "sg:address":"701 N Martin Luther King Jr St",
    "sg:city":"Natchez",
    "sg:classifiers":[
        {
            "category":"Education",
            "subcategory":"School",
            "type":"Public Place"
        }
    ],
    "sg:phone":"+1 601 442 1988",
    "sg:postcode":"39120",
    "sg:province":"MS",
    "wof:name":"Cathedral Unit School",
    "wof:placetype":"venue"
},
  "geometry": {"coordinates":[-91.39421,31.5631],"type":"Point"}
}