{
  "type": "Feature",
  "properties": {
    "addr:full":"146 S Thomas St Tupelo MS 38801",
    "addr:housenumber":"146",
    "addr:postcode":"38801",
    "addr:street":"S Thomas St",
    "iso:country":"US",
    "sg:address":"146 S Thomas St",
    "sg:city":"Tupelo",
    "sg:classifiers":[
        {
            "category":"Social Services",
            "subcategory":"Job Training",
            "type":"Services"
        }
    ],
    "sg:phone":"+1 662 842 4371",
    "sg:postcode":"38801",
    "sg:province":"MS",
    "sg:tags":[
        "rehab",
        "government"
    ],
    "wof:name":"Employment Security Commission",
    "wof:placetype":"venue"
},
  "geometry": {"coordinates":[-88.746233,34.25426],"type":"Point"}
}