{
  "type": "Feature",
  "properties": {
    "iso:country":"US",
    "sg:address":"233 W Main St",
    "sg:city":"Okolona",
    "sg:classifiers":[
        {
            "category":"Health Services",
            "subcategory":"Doctor",
            "type":"Services"
        }
    ],
    "sg:phone":"+1 662 447 2704",
    "sg:postcode":"38860",
    "sg:province":"MS",
    "sg:tags":[
        "dentist"
    ],
    "wof:name":"Okolona Family Dentistry",
    "wof:placetype":"venue"
},
  "geometry": {"coordinates":[-88.74758799999999,34.004153],"type":"Point"}
}