{
  "type": "Feature",
  "properties": {
    "iso:country":"US",
    "sg:address":"150 State Hwy 1",
    "sg:city":"Rosedale",
    "sg:classifiers":[
        {
            "category":"Organizations",
            "subcategory":"Religious Organization",
            "type":"Services"
        }
    ],
    "sg:phone":"+1 662 759 3703",
    "sg:postcode":"38769",
    "sg:province":"MS",
    "sg:tags":[
        "church"
    ],
    "wof:name":"Bible Way Assembly Church",
    "wof:placetype":"venue"
},
  "geometry": {"coordinates":[-91.02746999999999,33.861165],"type":"Point"}
}