{
  "type": "Feature",
  "properties": {
    "iso:country":"US",
    "sg:address":"1600 W Tallahatchie St",
    "sg:city":"Clarksdale",
    "sg:classifiers":[
        {
            "category":"Mining & Drilling",
            "type":"Manufacturing & Wholesale Goods"
        }
    ],
    "sg:phone":"+1 662 627 3422",
    "sg:postcode":"38614",
    "sg:province":"MS",
    "sg:tags":[
        "limestone"
    ],
    "wof:name":"Mississippi Limestone Corp",
    "wof:placetype":"venue"
},
  "geometry": {"coordinates":[-90.564497,34.187782],"type":"Point"}
}