{
  "type": "Feature",
  "properties": {
    "iso:country":"US",
    "sg:address":"6507 Beatline Rd",
    "sg:city":"Long Beach",
    "sg:classifiers":[
        {
            "category":"Home & Garden",
            "subcategory":"Home Furnishings",
            "type":"Retail Goods"
        }
    ],
    "sg:phone":"+1 228 864 6444",
    "sg:postcode":"39560",
    "sg:province":"MS",
    "sg:tags":[
        "pottery"
    ],
    "wof:name":"Border Crossing II",
    "wof:placetype":"venue"
},
  "geometry": {"coordinates":[-89.187178,30.38211],"type":"Point"}
}