{
  "type": "Feature",
  "properties": {
    "addr:full":"825 S West St Jackson MS 39201",
    "addr:housenumber":"825",
    "addr:postcode":"39201",
    "addr:street":"S;St",
    "iso:country":"US",
    "sg:address":"825 S West St",
    "sg:city":"Jackson",
    "sg:classifiers":[
        {
            "category":"Wholesale",
            "subcategory":"Furniture",
            "type":"Manufacturing & Wholesale Goods"
        }
    ],
    "sg:phone":"+1 601 355 5799",
    "sg:postcode":"39201",
    "sg:province":"MS",
    "wof:name":"Office Zone",
    "wof:placetype":"venue"
},
  "geometry": {"coordinates":[-90.186138,32.289885],"type":"Point"}
}