{
  "type": "Feature",
  "properties": {
    "iso:country":"US",
    "sg:address":"804 North St",
    "sg:city":"Mccomb",
    "sg:classifiers":[
        {
            "category":"Wholesale",
            "subcategory":"Construction Materials",
            "type":"Manufacturing & Wholesale Goods"
        }
    ],
    "sg:phone":"+1 601 684 8698",
    "sg:postcode":"39648",
    "sg:province":"MS",
    "sg:tags":[
        "timberland",
        "company",
        "timber"
    ],
    "wof:name":"Kenneth Wilson Timber Co Inc",
    "wof:placetype":"venue"
},
  "geometry": {"coordinates":[-90.46170600000001,31.258774],"type":"Point"}
}