{
  "type": "Feature",
  "properties": {
    "iso:country":"US",
    "sg:address":"16 Northtown Dr",
    "sg:city":"Jackson",
    "sg:classifiers":[
        {
            "category":"Banks & Credit Unions",
            "subcategory":"Bank",
            "type":"Services"
        }
    ],
    "sg:phone":"+1 601 977 0709",
    "sg:postcode":"39211",
    "sg:province":"MS",
    "sg:tags":[
        "loan",
        "real estate"
    ],
    "wof:name":"Home Mortgage Solutions",
    "wof:placetype":"venue"
},
  "geometry": {"coordinates":[-90.113089,32.385736],"type":"Point"}
}