{
  "type": "Feature",
  "properties": {
    "addr:full":"237 Coleman Ave Waveland MS 39576",
    "addr:housenumber":"237",
    "addr:postcode":"39576",
    "addr:street":"Coleman Ave",
    "iso:country":"US",
    "sg:address":"237 Coleman Ave",
    "sg:city":"Waveland",
    "sg:classifiers":[
        {
            "category":"Shopping",
            "subcategory":"Used Merchandise",
            "type":"Retail Goods"
        }
    ],
    "sg:phone":"+1 228 467 3922",
    "sg:postcode":"39576",
    "sg:province":"MS",
    "wof:name":"That Cute Little Shoppe",
    "wof:placetype":"venue"
},
  "geometry": {"coordinates":[-89.371574,30.284236],"type":"Point"}
}