{
  "type": "Feature",
  "properties": {
    "addr:full":"617 Renaissance Way Ridgeland MS 39157",
    "addr:housenumber":"617",
    "addr:postcode":"39157",
    "addr:street":"Renaissance Way",
    "iso:country":"US",
    "sg:address":"617 Renaissance Way",
    "sg:city":"Ridgeland",
    "sg:classifiers":[
        {
            "category":"Professional",
            "subcategory":"Lawyer & Legal Services",
            "type":"Services"
        }
    ],
    "sg:phone":"+1 601 605 6345",
    "sg:postcode":"39157",
    "sg:province":"MS",
    "sg:tags":[
        "attorney"
    ],
    "wof:name":"Montgomery Mc Graw Collins",
    "wof:placetype":"venue"
},
  "geometry": {"coordinates":[-90.160618,32.417611],"type":"Point"}
}