{
  "type": "Feature",
  "properties": {
    "addr:full":"943 N Jackson St Houston MS 38851",
    "addr:housenumber":"943",
    "addr:postcode":"38851",
    "addr:street":"N Jackson St",
    "iso:country":"US",
    "sg:address":"943 N Jackson St",
    "sg:city":"Houston",
    "sg:classifiers":[
        {
            "category":"Food & Beverages",
            "subcategory":"Groceries & Convenience Stores",
            "type":"Retail Goods"
        }
    ],
    "sg:phone":"+1 662 456 9432",
    "sg:postcode":"38851",
    "sg:province":"MS",
    "wof:name":"Handy Corner",
    "wof:placetype":"venue"
},
  "geometry": {"coordinates":[-89.004913,33.912727],"type":"Point"}
}