{
  "type": "Feature",
  "properties": {
    "iso:country":"US",
    "sg:address":"1317 Fred St",
    "sg:city":"Prentiss",
    "sg:classifiers":[
        {
            "category":"Personal",
            "subcategory":"Beauty Salon",
            "type":"Services"
        }
    ],
    "sg:phone":"+1 601 792 4040",
    "sg:postcode":"39474",
    "sg:province":"MS",
    "wof:name":"Jay's Beauty Salon",
    "wof:placetype":"venue"
},
  "geometry": {"coordinates":[-89.870025,31.598484],"type":"Point"}
}