{
  "type": "Feature",
  "properties": {
    "iso:country":"US",
    "sg:address":"14 R C Thomas Rd",
    "sg:city":"Hattiesburg",
    "sg:classifiers":[
        {
            "category":"Retail",
            "subcategory":"Auto Repair",
            "type":"Services"
        }
    ],
    "sg:phone":"+1 601 582 4793",
    "sg:postcode":"39401",
    "sg:province":"MS",
    "sg:tags":[
        "repairing",
        "tire"
    ],
    "wof:name":"Thomas Tire Repair Service",
    "wof:placetype":"venue"
},
  "geometry": {"coordinates":[-89.27697499999999,31.249166],"type":"Point"}
}