{
  "type": "Feature",
  "properties": {
    "addr:full":"4750 Moncure Marble Rd Terry MS 39170",
    "addr:housenumber":"4750",
    "addr:postcode":"39170",
    "addr:street":"Moncure Marble Rd",
    "iso:country":"US",
    "sg:address":"4750 Moncure Marble Rd",
    "sg:city":"Terry",
    "sg:classifiers":[
        {
            "category":"Farming",
            "subcategory":"Livestock Farm",
            "type":"Manufacturing & Wholesale Goods"
        }
    ],
    "sg:phone":"+1 601 878 6627",
    "sg:postcode":"39170",
    "sg:province":"MS",
    "sg:tags":[
        "beef",
        "feedlot",
        "cattle"
    ],
    "wof:name":"Marble Farm",
    "wof:placetype":"venue"
},
  "geometry": {"coordinates":[-90.279757,32.056493],"type":"Point"}
}