{
  "type": "Feature",
  "properties": {
    "addr:full":"501 N Hayden St Belzoni MS 39038",
    "addr:housenumber":"501",
    "addr:postcode":"39038",
    "addr:street":"N Hayden St",
    "iso:country":"US",
    "sg:address":"501 N Hayden St",
    "sg:city":"Belzoni",
    "sg:classifiers":[
        {
            "category":"Social Services",
            "type":"Services"
        }
    ],
    "sg:phone":"+1 662 247 4048",
    "sg:postcode":"39038",
    "sg:province":"MS",
    "sg:tags":[
        "organization",
        "welfare"
    ],
    "wof:name":"Sunflower Humpries County Svc",
    "wof:placetype":"venue"
},
  "geometry": {"coordinates":[-90.48823400000001,33.191666],"type":"Point"}
}