{
  "type": "Feature",
  "properties": {
    "addr:full":"7900 Airways Blvd Bldg C6 Southaven MS 38671",
    "addr:postcode":"7900;38671",
    "addr:street":"Airways Blvd Bldg C6",
    "iso:country":"US",
    "sg:address":"7900 Airways Blvd Bldg C6",
    "sg:city":"Southaven",
    "sg:classifiers":[
        {
            "category":"Health Services",
            "subcategory":"Clinic",
            "type":"Services"
        },
        {
            "category":"Community Center",
            "type":"Public Place"
        }
    ],
    "sg:phone":"+1 662 349 2442",
    "sg:postcode":"38671",
    "sg:province":"MS",
    "sg:tags":[
        "medical"
    ],
    "wof:name":"University Of Tennessee Cancer Institute",
    "wof:placetype":"venue"
},
  "geometry": {"coordinates":[-89.989891,34.976084],"type":"Point"}
}