{
  "type": "Feature",
  "properties": {
    "iso:country":"US",
    "sg:address":"310 Greymont Ave",
    "sg:city":"Jackson",
    "sg:classifiers":[
        {
            "category":"Travel",
            "subcategory":"Hotels & Motels",
            "type":"Entertainment"
        }
    ],
    "sg:phone":"+1 601 948 4466",
    "sg:postcode":"39202",
    "sg:province":"MS",
    "sg:website":"www.holidayinn.com",
    "wof:name":"Holiday Inn Express Jackson",
    "wof:placetype":"venue"
},
  "geometry": {"coordinates":[-90.176011,32.297622],"type":"Point"}
}