{
  "type": "Feature",
  "properties": {
    "iso:country":"US",
    "sg:address":"2176 Willis Cotton Rd",
    "sg:city":"Summit",
    "sg:classifiers":[
        {
            "category":"Farming",
            "subcategory":"Farm",
            "type":"Manufacturing & Wholesale Goods"
        }
    ],
    "sg:phone":"+1 601 276 7847",
    "sg:postcode":"39666",
    "sg:province":"MS",
    "sg:tags":[
        "crop",
        "general"
    ],
    "wof:name":"Alfred Rimes",
    "wof:placetype":"venue"
},
  "geometry": {"coordinates":[-90.531539,31.307234],"type":"Point"}
}