{
  "type": "Feature",
  "properties": {
    "iso:country":"US",
    "sg:address":"50 State Hwy 587",
    "sg:city":"Foxworth",
    "sg:classifiers":[
        {
            "category":"Home & Garden",
            "subcategory":"Building Materials",
            "type":"Retail Goods"
        }
    ],
    "sg:phone":"+1 601 736 0830",
    "sg:postcode":"39483",
    "sg:province":"MS",
    "sg:tags":[
        "paint"
    ],
    "wof:name":"Owens Auto Parts",
    "wof:placetype":"venue"
},
  "geometry": {"coordinates":[-89.86579399999999,31.233949],"type":"Point"}
}