{
  "type": "Feature",
  "properties": {
    "addr:full":"428 State Hwy 145 N Booneville MS 38829",
    "addr:housenumber":"428",
    "addr:postcode":"38829",
    "addr:street":"State Hwy 145 N",
    "iso:country":"US",
    "sg:address":"428 State Hwy 145 N",
    "sg:city":"Booneville",
    "sg:classifiers":[
        {
            "category":"Retail",
            "subcategory":"Auto Repair",
            "type":"Services"
        }
    ],
    "sg:phone":"+1 662 720 1024",
    "sg:postcode":"38829",
    "sg:province":"MS",
    "sg:tags":[
        "transmission"
    ],
    "wof:name":"S & T Transmission",
    "wof:placetype":"venue"
},
  "geometry": {"coordinates":[-88.560523,34.722766],"type":"Point"}
}