{
  "type": "Feature",
  "properties": {
    "addr:full":"330 Hwy 12 W Starkville MS 39759",
    "addr:housenumber":"330",
    "addr:postcode":"39759",
    "addr:street":"Hwy 12 W",
    "iso:country":"US",
    "sg:address":"330 Hwy 12 W",
    "sg:city":"Starkville",
    "sg:classifiers":[
        {
            "category":"Shopping",
            "type":"Retail Goods"
        }
    ],
    "sg:phone":"+1 662 615 9920",
    "sg:postcode":"39759",
    "sg:province":"MS",
    "sg:tags":[
        "telephone",
        "cellular"
    ],
    "wof:name":"City Cellular II",
    "wof:placetype":"venue"
},
  "geometry": {"coordinates":[-88.823544,33.454004],"type":"Point"}
}