{
  "type": "Feature",
  "properties": {
    "iso:country":"US",
    "sg:address":"100 Ridgemont Cir",
    "sg:city":"Booneville",
    "sg:classifiers":[
        {
            "category":"Shopping",
            "subcategory":"Beauty & Cosmetics",
            "type":"Retail Goods"
        }
    ],
    "sg:phone":"+1 662 728 6613",
    "sg:postcode":"38829",
    "sg:province":"MS",
    "sg:tags":[
        "merchandise"
    ],
    "wof:name":"Merle Norman Cosmetics",
    "wof:placetype":"venue"
},
  "geometry": {"coordinates":[-88.566481,34.69607],"type":"Point"}
}