{
  "type": "Feature",
  "properties": {
    "iso:country":"US",
    "sg:address":"1305 Washington St",
    "sg:city":"Vicksburg",
    "sg:classifiers":[
        {
            "category":"Home & Garden",
            "subcategory":"Furniture",
            "type":"Retail Goods"
        },
        {
            "category":"Shopping",
            "subcategory":"Gifts & Souvenirs",
            "type":"Retail Goods"
        }
    ],
    "sg:phone":"+1 601 631 0081",
    "sg:postcode":"39180",
    "sg:province":"MS",
    "sg:tags":[
        "shop"
    ],
    "wof:name":"Willingham's",
    "wof:placetype":"venue"
},
  "geometry": {"coordinates":[-90.882057,32.350056],"type":"Point"}
}