{
  "type": "Feature",
  "properties": {
    "addr:full":"16334 Delancey Rd Saucier MS 39574",
    "addr:housenumber":"16334",
    "addr:postcode":"39574",
    "addr:street":"Delancey Rd",
    "iso:country":"US",
    "sg:address":"16334 Delancey Rd",
    "sg:city":"Saucier",
    "sg:classifiers":[
        {
            "category":"Personal",
            "subcategory":"Beauty Salon",
            "type":"Services"
        }
    ],
    "sg:phone":"+1 228 831 1020",
    "sg:postcode":"39574",
    "sg:province":"MS",
    "sg:tags":[
        "shop"
    ],
    "wof:name":"Cindys Nail & Tan Shop",
    "wof:placetype":"venue"
},
  "geometry": {"coordinates":[-89.11381299999999,30.584132],"type":"Point"}
}