{
  "type": "Feature",
  "properties": {
    "iso:country":"US",
    "sg:address":"3909 Halls Ferry Rd",
    "sg:city":"Vicksburg",
    "sg:classifiers":[
        {
            "category":"Professional",
            "subcategory":"Engineering",
            "type":"Services"
        }
    ],
    "sg:phone":"+1 601 634 3874",
    "sg:postcode":"39180",
    "sg:province":"MS",
    "sg:tags":[
        "electrical"
    ],
    "wof:name":"Craig Williamson",
    "wof:placetype":"venue"
},
  "geometry": {"coordinates":[-90.87334199999999,32.30195],"type":"Point"}
}