{
  "type": "Feature",
  "properties": {
    "addr:full":"415 S Commerce St Natchez MS 39120",
    "addr:housenumber":"415",
    "addr:postcode":"39120",
    "addr:street":"S Commerce St",
    "iso:country":"US",
    "sg:address":"415 S Commerce St",
    "sg:city":"Natchez",
    "sg:classifiers":[
        {
            "category":"Real Estate",
            "subcategory":"Real Estate Agent",
            "type":"Services"
        }
    ],
    "sg:phone":"+1 601 445 0504",
    "sg:postcode":"39120",
    "sg:province":"MS",
    "wof:name":"Stout & Co",
    "wof:placetype":"venue"
},
  "geometry": {"coordinates":[-91.404871,31.556779],"type":"Point"}
}