{
  "type": "Feature",
  "properties": {
    "iso:country":"US",
    "sg:address":"421 W Pearl St",
    "sg:city":"Grenada",
    "sg:classifiers":[
        {
            "category":"Home & Garden",
            "subcategory":"Household Appliances",
            "type":"Retail Goods"
        }
    ],
    "sg:phone":"+1 662 226 4014",
    "sg:postcode":"38901",
    "sg:province":"MS",
    "sg:website":"www.graebergas.com",
    "wof:name":"Graeber Brothers Inc-Grenada",
    "wof:placetype":"venue"
},
  "geometry": {"coordinates":[-89.80880000000001,33.786257],"type":"Point"}
}