{
  "type": "Feature",
  "properties": {
    "iso:country":"US",
    "sg:address":"4076 Rosebury Ln",
    "sg:city":"Horn Lake",
    "sg:classifiers":[
        {
            "category":"Building & Trades",
            "subcategory":"Construction",
            "type":"Services"
        }
    ],
    "sg:phone":"+1 662 393 8923",
    "sg:postcode":"38637",
    "sg:province":"MS",
    "sg:tags":[
        "carpentry",
        "contractor"
    ],
    "wof:name":"Newlife Construction",
    "wof:placetype":"venue"
},
  "geometry": {"coordinates":[-90.06153500000001,34.959597],"type":"Point"}
}