{
  "type": "Feature",
  "properties": {
    "iso:country":"US",
    "sg:address":"313 S 1st St NE",
    "sg:city":"Brookhaven",
    "sg:classifiers":[
        {
            "category":"Personal",
            "subcategory":"Beauty Salon",
            "type":"Services"
        }
    ],
    "sg:phone":"+1 601 833 8094",
    "sg:postcode":"39601",
    "sg:province":"MS",
    "wof:name":"LA-Shannon Hair Doctor",
    "wof:placetype":"venue"
},
  "geometry": {"coordinates":[-90.441664,31.576472],"type":"Point"}
}