{
  "type": "Feature",
  "properties": {
    "addr:full":"115 Hwy 19 N Meridian MS 39307",
    "addr:housenumber":"115",
    "addr:postcode":"39307",
    "addr:street":"Hwy 19 N",
    "iso:country":"US",
    "sg:address":"115 Hwy 19 N",
    "sg:city":"Meridian",
    "sg:classifiers":[
        {
            "category":"Home & Garden",
            "subcategory":"Household Appliances",
            "type":"Retail Goods"
        }
    ],
    "sg:phone":"+1 601 483 4011",
    "sg:postcode":"39307",
    "sg:province":"MS",
    "sg:tags":[
        "equipment",
        "lawn"
    ],
    "wof:name":"Cash Salvage Store",
    "wof:placetype":"venue"
},
  "geometry": {"coordinates":[-88.73043800000001,32.357467],"type":"Point"}
}