{
  "type": "Feature",
  "properties": {
    "addr:full":"214 S High School Ave Columbia MS 39429",
    "addr:housenumber":"214",
    "addr:postcode":"39429",
    "addr:street":"S;Ave",
    "iso:country":"US",
    "sg:address":"214 S High School Ave",
    "sg:city":"Columbia",
    "sg:classifiers":[
        {
            "category":"Manufacturing",
            "subcategory":"Tools & Machinery",
            "type":"Manufacturing & Wholesale Goods"
        }
    ],
    "sg:phone":"+1 601 731 1480",
    "sg:postcode":"39429",
    "sg:province":"MS",
    "sg:tags":[
        "machine",
        "shop"
    ],
    "wof:name":"Gas Processors Inc",
    "wof:placetype":"venue"
},
  "geometry": {"coordinates":[-89.832469,31.244736],"type":"Point"}
}