{
  "type": "Feature",
  "properties": {
    "addr:full":"1608 23rd Ave Gulfport MS 39501",
    "addr:housenumber":"1608",
    "addr:postcode":"39501",
    "addr:street":"23Rd Ave",
    "iso:country":"US",
    "sg:address":"1608 23rd Ave",
    "sg:city":"Gulfport",
    "sg:classifiers":[
        {
            "category":"Utilities",
            "subcategory":"Telephone",
            "type":"Services"
        }
    ],
    "sg:phone":"+1 228 863 1479",
    "sg:postcode":"39501",
    "sg:province":"MS",
    "sg:tags":[
        "communications"
    ],
    "wof:name":"MCI",
    "wof:placetype":"venue"
},
  "geometry": {"coordinates":[-89.09006100000001,30.371241],"type":"Point"}
}