{
  "type": "Feature",
  "properties": {
    "addr:full":"3232 Quave Rd Diberville MS 39540",
    "addr:housenumber":"3232",
    "addr:postcode":"39540",
    "addr:street":"Quave Rd",
    "iso:country":"US",
    "sg:address":"3232 Quave Rd",
    "sg:city":"Diberville",
    "sg:classifiers":[
        {
            "category":"Building & Trades",
            "subcategory":"Plumbing",
            "type":"Services"
        }
    ],
    "sg:phone":"+1 228 392 3773",
    "sg:postcode":"39540",
    "sg:province":"MS",
    "sg:tags":[
        "heating",
        "contractor"
    ],
    "wof:name":"Radich Heating Air Cond Inc",
    "wof:placetype":"venue"
},
  "geometry": {"coordinates":[-88.890351,30.431922],"type":"Point"}
}