{
  "type": "Feature",
  "properties": {
    "addr:full":"803 Garfield St Tupelo MS 38801",
    "addr:housenumber":"803",
    "addr:postcode":"38801",
    "addr:street":"Garfield St",
    "iso:country":"US",
    "sg:address":"803 Garfield St",
    "sg:city":"Tupelo",
    "sg:classifiers":[
        {
            "category":"Personal",
            "subcategory":"Beauty Salon",
            "type":"Services"
        }
    ],
    "sg:phone":"+1 662 620 7780",
    "sg:postcode":"38801",
    "sg:province":"MS",
    "wof:name":"Mixed Co Beauty Salon",
    "wof:placetype":"venue"
},
  "geometry": {"coordinates":[-88.718992,34.241184],"type":"Point"}
}