{
  "type": "Feature",
  "properties": {
    "addr:full":"1055 Lakeview Dr Grenada MS 38901",
    "addr:housenumber":"1055",
    "addr:postcode":"38901",
    "addr:street":"Lakeview Dr",
    "iso:country":"US",
    "sg:address":"1055 Lakeview Dr",
    "sg:city":"Grenada",
    "sg:classifiers":[
        {
            "category":"Wholesale",
            "subcategory":"Electrical",
            "type":"Manufacturing & Wholesale Goods"
        }
    ],
    "sg:phone":"+1 662 226 2293",
    "sg:postcode":"38901",
    "sg:province":"MS",
    "sg:tags":[
        "electric",
        "motor"
    ],
    "wof:name":"Grenada Electric Co",
    "wof:placetype":"venue"
},
  "geometry": {"coordinates":[-89.791972,33.771105],"type":"Point"}
}