{
  "type": "Feature",
  "properties": {
    "addr:full":"176 Gatorwood Rd Richton MS 39476",
    "addr:housenumber":"176",
    "addr:postcode":"39476",
    "addr:street":"Gatorwood Rd",
    "iso:country":"US",
    "sg:address":"176 Gatorwood Rd",
    "sg:city":"Richton",
    "sg:classifiers":[
        {
            "category":"Farming",
            "subcategory":"Livestock Farm",
            "type":"Manufacturing & Wholesale Goods"
        }
    ],
    "sg:phone":"+1 601 788 6773",
    "sg:postcode":"39476",
    "sg:province":"MS",
    "sg:tags":[
        "specialty",
        "animal"
    ],
    "wof:name":"Double E Kennels",
    "wof:placetype":"venue"
},
  "geometry": {"coordinates":[-88.95239100000001,31.404375],"type":"Point"}
}