{
  "type": "Feature",
  "properties": {
    "iso:country":"US",
    "sg:address":"9046 Millbranch Rd",
    "sg:city":"Southaven",
    "sg:classifiers":[
        {
            "category":"Restaurant",
            "type":"Food & Drink"
        }
    ],
    "sg:phone":"+1 662 393 4646",
    "sg:postcode":"38671",
    "sg:province":"MS",
    "wof:name":"Southern Blaze",
    "wof:placetype":"venue"
},
  "geometry": {"coordinates":[-90.007873,34.9926],"type":"Point"}
}