{
  "type": "Feature",
  "properties": {
    "addr:full":"6197 Hwy 613 Agricola MS 39452",
    "addr:housenumber":"6197",
    "addr:postcode":"39452",
    "addr:street":"Hwy 613 Agricola",
    "iso:country":"US",
    "sg:address":"6197 Hwy 613",
    "sg:city":"Agricola",
    "sg:classifiers":[
        {
            "category":"Food & Beverages",
            "subcategory":"Groceries & Convenience Stores",
            "type":"Retail Goods"
        }
    ],
    "sg:phone":"+1 601 947 7811",
    "sg:postcode":"39452",
    "sg:province":"MS",
    "sg:tags":[
        "grocer"
    ],
    "wof:name":"Agricola Quick Stop",
    "wof:placetype":"venue"
},
  "geometry": {"coordinates":[-88.517709,30.821379],"type":"Point"}
}