{
  "type": "Feature",
  "properties": {
    "iso:country":"US",
    "sg:address":"664 Hwy 6 W",
    "sg:city":"Oxford",
    "sg:classifiers":[
        {
            "category":"Shopping",
            "subcategory":"Discount & Variety Stores",
            "type":"Retail Goods"
        }
    ],
    "sg:phone":"+1 662 234 2353",
    "sg:postcode":"38655",
    "sg:province":"MS",
    "sg:tags":[
        "merchandise",
        "general"
    ],
    "wof:name":"Mid South Auto Store",
    "wof:placetype":"venue"
},
  "geometry": {"coordinates":[-89.630173,34.357725],"type":"Point"}
}