{
  "type": "Feature",
  "properties": {
    "addr:full":"548 S Archusa Ave Quitman MS 39355",
    "addr:housenumber":"548",
    "addr:postcode":"39355",
    "addr:street":"S Archusa Ave",
    "iso:country":"US",
    "sg:address":"548 S Archusa Ave",
    "sg:city":"Quitman",
    "sg:classifiers":[
        {
            "category":"Shopping",
            "subcategory":"Department Store",
            "type":"Retail Goods"
        }
    ],
    "sg:phone":"+1 601 776 3233",
    "sg:postcode":"39355",
    "sg:province":"MS",
    "sg:tags":[
        "shop"
    ],
    "wof:name":"Family Dollar Store",
    "wof:placetype":"venue"
},
  "geometry": {"coordinates":[-88.727981,32.036216],"type":"Point"}
}