{
  "type": "Feature",
  "properties": {
    "iso:country":"US",
    "sg:address":"10939 Hwy 178",
    "sg:city":"Olive Branch",
    "sg:classifiers":[
        {
            "category":"Building & Trades",
            "subcategory":"Construction",
            "type":"Services"
        }
    ],
    "sg:phone":"+1 662 890 3680",
    "sg:postcode":"38654",
    "sg:province":"MS",
    "sg:tags":[
        "resurfacing",
        "laying",
        "refinishing",
        "floor"
    ],
    "wof:name":"K & R Flooring",
    "wof:placetype":"venue"
},
  "geometry": {"coordinates":[-89.796442,34.933416],"type":"Point"}
}