{
  "type": "Feature",
  "properties": {
    "iso:country":"US",
    "sg:address":"1501 W Government St",
    "sg:city":"Brandon",
    "sg:classifiers":[
        {
            "category":"Autos & Motor Vehicles",
            "subcategory":"Automobile Sales",
            "type":"Retail Goods"
        }
    ],
    "sg:phone":"+1 601 825 2277",
    "sg:postcode":"39042",
    "sg:province":"MS",
    "sg:tags":[
        "truck"
    ],
    "sg:website":"www.rogersdabbs.com",
    "wof:name":"Rogers-Dabbs Chevrolet Hummer",
    "wof:placetype":"venue"
},
  "geometry": {"coordinates":[-90.003103,32.279891],"type":"Point"}
}