{
  "type": "Feature",
  "properties": {
    "iso:country":"US",
    "sg:address":"127 W Church St",
    "sg:city":"Newton",
    "sg:classifiers":[
        {
            "category":"Professional",
            "subcategory":"Accounting & Tax Preparation",
            "type":"Services"
        }
    ],
    "sg:phone":"+1 601 683 7206",
    "sg:postcode":"39345",
    "sg:province":"MS",
    "sg:tags":[
        "return",
        "filing"
    ],
    "wof:name":"Sav-A-Tax Svc",
    "wof:placetype":"venue"
},
  "geometry": {"coordinates":[-89.163946,32.32182],"type":"Point"}
}