{
  "type": "Feature",
  "properties": {
    "iso:country":"US",
    "sg:address":"100 Clinton Blvd",
    "sg:city":"Clinton",
    "sg:classifiers":[
        {
            "category":"Insurance",
            "subcategory":"Insurance Agent",
            "type":"Services"
        }
    ],
    "sg:phone":"+1 601 924 4541",
    "sg:postcode":"39056",
    "sg:province":"MS",
    "wof:name":"Nationwide Insurance",
    "wof:placetype":"venue"
},
  "geometry": {"coordinates":[-90.316884,32.335018],"type":"Point"}
}