{
  "type": "Feature",
  "properties": {
    "iso:country":"US",
    "sg:address":"296 Grimes Rd",
    "sg:city":"Carthage",
    "sg:classifiers":[
        {
            "category":"Farming",
            "subcategory":"Dairy Farm",
            "type":"Manufacturing & Wholesale Goods"
        }
    ],
    "sg:phone":"+1 601 267 0112",
    "sg:postcode":"39051",
    "sg:province":"MS",
    "wof:name":"Jerry Corkern",
    "wof:placetype":"venue"
},
  "geometry": {"coordinates":[-89.52713900000001,32.656677],"type":"Point"}
}