{
  "type": "Feature",
  "properties": {
    "iso:country":"US",
    "sg:address":"600 N Applegate St",
    "sg:city":"Winona",
    "sg:classifiers":[
        {
            "category":"Restaurant",
            "type":"Food & Drink"
        }
    ],
    "sg:phone":"+1 662 283 5806",
    "sg:postcode":"38967",
    "sg:province":"MS",
    "sg:tags":[
        "eating"
    ],
    "wof:name":"Winona City Cafe",
    "wof:placetype":"venue"
},
  "geometry": {"coordinates":[-89.736092,33.49206],"type":"Point"}
}