{
  "type": "Feature",
  "properties": {
    "addr:full":"4005 N State St Jackson MS 39206",
    "addr:housenumber":"4005",
    "addr:postcode":"39206",
    "addr:street":"N State St",
    "iso:country":"US",
    "sg:address":"4005 N State St",
    "sg:city":"Jackson",
    "sg:classifiers":[
        {
            "category":"Banks & Credit Unions",
            "subcategory":"Bank",
            "type":"Services"
        }
    ],
    "sg:phone":"+1 601 713 2770",
    "sg:postcode":"39206",
    "sg:province":"MS",
    "sg:tags":[
        "broker",
        "mortgage"
    ],
    "wof:name":"Hurricane Mortgage Company",
    "wof:placetype":"venue"
},
  "geometry": {"coordinates":[-90.175659,32.347627],"type":"Point"}
}