{
  "type": "Feature",
  "properties": {
    "iso:country":"US",
    "sg:address":"2300 N Hills St",
    "sg:city":"Meridian",
    "sg:classifiers":[
        {
            "category":"Cinema",
            "subcategory":"Movie Rental",
            "type":"Entertainment"
        }
    ],
    "sg:phone":"+1 601 482 7767",
    "sg:postcode":"39305",
    "sg:province":"MS",
    "sg:tags":[
        "video",
        "tape"
    ],
    "wof:name":"Blockbuster",
    "wof:placetype":"venue"
},
  "geometry": {"coordinates":[-88.698989,32.40943],"type":"Point"}
}