{
  "type": "Feature",
  "properties": {
    "iso:country":"US",
    "sg:address":"1940 29th St",
    "sg:city":"Gulfport",
    "sg:classifiers":[
        {
            "category":"Retail",
            "subcategory":"Auto Repair",
            "type":"Services"
        }
    ],
    "sg:phone":"+1 228 864 0047",
    "sg:postcode":"39501",
    "sg:province":"MS",
    "sg:tags":[
        "body",
        "automobile",
        "painting"
    ],
    "wof:name":"Kar Auto Body",
    "wof:placetype":"venue"
},
  "geometry": {"coordinates":[-89.085892,30.385435],"type":"Point"}
}