{
  "type": "Feature",
  "properties": {
    "iso:country":"US",
    "sg:address":"126 Crown Ct",
    "sg:city":"Natchez",
    "sg:classifiers":[
        {
            "category":"Organizations",
            "subcategory":"Religious Organization",
            "type":"Services"
        }
    ],
    "sg:phone":"+1 601 446 9480",
    "sg:postcode":"39120",
    "sg:province":"MS",
    "sg:tags":[
        "church"
    ],
    "wof:name":"Faith Tabernacle Church",
    "wof:placetype":"venue"
},
  "geometry": {"coordinates":[-91.35380600000001,31.593932],"type":"Point"}
}