{
  "type": "Feature",
  "properties": {
    "iso:country":"US",
    "sg:address":"1003 E Main St",
    "sg:city":"Philadelphia",
    "sg:classifiers":[
        {
            "category":"Health Services",
            "subcategory":"Optometrist",
            "type":"Services"
        }
    ],
    "sg:phone":"+1 601 656 8454",
    "sg:postcode":"39350",
    "sg:province":"MS",
    "sg:tags":[
        "clinic"
    ],
    "wof:name":"Vision Clinic",
    "wof:placetype":"venue"
},
  "geometry": {"coordinates":[-89.094127,32.770761],"type":"Point"}
}