{
  "type": "Feature",
  "properties": {
    "iso:country":"US",
    "sg:address":"7030 Hwy 72",
    "sg:city":"Walnut",
    "sg:classifiers":[
        {
            "category":"Autos & Motor Vehicles",
            "subcategory":"Fuel & Gas Station",
            "type":"Retail Goods"
        }
    ],
    "sg:phone":"+1 662 223 6721",
    "sg:postcode":"38683",
    "sg:province":"MS",
    "sg:tags":[
        "oil"
    ],
    "wof:name":"Walnut Exxon",
    "wof:placetype":"venue"
},
  "geometry": {"coordinates":[-88.891774,34.951914],"type":"Point"}
}