{
  "type": "Feature",
  "properties": {
    "iso:country":"US",
    "sg:address":"5100 N State St",
    "sg:city":"Jackson",
    "sg:classifiers":[
        {
            "category":"Food & Beverages",
            "subcategory":"Groceries & Convenience Stores",
            "type":"Retail Goods"
        }
    ],
    "sg:phone":"+1 601 982 0196",
    "sg:postcode":"39206",
    "sg:province":"MS",
    "wof:name":"Jr Food Market",
    "wof:placetype":"venue"
},
  "geometry": {"coordinates":[-90.169203,32.367136],"type":"Point"}
}