{
  "type": "Feature",
  "properties": {
    "iso:country":"US",
    "sg:address":"519 S Main St",
    "sg:city":"Forest",
    "sg:classifiers":[
        {
            "category":"Personal",
            "subcategory":"Beauty Salon",
            "type":"Services"
        }
    ],
    "sg:phone":"+1 601 469 3301",
    "sg:postcode":"39074",
    "sg:province":"MS",
    "wof:name":"KLIP-N-KURL Beauty Shop",
    "wof:placetype":"venue"
},
  "geometry": {"coordinates":[-89.474733,32.359202],"type":"Point"}
}