{
  "type": "Feature",
  "properties": {
    "iso:country":"US",
    "sg:address":"8138 Hwy 613",
    "sg:city":"Lucedale",
    "sg:classifiers":[
        {
            "category":"Home & Garden",
            "subcategory":"Garden Supply",
            "type":"Retail Goods"
        }
    ],
    "sg:phone":"+1 601 947 4185",
    "sg:postcode":"39452",
    "sg:province":"MS",
    "wof:name":"P & L Nursery",
    "wof:placetype":"venue"
},
  "geometry": {"coordinates":[-88.521434,30.83973],"type":"Point"}
}