{
  "type": "Feature",
  "properties": {
    "addr:full":"563 Hwy 7 N Oxford MS 38655",
    "addr:housenumber":"563",
    "addr:postcode":"38655",
    "addr:street":"Hwy 7 N",
    "iso:country":"US",
    "sg:address":"563 Hwy 7 N",
    "sg:city":"Oxford",
    "sg:classifiers":[
        {
            "category":"Organizations",
            "subcategory":"Religious Organization",
            "type":"Services"
        }
    ],
    "sg:phone":"+1 662 513 0160",
    "sg:postcode":"38655",
    "sg:province":"MS",
    "sg:tags":[
        "church"
    ],
    "wof:name":"Faith Baptist Church",
    "wof:placetype":"venue"
},
  "geometry": {"coordinates":[-89.500918,34.448667],"type":"Point"}
}