{
  "type": "Feature",
  "properties": {
    "addr:full":"4860 Bethel Rd Olive Branch MS 38654",
    "addr:housenumber":"4860",
    "addr:postcode":"38654",
    "addr:street":"Bethel Rd",
    "iso:country":"US",
    "sg:address":"4860 Bethel Rd",
    "sg:city":"Olive Branch",
    "sg:classifiers":[
        {
            "category":"Food & Beverages",
            "subcategory":"Liquor & Beverages",
            "type":"Retail Goods"
        }
    ],
    "sg:phone":"+1 662 890 7475",
    "sg:postcode":"38654",
    "sg:province":"MS",
    "wof:name":"Package Store",
    "wof:placetype":"venue"
},
  "geometry": {"coordinates":[-89.79481800000001,34.923658],"type":"Point"}
}