{
  "type": "Feature",
  "properties": {
    "iso:country":"US",
    "sg:address":"200 W Jefferson St",
    "sg:city":"Tupelo",
    "sg:classifiers":[
        {
            "category":"Government",
            "subcategory":"Office",
            "type":"Public Place"
        }
    ],
    "sg:phone":"+1 662 841 9103",
    "sg:postcode":"38804",
    "sg:province":"MS",
    "wof:name":"Lee County Purchasing",
    "wof:placetype":"venue"
},
  "geometry": {"coordinates":[-88.70544,34.259174],"type":"Point"}
}