{
  "type": "Feature",
  "properties": {
    "addr:full":"701 Main St Columbia MS 39429",
    "addr:housenumber":"701",
    "addr:postcode":"39429",
    "addr:street":"Main St",
    "iso:country":"US",
    "sg:address":"701 Main St",
    "sg:city":"Columbia",
    "sg:classifiers":[
        {
            "category":"Organizations",
            "subcategory":"Religious Organization",
            "type":"Services"
        }
    ],
    "sg:phone":"+1 601 736 7144",
    "sg:postcode":"39429",
    "sg:province":"MS",
    "sg:tags":[
        "church"
    ],
    "wof:name":"Church On Main",
    "wof:placetype":"venue"
},
  "geometry": {"coordinates":[-89.83524800000001,31.251807],"type":"Point"}
}