{
  "type": "Feature",
  "properties": {
    "addr:full":"210 Hwy 12 E Starkville MS 39759",
    "addr:housenumber":"210",
    "addr:postcode":"39759",
    "addr:street":"Hwy 12 E",
    "iso:country":"US",
    "sg:address":"210 Hwy 12 E",
    "sg:city":"Starkville",
    "sg:classifiers":[
        {
            "category":"Banks & Credit Unions",
            "subcategory":"Bank",
            "type":"Services"
        }
    ],
    "sg:phone":"+1 662 323 4740",
    "sg:postcode":"39759",
    "sg:province":"MS",
    "sg:tags":[
        "federal",
        "savings",
        "institution"
    ],
    "wof:name":"Citifinancial",
    "wof:placetype":"venue"
},
  "geometry": {"coordinates":[-88.80968900000001,33.454477],"type":"Point"}
}