{
  "type": "Feature",
  "properties": {
    "iso:country":"US",
    "sg:address":"549 Co Rd 362",
    "sg:city":"Enterprise",
    "sg:classifiers":[
        {
            "category":"Retail",
            "subcategory":"Auto Repair",
            "type":"Services"
        }
    ],
    "sg:phone":"+1 601 659 7400",
    "sg:postcode":"39330",
    "sg:province":"MS",
    "sg:tags":[
        "wrecker"
    ],
    "wof:name":"Larry King's Wrecking & Towing",
    "wof:placetype":"venue"
},
  "geometry": {"coordinates":[-88.88571399999999,32.196465],"type":"Point"}
}