{
  "type": "Feature",
  "properties": {
    "addr:full":"4143 Leroy St Moss Point MS 39563",
    "addr:housenumber":"4143",
    "addr:postcode":"39563",
    "addr:street":"Leroy St",
    "iso:country":"US",
    "sg:address":"4143 Leroy St",
    "sg:city":"Moss Point",
    "sg:classifiers":[
        {
            "category":"Shopping",
            "type":"Retail Goods"
        }
    ],
    "sg:phone":"+1 228 475 8599",
    "sg:postcode":"39563",
    "sg:province":"MS",
    "sg:tags":[
        "merchandise"
    ],
    "wof:name":"Artistic Affairs",
    "wof:placetype":"venue"
},
  "geometry": {"coordinates":[-88.521401,30.40176],"type":"Point"}
}