{
  "type": "Feature",
  "properties": {
    "addr:full":"321 W Madison St Houston MS 38851",
    "addr:housenumber":"321",
    "addr:postcode":"38851",
    "addr:street":"W Madison St",
    "iso:country":"US",
    "sg:address":"321 W Madison St",
    "sg:city":"Houston",
    "sg:classifiers":[
        {
            "category":"Manufacturing",
            "subcategory":"Tools & Machinery",
            "type":"Manufacturing & Wholesale Goods"
        }
    ],
    "sg:phone":"+1 662 456 5642",
    "sg:postcode":"38851",
    "sg:province":"MS",
    "sg:tags":[
        "industry",
        "mfg"
    ],
    "wof:name":"Chief Water Systems",
    "wof:placetype":"venue"
},
  "geometry": {"coordinates":[-89.003761,33.896522],"type":"Point"}
}