{
  "type": "Feature",
  "properties": {
    "iso:country":"US",
    "sg:address":"401 E Capitol St",
    "sg:city":"Jackson",
    "sg:classifiers":[
        {
            "category":"Mining & Drilling",
            "type":"Manufacturing & Wholesale Goods"
        },
        {
            "category":"Manufacturing",
            "subcategory":"Printing",
            "type":"Manufacturing & Wholesale Goods"
        }
    ],
    "sg:phone":"+1 601 353 6213",
    "sg:postcode":"39201",
    "sg:province":"MS",
    "sg:tags":[
        "report",
        "oil",
        "periodical"
    ],
    "wof:name":"Southeastern Oil Review",
    "wof:placetype":"venue"
},
  "geometry": {"coordinates":[-90.181732,32.299473],"type":"Point"}
}