{
  "type": "Feature",
  "properties": {
    "iso:country":"US",
    "sg:address":"722 W Bankhead St",
    "sg:city":"New Albany",
    "sg:classifiers":[
        {
            "category":"Real Estate",
            "subcategory":"Real Estate Services",
            "type":"Services"
        }
    ],
    "sg:phone":"+1 662 534 7773",
    "sg:postcode":"38652",
    "sg:province":"MS",
    "sg:tags":[
        "company",
        "title"
    ],
    "wof:name":"Beneficial Title Pledge",
    "wof:placetype":"venue"
},
  "geometry": {"coordinates":[-89.025445,34.50064],"type":"Point"}
}