{
  "type": "Feature",
  "properties": {
    "iso:country":"US",
    "sg:address":"115 W Main St",
    "sg:city":"Mc Lain",
    "sg:classifiers":[
        {
            "category":"Food & Beverages",
            "subcategory":"Groceries & Convenience Stores",
            "type":"Retail Goods"
        }
    ],
    "sg:phone":"+1 601 753 2519",
    "sg:postcode":"39456",
    "sg:province":"MS",
    "sg:tags":[
        "grocer"
    ],
    "wof:name":"Community Grocery",
    "wof:placetype":"venue"
},
  "geometry": {"coordinates":[-88.828247,31.109316],"type":"Point"}
}