{
  "type": "Feature",
  "properties": {
    "addr:full":"106 Hwy 12 W Kosciusko MS 39090",
    "addr:housenumber":"106",
    "addr:postcode":"39090",
    "addr:street":"Hwy 12 W",
    "iso:country":"US",
    "sg:address":"106 Hwy 12 W",
    "sg:city":"Kosciusko",
    "sg:classifiers":[
        {
            "category":"Banks & Credit Unions",
            "subcategory":"Bank",
            "type":"Services"
        }
    ],
    "sg:phone":"+1 662 289 3217",
    "sg:postcode":"39090",
    "sg:province":"MS",
    "sg:tags":[
        "cashing",
        "check"
    ],
    "wof:name":"Check Store",
    "wof:placetype":"venue"
},
  "geometry": {"coordinates":[-89.590554,33.065934],"type":"Point"}
}