{
  "type": "Feature",
  "properties": {
    "addr:full":"3602 Hardy St Hattiesburg MS 39402",
    "addr:housenumber":"3602",
    "addr:postcode":"39402",
    "addr:street":"Hardy St",
    "iso:country":"US",
    "sg:address":"3602 Hardy St",
    "sg:city":"Hattiesburg",
    "sg:classifiers":[
        {
            "category":"Utilities",
            "subcategory":"Mobile Phone",
            "type":"Services"
        }
    ],
    "sg:phone":"+1 601 579 9400",
    "sg:postcode":"39402",
    "sg:province":"MS",
    "sg:tags":[
        "communication",
        "radiotelephone"
    ],
    "wof:name":"Sprint",
    "wof:placetype":"venue"
},
  "geometry": {"coordinates":[-89.343785,31.324995],"type":"Point"}
}