{
  "type": "Feature",
  "properties": {
    "addr:full":"911 Bouie St Hattiesburg MS 39401",
    "addr:housenumber":"911",
    "addr:postcode":"39401",
    "addr:street":"Bouie St",
    "iso:country":"US",
    "sg:address":"911 Bouie St",
    "sg:city":"Hattiesburg",
    "sg:classifiers":[
        {
            "category":"Retail",
            "subcategory":"Auto Repair",
            "type":"Services"
        }
    ],
    "sg:phone":"+1 601 583 6959",
    "sg:postcode":"39401",
    "sg:province":"MS",
    "sg:tags":[
        "repairing",
        "automobile"
    ],
    "wof:name":"Gary's Auto Repair",
    "wof:placetype":"venue"
},
  "geometry": {"coordinates":[-89.287176,31.339416],"type":"Point"}
}