{
  "type": "Feature",
  "properties": {
    "addr:full":"19 Terrapin Hill Rd S Brandon MS 39042",
    "addr:housenumber":"19",
    "addr:postcode":"39042",
    "addr:street":"Terrapin Hill Rd S",
    "iso:country":"US",
    "sg:address":"19 Terrapin Hill Rd S",
    "sg:city":"Brandon",
    "sg:classifiers":[
        {
            "category":"Retail",
            "subcategory":"Laundry & Dry Cleaning",
            "type":"Services"
        }
    ],
    "sg:phone":"+1 601 591 4076",
    "sg:postcode":"39042",
    "sg:province":"MS",
    "sg:tags":[
        "sewing"
    ],
    "wof:name":"CK Designs",
    "wof:placetype":"venue"
},
  "geometry": {"coordinates":[-90.02691,32.291692],"type":"Point"}
}