{
  "type": "Feature",
  "properties": {
    "iso:country":"US",
    "sg:address":"18 Stafford Rd",
    "sg:city":"Picayune",
    "sg:classifiers":[
        {
            "category":"Organizations",
            "subcategory":"Religious Organization",
            "type":"Services"
        }
    ],
    "sg:phone":"+1 601 798 7655",
    "sg:postcode":"39466",
    "sg:province":"MS",
    "sg:tags":[
        "church"
    ],
    "wof:name":"Anointed Dove Gospel Baptist",
    "wof:placetype":"venue"
},
  "geometry": {"coordinates":[-89.64945400000001,30.518032],"type":"Point"}
}