{
  "type": "Feature",
  "properties": {
    "iso:country":"US",
    "sg:address":"1110 Wright St",
    "sg:city":"Greenwood",
    "sg:classifiers":[
        {
            "category":"Communications",
            "subcategory":"Radio Station",
            "type":"Services"
        }
    ],
    "sg:phone":"+1 662 453 1240",
    "sg:postcode":"38930",
    "sg:province":"MS",
    "sg:tags":[
        "broadcast"
    ],
    "wof:name":"Radio Station W G R M",
    "wof:placetype":"venue"
},
  "geometry": {"coordinates":[-90.195425,33.53375],"type":"Point"}
}