{
  "type": "Feature",
  "properties": {
    "addr:full":"2610 Hardy St Hattiesburg MS 39401",
    "addr:housenumber":"2610",
    "addr:postcode":"39401",
    "addr:street":"Hardy St",
    "iso:country":"US",
    "sg:address":"2610 Hardy St",
    "sg:city":"Hattiesburg",
    "sg:classifiers":[
        {
            "category":"Personal",
            "subcategory":"Tattoo Parlor",
            "type":"Services"
        }
    ],
    "sg:phone":"+1 601 450 8282",
    "sg:postcode":"39401",
    "sg:province":"MS",
    "sg:tags":[
        "tattooing"
    ],
    "wof:name":"Clan Of The Red Claw Tattoos",
    "wof:placetype":"venue"
},
  "geometry": {"coordinates":[-89.32932,31.324646],"type":"Point"}
}