{
  "type": "Feature",
  "properties": {
    "iso:country":"US",
    "sg:address":"1063 E County Line Rd",
    "sg:city":"Jackson",
    "sg:classifiers":[
        {
            "category":"Home & Garden",
            "subcategory":"Furniture",
            "type":"Retail Goods"
        }
    ],
    "sg:phone":"+1 601 991 9377",
    "sg:postcode":"39211",
    "sg:province":"MS",
    "sg:website":"www.unfinishedfurnitureshowcase.com",
    "wof:name":"Unfinished Furniture Showcase",
    "wof:placetype":"venue"
},
  "geometry": {"coordinates":[-90.140783,32.399406],"type":"Point"}
}