{
  "type": "Feature",
  "properties": {
    "addr:full":"1258 Mabry Rd Lake Cormorant MS 38641",
    "addr:housenumber":"1258",
    "addr:postcode":"38641",
    "addr:street":"Mabry Rd",
    "iso:country":"US",
    "sg:address":"1258 Mabry Rd",
    "sg:city":"Lake Cormorant",
    "sg:classifiers":[
        {
            "category":"Farming",
            "subcategory":"Farm & Veterinary Services",
            "type":"Manufacturing & Wholesale Goods"
        }
    ],
    "sg:phone":"+1 662 429 3831",
    "sg:postcode":"38641",
    "sg:province":"MS",
    "sg:tags":[
        "livestock"
    ],
    "wof:name":"Wallis Jewel D",
    "wof:placetype":"venue"
},
  "geometry": {"coordinates":[-90.10426099999999,34.879135],"type":"Point"}
}