{
  "type": "Feature",
  "properties": {
    "iso:country":"US",
    "sg:address":"975 Main St",
    "sg:city":"Southaven",
    "sg:classifiers":[
        {
            "category":"Restaurant",
            "type":"Food & Drink"
        }
    ],
    "sg:phone":"+1 662 393 5988",
    "sg:postcode":"38671",
    "sg:province":"MS",
    "sg:tags":[
        "chinese"
    ],
    "wof:name":"Lucky China",
    "wof:placetype":"venue"
},
  "geometry": {"coordinates":[-90.00739799999999,34.991857],"type":"Point"}
}