{
  "type": "Feature",
  "properties": {
    "addr:full":"307 E Gould Ave Eupora MS 39744",
    "addr:housenumber":"307",
    "addr:postcode":"39744",
    "addr:street":"E Gould Ave",
    "iso:country":"US",
    "sg:address":"307 E Gould Ave",
    "sg:city":"Eupora",
    "sg:classifiers":[
        {
            "category":"Building & Trades",
            "subcategory":"Construction",
            "type":"Services"
        }
    ],
    "sg:phone":"+1 662 258 8253",
    "sg:postcode":"39744",
    "sg:province":"MS",
    "sg:tags":[
        "marking",
        "maintenance",
        "parking"
    ],
    "wof:name":"Eupora City Street Dept",
    "wof:placetype":"venue"
},
  "geometry": {"coordinates":[-89.262339,33.535262],"type":"Point"}
}