{
  "type": "Feature",
  "properties": {
    "addr:full":"2924 US Hwy 51 Canton MS 39046",
    "addr:housenumber":"2924",
    "addr:postcode":"39046",
    "addr:street":"Us Hwy 51",
    "iso:country":"US",
    "sg:address":"2924 US Hwy 51",
    "sg:city":"Canton",
    "sg:classifiers":[
        {
            "category":"Government",
            "subcategory":"Office",
            "type":"Public Place"
        }
    ],
    "sg:phone":"+1 601 859 3692",
    "sg:postcode":"39046",
    "sg:province":"MS",
    "sg:tags":[
        "state",
        "security",
        "national"
    ],
    "wof:name":"National Guard",
    "wof:placetype":"venue"
},
  "geometry": {"coordinates":[-90.056038,32.568299],"type":"Point"}
}