{
  "type": "Feature",
  "properties": {
    "iso:country":"US",
    "sg:address":"4903 Halls Ferry Rd",
    "sg:city":"Vicksburg",
    "sg:classifiers":[
        {
            "category":"Professional",
            "subcategory":"Accounting & Tax Preparation",
            "type":"Services"
        }
    ],
    "sg:phone":"+1 601 661 0044",
    "sg:postcode":"39180",
    "sg:province":"MS",
    "sg:tags":[
        "return",
        "filing"
    ],
    "wof:name":"Lamax's Tax & Accounting",
    "wof:placetype":"venue"
},
  "geometry": {"coordinates":[-90.85035999999999,32.286449],"type":"Point"}
}