{
  "type": "Feature",
  "properties": {
    "addr:full":"3003 Belair St Pascagoula MS 39567",
    "addr:housenumber":"3003",
    "addr:postcode":"39567",
    "addr:street":"Belair St",
    "iso:country":"US",
    "sg:address":"3003 Belair St",
    "sg:city":"Pascagoula",
    "sg:classifiers":[
        {
            "category":"Organizations",
            "subcategory":"Religious Organization",
            "type":"Services"
        }
    ],
    "sg:phone":"+1 228 762 7293",
    "sg:postcode":"39567",
    "sg:province":"MS",
    "sg:tags":[
        "baptist",
        "church"
    ],
    "wof:name":"Lighthouse Baptist Church",
    "wof:placetype":"venue"
},
  "geometry": {"coordinates":[-88.53534000000001,30.365142],"type":"Point"}
}