{
  "type": "Feature",
  "properties": {
    "addr:full":"308 US Hwy 90 Waveland MS 39576",
    "addr:housenumber":"308",
    "addr:postcode":"39576",
    "addr:street":"Us Hwy 90",
    "iso:country":"US",
    "sg:address":"308 US Hwy 90",
    "sg:city":"Waveland",
    "sg:classifiers":[
        {
            "category":"Professional",
            "subcategory":"Accounting & Tax Preparation",
            "type":"Services"
        }
    ],
    "sg:phone":"+1 228 467 5994",
    "sg:postcode":"39576",
    "sg:province":"MS",
    "sg:tags":[
        "bookkeeping",
        "general"
    ],
    "wof:name":"BGN Accounting Svc",
    "wof:placetype":"venue"
},
  "geometry": {"coordinates":[-89.376769,30.306691],"type":"Point"}
}