{
  "type": "Feature",
  "properties": {
    "iso:country":"US",
    "sg:address":"107 L & W Rd",
    "sg:city":"Laurel",
    "sg:classifiers":[
        {
            "category":"Building & Trades",
            "subcategory":"Electrical",
            "type":"Services"
        }
    ],
    "sg:phone":"+1 601 649 2325",
    "sg:postcode":"39440",
    "sg:province":"MS",
    "sg:tags":[
        "electrical",
        "contractor"
    ],
    "wof:name":"Air Plus Haskel Stewart",
    "wof:placetype":"venue"
},
  "geometry": {"coordinates":[-89.1439,31.67504],"type":"Point"}
}