{
  "type": "Feature",
  "properties": {
    "iso:country":"US",
    "sg:address":"4560 Venture Dr",
    "sg:city":"Southaven",
    "sg:classifiers":[
        {
            "category":"Recreation",
            "subcategory":"Picnic Area",
            "type":"Entertainment"
        },
        {
            "category":"Community Center",
            "type":"Public Place"
        }
    ],
    "sg:phone":"+1 662 280 3454",
    "sg:postcode":"38671",
    "sg:province":"MS",
    "sg:tags":[
        "amusement",
        "arcade"
    ],
    "wof:name":"Ticketmaster",
    "wof:placetype":"venue"
},
  "geometry": {"coordinates":[-89.99919800000001,34.928399],"type":"Point"}
}