{
  "type": "Feature",
  "properties": {
    "iso:country":"US",
    "sg:address":"723 N College St",
    "sg:city":"Booneville",
    "sg:phone":"+1 662 728 5073",
    "sg:postcode":"38829",
    "sg:province":"MS",
    "sg:tags":[
        "gas"
    ],
    "wof:name":"Dowdle Gas Co",
    "wof:placetype":"venue"
},
  "geometry": {"coordinates":[-88.560304,34.663675],"type":"Point"}
}