{
  "type": "Feature",
  "properties": {
    "iso:country":"US",
    "sg:address":"490 E Woodrow Wilson Ave",
    "sg:city":"Jackson",
    "sg:classifiers":[
        {
            "category":"Manufacturing",
            "subcategory":"Lumber",
            "type":"Manufacturing & Wholesale Goods"
        }
    ],
    "sg:phone":"+1 601 362 0019",
    "sg:postcode":"39216",
    "sg:province":"MS",
    "wof:name":"Southern Lumber Co",
    "wof:placetype":"venue"
},
  "geometry": {"coordinates":[-90.17925700000001,32.326814],"type":"Point"}
}