{
  "type": "Feature",
  "properties": {
    "iso:country":"US",
    "sg:address":"393 Crossgates Blvd",
    "sg:city":"Brandon",
    "sg:classifiers":[
        {
            "category":"Health Services",
            "subcategory":"Clinic",
            "type":"Services"
        }
    ],
    "sg:phone":"+1 601 824 9700",
    "sg:postcode":"39042",
    "sg:province":"MS",
    "sg:tags":[
        "kidney",
        "dialysis",
        "center"
    ],
    "wof:name":"Rankin Dialysis Center",
    "wof:placetype":"venue"
},
  "geometry": {"coordinates":[-90.036034,32.285713],"type":"Point"}
}