{
  "type": "Feature",
  "properties": {
    "iso:country":"US",
    "sg:address":"191 Mask Rd",
    "sg:city":"Shannon",
    "sg:classifiers":[
        {
            "category":"Farming",
            "subcategory":"Farm",
            "type":"Manufacturing & Wholesale Goods"
        }
    ],
    "sg:phone":"+1 662 489 6453",
    "sg:postcode":"38868",
    "sg:province":"MS",
    "sg:tags":[
        "crop",
        "general"
    ],
    "wof:name":"Tracy Mask",
    "wof:placetype":"venue"
},
  "geometry": {"coordinates":[-88.864063,34.14766],"type":"Point"}
}