{
  "type": "Feature",
  "properties": {
    "addr:full":"6935 Old Canton Rd Ridgeland MS 39158",
    "addr:housenumber":"6935",
    "addr:postcode":"39158",
    "addr:street":"Old Canton Rd",
    "iso:country":"US",
    "sg:address":"6935 Old Canton Rd",
    "sg:city":"Ridgeland",
    "sg:classifiers":[
        {
            "category":"Health Services",
            "subcategory":"Chiropractor",
            "type":"Services"
        }
    ],
    "sg:phone":"+1 601 956 6151",
    "sg:postcode":"39158",
    "sg:province":"MS",
    "wof:name":"Action Chiropractic Center",
    "wof:placetype":"venue"
},
  "geometry": {"coordinates":[-90.10641,32.415319],"type":"Point"}
}