{
  "type": "Feature",
  "properties": {
    "addr:full":"104 W Franklin St Quitman MS 39355",
    "addr:housenumber":"104",
    "addr:postcode":"39355",
    "addr:street":"W Franklin St",
    "iso:country":"US",
    "sg:address":"104 W Franklin St",
    "sg:city":"Quitman",
    "sg:classifiers":[
        {
            "category":"Freight",
            "type":"Transportation"
        }
    ],
    "sg:phone":"+1 601 776 3722",
    "sg:postcode":"39355",
    "sg:province":"MS",
    "sg:tags":[
        "commercial",
        "storage"
    ],
    "wof:name":"Sellers Mini Storage",
    "wof:placetype":"venue"
},
  "geometry": {"coordinates":[-88.729471,32.03654],"type":"Point"}
}