{
  "type": "Feature",
  "properties": {
    "iso:country":"US",
    "sg:address":"963 Memorial Blvd",
    "sg:city":"Picayune",
    "sg:classifiers":[
        {
            "category":"Utilities",
            "subcategory":"Mobile Phone",
            "type":"Services"
        }
    ],
    "sg:phone":"+1 601 749 0389",
    "sg:postcode":"39466",
    "sg:province":"MS",
    "sg:tags":[
        "telephone",
        "cellular"
    ],
    "wof:name":"Talk N Tan",
    "wof:placetype":"venue"
},
  "geometry": {"coordinates":[-89.67093,30.517708],"type":"Point"}
}