{
  "type": "Feature",
  "properties": {
    "iso:country":"US",
    "sg:address":"505 Airport Rd",
    "sg:city":"Forest",
    "sg:classifiers":[
        {
            "category":"Autos & Motor Vehicles",
            "subcategory":"Auto Supplies",
            "type":"Retail Goods"
        }
    ],
    "sg:phone":"+1 601 469 9080",
    "sg:postcode":"39074",
    "sg:province":"MS",
    "sg:tags":[
        "tire"
    ],
    "wof:name":"J & J Tire",
    "wof:placetype":"venue"
},
  "geometry": {"coordinates":[-89.482404,32.354546],"type":"Point"}
}