{
  "type": "Feature",
  "properties": {
    "iso:country":"US",
    "sg:address":"1444 Hwy 25 S",
    "sg:city":"Starkville",
    "sg:classifiers":[
        {
            "category":"Personal",
            "subcategory":"Beauty Salon",
            "type":"Services"
        }
    ],
    "sg:phone":"+1 662 323 0054",
    "sg:postcode":"39759",
    "sg:province":"MS",
    "wof:name":"New Century Beauty & Barber",
    "wof:placetype":"venue"
},
  "geometry": {"coordinates":[-88.82947,33.431552],"type":"Point"}
}