{
  "type": "Feature",
  "properties": {
    "addr:full":"10541 Diberville Blvd Biloxi MS 39540",
    "addr:housenumber":"10541",
    "addr:postcode":"39540",
    "addr:street":"Diberville Blvd",
    "iso:country":"US",
    "sg:address":"10541 Diberville Blvd",
    "sg:city":"Biloxi",
    "sg:classifiers":[
        {
            "category":"Shopping",
            "subcategory":"Department Store",
            "type":"Retail Goods"
        }
    ],
    "sg:phone":"+1 601 392 2536",
    "sg:postcode":"39540",
    "sg:province":"MS",
    "wof:name":"Kmart",
    "wof:placetype":"venue"
},
  "geometry": {"coordinates":[-88.89739,30.440132],"type":"Point"}
}