{
  "type": "Feature",
  "properties": {
    "iso:country":"US",
    "sg:address":"1102 S Main St",
    "sg:city":"Poplarville",
    "sg:classifiers":[
        {
            "category":"Food & Beverages",
            "subcategory":"Groceries & Convenience Stores",
            "type":"Retail Goods"
        }
    ],
    "sg:phone":"+1 601 795 0780",
    "sg:postcode":"39470",
    "sg:province":"MS",
    "wof:name":"Big K Food Store",
    "wof:placetype":"venue"
},
  "geometry": {"coordinates":[-89.53228,30.837224],"type":"Point"}
}