{
  "type": "Feature",
  "properties": {
    "iso:country":"US",
    "sg:address":"5416 Suffolk Dr",
    "sg:city":"Jackson",
    "sg:classifiers":[
        {
            "category":"Building & Trades",
            "subcategory":"Construction",
            "type":"Services"
        }
    ],
    "sg:phone":"+1 601 956 6965",
    "sg:postcode":"39211",
    "sg:province":"MS",
    "sg:tags":[
        "house",
        "nonresidential"
    ],
    "wof:name":"Craft Master Inc",
    "wof:placetype":"venue"
},
  "geometry": {"coordinates":[-90.13931100000001,32.373504],"type":"Point"}
}