{
  "type": "Feature",
  "properties": {
    "addr:full":"1229 Street Rd Liberty MS 39645",
    "addr:housenumber":"1229",
    "addr:postcode":"39645",
    "addr:street":"Street Rd",
    "iso:country":"US",
    "sg:address":"1229 Street Rd",
    "sg:city":"Liberty",
    "sg:classifiers":[
        {
            "category":"Organizations",
            "subcategory":"Religious Organization",
            "type":"Services"
        }
    ],
    "sg:phone":"+1 601 657 9066",
    "sg:postcode":"39645",
    "sg:province":"MS",
    "sg:tags":[
        "church"
    ],
    "wof:name":"St Mary Baptist Church",
    "wof:placetype":"venue"
},
  "geometry": {"coordinates":[-90.883093,31.000417],"type":"Point"}
}