{
  "type": "Feature",
  "properties": {
    "iso:country":"US",
    "sg:address":"653 First West St S",
    "sg:city":"Woodville",
    "sg:classifiers":[
        {
            "category":"Government",
            "subcategory":"Office",
            "type":"Public Place"
        }
    ],
    "sg:phone":"+1 601 888 3332",
    "sg:postcode":"39669",
    "sg:province":"MS",
    "sg:tags":[
        "village"
    ],
    "wof:name":"Light & Water Plant",
    "wof:placetype":"venue"
},
  "geometry": {"coordinates":[-91.30038999999999,31.098871],"type":"Point"}
}