{
  "type": "Feature",
  "properties": {
    "iso:country":"US",
    "sg:address":"4005 Raymond Rd",
    "sg:city":"Hazlehurst",
    "sg:classifiers":[
        {
            "category":"Home & Garden",
            "subcategory":"Carpets & Floor Coverings",
            "type":"Retail Goods"
        }
    ],
    "sg:phone":"+1 601 894 1747",
    "sg:postcode":"39083",
    "sg:province":"MS",
    "wof:name":"Perrys Carpet & Floors",
    "wof:placetype":"venue"
},
  "geometry": {"coordinates":[-90.44623900000001,31.89296],"type":"Point"}
}