{
  "type": "Feature",
  "properties": {
    "iso:country":"US",
    "sg:address":"123 S Main St",
    "sg:city":"Petal",
    "sg:classifiers":[
        {
            "category":"Shopping",
            "subcategory":"Bicycles & Sporting Goods",
            "type":"Retail Goods"
        }
    ],
    "sg:phone":"+1 601 543 0071",
    "sg:postcode":"39465",
    "sg:province":"MS",
    "wof:name":"Sports Shop",
    "wof:placetype":"venue"
},
  "geometry": {"coordinates":[-89.262854,31.344554],"type":"Point"}
}