{
  "type": "Feature",
  "properties": {
    "iso:country":"US",
    "sg:address":"102 Kathy Dr",
    "sg:city":"Quitman",
    "sg:phone":"+1 601 776 6170",
    "sg:postcode":"39355",
    "sg:province":"MS",
    "sg:tags":[
        "wholesale",
        "industrial",
        "oil",
        "retail"
    ],
    "wof:name":"Lube Services",
    "wof:placetype":"venue"
},
  "geometry": {"coordinates":[-88.719274,32.035885],"type":"Point"}
}