{
  "type": "Feature",
  "properties": {
    "iso:country":"US",
    "sg:address":"224 Front St Exd",
    "sg:city":"Indianola",
    "sg:classifiers":[
        {
            "category":"Autos & Motor Vehicles",
            "subcategory":"Automobile Sales",
            "type":"Retail Goods"
        }
    ],
    "sg:phone":"+1 662 887 5158",
    "sg:postcode":"38751",
    "sg:province":"MS",
    "sg:tags":[
        "car",
        "dealer"
    ],
    "wof:name":"Bolden's Auto Sales",
    "wof:placetype":"venue"
},
  "geometry": {"coordinates":[-90.65157000000001,33.449474],"type":"Point"}
}