{
  "type": "Feature",
  "properties": {
    "addr:full":"909 Friars Point Rd Clarksdale MS 38614",
    "addr:housenumber":"909",
    "addr:postcode":"38614",
    "addr:street":"Friars Point Rd",
    "iso:country":"US",
    "sg:address":"909 Friars Point Rd",
    "sg:city":"Clarksdale",
    "sg:classifiers":[
        {
            "category":"Organizations",
            "subcategory":"Community Association",
            "type":"Services"
        }
    ],
    "sg:phone":"+1 662 624 8962",
    "sg:postcode":"38614",
    "sg:province":"MS",
    "sg:tags":[
        "club"
    ],
    "wof:name":"Clarskdale Country Club Pro",
    "wof:placetype":"venue"
},
  "geometry": {"coordinates":[-90.571155,34.229158],"type":"Point"}
}