{
  "type": "Feature",
  "properties": {
    "iso:country":"US",
    "sg:address":"1220 Co Rd 101",
    "sg:city":"New Albany",
    "sg:phone":"+1 662 534 4391",
    "sg:postcode":"38652",
    "sg:province":"MS",
    "sg:tags":[
        "farm"
    ],
    "wof:name":"Cleo Fooshee",
    "wof:placetype":"venue"
},
  "geometry": {"coordinates":[-89.071319,34.409288],"type":"Point"}
}