{
  "type": "Feature",
  "properties": {
    "addr:full":"3851 Hwy 12 W Sturgis MS 39769",
    "addr:housenumber":"3851",
    "addr:postcode":"39769",
    "addr:street":"Hwy 12 W",
    "iso:country":"US",
    "sg:address":"3851 Hwy 12 W",
    "sg:city":"Sturgis",
    "sg:classifiers":[
        {
            "category":"Government",
            "subcategory":"Office",
            "type":"Public Place"
        }
    ],
    "sg:phone":"+1 662 465 7970",
    "sg:postcode":"39769",
    "sg:province":"MS",
    "sg:tags":[
        "city"
    ],
    "sg:website":"www.sturgisms.com",
    "wof:name":"Sturgis Mayor's Office",
    "wof:placetype":"venue"
},
  "geometry": {"coordinates":[-89.047513,33.343298],"type":"Point"}
}