{
  "type": "Feature",
  "properties": {
    "iso:country":"US",
    "sg:address":"120 Eureka St",
    "sg:city":"Batesville",
    "sg:classifiers":[
        {
            "category":"Organizations",
            "subcategory":"Religious Organization",
            "type":"Services"
        }
    ],
    "sg:phone":"+1 662 563 7859",
    "sg:postcode":"38606",
    "sg:province":"MS",
    "sg:tags":[
        "church"
    ],
    "sg:website":"www.tsfbs3-edu.com",
    "wof:name":"Church Of Christ",
    "wof:placetype":"venue"
},
  "geometry": {"coordinates":[-89.951015,34.313749],"type":"Point"}
}