{
  "type": "Feature",
  "properties": {
    "iso:country":"US",
    "sg:address":"3688 Joe Coker Rd",
    "sg:city":"Jackson",
    "sg:classifiers":[
        {
            "category":"Organizations",
            "subcategory":"Labor Organization",
            "type":"Services"
        }
    ],
    "sg:phone":"+1 601 981 5990",
    "sg:postcode":"39213",
    "sg:province":"MS",
    "wof:name":"Cwa Water Association",
    "wof:placetype":"venue"
},
  "geometry": {"coordinates":[-90.244398,32.478366],"type":"Point"}
}