{
  "type": "Feature",
  "properties": {
    "iso:country":"US",
    "sg:address":"1278 King Bee Rd",
    "sg:city":"Perkinston",
    "sg:classifiers":[
        {
            "category":"Building & Trades",
            "subcategory":"Construction",
            "type":"Services"
        }
    ],
    "sg:phone":"+1 601 928 6079",
    "sg:postcode":"39573",
    "sg:province":"MS",
    "sg:tags":[
        "excavation",
        "contractor"
    ],
    "wof:name":"O&F Backhoe Serv",
    "wof:placetype":"venue"
},
  "geometry": {"coordinates":[-89.03452900000001,30.81037],"type":"Point"}
}