{
  "type": "Feature",
  "properties": {
    "iso:country":"US",
    "sg:address":"126 2nd St",
    "sg:city":"Golden",
    "sg:classifiers":[
        {
            "category":"Food & Beverages",
            "subcategory":"Groceries & Convenience Stores",
            "type":"Retail Goods"
        }
    ],
    "sg:phone":"+1 662 454 7920",
    "sg:postcode":"38847",
    "sg:province":"MS",
    "sg:tags":[
        "grocer"
    ],
    "wof:name":"Thomas Grocery",
    "wof:placetype":"venue"
},
  "geometry": {"coordinates":[-88.204762,34.477939],"type":"Point"}
}