{
  "type": "Feature",
  "properties": {
    "iso:country":"US",
    "sg:address":"173 Vernon Jones Ave",
    "sg:city":"Brandon",
    "sg:classifiers":[
        {
            "category":"Organizations",
            "subcategory":"Religious Organization",
            "type":"Services"
        }
    ],
    "sg:phone":"+1 601 992 3331",
    "sg:postcode":"39047",
    "sg:province":"MS",
    "sg:tags":[
        "church"
    ],
    "wof:name":"Hindu Temple",
    "wof:placetype":"venue"
},
  "geometry": {"coordinates":[-90.05603000000001,32.372776],"type":"Point"}
}