{
  "type": "Feature",
  "properties": {
    "iso:country":"US",
    "sg:address":"517 Linden Hill St",
    "sg:city":"Tupelo",
    "sg:classifiers":[
        {
            "category":"Social Services",
            "subcategory":"Child Care",
            "type":"Services"
        }
    ],
    "sg:phone":"+1 662 844 1351",
    "sg:postcode":"38801",
    "sg:province":"MS",
    "sg:tags":[
        "day"
    ],
    "wof:name":"Northside Head Start Center",
    "wof:placetype":"venue"
},
  "geometry": {"coordinates":[-88.706345,34.277978],"type":"Point"}
}