{
  "type": "Feature",
  "properties": {
    "iso:country":"US",
    "sg:address":"209 Westview Cir",
    "sg:city":"Mc Comb",
    "sg:classifiers":[
        {
            "category":"Insurance",
            "subcategory":"Insurance Agent",
            "type":"Services"
        }
    ],
    "sg:phone":"+1 601 684 0791",
    "sg:postcode":"39648",
    "sg:province":"MS",
    "wof:name":"Blue Cross & Blue Shield of Ms",
    "wof:placetype":"venue"
},
  "geometry": {"coordinates":[-90.47028899999999,31.236169],"type":"Point"}
}