{
  "type": "Feature",
  "properties": {
    "addr:full":"4670 Katherine Blvd Jackson MS 39211",
    "addr:housenumber":"4670",
    "addr:postcode":"39211",
    "addr:street":"Katherine Blvd",
    "iso:country":"US",
    "sg:address":"4670 Katherine Blvd",
    "sg:city":"Jackson",
    "sg:classifiers":[
        {
            "category":"Professional",
            "subcategory":"Computer Services",
            "type":"Services"
        }
    ],
    "sg:phone":"+1 601 984 3620",
    "sg:postcode":"39211",
    "sg:province":"MS",
    "sg:tags":[
        "consulting",
        "e",
        "mfg"
    ],
    "wof:name":"Mpact Inc",
    "wof:placetype":"venue"
},
  "geometry": {"coordinates":[-90.123741,32.357726],"type":"Point"}
}