{
  "type": "Feature",
  "properties": {
    "iso:country":"US",
    "sg:address":"5306 C C Rd",
    "sg:city":"Saucier",
    "sg:classifiers":[
        {
            "category":"Personal",
            "subcategory":"Beauty Salon",
            "type":"Services"
        }
    ],
    "sg:phone":"+1 228 392 0290",
    "sg:postcode":"39574",
    "sg:province":"MS",
    "wof:name":"Kutz Too",
    "wof:placetype":"venue"
},
  "geometry": {"coordinates":[-88.925729,30.552261],"type":"Point"}
}