{
  "type": "Feature",
  "properties": {
    "iso:country":"US",
    "sg:address":"355 Goss Bunker Hill Rd",
    "sg:city":"Columbia",
    "sg:classifiers":[
        {
            "category":"Farming",
            "subcategory":"Fish & Marine Products",
            "type":"Manufacturing & Wholesale Goods"
        }
    ],
    "sg:phone":"+1 601 731 2910",
    "sg:postcode":"39429",
    "sg:province":"MS",
    "sg:tags":[
        "preserves",
        "fishing",
        "hunting"
    ],
    "wof:name":"Saucier's Quail Farm",
    "wof:placetype":"venue"
},
  "geometry": {"coordinates":[-89.867785,31.365341],"type":"Point"}
}