{
  "type": "Feature",
  "properties": {
    "iso:country":"US",
    "sg:address":"265 Lakeshore Dr",
    "sg:city":"Pontotoc",
    "sg:classifiers":[
        {
            "category":"Real Estate",
            "subcategory":"Real Estate Operator",
            "type":"Services"
        }
    ],
    "sg:phone":"+1 662 488 9661",
    "sg:postcode":"38863",
    "sg:province":"MS",
    "sg:tags":[
        "building",
        "apartment"
    ],
    "wof:name":"Pontotoc Senior Apartments",
    "wof:placetype":"venue"
},
  "geometry": {"coordinates":[-89.015677,34.237482],"type":"Point"}
}