{
  "type": "Feature",
  "properties": {
    "iso:country":"US",
    "sg:address":"604 Co Rd 1725",
    "sg:city":"Bay Springs",
    "sg:classifiers":[
        {
            "category":"Organizations",
            "subcategory":"Community Association",
            "type":"Services"
        }
    ],
    "sg:phone":"+1 601 764 2648",
    "sg:postcode":"39422",
    "sg:province":"MS",
    "sg:tags":[
        "club"
    ],
    "wof:name":"Mud Line Club",
    "wof:placetype":"venue"
},
  "geometry": {"coordinates":[-89.245238,31.948698],"type":"Point"}
}