{
  "type": "Feature",
  "properties": {
    "iso:country":"US",
    "sg:address":"546 S Archusa Ave",
    "sg:city":"Quitman",
    "sg:classifiers":[
        {
            "category":"Banks & Credit Unions",
            "subcategory":"Bank",
            "type":"Services"
        }
    ],
    "sg:phone":"+1 601 776 7476",
    "sg:postcode":"39355",
    "sg:province":"MS",
    "sg:tags":[
        "cashing",
        "check"
    ],
    "wof:name":"Check Now",
    "wof:placetype":"venue"
},
  "geometry": {"coordinates":[-88.727981,32.036244],"type":"Point"}
}