{
  "type": "Feature",
  "properties": {
    "iso:country":"US",
    "sg:address":"444 Abbey Woods",
    "sg:city":"Brandon",
    "sg:classifiers":[
        {
            "category":"Shopping",
            "subcategory":"Computers & Home Electronics",
            "type":"Retail Goods"
        }
    ],
    "sg:phone":"+1 601 992 0840",
    "sg:postcode":"39047",
    "sg:province":"MS",
    "sg:tags":[
        "equipment",
        "dealer"
    ],
    "wof:name":"Computer & Networking",
    "wof:placetype":"venue"
},
  "geometry": {"coordinates":[-90.041988,32.372832],"type":"Point"}
}