{
  "type": "Feature",
  "properties": {
    "addr:full":"11237 Tanner Rd Gulfport MS 39503",
    "addr:housenumber":"11237",
    "addr:postcode":"39503",
    "addr:street":"Tanner Rd",
    "iso:country":"US",
    "sg:address":"11237 Tanner Rd",
    "sg:city":"Gulfport",
    "sg:classifiers":[
        {
            "category":"Retail",
            "subcategory":"Auto Repair",
            "type":"Services"
        }
    ],
    "sg:phone":"+1 228 539 1209",
    "sg:postcode":"39503",
    "sg:province":"MS",
    "sg:tags":[
        "repairing",
        "automobile"
    ],
    "wof:name":"Downtown Service Station",
    "wof:placetype":"venue"
},
  "geometry": {"coordinates":[-89.080175,30.448363],"type":"Point"}
}