{
  "type": "Feature",
  "properties": {
    "iso:country":"US",
    "sg:address":"519 W Silas Brown St",
    "sg:city":"Jackson",
    "sg:classifiers":[
        {
            "category":"Organizations",
            "subcategory":"Religious Organization",
            "type":"Services"
        }
    ],
    "sg:phone":"+1 601 948 1874",
    "sg:postcode":"39204",
    "sg:province":"MS",
    "sg:tags":[
        "church"
    ],
    "wof:name":"Jackson Revival Center Church",
    "wof:placetype":"venue"
},
  "geometry": {"coordinates":[-90.194864,32.291241],"type":"Point"}
}