{
  "type": "Feature",
  "properties": {
    "iso:country":"US",
    "sg:address":"720 Hwy 82 W",
    "sg:city":"Greenwood",
    "sg:classifiers":[
        {
            "category":"Wholesale",
            "subcategory":"Beer",
            "type":"Manufacturing & Wholesale Goods"
        }
    ],
    "sg:phone":"+1 662 453 4141",
    "sg:postcode":"38930",
    "sg:province":"MS",
    "sg:tags":[
        "ale"
    ],
    "wof:name":"Marascalco Distributing Co",
    "wof:placetype":"venue"
},
  "geometry": {"coordinates":[-90.19051899999999,33.506572],"type":"Point"}
}