{
  "type": "Feature",
  "properties": {
    "addr:full":"3137 Crigler Rd Crawford MS 39743",
    "addr:housenumber":"3137",
    "addr:postcode":"39743",
    "addr:street":"Crigler Rd",
    "iso:country":"US",
    "sg:address":"3137 Crigler Rd",
    "sg:city":"Crawford",
    "sg:phone":"+1 662 272 5789",
    "sg:postcode":"39743",
    "sg:province":"MS",
    "sg:tags":[
        "farm",
        "field",
        "crop"
    ],
    "wof:name":"Bobby Johnson",
    "wof:placetype":"venue"
},
  "geometry": {"coordinates":[-88.701629,33.323354],"type":"Point"}
}