{
  "type": "Feature",
  "properties": {
    "iso:country":"US",
    "sg:address":"140 Trade Center Ln",
    "sg:city":"Hazlehurst",
    "sg:classifiers":[
        {
            "category":"Shopping",
            "subcategory":"Pharmacy",
            "type":"Retail Goods"
        }
    ],
    "sg:phone":"+1 601 894 3008",
    "sg:postcode":"39083",
    "sg:province":"MS",
    "wof:name":"Freds Pharmacy 1836 Hazelhur",
    "wof:placetype":"venue"
},
  "geometry": {"coordinates":[-90.397774,31.873886],"type":"Point"}
}