{
  "type": "Feature",
  "properties": {
    "iso:country":"US",
    "sg:address":"1468 Co Rd 961",
    "sg:city":"Belmont",
    "sg:classifiers":[
        {
            "category":"Building & Trades",
            "subcategory":"Construction",
            "type":"Services"
        }
    ],
    "sg:phone":"+1 662 454 9914",
    "sg:postcode":"38827",
    "sg:province":"MS",
    "sg:tags":[
        "house"
    ],
    "wof:name":"G & M Metal Roofing",
    "wof:placetype":"venue"
},
  "geometry": {"coordinates":[-88.238117,34.505317],"type":"Point"}
}