{
  "type": "Feature",
  "properties": {
    "iso:country":"US",
    "sg:address":"1856 Hospital Dr",
    "sg:city":"Jackson",
    "sg:classifiers":[
        {
            "category":"Health Services",
            "subcategory":"Doctor",
            "type":"Services"
        }
    ],
    "sg:phone":"+1 601 371 2896",
    "sg:postcode":"39204",
    "sg:province":"MS",
    "sg:tags":[
        "clinic"
    ],
    "wof:name":"Central Dialysis Southwest",
    "wof:placetype":"venue"
},
  "geometry": {"coordinates":[-90.25366099999999,32.282719],"type":"Point"}
}