{
  "type": "Feature",
  "properties": {
    "addr:full":"970 N State St Jackson MS 39202",
    "addr:housenumber":"970",
    "addr:postcode":"39202",
    "addr:street":"N State St",
    "iso:country":"US",
    "sg:address":"970 N State St",
    "sg:city":"Jackson",
    "sg:classifiers":[
        {
            "category":"Autos & Motor Vehicles",
            "subcategory":"Fuel & Gas Station",
            "type":"Retail Goods"
        }
    ],
    "sg:phone":"+1 601 352 7666",
    "sg:postcode":"39202",
    "sg:province":"MS",
    "sg:tags":[
        "oil"
    ],
    "wof:name":"Fuel Depot",
    "wof:placetype":"venue"
},
  "geometry": {"coordinates":[-90.17816500000001,32.310595],"type":"Point"}
}