{
  "type": "Feature",
  "properties": {
    "iso:country":"US",
    "sg:address":"18337 US Hwy 49",
    "sg:city":"Saucier",
    "sg:classifiers":[
        {
            "category":"Real Estate",
            "subcategory":"Developer",
            "type":"Services"
        }
    ],
    "sg:phone":"+1 228 832 5665",
    "sg:postcode":"39574",
    "sg:province":"MS",
    "sg:tags":[
        "company",
        "land"
    ],
    "wof:name":"First National Properties Inc",
    "wof:placetype":"venue"
},
  "geometry": {"coordinates":[-89.12123200000001,30.553682],"type":"Point"}
}