{
  "type": "Feature",
  "properties": {
    "iso:country":"US",
    "sg:address":"204 E Georgetown St",
    "sg:city":"Crystal Springs",
    "sg:classifiers":[
        {
            "category":"Home & Garden",
            "subcategory":"Furniture",
            "type":"Retail Goods"
        }
    ],
    "sg:phone":"+1 601 892 3102",
    "sg:postcode":"39059",
    "sg:province":"MS",
    "wof:name":"Garlands Used Furn & Salv Co",
    "wof:placetype":"venue"
},
  "geometry": {"coordinates":[-90.356341,31.98705],"type":"Point"}
}