{
  "type": "Feature",
  "properties": {
    "iso:country":"US",
    "sg:address":"1870 Wilson Chapel Rd",
    "sg:city":"Pontotoc",
    "sg:classifiers":[
        {
            "category":"Organizations",
            "subcategory":"Religious Organization",
            "type":"Services"
        }
    ],
    "sg:phone":"+1 662 488 4022",
    "sg:postcode":"38863",
    "sg:province":"MS",
    "wof:name":"Wilson Chapel Baptist Church",
    "wof:placetype":"venue"
},
  "geometry": {"coordinates":[-88.971318,34.283995],"type":"Point"}
}