{
  "type": "Feature",
  "properties": {
    "iso:country":"US",
    "sg:address":"1414 Old Brandon Rd",
    "sg:city":"Flowood",
    "sg:classifiers":[
        {
            "category":"Wholesale",
            "subcategory":"Electrical",
            "type":"Manufacturing & Wholesale Goods"
        }
    ],
    "sg:phone":"+1 601 981 7877",
    "sg:postcode":"39232",
    "sg:province":"MS",
    "sg:tags":[
        "alarm",
        "burglar",
        "system"
    ],
    "sg:website":"www.thugproof.com",
    "wof:name":"Alarm Co",
    "wof:placetype":"venue"
},
  "geometry": {"coordinates":[-90.15738899999999,32.281429],"type":"Point"}
}