{
  "type": "Feature",
  "properties": {
    "addr:full":"13118 Old Hwy 61 Robinsonville MS 38664",
    "addr:housenumber":"13118",
    "addr:postcode":"38664",
    "addr:street":"Old Hwy 61",
    "iso:country":"US",
    "sg:address":"13118 Old Hwy 61",
    "sg:city":"Robinsonville",
    "sg:classifiers":[
        {
            "category":"Shopping",
            "subcategory":"Clothing, Apparel, & Fashions",
            "type":"Retail Goods"
        }
    ],
    "sg:phone":"+1 662 363 1022",
    "sg:postcode":"38664",
    "sg:province":"MS",
    "wof:name":"Capacity",
    "wof:placetype":"venue"
},
  "geometry": {"coordinates":[-90.299747,34.839242],"type":"Point"}
}