{
  "type": "Feature",
  "properties": {
    "iso:country":"US",
    "sg:address":"232 Yorkville Rd E",
    "sg:city":"Columbus",
    "sg:classifiers":[
        {
            "category":"Organizations",
            "subcategory":"Religious Organization",
            "type":"Services"
        }
    ],
    "sg:phone":"+1 662 329 5061",
    "sg:postcode":"39702",
    "sg:province":"MS",
    "sg:tags":[
        "church"
    ],
    "wof:name":"United Christian Day Care Inc",
    "wof:placetype":"venue"
},
  "geometry": {"coordinates":[-88.385283,33.47832],"type":"Point"}
}