{
  "type": "Feature",
  "properties": {
    "iso:country":"US",
    "sg:address":"6331 US Hwy 90",
    "sg:city":"Moss Point",
    "sg:classifiers":[
        {
            "category":"Building & Trades",
            "subcategory":"Construction",
            "type":"Services"
        }
    ],
    "sg:phone":"+1 228 474 2434",
    "sg:postcode":"39563",
    "sg:province":"MS",
    "sg:tags":[
        "general",
        "contractor"
    ],
    "wof:name":"Masse Contracting",
    "wof:placetype":"venue"
},
  "geometry": {"coordinates":[-88.505527,30.391825],"type":"Point"}
}