{
  "type": "Feature",
  "properties": {
    "addr:full":"1010 Kiln Delisle Rd Pass Christian MS 39571",
    "addr:housenumber":"1010",
    "addr:postcode":"39571",
    "addr:street":"Kiln Delisle Rd",
    "iso:country":"US",
    "sg:address":"1010 Kiln Delisle Rd",
    "sg:city":"Pass Christian",
    "sg:classifiers":[
        {
            "category":"Recreation",
            "type":"Entertainment"
        }
    ],
    "sg:phone":"+1 228 255 5024",
    "sg:postcode":"39571",
    "sg:province":"MS",
    "wof:name":"Diamondhead Martial Arts",
    "wof:placetype":"venue"
},
  "geometry": {"coordinates":[-89.343925,30.419341],"type":"Point"}
}