{
  "type": "Feature",
  "properties": {
    "iso:country":"US",
    "sg:address":"219 Bass Rd",
    "sg:city":"Florence",
    "sg:classifiers":[
        {
            "category":"Health Services",
            "subcategory":"Nursing And Care Facility",
            "type":"Services"
        }
    ],
    "sg:phone":"+1 601 845 8836",
    "sg:postcode":"39073",
    "sg:province":"MS",
    "sg:tags":[
        "intermediate"
    ],
    "wof:name":"Castin Home Inc",
    "wof:placetype":"venue"
},
  "geometry": {"coordinates":[-89.991896,32.064688],"type":"Point"}
}