{
  "type": "Feature",
  "properties": {
    "addr:full":"4753 McWillie Dr Jackson MS 39206",
    "addr:housenumber":"4753",
    "addr:postcode":"39206",
    "addr:street":"Mcwillie Dr",
    "iso:country":"US",
    "sg:address":"4753 McWillie Dr",
    "sg:city":"Jackson",
    "sg:classifiers":[
        {
            "category":"Social Services",
            "subcategory":"Child Care",
            "type":"Services"
        }
    ],
    "sg:phone":"+1 601 982 0305",
    "sg:postcode":"39206",
    "sg:province":"MS",
    "sg:tags":[
        "day"
    ],
    "wof:name":"Education Depot Inc",
    "wof:placetype":"venue"
},
  "geometry": {"coordinates":[-90.15382099999999,32.358198],"type":"Point"}
}