{
  "type": "Feature",
  "properties": {
    "iso:country":"US",
    "sg:address":"602 N Davis Ave",
    "sg:city":"Cleveland",
    "sg:classifiers":[
        {
            "category":"Food & Beverages",
            "subcategory":"Groceries & Convenience Stores",
            "type":"Retail Goods"
        }
    ],
    "sg:phone":"+1 662 843 0834",
    "sg:postcode":"38732",
    "sg:province":"MS",
    "wof:name":"Kroger",
    "wof:placetype":"venue"
},
  "geometry": {"coordinates":[-90.71561199999999,33.751704],"type":"Point"}
}