{
  "type": "Feature",
  "properties": {
    "iso:country":"US",
    "sg:address":"220 Main St",
    "sg:city":"Mccomb",
    "sg:classifiers":[
        {
            "category":"Personal",
            "subcategory":"Beauty Salon",
            "type":"Services"
        }
    ],
    "sg:phone":"+1 601 684 5345",
    "sg:postcode":"39648",
    "sg:province":"MS",
    "wof:name":"Salon Services",
    "wof:placetype":"venue"
},
  "geometry": {"coordinates":[-90.452394,31.243735],"type":"Point"}
}