{
  "type": "Feature",
  "properties": {
    "addr:full":"104 W Erlanger St Poplarville MS 39470",
    "addr:housenumber":"104",
    "addr:postcode":"39470",
    "addr:street":"W Erlanger St",
    "iso:country":"US",
    "sg:address":"104 W Erlanger St",
    "sg:city":"Poplarville",
    "sg:classifiers":[
        {
            "category":"Professional",
            "subcategory":"Accounting & Tax Preparation",
            "type":"Services"
        }
    ],
    "sg:phone":"+1 601 795 0630",
    "sg:postcode":"39470",
    "sg:province":"MS",
    "sg:tags":[
        "accountant"
    ],
    "wof:name":"Donna Carter & Associates",
    "wof:placetype":"venue"
},
  "geometry": {"coordinates":[-89.53477700000001,30.841042],"type":"Point"}
}