{
  "type": "Feature",
  "properties": {
    "iso:country":"US",
    "sg:address":"220 N James Ave",
    "sg:city":"Mc Comb",
    "sg:classifiers":[
        {
            "category":"Organizations",
            "subcategory":"Religious Organization",
            "type":"Services"
        }
    ],
    "sg:phone":"+1 601 249 3699",
    "sg:postcode":"39648",
    "sg:province":"MS",
    "wof:name":"St Mary 2",
    "wof:placetype":"venue"
},
  "geometry": {"coordinates":[-90.463499,31.24983],"type":"Point"}
}