{
  "type": "Feature",
  "properties": {
    "iso:country":"US",
    "sg:address":"2112 24th Ave",
    "sg:city":"Meridian",
    "sg:classifiers":[
        {
            "category":"Manufacturing",
            "subcategory":"Printing",
            "type":"Manufacturing & Wholesale Goods"
        }
    ],
    "sg:phone":"+1 601 482 5140",
    "sg:postcode":"39301",
    "sg:province":"MS",
    "sg:tags":[
        "publishing"
    ],
    "wof:name":"Red Metro Phonebook",
    "wof:placetype":"venue"
},
  "geometry": {"coordinates":[-88.702601,32.380308],"type":"Point"}
}