{
  "type": "Feature",
  "properties": {
    "iso:country":"US",
    "sg:address":"101 W Main St",
    "sg:city":"Mc Lain",
    "sg:classifiers":[
        {
            "category":"Autos & Motor Vehicles",
            "subcategory":"Auto Supplies",
            "type":"Retail Goods"
        }
    ],
    "sg:phone":"+1 601 753 2222",
    "sg:postcode":"39456",
    "sg:province":"MS",
    "sg:tags":[
        "automobile",
        "parts"
    ],
    "wof:name":"C E Rogers Western Auto",
    "wof:placetype":"venue"
},
  "geometry": {"coordinates":[-88.828306,31.109499],"type":"Point"}
}