{
  "type": "Feature",
  "properties": {
    "addr:full":"203 Harvest Dr Ridgeland MS 39157",
    "addr:housenumber":"203",
    "addr:postcode":"39157",
    "addr:street":"Harvest Dr",
    "iso:country":"US",
    "sg:address":"203 Harvest Dr",
    "sg:city":"Ridgeland",
    "sg:classifiers":[
        {
            "category":"Utilities",
            "subcategory":"Telephone",
            "type":"Services"
        }
    ],
    "sg:phone":"+1 601 856 4511",
    "sg:postcode":"39157",
    "sg:province":"MS",
    "sg:tags":[
        "company"
    ],
    "wof:name":"Evercom Systems",
    "wof:placetype":"venue"
},
  "geometry": {"coordinates":[-90.135898,32.410872],"type":"Point"}
}