{
  "type": "Feature",
  "properties": {
    "addr:full":"2290 Hwy 49 S Florence MS 39073",
    "addr:housenumber":"2290",
    "addr:postcode":"39073",
    "addr:street":"Hwy 49 S",
    "iso:country":"US",
    "sg:address":"2290 Hwy 49 S",
    "sg:city":"Florence",
    "sg:classifiers":[
        {
            "category":"Banks & Credit Unions",
            "subcategory":"Investment Brokerage",
            "type":"Services"
        }
    ],
    "sg:phone":"+1 601 845 2555",
    "sg:postcode":"39073",
    "sg:province":"MS",
    "wof:name":"South Eastern Investment",
    "wof:placetype":"venue"
},
  "geometry": {"coordinates":[-90.12474899999999,32.155124],"type":"Point"}
}