{
  "type": "Feature",
  "properties": {
    "iso:country":"US",
    "sg:address":"29 Co Rd 176",
    "sg:city":"Iuka",
    "sg:classifiers":[
        {
            "category":"Health Services",
            "subcategory":"Clinic",
            "type":"Services"
        }
    ],
    "sg:phone":"+1 662 424 9840",
    "sg:postcode":"38852",
    "sg:province":"MS",
    "sg:tags":[
        "home",
        "care"
    ],
    "wof:name":"Aci Inc - Alabama",
    "wof:placetype":"venue"
},
  "geometry": {"coordinates":[-88.252871,34.772452],"type":"Point"}
}