{
  "type": "Feature",
  "properties": {
    "iso:country":"US",
    "sg:address":"6819 Washington Ave",
    "sg:city":"Ocean Springs",
    "sg:classifiers":[
        {
            "category":"Utilities",
            "subcategory":"Mobile Phone",
            "type":"Services"
        }
    ],
    "sg:phone":"+1 228 818 9731",
    "sg:postcode":"39564",
    "sg:province":"MS",
    "sg:tags":[
        "telephone",
        "cellular"
    ],
    "wof:name":"Magnolia Wireless",
    "wof:placetype":"venue"
},
  "geometry": {"coordinates":[-88.836848,30.441266],"type":"Point"}
}