{
  "type": "Feature",
  "properties": {
    "iso:country":"US",
    "sg:address":"119 Malcomb St",
    "sg:city":"Houston",
    "sg:classifiers":[
        {
            "category":"Personal",
            "subcategory":"Beauty Salon",
            "type":"Services"
        }
    ],
    "sg:phone":"+1 662 456 1494",
    "sg:postcode":"38851",
    "sg:province":"MS",
    "sg:tags":[
        "shop"
    ],
    "wof:name":"Pam's Hair Gallery",
    "wof:placetype":"venue"
},
  "geometry": {"coordinates":[-89.002202,33.906575],"type":"Point"}
}