{
  "type": "Feature",
  "properties": {
    "iso:country":"US",
    "sg:address":"309 W Cypress St",
    "sg:city":"Charleston",
    "sg:classifiers":[
        {
            "category":"Government",
            "subcategory":"Office",
            "type":"Public Place"
        }
    ],
    "sg:phone":"+1 662 647 8857",
    "sg:postcode":"38921",
    "sg:province":"MS",
    "sg:tags":[
        "federal"
    ],
    "wof:name":"US Consolidated Farm Svc Agcy",
    "wof:placetype":"venue"
},
  "geometry": {"coordinates":[-90.061701,34.005035],"type":"Point"}
}