{
  "type": "Feature",
  "properties": {
    "iso:country":"US",
    "sg:address":"124 Parkway Plz",
    "sg:city":"Kosciusko",
    "sg:classifiers":[
        {
            "category":"Banks & Credit Unions",
            "subcategory":"Bank",
            "type":"Services"
        }
    ],
    "sg:phone":"+1 662 290 0909",
    "sg:postcode":"39090",
    "sg:province":"MS",
    "sg:tags":[
        "cashing",
        "check"
    ],
    "wof:name":"Rapid Cash Inc",
    "wof:placetype":"venue"
},
  "geometry": {"coordinates":[-89.60683899999999,33.060374],"type":"Point"}
}