{
  "type": "Feature",
  "properties": {
    "iso:country":"US",
    "sg:address":"2202 Jackson Ave W",
    "sg:city":"Oxford",
    "sg:classifiers":[
        {
            "category":"Building & Trades",
            "subcategory":"Equipment Rental",
            "type":"Services"
        }
    ],
    "sg:phone":"+1 662 234 4004",
    "sg:postcode":"38655",
    "sg:province":"MS",
    "sg:tags":[
        "passenger",
        "pas",
        "local",
        "car"
    ],
    "wof:name":"Sensible Car Rental",
    "wof:placetype":"venue"
},
  "geometry": {"coordinates":[-89.56179899999999,34.362454],"type":"Point"}
}