{
  "type": "Feature",
  "properties": {
    "addr:full":"15465 Hudson Krohn Rd Biloxi MS 39532",
    "addr:housenumber":"15465",
    "addr:postcode":"39532",
    "addr:street":"Hudson Krohn Rd",
    "iso:country":"US",
    "sg:address":"15465 Hudson Krohn Rd",
    "sg:city":"Biloxi",
    "sg:classifiers":[
        {
            "category":"Building & Trades",
            "subcategory":"Construction",
            "type":"Services"
        }
    ],
    "sg:phone":"+1 228 396 1640",
    "sg:postcode":"39532",
    "sg:province":"MS",
    "sg:tags":[
        "general",
        "contractor"
    ],
    "wof:name":"DNP Inc",
    "wof:placetype":"venue"
},
  "geometry": {"coordinates":[-88.95197,30.508831],"type":"Point"}
}