{
  "type": "Feature",
  "properties": {
    "addr:full":"406 W Fortification St Jackson MS 39203",
    "addr:housenumber":"406",
    "addr:postcode":"39203",
    "addr:street":"W Fortification St",
    "iso:country":"US",
    "sg:address":"406 W Fortification St",
    "sg:city":"Jackson",
    "sg:classifiers":[
        {
            "category":"Professional",
            "subcategory":"Engineering",
            "type":"Services"
        }
    ],
    "sg:phone":"+1 601 354 5220",
    "sg:postcode":"39203",
    "sg:province":"MS",
    "sg:tags":[
        "engineer"
    ],
    "wof:name":"Tru-Amp Corp",
    "wof:placetype":"venue"
},
  "geometry": {"coordinates":[-90.19506199999999,32.312165],"type":"Point"}
}