{
  "type": "Feature",
  "properties": {
    "iso:country":"US",
    "sg:address":"1823 34th St",
    "sg:city":"Meridian",
    "sg:classifiers":[
        {
            "category":"Arts & Performance",
            "subcategory":"Theater",
            "type":"Entertainment"
        }
    ],
    "sg:phone":"+1 601 483 2461",
    "sg:postcode":"39305",
    "sg:province":"MS",
    "sg:tags":[
        "group"
    ],
    "wof:name":"Rogers Hunting Club",
    "wof:placetype":"venue"
},
  "geometry": {"coordinates":[-88.698798,32.392362],"type":"Point"}
}