{
  "type": "Feature",
  "properties": {
    "addr:full":"13035 Circle G Ranch Rd Picayune MS 39466",
    "addr:housenumber":"13035",
    "addr:postcode":"39466",
    "addr:street":"Circle G Ranch Rd",
    "iso:country":"US",
    "sg:address":"13035 Circle G Ranch Rd",
    "sg:city":"Picayune",
    "sg:classifiers":[
        {
            "category":"Education",
            "subcategory":"Special Training",
            "type":"Public Place"
        }
    ],
    "sg:phone":"+1 601 749 0870",
    "sg:postcode":"39466",
    "sg:province":"MS",
    "sg:tags":[
        "reading",
        "instruction",
        "improvement"
    ],
    "wof:name":"Fleming Enterprises",
    "wof:placetype":"venue"
},
  "geometry": {"coordinates":[-89.545265,30.509146],"type":"Point"}
}