{
  "type": "Feature",
  "properties": {
    "iso:country":"US",
    "sg:address":"3603 State Hwy 178",
    "sg:city":"Holly Springs",
    "sg:classifiers":[
        {
            "category":"Freight",
            "type":"Transportation"
        }
    ],
    "sg:phone":"+1 662 252 3289",
    "sg:postcode":"38635",
    "sg:province":"MS",
    "sg:tags":[
        "operator",
        "local",
        "trucking"
    ],
    "wof:name":"Echols Trucking",
    "wof:placetype":"venue"
},
  "geometry": {"coordinates":[-89.550794,34.823335],"type":"Point"}
}