{
  "type": "Feature",
  "properties": {
    "iso:country":"US",
    "sg:address":"106 N 2nd St",
    "sg:city":"Brookhaven",
    "sg:classifiers":[
        {
            "category":"Restaurant",
            "type":"Food & Drink"
        }
    ],
    "sg:phone":"+1 601 833 1337",
    "sg:postcode":"39601",
    "sg:province":"MS",
    "sg:tags":[
        "out"
    ],
    "wof:name":"Corner Fish Market",
    "wof:placetype":"venue"
},
  "geometry": {"coordinates":[-90.438812,31.579929],"type":"Point"}
}