{
  "type": "Feature",
  "properties": {
    "iso:country":"US",
    "sg:address":"20 The Rays Trl SE",
    "sg:city":"Bogue Chitto",
    "sg:classifiers":[
        {
            "category":"Organizations",
            "subcategory":"Religious Organization",
            "type":"Services"
        }
    ],
    "sg:phone":"+1 601 833 8363",
    "sg:postcode":"39629",
    "sg:province":"MS",
    "sg:tags":[
        "house",
        "retreat"
    ],
    "sg:website":"www.therays.org",
    "wof:name":"Rays",
    "wof:placetype":"venue"
},
  "geometry": {"coordinates":[-90.46619,31.507199],"type":"Point"}
}