{
  "type": "Feature",
  "properties": {
    "iso:country":"US",
    "sg:address":"3635 14th St",
    "sg:city":"Pascagoula",
    "sg:classifiers":[
        {
            "category":"Autos & Motor Vehicles",
            "subcategory":"Automobile Sales",
            "type":"Retail Goods"
        }
    ],
    "sg:phone":"+1 228 762 5455",
    "sg:postcode":"39567",
    "sg:province":"MS",
    "sg:tags":[
        "car",
        "dealer"
    ],
    "wof:name":"Sun Coast Auto Sales",
    "wof:placetype":"venue"
},
  "geometry": {"coordinates":[-88.53921800000001,30.373013],"type":"Point"}
}