{
  "type": "Feature",
  "properties": {
    "addr:full":"500 S Loftin St Picayune MS 39466",
    "addr:housenumber":"500",
    "addr:postcode":"39466",
    "addr:street":"S Loftin St",
    "iso:country":"US",
    "sg:address":"500 S Loftin St",
    "sg:city":"Picayune",
    "sg:classifiers":[
        {
            "category":"Restaurant",
            "type":"Food & Drink"
        }
    ],
    "sg:phone":"+1 601 799 2992",
    "sg:postcode":"39466",
    "sg:province":"MS",
    "sg:tags":[
        "eating"
    ],
    "wof:name":"Shoneys 1513",
    "wof:placetype":"venue"
},
  "geometry": {"coordinates":[-89.665103,30.521406],"type":"Point"}
}