{
  "type": "Feature",
  "properties": {
    "iso:country":"US",
    "sg:address":"4656 Hwy 18",
    "sg:city":"Brandon",
    "sg:classifiers":[
        {
            "category":"Organizations",
            "subcategory":"Religious Organization",
            "type":"Services"
        }
    ],
    "sg:phone":"+1 601 825 5804",
    "sg:postcode":"39042",
    "sg:province":"MS",
    "wof:name":"Rock Hill Baptist Church Inc",
    "wof:placetype":"venue"
},
  "geometry": {"coordinates":[-89.835459,32.13036],"type":"Point"}
}