{
  "type": "Feature",
  "properties": {
    "addr:full":"14021 Suburban Dr Ocean Springs MS 39565",
    "addr:housenumber":"14021",
    "addr:postcode":"39565",
    "addr:street":"Suburban Dr",
    "iso:country":"US",
    "sg:address":"14021 Suburban Dr",
    "sg:city":"Ocean Springs",
    "sg:classifiers":[
        {
            "category":"Professional",
            "subcategory":"Business Services",
            "type":"Services"
        }
    ],
    "sg:phone":"+1 228 875 3921",
    "sg:postcode":"39565",
    "sg:province":"MS",
    "wof:name":"Hungerford Company",
    "wof:placetype":"venue"
},
  "geometry": {"coordinates":[-88.843174,30.471525],"type":"Point"}
}