{
  "type": "Feature",
  "properties": {
    "addr:full":"60019 McKenzie Rd Smithville MS 38870",
    "addr:housenumber":"60019",
    "addr:postcode":"38870",
    "addr:street":"Mckenzie Rd",
    "iso:country":"US",
    "sg:address":"60019 McKenzie Rd",
    "sg:city":"Smithville",
    "sg:classifiers":[
        {
            "category":"Building & Trades",
            "subcategory":"Plumbing",
            "type":"Services"
        }
    ],
    "sg:phone":"+1 662 651 4631",
    "sg:postcode":"38870",
    "sg:province":"MS",
    "sg:tags":[
        "contractor"
    ],
    "wof:name":"Stephenson Plumbing",
    "wof:placetype":"venue"
},
  "geometry": {"coordinates":[-88.336618,34.067668],"type":"Point"}
}