{
  "type": "Feature",
  "properties": {
    "addr:full":"310 E Main St Starkville MS 39759",
    "addr:housenumber":"310",
    "addr:postcode":"39759",
    "addr:street":"E Main St",
    "iso:country":"US",
    "sg:address":"310 E Main St",
    "sg:city":"Starkville",
    "sg:classifiers":[
        {
            "category":"Food & Beverages",
            "subcategory":"Groceries & Convenience Stores",
            "type":"Retail Goods"
        }
    ],
    "sg:phone":"+1 662 324 1696",
    "sg:postcode":"39759",
    "sg:province":"MS",
    "wof:name":"Major Mart Inc",
    "wof:placetype":"venue"
},
  "geometry": {"coordinates":[-88.812382,33.46384],"type":"Point"}
}