{
  "type": "Feature",
  "properties": {
    "iso:country":"US",
    "sg:address":"1000 Bonita Dr",
    "sg:city":"Meridian",
    "sg:classifiers":[
        {
            "category":"Shopping",
            "subcategory":"Beauty & Cosmetics",
            "type":"Retail Goods"
        }
    ],
    "sg:phone":"+1 601 485 3345",
    "sg:postcode":"39301",
    "sg:province":"MS",
    "sg:tags":[
        "personal",
        "product",
        "care"
    ],
    "wof:name":"Bath & Body Works 117",
    "wof:placetype":"venue"
},
  "geometry": {"coordinates":[-88.64173599999999,32.370554],"type":"Point"}
}