{
  "type": "Feature",
  "properties": {
    "addr:full":"207 Main St Mccomb MS 39648",
    "addr:housenumber":"207",
    "addr:postcode":"39648",
    "addr:street":"Main St",
    "iso:country":"US",
    "sg:address":"207 Main St",
    "sg:city":"Mccomb",
    "sg:classifiers":[
        {
            "category":"Home & Garden",
            "subcategory":"Furniture",
            "type":"Retail Goods"
        }
    ],
    "sg:phone":"+1 601 684 4551",
    "sg:postcode":"39648",
    "sg:province":"MS",
    "wof:name":"Lott Furniture Co",
    "wof:placetype":"venue"
},
  "geometry": {"coordinates":[-90.452189,31.243924],"type":"Point"}
}