{
  "type": "Feature",
  "properties": {
    "iso:country":"US",
    "sg:address":"1436 Reddix St",
    "sg:city":"Jackson",
    "sg:classifiers":[
        {
            "category":"Organizations",
            "subcategory":"Religious Organization",
            "type":"Services"
        }
    ],
    "sg:phone":"+1 601 922 6976",
    "sg:postcode":"39209",
    "sg:province":"MS",
    "wof:name":"Gray Christ Holiness Apostolic",
    "wof:placetype":"venue"
},
  "geometry": {"coordinates":[-90.283919,32.309847],"type":"Point"}
}