{
  "type": "Feature",
  "properties": {
    "iso:country":"US",
    "sg:address":"9805 Hwy 24 E",
    "sg:city":"Centreville",
    "sg:classifiers":[
        {
            "category":"Manufacturing",
            "subcategory":"Lumber",
            "type":"Manufacturing & Wholesale Goods"
        }
    ],
    "sg:phone":"+1 601 645 6363",
    "sg:postcode":"39631",
    "sg:province":"MS",
    "wof:name":"LAE Inc",
    "wof:placetype":"venue"
},
  "geometry": {"coordinates":[-91.13405400000001,31.078935],"type":"Point"}
}