{
  "type": "Feature",
  "properties": {
    "iso:country":"US",
    "sg:address":"2012 US Hwy 90",
    "sg:city":"Gautier",
    "sg:classifiers":[
        {
            "category":"Professional",
            "subcategory":"Business Services",
            "type":"Services"
        },
        {
            "category":"Professional",
            "subcategory":"Advertising",
            "type":"Services"
        }
    ],
    "sg:phone":"+1 228 497 4443",
    "sg:postcode":"39553",
    "sg:province":"MS",
    "sg:tags":[
        "guide"
    ],
    "wof:name":"Real Estate Guide Inc",
    "wof:placetype":"venue"
},
  "geometry": {"coordinates":[-88.641863,30.390527],"type":"Point"}
}