{
  "type": "Feature",
  "properties": {
    "iso:country":"US",
    "sg:address":"7603 Southcrest Pkwy",
    "sg:city":"Southaven",
    "sg:classifiers":[
        {
            "category":"Health Services",
            "subcategory":"Doctor",
            "type":"Services"
        }
    ],
    "sg:phone":"+1 662 349 8323",
    "sg:postcode":"38671",
    "sg:province":"MS",
    "sg:tags":[
        "medical"
    ],
    "wof:name":"Jacinto Hernandez MD",
    "wof:placetype":"venue"
},
  "geometry": {"coordinates":[-89.995425,34.968022],"type":"Point"}
}