{
  "type": "Feature",
  "properties": {
    "iso:country":"US",
    "sg:address":"3610 New Hope Rd",
    "sg:city":"Columbus",
    "sg:classifiers":[
        {
            "category":"Food & Beverages",
            "subcategory":"Groceries & Convenience Stores",
            "type":"Retail Goods"
        }
    ],
    "sg:phone":"+1 662 327 9447",
    "sg:postcode":"39702",
    "sg:province":"MS",
    "wof:name":"Piggly Wiggly",
    "wof:placetype":"venue"
},
  "geometry": {"coordinates":[-88.32723300000001,33.447778],"type":"Point"}
}