{
  "type": "Feature",
  "properties": {
    "addr:full":"321 Hwy 12 E Kosciusko MS 39090",
    "addr:housenumber":"321",
    "addr:postcode":"39090",
    "addr:street":"Hwy 12 E",
    "iso:country":"US",
    "sg:address":"321 Hwy 12 E",
    "sg:city":"Kosciusko",
    "sg:classifiers":[
        {
            "category":"Travel",
            "subcategory":"Hotels & Motels",
            "type":"Entertainment"
        }
    ],
    "sg:phone":"+1 662 289 4151",
    "sg:postcode":"39090",
    "sg:province":"MS",
    "wof:name":"Campbell Motel",
    "wof:placetype":"venue"
},
  "geometry": {"coordinates":[-89.585567,33.065864],"type":"Point"}
}