{
  "type": "Feature",
  "properties": {
    "addr:full":"36 Summer Pl Laurel MS 39402",
    "addr:housenumber":"36",
    "addr:postcode":"39402",
    "addr:street":"Summer Pl",
    "iso:country":"US",
    "sg:address":"36 Summer Pl",
    "sg:city":"Laurel",
    "sg:classifiers":[
        {
            "category":"Recreation",
            "type":"Entertainment"
        }
    ],
    "sg:phone":"+1 601 649 7953",
    "sg:postcode":"39402",
    "sg:province":"MS",
    "sg:tags":[
        "club",
        "membership"
    ],
    "wof:name":"Racks Hunting Club LLC",
    "wof:placetype":"venue"
},
  "geometry": {"coordinates":[-89.43733899999999,31.279508],"type":"Point"}
}