{
  "type": "Feature",
  "properties": {
    "addr:full":"2626 Hampton Ave Tupelo MS 38801",
    "addr:housenumber":"2626",
    "addr:postcode":"38801",
    "addr:street":"Hampton Ave",
    "iso:country":"US",
    "sg:address":"2626 Hampton Ave",
    "sg:city":"Tupelo",
    "sg:classifiers":[
        {
            "category":"Shopping",
            "subcategory":"Hobbies, Toys, & Games",
            "type":"Retail Goods"
        }
    ],
    "sg:phone":"+1 662 842 9058",
    "sg:postcode":"38801",
    "sg:province":"MS",
    "wof:name":"Jukes & Toys",
    "wof:placetype":"venue"
},
  "geometry": {"coordinates":[-88.751713,34.248029],"type":"Point"}
}