{
  "type": "Feature",
  "properties": {
    "iso:country":"US",
    "sg:address":"210 Goodman Rd E",
    "sg:city":"Southaven",
    "sg:classifiers":[
        {
            "category":"Health Services",
            "subcategory":"Doctor",
            "type":"Services"
        }
    ],
    "sg:phone":"+1 662 349 2251",
    "sg:postcode":"38671",
    "sg:province":"MS",
    "sg:tags":[
        "physician",
        "surgeon"
    ],
    "wof:name":"Richard A Kelly MD",
    "wof:placetype":"venue"
},
  "geometry": {"coordinates":[-89.985553,34.962807],"type":"Point"}
}