{
  "type": "Feature",
  "properties": {
    "addr:full":"3505 Terry Rd Jackson MS 39212",
    "addr:housenumber":"3505",
    "addr:postcode":"39212",
    "addr:street":"Terry Rd",
    "iso:country":"US",
    "sg:address":"3505 Terry Rd",
    "sg:city":"Jackson",
    "sg:classifiers":[
        {
            "category":"Professional",
            "subcategory":"Accounting & Tax Preparation",
            "type":"Services"
        }
    ],
    "sg:phone":"+1 601 373 7912",
    "sg:postcode":"39212",
    "sg:province":"MS",
    "sg:tags":[
        "return"
    ],
    "wof:name":"H & R Block",
    "wof:placetype":"venue"
},
  "geometry": {"coordinates":[-90.23154599999999,32.240638],"type":"Point"}
}