{
  "type": "Feature",
  "properties": {
    "iso:country":"US",
    "sg:address":"103 S Pearl St",
    "sg:city":"Natchez",
    "sg:classifiers":[
        {
            "category":"Professional",
            "subcategory":"Lawyer & Legal Services",
            "type":"Services"
        }
    ],
    "sg:phone":"+1 601 446 5366",
    "sg:postcode":"39120",
    "sg:province":"MS",
    "sg:tags":[
        "attorney"
    ],
    "wof:name":"County Prosecuting Attorney",
    "wof:placetype":"venue"
},
  "geometry": {"coordinates":[-91.403212,31.560119],"type":"Point"}
}