{
  "type": "Feature",
  "properties": {
    "addr:full":"1020 Mobile St Hattiesburg MS 39401",
    "addr:housenumber":"1020",
    "addr:postcode":"39401",
    "addr:street":"Mobile St",
    "iso:country":"US",
    "sg:address":"1020 Mobile St",
    "sg:city":"Hattiesburg",
    "sg:classifiers":[
        {
            "category":"Food & Beverages",
            "subcategory":"Candy",
            "type":"Retail Goods"
        }
    ],
    "sg:phone":"+1 601 582 4460",
    "sg:postcode":"39401",
    "sg:province":"MS",
    "wof:name":"Fannie Knight",
    "wof:placetype":"venue"
},
  "geometry": {"coordinates":[-89.29003,31.341054],"type":"Point"}
}