{
  "type": "Feature",
  "properties": {
    "iso:country":"US",
    "sg:address":"101 Edgewood Dr",
    "sg:city":"Mccomb",
    "sg:classifiers":[
        {
            "category":"Building & Trades",
            "subcategory":"Construction",
            "type":"Services"
        }
    ],
    "sg:phone":"+1 601 250 1006",
    "sg:postcode":"39648",
    "sg:province":"MS",
    "sg:tags":[
        "general",
        "contractor"
    ],
    "wof:name":"Winesett Hill Constuctors",
    "wof:placetype":"venue"
},
  "geometry": {"coordinates":[-90.47830999999999,31.261229],"type":"Point"}
}