{
  "type": "Feature",
  "properties": {
    "iso:country":"US",
    "sg:address":"803 Moselle-Seminary Rd",
    "sg:city":"Moselle",
    "sg:classifiers":[
        {
            "category":"Government",
            "subcategory":"Office",
            "type":"Public Place"
        }
    ],
    "sg:phone":"+1 601 752 5099",
    "sg:postcode":"39459",
    "sg:province":"MS",
    "sg:tags":[
        "program",
        "state",
        "adm"
    ],
    "wof:name":"Ms Agriculture & Commerce Dept",
    "wof:placetype":"venue"
},
  "geometry": {"coordinates":[-89.34008900000001,31.54189],"type":"Point"}
}