{
  "type": "Feature",
  "properties": {
    "iso:country":"US",
    "sg:address":"893 Hwy 82 W",
    "sg:city":"Greenville",
    "sg:classifiers":[
        {
            "category":"Freight",
            "type":"Transportation"
        },
        {
            "category":"Shopping",
            "subcategory":"Jewelry",
            "type":"Retail Goods"
        }
    ],
    "sg:phone":"+1 662 378 2140",
    "sg:postcode":"38701",
    "sg:province":"MS",
    "sg:tags":[
        "hauler",
        "used",
        "hauling",
        "merchandise",
        "trucking"
    ],
    "wof:name":"H & H Freight Lines Inc",
    "wof:placetype":"venue"
},
  "geometry": {"coordinates":[-91.059428,33.394488],"type":"Point"}
}