{
  "type": "Feature",
  "properties": {
    "iso:country":"US",
    "sg:address":"1583 Oak Park Ln",
    "sg:city":"Tupelo",
    "sg:classifiers":[
        {
            "category":"Building & Trades",
            "subcategory":"Electrical",
            "type":"Services"
        }
    ],
    "sg:phone":"+1 662 842 3555",
    "sg:postcode":"38801",
    "sg:province":"MS",
    "sg:tags":[
        "electrical",
        "contractor"
    ],
    "wof:name":"Burleson Elec Co",
    "wof:placetype":"venue"
},
  "geometry": {"coordinates":[-88.740937,34.234074],"type":"Point"}
}