{
  "type": "Feature",
  "properties": {
    "iso:country":"US",
    "sg:address":"5150 Sharon Dr",
    "sg:city":"Meridian",
    "sg:classifiers":[
        {
            "category":"Personal",
            "subcategory":"Beauty Salon",
            "type":"Services"
        }
    ],
    "sg:phone":"+1 601 483 0780",
    "sg:postcode":"39301",
    "sg:province":"MS",
    "sg:tags":[
        "shop"
    ],
    "wof:name":"Debbies Cut Curls",
    "wof:placetype":"venue"
},
  "geometry": {"coordinates":[-88.691023,32.291761],"type":"Point"}
}