{
  "type": "Feature",
  "properties": {
    "iso:country":"US",
    "sg:address":"3305 33rd St",
    "sg:city":"Gulfport",
    "sg:classifiers":[
        {
            "category":"Wholesale",
            "subcategory":"Construction Materials",
            "type":"Manufacturing & Wholesale Goods"
        }
    ],
    "sg:phone":"+1 228 863 6121",
    "sg:postcode":"39501",
    "sg:province":"MS",
    "sg:tags":[
        "siding"
    ],
    "wof:name":"American Wholesale Bldg Prods",
    "wof:placetype":"venue"
},
  "geometry": {"coordinates":[-89.100407,30.390095],"type":"Point"}
}