{
  "type": "Feature",
  "properties": {
    "iso:country":"US",
    "sg:address":"119 Tiffany Dr",
    "sg:city":"Brandon",
    "sg:classifiers":[
        {
            "category":"Organizations",
            "subcategory":"Religious Organization",
            "type":"Services"
        }
    ],
    "sg:phone":"+1 601 825 1043",
    "sg:postcode":"39042",
    "sg:province":"MS",
    "wof:name":"Gary Bowlin Evangelistic",
    "wof:placetype":"venue"
},
  "geometry": {"coordinates":[-89.93559500000001,32.300505],"type":"Point"}
}