{
  "type": "Feature",
  "properties": {
    "addr:full":"600 Chickasawhay St Waynesboro MS 39367",
    "addr:housenumber":"600",
    "addr:postcode":"39367",
    "addr:street":"Chickasawhay St",
    "iso:country":"US",
    "sg:address":"600 Chickasawhay St",
    "sg:city":"Waynesboro",
    "sg:classifiers":[
        {
            "category":"Wholesale",
            "subcategory":"Farm Supplies",
            "type":"Manufacturing & Wholesale Goods"
        }
    ],
    "sg:phone":"+1 601 735 5100",
    "sg:postcode":"39367",
    "sg:province":"MS",
    "wof:name":"Wayne County Farm Ctr",
    "wof:placetype":"venue"
},
  "geometry": {"coordinates":[-88.645746,31.673306],"type":"Point"}
}