{
  "type": "Feature",
  "properties": {
    "iso:country":"US",
    "sg:address":"321 Pass Rd",
    "sg:city":"Gulfport",
    "sg:classifiers":[
        {
            "category":"Wholesale",
            "subcategory":"Toys & Hobbies",
            "type":"Manufacturing & Wholesale Goods"
        }
    ],
    "sg:phone":"+1 228 865 1998",
    "sg:postcode":"39501",
    "sg:province":"MS",
    "sg:tags":[
        "wholesaler"
    ],
    "wof:name":"Schneider's Wholesale Outlet",
    "wof:placetype":"venue"
},
  "geometry": {"coordinates":[-89.056669,30.390492],"type":"Point"}
}