{
  "type": "Feature",
  "properties": {
    "iso:country":"US",
    "sg:address":"226 W Park Ave",
    "sg:city":"Drew",
    "sg:classifiers":[
        {
            "category":"Food & Beverages",
            "subcategory":"Groceries & Convenience Stores",
            "type":"Retail Goods"
        }
    ],
    "sg:phone":"+1 662 745 2146",
    "sg:postcode":"38737",
    "sg:province":"MS",
    "wof:name":"Village Grocery",
    "wof:placetype":"venue"
},
  "geometry": {"coordinates":[-90.53029600000001,33.812187],"type":"Point"}
}