{
  "type": "Feature",
  "properties": {
    "iso:country":"US",
    "sg:address":"4081 Co Rd 200",
    "sg:city":"Corinth",
    "sg:classifiers":[
        {
            "category":"Autos & Motor Vehicles",
            "subcategory":"Automobile Sales",
            "type":"Retail Goods"
        }
    ],
    "sg:phone":"+1 662 287 3895",
    "sg:postcode":"38834",
    "sg:province":"MS",
    "sg:tags":[
        "car",
        "dealer"
    ],
    "wof:name":"Burcham Used Cars & Body Shop",
    "wof:placetype":"venue"
},
  "geometry": {"coordinates":[-88.46142500000001,34.930633],"type":"Point"}
}