{
  "type": "Feature",
  "properties": {
    "addr:full":"95 Oakridge Rd Boyle MS 38730",
    "addr:housenumber":"95",
    "addr:postcode":"38730",
    "addr:street":"Oakridge Rd",
    "iso:country":"US",
    "sg:address":"95 Oakridge Rd",
    "sg:city":"Boyle",
    "sg:classifiers":[
        {
            "category":"Building & Trades",
            "subcategory":"Construction",
            "type":"Services"
        }
    ],
    "sg:phone":"+1 662 843 0200",
    "sg:postcode":"38730",
    "sg:province":"MS",
    "sg:tags":[
        "designer",
        "general",
        "contractor",
        "dealer",
        "pool",
        "swimming"
    ],
    "wof:name":"Pools By Byron Inc",
    "wof:placetype":"venue"
},
  "geometry": {"coordinates":[-90.730987,33.718099],"type":"Point"}
}