{
  "type": "Feature",
  "properties": {
    "iso:country":"US",
    "sg:address":"71 Hwy 341",
    "sg:city":"Pontotoc",
    "sg:classifiers":[
        {
            "category":"Retail",
            "subcategory":"Repair Shop",
            "type":"Services"
        }
    ],
    "sg:phone":"+1 662 489 2172",
    "sg:postcode":"38863",
    "sg:province":"MS",
    "wof:name":"Waldos Upholstery",
    "wof:placetype":"venue"
},
  "geometry": {"coordinates":[-89.044146,34.234584],"type":"Point"}
}