{
  "type": "Feature",
  "properties": {
    "addr:full":"503 Silver Cross Dr Brookhaven MS 39601",
    "addr:housenumber":"503",
    "addr:postcode":"39601",
    "addr:street":"Silver Cross Dr",
    "iso:country":"US",
    "sg:address":"503 Silver Cross Dr",
    "sg:city":"Brookhaven",
    "sg:classifiers":[
        {
            "category":"Social Services",
            "subcategory":"Job Training",
            "type":"Services"
        }
    ],
    "sg:phone":"+1 601 833 2353",
    "sg:postcode":"39601",
    "sg:province":"MS",
    "sg:tags":[
        "rehabilitation"
    ],
    "wof:name":"Summit The Health & Rehab Svc",
    "wof:placetype":"venue"
},
  "geometry": {"coordinates":[-90.460497,31.588235],"type":"Point"}
}