{
  "type": "Feature",
  "properties": {
    "addr:full":"9008 Highway 19 N Collinsville MS 39325",
    "addr:housenumber":"9008",
    "addr:postcode":"39325",
    "addr:street":"Highway 19 N",
    "iso:country":"US",
    "sg:address":"9008 Highway 19 N",
    "sg:city":"Collinsville",
    "sg:classifiers":[
        {
            "category":"Shopping",
            "subcategory":"Department Store",
            "type":"Retail Goods"
        },
        {
            "category":"Shopping",
            "subcategory":"Discount & Variety Stores",
            "type":"Retail Goods"
        },
        {
            "category":"Shopping",
            "type":"Retail Goods"
        },
        {
            "category":"Food & Beverages",
            "subcategory":"Groceries & Convenience Stores",
            "type":"Retail Goods"
        }
    ],
    "sg:phone":"+1 601 626 0375",
    "sg:postcode":"39325",
    "sg:province":"MS",
    "sg:tags":[
        "merchandise"
    ],
    "sg:website":"http://www.dollargeneral.com",
    "wof:name":"Dollar General",
    "wof:placetype":"venue"
},
  "geometry": {"coordinates":[-88.841784,32.491946],"type":"Point"}
}