{
  "type": "Feature",
  "properties": {
    "iso:country":"US",
    "sg:address":"538 Vaiden Kilmichael Rd",
    "sg:city":"Kilmichael",
    "sg:classifiers":[
        {
            "category":"Home & Garden",
            "subcategory":"Hardware",
            "type":"Retail Goods"
        }
    ],
    "sg:phone":"+1 662 262 4570",
    "sg:postcode":"39747",
    "sg:province":"MS",
    "sg:tags":[
        "repair"
    ],
    "wof:name":"Massey S D",
    "wof:placetype":"venue"
},
  "geometry": {"coordinates":[-89.59577299999999,33.420116],"type":"Point"}
}