{
  "type": "Feature",
  "properties": {
    "addr:full":"304 E Railroad Ave Crystal Springs MS 39059",
    "addr:housenumber":"304",
    "addr:postcode":"39059",
    "addr:street":"E Railroad Ave",
    "iso:country":"US",
    "sg:address":"304 E Railroad Ave",
    "sg:city":"Crystal Springs",
    "sg:classifiers":[
        {
            "category":"Personal",
            "subcategory":"Beauty Salon",
            "type":"Services"
        }
    ],
    "sg:phone":"+1 601 892 2892",
    "sg:postcode":"39059",
    "sg:province":"MS",
    "sg:tags":[
        "shop"
    ],
    "wof:name":"Hair Designs",
    "wof:placetype":"venue"
},
  "geometry": {"coordinates":[-90.358148,31.986937],"type":"Point"}
}