{
  "type": "Feature",
  "properties": {
    "iso:country":"US",
    "sg:address":"12219 Highway 49",
    "sg:city":"Gulfport",
    "sg:classifiers":[
        {
            "category":"Restaurant",
            "type":"Food & Drink"
        }
    ],
    "sg:menulink":"http://www.allmenus.com/ms/gulfport/156116-hardees/menu/",
    "sg:phone":"+1 228 831 2248",
    "sg:postcode":"39503",
    "sg:province":"MS",
    "sg:tags":[
        "burger",
        "american"
    ],
    "wof:name":"Hardee's",
    "wof:placetype":"venue"
},
  "geometry": {"coordinates":[-89.101752,30.46285],"type":"Point"}
}