{
  "type": "Feature",
  "properties": {
    "iso:country":"US",
    "sg:address":"3199 Georgette Ln",
    "sg:city":"Biloxi",
    "sg:classifiers":[
        {
            "category":"Professional",
            "subcategory":"Business Services",
            "type":"Services"
        }
    ],
    "sg:phone":"+1 228 392 0036",
    "sg:postcode":"39540",
    "sg:province":"MS",
    "wof:name":"Nikis Bottoms",
    "wof:placetype":"venue"
},
  "geometry": {"coordinates":[-88.88339499999999,30.453253],"type":"Point"}
}