{
  "type": "Feature",
  "properties": {
    "iso:country":"US",
    "sg:address":"4400 Peters St",
    "sg:city":"Moss Point",
    "sg:classifiers":[
        {
            "category":"Government",
            "subcategory":"Office",
            "type":"Public Place"
        }
    ],
    "sg:phone":"+1 228 475 8271",
    "sg:postcode":"39563",
    "sg:province":"MS",
    "wof:name":"Ted B Hinson Homes",
    "wof:placetype":"venue"
},
  "geometry": {"coordinates":[-88.509236,30.40606],"type":"Point"}
}