{
  "type": "Feature",
  "properties": {
    "iso:country":"US",
    "sg:address":"204 Pine St",
    "sg:city":"Shuqualak",
    "sg:classifiers":[
        {
            "category":"Government",
            "subcategory":"Office",
            "type":"Public Place"
        }
    ],
    "sg:phone":"+1 662 793 4521",
    "sg:postcode":"39339",
    "sg:province":"MS",
    "sg:tags":[
        "city"
    ],
    "wof:name":"Shuqualak Mayor's Office",
    "wof:placetype":"venue"
},
  "geometry": {"coordinates":[-89.055143,33.113863],"type":"Point"}
}