{
  "type": "Feature",
  "properties": {
    "iso:country":"US",
    "sg:address":"3 Lafayette Cir",
    "sg:city":"Clinton",
    "sg:classifiers":[
        {
            "category":"Wholesale",
            "subcategory":"Furniture",
            "type":"Manufacturing & Wholesale Goods"
        }
    ],
    "sg:phone":"+1 601 924 1696",
    "sg:postcode":"39056",
    "sg:province":"MS",
    "wof:name":"Gilstraps Sales Inc",
    "wof:placetype":"venue"
},
  "geometry": {"coordinates":[-90.31011100000001,32.373725],"type":"Point"}
}