{
  "type": "Feature",
  "properties": {
    "iso:country":"US",
    "sg:address":"302 Sandy St",
    "sg:city":"Waveland",
    "sg:classifiers":[
        {
            "category":"Manufacturing",
            "subcategory":"Lumber",
            "type":"Manufacturing & Wholesale Goods"
        }
    ],
    "sg:phone":"+1 228 463 9505",
    "sg:postcode":"39576",
    "sg:province":"MS",
    "sg:tags":[
        "woodcarver",
        "arts",
        "ceramic",
        "artist"
    ],
    "wof:name":"Bowens and Company",
    "wof:placetype":"venue"
},
  "geometry": {"coordinates":[-89.381182,30.278125],"type":"Point"}
}