{
  "type": "Feature",
  "properties": {
    "iso:country":"US",
    "sg:address":"1397 Wildcat Bottom Rd",
    "sg:city":"Red Banks",
    "sg:classifiers":[
        {
            "category":"Building & Trades",
            "subcategory":"Construction",
            "type":"Services"
        }
    ],
    "sg:phone":"+1 662 851 3364",
    "sg:postcode":"38661",
    "sg:province":"MS",
    "sg:tags":[
        "custom",
        "kitchen",
        "cabinet"
    ],
    "wof:name":"Heritage Custom Cabinets",
    "wof:placetype":"venue"
},
  "geometry": {"coordinates":[-89.529449,34.905356],"type":"Point"}
}