{
  "type": "Feature",
  "properties": {
    "iso:country":"US",
    "sg:address":"118 Dean Dr",
    "sg:city":"Verona",
    "sg:classifiers":[
        {
            "category":"Building & Trades",
            "subcategory":"Plumbing",
            "type":"Services"
        }
    ],
    "sg:phone":"+1 662 840 2025",
    "sg:postcode":"38879",
    "sg:province":"MS",
    "sg:tags":[
        "plumbing",
        "contractor"
    ],
    "wof:name":"Joey Campbell Sewer & Drain",
    "wof:placetype":"venue"
},
  "geometry": {"coordinates":[-88.70892499999999,34.186799],"type":"Point"}
}