{
  "type": "Feature",
  "properties": {
    "iso:country":"US",
    "sg:address":"1035 Desoto Ave",
    "sg:city":"Clarksdale",
    "sg:classifiers":[
        {
            "category":"Autos & Motor Vehicles",
            "subcategory":"Fuel & Gas Station",
            "type":"Retail Goods"
        },
        {
            "category":"Food & Beverages",
            "subcategory":"Groceries & Convenience Stores",
            "type":"Retail Goods"
        }
    ],
    "sg:phone":"+1 662 624 2060",
    "sg:postcode":"38614",
    "sg:province":"MS",
    "wof:name":"Filling Station 32",
    "wof:placetype":"venue"
},
  "geometry": {"coordinates":[-90.561955,34.190935],"type":"Point"}
}