{
  "type": "Feature",
  "properties": {
    "addr:full":"1469 Macedonia Rd Ellisville MS 39465",
    "addr:housenumber":"1469",
    "addr:postcode":"39465",
    "addr:street":"Macedonia Rd",
    "iso:country":"US",
    "sg:address":"1469 Macedonia Rd",
    "sg:city":"Ellisville",
    "sg:classifiers":[
        {
            "category":"Building & Trades",
            "subcategory":"Construction",
            "type":"Services"
        }
    ],
    "sg:phone":"+1 601 582 9224",
    "sg:postcode":"39465",
    "sg:province":"MS",
    "sg:tags":[
        "contractor"
    ],
    "wof:name":"Stan R Williams Masonry",
    "wof:placetype":"venue"
},
  "geometry": {"coordinates":[-89.18050599999999,31.441658],"type":"Point"}
}