{
  "type": "Feature",
  "properties": {
    "iso:country":"US",
    "sg:address":"1300 N Lamar Blvd",
    "sg:city":"Oxford",
    "sg:classifiers":[
        {
            "category":"Personal",
            "subcategory":"Beauty Salon",
            "type":"Services"
        }
    ],
    "sg:phone":"+1 662 234 5501",
    "sg:postcode":"38655",
    "sg:province":"MS",
    "wof:name":"Casa Bella Hair Designs",
    "wof:placetype":"venue"
},
  "geometry": {"coordinates":[-89.510632,34.379717],"type":"Point"}
}