{
  "type": "Feature",
  "properties": {
    "addr:full":"2567 N West St Jackson MS 39202",
    "addr:housenumber":"2567",
    "addr:postcode":"39202",
    "addr:street":"N West St",
    "iso:country":"US",
    "sg:address":"2567 N West St",
    "sg:city":"Jackson",
    "sg:classifiers":[
        {
            "category":"Government",
            "subcategory":"Office",
            "type":"Public Place"
        }
    ],
    "sg:phone":"+1 601 359 1424",
    "sg:postcode":"39202",
    "sg:province":"MS",
    "wof:name":"Highway Building & Ground",
    "wof:placetype":"venue"
},
  "geometry": {"coordinates":[-90.182215,32.331756],"type":"Point"}
}