{
  "type": "Feature",
  "properties": {
    "addr:full":"1000 S State St Clarksdale MS 38614",
    "addr:housenumber":"1000",
    "addr:postcode":"38614",
    "addr:street":"S State St",
    "iso:country":"US",
    "sg:address":"1000 S State St",
    "sg:city":"Clarksdale",
    "sg:classifiers":[
        {
            "category":"Restaurant",
            "type":"Food & Drink"
        }
    ],
    "sg:menulink":"http://www.allmenus.com/ms/5/132904-subway/menu/",
    "sg:phone":"+1 662 624 9291",
    "sg:postcode":"38614",
    "sg:province":"MS",
    "sg:tags":[
        "american",
        "sandwich"
    ],
    "wof:name":"Subway",
    "wof:placetype":"venue"
},
  "geometry": {"coordinates":[-90.588962,34.185109],"type":"Point"}
}