{
  "type": "Feature",
  "properties": {
    "iso:country":"US",
    "sg:address":"2703 US Hwy 90",
    "sg:city":"Gautier",
    "sg:classifiers":[
        {
            "category":"Professional",
            "type":"Services"
        }
    ],
    "sg:phone":"+1 228 769 8898",
    "sg:postcode":"39553",
    "sg:province":"MS",
    "sg:tags":[
        "establishment"
    ],
    "wof:name":"Yellow Pages By Berry",
    "wof:placetype":"venue"
},
  "geometry": {"coordinates":[-88.651816,30.391711],"type":"Point"}
}