{
  "type": "Feature",
  "properties": {
    "iso:country":"US",
    "sg:address":"4420 8th St",
    "sg:city":"Meridian",
    "sg:classifiers":[
        {
            "category":"Shopping",
            "subcategory":"Pharmacy",
            "type":"Retail Goods"
        }
    ],
    "sg:phone":"+1 601 482 5578",
    "sg:postcode":"39301",
    "sg:province":"MS",
    "wof:name":"Mr Discount Drugs",
    "wof:placetype":"venue"
},
  "geometry": {"coordinates":[-88.72279899999999,32.364625],"type":"Point"}
}