{
  "type": "Feature",
  "properties": {
    "addr:full":"10049 1st Ave W Diberville MS 39532",
    "addr:housenumber":"10049",
    "addr:postcode":"39532",
    "addr:street":"1St Ave W Diberville",
    "iso:country":"US",
    "sg:address":"10049 1st Ave W",
    "sg:city":"Diberville",
    "sg:classifiers":[
        {
            "category":"Insurance",
            "subcategory":"Insurance Agent",
            "type":"Services"
        }
    ],
    "sg:phone":"+1 228 392 3338",
    "sg:postcode":"39532",
    "sg:province":"MS",
    "wof:name":"State Farm Insurance",
    "wof:placetype":"venue"
},
  "geometry": {"coordinates":[-88.891701,30.426738],"type":"Point"}
}