{
  "type": "Feature",
  "properties": {
    "iso:country":"US",
    "sg:address":"40 Timberland Dr",
    "sg:city":"Purvis",
    "sg:classifiers":[
        {
            "category":"Shopping",
            "subcategory":"Florist",
            "type":"Retail Goods"
        }
    ],
    "sg:phone":"+1 601 794 4612",
    "sg:postcode":"39475",
    "sg:province":"MS",
    "wof:name":"Rose Garden Florist",
    "wof:placetype":"venue"
},
  "geometry": {"coordinates":[-89.423258,31.159386],"type":"Point"}
}