{
  "type": "Feature",
  "properties": {
    "iso:country":"US",
    "sg:address":"2313 Ellis Merchant Rd",
    "sg:city":"Moss Point",
    "sg:classifiers":[
        {
            "category":"Wholesale",
            "subcategory":"Electrical",
            "type":"Manufacturing & Wholesale Goods"
        }
    ],
    "sg:phone":"+1 228 588 2107",
    "sg:postcode":"39562",
    "sg:province":"MS",
    "sg:tags":[
        "equipment"
    ],
    "wof:name":"Southern Consolidated Elec Sls",
    "wof:placetype":"venue"
},
  "geometry": {"coordinates":[-88.57178399999999,30.647947],"type":"Point"}
}