{
  "type": "Feature",
  "properties": {
    "iso:country":"US",
    "sg:address":"2908 Hunter Rd",
    "sg:city":"Nesbit",
    "sg:classifiers":[
        {
            "category":"Building & Trades",
            "subcategory":"Construction",
            "type":"Services"
        }
    ],
    "sg:phone":"+1 662 449 2644",
    "sg:postcode":"38651",
    "sg:province":"MS",
    "sg:tags":[
        "general",
        "contractor"
    ],
    "wof:name":"National Home",
    "wof:placetype":"venue"
},
  "geometry": {"coordinates":[-89.98099000000001,34.903606],"type":"Point"}
}