{
  "type": "Feature",
  "properties": {
    "addr:full":"1200 Olive St Moorhead MS 38761",
    "addr:housenumber":"1200",
    "addr:postcode":"38761",
    "addr:street":"Olive St",
    "iso:country":"US",
    "sg:address":"1200 Olive St",
    "sg:city":"Moorhead",
    "sg:classifiers":[
        {
            "category":"Food & Beverages",
            "subcategory":"Groceries & Convenience Stores",
            "type":"Retail Goods"
        }
    ],
    "sg:phone":"+1 662 246 8550",
    "sg:postcode":"38761",
    "sg:province":"MS",
    "wof:name":"Delta Quick Stop",
    "wof:placetype":"venue"
},
  "geometry": {"coordinates":[-90.505742,33.454011],"type":"Point"}
}