{
  "type": "Feature",
  "properties": {
    "iso:country":"US",
    "sg:address":"2105 N 14th Ave",
    "sg:city":"Columbus",
    "sg:classifiers":[
        {
            "category":"Food & Beverages",
            "subcategory":"Liquor & Beverages",
            "type":"Retail Goods"
        }
    ],
    "sg:phone":"+1 662 329 2035",
    "sg:postcode":"39701",
    "sg:province":"MS",
    "wof:name":"Hill's Package Store",
    "wof:placetype":"venue"
},
  "geometry": {"coordinates":[-88.409727,33.510834],"type":"Point"}
}