{
  "type": "Feature",
  "properties": {
    "iso:country":"US",
    "sg:address":"500 Washington St",
    "sg:city":"Booneville",
    "sg:classifiers":[
        {
            "category":"Personal",
            "subcategory":"Beauty Salon",
            "type":"Services"
        }
    ],
    "sg:phone":"+1 662 720 1002",
    "sg:postcode":"38829",
    "sg:province":"MS",
    "wof:name":"Salon Esthetique",
    "wof:placetype":"venue"
},
  "geometry": {"coordinates":[-88.569002,34.658164],"type":"Point"}
}