{
  "type": "Feature",
  "properties": {
    "iso:country":"US",
    "sg:address":"110 Jones St",
    "sg:city":"Jackson",
    "sg:classifiers":[
        {
            "category":"Health Services",
            "subcategory":"Health Practitioner",
            "type":"Services"
        }
    ],
    "sg:phone":"+1 601 932 2493",
    "sg:postcode":"39218",
    "sg:province":"MS",
    "wof:name":"River Oaks Counseling Center",
    "wof:placetype":"venue"
},
  "geometry": {"coordinates":[-90.17173200000001,32.236116],"type":"Point"}
}