{
  "type": "Feature",
  "properties": {
    "addr:full":"1002 Telephone Rd Pascagoula MS 39567",
    "addr:housenumber":"1002",
    "addr:postcode":"39567",
    "addr:street":"Telephone Rd",
    "iso:country":"US",
    "sg:address":"1002 Telephone Rd",
    "sg:city":"Pascagoula",
    "sg:classifiers":[
        {
            "category":"Personal",
            "subcategory":"Beauty Salon",
            "type":"Services"
        }
    ],
    "sg:phone":"+1 228 769 8000",
    "sg:postcode":"39567",
    "sg:province":"MS",
    "wof:name":"En-Vogue",
    "wof:placetype":"venue"
},
  "geometry": {"coordinates":[-88.553327,30.370766],"type":"Point"}
}