{
  "type": "Feature",
  "properties": {
    "addr:full":"177 Mount Pisgah Rd NW Mantachie MS 38855",
    "addr:housenumber":"177",
    "addr:postcode":"38855",
    "addr:street":"Mount Pisgah Rd Nw Mantachie",
    "iso:country":"US",
    "sg:address":"177 Mount Pisgah Rd NW",
    "sg:city":"Mantachie",
    "sg:classifiers":[
        {
            "category":"Retail",
            "subcategory":"Repair Shop",
            "type":"Services"
        }
    ],
    "sg:phone":"+1 662 282 5154",
    "sg:postcode":"38855",
    "sg:province":"MS",
    "sg:tags":[
        "taxidermist"
    ],
    "wof:name":"Mantachie Taxidermy",
    "wof:placetype":"venue"
},
  "geometry": {"coordinates":[-88.482443,34.34094],"type":"Point"}
}