{
  "type": "Feature",
  "properties": {
    "addr:full":"12332 Cedar Lake Rd Biloxi MS 39532",
    "addr:housenumber":"12332",
    "addr:postcode":"39532",
    "addr:street":"Cedar Lake Rd",
    "iso:country":"US",
    "sg:address":"12332 Cedar Lake Rd",
    "sg:city":"Biloxi",
    "sg:classifiers":[
        {
            "category":"Organizations",
            "subcategory":"Religious Organization",
            "type":"Services"
        }
    ],
    "sg:phone":"+1 228 392 9585",
    "sg:postcode":"39532",
    "sg:province":"MS",
    "sg:tags":[
        "church"
    ],
    "wof:name":"Cedar Lake United Methodist",
    "wof:placetype":"venue"
},
  "geometry": {"coordinates":[-88.938863,30.460653],"type":"Point"}
}