{
  "type": "Feature",
  "properties": {
    "addr:full":"1024 Hwy 471 Brandon MS 39042",
    "addr:housenumber":"1024",
    "addr:postcode":"39042",
    "addr:street":"Hwy 471",
    "iso:country":"US",
    "sg:address":"1024 Hwy 471",
    "sg:city":"Brandon",
    "sg:classifiers":[
        {
            "category":"Restaurant",
            "type":"Food & Drink"
        }
    ],
    "sg:phone":"+1 601 824 1379",
    "sg:postcode":"39042",
    "sg:province":"MS",
    "wof:name":"Burger King",
    "wof:placetype":"venue"
},
  "geometry": {"coordinates":[-89.99460500000001,32.301085],"type":"Point"}
}