{
  "type": "Feature",
  "properties": {
    "iso:country":"US",
    "sg:address":"1109 Bienville Blvd",
    "sg:city":"Ocean Springs",
    "sg:classifiers":[
        {
            "category":"Retail",
            "subcategory":"Auto Repair",
            "type":"Services"
        }
    ],
    "sg:phone":"+1 228 818 4858",
    "sg:postcode":"39564",
    "sg:province":"MS",
    "sg:tags":[
        "repairing",
        "automobile"
    ],
    "wof:name":"T & D Auto Repair",
    "wof:placetype":"venue"
},
  "geometry": {"coordinates":[-88.81892000000001,30.416304],"type":"Point"}
}