{
  "type": "Feature",
  "properties": {
    "iso:country":"US",
    "sg:address":"172 Houston Acres",
    "sg:city":"Florence",
    "sg:classifiers":[
        {
            "category":"Professional",
            "subcategory":"Business Services",
            "type":"Services"
        }
    ],
    "sg:phone":"+1 601 845 7062",
    "sg:postcode":"39073",
    "sg:province":"MS",
    "sg:tags":[
        "inspection"
    ],
    "wof:name":"Hawthorne Plumbing & Heating",
    "wof:placetype":"venue"
},
  "geometry": {"coordinates":[-90.120727,32.179723],"type":"Point"}
}