{
  "type": "Feature",
  "properties": {
    "iso:country":"US",
    "sg:address":"10809 Hwy 432",
    "sg:city":"Pickens",
    "sg:classifiers":[
        {
            "category":"Food & Beverages",
            "subcategory":"Liquor & Beverages",
            "type":"Retail Goods"
        }
    ],
    "sg:phone":"+1 662 468 2507",
    "sg:postcode":"39146",
    "sg:province":"MS",
    "sg:tags":[
        "alcoholic"
    ],
    "wof:name":"Pickens Package Store",
    "wof:placetype":"venue"
},
  "geometry": {"coordinates":[-90.068471,32.875166],"type":"Point"}
}