{
  "type": "Feature",
  "properties": {
    "iso:country":"US",
    "sg:address":"4075 S Siwell Rd",
    "sg:city":"Jackson",
    "sg:classifiers":[
        {
            "category":"Organizations",
            "subcategory":"Religious Organization",
            "type":"Services"
        }
    ],
    "sg:phone":"+1 601 372 2551",
    "sg:postcode":"39212",
    "sg:province":"MS",
    "sg:tags":[
        "church"
    ],
    "sg:website":"www.siwellroad.org",
    "wof:name":"Siwell Road Church Of Christ",
    "wof:placetype":"venue"
},
  "geometry": {"coordinates":[-90.300915,32.239995],"type":"Point"}
}