{
  "type": "Feature",
  "properties": {
    "addr:full":"3346 Goodman Rd W Horn Lake MS 38637",
    "addr:housenumber":"3346",
    "addr:postcode":"38637",
    "addr:street":"Goodman Rd W Horn Lake",
    "iso:country":"US",
    "sg:address":"3346 Goodman Rd W",
    "sg:city":"Horn Lake",
    "sg:classifiers":[
        {
            "category":"Personal",
            "type":"Services"
        }
    ],
    "sg:phone":"+1 662 342 8267",
    "sg:postcode":"38637",
    "sg:province":"MS",
    "wof:name":"Sun Tans Inc",
    "wof:placetype":"venue"
},
  "geometry": {"coordinates":[-90.05190399999999,34.962713],"type":"Point"}
}