{
  "type": "Feature",
  "properties": {
    "iso:country":"US",
    "sg:address":"402 Franklin St",
    "sg:city":"Corinth",
    "sg:classifiers":[
        {
            "category":"Real Estate",
            "subcategory":"Developer",
            "type":"Services"
        }
    ],
    "sg:phone":"+1 662 286 2382",
    "sg:postcode":"38834",
    "sg:province":"MS",
    "wof:name":"LIDDON Hills",
    "wof:placetype":"venue"
},
  "geometry": {"coordinates":[-88.51946700000001,34.934783],"type":"Point"}
}