{
  "type": "Feature",
  "properties": {
    "addr:full":"17 Lafayette St Pontotoc MS 38863",
    "addr:housenumber":"17",
    "addr:postcode":"38863",
    "addr:street":"Lafayette St",
    "iso:country":"US",
    "sg:address":"17 Lafayette St",
    "sg:city":"Pontotoc",
    "sg:classifiers":[
        {
            "category":"Building & Trades",
            "subcategory":"Construction",
            "type":"Services"
        }
    ],
    "sg:phone":"+1 662 488 0005",
    "sg:postcode":"38863",
    "sg:province":"MS",
    "sg:tags":[
        "contractor"
    ],
    "wof:name":"North Mississippi Pools",
    "wof:placetype":"venue"
},
  "geometry": {"coordinates":[-89.00006399999999,34.248397],"type":"Point"}
}