{
  "type": "Feature",
  "properties": {
    "addr:full":"1043 School St Tunica MS 38676",
    "addr:housenumber":"1043",
    "addr:postcode":"38676",
    "addr:street":"School St",
    "iso:country":"US",
    "sg:address":"1043 School St",
    "sg:city":"Tunica",
    "sg:classifiers":[
        {
            "category":"Place Of Worship",
            "type":"Public Place"
        }
    ],
    "sg:phone":"+1 662 363 2137",
    "sg:postcode":"38676",
    "sg:province":"MS",
    "sg:tags":[
        "church"
    ],
    "wof:name":"Tunica United Methodist Church",
    "wof:placetype":"venue"
},
  "geometry": {"coordinates":[-90.38154299999999,34.685527],"type":"Point"}
}