{
  "type": "Feature",
  "properties": {
    "addr:full":"14521 Cemetery Rd Gulfport MS 39503",
    "addr:housenumber":"14521",
    "addr:postcode":"39503",
    "addr:street":"Cemetery Rd",
    "iso:country":"US",
    "sg:address":"14521 Cemetery Rd",
    "sg:city":"Gulfport",
    "sg:classifiers":[
        {
            "category":"Retail",
            "subcategory":"Auto Repair",
            "type":"Services"
        }
    ],
    "sg:phone":"+1 228 832 7140",
    "sg:postcode":"39503",
    "sg:province":"MS",
    "sg:tags":[
        "shop"
    ],
    "wof:name":"Mark Frleys Tire Sp Diesl Repr",
    "wof:placetype":"venue"
},
  "geometry": {"coordinates":[-89.261763,30.498157],"type":"Point"}
}