{
  "type": "Feature",
  "properties": {
    "iso:country":"US",
    "sg:address":"1544 V F W Rd",
    "sg:city":"Greenville",
    "sg:classifiers":[
        {
            "category":"Building & Trades",
            "subcategory":"Construction",
            "type":"Services"
        }
    ],
    "sg:phone":"+1 662 334 4317",
    "sg:postcode":"38701",
    "sg:province":"MS",
    "sg:tags":[
        "hanging",
        "painter",
        "contractor"
    ],
    "wof:name":"Everitt James Painting Contrs",
    "wof:placetype":"venue"
},
  "geometry": {"coordinates":[-91.029856,33.356361],"type":"Point"}
}