{
  "type": "Feature",
  "properties": {
    "addr:full":"147 River Terminal Rd Natchez MS 39120",
    "addr:housenumber":"147",
    "addr:postcode":"39120",
    "addr:street":"River Terminal Rd",
    "iso:country":"US",
    "sg:address":"147 River Terminal Rd",
    "sg:city":"Natchez",
    "sg:classifiers":[
        {
            "category":"Manufacturing",
            "subcategory":"Retail Goods",
            "type":"Manufacturing & Wholesale Goods"
        }
    ],
    "sg:phone":"+1 601 442 1630",
    "sg:postcode":"39120",
    "sg:province":"MS",
    "sg:tags":[
        "manufacturer"
    ],
    "wof:name":"Creative Marine Products",
    "wof:placetype":"venue"
},
  "geometry": {"coordinates":[-91.424156,31.524998],"type":"Point"}
}