{
  "type": "Feature",
  "properties": {
    "iso:country":"US",
    "sg:address":"4049 Torrey Pines Dr",
    "sg:city":"Jackson",
    "sg:classifiers":[
        {
            "category":"Building & Trades",
            "subcategory":"Electrical",
            "type":"Services"
        }
    ],
    "sg:phone":"+1 601 373 5061",
    "sg:postcode":"39272",
    "sg:province":"MS",
    "sg:tags":[
        "electrical",
        "contractor"
    ],
    "wof:name":"Steele Electric",
    "wof:placetype":"venue"
},
  "geometry": {"coordinates":[-90.25966099999999,32.209396],"type":"Point"}
}