{
  "type": "Feature",
  "properties": {
    "iso:country":"US",
    "sg:address":"246 Dauphine St",
    "sg:city":"Hattiesburg",
    "sg:classifiers":[
        {
            "category":"Professional",
            "subcategory":"Business Services",
            "type":"Services"
        }
    ],
    "sg:phone":"+1 601 582 3634",
    "sg:postcode":"39401",
    "sg:province":"MS",
    "sg:tags":[
        "specialty",
        "mfg"
    ],
    "wof:name":"Thomas Sign Company",
    "wof:placetype":"venue"
},
  "geometry": {"coordinates":[-89.298199,31.327814],"type":"Point"}
}