{
  "type": "Feature",
  "properties": {
    "addr:full":"3545 Lakeland Dr Flowood MS 39232",
    "addr:housenumber":"3545",
    "addr:postcode":"39232",
    "addr:street":"Lakeland Dr",
    "iso:country":"US",
    "sg:address":"3545 Lakeland Dr",
    "sg:city":"Flowood",
    "sg:classifiers":[
        {
            "category":"Health Services",
            "subcategory":"Hospital",
            "type":"Services"
        },
        {
            "category":"Insurance",
            "subcategory":"Hazard Insurance",
            "type":"Services"
        }
    ],
    "sg:phone":"+1 601 932 3704",
    "sg:postcode":"39232",
    "sg:province":"MS",
    "sg:tags":[
        "plan",
        "medical",
        "hospitalization",
        "surgical"
    ],
    "sg:website":"http://www.bcbsms.com",
    "wof:name":"Blue Cross & Blue Shield Of Mississippi",
    "wof:placetype":"venue"
},
  "geometry": {"coordinates":[-90.102576,32.333127],"type":"Point"}
}