{
  "type": "Feature",
  "properties": {
    "addr:full":"320 S 3rd St Wiggins MS 39577",
    "addr:housenumber":"320",
    "addr:postcode":"39577",
    "addr:street":"S 3Rd St",
    "iso:country":"US",
    "sg:address":"320 S 3rd St",
    "sg:city":"Wiggins",
    "sg:classifiers":[
        {
            "category":"Shopping",
            "subcategory":"Stationery & Office Supplies",
            "type":"Retail Goods"
        }
    ],
    "sg:phone":"+1 601 928 4912",
    "sg:postcode":"39577",
    "sg:province":"MS",
    "wof:name":"Southern Office Supply",
    "wof:placetype":"venue"
},
  "geometry": {"coordinates":[-89.13426800000001,30.856365],"type":"Point"}
}