{
  "type": "Feature",
  "properties": {
    "iso:country":"US",
    "sg:address":"320 S 3rd St",
    "sg:city":"Wiggins",
    "sg:classifiers":[
        {
            "category":"Shopping",
            "subcategory":"Stationery & Office Supplies",
            "type":"Retail Goods"
        }
    ],
    "sg:phone":"+1 601 928 4912",
    "sg:postcode":"39577",
    "sg:province":"MS",
    "wof:name":"Southern Office Supply",
    "wof:placetype":"venue"
},
  "geometry": {"coordinates":[-89.13426800000001,30.856365],"type":"Point"}
}