{
  "type": "Feature",
  "properties": {
    "addr:full":"25 Co Rd 104 Oxford MS 38655",
    "addr:housenumber":"25;104",
    "addr:postcode":"38655",
    "addr:street":"Co Rd",
    "iso:country":"US",
    "sg:address":"25 Co Rd 104",
    "sg:city":"Oxford",
    "sg:classifiers":[
        {
            "category":"Organizations",
            "subcategory":"Religious Organization",
            "type":"Services"
        }
    ],
    "sg:phone":"+1 662 234 8578",
    "sg:postcode":"38655",
    "sg:province":"MS",
    "sg:tags":[
        "church"
    ],
    "wof:name":"Faith Assembly-God In Christ",
    "wof:placetype":"venue"
},
  "geometry": {"coordinates":[-89.523809,34.415576],"type":"Point"}
}