{
  "type": "Feature",
  "properties": {
    "iso:country":"US",
    "sg:address":"307 S Jackson St",
    "sg:city":"Starkville",
    "sg:classifiers":[
        {
            "category":"Education",
            "subcategory":"School",
            "type":"Public Place"
        }
    ],
    "sg:phone":"+1 662 324 4090",
    "sg:postcode":"39759",
    "sg:province":"MS",
    "wof:name":"Over Street",
    "wof:placetype":"venue"
},
  "geometry": {"coordinates":[-88.81380299999999,33.460949],"type":"Point"}
}