{
  "type": "Feature",
  "properties": {
    "iso:country":"US",
    "sg:address":"115 Hall Rd",
    "sg:city":"Eupora",
    "sg:classifiers":[
        {
            "category":"Building & Trades",
            "subcategory":"Equipment Rental",
            "type":"Services"
        }
    ],
    "sg:phone":"+1 662 258 2252",
    "sg:postcode":"39744",
    "sg:province":"MS",
    "wof:name":"Gladney Rental",
    "wof:placetype":"venue"
},
  "geometry": {"coordinates":[-89.27838,33.54719],"type":"Point"}
}