{
  "type": "Feature",
  "properties": {
    "iso:country":"US",
    "sg:address":"4331 Jackson St",
    "sg:city":"Moss Point",
    "sg:classifiers":[
        {
            "category":"Recreation",
            "type":"Entertainment"
        }
    ],
    "sg:phone":"+1 228 475 9138",
    "sg:postcode":"39563",
    "sg:province":"MS",
    "sg:tags":[
        "skating",
        "rink"
    ],
    "wof:name":"Tigertown Skating Rink",
    "wof:placetype":"venue"
},
  "geometry": {"coordinates":[-88.537657,30.40128],"type":"Point"}
}