{
  "type": "Feature",
  "properties": {
    "iso:country":"US",
    "sg:address":"1886 Old Richton Rd",
    "sg:city":"Petal",
    "sg:classifiers":[
        {
            "category":"Personal",
            "subcategory":"Beauty Salon",
            "type":"Services"
        }
    ],
    "sg:phone":"+1 601 544 8727",
    "sg:postcode":"39465",
    "sg:province":"MS",
    "sg:tags":[
        "shop"
    ],
    "wof:name":"Hair Styles By Mary",
    "wof:placetype":"venue"
},
  "geometry": {"coordinates":[-89.233842,31.364931],"type":"Point"}
}