{
  "type": "Feature",
  "properties": {
    "addr:full":"1176 Hwy 15 N Laurel MS 39440",
    "addr:housenumber":"1176",
    "addr:postcode":"39440",
    "addr:street":"Hwy 15 N",
    "iso:country":"US",
    "sg:address":"1176 Hwy 15 N",
    "sg:city":"Laurel",
    "sg:classifiers":[
        {
            "category":"Food & Beverages",
            "subcategory":"Groceries & Convenience Stores",
            "type":"Retail Goods"
        }
    ],
    "sg:phone":"+1 601 428 5253",
    "sg:postcode":"39440",
    "sg:province":"MS",
    "wof:name":"Stringer Red Apple",
    "wof:placetype":"venue"
},
  "geometry": {"coordinates":[-89.14712,31.69934],"type":"Point"}
}