{
  "type": "Feature",
  "properties": {
    "addr:full":"355 N Ruby Ave Ruleville MS 38771",
    "addr:housenumber":"355",
    "addr:postcode":"38771",
    "addr:street":"N Ruby Ave",
    "iso:country":"US",
    "sg:address":"355 N Ruby Ave",
    "sg:city":"Ruleville",
    "sg:classifiers":[
        {
            "category":"Professional",
            "subcategory":"Management & Consulting",
            "type":"Services"
        }
    ],
    "sg:phone":"+1 662 756 4119",
    "sg:postcode":"38771",
    "sg:province":"MS",
    "sg:tags":[
        "business"
    ],
    "wof:name":"Chacon AG Services Inc",
    "wof:placetype":"venue"
},
  "geometry": {"coordinates":[-90.548778,33.731216],"type":"Point"}
}