{
  "type": "Feature",
  "properties": {
    "iso:country":"US",
    "sg:address":"222 Lynett Dr",
    "sg:city":"Byhalia",
    "sg:classifiers":[
        {
            "category":"Shopping",
            "subcategory":"Books",
            "type":"Retail Goods"
        }
    ],
    "sg:phone":"+1 662 838 2419",
    "sg:postcode":"38611",
    "sg:province":"MS",
    "sg:tags":[
        "dealer"
    ],
    "wof:name":"KJR Enterprises Inc",
    "wof:placetype":"venue"
},
  "geometry": {"coordinates":[-89.69523599999999,34.839473],"type":"Point"}
}