{
  "type": "Feature",
  "properties": {
    "iso:country":"US",
    "sg:address":"241 S Main St",
    "sg:city":"Yazoo City",
    "sg:classifiers":[
        {
            "category":"Home & Garden",
            "subcategory":"Furniture",
            "type":"Retail Goods"
        }
    ],
    "sg:phone":"+1 662 746 1802",
    "sg:postcode":"39194",
    "sg:province":"MS",
    "sg:tags":[
        "store"
    ],
    "wof:name":"Ferguson Furniture Company",
    "wof:placetype":"venue"
},
  "geometry": {"coordinates":[-90.41636800000001,32.843571],"type":"Point"}
}