{
  "type": "Feature",
  "properties": {
    "addr:full":"123 Tate Rd Greenville MS 38701",
    "addr:housenumber":"123",
    "addr:postcode":"38701",
    "addr:street":"Tate Rd",
    "iso:country":"US",
    "sg:address":"123 Tate Rd",
    "sg:city":"Greenville",
    "sg:classifiers":[
        {
            "category":"Building & Trades",
            "subcategory":"Construction",
            "type":"Services"
        }
    ],
    "sg:phone":"+1 662 332 0298",
    "sg:postcode":"38701",
    "sg:province":"MS",
    "sg:tags":[
        "painter"
    ],
    "wof:name":"Robert Armstrong Painting Svc",
    "wof:placetype":"venue"
},
  "geometry": {"coordinates":[-91.035847,33.309452],"type":"Point"}
}