{
  "type": "Feature",
  "properties": {
    "iso:country":"US",
    "sg:address":"1065 Lynn Ave",
    "sg:city":"Clarksdale",
    "sg:classifiers":[
        {
            "category":"Social Services",
            "subcategory":"Child Care",
            "type":"Services"
        }
    ],
    "sg:phone":"+1 662 624 6467",
    "sg:postcode":"38614",
    "sg:province":"MS",
    "wof:name":"Creative Children Ccc",
    "wof:placetype":"venue"
},
  "geometry": {"coordinates":[-90.601546,34.204356],"type":"Point"}
}