{
  "type": "Feature",
  "properties": {
    "iso:country":"US",
    "sg:address":"2103 Grenada Blvd",
    "sg:city":"Greenwood",
    "sg:classifiers":[
        {
            "category":"Organizations",
            "subcategory":"Religious Organization",
            "type":"Services"
        }
    ],
    "sg:phone":"+1 662 453 0011",
    "sg:postcode":"38930",
    "sg:province":"MS",
    "sg:tags":[
        "church"
    ],
    "wof:name":"Light Ministries",
    "wof:placetype":"venue"
},
  "geometry": {"coordinates":[-90.156188,33.52183],"type":"Point"}
}