{
  "type": "Feature",
  "properties": {
    "iso:country":"US",
    "sg:address":"340 Hwy 35 N",
    "sg:city":"Batesville",
    "sg:classifiers":[
        {
            "category":"Retail",
            "subcategory":"Funeral Services",
            "type":"Services"
        }
    ],
    "sg:phone":"+1 662 563 5700",
    "sg:postcode":"38606",
    "sg:province":"MS",
    "sg:tags":[
        "director"
    ],
    "wof:name":"Wells Funeral Home",
    "wof:placetype":"venue"
},
  "geometry": {"coordinates":[-89.926333,34.342972],"type":"Point"}
}