{
  "type": "Feature",
  "properties": {
    "iso:country":"US",
    "sg:address":"322 Clark Ave",
    "sg:city":"Pass Christian",
    "sg:classifiers":[
        {
            "category":"Organizations",
            "subcategory":"Religious Organization",
            "type":"Services"
        }
    ],
    "sg:phone":"+1 228 452 7105",
    "sg:postcode":"39571",
    "sg:province":"MS",
    "sg:tags":[
        "church"
    ],
    "wof:name":"St Paul United Methodist Chr",
    "wof:placetype":"venue"
},
  "geometry": {"coordinates":[-89.251829,30.323665],"type":"Point"}
}