{
  "type": "Feature",
  "properties": {
    "iso:country":"US",
    "sg:address":"201 Magazine St",
    "sg:city":"Tupelo",
    "sg:classifiers":[
        {
            "category":"Manufacturing",
            "subcategory":"Lumber",
            "type":"Manufacturing & Wholesale Goods"
        }
    ],
    "sg:phone":"+1 662 844 8006",
    "sg:postcode":"38804",
    "sg:province":"MS",
    "sg:tags":[
        "forestry",
        "firm",
        "consulting"
    ],
    "wof:name":"Southern Forest Resources",
    "wof:placetype":"venue"
},
  "geometry": {"coordinates":[-88.704427,34.255891],"type":"Point"}
}