{
  "type": "Feature",
  "properties": {
    "iso:country":"US",
    "sg:address":"4774 Alden Lake Dr E",
    "sg:city":"Horn Lake",
    "sg:classifiers":[
        {
            "category":"Building & Trades",
            "subcategory":"Construction",
            "type":"Services"
        }
    ],
    "sg:phone":"+1 662 280 0533",
    "sg:postcode":"38637",
    "sg:province":"MS",
    "sg:tags":[
        "paving",
        "contractor"
    ],
    "wof:name":"Smith's Paving & Sealing",
    "wof:placetype":"venue"
},
  "geometry": {"coordinates":[-90.01832400000001,34.929659],"type":"Point"}
}