{
  "type": "Feature",
  "properties": {
    "iso:country":"US",
    "sg:address":"4477 E Northside Dr",
    "sg:city":"Jackson",
    "sg:classifiers":[
        {
            "category":"Freight",
            "type":"Transportation"
        }
    ],
    "sg:phone":"+1 601 922 3304",
    "sg:postcode":"39209",
    "sg:province":"MS",
    "sg:tags":[
        "general"
    ],
    "wof:name":"Northwest Mini Storage Inc",
    "wof:placetype":"venue"
},
  "geometry": {"coordinates":[-90.247973,32.35612],"type":"Point"}
}