{
  "type": "Feature",
  "properties": {
    "addr:full":"12056 Mobile Ave Gulfport MS 39503",
    "addr:housenumber":"12056",
    "addr:postcode":"39503",
    "addr:street":"Mobile Ave",
    "iso:country":"US",
    "sg:address":"12056 Mobile Ave",
    "sg:city":"Gulfport",
    "sg:classifiers":[
        {
            "category":"Health Services",
            "subcategory":"Podiatrist",
            "type":"Services"
        }
    ],
    "sg:phone":"+1 228 832 2023",
    "sg:postcode":"39503",
    "sg:province":"MS",
    "wof:name":"Gulfport Foot Surgical Ctr",
    "wof:placetype":"venue"
},
  "geometry": {"coordinates":[-89.099389,30.460231],"type":"Point"}
}