{
  "type": "Feature",
  "properties": {
    "iso:country":"US",
    "sg:address":"223 Martin Luther King Jr Dr W",
    "sg:city":"Starkville",
    "sg:classifiers":[
        {
            "category":"Organizations",
            "subcategory":"Religious Organization",
            "type":"Services"
        }
    ],
    "sg:phone":"+1 662 323 5119",
    "sg:postcode":"39759",
    "sg:province":"MS",
    "wof:name":"Peters Rck Chrch of God In",
    "wof:placetype":"venue"
},
  "geometry": {"coordinates":[-88.819518,33.466007],"type":"Point"}
}