{
  "type": "Feature",
  "properties": {
    "addr:full":"108 Mc Leod St Hattiesburg MS 39401",
    "addr:housenumber":"108",
    "addr:postcode":"39401",
    "addr:street":"Mc Leod St",
    "iso:country":"US",
    "sg:address":"108 Mc Leod St",
    "sg:city":"Hattiesburg",
    "sg:classifiers":[
        {
            "category":"Personal",
            "subcategory":"Beauty Salon",
            "type":"Services"
        }
    ],
    "sg:phone":"+1 601 544 3557",
    "sg:postcode":"39401",
    "sg:province":"MS",
    "sg:tags":[
        "shop"
    ],
    "wof:name":"Styles Elegant",
    "wof:placetype":"venue"
},
  "geometry": {"coordinates":[-89.294152,31.327216],"type":"Point"}
}