{
  "type": "Feature",
  "properties": {
    "addr:full":"118 N Commerce St Natchez MS 39120",
    "addr:housenumber":"118",
    "addr:postcode":"39120",
    "addr:street":"N Commerce St",
    "iso:country":"US",
    "sg:address":"118 N Commerce St",
    "sg:city":"Natchez",
    "sg:classifiers":[
        {
            "category":"Real Estate",
            "subcategory":"Real Estate Agent",
            "type":"Services"
        }
    ],
    "sg:phone":"+1 601 442 9888",
    "sg:postcode":"39120",
    "sg:province":"MS",
    "wof:name":"Good Hope Timber",
    "wof:placetype":"venue"
},
  "geometry": {"coordinates":[-91.401715,31.560453],"type":"Point"}
}