{
  "type": "Feature",
  "properties": {
    "addr:full":"114 Mason St Laurel MS 39440",
    "addr:housenumber":"114",
    "addr:postcode":"39440",
    "addr:street":"Mason St",
    "iso:country":"US",
    "sg:address":"114 Mason St",
    "sg:city":"Laurel",
    "sg:classifiers":[
        {
            "category":"Shopping",
            "subcategory":"Used Merchandise",
            "type":"Retail Goods"
        }
    ],
    "sg:phone":"+1 601 649 7296",
    "sg:postcode":"39440",
    "sg:province":"MS",
    "sg:tags":[
        "pawnbroker"
    ],
    "wof:name":"Top Dollar Pawn Shop",
    "wof:placetype":"venue"
},
  "geometry": {"coordinates":[-89.136611,31.68932],"type":"Point"}
}