{
  "type": "Feature",
  "properties": {
    "addr:full":"369 Strider Rd Tillatoba MS 38901",
    "addr:housenumber":"369",
    "addr:postcode":"38901",
    "addr:street":"Strider Rd",
    "iso:country":"US",
    "sg:address":"369 Strider Rd",
    "sg:city":"Tillatoba",
    "sg:classifiers":[
        {
            "category":"Building & Trades",
            "subcategory":"Construction",
            "type":"Services"
        }
    ],
    "sg:phone":"+1 662 227 1815",
    "sg:postcode":"38901",
    "sg:province":"MS",
    "sg:tags":[
        "contractor"
    ],
    "wof:name":"Choice Builders Inc",
    "wof:placetype":"venue"
},
  "geometry": {"coordinates":[-89.90912,33.886208],"type":"Point"}
}