{
  "type": "Feature",
  "properties": {
    "iso:country":"US",
    "sg:address":"800 Pecan Cir",
    "sg:city":"Lucedale",
    "sg:classifiers":[
        {
            "category":"Government",
            "subcategory":"Office",
            "type":"Public Place"
        }
    ],
    "sg:phone":"+1 601 947 7414",
    "sg:postcode":"39452",
    "sg:province":"MS",
    "sg:tags":[
        "housing",
        "program"
    ],
    "wof:name":"Peacan Circle Homes",
    "wof:placetype":"venue"
},
  "geometry": {"coordinates":[-88.595744,30.913392],"type":"Point"}
}