{
  "type": "Feature",
  "properties": {
    "addr:full":"35 Goodman Rd W Southaven MS 38671",
    "addr:housenumber":"35",
    "addr:postcode":"38671",
    "addr:street":"Goodman Rd W",
    "iso:country":"US",
    "sg:address":"35 Goodman Rd W",
    "sg:city":"Southaven",
    "sg:classifiers":[
        {
            "category":"Home & Garden",
            "subcategory":"Furniture",
            "type":"Retail Goods"
        }
    ],
    "sg:phone":"+1 662 349 4933",
    "sg:postcode":"38671",
    "sg:province":"MS",
    "sg:tags":[
        "equipment",
        "mattress"
    ],
    "wof:name":"Mattress Firm",
    "wof:placetype":"venue"
},
  "geometry": {"coordinates":[-89.990416,34.962614],"type":"Point"}
}