{
  "type": "Feature",
  "properties": {
    "iso:country":"US",
    "sg:address":"20578 Egypt Rd",
    "sg:city":"Aberdeen",
    "sg:classifiers":[
        {
            "category":"Manufacturing",
            "subcategory":"Glass & Minerals",
            "type":"Manufacturing & Wholesale Goods"
        }
    ],
    "sg:phone":"+1 662 369 8935",
    "sg:postcode":"39730",
    "sg:province":"MS",
    "sg:tags":[
        "plumbing",
        "concrete",
        "product",
        "mfg"
    ],
    "wof:name":"Lees Wholesale",
    "wof:placetype":"venue"
},
  "geometry": {"coordinates":[-88.625866,33.873152],"type":"Point"}
}