{
  "type": "Feature",
  "properties": {
    "iso:country":"US",
    "sg:address":"1134 Howell Rd",
    "sg:city":"Purvis",
    "sg:classifiers":[
        {
            "category":"Autos & Motor Vehicles",
            "subcategory":"Automobile Sales",
            "type":"Retail Goods"
        }
    ],
    "sg:phone":"+1 601 264 1624",
    "sg:postcode":"39475",
    "sg:province":"MS",
    "sg:tags":[
        "used"
    ],
    "wof:name":"Auto Smart Inc",
    "wof:placetype":"venue"
},
  "geometry": {"coordinates":[-89.422042,31.262578],"type":"Point"}
}