{
  "type": "Feature",
  "properties": {
    "iso:country":"US",
    "sg:address":"1600 E Hardy St",
    "sg:city":"Hattiesburg",
    "sg:classifiers":[
        {
            "category":"Autos & Motor Vehicles",
            "subcategory":"Automobile Sales",
            "type":"Retail Goods"
        }
    ],
    "sg:phone":"+1 601 582 9462",
    "sg:postcode":"39401",
    "sg:province":"MS",
    "sg:tags":[
        "car",
        "dealer"
    ],
    "wof:name":"Cadillac Corner",
    "wof:placetype":"venue"
},
  "geometry": {"coordinates":[-89.27380599999999,31.325079],"type":"Point"}
}