{
  "type": "Feature",
  "properties": {
    "iso:country":"US",
    "sg:address":"1320 Henleyfield McNeill Rd",
    "sg:city":"Carriere",
    "sg:classifiers":[
        {
            "category":"Shopping",
            "subcategory":"Gifts & Souvenirs",
            "type":"Retail Goods"
        }
    ],
    "sg:phone":"+1 601 798 5029",
    "sg:postcode":"39426",
    "sg:province":"MS",
    "sg:tags":[
        "balloon"
    ],
    "wof:name":"Formal Wear Unlimited",
    "wof:placetype":"venue"
},
  "geometry": {"coordinates":[-89.66184199999999,30.663781],"type":"Point"}
}