{
  "type": "Feature",
  "properties": {
    "iso:country":"US",
    "sg:address":"304 Robb St",
    "sg:city":"Summit",
    "sg:classifiers":[
        {
            "category":"Banks & Credit Unions",
            "subcategory":"Bank",
            "type":"Services"
        }
    ],
    "sg:phone":"+1 601 684 2231",
    "sg:postcode":"39666",
    "sg:province":"MS",
    "wof:name":"First Bank",
    "wof:placetype":"venue"
},
  "geometry": {"coordinates":[-90.47338000000001,31.284012],"type":"Point"}
}