{
  "type": "Feature",
  "properties": {
    "iso:country":"US",
    "sg:address":"3312 Martin Luther King Jr Blvd",
    "sg:city":"Gulfport",
    "sg:classifiers":[
        {
            "category":"Education",
            "subcategory":"Library",
            "type":"Public Place"
        }
    ],
    "sg:phone":"+1 228 868 7149",
    "sg:postcode":"39501",
    "sg:province":"MS",
    "wof:name":"Isiah Fredericks Study Ctr",
    "wof:placetype":"venue"
},
  "geometry": {"coordinates":[-89.101508,30.403943],"type":"Point"}
}