{
  "type": "Feature",
  "properties": {
    "iso:country":"US",
    "sg:address":"139 Hwy 51 N",
    "sg:city":"Batesville",
    "sg:classifiers":[
        {
            "category":"Home & Garden",
            "subcategory":"Hardware",
            "type":"Retail Goods"
        }
    ],
    "sg:phone":"+1 662 563 4672",
    "sg:postcode":"38606",
    "sg:province":"MS",
    "wof:name":"Lott Ace Hardware",
    "wof:placetype":"venue"
},
  "geometry": {"coordinates":[-89.943804,34.314232],"type":"Point"}
}