{
  "type": "Feature",
  "properties": {
    "addr:full":"212 W Main St Tupelo MS 38804",
    "addr:housenumber":"212",
    "addr:postcode":"38804",
    "addr:street":"W Main St",
    "iso:country":"US",
    "sg:address":"212 W Main St",
    "sg:city":"Tupelo",
    "sg:classifiers":[
        {
            "category":"Shopping",
            "subcategory":"Clothing, Apparel, & Fashions",
            "type":"Retail Goods"
        }
    ],
    "sg:phone":"+1 662 840 3508",
    "sg:postcode":"38804",
    "sg:province":"MS",
    "sg:tags":[
        "maternity"
    ],
    "wof:name":"Sassy Mama",
    "wof:placetype":"venue"
},
  "geometry": {"coordinates":[-88.705279,34.257487],"type":"Point"}
}