{
  "type": "Feature",
  "properties": {
    "addr:full":"62921 Hwy 25 N Amory MS 38821",
    "addr:housenumber":"62921",
    "addr:postcode":"38821",
    "addr:street":"Hwy 25 N",
    "iso:country":"US",
    "sg:address":"62921 Hwy 25 N",
    "sg:city":"Amory",
    "sg:classifiers":[
        {
            "category":"Farming",
            "subcategory":"Farm",
            "type":"Manufacturing & Wholesale Goods"
        }
    ],
    "sg:phone":"+1 662 256 3245",
    "sg:postcode":"38821",
    "sg:province":"MS",
    "sg:tags":[
        "crop",
        "general"
    ],
    "wof:name":"Cadden Farms Inc",
    "wof:placetype":"venue"
},
  "geometry": {"coordinates":[-88.462487,34.020397],"type":"Point"}
}