{
  "type": "Feature",
  "properties": {
    "iso:country":"US",
    "sg:address":"41 Cemetery Rd",
    "sg:city":"Natchez",
    "sg:classifiers":[
        {
            "category":"Real Estate",
            "subcategory":"Developer",
            "type":"Services"
        }
    ],
    "sg:phone":"+1 601 445 4981",
    "sg:postcode":"39120",
    "sg:province":"MS",
    "sg:tags":[
        "national",
        "cemetery",
        "government"
    ],
    "wof:name":"Natchez National Cemetery",
    "wof:placetype":"venue"
},
  "geometry": {"coordinates":[-91.396039,31.57962],"type":"Point"}
}