{
  "type": "Feature",
  "properties": {
    "iso:country":"US",
    "sg:address":"246 Saddlewood Dr",
    "sg:city":"Clinton",
    "sg:classifiers":[
        {
            "category":"Education",
            "subcategory":"School",
            "type":"Public Place"
        }
    ],
    "sg:phone":"+1 601 924 7017",
    "sg:postcode":"39056",
    "sg:province":"MS",
    "wof:name":"Middle Man Mediation & Arbitra",
    "wof:placetype":"venue"
},
  "geometry": {"coordinates":[-90.289968,32.354805],"type":"Point"}
}