{
  "type": "Feature",
  "properties": {
    "addr:full":"832 Hwy 19 N Meridian MS 39307",
    "addr:housenumber":"832",
    "addr:postcode":"39307",
    "addr:street":"Hwy 19 N",
    "iso:country":"US",
    "sg:address":"832 Hwy 19 N",
    "sg:city":"Meridian",
    "sg:classifiers":[
        {
            "category":"Shopping",
            "subcategory":"Pharmacy",
            "type":"Retail Goods"
        }
    ],
    "sg:phone":"+1 601 482 7194",
    "sg:postcode":"39307",
    "sg:province":"MS",
    "wof:name":"Eckerd",
    "wof:placetype":"venue"
},
  "geometry": {"coordinates":[-88.730666,32.365353],"type":"Point"}
}