{
  "type": "Feature",
  "properties": {
    "addr:full":"141 Peyton Cir Oxford MS 38655",
    "addr:housenumber":"141",
    "addr:postcode":"38655",
    "addr:street":"Peyton Cir",
    "iso:country":"US",
    "sg:address":"141 Peyton Cir",
    "sg:city":"Oxford",
    "sg:classifiers":[
        {
            "category":"Building & Trades",
            "subcategory":"Construction",
            "type":"Services"
        }
    ],
    "sg:phone":"+1 662 238 2625",
    "sg:postcode":"38655",
    "sg:province":"MS",
    "wof:name":"Nutek Inc",
    "wof:placetype":"venue"
},
  "geometry": {"coordinates":[-89.524359,34.313475],"type":"Point"}
}