{
  "type": "Feature",
  "properties": {
    "addr:full":"880 Stateline Rd E Southaven MS 38671",
    "addr:housenumber":"880",
    "addr:postcode":"38671",
    "addr:street":"Stateline Rd E",
    "iso:country":"US",
    "sg:address":"880 Stateline Rd E",
    "sg:city":"Southaven",
    "sg:classifiers":[
        {
            "category":"Restaurant",
            "type":"Food & Drink"
        }
    ],
    "sg:phone":"+1 662 393 9448",
    "sg:postcode":"38671",
    "sg:province":"MS",
    "sg:tags":[
        "eating"
    ],
    "wof:name":"Wendys",
    "wof:placetype":"venue"
},
  "geometry": {"coordinates":[-89.97537,34.991864],"type":"Point"}
}