{
  "type": "Feature",
  "properties": {
    "addr:full":"211 Church St Belzoni MS 39038",
    "addr:housenumber":"211",
    "addr:postcode":"39038",
    "addr:street":"Church St",
    "iso:country":"US",
    "sg:address":"211 Church St",
    "sg:city":"Belzoni",
    "sg:classifiers":[
        {
            "category":"Insurance",
            "subcategory":"Insurance Agent",
            "type":"Services"
        }
    ],
    "sg:phone":"+1 662 247 3218",
    "sg:postcode":"39038",
    "sg:province":"MS",
    "wof:name":"Belzoni Insurance",
    "wof:placetype":"venue"
},
  "geometry": {"coordinates":[-90.48780499999999,33.178842],"type":"Point"}
}