{
  "type": "Feature",
  "properties": {
    "iso:country":"US",
    "sg:address":"623 W Main St",
    "sg:city":"Tupelo",
    "sg:classifiers":[
        {
            "category":"Shopping",
            "subcategory":"Used Merchandise",
            "type":"Retail Goods"
        }
    ],
    "sg:phone":"+1 662 844 8811",
    "sg:postcode":"38804",
    "sg:province":"MS",
    "wof:name":"Serendipity Eclectic",
    "wof:placetype":"venue"
},
  "geometry": {"coordinates":[-88.71125000000001,34.257331],"type":"Point"}
}