{
  "type": "Feature",
  "properties": {
    "iso:country":"US",
    "sg:address":"113 Main St",
    "sg:city":"Collins",
    "sg:classifiers":[
        {
            "category":"Professional",
            "subcategory":"Accounting & Tax Preparation",
            "type":"Services"
        }
    ],
    "sg:phone":"+1 601 765 4692",
    "sg:postcode":"39428",
    "sg:province":"MS",
    "sg:tags":[
        "return",
        "filing"
    ],
    "wof:name":"H & R Block Tax Svc",
    "wof:placetype":"venue"
},
  "geometry": {"coordinates":[-89.57263,31.657793],"type":"Point"}
}