{
  "type": "Feature",
  "properties": {
    "addr:full":"18779 Robins Cove Saucier MS 39574",
    "addr:housenumber":"18779",
    "addr:postcode":"39574",
    "addr:street":"Robins Cove",
    "iso:country":"US",
    "sg:address":"18779 Robins Cove",
    "sg:city":"Saucier",
    "sg:classifiers":[
        {
            "category":"Shopping",
            "subcategory":"Beauty & Cosmetics",
            "type":"Retail Goods"
        }
    ],
    "sg:phone":"+1 228 831 5639",
    "sg:postcode":"39574",
    "sg:province":"MS",
    "sg:tags":[
        "merchandise"
    ],
    "wof:name":"Beauticontrol Cosmetics",
    "wof:placetype":"venue"
},
  "geometry": {"coordinates":[-89.14617800000001,30.555543],"type":"Point"}
}