{
  "type": "Feature",
  "properties": {
    "addr:full":"436 US Hwy 61 Bus Natchez MS 39120",
    "addr:housenumber":"436",
    "addr:postcode":"39120",
    "addr:street":"Us Hwy 61 Bus Natchez",
    "iso:country":"US",
    "sg:address":"436 US Hwy 61 Bus",
    "sg:city":"Natchez",
    "sg:classifiers":[
        {
            "category":"Shopping",
            "subcategory":"Pharmacy",
            "type":"Retail Goods"
        }
    ],
    "sg:phone":"+1 601 446 7167",
    "sg:postcode":"39120",
    "sg:province":"MS",
    "wof:name":"Eckerd",
    "wof:placetype":"venue"
},
  "geometry": {"coordinates":[-91.402157,31.554549],"type":"Point"}
}