{
  "type": "Feature",
  "properties": {
    "iso:country":"US",
    "sg:address":"244 Henry Dr",
    "sg:city":"Greenville",
    "sg:classifiers":[
        {
            "category":"Freight",
            "type":"Transportation"
        }
    ],
    "sg:phone":"+1 662 335 4409",
    "sg:postcode":"38703",
    "sg:province":"MS",
    "sg:tags":[
        "operator",
        "local",
        "trucking"
    ],
    "wof:name":"Jl Trucking",
    "wof:placetype":"venue"
},
  "geometry": {"coordinates":[-91.01450800000001,33.405379],"type":"Point"}
}