{
  "type": "Feature",
  "properties": {
    "iso:country":"US",
    "sg:address":"407 Briarwood Dr",
    "sg:city":"Jackson",
    "sg:classifiers":[
        {
            "category":"Insurance",
            "subcategory":"Hazard Insurance",
            "type":"Services"
        },
        {
            "category":"Insurance",
            "subcategory":"Life Insurance",
            "type":"Services"
        }
    ],
    "sg:phone":"+1 601 977 9003",
    "sg:postcode":"39206",
    "sg:province":"MS",
    "sg:website":"http://www.newyorklife.com",
    "wof:name":"New York Life Insurance Company",
    "wof:placetype":"venue"
},
  "geometry": {"coordinates":[-90.151152,32.38029],"type":"Point"}
}