{
  "type": "Feature",
  "properties": {
    "iso:country":"US",
    "sg:address":"1105 B St",
    "sg:city":"Meridian",
    "sg:classifiers":[
        {
            "category":"Wholesale",
            "subcategory":"Electrical",
            "type":"Manufacturing & Wholesale Goods"
        }
    ],
    "sg:phone":"+1 601 482 2617",
    "sg:postcode":"39301",
    "sg:province":"MS",
    "wof:name":"Solar Supply",
    "wof:placetype":"venue"
},
  "geometry": {"coordinates":[-88.688321,32.365612],"type":"Point"}
}