{
  "type": "Feature",
  "properties": {
    "iso:country":"US",
    "sg:address":"759 Glencross Dr",
    "sg:city":"Jackson",
    "sg:classifiers":[
        {
            "category":"Health Services",
            "subcategory":"Doctor",
            "type":"Services"
        }
    ],
    "sg:phone":"+1 601 957 0655",
    "sg:postcode":"39206",
    "sg:province":"MS",
    "sg:tags":[
        "clinic"
    ],
    "wof:name":"Neighborhood Medical Clinic",
    "wof:placetype":"venue"
},
  "geometry": {"coordinates":[-90.162638,32.392437],"type":"Point"}
}