{
  "type": "Feature",
  "properties": {
    "iso:country":"US",
    "sg:address":"2532 Greenview Dr",
    "sg:city":"Gulfport",
    "sg:classifiers":[
        {
            "category":"Real Estate",
            "subcategory":"Real Estate Agent",
            "type":"Services"
        }
    ],
    "sg:phone":"+1 228 896 8888",
    "sg:postcode":"39507",
    "sg:province":"MS",
    "wof:name":"Bob Usey Properties",
    "wof:placetype":"venue"
},
  "geometry": {"coordinates":[-89.00981299999999,30.395626],"type":"Point"}
}