{
  "type": "Feature",
  "properties": {
    "addr:full":"1305 Sheriff Ridge Ave Friars Point MS 38631",
    "addr:housenumber":"1305",
    "addr:postcode":"38631",
    "addr:street":"Sheriff Ridge Ave",
    "iso:country":"US",
    "sg:address":"1305 Sheriff Ridge Ave",
    "sg:city":"Friars Point",
    "sg:classifiers":[
        {
            "category":"Restaurant",
            "type":"Food & Drink"
        }
    ],
    "sg:phone":"+1 662 383 0045",
    "sg:postcode":"38631",
    "sg:province":"MS",
    "wof:name":"Brotherhood Grocery & Rstrnt",
    "wof:placetype":"venue"
},
  "geometry": {"coordinates":[-90.638143,34.362648],"type":"Point"}
}