{
  "type": "Feature",
  "properties": {
    "iso:country":"US",
    "sg:address":"1870 Ott Rd",
    "sg:city":"Caledonia",
    "sg:phone":"+1 662 356 6864",
    "sg:postcode":"39701",
    "sg:province":"MS",
    "sg:tags":[
        "farm",
        "cotton"
    ],
    "wof:name":"Brock Farms",
    "wof:placetype":"venue"
},
  "geometry": {"coordinates":[-88.29307,33.706636],"type":"Point"}
}