{
  "type": "Feature",
  "properties": {
    "addr:full":"8195 Woolmarket Rd Biloxi MS 39532",
    "addr:housenumber":"8195",
    "addr:postcode":"39532",
    "addr:street":"Woolmarket Rd",
    "iso:country":"US",
    "sg:address":"8195 Woolmarket Rd",
    "sg:city":"Biloxi",
    "sg:classifiers":[
        {
            "category":"Retail",
            "subcategory":"Veterinary Services",
            "type":"Services"
        }
    ],
    "sg:phone":"+1 228 392 0327",
    "sg:postcode":"39532",
    "sg:province":"MS",
    "wof:name":"Pet Clinic",
    "wof:placetype":"venue"
},
  "geometry": {"coordinates":[-88.973094,30.469741],"type":"Point"}
}