{
  "type": "Feature",
  "properties": {
    "addr:full":"1091 Hwy 1 S Greenville MS 38701",
    "addr:housenumber":"1091",
    "addr:postcode":"38701",
    "addr:street":"Hwy 1 S",
    "iso:country":"US",
    "sg:address":"1091 Hwy 1 S",
    "sg:city":"Greenville",
    "sg:classifiers":[
        {
            "category":"Social Services",
            "subcategory":"Child Care",
            "type":"Services"
        }
    ],
    "sg:phone":"+1 662 334 3617",
    "sg:postcode":"38701",
    "sg:province":"MS",
    "wof:name":"Gift Of Love",
    "wof:placetype":"venue"
},
  "geometry": {"coordinates":[-91.038572,33.390319],"type":"Point"}
}