{
  "type": "Feature",
  "properties": {
    "addr:full":"3801 Kelly Moss Point MS 39563",
    "addr:housenumber":"3801",
    "addr:postcode":"39563",
    "addr:street":"Kelly Moss",
    "iso:country":"US",
    "sg:address":"3801 Kelly",
    "sg:city":"Moss Point",
    "sg:classifiers":[
        {
            "category":"Restaurant",
            "type":"Food & Drink"
        }
    ],
    "sg:phone":"+1 228 475 4952",
    "sg:postcode":"39563",
    "sg:province":"MS",
    "sg:tags":[
        "eating"
    ],
    "wof:name":"Charlie Browns B-B-Q",
    "wof:placetype":"venue"
},
  "geometry": {"coordinates":[-88.505785,30.396417],"type":"Point"}
}