{
  "type": "Feature",
  "properties": {
    "iso:country":"US",
    "sg:address":"1910 Denny Ave",
    "sg:city":"Pascagoula",
    "sg:classifiers":[
        {
            "category":"Professional",
            "subcategory":"Lawyer & Legal Services",
            "type":"Services"
        }
    ],
    "sg:phone":"+1 228 769 2009",
    "sg:postcode":"39567",
    "sg:province":"MS",
    "sg:tags":[
        "attorney"
    ],
    "wof:name":"Richard C Conant",
    "wof:placetype":"venue"
},
  "geometry": {"coordinates":[-88.54241,30.370724],"type":"Point"}
}