{
  "type": "Feature",
  "properties": {
    "iso:country":"US",
    "sg:address":"654 Hwy 4 E",
    "sg:city":"Booneville",
    "sg:classifiers":[
        {
            "category":"Education",
            "subcategory":"Dance Studio",
            "type":"Public Place"
        }
    ],
    "sg:phone":"+1 662 728 8005",
    "sg:postcode":"38829",
    "sg:province":"MS",
    "sg:tags":[
        "instruction",
        "dancing"
    ],
    "wof:name":"Ray's Place",
    "wof:placetype":"venue"
},
  "geometry": {"coordinates":[-88.47097599999999,34.565698],"type":"Point"}
}