{
  "type": "Feature",
  "properties": {
    "iso:country":"US",
    "sg:address":"151 Smithfield Rd",
    "sg:city":"Lucedale",
    "sg:classifiers":[
        {
            "category":"Building & Trades",
            "subcategory":"Plumbing",
            "type":"Services"
        }
    ],
    "sg:phone":"+1 601 947 6540",
    "sg:postcode":"39452",
    "sg:province":"MS",
    "sg:tags":[
        "septic"
    ],
    "wof:name":"B & L Vacuum Svc",
    "wof:placetype":"venue"
},
  "geometry": {"coordinates":[-88.56176000000001,30.856216],"type":"Point"}
}