{
  "type": "Feature",
  "properties": {
    "iso:country":"US",
    "sg:address":"432 Hwy 49 S",
    "sg:city":"Jackson",
    "sg:classifiers":[
        {
            "category":"Retail",
            "subcategory":"Auto Repair",
            "type":"Services"
        }
    ],
    "sg:phone":"+1 601 932 4030",
    "sg:postcode":"39218",
    "sg:province":"MS",
    "sg:tags":[
        "repairing",
        "automobile",
        "general"
    ],
    "wof:name":"Integrity Automotive",
    "wof:placetype":"venue"
},
  "geometry": {"coordinates":[-90.137018,32.184224],"type":"Point"}
}