{
  "type": "Feature",
  "properties": {
    "iso:country":"US",
    "sg:address":"32 Lawson Oneal Rd",
    "sg:city":"Perkinston",
    "sg:classifiers":[
        {
            "category":"Manufacturing",
            "subcategory":"Lumber",
            "type":"Manufacturing & Wholesale Goods"
        }
    ],
    "sg:phone":"+1 601 928 2321",
    "sg:postcode":"39573",
    "sg:province":"MS",
    "sg:tags":[
        "logging"
    ],
    "wof:name":"Scott Strickland Sons Inc",
    "wof:placetype":"venue"
},
  "geometry": {"coordinates":[-89.096666,30.726525],"type":"Point"}
}