{
  "type": "Feature",
  "properties": {
    "addr:full":"1735 Douglas Dr Jackson MS 39211",
    "addr:housenumber":"1735",
    "addr:postcode":"39211",
    "addr:street":"Douglas Dr",
    "iso:country":"US",
    "sg:address":"1735 Douglas Dr",
    "sg:city":"Jackson",
    "sg:classifiers":[
        {
            "category":"Professional",
            "subcategory":"Business Services",
            "type":"Services"
        }
    ],
    "sg:phone":"+1 601 982 3628",
    "sg:postcode":"39211",
    "sg:province":"MS",
    "wof:name":"Wallace Interior Designs",
    "wof:placetype":"venue"
},
  "geometry": {"coordinates":[-90.145521,32.346161],"type":"Point"}
}