{
  "type": "Feature",
  "properties": {
    "iso:country":"US",
    "sg:address":"6336 State Hwy 567",
    "sg:city":"Liberty",
    "sg:classifiers":[
        {
            "category":"Building & Trades",
            "subcategory":"Electrical",
            "type":"Services"
        }
    ],
    "sg:phone":"+1 601 657 4474",
    "sg:postcode":"39645",
    "sg:province":"MS",
    "sg:tags":[
        "specializing",
        "general",
        "electrical",
        "contractor"
    ],
    "wof:name":"Stokes Electric",
    "wof:placetype":"venue"
},
  "geometry": {"coordinates":[-90.82675500000001,31.305559],"type":"Point"}
}