{
  "type": "Feature",
  "properties": {
    "addr:full":"2033 Oak Grove Rd Hattiesburg MS 39402",
    "addr:housenumber":"2033",
    "addr:postcode":"39402",
    "addr:street":"Oak Grove Rd",
    "iso:country":"US",
    "sg:address":"2033 Oak Grove Rd",
    "sg:city":"Hattiesburg",
    "sg:classifiers":[
        {
            "category":"Freight",
            "type":"Transportation"
        }
    ],
    "sg:phone":"+1 601 261 9198",
    "sg:postcode":"39402",
    "sg:province":"MS",
    "sg:tags":[
        "commercial",
        "storage"
    ],
    "wof:name":"Outback Storage Co",
    "wof:placetype":"venue"
},
  "geometry": {"coordinates":[-89.35711999999999,31.320841],"type":"Point"}
}