{
  "type": "Feature",
  "properties": {
    "iso:country":"US",
    "sg:address":"109 Glendale St",
    "sg:city":"Booneville",
    "sg:classifiers":[
        {
            "category":"Social Services",
            "subcategory":"Child Care",
            "type":"Services"
        }
    ],
    "sg:phone":"+1 662 728 6818",
    "sg:postcode":"38829",
    "sg:province":"MS",
    "sg:tags":[
        "day"
    ],
    "wof:name":"Sherry Nanney Day Care",
    "wof:placetype":"venue"
},
  "geometry": {"coordinates":[-88.55643499999999,34.650445],"type":"Point"}
}