{
  "type": "Feature",
  "properties": {
    "addr:full":"4455 Co Rd 200 Corinth MS 38834",
    "addr:housenumber":"4455;200",
    "addr:postcode":"38834",
    "addr:street":"Co Rd",
    "iso:country":"US",
    "sg:address":"4455 Co Rd 200",
    "sg:city":"Corinth",
    "sg:classifiers":[
        {
            "category":"Food & Beverages",
            "subcategory":"Groceries & Convenience Stores",
            "type":"Retail Goods"
        }
    ],
    "sg:phone":"+1 662 286 8605",
    "sg:postcode":"38834",
    "sg:province":"MS",
    "sg:tags":[
        "grocer"
    ],
    "wof:name":"Parker Grocery",
    "wof:placetype":"venue"
},
  "geometry": {"coordinates":[-88.403818,34.924324],"type":"Point"}
}