{
  "type": "Feature",
  "properties": {
    "iso:country":"US",
    "sg:address":"2302 Denny Ave",
    "sg:city":"Pascagoula",
    "sg:classifiers":[
        {
            "category":"Autos & Motor Vehicles",
            "subcategory":"Automobile Sales",
            "type":"Retail Goods"
        }
    ],
    "sg:phone":"+1 228 762 3325",
    "sg:postcode":"39567",
    "sg:province":"MS",
    "sg:tags":[
        "car",
        "dealer"
    ],
    "sg:website":"www.kimbeckkia.com",
    "wof:name":"Kim Beck KIA",
    "wof:placetype":"venue"
},
  "geometry": {"coordinates":[-88.539152,30.371068],"type":"Point"}
}