{
  "type": "Feature",
  "properties": {
    "addr:full":"921 Co Rd 624 Ripley MS 38663",
    "addr:housenumber":"921;624",
    "addr:postcode":"38663",
    "addr:street":"Co Rd",
    "iso:country":"US",
    "sg:address":"921 Co Rd 624",
    "sg:city":"Ripley",
    "sg:classifiers":[
        {
            "category":"Manufacturing",
            "subcategory":"Lumber",
            "type":"Manufacturing & Wholesale Goods"
        }
    ],
    "sg:phone":"+1 662 837 4366",
    "sg:postcode":"38663",
    "sg:province":"MS",
    "sg:tags":[
        "operation",
        "timber",
        "tract"
    ],
    "wof:name":"Stroupe Reaford",
    "wof:placetype":"venue"
},
  "geometry": {"coordinates":[-88.755223,34.687053],"type":"Point"}
}