{
  "type": "Feature",
  "properties": {
    "iso:country":"US",
    "sg:address":"225 E Amite St",
    "sg:city":"Jackson",
    "sg:classifiers":[
        {
            "category":"Parking",
            "type":"Transportation"
        }
    ],
    "sg:phone":"+1 601 969 6672",
    "sg:postcode":"39201",
    "sg:province":"MS",
    "sg:tags":[
        "garage"
    ],
    "wof:name":"Central Parking System",
    "wof:placetype":"venue"
},
  "geometry": {"coordinates":[-90.18438999999999,32.300868],"type":"Point"}
}