{
  "type": "Feature",
  "properties": {
    "iso:country":"US",
    "sg:address":"300 Commerce Park Dr",
    "sg:city":"Jackson",
    "sg:classifiers":[
        {
            "category":"Manufacturing",
            "subcategory":"Tools & Machinery",
            "type":"Manufacturing & Wholesale Goods"
        }
    ],
    "sg:phone":"+1 601 982 5581",
    "sg:postcode":"39213",
    "sg:province":"MS",
    "sg:tags":[
        "mold"
    ],
    "sg:website":"www.euroamericanplastics.com",
    "wof:name":"Euro-American Plastics Inc",
    "wof:placetype":"venue"
},
  "geometry": {"coordinates":[-90.19035700000001,32.334725],"type":"Point"}
}