{
  "type": "Feature",
  "properties": {
    "iso:country":"US",
    "sg:address":"1718 Old Leland Rd",
    "sg:city":"Greenville",
    "sg:classifiers":[
        {
            "category":"Restaurant",
            "type":"Food & Drink"
        }
    ],
    "sg:phone":"+1 662 378 8654",
    "sg:postcode":"38703",
    "sg:province":"MS",
    "sg:tags":[
        "eating"
    ],
    "wof:name":"Bud's Cafe",
    "wof:placetype":"venue"
},
  "geometry": {"coordinates":[-91.036359,33.416108],"type":"Point"}
}