{
  "type": "Feature",
  "properties": {
    "addr:full":"3916 15th St Gulfport MS 39501",
    "addr:housenumber":"3916",
    "addr:postcode":"39501",
    "addr:street":"15Th St",
    "iso:country":"US",
    "sg:address":"3916 15th St",
    "sg:city":"Gulfport",
    "sg:classifiers":[
        {
            "category":"Organizations",
            "subcategory":"Religious Organization",
            "type":"Services"
        }
    ],
    "sg:phone":"+1 228 868 1729",
    "sg:postcode":"39501",
    "sg:province":"MS",
    "wof:name":"Grace Temple Baptist Church",
    "wof:placetype":"venue"
},
  "geometry": {"coordinates":[-89.110033,30.369308],"type":"Point"}
}