{
  "type": "Feature",
  "properties": {
    "iso:country":"US",
    "sg:address":"117 S 4th St",
    "sg:city":"Baldwyn",
    "sg:classifiers":[
        {
            "category":"Autos & Motor Vehicles",
            "subcategory":"Fuel & Gas Station",
            "type":"Retail Goods"
        }
    ],
    "sg:phone":"+1 662 365 8251",
    "sg:postcode":"38824",
    "sg:province":"MS",
    "sg:tags":[
        "oil"
    ],
    "wof:name":"Rutherford's Texaco",
    "wof:placetype":"venue"
},
  "geometry": {"coordinates":[-88.63570199999999,34.509759],"type":"Point"}
}