{
  "type": "Feature",
  "properties": {
    "addr:full":"109 Locksley Way Starkville MS 39759",
    "addr:housenumber":"109",
    "addr:postcode":"39759",
    "addr:street":"Locksley Way",
    "iso:country":"US",
    "sg:address":"109 Locksley Way",
    "sg:city":"Starkville",
    "sg:classifiers":[
        {
            "category":"Real Estate",
            "subcategory":"Real Estate Operator",
            "type":"Services"
        }
    ],
    "sg:phone":"+1 662 323 6373",
    "sg:postcode":"39759",
    "sg:province":"MS",
    "sg:tags":[
        "apartment"
    ],
    "wof:name":"Polo's",
    "wof:placetype":"venue"
},
  "geometry": {"coordinates":[-88.80903600000001,33.448548],"type":"Point"}
}