{
  "type": "Feature",
  "properties": {
    "iso:country":"US",
    "sg:address":"828 Pass Rd",
    "sg:city":"Gulfport",
    "sg:classifiers":[
        {
            "category":"Home & Garden",
            "subcategory":"Household Appliances",
            "type":"Retail Goods"
        }
    ],
    "sg:phone":"+1 228 868 1293",
    "sg:postcode":"39501",
    "sg:province":"MS",
    "sg:tags":[
        "cleaners",
        "vacuum"
    ],
    "wof:name":"Coast Vacuum Co",
    "wof:placetype":"venue"
},
  "geometry": {"coordinates":[-89.067218,30.387003],"type":"Point"}
}