{
  "type": "Feature",
  "properties": {
    "addr:full":"233 E Rankin St Jackson MS 39201",
    "addr:housenumber":"233",
    "addr:postcode":"39201",
    "addr:street":"E Rankin St",
    "iso:country":"US",
    "sg:address":"233 E Rankin St",
    "sg:city":"Jackson",
    "sg:classifiers":[
        {
            "category":"Wholesale",
            "subcategory":"Machinery & Supplies",
            "type":"Manufacturing & Wholesale Goods"
        }
    ],
    "sg:phone":"+1 601 969 9266",
    "sg:postcode":"39201",
    "sg:province":"MS",
    "sg:tags":[
        "equipment",
        "welding"
    ],
    "wof:name":"Capweld Inc",
    "wof:placetype":"venue"
},
  "geometry": {"coordinates":[-90.18665,32.286311],"type":"Point"}
}