{
  "type": "Feature",
  "properties": {
    "iso:country":"US",
    "sg:address":"4511 Terry Rd",
    "sg:city":"Jackson",
    "sg:classifiers":[
        {
            "category":"Retail",
            "subcategory":"Animal Services",
            "type":"Services"
        }
    ],
    "sg:phone":"+1 601 376 0203",
    "sg:postcode":"39212",
    "sg:province":"MS",
    "wof:name":"Puppy Parlor",
    "wof:placetype":"venue"
},
  "geometry": {"coordinates":[-90.24999800000001,32.201378],"type":"Point"}
}