{
  "type": "Feature",
  "properties": {
    "iso:country":"US",
    "sg:address":"554 Barksdale Rd",
    "sg:city":"Brandon",
    "sg:classifiers":[
        {
            "category":"Building & Trades",
            "subcategory":"Construction",
            "type":"Services"
        }
    ],
    "sg:phone":"+1 601 829 9069",
    "sg:postcode":"39094",
    "sg:province":"MS",
    "sg:tags":[
        "house"
    ],
    "wof:name":"Larry Berg Builder Inc &",
    "wof:placetype":"venue"
},
  "geometry": {"coordinates":[-89.934668,32.485968],"type":"Point"}
}