{
  "type": "Feature",
  "properties": {
    "iso:country":"US",
    "sg:address":"11213 US Hwy 49",
    "sg:city":"Gulfport",
    "sg:classifiers":[
        {
            "category":"Retail",
            "subcategory":"Funeral Services",
            "type":"Services"
        }
    ],
    "sg:phone":"+1 228 863 1522",
    "sg:postcode":"39503",
    "sg:province":"MS",
    "sg:tags":[
        "director"
    ],
    "wof:name":"Riemann Funeral Homes Inc",
    "wof:placetype":"venue"
},
  "geometry": {"coordinates":[-89.099448,30.448784],"type":"Point"}
}