{
  "type": "Feature",
  "properties": {
    "addr:full":"3017 State Hwy 43 S Picayune MS 39466",
    "addr:housenumber":"3017",
    "addr:postcode":"39466",
    "addr:street":"State Hwy 43 S",
    "iso:country":"US",
    "sg:address":"3017 State Hwy 43 S",
    "sg:city":"Picayune",
    "sg:classifiers":[
        {
            "category":"Wholesale",
            "subcategory":"Electrical",
            "type":"Manufacturing & Wholesale Goods"
        }
    ],
    "sg:phone":"+1 601 749 7988",
    "sg:postcode":"39466",
    "sg:province":"MS",
    "sg:tags":[
        "control",
        "security",
        "system"
    ],
    "wof:name":"Fort KNOX Security Systems",
    "wof:placetype":"venue"
},
  "geometry": {"coordinates":[-89.598625,30.519162],"type":"Point"}
}