{
  "type": "Feature",
  "properties": {
    "addr:full":"175 Quitman Perry Rd Carriere MS 39426",
    "addr:housenumber":"175",
    "addr:postcode":"39426",
    "addr:street":"Quitman Perry Rd",
    "iso:country":"US",
    "sg:address":"175 Quitman Perry Rd",
    "sg:city":"Carriere",
    "sg:classifiers":[
        {
            "category":"Manufacturing",
            "subcategory":"Lumber",
            "type":"Manufacturing & Wholesale Goods"
        }
    ],
    "sg:phone":"+1 601 799 2651",
    "sg:postcode":"39426",
    "sg:province":"MS",
    "sg:tags":[
        "operation",
        "timber",
        "tract"
    ],
    "wof:name":"Belles Collines Farm LP",
    "wof:placetype":"venue"
},
  "geometry": {"coordinates":[-89.74755999999999,30.729761],"type":"Point"}
}