{
  "type": "Feature",
  "properties": {
    "addr:full":"2222 17th St Gulfport MS 39501",
    "addr:housenumber":"2222",
    "addr:postcode":"39501",
    "addr:street":"17Th St",
    "iso:country":"US",
    "sg:address":"2222 17th St",
    "sg:city":"Gulfport",
    "sg:classifiers":[
        {
            "category":"Professional",
            "subcategory":"Lawyer & Legal Services",
            "type":"Services"
        }
    ],
    "sg:phone":"+1 228 868 2057",
    "sg:postcode":"39501",
    "sg:province":"MS",
    "sg:tags":[
        "attorney"
    ],
    "wof:name":"Laurie Caldwell",
    "wof:placetype":"venue"
},
  "geometry": {"coordinates":[-89.089879,30.371401],"type":"Point"}
}