{
  "type": "Feature",
  "properties": {
    "addr:full":"622 New Orleans St Hattiesburg MS 39401",
    "addr:housenumber":"622",
    "addr:postcode":"39401",
    "addr:street":"New Orleans St",
    "iso:country":"US",
    "sg:address":"622 New Orleans St",
    "sg:city":"Hattiesburg",
    "sg:classifiers":[
        {
            "category":"Insurance",
            "subcategory":"Insurance Agent",
            "type":"Services"
        },
        {
            "category":"Insurance",
            "subcategory":"Life Insurance",
            "type":"Services"
        }
    ],
    "sg:phone":"+1 601 583 1762",
    "sg:postcode":"39401",
    "sg:province":"MS",
    "wof:name":"Central Burial Assoc",
    "wof:placetype":"venue"
},
  "geometry": {"coordinates":[-89.29156,31.335021],"type":"Point"}
}