{
  "type": "Feature",
  "properties": {
    "addr:full":"283 Quail Rd Canton MS 39046",
    "addr:housenumber":"283",
    "addr:postcode":"39046",
    "addr:street":"Quail Rd",
    "iso:country":"US",
    "sg:address":"283 Quail Rd",
    "sg:city":"Canton",
    "sg:classifiers":[
        {
            "category":"Building & Trades",
            "subcategory":"Plumbing",
            "type":"Services"
        }
    ],
    "sg:phone":"+1 601 859 3394",
    "sg:postcode":"39046",
    "sg:province":"MS",
    "sg:tags":[
        "heating",
        "contractor"
    ],
    "wof:name":"F J Hamel Plumbing & Electric",
    "wof:placetype":"venue"
},
  "geometry": {"coordinates":[-89.96895600000001,32.658062],"type":"Point"}
}