{
  "type": "Feature",
  "properties": {
    "iso:country":"US",
    "sg:address":"169 Co Rd 509",
    "sg:city":"Corinth",
    "sg:classifiers":[
        {
            "category":"Retail",
            "subcategory":"Auto Repair",
            "type":"Services"
        }
    ],
    "sg:phone":"+1 662 284 9969",
    "sg:postcode":"38834",
    "sg:province":"MS",
    "sg:tags":[
        "repairing",
        "automobile",
        "automotive"
    ],
    "wof:name":"Carter's Auto Tech",
    "wof:placetype":"venue"
},
  "geometry": {"coordinates":[-88.549937,34.899367],"type":"Point"}
}