{
  "type": "Feature",
  "properties": {
    "iso:country":"US",
    "sg:address":"610 W Bankhead St",
    "sg:city":"New Albany",
    "sg:classifiers":[
        {
            "category":"Shopping",
            "subcategory":"Gifts & Souvenirs",
            "type":"Retail Goods"
        }
    ],
    "sg:phone":"+1 662 539 0061",
    "sg:postcode":"38652",
    "sg:province":"MS",
    "wof:name":"Bead Shack",
    "wof:placetype":"venue"
},
  "geometry": {"coordinates":[-89.024447,34.499592],"type":"Point"}
}