{
  "type": "Feature",
  "properties": {
    "iso:country":"US",
    "sg:address":"1909 E Pass Rd",
    "sg:city":"Gulfport",
    "sg:classifiers":[
        {
            "category":"Professional",
            "type":"Services"
        }
    ],
    "sg:phone":"+1 228 897 2703",
    "sg:postcode":"39507",
    "sg:province":"MS",
    "sg:tags":[
        "establishment"
    ],
    "wof:name":"Tom Henry Design",
    "wof:placetype":"venue"
},
  "geometry": {"coordinates":[-89.017337,30.400638],"type":"Point"}
}