{
  "type": "Feature",
  "properties": {
    "iso:country":"US",
    "sg:address":"3057 Hwy 80 E",
    "sg:city":"Pearl",
    "sg:classifiers":[
        {
            "category":"Autos & Motor Vehicles",
            "subcategory":"Automobile Sales",
            "type":"Retail Goods"
        }
    ],
    "sg:phone":"+1 601 936 3422",
    "sg:postcode":"39208",
    "sg:province":"MS",
    "sg:tags":[
        "used"
    ],
    "wof:name":"T & T Motor Co Inc",
    "wof:placetype":"venue"
},
  "geometry": {"coordinates":[-90.11780400000001,32.282833],"type":"Point"}
}