{
  "type": "Feature",
  "properties": {
    "iso:country":"US",
    "sg:address":"2208 16th St",
    "sg:city":"Meridian",
    "sg:classifiers":[
        {
            "category":"Building & Trades",
            "subcategory":"Construction",
            "type":"Services"
        }
    ],
    "sg:phone":"+1 601 483 1253",
    "sg:postcode":"39301",
    "sg:province":"MS",
    "sg:tags":[
        "general",
        "contractor"
    ],
    "wof:name":"W G Yates & Sons Construction",
    "wof:placetype":"venue"
},
  "geometry": {"coordinates":[-88.70123599999999,32.373176],"type":"Point"}
}