{
  "type": "Feature",
  "properties": {
    "iso:country":"US",
    "sg:address":"186 Edgar Holmes Rd",
    "sg:city":"Tylertown",
    "sg:classifiers":[
        {
            "category":"Farming",
            "subcategory":"Farm",
            "type":"Manufacturing & Wholesale Goods"
        }
    ],
    "sg:phone":"+1 601 876 2747",
    "sg:postcode":"39667",
    "sg:province":"MS",
    "sg:tags":[
        "dairy",
        "crop",
        "general"
    ],
    "wof:name":"Dillon Truly",
    "wof:placetype":"venue"
},
  "geometry": {"coordinates":[-90.138638,31.050452],"type":"Point"}
}