{
  "type": "Feature",
  "properties": {
    "iso:country":"US",
    "sg:address":"4604 Lee Rd",
    "sg:city":"Vicksburg",
    "sg:classifiers":[
        {
            "category":"Professional",
            "subcategory":"Business Services",
            "type":"Services"
        }
    ],
    "sg:phone":"+1 601 638 8588",
    "sg:postcode":"39180",
    "sg:province":"MS",
    "sg:tags":[
        "carrier",
        "surety",
        "insurance"
    ],
    "wof:name":"Bishop Bonding Co",
    "wof:placetype":"venue"
},
  "geometry": {"coordinates":[-90.827062,32.303546],"type":"Point"}
}