{
  "type": "Feature",
  "properties": {
    "addr:full":"803 Deer Park St Jackson MS 39203",
    "addr:housenumber":"803",
    "addr:postcode":"39203",
    "addr:street":"Deer Park St",
    "iso:country":"US",
    "sg:address":"803 Deer Park St",
    "sg:city":"Jackson",
    "sg:classifiers":[
        {
            "category":"Travel",
            "subcategory":"Hotels & Motels",
            "type":"Entertainment"
        }
    ],
    "sg:phone":"+1 601 944 1392",
    "sg:postcode":"39203",
    "sg:province":"MS",
    "sg:tags":[
        "operation"
    ],
    "wof:name":"Park Inn",
    "wof:placetype":"venue"
},
  "geometry": {"coordinates":[-90.19951,32.301251],"type":"Point"}
}