{
  "type": "Feature",
  "properties": {
    "iso:country":"US",
    "sg:address":"3330 Hwy 82 E",
    "sg:city":"Greenville",
    "sg:classifiers":[
        {
            "category":"Government",
            "subcategory":"Office",
            "type":"Public Place"
        }
    ],
    "sg:phone":"+1 662 334 2756",
    "sg:postcode":"38703",
    "sg:province":"MS",
    "wof:name":"Washington Cnty Juvenile Hldng",
    "wof:placetype":"venue"
},
  "geometry": {"coordinates":[-91.00490600000001,33.400363],"type":"Point"}
}