{
  "type": "Feature",
  "properties": {
    "iso:country":"US",
    "sg:address":"1192 Askew Ferry Rd",
    "sg:city":"Edwards",
    "sg:classifiers":[
        {
            "category":"Building & Trades",
            "subcategory":"Construction",
            "type":"Services"
        }
    ],
    "sg:phone":"+1 601 852 4501",
    "sg:postcode":"39066",
    "sg:province":"MS",
    "sg:tags":[
        "general",
        "contractor"
    ],
    "wof:name":"Mc Hann Railroad Svc",
    "wof:placetype":"venue"
},
  "geometry": {"coordinates":[-90.59952699999999,32.341812],"type":"Point"}
}