{
  "type": "Feature",
  "properties": {
    "addr:full":"111 S Fulton St Iuka MS 38852",
    "addr:housenumber":"111",
    "addr:postcode":"38852",
    "addr:street":"S Fulton St",
    "iso:country":"US",
    "sg:address":"111 S Fulton St",
    "sg:city":"Iuka",
    "sg:classifiers":[
        {
            "category":"Shopping",
            "subcategory":"Stationery & Office Supplies",
            "type":"Retail Goods"
        }
    ],
    "sg:phone":"+1 662 423 2755",
    "sg:postcode":"38852",
    "sg:province":"MS",
    "wof:name":"Alpha Office & Educational",
    "wof:placetype":"venue"
},
  "geometry": {"coordinates":[-88.189379,34.81175],"type":"Point"}
}