{
  "type": "Feature",
  "properties": {
    "iso:country":"US",
    "sg:address":"3389 Co Rd 406",
    "sg:city":"Okolona",
    "sg:classifiers":[
        {
            "category":"Home & Garden",
            "subcategory":"Furniture",
            "type":"Retail Goods"
        }
    ],
    "sg:phone":"+1 662 447 3144",
    "sg:postcode":"38851",
    "sg:province":"MS",
    "wof:name":"Johnson Furniture",
    "wof:placetype":"venue"
},
  "geometry": {"coordinates":[-88.727966,33.898424],"type":"Point"}
}