{
  "type": "Feature",
  "properties": {
    "iso:country":"US",
    "sg:address":"1659 State Hwy 15",
    "sg:city":"Louisville",
    "sg:classifiers":[
        {
            "category":"Real Estate",
            "subcategory":"Real Estate Operator",
            "type":"Services"
        }
    ],
    "sg:phone":"+1 662 773 6269",
    "sg:postcode":"39339",
    "sg:province":"MS",
    "sg:tags":[
        "apartment"
    ],
    "wof:name":"Hughes Management",
    "wof:placetype":"venue"
},
  "geometry": {"coordinates":[-89.07231299999999,33.102854],"type":"Point"}
}