{
  "type": "Feature",
  "properties": {
    "iso:country":"US",
    "sg:address":"750 Woodlands Pkwy",
    "sg:city":"Ridgeland",
    "sg:classifiers":[
        {
            "category":"Banks & Credit Unions",
            "subcategory":"Investment Brokerage",
            "type":"Services"
        }
    ],
    "sg:phone":"+1 601 957 9557",
    "sg:postcode":"39157",
    "sg:province":"MS",
    "sg:tags":[
        "advisory",
        "financial"
    ],
    "wof:name":"Mowdy Financial LLC",
    "wof:placetype":"venue"
},
  "geometry": {"coordinates":[-90.112673,32.403282],"type":"Point"}
}