{
  "type": "Feature",
  "properties": {
    "iso:country":"US",
    "sg:address":"5959 Manship Rd",
    "sg:city":"Brandon",
    "sg:classifiers":[
        {
            "category":"Real Estate",
            "subcategory":"Real Estate Operator",
            "type":"Services"
        }
    ],
    "sg:phone":"+1 601 992 0687",
    "sg:postcode":"39232",
    "sg:province":"MS",
    "sg:tags":[
        "mall",
        "shopping",
        "center"
    ],
    "wof:name":"Magnolia Marketplace",
    "wof:placetype":"venue"
},
  "geometry": {"coordinates":[-90.03255900000001,32.353425],"type":"Point"}
}