{
  "type": "Feature",
  "properties": {
    "addr:full":"1024 Gardner Blvd Columbus MS 39702",
    "addr:housenumber":"1024",
    "addr:postcode":"39702",
    "addr:street":"Gardner Blvd",
    "iso:country":"US",
    "sg:address":"1024 Gardner Blvd",
    "sg:city":"Columbus",
    "sg:classifiers":[
        {
            "category":"Retail",
            "subcategory":"Auto Repair",
            "type":"Services"
        }
    ],
    "sg:phone":"+1 662 328 8277",
    "sg:postcode":"39702",
    "sg:province":"MS",
    "sg:tags":[
        "body",
        "automobile",
        "painting"
    ],
    "wof:name":"Shelton's Body Shop",
    "wof:placetype":"venue"
},
  "geometry": {"coordinates":[-88.38946199999999,33.50719],"type":"Point"}
}