{
  "type": "Feature",
  "properties": {
    "iso:country":"US",
    "sg:address":"431 Old Hwy 13 S",
    "sg:city":"Columbia",
    "sg:classifiers":[
        {
            "category":"Social Services",
            "type":"Services"
        }
    ],
    "sg:phone":"+1 601 736 7882",
    "sg:postcode":"39429",
    "sg:province":"MS",
    "sg:tags":[
        "organization",
        "welfare"
    ],
    "wof:name":"Pearl River Valley-Hub Ctr",
    "wof:placetype":"venue"
},
  "geometry": {"coordinates":[-89.751221,31.148041],"type":"Point"}
}