{
  "type": "Feature",
  "properties": {
    "addr:full":"102 Rankin Blvd Exd Tupelo MS 38801",
    "addr:housenumber":"102",
    "addr:postcode":"38801",
    "addr:street":"Rankin Blvd Exd",
    "iso:country":"US",
    "sg:address":"102 Rankin Blvd Exd",
    "sg:city":"Tupelo",
    "sg:classifiers":[
        {
            "category":"Sports & Exercise",
            "subcategory":"Gym",
            "type":"Entertainment"
        }
    ],
    "sg:phone":"+1 662 841 0297",
    "sg:postcode":"38801",
    "sg:province":"MS",
    "sg:tags":[
        "club",
        "health",
        "studio",
        "gymnasium"
    ],
    "wof:name":"Fitness Max Inc",
    "wof:placetype":"venue"
},
  "geometry": {"coordinates":[-88.71817799999999,34.254745],"type":"Point"}
}