{
  "type": "Feature",
  "properties": {
    "iso:country":"US",
    "sg:address":"128 Cherry St",
    "sg:city":"Grenada",
    "sg:classifiers":[
        {
            "category":"Social Services",
            "subcategory":"Child Care",
            "type":"Services"
        }
    ],
    "sg:phone":"+1 662 227 9112",
    "sg:postcode":"38901",
    "sg:province":"MS",
    "wof:name":"A Ray Of Hope Preschool",
    "wof:placetype":"venue"
},
  "geometry": {"coordinates":[-89.806026,33.785516],"type":"Point"}
}