{
  "type": "Feature",
  "properties": {
    "addr:full":"48 Tate Rd Greenville MS 38701",
    "addr:housenumber":"48",
    "addr:postcode":"38701",
    "addr:street":"Tate Rd",
    "iso:country":"US",
    "sg:address":"48 Tate Rd",
    "sg:city":"Greenville",
    "sg:classifiers":[
        {
            "category":"Professional",
            "subcategory":"Business Services",
            "type":"Services"
        }
    ],
    "sg:phone":"+1 662 334 3902",
    "sg:postcode":"38701",
    "sg:province":"MS",
    "sg:tags":[
        "appraiser"
    ],
    "wof:name":"Wise Appraisal And Real Estate",
    "wof:placetype":"venue"
},
  "geometry": {"coordinates":[-91.036176,33.319373],"type":"Point"}
}