{
  "type": "Feature",
  "properties": {
    "iso:country":"US",
    "sg:address":"533 Peebles Ave",
    "sg:city":"Philadelphia",
    "sg:classifiers":[
        {
            "category":"Freight",
            "type":"Transportation"
        }
    ],
    "sg:phone":"+1 601 656 1936",
    "sg:postcode":"39350",
    "sg:province":"MS",
    "sg:tags":[
        "commercial",
        "storage"
    ],
    "wof:name":"Northside Self Storage",
    "wof:placetype":"venue"
},
  "geometry": {"coordinates":[-89.108571,32.763071],"type":"Point"}
}