{
  "type": "Feature",
  "properties": {
    "iso:country":"US",
    "sg:address":"227 N Main St",
    "sg:city":"Yazoo City",
    "sg:classifiers":[
        {
            "category":"Personal",
            "subcategory":"Barber",
            "type":"Services"
        }
    ],
    "sg:phone":"+1 662 746 7170",
    "sg:postcode":"39194",
    "sg:province":"MS",
    "wof:name":"Calvin's Barber Shop",
    "wof:placetype":"venue"
},
  "geometry": {"coordinates":[-90.412672,32.84881],"type":"Point"}
}