{
  "type": "Feature",
  "properties": {
    "addr:full":"1300 25th St Gulfport MS 39501",
    "addr:housenumber":"1300",
    "addr:postcode":"39501",
    "addr:street":"25Th St",
    "iso:country":"US",
    "sg:address":"1300 25th St",
    "sg:city":"Gulfport",
    "sg:classifiers":[
        {
            "category":"Professional",
            "subcategory":"Lawyer & Legal Services",
            "type":"Services"
        }
    ],
    "sg:phone":"+1 228 863 9975",
    "sg:postcode":"39501",
    "sg:province":"MS",
    "sg:tags":[
        "attorney",
        "practice",
        "general"
    ],
    "wof:name":"G Martin Warren Jr Pllc",
    "wof:placetype":"venue"
},
  "geometry": {"coordinates":[-89.07885400000001,30.380369],"type":"Point"}
}