{
  "type": "Feature",
  "properties": {
    "addr:full":"916 N Jackson St Houston MS 38851",
    "addr:housenumber":"916",
    "addr:postcode":"38851",
    "addr:street":"N Jackson St",
    "iso:country":"US",
    "sg:address":"916 N Jackson St",
    "sg:city":"Houston",
    "sg:classifiers":[
        {
            "category":"Autos & Motor Vehicles",
            "subcategory":"Auto Supplies",
            "type":"Retail Goods"
        }
    ],
    "sg:phone":"+1 662 456 3344",
    "sg:postcode":"38851",
    "sg:province":"MS",
    "sg:tags":[
        "tire"
    ],
    "wof:name":"Chickasaw Tire Svc",
    "wof:placetype":"venue"
},
  "geometry": {"coordinates":[-89.005178,33.91413],"type":"Point"}
}