{
  "type": "Feature",
  "properties": {
    "addr:full":"6194 US Hwy 49 Hattiesburg MS 39401",
    "addr:housenumber":"6194",
    "addr:postcode":"39401",
    "addr:street":"Us Hwy 49",
    "iso:country":"US",
    "sg:address":"6194 US Hwy 49",
    "sg:city":"Hattiesburg",
    "sg:classifiers":[
        {
            "category":"Restaurant",
            "type":"Food & Drink"
        }
    ],
    "sg:phone":"+1 601 545 9393",
    "sg:postcode":"39401",
    "sg:province":"MS",
    "sg:tags":[
        "eating"
    ],
    "wof:name":"Sakura",
    "wof:placetype":"venue"
},
  "geometry": {"coordinates":[-89.34244700000001,31.353329],"type":"Point"}
}