{
  "type": "Feature",
  "properties": {
    "iso:country":"US",
    "sg:address":"24480 Cuevas Delisle Rd",
    "sg:city":"Pass Christian",
    "sg:classifiers":[
        {
            "category":"Retail",
            "subcategory":"Auto Repair",
            "type":"Services"
        }
    ],
    "sg:phone":"+1 228 452 9925",
    "sg:postcode":"39571",
    "sg:province":"MS",
    "sg:tags":[
        "automotive"
    ],
    "wof:name":"Bucks Towing",
    "wof:placetype":"venue"
},
  "geometry": {"coordinates":[-89.255363,30.38329],"type":"Point"}
}