{
  "type": "Feature",
  "properties": {
    "addr:full":"1710 Hwy 9 N Pontotoc MS 38863",
    "addr:housenumber":"1710",
    "addr:postcode":"38863",
    "addr:street":"Hwy 9 N",
    "iso:country":"US",
    "sg:address":"1710 Hwy 9 N",
    "sg:city":"Pontotoc",
    "sg:classifiers":[
        {
            "category":"Shopping",
            "subcategory":"Used Merchandise",
            "type":"Retail Goods"
        }
    ],
    "sg:phone":"+1 662 489 7673",
    "sg:postcode":"38863",
    "sg:province":"MS",
    "sg:tags":[
        "antique"
    ],
    "wof:name":"Westmoreland Antique Exhibit",
    "wof:placetype":"venue"
},
  "geometry": {"coordinates":[-88.983861,34.271927],"type":"Point"}
}