{
  "type": "Feature",
  "properties": {
    "iso:country":"US",
    "sg:address":"1510 US Hwy 82 E",
    "sg:city":"Indianola",
    "sg:classifiers":[
        {
            "category":"Shopping",
            "subcategory":"Pharmacy",
            "type":"Retail Goods"
        }
    ],
    "sg:phone":"+1 662 887 5004",
    "sg:postcode":"38751",
    "sg:province":"MS",
    "wof:name":"Pharm Services Inc",
    "wof:placetype":"venue"
},
  "geometry": {"coordinates":[-90.616823,33.45971],"type":"Point"}
}