{
  "type": "Feature",
  "properties": {
    "iso:country":"US",
    "sg:address":"14100 Seaway Rd",
    "sg:city":"Gulfport",
    "sg:classifiers":[
        {
            "category":"Freight",
            "type":"Transportation"
        }
    ],
    "sg:phone":"+1 228 863 4336",
    "sg:postcode":"39503",
    "sg:province":"MS",
    "sg:tags":[
        "operator",
        "local",
        "trucking"
    ],
    "wof:name":"Shippers Express Inc",
    "wof:placetype":"venue"
},
  "geometry": {"coordinates":[-89.07379299999999,30.434306],"type":"Point"}
}