{
  "type": "Feature",
  "properties": {
    "addr:full":"2800 US Hwy 90 Gautier MS 39553",
    "addr:housenumber":"2800",
    "addr:postcode":"39553",
    "addr:street":"Us Hwy 90",
    "iso:country":"US",
    "sg:address":"2800 US Hwy 90",
    "sg:city":"Gautier",
    "sg:classifiers":[
        {
            "category":"Shopping",
            "subcategory":"Gifts & Souvenirs",
            "type":"Retail Goods"
        }
    ],
    "sg:phone":"+1 228 497 5122",
    "sg:postcode":"39553",
    "sg:province":"MS",
    "sg:tags":[
        "shop"
    ],
    "sg:website":"www.coachhousegifts.com",
    "wof:name":"Coach House",
    "wof:placetype":"venue"
},
  "geometry": {"coordinates":[-88.65346,30.392307],"type":"Point"}
}