{
  "type": "Feature",
  "properties": {
    "iso:country":"US",
    "sg:address":"6416 Washington Ave",
    "sg:city":"Ocean Springs",
    "sg:classifiers":[
        {
            "category":"Banks & Credit Unions",
            "subcategory":"Bank",
            "type":"Services"
        }
    ],
    "sg:phone":"+1 228 875 1227",
    "sg:postcode":"39564",
    "sg:province":"MS",
    "wof:name":"Merchants & Marine Bank",
    "wof:placetype":"venue"
},
  "geometry": {"coordinates":[-88.830331,30.435354],"type":"Point"}
}