{
  "type": "Feature",
  "properties": {
    "addr:full":"208 E Bankhead St New Albany MS 38652",
    "addr:housenumber":"208",
    "addr:postcode":"38652",
    "addr:street":"E Bankhead St",
    "iso:country":"US",
    "sg:address":"208 E Bankhead St",
    "sg:city":"New Albany",
    "sg:classifiers":[
        {
            "category":"Shopping",
            "subcategory":"Florist",
            "type":"Retail Goods"
        }
    ],
    "sg:phone":"+1 662 534 9051",
    "sg:postcode":"38652",
    "sg:province":"MS",
    "wof:name":"New Albany Flower Shop",
    "wof:placetype":"venue"
},
  "geometry": {"coordinates":[-89.00667300000001,34.492577],"type":"Point"}
}