{
  "type": "Feature",
  "properties": {
    "iso:country":"US",
    "sg:address":"2308 10th St",
    "sg:city":"Meridian",
    "sg:classifiers":[
        {
            "category":"Organizations",
            "subcategory":"Religious Organization",
            "type":"Services"
        }
    ],
    "sg:phone":"+1 601 693 1521",
    "sg:postcode":"39301",
    "sg:province":"MS",
    "sg:tags":[
        "church"
    ],
    "wof:name":"Central United Methodist Chr",
    "wof:placetype":"venue"
},
  "geometry": {"coordinates":[-88.702501,32.366933],"type":"Point"}
}