{
  "type": "Feature",
  "properties": {
    "iso:country":"US",
    "sg:address":"1611 20th St",
    "sg:city":"Meridian",
    "sg:classifiers":[
        {
            "category":"Building & Trades",
            "subcategory":"Landscaping Services",
            "type":"Services"
        }
    ],
    "sg:phone":"+1 601 485 3255",
    "sg:postcode":"39301",
    "sg:province":"MS",
    "sg:tags":[
        "tree"
    ],
    "wof:name":"S & C Tree Svc",
    "wof:placetype":"venue"
},
  "geometry": {"coordinates":[-88.695217,32.37811],"type":"Point"}
}