{
  "type": "Feature",
  "properties": {
    "iso:country":"US",
    "sg:address":"728 State Hwy 8",
    "sg:city":"Vardaman",
    "sg:classifiers":[
        {
            "category":"Personal",
            "subcategory":"Beauty Salon",
            "type":"Services"
        }
    ],
    "sg:phone":"+1 662 682 7812",
    "sg:postcode":"38878",
    "sg:province":"MS",
    "wof:name":"Virginia's Beauty Salon",
    "wof:placetype":"venue"
},
  "geometry": {"coordinates":[-89.181738,33.875326],"type":"Point"}
}