{
  "type": "Feature",
  "properties": {
    "iso:country":"US",
    "sg:address":"1140 Hwy 98 E",
    "sg:city":"Mccomb",
    "sg:classifiers":[
        {
            "category":"Autos & Motor Vehicles",
            "subcategory":"Automobile Sales",
            "type":"Retail Goods"
        }
    ],
    "sg:phone":"+1 601 684 7745",
    "sg:postcode":"39648",
    "sg:province":"MS",
    "sg:tags":[
        "car",
        "used",
        "dealer"
    ],
    "wof:name":"Oliver's Used Cars",
    "wof:placetype":"venue"
},
  "geometry": {"coordinates":[-90.42738199999999,31.225729],"type":"Point"}
}