{
  "type": "Feature",
  "properties": {
    "iso:country":"US",
    "sg:address":"5541 Robinson Rd Exd",
    "sg:city":"Jackson",
    "sg:classifiers":[
        {
            "category":"Food & Beverages",
            "subcategory":"Liquor & Beverages",
            "type":"Retail Goods"
        }
    ],
    "sg:phone":"+1 601 373 0209",
    "sg:postcode":"39204",
    "sg:province":"MS",
    "wof:name":"Joe's Package Store",
    "wof:placetype":"venue"
},
  "geometry": {"coordinates":[-90.260848,32.271015],"type":"Point"}
}