{
  "type": "Feature",
  "properties": {
    "iso:country":"US",
    "sg:address":"317 Van Dorn St",
    "sg:city":"Grenada",
    "sg:classifiers":[
        {
            "category":"Wholesale",
            "subcategory":"Construction Materials",
            "type":"Manufacturing & Wholesale Goods"
        }
    ],
    "sg:phone":"+1 662 226 3008",
    "sg:postcode":"38901",
    "sg:province":"MS",
    "sg:tags":[
        "timberland",
        "company",
        "timber"
    ],
    "wof:name":"Georgia Pacific Corp",
    "wof:placetype":"venue"
},
  "geometry": {"coordinates":[-89.808892,33.765988],"type":"Point"}
}