{
  "type": "Feature",
  "properties": {
    "addr:full":"2475 Ratliff Rd Raymond MS 39154",
    "addr:housenumber":"2475",
    "addr:postcode":"39154",
    "addr:street":"Ratliff Rd",
    "iso:country":"US",
    "sg:address":"2475 Ratliff Rd",
    "sg:city":"Raymond",
    "sg:classifiers":[
        {
            "category":"Professional",
            "subcategory":"Advertising",
            "type":"Services"
        }
    ],
    "sg:phone":"+1 601 857 0903",
    "sg:postcode":"39154",
    "sg:province":"MS",
    "sg:tags":[
        "agency"
    ],
    "wof:name":"Kim Townsend Advertisingnb",
    "wof:placetype":"venue"
},
  "geometry": {"coordinates":[-90.479116,32.25454],"type":"Point"}
}