{
  "type": "Feature",
  "properties": {
    "iso:country":"US",
    "sg:address":"22 E Lake Rd",
    "sg:city":"Hattiesburg",
    "sg:classifiers":[
        {
            "category":"Real Estate",
            "subcategory":"Real Estate Agent",
            "type":"Services"
        }
    ],
    "sg:phone":"+1 601 296 9390",
    "sg:postcode":"39402",
    "sg:province":"MS",
    "wof:name":"Cs Cranford Realtor",
    "wof:placetype":"venue"
},
  "geometry": {"coordinates":[-89.428864,31.307323],"type":"Point"}
}