{
  "type": "Feature",
  "properties": {
    "iso:country":"US",
    "sg:address":"301 S 40th Ave",
    "sg:city":"Hattiesburg",
    "sg:classifiers":[
        {
            "category":"Insurance",
            "subcategory":"Insurance Agent",
            "type":"Services"
        }
    ],
    "sg:phone":"+1 601 264 1911",
    "sg:postcode":"39402",
    "sg:province":"MS",
    "wof:name":"Cornett Group Inc",
    "wof:placetype":"venue"
},
  "geometry": {"coordinates":[-89.347999,31.321835],"type":"Point"}
}