{
  "type": "Feature",
  "properties": {
    "addr:full":"103 W Main St Utica MS 39175",
    "addr:housenumber":"103",
    "addr:postcode":"39175",
    "addr:street":"W Main St",
    "iso:country":"US",
    "sg:address":"103 W Main St",
    "sg:city":"Utica",
    "sg:classifiers":[
        {
            "category":"Retail",
            "subcategory":"Laundry & Dry Cleaning",
            "type":"Services"
        }
    ],
    "sg:phone":"+1 601 885 6168",
    "sg:postcode":"39175",
    "sg:province":"MS",
    "sg:tags":[
        "drycleaning",
        "plant"
    ],
    "wof:name":"Korner Kleaners",
    "wof:placetype":"venue"
},
  "geometry": {"coordinates":[-90.62401199999999,32.10959],"type":"Point"}
}