{
  "type": "Feature",
  "properties": {
    "iso:country":"US",
    "sg:address":"1136 Cliff Gookin Blvd",
    "sg:city":"Tupelo",
    "sg:classifiers":[
        {
            "category":"Freight",
            "type":"Transportation"
        }
    ],
    "sg:phone":"+1 662 680 9600",
    "sg:postcode":"38801",
    "sg:province":"MS",
    "sg:tags":[
        "trucking"
    ],
    "wof:name":"CMT Inc",
    "wof:placetype":"venue"
},
  "geometry": {"coordinates":[-88.754374,34.224308],"type":"Point"}
}