{
  "type": "Feature",
  "properties": {
    "addr:full":"1500 E Woodrow Wilson Ave Jackson MS 39216",
    "addr:housenumber":"1500",
    "addr:postcode":"39216",
    "addr:street":"E Woodrow Wilson Ave",
    "iso:country":"US",
    "sg:address":"1500 E Woodrow Wilson Ave",
    "sg:city":"Jackson",
    "sg:classifiers":[
        {
            "category":"Professional",
            "subcategory":"Research",
            "type":"Services"
        }
    ],
    "sg:phone":"+1 601 364 1315",
    "sg:postcode":"39216",
    "sg:province":"MS",
    "sg:tags":[
        "medical"
    ],
    "wof:name":"Research Mississippi Inc",
    "wof:placetype":"venue"
},
  "geometry": {"coordinates":[-90.16483599999999,32.326559],"type":"Point"}
}