{
  "type": "Feature",
  "properties": {
    "addr:full":"7504 Martin Bluff Rd Gautier MS 39553",
    "addr:housenumber":"7504",
    "addr:postcode":"39553",
    "addr:street":"Martin Bluff Rd",
    "iso:country":"US",
    "sg:address":"7504 Martin Bluff Rd",
    "sg:city":"Gautier",
    "sg:classifiers":[
        {
            "category":"Restaurant",
            "type":"Food & Drink"
        }
    ],
    "sg:phone":"+1 228 497 9000",
    "sg:postcode":"39553",
    "sg:province":"MS",
    "sg:tags":[
        "grocery",
        "store"
    ],
    "wof:name":"Singing River Grocery",
    "wof:placetype":"venue"
},
  "geometry": {"coordinates":[-88.631575,30.451998],"type":"Point"}
}