{
  "type": "Feature",
  "properties": {
    "iso:country":"US",
    "sg:address":"178 Commerce St",
    "sg:city":"Batesville",
    "sg:classifiers":[
        {
            "category":"Banks & Credit Unions",
            "subcategory":"Bank",
            "type":"Services"
        }
    ],
    "sg:phone":"+1 662 563 5673",
    "sg:postcode":"38606",
    "sg:province":"MS",
    "sg:tags":[
        "state",
        "commercial"
    ],
    "wof:name":"Bancorpsouth",
    "wof:placetype":"venue"
},
  "geometry": {"coordinates":[-89.94372199999999,34.310543],"type":"Point"}
}