{
  "type": "Feature",
  "properties": {
    "iso:country":"US",
    "sg:address":"123 S Main St",
    "sg:city":"Drew",
    "sg:classifiers":[
        {
            "category":"Organizations",
            "subcategory":"Religious Organization",
            "type":"Services"
        }
    ],
    "sg:phone":"+1 662 745 6587",
    "sg:postcode":"38737",
    "sg:province":"MS",
    "sg:tags":[
        "church"
    ],
    "wof:name":"Countywide Outreach Ministry",
    "wof:placetype":"venue"
},
  "geometry": {"coordinates":[-90.528651,33.809243],"type":"Point"}
}