{
  "type": "Feature",
  "properties": {
    "iso:country":"US",
    "sg:address":"77 Midway Church Rd",
    "sg:city":"Sumrall",
    "sg:classifiers":[
        {
            "category":"Organizations",
            "subcategory":"Religious Organization",
            "type":"Services"
        }
    ],
    "sg:phone":"+1 601 264 6647",
    "sg:postcode":"39482",
    "sg:province":"MS",
    "wof:name":"Midway First Baptist Church",
    "wof:placetype":"venue"
},
  "geometry": {"coordinates":[-89.52757699999999,31.292014],"type":"Point"}
}