{
  "type": "Feature",
  "properties": {
    "addr:full":"200 S Main St Poplarville MS 39470",
    "addr:housenumber":"200",
    "addr:postcode":"39470",
    "addr:street":"S Main St",
    "iso:country":"US",
    "sg:address":"200 S Main St",
    "sg:city":"Poplarville",
    "sg:classifiers":[
        {
            "category":"Government",
            "subcategory":"Police Station",
            "type":"Public Place"
        }
    ],
    "sg:phone":"+1 601 403 2300",
    "sg:postcode":"39470",
    "sg:province":"MS",
    "sg:tags":[
        "sheriff"
    ],
    "sg:website":"www.pearlrivercounty.net",
    "wof:name":"Pearl River Cnty Chancery Clrk",
    "wof:placetype":"venue"
},
  "geometry": {"coordinates":[-89.53519300000001,30.842915],"type":"Point"}
}