{
  "type": "Feature",
  "properties": {
    "iso:country":"US",
    "sg:address":"1625 Springridge Dr",
    "sg:city":"Jackson",
    "sg:classifiers":[
        {
            "category":"Mining & Drilling",
            "type":"Manufacturing & Wholesale Goods"
        }
    ],
    "sg:phone":"+1 601 956 2139",
    "sg:postcode":"39211",
    "sg:province":"MS",
    "sg:tags":[
        "field"
    ],
    "wof:name":"James M Nix",
    "wof:placetype":"venue"
},
  "geometry": {"coordinates":[-90.12538600000001,32.385339],"type":"Point"}
}