{
  "type": "Feature",
  "properties": {
    "addr:full":"1070 Raymond Rd Jackson MS 39204",
    "addr:housenumber":"1070",
    "addr:postcode":"39204",
    "addr:street":"Raymond Rd",
    "iso:country":"US",
    "sg:address":"1070 Raymond Rd",
    "sg:city":"Jackson",
    "sg:classifiers":[
        {
            "category":"Food & Beverages",
            "subcategory":"Groceries & Convenience Stores",
            "type":"Retail Goods"
        }
    ],
    "sg:phone":"+1 601 372 8384",
    "sg:postcode":"39204",
    "sg:province":"MS",
    "wof:name":"Mark Store",
    "wof:placetype":"venue"
},
  "geometry": {"coordinates":[-90.237906,32.284216],"type":"Point"}
}