{
  "type": "Feature",
  "properties": {
    "iso:country":"US",
    "sg:address":"1409 E Union St",
    "sg:city":"Greenville",
    "sg:classifiers":[
        {
            "category":"Wholesale",
            "subcategory":"Medical Equipment & Supplies",
            "type":"Manufacturing & Wholesale Goods"
        }
    ],
    "sg:phone":"+1 662 332 7100",
    "sg:postcode":"38703",
    "sg:province":"MS",
    "sg:tags":[
        "physician",
        "surgeon"
    ],
    "wof:name":"Norfolk Supply Co",
    "wof:placetype":"venue"
},
  "geometry": {"coordinates":[-91.035293,33.409843],"type":"Point"}
}