{
  "type": "Feature",
  "properties": {
    "iso:country":"US",
    "sg:address":"1010 Goodman Rd W",
    "sg:city":"Horn Lake",
    "sg:classifiers":[
        {
            "category":"Autos & Motor Vehicles",
            "subcategory":"Auto Supplies",
            "type":"Retail Goods"
        }
    ],
    "sg:phone":"+1 662 349 0055",
    "sg:postcode":"38637",
    "sg:province":"MS",
    "wof:name":"Gateway Tire Co Inc",
    "wof:placetype":"venue"
},
  "geometry": {"coordinates":[-90.00616599999999,34.962785],"type":"Point"}
}