{
  "type": "Feature",
  "properties": {
    "iso:country":"US",
    "sg:address":"412 E Main St",
    "sg:city":"Tupelo",
    "sg:classifiers":[
        {
            "category":"Organizations",
            "subcategory":"Professional Association",
            "type":"Services"
        }
    ],
    "sg:phone":"+1 662 840 0787",
    "sg:postcode":"38804",
    "sg:province":"MS",
    "wof:name":"Shepherd Center Of Greater Tup",
    "wof:placetype":"venue"
},
  "geometry": {"coordinates":[-88.698273,34.257395],"type":"Point"}
}