{
  "type": "Feature",
  "properties": {
    "iso:country":"US",
    "sg:address":"109 Dillard Ave",
    "sg:city":"Pelahatchie",
    "sg:classifiers":[
        {
            "category":"Organizations",
            "subcategory":"Religious Organization",
            "type":"Services"
        }
    ],
    "sg:phone":"+1 601 854 8664",
    "sg:postcode":"39145",
    "sg:province":"MS",
    "sg:tags":[
        "church"
    ],
    "wof:name":"Sweet Home Church Christ Ho",
    "wof:placetype":"venue"
},
  "geometry": {"coordinates":[-89.788962,32.316775],"type":"Point"}
}