{
  "type": "Feature",
  "properties": {
    "iso:country":"US",
    "sg:address":"201 Forrest St",
    "sg:city":"Hattiesburg",
    "sg:classifiers":[
        {
            "category":"Arts & Performance",
            "subcategory":"Theater",
            "type":"Entertainment"
        }
    ],
    "sg:phone":"+1 601 584 4888",
    "sg:postcode":"39401",
    "sg:province":"MS",
    "wof:name":"Hattiesburg Saenger Theatre",
    "wof:placetype":"venue"
},
  "geometry": {"coordinates":[-89.291192,31.32631],"type":"Point"}
}