{
  "type": "Feature",
  "properties": {
    "iso:country":"US",
    "sg:address":"6166 W Kemper St",
    "sg:city":"Bay St Louis",
    "sg:classifiers":[
        {
            "category":"Organizations",
            "subcategory":"Religious Organization",
            "type":"Services"
        }
    ],
    "sg:phone":"+1 228 467 2286",
    "sg:postcode":"39520",
    "sg:province":"MS",
    "sg:tags":[
        "church"
    ],
    "wof:name":"Church Of The Lord Jesus",
    "wof:placetype":"venue"
},
  "geometry": {"coordinates":[-89.442106,30.29051],"type":"Point"}
}