{
  "type": "Feature",
  "properties": {
    "addr:full":"3115 Periwinkle Cove Gautier MS 39553",
    "addr:housenumber":"3115",
    "addr:postcode":"39553",
    "addr:street":"Periwinkle Cove",
    "iso:country":"US",
    "sg:address":"3115 Periwinkle Cove",
    "sg:city":"Gautier",
    "sg:classifiers":[
        {
            "category":"Building & Trades",
            "subcategory":"Construction",
            "type":"Services"
        }
    ],
    "sg:phone":"+1 228 497 6046",
    "sg:postcode":"39553",
    "sg:province":"MS",
    "sg:tags":[
        "painter"
    ],
    "wof:name":"Coastal Painting & Contracting",
    "wof:placetype":"venue"
},
  "geometry": {"coordinates":[-88.660651,30.367704],"type":"Point"}
}