{
  "type": "Feature",
  "properties": {
    "iso:country":"US",
    "sg:address":"102 N Ruby Ave",
    "sg:city":"Ruleville",
    "sg:classifiers":[
        {
            "category":"Health Services",
            "subcategory":"Doctor",
            "type":"Services"
        }
    ],
    "sg:phone":"+1 662 756 0000",
    "sg:postcode":"38771",
    "sg:province":"MS",
    "sg:tags":[
        "dentist"
    ],
    "wof:name":"Ruleville Dental Clinic",
    "wof:placetype":"venue"
},
  "geometry": {"coordinates":[-90.551152,33.727017],"type":"Point"}
}