{
  "type": "Feature",
  "properties": {
    "iso:country":"US",
    "sg:address":"2061 Hwy 51",
    "sg:city":"Wesson",
    "sg:classifiers":[
        {
            "category":"Food & Beverages",
            "subcategory":"Groceries & Convenience Stores",
            "type":"Retail Goods"
        }
    ],
    "sg:phone":"+1 601 643 2996",
    "sg:postcode":"39191",
    "sg:province":"MS",
    "wof:name":"Wesson Shopping Ctr",
    "wof:placetype":"venue"
},
  "geometry": {"coordinates":[-90.404397,31.692136],"type":"Point"}
}