{
  "type": "Feature",
  "properties": {
    "iso:country":"US",
    "sg:address":"5800 Center Hill Rd",
    "sg:city":"Olive Branch",
    "sg:classifiers":[
        {
            "category":"Freight",
            "type":"Transportation"
        }
    ],
    "sg:phone":"+1 662 895 2345",
    "sg:postcode":"38654",
    "sg:province":"MS",
    "sg:tags":[
        "operator",
        "trucking"
    ],
    "wof:name":"Richard E Ingram",
    "wof:placetype":"venue"
},
  "geometry": {"coordinates":[-89.74181799999999,34.944763],"type":"Point"}
}