{
  "type": "Feature",
  "properties": {
    "iso:country":"US",
    "sg:address":"915 First East St",
    "sg:city":"Vicksburg",
    "sg:classifiers":[
        {
            "category":"Organizations",
            "subcategory":"Religious Organization",
            "type":"Services"
        }
    ],
    "sg:phone":"+1 601 638 0389",
    "sg:postcode":"39183",
    "sg:province":"MS",
    "sg:tags":[
        "church"
    ],
    "wof:name":"St Luke Church Of God",
    "wof:placetype":"venue"
},
  "geometry": {"coordinates":[-90.87879599999999,32.354874],"type":"Point"}
}