{
  "type": "Feature",
  "properties": {
    "iso:country":"US",
    "sg:address":"706 S Tate St",
    "sg:city":"Corinth",
    "sg:classifiers":[
        {
            "category":"Shopping",
            "subcategory":"Jewelry",
            "type":"Retail Goods"
        }
    ],
    "sg:phone":"+1 662 287 7229",
    "sg:postcode":"38834",
    "sg:province":"MS",
    "sg:tags":[
        "jeweler"
    ],
    "wof:name":"Jewelry Box",
    "wof:placetype":"venue"
},
  "geometry": {"coordinates":[-88.527621,34.92928],"type":"Point"}
}