{
  "type": "Feature",
  "properties": {
    "iso:country":"US",
    "sg:address":"900 N Main St",
    "sg:city":"Columbia",
    "sg:classifiers":[
        {
            "category":"Personal",
            "subcategory":"Barber",
            "type":"Services"
        }
    ],
    "sg:phone":"+1 601 731 5374",
    "sg:postcode":"39429",
    "sg:province":"MS",
    "sg:tags":[
        "shop",
        "beauty"
    ],
    "wof:name":"Jennings Hairdressers",
    "wof:placetype":"venue"
},
  "geometry": {"coordinates":[-89.835458,31.256086],"type":"Point"}
}