{
  "type": "Feature",
  "properties": {
    "addr:full":"510 E Main St New Albany MS 38652",
    "addr:housenumber":"510",
    "addr:postcode":"38652",
    "addr:street":"E Main St",
    "iso:country":"US",
    "sg:address":"510 E Main St",
    "sg:city":"New Albany",
    "sg:classifiers":[
        {
            "category":"Autos & Motor Vehicles",
            "subcategory":"Auto Supplies",
            "type":"Retail Goods"
        }
    ],
    "sg:phone":"+1 662 534 5224",
    "sg:postcode":"38652",
    "sg:province":"MS",
    "sg:tags":[
        "automobile",
        "parts"
    ],
    "wof:name":"L & S Parts Inc",
    "wof:placetype":"venue"
},
  "geometry": {"coordinates":[-89.003179,34.488305],"type":"Point"}
}