{
  "type": "Feature",
  "properties": {
    "iso:country":"US",
    "sg:address":"884 Lakeland Dr",
    "sg:city":"Jackson",
    "sg:classifiers":[
        {
            "category":"Health Services",
            "subcategory":"Health Practitioner",
            "type":"Services"
        }
    ],
    "sg:phone":"+1 601 984 6830",
    "sg:postcode":"39216",
    "sg:province":"MS",
    "wof:name":"Department of Family Medicine",
    "wof:placetype":"venue"
},
  "geometry": {"coordinates":[-90.167664,32.333911],"type":"Point"}
}