{
  "type": "Feature",
  "properties": {
    "iso:country":"US",
    "sg:address":"306 E Westbrook St",
    "sg:city":"West Point",
    "sg:classifiers":[
        {
            "category":"Organizations",
            "subcategory":"Religious Organization",
            "type":"Services"
        }
    ],
    "sg:phone":"+1 662 494 8693",
    "sg:postcode":"39773",
    "sg:province":"MS",
    "sg:tags":[
        "church"
    ],
    "wof:name":"Bryan Youth Ctr",
    "wof:placetype":"venue"
},
  "geometry": {"coordinates":[-88.648381,33.603539],"type":"Point"}
}