{
  "type": "Feature",
  "properties": {
    "iso:country":"US",
    "sg:address":"207 Industrial Dr",
    "sg:city":"Ridgeland",
    "sg:classifiers":[
        {
            "category":"Building & Trades",
            "subcategory":"Construction",
            "type":"Services"
        }
    ],
    "sg:phone":"+1 601 605 2946",
    "sg:postcode":"39157",
    "sg:province":"MS",
    "sg:tags":[
        "contractor"
    ],
    "wof:name":"Cut Technologies Southern",
    "wof:placetype":"venue"
},
  "geometry": {"coordinates":[-90.14118999999999,32.421907],"type":"Point"}
}