{
  "type": "Feature",
  "properties": {
    "iso:country":"US",
    "sg:address":"629 Dr Martin Luther King Dr N",
    "sg:city":"Canton",
    "sg:classifiers":[
        {
            "category":"Food & Beverages",
            "subcategory":"Groceries & Convenience Stores",
            "type":"Retail Goods"
        }
    ],
    "sg:phone":"+1 601 859 1096",
    "sg:postcode":"39046",
    "sg:province":"MS",
    "sg:tags":[
        "grocer"
    ],
    "wof:name":"Frey's Lane Grocery",
    "wof:placetype":"venue"
},
  "geometry": {"coordinates":[-90.040378,32.623617],"type":"Point"}
}