{
  "type": "Feature",
  "properties": {
    "addr:full":"109 S Columbia St Pontotoc MS 38863",
    "addr:housenumber":"109",
    "addr:postcode":"38863",
    "addr:street":"S Columbia St",
    "iso:country":"US",
    "sg:address":"109 S Columbia St",
    "sg:city":"Pontotoc",
    "sg:classifiers":[
        {
            "category":"Manufacturing",
            "subcategory":"Furniture",
            "type":"Manufacturing & Wholesale Goods"
        }
    ],
    "sg:phone":"+1 662 489 2227",
    "sg:postcode":"38863",
    "sg:province":"MS",
    "sg:tags":[
        "upholstered",
        "household",
        "mfg"
    ],
    "wof:name":"Southern Seating",
    "wof:placetype":"venue"
},
  "geometry": {"coordinates":[-89.009259,34.247739],"type":"Point"}
}