{
  "type": "Feature",
  "properties": {
    "iso:country":"US",
    "sg:address":"1136 Maple St",
    "sg:city":"Jackson",
    "sg:classifiers":[
        {
            "category":"Food & Beverages",
            "subcategory":"Groceries & Convenience Stores",
            "type":"Retail Goods"
        }
    ],
    "sg:phone":"+1 601 353 2639",
    "sg:postcode":"39203",
    "sg:province":"MS",
    "sg:tags":[
        "grocer"
    ],
    "wof:name":"D & D Grocery & Market",
    "wof:placetype":"venue"
},
  "geometry": {"coordinates":[-90.205748,32.316829],"type":"Point"}
}