{
  "type": "Feature",
  "properties": {
    "iso:country":"US",
    "sg:address":"1196 S Mound St",
    "sg:city":"Grenada",
    "sg:classifiers":[
        {
            "category":"Health Services",
            "subcategory":"Doctor",
            "type":"Services"
        }
    ],
    "sg:phone":"+1 662 226 2021",
    "sg:postcode":"38901",
    "sg:province":"MS",
    "sg:tags":[
        "physician",
        "clinic"
    ],
    "wof:name":"Grenada Doctor's Clinic",
    "wof:placetype":"venue"
},
  "geometry": {"coordinates":[-89.801841,33.772007],"type":"Point"}
}