{
  "type": "Feature",
  "properties": {
    "addr:full":"28073 Hwy 28 Hazlehurst MS 39083",
    "addr:housenumber":"28073",
    "addr:postcode":"39083",
    "addr:street":"Hwy 28 Hazlehurst",
    "iso:country":"US",
    "sg:address":"28073 Hwy 28",
    "sg:city":"Hazlehurst",
    "sg:classifiers":[
        {
            "category":"Restaurant",
            "type":"Food & Drink"
        }
    ],
    "sg:phone":"+1 601 894 5920",
    "sg:postcode":"39083",
    "sg:province":"MS",
    "sg:tags":[
        "eating"
    ],
    "wof:name":"KFC",
    "wof:placetype":"venue"
},
  "geometry": {"coordinates":[-90.371999,31.874529],"type":"Point"}
}