{
  "type": "Feature",
  "properties": {
    "iso:country":"US",
    "sg:address":"2839 Columbia Ave",
    "sg:city":"Prentiss",
    "sg:classifiers":[
        {
            "category":"Food & Beverages",
            "subcategory":"Groceries & Convenience Stores",
            "type":"Retail Goods"
        }
    ],
    "sg:phone":"+1 601 792 4218",
    "sg:postcode":"39474",
    "sg:province":"MS",
    "sg:tags":[
        "grocer"
    ],
    "wof:name":"Emmett Smith's Market",
    "wof:placetype":"venue"
},
  "geometry": {"coordinates":[-89.862494,31.603045],"type":"Point"}
}