{
  "type": "Feature",
  "properties": {
    "iso:country":"US",
    "sg:address":"206 W Capitol St",
    "sg:city":"Jackson",
    "sg:classifiers":[
        {
            "category":"Restaurant",
            "type":"Food & Drink"
        }
    ],
    "sg:phone":"+1 601 355 0577",
    "sg:postcode":"39201",
    "sg:province":"MS",
    "sg:tags":[
        "shop",
        "coffee"
    ],
    "wof:name":"Seven",
    "wof:placetype":"venue"
},
  "geometry": {"coordinates":[-90.19068900000001,32.300747],"type":"Point"}
}