{
  "type": "Feature",
  "properties": {
    "iso:country":"US",
    "sg:address":"706 S 2nd St",
    "sg:city":"Booneville",
    "sg:classifiers":[
        {
            "category":"Retail",
            "subcategory":"Funeral Services",
            "type":"Services"
        }
    ],
    "sg:phone":"+1 662 728 6275",
    "sg:postcode":"38829",
    "sg:province":"MS",
    "sg:tags":[
        "home"
    ],
    "wof:name":"Salts Funeral Home Inc",
    "wof:placetype":"venue"
},
  "geometry": {"coordinates":[-88.567032,34.65078],"type":"Point"}
}