{
  "type": "Feature",
  "properties": {
    "addr:full":"119 N Whitworth Ave Brookhaven MS 39601",
    "addr:housenumber":"119",
    "addr:postcode":"39601",
    "addr:street":"N Whitworth Ave",
    "iso:country":"US",
    "sg:address":"119 N Whitworth Ave",
    "sg:city":"Brookhaven",
    "sg:classifiers":[
        {
            "category":"Shopping",
            "subcategory":"Used Merchandise",
            "type":"Retail Goods"
        }
    ],
    "sg:phone":"+1 601 833 3222",
    "sg:postcode":"39601",
    "sg:province":"MS",
    "sg:tags":[
        "shop",
        "loan",
        "pawn"
    ],
    "wof:name":"Southern Pawn",
    "wof:placetype":"venue"
},
  "geometry": {"coordinates":[-90.44256900000001,31.580806],"type":"Point"}
}