{
  "type": "Feature",
  "properties": {
    "addr:full":"2001 Mabyline St Greenwood MS 38930",
    "addr:housenumber":"2001",
    "addr:postcode":"38930",
    "addr:street":"Mabyline St",
    "iso:country":"US",
    "sg:address":"2001 Mabyline St",
    "sg:city":"Greenwood",
    "sg:classifiers":[
        {
            "category":"Autos & Motor Vehicles",
            "subcategory":"Motorcycle Sales",
            "type":"Retail Goods"
        }
    ],
    "sg:phone":"+1 662 453 5646",
    "sg:postcode":"38930",
    "sg:province":"MS",
    "sg:tags":[
        "scooter"
    ],
    "wof:name":"Top Dog Powersports LLC",
    "wof:placetype":"venue"
},
  "geometry": {"coordinates":[-90.158119,33.510985],"type":"Point"}
}