{
  "type": "Feature",
  "properties": {
    "addr:full":"533 Highway 90 Bay St Louis MS 39520",
    "addr:housenumber":"533",
    "addr:postcode":"39520",
    "addr:street":"Highway 90",
    "iso:country":"US",
    "sg:address":"533 Highway 90",
    "sg:city":"Bay St Louis",
    "sg:classifiers":[
        {
            "category":"Restaurant",
            "type":"Food & Drink"
        }
    ],
    "sg:menulink":"http://www.allmenus.com/ms/fenton/155456-popeyes-chicken--biscuits/menu/",
    "sg:phone":"+1 228 467 2085",
    "sg:postcode":"39520",
    "sg:province":"MS",
    "sg:tags":[
        "american",
        "wing"
    ],
    "wof:name":"Popeye's Chicken & Biscuits",
    "wof:placetype":"venue"
},
  "geometry": {"coordinates":[-89.344792,30.317753],"type":"Point"}
}