{
  "type": "Feature",
  "properties": {
    "iso:country":"US",
    "sg:address":"2227 Old Vicksburg Rd",
    "sg:city":"Clinton",
    "sg:classifiers":[
        {
            "category":"Personal",
            "type":"Services"
        }
    ],
    "sg:phone":"+1 601 924 2212",
    "sg:postcode":"39056",
    "sg:province":"MS",
    "sg:tags":[
        "miscellaneous"
    ],
    "wof:name":"Hope Personal Care Home",
    "wof:placetype":"venue"
},
  "geometry": {"coordinates":[-90.283039,32.342951],"type":"Point"}
}