{
  "type": "Feature",
  "properties": {
    "iso:country":"US",
    "sg:address":"201 W 10th Ave",
    "sg:city":"Petal",
    "sg:classifiers":[
        {
            "category":"Health Services",
            "subcategory":"Nursing And Care Facility",
            "type":"Services"
        }
    ],
    "sg:phone":"+1 601 544 7444",
    "sg:postcode":"39465",
    "sg:province":"MS",
    "sg:tags":[
        "home",
        "convalescent"
    ],
    "wof:name":"Bedford Care Ctr",
    "wof:placetype":"venue"
},
  "geometry": {"coordinates":[-89.267071,31.331915],"type":"Point"}
}