{
  "type": "Feature",
  "properties": {
    "addr:full":"123 Shelby Speights Dr Purvis MS 39475",
    "addr:housenumber":"123",
    "addr:postcode":"39475",
    "addr:street":"Shelby Speights Dr",
    "iso:country":"US",
    "sg:address":"123 Shelby Speights Dr",
    "sg:city":"Purvis",
    "sg:classifiers":[
        {
            "category":"Restaurant",
            "type":"Food & Drink"
        }
    ],
    "sg:phone":"+1 601 744 9900",
    "sg:postcode":"39475",
    "sg:province":"MS",
    "sg:tags":[
        "delicatessen"
    ],
    "wof:name":"Jeff & Sharon Homestyle Deli",
    "wof:placetype":"venue"
},
  "geometry": {"coordinates":[-89.418251,31.143343],"type":"Point"}
}