{
  "type": "Feature",
  "properties": {
    "addr:full":"219 Robert Baggett Rd Bassfield MS 39429",
    "addr:housenumber":"219",
    "addr:postcode":"39429",
    "addr:street":"Robert Baggett Rd",
    "iso:country":"US",
    "sg:address":"219 Robert Baggett Rd",
    "sg:city":"Bassfield",
    "sg:classifiers":[
        {
            "category":"Banks & Credit Unions",
            "subcategory":"Bank",
            "type":"Services"
        }
    ],
    "sg:phone":"+1 601 943 5173",
    "sg:postcode":"39429",
    "sg:province":"MS",
    "wof:name":"Union Planters Bank",
    "wof:placetype":"venue"
},
  "geometry": {"coordinates":[-89.785285,31.241456],"type":"Point"}
}