{
  "type": "Feature",
  "properties": {
    "iso:country":"US",
    "sg:address":"962 Sullivan Dr",
    "sg:city":"Hattiesburg",
    "sg:classifiers":[
        {
            "category":"Personal",
            "type":"Services"
        }
    ],
    "sg:phone":"+1 601 583 7500",
    "sg:postcode":"39401",
    "sg:province":"MS",
    "wof:name":"Forrest City Multi Cente",
    "wof:placetype":"venue"
},
  "geometry": {"coordinates":[-89.277737,31.257481],"type":"Point"}
}