{
  "type": "Feature",
  "properties": {
    "iso:country":"US",
    "sg:address":"311 Mount Carmel Rd",
    "sg:city":"Carriere",
    "sg:classifiers":[
        {
            "category":"Government",
            "subcategory":"Fire Station",
            "type":"Public Place"
        }
    ],
    "sg:phone":"+1 601 749 8447",
    "sg:postcode":"39426",
    "sg:province":"MS",
    "sg:tags":[
        "department"
    ],
    "wof:name":"Southeast Fire Dept",
    "wof:placetype":"venue"
},
  "geometry": {"coordinates":[-89.579329,30.606052],"type":"Point"}
}