{
  "type": "Feature",
  "properties": {
    "addr:full":"2030 Beach Blvd Biloxi MS 39531",
    "addr:housenumber":"2030",
    "addr:postcode":"39531",
    "addr:street":"Beach Blvd",
    "iso:country":"US",
    "sg:address":"2030 Beach Blvd",
    "sg:city":"Biloxi",
    "sg:classifiers":[
        {
            "category":"Shopping",
            "subcategory":"Gifts & Souvenirs",
            "type":"Retail Goods"
        }
    ],
    "sg:phone":"+1 228 388 5486",
    "sg:postcode":"39531",
    "sg:province":"MS",
    "wof:name":"Bossier's Souvenirs & Beach",
    "wof:placetype":"venue"
},
  "geometry": {"coordinates":[-88.957916,30.392344],"type":"Point"}
}