{
  "type": "Feature",
  "properties": {
    "iso:country":"US",
    "sg:address":"35 Rustin Thompson Rd",
    "sg:city":"Laurel",
    "sg:classifiers":[
        {
            "category":"Farming",
            "subcategory":"Farm",
            "type":"Manufacturing & Wholesale Goods"
        }
    ],
    "sg:phone":"+1 601 649 8986",
    "sg:postcode":"39443",
    "sg:province":"MS",
    "sg:tags":[
        "crop",
        "general"
    ],
    "wof:name":"Browniee Farm",
    "wof:placetype":"venue"
},
  "geometry": {"coordinates":[-88.944847,31.76011],"type":"Point"}
}