{
  "type": "Feature",
  "properties": {
    "addr:full":"1861 Spillway Rd Brandon MS 39047",
    "addr:housenumber":"1861",
    "addr:postcode":"39047",
    "addr:street":"Spillway Rd",
    "iso:country":"US",
    "sg:address":"1861 Spillway Rd",
    "sg:city":"Brandon",
    "sg:classifiers":[
        {
            "category":"Restaurant",
            "type":"Food & Drink"
        }
    ],
    "sg:menulink":"http://www.allmenus.com/ms/fannin/199545-sonic/menu/",
    "sg:phone":"+1 601 919 8504",
    "sg:postcode":"39047",
    "sg:province":"MS",
    "sg:tags":[
        "burger",
        "american"
    ],
    "wof:name":"Sonic",
    "wof:placetype":"venue"
},
  "geometry": {"coordinates":[-90.041179,32.382428],"type":"Point"}
}