{
  "type": "Feature",
  "properties": {
    "addr:full":"705 Robb St Summit MS 39666",
    "addr:housenumber":"705",
    "addr:postcode":"39666",
    "addr:street":"Robb St",
    "iso:country":"US",
    "sg:address":"705 Robb St",
    "sg:city":"Summit",
    "sg:classifiers":[
        {
            "category":"Shopping",
            "subcategory":"Jewelry",
            "type":"Retail Goods"
        }
    ],
    "sg:phone":"+1 601 276 9400",
    "sg:postcode":"39666",
    "sg:province":"MS",
    "sg:tags":[
        "jeweler"
    ],
    "wof:name":"Ben Gilbert Inc",
    "wof:placetype":"venue"
},
  "geometry": {"coordinates":[-90.469798,31.28392],"type":"Point"}
}