{
  "type": "Feature",
  "properties": {
    "iso:country":"US",
    "sg:address":"375 Davis St",
    "sg:city":"Biloxi",
    "sg:classifiers":[
        {
            "category":"Building & Trades",
            "subcategory":"Cleaning & Sanitation",
            "type":"Services"
        }
    ],
    "sg:phone":"+1 228 374 0410",
    "sg:postcode":"39530",
    "sg:province":"MS",
    "sg:tags":[
        "janitor",
        "maintenance"
    ],
    "wof:name":"Ratliff Janitorial Svc",
    "wof:placetype":"venue"
},
  "geometry": {"coordinates":[-88.88493800000001,30.407481],"type":"Point"}
}