{
  "type": "Feature",
  "properties": {
    "addr:full":"10109 Central Ave Biloxi MS 39540",
    "addr:housenumber":"10109",
    "addr:postcode":"39540",
    "addr:street":"Central Ave",
    "iso:country":"US",
    "sg:address":"10109 Central Ave",
    "sg:city":"Biloxi",
    "sg:classifiers":[
        {
            "category":"Building & Trades",
            "subcategory":"Equipment Rental",
            "type":"Services"
        }
    ],
    "sg:phone":"+1 228 392 5412",
    "sg:postcode":"39540",
    "sg:province":"MS",
    "sg:tags":[
        "purchase",
        "leasing",
        "to",
        "rent",
        "store",
        "furniture"
    ],
    "wof:name":"Rental Express",
    "wof:placetype":"venue"
},
  "geometry": {"coordinates":[-88.89120800000001,30.430803],"type":"Point"}
}