{
  "type": "Feature",
  "properties": {
    "iso:country":"US",
    "sg:address":"3403 E Chambers Dr",
    "sg:city":"Booneville",
    "sg:classifiers":[
        {
            "category":"Autos & Motor Vehicles",
            "subcategory":"Automobile Sales",
            "type":"Retail Goods"
        }
    ],
    "sg:phone":"+1 662 728 2274",
    "sg:postcode":"38829",
    "sg:province":"MS",
    "sg:tags":[
        "car",
        "used",
        "dealer"
    ],
    "wof:name":"City Motor Co Inc",
    "wof:placetype":"venue"
},
  "geometry": {"coordinates":[-88.52874799999999,34.641171],"type":"Point"}
}