{
  "type": "Feature",
  "properties": {
    "iso:country":"US",
    "sg:address":"412 Hospital St",
    "sg:city":"Philadelphia",
    "sg:classifiers":[
        {
            "category":"Real Estate",
            "subcategory":"Real Estate Agent",
            "type":"Services"
        }
    ],
    "sg:phone":"+1 601 656 1200",
    "sg:postcode":"39350",
    "sg:province":"MS",
    "wof:name":"Joseph B Tullos",
    "wof:placetype":"venue"
},
  "geometry": {"coordinates":[-89.10226299999999,32.779662],"type":"Point"}
}