{
  "type": "Feature",
  "properties": {
    "addr:full":"165 Teagarden Rd Gulfport MS 39507",
    "addr:housenumber":"165",
    "addr:postcode":"39507",
    "addr:street":"Teagarden Rd",
    "iso:country":"US",
    "sg:address":"165 Teagarden Rd",
    "sg:city":"Gulfport",
    "sg:classifiers":[
        {
            "category":"Shopping",
            "subcategory":"Hobbies, Toys, & Games",
            "type":"Retail Goods"
        }
    ],
    "sg:phone":"+1 228 897 9788",
    "sg:postcode":"39507",
    "sg:province":"MS",
    "wof:name":"Bluewater Beads",
    "wof:placetype":"venue"
},
  "geometry": {"coordinates":[-89.03566600000001,30.383955],"type":"Point"}
}