{
  "type": "Feature",
  "properties": {
    "iso:country":"US",
    "sg:address":"12126 Hwy 63 S",
    "sg:city":"Lucedale",
    "sg:classifiers":[
        {
            "category":"Wholesale",
            "subcategory":"Tobacco Products",
            "type":"Manufacturing & Wholesale Goods"
        }
    ],
    "sg:phone":"+1 601 766 0712",
    "sg:postcode":"39452",
    "sg:province":"MS",
    "sg:tags":[
        "cigarette",
        "cigar",
        "dealer"
    ],
    "wof:name":"Tobacco Discount",
    "wof:placetype":"venue"
},
  "geometry": {"coordinates":[-88.597881,30.908832],"type":"Point"}
}