{
  "type": "Feature",
  "properties": {
    "addr:full":"231 Martin Luther King Jr Dr Holly Springs MS 38635",
    "addr:housenumber":"231",
    "addr:postcode":"38635",
    "addr:street":"Martin Luther King Jr Dr",
    "iso:country":"US",
    "sg:address":"231 Martin Luther King Jr Dr",
    "sg:city":"Holly Springs",
    "sg:classifiers":[
        {
            "category":"Personal",
            "type":"Services"
        },
        {
            "category":"Restaurant",
            "type":"Food & Drink"
        }
    ],
    "sg:phone":"+1 662 252 4144",
    "sg:postcode":"38635",
    "sg:province":"MS",
    "sg:tags":[
        "banquet",
        "rooms"
    ],
    "wof:name":"Dreamland Inc",
    "wof:placetype":"venue"
},
  "geometry": {"coordinates":[-89.451937,34.780914],"type":"Point"}
}