{
  "type": "Feature",
  "properties": {
    "iso:country":"US",
    "sg:address":"15810 Old Port Gibson Rd",
    "sg:city":"Raymond",
    "sg:classifiers":[
        {
            "category":"Building & Trades",
            "subcategory":"Construction",
            "type":"Services"
        }
    ],
    "sg:phone":"+1 601 857 5822",
    "sg:postcode":"39154",
    "sg:province":"MS",
    "sg:tags":[
        "general",
        "contractor"
    ],
    "wof:name":"Affordable Builders",
    "wof:placetype":"venue"
},
  "geometry": {"coordinates":[-90.507617,32.233131],"type":"Point"}
}