{
  "type": "Feature",
  "properties": {
    "iso:country":"US",
    "sg:address":"3011 Doby St",
    "sg:city":"Pascagoula",
    "sg:classifiers":[
        {
            "category":"Freight",
            "type":"Transportation"
        }
    ],
    "sg:phone":"+1 228 762 3498",
    "sg:postcode":"39581",
    "sg:province":"MS",
    "sg:tags":[
        "local",
        "without",
        "storage",
        "trucking"
    ],
    "wof:name":"Rufus E Hill",
    "wof:placetype":"venue"
},
  "geometry": {"coordinates":[-88.52030000000001,30.364654],"type":"Point"}
}