{
  "type": "Feature",
  "properties": {
    "iso:country":"US",
    "sg:address":"703 Monroe St",
    "sg:city":"Vicksburg",
    "sg:classifiers":[
        {
            "category":"Personal",
            "subcategory":"Beauty Salon",
            "type":"Services"
        }
    ],
    "sg:phone":"+1 601 629 2777",
    "sg:postcode":"39183",
    "sg:province":"MS",
    "sg:tags":[
        "shop"
    ],
    "wof:name":"Vivid Salon",
    "wof:placetype":"venue"
},
  "geometry": {"coordinates":[-90.87880800000001,32.355517],"type":"Point"}
}