{
  "type": "Feature",
  "properties": {
    "addr:full":"1207 Church St Port Gibson MS 39150",
    "addr:housenumber":"1207",
    "addr:postcode":"39150",
    "addr:street":"Church St",
    "iso:country":"US",
    "sg:address":"1207 Church St",
    "sg:city":"Port Gibson",
    "sg:classifiers":[
        {
            "category":"Travel",
            "subcategory":"Hotels & Motels",
            "type":"Entertainment"
        }
    ],
    "sg:phone":"+1 601 437 4350",
    "sg:postcode":"39150",
    "sg:province":"MS",
    "sg:tags":[
        "operation"
    ],
    "wof:name":"Oak Square",
    "wof:placetype":"venue"
},
  "geometry": {"coordinates":[-90.984189,31.954848],"type":"Point"}
}