{
  "type": "Feature",
  "properties": {
    "iso:country":"US",
    "sg:address":"23805 Red Bluff Rd",
    "sg:city":"Moss Point",
    "sg:classifiers":[
        {
            "category":"Building & Trades",
            "subcategory":"Plumbing",
            "type":"Services"
        }
    ],
    "sg:phone":"+1 228 588 9274",
    "sg:postcode":"39562",
    "sg:province":"MS",
    "sg:tags":[
        "plumbing",
        "contractor"
    ],
    "wof:name":"Plumb-Tech",
    "wof:placetype":"venue"
},
  "geometry": {"coordinates":[-88.45567699999999,30.684426],"type":"Point"}
}