{
  "type": "Feature",
  "properties": {
    "iso:country":"US",
    "sg:address":"7135 Hacks Cross Rd",
    "sg:city":"Olive Branch",
    "sg:classifiers":[
        {
            "category":"Personal",
            "subcategory":"Tanning Parlor",
            "type":"Services"
        }
    ],
    "sg:phone":"+1 662 895 6325",
    "sg:postcode":"38654",
    "sg:province":"MS",
    "sg:tags":[
        "salon"
    ],
    "wof:name":"Super Tans",
    "wof:placetype":"venue"
},
  "geometry": {"coordinates":[-89.795209,34.963931],"type":"Point"}
}