{
  "type": "Feature",
  "properties": {
    "iso:country":"US",
    "sg:address":"3214 New York Ave",
    "sg:city":"Pascagoula",
    "sg:classifiers":[
        {
            "category":"Education",
            "subcategory":"Special Training",
            "type":"Public Place"
        }
    ],
    "sg:phone":"+1 228 769 2916",
    "sg:postcode":"39581",
    "sg:province":"MS",
    "sg:tags":[
        "instruction",
        "music"
    ],
    "wof:name":"Rejoice School Of Music",
    "wof:placetype":"venue"
},
  "geometry": {"coordinates":[-88.526143,30.371216],"type":"Point"}
}