{
  "type": "Feature",
  "properties": {
    "iso:country":"US",
    "sg:address":"200 State Hwy 35",
    "sg:city":"Kosciusko",
    "sg:classifiers":[
        {
            "category":"Manufacturing",
            "subcategory":"Tools & Machinery",
            "type":"Manufacturing & Wholesale Goods"
        }
    ],
    "sg:phone":"+1 662 289 7510",
    "sg:postcode":"39090",
    "sg:province":"MS",
    "sg:tags":[
        "die",
        "maker"
    ],
    "wof:name":"Jaken Industries",
    "wof:placetype":"venue"
},
  "geometry": {"coordinates":[-89.569779,33.058296],"type":"Point"}
}