{
  "type": "Feature",
  "properties": {
    "iso:country":"US",
    "sg:address":"201 N Pearl St",
    "sg:city":"Natchez",
    "sg:classifiers":[
        {
            "category":"Travel",
            "subcategory":"Hotels & Motels",
            "type":"Entertainment"
        }
    ],
    "sg:phone":"+1 601 442 8848",
    "sg:postcode":"39120",
    "sg:province":"MS",
    "sg:tags":[
        "chalet",
        "rental",
        "cabin"
    ],
    "wof:name":"Garden Court Bistro",
    "wof:placetype":"venue"
},
  "geometry": {"coordinates":[-91.40249900000001,31.56101],"type":"Point"}
}