{
  "type": "Feature",
  "properties": {
    "addr:full":"12601 State Hwy 57 Ocean Springs MS 39565",
    "addr:housenumber":"12601",
    "addr:postcode":"39565",
    "addr:street":"State Hwy 57",
    "iso:country":"US",
    "sg:address":"12601 State Hwy 57",
    "sg:city":"Ocean Springs",
    "sg:classifiers":[
        {
            "category":"Food & Beverages",
            "subcategory":"Groceries & Convenience Stores",
            "type":"Retail Goods"
        }
    ],
    "sg:phone":"+1 228 826 5275",
    "sg:postcode":"39565",
    "sg:province":"MS",
    "sg:tags":[
        "grocer"
    ],
    "wof:name":"H P Davis Store",
    "wof:placetype":"venue"
},
  "geometry": {"coordinates":[-88.68762700000001,30.530437],"type":"Point"}
}