{
  "type": "Feature",
  "properties": {
    "iso:country":"US",
    "sg:address":"6818 Awini St",
    "sg:city":"Diamondhead",
    "sg:classifiers":[
        {
            "category":"Autos & Motor Vehicles",
            "subcategory":"Automobile Sales",
            "type":"Retail Goods"
        }
    ],
    "sg:phone":"+1 228 255 2046",
    "sg:postcode":"39525",
    "sg:province":"MS",
    "sg:tags":[
        "used"
    ],
    "wof:name":"Yelverton Holmes Autos LLC",
    "wof:placetype":"venue"
},
  "geometry": {"coordinates":[-89.349913,30.384625],"type":"Point"}
}