{
  "type": "Feature",
  "properties": {
    "addr:full":"50306 Old Columbus Rd Aberdeen MS 39730",
    "addr:housenumber":"50306",
    "addr:postcode":"39730",
    "addr:street":"Old Columbus Rd",
    "iso:country":"US",
    "sg:address":"50306 Old Columbus Rd",
    "sg:city":"Aberdeen",
    "sg:classifiers":[
        {
            "category":"Shopping",
            "subcategory":"Clothing, Apparel, & Fashions",
            "type":"Retail Goods"
        }
    ],
    "sg:phone":"+1 662 257 2019",
    "sg:postcode":"39730",
    "sg:province":"MS",
    "sg:tags":[
        "wear"
    ],
    "wof:name":"Childrens Shoppe",
    "wof:placetype":"venue"
},
  "geometry": {"coordinates":[-88.46614599999999,33.850964],"type":"Point"}
}