{
  "type": "Feature",
  "properties": {
    "iso:country":"US",
    "sg:address":"303 Hwy 1 S",
    "sg:city":"Greenville",
    "sg:classifiers":[
        {
            "category":"Wholesale",
            "subcategory":"Auto Parts",
            "type":"Manufacturing & Wholesale Goods"
        }
    ],
    "sg:phone":"+1 662 335 1211",
    "sg:postcode":"38701",
    "sg:province":"MS",
    "wof:name":"Jerrys Muffler Service",
    "wof:placetype":"venue"
},
  "geometry": {"coordinates":[-91.037978,33.4041],"type":"Point"}
}