{
  "type": "Feature",
  "properties": {
    "iso:country":"US",
    "sg:address":"227 Coon Hunters Rd",
    "sg:city":"Brandon",
    "sg:classifiers":[
        {
            "category":"Professional",
            "subcategory":"Management & Consulting",
            "type":"Services"
        }
    ],
    "sg:phone":"+1 601 824 4540",
    "sg:postcode":"39042",
    "sg:province":"MS",
    "sg:tags":[
        "marketing",
        "medium",
        "public",
        "relations"
    ],
    "wof:name":"N/A",
    "wof:placetype":"venue"
},
  "geometry": {"coordinates":[-89.977058,32.320265],"type":"Point"}
}