{
  "type": "Feature",
  "properties": {
    "addr:full":"690 Old Robinson Rd Louisville MS 39339",
    "addr:housenumber":"690",
    "addr:postcode":"39339",
    "addr:street":"Old Robinson Rd",
    "iso:country":"US",
    "sg:address":"690 Old Robinson Rd",
    "sg:city":"Louisville",
    "sg:classifiers":[
        {
            "category":"Organizations",
            "subcategory":"Professional Association",
            "type":"Services"
        }
    ],
    "sg:phone":"+1 662 773 3465",
    "sg:postcode":"39339",
    "sg:province":"MS",
    "sg:tags":[
        "business"
    ],
    "wof:name":"Prairie Opportunity Inc",
    "wof:placetype":"venue"
},
  "geometry": {"coordinates":[-89.079408,33.118071],"type":"Point"}
}