{
  "type": "Feature",
  "properties": {
    "addr:full":"113 Timbercrest Dr Ridgeland MS 39157",
    "addr:housenumber":"113",
    "addr:postcode":"39157",
    "addr:street":"Timbercrest Dr",
    "iso:country":"US",
    "sg:address":"113 Timbercrest Dr",
    "sg:city":"Ridgeland",
    "sg:classifiers":[
        {
            "category":"Professional",
            "subcategory":"Management & Consulting",
            "type":"Services"
        }
    ],
    "sg:phone":"+1 601 853 2929",
    "sg:postcode":"39157",
    "sg:province":"MS",
    "wof:name":"Dbr Management LLC",
    "wof:placetype":"venue"
},
  "geometry": {"coordinates":[-90.121135,32.432984],"type":"Point"}
}