{
  "type": "Feature",
  "properties": {
    "iso:country":"US",
    "sg:address":"2369 Sims Rd",
    "sg:city":"Louisville",
    "sg:classifiers":[
        {
            "category":"Building & Trades",
            "subcategory":"Construction",
            "type":"Services"
        }
    ],
    "sg:phone":"+1 662 779 2812",
    "sg:postcode":"39339",
    "sg:province":"MS",
    "sg:tags":[
        "steel",
        "erection",
        "structural"
    ],
    "wof:name":"P&S Steel Inc",
    "wof:placetype":"venue"
},
  "geometry": {"coordinates":[-89.113446,33.044654],"type":"Point"}
}