{
  "type": "Feature",
  "properties": {
    "iso:country":"US",
    "sg:address":"300 University Dr",
    "sg:city":"Starkville",
    "sg:classifiers":[
        {
            "category":"Insurance",
            "subcategory":"Insurance Agent",
            "type":"Services"
        }
    ],
    "sg:phone":"+1 662 324 9400",
    "sg:postcode":"39759",
    "sg:province":"MS",
    "wof:name":"Woodmen Of The World Insurance",
    "wof:placetype":"venue"
},
  "geometry": {"coordinates":[-88.812382,33.46384],"type":"Point"}
}