{
  "type": "Feature",
  "properties": {
    "addr:full":"1102 Constitution Ave Meridian MS 39301",
    "addr:housenumber":"1102",
    "addr:postcode":"39301",
    "addr:street":"Constitution Ave",
    "iso:country":"US",
    "sg:address":"1102 Constitution Ave",
    "sg:city":"Meridian",
    "sg:classifiers":[
        {
            "category":"Food & Beverages",
            "subcategory":"Groceries & Convenience Stores",
            "type":"Retail Goods"
        }
    ],
    "sg:phone":"+1 601 485 3072",
    "sg:postcode":"39301",
    "sg:province":"MS",
    "wof:name":"Key Field Base Exchange",
    "wof:placetype":"venue"
},
  "geometry": {"coordinates":[-88.69931800000001,32.367789],"type":"Point"}
}