{
  "type": "Feature",
  "properties": {
    "iso:country":"US",
    "sg:address":"609 S 16th St",
    "sg:city":"Oxford",
    "sg:classifiers":[
        {
            "category":"Professional",
            "subcategory":"Computer Services",
            "type":"Services"
        }
    ],
    "sg:phone":"+1 662 513 3935",
    "sg:postcode":"38655",
    "sg:province":"MS",
    "sg:tags":[
        "internet"
    ],
    "wof:name":"D 2 Interactive",
    "wof:placetype":"venue"
},
  "geometry": {"coordinates":[-89.514128,34.363199],"type":"Point"}
}