{
  "type": "Feature",
  "properties": {
    "iso:country":"US",
    "sg:address":"101 Mixon St",
    "sg:city":"Hattiesburg",
    "sg:classifiers":[
        {
            "category":"Freight",
            "type":"Transportation"
        }
    ],
    "sg:phone":"+1 601 582 8358",
    "sg:postcode":"39401",
    "sg:province":"MS",
    "sg:tags":[
        "dry",
        "bulk",
        "trucking"
    ],
    "sg:website":"www.millert.com",
    "wof:name":"Miller Transporters Inc",
    "wof:placetype":"venue"
},
  "geometry": {"coordinates":[-89.31614500000001,31.344747],"type":"Point"}
}