{
  "type": "Feature",
  "properties": {
    "iso:country":"US",
    "sg:address":"131 S Pearson Rd",
    "sg:city":"Pearl",
    "sg:classifiers":[
        {
            "category":"Retail",
            "subcategory":"Auto Repair",
            "type":"Services"
        }
    ],
    "sg:phone":"+1 601 932 6737",
    "sg:postcode":"39208",
    "sg:province":"MS",
    "sg:tags":[
        "transmission"
    ],
    "wof:name":"High Tech Transmission",
    "wof:placetype":"venue"
},
  "geometry": {"coordinates":[-90.136295,32.272639],"type":"Point"}
}