{
  "type": "Feature",
  "properties": {
    "addr:full":"143 W Cane Brake Blvd Hattiesburg MS 39402",
    "addr:housenumber":"143",
    "addr:postcode":"39402",
    "addr:street":"W Cane Brake Blvd",
    "iso:country":"US",
    "sg:address":"143 W Cane Brake Blvd",
    "sg:city":"Hattiesburg",
    "sg:classifiers":[
        {
            "category":"Professional",
            "subcategory":"Business Services",
            "type":"Services"
        }
    ],
    "sg:phone":"+1 601 264 7749",
    "sg:postcode":"39402",
    "sg:province":"MS",
    "wof:name":"Azar Enterprises LLC",
    "wof:placetype":"venue"
},
  "geometry": {"coordinates":[-89.47159499999999,31.321185],"type":"Point"}
}