{
  "type": "Feature",
  "properties": {
    "addr:full":"408 State Hwy 350 Corinth MS 38834",
    "addr:housenumber":"408",
    "addr:postcode":"38834",
    "addr:street":"State Hwy 350",
    "iso:country":"US",
    "sg:address":"408 State Hwy 350",
    "sg:city":"Corinth",
    "sg:classifiers":[
        {
            "category":"Manufacturing",
            "subcategory":"Retail Goods",
            "type":"Manufacturing & Wholesale Goods"
        }
    ],
    "sg:phone":"+1 662 286 5204",
    "sg:postcode":"38834",
    "sg:province":"MS",
    "sg:tags":[
        "manufacturer"
    ],
    "wof:name":"J Ps Industries",
    "wof:placetype":"venue"
},
  "geometry": {"coordinates":[-88.384137,34.991554],"type":"Point"}
}