{
  "type": "Feature",
  "properties": {
    "addr:full":"176 S Main St Pontotoc MS 38863",
    "addr:housenumber":"176",
    "addr:postcode":"38863",
    "addr:street":"S Main St",
    "iso:country":"US",
    "sg:address":"176 S Main St",
    "sg:city":"Pontotoc",
    "sg:classifiers":[
        {
            "category":"Health Services",
            "subcategory":"Hospital",
            "type":"Services"
        }
    ],
    "sg:phone":"+1 662 489 5510",
    "sg:postcode":"38863",
    "sg:province":"MS",
    "wof:name":"NMMC Pontotoc Hospital",
    "wof:placetype":"venue"
},
  "geometry": {"coordinates":[-88.99667100000001,34.242605],"type":"Point"}
}