{
  "type": "Feature",
  "properties": {
    "iso:country":"US",
    "sg:address":"223 Winter St",
    "sg:city":"Lucedale",
    "sg:classifiers":[
        {
            "category":"Personal",
            "subcategory":"Beauty Salon",
            "type":"Services"
        }
    ],
    "sg:phone":"+1 601 766 0102",
    "sg:postcode":"39452",
    "sg:province":"MS",
    "sg:tags":[
        "shop"
    ],
    "wof:name":"Nails With An Attitude",
    "wof:placetype":"venue"
},
  "geometry": {"coordinates":[-88.59576199999999,30.914906],"type":"Point"}
}