{
  "type": "Feature",
  "properties": {
    "addr:full":"1716 Sessums Rd Starkville MS 39759",
    "addr:housenumber":"1716",
    "addr:postcode":"39759",
    "addr:street":"Sessums Rd",
    "iso:country":"US",
    "sg:address":"1716 Sessums Rd",
    "sg:city":"Starkville",
    "sg:classifiers":[
        {
            "category":"Farming",
            "subcategory":"Berry Farm",
            "type":"Manufacturing & Wholesale Goods"
        }
    ],
    "sg:phone":"+1 662 324 1509",
    "sg:postcode":"39759",
    "sg:province":"MS",
    "sg:tags":[
        "blueberry"
    ],
    "wof:name":"Reese Orchard",
    "wof:placetype":"venue"
},
  "geometry": {"coordinates":[-88.71441,33.417323],"type":"Point"}
}