{
  "type": "Feature",
  "properties": {
    "addr:full":"1938 Baldwin Ferry Rd Vicksburg MS 39180",
    "addr:housenumber":"1938",
    "addr:postcode":"39180",
    "addr:street":"Baldwin Ferry Rd",
    "iso:country":"US",
    "sg:address":"1938 Baldwin Ferry Rd",
    "sg:city":"Vicksburg",
    "sg:classifiers":[
        {
            "category":"Shopping",
            "type":"Retail Goods"
        }
    ],
    "sg:phone":"+1 601 636 1247",
    "sg:postcode":"39180",
    "sg:province":"MS",
    "sg:tags":[
        "monument"
    ],
    "wof:name":"Delta Monument Co",
    "wof:placetype":"venue"
},
  "geometry": {"coordinates":[-90.86190499999999,32.344211],"type":"Point"}
}