{
  "type": "Feature",
  "properties": {
    "iso:country":"US",
    "sg:address":"12412 Forts Lake Rd",
    "sg:city":"Moss Point",
    "sg:classifiers":[
        {
            "category":"Organizations",
            "subcategory":"Religious Organization",
            "type":"Services"
        }
    ],
    "sg:phone":"+1 228 475 8615",
    "sg:postcode":"39562",
    "sg:province":"MS",
    "sg:tags":[
        "church"
    ],
    "wof:name":"Forts Lake Assembly Of God Chr",
    "wof:placetype":"venue"
},
  "geometry": {"coordinates":[-88.412415,30.52685],"type":"Point"}
}