{
  "type": "Feature",
  "properties": {
    "addr:full":"1976 State Hwy 43 Canton MS 39046",
    "addr:housenumber":"1976",
    "addr:postcode":"39046",
    "addr:street":"State Hwy 43",
    "iso:country":"US",
    "sg:address":"1976 State Hwy 43",
    "sg:city":"Canton",
    "sg:classifiers":[
        {
            "category":"Home & Garden",
            "subcategory":"Furniture",
            "type":"Retail Goods"
        }
    ],
    "sg:phone":"+1 601 407 1120",
    "sg:postcode":"39046",
    "sg:province":"MS",
    "wof:name":"Big Daddys Sales & Leasing",
    "wof:placetype":"venue"
},
  "geometry": {"coordinates":[-90.000778,32.61826],"type":"Point"}
}