{
  "type": "Feature",
  "properties": {
    "addr:full":"123 W Broadway St Yazoo City MS 39194",
    "addr:housenumber":"123",
    "addr:postcode":"39194",
    "addr:street":"W Broadway St",
    "iso:country":"US",
    "sg:address":"123 W Broadway St",
    "sg:city":"Yazoo City",
    "sg:classifiers":[
        {
            "category":"Shopping",
            "type":"Retail Goods"
        }
    ],
    "sg:phone":"+1 662 746 0620",
    "sg:postcode":"39194",
    "sg:province":"MS",
    "sg:tags":[
        "cosmetic",
        "perfume"
    ],
    "wof:name":"Sensational U",
    "wof:placetype":"venue"
},
  "geometry": {"coordinates":[-90.414501,32.847504],"type":"Point"}
}