{
  "type": "Feature",
  "properties": {
    "iso:country":"US",
    "sg:address":"220 Henderson Ave",
    "sg:city":"Pass Christian",
    "sg:classifiers":[
        {
            "category":"Social Services",
            "type":"Services"
        }
    ],
    "sg:phone":"+1 228 452 4190",
    "sg:postcode":"39571",
    "sg:province":"MS",
    "sg:tags":[
        "health",
        "counselor",
        "marriage",
        "family"
    ],
    "wof:name":"Bay Area Family Counselors",
    "wof:placetype":"venue"
},
  "geometry": {"coordinates":[-89.257538,30.315129],"type":"Point"}
}