{
  "type": "Feature",
  "properties": {
    "iso:country":"US",
    "sg:address":"106 S Washington St",
    "sg:city":"Starkville",
    "sg:classifiers":[
        {
            "category":"Professional",
            "subcategory":"Accounting & Tax Preparation",
            "type":"Services"
        }
    ],
    "sg:phone":"+1 662 323 1234",
    "sg:postcode":"39759",
    "sg:province":"MS",
    "sg:tags":[
        "accountant"
    ],
    "wof:name":"T E Lott & Co",
    "wof:placetype":"venue"
},
  "geometry": {"coordinates":[-88.816548,33.463758],"type":"Point"}
}