{
  "type": "Feature",
  "properties": {
    "addr:full":"3625 Hawthorn Dr Jackson MS 39216",
    "addr:housenumber":"3625",
    "addr:postcode":"39216",
    "addr:street":"Hawthorn Dr",
    "iso:country":"US",
    "sg:address":"3625 Hawthorn Dr",
    "sg:city":"Jackson",
    "sg:classifiers":[
        {
            "category":"Professional",
            "subcategory":"Employment Agencies",
            "type":"Services"
        }
    ],
    "sg:phone":"+1 601 362 4389",
    "sg:postcode":"39216",
    "sg:province":"MS",
    "sg:tags":[
        "help",
        "supply"
    ],
    "wof:name":"P 40 Warhawk Pilots Assoc",
    "wof:placetype":"venue"
},
  "geometry": {"coordinates":[-90.169888,32.340193],"type":"Point"}
}