{
  "type": "Feature",
  "properties": {
    "iso:country":"US",
    "sg:address":"5001 Chicot St",
    "sg:city":"Pascagoula",
    "sg:classifiers":[
        {
            "category":"Autos & Motor Vehicles",
            "subcategory":"Motorcycle Sales",
            "type":"Retail Goods"
        }
    ],
    "sg:phone":"+1 228 762 6300",
    "sg:postcode":"39581",
    "sg:province":"MS",
    "sg:tags":[
        "scooter"
    ],
    "wof:name":"R & J Cycle",
    "wof:placetype":"venue"
},
  "geometry": {"coordinates":[-88.52766200000001,30.381282],"type":"Point"}
}