{
  "type": "Feature",
  "properties": {
    "addr:full":"662 W Frontage Dr Wiggins MS 39577",
    "addr:housenumber":"662",
    "addr:postcode":"39577",
    "addr:street":"W Frontage Dr",
    "iso:country":"US",
    "sg:address":"662 W Frontage Dr",
    "sg:city":"Wiggins",
    "sg:classifiers":[
        {
            "category":"Government",
            "subcategory":"Office",
            "type":"Public Place"
        }
    ],
    "sg:phone":"+1 601 928 1778",
    "sg:postcode":"39577",
    "sg:province":"MS",
    "wof:name":"Us Mississippi Interagency Ctr",
    "wof:placetype":"venue"
},
  "geometry": {"coordinates":[-89.156752,30.850926],"type":"Point"}
}