{
  "type": "Feature",
  "properties": {
    "iso:country":"US",
    "sg:address":"167 Briarwood Dr",
    "sg:city":"Jackson",
    "sg:classifiers":[
        {
            "category":"Real Estate",
            "subcategory":"Real Estate Operator",
            "type":"Services"
        }
    ],
    "sg:phone":"+1 601 956 7122",
    "sg:postcode":"39206",
    "sg:province":"MS",
    "sg:tags":[
        "apartment"
    ],
    "wof:name":"Sherwood Forest Apartments",
    "wof:placetype":"venue"
},
  "geometry": {"coordinates":[-90.161025,32.380254],"type":"Point"}
}