{
  "type": "Feature",
  "properties": {
    "iso:country":"US",
    "sg:address":"4520 Hardy St",
    "sg:city":"Hattiesburg",
    "sg:classifiers":[
        {
            "category":"Restaurant",
            "type":"Food & Drink"
        }
    ],
    "sg:menulink":"http://www.allmenus.com/ms/purvis/153706-zaxbys/menu/",
    "sg:phone":"+1 601 264 5254",
    "sg:postcode":"39402",
    "sg:province":"MS",
    "sg:tags":[
        "american",
        "wing"
    ],
    "wof:name":"Zaxby's",
    "wof:placetype":"venue"
},
  "geometry": {"coordinates":[-89.357814,31.324104],"type":"Point"}
}