{
  "type": "Feature",
  "properties": {
    "iso:country":"US",
    "sg:address":"405 Beasley Rd",
    "sg:city":"Jackson",
    "sg:classifiers":[
        {
            "category":"Personal",
            "subcategory":"Beauty Salon",
            "type":"Services"
        }
    ],
    "sg:phone":"+1 601 713 0092",
    "sg:postcode":"39206",
    "sg:province":"MS",
    "sg:tags":[
        "shop"
    ],
    "wof:name":"Phase One Beauty & Barber",
    "wof:placetype":"venue"
},
  "geometry": {"coordinates":[-90.168532,32.385427],"type":"Point"}
}