{
  "type": "Feature",
  "properties": {
    "addr:full":"131 A St Brandon MS 39042",
    "addr:housenumber":"131",
    "addr:postcode":"39042",
    "addr:street":"A St",
    "iso:country":"US",
    "sg:address":"131 A St",
    "sg:city":"Brandon",
    "sg:classifiers":[
        {
            "category":"Shopping",
            "type":"Retail Goods"
        }
    ],
    "sg:phone":"+1 601 825 3365",
    "sg:postcode":"39042",
    "sg:province":"MS",
    "sg:tags":[
        "trophy",
        "engraving",
        "stamp",
        "sign",
        "rubber",
        "plaque"
    ],
    "wof:name":"Mississippi Wholesale Trophys",
    "wof:placetype":"venue"
},
  "geometry": {"coordinates":[-89.967089,32.207956],"type":"Point"}
}