{
  "type": "Feature",
  "properties": {
    "addr:full":"1130 Weems St Pearl MS 39208",
    "addr:housenumber":"1130",
    "addr:postcode":"39208",
    "addr:street":"Weems St",
    "iso:country":"US",
    "sg:address":"1130 Weems St",
    "sg:city":"Pearl",
    "sg:classifiers":[
        {
            "category":"Wholesale",
            "subcategory":"Toys & Hobbies",
            "type":"Manufacturing & Wholesale Goods"
        }
    ],
    "sg:phone":"+1 601 664 3449",
    "sg:postcode":"39208",
    "sg:province":"MS",
    "sg:tags":[
        "wholesaler"
    ],
    "wof:name":"Triangle Fastner Corp",
    "wof:placetype":"venue"
},
  "geometry": {"coordinates":[-90.13821299999999,32.248101],"type":"Point"}
}