{
  "type": "Feature",
  "properties": {
    "iso:country":"US",
    "sg:address":"126 W Central Ave",
    "sg:city":"Petal",
    "sg:classifiers":[
        {
            "category":"Professional",
            "subcategory":"Lawyer & Legal Services",
            "type":"Services"
        }
    ],
    "sg:phone":"+1 601 544 8500",
    "sg:postcode":"39465",
    "sg:province":"MS",
    "sg:tags":[
        "attorney"
    ],
    "wof:name":"Phillips Law Firm",
    "wof:placetype":"venue"
},
  "geometry": {"coordinates":[-89.267522,31.346761],"type":"Point"}
}