{
  "type": "Feature",
  "properties": {
    "iso:country":"US",
    "sg:address":"101 Main St",
    "sg:city":"Benoit",
    "sg:classifiers":[
        {
            "category":"Place Of Worship",
            "type":"Public Place"
        },
        {
            "category":"Community Center",
            "type":"Public Place"
        }
    ],
    "sg:phone":"+1 662 335 2074",
    "sg:postcode":"38725",
    "sg:province":"MS",
    "sg:tags":[
        "recreation",
        "church"
    ],
    "wof:name":"Benoit Christian Community Center",
    "wof:placetype":"venue"
},
  "geometry": {"coordinates":[-91.01486199999999,33.646696],"type":"Point"}
}