{
  "type": "Feature",
  "properties": {
    "addr:full":"2721 25th Ave Gulfport MS 39501",
    "addr:housenumber":"2721",
    "addr:postcode":"39501",
    "addr:street":"25Th Ave",
    "iso:country":"US",
    "sg:address":"2721 25th Ave",
    "sg:city":"Gulfport",
    "sg:classifiers":[
        {
            "category":"Retail",
            "subcategory":"Auto Repair",
            "type":"Services"
        }
    ],
    "sg:phone":"+1 228 864 5264",
    "sg:postcode":"39501",
    "sg:province":"MS",
    "sg:tags":[
        "automobile",
        "lubrication"
    ],
    "wof:name":"Bill's Quick Lube",
    "wof:placetype":"venue"
},
  "geometry": {"coordinates":[-89.093295,30.383773],"type":"Point"}
}