{
  "type": "Feature",
  "properties": {
    "iso:country":"US",
    "sg:address":"4909 Great River Dr",
    "sg:city":"Meridian",
    "sg:classifiers":[
        {
            "category":"Shopping",
            "subcategory":"Computers & Home Electronics",
            "type":"Retail Goods"
        }
    ],
    "sg:phone":"+1 601 482 5034",
    "sg:postcode":"39305",
    "sg:province":"MS",
    "sg:tags":[
        "equipment",
        "dealer"
    ],
    "wof:name":"Ideal Solutions",
    "wof:placetype":"venue"
},
  "geometry": {"coordinates":[-88.70670800000001,32.413804],"type":"Point"}
}