{
  "type": "Feature",
  "properties": {
    "addr:full":"756 W Cooper St Ripley MS 38663",
    "addr:housenumber":"756",
    "addr:postcode":"38663",
    "addr:street":"W Cooper St",
    "iso:country":"US",
    "sg:address":"756 W Cooper St",
    "sg:city":"Ripley",
    "sg:classifiers":[
        {
            "category":"Organizations",
            "subcategory":"Religious Organization",
            "type":"Services"
        }
    ],
    "sg:phone":"+1 662 837 8590",
    "sg:postcode":"38663",
    "sg:province":"MS",
    "wof:name":"Ripley Primitive Baptst Church",
    "wof:placetype":"venue"
},
  "geometry": {"coordinates":[-88.961271,34.73604],"type":"Point"}
}