{
  "type": "Feature",
  "properties": {
    "iso:country":"US",
    "sg:address":"6659 US Hwy 98",
    "sg:city":"Hattiesburg",
    "sg:classifiers":[
        {
            "category":"Professional",
            "subcategory":"Accounting & Tax Preparation",
            "type":"Services"
        }
    ],
    "sg:phone":"+1 601 264 5443",
    "sg:postcode":"39402",
    "sg:province":"MS",
    "sg:tags":[
        "return"
    ],
    "wof:name":"Tax Corp 93",
    "wof:placetype":"venue"
},
  "geometry": {"coordinates":[-89.428702,31.316849],"type":"Point"}
}