{
  "type": "Feature",
  "properties": {
    "iso:country":"US",
    "sg:address":"125 W Canal St",
    "sg:city":"Picayune",
    "sg:classifiers":[
        {
            "category":"Home & Garden",
            "subcategory":"Garden Supply",
            "type":"Retail Goods"
        }
    ],
    "sg:phone":"+1 601 798 6891",
    "sg:postcode":"39466",
    "sg:province":"MS",
    "sg:tags":[
        "repair"
    ],
    "wof:name":"Lawn Mower & Small Engine Svc",
    "wof:placetype":"venue"
},
  "geometry": {"coordinates":[-89.68180099999999,30.52627],"type":"Point"}
}