{
  "type": "Feature",
  "properties": {
    "iso:country":"US",
    "sg:address":"5319 Teal Dr",
    "sg:city":"Byram",
    "sg:classifiers":[
        {
            "category":"Building & Trades",
            "subcategory":"Construction",
            "type":"Services"
        }
    ],
    "sg:phone":"+1 601 316 2053",
    "sg:postcode":"39272",
    "sg:province":"MS",
    "sg:tags":[
        "restoration",
        "cleaning",
        "patio",
        "deck"
    ],
    "wof:name":"Millennium Cleaning Inc",
    "wof:placetype":"venue"
},
  "geometry": {"coordinates":[-90.254075,32.210063],"type":"Point"}
}