{
  "type": "Feature",
  "properties": {
    "iso:country":"US",
    "sg:address":"346 W Oxford St",
    "sg:city":"Pontotoc",
    "sg:classifiers":[
        {
            "category":"Banks & Credit Unions",
            "subcategory":"Bank",
            "type":"Services"
        }
    ],
    "sg:phone":"+1 662 489 7988",
    "sg:postcode":"38863",
    "sg:province":"MS",
    "sg:tags":[
        "cashing",
        "check"
    ],
    "wof:name":"Family Check Advance",
    "wof:placetype":"venue"
},
  "geometry": {"coordinates":[-89.01813300000001,34.251721],"type":"Point"}
}