{
  "type": "Feature",
  "properties": {
    "iso:country":"US",
    "sg:address":"1418 Marwood Rd",
    "sg:city":"Byram",
    "sg:classifiers":[
        {
            "category":"Bars & Pubs",
            "type":"Food & Drink"
        }
    ],
    "sg:phone":"+1 601 981 9978",
    "sg:postcode":"39272",
    "sg:province":"MS",
    "sg:tags":[
        "club",
        "night"
    ],
    "wof:name":"Recovery Room",
    "wof:placetype":"venue"
},
  "geometry": {"coordinates":[-90.28437700000001,32.205275],"type":"Point"}
}