{
  "type": "Feature",
  "properties": {
    "iso:country":"US",
    "sg:address":"238 S Pearson Rd",
    "sg:city":"Pearl",
    "sg:classifiers":[
        {
            "category":"Autos & Motor Vehicles",
            "subcategory":"Fuel & Gas Station",
            "type":"Retail Goods"
        }
    ],
    "sg:phone":"+1 601 939 2151",
    "sg:postcode":"39208",
    "sg:province":"MS",
    "sg:tags":[
        "grocery",
        "station",
        "gasoline"
    ],
    "wof:name":"Speedway 9048",
    "wof:placetype":"venue"
},
  "geometry": {"coordinates":[-90.13540999999999,32.270018],"type":"Point"}
}