{
  "type": "Feature",
  "properties": {
    "iso:country":"US",
    "sg:address":"214 Country Ln",
    "sg:city":"Columbus",
    "sg:classifiers":[
        {
            "category":"Home & Garden",
            "subcategory":"Home Furnishings",
            "type":"Retail Goods"
        }
    ],
    "sg:phone":"+1 662 327 1084",
    "sg:postcode":"39702",
    "sg:province":"MS",
    "wof:name":"Kyles Drapery",
    "wof:placetype":"venue"
},
  "geometry": {"coordinates":[-88.29325900000001,33.520974],"type":"Point"}
}