{
  "type": "Feature",
  "properties": {
    "iso:country":"US",
    "sg:address":"117 Oak St",
    "sg:city":"Greenville",
    "sg:classifiers":[
        {
            "category":"Shopping",
            "subcategory":"Used Merchandise",
            "type":"Retail Goods"
        }
    ],
    "sg:phone":"+1 662 378 9116",
    "sg:postcode":"38701",
    "sg:province":"MS",
    "sg:tags":[
        "shop",
        "consignment"
    ],
    "wof:name":"Barnett Resale Store",
    "wof:placetype":"venue"
},
  "geometry": {"coordinates":[-91.073055,33.373551],"type":"Point"}
}