{
  "type": "Feature",
  "properties": {
    "iso:country":"US",
    "sg:address":"7304 Washington Ave",
    "sg:city":"Ocean Springs",
    "sg:classifiers":[
        {
            "category":"Travel",
            "subcategory":"Hotels & Motels",
            "type":"Entertainment"
        }
    ],
    "sg:phone":"+1 228 875 7555",
    "sg:postcode":"39564",
    "sg:province":"MS",
    "wof:name":"Holiday Inn",
    "wof:placetype":"venue"
},
  "geometry": {"coordinates":[-88.84038,30.44762],"type":"Point"}
}