{
  "type": "Feature",
  "properties": {
    "addr:full":"1088 Kennebrew Rd Flora MS 39071",
    "addr:housenumber":"1088",
    "addr:postcode":"39071",
    "addr:street":"Kennebrew Rd",
    "iso:country":"US",
    "sg:address":"1088 Kennebrew Rd",
    "sg:city":"Flora",
    "sg:classifiers":[
        {
            "category":"Organizations",
            "subcategory":"Religious Organization",
            "type":"Services"
        }
    ],
    "sg:phone":"+1 601 879 3172",
    "sg:postcode":"39071",
    "sg:province":"MS",
    "sg:tags":[
        "church"
    ],
    "wof:name":"Lula Baptist Church",
    "wof:placetype":"venue"
},
  "geometry": {"coordinates":[-90.380289,32.489042],"type":"Point"}
}