{
  "type": "Feature",
  "properties": {
    "iso:country":"US",
    "sg:address":"107 Quail Field Run",
    "sg:city":"Brandon",
    "sg:classifiers":[
        {
            "category":"Building & Trades",
            "subcategory":"Plumbing",
            "type":"Services"
        }
    ],
    "sg:phone":"+1 601 824 5086",
    "sg:postcode":"39042",
    "sg:province":"MS",
    "sg:tags":[
        "contractor"
    ],
    "wof:name":"Mc Neese Mechanical Services",
    "wof:placetype":"venue"
},
  "geometry": {"coordinates":[-89.939639,32.299577],"type":"Point"}
}