{
  "type": "Feature",
  "properties": {
    "iso:country":"US",
    "sg:address":"1347 Old Hwy 82 E",
    "sg:city":"Starkville",
    "sg:classifiers":[
        {
            "category":"Home & Garden",
            "subcategory":"Carpets & Floor Coverings",
            "type":"Retail Goods"
        }
    ],
    "sg:phone":"+1 662 323 6086",
    "sg:postcode":"39759",
    "sg:province":"MS",
    "sg:tags":[
        "drape",
        "linoleum",
        "rug",
        "wallpaper",
        "dealer"
    ],
    "wof:name":"Deens Carpets and Interiors",
    "wof:placetype":"venue"
},
  "geometry": {"coordinates":[-88.75506799999999,33.474505],"type":"Point"}
}