{
  "type": "Feature",
  "properties": {
    "iso:country":"US",
    "sg:address":"2226 Bienville Blvd",
    "sg:city":"Ocean Springs",
    "sg:classifiers":[
        {
            "category":"Recreation",
            "type":"Entertainment"
        }
    ],
    "sg:phone":"+1 228 818 2830",
    "sg:postcode":"39564",
    "sg:province":"MS",
    "sg:tags":[
        "skating",
        "rink"
    ],
    "wof:name":"Skate Zone",
    "wof:placetype":"venue"
},
  "geometry": {"coordinates":[-88.80353100000001,30.415931],"type":"Point"}
}