{
  "type": "Feature",
  "properties": {
    "addr:full":"126 Somerset Dr Hattiesburg MS 39402",
    "addr:housenumber":"126",
    "addr:postcode":"39402",
    "addr:street":"Somerset Dr",
    "iso:country":"US",
    "sg:address":"126 Somerset Dr",
    "sg:city":"Hattiesburg",
    "sg:classifiers":[
        {
            "category":"Professional",
            "subcategory":"Management & Consulting",
            "type":"Services"
        }
    ],
    "sg:phone":"+1 601 268 6933",
    "sg:postcode":"39402",
    "sg:province":"MS",
    "sg:tags":[
        "business"
    ],
    "wof:name":"Soberoski Consulting LLC",
    "wof:placetype":"venue"
},
  "geometry": {"coordinates":[-89.35907899999999,31.28211],"type":"Point"}
}