{
  "type": "Feature",
  "properties": {
    "iso:country":"US",
    "sg:address":"3885 Terry Rd",
    "sg:city":"Jackson",
    "sg:classifiers":[
        {
            "category":"Organizations",
            "subcategory":"Religious Organization",
            "type":"Services"
        }
    ],
    "sg:phone":"+1 601 502 1273",
    "sg:postcode":"39212",
    "sg:province":"MS",
    "sg:tags":[
        "church"
    ],
    "wof:name":"True Gospel Intl Church",
    "wof:placetype":"venue"
},
  "geometry": {"coordinates":[-90.23854900000001,32.226425],"type":"Point"}
}