{
  "type": "Feature",
  "properties": {
    "addr:full":"19 Graham Rd Hattiesburg MS 39482",
    "addr:housenumber":"19",
    "addr:postcode":"39482",
    "addr:street":"Graham Rd",
    "iso:country":"US",
    "sg:address":"19 Graham Rd",
    "sg:city":"Hattiesburg",
    "sg:classifiers":[
        {
            "category":"Real Estate",
            "subcategory":"Real Estate Agent",
            "type":"Services"
        }
    ],
    "sg:phone":"+1 601 268 3790",
    "sg:postcode":"39482",
    "sg:province":"MS",
    "wof:name":"Kevin Graham Properties LLC",
    "wof:placetype":"venue"
},
  "geometry": {"coordinates":[-89.484906,31.310454],"type":"Point"}
}