{
  "type": "Feature",
  "properties": {
    "addr:full":"2198 Alice Dr Biloxi MS 39531",
    "addr:housenumber":"2198",
    "addr:postcode":"39531",
    "addr:street":"Alice Dr",
    "iso:country":"US",
    "sg:address":"2198 Alice Dr",
    "sg:city":"Biloxi",
    "sg:classifiers":[
        {
            "category":"Restaurant",
            "type":"Food & Drink"
        }
    ],
    "sg:phone":"+1 228 388 6274",
    "sg:postcode":"39531",
    "sg:province":"MS",
    "sg:tags":[
        "catering"
    ],
    "wof:name":"Galarza Catering",
    "wof:placetype":"venue"
},
  "geometry": {"coordinates":[-88.96611799999999,30.407308],"type":"Point"}
}