{
  "type": "Feature",
  "properties": {
    "addr:full":"1615 Westward Dr Gulfport MS 39501",
    "addr:housenumber":"1615",
    "addr:postcode":"39501",
    "addr:street":"Westward Dr",
    "iso:country":"US",
    "sg:address":"1615 Westward Dr",
    "sg:city":"Gulfport",
    "sg:classifiers":[
        {
            "category":"Professional",
            "subcategory":"Computer Services",
            "type":"Services"
        }
    ],
    "sg:phone":"+1 228 871 5672",
    "sg:postcode":"39501",
    "sg:province":"MS",
    "sg:tags":[
        "related"
    ],
    "wof:name":"Everything Computers & Communi",
    "wof:placetype":"venue"
},
  "geometry": {"coordinates":[-89.106754,30.371291],"type":"Point"}
}