{
  "type": "Feature",
  "properties": {
    "iso:country":"US",
    "sg:address":"5710 Liberty Church Rd",
    "sg:city":"Newton",
    "sg:classifiers":[
        {
            "category":"Food & Beverages",
            "subcategory":"Specialty",
            "type":"Retail Goods"
        }
    ],
    "sg:phone":"+1 601 683 2565",
    "sg:postcode":"39345",
    "sg:province":"MS",
    "wof:name":"Allstar Marketing",
    "wof:placetype":"venue"
},
  "geometry": {"coordinates":[-89.08738700000001,32.243671],"type":"Point"}
}