{
  "type": "Feature",
  "properties": {
    "iso:country":"US",
    "sg:address":"2298 Land Rd",
    "sg:city":"Columbus",
    "sg:classifiers":[
        {
            "category":"Food & Beverages",
            "subcategory":"Groceries & Convenience Stores",
            "type":"Retail Goods"
        }
    ],
    "sg:phone":"+1 662 434 8686",
    "sg:postcode":"39705",
    "sg:province":"MS",
    "wof:name":"Land Road Quick Stop",
    "wof:placetype":"venue"
},
  "geometry": {"coordinates":[-88.41955,33.62334],"type":"Point"}
}