{
  "type": "Feature",
  "properties": {
    "addr:full":"103 Access Rd Fulton MS 38843",
    "addr:housenumber":"103",
    "addr:postcode":"38843",
    "addr:street":"Access Rd",
    "iso:country":"US",
    "sg:address":"103 Access Rd",
    "sg:city":"Fulton",
    "sg:classifiers":[
        {
            "category":"Personal",
            "subcategory":"Beauty Salon",
            "type":"Services"
        }
    ],
    "sg:phone":"+1 662 862 3130",
    "sg:postcode":"38843",
    "sg:province":"MS",
    "sg:tags":[
        "shop"
    ],
    "wof:name":"Pat's Place",
    "wof:placetype":"venue"
},
  "geometry": {"coordinates":[-88.404245,34.245699],"type":"Point"}
}