{
  "type": "Feature",
  "properties": {
    "iso:country":"US",
    "sg:address":"1683 S Green St",
    "sg:city":"Tupelo",
    "sg:classifiers":[
        {
            "category":"Wholesale",
            "subcategory":"Stationery",
            "type":"Manufacturing & Wholesale Goods"
        }
    ],
    "sg:phone":"+1 662 680 5060",
    "sg:postcode":"38804",
    "sg:province":"MS",
    "sg:tags":[
        "packaging",
        "material"
    ],
    "wof:name":"Rusken Packaging Inc",
    "wof:placetype":"venue"
},
  "geometry": {"coordinates":[-88.71106399999999,34.234526],"type":"Point"}
}