{
  "type": "Feature",
  "properties": {
    "iso:country":"US",
    "sg:address":"700 N Clark Ave",
    "sg:city":"Magnolia",
    "sg:classifiers":[
        {
            "category":"Insurance",
            "subcategory":"Insurance Agent",
            "type":"Services"
        }
    ],
    "sg:phone":"+1 601 783 2881",
    "sg:postcode":"39652",
    "sg:province":"MS",
    "wof:name":"Winns Insurance Agency",
    "wof:placetype":"venue"
},
  "geometry": {"coordinates":[-90.45743899999999,31.152739],"type":"Point"}
}