{
  "type": "Feature",
  "properties": {
    "addr:full":"381 Hwy 51 S Batesville MS 38620",
    "addr:housenumber":"381",
    "addr:postcode":"38620",
    "addr:street":"Hwy 51 S Batesville",
    "iso:country":"US",
    "sg:address":"381 Hwy 51 S",
    "sg:city":"Batesville",
    "sg:classifiers":[
        {
            "category":"Government",
            "subcategory":"Office",
            "type":"Public Place"
        }
    ],
    "sg:phone":"+1 662 563 4616",
    "sg:postcode":"38620",
    "sg:province":"MS",
    "sg:tags":[
        "administrative",
        "program",
        "health"
    ],
    "wof:name":"Panola County Health Dept",
    "wof:placetype":"venue"
},
  "geometry": {"coordinates":[-89.945821,34.304394],"type":"Point"}
}