{
  "type": "Feature",
  "properties": {
    "iso:country":"US",
    "sg:address":"647 US Hwy 51",
    "sg:city":"Ridgeland",
    "sg:classifiers":[
        {
            "category":"Personal",
            "type":"Services"
        },
        {
            "category":"Professional",
            "subcategory":"Management & Consulting",
            "type":"Services"
        }
    ],
    "sg:phone":"+1 601 856 5296",
    "sg:postcode":"39157",
    "sg:province":"MS",
    "sg:tags":[
        "party"
    ],
    "wof:name":"Play Place The",
    "wof:placetype":"venue"
},
  "geometry": {"coordinates":[-90.128355,32.429088],"type":"Point"}
}