{
  "type": "Feature",
  "properties": {
    "addr:full":"357 Morton Ave Pass Christian MS 39571",
    "addr:housenumber":"357",
    "addr:postcode":"39571",
    "addr:street":"Morton Ave",
    "iso:country":"US",
    "sg:address":"357 Morton Ave",
    "sg:city":"Pass Christian",
    "sg:classifiers":[
        {
            "category":"Building & Trades",
            "subcategory":"Landscaping Services",
            "type":"Services"
        }
    ],
    "sg:phone":"+1 228 452 4590",
    "sg:postcode":"39571",
    "sg:province":"MS",
    "sg:tags":[
        "landscape"
    ],
    "wof:name":"Dedeaux Construction",
    "wof:placetype":"venue"
},
  "geometry": {"coordinates":[-89.24115399999999,30.323449],"type":"Point"}
}