{
  "type": "Feature",
  "properties": {
    "addr:full":"450 Shady Dr Yazoo City MS 39194",
    "addr:housenumber":"450",
    "addr:postcode":"39194",
    "addr:street":"Shady Dr",
    "iso:country":"US",
    "sg:address":"450 Shady Dr",
    "sg:city":"Yazoo City",
    "sg:classifiers":[
        {
            "category":"Food & Beverages",
            "subcategory":"Groceries & Convenience Stores",
            "type":"Retail Goods"
        }
    ],
    "sg:phone":"+1 662 746 7664",
    "sg:postcode":"39194",
    "sg:province":"MS",
    "sg:tags":[
        "grocer"
    ],
    "wof:name":"Neighborhood Grocery & Diner",
    "wof:placetype":"venue"
},
  "geometry": {"coordinates":[-90.414596,32.864175],"type":"Point"}
}