{
  "type": "Feature",
  "properties": {
    "iso:country":"US",
    "sg:address":"12394 Cypress Dr",
    "sg:city":"Gulfport",
    "sg:classifiers":[
        {
            "category":"Shopping",
            "subcategory":"Used Merchandise",
            "type":"Retail Goods"
        }
    ],
    "sg:phone":"+1 228 832 6017",
    "sg:postcode":"39503",
    "sg:province":"MS",
    "sg:tags":[
        "antique"
    ],
    "sg:website":"www.dearheartsantiques.com",
    "wof:name":"Dear Heart Creations & Collect",
    "wof:placetype":"venue"
},
  "geometry": {"coordinates":[-89.098674,30.467288],"type":"Point"}
}