{
  "type": "Feature",
  "properties": {
    "iso:country":"US",
    "sg:address":"1604 US Hwy 90",
    "sg:city":"Gautier",
    "sg:classifiers":[
        {
            "category":"Shopping",
            "subcategory":"Gifts & Souvenirs",
            "type":"Retail Goods"
        }
    ],
    "sg:phone":"+1 228 497 5872",
    "sg:postcode":"39553",
    "sg:province":"MS",
    "sg:tags":[
        "stationery",
        "merchandise"
    ],
    "wof:name":"School & Carnival Supply Inc",
    "wof:placetype":"venue"
},
  "geometry": {"coordinates":[-88.635182,30.389212],"type":"Point"}
}