{
  "type": "Feature",
  "properties": {
    "iso:country":"US",
    "sg:address":"2682 N Hills St",
    "sg:city":"Meridian",
    "sg:classifiers":[
        {
            "category":"Restaurant",
            "type":"Food & Drink"
        }
    ],
    "sg:phone":"+1 601 484 6333",
    "sg:postcode":"39305",
    "sg:province":"MS",
    "sg:tags":[
        "style",
        "mexican",
        "american",
        "family"
    ],
    "wof:name":"El Norte Mexican Restaurant",
    "wof:placetype":"venue"
},
  "geometry": {"coordinates":[-88.70584700000001,32.409027],"type":"Point"}
}