{
  "type": "Feature",
  "properties": {
    "iso:country":"US",
    "sg:address":"528 Klondyke Rd",
    "sg:city":"Long Beach",
    "sg:classifiers":[
        {
            "category":"Professional",
            "type":"Services"
        }
    ],
    "sg:phone":"+1 228 864 7724",
    "sg:postcode":"39560",
    "sg:province":"MS",
    "wof:name":"National Pizza Co",
    "wof:placetype":"venue"
},
  "geometry": {"coordinates":[-89.153237,30.365776],"type":"Point"}
}