{
  "type": "Feature",
  "properties": {
    "addr:full":"58 Co Rd 4070 Marietta MS 38856",
    "addr:housenumber":"58",
    "addr:postcode":"4070;38856",
    "addr:street":"Co Rd",
    "iso:country":"US",
    "sg:address":"58 Co Rd 4070",
    "sg:city":"Marietta",
    "sg:classifiers":[
        {
            "category":"Social Services",
            "subcategory":"Child Care",
            "type":"Services"
        }
    ],
    "sg:phone":"+1 662 728 2267",
    "sg:postcode":"38856",
    "sg:province":"MS",
    "wof:name":"Marietta Day Care Ctr",
    "wof:placetype":"venue"
},
  "geometry": {"coordinates":[-88.46490799999999,34.497194],"type":"Point"}
}