{
  "type": "Feature",
  "properties": {
    "addr:full":"9506 Creosote Rd Gulfport MS 39503",
    "addr:housenumber":"9506",
    "addr:postcode":"39503",
    "addr:street":"Creosote Rd",
    "iso:country":"US",
    "sg:address":"9506 Creosote Rd",
    "sg:city":"Gulfport",
    "sg:classifiers":[
        {
            "category":"Wholesale",
            "subcategory":"Machinery & Supplies",
            "type":"Manufacturing & Wholesale Goods"
        }
    ],
    "sg:phone":"+1 228 864 0086",
    "sg:postcode":"39503",
    "sg:province":"MS",
    "sg:tags":[
        "equipment",
        "industrial"
    ],
    "sg:website":"www.gulfportindustrial.com",
    "wof:name":"Gulfport Industrial Supply Co",
    "wof:placetype":"venue"
},
  "geometry": {"coordinates":[-89.077618,30.426465],"type":"Point"}
}