{
  "type": "Feature",
  "properties": {
    "iso:country":"US",
    "sg:address":"255 Twin Lakes Dr",
    "sg:city":"Canton",
    "sg:classifiers":[
        {
            "category":"Personal",
            "type":"Services"
        }
    ],
    "sg:phone":"+1 601 624 3596",
    "sg:postcode":"39046",
    "sg:province":"MS",
    "wof:name":"Essential Body Therapies",
    "wof:placetype":"venue"
},
  "geometry": {"coordinates":[-89.981905,32.537877],"type":"Point"}
}