{
  "type": "Feature",
  "properties": {
    "addr:full":"4919 Denny Ave Pascagoula MS 39581",
    "addr:housenumber":"4919",
    "addr:postcode":"39581",
    "addr:street":"Denny Ave",
    "iso:country":"US",
    "sg:address":"4919 Denny Ave",
    "sg:city":"Pascagoula",
    "sg:classifiers":[
        {
            "category":"Travel",
            "subcategory":"Hotels & Motels",
            "type":"Entertainment"
        }
    ],
    "sg:phone":"+1 228 762 9414",
    "sg:postcode":"39581",
    "sg:province":"MS",
    "sg:tags":[
        "operation"
    ],
    "wof:name":"Super 8 Motel",
    "wof:placetype":"venue"
},
  "geometry": {"coordinates":[-88.52646300000001,30.378681],"type":"Point"}
}