{
  "type": "Feature",
  "properties": {
    "iso:country":"US",
    "sg:address":"2505 Bethel Rd",
    "sg:city":"Starkville",
    "sg:classifiers":[
        {
            "category":"Building & Trades",
            "subcategory":"Construction",
            "type":"Services"
        }
    ],
    "sg:phone":"+1 662 324 7478",
    "sg:postcode":"39759",
    "sg:province":"MS",
    "sg:tags":[
        "nonresidential"
    ],
    "wof:name":"S&J Enterprise",
    "wof:placetype":"venue"
},
  "geometry": {"coordinates":[-88.817536,33.370371],"type":"Point"}
}