{
  "type": "Feature",
  "properties": {
    "iso:country":"US",
    "sg:address":"1047 Lyles Ln",
    "sg:city":"Raymond",
    "sg:classifiers":[
        {
            "category":"Professional",
            "subcategory":"Business Services",
            "type":"Services"
        }
    ],
    "sg:phone":"+1 601 372 4033",
    "sg:postcode":"39154",
    "sg:province":"MS",
    "sg:tags":[
        "equipment"
    ],
    "wof:name":"Capitol Pool Service",
    "wof:placetype":"venue"
},
  "geometry": {"coordinates":[-90.331369,32.290731],"type":"Point"}
}