{
  "type": "Feature",
  "properties": {
    "iso:country":"US",
    "sg:address":"215 Co Rd 144",
    "sg:city":"Iuka",
    "sg:classifiers":[
        {
            "category":"Retail",
            "subcategory":"Repair Shop",
            "type":"Services"
        }
    ],
    "sg:phone":"+1 662 424 0292",
    "sg:postcode":"38852",
    "sg:province":"MS",
    "wof:name":"Coxes Garage",
    "wof:placetype":"venue"
},
  "geometry": {"coordinates":[-88.201808,34.70677],"type":"Point"}
}