{
  "type": "Feature",
  "properties": {
    "addr:full":"1180 Windrose Cir Madison MS 39110",
    "addr:housenumber":"1180",
    "addr:postcode":"39110",
    "addr:street":"Windrose Cir",
    "iso:country":"US",
    "sg:address":"1180 Windrose Cir",
    "sg:city":"Madison",
    "sg:classifiers":[
        {
            "category":"Autos & Motor Vehicles",
            "subcategory":"Automobile Sales",
            "type":"Retail Goods"
        }
    ],
    "sg:phone":"+1 601 853 7786",
    "sg:postcode":"39110",
    "sg:province":"MS",
    "sg:tags":[
        "new",
        "used",
        "car"
    ],
    "wof:name":"Brook Ole Motors Inc",
    "wof:placetype":"venue"
},
  "geometry": {"coordinates":[-90.09880800000001,32.466789],"type":"Point"}
}