{
  "type": "Feature",
  "properties": {
    "addr:full":"208 N Main St Poplarville MS 39470",
    "addr:housenumber":"208",
    "addr:postcode":"39470",
    "addr:street":"N Main St",
    "iso:country":"US",
    "sg:address":"208 N Main St",
    "sg:city":"Poplarville",
    "sg:classifiers":[
        {
            "category":"Food & Beverages",
            "subcategory":"Groceries & Convenience Stores",
            "type":"Retail Goods"
        }
    ],
    "sg:phone":"+1 601 795 6655",
    "sg:postcode":"39470",
    "sg:province":"MS",
    "sg:tags":[
        "grocer"
    ],
    "wof:name":"Super Salvage",
    "wof:placetype":"venue"
},
  "geometry": {"coordinates":[-89.535596,30.845714],"type":"Point"}
}