{
  "type": "Feature",
  "properties": {
    "iso:country":"US",
    "sg:address":"3550 Hwy 468",
    "sg:city":"Pearl",
    "sg:classifiers":[
        {
            "category":"Health Services",
            "subcategory":"Hospital",
            "type":"Services"
        }
    ],
    "sg:phone":"+1 601 351 8000",
    "sg:postcode":"39208",
    "sg:province":"MS",
    "wof:name":"Mississippi State Hospital",
    "wof:placetype":"venue"
},
  "geometry": {"coordinates":[-90.08838799999999,32.236084],"type":"Point"}
}