{
  "type": "Feature",
  "properties": {
    "iso:country":"US",
    "sg:address":"4803 29th Ave",
    "sg:city":"Meridian",
    "sg:classifiers":[
        {
            "category":"Retail",
            "subcategory":"Laundry & Dry Cleaning",
            "type":"Services"
        }
    ],
    "sg:phone":"+1 601 693 0560",
    "sg:postcode":"39305",
    "sg:province":"MS",
    "sg:tags":[
        "cleaners"
    ],
    "wof:name":"Troy Laundry & Cleaners",
    "wof:placetype":"venue"
},
  "geometry": {"coordinates":[-88.707965,32.406295],"type":"Point"}
}