{
  "type": "Feature",
  "properties": {
    "iso:country":"US",
    "sg:address":"766 N Lamar Blvd",
    "sg:city":"Oxford",
    "sg:classifiers":[
        {
            "category":"Retail",
            "subcategory":"Car Wash",
            "type":"Services"
        },
        {
            "category":"Retail",
            "subcategory":"Auto Repair",
            "type":"Services"
        }
    ],
    "sg:phone":"+1 662 234 0617",
    "sg:postcode":"38655",
    "sg:province":"MS",
    "sg:tags":[
        "carwash",
        "automotive",
        "polishing",
        "washing",
        "general"
    ],
    "wof:name":"Ultimate Auto Center",
    "wof:placetype":"venue"
},
  "geometry": {"coordinates":[-89.516597,34.373466],"type":"Point"}
}