{
  "type": "Feature",
  "properties": {
    "iso:country":"US",
    "sg:address":"1799 Pass Rd",
    "sg:city":"Gulfport",
    "sg:classifiers":[
        {
            "category":"Retail",
            "subcategory":"Repair Shop",
            "type":"Services"
        }
    ],
    "sg:phone":"+1 228 864 2011",
    "sg:postcode":"39501",
    "sg:province":"MS",
    "sg:tags":[
        "machine",
        "copying"
    ],
    "wof:name":"Welchs Office Machine",
    "wof:placetype":"venue"
},
  "geometry": {"coordinates":[-89.08301899999999,30.38035],"type":"Point"}
}