{
  "type": "Feature",
  "properties": {
    "addr:full":"711 Farmer St Port Gibson MS 39150",
    "addr:housenumber":"711",
    "addr:postcode":"39150",
    "addr:street":"Farmer St",
    "iso:country":"US",
    "sg:address":"711 Farmer St",
    "sg:city":"Port Gibson",
    "sg:classifiers":[
        {
            "category":"Shopping",
            "subcategory":"Optical Goods",
            "type":"Retail Goods"
        },
        {
            "category":"Health Services",
            "subcategory":"Optometrist",
            "type":"Services"
        }
    ],
    "sg:phone":"+1 601 437 5701",
    "sg:postcode":"39150",
    "sg:province":"MS",
    "wof:name":"Doherty Vision Clinic Inc",
    "wof:placetype":"venue"
},
  "geometry": {"coordinates":[-90.983405,31.959785],"type":"Point"}
}