{
  "type": "Feature",
  "properties": {
    "addr:full":"739 E Pass Rd Gulfport MS 39507",
    "addr:housenumber":"739",
    "addr:postcode":"39507",
    "addr:street":"E Pass Rd",
    "iso:country":"US",
    "sg:address":"739 E Pass Rd",
    "sg:city":"Gulfport",
    "sg:classifiers":[
        {
            "category":"Autos & Motor Vehicles",
            "subcategory":"Automobile Sales",
            "type":"Retail Goods"
        }
    ],
    "sg:phone":"+1 228 604 0058",
    "sg:postcode":"39507",
    "sg:province":"MS",
    "sg:tags":[
        "car",
        "dealer"
    ],
    "wof:name":"Best Buy Auto Sales",
    "wof:placetype":"venue"
},
  "geometry": {"coordinates":[-89.038017,30.395666],"type":"Point"}
}