{
  "type": "Feature",
  "properties": {
    "iso:country":"US",
    "sg:address":"512 N Vardaman St",
    "sg:city":"Wiggins",
    "sg:classifiers":[
        {
            "category":"Insurance",
            "subcategory":"Insurance Agent",
            "type":"Services"
        }
    ],
    "sg:phone":"+1 601 928 3683",
    "sg:postcode":"39577",
    "sg:province":"MS",
    "wof:name":"State Farm Insurance",
    "wof:placetype":"venue"
},
  "geometry": {"coordinates":[-89.139596,30.864993],"type":"Point"}
}