{
  "type": "Feature",
  "properties": {
    "iso:country":"US",
    "sg:address":"995 S College St",
    "sg:city":"Brandon",
    "sg:classifiers":[
        {
            "category":"Organizations",
            "subcategory":"Religious Organization",
            "type":"Services"
        }
    ],
    "sg:phone":"+1 601 825 8188",
    "sg:postcode":"39042",
    "sg:province":"MS",
    "wof:name":"Brandon Assembly Of God",
    "wof:placetype":"venue"
},
  "geometry": {"coordinates":[-89.989192,32.267181],"type":"Point"}
}