{
  "type": "Feature",
  "properties": {
    "iso:country":"US",
    "sg:address":"12 Roselawn Dr",
    "sg:city":"Natchez",
    "sg:classifiers":[
        {
            "category":"Building & Trades",
            "subcategory":"Construction",
            "type":"Services"
        }
    ],
    "sg:phone":"+1 601 446 8224",
    "sg:postcode":"39120",
    "sg:province":"MS",
    "sg:tags":[
        "contractor"
    ],
    "wof:name":"Kl Jones Masonry Construc",
    "wof:placetype":"venue"
},
  "geometry": {"coordinates":[-91.383409,31.547321],"type":"Point"}
}