{
  "type": "Feature",
  "properties": {
    "addr:full":"1805 Hwy 15 N Ripley MS 38663",
    "addr:housenumber":"1805",
    "addr:postcode":"38663",
    "addr:street":"Hwy 15 N",
    "iso:country":"US",
    "sg:address":"1805 Hwy 15 N",
    "sg:city":"Ripley",
    "sg:phone":"+1 662 837 8198",
    "sg:postcode":"38663",
    "sg:province":"MS",
    "sg:tags":[
        "gas"
    ],
    "wof:name":"Rebel LP Gas Inc",
    "wof:placetype":"venue"
},
  "geometry": {"coordinates":[-88.938513,34.760874],"type":"Point"}
}