{
  "type": "Feature",
  "properties": {
    "iso:country":"US",
    "sg:address":"5268 Old Hwy 11",
    "sg:city":"Hattiesburg",
    "sg:classifiers":[
        {
            "category":"Shopping",
            "subcategory":"Gifts & Souvenirs",
            "type":"Retail Goods"
        }
    ],
    "sg:phone":"+1 601 264 1227",
    "sg:postcode":"39402",
    "sg:province":"MS",
    "sg:tags":[
        "shop"
    ],
    "wof:name":"Perfect Gift Shop",
    "wof:placetype":"venue"
},
  "geometry": {"coordinates":[-89.410398,31.310823],"type":"Point"}
}