{
  "type": "Feature",
  "properties": {
    "iso:country":"US",
    "sg:address":"1101 Co Rd 16",
    "sg:city":"Myrtle",
    "sg:classifiers":[
        {
            "category":"Building & Trades",
            "subcategory":"Construction",
            "type":"Services"
        }
    ],
    "sg:phone":"+1 662 534 3513",
    "sg:postcode":"38650",
    "sg:province":"MS",
    "sg:tags":[
        "kitchen",
        "build",
        "cabinet"
    ],
    "wof:name":"Bill Wooten Cabinets",
    "wof:placetype":"venue"
},
  "geometry": {"coordinates":[-89.163003,34.467243],"type":"Point"}
}