{
  "type": "Feature",
  "properties": {
    "addr:full":"4560 Venture Dr Southaven MS 38671",
    "addr:housenumber":"4560",
    "addr:postcode":"38671",
    "addr:street":"Venture Dr",
    "iso:country":"US",
    "sg:address":"4560 Venture Dr",
    "sg:city":"Southaven",
    "sg:classifiers":[
        {
            "category":"Arena",
            "subcategory":"Sports Club",
            "type":"Entertainment"
        },
        {
            "category":"Landmark",
            "subcategory":"Tourist Information",
            "type":"Public Place"
        }
    ],
    "sg:phone":"+1 662 342 1755",
    "sg:postcode":"38671",
    "sg:province":"MS",
    "sg:tags":[
        "attraction",
        "ticket",
        "sale"
    ],
    "sg:website":"http://www.riverkings.com",
    "wof:name":"River Kings",
    "wof:placetype":"venue"
},
  "geometry": {"coordinates":[-89.99919800000001,34.928399],"type":"Point"}
}