{
  "type": "Feature",
  "properties": {
    "addr:full":"2469 Livingston Rd Jackson MS 39213",
    "addr:housenumber":"2469",
    "addr:postcode":"39213",
    "addr:street":"Livingston Rd",
    "iso:country":"US",
    "sg:address":"2469 Livingston Rd",
    "sg:city":"Jackson",
    "sg:classifiers":[
        {
            "category":"Shopping",
            "subcategory":"Beauty & Cosmetics",
            "type":"Retail Goods"
        }
    ],
    "sg:phone":"+1 601 362 9118",
    "sg:postcode":"39213",
    "sg:province":"MS",
    "sg:tags":[
        "supply"
    ],
    "wof:name":"Hair Plus",
    "wof:placetype":"venue"
},
  "geometry": {"coordinates":[-90.197003,32.33],"type":"Point"}
}