{
  "type": "Feature",
  "properties": {
    "addr:full":"3989 Chesapeake Way Memphis MS 38125",
    "addr:housenumber":"3989",
    "addr:postcode":"38125",
    "addr:street":"Chesapeake Way",
    "iso:country":"US",
    "sg:address":"3989 Chesapeake Way",
    "sg:city":"Memphis",
    "sg:classifiers":[
        {
            "category":"Building & Trades",
            "subcategory":"Landscaping Services",
            "type":"Services"
        }
    ],
    "sg:phone":"+1 901 737 6980",
    "sg:postcode":"38125",
    "sg:province":"MS",
    "sg:tags":[
        "lawn",
        "maintenance",
        "grounds"
    ],
    "wof:name":"Landscape Pest Management",
    "wof:placetype":"venue"
},
  "geometry": {"coordinates":[-89.82903399999999,35.038405],"type":"Point"}
}