{
  "type": "Feature",
  "properties": {
    "addr:full":"2012 US Hwy 90 Gautier MS 39553",
    "addr:housenumber":"2012",
    "addr:postcode":"39553",
    "addr:street":"Us Hwy 90",
    "iso:country":"US",
    "sg:address":"2012 US Hwy 90",
    "sg:city":"Gautier",
    "sg:classifiers":[
        {
            "category":"Professional",
            "subcategory":"Engineering",
            "type":"Services"
        }
    ],
    "sg:phone":"+1 228 522 3939",
    "sg:postcode":"39553",
    "sg:province":"MS",
    "sg:tags":[
        "information",
        "management",
        "technology",
        "consult"
    ],
    "wof:name":"Anteon Corporation (va)",
    "wof:placetype":"venue"
},
  "geometry": {"coordinates":[-88.641863,30.390527],"type":"Point"}
}