{
  "type": "Feature",
  "properties": {
    "iso:country":"US",
    "sg:address":"104 Depot Ave",
    "sg:city":"Louisville",
    "sg:classifiers":[
        {
            "category":"Railroad",
            "type":"Transportation"
        }
    ],
    "sg:phone":"+1 662 779 2204",
    "sg:postcode":"39339",
    "sg:province":"MS",
    "wof:name":"Kansas City Southern Railroad",
    "wof:placetype":"venue"
},
  "geometry": {"coordinates":[-89.058258,33.119508],"type":"Point"}
}