{
  "type": "Feature",
  "properties": {
    "iso:country":"US",
    "sg:address":"2000 Byron St",
    "sg:city":"Hattiesburg",
    "sg:classifiers":[
        {
            "category":"Building & Trades",
            "subcategory":"Electrical",
            "type":"Services"
        }
    ],
    "sg:phone":"+1 601 268 1586",
    "sg:postcode":"39402",
    "sg:province":"MS",
    "sg:tags":[
        "electrical",
        "merchandise",
        "contractor"
    ],
    "wof:name":"Sentry Security & Sound",
    "wof:placetype":"venue"
},
  "geometry": {"coordinates":[-89.318996,31.302926],"type":"Point"}
}