{
  "type": "Feature",
  "properties": {
    "iso:country":"US",
    "sg:address":"107 Shadia Dr",
    "sg:city":"Clinton",
    "sg:classifiers":[
        {
            "category":"Utilities",
            "subcategory":"Telephone",
            "type":"Services"
        },
        {
            "category":"Shopping",
            "type":"Retail Goods"
        }
    ],
    "sg:phone":"+1 601 924 2479",
    "sg:postcode":"39056",
    "sg:province":"MS",
    "sg:tags":[
        "equipment",
        "supply",
        "communications"
    ],
    "wof:name":"Central Mississippi Telephone",
    "wof:placetype":"venue"
},
  "geometry": {"coordinates":[-90.317492,32.372524],"type":"Point"}
}