{
  "type": "Feature",
  "properties": {
    "iso:country":"US",
    "sg:address":"250 Co Rd 204",
    "sg:city":"Abbeville",
    "sg:classifiers":[
        {
            "category":"Professional",
            "subcategory":"Detective & Security Services",
            "type":"Services"
        }
    ],
    "sg:phone":"+1 662 234 4072",
    "sg:postcode":"38601",
    "sg:province":"MS",
    "sg:tags":[
        "marshal",
        "us"
    ],
    "wof:name":"David Box Hoit",
    "wof:placetype":"venue"
},
  "geometry": {"coordinates":[-89.48307,34.433897],"type":"Point"}
}