{
  "type": "Feature",
  "properties": {
    "iso:country":"US",
    "sg:address":"11325 Cedar Lake Rd",
    "sg:city":"Biloxi",
    "sg:classifiers":[
        {
            "category":"Professional",
            "type":"Services"
        }
    ],
    "sg:phone":"+1 228 392 0955",
    "sg:postcode":"39532",
    "sg:province":"MS",
    "sg:tags":[
        "establishment"
    ],
    "wof:name":"Carl E Woodward LLC",
    "wof:placetype":"venue"
},
  "geometry": {"coordinates":[-88.93437900000001,30.451589],"type":"Point"}
}