{
  "type": "Feature",
  "properties": {
    "iso:country":"US",
    "sg:address":"757 Hwy 98 E",
    "sg:city":"Columbia",
    "sg:classifiers":[
        {
            "category":"Autos & Motor Vehicles",
            "subcategory":"Fuel & Gas Station",
            "type":"Retail Goods"
        }
    ],
    "sg:phone":"+1 601 736 7927",
    "sg:postcode":"39429",
    "sg:province":"MS",
    "sg:tags":[
        "oil"
    ],
    "wof:name":"Texaco",
    "wof:placetype":"venue"
},
  "geometry": {"coordinates":[-89.81660100000001,31.23946],"type":"Point"}
}