{
  "type": "Feature",
  "properties": {
    "iso:country":"US",
    "sg:address":"103 Main St",
    "sg:city":"Purvis",
    "sg:classifiers":[
        {
            "category":"Shopping",
            "subcategory":"Used Merchandise",
            "type":"Retail Goods"
        }
    ],
    "sg:phone":"+1 601 794 8237",
    "sg:postcode":"39475",
    "sg:province":"MS",
    "sg:tags":[
        "pawnbroker"
    ],
    "wof:name":"Pearson's Pawn & Gift",
    "wof:placetype":"venue"
},
  "geometry": {"coordinates":[-89.412441,31.144037],"type":"Point"}
}