{
  "type": "Feature",
  "properties": {
    "iso:country":"US",
    "sg:address":"704 N 20th St",
    "sg:city":"Columbus",
    "sg:classifiers":[
        {
            "category":"Personal",
            "type":"Services"
        }
    ],
    "sg:phone":"+1 662 327 6714",
    "sg:postcode":"39701",
    "sg:province":"MS",
    "sg:tags":[
        "wear",
        "formal"
    ],
    "wof:name":"Young's Formal Wear",
    "wof:placetype":"venue"
},
  "geometry": {"coordinates":[-88.41113300000001,33.504305],"type":"Point"}
}