{
  "type": "Feature",
  "properties": {
    "iso:country":"US",
    "sg:address":"300 Harold T White Memorial Dr",
    "sg:city":"Booneville",
    "sg:classifiers":[
        {
            "category":"Health Services",
            "subcategory":"Nursing And Care Facility",
            "type":"Services"
        }
    ],
    "sg:phone":"+1 662 720 1121",
    "sg:postcode":"38829",
    "sg:province":"MS",
    "sg:tags":[
        "home",
        "retirement",
        "community"
    ],
    "wof:name":"Chriswood Inc Assisted Living",
    "wof:placetype":"venue"
},
  "geometry": {"coordinates":[-88.57194200000001,34.66183],"type":"Point"}
}