{
  "type": "Feature",
  "properties": {
    "addr:full":"197 Scott Rd Lucedale MS 39452",
    "addr:housenumber":"197",
    "addr:postcode":"39452",
    "addr:street":"Scott Rd",
    "iso:country":"US",
    "sg:address":"197 Scott Rd",
    "sg:city":"Lucedale",
    "sg:classifiers":[
        {
            "category":"Insurance",
            "subcategory":"Insurance Agent",
            "type":"Services"
        }
    ],
    "sg:phone":"+1 601 947 8770",
    "sg:postcode":"39452",
    "sg:province":"MS",
    "wof:name":"Bradshaw Insurance",
    "wof:placetype":"venue"
},
  "geometry": {"coordinates":[-88.59801899999999,30.899242],"type":"Point"}
}