{
  "type": "Feature",
  "properties": {
    "iso:country":"US",
    "sg:address":"322 Sunset Dr",
    "sg:city":"Grenada",
    "sg:classifiers":[
        {
            "category":"Cinema",
            "subcategory":"Movie Rental",
            "type":"Entertainment"
        }
    ],
    "sg:phone":"+1 662 227 1313",
    "sg:postcode":"38901",
    "sg:province":"MS",
    "sg:tags":[
        "video",
        "tape"
    ],
    "wof:name":"Video Store",
    "wof:placetype":"venue"
},
  "geometry": {"coordinates":[-89.807332,33.769133],"type":"Point"}
}