{
  "type": "Feature",
  "properties": {
    "addr:full":"12405 Hanover Dr Ocean Springs MS 39564",
    "addr:housenumber":"12405",
    "addr:postcode":"39564",
    "addr:street":"Hanover Dr",
    "iso:country":"US",
    "sg:address":"12405 Hanover Dr",
    "sg:city":"Ocean Springs",
    "sg:classifiers":[
        {
            "category":"Professional",
            "subcategory":"Management & Consulting",
            "type":"Services"
        }
    ],
    "sg:phone":"+1 228 875 1589",
    "sg:postcode":"39564",
    "sg:province":"MS",
    "sg:tags":[
        "business"
    ],
    "wof:name":"LDS & Associates",
    "wof:placetype":"venue"
},
  "geometry": {"coordinates":[-88.816872,30.430046],"type":"Point"}
}