{
  "type": "Feature",
  "properties": {
    "iso:country":"US",
    "sg:address":"3201 23rd Ave",
    "sg:city":"Meridian",
    "sg:classifiers":[
        {
            "category":"Professional",
            "subcategory":"Art Services",
            "type":"Services"
        }
    ],
    "sg:phone":"+1 601 482 4801",
    "sg:postcode":"39305",
    "sg:province":"MS",
    "sg:tags":[
        "photo",
        "photography",
        "commercial",
        "studio",
        "portrait"
    ],
    "wof:name":"Impressions Photography",
    "wof:placetype":"venue"
},
  "geometry": {"coordinates":[-88.701274,32.392716],"type":"Point"}
}