{
  "type": "Feature",
  "properties": {
    "iso:country":"US",
    "sg:address":"2132 Berwick Cassels Rd",
    "sg:city":"Liberty",
    "sg:classifiers":[
        {
            "category":"Farming",
            "subcategory":"Dairy Farm",
            "type":"Manufacturing & Wholesale Goods"
        }
    ],
    "sg:phone":"+1 601 657 8761",
    "sg:postcode":"39645",
    "sg:province":"MS",
    "wof:name":"Gurneys Dairy Farm",
    "wof:placetype":"venue"
},
  "geometry": {"coordinates":[-90.92071799999999,31.055559],"type":"Point"}
}