{
  "type": "Feature",
  "properties": {
    "iso:country":"US",
    "sg:address":"340 Van Dorn St",
    "sg:city":"Grenada",
    "sg:classifiers":[
        {
            "category":"Health Services",
            "subcategory":"Doctor",
            "type":"Services"
        }
    ],
    "sg:phone":"+1 662 226 0325",
    "sg:postcode":"38901",
    "sg:province":"MS",
    "sg:tags":[
        "physician",
        "surgeon",
        "medical"
    ],
    "wof:name":"Grenada Children's Clinic",
    "wof:placetype":"venue"
},
  "geometry": {"coordinates":[-89.80832700000001,33.766114],"type":"Point"}
}