{
  "type": "Feature",
  "properties": {
    "iso:country":"US",
    "sg:address":"833 Old Hwy 45",
    "sg:city":"Saltillo",
    "sg:classifiers":[
        {
            "category":"Food & Beverages",
            "subcategory":"Groceries & Convenience Stores",
            "type":"Retail Goods"
        }
    ],
    "sg:phone":"+1 662 869 8384",
    "sg:postcode":"38866",
    "sg:province":"MS",
    "wof:name":"Morgan's Quick Stop",
    "wof:placetype":"venue"
},
  "geometry": {"coordinates":[-88.708707,34.371712],"type":"Point"}
}