{
  "type": "Feature",
  "properties": {
    "iso:country":"US",
    "sg:address":"1604 Gardner Blvd",
    "sg:city":"Columbus",
    "sg:classifiers":[
        {
            "category":"Autos & Motor Vehicles",
            "subcategory":"Fuel & Gas Station",
            "type":"Retail Goods"
        }
    ],
    "sg:phone":"+1 662 327 0307",
    "sg:postcode":"39702",
    "sg:province":"MS",
    "sg:tags":[
        "grocery",
        "station",
        "gasoline"
    ],
    "wof:name":"Express Mart",
    "wof:placetype":"venue"
},
  "geometry": {"coordinates":[-88.389571,33.51253],"type":"Point"}
}