{
  "type": "Feature",
  "properties": {
    "addr:full":"428 Mill Ln Bude MS 39631",
    "addr:housenumber":"428",
    "addr:postcode":"39631",
    "addr:street":"Mill Ln",
    "iso:country":"US",
    "sg:address":"428 Mill Ln",
    "sg:city":"Bude",
    "sg:classifiers":[
        {
            "category":"Government",
            "subcategory":"Office",
            "type":"Public Place"
        }
    ],
    "sg:phone":"+1 601 384 2369",
    "sg:postcode":"39631",
    "sg:province":"MS",
    "sg:tags":[
        "state",
        "resource"
    ],
    "wof:name":"Human Services Dept",
    "wof:placetype":"venue"
},
  "geometry": {"coordinates":[-91.096665,31.087245],"type":"Point"}
}