{
  "type": "Feature",
  "properties": {
    "addr:full":"304 Foster Park Dr Booneville MS 38829",
    "addr:housenumber":"304",
    "addr:postcode":"38829",
    "addr:street":"Foster Park Dr",
    "iso:country":"US",
    "sg:address":"304 Foster Park Dr",
    "sg:city":"Booneville",
    "sg:classifiers":[
        {
            "category":"Building & Trades",
            "subcategory":"Plumbing",
            "type":"Services"
        }
    ],
    "sg:phone":"+1 662 728 5957",
    "sg:postcode":"38829",
    "sg:province":"MS",
    "sg:tags":[
        "installs",
        "system",
        "air",
        "heat",
        "conditioning",
        "contractor"
    ],
    "wof:name":"Booneville Refrigeration Svc",
    "wof:placetype":"venue"
},
  "geometry": {"coordinates":[-88.573312,34.65185],"type":"Point"}
}