{
  "type": "Feature",
  "properties": {
    "iso:country":"US",
    "sg:address":"5510 Laurel Manor Cove",
    "sg:city":"Memphis",
    "sg:classifiers":[
        {
            "category":"Autos & Motor Vehicles",
            "subcategory":"Automobile Sales",
            "type":"Retail Goods"
        }
    ],
    "sg:phone":"+1 901 753 6056",
    "sg:postcode":"38125",
    "sg:province":"MS",
    "sg:tags":[
        "car",
        "dealer"
    ],
    "wof:name":"Willie Peeples Auto Sales",
    "wof:placetype":"venue"
},
  "geometry": {"coordinates":[-89.82946699999999,34.998134],"type":"Point"}
}