{
  "type": "Feature",
  "properties": {
    "iso:country":"US",
    "sg:address":"3350 Hwy 468",
    "sg:city":"Pearl",
    "sg:classifiers":[
        {
            "category":"Government",
            "subcategory":"Court House",
            "type":"Public Place"
        }
    ],
    "sg:phone":"+1 601 932 5766",
    "sg:postcode":"39208",
    "sg:province":"MS",
    "sg:tags":[
        "county"
    ],
    "wof:name":"Youth Court",
    "wof:placetype":"venue"
},
  "geometry": {"coordinates":[-90.08838799999999,32.236084],"type":"Point"}
}