{
  "type": "Feature",
  "properties": {
    "iso:country":"US",
    "sg:address":"655 Beasley Rd",
    "sg:city":"Jackson",
    "sg:classifiers":[
        {
            "category":"Organizations",
            "subcategory":"Religious Organization",
            "type":"Services"
        }
    ],
    "sg:phone":"+1 601 366 8071",
    "sg:postcode":"39206",
    "sg:province":"MS",
    "wof:name":"Aldersgate Untd Methdst Church",
    "wof:placetype":"venue"
},
  "geometry": {"coordinates":[-90.176087,32.385348],"type":"Point"}
}