{
  "type": "Feature",
  "properties": {
    "iso:country":"US",
    "sg:address":"295 F Fortenberry Ave",
    "sg:city":"Magnolia",
    "sg:classifiers":[
        {
            "category":"Personal",
            "subcategory":"Beauty Salon",
            "type":"Services"
        }
    ],
    "sg:phone":"+1 601 783 0872",
    "sg:postcode":"39652",
    "sg:province":"MS",
    "sg:tags":[
        "shop",
        "barber"
    ],
    "wof:name":"New Wave Beauty Salon",
    "wof:placetype":"venue"
},
  "geometry": {"coordinates":[-90.458522,31.157797],"type":"Point"}
}