{
  "type": "Feature",
  "properties": {
    "iso:country":"US",
    "sg:address":"618 Center Park Ln",
    "sg:city":"Yazoo City",
    "sg:classifiers":[
        {
            "category":"Restaurant",
            "type":"Food & Drink"
        }
    ],
    "sg:phone":"+1 662 746 9194",
    "sg:postcode":"39194",
    "sg:province":"MS",
    "wof:name":"Howell's",
    "wof:placetype":"venue"
},
  "geometry": {"coordinates":[-90.39661,32.865662],"type":"Point"}
}