{
  "type": "Feature",
  "properties": {
    "iso:country":"US",
    "sg:address":"256 Northwood Dr",
    "sg:city":"Carriere",
    "sg:classifiers":[
        {
            "category":"Building & Trades",
            "subcategory":"Construction",
            "type":"Services"
        }
    ],
    "sg:phone":"+1 601 798 3183",
    "sg:postcode":"39426",
    "sg:province":"MS",
    "sg:tags":[
        "contractor"
    ],
    "wof:name":"Jason Masonary",
    "wof:placetype":"venue"
},
  "geometry": {"coordinates":[-89.645325,30.534492],"type":"Point"}
}