{
  "type": "Feature",
  "properties": {
    "iso:country":"US",
    "sg:address":"800 Ridgewood Rd",
    "sg:city":"Ridgeland",
    "sg:classifiers":[
        {
            "category":"Travel",
            "subcategory":"Hotels & Motels",
            "type":"Entertainment"
        }
    ],
    "sg:phone":"+1 601 956 0884",
    "sg:postcode":"39157",
    "sg:province":"MS",
    "wof:name":"Studio Plus Hotels Inc",
    "wof:placetype":"venue"
},
  "geometry": {"coordinates":[-90.140862,32.411249],"type":"Point"}
}