{
  "type": "Feature",
  "properties": {
    "iso:country":"US",
    "sg:address":"2405 Callie Rd",
    "sg:city":"Gautier",
    "sg:classifiers":[
        {
            "category":"Organizations",
            "subcategory":"Religious Organization",
            "type":"Services"
        }
    ],
    "sg:phone":"+1 228 497 2373",
    "sg:postcode":"39553",
    "sg:province":"MS",
    "sg:tags":[
        "church"
    ],
    "wof:name":"North Gautier Baptist Church",
    "wof:placetype":"venue"
},
  "geometry": {"coordinates":[-88.64864,30.418769],"type":"Point"}
}