{
  "type": "Feature",
  "properties": {
    "iso:country":"US",
    "sg:address":"880 Stateline Rd E",
    "sg:city":"Southaven",
    "sg:classifiers":[
        {
            "category":"Social Services",
            "type":"Services"
        }
    ],
    "sg:phone":"+1 662 796 2287",
    "sg:postcode":"38671",
    "sg:province":"MS",
    "sg:tags":[
        "human"
    ],
    "wof:name":"Access Connections To Success",
    "wof:placetype":"venue"
},
  "geometry": {"coordinates":[-90.001564,34.991859],"type":"Point"}
}