{
  "type": "Feature",
  "properties": {
    "iso:country":"US",
    "sg:address":"495 Hwy 29",
    "sg:city":"Wiggins",
    "sg:classifiers":[
        {
            "category":"Building & Trades",
            "subcategory":"Construction",
            "type":"Services"
        }
    ],
    "sg:phone":"+1 601 928 5004",
    "sg:postcode":"39577",
    "sg:province":"MS",
    "sg:tags":[
        "heavy",
        "contractor"
    ],
    "wof:name":"David Pearson Contracting",
    "wof:placetype":"venue"
},
  "geometry": {"coordinates":[-89.13280399999999,30.857874],"type":"Point"}
}