{
  "type": "Feature",
  "properties": {
    "iso:country":"US",
    "sg:address":"3 Wadley Lane Dr",
    "sg:city":"Buckatunna",
    "sg:classifiers":[
        {
            "category":"Shopping",
            "subcategory":"Music",
            "type":"Retail Goods"
        }
    ],
    "sg:phone":"+1 601 648 2684",
    "sg:postcode":"39322",
    "sg:province":"MS",
    "sg:tags":[
        "video",
        "disc",
        "tape",
        "cassette"
    ],
    "wof:name":"Kountry Videos",
    "wof:placetype":"venue"
},
  "geometry": {"coordinates":[-88.525649,31.537164],"type":"Point"}
}