{
  "type": "Feature",
  "properties": {
    "iso:country":"US",
    "sg:address":"3830 N Flag Chapel Rd",
    "sg:city":"Jackson",
    "sg:classifiers":[
        {
            "category":"Organizations",
            "subcategory":"Religious Organization",
            "type":"Services"
        }
    ],
    "sg:phone":"+1 601 366 6667",
    "sg:postcode":"39213",
    "sg:province":"MS",
    "wof:name":"New Galilean Baptist Church",
    "wof:placetype":"venue"
},
  "geometry": {"coordinates":[-90.270037,32.370292],"type":"Point"}
}