{
  "type": "Feature",
  "properties": {
    "iso:country":"US",
    "sg:address":"1639 E Pass Rd",
    "sg:city":"Gulfport",
    "sg:classifiers":[
        {
            "category":"Professional",
            "type":"Services"
        }
    ],
    "sg:phone":"+1 228 604 4679",
    "sg:postcode":"39507",
    "sg:province":"MS",
    "sg:tags":[
        "establishment"
    ],
    "wof:name":"Thrifty Nickel",
    "wof:placetype":"venue"
},
  "geometry": {"coordinates":[-89.02085599999999,30.399946],"type":"Point"}
}