{
  "type": "Feature",
  "properties": {
    "iso:country":"US",
    "sg:address":"1253 Main St",
    "sg:city":"Southaven",
    "sg:classifiers":[
        {
            "category":"Insurance",
            "subcategory":"Insurance Agent",
            "type":"Services"
        }
    ],
    "sg:phone":"+1 662 393 5617",
    "sg:postcode":"38671",
    "sg:province":"MS",
    "wof:name":"Nelson Insurance Svc",
    "wof:placetype":"venue"
},
  "geometry": {"coordinates":[-90.01194599999999,34.991773],"type":"Point"}
}