{
  "type": "Feature",
  "properties": {
    "addr:full":"1722 Smithdale Rd Mccomb MS 39648",
    "addr:housenumber":"1722",
    "addr:postcode":"39648",
    "addr:street":"Smithdale Rd",
    "iso:country":"US",
    "sg:address":"1722 Smithdale Rd",
    "sg:city":"Mccomb",
    "sg:classifiers":[
        {
            "category":"Restaurant",
            "type":"Food & Drink"
        },
        {
            "category":"Wholesale",
            "subcategory":"Groceries",
            "type":"Manufacturing & Wholesale Goods"
        }
    ],
    "sg:phone":"+1 601 684 3557",
    "sg:postcode":"39648",
    "sg:province":"MS",
    "sg:tags":[
        "bakery",
        "retail",
        "parlor",
        "ice",
        "cream"
    ],
    "wof:name":"Classic Cookie",
    "wof:placetype":"venue"
},
  "geometry": {"coordinates":[-90.47417,31.260546],"type":"Point"}
}