{
  "type": "Feature",
  "properties": {
    "addr:full":"9245 Pigeon Roost Rd Olive Branch MS 38654",
    "addr:housenumber":"9245",
    "addr:postcode":"38654",
    "addr:street":"Pigeon Roost Rd",
    "iso:country":"US",
    "sg:address":"9245 Pigeon Roost Rd",
    "sg:city":"Olive Branch",
    "sg:classifiers":[
        {
            "category":"Government",
            "subcategory":"Court House",
            "type":"Public Place"
        }
    ],
    "sg:phone":"+1 662 895 4046",
    "sg:postcode":"38654",
    "sg:province":"MS",
    "sg:tags":[
        "city"
    ],
    "wof:name":"Municipal Court Clerk Office",
    "wof:placetype":"venue"
},
  "geometry": {"coordinates":[-89.82697,34.961091],"type":"Point"}
}