{
  "type": "Feature",
  "properties": {
    "iso:country":"US",
    "sg:address":"2900 W 7th St",
    "sg:city":"Hattiesburg",
    "sg:classifiers":[
        {
            "category":"Professional",
            "type":"Services"
        }
    ],
    "sg:phone":"+1 601 264 1830",
    "sg:postcode":"39401",
    "sg:province":"MS",
    "sg:tags":[
        "establishment"
    ],
    "wof:name":"Fowler Co",
    "wof:placetype":"venue"
},
  "geometry": {"coordinates":[-89.333337,31.335713],"type":"Point"}
}