{
  "type": "Feature",
  "properties": {
    "iso:country":"US",
    "sg:address":"27 Mitchell St",
    "sg:city":"Wiggins",
    "sg:classifiers":[
        {
            "category":"Manufacturing",
            "subcategory":"Retail Goods",
            "type":"Manufacturing & Wholesale Goods"
        }
    ],
    "sg:phone":"+1 601 928 2036",
    "sg:postcode":"39577",
    "sg:province":"MS",
    "sg:tags":[
        "manufacturer"
    ],
    "wof:name":"H & H Industries Inc",
    "wof:placetype":"venue"
},
  "geometry": {"coordinates":[-89.164936,30.892618],"type":"Point"}
}