{
  "type": "Feature",
  "properties": {
    "iso:country":"US",
    "sg:address":"714 2nd St",
    "sg:city":"Tylertown",
    "sg:classifiers":[
        {
            "category":"Retail",
            "subcategory":"Funeral Services",
            "type":"Services"
        }
    ],
    "sg:phone":"+1 601 876 3634",
    "sg:postcode":"39667",
    "sg:province":"MS",
    "sg:tags":[
        "director"
    ],
    "wof:name":"Washington Funeral Home",
    "wof:placetype":"venue"
},
  "geometry": {"coordinates":[-90.14068399999999,31.113783],"type":"Point"}
}