{
  "type": "Feature",
  "properties": {
    "iso:country":"US",
    "sg:address":"2941 Market St",
    "sg:city":"Pascagoula",
    "sg:classifiers":[
        {
            "category":"Organizations",
            "subcategory":"Labor Organization",
            "type":"Services"
        }
    ],
    "sg:phone":"+1 228 762 1806",
    "sg:postcode":"39567",
    "sg:province":"MS",
    "wof:name":"Painters Local Union 1225",
    "wof:placetype":"venue"
},
  "geometry": {"coordinates":[-88.54859500000001,30.363736],"type":"Point"}
}