{
  "type": "Feature",
  "properties": {
    "addr:full":"191 Co Rd 690 Tupelo MS 38801",
    "addr:housenumber":"191;690",
    "addr:postcode":"38801",
    "addr:street":"Co Rd",
    "iso:country":"US",
    "sg:address":"191 Co Rd 690",
    "sg:city":"Tupelo",
    "sg:classifiers":[
        {
            "category":"Building & Trades",
            "subcategory":"Electrical",
            "type":"Services"
        }
    ],
    "sg:phone":"+1 662 566 2756",
    "sg:postcode":"38801",
    "sg:province":"MS",
    "sg:tags":[
        "electrical",
        "electric",
        "contractor"
    ],
    "wof:name":"Keith Electric",
    "wof:placetype":"venue"
},
  "geometry": {"coordinates":[-88.768058,34.180631],"type":"Point"}
}