{
  "type": "Feature",
  "properties": {
    "addr:full":"209 Sisk Ave Oxford MS 38655",
    "addr:housenumber":"209",
    "addr:postcode":"38655",
    "addr:street":"Sisk Ave",
    "iso:country":"US",
    "sg:address":"209 Sisk Ave",
    "sg:city":"Oxford",
    "sg:classifiers":[
        {
            "category":"Professional",
            "subcategory":"Engineering",
            "type":"Services"
        }
    ],
    "sg:phone":"+1 662 236 6776",
    "sg:postcode":"38655",
    "sg:province":"MS",
    "wof:name":"W L Burle Engineers",
    "wof:placetype":"venue"
},
  "geometry": {"coordinates":[-89.51258,34.373157],"type":"Point"}
}