{
  "type": "Feature",
  "properties": {
    "iso:country":"US",
    "sg:address":"172 Annandale Pkwy E",
    "sg:city":"Madison",
    "sg:classifiers":[
        {
            "category":"Professional",
            "subcategory":"Business Services",
            "type":"Services"
        },
        {
            "category":"Home & Garden",
            "subcategory":"Home Furnishings",
            "type":"Retail Goods"
        }
    ],
    "sg:phone":"+1 601 853 0072",
    "sg:postcode":"39110",
    "sg:province":"MS",
    "sg:tags":[
        "interior",
        "consultant",
        "design",
        "decorator"
    ],
    "wof:name":"Anne Cook Interior Design",
    "wof:placetype":"venue"
},
  "geometry": {"coordinates":[-90.182834,32.50188],"type":"Point"}
}