{
  "type": "Feature",
  "properties": {
    "addr:full":"770 Grant Pl Clarksdale MS 38614",
    "addr:housenumber":"770",
    "addr:postcode":"38614",
    "addr:street":"Grant Pl",
    "iso:country":"US",
    "sg:address":"770 Grant Pl",
    "sg:city":"Clarksdale",
    "sg:classifiers":[
        {
            "category":"Education",
            "subcategory":"School",
            "type":"Public Place"
        }
    ],
    "sg:phone":"+1 662 627 8595",
    "sg:postcode":"38614",
    "sg:province":"MS",
    "wof:name":"Clarksdale Municipal School District",
    "wof:placetype":"venue"
},
  "geometry": {"coordinates":[-90.56144500000001,34.196026],"type":"Point"}
}