{
  "type": "Feature",
  "properties": {
    "iso:country":"US",
    "sg:address":"27 Power Ln",
    "sg:city":"Hattiesburg",
    "sg:classifiers":[
        {
            "category":"Home & Garden",
            "subcategory":"Carpets & Floor Coverings",
            "type":"Retail Goods"
        }
    ],
    "sg:phone":"+1 601 296 1827",
    "sg:postcode":"39402",
    "sg:province":"MS",
    "sg:tags":[
        "material"
    ],
    "wof:name":"Craft-Croswell Contract Furn",
    "wof:placetype":"venue"
},
  "geometry": {"coordinates":[-89.44108900000001,31.316546],"type":"Point"}
}