{
  "type": "Feature",
  "properties": {
    "addr:full":"406 Chandler St Inverness MS 38753",
    "addr:housenumber":"406",
    "addr:postcode":"38753",
    "addr:street":"Chandler St",
    "iso:country":"US",
    "sg:address":"406 Chandler St",
    "sg:city":"Inverness",
    "sg:classifiers":[
        {
            "category":"Organizations",
            "subcategory":"Religious Organization",
            "type":"Services"
        }
    ],
    "sg:phone":"+1 662 265 5570",
    "sg:postcode":"38753",
    "sg:province":"MS",
    "sg:tags":[
        "church"
    ],
    "wof:name":"New Hope Missionary Baptist",
    "wof:placetype":"venue"
},
  "geometry": {"coordinates":[-90.596417,33.347318],"type":"Point"}
}