{
  "type": "Feature",
  "properties": {
    "iso:country":"US",
    "sg:address":"512 Branton Ave",
    "sg:city":"Columbia",
    "sg:classifiers":[
        {
            "category":"Mining & Drilling",
            "type":"Manufacturing & Wholesale Goods"
        }
    ],
    "sg:phone":"+1 601 736 8494",
    "sg:postcode":"39429",
    "sg:province":"MS",
    "sg:tags":[
        "crude",
        "production",
        "gas"
    ],
    "wof:name":"Regan Enterprises Inc",
    "wof:placetype":"venue"
},
  "geometry": {"coordinates":[-89.81922900000001,31.248009],"type":"Point"}
}