{
  "type": "Feature",
  "properties": {
    "addr:full":"2325 Lakeland Dr Flowood MS 39232",
    "addr:housenumber":"2325",
    "addr:postcode":"39232",
    "addr:street":"Lakeland Dr",
    "iso:country":"US",
    "sg:address":"2325 Lakeland Dr",
    "sg:city":"Flowood",
    "sg:classifiers":[
        {
            "category":"Restaurant",
            "type":"Food & Drink"
        }
    ],
    "sg:menulink":"http://www.allmenus.com/ms/pearl/156484-krystal-burgers/menu/",
    "sg:phone":"+1 601 932 6106",
    "sg:postcode":"39232",
    "sg:province":"MS",
    "sg:tags":[
        "burger",
        "chicken",
        "american"
    ],
    "wof:name":"Krystal Burgers",
    "wof:placetype":"venue"
},
  "geometry": {"coordinates":[-90.124617,32.330281],"type":"Point"}
}