{
  "type": "Feature",
  "properties": {
    "addr:full":"63383 Hwy 25 N Smithville MS 38870",
    "addr:housenumber":"63383",
    "addr:postcode":"38870",
    "addr:street":"Hwy 25 N",
    "iso:country":"US",
    "sg:address":"63383 Hwy 25 N",
    "sg:city":"Smithville",
    "sg:classifiers":[
        {
            "category":"Organizations",
            "subcategory":"Religious Organization",
            "type":"Services"
        }
    ],
    "sg:phone":"+1 662 651 4226",
    "sg:postcode":"38870",
    "sg:province":"MS",
    "sg:tags":[
        "church"
    ],
    "wof:name":"Victory Baptist Church",
    "wof:placetype":"venue"
},
  "geometry": {"coordinates":[-88.40903400000001,34.063567],"type":"Point"}
}