{
  "type": "Feature",
  "properties": {
    "addr:full":"1262 Main St Fayette MS 39069",
    "addr:housenumber":"1262",
    "addr:postcode":"39069",
    "addr:street":"Main St",
    "iso:country":"US",
    "sg:address":"1262 Main St",
    "sg:city":"Fayette",
    "sg:classifiers":[
        {
            "category":"Manufacturing",
            "subcategory":"Lumber",
            "type":"Manufacturing & Wholesale Goods"
        }
    ],
    "sg:phone":"+1 601 786 6440",
    "sg:postcode":"39069",
    "sg:province":"MS",
    "sg:tags":[
        "government"
    ],
    "wof:name":"Forestry Dept",
    "wof:placetype":"venue"
},
  "geometry": {"coordinates":[-91.07606199999999,31.702673],"type":"Point"}
}