{
  "type": "Feature",
  "properties": {
    "addr:full":"8490 Okatibbee Dam Rd Collinsville MS 39325",
    "addr:housenumber":"8490",
    "addr:postcode":"39325",
    "addr:street":"Okatibbee Dam Rd",
    "iso:country":"US",
    "sg:address":"8490 Okatibbee Dam Rd",
    "sg:city":"Collinsville",
    "sg:classifiers":[
        {
            "category":"Government",
            "subcategory":"Office",
            "type":"Public Place"
        }
    ],
    "sg:phone":"+1 601 626 8431",
    "sg:postcode":"39325",
    "sg:province":"MS",
    "sg:tags":[
        "federal"
    ],
    "wof:name":"US Army Corps Of Engineers",
    "wof:placetype":"venue"
},
  "geometry": {"coordinates":[-88.812997,32.475442],"type":"Point"}
}