{
  "type": "Feature",
  "properties": {
    "iso:country":"US",
    "sg:address":"1025 Division St",
    "sg:city":"Biloxi",
    "sg:classifiers":[
        {
            "category":"Professional",
            "subcategory":"Lawyer & Legal Services",
            "type":"Services"
        }
    ],
    "sg:phone":"+1 228 374 0700",
    "sg:postcode":"39530",
    "sg:province":"MS",
    "sg:tags":[
        "attorney"
    ],
    "wof:name":"Waltzer & Associates Attorneys",
    "wof:placetype":"venue"
},
  "geometry": {"coordinates":[-88.899879,30.403407],"type":"Point"}
}