{
  "type": "Feature",
  "properties": {
    "addr:full":"465 Goodman Rd E Southaven MS 38671",
    "addr:housenumber":"465",
    "addr:postcode":"38671",
    "addr:street":"Goodman Rd E",
    "iso:country":"US",
    "sg:address":"465 Goodman Rd E",
    "sg:city":"Southaven",
    "sg:classifiers":[
        {
            "category":"Autos & Motor Vehicles",
            "subcategory":"Auto Supplies",
            "type":"Retail Goods"
        },
        {
            "category":"Shopping",
            "subcategory":"Discount & Variety Stores",
            "type":"Retail Goods"
        },
        {
            "category":"Food & Beverages",
            "subcategory":"Supermarket",
            "type":"Retail Goods"
        },
        {
            "category":"Shopping",
            "type":"Retail Goods"
        }
    ],
    "sg:phone":"+1 662 349 0723",
    "sg:postcode":"38671",
    "sg:province":"MS",
    "sg:tags":[
        "super",
        "merchandise",
        "tire"
    ],
    "sg:website":"http://www.samsclub.com",
    "wof:name":"Sam's Club",
    "wof:placetype":"venue"
},
  "geometry": {"coordinates":[-89.981678,34.962761],"type":"Point"}
}