{
  "type": "Feature",
  "properties": {
    "addr:full":"110 Service Dr Brandon MS 39042",
    "addr:housenumber":"110",
    "addr:postcode":"39042",
    "addr:street":"Service Dr",
    "iso:country":"US",
    "sg:address":"110 Service Dr",
    "sg:city":"Brandon",
    "sg:classifiers":[
        {
            "category":"Personal",
            "subcategory":"Beauty Salon",
            "type":"Services"
        }
    ],
    "sg:phone":"+1 601 825 9560",
    "sg:postcode":"39042",
    "sg:province":"MS",
    "wof:name":"Studio A Hair Design",
    "wof:placetype":"venue"
},
  "geometry": {"coordinates":[-90.02847,32.2833],"type":"Point"}
}