{
  "type": "Feature",
  "properties": {
    "iso:country":"US",
    "sg:address":"97 Morris St",
    "sg:city":"Petal",
    "sg:classifiers":[
        {
            "category":"Restaurant",
            "type":"Food & Drink"
        }
    ],
    "sg:menulink":"http://www.allmenus.com/ms/petal/76306-dominos-pizza/menu/",
    "sg:phone":"+1 601 544 3030",
    "sg:postcode":"39465",
    "sg:province":"MS",
    "sg:tags":[
        "american",
        "wing",
        "pizza"
    ],
    "wof:name":"Domino's Pizza",
    "wof:placetype":"venue"
},
  "geometry": {"coordinates":[-89.26066400000001,31.346087],"type":"Point"}
}