{
  "type": "Feature",
  "properties": {
    "iso:country":"US",
    "sg:address":"179 Drinkwater Rd",
    "sg:city":"Bay St Louis",
    "sg:classifiers":[
        {
            "category":"Health Services",
            "subcategory":"Doctor",
            "type":"Services"
        }
    ],
    "sg:phone":"+1 228 467 5900",
    "sg:postcode":"39520",
    "sg:province":"MS",
    "sg:tags":[
        "physician",
        "surgeon"
    ],
    "wof:name":"Coast Heart Institute",
    "wof:placetype":"venue"
},
  "geometry": {"coordinates":[-89.355555,30.31545],"type":"Point"}
}