{
  "type": "Feature",
  "properties": {
    "iso:country":"US",
    "sg:address":"200 W Leake St",
    "sg:city":"Clinton",
    "sg:classifiers":[
        {
            "category":"Building & Trades",
            "subcategory":"Construction",
            "type":"Services"
        }
    ],
    "sg:phone":"+1 601 924 2239",
    "sg:postcode":"39056",
    "sg:province":"MS",
    "sg:tags":[
        "marking",
        "maintenance",
        "parking"
    ],
    "wof:name":"Clinton Public Works Dept",
    "wof:placetype":"venue"
},
  "geometry": {"coordinates":[-90.33174,32.340154],"type":"Point"}
}