{
  "type": "Feature",
  "properties": {
    "addr:full":"2717 Oktoc Rd Starkville MS 39759",
    "addr:housenumber":"2717",
    "addr:postcode":"39759",
    "addr:street":"Oktoc Rd",
    "iso:country":"US",
    "sg:address":"2717 Oktoc Rd",
    "sg:city":"Starkville",
    "sg:classifiers":[
        {
            "category":"Farming",
            "subcategory":"Dairy Farm",
            "type":"Manufacturing & Wholesale Goods"
        }
    ],
    "sg:phone":"+1 662 324 3101",
    "sg:postcode":"39759",
    "sg:province":"MS",
    "wof:name":"Mactoc Farm",
    "wof:placetype":"venue"
},
  "geometry": {"coordinates":[-88.75808000000001,33.345487],"type":"Point"}
}