{
  "type": "Feature",
  "properties": {
    "addr:full":"9049 Hwy 51 N Southaven MS 38671",
    "addr:housenumber":"9049",
    "addr:postcode":"38671",
    "addr:street":"Hwy 51 N",
    "iso:country":"US",
    "sg:address":"9049 Hwy 51 N",
    "sg:city":"Southaven",
    "sg:classifiers":[
        {
            "category":"Sports & Exercise",
            "subcategory":"Gym",
            "type":"Entertainment"
        }
    ],
    "sg:phone":"+1 662 280 8500",
    "sg:postcode":"38671",
    "sg:province":"MS",
    "sg:tags":[
        "club",
        "health",
        "studio",
        "gymnasium"
    ],
    "wof:name":"Curves For Women",
    "wof:placetype":"venue"
},
  "geometry": {"coordinates":[-90.022949,34.992275],"type":"Point"}
}