{
  "type": "Feature",
  "properties": {
    "addr:full":"9390 E Pkwy N Lauderdale MS 39335",
    "addr:housenumber":"9390",
    "addr:postcode":"39335",
    "addr:street":"E Pkwy N",
    "iso:country":"US",
    "sg:address":"9390 E Pkwy N",
    "sg:city":"Lauderdale",
    "sg:classifiers":[
        {
            "category":"Organizations",
            "subcategory":"Professional Association",
            "type":"Services"
        }
    ],
    "sg:phone":"+1 601 632 4315",
    "sg:postcode":"39335",
    "sg:province":"MS",
    "wof:name":"Dalewood Property Owners Inc",
    "wof:placetype":"venue"
},
  "geometry": {"coordinates":[-88.503812,32.502163],"type":"Point"}
}