{
  "type": "Feature",
  "properties": {
    "addr:full":"310 E Westbrook St West Point MS 39773",
    "addr:housenumber":"310",
    "addr:postcode":"39773",
    "addr:street":"E Westbrook St",
    "iso:country":"US",
    "sg:address":"310 E Westbrook St",
    "sg:city":"West Point",
    "sg:classifiers":[
        {
            "category":"Government",
            "subcategory":"Jail",
            "type":"Public Place"
        }
    ],
    "sg:phone":"+1 662 494 1713",
    "sg:postcode":"39773",
    "sg:province":"MS",
    "sg:tags":[
        "govt",
        "state",
        "institution"
    ],
    "wof:name":"Corrections DEPT",
    "wof:placetype":"venue"
},
  "geometry": {"coordinates":[-88.648338,33.603538],"type":"Point"}
}