{
  "type": "Feature",
  "properties": {
    "iso:country":"US",
    "sg:address":"4850 Watkins Dr",
    "sg:city":"Jackson",
    "sg:classifiers":[
        {
            "category":"Social Services",
            "type":"Services"
        }
    ],
    "sg:phone":"+1 601 982 0526",
    "sg:postcode":"39206",
    "sg:province":"MS",
    "wof:name":"Family Youth Initiatives Inc",
    "wof:placetype":"venue"
},
  "geometry": {"coordinates":[-90.192701,32.368298],"type":"Point"}
}