{
  "type": "Feature",
  "properties": {
    "iso:country":"US",
    "sg:address":"108 Basket St",
    "sg:city":"Itta Bena",
    "sg:classifiers":[
        {
            "category":"Health Services",
            "subcategory":"Clinic",
            "type":"Services"
        }
    ],
    "sg:phone":"+1 662 254 6004",
    "sg:postcode":"38941",
    "sg:province":"MS",
    "sg:tags":[
        "information",
        "program",
        "referral"
    ],
    "sg:website":"www.deltahealthpartners.com",
    "wof:name":"Delta Healthpartners",
    "wof:placetype":"venue"
},
  "geometry": {"coordinates":[-90.319913,33.494622],"type":"Point"}
}