{
  "type": "Feature",
  "properties": {
    "iso:country":"US",
    "sg:address":"400 E Gillespie St",
    "sg:city":"Starkville",
    "sg:classifiers":[
        {
            "category":"Real Estate",
            "subcategory":"Real Estate Operator",
            "type":"Services"
        }
    ],
    "sg:phone":"+1 662 323 6704",
    "sg:postcode":"39759",
    "sg:province":"MS",
    "sg:tags":[
        "building",
        "apartment",
        "association"
    ],
    "wof:name":"Colonial Arms",
    "wof:placetype":"venue"
},
  "geometry": {"coordinates":[-88.811904,33.45803],"type":"Point"}
}