{
  "type": "Feature",
  "properties": {
    "iso:country":"US",
    "sg:address":"4024 Westside Dr",
    "sg:city":"Tupelo",
    "sg:classifiers":[
        {
            "category":"Home & Garden",
            "subcategory":"Hardware",
            "type":"Retail Goods"
        }
    ],
    "sg:phone":"+1 662 841 0033",
    "sg:postcode":"38801",
    "sg:province":"MS",
    "sg:tags":[
        "tool",
        "used"
    ],
    "wof:name":"Drake Atwood Tool & Supply",
    "wof:placetype":"venue"
},
  "geometry": {"coordinates":[-88.77290000000001,34.250795],"type":"Point"}
}