{
  "type": "Feature",
  "properties": {
    "iso:country":"US",
    "sg:address":"2501 Glendale Ave",
    "sg:city":"Hattiesburg",
    "sg:classifiers":[
        {
            "category":"Wholesale",
            "subcategory":"Meat",
            "type":"Manufacturing & Wholesale Goods"
        }
    ],
    "sg:phone":"+1 601 582 9300",
    "sg:postcode":"39401",
    "sg:province":"MS",
    "sg:tags":[
        "prod",
        "prepared"
    ],
    "wof:name":"Enslin & Son Packing Co",
    "wof:placetype":"venue"
},
  "geometry": {"coordinates":[-89.30561,31.363491],"type":"Point"}
}