{
  "type": "Feature",
  "properties": {
    "iso:country":"US",
    "sg:address":"2837 Co Rd 440",
    "sg:city":"Quitman",
    "sg:classifiers":[
        {
            "category":"Farming",
            "subcategory":"Farm & Veterinary Services",
            "type":"Manufacturing & Wholesale Goods"
        }
    ],
    "sg:phone":"+1 601 776 2561",
    "sg:postcode":"39355",
    "sg:province":"MS",
    "sg:tags":[
        "livestock"
    ],
    "wof:name":"Slay Processing",
    "wof:placetype":"venue"
},
  "geometry": {"coordinates":[-88.617345,32.05611],"type":"Point"}
}