{
  "type": "Feature",
  "properties": {
    "addr:full":"125 Culley Dr Jackson MS 39206",
    "addr:housenumber":"125",
    "addr:postcode":"39206",
    "addr:street":"Culley Dr",
    "iso:country":"US",
    "sg:address":"125 Culley Dr",
    "sg:city":"Jackson",
    "sg:classifiers":[
        {
            "category":"Building & Trades",
            "subcategory":"Landscaping Services",
            "type":"Services"
        }
    ],
    "sg:phone":"+1 601 981 2175",
    "sg:postcode":"39206",
    "sg:province":"MS",
    "sg:tags":[
        "lawn",
        "garden"
    ],
    "wof:name":"Halle Landscape Maintenance",
    "wof:placetype":"venue"
},
  "geometry": {"coordinates":[-90.16112200000001,32.377966],"type":"Point"}
}