{
  "type": "Feature",
  "properties": {
    "iso:country":"US",
    "sg:address":"2944 Woodbine St",
    "sg:city":"Jackson",
    "sg:classifiers":[
        {
            "category":"Building & Trades",
            "subcategory":"Construction",
            "type":"Services"
        }
    ],
    "sg:phone":"+1 601 371 8707",
    "sg:postcode":"39212",
    "sg:province":"MS",
    "sg:tags":[
        "paving",
        "contractor"
    ],
    "wof:name":"Jackson Asphalt & Concrete",
    "wof:placetype":"venue"
},
  "geometry": {"coordinates":[-90.229083,32.261958],"type":"Point"}
}