{
  "type": "Feature",
  "properties": {
    "addr:full":"20 Eastgate Dr Brandon MS 39042",
    "addr:housenumber":"20",
    "addr:postcode":"39042",
    "addr:street":"Eastgate Dr",
    "iso:country":"US",
    "sg:address":"20 Eastgate Dr",
    "sg:city":"Brandon",
    "sg:classifiers":[
        {
            "category":"Real Estate",
            "subcategory":"Real Estate Services",
            "type":"Services"
        }
    ],
    "sg:phone":"+1 601 824 9464",
    "sg:postcode":"39042",
    "sg:province":"MS",
    "sg:tags":[
        "abstract",
        "title"
    ],
    "wof:name":"Stewart Information Svcs Corp",
    "wof:placetype":"venue"
},
  "geometry": {"coordinates":[-90.006502,32.294858],"type":"Point"}
}