{
  "type": "Feature",
  "properties": {
    "iso:country":"US",
    "sg:address":"207 Old Hwy 26 W",
    "sg:city":"Poplarville",
    "sg:classifiers":[
        {
            "category":"Manufacturing",
            "subcategory":"Lumber",
            "type":"Manufacturing & Wholesale Goods"
        }
    ],
    "sg:phone":"+1 601 795 2286",
    "sg:postcode":"39470",
    "sg:province":"MS",
    "sg:tags":[
        "forester"
    ],
    "wof:name":"Bennett & Peters Inc",
    "wof:placetype":"venue"
},
  "geometry": {"coordinates":[-89.618944,30.814961],"type":"Point"}
}