{
  "type": "Feature",
  "properties": {
    "iso:country":"US",
    "sg:address":"1106 Government St",
    "sg:city":"Ocean Springs",
    "sg:classifiers":[
        {
            "category":"Travel",
            "subcategory":"Travel Agent",
            "type":"Entertainment"
        }
    ],
    "sg:phone":"+1 228 818 9255",
    "sg:postcode":"39564",
    "sg:province":"MS",
    "sg:tags":[
        "tours",
        "promoter"
    ],
    "wof:name":"Pero Guides",
    "wof:placetype":"venue"
},
  "geometry": {"coordinates":[-88.825757,30.413529],"type":"Point"}
}