{
  "type": "Feature",
  "properties": {
    "addr:full":"100 Eddie Smith Rd Hattiesburg MS 39401",
    "addr:housenumber":"100",
    "addr:postcode":"39401",
    "addr:street":"Eddie Smith Rd",
    "iso:country":"US",
    "sg:address":"100 Eddie Smith Rd",
    "sg:city":"Hattiesburg",
    "sg:classifiers":[
        {
            "category":"Personal",
            "type":"Services"
        }
    ],
    "sg:phone":"+1 601 583 0599",
    "sg:postcode":"39401",
    "sg:province":"MS",
    "sg:tags":[
        "consultant",
        "program",
        "health",
        "fitness"
    ],
    "wof:name":"Caffee Caffee & Assoc",
    "wof:placetype":"venue"
},
  "geometry": {"coordinates":[-89.3794,31.42809],"type":"Point"}
}