{
  "type": "Feature",
  "properties": {
    "iso:country":"US",
    "sg:address":"34 Fred Ellzey Rd",
    "sg:city":"Soso",
    "sg:classifiers":[
        {
            "category":"Building & Trades",
            "subcategory":"Construction",
            "type":"Services"
        }
    ],
    "sg:phone":"+1 601 763 3477",
    "sg:postcode":"39480",
    "sg:province":"MS",
    "sg:tags":[
        "water",
        "well",
        "drilling"
    ],
    "wof:name":"Patterson Drilling",
    "wof:placetype":"venue"
},
  "geometry": {"coordinates":[-89.32284799999999,31.659721],"type":"Point"}
}