{
  "type": "Feature",
  "properties": {
    "iso:country":"US",
    "sg:address":"5207 Main St",
    "sg:city":"Lucedale",
    "sg:classifiers":[
        {
            "category":"Autos & Motor Vehicles",
            "subcategory":"Fuel & Gas Station",
            "type":"Retail Goods"
        }
    ],
    "sg:phone":"+1 601 947 6581",
    "sg:postcode":"39452",
    "sg:province":"MS",
    "sg:tags":[
        "oil"
    ],
    "wof:name":"Pure Oil",
    "wof:placetype":"venue"
},
  "geometry": {"coordinates":[-88.58469100000001,30.924779],"type":"Point"}
}