{
  "type": "Feature",
  "properties": {
    "iso:country":"US",
    "sg:address":"1405 E Northside Dr",
    "sg:city":"Clinton",
    "sg:classifiers":[
        {
            "category":"Autos & Motor Vehicles",
            "subcategory":"Auto Supplies",
            "type":"Retail Goods"
        }
    ],
    "sg:phone":"+1 601 924 3800",
    "sg:postcode":"39056",
    "sg:province":"MS",
    "sg:tags":[
        "tire"
    ],
    "wof:name":"Northside Firestone",
    "wof:placetype":"venue"
},
  "geometry": {"coordinates":[-90.307395,32.351802],"type":"Point"}
}