{
  "type": "Feature",
  "properties": {
    "addr:full":"1804 N Frontage Rd Meridian MS 39301",
    "addr:housenumber":"1804",
    "addr:postcode":"39301",
    "addr:street":"N Frontage Rd",
    "iso:country":"US",
    "sg:address":"1804 N Frontage Rd",
    "sg:city":"Meridian",
    "sg:classifiers":[
        {
            "category":"Restaurant",
            "type":"Food & Drink"
        }
    ],
    "sg:menulink":"http://www.allmenus.com/ms/meridian/183243-kfc---kentucky-fried-chicken/menu/",
    "sg:phone":"+1 601 693 4431",
    "sg:postcode":"39301",
    "sg:province":"MS",
    "sg:tags":[
        "american",
        "chicken"
    ],
    "wof:name":"KFC - Kentucky Fried Chicken",
    "wof:placetype":"venue"
},
  "geometry": {"coordinates":[-88.687563,32.355981],"type":"Point"}
}