{
  "type": "Feature",
  "properties": {
    "iso:country":"US",
    "sg:address":"3958 Shaw Rd",
    "sg:city":"Sturgis",
    "sg:classifiers":[
        {
            "category":"Personal",
            "subcategory":"Beauty Salon",
            "type":"Services"
        }
    ],
    "sg:phone":"+1 662 323 4247",
    "sg:postcode":"39769",
    "sg:province":"MS",
    "sg:tags":[
        "shop"
    ],
    "wof:name":"Head Hunters Beauty Salon",
    "wof:placetype":"venue"
},
  "geometry": {"coordinates":[-89.07867299999999,33.356792],"type":"Point"}
}