{
  "type": "Feature",
  "properties": {
    "iso:country":"US",
    "sg:address":"944 Poplar Blvd",
    "sg:city":"Jackson",
    "sg:classifiers":[
        {
            "category":"Real Estate",
            "subcategory":"Real Estate Agent",
            "type":"Services"
        }
    ],
    "sg:phone":"+1 601 949 9999",
    "sg:postcode":"39202",
    "sg:province":"MS",
    "sg:website":"www.henrylarose.com",
    "wof:name":"Bellhaven Properties Inc",
    "wof:placetype":"venue"
},
  "geometry": {"coordinates":[-90.17432100000001,32.315121],"type":"Point"}
}