{
  "type": "Feature",
  "properties": {
    "iso:country":"US",
    "sg:address":"13368 C Necaise Rd",
    "sg:city":"Pass Christian",
    "sg:classifiers":[
        {
            "category":"Organizations",
            "subcategory":"Religious Organization",
            "type":"Services"
        }
    ],
    "sg:phone":"+1 228 255 4017",
    "sg:postcode":"39571",
    "sg:province":"MS",
    "wof:name":"Herbert Dorman Rev",
    "wof:placetype":"venue"
},
  "geometry": {"coordinates":[-89.319936,30.479742],"type":"Point"}
}