{
  "type": "Feature",
  "properties": {
    "addr:full":"231 Main St Greenville MS 38701",
    "addr:housenumber":"231",
    "addr:postcode":"38701",
    "addr:street":"Main St",
    "iso:country":"US",
    "sg:address":"231 Main St",
    "sg:city":"Greenville",
    "sg:classifiers":[
        {
            "category":"Shopping",
            "subcategory":"Pharmacy",
            "type":"Retail Goods"
        }
    ],
    "sg:phone":"+1 662 332 0913",
    "sg:postcode":"38701",
    "sg:province":"MS",
    "wof:name":"Connected Office Products Inc",
    "wof:placetype":"venue"
},
  "geometry": {"coordinates":[-91.064527,33.41148],"type":"Point"}
}