{
  "type": "Feature",
  "properties": {
    "iso:country":"US",
    "sg:address":"8705 US Hwy 61",
    "sg:city":"Walls",
    "sg:classifiers":[
        {
            "category":"Real Estate",
            "subcategory":"Real Estate Operator",
            "type":"Services"
        }
    ],
    "sg:phone":"+1 662 781 1010",
    "sg:postcode":"38680",
    "sg:province":"MS",
    "sg:tags":[
        "mobile",
        "home",
        "community"
    ],
    "wof:name":"Lakeview Mobile Home Park",
    "wof:placetype":"venue"
},
  "geometry": {"coordinates":[-90.13815099999999,34.982671],"type":"Point"}
}