{
  "type": "Feature",
  "properties": {
    "iso:country":"US",
    "sg:address":"14504 Dedeaux Rd",
    "sg:city":"Gulfport",
    "sg:classifiers":[
        {
            "category":"Retail",
            "subcategory":"Auto Repair",
            "type":"Services"
        }
    ],
    "sg:phone":"+1 228 832 9257",
    "sg:postcode":"39503",
    "sg:province":"MS",
    "sg:tags":[
        "exhaust"
    ],
    "wof:name":"Klein Muffler and Brake Inc",
    "wof:placetype":"venue"
},
  "geometry": {"coordinates":[-89.08647000000001,30.449567],"type":"Point"}
}