{
  "type": "Feature",
  "properties": {
    "iso:country":"US",
    "sg:address":"1509 S Adams St",
    "sg:city":"Fulton",
    "sg:classifiers":[
        {
            "category":"Shopping",
            "subcategory":"Tobacco",
            "type":"Retail Goods"
        }
    ],
    "sg:phone":"+1 662 862 5089",
    "sg:postcode":"38843",
    "sg:province":"MS",
    "sg:tags":[
        "cigarette",
        "cigar",
        "dealer"
    ],
    "wof:name":"Tobacco Center",
    "wof:placetype":"venue"
},
  "geometry": {"coordinates":[-88.40423699999999,34.252433],"type":"Point"}
}