{
  "type": "Feature",
  "properties": {
    "addr:full":"709 N Adams St Ripley MS 38663",
    "addr:housenumber":"709",
    "addr:postcode":"38663",
    "addr:street":"N Adams St",
    "iso:country":"US",
    "sg:address":"709 N Adams St",
    "sg:city":"Ripley",
    "sg:classifiers":[
        {
            "category":"Organizations",
            "subcategory":"Religious Organization",
            "type":"Services"
        }
    ],
    "sg:phone":"+1 662 837 4438",
    "sg:postcode":"38663",
    "sg:province":"MS",
    "sg:tags":[
        "church"
    ],
    "wof:name":"Ripley Second Baptist Church",
    "wof:placetype":"venue"
},
  "geometry": {"coordinates":[-88.95090399999999,34.735683],"type":"Point"}
}