{
  "type": "Feature",
  "properties": {
    "iso:country":"US",
    "sg:address":"119 N Washington St",
    "sg:city":"Starkville",
    "sg:classifiers":[
        {
            "category":"Education",
            "subcategory":"Vocational School",
            "type":"Public Place"
        }
    ],
    "sg:phone":"+1 662 320 4171",
    "sg:postcode":"39759",
    "sg:province":"MS",
    "sg:tags":[
        "training",
        "computer"
    ],
    "wof:name":"Evolution Technology Ctr",
    "wof:placetype":"venue"
},
  "geometry": {"coordinates":[-88.816552,33.46468],"type":"Point"}
}