{
  "type": "Feature",
  "properties": {
    "addr:full":"1040 Perry Farm Rd Tunica MS 38676",
    "addr:housenumber":"1040",
    "addr:postcode":"38676",
    "addr:street":"Perry Farm Rd",
    "iso:country":"US",
    "sg:address":"1040 Perry Farm Rd",
    "sg:city":"Tunica",
    "sg:classifiers":[
        {
            "category":"Farming",
            "subcategory":"Farm",
            "type":"Manufacturing & Wholesale Goods"
        }
    ],
    "sg:phone":"+1 662 363 2345",
    "sg:postcode":"38676",
    "sg:province":"MS",
    "sg:tags":[
        "crop",
        "general"
    ],
    "wof:name":"Zig Zag Farms Inc",
    "wof:placetype":"venue"
},
  "geometry": {"coordinates":[-90.406023,34.743234],"type":"Point"}
}