{
  "type": "Feature",
  "properties": {
    "iso:country":"US",
    "sg:address":"243 N Broadway St",
    "sg:city":"Greenville",
    "sg:classifiers":[
        {
            "category":"Food & Beverages",
            "subcategory":"Liquor & Beverages",
            "type":"Retail Goods"
        }
    ],
    "sg:phone":"+1 662 335 9516",
    "sg:postcode":"38701",
    "sg:province":"MS",
    "sg:tags":[
        "alcoholic"
    ],
    "wof:name":"J & J Package Store",
    "wof:placetype":"venue"
},
  "geometry": {"coordinates":[-91.056612,33.412621],"type":"Point"}
}