{
  "type": "Feature",
  "properties": {
    "iso:country":"US",
    "sg:address":"1109 E Main St",
    "sg:city":"Tupelo",
    "sg:classifiers":[
        {
            "category":"Home & Garden",
            "subcategory":"Household Appliances",
            "type":"Retail Goods"
        }
    ],
    "sg:phone":"+1 662 844 9505",
    "sg:postcode":"38804",
    "sg:province":"MS",
    "sg:tags":[
        "repair",
        "electrical"
    ],
    "wof:name":"Rayburns Vaccuum Shop",
    "wof:placetype":"venue"
},
  "geometry": {"coordinates":[-88.681084,34.257549],"type":"Point"}
}