{
  "type": "Feature",
  "properties": {
    "iso:country":"US",
    "sg:address":"254 Yazoo Ave",
    "sg:city":"Clarksdale",
    "sg:classifiers":[
        {
            "category":"Banks & Credit Unions",
            "subcategory":"Bank",
            "type":"Services"
        }
    ],
    "sg:phone":"+1 662 624 6736",
    "sg:postcode":"38614",
    "sg:province":"MS",
    "sg:tags":[
        "loan"
    ],
    "wof:name":"Tower Loan",
    "wof:placetype":"venue"
},
  "geometry": {"coordinates":[-90.573516,34.202141],"type":"Point"}
}