{
  "type": "Feature",
  "properties": {
    "iso:country":"US",
    "sg:address":"1400 Country Club Rd",
    "sg:city":"Hattiesburg",
    "sg:classifiers":[
        {
            "category":"Organizations",
            "subcategory":"Religious Organization",
            "type":"Services"
        }
    ],
    "sg:phone":"+1 601 584 8364",
    "sg:postcode":"39401",
    "sg:province":"MS",
    "wof:name":"Mississippi Baptist Seminary",
    "wof:placetype":"venue"
},
  "geometry": {"coordinates":[-89.31125900000001,31.304183],"type":"Point"}
}