{
  "type": "Feature",
  "properties": {
    "iso:country":"US",
    "sg:address":"9181 Collinsville Cir",
    "sg:city":"Collinsville",
    "sg:classifiers":[
        {
            "category":"Insurance",
            "subcategory":"Insurance Agent",
            "type":"Services"
        }
    ],
    "sg:phone":"+1 601 626 0089",
    "sg:postcode":"39325",
    "sg:province":"MS",
    "wof:name":"Mony Group",
    "wof:placetype":"venue"
},
  "geometry": {"coordinates":[-88.85380499999999,32.50014],"type":"Point"}
}