{
  "type": "Feature",
  "properties": {
    "iso:country":"US",
    "sg:address":"6895 US Hwy 49",
    "sg:city":"Hattiesburg",
    "sg:classifiers":[
        {
            "category":"Retail",
            "subcategory":"Auto Repair",
            "type":"Services"
        }
    ],
    "sg:phone":"+1 601 296 0322",
    "sg:postcode":"39402",
    "sg:province":"MS",
    "sg:tags":[
        "repairing",
        "automobile"
    ],
    "wof:name":"Big 10 Tire",
    "wof:placetype":"venue"
},
  "geometry": {"coordinates":[-89.35709199999999,31.36831],"type":"Point"}
}