{
  "type": "Feature",
  "properties": {
    "iso:country":"US",
    "sg:address":"201 S Spring St",
    "sg:city":"Tupelo",
    "sg:classifiers":[
        {
            "category":"Professional",
            "subcategory":"Lawyer & Legal Services",
            "type":"Services"
        }
    ],
    "sg:phone":"+1 662 842 7907",
    "sg:postcode":"38804",
    "sg:province":"MS",
    "sg:tags":[
        "attorney"
    ],
    "sg:website":"www.phelpsdunbar.com",
    "wof:name":"Phelps Dunbar",
    "wof:placetype":"venue"
},
  "geometry": {"coordinates":[-88.704441,34.256644],"type":"Point"}
}