{
  "type": "Feature",
  "properties": {
    "iso:country":"US",
    "sg:address":"1013 S Main St",
    "sg:city":"Petal",
    "sg:classifiers":[
        {
            "category":"Retail",
            "subcategory":"Laundry & Dry Cleaning",
            "type":"Services"
        }
    ],
    "sg:phone":"+1 601 544 5866",
    "sg:postcode":"39465",
    "sg:province":"MS",
    "sg:tags":[
        "a",
        "garment",
        "agent"
    ],
    "wof:name":"Magnolia Cleaners",
    "wof:placetype":"venue"
},
  "geometry": {"coordinates":[-89.26340999999999,31.329378],"type":"Point"}
}