{
  "type": "Feature",
  "properties": {
    "iso:country":"US",
    "sg:address":"6071 US Hwy 49",
    "sg:city":"Hattiesburg",
    "sg:classifiers":[
        {
            "category":"Health Services",
            "subcategory":"Doctor",
            "type":"Services"
        }
    ],
    "sg:phone":"+1 601 579 6485",
    "sg:postcode":"39401",
    "sg:province":"MS",
    "sg:tags":[
        "physician",
        "surgeon"
    ],
    "wof:name":"Southern Neurologic & Spinal",
    "wof:placetype":"venue"
},
  "geometry": {"coordinates":[-89.341476,31.352292],"type":"Point"}
}