{
  "type": "Feature",
  "properties": {
    "addr:full":"5815 W 4th St Hattiesburg MS 39402",
    "addr:housenumber":"5815",
    "addr:postcode":"39402",
    "addr:street":"W 4Th St",
    "iso:country":"US",
    "sg:address":"5815 W 4th St",
    "sg:city":"Hattiesburg",
    "sg:classifiers":[
        {
            "category":"Building & Trades",
            "subcategory":"Landscaping Services",
            "type":"Services"
        }
    ],
    "sg:phone":"+1 601 264 9223",
    "sg:postcode":"39402",
    "sg:province":"MS",
    "sg:tags":[
        "lawn",
        "maintenance",
        "grounds"
    ],
    "wof:name":"Prestige Landscape LLC",
    "wof:placetype":"venue"
},
  "geometry": {"coordinates":[-89.430477,31.332149],"type":"Point"}
}