{
  "type": "Feature",
  "properties": {
    "addr:full":"9008 McLaurin St Bay St Louis MS 39520",
    "addr:housenumber":"9008",
    "addr:postcode":"39520",
    "addr:street":"Mclaurin St",
    "iso:country":"US",
    "sg:address":"9008 McLaurin St",
    "sg:city":"Bay St Louis",
    "sg:classifiers":[
        {
            "category":"Recreation",
            "type":"Entertainment"
        }
    ],
    "sg:phone":"+1 228 467 9116",
    "sg:postcode":"39520",
    "sg:province":"MS",
    "sg:tags":[
        "skating",
        "sporting",
        "rink"
    ],
    "wof:name":"Twin Pines Roller Rink",
    "wof:placetype":"venue"
},
  "geometry": {"coordinates":[-89.37520600000001,30.308832],"type":"Point"}
}