{
  "type": "Feature",
  "properties": {
    "addr:full":"6065 State Hwy 15 Louisville MS 39339",
    "addr:housenumber":"6065",
    "addr:postcode":"39339",
    "addr:street":"State Hwy 15",
    "iso:country":"US",
    "sg:address":"6065 State Hwy 15",
    "sg:city":"Louisville",
    "sg:classifiers":[
        {
            "category":"Retail",
            "subcategory":"Repair Shop",
            "type":"Services"
        }
    ],
    "sg:phone":"+1 662 773 8236",
    "sg:postcode":"39339",
    "sg:province":"MS",
    "sg:tags":[
        "refinishing",
        "furniture"
    ],
    "wof:name":"Gene's Wood Craft Ctr",
    "wof:placetype":"venue"
},
  "geometry": {"coordinates":[-89.060548,33.035967],"type":"Point"}
}