{
  "type": "Feature",
  "properties": {
    "addr:full":"200 N Canal St Natchez MS 39120",
    "addr:housenumber":"200",
    "addr:postcode":"39120",
    "addr:street":"N Canal St",
    "iso:country":"US",
    "sg:address":"200 N Canal St",
    "sg:city":"Natchez",
    "sg:classifiers":[
        {
            "category":"Mining & Drilling",
            "type":"Manufacturing & Wholesale Goods"
        }
    ],
    "sg:phone":"+1 601 442 1601",
    "sg:postcode":"39120",
    "sg:province":"MS",
    "sg:tags":[
        "development",
        "gas",
        "oil",
        "exploration"
    ],
    "sg:website":"www.callon.com",
    "wof:name":"Callon Petroleum Co",
    "wof:placetype":"venue"
},
  "geometry": {"coordinates":[-91.40379900000001,31.563209],"type":"Point"}
}