{
  "type": "Feature",
  "properties": {
    "addr:full":"2111 W 4th St Hattiesburg MS 39401",
    "addr:housenumber":"2111",
    "addr:postcode":"39401",
    "addr:street":"W 4Th St",
    "iso:country":"US",
    "sg:address":"2111 W 4th St",
    "sg:city":"Hattiesburg",
    "sg:classifiers":[
        {
            "category":"Retail",
            "subcategory":"Repair Shop",
            "type":"Services"
        }
    ],
    "sg:phone":"+1 601 583 4858",
    "sg:postcode":"39401",
    "sg:province":"MS",
    "sg:tags":[
        "equipment",
        "electronic",
        "supply"
    ],
    "wof:name":"Electronic Repairs",
    "wof:placetype":"venue"
},
  "geometry": {"coordinates":[-89.32231400000001,31.331953],"type":"Point"}
}