{
  "type": "Feature",
  "properties": {
    "iso:country":"US",
    "sg:address":"114 Veterans Memorial Dr",
    "sg:city":"Kosciusko",
    "sg:classifiers":[
        {
            "category":"Banks & Credit Unions",
            "subcategory":"Bank",
            "type":"Services"
        }
    ],
    "sg:phone":"+1 662 289 2323",
    "sg:postcode":"39090",
    "sg:province":"MS",
    "sg:tags":[
        "personal",
        "institution"
    ],
    "wof:name":"Citifinancial",
    "wof:placetype":"venue"
},
  "geometry": {"coordinates":[-89.57731800000001,33.063999],"type":"Point"}
}