{
  "type": "Feature",
  "properties": {
    "iso:country":"US",
    "sg:address":"1910 N 14th Ave",
    "sg:city":"Columbus",
    "sg:classifiers":[
        {
            "category":"Communications",
            "subcategory":"Radio Station",
            "type":"Services"
        }
    ],
    "sg:phone":"+1 662 328 9227",
    "sg:postcode":"39701",
    "sg:province":"MS",
    "sg:tags":[
        "company",
        "broadcasting"
    ],
    "wof:name":"FM Request Line",
    "wof:placetype":"venue"
},
  "geometry": {"coordinates":[-88.412307,33.510656],"type":"Point"}
}