{
  "type": "Feature",
  "properties": {
    "addr:full":"706 US Hwy 61 Clarksdale MS 38614",
    "addr:housenumber":"706",
    "addr:postcode":"38614",
    "addr:street":"Us Hwy 61",
    "iso:country":"US",
    "sg:address":"706 US Hwy 61",
    "sg:city":"Clarksdale",
    "sg:classifiers":[
        {
            "category":"Restaurant",
            "type":"Food & Drink"
        }
    ],
    "sg:phone":"+1 662 627 5223",
    "sg:postcode":"38614",
    "sg:province":"MS",
    "sg:tags":[
        "eating"
    ],
    "wof:name":"Shoneys Restaurant",
    "wof:placetype":"venue"
},
  "geometry": {"coordinates":[-90.580303,34.188728],"type":"Point"}
}