{
  "type": "Feature",
  "properties": {
    "iso:country":"US",
    "sg:address":"360 Co Rd 409",
    "sg:city":"Houlka",
    "sg:classifiers":[
        {
            "category":"Manufacturing",
            "subcategory":"Furniture",
            "type":"Manufacturing & Wholesale Goods"
        }
    ],
    "sg:phone":"+1 662 568 2614",
    "sg:postcode":"38850",
    "sg:province":"MS",
    "sg:tags":[
        "wood"
    ],
    "wof:name":"C & L Furniture Mfg Co",
    "wof:placetype":"venue"
},
  "geometry": {"coordinates":[-89.06912199999999,34.065297],"type":"Point"}
}