{
  "type": "Feature",
  "properties": {
    "addr:full":"139 Lakeshore Rd Pelahatchie MS 39145",
    "addr:housenumber":"139",
    "addr:postcode":"39145",
    "addr:street":"Lakeshore Rd",
    "iso:country":"US",
    "sg:address":"139 Lakeshore Rd",
    "sg:city":"Pelahatchie",
    "sg:classifiers":[
        {
            "category":"Building & Trades",
            "subcategory":"Construction",
            "type":"Services"
        }
    ],
    "sg:phone":"+1 601 854 6006",
    "sg:postcode":"39145",
    "sg:province":"MS",
    "sg:tags":[
        "contractor"
    ],
    "wof:name":"JP Drywall Painting",
    "wof:placetype":"venue"
},
  "geometry": {"coordinates":[-89.81408399999999,32.337651],"type":"Point"}
}