{
  "type": "Feature",
  "properties": {
    "iso:country":"US",
    "sg:address":"20 Co Rd 508",
    "sg:city":"Corinth",
    "sg:classifiers":[
        {
            "category":"Farming",
            "subcategory":"Poultry Farm",
            "type":"Manufacturing & Wholesale Goods"
        }
    ],
    "sg:phone":"+1 662 287 1574",
    "sg:postcode":"38834",
    "sg:province":"MS",
    "sg:tags":[
        "operation",
        "timber",
        "egg",
        "tract"
    ],
    "wof:name":"Don Jobe Farm",
    "wof:placetype":"venue"
},
  "geometry": {"coordinates":[-88.554652,34.896649],"type":"Point"}
}