{
  "type": "Feature",
  "properties": {
    "addr:full":"129 Craig Dr Saltillo MS 38851",
    "addr:housenumber":"129",
    "addr:postcode":"38851",
    "addr:street":"Craig Dr",
    "iso:country":"US",
    "sg:address":"129 Craig Dr",
    "sg:city":"Saltillo",
    "sg:classifiers":[
        {
            "category":"Restaurant",
            "type":"Food & Drink"
        }
    ],
    "sg:phone":"+1 662 869 3347",
    "sg:postcode":"38851",
    "sg:province":"MS",
    "wof:name":"Subway Sandwiches & Salads",
    "wof:placetype":"venue"
},
  "geometry": {"coordinates":[-89.000461,33.930204],"type":"Point"}
}