{
  "type": "Feature",
  "properties": {
    "iso:country":"US",
    "sg:address":"7024 Washington Ave",
    "sg:city":"Ocean Springs",
    "sg:classifiers":[
        {
            "category":"Building & Trades",
            "subcategory":"Construction",
            "type":"Services"
        }
    ],
    "sg:phone":"+1 228 875 5902",
    "sg:postcode":"39564",
    "sg:province":"MS",
    "sg:tags":[
        "contractor"
    ],
    "wof:name":"Johnson Homes Inc",
    "wof:placetype":"venue"
},
  "geometry": {"coordinates":[-88.838807,30.443477],"type":"Point"}
}