{
  "type": "Feature",
  "properties": {
    "addr:full":"6217 US Hwy 84 Soso MS 39480",
    "addr:housenumber":"6217",
    "addr:postcode":"39480",
    "addr:street":"Us Hwy 84",
    "iso:country":"US",
    "sg:address":"6217 US Hwy 84",
    "sg:city":"Soso",
    "sg:classifiers":[
        {
            "category":"Farming",
            "subcategory":"Poultry Farm",
            "type":"Manufacturing & Wholesale Goods"
        }
    ],
    "sg:phone":"+1 601 763 6003",
    "sg:postcode":"39480",
    "sg:province":"MS",
    "sg:tags":[
        "chicken"
    ],
    "wof:name":"Morgan Poultry Farm",
    "wof:placetype":"venue"
},
  "geometry": {"coordinates":[-89.26076999999999,31.6753],"type":"Point"}
}