{
  "type": "Feature",
  "properties": {
    "iso:country":"US",
    "sg:address":"1700 Terry Rd",
    "sg:city":"Jackson",
    "sg:classifiers":[
        {
            "category":"Building & Trades",
            "subcategory":"Equipment Rental",
            "type":"Services"
        }
    ],
    "sg:phone":"+1 601 969 0026",
    "sg:postcode":"39204",
    "sg:province":"MS",
    "wof:name":"Rto Super Store",
    "wof:placetype":"venue"
},
  "geometry": {"coordinates":[-90.207184,32.284923],"type":"Point"}
}