{
  "type": "Feature",
  "properties": {
    "iso:country":"US",
    "sg:address":"168 Kennel Rd",
    "sg:city":"Columbus",
    "sg:classifiers":[
        {
            "category":"Retail",
            "subcategory":"Animal Services",
            "type":"Services"
        }
    ],
    "sg:phone":"+1 662 328 8877",
    "sg:postcode":"39705",
    "sg:province":"MS",
    "sg:tags":[
        "pet",
        "boarding",
        "sitting"
    ],
    "wof:name":"Swan Kennels & Training Ctr",
    "wof:placetype":"venue"
},
  "geometry": {"coordinates":[-88.40621400000001,33.532592],"type":"Point"}
}