{
  "type": "Feature",
  "properties": {
    "addr:full":"1844 Hwy 11 and 80 Meridian MS 39301",
    "addr:housenumber":"1844;80",
    "addr:postcode":"39301",
    "addr:street":"Hwy 11 And;Meridian",
    "iso:country":"US",
    "sg:address":"1844 Hwy 11 and 80",
    "sg:city":"Meridian",
    "sg:classifiers":[
        {
            "category":"Social Services",
            "subcategory":"Child Care",
            "type":"Services"
        }
    ],
    "sg:phone":"+1 601 483 0878",
    "sg:postcode":"39301",
    "sg:province":"MS",
    "wof:name":"Potter's Wheel Christian Dycr",
    "wof:placetype":"venue"
},
  "geometry": {"coordinates":[-88.590506,32.404872],"type":"Point"}
}