{
  "type": "Feature",
  "properties": {
    "iso:country":"US",
    "sg:address":"1350 N Lamar Blvd",
    "sg:city":"Oxford",
    "sg:classifiers":[
        {
            "category":"Retail",
            "subcategory":"Funeral Services",
            "type":"Services"
        }
    ],
    "sg:phone":"+1 662 238 7787",
    "sg:postcode":"38655",
    "sg:province":"MS",
    "sg:tags":[
        "director"
    ],
    "wof:name":"Serenity Funeral Home",
    "wof:placetype":"venue"
},
  "geometry": {"coordinates":[-89.51006599999999,34.381415],"type":"Point"}
}