{
  "type": "Feature",
  "properties": {
    "iso:country":"US",
    "sg:address":"3263 Hwy 80 W",
    "sg:city":"Jackson",
    "sg:classifiers":[
        {
            "category":"Wholesale",
            "subcategory":"Machinery & Supplies",
            "type":"Manufacturing & Wholesale Goods"
        }
    ],
    "sg:phone":"+1 601 969 6000",
    "sg:postcode":"39204",
    "sg:province":"MS",
    "sg:tags":[
        "contractor"
    ],
    "sg:website":"www.puckettmachinery.com",
    "wof:name":"Caterpillar Inc",
    "wof:placetype":"venue"
},
  "geometry": {"coordinates":[-90.237849,32.29614],"type":"Point"}
}