{
  "type": "Feature",
  "properties": {
    "iso:country":"US",
    "sg:address":"139 W Bankhead St",
    "sg:city":"New Albany",
    "sg:classifiers":[
        {
            "category":"Home & Garden",
            "subcategory":"Carpets & Floor Coverings",
            "type":"Retail Goods"
        }
    ],
    "sg:phone":"+1 662 534 7847",
    "sg:postcode":"38652",
    "sg:province":"MS",
    "sg:tags":[
        "rug"
    ],
    "wof:name":"Downtown Interiors",
    "wof:placetype":"venue"
},
  "geometry": {"coordinates":[-89.008692,34.494126],"type":"Point"}
}