{
  "type": "Feature",
  "properties": {
    "addr:full":"1158 Church Rd W Southaven MS 38671",
    "addr:housenumber":"1158",
    "addr:postcode":"38671",
    "addr:street":"Church Rd W",
    "iso:country":"US",
    "sg:address":"1158 Church Rd W",
    "sg:city":"Southaven",
    "sg:classifiers":[
        {
            "category":"Utilities",
            "subcategory":"Mobile Phone",
            "type":"Services"
        }
    ],
    "sg:phone":"+1 662 393 5305",
    "sg:postcode":"38671",
    "sg:province":"MS",
    "sg:tags":[
        "wireless",
        "communication"
    ],
    "wof:name":"Thompson Wireless - Cingular Wireless Authorized Dealer",
    "wof:placetype":"venue"
},
  "geometry": {"coordinates":[-90.010659,34.933554],"type":"Point"}
}