{
  "type": "Feature",
  "properties": {
    "addr:full":"1101 Memorial Blvd Picayune MS 39466",
    "addr:housenumber":"1101",
    "addr:postcode":"39466",
    "addr:street":"Memorial Blvd",
    "iso:country":"US",
    "sg:address":"1101 Memorial Blvd",
    "sg:city":"Picayune",
    "sg:classifiers":[
        {
            "category":"Autos & Motor Vehicles",
            "subcategory":"Fuel & Gas Station",
            "type":"Retail Goods"
        }
    ],
    "sg:phone":"+1 601 798 8518",
    "sg:postcode":"39466",
    "sg:province":"MS",
    "sg:tags":[
        "station",
        "gasoline"
    ],
    "wof:name":"Texaco",
    "wof:placetype":"venue"
},
  "geometry": {"coordinates":[-89.666416,30.517837],"type":"Point"}
}