{
  "type": "Feature",
  "properties": {
    "addr:full":"491 New Hope Church Rd Foxworth MS 39483",
    "addr:housenumber":"491",
    "addr:postcode":"39483",
    "addr:street":"New Hope Church Rd",
    "iso:country":"US",
    "sg:address":"491 New Hope Church Rd",
    "sg:city":"Foxworth",
    "sg:classifiers":[
        {
            "category":"Food & Beverages",
            "subcategory":"Groceries & Convenience Stores",
            "type":"Retail Goods"
        }
    ],
    "sg:phone":"+1 601 736 6582",
    "sg:postcode":"39483",
    "sg:province":"MS",
    "sg:tags":[
        "grocer"
    ],
    "wof:name":"Slocum's Grocery",
    "wof:placetype":"venue"
},
  "geometry": {"coordinates":[-89.91240999999999,31.154239],"type":"Point"}
}