{
  "type": "Feature",
  "properties": {
    "iso:country":"US",
    "sg:address":"10196 Lorraine Rd",
    "sg:city":"Gulfport",
    "sg:classifiers":[
        {
            "category":"Building & Trades",
            "subcategory":"Equipment Rental",
            "type":"Services"
        }
    ],
    "sg:phone":"+1 228 896 5383",
    "sg:postcode":"39501",
    "sg:province":"MS",
    "sg:tags":[
        "scaffolding"
    ],
    "wof:name":"Crenshaw Supply Co",
    "wof:placetype":"venue"
},
  "geometry": {"coordinates":[-89.03107,30.429227],"type":"Point"}
}