{
  "type": "Feature",
  "properties": {
    "iso:country":"US",
    "sg:address":"122 T Smith Rd",
    "sg:city":"Hattiesburg",
    "sg:classifiers":[
        {
            "category":"Shopping",
            "type":"Retail Goods"
        }
    ],
    "sg:phone":"+1 601 583 0828",
    "sg:postcode":"39401",
    "sg:province":"MS",
    "sg:tags":[
        "repair",
        "livestock",
        "merchandise"
    ],
    "wof:name":"T Smith Livestock Sales",
    "wof:placetype":"venue"
},
  "geometry": {"coordinates":[-89.328638,31.405089],"type":"Point"}
}