{
  "type": "Feature",
  "properties": {
    "addr:full":"769 Brookway Blvd Brookhaven MS 39601",
    "addr:housenumber":"769",
    "addr:postcode":"39601",
    "addr:street":"Brookway Blvd",
    "iso:country":"US",
    "sg:address":"769 Brookway Blvd",
    "sg:city":"Brookhaven",
    "sg:classifiers":[
        {
            "category":"Building & Trades",
            "subcategory":"Equipment Rental",
            "type":"Services"
        }
    ],
    "sg:phone":"+1 601 835 3225",
    "sg:postcode":"39601",
    "sg:province":"MS",
    "sg:tags":[
        "leasing",
        "furniture"
    ],
    "wof:name":"Rent Way",
    "wof:placetype":"venue"
},
  "geometry": {"coordinates":[-90.459125,31.579427],"type":"Point"}
}