{
  "type": "Feature",
  "properties": {
    "iso:country":"US",
    "sg:address":"5250 I- 55 N",
    "sg:city":"Jackson",
    "sg:classifiers":[
        {
            "category":"Banks & Credit Unions",
            "subcategory":"Investment Brokerage",
            "type":"Services"
        }
    ],
    "sg:phone":"+1 601 956 0990",
    "sg:postcode":"39211",
    "sg:province":"MS",
    "sg:tags":[
        "stockbroker",
        "stock",
        "bond"
    ],
    "wof:name":"H & R Block Financial Advisors",
    "wof:placetype":"venue"
},
  "geometry": {"coordinates":[-90.14696600000001,32.37831],"type":"Point"}
}