{
  "type": "Feature",
  "properties": {
    "addr:full":"2248 N Country Club Ln Biloxi MS 39532",
    "addr:housenumber":"2248",
    "addr:postcode":"39532",
    "addr:street":"N Country Club Ln",
    "iso:country":"US",
    "sg:address":"2248 N Country Club Ln",
    "sg:city":"Biloxi",
    "sg:classifiers":[
        {
            "category":"Professional",
            "type":"Services"
        }
    ],
    "sg:phone":"+1 228 896 5005",
    "sg:postcode":"39532",
    "sg:province":"MS",
    "wof:name":"Webspinners Inc",
    "wof:placetype":"venue"
},
  "geometry": {"coordinates":[-88.971175,30.435508],"type":"Point"}
}