{
  "type": "Feature",
  "properties": {
    "addr:full":"7028 US Hwy 49 Hattiesburg MS 39402",
    "addr:housenumber":"7028",
    "addr:postcode":"39402",
    "addr:street":"Us Hwy 49",
    "iso:country":"US",
    "sg:address":"7028 US Hwy 49",
    "sg:city":"Hattiesburg",
    "sg:classifiers":[
        {
            "category":"Shopping",
            "subcategory":"Clothing, Apparel, & Fashions",
            "type":"Retail Goods"
        }
    ],
    "sg:phone":"+1 601 268 1244",
    "sg:postcode":"39402",
    "sg:province":"MS",
    "sg:tags":[
        "uniform",
        "supply"
    ],
    "sg:website":"www.gkservices.com",
    "wof:name":"G & K Svc",
    "wof:placetype":"venue"
},
  "geometry": {"coordinates":[-89.3651,31.377519],"type":"Point"}
}