{
  "type": "Feature",
  "properties": {
    "iso:country":"US",
    "sg:address":"1843 W Irwin Ave",
    "sg:city":"Tunica",
    "sg:classifiers":[
        {
            "category":"Retail",
            "subcategory":"Animal Services",
            "type":"Services"
        }
    ],
    "sg:phone":"+1 662 363 3009",
    "sg:postcode":"38676",
    "sg:province":"MS",
    "wof:name":"Happy Tails Groom & Board Inc",
    "wof:placetype":"venue"
},
  "geometry": {"coordinates":[-90.379749,34.697138],"type":"Point"}
}