{
  "type": "Feature",
  "properties": {
    "iso:country":"US",
    "sg:address":"411 Desert Ln",
    "sg:city":"Woodville",
    "sg:classifiers":[
        {
            "category":"Farming",
            "subcategory":"Livestock Farm",
            "type":"Manufacturing & Wholesale Goods"
        },
        {
            "category":"Travel",
            "subcategory":"Hotels & Motels",
            "type":"Entertainment"
        }
    ],
    "sg:phone":"+1 601 888 6889",
    "sg:postcode":"39669",
    "sg:province":"MS",
    "sg:tags":[
        "breakfast",
        "accommodation",
        "bed",
        "general"
    ],
    "wof:name":"Desert Plantation B & B",
    "wof:placetype":"venue"
},
  "geometry": {"coordinates":[-91.47468000000001,31.025987],"type":"Point"}
}