{
  "type": "Feature",
  "properties": {
    "addr:full":"7024 Oakley Palestine Rd Terry MS 39170",
    "addr:housenumber":"7024",
    "addr:postcode":"39170",
    "addr:street":"Oakley Palestine Rd",
    "iso:country":"US",
    "sg:address":"7024 Oakley Palestine Rd",
    "sg:city":"Terry",
    "sg:classifiers":[
        {
            "category":"Wholesale",
            "subcategory":"Farm Supplies",
            "type":"Manufacturing & Wholesale Goods"
        }
    ],
    "sg:phone":"+1 601 857 5232",
    "sg:postcode":"39170",
    "sg:province":"MS",
    "sg:tags":[
        "buyer",
        "livestock"
    ],
    "wof:name":"Ross Cattle Co",
    "wof:placetype":"venue"
},
  "geometry": {"coordinates":[-90.38031599999999,32.188236],"type":"Point"}
}