{
  "type": "Feature",
  "properties": {
    "iso:country":"US",
    "sg:address":"3535 Albermarle Rd",
    "sg:city":"Jackson",
    "sg:classifiers":[
        {
            "category":"Education",
            "subcategory":"School",
            "type":"Public Place"
        }
    ],
    "sg:phone":"+1 601 987 3573",
    "sg:postcode":"39213",
    "sg:province":"MS",
    "wof:name":"Brinkley Middle School",
    "wof:placetype":"venue"
},
  "geometry": {"coordinates":[-90.20384799999999,32.33996],"type":"Point"}
}