{
  "type": "Feature",
  "properties": {
    "iso:country":"US",
    "sg:address":"4330 Hwy 39 N",
    "sg:city":"Meridian",
    "sg:classifiers":[
        {
            "category":"Wholesale",
            "subcategory":"Hardware",
            "type":"Manufacturing & Wholesale Goods"
        }
    ],
    "sg:phone":"+1 601 693 2911",
    "sg:postcode":"39301",
    "sg:province":"MS",
    "sg:tags":[
        "plumbing",
        "fixture",
        "supply"
    ],
    "sg:website":"www.southernpipe.com",
    "wof:name":"Southern Pipe & Supply Co Inc",
    "wof:placetype":"venue"
},
  "geometry": {"coordinates":[-88.67846400000001,32.402182],"type":"Point"}
}