{
  "type": "Feature",
  "properties": {
    "iso:country":"US",
    "sg:address":"4510 Hanging Moss Rd",
    "sg:city":"Jackson",
    "sg:classifiers":[
        {
            "category":"Health Services",
            "subcategory":"Doctor",
            "type":"Services"
        }
    ],
    "sg:phone":"+1 601 981 6011",
    "sg:postcode":"39206",
    "sg:province":"MS",
    "sg:tags":[
        "physician",
        "surgeon"
    ],
    "wof:name":"Visions Physical Therapy",
    "wof:placetype":"venue"
},
  "geometry": {"coordinates":[-90.179773,32.365715],"type":"Point"}
}