{
  "type": "Feature",
  "properties": {
    "iso:country":"US",
    "sg:address":"55 Susanne St",
    "sg:city":"Lucedale",
    "sg:classifiers":[
        {
            "category":"Health Services",
            "subcategory":"Nursing And Care Facility",
            "type":"Services"
        }
    ],
    "sg:phone":"+1 601 947 2784",
    "sg:postcode":"39452",
    "sg:province":"MS",
    "sg:tags":[
        "skilled"
    ],
    "wof:name":"Delco Inc",
    "wof:placetype":"venue"
},
  "geometry": {"coordinates":[-88.600908,30.912026],"type":"Point"}
}