{
  "type": "Feature",
  "properties": {
    "iso:country":"US",
    "sg:address":"510 Shannon St",
    "sg:city":"Belzoni",
    "sg:classifiers":[
        {
            "category":"Banks & Credit Unions",
            "subcategory":"Bank",
            "type":"Services"
        }
    ],
    "sg:phone":"+1 662 247 1664",
    "sg:postcode":"39038",
    "sg:province":"MS",
    "sg:tags":[
        "depository",
        "banking"
    ],
    "wof:name":"Fast Cash",
    "wof:placetype":"venue"
},
  "geometry": {"coordinates":[-90.47355,33.183603],"type":"Point"}
}