{
  "type": "Feature",
  "properties": {
    "iso:country":"US",
    "sg:address":"3255 Pascagoula St",
    "sg:city":"Pascagoula",
    "sg:classifiers":[
        {
            "category":"Food & Beverages",
            "subcategory":"Bakery",
            "type":"Retail Goods"
        }
    ],
    "sg:phone":"+1 228 769 5944",
    "sg:postcode":"39567",
    "sg:province":"MS",
    "sg:tags":[
        "baker"
    ],
    "wof:name":"Scranton's Catering",
    "wof:placetype":"venue"
},
  "geometry": {"coordinates":[-88.556658,30.367161],"type":"Point"}
}