{
  "type": "Feature",
  "properties": {
    "addr:full":"3100 Pascagoula St Pascagoula MS 39567",
    "addr:housenumber":"3100",
    "addr:postcode":"39567",
    "addr:street":"Pascagoula St",
    "iso:country":"US",
    "sg:address":"3100 Pascagoula St",
    "sg:city":"Pascagoula",
    "sg:classifiers":[
        {
            "category":"Government",
            "subcategory":"Office",
            "type":"Public Place"
        }
    ],
    "sg:phone":"+1 228 762 5400",
    "sg:postcode":"39567",
    "sg:province":"MS",
    "sg:tags":[
        "executive"
    ],
    "wof:name":"Lott Clint US Senator",
    "wof:placetype":"venue"
},
  "geometry": {"coordinates":[-88.556501,30.365662],"type":"Point"}
}