{
  "type": "Feature",
  "properties": {
    "iso:country":"US",
    "sg:address":"2735 Bailey Ave",
    "sg:city":"Jackson",
    "sg:classifiers":[
        {
            "category":"Wholesale",
            "subcategory":"Construction Materials",
            "type":"Manufacturing & Wholesale Goods"
        }
    ],
    "sg:phone":"+1 601 368 3000",
    "sg:postcode":"39213",
    "sg:province":"MS",
    "sg:tags":[
        "insulation"
    ],
    "wof:name":"Branton Industries Inc",
    "wof:placetype":"venue"
},
  "geometry": {"coordinates":[-90.192769,32.333279],"type":"Point"}
}