{
  "type": "Feature",
  "properties": {
    "iso:country":"US",
    "sg:address":"5205 I- 55 N",
    "sg:city":"Jackson",
    "sg:classifiers":[
        {
            "category":"Wholesale",
            "subcategory":"Meat",
            "type":"Manufacturing & Wholesale Goods"
        }
    ],
    "sg:phone":"+1 601 372 7554",
    "sg:postcode":"39206",
    "sg:province":"MS",
    "sg:tags":[
        "packer"
    ],
    "wof:name":"Lee's Venison Charcuterie",
    "wof:placetype":"venue"
},
  "geometry": {"coordinates":[-90.149736,32.369075],"type":"Point"}
}