{
  "type": "Feature",
  "properties": {
    "addr:full":"121 Main St Raleigh MS 39154",
    "addr:housenumber":"121",
    "addr:postcode":"39154",
    "addr:street":"Main St",
    "iso:country":"US",
    "sg:address":"121 Main St",
    "sg:city":"Raleigh",
    "sg:classifiers":[
        {
            "category":"Professional",
            "subcategory":"Lawyer & Legal Services",
            "type":"Services"
        }
    ],
    "sg:phone":"+1 601 782 4273",
    "sg:postcode":"39154",
    "sg:province":"MS",
    "sg:tags":[
        "attorney"
    ],
    "wof:name":"Gary R King",
    "wof:placetype":"venue"
},
  "geometry": {"coordinates":[-90.546908,32.196983],"type":"Point"}
}