{
  "type": "Feature",
  "properties": {
    "addr:full":"399 Cauthen St Canton MS 39046",
    "addr:housenumber":"399",
    "addr:postcode":"39046",
    "addr:street":"Cauthen St",
    "iso:country":"US",
    "sg:address":"399 Cauthen St",
    "sg:city":"Canton",
    "sg:classifiers":[
        {
            "category":"Health Services",
            "subcategory":"Nursing And Care Facility",
            "type":"Services"
        }
    ],
    "sg:phone":"+1 601 859 8414",
    "sg:postcode":"39046",
    "sg:province":"MS",
    "sg:tags":[
        "skilled"
    ],
    "wof:name":"Christian Care Asstd Lvng Cntr",
    "wof:placetype":"venue"
},
  "geometry": {"coordinates":[-90.046379,32.607763],"type":"Point"}
}