{
  "type": "Feature",
  "properties": {
    "addr:full":"114 Lower Woodville Rd Natchez MS 39120",
    "addr:housenumber":"114",
    "addr:postcode":"39120",
    "addr:street":"Lower Woodville Rd",
    "iso:country":"US",
    "sg:address":"114 Lower Woodville Rd",
    "sg:city":"Natchez",
    "sg:classifiers":[
        {
            "category":"Health Services",
            "subcategory":"Clinic",
            "type":"Services"
        }
    ],
    "sg:phone":"+1 601 446 8622",
    "sg:postcode":"39120",
    "sg:province":"MS",
    "sg:tags":[
        "specialty",
        "outpatient"
    ],
    "wof:name":"Brentwood Bhvral Hlthcare Miss",
    "wof:placetype":"venue"
},
  "geometry": {"coordinates":[-91.397526,31.538334],"type":"Point"}
}