{
  "type": "Feature",
  "properties": {
    "addr:full":"1610 Curtis Dr Iuka MS 38852",
    "addr:housenumber":"1610",
    "addr:postcode":"38852",
    "addr:street":"Curtis Dr",
    "iso:country":"US",
    "sg:address":"1610 Curtis Dr",
    "sg:city":"Iuka",
    "sg:classifiers":[
        {
            "category":"Restaurant",
            "type":"Food & Drink"
        }
    ],
    "sg:menulink":"http://www.allmenus.com/ms/blythe-crossing/156119-hardees/menu/",
    "sg:phone":"+1 662 423 1008",
    "sg:postcode":"38852",
    "sg:province":"MS",
    "sg:tags":[
        "burger",
        "american"
    ],
    "wof:name":"Hardee's",
    "wof:placetype":"venue"
},
  "geometry": {"coordinates":[-88.206597,34.803658],"type":"Point"}
}