{
  "type": "Feature",
  "properties": {
    "iso:country":"US",
    "sg:address":"253 Spring St",
    "sg:city":"Waynesboro",
    "sg:classifiers":[
        {
            "category":"Organizations",
            "subcategory":"Religious Organization",
            "type":"Services"
        }
    ],
    "sg:phone":"+1 601 735 2479",
    "sg:postcode":"39367",
    "sg:province":"MS",
    "sg:tags":[
        "church"
    ],
    "wof:name":"St Luke Baptist Church",
    "wof:placetype":"venue"
},
  "geometry": {"coordinates":[-88.636867,31.669824],"type":"Point"}
}