{
  "type": "Feature",
  "properties": {
    "addr:full":"111 Co Rd 1119 Saltillo MS 38866",
    "addr:housenumber":"111;1119",
    "addr:postcode":"38866",
    "addr:street":"Co Rd",
    "iso:country":"US",
    "sg:address":"111 Co Rd 1119",
    "sg:city":"Saltillo",
    "sg:classifiers":[
        {
            "category":"Building & Trades",
            "subcategory":"Construction",
            "type":"Services"
        }
    ],
    "sg:phone":"+1 662 869 1766",
    "sg:postcode":"38866",
    "sg:province":"MS",
    "sg:tags":[
        "concrete",
        "contractor"
    ],
    "wof:name":"Slaytons Concrete Construction",
    "wof:placetype":"venue"
},
  "geometry": {"coordinates":[-88.636909,34.361804],"type":"Point"}
}