{
  "type": "Feature",
  "properties": {
    "iso:country":"US",
    "sg:address":"318 Memorial Blvd",
    "sg:city":"Picayune",
    "sg:classifiers":[
        {
            "category":"Health Services",
            "subcategory":"Clinic",
            "type":"Services"
        }
    ],
    "sg:phone":"+1 601 798 9693",
    "sg:postcode":"39466",
    "sg:province":"MS",
    "sg:tags":[
        "banks",
        "blood",
        "center"
    ],
    "wof:name":"Blood Center Of Picayune",
    "wof:placetype":"venue"
},
  "geometry": {"coordinates":[-89.67767000000001,30.516376],"type":"Point"}
}