{
  "type": "Feature",
  "properties": {
    "addr:full":"131 Rue Magnolia Biloxi MS 39530",
    "addr:housenumber":"131",
    "addr:postcode":"39530",
    "addr:street":"Rue Magnolia",
    "iso:country":"US",
    "sg:address":"131 Rue Magnolia",
    "sg:city":"Biloxi",
    "sg:classifiers":[
        {
            "category":"Real Estate",
            "subcategory":"Architect",
            "type":"Services"
        }
    ],
    "sg:phone":"+1 228 436 4222",
    "sg:postcode":"39530",
    "sg:province":"MS",
    "wof:name":"Studio South Architects",
    "wof:placetype":"venue"
},
  "geometry": {"coordinates":[-88.88902400000001,30.395014],"type":"Point"}
}