{
  "type": "Feature",
  "properties": {
    "iso:country":"US",
    "sg:address":"520 College Hill Rd",
    "sg:city":"Oxford",
    "sg:classifiers":[
        {
            "category":"Health Services",
            "subcategory":"Health Practitioner",
            "type":"Services"
        },
        {
            "category":"Social Services",
            "type":"Services"
        }
    ],
    "sg:phone":"+1 662 234 8611",
    "sg:postcode":"38655",
    "sg:province":"MS",
    "sg:tags":[
        "psychotherapist"
    ],
    "wof:name":"Anne Strand Dr",
    "wof:placetype":"venue"
},
  "geometry": {"coordinates":[-89.539242,34.376335],"type":"Point"}
}