{
  "type": "Feature",
  "properties": {
    "iso:country":"US",
    "sg:address":"1423 Old Square Rd",
    "sg:city":"Jackson",
    "sg:classifiers":[
        {
            "category":"Sports & Exercise",
            "subcategory":"Bowling",
            "type":"Entertainment"
        }
    ],
    "sg:phone":"+1 601 362 1513",
    "sg:postcode":"39211",
    "sg:province":"MS",
    "wof:name":"Larwil Lanes Bowling Ctr",
    "wof:placetype":"venue"
},
  "geometry": {"coordinates":[-90.148802,32.362018],"type":"Point"}
}