{
  "type": "Feature",
  "properties": {
    "iso:country":"US",
    "sg:address":"555 Industrial Dr S",
    "sg:city":"Madison",
    "sg:classifiers":[
        {
            "category":"Retail",
            "subcategory":"Repair Shop",
            "type":"Services"
        }
    ],
    "sg:phone":"+1 601 856 2274",
    "sg:postcode":"39110",
    "sg:province":"MS",
    "sg:tags":[
        "helicopter",
        "support",
        "maintenance",
        "government"
    ],
    "wof:name":"Army Fleet Support LLC",
    "wof:placetype":"venue"
},
  "geometry": {"coordinates":[-90.09768200000001,32.514076],"type":"Point"}
}