{
  "type": "Feature",
  "properties": {
    "iso:country":"US",
    "sg:address":"10216 3rd Ave",
    "sg:city":"Diberville",
    "sg:classifiers":[
        {
            "category":"Wholesale",
            "subcategory":"Medical Equipment & Supplies",
            "type":"Manufacturing & Wholesale Goods"
        }
    ],
    "sg:phone":"+1 228 354 0010",
    "sg:postcode":"39540",
    "sg:province":"MS",
    "sg:tags":[
        "physician",
        "surgeon"
    ],
    "wof:name":"Oxy Pro Inc",
    "wof:placetype":"venue"
},
  "geometry": {"coordinates":[-88.89294599999999,30.433453],"type":"Point"}
}