{
  "type": "Feature",
  "properties": {
    "addr:full":"5651 Hwy 25 Brandon MS 39232",
    "addr:housenumber":"5651",
    "addr:postcode":"39232",
    "addr:street":"Hwy 25",
    "iso:country":"US",
    "sg:address":"5651 Hwy 25",
    "sg:city":"Brandon",
    "sg:classifiers":[
        {
            "category":"Restaurant",
            "type":"Food & Drink"
        }
    ],
    "sg:phone":"+1 601 919 2000",
    "sg:postcode":"39232",
    "sg:province":"MS",
    "sg:tags":[
        "eating",
        "pizza"
    ],
    "sg:website":"www.soulshinepizza.com",
    "wof:name":"Soulshine Pizza Co",
    "wof:placetype":"venue"
},
  "geometry": {"coordinates":[-90.03411199999999,32.350473],"type":"Point"}
}