{
  "type": "Feature",
  "properties": {
    "iso:country":"US",
    "sg:address":"2315 4th St",
    "sg:city":"Meridian",
    "sg:classifiers":[
        {
            "category":"Recreation",
            "subcategory":"Amusement Park",
            "type":"Entertainment"
        }
    ],
    "sg:phone":"+1 601 483 1180",
    "sg:postcode":"39301",
    "sg:province":"MS",
    "wof:name":"Lucky's Sports",
    "wof:placetype":"venue"
},
  "geometry": {"coordinates":[-88.70046499999999,32.362622],"type":"Point"}
}