{
  "type": "Feature",
  "properties": {
    "iso:country":"US",
    "sg:address":"805 W Park Ave",
    "sg:city":"Greenwood",
    "sg:classifiers":[
        {
            "category":"Real Estate",
            "subcategory":"Real Estate Agent",
            "type":"Services"
        }
    ],
    "sg:phone":"+1 662 453 5153",
    "sg:postcode":"38930",
    "sg:province":"MS",
    "wof:name":"Henderson Investment Co",
    "wof:placetype":"venue"
},
  "geometry": {"coordinates":[-90.201723,33.527765],"type":"Point"}
}