{
  "type": "Feature",
  "properties": {
    "iso:country":"US",
    "sg:address":"189 Colonial Cir",
    "sg:city":"Magee",
    "sg:classifiers":[
        {
            "category":"Wholesale",
            "subcategory":"Jewelry",
            "type":"Manufacturing & Wholesale Goods"
        }
    ],
    "sg:phone":"+1 601 261 2767",
    "sg:postcode":"39111",
    "sg:province":"MS",
    "sg:tags":[
        "stone"
    ],
    "wof:name":"B & A Bead Company",
    "wof:placetype":"venue"
},
  "geometry": {"coordinates":[-89.728292,31.887955],"type":"Point"}
}