{
  "type": "Feature",
  "properties": {
    "addr:full":"214 James St Union MS 39365",
    "addr:housenumber":"214",
    "addr:postcode":"39365",
    "addr:street":"James St",
    "iso:country":"US",
    "sg:address":"214 James St",
    "sg:city":"Union",
    "sg:classifiers":[
        {
            "category":"Shopping",
            "subcategory":"Bicycles & Sporting Goods",
            "type":"Retail Goods"
        }
    ],
    "sg:phone":"+1 601 774 8983",
    "sg:postcode":"39365",
    "sg:province":"MS",
    "wof:name":"Ferrell & Co",
    "wof:placetype":"venue"
},
  "geometry": {"coordinates":[-89.11406100000001,32.567052],"type":"Point"}
}