{
  "type": "Feature",
  "properties": {
    "iso:country":"US",
    "sg:address":"620 S Applegate St",
    "sg:city":"Winona",
    "sg:classifiers":[
        {
            "category":"Professional",
            "subcategory":"Accounting & Tax Preparation",
            "type":"Services"
        }
    ],
    "sg:phone":"+1 662 283 4401",
    "sg:postcode":"38967",
    "sg:province":"MS",
    "sg:tags":[
        "return",
        "filing"
    ],
    "wof:name":"H & R Block Tax Svc",
    "wof:placetype":"venue"
},
  "geometry": {"coordinates":[-89.735428,33.471565],"type":"Point"}
}