{
  "type": "Feature",
  "properties": {
    "iso:country":"US",
    "sg:address":"311 W Russell Ave",
    "sg:city":"Calhoun City",
    "sg:classifiers":[
        {
            "category":"Personal",
            "subcategory":"Beauty Salon",
            "type":"Services"
        }
    ],
    "sg:phone":"+1 662 628 5344",
    "sg:postcode":"38916",
    "sg:province":"MS",
    "wof:name":"Hair Reflections",
    "wof:placetype":"venue"
},
  "geometry": {"coordinates":[-89.31532799999999,33.855169],"type":"Point"}
}