{
  "type": "Feature",
  "properties": {
    "addr:full":"228 1st St Grenada MS 38901",
    "addr:housenumber":"228",
    "addr:postcode":"38901",
    "addr:street":"1St St",
    "iso:country":"US",
    "sg:address":"228 1st St",
    "sg:city":"Grenada",
    "sg:classifiers":[
        {
            "category":"Real Estate",
            "subcategory":"Surveying",
            "type":"Services"
        }
    ],
    "sg:phone":"+1 662 226 3505",
    "sg:postcode":"38901",
    "sg:province":"MS",
    "sg:tags":[
        "surveyor"
    ],
    "wof:name":"Joe A Sutherland Jr",
    "wof:placetype":"venue"
},
  "geometry": {"coordinates":[-89.802021,33.784497],"type":"Point"}
}