{
  "type": "Feature",
  "properties": {
    "iso:country":"US",
    "sg:address":"118 S Glenfield Rd",
    "sg:city":"New Albany",
    "sg:classifiers":[
        {
            "category":"Health Services",
            "subcategory":"Nursing And Care Facility",
            "type":"Services"
        }
    ],
    "sg:phone":"+1 662 534 9506",
    "sg:postcode":"38652",
    "sg:province":"MS",
    "sg:tags":[
        "skilled"
    ],
    "wof:name":"Rose Lawn Retirement Home",
    "wof:placetype":"venue"
},
  "geometry": {"coordinates":[-89.03423600000001,34.508584],"type":"Point"}
}