{
  "type": "Feature",
  "properties": {
    "iso:country":"US",
    "sg:address":"2531 45th Ave",
    "sg:city":"Meridian",
    "sg:classifiers":[
        {
            "category":"Building & Trades",
            "subcategory":"Plumbing",
            "type":"Services"
        }
    ],
    "sg:phone":"+1 601 485 9828",
    "sg:postcode":"39307",
    "sg:province":"MS",
    "sg:tags":[
        "plumbing",
        "contractor"
    ],
    "wof:name":"Tibbetts Plumbing Inc",
    "wof:placetype":"venue"
},
  "geometry": {"coordinates":[-88.723187,32.384369],"type":"Point"}
}