{
  "type": "Feature",
  "properties": {
    "iso:country":"US",
    "sg:address":"302 N Jackson St",
    "sg:city":"Starkville",
    "sg:classifiers":[
        {
            "category":"Government",
            "subcategory":"Office",
            "type":"Public Place"
        }
    ],
    "sg:phone":"+1 662 323 9261",
    "sg:postcode":"39759",
    "sg:province":"MS",
    "sg:website":"www.ccs.state.ms.us",
    "wof:name":"Community Counseling Svc",
    "wof:placetype":"venue"
},
  "geometry": {"coordinates":[-88.81451,33.471131],"type":"Point"}
}