{
  "type": "Feature",
  "properties": {
    "addr:full":"2009 Carrollton Ave Greenwood MS 38930",
    "addr:housenumber":"2009",
    "addr:postcode":"38930",
    "addr:street":"Carrollton Ave",
    "iso:country":"US",
    "sg:address":"2009 Carrollton Ave",
    "sg:city":"Greenwood",
    "sg:classifiers":[
        {
            "category":"Wholesale",
            "subcategory":"Auto Parts",
            "type":"Manufacturing & Wholesale Goods"
        }
    ],
    "sg:phone":"+1 662 453 0600",
    "sg:postcode":"38930",
    "sg:province":"MS",
    "wof:name":"Bucks-City Radiator",
    "wof:placetype":"venue"
},
  "geometry": {"coordinates":[-90.158023,33.517439],"type":"Point"}
}