{
  "type": "Feature",
  "properties": {
    "iso:country":"US",
    "sg:address":"126 Sassafrass Ln",
    "sg:city":"Florence",
    "sg:classifiers":[
        {
            "category":"Professional",
            "subcategory":"Management & Consulting",
            "type":"Services"
        }
    ],
    "sg:phone":"+1 601 939 5168",
    "sg:postcode":"39073",
    "sg:province":"MS",
    "wof:name":"Linda Hales",
    "wof:placetype":"venue"
},
  "geometry": {"coordinates":[-90.127171,32.188856],"type":"Point"}
}