{
  "type": "Feature",
  "properties": {
    "iso:country":"US",
    "sg:address":"6600 Amherst Dr",
    "sg:city":"Ocean Springs",
    "sg:classifiers":[
        {
            "category":"Professional",
            "subcategory":"Business Services",
            "type":"Services"
        }
    ],
    "sg:phone":"+1 228 324 3286",
    "sg:postcode":"39564",
    "sg:province":"MS",
    "sg:tags":[
        "pool"
    ],
    "wof:name":"Webbs Pool Service",
    "wof:placetype":"venue"
},
  "geometry": {"coordinates":[-88.81997699999999,30.43895],"type":"Point"}
}