{
  "type": "Feature",
  "properties": {
    "iso:country":"US",
    "sg:address":"934 Denny Ave",
    "sg:city":"Pascagoula",
    "sg:classifiers":[
        {
            "category":"Food & Beverages",
            "subcategory":"Groceries & Convenience Stores",
            "type":"Retail Goods"
        }
    ],
    "sg:phone":"+1 228 762 7478",
    "sg:postcode":"39567",
    "sg:province":"MS",
    "wof:name":"Fast Trac",
    "wof:placetype":"venue"
},
  "geometry": {"coordinates":[-88.55522999999999,30.370784],"type":"Point"}
}