{
  "type": "Feature",
  "properties": {
    "iso:country":"US",
    "sg:address":"1605 S Gallatin St",
    "sg:city":"Jackson",
    "sg:classifiers":[
        {
            "category":"Building & Trades",
            "subcategory":"Pest Control",
            "type":"Services"
        }
    ],
    "sg:phone":"+1 601 353 5111",
    "sg:postcode":"39201",
    "sg:province":"MS",
    "wof:name":"H & H Termite & Lawn Care",
    "wof:placetype":"venue"
},
  "geometry": {"coordinates":[-90.193022,32.282896],"type":"Point"}
}