{
  "type": "Feature",
  "properties": {
    "iso:country":"US",
    "sg:address":"701 Hillcrest Dr",
    "sg:city":"Laurel",
    "sg:classifiers":[
        {
            "category":"Government",
            "subcategory":"Fire Station",
            "type":"Public Place"
        }
    ],
    "sg:phone":"+1 601 428 6470",
    "sg:postcode":"39440",
    "sg:province":"MS",
    "sg:tags":[
        "department"
    ],
    "wof:name":"Laurel Fire Training Ctr",
    "wof:placetype":"venue"
},
  "geometry": {"coordinates":[-89.16366600000001,31.678341],"type":"Point"}
}