{
  "type": "Feature",
  "properties": {
    "iso:country":"US",
    "sg:address":"1214 Terry Rd",
    "sg:city":"Jackson",
    "sg:classifiers":[
        {
            "category":"Food & Beverages",
            "subcategory":"Liquor & Beverages",
            "type":"Retail Goods"
        }
    ],
    "sg:phone":"+1 601 354 3789",
    "sg:postcode":"39204",
    "sg:province":"MS",
    "wof:name":"Cedar Package Store",
    "wof:placetype":"venue"
},
  "geometry": {"coordinates":[-90.202265,32.2907],"type":"Point"}
}