{
  "type": "Feature",
  "properties": {
    "iso:country":"US",
    "sg:address":"14 Hughes Rd",
    "sg:city":"Hattiesburg",
    "sg:classifiers":[
        {
            "category":"Retail",
            "subcategory":"Auto Repair",
            "type":"Services"
        }
    ],
    "sg:phone":"+1 601 583 1317",
    "sg:postcode":"39402",
    "sg:province":"MS",
    "sg:tags":[
        "wrecker"
    ],
    "wof:name":"Walley's Quality Towing",
    "wof:placetype":"venue"
},
  "geometry": {"coordinates":[-89.44589499999999,31.262643],"type":"Point"}
}