{
  "type": "Feature",
  "properties": {
    "addr:full":"3510 Manor Dr Vicksburg MS 39180",
    "addr:housenumber":"3510",
    "addr:postcode":"39180",
    "addr:street":"Manor Dr",
    "iso:country":"US",
    "sg:address":"3510 Manor Dr",
    "sg:city":"Vicksburg",
    "sg:classifiers":[
        {
            "category":"Manufacturing",
            "subcategory":"Printing",
            "type":"Manufacturing & Wholesale Goods"
        }
    ],
    "sg:phone":"+1 601 638 0962",
    "sg:postcode":"39180",
    "sg:province":"MS",
    "sg:tags":[
        "printer"
    ],
    "wof:name":"Print Shop",
    "wof:placetype":"venue"
},
  "geometry": {"coordinates":[-90.866899,32.319041],"type":"Point"}
}