{
  "type": "Feature",
  "properties": {
    "addr:full":"835 Main St Greenville MS 38701",
    "addr:housenumber":"835",
    "addr:postcode":"38701",
    "addr:street":"Main St",
    "iso:country":"US",
    "sg:address":"835 Main St",
    "sg:city":"Greenville",
    "sg:classifiers":[
        {
            "category":"Organizations",
            "subcategory":"Political Organization",
            "type":"Services"
        }
    ],
    "sg:phone":"+1 662 335 1041",
    "sg:postcode":"38701",
    "sg:province":"MS",
    "wof:name":"Artman For Mayor Campaign",
    "wof:placetype":"venue"
},
  "geometry": {"coordinates":[-91.055351,33.406457],"type":"Point"}
}