{
  "type": "Feature",
  "properties": {
    "addr:full":"1716 26th Ave Gulfport MS 39501",
    "addr:housenumber":"1716",
    "addr:postcode":"39501",
    "addr:street":"26Th Ave",
    "iso:country":"US",
    "sg:address":"1716 26th Ave",
    "sg:city":"Gulfport",
    "sg:classifiers":[
        {
            "category":"Social Services",
            "subcategory":"Child Care",
            "type":"Services"
        }
    ],
    "sg:phone":"+1 228 868 2277",
    "sg:postcode":"39501",
    "sg:province":"MS",
    "sg:tags":[
        "day"
    ],
    "sg:website":"www.kdsahoy.com",
    "wof:name":"Kids Ahoy Inc",
    "wof:placetype":"venue"
},
  "geometry": {"coordinates":[-89.093898,30.372181],"type":"Point"}
}