{
  "type": "Feature",
  "properties": {
    "addr:full":"2300 Martin Luther King Blvd Clarksdale MS 38614",
    "addr:housenumber":"2300",
    "addr:postcode":"38614",
    "addr:street":"Martin Luther King Blvd",
    "iso:country":"US",
    "sg:address":"2300 Martin Luther King Blvd",
    "sg:city":"Clarksdale",
    "sg:classifiers":[
        {
            "category":"Place Of Worship",
            "subcategory":"Church",
            "type":"Public Place"
        },
        {
            "category":"Place Of Worship",
            "type":"Public Place"
        }
    ],
    "sg:phone":"+1 662 624 4713",
    "sg:postcode":"38614",
    "sg:province":"MS",
    "sg:tags":[
        "churches-baptist-general",
        "churches-baptist"
    ],
    "wof:name":"Damacus Missionary Baptists Ch",
    "wof:placetype":"venue"
},
  "geometry": {"coordinates":[-90.54866,34.206848],"type":"Point"}
}