{
  "type": "Feature",
  "properties": {
    "addr:full":"509 Campbell St Winona MS 38967",
    "addr:housenumber":"509",
    "addr:postcode":"38967",
    "addr:street":"Campbell St",
    "iso:country":"US",
    "sg:address":"509 Campbell St",
    "sg:city":"Winona",
    "sg:classifiers":[
        {
            "category":"Organizations",
            "subcategory":"Religious Organization",
            "type":"Services"
        }
    ],
    "sg:phone":"+1 662 283 4864",
    "sg:postcode":"38967",
    "sg:province":"MS",
    "sg:tags":[
        "church"
    ],
    "wof:name":"Haven United Methodist Church",
    "wof:placetype":"venue"
},
  "geometry": {"coordinates":[-89.734334,33.480288],"type":"Point"}
}