{
  "type": "Feature",
  "properties": {
    "iso:country":"US",
    "sg:address":"110 E Railroad Ave",
    "sg:city":"Calhoun City",
    "sg:classifiers":[
        {
            "category":"Wholesale",
            "subcategory":"Farm Supplies",
            "type":"Manufacturing & Wholesale Goods"
        }
    ],
    "sg:phone":"+1 662 628 6682",
    "sg:postcode":"38954",
    "sg:province":"MS",
    "wof:name":"Calhoun County Cooperative",
    "wof:placetype":"venue"
},
  "geometry": {"coordinates":[-90.207628,33.40866],"type":"Point"}
}