{
  "type": "Feature",
  "properties": {
    "addr:full":"1 Fioranelli Dr Cleveland MS 38732",
    "addr:housenumber":"1",
    "addr:postcode":"38732",
    "addr:street":"Fioranelli Dr",
    "iso:country":"US",
    "sg:address":"1 Fioranelli Dr",
    "sg:city":"Cleveland",
    "sg:classifiers":[
        {
            "category":"Real Estate",
            "subcategory":"Real Estate Operator",
            "type":"Services"
        }
    ],
    "sg:phone":"+1 662 843 7369",
    "sg:postcode":"38732",
    "sg:province":"MS",
    "sg:tags":[
        "mobile",
        "home",
        "community"
    ],
    "wof:name":"Fioranelli Mobile Home Court",
    "wof:placetype":"venue"
},
  "geometry": {"coordinates":[-90.759096,33.741092],"type":"Point"}
}