{
  "type": "Feature",
  "properties": {
    "iso:country":"US",
    "sg:address":"1055 Mendell Davis Dr",
    "sg:city":"Byram",
    "sg:classifiers":[
        {
            "category":"Manufacturing",
            "subcategory":"Tools & Machinery",
            "type":"Manufacturing & Wholesale Goods"
        }
    ],
    "sg:phone":"+1 601 372 3903",
    "sg:postcode":"39272",
    "sg:province":"MS",
    "sg:tags":[
        "industry"
    ],
    "wof:name":"Groen",
    "wof:placetype":"venue"
},
  "geometry": {"coordinates":[-90.26134399999999,32.165138],"type":"Point"}
}