{
  "type": "Feature",
  "properties": {
    "iso:country":"US",
    "sg:address":"645 Hwy 1 S",
    "sg:city":"Greenville",
    "sg:classifiers":[
        {
            "category":"Shopping",
            "subcategory":"Department Store",
            "type":"Retail Goods"
        }
    ],
    "sg:phone":"+1 662 335 6888",
    "sg:postcode":"38701",
    "sg:province":"MS",
    "wof:name":"Dollar Mainia",
    "wof:placetype":"venue"
},
  "geometry": {"coordinates":[-91.037921,33.399348],"type":"Point"}
}