{
  "type": "Feature",
  "properties": {
    "iso:country":"US",
    "sg:address":"46 Cherry St",
    "sg:city":"Grenada",
    "sg:classifiers":[
        {
            "category":"Personal",
            "subcategory":"Beauty Salon",
            "type":"Services"
        }
    ],
    "sg:phone":"+1 662 227 9851",
    "sg:postcode":"38901",
    "sg:province":"MS",
    "sg:tags":[
        "shop"
    ],
    "wof:name":"A Cut Above The Rest",
    "wof:placetype":"venue"
},
  "geometry": {"coordinates":[-89.805063,33.785526],"type":"Point"}
}