{
  "type": "Feature",
  "properties": {
    "iso:country":"US",
    "sg:address":"6129 U S Highway 98",
    "sg:city":"Hattiesburg",
    "sg:classifiers":[
        {
            "category":"Deli",
            "type":"Food & Drink"
        }
    ],
    "sg:menulink":"http://www.allmenus.com/ms/oloh/230009-lions-choice/menu/",
    "sg:phone":"+1 601 579 7077",
    "sg:postcode":"39402",
    "sg:province":"MS",
    "sg:tags":[
        "wrap",
        "american",
        "sandwich"
    ],
    "wof:name":"Lion's Choice",
    "wof:placetype":"venue"
},
  "geometry": {"coordinates":[-89.383743,31.321483],"type":"Point"}
}