{
  "type": "Feature",
  "properties": {
    "addr:full":"127 Mayfair Dr Jackson MS 39212",
    "addr:housenumber":"127",
    "addr:postcode":"39212",
    "addr:street":"Mayfair Dr",
    "iso:country":"US",
    "sg:address":"127 Mayfair Dr",
    "sg:city":"Jackson",
    "sg:classifiers":[
        {
            "category":"Building & Trades",
            "subcategory":"Cleaning & Sanitation",
            "type":"Services"
        }
    ],
    "sg:phone":"+1 601 346 6535",
    "sg:postcode":"39212",
    "sg:province":"MS",
    "sg:tags":[
        "maintenance"
    ],
    "wof:name":"Redds Commercial Cleaning Inc",
    "wof:placetype":"venue"
},
  "geometry": {"coordinates":[-90.24321399999999,32.21773],"type":"Point"}
}