{
  "type": "Feature",
  "properties": {
    "iso:country":"US",
    "sg:address":"378 E Academy St",
    "sg:city":"Canton",
    "sg:classifiers":[
        {
            "category":"Retail",
            "subcategory":"Repair Shop",
            "type":"Services"
        }
    ],
    "sg:phone":"+1 601 859 6156",
    "sg:postcode":"39046",
    "sg:province":"MS",
    "wof:name":"Poston TV",
    "wof:placetype":"venue"
},
  "geometry": {"coordinates":[-90.026869,32.610051],"type":"Point"}
}