{
  "type": "Feature",
  "properties": {
    "iso:country":"US",
    "sg:address":"803 N 2nd St",
    "sg:city":"Booneville",
    "sg:classifiers":[
        {
            "category":"Restaurant",
            "type":"Food & Drink"
        }
    ],
    "sg:phone":"+1 662 728 3550",
    "sg:postcode":"38829",
    "sg:province":"MS",
    "wof:name":"Mc Donald's",
    "wof:placetype":"venue"
},
  "geometry": {"coordinates":[-88.564193,34.669015],"type":"Point"}
}