{
  "type": "Feature",
  "properties": {
    "iso:country":"US",
    "sg:address":"216 S Columbus Ave",
    "sg:city":"Louisville",
    "sg:classifiers":[
        {
            "category":"Utilities",
            "subcategory":"Natural Gas",
            "type":"Services"
        }
    ],
    "sg:phone":"+1 662 773 6243",
    "sg:postcode":"39339",
    "sg:province":"MS",
    "sg:tags":[
        "company"
    ],
    "wof:name":"Atmos Energy Mississippi",
    "wof:placetype":"venue"
},
  "geometry": {"coordinates":[-89.053239,33.122134],"type":"Point"}
}