{
  "type": "Feature",
  "properties": {
    "iso:country":"US",
    "sg:address":"1185 V F W Rd",
    "sg:city":"Greenville",
    "sg:classifiers":[
        {
            "category":"Wholesale",
            "subcategory":"Durable Goods & Equipment",
            "type":"Manufacturing & Wholesale Goods"
        }
    ],
    "sg:phone":"+1 662 332 8793",
    "sg:postcode":"38701",
    "sg:province":"MS",
    "sg:tags":[
        "fire",
        "extinguisher"
    ],
    "wof:name":"Dixie Fire Protection Inc",
    "wof:placetype":"venue"
},
  "geometry": {"coordinates":[-91.036299,33.356166],"type":"Point"}
}