{
  "type": "Feature",
  "properties": {
    "iso:country":"US",
    "sg:address":"403 SE Frontage Rd",
    "sg:city":"Winona",
    "sg:classifiers":[
        {
            "category":"Autos & Motor Vehicles",
            "subcategory":"Fuel & Gas Station",
            "type":"Retail Goods"
        }
    ],
    "sg:phone":"+1 662 283 5985",
    "sg:postcode":"38967",
    "sg:province":"MS",
    "sg:tags":[
        "plaza",
        "truck",
        "stops"
    ],
    "wof:name":"High Point Travel Ctr",
    "wof:placetype":"venue"
},
  "geometry": {"coordinates":[-89.759491,33.486408],"type":"Point"}
}