{
  "type": "Feature",
  "properties": {
    "iso:country":"US",
    "sg:address":"209 Hwy 82 W",
    "sg:city":"Starkville",
    "sg:classifiers":[
        {
            "category":"Food & Beverages",
            "subcategory":"Meat & Fish",
            "type":"Retail Goods"
        }
    ],
    "sg:phone":"+1 662 324 6328",
    "sg:postcode":"39759",
    "sg:province":"MS",
    "wof:name":"Mac's Meat Market",
    "wof:placetype":"venue"
},
  "geometry": {"coordinates":[-88.819108,33.466012],"type":"Point"}
}