{
  "type": "Feature",
  "properties": {
    "iso:country":"US",
    "sg:address":"9177 Selena Dr",
    "sg:city":"Biloxi",
    "sg:classifiers":[
        {
            "category":"Professional",
            "subcategory":"Engineering",
            "type":"Services"
        }
    ],
    "sg:phone":"+1 228 392 7267",
    "sg:postcode":"39532",
    "sg:province":"MS",
    "sg:tags":[
        "engineer"
    ],
    "wof:name":"Speedwork Inc",
    "wof:placetype":"venue"
},
  "geometry": {"coordinates":[-88.989437,30.479863],"type":"Point"}
}