{
  "type": "Feature",
  "properties": {
    "iso:country":"US",
    "sg:address":"30 Buckley Jones Rd",
    "sg:city":"Cleveland",
    "sg:classifiers":[
        {
            "category":"Building & Trades",
            "subcategory":"Landscaping Services",
            "type":"Services"
        }
    ],
    "sg:phone":"+1 662 843 6102",
    "sg:postcode":"38732",
    "sg:province":"MS",
    "wof:name":"C S & S Landscape Inc",
    "wof:placetype":"venue"
},
  "geometry": {"coordinates":[-90.658162,33.762966],"type":"Point"}
}