{
  "type": "Feature",
  "properties": {
    "iso:country":"US",
    "sg:address":"1135 Weems St",
    "sg:city":"Jackson",
    "sg:classifiers":[
        {
            "category":"Building & Trades",
            "subcategory":"Construction",
            "type":"Services"
        }
    ],
    "sg:phone":"+1 601 346 0171",
    "sg:postcode":"39208",
    "sg:province":"MS",
    "sg:tags":[
        "insulation",
        "heat",
        "contractor"
    ],
    "sg:website":"www.pcg.com",
    "wof:name":"North Brohters Inc",
    "wof:placetype":"venue"
},
  "geometry": {"coordinates":[-90.13745299999999,32.249913],"type":"Point"}
}