{
  "type": "Feature",
  "properties": {
    "iso:country":"US",
    "sg:address":"1723 Beach Blvd",
    "sg:city":"Biloxi",
    "sg:classifiers":[
        {
            "category":"Shopping",
            "subcategory":"Shoes",
            "type":"Retail Goods"
        }
    ],
    "sg:phone":"+1 228 435 3899",
    "sg:postcode":"39531",
    "sg:province":"MS",
    "sg:website":"www.walkncomfort.com",
    "wof:name":"Walk'n Comfort",
    "wof:placetype":"venue"
},
  "geometry": {"coordinates":[-88.940135,30.393562],"type":"Point"}
}