{
  "type": "Feature",
  "properties": {
    "addr:full":"5930 Warriors Trl Vicksburg MS 39180",
    "addr:housenumber":"5930",
    "addr:postcode":"39180",
    "addr:street":"Warriors Trl",
    "iso:country":"US",
    "sg:address":"5930 Warriors Trl",
    "sg:city":"Vicksburg",
    "sg:classifiers":[
        {
            "category":"Organizations",
            "subcategory":"Religious Organization",
            "type":"Services"
        }
    ],
    "sg:phone":"+1 601 636 6687",
    "sg:postcode":"39180",
    "sg:province":"MS",
    "sg:tags":[
        "church"
    ],
    "wof:name":"St Albans Episcopal Church",
    "wof:placetype":"venue"
},
  "geometry": {"coordinates":[-90.741032,32.348062],"type":"Point"}
}