{
  "type": "Feature",
  "properties": {
    "iso:country":"US",
    "sg:address":"4656 State Hwy 53",
    "sg:city":"Poplarville",
    "sg:classifiers":[
        {
            "category":"Freight",
            "type":"Transportation"
        }
    ],
    "sg:phone":"+1 601 795 9122",
    "sg:postcode":"39470",
    "sg:province":"MS",
    "sg:tags":[
        "trucking"
    ],
    "wof:name":"Elvis Williamson Trucking",
    "wof:placetype":"venue"
},
  "geometry": {"coordinates":[-89.504317,30.795227],"type":"Point"}
}