{
  "type": "Feature",
  "properties": {
    "iso:country":"US",
    "sg:address":"10519 Riviere Vue Dr",
    "sg:city":"Biloxi",
    "sg:classifiers":[
        {
            "category":"Building & Trades",
            "subcategory":"Landscaping Services",
            "type":"Services"
        }
    ],
    "sg:phone":"+1 228 392 1710",
    "sg:postcode":"39532",
    "sg:province":"MS",
    "wof:name":"Lawnscape",
    "wof:placetype":"venue"
},
  "geometry": {"coordinates":[-89.003197,30.437993],"type":"Point"}
}