{
  "type": "Feature",
  "properties": {
    "iso:country":"US",
    "sg:address":"425 Hospital Dr",
    "sg:city":"Columbus",
    "sg:classifiers":[
        {
            "category":"Shopping",
            "subcategory":"Optical Goods",
            "type":"Retail Goods"
        }
    ],
    "sg:phone":"+1 662 327 6341",
    "sg:postcode":"39705",
    "sg:province":"MS",
    "wof:name":"GTR Optical Dispensary",
    "wof:placetype":"venue"
},
  "geometry": {"coordinates":[-88.42967,33.52662],"type":"Point"}
}