{
  "type": "Feature",
  "properties": {
    "iso:country":"US",
    "sg:address":"1181 Judge Sekul Ave",
    "sg:city":"Biloxi",
    "sg:classifiers":[
        {
            "category":"Recreation",
            "subcategory":"Arcade",
            "type":"Entertainment"
        },
        {
            "category":"Building & Trades",
            "subcategory":"Equipment Rental",
            "type":"Services"
        }
    ],
    "sg:phone":"+1 228 432 1075",
    "sg:postcode":"39530",
    "sg:province":"MS",
    "sg:tags":[
        "amusement",
        "devices",
        "nonresidential"
    ],
    "wof:name":"Taranto Amusement Corporation",
    "wof:placetype":"venue"
},
  "geometry": {"coordinates":[-88.908494,30.401147],"type":"Point"}
}