{
  "type": "Feature",
  "properties": {
    "addr:full":"425 Beasley Rd Jackson MS 39206",
    "addr:housenumber":"425",
    "addr:postcode":"39206",
    "addr:street":"Beasley Rd",
    "iso:country":"US",
    "sg:address":"425 Beasley Rd",
    "sg:city":"Jackson",
    "sg:classifiers":[
        {
            "category":"Real Estate",
            "subcategory":"Real Estate Operator",
            "type":"Services"
        }
    ],
    "sg:phone":"+1 601 982 2714",
    "sg:postcode":"39206",
    "sg:province":"MS",
    "sg:tags":[
        "apartment"
    ],
    "wof:name":"Forest Ridge",
    "wof:placetype":"venue"
},
  "geometry": {"coordinates":[-90.169055,32.385419],"type":"Point"}
}