{
  "type": "Feature",
  "properties": {
    "addr:full":"529 Co Rd 989 Iuka MS 38852",
    "addr:housenumber":"529",
    "addr:postcode":"38852",
    "addr:street":"Co Rd 989",
    "iso:country":"US",
    "sg:address":"529 Co Rd 989",
    "sg:city":"Iuka",
    "sg:classifiers":[
        {
            "category":"Building & Trades",
            "subcategory":"Construction",
            "type":"Services"
        }
    ],
    "sg:phone":"+1 662 423 9098",
    "sg:postcode":"38852",
    "sg:province":"MS",
    "sg:tags":[
        "house"
    ],
    "wof:name":"Pete Trickey",
    "wof:placetype":"venue"
},
  "geometry": {"coordinates":[-88.199473,34.924048],"type":"Point"}
}