{
  "type": "Feature",
  "properties": {
    "iso:country":"US",
    "sg:address":"105 Industrial Dr",
    "sg:city":"Hattiesburg",
    "sg:classifiers":[
        {
            "category":"Professional",
            "subcategory":"Advertising",
            "type":"Services"
        }
    ],
    "sg:phone":"+1 601 544 7412",
    "sg:postcode":"39401",
    "sg:province":"MS",
    "wof:name":"RAY'SMARINE.COM",
    "wof:placetype":"venue"
},
  "geometry": {"coordinates":[-89.321439,31.343977],"type":"Point"}
}