{
  "type": "Feature",
  "properties": {
    "iso:country":"US",
    "sg:address":"1621 Hwy 15 N",
    "sg:city":"Laurel",
    "sg:classifiers":[
        {
            "category":"Personal",
            "subcategory":"Beauty Salon",
            "type":"Services"
        }
    ],
    "sg:phone":"+1 601 649 9862",
    "sg:postcode":"39440",
    "sg:province":"MS",
    "wof:name":"Smart Style Family Hair Salon",
    "wof:placetype":"venue"
},
  "geometry": {"coordinates":[-89.148545,31.708869],"type":"Point"}
}