{
  "type": "Feature",
  "properties": {
    "iso:country":"US",
    "sg:address":"995 Sunrise Rd",
    "sg:city":"Petal",
    "sg:classifiers":[
        {
            "category":"Autos & Motor Vehicles",
            "subcategory":"Fuel & Gas Station",
            "type":"Retail Goods"
        }
    ],
    "sg:phone":"+1 601 544 6041",
    "sg:postcode":"39465",
    "sg:province":"MS",
    "sg:tags":[
        "station",
        "gasoline"
    ],
    "wof:name":"Burks BP",
    "wof:placetype":"venue"
},
  "geometry": {"coordinates":[-89.179731,31.340036],"type":"Point"}
}