{
  "type": "Feature",
  "properties": {
    "iso:country":"US",
    "sg:address":"909 S Locust St",
    "sg:city":"Mccomb",
    "sg:classifiers":[
        {
            "category":"Home & Garden",
            "subcategory":"Mobile Homes",
            "type":"Retail Goods"
        }
    ],
    "sg:phone":"+1 601 250 5318",
    "sg:postcode":"39648",
    "sg:province":"MS",
    "sg:tags":[
        "manufactured",
        "sales"
    ],
    "wof:name":"Quality Homes of Mc Comb Inc",
    "wof:placetype":"venue"
},
  "geometry": {"coordinates":[-90.438923,31.235558],"type":"Point"}
}