{
  "type": "Feature",
  "properties": {
    "iso:country":"US",
    "sg:address":"431 W College Ave",
    "sg:city":"Holly Springs",
    "sg:classifiers":[
        {
            "category":"Food & Beverages",
            "subcategory":"Groceries & Convenience Stores",
            "type":"Retail Goods"
        }
    ],
    "sg:phone":"+1 662 274 0015",
    "sg:postcode":"38635",
    "sg:province":"MS",
    "wof:name":"Jarvis' Mini Mart",
    "wof:placetype":"venue"
},
  "geometry": {"coordinates":[-89.45962299999999,34.768534],"type":"Point"}
}