{
  "type": "Feature",
  "properties": {
    "iso:country":"US",
    "sg:address":"1164 State Hwy 15",
    "sg:city":"Ellisville",
    "sg:classifiers":[
        {
            "category":"Organizations",
            "subcategory":"Religious Organization",
            "type":"Services"
        }
    ],
    "sg:phone":"+1 601 428 8004",
    "sg:postcode":"39443",
    "sg:province":"MS",
    "sg:tags":[
        "church"
    ],
    "wof:name":"Mount Moriah Baptist Church",
    "wof:placetype":"venue"
},
  "geometry": {"coordinates":[-89.09669,31.64128],"type":"Point"}
}