{
  "type": "Feature",
  "properties": {
    "iso:country":"US",
    "sg:address":"447 Hickory Hill Pl",
    "sg:city":"Pearl",
    "sg:classifiers":[
        {
            "category":"Building & Trades",
            "subcategory":"Construction",
            "type":"Services"
        }
    ],
    "sg:phone":"+1 601 932 4358",
    "sg:postcode":"39208",
    "sg:province":"MS",
    "sg:tags":[
        "contractor"
    ],
    "wof:name":"Blounts Drywall Painting",
    "wof:placetype":"venue"
},
  "geometry": {"coordinates":[-90.08189900000001,32.189164],"type":"Point"}
}