{
  "type": "Feature",
  "properties": {
    "iso:country":"US",
    "sg:address":"418 Jefferson St",
    "sg:city":"Ellisville",
    "sg:classifiers":[
        {
            "category":"Home & Garden",
            "subcategory":"Hardware",
            "type":"Retail Goods"
        }
    ],
    "sg:phone":"+1 601 477 3077",
    "sg:postcode":"39437",
    "sg:province":"MS",
    "wof:name":"Smith County Hardware",
    "wof:placetype":"venue"
},
  "geometry": {"coordinates":[-89.20442799999999,31.614144],"type":"Point"}
}