{
  "type": "Feature",
  "properties": {
    "addr:full":"3107 Hwy 13 S Columbia MS 39429",
    "addr:housenumber":"3107",
    "addr:postcode":"39429",
    "addr:street":"Hwy 13 S",
    "iso:country":"US",
    "sg:address":"3107 Hwy 13 S",
    "sg:city":"Columbia",
    "sg:classifiers":[
        {
            "category":"Manufacturing",
            "subcategory":"Lumber",
            "type":"Manufacturing & Wholesale Goods"
        }
    ],
    "sg:phone":"+1 601 736 7159",
    "sg:postcode":"39429",
    "sg:province":"MS",
    "sg:tags":[
        "timber",
        "tract"
    ],
    "wof:name":"Georgia-Pacific",
    "wof:placetype":"venue"
},
  "geometry": {"coordinates":[-89.704168,31.134698],"type":"Point"}
}