{
  "type": "Feature",
  "properties": {
    "addr:full":"319 Courthouse Rd Gulfport MS 39507",
    "addr:housenumber":"319",
    "addr:postcode":"39507",
    "addr:street":"Courthouse Rd",
    "iso:country":"US",
    "sg:address":"319 Courthouse Rd",
    "sg:city":"Gulfport",
    "sg:classifiers":[
        {
            "category":"Insurance",
            "subcategory":"Insurance Agent",
            "type":"Services"
        }
    ],
    "sg:phone":"+1 228 604 0150",
    "sg:postcode":"39507",
    "sg:province":"MS",
    "wof:name":"Primerica Financial Svc",
    "wof:placetype":"venue"
},
  "geometry": {"coordinates":[-89.04409099999999,30.38211],"type":"Point"}
}