{
  "type": "Feature",
  "properties": {
    "iso:country":"US",
    "sg:address":"50 Sycamore Rd",
    "sg:city":"Coldwater",
    "sg:classifiers":[
        {
            "category":"Shopping",
            "subcategory":"Clothing, Apparel, & Fashions",
            "type":"Retail Goods"
        }
    ],
    "sg:phone":"+1 662 233 2006",
    "sg:postcode":"38618",
    "sg:province":"MS",
    "sg:tags":[
        "item",
        "boutique"
    ],
    "wof:name":"Bucksnorts Unique Boutique",
    "wof:placetype":"venue"
},
  "geometry": {"coordinates":[-89.809682,34.705477],"type":"Point"}
}