{
  "type": "Feature",
  "properties": {
    "iso:country":"US",
    "sg:address":"12012 Rio Lado Ln",
    "sg:city":"Biloxi",
    "sg:classifiers":[
        {
            "category":"Building & Trades",
            "subcategory":"Construction",
            "type":"Services"
        }
    ],
    "sg:phone":"+1 228 392 1833",
    "sg:postcode":"39532",
    "sg:province":"MS",
    "sg:tags":[
        "house"
    ],
    "wof:name":"Kingsley Homes Inc",
    "wof:placetype":"venue"
},
  "geometry": {"coordinates":[-88.920798,30.456258],"type":"Point"}
}