{
  "type": "Feature",
  "properties": {
    "addr:full":"1108 Sand Rd Kilmichael MS 39702",
    "addr:housenumber":"1108",
    "addr:postcode":"39702",
    "addr:street":"Sand Rd",
    "iso:country":"US",
    "sg:address":"1108 Sand Rd",
    "sg:city":"Kilmichael",
    "sg:classifiers":[
        {
            "category":"Organizations",
            "subcategory":"Religious Organization",
            "type":"Services"
        }
    ],
    "sg:phone":"+1 662 262 4230",
    "sg:postcode":"39702",
    "sg:province":"MS",
    "sg:tags":[
        "church"
    ],
    "wof:name":"St Paul Church Of God",
    "wof:placetype":"venue"
},
  "geometry": {"coordinates":[-88.37411,33.531875],"type":"Point"}
}