{
  "type": "Feature",
  "properties": {
    "addr:full":"922 Hickory Grove Rd Lumberton MS 39455",
    "addr:housenumber":"922",
    "addr:postcode":"39455",
    "addr:street":"Hickory Grove Rd",
    "iso:country":"US",
    "sg:address":"922 Hickory Grove Rd",
    "sg:city":"Lumberton",
    "sg:classifiers":[
        {
            "category":"Retail",
            "subcategory":"Repair Shop",
            "type":"Services"
        }
    ],
    "sg:phone":"+1 601 796 5056",
    "sg:postcode":"39455",
    "sg:province":"MS",
    "sg:tags":[
        "scooter",
        "motorcycle",
        "motor"
    ],
    "wof:name":"Jammer HD Customs",
    "wof:placetype":"venue"
},
  "geometry": {"coordinates":[-89.346913,30.962838],"type":"Point"}
}