{
  "type": "Feature",
  "properties": {
    "iso:country":"US",
    "sg:address":"175 Main St",
    "sg:city":"Meadville",
    "sg:phone":"+1 601 384 5831",
    "sg:postcode":"39601",
    "sg:province":"MS",
    "sg:tags":[
        "gas"
    ],
    "sg:website":"www.herringgas.com",
    "wof:name":"Herring Gas Co",
    "wof:placetype":"venue"
},
  "geometry": {"coordinates":[-90.43620900000001,31.586029],"type":"Point"}
}