{
  "type": "Feature",
  "properties": {
    "iso:country":"US",
    "sg:address":"8001 US Hwy 49",
    "sg:city":"Jackson",
    "sg:classifiers":[
        {
            "category":"Real Estate",
            "subcategory":"Real Estate Agent",
            "type":"Services"
        }
    ],
    "sg:phone":"+1 601 362 6899",
    "sg:postcode":"39209",
    "sg:province":"MS",
    "wof:name":"Paine Properties Inc",
    "wof:placetype":"venue"
},
  "geometry": {"coordinates":[-90.269685,32.391709],"type":"Point"}
}