{
  "type": "Feature",
  "properties": {
    "addr:full":"320 S Martin Luther King Jr St Natchez MS 39120",
    "addr:housenumber":"320",
    "addr:postcode":"39120",
    "addr:street":"S Martin Luther King Jr St",
    "iso:country":"US",
    "sg:address":"320 S Martin Luther King Jr St",
    "sg:city":"Natchez",
    "sg:classifiers":[
        {
            "category":"Food & Beverages",
            "subcategory":"Groceries & Convenience Stores",
            "type":"Retail Goods"
        }
    ],
    "sg:phone":"+1 601 442 1488",
    "sg:postcode":"39120",
    "sg:province":"MS",
    "wof:name":"Zipy Foods",
    "wof:placetype":"venue"
},
  "geometry": {"coordinates":[-91.40159300000001,31.555681],"type":"Point"}
}