{
  "type": "Feature",
  "properties": {
    "iso:country":"US",
    "sg:address":"40105 New Prospect Rd",
    "sg:city":"Hamilton",
    "sg:classifiers":[
        {
            "category":"Organizations",
            "subcategory":"Religious Organization",
            "type":"Services"
        }
    ],
    "sg:phone":"+1 662 369 7300",
    "sg:postcode":"39746",
    "sg:province":"MS",
    "wof:name":"New Prospect Baptist Church",
    "wof:placetype":"venue"
},
  "geometry": {"coordinates":[-88.426586,33.812068],"type":"Point"}
}