{
  "type": "Feature",
  "properties": {
    "iso:country":"US",
    "sg:address":"65 Stonewall Rd",
    "sg:city":"Byhalia",
    "sg:classifiers":[
        {
            "category":"Restaurant",
            "type":"Food & Drink"
        }
    ],
    "sg:phone":"+1 662 838 5155",
    "sg:postcode":"38611",
    "sg:province":"MS",
    "wof:name":"Robbie's Drive In",
    "wof:placetype":"venue"
},
  "geometry": {"coordinates":[-89.693305,34.859981],"type":"Point"}
}