{
  "type": "Feature",
  "properties": {
    "addr:full":"2603 7th St Meridian MS 39301",
    "addr:housenumber":"2603",
    "addr:postcode":"39301",
    "addr:street":"7Th St",
    "iso:country":"US",
    "sg:address":"2603 7th St",
    "sg:city":"Meridian",
    "sg:classifiers":[
        {
            "category":"Autos & Motor Vehicles",
            "subcategory":"Auto Supplies",
            "type":"Retail Goods"
        }
    ],
    "sg:phone":"+1 601 693 1391",
    "sg:postcode":"39301",
    "sg:province":"MS",
    "sg:tags":[
        "tire"
    ],
    "wof:name":"Firestone Tire & Svc Ctr",
    "wof:placetype":"venue"
},
  "geometry": {"coordinates":[-88.704688,32.363999],"type":"Point"}
}