{
  "type": "Feature",
  "properties": {
    "iso:country":"US",
    "sg:address":"520 N 11th St",
    "sg:city":"Columbus",
    "sg:classifiers":[
        {
            "category":"Education",
            "subcategory":"College",
            "type":"Public Place"
        }
    ],
    "sg:phone":"+1 662 329 7175",
    "sg:postcode":"39701",
    "sg:province":"MS",
    "sg:tags":[
        "academic",
        "school"
    ],
    "sg:website":"www.muw.edu",
    "wof:name":"Education & Human Sciences",
    "wof:placetype":"venue"
},
  "geometry": {"coordinates":[-88.421689,33.501143],"type":"Point"}
}