{
  "type": "Feature",
  "properties": {
    "iso:country":"US",
    "sg:address":"115 Williams Ave",
    "sg:city":"Jackson",
    "sg:classifiers":[
        {
            "category":"Retail",
            "subcategory":"Auto Repair",
            "type":"Services"
        }
    ],
    "sg:phone":"+1 601 362 9989",
    "sg:postcode":"39213",
    "sg:province":"MS",
    "sg:tags":[
        "body",
        "automobile",
        "painting"
    ],
    "wof:name":"Donerson Auto Body",
    "wof:placetype":"venue"
},
  "geometry": {"coordinates":[-90.246717,32.373979],"type":"Point"}
}