{
  "type": "Feature",
  "properties": {
    "iso:country":"US",
    "sg:address":"1300 Greenleaf Rd",
    "sg:city":"Coldwater",
    "sg:classifiers":[
        {
            "category":"Wholesale",
            "subcategory":"Medical Equipment & Supplies",
            "type":"Manufacturing & Wholesale Goods"
        }
    ],
    "sg:phone":"+1 662 233 2364",
    "sg:postcode":"38618",
    "sg:province":"MS",
    "sg:tags":[
        "hospital"
    ],
    "wof:name":"Pioneer Express Respiratory",
    "wof:placetype":"venue"
},
  "geometry": {"coordinates":[-89.877591,34.758157],"type":"Point"}
}