{
  "type": "Feature",
  "properties": {
    "addr:full":"549 Medical Dr Clarksdale MS 38614",
    "addr:housenumber":"549",
    "addr:postcode":"38614",
    "addr:street":"Medical Dr Clarksdale",
    "iso:country":"US",
    "sg:address":"549 Medical Dr",
    "sg:city":"Clarksdale",
    "sg:classifiers":[
        {
            "category":"Shopping",
            "subcategory":"Pharmacy",
            "type":"Retail Goods"
        }
    ],
    "sg:phone":"+1 662 624 2526",
    "sg:postcode":"38614",
    "sg:province":"MS",
    "wof:name":"Haire Drug Ctr",
    "wof:placetype":"venue"
},
  "geometry": {"coordinates":[-90.54398500000001,34.206501],"type":"Point"}
}