{
  "type": "Feature",
  "properties": {
    "addr:full":"150 Jeff Davis Blvd Natchez MS 39120",
    "addr:housenumber":"150",
    "addr:postcode":"39120",
    "addr:street":"Jeff Davis Blvd",
    "iso:country":"US",
    "sg:address":"150 Jeff Davis Blvd",
    "sg:city":"Natchez",
    "sg:classifiers":[
        {
            "category":"Professional",
            "subcategory":"Computer Services",
            "type":"Services"
        },
        {
            "category":"Health Services",
            "subcategory":"Doctor",
            "type":"Services"
        }
    ],
    "sg:phone":"+1 601 443 9818",
    "sg:postcode":"39120",
    "sg:province":"MS",
    "sg:tags":[
        "medical",
        "datum"
    ],
    "wof:name":"Medical Data Service Inc",
    "wof:placetype":"venue"
},
  "geometry": {"coordinates":[-91.38632,31.52388],"type":"Point"}
}