{
  "type": "Feature",
  "properties": {
    "iso:country":"US",
    "sg:address":"4253 Denny Ave",
    "sg:city":"Pascagoula",
    "sg:classifiers":[
        {
            "category":"Personal",
            "subcategory":"Beauty Salon",
            "type":"Services"
        }
    ],
    "sg:phone":"+1 228 712 2996",
    "sg:postcode":"39581",
    "sg:province":"MS",
    "wof:name":"Smart Style Family Hair Salon",
    "wof:placetype":"venue"
},
  "geometry": {"coordinates":[-88.52739800000001,30.377992],"type":"Point"}
}