{
  "type": "Feature",
  "properties": {
    "addr:full":"2405 State Blvd Meridian MS 39307",
    "addr:housenumber":"2405",
    "addr:postcode":"39307",
    "addr:street":"State Blvd",
    "iso:country":"US",
    "sg:address":"2405 State Blvd",
    "sg:city":"Meridian",
    "sg:classifiers":[
        {
            "category":"Retail",
            "subcategory":"Auto Repair",
            "type":"Services"
        }
    ],
    "sg:phone":"+1 601 693 6161",
    "sg:postcode":"39307",
    "sg:province":"MS",
    "sg:tags":[
        "repairing",
        "automobile"
    ],
    "wof:name":"State Boulevard Automotive",
    "wof:placetype":"venue"
},
  "geometry": {"coordinates":[-88.72809700000001,32.38468],"type":"Point"}
}