{
  "type": "Feature",
  "properties": {
    "iso:country":"US",
    "sg:address":"2810 Andrew Ave",
    "sg:city":"Pascagoula",
    "sg:classifiers":[
        {
            "category":"Professional",
            "subcategory":"Management & Consulting",
            "type":"Services"
        }
    ],
    "sg:phone":"+1 228 762 5553",
    "sg:postcode":"39567",
    "sg:province":"MS",
    "sg:tags":[
        "business"
    ],
    "wof:name":"N & M Inc",
    "wof:placetype":"venue"
},
  "geometry": {"coordinates":[-88.530942,30.382283],"type":"Point"}
}