{
  "type": "Feature",
  "properties": {
    "iso:country":"US",
    "sg:address":"643 Howard Ave",
    "sg:city":"Biloxi",
    "sg:classifiers":[
        {
            "category":"Real Estate",
            "subcategory":"Real Estate Operator",
            "type":"Services"
        }
    ],
    "sg:phone":"+1 228 435 5566",
    "sg:postcode":"39530",
    "sg:province":"MS",
    "sg:tags":[
        "apartment"
    ],
    "wof:name":"Lots Of Biloxi",
    "wof:placetype":"venue"
},
  "geometry": {"coordinates":[-88.88307500000001,30.395894],"type":"Point"}
}