{
  "type": "Feature",
  "properties": {
    "addr:full":"925 Flowood Dr Flowood MS 39232",
    "addr:housenumber":"925",
    "addr:postcode":"39232",
    "addr:street":"Flowood Dr",
    "iso:country":"US",
    "sg:address":"925 Flowood Dr",
    "sg:city":"Flowood",
    "sg:classifiers":[
        {
            "category":"Organizations",
            "subcategory":"Religious Organization",
            "type":"Services"
        }
    ],
    "sg:phone":"+1 601 932 6507",
    "sg:postcode":"39232",
    "sg:province":"MS",
    "sg:tags":[
        "church"
    ],
    "wof:name":"Greer Chapel United Methodist",
    "wof:placetype":"venue"
},
  "geometry": {"coordinates":[-90.141463,32.304415],"type":"Point"}
}