{
  "type": "Feature",
  "properties": {
    "iso:country":"US",
    "sg:address":"508 Humphrey Ave",
    "sg:city":"Marks",
    "sg:classifiers":[
        {
            "category":"Building & Trades",
            "subcategory":"Construction",
            "type":"Services"
        }
    ],
    "sg:phone":"+1 662 326 2723",
    "sg:postcode":"38646",
    "sg:province":"MS",
    "sg:tags":[
        "house"
    ],
    "wof:name":"Kbs Construction",
    "wof:placetype":"venue"
},
  "geometry": {"coordinates":[-90.278519,34.255374],"type":"Point"}
}