{
  "type": "Feature",
  "properties": {
    "iso:country":"US",
    "sg:address":"5182 US Hwy 90",
    "sg:city":"Bay St Louis",
    "sg:classifiers":[
        {
            "category":"Bars & Pubs",
            "type":"Food & Drink"
        }
    ],
    "sg:phone":"+1 228 467 7746",
    "sg:postcode":"39520",
    "sg:province":"MS",
    "sg:tags":[
        "club",
        "drinking",
        "night"
    ],
    "wof:name":"Brass Anchor Club",
    "wof:placetype":"venue"
},
  "geometry": {"coordinates":[-89.419628,30.299243],"type":"Point"}
}