{
  "type": "Feature",
  "properties": {
    "addr:full":"203 Ryan St Belzoni MS 39038",
    "addr:housenumber":"203",
    "addr:postcode":"39038",
    "addr:street":"Ryan St",
    "iso:country":"US",
    "sg:address":"203 Ryan St",
    "sg:city":"Belzoni",
    "sg:classifiers":[
        {
            "category":"Real Estate",
            "subcategory":"Real Estate Operator",
            "type":"Services"
        }
    ],
    "sg:phone":"+1 662 247 1997",
    "sg:postcode":"39038",
    "sg:province":"MS",
    "sg:tags":[
        "apartment"
    ],
    "wof:name":"Beech Lane Apartments",
    "wof:placetype":"venue"
},
  "geometry": {"coordinates":[-90.495392,33.176444],"type":"Point"}
}