{
  "type": "Feature",
  "properties": {
    "iso:country":"US",
    "sg:address":"706 Desoto Ave",
    "sg:city":"Clarksdale",
    "sg:classifiers":[
        {
            "category":"Fast Food",
            "type":"Food & Drink"
        }
    ],
    "sg:phone":"+1 662 627 1100",
    "sg:postcode":"38614",
    "sg:province":"MS",
    "sg:tags":[
        "restaurant"
    ],
    "sg:website":"http://www.mcdonalds.com",
    "wof:name":"McDonald's",
    "wof:placetype":"venue"
},
  "geometry": {"coordinates":[-90.56458499999999,34.195781],"type":"Point"}
}