{
  "type": "Feature",
  "properties": {
    "addr:full":"619 Lottville Rd Canton MS 39046",
    "addr:housenumber":"619",
    "addr:postcode":"39046",
    "addr:street":"Lottville Rd",
    "iso:country":"US",
    "sg:address":"619 Lottville Rd",
    "sg:city":"Canton",
    "sg:classifiers":[
        {
            "category":"Sports & Exercise",
            "subcategory":"Race Track",
            "type":"Entertainment"
        }
    ],
    "sg:phone":"+1 601 855 0704",
    "sg:postcode":"39046",
    "sg:province":"MS",
    "wof:name":"Junkyard 1 Speedway",
    "wof:placetype":"venue"
},
  "geometry": {"coordinates":[-89.826937,32.701017],"type":"Point"}
}