{
  "type": "Feature",
  "properties": {
    "iso:country":"US",
    "sg:address":"260 Hwy 35 N",
    "sg:city":"Batesville",
    "sg:classifiers":[
        {
            "category":"Home & Garden",
            "subcategory":"Furniture",
            "type":"Retail Goods"
        }
    ],
    "sg:phone":"+1 662 563 1346",
    "sg:postcode":"38606",
    "sg:province":"MS",
    "sg:tags":[
        "mattress"
    ],
    "sg:website":"www.serta.com",
    "wof:name":"Serta Mattress",
    "wof:placetype":"venue"
},
  "geometry": {"coordinates":[-89.933854,34.335377],"type":"Point"}
}