{
  "type": "Feature",
  "properties": {
    "iso:country":"US",
    "sg:address":"402 Feltus Blvd",
    "sg:city":"Leland",
    "sg:classifiers":[
        {
            "category":"Building & Trades",
            "subcategory":"Construction",
            "type":"Services"
        }
    ],
    "sg:phone":"+1 662 686 2617",
    "sg:postcode":"38756",
    "sg:province":"MS",
    "sg:tags":[
        "contractor"
    ],
    "wof:name":"Landers Roofing Co",
    "wof:placetype":"venue"
},
  "geometry": {"coordinates":[-90.89317800000001,33.405525],"type":"Point"}
}