{
  "type": "Feature",
  "properties": {
    "iso:country":"US",
    "sg:address":"225 McCarty Cove",
    "sg:city":"Jackson",
    "sg:classifiers":[
        {
            "category":"Building & Trades",
            "subcategory":"Construction",
            "type":"Services"
        }
    ],
    "sg:phone":"+1 601 372 2882",
    "sg:postcode":"39212",
    "sg:province":"MS",
    "sg:tags":[
        "hanging",
        "contractor"
    ],
    "wof:name":"Alston Painting",
    "wof:placetype":"venue"
},
  "geometry": {"coordinates":[-90.310722,32.208847],"type":"Point"}
}