{
  "type": "Feature",
  "properties": {
    "iso:country":"US",
    "sg:address":"431 N State St",
    "sg:city":"Jackson",
    "sg:classifiers":[
        {
            "category":"Organizations",
            "subcategory":"Religious Organization",
            "type":"Services"
        }
    ],
    "sg:phone":"+1 601 949 1949",
    "sg:postcode":"39201",
    "sg:province":"MS",
    "wof:name":"Counselin Ministry of First",
    "wof:placetype":"venue"
},
  "geometry": {"coordinates":[-90.179754,32.30316],"type":"Point"}
}