{
  "type": "Feature",
  "properties": {
    "iso:country":"US",
    "sg:address":"2323 Lakeland Dr",
    "sg:city":"Jackson",
    "sg:classifiers":[
        {
            "category":"Professional",
            "subcategory":"Computer Services",
            "type":"Services"
        }
    ],
    "sg:phone":"+1 601 420 3477",
    "sg:postcode":"39208",
    "sg:province":"MS",
    "sg:tags":[
        "r",
        "related"
    ],
    "wof:name":"Pcw Synergeticsdcs Inc",
    "wof:placetype":"venue"
},
  "geometry": {"coordinates":[-90.10366399999999,32.332751],"type":"Point"}
}