{
  "type": "Feature",
  "properties": {
    "iso:country":"US",
    "sg:address":"121 Maxwell Ln",
    "sg:city":"Columbus",
    "sg:classifiers":[
        {
            "category":"Building & Trades",
            "subcategory":"Construction",
            "type":"Services"
        }
    ],
    "sg:phone":"+1 662 328 2286",
    "sg:postcode":"39702",
    "sg:province":"MS",
    "sg:tags":[
        "asbestos",
        "removal"
    ],
    "wof:name":"Environmental Evaluation",
    "wof:placetype":"venue"
},
  "geometry": {"coordinates":[-88.386878,33.498845],"type":"Point"}
}