{
  "type": "Feature",
  "properties": {
    "iso:country":"US",
    "sg:address":"60677 Smithville Rd",
    "sg:city":"Smithville",
    "sg:classifiers":[
        {
            "category":"Real Estate",
            "subcategory":"Real Estate Operator",
            "type":"Services"
        }
    ],
    "sg:phone":"+1 662 651 4275",
    "sg:postcode":"38870",
    "sg:province":"MS",
    "sg:tags":[
        "apartment"
    ],
    "wof:name":"Smithville Meadows Apts",
    "wof:placetype":"venue"
},
  "geometry": {"coordinates":[-88.391885,34.068574],"type":"Point"}
}