{
  "type": "Feature",
  "properties": {
    "iso:country":"US",
    "sg:address":"204 Heritage Dr",
    "sg:city":"Holly Springs",
    "sg:classifiers":[
        {
            "category":"Professional",
            "subcategory":"Management & Consulting",
            "type":"Services"
        }
    ],
    "sg:phone":"+1 662 551 1234",
    "sg:postcode":"38655",
    "sg:province":"MS",
    "wof:name":"Thomas Arena",
    "wof:placetype":"venue"
},
  "geometry": {"coordinates":[-89.558384,34.365248],"type":"Point"}
}