{
  "type": "Feature",
  "properties": {
    "iso:country":"US",
    "sg:address":"602 Brumbaugh Rd",
    "sg:city":"Ocean Springs",
    "sg:classifiers":[
        {
            "category":"Social Services",
            "subcategory":"Child Care",
            "type":"Services"
        }
    ],
    "sg:phone":"+1 228 872 4031",
    "sg:postcode":"39564",
    "sg:province":"MS",
    "sg:tags":[
        "day"
    ],
    "wof:name":"Marilyns Day Care",
    "wof:placetype":"venue"
},
  "geometry": {"coordinates":[-88.801614,30.399144],"type":"Point"}
}