{
  "type": "Feature",
  "properties": {
    "iso:country":"US",
    "sg:address":"209 W Georgetown St",
    "sg:city":"Crystal Springs",
    "sg:classifiers":[
        {
            "category":"Restaurant",
            "type":"Food & Drink"
        }
    ],
    "sg:phone":"+1 601 892 5276",
    "sg:postcode":"39059",
    "sg:province":"MS",
    "sg:tags":[
        "eating"
    ],
    "wof:name":"Charlie's Family Restaurant",
    "wof:placetype":"venue"
},
  "geometry": {"coordinates":[-90.35844,31.98793],"type":"Point"}
}