{
  "type": "Feature",
  "properties": {
    "addr:full":"8786 Center Hill Rd Olive Branch MS 38654",
    "addr:housenumber":"8786",
    "addr:postcode":"38654",
    "addr:street":"Center Hill Rd",
    "iso:country":"US",
    "sg:address":"8786 Center Hill Rd",
    "sg:city":"Olive Branch",
    "sg:classifiers":[
        {
            "category":"Building & Trades",
            "subcategory":"Landscaping Services",
            "type":"Services"
        }
    ],
    "sg:phone":"+1 662 893 3914",
    "sg:postcode":"38654",
    "sg:province":"MS",
    "wof:name":"M & W Trees",
    "wof:placetype":"venue"
},
  "geometry": {"coordinates":[-89.74187000000001,34.988483],"type":"Point"}
}