{
  "type": "Feature",
  "properties": {
    "iso:country":"US",
    "sg:address":"2268 Shadow Main",
    "sg:city":"Olive Branch",
    "sg:classifiers":[
        {
            "category":"Shopping",
            "subcategory":"Bicycles & Sporting Goods",
            "type":"Retail Goods"
        }
    ],
    "sg:phone":"+1 662 890 4868",
    "sg:postcode":"38654",
    "sg:province":"MS",
    "sg:tags":[
        "tackle",
        "fishing"
    ],
    "wof:name":"Southern Outdoors",
    "wof:placetype":"venue"
},
  "geometry": {"coordinates":[-89.807626,34.893792],"type":"Point"}
}