{
  "type": "Feature",
  "properties": {
    "iso:country":"US",
    "sg:address":"629 Carnation St",
    "sg:city":"Tupelo",
    "sg:classifiers":[
        {
            "category":"Taxi",
            "type":"Transportation"
        }
    ],
    "sg:phone":"+1 662 840 0920",
    "sg:postcode":"38804",
    "sg:province":"MS",
    "sg:tags":[
        "taxicab"
    ],
    "wof:name":"Chico's Cab Co",
    "wof:placetype":"venue"
},
  "geometry": {"coordinates":[-88.709503,34.253366],"type":"Point"}
}