{
  "type": "Feature",
  "properties": {
    "addr:full":"808 China St Vicksburg MS 39183",
    "addr:housenumber":"808",
    "addr:postcode":"39183",
    "addr:street":"China St",
    "iso:country":"US",
    "sg:address":"808 China St",
    "sg:city":"Vicksburg",
    "sg:classifiers":[
        {
            "category":"Personal",
            "subcategory":"Barber",
            "type":"Services"
        }
    ],
    "sg:phone":"+1 601 638 6050",
    "sg:postcode":"39183",
    "sg:province":"MS",
    "sg:tags":[
        "shop"
    ],
    "wof:name":"Hairmasters",
    "wof:placetype":"venue"
},
  "geometry": {"coordinates":[-90.88072200000001,32.350854],"type":"Point"}
}