{
  "type": "Feature",
  "properties": {
    "iso:country":"US",
    "sg:address":"473 Jess Lyons Rd",
    "sg:city":"Columbus",
    "sg:classifiers":[
        {
            "category":"Manufacturing",
            "subcategory":"Metals",
            "type":"Manufacturing & Wholesale Goods"
        }
    ],
    "sg:phone":"+1 662 329 2626",
    "sg:postcode":"39705",
    "sg:province":"MS",
    "sg:tags":[
        "building",
        "system"
    ],
    "wof:name":"Magnolia Drafting",
    "wof:placetype":"venue"
},
  "geometry": {"coordinates":[-88.429987,33.58135],"type":"Point"}
}