{
  "type": "Feature",
  "properties": {
    "iso:country":"US",
    "sg:address":"530 S 2nd Ave",
    "sg:city":"Columbus",
    "sg:classifiers":[
        {
            "category":"Insurance",
            "subcategory":"Insurance Agent",
            "type":"Services"
        }
    ],
    "sg:phone":"+1 662 327 4330",
    "sg:postcode":"39701",
    "sg:province":"MS",
    "wof:name":"Pate Insurance",
    "wof:placetype":"venue"
},
  "geometry": {"coordinates":[-88.427035,33.493998],"type":"Point"}
}