{
  "type": "Feature",
  "properties": {
    "iso:country":"US",
    "sg:address":"224 Porter Ave",
    "sg:city":"Biloxi",
    "sg:classifiers":[
        {
            "category":"Building & Trades",
            "subcategory":"Equipment Rental",
            "type":"Services"
        }
    ],
    "sg:phone":"+1 228 432 7433",
    "sg:postcode":"39530",
    "sg:province":"MS",
    "sg:tags":[
        "to",
        "electronics",
        "own",
        "appliance",
        "rent"
    ],
    "wof:name":"Biloxi Rent-All",
    "wof:placetype":"venue"
},
  "geometry": {"coordinates":[-88.901836,30.399976],"type":"Point"}
}