{
  "type": "Feature",
  "properties": {
    "addr:full":"601 22nd Ave Meridian MS 39301",
    "addr:housenumber":"601",
    "addr:postcode":"39301",
    "addr:street":"22Nd Ave",
    "iso:country":"US",
    "sg:address":"601 22nd Ave",
    "sg:city":"Meridian",
    "sg:classifiers":[
        {
            "category":"Health Services",
            "subcategory":"Doctor",
            "type":"Services"
        }
    ],
    "sg:phone":"+1 601 693 6612",
    "sg:postcode":"39301",
    "sg:province":"MS",
    "sg:tags":[
        "medical"
    ],
    "wof:name":"Rod Holland Dr",
    "wof:placetype":"venue"
},
  "geometry": {"coordinates":[-88.700501,32.36507],"type":"Point"}
}