{
  "type": "Feature",
  "properties": {
    "iso:country":"US",
    "sg:address":"405 N Applegate St",
    "sg:city":"Winona",
    "sg:classifiers":[
        {
            "category":"Banks & Credit Unions",
            "subcategory":"Bank",
            "type":"Services"
        }
    ],
    "sg:phone":"+1 662 283 1112",
    "sg:postcode":"38967",
    "sg:province":"MS",
    "sg:tags":[
        "depository",
        "banking"
    ],
    "wof:name":"Check Advance",
    "wof:placetype":"venue"
},
  "geometry": {"coordinates":[-89.736064,33.488386],"type":"Point"}
}