{
  "type": "Feature",
  "properties": {
    "addr:full":"1601 Clay St Vicksburg MS 39183",
    "addr:housenumber":"1601",
    "addr:postcode":"39183",
    "addr:street":"Clay St",
    "iso:country":"US",
    "sg:address":"1601 Clay St",
    "sg:city":"Vicksburg",
    "sg:classifiers":[
        {
            "category":"Autos & Motor Vehicles",
            "subcategory":"Auto Supplies",
            "type":"Retail Goods"
        }
    ],
    "sg:phone":"+1 601 636 8621",
    "sg:postcode":"39183",
    "sg:province":"MS",
    "sg:tags":[
        "automobile",
        "parts"
    ],
    "wof:name":"Auto Supply Inc",
    "wof:placetype":"venue"
},
  "geometry": {"coordinates":[-90.87175999999999,32.34872],"type":"Point"}
}