{
  "type": "Feature",
  "properties": {
    "iso:country":"US",
    "sg:address":"220 W Pine St",
    "sg:city":"Hattiesburg",
    "sg:classifiers":[
        {
            "category":"Professional",
            "subcategory":"Lawyer & Legal Services",
            "type":"Services"
        }
    ],
    "sg:phone":"+1 601 544 9700",
    "sg:postcode":"39401",
    "sg:province":"MS",
    "sg:tags":[
        "attorney"
    ],
    "wof:name":"Finch & Wicht",
    "wof:placetype":"venue"
},
  "geometry": {"coordinates":[-89.291569,31.325876],"type":"Point"}
}