{
  "type": "Feature",
  "properties": {
    "iso:country":"US",
    "sg:address":"409 Saint Louis St",
    "sg:city":"Pass Christian",
    "sg:classifiers":[
        {
            "category":"Retail",
            "subcategory":"Veterinary Services",
            "type":"Services"
        }
    ],
    "sg:phone":"+1 228 452 8838",
    "sg:postcode":"39571",
    "sg:province":"MS",
    "wof:name":"Live Oak Animal Hospital",
    "wof:placetype":"venue"
},
  "geometry": {"coordinates":[-89.257426,30.313433],"type":"Point"}
}