{
  "type": "Feature",
  "properties": {
    "iso:country":"US",
    "sg:address":"12056 Mobile Ave",
    "sg:city":"Gulfport",
    "sg:classifiers":[
        {
            "category":"Health Services",
            "subcategory":"Podiatrist",
            "type":"Services"
        }
    ],
    "sg:phone":"+1 228 832 4475",
    "sg:postcode":"39503",
    "sg:province":"MS",
    "wof:name":"Cohen Podiatry Clinic",
    "wof:placetype":"venue"
},
  "geometry": {"coordinates":[-89.099389,30.460231],"type":"Point"}
}