{
  "type": "Feature",
  "properties": {
    "iso:country":"US",
    "sg:address":"13109 Old Hwy 67",
    "sg:city":"Biloxi",
    "sg:classifiers":[
        {
            "category":"Professional",
            "subcategory":"Management & Consulting",
            "type":"Services"
        }
    ],
    "sg:phone":"+1 228 354 0091",
    "sg:postcode":"39532",
    "sg:province":"MS",
    "sg:tags":[
        "consultant",
        "educational"
    ],
    "wof:name":"Ed Solutions Inc",
    "wof:placetype":"venue"
},
  "geometry": {"coordinates":[-88.946434,30.47489],"type":"Point"}
}