{
  "type": "Feature",
  "properties": {
    "iso:country":"US",
    "sg:address":"7825 Hwy 51 N",
    "sg:city":"Southaven",
    "sg:classifiers":[
        {
            "category":"Food & Beverages",
            "subcategory":"Groceries & Convenience Stores",
            "type":"Retail Goods"
        }
    ],
    "sg:phone":"+1 662 393 0520",
    "sg:postcode":"38671",
    "sg:province":"MS",
    "wof:name":"Sid's Food Mart",
    "wof:placetype":"venue"
},
  "geometry": {"coordinates":[-90.016294,34.96906],"type":"Point"}
}