{
  "type": "Feature",
  "properties": {
    "addr:full":"821 Summit St Mccomb MS 39648",
    "addr:housenumber":"821",
    "addr:postcode":"39648",
    "addr:street":"Summit St",
    "iso:country":"US",
    "sg:address":"821 Summit St",
    "sg:city":"Mccomb",
    "sg:classifiers":[
        {
            "category":"Banks & Credit Unions",
            "subcategory":"Bank",
            "type":"Services"
        }
    ],
    "sg:phone":"+1 601 684 6278",
    "sg:postcode":"39648",
    "sg:province":"MS",
    "wof:name":"Pike County Teacher FCU",
    "wof:placetype":"venue"
},
  "geometry": {"coordinates":[-90.453945,31.25692],"type":"Point"}
}