{
  "type": "Feature",
  "properties": {
    "iso:country":"US",
    "sg:address":"716 W Georgetown St",
    "sg:city":"Crystal Springs",
    "sg:classifiers":[
        {
            "category":"Building & Trades",
            "subcategory":"Construction",
            "type":"Services"
        }
    ],
    "sg:phone":"+1 601 892 0825",
    "sg:postcode":"39059",
    "sg:province":"MS",
    "sg:tags":[
        "dry wall",
        "contractor"
    ],
    "wof:name":"Peveyco",
    "wof:placetype":"venue"
},
  "geometry": {"coordinates":[-90.363794,31.990388],"type":"Point"}
}