{
  "type": "Feature",
  "properties": {
    "iso:country":"US",
    "sg:address":"71 Tower Rd",
    "sg:city":"Wiggins",
    "sg:classifiers":[
        {
            "category":"Building & Trades",
            "subcategory":"Electrical",
            "type":"Services"
        }
    ],
    "sg:phone":"+1 601 928 2467",
    "sg:postcode":"39577",
    "sg:province":"MS",
    "sg:tags":[
        "electrical",
        "contractor"
    ],
    "wof:name":"Chad Ladnier",
    "wof:placetype":"venue"
},
  "geometry": {"coordinates":[-89.111633,30.963436],"type":"Point"}
}