{
  "type": "Feature",
  "properties": {
    "iso:country":"US",
    "sg:address":"2102 Clay St",
    "sg:city":"Vicksburg",
    "sg:classifiers":[
        {
            "category":"Retail",
            "subcategory":"Funeral Services",
            "type":"Services"
        }
    ],
    "sg:phone":"+1 601 629 3500",
    "sg:postcode":"39183",
    "sg:province":"MS",
    "sg:tags":[
        "director"
    ],
    "wof:name":"Lakeview Memorial Funeral Home",
    "wof:placetype":"venue"
},
  "geometry": {"coordinates":[-90.866663,32.347994],"type":"Point"}
}