{
  "type": "Feature",
  "properties": {
    "iso:country":"US",
    "sg:address":"1107 Hwy 44 E",
    "sg:city":"Mccomb",
    "sg:classifiers":[
        {
            "category":"Organizations",
            "subcategory":"Religious Organization",
            "type":"Services"
        }
    ],
    "sg:phone":"+1 601 249 2337",
    "sg:postcode":"39648",
    "sg:province":"MS",
    "sg:tags":[
        "church"
    ],
    "wof:name":"Gospel Assembly Church",
    "wof:placetype":"venue"
},
  "geometry": {"coordinates":[-90.427582,31.24791],"type":"Point"}
}