{
  "type": "Feature",
  "properties": {
    "iso:country":"US",
    "sg:address":"1710 Battleground Dr",
    "sg:city":"Iuka",
    "sg:classifiers":[
        {
            "category":"Professional",
            "subcategory":"Business Services",
            "type":"Services"
        }
    ],
    "sg:phone":"+1 662 423 3203",
    "sg:postcode":"38852",
    "sg:province":"MS",
    "sg:tags":[
        "monument"
    ],
    "wof:name":"Iuka Monument Co",
    "wof:placetype":"venue"
},
  "geometry": {"coordinates":[-88.206481,34.798094],"type":"Point"}
}