{
  "type": "Feature",
  "properties": {
    "iso:country":"US",
    "sg:address":"5404 I- 55 N",
    "sg:city":"Jackson",
    "sg:classifiers":[
        {
            "category":"Personal",
            "type":"Services"
        },
        {
            "category":"Shopping",
            "subcategory":"Clothing, Apparel, & Fashions",
            "type":"Retail Goods"
        }
    ],
    "sg:phone":"+1 601 957 2999",
    "sg:postcode":"39211",
    "sg:province":"MS",
    "sg:tags":[
        "fa",
        "rental",
        "costume",
        "party",
        "supply"
    ],
    "wof:name":"Jakis Bridal and Formal Wear",
    "wof:placetype":"venue"
},
  "geometry": {"coordinates":[-90.14771,32.375236],"type":"Point"}
}