{
  "type": "Feature",
  "properties": {
    "iso:country":"US",
    "sg:address":"944 Little St",
    "sg:city":"West Point",
    "sg:classifiers":[
        {
            "category":"Retail",
            "subcategory":"Auto Rental",
            "type":"Services"
        }
    ],
    "sg:phone":"+1 662 494 0108",
    "sg:postcode":"39773",
    "sg:province":"MS",
    "sg:tags":[
        "passenger",
        "car"
    ],
    "wof:name":"Avis Shelton Ind",
    "wof:placetype":"venue"
},
  "geometry": {"coordinates":[-88.655963,33.594893],"type":"Point"}
}