{
  "type": "Feature",
  "properties": {
    "iso:country":"US",
    "sg:address":"1090 Sam Lackey Rd",
    "sg:city":"Meridian",
    "sg:classifiers":[
        {
            "category":"Building & Trades",
            "subcategory":"Construction",
            "type":"Services"
        }
    ],
    "sg:phone":"+1 601 679 8323",
    "sg:postcode":"39305",
    "sg:province":"MS",
    "sg:tags":[
        "designer",
        "dealer",
        "pool",
        "swimming"
    ],
    "wof:name":"Pritchett Construction Co Inc",
    "wof:placetype":"venue"
},
  "geometry": {"coordinates":[-88.62902099999999,32.450238],"type":"Point"}
}