{
  "type": "Feature",
  "properties": {
    "iso:country":"US",
    "sg:address":"1076 Enterprise Rd SE",
    "sg:city":"Bogue Chitto",
    "sg:classifiers":[
        {
            "category":"Wholesale",
            "subcategory":"Petroleum",
            "type":"Manufacturing & Wholesale Goods"
        }
    ],
    "sg:phone":"+1 601 734 2725",
    "sg:postcode":"39629",
    "sg:province":"MS",
    "sg:tags":[
        "pipe",
        "line",
        "company"
    ],
    "wof:name":"Genesis Crude Oil Pipeline Div",
    "wof:placetype":"venue"
},
  "geometry": {"coordinates":[-90.42346499999999,31.467899],"type":"Point"}
}