{
  "type": "Feature",
  "properties": {
    "iso:country":"US",
    "sg:address":"125 E St",
    "sg:city":"Kosciusko",
    "sg:classifiers":[
        {
            "category":"Professional",
            "subcategory":"Business Services",
            "type":"Services"
        }
    ],
    "sg:phone":"+1 662 289 7064",
    "sg:postcode":"39090",
    "sg:province":"MS",
    "sg:tags":[
        "janitorial"
    ],
    "wof:name":"Foster Jimmy L Janitorial Svcs",
    "wof:placetype":"venue"
},
  "geometry": {"coordinates":[-89.586759,33.069696],"type":"Point"}
}