{
  "type": "Feature",
  "properties": {
    "addr:full":"785 Vieux Marche Ml Biloxi MS 39530",
    "addr:housenumber":"785",
    "addr:postcode":"39530",
    "addr:street":"Vieux Marche Ml",
    "iso:country":"US",
    "sg:address":"785 Vieux Marche Ml",
    "sg:city":"Biloxi",
    "sg:classifiers":[
        {
            "category":"Bars & Pubs",
            "type":"Food & Drink"
        }
    ],
    "sg:phone":"+1 228 374 5291",
    "sg:postcode":"39530",
    "sg:province":"MS",
    "sg:tags":[
        "drinking"
    ],
    "wof:name":"Upstair Downstairs Club Lounge",
    "wof:placetype":"venue"
},
  "geometry": {"coordinates":[-88.888762,30.396482],"type":"Point"}
}