{
  "type": "Feature",
  "properties": {
    "iso:country":"US",
    "sg:address":"10740 Linohau Way",
    "sg:city":"Diamondhead",
    "sg:classifiers":[
        {
            "category":"Building & Trades",
            "subcategory":"Construction",
            "type":"Services"
        }
    ],
    "sg:phone":"+1 228 255 7970",
    "sg:postcode":"39525",
    "sg:province":"MS",
    "sg:tags":[
        "general",
        "contractor"
    ],
    "wof:name":"Trinity Construction Inc",
    "wof:placetype":"venue"
},
  "geometry": {"coordinates":[-89.357674,30.404407],"type":"Point"}
}