{
  "type": "Feature",
  "properties": {
    "iso:country":"US",
    "sg:address":"630 W North St",
    "sg:city":"Canton",
    "sg:classifiers":[
        {
            "category":"Organizations",
            "subcategory":"Community Association",
            "type":"Services"
        }
    ],
    "sg:phone":"+1 601 855 2441",
    "sg:postcode":"39046",
    "sg:province":"MS",
    "wof:name":"Elks Lodge",
    "wof:placetype":"venue"
},
  "geometry": {"coordinates":[-90.04274100000001,32.615111],"type":"Point"}
}