{
  "type": "Feature",
  "properties": {
    "iso:country":"US",
    "sg:address":"1014 McCluer Rd",
    "sg:city":"Jackson",
    "sg:classifiers":[
        {
            "category":"Manufacturing",
            "subcategory":"Printing",
            "type":"Manufacturing & Wholesale Goods"
        }
    ],
    "sg:phone":"+1 601 372 5365",
    "sg:postcode":"39212",
    "sg:province":"MS",
    "sg:tags":[
        "label"
    ],
    "wof:name":"Magnolia Label Co Inc",
    "wof:placetype":"venue"
},
  "geometry": {"coordinates":[-90.249055,32.236866],"type":"Point"}
}