{
  "type": "Feature",
  "properties": {
    "addr:full":"215 Hwy 82 E Greenville MS 38701",
    "addr:housenumber":"215",
    "addr:postcode":"38701",
    "addr:street":"Hwy 82 E",
    "iso:country":"US",
    "sg:address":"215 Hwy 82 E",
    "sg:city":"Greenville",
    "sg:classifiers":[
        {
            "category":"Banks & Credit Unions",
            "subcategory":"Bank",
            "type":"Services"
        }
    ],
    "sg:phone":"+1 662 332 0026",
    "sg:postcode":"38701",
    "sg:province":"MS",
    "sg:tags":[
        "mortgage",
        "loan",
        "broker",
        "real estate"
    ],
    "wof:name":"Loans Are US",
    "wof:placetype":"venue"
},
  "geometry": {"coordinates":[-91.050155,33.399203],"type":"Point"}
}