{
  "type": "Feature",
  "properties": {
    "iso:country":"US",
    "sg:address":"122 Trestle Rd",
    "sg:city":"Columbia",
    "sg:classifiers":[
        {
            "category":"Home & Garden",
            "subcategory":"Building Materials",
            "type":"Retail Goods"
        }
    ],
    "sg:phone":"+1 601 736 9416",
    "sg:postcode":"39429",
    "sg:province":"MS",
    "wof:name":"Reid & Sons Sand & Gravel Inc",
    "wof:placetype":"venue"
},
  "geometry": {"coordinates":[-89.89210300000001,31.346313],"type":"Point"}
}