{
  "type": "Feature",
  "properties": {
    "iso:country":"US",
    "sg:address":"1855 Amhurst Cove",
    "sg:city":"Southaven",
    "sg:classifiers":[
        {
            "category":"Building & Trades",
            "subcategory":"Construction",
            "type":"Services"
        }
    ],
    "sg:phone":"+1 662 393 2258",
    "sg:postcode":"38671",
    "sg:province":"MS",
    "sg:tags":[
        "housing"
    ],
    "wof:name":"Pruitts Painting",
    "wof:placetype":"venue"
},
  "geometry": {"coordinates":[-90.02304599999999,34.973443],"type":"Point"}
}