{
  "type": "Feature",
  "properties": {
    "iso:country":"US",
    "sg:address":"2606 6th St",
    "sg:city":"Meridian",
    "sg:classifiers":[
        {
            "category":"Autos & Motor Vehicles",
            "subcategory":"Fuel & Gas Station",
            "type":"Retail Goods"
        }
    ],
    "sg:phone":"+1 601 693 9290",
    "sg:postcode":"39301",
    "sg:province":"MS",
    "sg:tags":[
        "oil"
    ],
    "wof:name":"U L Collins Amoco",
    "wof:placetype":"venue"
},
  "geometry": {"coordinates":[-88.703728,32.362659],"type":"Point"}
}