{
  "type": "Feature",
  "properties": {
    "iso:country":"US",
    "sg:address":"3593 Co Rd 961",
    "sg:city":"Tishomingo",
    "sg:classifiers":[
        {
            "category":"Retail",
            "subcategory":"Auto Repair",
            "type":"Services"
        }
    ],
    "sg:phone":"+1 662 438 6323",
    "sg:postcode":"38873",
    "sg:province":"MS",
    "sg:tags":[
        "body",
        "automobile",
        "painting"
    ],
    "wof:name":"Harris' Auto Body",
    "wof:placetype":"venue"
},
  "geometry": {"coordinates":[-88.266998,34.675601],"type":"Point"}
}