{
  "type": "Feature",
  "properties": {
    "iso:country":"US",
    "sg:address":"658 Pecan Grove Rd",
    "sg:city":"Ellisville",
    "sg:classifiers":[
        {
            "category":"Farming",
            "subcategory":"Berry Farm",
            "type":"Manufacturing & Wholesale Goods"
        }
    ],
    "sg:phone":"+1 601 477 8442",
    "sg:postcode":"39437",
    "sg:province":"MS",
    "sg:tags":[
        "crop"
    ],
    "wof:name":"Ainsworth Blueberry Farms",
    "wof:placetype":"venue"
},
  "geometry": {"coordinates":[-89.13446999999999,31.586949],"type":"Point"}
}