{
  "type": "Feature",
  "properties": {
    "iso:country":"US",
    "sg:address":"201 S 28th Ave",
    "sg:city":"Hattiesburg",
    "sg:classifiers":[
        {
            "category":"Shopping",
            "subcategory":"Pharmacy",
            "type":"Retail Goods"
        }
    ],
    "sg:phone":"+1 601 261 6150",
    "sg:postcode":"39401",
    "sg:province":"MS",
    "sg:website":"www.superd.com",
    "wof:name":"Super D Drug Express RX",
    "wof:placetype":"venue"
},
  "geometry": {"coordinates":[-89.33138,31.322705],"type":"Point"}
}