{
  "type": "Feature",
  "properties": {
    "iso:country":"US",
    "sg:address":"5025 Wayneland Dr",
    "sg:city":"Jackson",
    "sg:classifiers":[
        {
            "category":"Health Services",
            "subcategory":"Doctor",
            "type":"Services"
        }
    ],
    "sg:phone":"+1 601 956 7107",
    "sg:postcode":"39211",
    "sg:province":"MS",
    "sg:tags":[
        "medical"
    ],
    "wof:name":"Norman Cora PHD",
    "wof:placetype":"venue"
},
  "geometry": {"coordinates":[-90.146108,32.367529],"type":"Point"}
}