{
  "type": "Feature",
  "properties": {
    "iso:country":"US",
    "sg:address":"1700 Clay St",
    "sg:city":"Vicksburg",
    "sg:classifiers":[
        {
            "category":"Retail",
            "subcategory":"Auto Repair",
            "type":"Services"
        }
    ],
    "sg:phone":"+1 601 661 7800",
    "sg:postcode":"39183",
    "sg:province":"MS",
    "sg:tags":[
        "repairing",
        "automobile"
    ],
    "wof:name":"A-Tech Transmission Svc",
    "wof:placetype":"venue"
},
  "geometry": {"coordinates":[-90.87069,32.348569],"type":"Point"}
}