{
  "type": "Feature",
  "properties": {
    "iso:country":"US",
    "sg:address":"124 S Thomas St",
    "sg:city":"Tupelo",
    "sg:classifiers":[
        {
            "category":"Local Transit",
            "type":"Transportation"
        }
    ],
    "sg:phone":"+1 662 840 9484",
    "sg:postcode":"38801",
    "sg:province":"MS",
    "sg:tags":[
        "limousine"
    ],
    "wof:name":"Limousine Connection",
    "wof:placetype":"venue"
},
  "geometry": {"coordinates":[-88.746235,34.254446],"type":"Point"}
}