{
  "type": "Feature",
  "properties": {
    "iso:country":"US",
    "sg:address":"2700 Flowood Dr",
    "sg:city":"Flowood",
    "sg:classifiers":[
        {
            "category":"Home & Garden",
            "subcategory":"Carpets & Floor Coverings",
            "type":"Retail Goods"
        }
    ],
    "sg:phone":"+1 601 939 6800",
    "sg:postcode":"39232",
    "sg:province":"MS",
    "sg:tags":[
        "material"
    ],
    "wof:name":"Crescent Hardwood Supply",
    "wof:placetype":"venue"
},
  "geometry": {"coordinates":[-90.107574,32.323682],"type":"Point"}
}