{
  "type": "Feature",
  "properties": {
    "addr:full":"107 N Davis Ave Cleveland MS 38732",
    "addr:housenumber":"107",
    "addr:postcode":"38732",
    "addr:street":"N Davis Ave",
    "iso:country":"US",
    "sg:address":"107 N Davis Ave",
    "sg:city":"Cleveland",
    "sg:classifiers":[
        {
            "category":"Food & Beverages",
            "subcategory":"Bakery",
            "type":"Retail Goods"
        }
    ],
    "sg:phone":"+1 662 843 3930",
    "sg:postcode":"38732",
    "sg:province":"MS",
    "sg:tags":[
        "doughnut"
    ],
    "wof:name":"Delta Cream Donut Shop",
    "wof:placetype":"venue"
},
  "geometry": {"coordinates":[-90.71596099999999,33.74476],"type":"Point"}
}