{
  "type": "Feature",
  "properties": {
    "iso:country":"US",
    "sg:address":"9175 US Hwy 49",
    "sg:city":"Gulfport",
    "sg:classifiers":[
        {
            "category":"Manufacturing",
            "subcategory":"Musical Instruments",
            "type":"Manufacturing & Wholesale Goods"
        },
        {
            "category":"Shopping",
            "subcategory":"Musical Instruments",
            "type":"Retail Goods"
        }
    ],
    "sg:phone":"+1 228 575 9800",
    "sg:postcode":"39503",
    "sg:province":"MS",
    "sg:tags":[
        "mfg"
    ],
    "wof:name":"Magnolia Music I",
    "wof:placetype":"venue"
},
  "geometry": {"coordinates":[-89.09293700000001,30.418452],"type":"Point"}
}