{
  "type": "Feature",
  "properties": {
    "addr:full":"14473 Creosote Rd Gulfport MS 39503",
    "addr:housenumber":"14473",
    "addr:postcode":"39503",
    "addr:street":"Creosote Rd",
    "iso:country":"US",
    "sg:address":"14473 Creosote Rd",
    "sg:city":"Gulfport",
    "sg:classifiers":[
        {
            "category":"Autos & Motor Vehicles",
            "subcategory":"Auto Supplies",
            "type":"Retail Goods"
        }
    ],
    "sg:phone":"+1 228 863 1100",
    "sg:postcode":"39503",
    "sg:province":"MS",
    "wof:name":"Maximum Auto Parts & Supply",
    "wof:placetype":"venue"
},
  "geometry": {"coordinates":[-89.081777,30.427551],"type":"Point"}
}