{
  "type": "Feature",
  "properties": {
    "iso:country":"US",
    "sg:address":"530 W Main St",
    "sg:city":"Tupelo",
    "sg:classifiers":[
        {
            "category":"Restaurant",
            "type":"Food & Drink"
        }
    ],
    "sg:phone":"+1 662 680 3122",
    "sg:postcode":"38804",
    "sg:province":"MS",
    "sg:tags":[
        "caterer"
    ],
    "wof:name":"Rankin House",
    "wof:placetype":"venue"
},
  "geometry": {"coordinates":[-88.709673,34.257404],"type":"Point"}
}