{
  "type": "Feature",
  "properties": {
    "iso:country":"US",
    "sg:address":"107 Basket St",
    "sg:city":"Itta Bena",
    "sg:classifiers":[
        {
            "category":"Restaurant",
            "type":"Food & Drink"
        }
    ],
    "sg:phone":"+1 662 254 6688",
    "sg:postcode":"38941",
    "sg:province":"MS",
    "wof:name":"E & L",
    "wof:placetype":"venue"
},
  "geometry": {"coordinates":[-90.31984300000001,33.494683],"type":"Point"}
}