{
  "type": "Feature",
  "properties": {
    "addr:full":"813 30th Ave Meridian MS 39301",
    "addr:housenumber":"813",
    "addr:postcode":"39301",
    "addr:street":"30Th Ave",
    "iso:country":"US",
    "sg:address":"813 30th Ave",
    "sg:city":"Meridian",
    "sg:classifiers":[
        {
            "category":"Retail",
            "subcategory":"Portrait Studio",
            "type":"Services"
        }
    ],
    "sg:phone":"+1 601 696 9659",
    "sg:postcode":"39301",
    "sg:province":"MS",
    "sg:tags":[
        "photographer"
    ],
    "wof:name":"Perfection Video Productions",
    "wof:placetype":"venue"
},
  "geometry": {"coordinates":[-88.708809,32.365701],"type":"Point"}
}