{
  "type": "Feature",
  "properties": {
    "addr:full":"6973 Hwy 305 N Olive Branch MS 38654",
    "addr:housenumber":"6973",
    "addr:postcode":"38654",
    "addr:street":"Hwy 305 N",
    "iso:country":"US",
    "sg:address":"6973 Hwy 305 N",
    "sg:city":"Olive Branch",
    "sg:classifiers":[
        {
            "category":"Wholesale",
            "subcategory":"Electrical",
            "type":"Manufacturing & Wholesale Goods"
        }
    ],
    "sg:phone":"+1 662 895 3889",
    "sg:postcode":"38654",
    "sg:province":"MS",
    "sg:tags":[
        "operated",
        "telephone",
        "card"
    ],
    "wof:name":"Telaleasing Enterprises Inc",
    "wof:placetype":"venue"
},
  "geometry": {"coordinates":[-89.83047500000001,34.961434],"type":"Point"}
}