{
  "type": "Feature",
  "properties": {
    "iso:country":"US",
    "sg:address":"3680 N Gloster St",
    "sg:city":"Tupelo",
    "sg:classifiers":[
        {
            "category":"Banks & Credit Unions",
            "subcategory":"Bank",
            "type":"Services"
        }
    ],
    "sg:phone":"+1 662 680 1001",
    "sg:postcode":"38804",
    "sg:province":"MS",
    "wof:name":"Peoples Bank & Trust Co",
    "wof:placetype":"venue"
},
  "geometry": {"coordinates":[-88.707004,34.308871],"type":"Point"}
}