{
  "type": "Feature",
  "properties": {
    "addr:full":"601 Hwy 481 Pelahatchie MS 39145",
    "addr:housenumber":"601",
    "addr:postcode":"39145",
    "addr:street":"Hwy 481",
    "iso:country":"US",
    "sg:address":"601 Hwy 481",
    "sg:city":"Pelahatchie",
    "sg:classifiers":[
        {
            "category":"Farming",
            "subcategory":"Farm",
            "type":"Manufacturing & Wholesale Goods"
        }
    ],
    "sg:phone":"+1 601 854 8058",
    "sg:postcode":"39145",
    "sg:province":"MS",
    "sg:tags":[
        "crop",
        "general"
    ],
    "wof:name":"R McKay",
    "wof:placetype":"venue"
},
  "geometry": {"coordinates":[-89.771629,32.44008],"type":"Point"}
}