{
  "type": "Feature",
  "properties": {
    "iso:country":"US",
    "sg:address":"2059 Bankhead St",
    "sg:city":"Myrtle",
    "sg:classifiers":[
        {
            "category":"Organizations",
            "subcategory":"Religious Organization",
            "type":"Services"
        }
    ],
    "sg:phone":"+1 662 988 2939",
    "sg:postcode":"38650",
    "sg:province":"MS",
    "wof:name":"Greater New Hope Church",
    "wof:placetype":"venue"
},
  "geometry": {"coordinates":[-89.117529,34.558318],"type":"Point"}
}