{
  "type": "Feature",
  "properties": {
    "addr:full":"236 Pimlico Pl Jackson MS 39211",
    "addr:housenumber":"236",
    "addr:postcode":"39211",
    "addr:street":"Pimlico Pl",
    "iso:country":"US",
    "sg:address":"236 Pimlico Pl",
    "sg:city":"Jackson",
    "sg:classifiers":[
        {
            "category":"Professional",
            "subcategory":"Management & Consulting",
            "type":"Services"
        }
    ],
    "sg:phone":"+1 601 956 8004",
    "sg:postcode":"39211",
    "sg:province":"MS",
    "sg:tags":[
        "consultant",
        "educational"
    ],
    "wof:name":"Plato Learning",
    "wof:placetype":"venue"
},
  "geometry": {"coordinates":[-90.14323400000001,32.369271],"type":"Point"}
}