{
  "type": "Feature",
  "properties": {
    "addr:full":"304 N Main St Vardaman MS 38878",
    "addr:housenumber":"304",
    "addr:postcode":"38878",
    "addr:street":"N Main St",
    "iso:country":"US",
    "sg:address":"304 N Main St",
    "sg:city":"Vardaman",
    "sg:classifiers":[
        {
            "category":"Social Services",
            "type":"Services"
        }
    ],
    "sg:phone":"+1 662 682 7259",
    "sg:postcode":"38878",
    "sg:province":"MS",
    "sg:tags":[
        "organization",
        "welfare"
    ],
    "wof:name":"Vardaman Senior Citizen Nutri",
    "wof:placetype":"venue"
},
  "geometry": {"coordinates":[-89.17755200000001,33.87917],"type":"Point"}
}