{
  "type": "Feature",
  "properties": {
    "addr:full":"900 E Commerce St Hernando MS 38632",
    "addr:housenumber":"900",
    "addr:postcode":"38632",
    "addr:street":"E Commerce St",
    "iso:country":"US",
    "sg:address":"900 E Commerce St",
    "sg:city":"Hernando",
    "sg:classifiers":[
        {
            "category":"Travel",
            "subcategory":"Hotels & Motels",
            "type":"Entertainment"
        }
    ],
    "sg:phone":"+1 662 429 7811",
    "sg:postcode":"38632",
    "sg:province":"MS",
    "sg:tags":[
        "inn"
    ],
    "wof:name":"Hernando Inn",
    "wof:placetype":"venue"
},
  "geometry": {"coordinates":[-89.972855,34.823908],"type":"Point"}
}