{
  "type": "Feature",
  "properties": {
    "iso:country":"US",
    "sg:address":"1855 Lakeland Dr",
    "sg:city":"Jackson",
    "sg:classifiers":[
        {
            "category":"Professional",
            "subcategory":"Advertising",
            "type":"Services"
        }
    ],
    "sg:phone":"+1 601 366 6814",
    "sg:postcode":"39216",
    "sg:province":"MS",
    "sg:tags":[
        "counselor",
        "agency"
    ],
    "sg:website":"www.theeversolegroup.com",
    "wof:name":"Eversole Group",
    "wof:placetype":"venue"
},
  "geometry": {"coordinates":[-90.139017,32.333867],"type":"Point"}
}