{
  "type": "Feature",
  "properties": {
    "iso:country":"US",
    "sg:address":"10136 Magnolia Dr",
    "sg:city":"Olive Branch",
    "sg:classifiers":[
        {
            "category":"Manufacturing",
            "subcategory":"Textiles",
            "type":"Manufacturing & Wholesale Goods"
        }
    ],
    "sg:phone":"+1 662 895 5594",
    "sg:postcode":"38654",
    "sg:province":"MS",
    "sg:tags":[
        "material",
        "waterproofing"
    ],
    "sg:website":"www.sherwin.com",
    "wof:name":"Sherwin-Williams Paints",
    "wof:placetype":"venue"
},
  "geometry": {"coordinates":[-89.811549,34.949383],"type":"Point"}
}