{
  "type": "Feature",
  "properties": {
    "iso:country":"US",
    "sg:address":"223 Eastbrooke St",
    "sg:city":"Jackson",
    "sg:classifiers":[
        {
            "category":"Banks & Credit Unions",
            "subcategory":"Investment Brokerage",
            "type":"Services"
        }
    ],
    "sg:phone":"+1 601 981 4595",
    "sg:postcode":"39216",
    "sg:province":"MS",
    "sg:tags":[
        "security"
    ],
    "wof:name":"Hully Corporation",
    "wof:placetype":"venue"
},
  "geometry": {"coordinates":[-90.14853599999999,32.336059],"type":"Point"}
}