{
  "type": "Feature",
  "properties": {
    "iso:country":"US",
    "sg:address":"15171 Lamey Bridge Rd",
    "sg:city":"Biloxi",
    "sg:classifiers":[
        {
            "category":"Home & Garden",
            "subcategory":"Building Materials",
            "type":"Retail Goods"
        }
    ],
    "sg:phone":"+1 228 760 9929",
    "sg:postcode":"39532",
    "sg:province":"MS",
    "sg:tags":[
        "frame",
        "lumber",
        "marine"
    ],
    "wof:name":"Diamond Lumber Co",
    "wof:placetype":"venue"
},
  "geometry": {"coordinates":[-88.921288,30.501775],"type":"Point"}
}