{
  "type": "Feature",
  "properties": {
    "addr:full":"210 W Georgia Ave Mc Comb MS 39648",
    "addr:housenumber":"210",
    "addr:postcode":"39648",
    "addr:street":"W Georgia Ave Mc Comb",
    "iso:country":"US",
    "sg:address":"210 W Georgia Ave",
    "sg:city":"Mc Comb",
    "sg:classifiers":[
        {
            "category":"Wholesale",
            "subcategory":"Machinery & Supplies",
            "type":"Manufacturing & Wholesale Goods"
        }
    ],
    "sg:phone":"+1 601 250 6101",
    "sg:postcode":"39648",
    "sg:province":"MS",
    "sg:tags":[
        "fastener",
        "threaded"
    ],
    "wof:name":"Fastenal Company",
    "wof:placetype":"venue"
},
  "geometry": {"coordinates":[-90.454272,31.250309],"type":"Point"}
}