{
  "type": "Feature",
  "properties": {
    "iso:country":"US",
    "sg:address":"516 Melba St",
    "sg:city":"Jackson",
    "sg:classifiers":[
        {
            "category":"Health Services",
            "subcategory":"Nursing And Care Facility",
            "type":"Services"
        }
    ],
    "sg:phone":"+1 601 944 1208",
    "sg:postcode":"39203",
    "sg:province":"MS",
    "sg:tags":[
        "home",
        "retirement",
        "community"
    ],
    "wof:name":"Strickland's Personal Care Hm",
    "wof:placetype":"venue"
},
  "geometry": {"coordinates":[-90.200276,32.301797],"type":"Point"}
}