{
  "type": "Feature",
  "properties": {
    "iso:country":"US",
    "sg:address":"520 Belle Aire St",
    "sg:city":"Greenville",
    "sg:classifiers":[
        {
            "category":"Organizations",
            "subcategory":"Religious Organization",
            "type":"Services"
        }
    ],
    "sg:phone":"+1 662 332 4010",
    "sg:postcode":"38701",
    "sg:province":"MS",
    "wof:name":"Evergreen Baptist Church",
    "wof:placetype":"venue"
},
  "geometry": {"coordinates":[-91.05348499999999,33.418872],"type":"Point"}
}