{
  "type": "Feature",
  "properties": {
    "iso:country":"US",
    "sg:address":"2300 Demaret Dr",
    "sg:city":"Gulfport",
    "sg:classifiers":[
        {
            "category":"Retail",
            "subcategory":"Laundry & Dry Cleaning",
            "type":"Services"
        }
    ],
    "sg:phone":"+1 228 255 2002",
    "sg:postcode":"39507",
    "sg:province":"MS",
    "sg:tags":[
        "cleaners",
        "rug",
        "carpet"
    ],
    "wof:name":"Teddy Bear's Carpet Cleaning",
    "wof:placetype":"venue"
},
  "geometry": {"coordinates":[-89.014281,30.398228],"type":"Point"}
}