{
  "type": "Feature",
  "properties": {
    "iso:country":"US",
    "sg:address":"145 3rd St E",
    "sg:city":"Sledge",
    "sg:classifiers":[
        {
            "category":"Professional",
            "type":"Services"
        }
    ],
    "sg:phone":"+1 662 382 8989",
    "sg:postcode":"38606",
    "sg:province":"MS",
    "sg:tags":[
        "establishment"
    ],
    "wof:name":"Taylor & Butler's One Step",
    "wof:placetype":"venue"
},
  "geometry": {"coordinates":[-90.13352999999999,34.173519],"type":"Point"}
}