{
  "type": "Feature",
  "properties": {
    "iso:country":"US",
    "sg:address":"806 Belmont St",
    "sg:city":"Vicksburg",
    "sg:classifiers":[
        {
            "category":"Banks & Credit Unions",
            "subcategory":"Bank",
            "type":"Services"
        }
    ],
    "sg:phone":"+1 601 636 7700",
    "sg:postcode":"39180",
    "sg:province":"MS",
    "sg:tags":[
        "financing"
    ],
    "wof:name":"Republic Finance Inc",
    "wof:placetype":"venue"
},
  "geometry": {"coordinates":[-90.882852,32.342451],"type":"Point"}
}