{
  "type": "Feature",
  "properties": {
    "iso:country":"US",
    "sg:address":"131 Wash Dr",
    "sg:city":"Forest",
    "sg:classifiers":[
        {
            "category":"Farming",
            "subcategory":"Poultry Farm",
            "type":"Manufacturing & Wholesale Goods"
        }
    ],
    "sg:phone":"+1 601 469 2876",
    "sg:postcode":"39074",
    "sg:province":"MS",
    "wof:name":"Patrick Farm",
    "wof:placetype":"venue"
},
  "geometry": {"coordinates":[-89.43813299999999,32.463917],"type":"Point"}
}