{
  "type": "Feature",
  "properties": {
    "addr:full":"300 Cherry St Marks MS 38614",
    "addr:housenumber":"300",
    "addr:postcode":"38614",
    "addr:street":"Cherry St",
    "iso:country":"US",
    "sg:address":"300 Cherry St",
    "sg:city":"Marks",
    "sg:classifiers":[
        {
            "category":"Insurance",
            "subcategory":"Insurance Agent",
            "type":"Services"
        }
    ],
    "sg:phone":"+1 662 326 5777",
    "sg:postcode":"38614",
    "sg:province":"MS",
    "wof:name":"L F Vincent Insurance",
    "wof:placetype":"venue"
},
  "geometry": {"coordinates":[-90.58291699999999,34.198586],"type":"Point"}
}