{
  "type": "Feature",
  "properties": {
    "iso:country":"US",
    "sg:address":"302 Vorhees St",
    "sg:city":"Rosedale",
    "sg:classifiers":[
        {
            "category":"Insurance",
            "subcategory":"Insurance Agent",
            "type":"Services"
        }
    ],
    "sg:phone":"+1 662 759 6435",
    "sg:postcode":"38769",
    "sg:province":"MS",
    "wof:name":"Mc Caslin Insurance",
    "wof:placetype":"venue"
},
  "geometry": {"coordinates":[-91.02769000000001,33.855733],"type":"Point"}
}