{
  "type": "Feature",
  "properties": {
    "addr:full":"705 Bowie Ln Greenwood MS 38930",
    "addr:housenumber":"705",
    "addr:postcode":"38930",
    "addr:street":"Bowie Ln",
    "iso:country":"US",
    "sg:address":"705 Bowie Ln",
    "sg:city":"Greenwood",
    "sg:classifiers":[
        {
            "category":"Health Services",
            "subcategory":"Clinic",
            "type":"Services"
        }
    ],
    "sg:phone":"+1 662 455 4513",
    "sg:postcode":"38930",
    "sg:province":"MS",
    "sg:tags":[
        "allied"
    ],
    "wof:name":"Jesus First Christn Child Care",
    "wof:placetype":"venue"
},
  "geometry": {"coordinates":[-90.15916900000001,33.512543],"type":"Point"}
}