{
  "type": "Feature",
  "properties": {
    "iso:country":"US",
    "sg:address":"590 E Main St",
    "sg:city":"Louisville",
    "sg:classifiers":[
        {
            "category":"Autos & Motor Vehicles",
            "subcategory":"Auto Supplies",
            "type":"Retail Goods"
        }
    ],
    "sg:phone":"+1 662 773 9985",
    "sg:postcode":"39339",
    "sg:province":"MS",
    "sg:tags":[
        "tire"
    ],
    "wof:name":"Louisville Tire & Brakes Inc",
    "wof:placetype":"venue"
},
  "geometry": {"coordinates":[-89.030371,33.124698],"type":"Point"}
}