{
  "type": "Feature",
  "properties": {
    "iso:country":"US",
    "sg:address":"133 Wallace St",
    "sg:city":"Tupelo",
    "sg:classifiers":[
        {
            "category":"Wholesale",
            "subcategory":"Hardware",
            "type":"Manufacturing & Wholesale Goods"
        }
    ],
    "sg:phone":"+1 662 844 1952",
    "sg:postcode":"38804",
    "sg:province":"MS",
    "sg:tags":[
        "plumbing",
        "fixture",
        "supply"
    ],
    "wof:name":"Southern Pipe & Supply Co",
    "wof:placetype":"venue"
},
  "geometry": {"coordinates":[-88.708127,34.238217],"type":"Point"}
}