{
  "type": "Feature",
  "properties": {
    "addr:full":"212 Fannin Landing Cir Brandon MS 39047",
    "addr:housenumber":"212",
    "addr:postcode":"39047",
    "addr:street":"Fannin Landing Cir",
    "iso:country":"US",
    "sg:address":"212 Fannin Landing Cir",
    "sg:city":"Brandon",
    "sg:classifiers":[
        {
            "category":"Building & Trades",
            "subcategory":"Equipment Rental",
            "type":"Services"
        }
    ],
    "sg:phone":"+1 601 829 3721",
    "sg:postcode":"39047",
    "sg:province":"MS",
    "sg:tags":[
        "toilet"
    ],
    "wof:name":"Amer-Comf Portable Toilet",
    "wof:placetype":"venue"
},
  "geometry": {"coordinates":[-89.974575,32.421624],"type":"Point"}
}