{
  "type": "Feature",
  "properties": {
    "addr:full":"30 Collins Rd Collins MS 39401",
    "addr:housenumber":"30",
    "addr:postcode":"39401",
    "addr:street":"Collins Rd",
    "iso:country":"US",
    "sg:address":"30 Collins Rd",
    "sg:city":"Collins",
    "sg:classifiers":[
        {
            "category":"Retail",
            "subcategory":"Auto Repair",
            "type":"Services"
        }
    ],
    "sg:phone":"+1 601 765 3254",
    "sg:postcode":"39401",
    "sg:province":"MS",
    "sg:tags":[
        "repairing",
        "automobile",
        "general"
    ],
    "wof:name":"Eddie's Auto",
    "wof:placetype":"venue"
},
  "geometry": {"coordinates":[-89.281115,31.291947],"type":"Point"}
}