{
  "type": "Feature",
  "properties": {
    "iso:country":"US",
    "sg:address":"1142 Raymond Rd",
    "sg:city":"Jackson",
    "sg:classifiers":[
        {
            "category":"Real Estate",
            "subcategory":"Real Estate Operator",
            "type":"Services"
        }
    ],
    "sg:phone":"+1 601 502 2940",
    "sg:postcode":"39204",
    "sg:province":"MS",
    "sg:tags":[
        "apartment"
    ],
    "wof:name":"Wingfield Apartments",
    "wof:placetype":"venue"
},
  "geometry": {"coordinates":[-90.239541,32.284257],"type":"Point"}
}