{
  "type": "Feature",
  "properties": {
    "addr:full":"2401 Goodman Rd W Horn Lake MS 38637",
    "addr:housenumber":"2401",
    "addr:postcode":"38637",
    "addr:street":"Goodman Rd W Horn Lake",
    "iso:country":"US",
    "sg:address":"2401 Goodman Rd W",
    "sg:city":"Horn Lake",
    "sg:classifiers":[
        {
            "category":"Shopping",
            "subcategory":"Department Store",
            "type":"Retail Goods"
        }
    ],
    "sg:phone":"+1 662 342 5929",
    "sg:postcode":"38637",
    "sg:province":"MS",
    "sg:website":"www.walmart.com",
    "wof:name":"Wal-Mart",
    "wof:placetype":"venue"
},
  "geometry": {"coordinates":[-90.032421,34.962569],"type":"Point"}
}