{
  "type": "Feature",
  "properties": {
    "iso:country":"US",
    "sg:address":"1033 Church St",
    "sg:city":"Myrtle",
    "sg:classifiers":[
        {
            "category":"Organizations",
            "subcategory":"Religious Organization",
            "type":"Services"
        }
    ],
    "sg:phone":"+1 662 988 2516",
    "sg:postcode":"38650",
    "sg:province":"MS",
    "sg:tags":[
        "church"
    ],
    "wof:name":"Myrtle United Methodist Church",
    "wof:placetype":"venue"
},
  "geometry": {"coordinates":[-89.11448,34.558102],"type":"Point"}
}