{
  "type": "Feature",
  "properties": {
    "iso:country":"US",
    "sg:address":"2948 Market St",
    "sg:city":"Pascagoula",
    "sg:classifiers":[
        {
            "category":"Shopping",
            "subcategory":"Pharmacy",
            "type":"Retail Goods"
        }
    ],
    "sg:phone":"+1 228 762 5664",
    "sg:postcode":"39567",
    "sg:province":"MS",
    "wof:name":"Medicine Shoppe Pharmacy",
    "wof:placetype":"venue"
},
  "geometry": {"coordinates":[-88.548445,30.363628],"type":"Point"}
}