{
  "type": "Feature",
  "properties": {
    "iso:country":"US",
    "sg:address":"136 Courthouse Sq",
    "sg:city":"Oxford",
    "sg:classifiers":[
        {
            "category":"Shopping",
            "type":"Retail Goods"
        }
    ],
    "sg:phone":"+1 662 234 9907",
    "sg:postcode":"38655",
    "sg:province":"MS",
    "sg:tags":[
        "cosmetic",
        "perfume"
    ],
    "wof:name":"Therapy",
    "wof:placetype":"venue"
},
  "geometry": {"coordinates":[-89.51876900000001,34.366539],"type":"Point"}
}