{
  "type": "Feature",
  "properties": {
    "iso:country":"US",
    "sg:address":"6312 Longview Rd",
    "sg:city":"Tupelo",
    "sg:classifiers":[
        {
            "category":"Organizations",
            "subcategory":"Religious Organization",
            "type":"Services"
        }
    ],
    "sg:phone":"+1 662 841 1448",
    "sg:postcode":"38826",
    "sg:province":"MS",
    "sg:tags":[
        "church"
    ],
    "wof:name":"Chapel Grove Holiness Church",
    "wof:placetype":"venue"
},
  "geometry": {"coordinates":[-88.853145,34.276686],"type":"Point"}
}