{
  "type": "Feature",
  "properties": {
    "iso:country":"US",
    "sg:address":"114 N Montgomery St",
    "sg:city":"Starkville",
    "sg:classifiers":[
        {
            "category":"Health Services",
            "subcategory":"Nursing And Care Facility",
            "type":"Services"
        }
    ],
    "sg:phone":"+1 662 323 4617",
    "sg:postcode":"39759",
    "sg:province":"MS",
    "sg:tags":[
        "personal",
        "home"
    ],
    "wof:name":"Scribner's Personal Care Home",
    "wof:placetype":"venue"
},
  "geometry": {"coordinates":[-88.810165,33.465579],"type":"Point"}
}