{
  "type": "Feature",
  "properties": {
    "iso:country":"US",
    "sg:address":"1030 S Meridian St",
    "sg:city":"Aberdeen",
    "sg:classifiers":[
        {
            "category":"Organizations",
            "subcategory":"Religious Organization",
            "type":"Services"
        }
    ],
    "sg:phone":"+1 662 369 2622",
    "sg:postcode":"39730",
    "sg:province":"MS",
    "sg:tags":[
        "church"
    ],
    "wof:name":"Southside Baptist Church",
    "wof:placetype":"venue"
},
  "geometry": {"coordinates":[-88.544079,33.810598],"type":"Point"}
}