{
  "type": "Feature",
  "properties": {
    "iso:country":"US",
    "sg:address":"15 Top of Hill Ln",
    "sg:city":"Carriere",
    "sg:classifiers":[
        {
            "category":"Real Estate",
            "subcategory":"Real Estate Agent",
            "type":"Services"
        }
    ],
    "sg:phone":"+1 601 749 3413",
    "sg:postcode":"39426",
    "sg:province":"MS",
    "wof:name":"Musgrove Appraisals",
    "wof:placetype":"venue"
},
  "geometry": {"coordinates":[-89.643621,30.589551],"type":"Point"}
}