{
  "type": "Feature",
  "properties": {
    "iso:country":"US",
    "sg:address":"11163 US Hwy 49",
    "sg:city":"Gulfport",
    "sg:classifiers":[
        {
            "category":"Organizations",
            "subcategory":"Religious Organization",
            "type":"Services"
        }
    ],
    "sg:phone":"+1 228 328 2481",
    "sg:postcode":"39503",
    "sg:province":"MS",
    "sg:tags":[
        "church"
    ],
    "wof:name":"Crosspoint Church",
    "wof:placetype":"venue"
},
  "geometry": {"coordinates":[-89.099233,30.448204],"type":"Point"}
}