{
  "type": "Feature",
  "properties": {
    "iso:country":"US",
    "sg:address":"1105 S Gloster St",
    "sg:city":"Tupelo",
    "sg:classifiers":[
        {
            "category":"Home & Garden",
            "subcategory":"Mobile Homes",
            "type":"Retail Goods"
        }
    ],
    "sg:phone":"+1 662 842 1024",
    "sg:postcode":"38801",
    "sg:province":"MS",
    "wof:name":"Wheel Estate Mobile Homes",
    "wof:placetype":"venue"
},
  "geometry": {"coordinates":[-88.7193,34.232712],"type":"Point"}
}