{
  "type": "Feature",
  "properties": {
    "addr:full":"205 Royal Dr Long Beach MS 39560",
    "addr:housenumber":"205",
    "addr:postcode":"39560",
    "addr:street":"Royal Dr",
    "iso:country":"US",
    "sg:address":"205 Royal Dr",
    "sg:city":"Long Beach",
    "sg:classifiers":[
        {
            "category":"Building & Trades",
            "subcategory":"Electrical",
            "type":"Services"
        }
    ],
    "sg:phone":"+1 228 863 6072",
    "sg:postcode":"39560",
    "sg:province":"MS",
    "sg:tags":[
        "electric",
        "contractor"
    ],
    "wof:name":"Paige Electric",
    "wof:placetype":"venue"
},
  "geometry": {"coordinates":[-89.167557,30.365503],"type":"Point"}
}