{
  "type": "Feature",
  "properties": {
    "iso:country":"US",
    "sg:address":"3716 I- 55 N",
    "sg:city":"Jackson",
    "sg:classifiers":[
        {
            "category":"Restaurant",
            "type":"Food & Drink"
        }
    ],
    "sg:phone":"+1 601 713 2700",
    "sg:postcode":"39211",
    "sg:province":"MS",
    "wof:name":"Last Call",
    "wof:placetype":"venue"
},
  "geometry": {"coordinates":[-90.160594,32.338239],"type":"Point"}
}