{
  "type": "Feature",
  "properties": {
    "iso:country":"US",
    "sg:address":"200 Marion Ave",
    "sg:city":"Mc Comb",
    "sg:classifiers":[
        {
            "category":"Shopping",
            "subcategory":"Pharmacy",
            "type":"Retail Goods"
        }
    ],
    "sg:phone":"+1 601 684 7621",
    "sg:postcode":"39648",
    "sg:province":"MS",
    "wof:name":"SUPER D EXPRESS #231",
    "wof:placetype":"venue"
},
  "geometry": {"coordinates":[-90.47299,31.25107],"type":"Point"}
}