{
  "type": "Feature",
  "properties": {
    "iso:country":"US",
    "sg:address":"1145 Hillcrest Dr",
    "sg:city":"Laurel",
    "sg:classifiers":[
        {
            "category":"Freight",
            "type":"Transportation"
        }
    ],
    "sg:phone":"+1 601 425 9120",
    "sg:postcode":"39440",
    "sg:province":"MS",
    "sg:tags":[
        "hauling",
        "trucking"
    ],
    "wof:name":"Walters Transport",
    "wof:placetype":"venue"
},
  "geometry": {"coordinates":[-89.163695,31.669455],"type":"Point"}
}