{
  "type": "Feature",
  "properties": {
    "addr:full":"5820 N Commerce Plz Jackson MS 39206",
    "addr:housenumber":"5820",
    "addr:postcode":"39206",
    "addr:street":"N Commerce Plz",
    "iso:country":"US",
    "sg:address":"5820 N Commerce Plz",
    "sg:city":"Jackson",
    "sg:classifiers":[
        {
            "category":"Wholesale",
            "subcategory":"Hardware",
            "type":"Manufacturing & Wholesale Goods"
        }
    ],
    "sg:phone":"+1 601 957 1503",
    "sg:postcode":"39206",
    "sg:province":"MS",
    "sg:tags":[
        "fastener"
    ],
    "wof:name":"Sunbelt Bolt & Screw Co Inc",
    "wof:placetype":"venue"
},
  "geometry": {"coordinates":[-90.160608,32.384327],"type":"Point"}
}