{
  "type": "Feature",
  "properties": {
    "addr:full":"331 Park Ave Indianola MS 38751",
    "addr:housenumber":"331",
    "addr:postcode":"38751",
    "addr:street":"Park Ave",
    "iso:country":"US",
    "sg:address":"331 Park Ave",
    "sg:city":"Indianola",
    "sg:classifiers":[
        {
            "category":"Shopping",
            "subcategory":"Shoes",
            "type":"Retail Goods"
        }
    ],
    "sg:phone":"+1 662 445 2145",
    "sg:postcode":"38751",
    "sg:province":"MS",
    "wof:name":"Ola's Shoes Inc",
    "wof:placetype":"venue"
},
  "geometry": {"coordinates":[-90.643878,33.45554],"type":"Point"}
}