{
  "type": "Feature",
  "properties": {
    "iso:country":"US",
    "sg:address":"4613 8th St",
    "sg:city":"Meridian",
    "sg:classifiers":[
        {
            "category":"Personal",
            "subcategory":"Barber",
            "type":"Services"
        }
    ],
    "sg:phone":"+1 601 483 3852",
    "sg:postcode":"39307",
    "sg:province":"MS",
    "sg:tags":[
        "shop"
    ],
    "wof:name":"Golden Shears Barber Shop",
    "wof:placetype":"venue"
},
  "geometry": {"coordinates":[-88.725126,32.364473],"type":"Point"}
}