{
  "type": "Feature",
  "properties": {
    "addr:full":"530 Vaiden Dr Hernando MS 38632",
    "addr:housenumber":"530",
    "addr:postcode":"38632",
    "addr:street":"Vaiden Dr",
    "iso:country":"US",
    "sg:address":"530 Vaiden Dr",
    "sg:city":"Hernando",
    "sg:classifiers":[
        {
            "category":"Manufacturing",
            "subcategory":"Signs",
            "type":"Manufacturing & Wholesale Goods"
        }
    ],
    "sg:phone":"+1 662 449 4026",
    "sg:postcode":"38632",
    "sg:province":"MS",
    "sg:tags":[
        "specialty",
        "mfg"
    ],
    "wof:name":"M&R Signs",
    "wof:placetype":"venue"
},
  "geometry": {"coordinates":[-89.977062,34.815422],"type":"Point"}
}