{
  "type": "Feature",
  "properties": {
    "addr:full":"565 Hwy 41 E Okolona MS 38860",
    "addr:housenumber":"565",
    "addr:postcode":"38860",
    "addr:street":"Hwy 41 E Okolona",
    "iso:country":"US",
    "sg:address":"565 Hwy 41 E",
    "sg:city":"Okolona",
    "sg:classifiers":[
        {
            "category":"Professional",
            "subcategory":"Business Services",
            "type":"Services"
        }
    ],
    "sg:phone":"+1 662 447 9990",
    "sg:postcode":"38860",
    "sg:province":"MS",
    "sg:tags":[
        "liquidator"
    ],
    "wof:name":"Okolona Merchandise Liquidator",
    "wof:placetype":"venue"
},
  "geometry": {"coordinates":[-88.732523,34.001442],"type":"Point"}
}