{
  "type": "Feature",
  "properties": {
    "addr:full":"8802 Old Craft Rd Olive Branch MS 38654",
    "addr:housenumber":"8802",
    "addr:postcode":"38654",
    "addr:street":"Old Craft Rd",
    "iso:country":"US",
    "sg:address":"8802 Old Craft Rd",
    "sg:city":"Olive Branch",
    "sg:classifiers":[
        {
            "category":"Recreation",
            "type":"Entertainment"
        }
    ],
    "sg:phone":"+1 662 893 2119",
    "sg:postcode":"38654",
    "sg:province":"MS",
    "sg:tags":[
        "instruction",
        "gymnastic"
    ],
    "wof:name":"Our Gym",
    "wof:placetype":"venue"
},
  "geometry": {"coordinates":[-89.861552,34.989305],"type":"Point"}
}