{
  "type": "Feature",
  "properties": {
    "iso:country":"US",
    "sg:address":"231 Hillandale Ln",
    "sg:city":"Pearl",
    "sg:classifiers":[
        {
            "category":"Wholesale",
            "subcategory":"Hardware",
            "type":"Manufacturing & Wholesale Goods"
        }
    ],
    "sg:phone":"+1 601 420 4299",
    "sg:postcode":"39208",
    "sg:province":"MS",
    "sg:tags":[
        "air",
        "parts",
        "conditioning",
        "supply"
    ],
    "wof:name":"M & A Supply Inc",
    "wof:placetype":"venue"
},
  "geometry": {"coordinates":[-90.055133,32.286975],"type":"Point"}
}