{
  "type": "Feature",
  "properties": {
    "iso:country":"US",
    "sg:address":"747 S Washington Ave",
    "sg:city":"Greenville",
    "sg:classifiers":[
        {
            "category":"Shopping",
            "subcategory":"Stationery & Office Supplies",
            "type":"Retail Goods"
        }
    ],
    "sg:phone":"+1 662 347 5757",
    "sg:postcode":"38701",
    "sg:province":"MS",
    "wof:name":"Office Supplies & More",
    "wof:placetype":"venue"
},
  "geometry": {"coordinates":[-91.05211,33.396898],"type":"Point"}
}