{
  "type": "Feature",
  "properties": {
    "iso:country":"US",
    "sg:address":"8829 Centre St",
    "sg:city":"Southaven",
    "sg:classifiers":[
        {
            "category":"Health Services",
            "subcategory":"Health Practitioner",
            "type":"Services"
        }
    ],
    "sg:phone":"+1 662 342 2733",
    "sg:postcode":"38671",
    "sg:province":"MS",
    "sg:tags":[
        "psychologist"
    ],
    "wof:name":"Evergreen Behavioral Services",
    "wof:placetype":"venue"
},
  "geometry": {"coordinates":[-89.987531,34.991805],"type":"Point"}
}