{
  "type": "Feature",
  "properties": {
    "iso:country":"US",
    "sg:address":"105 Pruitt Ln",
    "sg:city":"Pearl",
    "sg:classifiers":[
        {
            "category":"Banks & Credit Unions",
            "subcategory":"Bank",
            "type":"Services"
        }
    ],
    "sg:phone":"+1 601 939 9600",
    "sg:postcode":"39208",
    "sg:province":"MS",
    "sg:tags":[
        "financing"
    ],
    "wof:name":"Hoover Finance Co Inc",
    "wof:placetype":"venue"
},
  "geometry": {"coordinates":[-90.096498,32.281458],"type":"Point"}
}