{
  "type": "Feature",
  "properties": {
    "addr:full":"2058 Flowood Dr Jackson MS 39232",
    "addr:housenumber":"2058",
    "addr:postcode":"39232",
    "addr:street":"Flowood Dr",
    "iso:country":"US",
    "sg:address":"2058 Flowood Dr",
    "sg:city":"Jackson",
    "sg:classifiers":[
        {
            "category":"Shopping",
            "type":"Retail Goods"
        }
    ],
    "sg:phone":"+1 601 939 8104",
    "sg:postcode":"39232",
    "sg:province":"MS",
    "sg:tags":[
        "phone",
        "sales",
        "cellular",
        "for"
    ],
    "wof:name":"Cingular Wireless",
    "wof:placetype":"venue"
},
  "geometry": {"coordinates":[-90.12582,32.319735],"type":"Point"}
}