{
  "type": "Feature",
  "properties": {
    "addr:full":"160 N Sharpe Ave Cleveland MS 38732",
    "addr:housenumber":"160",
    "addr:postcode":"38732",
    "addr:street":"N Sharpe Ave",
    "iso:country":"US",
    "sg:address":"160 N Sharpe Ave",
    "sg:city":"Cleveland",
    "sg:classifiers":[
        {
            "category":"Shopping",
            "subcategory":"Florist",
            "type":"Retail Goods"
        }
    ],
    "sg:phone":"+1 662 846 6136",
    "sg:postcode":"38732",
    "sg:province":"MS",
    "sg:website":"www.flowersnthings.com",
    "wof:name":"Flowers & Things",
    "wof:placetype":"venue"
},
  "geometry": {"coordinates":[-90.721504,33.745228],"type":"Point"}
}