{
  "type": "Feature",
  "properties": {
    "addr:full":"1022 Adkins Blvd Jackson MS 39211",
    "addr:housenumber":"1022",
    "addr:postcode":"39211",
    "addr:street":"Adkins Blvd",
    "iso:country":"US",
    "sg:address":"1022 Adkins Blvd",
    "sg:city":"Jackson",
    "sg:classifiers":[
        {
            "category":"Insurance",
            "subcategory":"Insurance Agent",
            "type":"Services"
        }
    ],
    "sg:phone":"+1 601 978 3750",
    "sg:postcode":"39211",
    "sg:province":"MS",
    "wof:name":"Crocker Claims Service",
    "wof:placetype":"venue"
},
  "geometry": {"coordinates":[-90.138631,32.384326],"type":"Point"}
}