{
  "type": "Feature",
  "properties": {
    "addr:full":"1305 Church Ave Cleveland MS 38732",
    "addr:housenumber":"1305",
    "addr:postcode":"38732",
    "addr:street":"Church Ave",
    "iso:country":"US",
    "sg:address":"1305 Church Ave",
    "sg:city":"Cleveland",
    "sg:classifiers":[
        {
            "category":"Professional",
            "subcategory":"Business Services",
            "type":"Services"
        }
    ],
    "sg:phone":"+1 662 843 4704",
    "sg:postcode":"38732",
    "sg:province":"MS",
    "wof:name":"Leroylambert",
    "wof:placetype":"venue"
},
  "geometry": {"coordinates":[-90.71983899999999,33.731208],"type":"Point"}
}