{
  "type": "Feature",
  "properties": {
    "iso:country":"US",
    "sg:address":"6 Bonnie St",
    "sg:city":"Hattiesburg",
    "sg:classifiers":[
        {
            "category":"Organizations",
            "subcategory":"Religious Organization",
            "type":"Services"
        }
    ],
    "sg:phone":"+1 601 545 2606",
    "sg:postcode":"39401",
    "sg:province":"MS",
    "sg:tags":[
        "church"
    ],
    "wof:name":"Pentecostal Temple Community",
    "wof:placetype":"venue"
},
  "geometry": {"coordinates":[-89.27941800000001,31.328796],"type":"Point"}
}