{
  "type": "Feature",
  "properties": {
    "iso:country":"US",
    "sg:address":"304 S State St",
    "sg:city":"Jackson",
    "sg:classifiers":[
        {
            "category":"Freight",
            "type":"Transportation"
        }
    ],
    "sg:phone":"+1 601 354 5333",
    "sg:postcode":"39201",
    "sg:province":"MS",
    "sg:tags":[
        "general"
    ],
    "wof:name":"Metroplex National Mini Stor",
    "wof:placetype":"venue"
},
  "geometry": {"coordinates":[-90.180982,32.296127],"type":"Point"}
}