{
  "type": "Feature",
  "properties": {
    "addr:full":"4600 Pope Crowder Rd Enid MS 38927",
    "addr:housenumber":"4600",
    "addr:postcode":"38927",
    "addr:street":"Pope Crowder Rd;Ms",
    "iso:country":"US",
    "sg:address":"4600 Pope Crowder Rd",
    "sg:city":"Enid",
    "sg:classifiers":[
        {
            "category":"Organizations",
            "subcategory":"Religious Organization",
            "type":"Services"
        }
    ],
    "sg:phone":"+1 662 563 9443",
    "sg:postcode":"38927",
    "sg:province":"MS",
    "wof:name":"Willow Sprng Assmbly God Chrch",
    "wof:placetype":"venue"
},
  "geometry": {"coordinates":[-89.988399,34.174284],"type":"Point"}
}