{
  "type": "Feature",
  "properties": {
    "addr:full":"6380 Ridgewood Court Dr Jackson MS 39211",
    "addr:housenumber":"6380",
    "addr:postcode":"39211",
    "addr:street":"Ridgewood Court Dr",
    "iso:country":"US",
    "sg:address":"6380 Ridgewood Court Dr",
    "sg:city":"Jackson",
    "sg:classifiers":[
        {
            "category":"Shopping",
            "subcategory":"Bicycles & Sporting Goods",
            "type":"Retail Goods"
        }
    ],
    "sg:phone":"+1 601 956 5500",
    "sg:postcode":"39211",
    "sg:province":"MS",
    "wof:name":"Play It Again Sports",
    "wof:placetype":"venue"
},
  "geometry": {"coordinates":[-90.139291,32.398437],"type":"Point"}
}