{
  "type": "Feature",
  "properties": {
    "addr:full":"10 E St Charleston MS 38921",
    "addr:housenumber":"10",
    "addr:postcode":"38921",
    "addr:street":"E St",
    "iso:country":"US",
    "sg:address":"10 E St",
    "sg:city":"Charleston",
    "sg:classifiers":[
        {
            "category":"Government",
            "subcategory":"Police Station",
            "type":"Public Place"
        }
    ],
    "sg:phone":"+1 662 647 0358",
    "sg:postcode":"38921",
    "sg:province":"MS",
    "sg:tags":[
        "sheriff"
    ],
    "wof:name":"Tallahatchie County Sheriffs",
    "wof:placetype":"venue"
},
  "geometry": {"coordinates":[-90.073302,34.005555],"type":"Point"}
}