{
  "type": "Feature",
  "properties": {
    "addr:full":"4130 Main St Moss Point MS 39563",
    "addr:housenumber":"4130",
    "addr:postcode":"39563",
    "addr:street":"Main St",
    "iso:country":"US",
    "sg:address":"4130 Main St",
    "sg:city":"Moss Point",
    "sg:classifiers":[
        {
            "category":"Autos & Motor Vehicles",
            "subcategory":"Fuel & Gas Station",
            "type":"Retail Goods"
        }
    ],
    "sg:phone":"+1 228 475 2533",
    "sg:postcode":"39563",
    "sg:province":"MS",
    "sg:tags":[
        "grocery",
        "station",
        "gasoline"
    ],
    "wof:name":"Conocophillips Holding Company",
    "wof:placetype":"venue"
},
  "geometry": {"coordinates":[-88.538586,30.405715],"type":"Point"}
}