{
  "type": "Feature",
  "properties": {
    "iso:country":"US",
    "sg:address":"527 Hwy 82 E",
    "sg:city":"Greenville",
    "sg:classifiers":[
        {
            "category":"Real Estate",
            "subcategory":"Real Estate Agent",
            "type":"Services"
        }
    ],
    "sg:phone":"+1 662 335 4592",
    "sg:postcode":"38701",
    "sg:province":"MS",
    "wof:name":"Mc Garrh Agency Inc",
    "wof:placetype":"venue"
},
  "geometry": {"coordinates":[-91.044956,33.399364],"type":"Point"}
}