{
  "type": "Feature",
  "properties": {
    "iso:country":"US",
    "sg:address":"5723 I- 55 N",
    "sg:city":"Jackson",
    "sg:classifiers":[
        {
            "category":"Travel",
            "subcategory":"Hotels & Motels",
            "type":"Entertainment"
        }
    ],
    "sg:phone":"+1 601 957 8557",
    "sg:postcode":"39206",
    "sg:province":"MS",
    "wof:name":"Fairfield Inn",
    "wof:placetype":"venue"
},
  "geometry": {"coordinates":[-90.147621,32.381363],"type":"Point"}
}