{
  "type": "Feature",
  "properties": {
    "iso:country":"US",
    "sg:address":"690 School St",
    "sg:city":"Tunica",
    "sg:classifiers":[
        {
            "category":"Education",
            "subcategory":"School",
            "type":"Public Place"
        }
    ],
    "sg:phone":"+1 662 363 1442",
    "sg:postcode":"38676",
    "sg:province":"MS",
    "wof:name":"Tunica Elementary School",
    "wof:placetype":"venue"
},
  "geometry": {"coordinates":[-90.382273,34.680237],"type":"Point"}
}