{
  "type": "Feature",
  "properties": {
    "iso:country":"US",
    "sg:address":"8520 Hwy 51 N",
    "sg:city":"Southaven",
    "sg:classifiers":[
        {
            "category":"Shopping",
            "subcategory":"Clothing, Apparel, & Fashions",
            "type":"Retail Goods"
        }
    ],
    "sg:phone":"+1 662 393 7396",
    "sg:postcode":"38671",
    "sg:province":"MS",
    "sg:tags":[
        "navy",
        "army"
    ],
    "wof:name":"Army Surplus Outlet Inc",
    "wof:placetype":"venue"
},
  "geometry": {"coordinates":[-90.01675899999999,34.985203],"type":"Point"}
}