{
  "type": "Feature",
  "properties": {
    "iso:country":"US",
    "sg:address":"224 Delta Pine Rd",
    "sg:city":"Beaumont",
    "sg:classifiers":[
        {
            "category":"Manufacturing",
            "subcategory":"Retail Goods",
            "type":"Manufacturing & Wholesale Goods"
        }
    ],
    "sg:phone":"+1 601 784 3414",
    "sg:postcode":"39423",
    "sg:province":"MS",
    "sg:tags":[
        "manufacturer"
    ],
    "wof:name":"Hood Industries Inc",
    "wof:placetype":"venue"
},
  "geometry": {"coordinates":[-88.92979200000001,31.177985],"type":"Point"}
}