{
  "type": "Feature",
  "properties": {
    "addr:full":"230 W McDowell Rd Jackson MS 39204",
    "addr:housenumber":"230",
    "addr:postcode":"39204",
    "addr:street":"W Mcdowell Rd",
    "iso:country":"US",
    "sg:address":"230 W McDowell Rd",
    "sg:city":"Jackson",
    "sg:classifiers":[
        {
            "category":"Building & Trades",
            "subcategory":"Plumbing",
            "type":"Services"
        }
    ],
    "sg:phone":"+1 601 372 9977",
    "sg:postcode":"39204",
    "sg:province":"MS",
    "sg:tags":[
        "conditioning",
        "air",
        "system",
        "contractor"
    ],
    "wof:name":"Little's Service Co",
    "wof:placetype":"venue"
},
  "geometry": {"coordinates":[-90.220978,32.268509],"type":"Point"}
}