{
  "type": "Feature",
  "properties": {
    "addr:full":"6135 Friars Point Rd Clarksdale MS 38614",
    "addr:housenumber":"6135",
    "addr:postcode":"38614",
    "addr:street":"Friars Point Rd",
    "iso:country":"US",
    "sg:address":"6135 Friars Point Rd",
    "sg:city":"Clarksdale",
    "sg:classifiers":[
        {
            "category":"Manufacturing",
            "subcategory":"Food",
            "type":"Manufacturing & Wholesale Goods"
        },
        {
            "category":"Farming",
            "subcategory":"Farm",
            "type":"Manufacturing & Wholesale Goods"
        }
    ],
    "sg:phone":"+1 662 627 7817",
    "sg:postcode":"38614",
    "sg:province":"MS",
    "sg:tags":[
        "corn",
        "product"
    ],
    "wof:name":"Tim Morris",
    "wof:placetype":"venue"
},
  "geometry": {"coordinates":[-90.602699,34.289532],"type":"Point"}
}