{
  "type": "Feature",
  "properties": {
    "iso:country":"US",
    "sg:address":"534 E Mitchell Ave",
    "sg:city":"Jackson",
    "sg:classifiers":[
        {
            "category":"Shopping",
            "subcategory":"Florist",
            "type":"Retail Goods"
        }
    ],
    "sg:phone":"+1 601 362 8611",
    "sg:postcode":"39216",
    "sg:province":"MS",
    "wof:name":"Bo-KAYS",
    "wof:placetype":"venue"
},
  "geometry": {"coordinates":[-90.177283,32.335394],"type":"Point"}
}