{
  "type": "Feature",
  "properties": {
    "addr:full":"1300 School St Tunica MS 38676",
    "addr:housenumber":"1300",
    "addr:postcode":"38676",
    "addr:street":"School St",
    "iso:country":"US",
    "sg:address":"1300 School St",
    "sg:city":"Tunica",
    "sg:classifiers":[
        {
            "category":"Government",
            "subcategory":"Office",
            "type":"Public Place"
        }
    ],
    "sg:phone":"+1 662 363 2451",
    "sg:postcode":"38676",
    "sg:province":"MS",
    "wof:name":"Chancery Clerk",
    "wof:placetype":"venue"
},
  "geometry": {"coordinates":[-90.381069,34.688862],"type":"Point"}
}