{
  "type": "Feature",
  "properties": {
    "iso:country":"US",
    "sg:address":"1172 Cottage Dr",
    "sg:city":"Greenville",
    "sg:classifiers":[
        {
            "category":"Insurance",
            "subcategory":"Insurance Agent",
            "type":"Services"
        }
    ],
    "sg:phone":"+1 662 335 0488",
    "sg:postcode":"38703",
    "sg:province":"MS",
    "sg:tags":[
        "adjuster"
    ],
    "wof:name":"Sorrells Bowers & Coats Inc",
    "wof:placetype":"venue"
},
  "geometry": {"coordinates":[-91.027084,33.388505],"type":"Point"}
}