{
  "type": "Feature",
  "properties": {
    "iso:country":"US",
    "sg:address":"110 Priester Dr",
    "sg:city":"Pearl",
    "sg:classifiers":[
        {
            "category":"Wholesale",
            "subcategory":"Chemicals & Plastics",
            "type":"Manufacturing & Wholesale Goods"
        }
    ],
    "sg:phone":"+1 601 936 9353",
    "sg:postcode":"39208",
    "sg:province":"MS",
    "wof:name":"Nexair LLC",
    "wof:placetype":"venue"
},
  "geometry": {"coordinates":[-90.126439,32.282984],"type":"Point"}
}