{
  "type": "Feature",
  "properties": {
    "addr:full":"8711 Old Spanish Trl Ocean Springs MS 39564",
    "addr:housenumber":"8711",
    "addr:postcode":"39564",
    "addr:street":"Old Spanish Trl",
    "iso:country":"US",
    "sg:address":"8711 Old Spanish Trl",
    "sg:city":"Ocean Springs",
    "sg:classifiers":[
        {
            "category":"Recreation",
            "type":"Entertainment"
        }
    ],
    "sg:phone":"+1 228 875 6551",
    "sg:postcode":"39564",
    "sg:province":"MS",
    "sg:tags":[
        "cage",
        "batting"
    ],
    "wof:name":"Hit City Indoor Batting Cages",
    "wof:placetype":"venue"
},
  "geometry": {"coordinates":[-88.754654,30.395515],"type":"Point"}
}