{
  "type": "Feature",
  "properties": {
    "iso:country":"US",
    "sg:address":"502 N Seal Ave",
    "sg:city":"Long Beach",
    "sg:classifiers":[
        {
            "category":"Building & Trades",
            "subcategory":"Cleaning & Sanitation",
            "type":"Services"
        }
    ],
    "sg:phone":"+1 228 324 0213",
    "sg:postcode":"39560",
    "sg:province":"MS",
    "sg:tags":[
        "maintenance"
    ],
    "wof:name":"Absolute Refrigeration",
    "wof:placetype":"venue"
},
  "geometry": {"coordinates":[-89.157416,30.360914],"type":"Point"}
}