{
  "type": "Feature",
  "properties": {
    "iso:country":"US",
    "sg:address":"1233 Gum Grove Rd SW",
    "sg:city":"Brookhaven",
    "sg:classifiers":[
        {
            "category":"Organizations",
            "subcategory":"Religious Organization",
            "type":"Services"
        }
    ],
    "sg:phone":"+1 601 833 7102",
    "sg:postcode":"39601",
    "sg:province":"MS",
    "wof:name":"Gum Grove Baptist Church",
    "wof:placetype":"venue"
},
  "geometry": {"coordinates":[-90.55166699999999,31.469573],"type":"Point"}
}