{
  "type": "Feature",
  "properties": {
    "addr:full":"1605 S Gloster St Tupelo MS 38801",
    "addr:housenumber":"1605",
    "addr:postcode":"38801",
    "addr:street":"S Gloster St",
    "iso:country":"US",
    "sg:address":"1605 S Gloster St",
    "sg:city":"Tupelo",
    "sg:classifiers":[
        {
            "category":"Autos & Motor Vehicles",
            "subcategory":"Automobile Sales",
            "type":"Retail Goods"
        }
    ],
    "sg:phone":"+1 662 844 0717",
    "sg:postcode":"38801",
    "sg:province":"MS",
    "sg:tags":[
        "used"
    ],
    "wof:name":"Garriosn Used Cars",
    "wof:placetype":"venue"
},
  "geometry": {"coordinates":[-88.71982,34.221868],"type":"Point"}
}