{
  "type": "Feature",
  "properties": {
    "iso:country":"US",
    "sg:address":"175 Shelby Speights Dr",
    "sg:city":"Purvis",
    "sg:classifiers":[
        {
            "category":"Government",
            "subcategory":"Office",
            "type":"Public Place"
        }
    ],
    "sg:phone":"+1 601 794 8615",
    "sg:postcode":"39475",
    "sg:province":"MS",
    "sg:tags":[
        "federal"
    ],
    "wof:name":"US Consolidated Farm Svc Agcy",
    "wof:placetype":"venue"
},
  "geometry": {"coordinates":[-89.416026,31.143376],"type":"Point"}
}