{
  "type": "Feature",
  "properties": {
    "iso:country":"US",
    "sg:address":"607 Highland Colony Pkwy",
    "sg:city":"Ridgeland",
    "sg:classifiers":[
        {
            "category":"Real Estate",
            "subcategory":"Real Estate Agent",
            "type":"Services"
        }
    ],
    "sg:phone":"+1 601 856 0009",
    "sg:postcode":"39157",
    "sg:province":"MS",
    "sg:website":"www.msjordan.com",
    "wof:name":"Mark S Jordan Co",
    "wof:placetype":"venue"
},
  "geometry": {"coordinates":[-90.16047500000001,32.417284],"type":"Point"}
}