{
  "type": "Feature",
  "properties": {
    "iso:country":"US",
    "sg:address":"1444 Old Aberdeen Rd",
    "sg:city":"Columbus",
    "sg:classifiers":[
        {
            "category":"Home & Garden",
            "subcategory":"Household Appliances",
            "type":"Retail Goods"
        }
    ],
    "sg:phone":"+1 662 327 1365",
    "sg:postcode":"39705",
    "sg:province":"MS",
    "wof:name":"Cowboy Maloney's Electric City",
    "wof:placetype":"venue"
},
  "geometry": {"coordinates":[-88.4332,33.517393],"type":"Point"}
}