{
  "type": "Feature",
  "properties": {
    "iso:country":"US",
    "sg:address":"4902 Watkins Dr",
    "sg:city":"Jackson",
    "sg:classifiers":[
        {
            "category":"Autos & Motor Vehicles",
            "subcategory":"Fuel & Gas Station",
            "type":"Retail Goods"
        }
    ],
    "sg:phone":"+1 601 981 8533",
    "sg:postcode":"39206",
    "sg:province":"MS",
    "sg:tags":[
        "oil"
    ],
    "wof:name":"Conoco Success Automotive",
    "wof:placetype":"venue"
},
  "geometry": {"coordinates":[-90.192753,32.371656],"type":"Point"}
}