{
  "type": "Feature",
  "properties": {
    "iso:country":"US",
    "sg:address":"689 Livingston Vernon Rd",
    "sg:city":"Flora",
    "sg:classifiers":[
        {
            "category":"Building & Trades",
            "subcategory":"Construction",
            "type":"Services"
        }
    ],
    "sg:phone":"+1 601 879 8629",
    "sg:postcode":"39071",
    "sg:province":"MS",
    "sg:tags":[
        "excavation",
        "contractor"
    ],
    "wof:name":"Thrasher Foundation Specialist",
    "wof:placetype":"venue"
},
  "geometry": {"coordinates":[-90.297645,32.589166],"type":"Point"}
}