{
  "type": "Feature",
  "properties": {
    "addr:full":"1314 19th Ave Meridian MS 39301",
    "addr:housenumber":"1314",
    "addr:postcode":"39301",
    "addr:street":"19Th Ave",
    "iso:country":"US",
    "sg:address":"1314 19th Ave",
    "sg:city":"Meridian",
    "sg:classifiers":[
        {
            "category":"Health Services",
            "subcategory":"Doctor",
            "type":"Services"
        }
    ],
    "sg:phone":"+1 601 483 2680",
    "sg:postcode":"39301",
    "sg:province":"MS",
    "sg:tags":[
        "clinic"
    ],
    "wof:name":"Phillips Medical System",
    "wof:placetype":"venue"
},
  "geometry": {"coordinates":[-88.697746,32.370668],"type":"Point"}
}