{
  "type": "Feature",
  "properties": {
    "addr:full":"2410 Knox St Gulfport MS 39503",
    "addr:housenumber":"2410",
    "addr:postcode":"39503",
    "addr:street":"Knox St",
    "iso:country":"US",
    "sg:address":"2410 Knox St",
    "sg:city":"Gulfport",
    "sg:classifiers":[
        {
            "category":"Wholesale",
            "subcategory":"Construction Materials",
            "type":"Manufacturing & Wholesale Goods"
        }
    ],
    "sg:phone":"+1 228 832 6006",
    "sg:postcode":"39503",
    "sg:province":"MS",
    "sg:tags":[
        "repair"
    ],
    "wof:name":"Gulfport Garage Door",
    "wof:placetype":"venue"
},
  "geometry": {"coordinates":[-89.05497099999999,30.446844],"type":"Point"}
}