{
  "type": "Feature",
  "properties": {
    "iso:country":"US",
    "sg:address":"701 S Hill Ct",
    "sg:city":"Biloxi",
    "sg:classifiers":[
        {
            "category":"Real Estate",
            "subcategory":"Real Estate Agent",
            "type":"Services"
        }
    ],
    "sg:phone":"+1 228 388 2426",
    "sg:postcode":"39532",
    "sg:province":"MS",
    "wof:name":"All Pro Stanley Realty",
    "wof:placetype":"venue"
},
  "geometry": {"coordinates":[-88.955833,30.427574],"type":"Point"}
}