{
  "type": "Feature",
  "properties": {
    "iso:country":"US",
    "sg:address":"253 S High School Ave",
    "sg:city":"Columbia",
    "sg:classifiers":[
        {
            "category":"Building & Trades",
            "subcategory":"Construction",
            "type":"Services"
        }
    ],
    "sg:phone":"+1 601 736 7657",
    "sg:postcode":"39429",
    "sg:province":"MS",
    "sg:tags":[
        "carpentry",
        "contractor"
    ],
    "wof:name":"D & G Cabinets & Woodwork",
    "wof:placetype":"venue"
},
  "geometry": {"coordinates":[-89.832652,31.247224],"type":"Point"}
}