{
  "type": "Feature",
  "properties": {
    "iso:country":"US",
    "sg:address":"652 Hwy 469 N",
    "sg:city":"Florence",
    "sg:classifiers":[
        {
            "category":"Building & Trades",
            "subcategory":"Construction",
            "type":"Services"
        }
    ],
    "sg:phone":"+1 601 845 2366",
    "sg:postcode":"39073",
    "sg:province":"MS",
    "sg:tags":[
        "excavating",
        "contractor"
    ],
    "wof:name":"Neely Trucking & Excavating",
    "wof:placetype":"venue"
},
  "geometry": {"coordinates":[-90.057739,32.203504],"type":"Point"}
}