{
  "type": "Feature",
  "properties": {
    "iso:country":"US",
    "sg:address":"864 Avery Blvd N",
    "sg:city":"Ridgeland",
    "sg:classifiers":[
        {
            "category":"Shopping",
            "subcategory":"Jewelry",
            "type":"Retail Goods"
        }
    ],
    "sg:phone":"+1 601 957 1975",
    "sg:postcode":"39157",
    "sg:province":"MS",
    "sg:tags":[
        "mail",
        "house"
    ],
    "wof:name":"Judy C Martin Inc",
    "wof:placetype":"venue"
},
  "geometry": {"coordinates":[-90.11553000000001,32.403474],"type":"Point"}
}