{
  "type": "Feature",
  "properties": {
    "addr:full":"1125 Bay St Picayune MS 39466",
    "addr:housenumber":"1125",
    "addr:postcode":"39466",
    "addr:street":"Bay St",
    "iso:country":"US",
    "sg:address":"1125 Bay St",
    "sg:city":"Picayune",
    "sg:classifiers":[
        {
            "category":"Freight",
            "type":"Transportation"
        }
    ],
    "sg:phone":"+1 601 799 0797",
    "sg:postcode":"39466",
    "sg:province":"MS",
    "wof:name":"Lagniappe Logistics Inc",
    "wof:placetype":"venue"
},
  "geometry": {"coordinates":[-89.69310400000001,30.53024],"type":"Point"}
}