{
  "type": "Feature",
  "properties": {
    "iso:country":"US",
    "sg:address":"916 Hwy 82 W",
    "sg:city":"Greenwood",
    "sg:classifiers":[
        {
            "category":"Banks & Credit Unions",
            "subcategory":"Financial Services",
            "type":"Services"
        }
    ],
    "sg:phone":"+1 662 453 6811",
    "sg:postcode":"38930",
    "sg:province":"MS",
    "sg:tags":[
        "company",
        "holding"
    ],
    "sg:website":"www.statecapitalcorp.com",
    "wof:name":"State Capital Corp",
    "wof:placetype":"venue"
},
  "geometry": {"coordinates":[-90.194513,33.507763],"type":"Point"}
}