{
  "type": "Feature",
  "properties": {
    "iso:country":"US",
    "sg:address":"4580 Parker Ln",
    "sg:city":"Bailey",
    "sg:classifiers":[
        {
            "category":"Building & Trades",
            "subcategory":"Construction",
            "type":"Services"
        },
        {
            "category":"Manufacturing",
            "subcategory":"Printing",
            "type":"Manufacturing & Wholesale Goods"
        }
    ],
    "sg:phone":"+1 601 737 5847",
    "sg:postcode":"39320",
    "sg:province":"MS",
    "sg:tags":[
        "newspaper",
        "general",
        "contractor"
    ],
    "wof:name":"Daily & Sons Construction Inc",
    "wof:placetype":"venue"
},
  "geometry": {"coordinates":[-88.72543,32.494316],"type":"Point"}
}