{
  "type": "Feature",
  "properties": {
    "addr:full":"1436 Isom Chapel Rd Holly Springs MS 38635",
    "addr:housenumber":"1436",
    "addr:postcode":"38635",
    "addr:street":"Isom Chapel Rd",
    "iso:country":"US",
    "sg:address":"1436 Isom Chapel Rd",
    "sg:city":"Holly Springs",
    "sg:classifiers":[
        {
            "category":"Organizations",
            "subcategory":"Religious Organization",
            "type":"Services"
        }
    ],
    "sg:phone":"+1 662 252 2859",
    "sg:postcode":"38635",
    "sg:province":"MS",
    "sg:tags":[
        "church"
    ],
    "wof:name":"Isom Chapel C M E Church",
    "wof:placetype":"venue"
},
  "geometry": {"coordinates":[-89.47630599999999,34.906772],"type":"Point"}
}