{
  "type": "Feature",
  "properties": {
    "iso:country":"US",
    "sg:address":"2400 16th St",
    "sg:city":"Meridian",
    "sg:classifiers":[
        {
            "category":"Health Services",
            "subcategory":"Doctor",
            "type":"Services"
        }
    ],
    "sg:phone":"+1 601 482 7570",
    "sg:postcode":"39301",
    "sg:province":"MS",
    "sg:tags":[
        "dentist"
    ],
    "wof:name":"Esthetics Unlimited",
    "wof:placetype":"venue"
},
  "geometry": {"coordinates":[-88.703693,32.373117],"type":"Point"}
}