{
  "type": "Feature",
  "properties": {
    "iso:country":"US",
    "sg:address":"75 Bratton Rd",
    "sg:city":"Grenada",
    "sg:classifiers":[
        {
            "category":"Restaurant",
            "type":"Food & Drink"
        }
    ],
    "sg:phone":"+1 662 227 1353",
    "sg:postcode":"38901",
    "sg:province":"MS",
    "sg:tags":[
        "eating"
    ],
    "wof:name":"Sisters Catfish & Steak",
    "wof:placetype":"venue"
},
  "geometry": {"coordinates":[-89.845251,33.82436],"type":"Point"}
}