{
  "type": "Feature",
  "properties": {
    "iso:country":"US",
    "sg:address":"4805 Maplewood Dr",
    "sg:city":"Jackson",
    "sg:classifiers":[
        {
            "category":"Professional",
            "subcategory":"Employment Agencies",
            "type":"Services"
        }
    ],
    "sg:phone":"+1 601 918 8100",
    "sg:postcode":"39206",
    "sg:province":"MS",
    "sg:tags":[
        "help",
        "supply"
    ],
    "wof:name":"Critical Care Rgestered Nurses",
    "wof:placetype":"venue"
},
  "geometry": {"coordinates":[-90.16778600000001,32.362868],"type":"Point"}
}