{
  "type": "Feature",
  "properties": {
    "iso:country":"US",
    "sg:address":"3010 Bond Rd",
    "sg:city":"Louisville",
    "sg:classifiers":[
        {
            "category":"Building & Trades",
            "subcategory":"Plumbing",
            "type":"Services"
        }
    ],
    "sg:phone":"+1 662 773 3875",
    "sg:postcode":"39339",
    "sg:province":"MS",
    "sg:tags":[
        "specializing",
        "plumbing",
        "general",
        "water",
        "contractor"
    ],
    "wof:name":"Hindman Plumbing & Water Svc",
    "wof:placetype":"venue"
},
  "geometry": {"coordinates":[-88.9841,33.130557],"type":"Point"}
}