{
  "type": "Feature",
  "properties": {
    "iso:country":"US",
    "sg:address":"4224 Prichard Rd",
    "sg:city":"Tunica",
    "sg:classifiers":[
        {
            "category":"Farming",
            "subcategory":"Farm & Veterinary Services",
            "type":"Manufacturing & Wholesale Goods"
        }
    ],
    "sg:phone":"+1 662 363 3806",
    "sg:postcode":"38676",
    "sg:province":"MS",
    "sg:tags":[
        "seed",
        "processing"
    ],
    "sg:website":"www.buckislandseed.com",
    "wof:name":"Buck Island Seed Co",
    "wof:placetype":"venue"
},
  "geometry": {"coordinates":[-90.326633,34.704669],"type":"Point"}
}