{
  "type": "Feature",
  "properties": {
    "iso:country":"US",
    "sg:address":"110 Service Dr",
    "sg:city":"Brandon",
    "sg:classifiers":[
        {
            "category":"Personal",
            "subcategory":"Tanning Parlor",
            "type":"Services"
        }
    ],
    "sg:phone":"+1 601 591 0210",
    "sg:postcode":"39042",
    "sg:province":"MS",
    "sg:tags":[
        "salon"
    ],
    "wof:name":"After Glow Tanning Salon",
    "wof:placetype":"venue"
},
  "geometry": {"coordinates":[-90.02847,32.2833],"type":"Point"}
}