{
  "type": "Feature",
  "properties": {
    "addr:full":"409 Briarwood Dr Jackson MS 39206",
    "addr:housenumber":"409",
    "addr:postcode":"39206",
    "addr:street":"Briarwood Dr",
    "iso:country":"US",
    "sg:address":"409 Briarwood Dr",
    "sg:city":"Jackson",
    "sg:classifiers":[
        {
            "category":"Professional",
            "subcategory":"Management & Consulting",
            "type":"Services"
        }
    ],
    "sg:phone":"+1 601 956 0395",
    "sg:postcode":"39206",
    "sg:province":"MS",
    "sg:tags":[
        "personnel",
        "consultant"
    ],
    "wof:name":"Staffmark",
    "wof:placetype":"venue"
},
  "geometry": {"coordinates":[-90.148819,32.380268],"type":"Point"}
}