{
  "type": "Feature",
  "properties": {
    "iso:country":"US",
    "sg:address":"106 S Whitworth Ave",
    "sg:city":"Brookhaven",
    "sg:classifiers":[
        {
            "category":"Restaurant",
            "type":"Food & Drink"
        }
    ],
    "sg:phone":"+1 601 833 2393",
    "sg:postcode":"39601",
    "sg:province":"MS",
    "sg:tags":[
        "eating"
    ],
    "wof:name":"Posey Place The Inc",
    "wof:placetype":"venue"
},
  "geometry": {"coordinates":[-90.443254,31.578514],"type":"Point"}
}