{
  "type": "Feature",
  "properties": {
    "addr:full":"412 N Gate Rd Hattiesburg MS 39401",
    "addr:housenumber":"412",
    "addr:postcode":"39401",
    "addr:street":"N Gate Rd",
    "iso:country":"US",
    "sg:address":"412 N Gate Rd",
    "sg:city":"Hattiesburg",
    "sg:classifiers":[
        {
            "category":"Government",
            "subcategory":"Office",
            "type":"Public Place"
        }
    ],
    "sg:phone":"+1 601 582 7576",
    "sg:postcode":"39401",
    "sg:province":"MS",
    "sg:tags":[
        "federal",
        "security"
    ],
    "wof:name":"Army National Guard-Ms State",
    "wof:placetype":"venue"
},
  "geometry": {"coordinates":[-89.23906700000001,31.231083],"type":"Point"}
}