{
  "type": "Feature",
  "properties": {
    "iso:country":"US",
    "sg:address":"1239 Hwy 1 N",
    "sg:city":"Greenville",
    "sg:classifiers":[
        {
            "category":"Real Estate",
            "subcategory":"Real Estate Agent",
            "type":"Services"
        }
    ],
    "sg:phone":"+1 662 335 0486",
    "sg:postcode":"38703",
    "sg:province":"MS",
    "sg:tags":[
        "management"
    ],
    "wof:name":"Mitchell Management",
    "wof:placetype":"venue"
},
  "geometry": {"coordinates":[-91.03874,33.424686],"type":"Point"}
}