{
  "type": "Feature",
  "properties": {
    "addr:full":"7491 Barbara Dr Hernando MS 38632",
    "addr:housenumber":"7491",
    "addr:postcode":"38632",
    "addr:street":"Barbara Dr",
    "iso:country":"US",
    "sg:address":"7491 Barbara Dr",
    "sg:city":"Hernando",
    "sg:classifiers":[
        {
            "category":"Professional",
            "type":"Services"
        }
    ],
    "sg:phone":"+1 662 429 2309",
    "sg:postcode":"38632",
    "sg:province":"MS",
    "wof:name":"Starward Internet Services LLC",
    "wof:placetype":"venue"
},
  "geometry": {"coordinates":[-89.980667,34.751366],"type":"Point"}
}