{
  "type": "Feature",
  "properties": {
    "iso:country":"US",
    "sg:address":"3195 Cooke Rd",
    "sg:city":"Houlka",
    "sg:classifiers":[
        {
            "category":"Real Estate",
            "subcategory":"Real Estate Operator",
            "type":"Services"
        }
    ],
    "sg:phone":"+1 662 568 2059",
    "sg:postcode":"38850",
    "sg:province":"MS",
    "sg:tags":[
        "property",
        "lessor"
    ],
    "wof:name":"Marvin Galloway",
    "wof:placetype":"venue"
},
  "geometry": {"coordinates":[-89.10041099999999,34.083923],"type":"Point"}
}