{
  "type": "Feature",
  "properties": {
    "iso:country":"US",
    "sg:address":"1209 Garrard Ave",
    "sg:city":"Greenwood",
    "sg:classifiers":[
        {
            "category":"Education",
            "subcategory":"School",
            "type":"Public Place"
        }
    ],
    "sg:phone":"+1 662 455 7450",
    "sg:postcode":"38930",
    "sg:province":"MS",
    "wof:name":"Greenwood High School",
    "wof:placetype":"venue"
},
  "geometry": {"coordinates":[-90.19839399999999,33.511791],"type":"Point"}
}