{
  "type": "Feature",
  "properties": {
    "iso:country":"US",
    "sg:address":"27 Barrontown Rd",
    "sg:city":"Petal",
    "sg:classifiers":[
        {
            "category":"Organizations",
            "subcategory":"Religious Organization",
            "type":"Services"
        }
    ],
    "sg:phone":"+1 601 582 4952",
    "sg:postcode":"39465",
    "sg:province":"MS",
    "wof:name":"Jehovahs Wtns Petal Kngdm Hall",
    "wof:placetype":"venue"
},
  "geometry": {"coordinates":[-89.205697,31.382818],"type":"Point"}
}