{
  "type": "Feature",
  "properties": {
    "iso:country":"US",
    "sg:address":"36 W Washington St",
    "sg:city":"Pontotoc",
    "sg:classifiers":[
        {
            "category":"Organizations",
            "subcategory":"Religious Organization",
            "type":"Services"
        }
    ],
    "sg:phone":"+1 662 489 5810",
    "sg:postcode":"38863",
    "sg:province":"MS",
    "sg:tags":[
        "church"
    ],
    "wof:name":"Christian Women Job Corps",
    "wof:placetype":"venue"
},
  "geometry": {"coordinates":[-88.999743,34.24705],"type":"Point"}
}