{
  "type": "Feature",
  "properties": {
    "iso:country":"US",
    "sg:address":"120 E Monticello St",
    "sg:city":"Brookhaven",
    "sg:classifiers":[
        {
            "category":"Personal",
            "subcategory":"Barber",
            "type":"Services"
        }
    ],
    "sg:phone":"+1 601 833 0056",
    "sg:postcode":"39601",
    "sg:province":"MS",
    "sg:tags":[
        "shop"
    ],
    "wof:name":"Grady's Barber Shop",
    "wof:placetype":"venue"
},
  "geometry": {"coordinates":[-90.441974,31.579385],"type":"Point"}
}