{
  "type": "Feature",
  "properties": {
    "iso:country":"US",
    "sg:address":"4351 Gautier Vancleave Rd",
    "sg:city":"Gautier",
    "sg:classifiers":[
        {
            "category":"Retail",
            "subcategory":"Laundry & Dry Cleaning",
            "type":"Services"
        }
    ],
    "sg:phone":"+1 228 497 6900",
    "sg:postcode":"39553",
    "sg:province":"MS",
    "sg:tags":[
        "cleaners"
    ],
    "wof:name":"St Peter Dry Cleaner",
    "wof:placetype":"venue"
},
  "geometry": {"coordinates":[-88.655828,30.405693],"type":"Point"}
}