{
  "type": "Feature",
  "properties": {
    "iso:country":"US",
    "sg:address":"7047 Bethel Rd",
    "sg:city":"Olive Branch",
    "sg:classifiers":[
        {
            "category":"Building & Trades",
            "subcategory":"Construction",
            "type":"Services"
        }
    ],
    "sg:phone":"+1 662 890 5647",
    "sg:postcode":"38654",
    "sg:province":"MS",
    "sg:tags":[
        "house"
    ],
    "wof:name":"Oakridge Homes",
    "wof:placetype":"venue"
},
  "geometry": {"coordinates":[-89.86499499999999,34.88943],"type":"Point"}
}