{
  "type": "Feature",
  "properties": {
    "iso:country":"US",
    "sg:address":"2500 Dana Rd",
    "sg:city":"Vicksburg",
    "sg:classifiers":[
        {
            "category":"Real Estate",
            "subcategory":"Real Estate Operator",
            "type":"Services"
        }
    ],
    "sg:phone":"+1 601 619 7759",
    "sg:postcode":"39180",
    "sg:province":"MS",
    "sg:tags":[
        "building",
        "nonresidential"
    ],
    "wof:name":"Southall Properties",
    "wof:placetype":"venue"
},
  "geometry": {"coordinates":[-90.89322,32.289196],"type":"Point"}
}