{
  "type": "Feature",
  "properties": {
    "addr:full":"3588 N Gloster St Tupelo MS 38804",
    "addr:housenumber":"3588",
    "addr:postcode":"38804",
    "addr:street":"N Gloster St",
    "iso:country":"US",
    "sg:address":"3588 N Gloster St",
    "sg:city":"Tupelo",
    "sg:classifiers":[
        {
            "category":"Restaurant",
            "type":"Food & Drink"
        }
    ],
    "sg:menulink":"http://www.allmenus.com/ms/saltillo/100819-captain-ds-seafood/menu/",
    "sg:phone":"+1 662 844 7440",
    "sg:postcode":"38804",
    "sg:province":"MS",
    "sg:tags":[
        "seafood",
        "american"
    ],
    "wof:name":"Captain D's Seafood",
    "wof:placetype":"venue"
},
  "geometry": {"coordinates":[-88.706267,34.322196],"type":"Point"}
}