{
  "type": "Feature",
  "properties": {
    "iso:country":"US",
    "sg:address":"4430 Nailor Rd",
    "sg:city":"Vicksburg",
    "sg:classifiers":[
        {
            "category":"Building & Trades",
            "subcategory":"Construction",
            "type":"Services"
        }
    ],
    "sg:phone":"+1 601 638 0919",
    "sg:postcode":"39180",
    "sg:province":"MS",
    "sg:tags":[
        "insulation",
        "heat",
        "contractor"
    ],
    "wof:name":"Insul-Pro Inc",
    "wof:placetype":"venue"
},
  "geometry": {"coordinates":[-90.858937,32.263611],"type":"Point"}
}