{
  "type": "Feature",
  "properties": {
    "addr:full":"307 Church St Columbia MS 39429",
    "addr:housenumber":"307",
    "addr:postcode":"39429",
    "addr:street":"Church St",
    "iso:country":"US",
    "sg:address":"307 Church St",
    "sg:city":"Columbia",
    "sg:classifiers":[
        {
            "category":"Professional",
            "subcategory":"Lawyer & Legal Services",
            "type":"Services"
        }
    ],
    "sg:phone":"+1 601 736 2084",
    "sg:postcode":"39429",
    "sg:province":"MS",
    "sg:tags":[
        "attorney"
    ],
    "wof:name":"T Michael Kuykendall",
    "wof:placetype":"venue"
},
  "geometry": {"coordinates":[-89.83442700000001,31.253283],"type":"Point"}
}