{
  "type": "Feature",
  "properties": {
    "iso:country":"US",
    "sg:address":"1014 Co Rd 326",
    "sg:city":"New Albany",
    "sg:classifiers":[
        {
            "category":"Organizations",
            "subcategory":"Religious Organization",
            "type":"Services"
        }
    ],
    "sg:phone":"+1 662 534 3020",
    "sg:postcode":"38652",
    "sg:province":"MS",
    "sg:tags":[
        "church"
    ],
    "wof:name":"Church Of Acts",
    "wof:placetype":"venue"
},
  "geometry": {"coordinates":[-89.01367999999999,34.419645],"type":"Point"}
}