{
  "type": "Feature",
  "properties": {
    "iso:country":"US",
    "sg:address":"1200 Country Club Rd",
    "sg:city":"Hattiesburg",
    "sg:classifiers":[
        {
            "category":"Organizations",
            "subcategory":"Religious Organization",
            "type":"Services"
        }
    ],
    "sg:phone":"+1 601 582 1740",
    "sg:postcode":"39401",
    "sg:province":"MS",
    "wof:name":"Pineview Presbyterian Church",
    "wof:placetype":"venue"
},
  "geometry": {"coordinates":[-89.30943000000001,31.305829],"type":"Point"}
}