{
  "type": "Feature",
  "properties": {
    "iso:country":"US",
    "sg:address":"268 Lester Rd",
    "sg:city":"Holly Springs",
    "sg:classifiers":[
        {
            "category":"Building & Trades",
            "subcategory":"Construction",
            "type":"Services"
        }
    ],
    "sg:phone":"+1 662 252 5845",
    "sg:postcode":"38635",
    "sg:province":"MS",
    "sg:tags":[
        "carpentry",
        "contractor"
    ],
    "wof:name":"Lester Construction",
    "wof:placetype":"venue"
},
  "geometry": {"coordinates":[-89.521081,34.780405],"type":"Point"}
}