{
  "type": "Feature",
  "properties": {
    "addr:full":"78 Lee Rd Natchez MS 39120",
    "addr:housenumber":"78",
    "addr:postcode":"39120",
    "addr:street":"Lee Rd",
    "iso:country":"US",
    "sg:address":"78 Lee Rd",
    "sg:city":"Natchez",
    "sg:classifiers":[
        {
            "category":"Manufacturing",
            "subcategory":"Metals",
            "type":"Manufacturing & Wholesale Goods"
        }
    ],
    "sg:phone":"+1 601 445 0288",
    "sg:postcode":"39120",
    "sg:province":"MS",
    "sg:tags":[
        "environmental",
        "fabrication"
    ],
    "wof:name":"Venco Industries Inc",
    "wof:placetype":"venue"
},
  "geometry": {"coordinates":[-91.27896699999999,31.601304],"type":"Point"}
}