{
  "type": "Feature",
  "properties": {
    "iso:country":"US",
    "sg:address":"6201 Hwy 18",
    "sg:city":"Brandon",
    "sg:classifiers":[
        {
            "category":"Shopping",
            "subcategory":"Bicycles & Sporting Goods",
            "type":"Retail Goods"
        }
    ],
    "sg:phone":"+1 601 824 4855",
    "sg:postcode":"39042",
    "sg:province":"MS",
    "sg:tags":[
        "equipment",
        "archery",
        "supply"
    ],
    "wof:name":"Highway 18 Svc Ctr",
    "wof:placetype":"venue"
},
  "geometry": {"coordinates":[-89.766481,32.074141],"type":"Point"}
}