{
  "type": "Feature",
  "properties": {
    "addr:full":"525 Brookman Dr Brookhaven MS 39601",
    "addr:housenumber":"525",
    "addr:postcode":"39601",
    "addr:street":"Brookman Dr",
    "iso:country":"US",
    "sg:address":"525 Brookman Dr",
    "sg:city":"Brookhaven",
    "sg:classifiers":[
        {
            "category":"Health Services",
            "subcategory":"Nursing And Care Facility",
            "type":"Services"
        }
    ],
    "sg:phone":"+1 601 833 2330",
    "sg:postcode":"39601",
    "sg:province":"MS",
    "sg:tags":[
        "skilled",
        "home",
        "retirement",
        "community"
    ],
    "wof:name":"Country Brook Living Ctr",
    "wof:placetype":"venue"
},
  "geometry": {"coordinates":[-90.45940899999999,31.58964],"type":"Point"}
}