{
  "type": "Feature",
  "properties": {
    "iso:country":"US",
    "sg:address":"301 US Hwy 98",
    "sg:city":"New Augusta",
    "sg:classifiers":[
        {
            "category":"Autos & Motor Vehicles",
            "subcategory":"Auto Supplies",
            "type":"Retail Goods"
        }
    ],
    "sg:phone":"+1 601 964 8355",
    "sg:postcode":"39462",
    "sg:province":"MS",
    "sg:tags":[
        "automobile",
        "parts"
    ],
    "wof:name":"New Augusta Auto Parts & Svc",
    "wof:placetype":"venue"
},
  "geometry": {"coordinates":[-89.02760600000001,31.200862],"type":"Point"}
}