{
  "type": "Feature",
  "properties": {
    "addr:full":"1417 Gardner Blvd Columbus MS 39702",
    "addr:housenumber":"1417",
    "addr:postcode":"39702",
    "addr:street":"Gardner Blvd",
    "iso:country":"US",
    "sg:address":"1417 Gardner Blvd",
    "sg:city":"Columbus",
    "sg:classifiers":[
        {
            "category":"Retail",
            "subcategory":"Repair Shop",
            "type":"Services"
        }
    ],
    "sg:phone":"+1 662 328 2557",
    "sg:postcode":"39702",
    "sg:province":"MS",
    "sg:tags":[
        "television",
        "radio"
    ],
    "wof:name":"Smith TV Buy Sell Trade & Rent",
    "wof:placetype":"venue"
},
  "geometry": {"coordinates":[-88.38968300000001,33.51054],"type":"Point"}
}