{
  "type": "Feature",
  "properties": {
    "iso:country":"US",
    "sg:address":"989 Springhill Rd",
    "sg:city":"Laurel",
    "sg:classifiers":[
        {
            "category":"Manufacturing",
            "subcategory":"Apparel",
            "type":"Manufacturing & Wholesale Goods"
        }
    ],
    "sg:phone":"+1 601 729 8891",
    "sg:postcode":"39443",
    "sg:province":"MS",
    "wof:name":"Blakeney Specialty Sewing",
    "wof:placetype":"venue"
},
  "geometry": {"coordinates":[-89.20566100000001,31.762795],"type":"Point"}
}