{
  "type": "Feature",
  "properties": {
    "iso:country":"US",
    "sg:address":"212 Issaquena Ave",
    "sg:city":"Clarksdale",
    "sg:classifiers":[
        {
            "category":"Shopping",
            "subcategory":"Florist",
            "type":"Retail Goods"
        }
    ],
    "sg:phone":"+1 662 627 7331",
    "sg:postcode":"38614",
    "sg:province":"MS",
    "wof:name":"J Craig Gaddy Florist",
    "wof:placetype":"venue"
},
  "geometry": {"coordinates":[-90.57249299999999,34.203223],"type":"Point"}
}