{
  "type": "Feature",
  "properties": {
    "addr:full":"50594 Greenwood Springs Rd Greenwood Spgs MS 38848",
    "addr:housenumber":"50594",
    "addr:postcode":"38848",
    "addr:street":"Greenwood Springs Rd",
    "iso:country":"US",
    "sg:address":"50594 Greenwood Springs Rd",
    "sg:city":"Greenwood Spgs",
    "sg:classifiers":[
        {
            "category":"Social Services",
            "subcategory":"Child Care",
            "type":"Services"
        }
    ],
    "sg:phone":"+1 662 257 6229",
    "sg:postcode":"38848",
    "sg:province":"MS",
    "wof:name":"Newlife Tabernacle & Daycare",
    "wof:placetype":"venue"
},
  "geometry": {"coordinates":[-88.31044799999999,33.88532],"type":"Point"}
}