{
  "type": "Feature",
  "properties": {
    "iso:country":"US",
    "sg:address":"124 Main St",
    "sg:city":"Raleigh",
    "sg:classifiers":[
        {
            "category":"Professional",
            "subcategory":"Lawyer & Legal Services",
            "type":"Services"
        }
    ],
    "sg:phone":"+1 601 782 9090",
    "sg:postcode":"39120",
    "sg:province":"MS",
    "sg:tags":[
        "attorney"
    ],
    "wof:name":"G David Garner",
    "wof:placetype":"venue"
},
  "geometry": {"coordinates":[-91.405936,31.561912],"type":"Point"}
}