{
  "type": "Feature",
  "properties": {
    "addr:full":"148 W Green St Hazlehurst MS 39083",
    "addr:housenumber":"148",
    "addr:postcode":"39083",
    "addr:street":"W Green St",
    "iso:country":"US",
    "sg:address":"148 W Green St",
    "sg:city":"Hazlehurst",
    "sg:classifiers":[
        {
            "category":"Shopping",
            "subcategory":"Pharmacy",
            "type":"Retail Goods"
        }
    ],
    "sg:phone":"+1 601 894 6098",
    "sg:postcode":"39083",
    "sg:province":"MS",
    "wof:name":"Concerned Care Pharmacy",
    "wof:placetype":"venue"
},
  "geometry": {"coordinates":[-90.395894,31.861942],"type":"Point"}
}