{
  "type": "Feature",
  "properties": {
    "addr:full":"103 Deletha Ln Brandon MS 39042",
    "addr:housenumber":"103",
    "addr:postcode":"39042",
    "addr:street":"Deletha Ln",
    "iso:country":"US",
    "sg:address":"103 Deletha Ln",
    "sg:city":"Brandon",
    "sg:classifiers":[
        {
            "category":"Real Estate",
            "subcategory":"Real Estate Operator",
            "type":"Services"
        }
    ],
    "sg:phone":"+1 601 824 7595",
    "sg:postcode":"39042",
    "sg:province":"MS",
    "sg:tags":[
        "building",
        "nonresidential"
    ],
    "wof:name":"Performance Properties LLC",
    "wof:placetype":"venue"
},
  "geometry": {"coordinates":[-89.930829,32.300316],"type":"Point"}
}