{
  "type": "Feature",
  "properties": {
    "addr:full":"205 Smith St Forest MS 39074",
    "addr:housenumber":"205",
    "addr:postcode":"39074",
    "addr:street":"Smith St",
    "iso:country":"US",
    "sg:address":"205 Smith St",
    "sg:city":"Forest",
    "sg:classifiers":[
        {
            "category":"Shopping",
            "subcategory":"Shoes",
            "type":"Retail Goods"
        }
    ],
    "sg:phone":"+1 601 469 3444",
    "sg:postcode":"39074",
    "sg:province":"MS",
    "wof:name":"Shoe Stop & More",
    "wof:placetype":"venue"
},
  "geometry": {"coordinates":[-89.47514099999999,32.362893],"type":"Point"}
}