{
  "type": "Feature",
  "properties": {
    "iso:country":"US",
    "sg:address":"18 Thorngate Dr",
    "sg:city":"Brandon",
    "sg:classifiers":[
        {
            "category":"Professional",
            "subcategory":"Accounting & Tax Preparation",
            "type":"Services"
        }
    ],
    "sg:phone":"+1 601 939 9500",
    "sg:postcode":"39042",
    "sg:province":"MS",
    "sg:tags":[
        "accountant"
    ],
    "wof:name":"Murphey & Assoc",
    "wof:placetype":"venue"
},
  "geometry": {"coordinates":[-90.01832400000001,32.289676],"type":"Point"}
}