{
  "type": "Feature",
  "properties": {
    "iso:country":"US",
    "sg:address":"701 Main St",
    "sg:city":"Greenwood",
    "sg:classifiers":[
        {
            "category":"Food & Beverages",
            "subcategory":"Groceries & Convenience Stores",
            "type":"Retail Goods"
        }
    ],
    "sg:phone":"+1 662 453 2837",
    "sg:postcode":"38930",
    "sg:province":"MS",
    "wof:name":"Double Quick 23",
    "wof:placetype":"venue"
},
  "geometry": {"coordinates":[-90.179969,33.515631],"type":"Point"}
}