{
  "type": "Feature",
  "properties": {
    "iso:country":"US",
    "sg:address":"4907 Hubert St",
    "sg:city":"Moss Point",
    "sg:classifiers":[
        {
            "category":"Personal",
            "subcategory":"Beauty Salon",
            "type":"Services"
        }
    ],
    "sg:phone":"+1 228 474 8313",
    "sg:postcode":"39563",
    "sg:province":"MS",
    "sg:tags":[
        "shop"
    ],
    "wof:name":"Jackson Park Beauty Salon",
    "wof:placetype":"venue"
},
  "geometry": {"coordinates":[-88.527384,30.396847],"type":"Point"}
}