{
  "type": "Feature",
  "properties": {
    "iso:country":"US",
    "sg:address":"3 Springlake Pt",
    "sg:city":"Pearl",
    "sg:classifiers":[
        {
            "category":"Professional",
            "subcategory":"Business Services",
            "type":"Services"
        }
    ],
    "sg:phone":"+1 601 932 1288",
    "sg:postcode":"39208",
    "sg:province":"MS",
    "wof:name":"Amme",
    "wof:placetype":"venue"
},
  "geometry": {"coordinates":[-90.079425,32.276623],"type":"Point"}
}