{
  "type": "Feature",
  "properties": {
    "iso:country":"US",
    "sg:address":"1000 Turtle Creek Dr",
    "sg:city":"Hattiesburg",
    "sg:classifiers":[
        {
            "category":"Professional",
            "type":"Services"
        }
    ],
    "sg:phone":"+1 601 261 0188",
    "sg:postcode":"39402",
    "sg:province":"MS",
    "sg:tags":[
        "establishment"
    ],
    "wof:name":"Teletouch",
    "wof:placetype":"venue"
},
  "geometry": {"coordinates":[-89.3762,31.330083],"type":"Point"}
}