{
  "type": "Feature",
  "properties": {
    "iso:country":"US",
    "sg:address":"7439 Goodman Rd",
    "sg:city":"Olive Branch",
    "sg:classifiers":[
        {
            "category":"Personal",
            "subcategory":"Beauty Salon",
            "type":"Services"
        }
    ],
    "sg:phone":"+1 662 893 4546",
    "sg:postcode":"38654",
    "sg:province":"MS",
    "sg:tags":[
        "shop"
    ],
    "wof:name":"Jennifer Nails Salon",
    "wof:placetype":"venue"
},
  "geometry": {"coordinates":[-89.856658,34.962125],"type":"Point"}
}