{
  "type": "Feature",
  "properties": {
    "addr:full":"325 W Bankhead St New Albany MS 38652",
    "addr:housenumber":"325",
    "addr:postcode":"38652",
    "addr:street":"W Bankhead St",
    "iso:country":"US",
    "sg:address":"325 W Bankhead St",
    "sg:city":"New Albany",
    "sg:classifiers":[
        {
            "category":"Autos & Motor Vehicles",
            "subcategory":"Auto Supplies",
            "type":"Retail Goods"
        }
    ],
    "sg:phone":"+1 662 534 0157",
    "sg:postcode":"38652",
    "sg:province":"MS",
    "sg:tags":[
        "parts"
    ],
    "wof:name":"Autozone 379",
    "wof:placetype":"venue"
},
  "geometry": {"coordinates":[-89.01778299999999,34.49587],"type":"Point"}
}