{
  "type": "Feature",
  "properties": {
    "addr:full":"202 2nd Ave N Amory MS 38821",
    "addr:housenumber":"202",
    "addr:postcode":"38821",
    "addr:street":"2Nd Ave N Amory",
    "iso:country":"US",
    "sg:address":"202 2nd Ave N",
    "sg:city":"Amory",
    "sg:classifiers":[
        {
            "category":"Insurance",
            "subcategory":"Insurance Agent",
            "type":"Services"
        }
    ],
    "sg:phone":"+1 662 256 1100",
    "sg:postcode":"38821",
    "sg:province":"MS",
    "wof:name":"Galloway-Chandler-Mc Kinney",
    "wof:placetype":"venue"
},
  "geometry": {"coordinates":[-88.488989,33.986896],"type":"Point"}
}