{
  "type": "Feature",
  "properties": {
    "iso:country":"US",
    "sg:address":"1331 Westhaven Blvd",
    "sg:city":"Jackson",
    "sg:classifiers":[
        {
            "category":"Food & Beverages",
            "subcategory":"Groceries & Convenience Stores",
            "type":"Retail Goods"
        }
    ],
    "sg:phone":"+1 601 922 7109",
    "sg:postcode":"39209",
    "sg:province":"MS",
    "wof:name":"Westhaven Shopette",
    "wof:placetype":"venue"
},
  "geometry": {"coordinates":[-90.27016,32.310842],"type":"Point"}
}