{
  "type": "Feature",
  "properties": {
    "addr:full":"317 S Magnolia St Laurel MS 39440",
    "addr:housenumber":"317",
    "addr:postcode":"39440",
    "addr:street":"S Magnolia St",
    "iso:country":"US",
    "sg:address":"317 S Magnolia St",
    "sg:city":"Laurel",
    "sg:classifiers":[
        {
            "category":"Government",
            "subcategory":"Police Station",
            "type":"Public Place"
        }
    ],
    "sg:phone":"+1 601 425 4711",
    "sg:postcode":"39440",
    "sg:province":"MS",
    "sg:tags":[
        "department"
    ],
    "wof:name":"Laurel City Police Dept",
    "wof:placetype":"venue"
},
  "geometry": {"coordinates":[-89.134021,31.687514],"type":"Point"}
}