{
  "type": "Feature",
  "properties": {
    "iso:country":"US",
    "sg:address":"5119 Frederick St",
    "sg:city":"Moss Point",
    "sg:classifiers":[
        {
            "category":"Organizations",
            "subcategory":"Religious Organization",
            "type":"Services"
        }
    ],
    "sg:phone":"+1 228 475 7374",
    "sg:postcode":"39563",
    "sg:province":"MS",
    "wof:name":"Full Gospel Pentecostal Church",
    "wof:placetype":"venue"
},
  "geometry": {"coordinates":[-88.524631,30.398858],"type":"Point"}
}