{
  "type": "Feature",
  "properties": {
    "addr:full":"414 Hwy 12 W Starkville MS 39759",
    "addr:housenumber":"414",
    "addr:postcode":"39759",
    "addr:street":"Hwy 12 W",
    "iso:country":"US",
    "sg:address":"414 Hwy 12 W",
    "sg:city":"Starkville",
    "sg:classifiers":[
        {
            "category":"Professional",
            "subcategory":"Accounting & Tax Preparation",
            "type":"Services"
        }
    ],
    "sg:phone":"+1 662 320 4704",
    "sg:postcode":"39759",
    "sg:province":"MS",
    "sg:tags":[
        "return"
    ],
    "wof:name":"Babers Tax Services",
    "wof:placetype":"venue"
},
  "geometry": {"coordinates":[-88.825503,33.453994],"type":"Point"}
}