{
  "type": "Feature",
  "properties": {
    "addr:full":"3003 Lakeland Cove Flowood MS 39232",
    "addr:housenumber":"3003",
    "addr:postcode":"39232",
    "addr:street":"Lakeland Cove",
    "iso:country":"US",
    "sg:address":"3003 Lakeland Cove",
    "sg:city":"Flowood",
    "sg:classifiers":[
        {
            "category":"Banks & Credit Unions",
            "subcategory":"Bank",
            "type":"Services"
        }
    ],
    "sg:phone":"+1 601 936 3535",
    "sg:postcode":"39232",
    "sg:province":"MS",
    "sg:tags":[
        "loan",
        "real estate"
    ],
    "wof:name":"Homefirst",
    "wof:placetype":"venue"
},
  "geometry": {"coordinates":[-90.12399000000001,32.329065],"type":"Point"}
}