{
  "type": "Feature",
  "properties": {
    "iso:country":"US",
    "sg:address":"4417 27th St",
    "sg:city":"Meridian",
    "sg:classifiers":[
        {
            "category":"Professional",
            "subcategory":"Management & Consulting",
            "type":"Services"
        }
    ],
    "sg:phone":"+1 601 693 8615",
    "sg:postcode":"39307",
    "sg:province":"MS",
    "sg:tags":[
        "business"
    ],
    "wof:name":"Rise Above Poverty",
    "wof:placetype":"venue"
},
  "geometry": {"coordinates":[-88.722679,32.386281],"type":"Point"}
}