{
  "type": "Feature",
  "properties": {
    "iso:country":"US",
    "sg:address":"201 S 28th Ave",
    "sg:city":"Hattiesburg",
    "sg:classifiers":[
        {
            "category":"Professional",
            "subcategory":"Management & Consulting",
            "type":"Services"
        }
    ],
    "sg:phone":"+1 601 261 9978",
    "sg:postcode":"39401",
    "sg:province":"MS",
    "sg:tags":[
        "consultant",
        "energy",
        "conservation"
    ],
    "wof:name":"Diversified System Resources",
    "wof:placetype":"venue"
},
  "geometry": {"coordinates":[-89.33138,31.322705],"type":"Point"}
}