{
  "type": "Feature",
  "properties": {
    "addr:full":"1241 Terry Rd Jackson MS 39204",
    "addr:housenumber":"1241",
    "addr:postcode":"39204",
    "addr:street":"Terry Rd",
    "iso:country":"US",
    "sg:address":"1241 Terry Rd",
    "sg:city":"Jackson",
    "sg:classifiers":[
        {
            "category":"Retail",
            "subcategory":"Auto Repair",
            "type":"Services"
        }
    ],
    "sg:phone":"+1 601 355 0202",
    "sg:postcode":"39204",
    "sg:province":"MS",
    "sg:tags":[
        "repairing",
        "automobile"
    ],
    "wof:name":"Greg & Greg",
    "wof:placetype":"venue"
},
  "geometry": {"coordinates":[-90.202276,32.290937],"type":"Point"}
}