{
  "type": "Feature",
  "properties": {
    "iso:country":"US",
    "sg:address":"144 Twelve Oaks Trce",
    "sg:city":"Canton",
    "sg:classifiers":[
        {
            "category":"Communications",
            "subcategory":"Film & Video Production",
            "type":"Services"
        }
    ],
    "sg:phone":"+1 601 853 9955",
    "sg:postcode":"39046",
    "sg:province":"MS",
    "sg:tags":[
        "motion"
    ],
    "wof:name":"Times Fly",
    "wof:placetype":"venue"
},
  "geometry": {"coordinates":[-90.036278,32.495323],"type":"Point"}
}