{
  "type": "Feature",
  "properties": {
    "iso:country":"US",
    "sg:address":"144 S Thomas St",
    "sg:city":"Tupelo",
    "sg:classifiers":[
        {
            "category":"Home & Garden",
            "subcategory":"Garden Supply",
            "type":"Retail Goods"
        }
    ],
    "sg:phone":"+1 662 844 1949",
    "sg:postcode":"38801",
    "sg:province":"MS",
    "sg:tags":[
        "bulb",
        "seed"
    ],
    "wof:name":"Delta & Pine Land Co",
    "wof:placetype":"venue"
},
  "geometry": {"coordinates":[-88.746234,34.254277],"type":"Point"}
}