{
  "type": "Feature",
  "properties": {
    "iso:country":"US",
    "sg:address":"4323 Mc Innis Ave",
    "sg:city":"Moss Point",
    "sg:classifiers":[
        {
            "category":"Government",
            "subcategory":"Fire Station",
            "type":"Public Place"
        }
    ],
    "sg:phone":"+1 228 474 1344",
    "sg:postcode":"39563",
    "sg:province":"MS",
    "sg:tags":[
        "department"
    ],
    "wof:name":"Fire Chief",
    "wof:placetype":"venue"
},
  "geometry": {"coordinates":[-88.510232,30.398798],"type":"Point"}
}