{
  "type": "Feature",
  "properties": {
    "iso:country":"US",
    "sg:address":"2314 Turkey Creek Rd",
    "sg:city":"Starkville",
    "sg:classifiers":[
        {
            "category":"Retail",
            "subcategory":"Repair Shop",
            "type":"Services"
        }
    ],
    "sg:phone":"+1 662 324 2658",
    "sg:postcode":"39759",
    "sg:province":"MS",
    "wof:name":"Boardtown Locksmith",
    "wof:placetype":"venue"
},
  "geometry": {"coordinates":[-88.720941,33.408408],"type":"Point"}
}