{
  "type": "Feature",
  "properties": {
    "addr:full":"2531 Lower Woodville Rd Woodville MS 39669",
    "addr:housenumber":"2531",
    "addr:postcode":"39669",
    "addr:street":"Lower Woodville Rd",
    "iso:country":"US",
    "sg:address":"2531 Lower Woodville Rd",
    "sg:city":"Woodville",
    "sg:classifiers":[
        {
            "category":"Farming",
            "subcategory":"Farm",
            "type":"Manufacturing & Wholesale Goods"
        }
    ],
    "sg:phone":"+1 601 888 4961",
    "sg:postcode":"39669",
    "sg:province":"MS",
    "wof:name":"C & C Farms & Rental",
    "wof:placetype":"venue"
},
  "geometry": {"coordinates":[-91.329864,31.142717],"type":"Point"}
}