{
  "type": "Feature",
  "properties": {
    "iso:country":"US",
    "sg:address":"1220 US Hwy 11",
    "sg:city":"Heidelberg",
    "sg:classifiers":[
        {
            "category":"Organizations",
            "subcategory":"Religious Organization",
            "type":"Services"
        }
    ],
    "sg:phone":"+1 601 787 4614",
    "sg:postcode":"39439",
    "sg:province":"MS",
    "wof:name":"Shady Grove Frst Baptst Church",
    "wof:placetype":"venue"
},
  "geometry": {"coordinates":[-88.946848,31.890793],"type":"Point"}
}