{
  "type": "Feature",
  "properties": {
    "iso:country":"US",
    "sg:address":"57 Pine Dr",
    "sg:city":"Picayune",
    "sg:classifiers":[
        {
            "category":"Organizations",
            "subcategory":"Religious Organization",
            "type":"Services"
        }
    ],
    "sg:phone":"+1 601 798 8858",
    "sg:postcode":"39466",
    "sg:province":"MS",
    "sg:tags":[
        "church"
    ],
    "wof:name":"Parkview Baptist Church",
    "wof:placetype":"venue"
},
  "geometry": {"coordinates":[-89.582385,30.556681],"type":"Point"}
}