{
  "type": "Feature",
  "properties": {
    "addr:full":"302 East Ave N Hollandale MS 38748",
    "addr:housenumber":"302",
    "addr:postcode":"38748",
    "addr:street":"East Ave N",
    "iso:country":"US",
    "sg:address":"302 East Ave N",
    "sg:city":"Hollandale",
    "sg:classifiers":[
        {
            "category":"Education",
            "subcategory":"Library",
            "type":"Public Place"
        }
    ],
    "sg:phone":"+1 662 827 2335",
    "sg:postcode":"38748",
    "sg:province":"MS",
    "wof:name":"Torrey Wood Memorial Library",
    "wof:placetype":"venue"
},
  "geometry": {"coordinates":[-90.85511099999999,33.17195],"type":"Point"}
}