{
  "type": "Feature",
  "properties": {
    "iso:country":"US",
    "sg:address":"3159 Edwards Ave",
    "sg:city":"Jackson",
    "sg:classifiers":[
        {
            "category":"Social Services",
            "subcategory":"Child Care",
            "type":"Services"
        }
    ],
    "sg:phone":"+1 601 960 1420",
    "sg:postcode":"39213",
    "sg:province":"MS",
    "sg:tags":[
        "day"
    ],
    "wof:name":"Virden Day Care",
    "wof:placetype":"venue"
},
  "geometry": {"coordinates":[-90.19489799999999,32.342081],"type":"Point"}
}