{
  "type": "Feature",
  "properties": {
    "iso:country":"US",
    "sg:address":"103 Elliott St",
    "sg:city":"Fulton",
    "sg:classifiers":[
        {
            "category":"Building & Trades",
            "subcategory":"Cleaning & Sanitation",
            "type":"Services"
        }
    ],
    "sg:phone":"+1 662 862 7540",
    "sg:postcode":"38843",
    "sg:province":"MS",
    "sg:tags":[
        "maintenance"
    ],
    "wof:name":"Neat Services",
    "wof:placetype":"venue"
},
  "geometry": {"coordinates":[-88.398319,34.277878],"type":"Point"}
}