{
  "type": "Feature",
  "properties": {
    "iso:country":"US",
    "sg:address":"44 Pittman Rd",
    "sg:city":"Ocean Springs",
    "sg:classifiers":[
        {
            "category":"Real Estate",
            "subcategory":"Surveying",
            "type":"Services"
        }
    ],
    "sg:phone":"+1 228 875 2692",
    "sg:postcode":"39564",
    "sg:province":"MS",
    "sg:tags":[
        "engineering"
    ],
    "wof:name":"Vickery Thomas M Pe Pls",
    "wof:placetype":"venue"
},
  "geometry": {"coordinates":[-88.76953,30.398321],"type":"Point"}
}