{
  "type": "Feature",
  "properties": {
    "iso:country":"US",
    "sg:address":"209 Main St",
    "sg:city":"Greenville",
    "sg:classifiers":[
        {
            "category":"Insurance",
            "subcategory":"Insurance Agent",
            "type":"Services"
        }
    ],
    "sg:phone":"+1 662 332 1553",
    "sg:postcode":"38701",
    "sg:province":"MS",
    "sg:website":"www.andrewsins.com",
    "wof:name":"Bill Andrews Insurance Inc",
    "wof:placetype":"venue"
},
  "geometry": {"coordinates":[-91.06483,33.41167],"type":"Point"}
}