{
  "type": "Feature",
  "properties": {
    "addr:full":"135 Motor Scooter Dr Nesbit MS 38651",
    "addr:housenumber":"135",
    "addr:postcode":"38651",
    "addr:street":"Scooter;Nesbit",
    "iso:country":"US",
    "sg:address":"135 Motor Scooter Dr",
    "sg:city":"Nesbit",
    "sg:classifiers":[
        {
            "category":"Mining & Drilling",
            "type":"Manufacturing & Wholesale Goods"
        }
    ],
    "sg:phone":"+1 662 449 0704",
    "sg:postcode":"38651",
    "sg:province":"MS",
    "sg:tags":[
        "field"
    ],
    "wof:name":"Centenial Pipeline",
    "wof:placetype":"venue"
},
  "geometry": {"coordinates":[-89.99276999999999,34.88869],"type":"Point"}
}