{
  "type": "Feature",
  "properties": {
    "iso:country":"US",
    "sg:address":"105 N 9th St",
    "sg:city":"Lumberton",
    "sg:classifiers":[
        {
            "category":"Social Services",
            "subcategory":"Child Care",
            "type":"Services"
        }
    ],
    "sg:phone":"+1 601 796 3990",
    "sg:postcode":"39455",
    "sg:province":"MS",
    "sg:tags":[
        "day"
    ],
    "wof:name":"Childcare Rogers & Learning",
    "wof:placetype":"venue"
},
  "geometry": {"coordinates":[-89.462502,31.006459],"type":"Point"}
}