{
  "type": "Feature",
  "properties": {
    "iso:country":"US",
    "sg:address":"500 Courthouse Rd",
    "sg:city":"Gulfport",
    "sg:classifiers":[
        {
            "category":"Shopping",
            "type":"Retail Goods"
        }
    ],
    "sg:phone":"+1 228 896 6816",
    "sg:postcode":"39507",
    "sg:province":"MS",
    "sg:tags":[
        "cosmetic",
        "perfume"
    ],
    "wof:name":"Avon Products",
    "wof:placetype":"venue"
},
  "geometry": {"coordinates":[-89.0442,30.389343],"type":"Point"}
}