{
  "type": "Feature",
  "properties": {
    "addr:full":"800 S 28th Ave Hattiesburg MS 39402",
    "addr:housenumber":"800",
    "addr:postcode":"39402",
    "addr:street":"S 28Th Ave",
    "iso:country":"US",
    "sg:address":"800 S 28th Ave",
    "sg:city":"Hattiesburg",
    "sg:classifiers":[
        {
            "category":"Health Services",
            "subcategory":"Doctor",
            "type":"Services"
        }
    ],
    "sg:phone":"+1 601 268 3333",
    "sg:postcode":"39402",
    "sg:province":"MS",
    "sg:tags":[
        "dentist"
    ],
    "wof:name":"Erik G Graham DDS",
    "wof:placetype":"venue"
},
  "geometry": {"coordinates":[-89.33120099999999,31.312037],"type":"Point"}
}