{
  "type": "Feature",
  "properties": {
    "iso:country":"US",
    "sg:address":"513 W Commerce St",
    "sg:city":"Aberdeen",
    "sg:classifiers":[
        {
            "category":"Health Services",
            "subcategory":"Doctor",
            "type":"Services"
        }
    ],
    "sg:phone":"+1 662 369 2063",
    "sg:postcode":"39730",
    "sg:province":"MS",
    "sg:tags":[
        "dentist"
    ],
    "wof:name":"Roger Wright Dental Clinic Inc",
    "wof:placetype":"venue"
},
  "geometry": {"coordinates":[-88.550524,33.825422],"type":"Point"}
}