{
  "type": "Feature",
  "properties": {
    "iso:country":"US",
    "sg:address":"11200 Goodman Rd",
    "sg:city":"Olive Branch",
    "sg:classifiers":[
        {
            "category":"Travel",
            "subcategory":"Hotels & Motels",
            "type":"Entertainment"
        }
    ],
    "sg:phone":"+1 662 893 6369",
    "sg:postcode":"38654",
    "sg:province":"MS",
    "wof:name":"Whispering Woods Hotel & Ctr",
    "wof:placetype":"venue"
},
  "geometry": {"coordinates":[-89.782268,34.96243],"type":"Point"}
}