{
  "type": "Feature",
  "properties": {
    "addr:full":"1188 Thomas Grove Rd Magnolia MS 39648",
    "addr:housenumber":"1188",
    "addr:postcode":"39648",
    "addr:street":"Thomas Grove Rd",
    "iso:country":"US",
    "sg:address":"1188 Thomas Grove Rd",
    "sg:city":"Magnolia",
    "sg:classifiers":[
        {
            "category":"Organizations",
            "subcategory":"Religious Organization",
            "type":"Services"
        }
    ],
    "sg:phone":"+1 601 783 5531",
    "sg:postcode":"39648",
    "sg:province":"MS",
    "sg:tags":[
        "church"
    ],
    "wof:name":"Jordan Temple Church-God",
    "wof:placetype":"venue"
},
  "geometry": {"coordinates":[-90.26011099999999,31.066113],"type":"Point"}
}