{
  "type": "Feature",
  "properties": {
    "iso:country":"US",
    "sg:address":"186 Rankin Rd",
    "sg:city":"Brandon",
    "sg:classifiers":[
        {
            "category":"Shopping",
            "subcategory":"Used Merchandise",
            "type":"Retail Goods"
        }
    ],
    "sg:phone":"+1 601 825 8887",
    "sg:postcode":"39042",
    "sg:province":"MS",
    "sg:tags":[
        "pawnbroker"
    ],
    "wof:name":"Metro Pawn",
    "wof:placetype":"venue"
},
  "geometry": {"coordinates":[-89.89863800000001,32.274499],"type":"Point"}
}