{
  "type": "Feature",
  "properties": {
    "iso:country":"US",
    "sg:address":"465 Highway 1 S",
    "sg:city":"Greenville",
    "sg:classifiers":[
        {
            "category":"Restaurant",
            "type":"Food & Drink"
        },
        {
            "category":"Food & Beverages",
            "subcategory":"Groceries & Convenience Stores",
            "type":"Retail Goods"
        }
    ],
    "sg:menulink":"http://www.allmenus.com/ms/empire/246374-krystal-185/menu/",
    "sg:phone":"+1 662 332 5333",
    "sg:postcode":"38701",
    "sg:province":"MS",
    "sg:tags":[
        "burger",
        "american"
    ],
    "wof:name":"Krystal 185",
    "wof:placetype":"venue"
},
  "geometry": {"coordinates":[-91.03805199999999,33.40172],"type":"Point"}
}