{
  "type": "Feature",
  "properties": {
    "addr:full":"1 Walker Levee Rd Fulton MS 38843",
    "addr:housenumber":"1",
    "addr:postcode":"38843",
    "addr:street":"Walker Levee Rd",
    "iso:country":"US",
    "sg:address":"1 Walker Levee Rd",
    "sg:city":"Fulton",
    "sg:classifiers":[
        {
            "category":"Travel",
            "subcategory":"Campground",
            "type":"Entertainment"
        }
    ],
    "sg:phone":"+1 662 585 3058",
    "sg:postcode":"38843",
    "sg:province":"MS",
    "sg:tags":[
        "trailer"
    ],
    "wof:name":"Murphree's Waterfront Camping",
    "wof:placetype":"venue"
},
  "geometry": {"coordinates":[-88.40314600000001,34.432769],"type":"Point"}
}