{
  "type": "Feature",
  "properties": {
    "addr:full":"169 McClure Rd Red Banks MS 38661",
    "addr:housenumber":"169",
    "addr:postcode":"38661",
    "addr:street":"Mcclure Rd",
    "iso:country":"US",
    "sg:address":"169 McClure Rd",
    "sg:city":"Red Banks",
    "sg:classifiers":[
        {
            "category":"Home & Garden",
            "subcategory":"Carpets & Floor Coverings",
            "type":"Retail Goods"
        }
    ],
    "sg:phone":"+1 662 851 7746",
    "sg:postcode":"38661",
    "sg:province":"MS",
    "sg:tags":[
        "rug"
    ],
    "wof:name":"Pams Imports",
    "wof:placetype":"venue"
},
  "geometry": {"coordinates":[-89.533404,34.904044],"type":"Point"}
}