{
  "type": "Feature",
  "properties": {
    "addr:full":"203 Goodyear Blvd Picayune MS 39466",
    "addr:housenumber":"203",
    "addr:postcode":"39466",
    "addr:street":"Goodyear Blvd",
    "iso:country":"US",
    "sg:address":"203 Goodyear Blvd",
    "sg:city":"Picayune",
    "sg:classifiers":[
        {
            "category":"Government",
            "subcategory":"Office",
            "type":"Public Place"
        }
    ],
    "sg:phone":"+1 601 798 9770",
    "sg:postcode":"39466",
    "sg:province":"MS",
    "sg:tags":[
        "city"
    ],
    "wof:name":"Picayune City Manager",
    "wof:placetype":"venue"
},
  "geometry": {"coordinates":[-89.68268399999999,30.527888],"type":"Point"}
}