{
  "type": "Feature",
  "properties": {
    "iso:country":"US",
    "sg:address":"7543 Coral Meadows Dr",
    "sg:city":"Southaven",
    "sg:classifiers":[
        {
            "category":"Retail",
            "subcategory":"Photofinishing",
            "type":"Services"
        }
    ],
    "sg:phone":"+1 901 691 9292",
    "sg:postcode":"38671",
    "sg:province":"MS",
    "sg:tags":[
        "laboratory"
    ],
    "wof:name":"Foto Pixels Inc",
    "wof:placetype":"venue"
},
  "geometry": {"coordinates":[-90.01965,34.972253],"type":"Point"}
}