{
  "type": "Feature",
  "properties": {
    "iso:country":"US",
    "sg:address":"4036 Caspian St",
    "sg:city":"Bay Saint Louis",
    "sg:classifiers":[
        {
            "category":"Building & Trades",
            "subcategory":"Construction",
            "type":"Services"
        }
    ],
    "sg:phone":"+1 228 466 0292",
    "sg:postcode":"39520",
    "sg:province":"MS",
    "sg:tags":[
        "contractor"
    ],
    "wof:name":"Stinson Fence",
    "wof:placetype":"venue"
},
  "geometry": {"coordinates":[-89.394194,30.308321],"type":"Point"}
}