{
  "type": "Feature",
  "properties": {
    "iso:country":"US",
    "sg:address":"38 Pass Rd",
    "sg:city":"Gulfport",
    "sg:classifiers":[
        {
            "category":"Health Services",
            "subcategory":"Doctor",
            "type":"Services"
        }
    ],
    "sg:phone":"+1 228 864 4041",
    "sg:postcode":"39507",
    "sg:province":"MS",
    "sg:tags":[
        "physician",
        "surgeon"
    ],
    "wof:name":"Family Medicine Assoc Of Gulf",
    "wof:placetype":"venue"
},
  "geometry": {"coordinates":[-89.04956199999999,30.392608],"type":"Point"}
}