{
  "type": "Feature",
  "properties": {
    "iso:country":"US",
    "sg:address":"146 Askew St",
    "sg:city":"Water Valley",
    "sg:classifiers":[
        {
            "category":"Building & Trades",
            "subcategory":"Landscaping Services",
            "type":"Services"
        }
    ],
    "sg:phone":"+1 662 473 1347",
    "sg:postcode":"38965",
    "sg:province":"MS",
    "wof:name":"Griffins Lawn Service",
    "wof:placetype":"venue"
},
  "geometry": {"coordinates":[-89.624796,34.164349],"type":"Point"}
}