{
  "type": "Feature",
  "properties": {
    "iso:country":"US",
    "sg:address":"128 W Main St",
    "sg:city":"West Point",
    "sg:classifiers":[
        {
            "category":"Personal",
            "subcategory":"Beauty Salon",
            "type":"Services"
        }
    ],
    "sg:phone":"+1 662 494 0230",
    "sg:postcode":"39773",
    "sg:province":"MS",
    "sg:tags":[
        "shop"
    ],
    "wof:name":"Kings and Queens Hair Salon",
    "wof:placetype":"venue"
},
  "geometry": {"coordinates":[-88.650857,33.607025],"type":"Point"}
}