{
  "type": "Feature",
  "properties": {
    "iso:country":"US",
    "sg:address":"1204 W Capitol St",
    "sg:city":"Jackson",
    "sg:classifiers":[
        {
            "category":"Banks & Credit Unions",
            "subcategory":"Bank",
            "type":"Services"
        }
    ],
    "sg:phone":"+1 601 352 4238",
    "sg:postcode":"39203",
    "sg:province":"MS",
    "sg:tags":[
        "cashing",
        "check"
    ],
    "wof:name":"Jackson Cash & Cash",
    "wof:placetype":"venue"
},
  "geometry": {"coordinates":[-90.203452,32.308794],"type":"Point"}
}