{
  "type": "Feature",
  "properties": {
    "iso:country":"US",
    "sg:address":"526 3rd St",
    "sg:city":"Clarksdale",
    "sg:classifiers":[
        {
            "category":"Health Services",
            "subcategory":"Clinic",
            "type":"Services"
        }
    ],
    "sg:phone":"+1 662 627 4786",
    "sg:postcode":"38614",
    "sg:province":"MS",
    "sg:tags":[
        "kidney",
        "dialysis",
        "center"
    ],
    "wof:name":"Rcg Mississippi Inc",
    "wof:placetype":"venue"
},
  "geometry": {"coordinates":[-90.56919000000001,34.202285],"type":"Point"}
}