{
  "type": "Feature",
  "properties": {
    "addr:full":"7138 S Siwell Rd Byram MS 39272",
    "addr:housenumber":"7138",
    "addr:postcode":"39272",
    "addr:street":"S Siwell Rd",
    "iso:country":"US",
    "sg:address":"7138 S Siwell Rd",
    "sg:city":"Byram",
    "sg:classifiers":[
        {
            "category":"Real Estate",
            "subcategory":"Real Estate Agent",
            "type":"Services"
        }
    ],
    "sg:phone":"+1 601 906 9053",
    "sg:postcode":"39272",
    "sg:province":"MS",
    "wof:name":"House Hunters",
    "wof:placetype":"venue"
},
  "geometry": {"coordinates":[-90.27115499999999,32.192617],"type":"Point"}
}