{
  "type": "Feature",
  "properties": {
    "iso:country":"US",
    "sg:address":"106 Saint Francis St",
    "sg:city":"Bay St Louis",
    "sg:classifiers":[
        {
            "category":"Utilities",
            "subcategory":"Telephone",
            "type":"Services"
        }
    ],
    "sg:phone":"+1 228 467 9028",
    "sg:postcode":"39520",
    "sg:province":"MS",
    "sg:tags":[
        "company"
    ],
    "wof:name":"Bell South",
    "wof:placetype":"venue"
},
  "geometry": {"coordinates":[-89.339623,30.313807],"type":"Point"}
}