{
  "type": "Feature",
  "properties": {
    "addr:full":"635 W Monroe St Grenada MS 38901",
    "addr:housenumber":"635",
    "addr:postcode":"38901",
    "addr:street":"W Monroe St",
    "iso:country":"US",
    "sg:address":"635 W Monroe St",
    "sg:city":"Grenada",
    "sg:classifiers":[
        {
            "category":"Restaurant",
            "type":"Food & Drink"
        }
    ],
    "sg:phone":"+1 662 229 0050",
    "sg:postcode":"38901",
    "sg:province":"MS",
    "wof:name":"Cafe Highlander",
    "wof:placetype":"venue"
},
  "geometry": {"coordinates":[-89.809888,33.764713],"type":"Point"}
}