{
  "type": "Feature",
  "properties": {
    "iso:country":"US",
    "sg:address":"220 S Wall St",
    "sg:city":"Natchez",
    "sg:classifiers":[
        {
            "category":"Professional",
            "subcategory":"Business Services",
            "type":"Services"
        }
    ],
    "sg:phone":"+1 601 445 9668",
    "sg:postcode":"39120",
    "sg:province":"MS",
    "wof:name":"Express Check Inc",
    "wof:placetype":"venue"
},
  "geometry": {"coordinates":[-91.405509,31.559769],"type":"Point"}
}