{
  "type": "Feature",
  "properties": {
    "iso:country":"US",
    "sg:address":"303 Commerce St",
    "sg:city":"Raleigh",
    "sg:classifiers":[
        {
            "category":"Retail",
            "subcategory":"Auto Repair",
            "type":"Services"
        }
    ],
    "sg:phone":"+1 601 782 4772",
    "sg:postcode":"39153",
    "sg:province":"MS",
    "sg:tags":[
        "repairing",
        "automobile"
    ],
    "wof:name":"S & R Auto Electric",
    "wof:placetype":"venue"
},
  "geometry": {"coordinates":[-89.53626300000001,32.038615],"type":"Point"}
}