{
  "type": "Feature",
  "properties": {
    "addr:full":"208 S Child St Okolona MS 38860",
    "addr:housenumber":"208",
    "addr:postcode":"38860",
    "addr:street":"S Child St",
    "iso:country":"US",
    "sg:address":"208 S Child St",
    "sg:city":"Okolona",
    "sg:classifiers":[
        {
            "category":"Manufacturing",
            "subcategory":"Furniture",
            "type":"Manufacturing & Wholesale Goods"
        }
    ],
    "sg:phone":"+1 662 447 3030",
    "sg:postcode":"38860",
    "sg:province":"MS",
    "wof:name":"S & J Upholstery",
    "wof:placetype":"venue"
},
  "geometry": {"coordinates":[-88.740842,34.001405],"type":"Point"}
}