{
  "type": "Feature",
  "properties": {
    "iso:country":"US",
    "sg:address":"515 Washington Ave",
    "sg:city":"Ocean Springs",
    "sg:classifiers":[
        {
            "category":"Professional",
            "subcategory":"Accounting & Tax Preparation",
            "type":"Services"
        }
    ],
    "sg:phone":"+1 228 875 4258",
    "sg:postcode":"39564",
    "sg:province":"MS",
    "sg:tags":[
        "accountant"
    ],
    "wof:name":"Toups Leach & Assoc",
    "wof:placetype":"venue"
},
  "geometry": {"coordinates":[-88.82780099999999,30.410304],"type":"Point"}
}