{
  "type": "Feature",
  "properties": {
    "addr:full":"3440 Wheeler Rd Hernando MS 38632",
    "addr:housenumber":"3440",
    "addr:postcode":"38632",
    "addr:street":"Wheeler Rd",
    "iso:country":"US",
    "sg:address":"3440 Wheeler Rd",
    "sg:city":"Hernando",
    "sg:classifiers":[
        {
            "category":"Organizations",
            "subcategory":"Religious Organization",
            "type":"Services"
        }
    ],
    "sg:phone":"+1 662 429 8726",
    "sg:postcode":"38632",
    "sg:province":"MS",
    "wof:name":"Oak Hill MB Church",
    "wof:placetype":"venue"
},
  "geometry": {"coordinates":[-90.048723,34.742142],"type":"Point"}
}