{
  "type": "Feature",
  "properties": {
    "iso:country":"US",
    "sg:address":"3800 Hospital St",
    "sg:city":"Pascagoula",
    "sg:classifiers":[
        {
            "category":"Travel",
            "subcategory":"Hotels & Motels",
            "type":"Entertainment"
        }
    ],
    "sg:phone":"+1 228 762 2800",
    "sg:postcode":"39581",
    "sg:province":"MS",
    "sg:tags":[
        "operation"
    ],
    "wof:name":"Loews Hotels Holding Corp",
    "wof:placetype":"venue"
},
  "geometry": {"coordinates":[-88.534237,30.372606],"type":"Point"}
}