{
  "type": "Feature",
  "properties": {
    "iso:country":"US",
    "sg:address":"1811 E Canal St",
    "sg:city":"Picayune",
    "sg:classifiers":[
        {
            "category":"Organizations",
            "subcategory":"Religious Organization",
            "type":"Services"
        }
    ],
    "sg:phone":"+1 601 798 8426",
    "sg:postcode":"39466",
    "sg:province":"MS",
    "sg:tags":[
        "church"
    ],
    "wof:name":"Church Of God Of Prophecy",
    "wof:placetype":"venue"
},
  "geometry": {"coordinates":[-89.66024,30.523726],"type":"Point"}
}