{
  "type": "Feature",
  "properties": {
    "iso:country":"US",
    "sg:address":"518 Hillcrest Loop",
    "sg:city":"Petal",
    "sg:classifiers":[
        {
            "category":"Organizations",
            "subcategory":"Religious Organization",
            "type":"Services"
        }
    ],
    "sg:phone":"+1 601 583 3553",
    "sg:postcode":"39465",
    "sg:province":"MS",
    "wof:name":"Calvary Fursquare Gospl Church",
    "wof:placetype":"venue"
},
  "geometry": {"coordinates":[-89.25608099999999,31.337801],"type":"Point"}
}