{
  "type": "Feature",
  "properties": {
    "iso:country":"US",
    "sg:address":"1520 25th Ave",
    "sg:city":"Meridian",
    "sg:classifiers":[
        {
            "category":"Social Services",
            "subcategory":"Child Care",
            "type":"Services"
        }
    ],
    "sg:phone":"+1 601 483 0166",
    "sg:postcode":"39301",
    "sg:province":"MS",
    "wof:name":"Litle Blessings Infant Ctr",
    "wof:placetype":"venue"
},
  "geometry": {"coordinates":[-88.703614,32.37288],"type":"Point"}
}