{
  "type": "Feature",
  "properties": {
    "addr:full":"615 Saint Charles St Greenwood MS 38930",
    "addr:housenumber":"615",
    "addr:postcode":"38930",
    "addr:street":"Saint Charles St",
    "iso:country":"US",
    "sg:address":"615 Saint Charles St",
    "sg:city":"Greenwood",
    "sg:classifiers":[
        {
            "category":"Organizations",
            "subcategory":"Religious Organization",
            "type":"Services"
        }
    ],
    "sg:phone":"+1 662 453 8891",
    "sg:postcode":"38930",
    "sg:province":"MS",
    "wof:name":"Union Grove Baptist Church",
    "wof:placetype":"venue"
},
  "geometry": {"coordinates":[-90.168346,33.512747],"type":"Point"}
}