{
  "type": "Feature",
  "properties": {
    "iso:country":"US",
    "sg:address":"12487 McCully Dr",
    "sg:city":"Biloxi",
    "sg:classifiers":[
        {
            "category":"Personal",
            "subcategory":"Beauty Salon",
            "type":"Services"
        }
    ],
    "sg:phone":"+1 228 392 9523",
    "sg:postcode":"39532",
    "sg:province":"MS",
    "sg:tags":[
        "shop"
    ],
    "wof:name":"Vickie Jordan",
    "wof:placetype":"venue"
},
  "geometry": {"coordinates":[-88.90087699999999,30.470026],"type":"Point"}
}