{
  "type": "Feature",
  "properties": {
    "iso:country":"US",
    "sg:address":"245 Eureka St",
    "sg:city":"Batesville",
    "sg:classifiers":[
        {
            "category":"Government",
            "subcategory":"Office",
            "type":"Public Place"
        }
    ],
    "sg:phone":"+1 662 563 6260",
    "sg:postcode":"38606",
    "sg:province":"MS",
    "wof:name":"Panola County Home Economist",
    "wof:placetype":"venue"
},
  "geometry": {"coordinates":[-89.94777499999999,34.305474],"type":"Point"}
}