{
  "type": "Feature",
  "properties": {
    "iso:country":"US",
    "sg:address":"125 Neely Rd",
    "sg:city":"Jackson",
    "sg:classifiers":[
        {
            "category":"Building & Trades",
            "subcategory":"Construction",
            "type":"Services"
        }
    ],
    "sg:phone":"+1 601 939 5025",
    "sg:postcode":"39218",
    "sg:province":"MS",
    "sg:tags":[
        "wall",
        "painting",
        "covering",
        "remodeling",
        "general"
    ],
    "wof:name":"Tri-M Company",
    "wof:placetype":"venue"
},
  "geometry": {"coordinates":[-90.16984600000001,32.231815],"type":"Point"}
}