{
  "type": "Feature",
  "properties": {
    "iso:country":"US",
    "sg:address":"430 Hawthorne Dr",
    "sg:city":"Madison",
    "sg:classifiers":[
        {
            "category":"Manufacturing",
            "subcategory":"Tools & Machinery",
            "type":"Manufacturing & Wholesale Goods"
        }
    ],
    "sg:phone":"+1 601 856 9802",
    "sg:postcode":"39110",
    "sg:province":"MS",
    "sg:tags":[
        "equipment",
        "electric"
    ],
    "wof:name":"R M Archibald Co",
    "wof:placetype":"venue"
},
  "geometry": {"coordinates":[-90.10901,32.475564],"type":"Point"}
}