{
  "type": "Feature",
  "properties": {
    "iso:country":"US",
    "sg:address":"3750 Hacks Cross Rd",
    "sg:city":"Memphis",
    "sg:classifiers":[
        {
            "category":"Restaurant",
            "type":"Food & Drink"
        }
    ],
    "sg:phone":"+1 901 624 4848",
    "sg:postcode":"38125",
    "sg:province":"MS",
    "sg:tags":[
        "delicatessen"
    ],
    "sg:website":"www.holidaydeli.com",
    "wof:name":"Holiday Ham & Deli",
    "wof:placetype":"venue"
},
  "geometry": {"coordinates":[-89.79595999999999,35.046753],"type":"Point"}
}