{
  "type": "Feature",
  "properties": {
    "iso:country":"US",
    "sg:address":"3387 Terry Rd",
    "sg:city":"Jackson",
    "sg:classifiers":[
        {
            "category":"Autos & Motor Vehicles",
            "subcategory":"Fuel & Gas Station",
            "type":"Retail Goods"
        }
    ],
    "sg:phone":"+1 601 373 9199",
    "sg:postcode":"39212",
    "sg:province":"MS",
    "sg:tags":[
        "grocery",
        "station",
        "gasoline"
    ],
    "wof:name":"B P Exploration",
    "wof:placetype":"venue"
},
  "geometry": {"coordinates":[-90.228908,32.245558],"type":"Point"}
}