{
  "type": "Feature",
  "properties": {
    "iso:country":"US",
    "sg:address":"220 Central Dr",
    "sg:city":"Vicksburg",
    "sg:classifiers":[
        {
            "category":"Building & Trades",
            "subcategory":"Construction",
            "type":"Services"
        }
    ],
    "sg:phone":"+1 601 638 4562",
    "sg:postcode":"39180",
    "sg:province":"MS",
    "sg:tags":[
        "floor",
        "laying",
        "contractor"
    ],
    "wof:name":"Kens Carpet Service",
    "wof:placetype":"venue"
},
  "geometry": {"coordinates":[-90.920416,32.266631],"type":"Point"}
}