{
  "type": "Feature",
  "properties": {
    "addr:full":"412 W Main St Tupelo MS 38804",
    "addr:housenumber":"412",
    "addr:postcode":"38804",
    "addr:street":"W Main St",
    "iso:country":"US",
    "sg:address":"412 W Main St",
    "sg:city":"Tupelo",
    "sg:classifiers":[
        {
            "category":"Organizations",
            "subcategory":"Religious Organization",
            "type":"Services"
        }
    ],
    "sg:phone":"+1 662 690 8100",
    "sg:postcode":"38804",
    "sg:province":"MS",
    "sg:tags":[
        "church"
    ],
    "sg:website":"www.fumctupelo.com",
    "wof:name":"First United Methodist Church",
    "wof:placetype":"venue"
},
  "geometry": {"coordinates":[-88.708502,34.257419],"type":"Point"}
}