{
  "type": "Feature",
  "properties": {
    "addr:full":"1830 S West St Jackson MS 39201",
    "addr:housenumber":"1830",
    "addr:postcode":"39201",
    "addr:street":"S;St",
    "iso:country":"US",
    "sg:address":"1830 S West St",
    "sg:city":"Jackson",
    "sg:classifiers":[
        {
            "category":"Home & Garden",
            "subcategory":"Building Materials",
            "type":"Retail Goods"
        }
    ],
    "sg:phone":"+1 601 353 8301",
    "sg:postcode":"39201",
    "sg:province":"MS",
    "sg:tags":[
        "paint"
    ],
    "wof:name":"ICI Dulux Paint",
    "wof:placetype":"venue"
},
  "geometry": {"coordinates":[-90.190944,32.27903],"type":"Point"}
}