{
  "type": "Feature",
  "properties": {
    "iso:country":"US",
    "sg:address":"15066 Eagle Bend Rd",
    "sg:city":"Yazoo City",
    "sg:classifiers":[
        {
            "category":"Building & Trades",
            "subcategory":"Landscaping Services",
            "type":"Services"
        }
    ],
    "sg:phone":"+1 662 746 7748",
    "sg:postcode":"39194",
    "sg:province":"MS",
    "sg:tags":[
        "sod",
        "sodding"
    ],
    "wof:name":"Eagle Bend Sod Farm Inc",
    "wof:placetype":"venue"
},
  "geometry": {"coordinates":[-90.46651900000001,32.812748],"type":"Point"}
}