{
  "type": "Feature",
  "properties": {
    "iso:country":"US",
    "sg:address":"1393 Co Rd 87",
    "sg:city":"New Albany",
    "sg:phone":"+1 662 534 3425",
    "sg:postcode":"38652",
    "sg:province":"MS",
    "sg:tags":[
        "farm",
        "soybean"
    ],
    "wof:name":"Dorrough Jewel",
    "wof:placetype":"venue"
},
  "geometry": {"coordinates":[-89.086995,34.395321],"type":"Point"}
}