{
  "type": "Feature",
  "properties": {
    "iso:country":"US",
    "sg:address":"172 Lower Myrick Rd",
    "sg:city":"Laurel",
    "sg:classifiers":[
        {
            "category":"Wholesale",
            "subcategory":"Electrical",
            "type":"Manufacturing & Wholesale Goods"
        }
    ],
    "sg:phone":"+1 601 649 2648",
    "sg:postcode":"39443",
    "sg:province":"MS",
    "sg:tags":[
        "equipment",
        "electric",
        "supply"
    ],
    "wof:name":"M & M Line Clearance Inc",
    "wof:placetype":"venue"
},
  "geometry": {"coordinates":[-89.09872900000001,31.672559],"type":"Point"}
}