{
  "type": "Feature",
  "properties": {
    "iso:country":"US",
    "sg:address":"106 W Jefferson St",
    "sg:city":"Tupelo",
    "sg:classifiers":[
        {
            "category":"Government",
            "subcategory":"Fire Station",
            "type":"Public Place"
        }
    ],
    "sg:phone":"+1 662 841 6439",
    "sg:postcode":"38804",
    "sg:province":"MS",
    "sg:tags":[
        "department"
    ],
    "wof:name":"Tupelo Fire Dept",
    "wof:placetype":"venue"
},
  "geometry": {"coordinates":[-88.703503,34.259276],"type":"Point"}
}