{
  "type": "Feature",
  "properties": {
    "iso:country":"US",
    "sg:address":"5093 Beatline Rd",
    "sg:city":"Long Beach",
    "sg:classifiers":[
        {
            "category":"Building & Trades",
            "subcategory":"Construction",
            "type":"Services"
        }
    ],
    "sg:phone":"+1 228 864 0081",
    "sg:postcode":"39560",
    "sg:province":"MS",
    "wof:name":"Morris Johnson Construction Co",
    "wof:placetype":"venue"
},
  "geometry": {"coordinates":[-89.187117,30.360703],"type":"Point"}
}