{
  "type": "Feature",
  "properties": {
    "iso:country":"US",
    "sg:address":"412 W Broadway St",
    "sg:city":"Yazoo City",
    "sg:classifiers":[
        {
            "category":"Organizations",
            "subcategory":"Religious Organization",
            "type":"Services"
        }
    ],
    "sg:phone":"+1 662 746 4689",
    "sg:postcode":"39194",
    "sg:province":"MS",
    "sg:tags":[
        "church"
    ],
    "wof:name":"Calvary Baptist Church",
    "wof:placetype":"venue"
},
  "geometry": {"coordinates":[-90.416989,32.848676],"type":"Point"}
}