{
  "type": "Feature",
  "properties": {
    "addr:full":"2600 Beach Blvd Biloxi MS 39531",
    "addr:housenumber":"2600",
    "addr:postcode":"39531",
    "addr:street":"Beach Blvd",
    "iso:country":"US",
    "sg:address":"2600 Beach Blvd",
    "sg:city":"Biloxi",
    "sg:classifiers":[
        {
            "category":"Bakery",
            "type":"Food & Drink"
        }
    ],
    "sg:menulink":"http://www.allmenus.com/ms/gulfport/220011-auntie-annes-pretzels/menu/",
    "sg:phone":"+1 228 388 3805",
    "sg:postcode":"39531",
    "sg:province":"MS",
    "sg:tags":[
        "american",
        "pastry"
    ],
    "wof:name":"Auntie Anne's Pretzels",
    "wof:placetype":"venue"
},
  "geometry": {"coordinates":[-88.989414,30.389565],"type":"Point"}
}