{
  "type": "Feature",
  "properties": {
    "iso:country":"US",
    "sg:address":"920 W Bankhead St",
    "sg:city":"New Albany",
    "sg:classifiers":[
        {
            "category":"Shopping",
            "type":"Retail Goods"
        }
    ],
    "sg:phone":"+1 662 534 2694",
    "sg:postcode":"38652",
    "sg:province":"MS",
    "sg:tags":[
        "merchandise"
    ],
    "wof:name":"Glenfield Monuments",
    "wof:placetype":"venue"
},
  "geometry": {"coordinates":[-89.031728,34.506874],"type":"Point"}
}