{
  "type": "Feature",
  "properties": {
    "iso:country":"US",
    "sg:address":"3040 Terry Rd",
    "sg:city":"Jackson",
    "sg:classifiers":[
        {
            "category":"Banks & Credit Unions",
            "subcategory":"Bank",
            "type":"Services"
        }
    ],
    "sg:phone":"+1 601 502 1050",
    "sg:postcode":"39212",
    "sg:province":"MS",
    "sg:tags":[
        "cashing",
        "check"
    ],
    "wof:name":"E-Z Cash",
    "wof:placetype":"venue"
},
  "geometry": {"coordinates":[-90.22148,32.258825],"type":"Point"}
}