{
  "type": "Feature",
  "properties": {
    "addr:full":"201 US Hwy 82 E Indianola MS 38751",
    "addr:housenumber":"201",
    "addr:postcode":"38751",
    "addr:street":"Us Hwy 82 E",
    "iso:country":"US",
    "sg:address":"201 US Hwy 82 E",
    "sg:city":"Indianola",
    "sg:classifiers":[
        {
            "category":"Banks & Credit Unions",
            "subcategory":"Bank",
            "type":"Services"
        }
    ],
    "sg:phone":"+1 662 887 1171",
    "sg:postcode":"38751",
    "sg:province":"MS",
    "sg:tags":[
        "financing"
    ],
    "wof:name":"Tower Loan",
    "wof:placetype":"venue"
},
  "geometry": {"coordinates":[-90.649886,33.458148],"type":"Point"}
}