{
  "type": "Feature",
  "properties": {
    "iso:country":"US",
    "sg:address":"6734 US Hwy 49",
    "sg:city":"Hattiesburg",
    "sg:classifiers":[
        {
            "category":"Food & Beverages",
            "subcategory":"Groceries & Convenience Stores",
            "type":"Retail Goods"
        }
    ],
    "sg:phone":"+1 601 264 1240",
    "sg:postcode":"39402",
    "sg:province":"MS",
    "wof:name":"Amoco Dandy Dan's",
    "wof:placetype":"venue"
},
  "geometry": {"coordinates":[-89.349289,31.359657],"type":"Point"}
}