{
  "type": "Feature",
  "properties": {
    "addr:full":"1110 Hatley Rd Amory MS 38821",
    "addr:housenumber":"1110",
    "addr:postcode":"38821",
    "addr:street":"Hatley Rd",
    "iso:country":"US",
    "sg:address":"1110 Hatley Rd",
    "sg:city":"Amory",
    "sg:classifiers":[
        {
            "category":"Manufacturing",
            "subcategory":"Tools & Machinery",
            "type":"Manufacturing & Wholesale Goods"
        }
    ],
    "sg:phone":"+1 662 256 7185",
    "sg:postcode":"38821",
    "sg:province":"MS",
    "sg:tags":[
        "control"
    ],
    "wof:name":"ITT Engineered Valves",
    "wof:placetype":"venue"
},
  "geometry": {"coordinates":[-88.473433,33.985555],"type":"Point"}
}