{
  "type": "Feature",
  "properties": {
    "iso:country":"US",
    "sg:address":"1497 Graham Rd",
    "sg:city":"Coldwater",
    "sg:classifiers":[
        {
            "category":"Freight",
            "type":"Transportation"
        }
    ],
    "sg:phone":"+1 662 233 0249",
    "sg:postcode":"38618",
    "sg:province":"MS",
    "sg:tags":[
        "consultant"
    ],
    "wof:name":"Trucking Graham",
    "wof:placetype":"venue"
},
  "geometry": {"coordinates":[-89.812011,34.761785],"type":"Point"}
}