{
  "type": "Feature",
  "properties": {
    "addr:full":"642 US Hwy 51 Ridgeland MS 39157",
    "addr:housenumber":"642",
    "addr:postcode":"39157",
    "addr:street":"Us Hwy 51",
    "iso:country":"US",
    "sg:address":"642 US Hwy 51",
    "sg:city":"Ridgeland",
    "sg:classifiers":[
        {
            "category":"Retail",
            "subcategory":"Veterinary Services",
            "type":"Services"
        }
    ],
    "sg:phone":"+1 601 856 3991",
    "sg:postcode":"39157",
    "sg:province":"MS",
    "sg:tags":[
        "veterinarian"
    ],
    "wof:name":"Madison-Ridgeland Animal Hosp",
    "wof:placetype":"venue"
},
  "geometry": {"coordinates":[-90.128334,32.429134],"type":"Point"}
}