{
  "type": "Feature",
  "properties": {
    "iso:country":"US",
    "sg:address":"2632 Bailey Ave",
    "sg:city":"Jackson",
    "sg:classifiers":[
        {
            "category":"Personal",
            "subcategory":"Beauty Salon",
            "type":"Services"
        }
    ],
    "sg:phone":"+1 601 981 9859",
    "sg:postcode":"39213",
    "sg:province":"MS",
    "sg:tags":[
        "shop"
    ],
    "wof:name":"Head Turner",
    "wof:placetype":"venue"
},
  "geometry": {"coordinates":[-90.192639,32.331695],"type":"Point"}
}