{
  "type": "Feature",
  "properties": {
    "addr:full":"5009 Old Hwy 11 Hattiesburg MS 39402",
    "addr:housenumber":"5009",
    "addr:postcode":"39402",
    "addr:street":"Old Hwy 11",
    "iso:country":"US",
    "sg:address":"5009 Old Hwy 11",
    "sg:city":"Hattiesburg",
    "sg:classifiers":[
        {
            "category":"Professional",
            "subcategory":"Computer Services",
            "type":"Services"
        }
    ],
    "sg:phone":"+1 601 450 4146",
    "sg:postcode":"39402",
    "sg:province":"MS",
    "sg:tags":[
        "hardware",
        "provider",
        "internet",
        "software"
    ],
    "wof:name":"Esitenow",
    "wof:placetype":"venue"
},
  "geometry": {"coordinates":[-89.411033,31.294446],"type":"Point"}
}