{
  "type": "Feature",
  "properties": {
    "addr:full":"1116 Pearl River Ave Mccomb MS 39648",
    "addr:housenumber":"1116",
    "addr:postcode":"39648",
    "addr:street":"Pearl River Ave",
    "iso:country":"US",
    "sg:address":"1116 Pearl River Ave",
    "sg:city":"Mccomb",
    "sg:classifiers":[
        {
            "category":"Organizations",
            "subcategory":"Religious Organization",
            "type":"Services"
        }
    ],
    "sg:phone":"+1 601 249 3606",
    "sg:postcode":"39648",
    "sg:province":"MS",
    "sg:tags":[
        "church"
    ],
    "wof:name":"Gloryland Full Gospel Holyness",
    "wof:placetype":"venue"
},
  "geometry": {"coordinates":[-90.43837600000001,31.245817],"type":"Point"}
}