{
  "type": "Feature",
  "properties": {
    "iso:country":"US",
    "sg:address":"445 Stateline Rd E",
    "sg:city":"Southaven",
    "sg:classifiers":[
        {
            "category":"Food & Beverages",
            "subcategory":"Liquor & Beverages",
            "type":"Retail Goods"
        }
    ],
    "sg:phone":"+1 662 393 8563",
    "sg:postcode":"38671",
    "sg:province":"MS",
    "sg:tags":[
        "alcoholic"
    ],
    "wof:name":"Norm Southaven Discount Liquor",
    "wof:placetype":"venue"
},
  "geometry": {"coordinates":[-89.97811900000001,34.991737],"type":"Point"}
}