{
  "type": "Feature",
  "properties": {
    "iso:country":"US",
    "sg:address":"1430 Bankhead Rd SW",
    "sg:city":"Mantachie",
    "sg:classifiers":[
        {
            "category":"Manufacturing",
            "subcategory":"Tools & Machinery",
            "type":"Manufacturing & Wholesale Goods"
        }
    ],
    "sg:phone":"+1 662 862 3781",
    "sg:postcode":"38855",
    "sg:province":"MS",
    "sg:tags":[
        "machine",
        "shop"
    ],
    "wof:name":"Irvin Machine Specialty Co",
    "wof:placetype":"venue"
},
  "geometry": {"coordinates":[-88.51126499999999,34.252723],"type":"Point"}
}