{
  "type": "Feature",
  "properties": {
    "iso:country":"US",
    "sg:address":"122 Desoto Ave",
    "sg:city":"Clarksdale",
    "sg:classifiers":[
        {
            "category":"Shopping",
            "subcategory":"Clothing, Apparel, & Fashions",
            "type":"Retail Goods"
        }
    ],
    "sg:phone":"+1 662 624 5546",
    "sg:postcode":"38614",
    "sg:province":"MS",
    "sg:tags":[
        "maternity",
        "wear",
        "uniform"
    ],
    "wof:name":"Jeans Uniform",
    "wof:placetype":"venue"
},
  "geometry": {"coordinates":[-90.56862599999999,34.20451],"type":"Point"}
}