{
  "type": "Feature",
  "properties": {
    "addr:full":"1615 Hwy 1 S Greenville MS 38701",
    "addr:housenumber":"1615",
    "addr:postcode":"38701",
    "addr:street":"Hwy 1 S",
    "iso:country":"US",
    "sg:address":"1615 Hwy 1 S",
    "sg:city":"Greenville",
    "sg:classifiers":[
        {
            "category":"Restaurant",
            "type":"Food & Drink"
        }
    ],
    "sg:phone":"+1 662 335 2374",
    "sg:postcode":"38701",
    "sg:province":"MS",
    "sg:tags":[
        "eating"
    ],
    "wof:name":"TCBY",
    "wof:placetype":"venue"
},
  "geometry": {"coordinates":[-91.03931,33.377929],"type":"Point"}
}