{
  "type": "Feature",
  "properties": {
    "iso:country":"US",
    "sg:address":"1058 Hwy 48 E",
    "sg:city":"Magnolia",
    "sg:classifiers":[
        {
            "category":"Wholesale",
            "subcategory":"Non-durable Goods",
            "type":"Manufacturing & Wholesale Goods"
        }
    ],
    "sg:phone":"+1 601 783 6154",
    "sg:postcode":"39652",
    "sg:province":"MS",
    "wof:name":"Barclay Enterprises Inc",
    "wof:placetype":"venue"
},
  "geometry": {"coordinates":[-90.29178,31.096449],"type":"Point"}
}