{
  "type": "Feature",
  "properties": {
    "iso:country":"US",
    "sg:address":"501 Boulevard Dr S",
    "sg:city":"Amory",
    "sg:classifiers":[
        {
            "category":"Personal",
            "subcategory":"Beauty Salon",
            "type":"Services"
        }
    ],
    "sg:phone":"+1 662 256 2716",
    "sg:postcode":"38821",
    "sg:province":"MS",
    "sg:tags":[
        "shop"
    ],
    "wof:name":"Beckys Beauty Shop",
    "wof:placetype":"venue"
},
  "geometry": {"coordinates":[-88.477711,33.983069],"type":"Point"}
}