{
  "type": "Feature",
  "properties": {
    "iso:country":"US",
    "sg:address":"253 Ridge Dr",
    "sg:city":"Jackson",
    "sg:classifiers":[
        {
            "category":"Professional",
            "subcategory":"Business Services",
            "type":"Services"
        }
    ],
    "sg:phone":"+1 601 987 5130",
    "sg:postcode":"39216",
    "sg:province":"MS",
    "wof:name":"Fondren Group LLC",
    "wof:placetype":"venue"
},
  "geometry": {"coordinates":[-90.168357,32.339816],"type":"Point"}
}