{
  "type": "Feature",
  "properties": {
    "addr:full":"737 Cooper Rd Jackson MS 39212",
    "addr:housenumber":"737",
    "addr:postcode":"39212",
    "addr:street":"Cooper Rd",
    "iso:country":"US",
    "sg:address":"737 Cooper Rd",
    "sg:city":"Jackson",
    "sg:classifiers":[
        {
            "category":"Shopping",
            "subcategory":"Clothing, Apparel, & Fashions",
            "type":"Retail Goods"
        }
    ],
    "sg:phone":"+1 601 502 2895",
    "sg:postcode":"39212",
    "sg:province":"MS",
    "sg:tags":[
        "item",
        "boutique"
    ],
    "wof:name":"Lacey's Boutique",
    "wof:placetype":"venue"
},
  "geometry": {"coordinates":[-90.24642299999999,32.253784],"type":"Point"}
}