{
  "type": "Feature",
  "properties": {
    "iso:country":"US",
    "sg:address":"852 E Peace St",
    "sg:city":"Canton",
    "sg:classifiers":[
        {
            "category":"Local Transit",
            "type":"Transportation"
        }
    ],
    "sg:phone":"+1 601 859 6135",
    "sg:postcode":"39046",
    "sg:province":"MS",
    "sg:tags":[
        "passenger"
    ],
    "wof:name":"American Medical Response Inc",
    "wof:placetype":"venue"
},
  "geometry": {"coordinates":[-90.015159,32.613185],"type":"Point"}
}