{
  "type": "Feature",
  "properties": {
    "addr:full":"710 Hwy 45 N Columbus MS 39701",
    "addr:housenumber":"710",
    "addr:postcode":"39701",
    "addr:street":"Hwy 45 N",
    "iso:country":"US",
    "sg:address":"710 Hwy 45 N",
    "sg:city":"Columbus",
    "sg:classifiers":[
        {
            "category":"Manufacturing",
            "subcategory":"Lumber",
            "type":"Manufacturing & Wholesale Goods"
        }
    ],
    "sg:phone":"+1 662 327 3352",
    "sg:postcode":"39701",
    "sg:province":"MS",
    "sg:tags":[
        "commission"
    ],
    "wof:name":"Forestry Commission Miss",
    "wof:placetype":"venue"
},
  "geometry": {"coordinates":[-88.43439600000001,33.514918],"type":"Point"}
}