{
  "type": "Feature",
  "properties": {
    "addr:full":"1152 Co Rd 96 New Albany MS 38652",
    "addr:housenumber":"1152;96",
    "addr:postcode":"38652",
    "addr:street":"Co Rd",
    "iso:country":"US",
    "sg:address":"1152 Co Rd 96",
    "sg:city":"New Albany",
    "sg:classifiers":[
        {
            "category":"Building & Trades",
            "subcategory":"Construction",
            "type":"Services"
        }
    ],
    "sg:phone":"+1 662 534 3138",
    "sg:postcode":"38652",
    "sg:province":"MS",
    "sg:tags":[
        "general",
        "contractor"
    ],
    "wof:name":"Hall & Hall Construction",
    "wof:placetype":"venue"
},
  "geometry": {"coordinates":[-89.048753,34.394599],"type":"Point"}
}