{
  "type": "Feature",
  "properties": {
    "addr:full":"519 Central Ave Laurel MS 39440",
    "addr:housenumber":"519",
    "addr:postcode":"39440",
    "addr:street":"Central Ave",
    "iso:country":"US",
    "sg:address":"519 Central Ave",
    "sg:city":"Laurel",
    "sg:classifiers":[
        {
            "category":"Professional",
            "subcategory":"Research",
            "type":"Services"
        }
    ],
    "sg:phone":"+1 601 649 8012",
    "sg:postcode":"39440",
    "sg:province":"MS",
    "sg:tags":[
        "environmental",
        "ecological"
    ],
    "wof:name":"Newpark Resources Inc",
    "wof:placetype":"venue"
},
  "geometry": {"coordinates":[-89.132847,31.693502],"type":"Point"}
}