{
  "type": "Feature",
  "properties": {
    "addr:full":"413 W Main St West Point MS 39773",
    "addr:housenumber":"413",
    "addr:postcode":"39773",
    "addr:street":"W Main St",
    "iso:country":"US",
    "sg:address":"413 W Main St",
    "sg:city":"West Point",
    "sg:classifiers":[
        {
            "category":"Professional",
            "subcategory":"Accounting & Tax Preparation",
            "type":"Services"
        }
    ],
    "sg:phone":"+1 662 494 9144",
    "sg:postcode":"39773",
    "sg:province":"MS",
    "sg:tags":[
        "return",
        "filing"
    ],
    "wof:name":"Jackson Hewitt Tax Svc",
    "wof:placetype":"venue"
},
  "geometry": {"coordinates":[-88.65543700000001,33.607185],"type":"Point"}
}