{
  "type": "Feature",
  "properties": {
    "iso:country":"US",
    "sg:address":"9471 Three Rivers Rd",
    "sg:city":"Gulfport",
    "sg:classifiers":[
        {
            "category":"Health Services",
            "subcategory":"Doctor",
            "type":"Services"
        }
    ],
    "sg:phone":"+1 228 864 4729",
    "sg:postcode":"39503",
    "sg:province":"MS",
    "sg:tags":[
        "physician",
        "surgeon"
    ],
    "wof:name":"Advanced Orthopedic Assoc PC",
    "wof:placetype":"venue"
},
  "geometry": {"coordinates":[-89.087835,30.423224],"type":"Point"}
}