{
  "type": "Feature",
  "properties": {
    "iso:country":"US",
    "sg:address":"202 Walker St",
    "sg:city":"Houlka",
    "sg:classifiers":[
        {
            "category":"Organizations",
            "subcategory":"Religious Organization",
            "type":"Services"
        }
    ],
    "sg:phone":"+1 662 568 7924",
    "sg:postcode":"38850",
    "sg:province":"MS",
    "sg:tags":[
        "church"
    ],
    "wof:name":"His Grace Ministries",
    "wof:placetype":"venue"
},
  "geometry": {"coordinates":[-89.022547,34.036753],"type":"Point"}
}