{
  "type": "Feature",
  "properties": {
    "addr:full":"33 Luther Walker Rd Picayune MS 39466",
    "addr:housenumber":"33",
    "addr:postcode":"39466",
    "addr:street":"Luther Walker Rd",
    "iso:country":"US",
    "sg:address":"33 Luther Walker Rd",
    "sg:city":"Picayune",
    "sg:classifiers":[
        {
            "category":"Professional",
            "subcategory":"Business Services",
            "type":"Services"
        }
    ],
    "sg:phone":"+1 601 799 3391",
    "sg:postcode":"39466",
    "sg:province":"MS",
    "wof:name":"Mark Moseley Detailing Inc",
    "wof:placetype":"venue"
},
  "geometry": {"coordinates":[-89.718925,30.494326],"type":"Point"}
}