{
  "type": "Feature",
  "properties": {
    "addr:full":"204 E 4th St Corinth MS 38834",
    "addr:housenumber":"204",
    "addr:postcode":"38834",
    "addr:street":"E 4Th St",
    "iso:country":"US",
    "sg:address":"204 E 4th St",
    "sg:city":"Corinth",
    "sg:classifiers":[
        {
            "category":"Museum",
            "type":"Entertainment"
        }
    ],
    "sg:phone":"+1 662 287 3120",
    "sg:postcode":"38834",
    "sg:province":"MS",
    "wof:name":"Northeast Mississippi Museum",
    "wof:placetype":"venue"
},
  "geometry": {"coordinates":[-88.521964,34.942478],"type":"Point"}
}