{
  "type": "Feature",
  "properties": {
    "iso:country":"US",
    "sg:address":"770 Cheyenne St",
    "sg:city":"Clarksdale",
    "sg:classifiers":[
        {
            "category":"Freight",
            "type":"Transportation"
        }
    ],
    "sg:phone":"+1 662 627 7394",
    "sg:postcode":"38614",
    "sg:province":"MS",
    "sg:tags":[
        "warehouse",
        "merchandise"
    ],
    "wof:name":"North Delta Compress & Wrhse",
    "wof:placetype":"venue"
},
  "geometry": {"coordinates":[-90.58886200000001,34.196602],"type":"Point"}
}