{
  "type": "Feature",
  "properties": {
    "iso:country":"US",
    "sg:address":"2450 Hickory Wood Dr",
    "sg:city":"Tupelo",
    "sg:classifiers":[
        {
            "category":"Farming",
            "subcategory":"Farm",
            "type":"Manufacturing & Wholesale Goods"
        }
    ],
    "sg:phone":"+1 662 841 9871",
    "sg:postcode":"38801",
    "sg:province":"MS",
    "sg:tags":[
        "crop",
        "general"
    ],
    "wof:name":"Doodledust Farm",
    "wof:placetype":"venue"
},
  "geometry": {"coordinates":[-88.746301,34.233222],"type":"Point"}
}