{
  "type": "Feature",
  "properties": {
    "iso:country":"US",
    "sg:address":"815 S West St",
    "sg:city":"Jackson",
    "sg:classifiers":[
        {
            "category":"Professional",
            "subcategory":"Lawyer & Legal Services",
            "type":"Services"
        }
    ],
    "sg:phone":"+1 601 352 7644",
    "sg:postcode":"39201",
    "sg:province":"MS",
    "sg:tags":[
        "attorney"
    ],
    "wof:name":"Greta Johnson Attorney",
    "wof:placetype":"venue"
},
  "geometry": {"coordinates":[-90.18617399999999,32.289751],"type":"Point"}
}