{
  "type": "Feature",
  "properties": {
    "addr:full":"4279 Sharon Rd Laurel MS 39443",
    "addr:housenumber":"4279",
    "addr:postcode":"39443",
    "addr:street":"Sharon Rd",
    "iso:country":"US",
    "sg:address":"4279 Sharon Rd",
    "sg:city":"Laurel",
    "sg:classifiers":[
        {
            "category":"Social Services",
            "subcategory":"Child Care",
            "type":"Services"
        }
    ],
    "sg:phone":"+1 601 425 4883",
    "sg:postcode":"39443",
    "sg:province":"MS",
    "sg:tags":[
        "day"
    ],
    "wof:name":"ABC Pre School",
    "wof:placetype":"venue"
},
  "geometry": {"coordinates":[-89.09647,31.784593],"type":"Point"}
}