{
  "type": "Feature",
  "properties": {
    "iso:country":"US",
    "sg:address":"117 Little Woods Rd",
    "sg:city":"Brandon",
    "sg:classifiers":[
        {
            "category":"Retail",
            "subcategory":"Repair Shop",
            "type":"Services"
        }
    ],
    "sg:phone":"+1 601 825 6201",
    "sg:postcode":"39042",
    "sg:province":"MS",
    "sg:tags":[
        "welding"
    ],
    "wof:name":"WR Richardson Welding &",
    "wof:placetype":"venue"
},
  "geometry": {"coordinates":[-89.928197,32.291579],"type":"Point"}
}