{
  "type": "Feature",
  "properties": {
    "iso:country":"US",
    "sg:address":"781 Larson St",
    "sg:city":"Jackson",
    "sg:classifiers":[
        {
            "category":"Building & Trades",
            "subcategory":"Construction",
            "type":"Services"
        }
    ],
    "sg:phone":"+1 601 352 7396",
    "sg:postcode":"39202",
    "sg:province":"MS",
    "sg:tags":[
        "general",
        "contractor"
    ],
    "wof:name":"Yates Construction",
    "wof:placetype":"venue"
},
  "geometry": {"coordinates":[-90.167956,32.305189],"type":"Point"}
}