{
  "type": "Feature",
  "properties": {
    "iso:country":"US",
    "sg:address":"504 N 2nd St",
    "sg:city":"Booneville",
    "sg:classifiers":[
        {
            "category":"Building & Trades",
            "subcategory":"Construction",
            "type":"Services"
        }
    ],
    "sg:phone":"+1 662 728 9520",
    "sg:postcode":"38829",
    "sg:province":"MS",
    "sg:tags":[
        "siding",
        "contractor"
    ],
    "wof:name":"Knight's Awning & Construction",
    "wof:placetype":"venue"
},
  "geometry": {"coordinates":[-88.566157,34.663584],"type":"Point"}
}