{
  "type": "Feature",
  "properties": {
    "addr:full":"5796 Ritcher Rd Ocean Springs MS 39564",
    "addr:housenumber":"5796",
    "addr:postcode":"39564",
    "addr:street":"Ritcher Rd",
    "iso:country":"US",
    "sg:address":"5796 Ritcher Rd",
    "sg:city":"Ocean Springs",
    "sg:classifiers":[
        {
            "category":"Museum",
            "type":"Entertainment"
        }
    ],
    "sg:phone":"+1 228 872 1943",
    "sg:postcode":"39564",
    "sg:province":"MS",
    "wof:name":"G I Museum",
    "wof:placetype":"venue"
},
  "geometry": {"coordinates":[-88.696834,30.408329],"type":"Point"}
}