{
  "type": "Feature",
  "properties": {
    "addr:full":"68 S Main St Grenada MS 38901",
    "addr:housenumber":"68",
    "addr:postcode":"38901",
    "addr:street":"S Main St",
    "iso:country":"US",
    "sg:address":"68 S Main St",
    "sg:city":"Grenada",
    "sg:classifiers":[
        {
            "category":"Professional",
            "subcategory":"Business Services",
            "type":"Services"
        }
    ],
    "sg:phone":"+1 662 227 1768",
    "sg:postcode":"38901",
    "sg:province":"MS",
    "wof:name":"U S Post Office",
    "wof:placetype":"venue"
},
  "geometry": {"coordinates":[-89.801969,33.784916],"type":"Point"}
}