{
  "type": "Feature",
  "properties": {
    "iso:country":"US",
    "sg:address":"1417 Trailwood Dr",
    "sg:city":"Greenville",
    "sg:classifiers":[
        {
            "category":"Farming",
            "subcategory":"Farm & Veterinary Services",
            "type":"Manufacturing & Wholesale Goods"
        }
    ],
    "sg:phone":"+1 662 332 2234",
    "sg:postcode":"38701",
    "sg:province":"MS",
    "sg:tags":[
        "management"
    ],
    "wof:name":"Chicago Mill & Lumber",
    "wof:placetype":"venue"
},
  "geometry": {"coordinates":[-91.06294699999999,33.384324],"type":"Point"}
}