{
  "type": "Feature",
  "properties": {
    "iso:country":"US",
    "sg:address":"4258 Hwy 373",
    "sg:city":"Columbus",
    "sg:classifiers":[
        {
            "category":"Shopping",
            "subcategory":"Used Merchandise",
            "type":"Retail Goods"
        }
    ],
    "sg:phone":"+1 662 240 0053",
    "sg:postcode":"39705",
    "sg:province":"MS",
    "sg:tags":[
        "pawnbroker"
    ],
    "wof:name":"Jami's Pawn & Gun",
    "wof:placetype":"venue"
},
  "geometry": {"coordinates":[-88.456605,33.660479],"type":"Point"}
}