{
  "type": "Feature",
  "properties": {
    "iso:country":"US",
    "sg:address":"119 Rankin Blvd Exd",
    "sg:city":"Tupelo",
    "sg:classifiers":[
        {
            "category":"Retail",
            "subcategory":"Repair Shop",
            "type":"Services"
        }
    ],
    "sg:phone":"+1 662 841 0282",
    "sg:postcode":"38801",
    "sg:province":"MS",
    "wof:name":"Hoopers",
    "wof:placetype":"venue"
},
  "geometry": {"coordinates":[-88.718135,34.255382],"type":"Point"}
}