{
  "type": "Feature",
  "properties": {
    "iso:country":"US",
    "sg:address":"963 Petrified Forest Rd",
    "sg:city":"Flora",
    "sg:classifiers":[
        {
            "category":"Building & Trades",
            "subcategory":"Construction",
            "type":"Services"
        }
    ],
    "sg:phone":"+1 601 879 9956",
    "sg:postcode":"39071",
    "sg:province":"MS",
    "sg:tags":[
        "house"
    ],
    "wof:name":"Special Homes LLC",
    "wof:placetype":"venue"
},
  "geometry": {"coordinates":[-90.32167699999999,32.510836],"type":"Point"}
}