{
  "type": "Feature",
  "properties": {
    "iso:country":"US",
    "sg:address":"400 S Lamar Blvd",
    "sg:city":"Oxford",
    "sg:classifiers":[
        {
            "category":"Professional",
            "subcategory":"Lawyer & Legal Services",
            "type":"Services"
        }
    ],
    "sg:phone":"+1 662 236 9996",
    "sg:postcode":"38655",
    "sg:province":"MS",
    "sg:tags":[
        "attorney"
    ],
    "wof:name":"Tannehill Law Firm",
    "wof:placetype":"venue"
},
  "geometry": {"coordinates":[-89.519013,34.365052],"type":"Point"}
}