{
  "type": "Feature",
  "properties": {
    "iso:country":"US",
    "sg:address":"1545 Lelia Dr",
    "sg:city":"Jackson",
    "sg:classifiers":[
        {
            "category":"Professional",
            "subcategory":"Lawyer & Legal Services",
            "type":"Services"
        }
    ],
    "sg:phone":"+1 601 366 5357",
    "sg:postcode":"39216",
    "sg:province":"MS",
    "wof:name":"McKibben & Associates",
    "wof:placetype":"venue"
},
  "geometry": {"coordinates":[-90.144648,32.332934],"type":"Point"}
}