{
  "type": "Feature",
  "properties": {
    "iso:country":"US",
    "sg:address":"337 Co Rd 47",
    "sg:city":"Tupelo",
    "sg:classifiers":[
        {
            "category":"Personal",
            "subcategory":"Beauty Salon",
            "type":"Services"
        }
    ],
    "sg:phone":"+1 662 566 1282",
    "sg:postcode":"38801",
    "sg:province":"MS",
    "wof:name":"Hands On Touch Beauty Salon",
    "wof:placetype":"venue"
},
  "geometry": {"coordinates":[-88.816171,34.178206],"type":"Point"}
}