{
  "type": "Feature",
  "properties": {
    "addr:full":"249 Lewis St Florence MS 39073",
    "addr:housenumber":"249",
    "addr:postcode":"39073",
    "addr:street":"Lewis St",
    "iso:country":"US",
    "sg:address":"249 Lewis St",
    "sg:city":"Florence",
    "sg:classifiers":[
        {
            "category":"Building & Trades",
            "subcategory":"Landscaping Services",
            "type":"Services"
        }
    ],
    "sg:phone":"+1 601 845 8553",
    "sg:postcode":"39073",
    "sg:province":"MS",
    "sg:tags":[
        "house",
        "construction"
    ],
    "wof:name":"Bnj Enterprises Inc",
    "wof:placetype":"venue"
},
  "geometry": {"coordinates":[-90.140203,32.151677],"type":"Point"}
}