{
  "type": "Feature",
  "properties": {
    "iso:country":"US",
    "sg:address":"401 Crockett Ave",
    "sg:city":"Greenwood",
    "sg:classifiers":[
        {
            "category":"Building & Trades",
            "subcategory":"Construction",
            "type":"Services"
        }
    ],
    "sg:phone":"+1 662 455 6064",
    "sg:postcode":"38930",
    "sg:province":"MS",
    "sg:tags":[
        "utility"
    ],
    "wof:name":"H & H Construction Inc",
    "wof:placetype":"venue"
},
  "geometry": {"coordinates":[-90.18055099999999,33.526852],"type":"Point"}
}