{
  "type": "Feature",
  "properties": {
    "addr:full":"3596 Greenside Dr Memphis MS 38125",
    "addr:housenumber":"3596",
    "addr:postcode":"38125",
    "addr:street":"Greenside Dr",
    "iso:country":"US",
    "sg:address":"3596 Greenside Dr",
    "sg:city":"Memphis",
    "sg:classifiers":[
        {
            "category":"Professional",
            "type":"Services"
        }
    ],
    "sg:phone":"+1 901 753 3043",
    "sg:postcode":"38125",
    "sg:province":"MS",
    "wof:name":"Km Concepts Inc",
    "wof:placetype":"venue"
},
  "geometry": {"coordinates":[-89.786742,35.051308],"type":"Point"}
}