{
  "type": "Feature",
  "properties": {
    "iso:country":"US",
    "sg:address":"501 Main St",
    "sg:city":"Corinth",
    "sg:classifiers":[
        {
            "category":"Organizations",
            "subcategory":"Religious Organization",
            "type":"Services"
        }
    ],
    "sg:phone":"+1 662 286 2208",
    "sg:postcode":"38834",
    "sg:province":"MS",
    "sg:tags":[
        "child",
        "day",
        "care",
        "church"
    ],
    "sg:website":"www.firstbaptistcorinth.org",
    "wof:name":"First Baptist Church Mothers",
    "wof:placetype":"venue"
},
  "geometry": {"coordinates":[-88.517127,34.939529],"type":"Point"}
}