{
  "type": "Feature",
  "properties": {
    "iso:country":"US",
    "sg:address":"7027 Greenbriar Dr",
    "sg:city":"Southaven",
    "sg:classifiers":[
        {
            "category":"Shopping",
            "subcategory":"Clothing, Apparel, & Fashions",
            "type":"Retail Goods"
        }
    ],
    "sg:phone":"+1 662 349 9005",
    "sg:postcode":"38671",
    "sg:province":"MS",
    "wof:name":"Intimate Fashion Lingerie",
    "wof:placetype":"venue"
},
  "geometry": {"coordinates":[-89.98257099999999,34.963913],"type":"Point"}
}