{
  "type": "Feature",
  "properties": {
    "addr:full":"81 Old Rice Rd Madison MS 39110",
    "addr:housenumber":"81",
    "addr:postcode":"39110",
    "addr:street":"Old Rice Rd",
    "iso:country":"US",
    "sg:address":"81 Old Rice Rd",
    "sg:city":"Madison",
    "sg:classifiers":[
        {
            "category":"Professional",
            "subcategory":"Business Services",
            "type":"Services"
        }
    ],
    "sg:phone":"+1 601 607 7861",
    "sg:postcode":"39110",
    "sg:province":"MS",
    "wof:name":"Nature By Design",
    "wof:placetype":"venue"
},
  "geometry": {"coordinates":[-90.063429,32.469869],"type":"Point"}
}