{
  "type": "Feature",
  "properties": {
    "iso:country":"US",
    "sg:address":"5310 Heatherton Cove",
    "sg:city":"Memphis",
    "sg:classifiers":[
        {
            "category":"Insurance",
            "subcategory":"Insurance Agent",
            "type":"Services"
        }
    ],
    "sg:phone":"+1 901 737 2908",
    "sg:postcode":"38125",
    "sg:province":"MS",
    "wof:name":"What A Deal Insurance",
    "wof:placetype":"venue"
},
  "geometry": {"coordinates":[-89.828688,35.003091],"type":"Point"}
}