{
  "type": "Feature",
  "properties": {
    "iso:country":"US",
    "sg:address":"1005 Posey Ave",
    "sg:city":"Philadelphia",
    "sg:classifiers":[
        {
            "category":"Social Services",
            "subcategory":"Child Care",
            "type":"Services"
        }
    ],
    "sg:phone":"+1 601 389 5437",
    "sg:postcode":"39350",
    "sg:province":"MS",
    "wof:name":"Creative Kids",
    "wof:placetype":"venue"
},
  "geometry": {"coordinates":[-89.101062,32.754037],"type":"Point"}
}