{
  "type": "Feature",
  "properties": {
    "addr:full":"1371 E Reed Rd Greenville MS 38703",
    "addr:housenumber":"1371",
    "addr:postcode":"38703",
    "addr:street":"E Reed Rd",
    "iso:country":"US",
    "sg:address":"1371 E Reed Rd",
    "sg:city":"Greenville",
    "sg:classifiers":[
        {
            "category":"Retail",
            "subcategory":"Laundry & Dry Cleaning",
            "type":"Services"
        }
    ],
    "sg:phone":"+1 662 332 0326",
    "sg:postcode":"38703",
    "sg:province":"MS",
    "sg:tags":[
        "cleaners"
    ],
    "wof:name":"Henry's Cleaners & Laundry",
    "wof:placetype":"venue"
},
  "geometry": {"coordinates":[-91.03290200000001,33.385275],"type":"Point"}
}