{
  "type": "Feature",
  "properties": {
    "addr:full":"212 Commerce Ave Cleveland MS 38732",
    "addr:housenumber":"212",
    "addr:postcode":"38732",
    "addr:street":"Commerce Ave",
    "iso:country":"US",
    "sg:address":"212 Commerce Ave",
    "sg:city":"Cleveland",
    "sg:classifiers":[
        {
            "category":"Insurance",
            "subcategory":"Insurance Agent",
            "type":"Services"
        }
    ],
    "sg:phone":"+1 662 843 1023",
    "sg:postcode":"38732",
    "sg:province":"MS",
    "wof:name":"Jamie Reynolds Insurance",
    "wof:placetype":"venue"
},
  "geometry": {"coordinates":[-90.71989600000001,33.74745],"type":"Point"}
}