{
  "type": "Feature",
  "properties": {
    "iso:country":"US",
    "sg:address":"122 E Van Dorn Ave",
    "sg:city":"Holly Springs",
    "sg:classifiers":[
        {
            "category":"Professional",
            "subcategory":"Printing & Photocopies",
            "type":"Services"
        }
    ],
    "sg:phone":"+1 662 252 7800",
    "sg:postcode":"38635",
    "sg:province":"MS",
    "sg:tags":[
        "duplicating",
        "copying"
    ],
    "wof:name":"Link Xpress",
    "wof:placetype":"venue"
},
  "geometry": {"coordinates":[-89.44786000000001,34.76743],"type":"Point"}
}