{
  "type": "Feature",
  "properties": {
    "addr:full":"345 Brame Rd Ridgeland MS 39157",
    "addr:housenumber":"345",
    "addr:postcode":"39157",
    "addr:street":"Brame Rd",
    "iso:country":"US",
    "sg:address":"345 Brame Rd",
    "sg:city":"Ridgeland",
    "sg:classifiers":[
        {
            "category":"Freight",
            "type":"Transportation"
        }
    ],
    "sg:phone":"+1 601 856 5233",
    "sg:postcode":"39157",
    "sg:province":"MS",
    "sg:tags":[
        "operator",
        "local",
        "trucking"
    ],
    "wof:name":"Trunnell Trucking Inc",
    "wof:placetype":"venue"
},
  "geometry": {"coordinates":[-90.15148499999999,32.414662],"type":"Point"}
}