{
  "type": "Feature",
  "properties": {
    "iso:country":"US",
    "sg:address":"309 US Hwy 11 S",
    "sg:city":"Poplarville",
    "sg:classifiers":[
        {
            "category":"Insurance",
            "subcategory":"Insurance Agent",
            "type":"Services"
        }
    ],
    "sg:phone":"+1 601 795 4585",
    "sg:postcode":"39470",
    "sg:province":"MS",
    "wof:name":"Farm Bureau Insurance",
    "wof:placetype":"venue"
},
  "geometry": {"coordinates":[-89.542637,30.838788],"type":"Point"}
}