{
  "type": "Feature",
  "properties": {
    "addr:full":"314 S Green St Tupelo MS 38804",
    "addr:housenumber":"314",
    "addr:postcode":"38804",
    "addr:street":"S Green St",
    "iso:country":"US",
    "sg:address":"314 S Green St",
    "sg:city":"Tupelo",
    "sg:classifiers":[
        {
            "category":"Shopping",
            "subcategory":"Gifts & Souvenirs",
            "type":"Retail Goods"
        }
    ],
    "sg:phone":"+1 662 844 3866",
    "sg:postcode":"38804",
    "sg:province":"MS",
    "wof:name":"Fun World",
    "wof:placetype":"venue"
},
  "geometry": {"coordinates":[-88.707035,34.255315],"type":"Point"}
}