{
  "type": "Feature",
  "properties": {
    "addr:full":"1000 Turtle Creek Dr Hattiesburg MS 39402",
    "addr:housenumber":"1000",
    "addr:postcode":"39402",
    "addr:street":"Turtle Creek Dr",
    "iso:country":"US",
    "sg:address":"1000 Turtle Creek Dr",
    "sg:city":"Hattiesburg",
    "sg:classifiers":[
        {
            "category":"Ice Cream",
            "type":"Food & Drink"
        }
    ],
    "sg:menulink":"http://www.allmenus.com/ms/oloh/227140-dippin-dots/menu/",
    "sg:phone":"+1 601 268 5551",
    "sg:postcode":"39402",
    "sg:province":"MS",
    "sg:tags":[
        "american"
    ],
    "wof:name":"Dippin' Dots",
    "wof:placetype":"venue"
},
  "geometry": {"coordinates":[-89.37441,31.324688],"type":"Point"}
}