{
  "type": "Feature",
  "properties": {
    "iso:country":"US",
    "sg:address":"1107 Lamar Ave",
    "sg:city":"Yazoo City",
    "sg:classifiers":[
        {
            "category":"Food & Beverages",
            "subcategory":"Groceries & Convenience Stores",
            "type":"Retail Goods"
        }
    ],
    "sg:phone":"+1 662 746 1128",
    "sg:postcode":"39194",
    "sg:province":"MS",
    "sg:tags":[
        "grocer"
    ],
    "wof:name":"Lamar Red Barn",
    "wof:placetype":"venue"
},
  "geometry": {"coordinates":[-90.405563,32.863728],"type":"Point"}
}