{
  "type": "Feature",
  "properties": {
    "iso:country":"US",
    "sg:address":"8035 Raymond Rd",
    "sg:city":"Hazlehurst",
    "sg:classifiers":[
        {
            "category":"Organizations",
            "subcategory":"Religious Organization",
            "type":"Services"
        }
    ],
    "sg:phone":"+1 601 894 8001",
    "sg:postcode":"39083",
    "sg:province":"MS",
    "sg:tags":[
        "church"
    ],
    "wof:name":"Springridge MB Church",
    "wof:placetype":"venue"
},
  "geometry": {"coordinates":[-90.431631,31.948347],"type":"Point"}
}