{
  "type": "Feature",
  "properties": {
    "addr:full":"65 Veterans Memorial Dr Kosciusko MS 39090",
    "addr:housenumber":"65",
    "addr:postcode":"39090",
    "addr:street":"Veterans Memorial Dr",
    "iso:country":"US",
    "sg:address":"65 Veterans Memorial Dr",
    "sg:city":"Kosciusko",
    "sg:classifiers":[
        {
            "category":"Government",
            "subcategory":"Post Office",
            "type":"Public Place"
        }
    ],
    "sg:phone":"+1 662 289 1181",
    "sg:postcode":"39090",
    "sg:province":"MS",
    "sg:tags":[
        "postal",
        "us"
    ],
    "sg:website":"www.usps.com",
    "wof:name":"US Post Office",
    "wof:placetype":"venue"
},
  "geometry": {"coordinates":[-89.57828600000001,33.065682],"type":"Point"}
}