{
  "type": "Feature",
  "properties": {
    "iso:country":"US",
    "sg:address":"2207 Milner Blvd",
    "sg:city":"Gulfport",
    "sg:classifiers":[
        {
            "category":"Real Estate",
            "subcategory":"Real Estate Agent",
            "type":"Services"
        }
    ],
    "sg:phone":"+1 228 896 2277",
    "sg:postcode":"39507",
    "sg:province":"MS",
    "sg:tags":[
        "business"
    ],
    "wof:name":"Streetman RE & Appraisal",
    "wof:placetype":"venue"
},
  "geometry": {"coordinates":[-89.02107100000001,30.395386],"type":"Point"}
}