{
  "type": "Feature",
  "properties": {
    "addr:full":"425 S Broadway St Mccomb MS 39648",
    "addr:housenumber":"425",
    "addr:postcode":"39648",
    "addr:street":"S Broadway St",
    "iso:country":"US",
    "sg:address":"425 S Broadway St",
    "sg:city":"Mccomb",
    "sg:classifiers":[
        {
            "category":"Wholesale",
            "subcategory":"Construction Materials",
            "type":"Manufacturing & Wholesale Goods"
        }
    ],
    "sg:phone":"+1 601 250 1422",
    "sg:postcode":"39648",
    "sg:province":"MS",
    "sg:tags":[
        "fence"
    ],
    "wof:name":"Simmons Iron Works Inc",
    "wof:placetype":"venue"
},
  "geometry": {"coordinates":[-90.452589,31.239342],"type":"Point"}
}