{
  "type": "Feature",
  "properties": {
    "addr:full":"530 Hiawatha St Jackson MS 39204",
    "addr:housenumber":"530",
    "addr:postcode":"39204",
    "addr:street":"Hiawatha St",
    "iso:country":"US",
    "sg:address":"530 Hiawatha St",
    "sg:city":"Jackson",
    "sg:classifiers":[
        {
            "category":"Professional",
            "subcategory":"Art Services",
            "type":"Services"
        }
    ],
    "sg:phone":"+1 601 354 0834",
    "sg:postcode":"39204",
    "sg:province":"MS",
    "sg:tags":[
        "graphic",
        "designer"
    ],
    "wof:name":"Concept 2 Completion Marketing",
    "wof:placetype":"venue"
},
  "geometry": {"coordinates":[-90.196459,32.292319],"type":"Point"}
}