{
  "type": "Feature",
  "properties": {
    "addr:full":"62 Moss Woods Dr Madison MS 39110",
    "addr:housenumber":"62",
    "addr:postcode":"39110",
    "addr:street":"Moss Woods Dr",
    "iso:country":"US",
    "sg:address":"62 Moss Woods Dr",
    "sg:city":"Madison",
    "sg:classifiers":[
        {
            "category":"Professional",
            "subcategory":"Management & Consulting",
            "type":"Services"
        }
    ],
    "sg:phone":"+1 601 605 5366",
    "sg:postcode":"39110",
    "sg:province":"MS",
    "sg:tags":[
        "consultant",
        "security",
        "system"
    ],
    "sg:website":"www.sourceonevideo.com",
    "wof:name":"Source One Video Inc",
    "wof:placetype":"venue"
},
  "geometry": {"coordinates":[-90.079882,32.45107],"type":"Point"}
}