{
  "type": "Feature",
  "properties": {
    "iso:country":"US",
    "sg:address":"608 14th Ave",
    "sg:city":"Meridian",
    "sg:classifiers":[
        {
            "category":"Organizations",
            "subcategory":"Religious Organization",
            "type":"Services"
        }
    ],
    "sg:phone":"+1 601 483 1243",
    "sg:postcode":"39301",
    "sg:province":"MS",
    "sg:tags":[
        "church"
    ],
    "wof:name":"Pilgrim Progress Baptist Chr",
    "wof:placetype":"venue"
},
  "geometry": {"coordinates":[-88.692891,32.369643],"type":"Point"}
}