{
  "type": "Feature",
  "properties": {
    "iso:country":"US",
    "sg:address":"400 Thomas St",
    "sg:city":"Oxford",
    "sg:classifiers":[
        {
            "category":"Professional",
            "subcategory":"Business Services",
            "type":"Services"
        }
    ],
    "sg:phone":"+1 662 234 3144",
    "sg:postcode":"38655",
    "sg:province":"MS",
    "wof:name":"Meadowood Ventures",
    "wof:placetype":"venue"
},
  "geometry": {"coordinates":[-89.50394900000001,34.378837],"type":"Point"}
}