{
  "type": "Feature",
  "properties": {
    "iso:country":"US",
    "sg:address":"729 Beulah Ave",
    "sg:city":"Tylertown",
    "sg:classifiers":[
        {
            "category":"Professional",
            "subcategory":"Lawyer & Legal Services",
            "type":"Services"
        }
    ],
    "sg:phone":"+1 601 876 2611",
    "sg:postcode":"39667",
    "sg:province":"MS",
    "sg:tags":[
        "attorney"
    ],
    "wof:name":"Conrad Mord",
    "wof:placetype":"venue"
},
  "geometry": {"coordinates":[-90.164964,31.123716],"type":"Point"}
}