{
  "type": "Feature",
  "properties": {
    "iso:country":"US",
    "sg:address":"1126 Park Cir",
    "sg:city":"Columbus",
    "sg:classifiers":[
        {
            "category":"Professional",
            "subcategory":"Secretarial Services",
            "type":"Services"
        }
    ],
    "sg:phone":"+1 662 328 5877",
    "sg:postcode":"39701",
    "sg:province":"MS",
    "sg:tags":[
        "hearing",
        "reporter"
    ],
    "wof:name":"Faye Tabor",
    "wof:placetype":"venue"
},
  "geometry": {"coordinates":[-88.42070699999999,33.509051],"type":"Point"}
}