{
  "type": "Feature",
  "properties": {
    "iso:country":"US",
    "sg:address":"1096 Beech St",
    "sg:city":"Wesson",
    "sg:classifiers":[
        {
            "category":"Health Services",
            "subcategory":"Doctor",
            "type":"Services"
        }
    ],
    "sg:phone":"+1 601 643 2432",
    "sg:postcode":"39191",
    "sg:province":"MS",
    "sg:tags":[
        "physician",
        "surgeon"
    ],
    "wof:name":"Burton Friedman MD",
    "wof:placetype":"venue"
},
  "geometry": {"coordinates":[-90.39806799999999,31.699918],"type":"Point"}
}