{
  "type": "Feature",
  "properties": {
    "addr:full":"9071 Goodman Rd Olive Branch MS 38654",
    "addr:housenumber":"9071",
    "addr:postcode":"38654",
    "addr:street":"Goodman Rd",
    "iso:country":"US",
    "sg:address":"9071 Goodman Rd",
    "sg:city":"Olive Branch",
    "sg:classifiers":[
        {
            "category":"Wholesale",
            "subcategory":"Auto Parts",
            "type":"Manufacturing & Wholesale Goods"
        }
    ],
    "sg:phone":"+1 662 895 2965",
    "sg:postcode":"38654",
    "sg:province":"MS",
    "sg:tags":[
        "supply"
    ],
    "wof:name":"NAPA Auto Parts",
    "wof:placetype":"venue"
},
  "geometry": {"coordinates":[-89.82875799999999,34.961789],"type":"Point"}
}