{
  "type": "Feature",
  "properties": {
    "iso:country":"US",
    "sg:address":"1999 Hwy 80 W",
    "sg:city":"Jackson",
    "sg:classifiers":[
        {
            "category":"Insurance",
            "subcategory":"Insurance Agent",
            "type":"Services"
        }
    ],
    "sg:phone":"+1 601 353 3811",
    "sg:postcode":"39204",
    "sg:province":"MS",
    "wof:name":"Festus Group Insurance",
    "wof:placetype":"venue"
},
  "geometry": {"coordinates":[-90.218586,32.287827],"type":"Point"}
}