{
  "type": "Feature",
  "properties": {
    "iso:country":"US",
    "sg:address":"3251 Hwy 50 E",
    "sg:city":"Columbus",
    "sg:classifiers":[
        {
            "category":"Retail",
            "subcategory":"Repair Shop",
            "type":"Services"
        }
    ],
    "sg:phone":"+1 662 328 3748",
    "sg:postcode":"39702",
    "sg:province":"MS",
    "sg:tags":[
        "appliance"
    ],
    "wof:name":"Lancaster Appliance Svc",
    "wof:placetype":"venue"
},
  "geometry": {"coordinates":[-88.354668,33.520016],"type":"Point"}
}