{
  "type": "Feature",
  "properties": {
    "addr:full":"3321 Yorkville Rd E Columbus MS 39702",
    "addr:housenumber":"3321",
    "addr:postcode":"39702",
    "addr:street":"Yorkville Rd E",
    "iso:country":"US",
    "sg:address":"3321 Yorkville Rd E",
    "sg:city":"Columbus",
    "sg:classifiers":[
        {
            "category":"Autos & Motor Vehicles",
            "subcategory":"Automobile Sales",
            "type":"Retail Goods"
        }
    ],
    "sg:phone":"+1 662 328 9677",
    "sg:postcode":"39702",
    "sg:province":"MS",
    "sg:tags":[
        "used"
    ],
    "wof:name":"Driveway Auto Mart",
    "wof:placetype":"venue"
},
  "geometry": {"coordinates":[-88.33926099999999,33.459955],"type":"Point"}
}