{
  "type": "Feature",
  "properties": {
    "addr:full":"225 Byrnes Cir Columbus MS 39701",
    "addr:housenumber":"225",
    "addr:postcode":"39701",
    "addr:street":"Byrnes Cir",
    "iso:country":"US",
    "sg:address":"225 Byrnes Cir",
    "sg:city":"Columbus",
    "sg:classifiers":[
        {
            "category":"Social Services",
            "subcategory":"Child Care",
            "type":"Services"
        }
    ],
    "sg:phone":"+1 662 328 1402",
    "sg:postcode":"39701",
    "sg:province":"MS",
    "wof:name":"Young's Christian Academy",
    "wof:placetype":"venue"
},
  "geometry": {"coordinates":[-88.39948,33.50618],"type":"Point"}
}