{
  "type": "Feature",
  "properties": {
    "addr:full":"125 E Commerce St Aberdeen MS 39730",
    "addr:housenumber":"125",
    "addr:postcode":"39730",
    "addr:street":"E Commerce St",
    "iso:country":"US",
    "sg:address":"125 E Commerce St",
    "sg:city":"Aberdeen",
    "sg:classifiers":[
        {
            "category":"Shopping",
            "subcategory":"Clothing, Apparel, & Fashions",
            "type":"Retail Goods"
        }
    ],
    "sg:phone":"+1 662 369 8463",
    "sg:postcode":"39730",
    "sg:province":"MS",
    "sg:tags":[
        "ready",
        "gift"
    ],
    "wof:name":"Carolyns",
    "wof:placetype":"venue"
},
  "geometry": {"coordinates":[-88.543423,33.825196],"type":"Point"}
}