{
  "type": "Feature",
  "properties": {
    "iso:country":"US",
    "sg:address":"2391 Culkin Rd",
    "sg:city":"Vicksburg",
    "sg:classifiers":[
        {
            "category":"Retail",
            "subcategory":"Repair Shop",
            "type":"Services"
        }
    ],
    "sg:phone":"+1 601 634 4794",
    "sg:postcode":"39183",
    "sg:province":"MS",
    "wof:name":"Kimberly Carebears & ACC",
    "wof:placetype":"venue"
},
  "geometry": {"coordinates":[-90.80958200000001,32.376775],"type":"Point"}
}