{
  "type": "Feature",
  "properties": {
    "addr:full":"10213 Hwy 51 Courtland MS 38606",
    "addr:housenumber":"10213",
    "addr:postcode":"38606",
    "addr:street":"Hwy 51",
    "iso:country":"US",
    "sg:address":"10213 Hwy 51",
    "sg:city":"Courtland",
    "sg:classifiers":[
        {
            "category":"Organizations",
            "subcategory":"Religious Organization",
            "type":"Services"
        }
    ],
    "sg:phone":"+1 662 563 5100",
    "sg:postcode":"38606",
    "sg:province":"MS",
    "sg:tags":[
        "church"
    ],
    "wof:name":"Courtland Church Of Christ",
    "wof:placetype":"venue"
},
  "geometry": {"coordinates":[-89.93844,34.270621],"type":"Point"}
}