{
  "type": "Feature",
  "properties": {
    "iso:country":"US",
    "sg:address":"390 S 4th St",
    "sg:city":"Morton",
    "sg:classifiers":[
        {
            "category":"Shopping",
            "subcategory":"Music",
            "type":"Retail Goods"
        }
    ],
    "sg:phone":"+1 601 732 8451",
    "sg:postcode":"39117",
    "sg:province":"MS",
    "sg:tags":[
        "video",
        "disc",
        "tape",
        "cassette"
    ],
    "wof:name":"Pop Video",
    "wof:placetype":"venue"
},
  "geometry": {"coordinates":[-89.65699600000001,32.3523],"type":"Point"}
}