{
  "type": "Feature",
  "properties": {
    "iso:country":"US",
    "sg:address":"603 US Hwy 90",
    "sg:city":"Bay Saint Louis",
    "sg:classifiers":[
        {
            "category":"Wholesale",
            "subcategory":"Non-durable Goods",
            "type":"Manufacturing & Wholesale Goods"
        }
    ],
    "sg:phone":"+1 228 466 0203",
    "sg:postcode":"39520",
    "sg:province":"MS",
    "sg:tags":[
        "specialty",
        "mfg"
    ],
    "wof:name":"Tri State Signs Company Inc",
    "wof:placetype":"venue"
},
  "geometry": {"coordinates":[-89.344967,30.317646],"type":"Point"}
}