{
  "type": "Feature",
  "properties": {
    "addr:full":"111 Rue Magnolia Biloxi MS 39530",
    "addr:housenumber":"111",
    "addr:postcode":"39530",
    "addr:street":"Rue Magnolia",
    "iso:country":"US",
    "sg:address":"111 Rue Magnolia",
    "sg:city":"Biloxi",
    "sg:classifiers":[
        {
            "category":"Shopping",
            "subcategory":"Gifts & Souvenirs",
            "type":"Retail Goods"
        }
    ],
    "sg:phone":"+1 228 436 9228",
    "sg:postcode":"39530",
    "sg:province":"MS",
    "sg:tags":[
        "shop",
        "m"
    ],
    "wof:name":"Roe's Hangups & Gifts",
    "wof:placetype":"venue"
},
  "geometry": {"coordinates":[-88.88901199999999,30.394131],"type":"Point"}
}