{
  "type": "Feature",
  "properties": {
    "addr:full":"3810 S Flora Dr Lauderdale MS 39335",
    "addr:housenumber":"3810",
    "addr:postcode":"39335",
    "addr:street":"S Flora Dr",
    "iso:country":"US",
    "sg:address":"3810 S Flora Dr",
    "sg:city":"Lauderdale",
    "sg:classifiers":[
        {
            "category":"Organizations",
            "subcategory":"Professional Association",
            "type":"Services"
        }
    ],
    "sg:phone":"+1 601 632 4536",
    "sg:postcode":"39335",
    "sg:province":"MS",
    "wof:name":"Dalewood Property Owners Inc",
    "wof:placetype":"venue"
},
  "geometry": {"coordinates":[-88.519554,32.489388],"type":"Point"}
}