{
  "type": "Feature",
  "properties": {
    "iso:country":"US",
    "sg:address":"4152 Raymond Rd",
    "sg:city":"Jackson",
    "sg:classifiers":[
        {
            "category":"Organizations",
            "subcategory":"Religious Organization",
            "type":"Services"
        }
    ],
    "sg:phone":"+1 601 371 7780",
    "sg:postcode":"39212",
    "sg:province":"MS",
    "sg:tags":[
        "church"
    ],
    "wof:name":"Mt Olive Church Of Christ",
    "wof:placetype":"venue"
},
  "geometry": {"coordinates":[-90.28406200000001,32.259325],"type":"Point"}
}