{
  "type": "Feature",
  "properties": {
    "addr:full":"1841 Paden St Jackson MS 39204",
    "addr:housenumber":"1841",
    "addr:postcode":"39204",
    "addr:street":"Paden St",
    "iso:country":"US",
    "sg:address":"1841 Paden St",
    "sg:city":"Jackson",
    "sg:classifiers":[
        {
            "category":"Education",
            "subcategory":"School",
            "type":"Public Place"
        }
    ],
    "sg:phone":"+1 601 373 1196",
    "sg:postcode":"39204",
    "sg:province":"MS",
    "wof:name":"Flying High MC",
    "wof:placetype":"venue"
},
  "geometry": {"coordinates":[-90.22593500000001,32.282344],"type":"Point"}
}