{
  "type": "Feature",
  "properties": {
    "addr:full":"3201 Clay St Vicksburg MS 39183",
    "addr:housenumber":"3201",
    "addr:postcode":"39183",
    "addr:street":"Clay St",
    "iso:country":"US",
    "sg:address":"3201 Clay St",
    "sg:city":"Vicksburg",
    "sg:classifiers":[
        {
            "category":"Professional",
            "type":"Services"
        }
    ],
    "sg:phone":"+1 601 638 4583",
    "sg:postcode":"39183",
    "sg:province":"MS",
    "sg:tags":[
        "establishment"
    ],
    "wof:name":"Eastern National Regional",
    "wof:placetype":"venue"
},
  "geometry": {"coordinates":[-90.85557,32.34552],"type":"Point"}
}