{
  "type": "Feature",
  "properties": {
    "addr:full":"293 Catlett Rd Madison MS 39110",
    "addr:housenumber":"293",
    "addr:postcode":"39110",
    "addr:street":"Catlett Rd",
    "iso:country":"US",
    "sg:address":"293 Catlett Rd",
    "sg:city":"Madison",
    "sg:classifiers":[
        {
            "category":"Building & Trades",
            "subcategory":"Construction",
            "type":"Services"
        }
    ],
    "sg:phone":"+1 601 856 8763",
    "sg:postcode":"39110",
    "sg:province":"MS",
    "sg:tags":[
        "house",
        "residential"
    ],
    "wof:name":"TT Construction Inc",
    "wof:placetype":"venue"
},
  "geometry": {"coordinates":[-90.13695800000001,32.541265],"type":"Point"}
}