{
  "type": "Feature",
  "properties": {
    "addr:full":"112 Walthall St Greenwood MS 38930",
    "addr:housenumber":"112",
    "addr:postcode":"38930",
    "addr:street":"Walthall St",
    "iso:country":"US",
    "sg:address":"112 Walthall St",
    "sg:city":"Greenwood",
    "sg:classifiers":[
        {
            "category":"Professional",
            "type":"Services"
        }
    ],
    "sg:phone":"+1 662 451 9090",
    "sg:postcode":"38930",
    "sg:province":"MS",
    "wof:name":"Funky Palette Design Studio",
    "wof:placetype":"venue"
},
  "geometry": {"coordinates":[-90.18057899999999,33.521342],"type":"Point"}
}