{
  "type": "Feature",
  "properties": {
    "iso:country":"US",
    "sg:address":"145 Rd 1325",
    "sg:city":"Saltillo",
    "sg:classifiers":[
        {
            "category":"Building & Trades",
            "subcategory":"Cleaning & Sanitation",
            "type":"Services"
        }
    ],
    "sg:phone":"+1 662 844 3838",
    "sg:postcode":"38866",
    "sg:province":"MS",
    "sg:tags":[
        "janitor"
    ],
    "wof:name":"Christie's Magik Maid",
    "wof:placetype":"venue"
},
  "geometry": {"coordinates":[-88.59465400000001,34.35133],"type":"Point"}
}