{
  "type": "Feature",
  "properties": {
    "iso:country":"US",
    "sg:address":"128 E 3rd St",
    "sg:city":"Picayune",
    "sg:classifiers":[
        {
            "category":"Retail",
            "subcategory":"Auto Repair",
            "type":"Services"
        }
    ],
    "sg:phone":"+1 601 799 1723",
    "sg:postcode":"39466",
    "sg:province":"MS",
    "sg:tags":[
        "repairing",
        "automobile"
    ],
    "wof:name":"A-1 Automotive Repair & Svc",
    "wof:placetype":"venue"
},
  "geometry": {"coordinates":[-89.67917199999999,30.52753],"type":"Point"}
}