{
  "type": "Feature",
  "properties": {
    "iso:country":"US",
    "sg:address":"1401 Broadway Dr",
    "sg:city":"Hattiesburg",
    "sg:classifiers":[
        {
            "category":"Autos & Motor Vehicles",
            "subcategory":"Automobile Sales",
            "type":"Retail Goods"
        }
    ],
    "sg:phone":"+1 601 296 9772",
    "sg:postcode":"39402",
    "sg:province":"MS",
    "sg:tags":[
        "car",
        "dealer"
    ],
    "wof:name":"J & L Motors Inc",
    "wof:placetype":"venue"
},
  "geometry": {"coordinates":[-89.319508,31.304831],"type":"Point"}
}