{
  "type": "Feature",
  "properties": {
    "addr:full":"356 Malvern Rd Columbus MS 39701",
    "addr:housenumber":"356",
    "addr:postcode":"39701",
    "addr:street":"Malvern Rd",
    "iso:country":"US",
    "sg:address":"356 Malvern Rd",
    "sg:city":"Columbus",
    "sg:classifiers":[
        {
            "category":"Building & Trades",
            "subcategory":"Construction",
            "type":"Services"
        }
    ],
    "sg:phone":"+1 662 329 2000",
    "sg:postcode":"39701",
    "sg:province":"MS",
    "sg:tags":[
        "roofing",
        "work",
        "contractor"
    ],
    "wof:name":"Horne Construction",
    "wof:placetype":"venue"
},
  "geometry": {"coordinates":[-88.528417,33.387214],"type":"Point"}
}