{
  "type": "Feature",
  "properties": {
    "iso:country":"US",
    "sg:address":"229 E Missouri Ave",
    "sg:city":"Crenshaw",
    "sg:classifiers":[
        {
            "category":"Organizations",
            "subcategory":"Religious Organization",
            "type":"Services"
        }
    ],
    "sg:phone":"+1 662 382 5945",
    "sg:postcode":"38621",
    "sg:province":"MS",
    "sg:tags":[
        "church"
    ],
    "wof:name":"Crenshaw Baptist Church",
    "wof:placetype":"venue"
},
  "geometry": {"coordinates":[-90.191427,34.5033],"type":"Point"}
}