{
  "type": "Feature",
  "properties": {
    "iso:country":"US",
    "sg:address":"1009 Memorial Blvd",
    "sg:city":"Picayune",
    "sg:classifiers":[
        {
            "category":"Autos & Motor Vehicles",
            "subcategory":"Fuel & Gas Station",
            "type":"Retail Goods"
        }
    ],
    "sg:phone":"+1 601 798 5621",
    "sg:postcode":"39466",
    "sg:province":"MS",
    "sg:tags":[
        "oil"
    ],
    "wof:name":"Spur K & T Quick Stop",
    "wof:placetype":"venue"
},
  "geometry": {"coordinates":[-89.66503299999999,30.517839],"type":"Point"}
}