{
  "type": "Feature",
  "properties": {
    "addr:full":"916 Hwy 278 E Amory MS 38821",
    "addr:housenumber":"916",
    "addr:postcode":"38821",
    "addr:street":"Hwy 278 E Amory",
    "iso:country":"US",
    "sg:address":"916 Hwy 278 E",
    "sg:city":"Amory",
    "sg:classifiers":[
        {
            "category":"Professional",
            "subcategory":"Accounting & Tax Preparation",
            "type":"Services"
        }
    ],
    "sg:phone":"+1 662 256 4868",
    "sg:postcode":"38821",
    "sg:province":"MS",
    "sg:tags":[
        "return",
        "filing"
    ],
    "wof:name":"H & R Block Tax Svc",
    "wof:placetype":"venue"
},
  "geometry": {"coordinates":[-88.47463999999999,33.979465],"type":"Point"}
}