{
  "type": "Feature",
  "properties": {
    "addr:full":"3400 Rouses Marina Rd Ocean Springs MS 39565",
    "addr:postcode":"3400;39565",
    "addr:street":"Rouses Marina Rd",
    "iso:country":"US",
    "sg:address":"3400 Rouses Marina Rd",
    "sg:city":"Ocean Springs",
    "sg:classifiers":[
        {
            "category":"Recreation",
            "subcategory":"Marina",
            "type":"Entertainment"
        }
    ],
    "sg:phone":"+1 228 826 4444",
    "sg:postcode":"39565",
    "sg:province":"MS",
    "wof:name":"Paige Bayou Marine",
    "wof:placetype":"venue"
},
  "geometry": {"coordinates":[-88.666437,30.498938],"type":"Point"}
}