{
  "type": "Feature",
  "properties": {
    "iso:country":"US",
    "sg:address":"539 Hugo St",
    "sg:city":"Vicksburg",
    "sg:classifiers":[
        {
            "category":"Building & Trades",
            "subcategory":"Construction",
            "type":"Services"
        }
    ],
    "sg:phone":"+1 601 634 1176",
    "sg:postcode":"39183",
    "sg:province":"MS",
    "sg:tags":[
        "house",
        "contractor"
    ],
    "wof:name":"Parson Construction Co",
    "wof:placetype":"venue"
},
  "geometry": {"coordinates":[-90.877781,32.357246],"type":"Point"}
}