{
  "type": "Feature",
  "properties": {
    "addr:full":"1831 Hwy 1 S Greenville MS 38701",
    "addr:housenumber":"1831",
    "addr:postcode":"38701",
    "addr:street":"Hwy 1 S",
    "iso:country":"US",
    "sg:address":"1831 Hwy 1 S",
    "sg:city":"Greenville",
    "sg:classifiers":[
        {
            "category":"Shopping",
            "subcategory":"Shoes",
            "type":"Retail Goods"
        }
    ],
    "sg:phone":"+1 662 335 6414",
    "sg:postcode":"38701",
    "sg:province":"MS",
    "wof:name":"Hibbett Sporting Goods Inc",
    "wof:placetype":"venue"
},
  "geometry": {"coordinates":[-91.040021,33.371285],"type":"Point"}
}