{
  "type": "Feature",
  "properties": {
    "addr:full":"212 S Main St Newton MS 39345",
    "addr:housenumber":"212",
    "addr:postcode":"39345",
    "addr:street":"S Main St",
    "iso:country":"US",
    "sg:address":"212 S Main St",
    "sg:city":"Newton",
    "sg:classifiers":[
        {
            "category":"Health Services",
            "subcategory":"Doctor",
            "type":"Services"
        }
    ],
    "sg:phone":"+1 601 683 3760",
    "sg:postcode":"39345",
    "sg:province":"MS",
    "sg:tags":[
        "physician",
        "surgeon"
    ],
    "wof:name":"Newton Regional Clinic",
    "wof:placetype":"venue"
},
  "geometry": {"coordinates":[-89.16339499999999,32.32019],"type":"Point"}
}