{
  "type": "Feature",
  "properties": {
    "iso:country":"US",
    "sg:address":"1316 Delaware Ave",
    "sg:city":"Mccomb",
    "sg:classifiers":[
        {
            "category":"Health Services",
            "subcategory":"Doctor",
            "type":"Services"
        }
    ],
    "sg:phone":"+1 601 684 1971",
    "sg:postcode":"39648",
    "sg:province":"MS",
    "sg:tags":[
        "dentist"
    ],
    "wof:name":"John T Felder DDS",
    "wof:placetype":"venue"
},
  "geometry": {"coordinates":[-90.467932,31.247643],"type":"Point"}
}