{
  "type": "Feature",
  "properties": {
    "addr:full":"3205 N Frontage Rd Vicksburg MS 39180",
    "addr:housenumber":"3205",
    "addr:postcode":"39180",
    "addr:street":"N Frontage Rd",
    "iso:country":"US",
    "sg:address":"3205 N Frontage Rd",
    "sg:city":"Vicksburg",
    "sg:classifiers":[
        {
            "category":"Real Estate",
            "subcategory":"Real Estate Agent",
            "type":"Services"
        }
    ],
    "sg:phone":"+1 601 638 2975",
    "sg:postcode":"39180",
    "sg:province":"MS",
    "wof:name":"Park Place Cottage Inc",
    "wof:placetype":"venue"
},
  "geometry": {"coordinates":[-90.853301,32.336905],"type":"Point"}
}