{
  "type": "Feature",
  "properties": {
    "addr:full":"202 E Starling St Greenville MS 38701",
    "addr:housenumber":"202",
    "addr:postcode":"38701",
    "addr:street":"E Starling St",
    "iso:country":"US",
    "sg:address":"202 E Starling St",
    "sg:city":"Greenville",
    "sg:classifiers":[
        {
            "category":"Shopping",
            "subcategory":"Pharmacy",
            "type":"Retail Goods"
        }
    ],
    "sg:phone":"+1 662 335 3385",
    "sg:postcode":"38701",
    "sg:province":"MS",
    "sg:tags":[
        "pharmaceutical",
        "consultant"
    ],
    "wof:name":"Sanders Pharmacy",
    "wof:placetype":"venue"
},
  "geometry": {"coordinates":[-91.050128,33.403054],"type":"Point"}
}