{
  "type": "Feature",
  "properties": {
    "iso:country":"US",
    "sg:address":"91 Shiloh-Firetower Rd",
    "sg:city":"Foxworth",
    "sg:classifiers":[
        {
            "category":"Organizations",
            "subcategory":"Religious Organization",
            "type":"Services"
        }
    ],
    "sg:phone":"+1 601 736 7977",
    "sg:postcode":"39483",
    "sg:province":"MS",
    "wof:name":"Shiloh Baptist Church",
    "wof:placetype":"venue"
},
  "geometry": {"coordinates":[-89.96672599999999,31.162677],"type":"Point"}
}