{
  "type": "Feature",
  "properties": {
    "addr:full":"906 Zetus Rd NW Brookhaven MS 39601",
    "addr:housenumber":"906",
    "addr:postcode":"39601",
    "addr:street":"Zetus Rd Nw",
    "iso:country":"US",
    "sg:address":"906 Zetus Rd NW",
    "sg:city":"Brookhaven",
    "sg:classifiers":[
        {
            "category":"Manufacturing",
            "subcategory":"Lumber",
            "type":"Manufacturing & Wholesale Goods"
        }
    ],
    "sg:phone":"+1 601 833 9593",
    "sg:postcode":"39601",
    "sg:province":"MS",
    "sg:tags":[
        "logging"
    ],
    "wof:name":"Cokers Timber Inc",
    "wof:placetype":"venue"
},
  "geometry": {"coordinates":[-90.49937799999999,31.560396],"type":"Point"}
}