{
  "type": "Feature",
  "properties": {
    "addr:full":"365 Losher St Hernando MS 38632",
    "addr:housenumber":"365",
    "addr:postcode":"38632",
    "addr:street":"Losher St",
    "iso:country":"US",
    "sg:address":"365 Losher St",
    "sg:city":"Hernando",
    "sg:classifiers":[
        {
            "category":"Bus Station",
            "type":"Transportation"
        }
    ],
    "sg:phone":"+1 662 429 5011",
    "sg:postcode":"38632",
    "sg:province":"MS",
    "sg:tags":[
        "maintenance",
        "facility"
    ],
    "wof:name":"4th District County Maint Fac",
    "wof:placetype":"venue"
},
  "geometry": {"coordinates":[-89.99598899999999,34.822393],"type":"Point"}
}