{
  "type": "Feature",
  "properties": {
    "iso:country":"US",
    "sg:address":"2509 20th Ave",
    "sg:city":"Gulfport",
    "sg:classifiers":[
        {
            "category":"Manufacturing",
            "subcategory":"Building Materials",
            "type":"Manufacturing & Wholesale Goods"
        }
    ],
    "sg:phone":"+1 228 868 8364",
    "sg:postcode":"39501",
    "sg:province":"MS",
    "wof:name":"Doors Glass & Millwork",
    "wof:placetype":"venue"
},
  "geometry": {"coordinates":[-89.08614799999999,30.381175],"type":"Point"}
}