{
  "type": "Feature",
  "properties": {
    "iso:country":"US",
    "sg:address":"7416 Goodman Rd",
    "sg:city":"Olive Branch",
    "sg:classifiers":[
        {
            "category":"Food & Beverages",
            "subcategory":"Groceries & Convenience Stores",
            "type":"Retail Goods"
        }
    ],
    "sg:phone":"+1 662 890 4978",
    "sg:postcode":"38654",
    "sg:province":"MS",
    "wof:name":"Fast Check Food Mart",
    "wof:placetype":"venue"
},
  "geometry": {"coordinates":[-89.85913600000001,34.96228],"type":"Point"}
}