{
  "type": "Feature",
  "properties": {
    "iso:country":"US",
    "sg:address":"1804 Hwy 80 W",
    "sg:city":"Jackson",
    "sg:classifiers":[
        {
            "category":"Retail",
            "subcategory":"Auto Repair",
            "type":"Services"
        }
    ],
    "sg:phone":"+1 601 355 8526",
    "sg:postcode":"39204",
    "sg:province":"MS",
    "sg:tags":[
        "transmission"
    ],
    "wof:name":"Coleman-Taylor Automatic Trans",
    "wof:placetype":"venue"
},
  "geometry": {"coordinates":[-90.21509399999999,32.287283],"type":"Point"}
}