{
  "type": "Feature",
  "properties": {
    "addr:full":"83 Prewitt Rd Shaw MS 38773",
    "addr:housenumber":"83",
    "addr:postcode":"38773",
    "addr:street":"Prewitt Rd",
    "iso:country":"US",
    "sg:address":"83 Prewitt Rd",
    "sg:city":"Shaw",
    "sg:phone":"+1 662 754 6542",
    "sg:postcode":"38773",
    "sg:province":"MS",
    "sg:tags":[
        "farm",
        "soybean"
    ],
    "wof:name":"Aubrey Corley",
    "wof:placetype":"venue"
},
  "geometry": {"coordinates":[-90.68465,33.618615],"type":"Point"}
}