{
  "type": "Feature",
  "properties": {
    "addr:full":"151 Mill Rd Columbus MS 39702",
    "addr:housenumber":"151",
    "addr:postcode":"39702",
    "addr:street":"Mill Rd",
    "iso:country":"US",
    "sg:address":"151 Mill Rd",
    "sg:city":"Columbus",
    "sg:classifiers":[
        {
            "category":"Retail",
            "subcategory":"Auto Rental",
            "type":"Services"
        }
    ],
    "sg:phone":"+1 662 327 1716",
    "sg:postcode":"39702",
    "sg:province":"MS",
    "sg:tags":[
        "truck"
    ],
    "wof:name":"Pete Repete Co Inc",
    "wof:placetype":"venue"
},
  "geometry": {"coordinates":[-88.33292899999999,33.5021],"type":"Point"}
}