{
  "type": "Feature",
  "properties": {
    "iso:country":"US",
    "sg:address":"1209 Nelle St",
    "sg:city":"Tupelo",
    "sg:classifiers":[
        {
            "category":"Organizations",
            "subcategory":"Religious Organization",
            "type":"Services"
        }
    ],
    "sg:phone":"+1 662 842 3103",
    "sg:postcode":"38801",
    "sg:province":"MS",
    "wof:name":"Harvest Time Assembly Of God",
    "wof:placetype":"venue"
},
  "geometry": {"coordinates":[-88.723946,34.257736],"type":"Point"}
}