{
  "type": "Feature",
  "properties": {
    "iso:country":"US",
    "sg:address":"1005 Country Club Dr",
    "sg:city":"Jackson",
    "sg:classifiers":[
        {
            "category":"Organizations",
            "subcategory":"Non-profit Organization",
            "type":"Services"
        }
    ],
    "sg:phone":"+1 601 922 0802",
    "sg:postcode":"39209",
    "sg:province":"MS",
    "sg:tags":[
        "information",
        "alcoholism",
        "treatment"
    ],
    "wof:name":"Country Oaks Recovery Ctr",
    "wof:placetype":"venue"
},
  "geometry": {"coordinates":[-90.24850000000001,32.336547],"type":"Point"}
}