{
  "type": "Feature",
  "properties": {
    "addr:full":"2384 Carrollton Rd Grenada MS 38901",
    "addr:housenumber":"2384",
    "addr:postcode":"38901",
    "addr:street":"Carrollton Rd",
    "iso:country":"US",
    "sg:address":"2384 Carrollton Rd",
    "sg:city":"Grenada",
    "sg:classifiers":[
        {
            "category":"Organizations",
            "subcategory":"Religious Organization",
            "type":"Services"
        }
    ],
    "sg:phone":"+1 662 226 5850",
    "sg:postcode":"38901",
    "sg:province":"MS",
    "wof:name":"Church Of God",
    "wof:placetype":"venue"
},
  "geometry": {"coordinates":[-89.80886099999999,33.755071],"type":"Point"}
}