{
  "type": "Feature",
  "properties": {
    "iso:country":"US",
    "sg:address":"123 S Commerce St",
    "sg:city":"Natchez",
    "sg:classifiers":[
        {
            "category":"Mining & Drilling",
            "type":"Manufacturing & Wholesale Goods"
        }
    ],
    "sg:phone":"+1 601 446 8090",
    "sg:postcode":"39120",
    "sg:province":"MS",
    "sg:tags":[
        "development",
        "gas",
        "oil",
        "exploration"
    ],
    "wof:name":"Nevanen Energy Inc",
    "wof:placetype":"venue"
},
  "geometry": {"coordinates":[-91.402479,31.55938],"type":"Point"}
}