{
  "type": "Feature",
  "properties": {
    "iso:country":"US",
    "sg:address":"3720 Hardy St",
    "sg:city":"Hattiesburg",
    "sg:classifiers":[
        {
            "category":"Home & Garden",
            "subcategory":"Home Furnishings",
            "type":"Retail Goods"
        }
    ],
    "sg:phone":"+1 601 261 2224",
    "sg:postcode":"39402",
    "sg:province":"MS",
    "sg:tags":[
        "utensil",
        "cooking"
    ],
    "wof:name":"Kitchen Table",
    "wof:placetype":"venue"
},
  "geometry": {"coordinates":[-89.34383800000001,31.324995],"type":"Point"}
}