{
  "type": "Feature",
  "properties": {
    "iso:country":"US",
    "sg:address":"290 Goodman Rd E",
    "sg:city":"Southaven",
    "sg:classifiers":[
        {
            "category":"Real Estate",
            "subcategory":"Developer",
            "type":"Services"
        }
    ],
    "sg:phone":"+1 662 349 9720",
    "sg:postcode":"38671",
    "sg:province":"MS",
    "sg:tags":[
        "home",
        "funeral",
        "cemetery"
    ],
    "wof:name":"Twin Oaks Memorial Gardens",
    "wof:placetype":"venue"
},
  "geometry": {"coordinates":[-89.984629,34.962814],"type":"Point"}
}