{
  "type": "Feature",
  "properties": {
    "iso:country":"US",
    "sg:address":"809 Tie Plant Rd",
    "sg:city":"Grenada",
    "sg:classifiers":[
        {
            "category":"Education",
            "subcategory":"School",
            "type":"Public Place"
        }
    ],
    "sg:phone":"+1 662 226 3311",
    "sg:postcode":"38901",
    "sg:province":"MS",
    "wof:name":"Tie Plant Alternative School",
    "wof:placetype":"venue"
},
  "geometry": {"coordinates":[-89.78505,33.741729],"type":"Point"}
}