{
  "type": "Feature",
  "properties": {
    "iso:country":"US",
    "sg:address":"2884 Timberland Dr",
    "sg:city":"Nesbit",
    "sg:classifiers":[
        {
            "category":"Wholesale",
            "subcategory":"Vending Machines",
            "type":"Manufacturing & Wholesale Goods"
        }
    ],
    "sg:phone":"+1 662 393 2541",
    "sg:postcode":"38651",
    "sg:province":"MS",
    "sg:tags":[
        "operator"
    ],
    "wof:name":"Holland Vending",
    "wof:placetype":"venue"
},
  "geometry": {"coordinates":[-90.04114,34.910446],"type":"Point"}
}