{
  "type": "Feature",
  "properties": {
    "iso:country":"US",
    "sg:address":"237 Loggins Rd",
    "sg:city":"Kilmichael",
    "sg:classifiers":[
        {
            "category":"Manufacturing",
            "subcategory":"Wood Products",
            "type":"Manufacturing & Wholesale Goods"
        }
    ],
    "sg:phone":"+1 662 283 5882",
    "sg:postcode":"39747",
    "sg:province":"MS",
    "sg:tags":[
        "mfg"
    ],
    "wof:name":"Loggins Woodwork",
    "wof:placetype":"venue"
},
  "geometry": {"coordinates":[-89.546036,33.56803],"type":"Point"}
}