{
  "type": "Feature",
  "properties": {
    "iso:country":"US",
    "sg:address":"1754 Cedarbrook Cir",
    "sg:city":"Belden",
    "sg:classifiers":[
        {
            "category":"Personal",
            "subcategory":"Beauty Salon",
            "type":"Services"
        }
    ],
    "sg:phone":"+1 662 256 8317",
    "sg:postcode":"38826",
    "sg:province":"MS",
    "wof:name":"Marion Thomas Salon",
    "wof:placetype":"venue"
},
  "geometry": {"coordinates":[-88.78919,34.285438],"type":"Point"}
}