{
  "type": "Feature",
  "properties": {
    "iso:country":"US",
    "sg:address":"3800 8th St",
    "sg:city":"Meridian",
    "sg:classifiers":[
        {
            "category":"Retail",
            "subcategory":"Auto Repair",
            "type":"Services"
        }
    ],
    "sg:phone":"+1 601 485 4276",
    "sg:postcode":"39301",
    "sg:province":"MS",
    "sg:tags":[
        "body",
        "used",
        "automobile",
        "coating",
        "tinting",
        "glass"
    ],
    "wof:name":"Quincy's Tint Shop",
    "wof:placetype":"venue"
},
  "geometry": {"coordinates":[-88.716965,32.364835],"type":"Point"}
}