{
  "type": "Feature",
  "properties": {
    "addr:full":"551 E Main St Marks MS 38646",
    "addr:housenumber":"551",
    "addr:postcode":"38646",
    "addr:street":"E Main St",
    "iso:country":"US",
    "sg:address":"551 E Main St",
    "sg:city":"Marks",
    "sg:classifiers":[
        {
            "category":"Organizations",
            "subcategory":"Religious Organization",
            "type":"Services"
        }
    ],
    "sg:phone":"+1 662 326 3808",
    "sg:postcode":"38646",
    "sg:province":"MS",
    "sg:tags":[
        "church"
    ],
    "wof:name":"Bellmount MB Church",
    "wof:placetype":"venue"
},
  "geometry": {"coordinates":[-90.267848,34.257653],"type":"Point"}
}