{
  "type": "Feature",
  "properties": {
    "iso:country":"US",
    "sg:address":"525 E Capitol St",
    "sg:city":"Jackson",
    "sg:classifiers":[
        {
            "category":"Professional",
            "subcategory":"Lawyer & Legal Services",
            "type":"Services"
        }
    ],
    "sg:phone":"+1 601 352 2092",
    "sg:postcode":"39201",
    "sg:province":"MS",
    "sg:tags":[
        "attorney"
    ],
    "wof:name":"Riley Ford Caldwell & Cork",
    "wof:placetype":"venue"
},
  "geometry": {"coordinates":[-90.18075899999999,32.299259],"type":"Point"}
}