{
  "type": "Feature",
  "properties": {
    "addr:full":"835 US Hwy 90 Bay Saint Louis MS 39520",
    "addr:housenumber":"835",
    "addr:postcode":"39520",
    "addr:street":"Us Hwy 90",
    "iso:country":"US",
    "sg:address":"835 US Hwy 90",
    "sg:city":"Bay Saint Louis",
    "sg:classifiers":[
        {
            "category":"Banks & Credit Unions",
            "subcategory":"Bank",
            "type":"Services"
        }
    ],
    "sg:phone":"+1 228 467 1411",
    "sg:postcode":"39520",
    "sg:province":"MS",
    "sg:tags":[
        "personal",
        "institution"
    ],
    "wof:name":"Citifinancial",
    "wof:placetype":"venue"
},
  "geometry": {"coordinates":[-89.352772,30.314954],"type":"Point"}
}