{
  "type": "Feature",
  "properties": {
    "iso:country":"US",
    "sg:address":"1231 N Main St",
    "sg:city":"Hattiesburg",
    "sg:classifiers":[
        {
            "category":"Shopping",
            "subcategory":"Books",
            "type":"Retail Goods"
        }
    ],
    "sg:phone":"+1 601 582 9121",
    "sg:postcode":"39401",
    "sg:province":"MS",
    "sg:tags":[
        "dealer"
    ],
    "wof:name":"One Way Christian Book Store",
    "wof:placetype":"venue"
},
  "geometry": {"coordinates":[-89.29880199999999,31.335339],"type":"Point"}
}