{
  "type": "Feature",
  "properties": {
    "addr:full":"6188 James Rd Hazlehurst MS 39083",
    "addr:housenumber":"6188",
    "addr:postcode":"39083",
    "addr:street":"James Rd",
    "iso:country":"US",
    "sg:address":"6188 James Rd",
    "sg:city":"Hazlehurst",
    "sg:classifiers":[
        {
            "category":"Personal",
            "subcategory":"Beauty Salon",
            "type":"Services"
        }
    ],
    "sg:phone":"+1 601 894 9060",
    "sg:postcode":"39083",
    "sg:province":"MS",
    "sg:tags":[
        "shop"
    ],
    "wof:name":"Teresa's Hair Salon",
    "wof:placetype":"venue"
},
  "geometry": {"coordinates":[-90.379749,31.83877],"type":"Point"}
}