{
  "type": "Feature",
  "properties": {
    "iso:country":"US",
    "sg:address":"332 Main St",
    "sg:city":"Greenville",
    "sg:classifiers":[
        {
            "category":"Utilities",
            "subcategory":"Natural Gas",
            "type":"Services"
        }
    ],
    "sg:phone":"+1 662 335 2656",
    "sg:postcode":"38701",
    "sg:province":"MS",
    "sg:tags":[
        "company"
    ],
    "wof:name":"Atmos Energy Mississippi",
    "wof:placetype":"venue"
},
  "geometry": {"coordinates":[-91.06294800000001,33.410815],"type":"Point"}
}