{
  "type": "Feature",
  "properties": {
    "addr:full":"110 Weisenberger Rd Madison MS 39110",
    "addr:housenumber":"110",
    "addr:postcode":"39110",
    "addr:street":"Weisenberger Rd",
    "iso:country":"US",
    "sg:address":"110 Weisenberger Rd",
    "sg:city":"Madison",
    "sg:classifiers":[
        {
            "category":"Professional",
            "subcategory":"Research",
            "type":"Services"
        }
    ],
    "sg:phone":"+1 601 853 2134",
    "sg:postcode":"39110",
    "sg:province":"MS",
    "sg:tags":[
        "environmental",
        "ecological"
    ],
    "sg:website":"www.earthcon.net",
    "wof:name":"Earth Consulting Group Inc",
    "wof:placetype":"venue"
},
  "geometry": {"coordinates":[-90.09479,32.516928],"type":"Point"}
}