{
  "type": "Feature",
  "properties": {
    "iso:country":"US",
    "sg:address":"221 River Rd",
    "sg:city":"Mantachie",
    "sg:classifiers":[
        {
            "category":"Building & Trades",
            "subcategory":"Plumbing",
            "type":"Services"
        }
    ],
    "sg:phone":"+1 662 862 4689",
    "sg:postcode":"38855",
    "sg:province":"MS",
    "sg:tags":[
        "contractor"
    ],
    "wof:name":"Larry Jones Backhoe & Trenchin",
    "wof:placetype":"venue"
},
  "geometry": {"coordinates":[-88.45658400000001,34.286923],"type":"Point"}
}