{
  "type": "Feature",
  "properties": {
    "addr:full":"3000 State Hwy 407 Kilmichael MS 39747",
    "addr:housenumber":"3000",
    "addr:postcode":"39747",
    "addr:street":"State Hwy 407 Kilmichael",
    "iso:country":"US",
    "sg:address":"3000 State Hwy 407",
    "sg:city":"Kilmichael",
    "sg:classifiers":[
        {
            "category":"Food & Beverages",
            "subcategory":"Groceries & Convenience Stores",
            "type":"Retail Goods"
        }
    ],
    "sg:phone":"+1 662 262 7228",
    "sg:postcode":"39747",
    "sg:province":"MS",
    "wof:name":"Poplar Creek Store",
    "wof:placetype":"venue"
},
  "geometry": {"coordinates":[-89.552718,33.352651],"type":"Point"}
}