{
  "type": "Feature",
  "properties": {
    "iso:country":"US",
    "sg:address":"14300 Dedeaux Rd",
    "sg:city":"Gulfport",
    "sg:classifiers":[
        {
            "category":"Personal",
            "subcategory":"Beauty Salon",
            "type":"Services"
        }
    ],
    "sg:phone":"+1 228 831 2207",
    "sg:postcode":"39503",
    "sg:province":"MS",
    "sg:tags":[
        "manicuring"
    ],
    "wof:name":"Superior Nails",
    "wof:placetype":"venue"
},
  "geometry": {"coordinates":[-89.07851599999999,30.449548],"type":"Point"}
}