{
  "type": "Feature",
  "properties": {
    "addr:full":"5924 Stateline Rd Walls MS 38680",
    "addr:housenumber":"5924",
    "addr:postcode":"38680",
    "addr:street":"Stateline Rd",
    "iso:country":"US",
    "sg:address":"5924 Stateline Rd",
    "sg:city":"Walls",
    "sg:classifiers":[
        {
            "category":"Shopping",
            "subcategory":"Department Store",
            "type":"Retail Goods"
        },
        {
            "category":"Shopping",
            "subcategory":"Discount & Variety Stores",
            "type":"Retail Goods"
        },
        {
            "category":"Shopping",
            "type":"Retail Goods"
        },
        {
            "category":"Food & Beverages",
            "subcategory":"Groceries & Convenience Stores",
            "type":"Retail Goods"
        }
    ],
    "sg:phone":"+1 662 781 0065",
    "sg:postcode":"38680",
    "sg:province":"MS",
    "sg:tags":[
        "merchandise"
    ],
    "sg:website":"http://www.dollargeneral.com",
    "wof:name":"Dollar General",
    "wof:placetype":"venue"
},
  "geometry": {"coordinates":[-90.094888,34.991641],"type":"Point"}
}