{
  "type": "Feature",
  "properties": {
    "addr:full":"10175 Kennedy St Coffeeville MS 38922",
    "addr:housenumber":"10175",
    "addr:postcode":"38922",
    "addr:street":"Kennedy St",
    "iso:country":"US",
    "sg:address":"10175 Kennedy St",
    "sg:city":"Coffeeville",
    "sg:classifiers":[
        {
            "category":"Insurance",
            "subcategory":"Insurance Agent",
            "type":"Services"
        }
    ],
    "sg:phone":"+1 662 675 2005",
    "sg:postcode":"38922",
    "sg:province":"MS",
    "wof:name":"George Shute Insurance",
    "wof:placetype":"venue"
},
  "geometry": {"coordinates":[-89.67204099999999,33.977453],"type":"Point"}
}