{
  "type": "Feature",
  "properties": {
    "iso:country":"US",
    "sg:address":"2102 Swetman Blvd",
    "sg:city":"Gulfport",
    "sg:classifiers":[
        {
            "category":"Restaurant",
            "type":"Food & Drink"
        }
    ],
    "sg:phone":"+1 228 896 1056",
    "sg:postcode":"39507",
    "sg:province":"MS",
    "sg:tags":[
        "eating"
    ],
    "wof:name":"Espresso Cafe",
    "wof:placetype":"venue"
},
  "geometry": {"coordinates":[-89.018466,30.393507],"type":"Point"}
}