{
  "type": "Feature",
  "properties": {
    "iso:country":"US",
    "sg:address":"1317 26th Ave",
    "sg:city":"Gulfport",
    "sg:classifiers":[
        {
            "category":"Home & Garden",
            "subcategory":"Furniture",
            "type":"Retail Goods"
        }
    ],
    "sg:phone":"+1 228 863 0361",
    "sg:postcode":"39501",
    "sg:province":"MS",
    "wof:name":"J C Clower Furniture Co Inc",
    "wof:placetype":"venue"
},
  "geometry": {"coordinates":[-89.093996,30.368009],"type":"Point"}
}