{
  "type": "Feature",
  "properties": {
    "addr:full":"2244 Hwy 82 E Greenville MS 38703",
    "addr:housenumber":"2244",
    "addr:postcode":"38703",
    "addr:street":"Hwy 82 E",
    "iso:country":"US",
    "sg:address":"2244 Hwy 82 E",
    "sg:city":"Greenville",
    "sg:classifiers":[
        {
            "category":"Retail",
            "subcategory":"Auto Repair",
            "type":"Services"
        }
    ],
    "sg:phone":"+1 662 332 3636",
    "sg:postcode":"38703",
    "sg:province":"MS",
    "sg:tags":[
        "automobile",
        "lubrication"
    ],
    "wof:name":"Shell Rapid Lube",
    "wof:placetype":"venue"
},
  "geometry": {"coordinates":[-91.020191,33.400011],"type":"Point"}
}