{
  "type": "Feature",
  "properties": {
    "iso:country":"US",
    "sg:address":"910 Courthouse Aly",
    "sg:city":"Greenville",
    "sg:classifiers":[
        {
            "category":"Government",
            "subcategory":"Court House",
            "type":"Public Place"
        }
    ],
    "sg:phone":"+1 662 378 2105",
    "sg:postcode":"38701",
    "sg:province":"MS",
    "sg:tags":[
        "state",
        "counsel"
    ],
    "wof:name":"Washington Cnty District Atty",
    "wof:placetype":"venue"
},
  "geometry": {"coordinates":[-91.052848,33.408583],"type":"Point"}
}