{
  "type": "Feature",
  "properties": {
    "addr:full":"2078 Herbert Smith Rd Mc Comb MS 39648",
    "addr:housenumber":"2078",
    "addr:postcode":"39648",
    "addr:street":"Herbert Smith Rd",
    "iso:country":"US",
    "sg:address":"2078 Herbert Smith Rd",
    "sg:city":"Mc Comb",
    "sg:classifiers":[
        {
            "category":"Building & Trades",
            "subcategory":"Construction",
            "type":"Services"
        }
    ],
    "sg:phone":"+1 601 542 3582",
    "sg:postcode":"39648",
    "sg:province":"MS",
    "sg:tags":[
        "system",
        "septic"
    ],
    "wof:name":"Browns Backhoe Service",
    "wof:placetype":"venue"
},
  "geometry": {"coordinates":[-90.262148,31.03863],"type":"Point"}
}