{
  "type": "Feature",
  "properties": {
    "addr:full":"13350 Dedeaux Rd Gulfport MS 39503",
    "addr:housenumber":"13350",
    "addr:postcode":"39503",
    "addr:street":"Dedeaux Rd",
    "iso:country":"US",
    "sg:address":"13350 Dedeaux Rd",
    "sg:city":"Gulfport",
    "sg:classifiers":[
        {
            "category":"Wholesale",
            "subcategory":"Groceries",
            "type":"Manufacturing & Wholesale Goods"
        }
    ],
    "sg:phone":"+1 228 832 8855",
    "sg:postcode":"39503",
    "sg:province":"MS",
    "sg:tags":[
        "food",
        "product"
    ],
    "sg:website":"www.fritolay.com",
    "wof:name":"Frito-Lay Inc",
    "wof:placetype":"venue"
},
  "geometry": {"coordinates":[-89.063616,30.44965],"type":"Point"}
}