{
  "type": "Feature",
  "properties": {
    "addr:full":"609 Cruise St Corinth MS 38834",
    "addr:housenumber":"609",
    "addr:postcode":"38834",
    "addr:street":"Cruise St",
    "iso:country":"US",
    "sg:address":"609 Cruise St",
    "sg:city":"Corinth",
    "sg:classifiers":[
        {
            "category":"Insurance",
            "subcategory":"Insurance Agent",
            "type":"Services"
        }
    ],
    "sg:phone":"+1 662 286 2046",
    "sg:postcode":"38834",
    "sg:province":"MS",
    "wof:name":"Woodmen Of The World Life Ins",
    "wof:placetype":"venue"
},
  "geometry": {"coordinates":[-88.51972499999999,34.934157],"type":"Point"}
}