{
  "type": "Feature",
  "properties": {
    "addr:full":"1503 Hwy 45 N Columbus MS 39705",
    "addr:housenumber":"1503",
    "addr:postcode":"39705",
    "addr:street":"Hwy 45 N",
    "iso:country":"US",
    "sg:address":"1503 Hwy 45 N",
    "sg:city":"Columbus",
    "sg:classifiers":[
        {
            "category":"Health Services",
            "subcategory":"Doctor",
            "type":"Services"
        }
    ],
    "sg:phone":"+1 662 328 9623",
    "sg:postcode":"39705",
    "sg:province":"MS",
    "sg:tags":[
        "clinic"
    ],
    "wof:name":"Family Medical Ctr",
    "wof:placetype":"venue"
},
  "geometry": {"coordinates":[-88.436504,33.527524],"type":"Point"}
}