{
  "type": "Feature",
  "properties": {
    "iso:country":"US",
    "sg:address":"300 Old Magee Rd",
    "sg:city":"Magee",
    "sg:classifiers":[
        {
            "category":"Farming",
            "subcategory":"Farm & Veterinary Services",
            "type":"Manufacturing & Wholesale Goods"
        }
    ],
    "sg:phone":"+1 601 849 5565",
    "sg:postcode":"39111",
    "sg:province":"MS",
    "sg:tags":[
        "labor",
        "contractor"
    ],
    "wof:name":"McAlpin Development LLP",
    "wof:placetype":"venue"
},
  "geometry": {"coordinates":[-89.75004,31.89435],"type":"Point"}
}