{
  "type": "Feature",
  "properties": {
    "iso:country":"US",
    "sg:address":"3 Oak Aly",
    "sg:city":"Clinton",
    "sg:classifiers":[
        {
            "category":"Manufacturing",
            "subcategory":"Glass & Minerals",
            "type":"Manufacturing & Wholesale Goods"
        }
    ],
    "sg:phone":"+1 601 924 0309",
    "sg:postcode":"39056",
    "sg:province":"MS",
    "sg:tags":[
        "mfg"
    ],
    "wof:name":"Kelly Lane LLC",
    "wof:placetype":"venue"
},
  "geometry": {"coordinates":[-90.308932,32.377657],"type":"Point"}
}