{
  "type": "Feature",
  "properties": {
    "addr:full":"444 Garden Grove St Vicksburg MS 39180",
    "addr:housenumber":"444",
    "addr:postcode":"39180",
    "addr:street":"Garden Grove St",
    "iso:country":"US",
    "sg:address":"444 Garden Grove St",
    "sg:city":"Vicksburg",
    "sg:classifiers":[
        {
            "category":"Health Services",
            "subcategory":"Doctor",
            "type":"Services"
        }
    ],
    "sg:phone":"+1 601 634 6294",
    "sg:postcode":"39180",
    "sg:province":"MS",
    "sg:tags":[
        "medical"
    ],
    "wof:name":"Pamela L Jett",
    "wof:placetype":"venue"
},
  "geometry": {"coordinates":[-90.838365,32.317324],"type":"Point"}
}