{
  "type": "Feature",
  "properties": {
    "iso:country":"US",
    "sg:address":"1501 Fillmore Dr",
    "sg:city":"Tupelo",
    "sg:classifiers":[
        {
            "category":"Home & Garden",
            "subcategory":"Building Materials",
            "type":"Retail Goods"
        }
    ],
    "sg:phone":"+1 662 844 4325",
    "sg:postcode":"38801",
    "sg:province":"MS",
    "wof:name":"Tiamingo Cabinets and Glass",
    "wof:placetype":"venue"
},
  "geometry": {"coordinates":[-88.727644,34.241631],"type":"Point"}
}