{
  "type": "Feature",
  "properties": {
    "iso:country":"US",
    "sg:address":"2125 N Frontage Rd",
    "sg:city":"Vicksburg",
    "sg:classifiers":[
        {
            "category":"Banks & Credit Unions",
            "subcategory":"Bank",
            "type":"Services"
        }
    ],
    "sg:phone":"+1 601 661 7312",
    "sg:postcode":"39180",
    "sg:province":"MS",
    "wof:name":"River Hills Bank",
    "wof:placetype":"venue"
},
  "geometry": {"coordinates":[-90.864875,32.325199],"type":"Point"}
}