{
  "type": "Feature",
  "properties": {
    "iso:country":"US",
    "sg:address":"30341 Old Hwy 6",
    "sg:city":"Nettleton",
    "sg:classifiers":[
        {
            "category":"Government",
            "subcategory":"Fire Station",
            "type":"Public Place"
        }
    ],
    "sg:phone":"+1 662 256 7581",
    "sg:postcode":"38858",
    "sg:province":"MS",
    "sg:tags":[
        "protection"
    ],
    "wof:name":"Cason Volunteer Fire Dept",
    "wof:placetype":"venue"
},
  "geometry": {"coordinates":[-88.516293,34.067748],"type":"Point"}
}