{
  "type": "Feature",
  "properties": {
    "iso:country":"US",
    "sg:address":"9476 County Farm Rd",
    "sg:city":"Gulfport",
    "sg:classifiers":[
        {
            "category":"Wholesale",
            "subcategory":"Machinery & Supplies",
            "type":"Manufacturing & Wholesale Goods"
        }
    ],
    "sg:phone":"+1 228 831 0002",
    "sg:postcode":"39503",
    "sg:province":"MS",
    "sg:tags":[
        "farm",
        "equipment"
    ],
    "wof:name":"All Seasons Farm Equipment",
    "wof:placetype":"venue"
},
  "geometry": {"coordinates":[-89.19167299999999,30.42744],"type":"Point"}
}