{
  "type": "Feature",
  "properties": {
    "iso:country":"US",
    "sg:address":"1622 Smith St",
    "sg:city":"Greenville",
    "sg:classifiers":[
        {
            "category":"Personal",
            "subcategory":"Beauty Salon",
            "type":"Services"
        }
    ],
    "sg:phone":"+1 662 335 0337",
    "sg:postcode":"38703",
    "sg:province":"MS",
    "wof:name":"Lady L's II Hairsalon",
    "wof:placetype":"venue"
},
  "geometry": {"coordinates":[-91.030486,33.398569],"type":"Point"}
}