{
  "type": "Feature",
  "properties": {
    "iso:country":"US",
    "sg:address":"1052 Ridgewood Pl",
    "sg:city":"Jackson",
    "sg:classifiers":[
        {
            "category":"Social Services",
            "subcategory":"Child Care",
            "type":"Services"
        }
    ],
    "sg:phone":"+1 601 956 7180",
    "sg:postcode":"39211",
    "sg:province":"MS",
    "wof:name":"Ridgewood Pre-School Ctr",
    "wof:placetype":"venue"
},
  "geometry": {"coordinates":[-90.142079,32.39376],"type":"Point"}
}