{
  "type": "Feature",
  "properties": {
    "iso:country":"US",
    "sg:address":"1529 University Ave",
    "sg:city":"Oxford",
    "sg:classifiers":[
        {
            "category":"Professional",
            "subcategory":"Computer Services",
            "type":"Services"
        }
    ],
    "sg:phone":"+1 662 236 6848",
    "sg:postcode":"38655",
    "sg:province":"MS",
    "sg:tags":[
        "repair"
    ],
    "wof:name":"Computer System Products",
    "wof:placetype":"venue"
},
  "geometry": {"coordinates":[-89.515586,34.36361],"type":"Point"}
}