{
  "type": "Feature",
  "properties": {
    "iso:country":"US",
    "sg:address":"102 S Child St",
    "sg:city":"Okolona",
    "sg:classifiers":[
        {
            "category":"Personal",
            "subcategory":"Beauty Salon",
            "type":"Services"
        }
    ],
    "sg:phone":"+1 662 447 5351",
    "sg:postcode":"38860",
    "sg:province":"MS",
    "sg:tags":[
        "shop"
    ],
    "wof:name":"B J's Beauty Shop",
    "wof:placetype":"venue"
},
  "geometry": {"coordinates":[-88.74281000000001,34.004781],"type":"Point"}
}