{
  "type": "Feature",
  "properties": {
    "iso:country":"US",
    "sg:address":"203 Alabama St",
    "sg:city":"Columbus",
    "sg:classifiers":[
        {
            "category":"Restaurant",
            "type":"Food & Drink"
        }
    ],
    "sg:menulink":"http://www.allmenus.com/ms/caledonia/156111-hardees/menu/",
    "sg:phone":"+1 662 327 0304",
    "sg:postcode":"39702",
    "sg:province":"MS",
    "sg:tags":[
        "burger",
        "american"
    ],
    "wof:name":"Hardee's",
    "wof:placetype":"venue"
},
  "geometry": {"coordinates":[-88.383296,33.495877],"type":"Point"}
}