{
  "type": "Feature",
  "properties": {
    "iso:country":"US",
    "sg:address":"530 George St",
    "sg:city":"Jackson",
    "sg:classifiers":[
        {
            "category":"Health Services",
            "subcategory":"Clinic",
            "type":"Services"
        }
    ],
    "sg:phone":"+1 601 948 4493",
    "sg:postcode":"39202",
    "sg:province":"MS",
    "wof:name":"Compass Project",
    "wof:placetype":"venue"
},
  "geometry": {"coordinates":[-90.180761,32.306199],"type":"Point"}
}