{
  "type": "Feature",
  "properties": {
    "iso:country":"US",
    "sg:address":"11097 Sylvarena Rd",
    "sg:city":"Wesson",
    "sg:classifiers":[
        {
            "category":"Social Services",
            "subcategory":"Child Care",
            "type":"Services"
        }
    ],
    "sg:phone":"+1 601 643 8821",
    "sg:postcode":"39191",
    "sg:province":"MS",
    "wof:name":"Precious Moments Learning Ctr",
    "wof:placetype":"venue"
},
  "geometry": {"coordinates":[-90.395718,31.704656],"type":"Point"}
}