{
  "type": "Feature",
  "properties": {
    "iso:country":"US",
    "sg:address":"7510 US Hwy 49",
    "sg:city":"Hattiesburg",
    "sg:classifiers":[
        {
            "category":"Wholesale",
            "subcategory":"Motor Vehicles",
            "type":"Manufacturing & Wholesale Goods"
        }
    ],
    "sg:phone":"+1 601 268 7550",
    "sg:postcode":"39402",
    "sg:province":"MS",
    "sg:tags":[
        "auction",
        "automobile"
    ],
    "wof:name":"Mississippi Auto Auction Inc",
    "wof:placetype":"venue"
},
  "geometry": {"coordinates":[-89.39023,31.401662],"type":"Point"}
}