{
  "type": "Feature",
  "properties": {
    "iso:country":"US",
    "sg:address":"328 Day St",
    "sg:city":"Rolling Fork",
    "sg:classifiers":[
        {
            "category":"Shopping",
            "type":"Retail Goods"
        }
    ],
    "sg:phone":"+1 662 873 4934",
    "sg:postcode":"39159",
    "sg:province":"MS",
    "sg:tags":[
        "cosmetic",
        "perfume"
    ],
    "wof:name":"Djuana Coleman",
    "wof:placetype":"venue"
},
  "geometry": {"coordinates":[-90.882244,32.908028],"type":"Point"}
}