{
  "type": "Feature",
  "properties": {
    "iso:country":"US",
    "sg:address":"226 Sgt Prentiss Dr",
    "sg:city":"Natchez",
    "sg:classifiers":[
        {
            "category":"Food & Beverages",
            "subcategory":"Groceries & Convenience Stores",
            "type":"Retail Goods"
        }
    ],
    "sg:phone":"+1 601 442 9364",
    "sg:postcode":"39120",
    "sg:province":"MS",
    "wof:name":"Gas Lane Convenience Store",
    "wof:placetype":"venue"
},
  "geometry": {"coordinates":[-91.374934,31.545506],"type":"Point"}
}