{
  "type": "Feature",
  "properties": {
    "iso:country":"US",
    "sg:address":"3880 Seven Springs Rd",
    "sg:city":"Raymond",
    "sg:classifiers":[
        {
            "category":"Organizations",
            "subcategory":"Religious Organization",
            "type":"Services"
        }
    ],
    "sg:phone":"+1 601 857 8222",
    "sg:postcode":"39154",
    "sg:province":"MS",
    "sg:tags":[
        "church"
    ],
    "wof:name":"Mt Bethel Baptist Church",
    "wof:placetype":"venue"
},
  "geometry": {"coordinates":[-90.38457099999999,32.225391],"type":"Point"}
}