{
  "type": "Feature",
  "properties": {
    "iso:country":"US",
    "sg:address":"906 6th Ave",
    "sg:city":"Picayune",
    "sg:classifiers":[
        {
            "category":"Health Services",
            "subcategory":"Doctor",
            "type":"Services"
        }
    ],
    "sg:phone":"+1 601 799 2442",
    "sg:postcode":"39466",
    "sg:province":"MS",
    "sg:tags":[
        "physician",
        "surgeon"
    ],
    "wof:name":"R Dale Le Blance Inc",
    "wof:placetype":"venue"
},
  "geometry": {"coordinates":[-89.690043,30.530166],"type":"Point"}
}