{
  "type": "Feature",
  "properties": {
    "iso:country":"US",
    "sg:address":"2400 Appleton Dr",
    "sg:city":"Southaven",
    "sg:classifiers":[
        {
            "category":"Banks & Credit Unions",
            "subcategory":"Bank",
            "type":"Services"
        }
    ],
    "sg:phone":"+1 662 449 3449",
    "sg:postcode":"38672",
    "sg:province":"MS",
    "sg:tags":[
        "mortgage"
    ],
    "wof:name":"W&P Mortgage Investors LLC",
    "wof:placetype":"venue"
},
  "geometry": {"coordinates":[-89.947963,34.924278],"type":"Point"}
}