{
  "type": "Feature",
  "properties": {
    "iso:country":"US",
    "sg:address":"2080 US Hwy 61",
    "sg:city":"Port Gibson",
    "sg:phone":"+1 601 437 3584",
    "sg:postcode":"39150",
    "sg:province":"MS",
    "sg:tags":[
        "gas"
    ],
    "wof:name":"Herring Gas Co",
    "wof:placetype":"venue"
},
  "geometry": {"coordinates":[-90.98788399999999,31.946541],"type":"Point"}
}