{
  "type": "Feature",
  "properties": {
    "iso:country":"US",
    "sg:address":"7285 Winchester Rd",
    "sg:city":"Memphis",
    "sg:classifiers":[
        {
            "category":"Professional",
            "subcategory":"Business Services",
            "type":"Services"
        }
    ],
    "sg:phone":"+1 901 737 7451",
    "sg:postcode":"38125",
    "sg:province":"MS",
    "sg:tags":[
        "embroidery"
    ],
    "wof:name":"Glory Apparel Custom",
    "wof:placetype":"venue"
},
  "geometry": {"coordinates":[-89.821854,35.048872],"type":"Point"}
}