{
  "type": "Feature",
  "properties": {
    "addr:full":"2812 Terry Rd Jackson MS 39212",
    "addr:housenumber":"2812",
    "addr:postcode":"39212",
    "addr:street":"Terry Rd",
    "iso:country":"US",
    "sg:address":"2812 Terry Rd",
    "sg:city":"Jackson",
    "sg:classifiers":[
        {
            "category":"Restaurant",
            "type":"Food & Drink"
        }
    ],
    "sg:phone":"+1 601 372 8221",
    "sg:postcode":"39212",
    "sg:province":"MS",
    "wof:name":"Mc Donald's",
    "wof:placetype":"venue"
},
  "geometry": {"coordinates":[-90.218546,32.267669],"type":"Point"}
}