{
  "type": "Feature",
  "properties": {
    "iso:country":"US",
    "sg:address":"34 Prentiss Dr",
    "sg:city":"Natchez",
    "sg:classifiers":[
        {
            "category":"Restaurant",
            "type":"Food & Drink"
        }
    ],
    "sg:phone":"+1 601 445 7494",
    "sg:postcode":"39120",
    "sg:province":"MS",
    "sg:tags":[
        "eating"
    ],
    "wof:name":"Taco Bell",
    "wof:placetype":"venue"
},
  "geometry": {"coordinates":[-91.38782999999999,31.566682],"type":"Point"}
}