{
  "type": "Feature",
  "properties": {
    "addr:full":"263 Wilmington St Jackson MS 39204",
    "addr:housenumber":"263",
    "addr:postcode":"39204",
    "addr:street":"Wilmington St",
    "iso:country":"US",
    "sg:address":"263 Wilmington St",
    "sg:city":"Jackson",
    "sg:phone":"+1 601 372 3531",
    "sg:postcode":"39204",
    "sg:province":"MS",
    "sg:tags":[
        "equipment",
        "station"
    ],
    "wof:name":"Cruzen Equipment Co Inc",
    "wof:placetype":"venue"
},
  "geometry": {"coordinates":[-90.208259,32.281276],"type":"Point"}
}