{
  "type": "Feature",
  "properties": {
    "addr:full":"2630 Beach Blvd Biloxi MS 39531",
    "addr:housenumber":"2630",
    "addr:postcode":"39531",
    "addr:street":"Beach Blvd",
    "iso:country":"US",
    "sg:address":"2630 Beach Blvd",
    "sg:city":"Biloxi",
    "sg:classifiers":[
        {
            "category":"Banks & Credit Unions",
            "subcategory":"Bank",
            "type":"Services"
        }
    ],
    "sg:phone":"+1 228 594 1231",
    "sg:postcode":"39531",
    "sg:province":"MS",
    "sg:tags":[
        "machine",
        "teller",
        "automated"
    ],
    "wof:name":"ATM Of Biloxi",
    "wof:placetype":"venue"
},
  "geometry": {"coordinates":[-88.99039999999999,30.389524],"type":"Point"}
}