{
  "type": "Feature",
  "properties": {
    "iso:country":"US",
    "sg:address":"301 Hwy 51 S",
    "sg:city":"Sardis",
    "sg:classifiers":[
        {
            "category":"Retail",
            "subcategory":"Laundry & Dry Cleaning",
            "type":"Services"
        }
    ],
    "sg:phone":"+1 662 487 9003",
    "sg:postcode":"38666",
    "sg:province":"MS",
    "sg:tags":[
        "cleaners",
        "rug",
        "carpet"
    ],
    "wof:name":"Johnson's Carpet Care & Detail",
    "wof:placetype":"venue"
},
  "geometry": {"coordinates":[-89.925601,34.432953],"type":"Point"}
}