{
  "type": "Feature",
  "properties": {
    "iso:country":"US",
    "sg:address":"1523 S Shivers St",
    "sg:city":"Poplarville",
    "sg:classifiers":[
        {
            "category":"Organizations",
            "subcategory":"Religious Organization",
            "type":"Services"
        }
    ],
    "sg:phone":"+1 601 795 6416",
    "sg:postcode":"39470",
    "sg:province":"MS",
    "sg:tags":[
        "church"
    ],
    "wof:name":"Merrill Chapel United Meth",
    "wof:placetype":"venue"
},
  "geometry": {"coordinates":[-89.531406,30.827759],"type":"Point"}
}