{
  "type": "Feature",
  "properties": {
    "iso:country":"US",
    "sg:address":"735 S State St",
    "sg:city":"Clarksdale",
    "sg:classifiers":[
        {
            "category":"Restaurant",
            "type":"Food & Drink"
        }
    ],
    "sg:menulink":"http://www.allmenus.com/ms/5/182562-wendys/menu/",
    "sg:phone":"+1 662 624 5391",
    "sg:postcode":"38614",
    "sg:province":"MS",
    "sg:tags":[
        "burger",
        "american",
        "soup"
    ],
    "wof:name":"Wendy's",
    "wof:placetype":"venue"
},
  "geometry": {"coordinates":[-90.581127,34.188559],"type":"Point"}
}