{
  "type": "Feature",
  "properties": {
    "iso:country":"US",
    "sg:address":"2010 E County Line Rd",
    "sg:city":"Ridgeland",
    "sg:classifiers":[
        {
            "category":"Restaurant",
            "type":"Food & Drink"
        }
    ],
    "sg:menulink":"http://www.allmenus.com/ms/madison/156496-krystal-burgers/menu/",
    "sg:phone":"+1 601 957 2041",
    "sg:postcode":"39157",
    "sg:province":"MS",
    "sg:tags":[
        "burger",
        "chicken",
        "american"
    ],
    "wof:name":"Krystal Burgers",
    "wof:placetype":"venue"
},
  "geometry": {"coordinates":[-90.10935499999999,32.399524],"type":"Point"}
}