{
  "type": "Feature",
  "properties": {
    "iso:country":"US",
    "sg:address":"931 Hwy 80 W",
    "sg:city":"Jackson",
    "sg:classifiers":[
        {
            "category":"Wholesale",
            "subcategory":"Machinery & Supplies",
            "type":"Manufacturing & Wholesale Goods"
        }
    ],
    "sg:phone":"+1 601 969 6880",
    "sg:postcode":"39204",
    "sg:province":"MS",
    "sg:tags":[
        "sprinkler"
    ],
    "wof:name":"American Fire Sprinkler Inc",
    "wof:placetype":"venue"
},
  "geometry": {"coordinates":[-90.200045,32.285228],"type":"Point"}
}