{
  "type": "Feature",
  "properties": {
    "iso:country":"US",
    "sg:address":"1835 Nelle St",
    "sg:city":"Tupelo",
    "sg:classifiers":[
        {
            "category":"Retail",
            "subcategory":"Auto Repair",
            "type":"Services"
        }
    ],
    "sg:phone":"+1 662 841 2226",
    "sg:postcode":"38801",
    "sg:province":"MS",
    "sg:tags":[
        "body",
        "automobile",
        "painting"
    ],
    "wof:name":"Corey's Customs & More",
    "wof:placetype":"venue"
},
  "geometry": {"coordinates":[-88.732518,34.259391],"type":"Point"}
}