{
  "type": "Feature",
  "properties": {
    "iso:country":"US",
    "sg:address":"902 N Main St",
    "sg:city":"Ripley",
    "sg:classifiers":[
        {
            "category":"Home & Garden",
            "subcategory":"Furniture",
            "type":"Retail Goods"
        }
    ],
    "sg:phone":"+1 662 837 6070",
    "sg:postcode":"38663",
    "sg:province":"MS",
    "sg:tags":[
        "cabinet"
    ],
    "wof:name":"Crawford Cabinet Company",
    "wof:placetype":"venue"
},
  "geometry": {"coordinates":[-88.948981,34.737545],"type":"Point"}
}