{
  "type": "Feature",
  "properties": {
    "addr:full":"811 N Davis Ave Cleveland MS 38732",
    "addr:housenumber":"811",
    "addr:postcode":"38732",
    "addr:street":"N Davis Ave",
    "iso:country":"US",
    "sg:address":"811 N Davis Ave",
    "sg:city":"Cleveland",
    "sg:classifiers":[
        {
            "category":"Autos & Motor Vehicles",
            "subcategory":"Automobile Sales",
            "type":"Retail Goods"
        }
    ],
    "sg:phone":"+1 662 843 9990",
    "sg:postcode":"38732",
    "sg:province":"MS",
    "sg:tags":[
        "car",
        "dealer"
    ],
    "wof:name":"61 Auto Mall",
    "wof:placetype":"venue"
},
  "geometry": {"coordinates":[-90.71592200000001,33.758473],"type":"Point"}
}