{
  "type": "Feature",
  "properties": {
    "addr:full":"1618 Eckford St Water Valley MS 38965",
    "addr:housenumber":"1618",
    "addr:postcode":"38965",
    "addr:street":"Eckford St",
    "iso:country":"US",
    "sg:address":"1618 Eckford St",
    "sg:city":"Water Valley",
    "sg:classifiers":[
        {
            "category":"Real Estate",
            "subcategory":"Real Estate Operator",
            "type":"Services"
        }
    ],
    "sg:phone":"+1 662 473 3327",
    "sg:postcode":"38965",
    "sg:province":"MS",
    "sg:tags":[
        "building",
        "apartment"
    ],
    "wof:name":"Water Valley Manor Apartments",
    "wof:placetype":"venue"
},
  "geometry": {"coordinates":[-89.62681499999999,34.168155],"type":"Point"}
}