{
  "type": "Feature",
  "properties": {
    "iso:country":"US",
    "sg:address":"237 Williams Dr",
    "sg:city":"Florence",
    "sg:classifiers":[
        {
            "category":"Building & Trades",
            "subcategory":"Electrical",
            "type":"Services"
        }
    ],
    "sg:phone":"+1 601 845 5683",
    "sg:postcode":"39073",
    "sg:province":"MS",
    "sg:tags":[
        "electrical",
        "electric",
        "contractor"
    ],
    "wof:name":"Ernie's Culpepper Electric Inc",
    "wof:placetype":"venue"
},
  "geometry": {"coordinates":[-90.049429,32.122222],"type":"Point"}
}