{
  "type": "Feature",
  "properties": {
    "iso:country":"US",
    "sg:address":"11370 Lorraine Rd",
    "sg:city":"Gulfport",
    "sg:classifiers":[
        {
            "category":"Freight",
            "type":"Transportation"
        }
    ],
    "sg:phone":"+1 228 596 4988",
    "sg:postcode":"39503",
    "sg:province":"MS",
    "sg:tags":[
        "commercial",
        "storage"
    ],
    "wof:name":"All Star Storage",
    "wof:placetype":"venue"
},
  "geometry": {"coordinates":[-89.028735,30.451959],"type":"Point"}
}