{
  "type": "Feature",
  "properties": {
    "iso:country":"US",
    "sg:address":"913 West Ave",
    "sg:city":"Columbia",
    "sg:classifiers":[
        {
            "category":"Education",
            "subcategory":"School",
            "type":"Public Place"
        }
    ],
    "sg:phone":"+1 601 736 7666",
    "sg:postcode":"39429",
    "sg:province":"MS",
    "wof:name":"Columbia Primary School",
    "wof:placetype":"venue"
},
  "geometry": {"coordinates":[-89.828086,31.255794],"type":"Point"}
}