{
  "type": "Feature",
  "properties": {
    "addr:full":"601 N 1st St Brookhaven MS 39601",
    "addr:housenumber":"601",
    "addr:postcode":"39601",
    "addr:street":"N 1St St",
    "iso:country":"US",
    "sg:address":"601 N 1st St",
    "sg:city":"Brookhaven",
    "sg:classifiers":[
        {
            "category":"Mining & Drilling",
            "type":"Manufacturing & Wholesale Goods"
        }
    ],
    "sg:phone":"+1 601 833 8272",
    "sg:postcode":"39601",
    "sg:province":"MS",
    "sg:tags":[
        "field",
        "oil"
    ],
    "wof:name":"Holmes Oil Field Svc Inc",
    "wof:placetype":"venue"
},
  "geometry": {"coordinates":[-90.43809899999999,31.58653],"type":"Point"}
}