{
  "type": "Feature",
  "properties": {
    "iso:country":"US",
    "sg:address":"4017 Old Spanish Trl",
    "sg:city":"Gautier",
    "sg:classifiers":[
        {
            "category":"Building & Trades",
            "subcategory":"Construction",
            "type":"Services"
        }
    ],
    "sg:phone":"+1 228 497 1022",
    "sg:postcode":"39553",
    "sg:province":"MS",
    "sg:tags":[
        "heavy"
    ],
    "wof:name":"Henze Enterprises Inc",
    "wof:placetype":"venue"
},
  "geometry": {"coordinates":[-88.677938,30.392756],"type":"Point"}
}