{
  "type": "Feature",
  "properties": {
    "iso:country":"US",
    "sg:address":"143 Mallard Point Dr",
    "sg:city":"Madison",
    "sg:classifiers":[
        {
            "category":"Wholesale",
            "subcategory":"Durable Goods & Equipment",
            "type":"Manufacturing & Wholesale Goods"
        }
    ],
    "sg:phone":"+1 601 898 9311",
    "sg:postcode":"39110",
    "sg:province":"MS",
    "wof:name":"International Wood Inc",
    "wof:placetype":"venue"
},
  "geometry": {"coordinates":[-90.07975999999999,32.429082],"type":"Point"}
}