{
  "type": "Feature",
  "properties": {
    "iso:country":"US",
    "sg:address":"950 N Broadway St",
    "sg:city":"Greenville",
    "sg:classifiers":[
        {
            "category":"Building & Trades",
            "subcategory":"Electrical",
            "type":"Services"
        }
    ],
    "sg:phone":"+1 662 334 1382",
    "sg:postcode":"38701",
    "sg:province":"MS",
    "sg:tags":[
        "electric",
        "contractor"
    ],
    "wof:name":"EMSCO Electric",
    "wof:placetype":"venue"
},
  "geometry": {"coordinates":[-91.048581,33.424209],"type":"Point"}
}