{
  "type": "Feature",
  "properties": {
    "addr:full":"7471 Hollyview Dr Memphis MS 38125",
    "addr:housenumber":"7471",
    "addr:postcode":"38125",
    "addr:street":"Hollyview Dr",
    "iso:country":"US",
    "sg:address":"7471 Hollyview Dr",
    "sg:city":"Memphis",
    "sg:classifiers":[
        {
            "category":"Professional",
            "subcategory":"Management & Consulting",
            "type":"Services"
        }
    ],
    "sg:phone":"+1 901 737 7640",
    "sg:postcode":"38125",
    "sg:province":"MS",
    "sg:tags":[
        "retail",
        "direct",
        "sales"
    ],
    "wof:name":"Jet Black Magazine",
    "wof:placetype":"venue"
},
  "geometry": {"coordinates":[-89.814685,35.013484],"type":"Point"}
}