{
  "type": "Feature",
  "properties": {
    "addr:full":"4 Oak Ln Natchez MS 39120",
    "addr:housenumber":"4",
    "addr:postcode":"39120",
    "addr:street":"Oak Ln",
    "iso:country":"US",
    "sg:address":"4 Oak Ln",
    "sg:city":"Natchez",
    "sg:classifiers":[
        {
            "category":"Organizations",
            "subcategory":"Religious Organization",
            "type":"Services"
        }
    ],
    "sg:phone":"+1 601 445 9044",
    "sg:postcode":"39120",
    "sg:province":"MS",
    "sg:tags":[
        "church"
    ],
    "wof:name":"Forest Aid Baptist Church",
    "wof:placetype":"venue"
},
  "geometry": {"coordinates":[-91.413398,31.510776],"type":"Point"}
}