{
  "type": "Feature",
  "properties": {
    "iso:country":"US",
    "sg:address":"2919 Old Mobile Ave",
    "sg:city":"Pascagoula",
    "sg:classifiers":[
        {
            "category":"Organizations",
            "subcategory":"Religious Organization",
            "type":"Services"
        }
    ],
    "sg:phone":"+1 228 762 8536",
    "sg:postcode":"39581",
    "sg:province":"MS",
    "wof:name":"Woodlawn Baptist Church",
    "wof:placetype":"venue"
},
  "geometry": {"coordinates":[-88.530916,30.368571],"type":"Point"}
}