{
  "type": "Feature",
  "properties": {
    "iso:country":"US",
    "sg:address":"7227 Winchester Rd",
    "sg:city":"Memphis",
    "sg:classifiers":[
        {
            "category":"Professional",
            "subcategory":"Advertising",
            "type":"Services"
        }
    ],
    "sg:phone":"+1 901 624 2220",
    "sg:postcode":"38125",
    "sg:province":"MS",
    "sg:tags":[
        "mail",
        "direct"
    ],
    "wof:name":"Mailing Enterprises",
    "wof:placetype":"venue"
},
  "geometry": {"coordinates":[-89.819788,35.049347],"type":"Point"}
}