{
  "type": "Feature",
  "properties": {
    "iso:country":"US",
    "sg:address":"124 Tanglewood Dr",
    "sg:city":"Hattiesburg",
    "sg:classifiers":[
        {
            "category":"Education",
            "subcategory":"Special Training",
            "type":"Public Place"
        }
    ],
    "sg:phone":"+1 601 264 6244",
    "sg:postcode":"39402",
    "sg:province":"MS",
    "wof:name":"C E U Centercom LLC",
    "wof:placetype":"venue"
},
  "geometry": {"coordinates":[-89.367689,31.312268],"type":"Point"}
}