{
  "type": "Feature",
  "properties": {
    "addr:full":"550 Miller Rd Clarksdale MS 38614",
    "addr:housenumber":"550",
    "addr:postcode":"38614",
    "addr:street":"Miller Rd",
    "iso:country":"US",
    "sg:address":"550 Miller Rd",
    "sg:city":"Clarksdale",
    "sg:classifiers":[
        {
            "category":"Farming",
            "subcategory":"Farm",
            "type":"Manufacturing & Wholesale Goods"
        }
    ],
    "sg:phone":"+1 662 627 7201",
    "sg:postcode":"38614",
    "sg:province":"MS",
    "wof:name":"Miller Farms",
    "wof:placetype":"venue"
},
  "geometry": {"coordinates":[-90.64972,34.305701],"type":"Point"}
}